Workbook

Sheet 目录
A1: 项目目录
A2: 序号 | B2: 项目名称 | C2: 项目简称 | D2: 备注 | F2: 汇总序号(辅助)
A3: 1 | B3: 重庆铜梁110kV淮阳站阳高线10kV配套送出工程（安装） | C3: 淮阳站阳高线 | F3: =IF(C3="","",IF(COUNTIF(C$3:C3,C3)=1,MAX(F$2:F2)+1,"")) -> 1
A4: 2 | B4: 重庆市合川区云门街道云龙社区居民委员会(铁工厂还房建设项目)高压新装用电工程 | C4: 云龙社区 | F4: =IF(C4="","",IF(COUNTIF(C$3:C4,C4)=1,MAX(F$2:F3)+1,"")) -> 2
A5: 3 | B5: 高新区厂房及配套设施提质改造项目开票到瑞翔厂区电力土建(管廊)建设工程 | C5: 合川瑞翔 | F5: =IF(C5="","",IF(COUNTIF(C$3:C5,C5)=1,MAX(F$2:F4)+1,"")) -> 3
A6: 4 | B6: 重庆铜梁铜城2回金龙物业管理有限公司10kV业扩配套工程 | C6: 铜城2回、玉璟尚线、铁井一回、淮拦线4 | F6: =IF(C6="","",IF(COUNTIF(C$3:C6,C6)=1,MAX(F$2:F5)+1,"")) -> 4
A7: 5 | B7: 重庆铜梁玉璟尚线金龙物业管理有限公司10kV业扩配套工程 | C7: 铜城2回、玉璟尚线、铁井一回、淮拦线4 | F7: =IF(C7="","",IF(COUNTIF(C$3:C7,C7)=1,MAX(F$2:F6)+1,""))
A8: 6 | B8: 重庆铜梁铁井一回1#环网柜等6个10kV老旧环网柜改造工程(安装) | C8: 铜城2回、玉璟尚线、铁井一回、淮拦线4 | F8: =IF(C8="","",IF(COUNTIF(C$3:C8,C8)=1,MAX(F$2:F7)+1,""))
A9: 7 | B9: 重庆铜梁淮拦线4#环网柜等6个10kV老旧环网柜改造工程（安装） | C9: 铜城2回、玉璟尚线、铁井一回、淮拦线4 | F9: =IF(C9="","",IF(COUNTIF(C$3:C9,C9)=1,MAX(F$2:F8)+1,""))
A10: 8 | B10: 国网重庆合川供电公司2026年用电信息采集系统建筑相关工程施工(包4) | C10: 合川表计 | F10: =IF(C10="","",IF(COUNTIF(C$3:C10,C10)=1,MAX(F$2:F9)+1,"")) -> 5
A11: 9 | B11: 铜梁区园区屋顶分布式光伏发电建设项目-蒲吕片区A段10千伏电力新建工程 | C11: 蒲吕片区A段 | F11: =IF(C11="","",IF(COUNTIF(C$3:C11,C11)=1,MAX(F$2:F10)+1,"")) -> 6
A12: 10 | F12: =IF(C12="","",IF(COUNTIF(C$3:C12,C12)=1,MAX(F$2:F11)+1,""))
A13: 11 | F13: =IF(C13="","",IF(COUNTIF(C$3:C13,C13)=1,MAX(F$2:F12)+1,""))
A14: 12 | F14: =IF(C14="","",IF(COUNTIF(C$3:C14,C14)=1,MAX(F$2:F13)+1,""))
A15: 13 | F15: =IF(C15="","",IF(COUNTIF(C$3:C15,C15)=1,MAX(F$2:F14)+1,""))
A16: 14 | F16: =IF(C16="","",IF(COUNTIF(C$3:C16,C16)=1,MAX(F$2:F15)+1,""))
A17: 15 | F17: =IF(C17="","",IF(COUNTIF(C$3:C17,C17)=1,MAX(F$2:F16)+1,""))
A18: 16 | F18: =IF(C18="","",IF(COUNTIF(C$3:C18,C18)=1,MAX(F$2:F17)+1,""))
A19: 17 | F19: =IF(C19="","",IF(COUNTIF(C$3:C19,C19)=1,MAX(F$2:F18)+1,""))
A20: 18 | F20: =IF(C20="","",IF(COUNTIF(C$3:C20,C20)=1,MAX(F$2:F19)+1,""))
A21: 19 | F21: =IF(C21="","",IF(COUNTIF(C$3:C21,C21)=1,MAX(F$2:F20)+1,""))
A22: 20 | F22: =IF(C22="","",IF(COUNTIF(C$3:C22,C22)=1,MAX(F$2:F21)+1,""))
F23: =IF(C23="","",IF(COUNTIF(C$3:C23,C23)=1,MAX(F$2:F22)+1,""))
F24: =IF(C24="","",IF(COUNTIF(C$3:C24,C24)=1,MAX(F$2:F23)+1,""))
F25: =IF(C25="","",IF(COUNTIF(C$3:C25,C25)=1,MAX(F$2:F24)+1,""))
F26: =IF(C26="","",IF(COUNTIF(C$3:C26,C26)=1,MAX(F$2:F25)+1,""))
F27: =IF(C27="","",IF(COUNTIF(C$3:C27,C27)=1,MAX(F$2:F26)+1,""))
F28: =IF(C28="","",IF(COUNTIF(C$3:C28,C28)=1,MAX(F$2:F27)+1,""))
F29: =IF(C29="","",IF(COUNTIF(C$3:C29,C29)=1,MAX(F$2:F28)+1,""))
F30: =IF(C30="","",IF(COUNTIF(C$3:C30,C30)=1,MAX(F$2:F29)+1,""))
F31: =IF(C31="","",IF(COUNTIF(C$3:C31,C31)=1,MAX(F$2:F30)+1,""))
F32: =IF(C32="","",IF(COUNTIF(C$3:C32,C32)=1,MAX(F$2:F31)+1,""))
F33: =IF(C33="","",IF(COUNTIF(C$3:C33,C33)=1,MAX(F$2:F32)+1,""))
F34: =IF(C34="","",IF(COUNTIF(C$3:C34,C34)=1,MAX(F$2:F33)+1,""))
... F102: =IF(C102="","",IF(COUNTIF(C$3:C102,C102)=1,MAX(F$2:F101)+1,""))

Sheet 发票统计
A1: 项目总台账
A2: 项目 简称 | B2: 月份 | C2: 项目 名称 | D2: 摘要 | E2: 收票 单位 | F2: 发票 性质 | G2: 管理 费点 | H2: 销售金额 | I2: 管理费 | J2: 应开 成本票 | K2: 已开 成本票 | L2: 未开 成本票 | M2: 应收款 | N2: 质保金 | O2: 已收款 | P2: 未收款 | Q2: 应付 工程款 | R2: 扣除 管理费 | S2: 已付 工程款 | T2: 未付 工程款 | U2: 备注 | V2: 校验 | W2: 取数键(辅助)
H3: =SUM(H4:H1003) -> 2206559.2 | I3: =SUM(I4:I1003) -> 65304.158 | J3: =SUM(J4:J1003) -> 2141255 | K3: =SUM(K4:K1003) -> 2098816.7 | L3: =J3-K3 -> 42438.29 | M3: =SUM(M4:M1003) -> 2206559.2 | N3: =SUM(N4:N1003) -> 0 | O3: =SUM(O4:O1003) -> 1500594.2 | P3: =M3-N3-O3 -> 705964.91 | Q3: =SUM(Q4:Q1003) -> 0 | R3: =SUM(R4:R1003) -> 0 | S3: =SUM(S4:S1003) -> 576643 | T3: =Q3-R3-S3 -> -576643 | V3: =IF(COUNTA(C4:C1003)>COUNTIF(W4:W1003,"?*"),"⚠ 有 "&(COUNTA(C4:C1003)-COUNTIF(W4:W1003,"?*"))&" 行缺公式或缺简称",IF(COUNTIF(V4:V1003,"⚠*")>0,"⚠ "&COUNTIF(V4:V1003,"⚠*")&" 行有错，往下看",IF(COUNTIF(V4:V1003,"△*")>0,"△ "&COUNTIF(V4:V1003,"△*")&" 行请留意","✓ 全部通过"))) -> △ 2 行请留意
A4: =IF($C4="","",IFERROR(VLOOKUP($C4,目录!$B:$C,2,0)&"","⚠目录里没有")) -> 淮阳站阳高线 | B4: =IF($D4="","",IFERROR(MID($D4,FIND(".",$D4)+1,FIND(".",$D4,FIND(".",$D4)+1)-FIND(".",$D4)-1)&"月","")) -> 3月 | C4: 重庆铜梁110kV淮阳站阳高线10kV配套送出工程（安装） | D4: 2026.3.25新德润开票到民能：淮阳站阳高线 | E4: 民能 | F4: 3%专票 | H4: 57824 | I4: =IF($H4="","",N($H4)*N($G4)) -> 0 | J4: =IF($H4="","",N($H4)-N($I4)) -> 57824 | K4: 57824 | L4: =IF($A4="","",SUMIF($A$4:$A4,$A4,$J$4:$J4)-SUMIF($A$4:$A4,$A4,$K$4:$K4)) -> 0 | M4: =IF($H4="","",N($H4)) -> 57824 | P4: =IF($A4="","",SUMIF($A$4:$A4,$A4,$M$4:$M4)-SUMIF($A$4:$A4,$A4,$N$4:$N4)-SUMIF($A$4:$A4,$A4,$O$4:$O4)) -> 57824 | R4: 0 | S4: 0 | T4: =IF($A4="","",SUMIF($A$4:$A4,$A4,$Q$4:$Q4)-SUMIF($A$4:$A4,$A4,$R$4:$R4)-SUMIF($A$4:$A4,$A4,$S$4:$S4)) -> 0 | V4: =IF(AND($C4="",COUNTA($D4:$H4,$K4,$N4:$O4,$Q4:$S4,$U4)=0),"",IF($C4="","⚠ 没填项目名称",IF($A4="⚠目录里没有","⚠ 项目名称在目录里找不到（先加到目录）",IF($A4="","⚠ 目录里这个项目没填简称",IF(ISTEXT($G4)+ISTEXT($H4)+ISTEXT($K4)+ISTEXT($N4)+ISTEXT($O4)+ISTEXT($Q4)+ISTEXT($R4)+ISTEXT($S4)>0,"⚠ 金额列里有文字，算不进合计",IF(N($G4)>=1,"⚠ 管理费点要填百分比，如 10%",IF(AND($D4<>"",$B4=""),"△ 摘要开头没写日期（如 2026.9.21），月份取不到",IF(AND(N($H4)<>0,COUNTIFS($A$4:$A$1003,$A4,$H$4:$H$1003,$H4,$D$4:$D$1003,LEFT($D4,9)&"*")>1),"△ 同一天同项目有一样的销售金额，看看是不是录重了","✓")))))))) -> ✓ | W4: =IF($A4="","",$A4&"#"&COUNTIF($A$4:$A4,$A4)) -> 淮阳站阳高线#1
A5: =IF($C5="","",IFERROR(VLOOKUP($C5,目录!$B:$C,2,0)&"","⚠目录里没有")) -> 淮阳站阳高线 | B5: =IF($D5="","",IFERROR(MID($D5,FIND(".",$D5)+1,FIND(".",$D5,FIND(".",$D5)+1)-FIND(".",$D5)-1)&"月","")) -> 3月 | C5: 重庆铜梁110kV淮阳站阳高线10kV配套送出工程（安装） | D5: 2026.3.25张氏机电-新德润：淮阳站阳高线 | E5: 新德润 | H5: 50120.61 | I5: =IF($H5="","",N($H5)*N($G5)) -> 0 | J5: =IF($H5="","",N($H5)-N($I5)) -> 50120.61 | K5: 50120.61 | L5: =IF($A5="","",SUMIF($A$4:$A5,$A5,$J$4:$J5)-SUMIF($A$4:$A5,$A5,$K$4:$K5)) -> 0 | M5: =IF($H5="","",N($H5)) -> 50120.61 | P5: =IF($A5="","",SUMIF($A$4:$A5,$A5,$M$4:$M5)-SUMIF($A$4:$A5,$A5,$N$4:$N5)-SUMIF($A$4:$A5,$A5,$O$4:$O5)) -> 107944.61 | T5: =IF($A5="","",SUMIF($A$4:$A5,$A5,$Q$4:$Q5)-SUMIF($A$4:$A5,$A5,$R$4:$R5)-SUMIF($A$4:$A5,$A5,$S$4:$S5)) -> 0 | V5: =IF(AND($C5="",COUNTA($D5:$H5,$K5,$N5:$O5,$Q5:$S5,$U5)=0),"",IF($C5="","⚠ 没填项目名称",IF($A5="⚠目录里没有","⚠ 项目名称在目录里找不到（先加到目录）",IF($A5="","⚠ 目录里这个项目没填简称",IF(ISTEXT($G5)+ISTEXT($H5)+ISTEXT($K5)+ISTEXT($N5)+ISTEXT($O5)+ISTEXT($Q5)+ISTEXT($R5)+ISTEXT($S5)>0,"⚠ 金额列里有文字，算不进合计",IF(N($G5)>=1,"⚠ 管理费点要填百分比，如 10%",IF(AND($D5<>"",$B5=""),"△ 摘要开头没写日期（如 2026.9.21），月份取不到",IF(AND(N($H5)<>0,COUNTIFS($A$4:$A$1003,$A5,$H$4:$H$1003,$H5,$D$4:$D$1003,LEFT($D5,9)&"*")>1),"△ 同一天同项目有一样的销售金额，看看是不是录重了","✓")))))))) -> ✓ | W5: =IF($A5="","",$A5&"#"&COUNTIF($A$4:$A5,$A5)) -> 淮阳站阳高线#2
A6: =IF($C6="","",IFERROR(VLOOKUP($C6,目录!$B:$C,2,0)&"","⚠目录里没有")) -> 云龙社区 | B6: =IF($D6="","",IFERROR(MID($D6,FIND(".",$D6)+1,FIND(".",$D6,FIND(".",$D6)+1)-FIND(".",$D6)-1)&"月","")) -> 4月 | C6: 重庆市合川区云门街道云龙社区居民委员会(铁工厂还房建设项目)高压新装用电工程 | D6: 2026.4.28庆文开票给新德润：云龙社区居民委员会 | E6: 新德润 | F6: 3%专票 | H6: 183486.24 | I6: =IF($H6="","",N($H6)*N($G6)) -> 0 | J6: =IF($H6="","",N($H6)-N($I6)) -> 183486.24 | K6: 183486.24 | L6: =IF($A6="","",SUMIF($A$4:$A6,$A6,$J$4:$J6)-SUMIF($A$4:$A6,$A6,$K$4:$K6)) -> 0 | M6: =IF($H6="","",N($H6)) -> 183486.24 | P6: =IF($A6="","",SUMIF($A$4:$A6,$A6,$M$4:$M6)-SUMIF($A$4:$A6,$A6,$N$4:$N6)-SUMIF($A$4:$A6,$A6,$O$4:$O6)) -> 183486.24 | T6: =IF($A6="","",SUMIF($A$4:$A6,$A6,$Q$4:$Q6)-SUMIF($A$4:$A6,$A6,$R$4:$R6)-SUMIF($A$4:$A6,$A6,$S$4:$S6)) -> 0 | V6: =IF(AND($C6="",COUNTA($D6:$H6,$K6,$N6:$O6,$Q6:$S6,$U6)=0),"",IF($C6="","⚠ 没填项目名称",IF($A6="⚠目录里没有","⚠ 项目名称在目录里找不到（先加到目录）",IF($A6="","⚠ 目录里这个项目没填简称",IF(ISTEXT($G6)+ISTEXT($H6)+ISTEXT($K6)+ISTEXT($N6)+ISTEXT($O6)+ISTEXT($Q6)+ISTEXT($R6)+ISTEXT($S6)>0,"⚠ 金额列里有文字，算不进合计",IF(N($G6)>=1,"⚠ 管理费点要填百分比，如 10%",IF(AND($D6<>"",$B6=""),"△ 摘要开头没写日期（如 2026.9.21），月份取不到",IF(AND(N($H6)<>0,COUNTIFS($A$4:$A$1003,$A6,$H$4:$H$1003,$H6,$D$4:$D$1003,LEFT($D6,9)&"*")>1),"△ 同一天同项目有一样的销售金额，看看是不是录重了","✓")))))))) -> ✓ | W6: =IF($A6="","",$A6&"#"&COUNTIF($A$4:$A6,$A6)) -> 云龙社区#1
A7: =IF($C7="","",IFERROR(VLOOKUP($C7,目录!$B:$C,2,0)&"","⚠目录里没有")) -> 云龙社区 | B7: =IF($D7="","",IFERROR(MID($D7,FIND(".",$D7)+1,FIND(".",$D7,FIND(".",$D7)+1)-FIND(".",$D7)-1)&"月","")) -> 4月 | C7: 重庆市合川区云门街道云龙社区居民委员会(铁工厂还房建设项目)高压新装用电工程 | D7: 2026.4.30莨富收到新德润款项：云龙社区居民委员会 | E7: 新德润 | I7: =IF($H7="","",N($H7)*N($G7)) | J7: =IF($H7="","",N($H7)-N($I7)) | L7: =IF($A7="","",SUMIF($A$4:$A7,$A7,$J$4:$J7)-SUMIF($A$4:$A7,$A7,$K$4:$K7)) -> 0 | M7: =IF($H7="","",N($H7)) | O7: 183486.24 | P7: =IF($A7="","",SUMIF($A$4:$A7,$A7,$M$4:$M7)-SUMIF($A$4:$A7,$A7,$N$4:$N7)-SUMIF($A$4:$A7,$A7,$O$4:$O7)) -> 0 | T7: =IF($A7="","",SUMIF($A$4:$A7,$A7,$Q$4:$Q7)-SUMIF($A$4:$A7,$A7,$R$4:$R7)-SUMIF($A$4:$A7,$A7,$S$4:$S7)) -> 0 | V7: =IF(AND($C7="",COUNTA($D7:$H7,$K7,$N7:$O7,$Q7:$S7,$U7)=0),"",IF($C7="","⚠ 没填项目名称",IF($A7="⚠目录里没有","⚠ 项目名称在目录里找不到（先加到目录）",IF($A7="","⚠ 目录里这个项目没填简称",IF(ISTEXT($G7)+ISTEXT($H7)+ISTEXT($K7)+ISTEXT($N7)+ISTEXT($O7)+ISTEXT($Q7)+ISTEXT($R7)+ISTEXT($S7)>0,"⚠ 金额列里有文字，算不进合计",IF(N($G7)>=1,"⚠ 管理费点要填百分比，如 10%",IF(AND($D7<>"",$B7=""),"△ 摘要开头没写日期（如 2026.9.21），月份取不到",IF(AND(N($H7)<>0,COUNTIFS($A$4:$A$1003,$A7,$H$4:$H$1003,$H7,$D$4:$D$1003,LEFT($D7,9)&"*")>1),"△ 同一天同项目有一样的销售金额，看看是不是录重了","✓")))))))) -> ✓ | W7: =IF($A7="","",$A7&"#"&COUNTIF($A$4:$A7,$A7)) -> 云龙社区#2
A8: =IF($C8="","",IFERROR(VLOOKUP($C8,目录!$B:$C,2,0)&"","⚠目录里没有")) -> 云龙社区 | B8: =IF($D8="","",IFERROR(MID($D8,FIND(".",$D8)+1,FIND(".",$D8,FIND(".",$D8)+1)-FIND(".",$D8)-1)&"月","")) -> 5月 | C8: 重庆市合川区云门街道云龙社区居民委员会(铁工厂还房建设项目)高压新装用电工程 | D8: 2026.5.7庆文开票给新德润：云龙社区居民委员会 | E8: 新德润 | F8: 3%专票 | H8: 43774.56 | I8: =IF($H8="","",N($H8)*N($G8)) -> 0 | J8: =IF($H8="","",N($H8)-N($I8)) -> 43774.56 | K8: 43774.56 | L8: =IF($A8="","",SUMIF($A$4:$A8,$A8,$J$4:$J8)-SUMIF($A$4:$A8,$A8,$K$4:$K8)) -> 0 | M8: =IF($H8="","",N($H8)) -> 43774.56 | P8: =IF($A8="","",SUMIF($A$4:$A8,$A8,$M$4:$M8)-SUMIF($A$4:$A8,$A8,$N$4:$N8)-SUMIF($A$4:$A8,$A8,$O$4:$O8)) -> 43774.56 | T8: =IF($A8="","",SUMIF($A$4:$A8,$A8,$Q$4:$Q8)-SUMIF($A$4:$A8,$A8,$R$4:$R8)-SUMIF($A$4:$A8,$A8,$S$4:$S8)) -> 0 | V8: =IF(AND($C8="",COUNTA($D8:$H8,$K8,$N8:$O8,$Q8:$S8,$U8)=0),"",IF($C8="","⚠ 没填项目名称",IF($A8="⚠目录里没有","⚠ 项目名称在目录里找不到（先加到目录）",IF($A8="","⚠ 目录里这个项目没填简称",IF(ISTEXT($G8)+ISTEXT($H8)+ISTEXT($K8)+ISTEXT($N8)+ISTEXT($O8)+ISTEXT($Q8)+ISTEXT($R8)+ISTEXT($S8)>0,"⚠ 金额列里有文字，算不进合计",IF(N($G8)>=1,"⚠ 管理费点要填百分比，如 10%",IF(AND($D8<>"",$B8=""),"△ 摘要开头没写日期（如 2026.9.21），月份取不到",IF(AND(N($H8)<>0,COUNTIFS($A$4:$A$1003,$A8,$H$4:$H$1003,$H8,$D$4:$D$1003,LEFT($D8,9)&"*")>1),"△ 同一天同项目有一样的销售金额，看看是不是录重了","✓")))))))) -> ✓ | W8: =IF($A8="","",$A8&"#"&COUNTIF($A$4:$A8,$A8)) -> 云龙社区#3
A9: =IF($C9="","",IFERROR(VLOOKUP($C9,目录!$B:$C,2,0)&"","⚠目录里没有")) -> 云龙社区 | B9: =IF($D9="","",IFERROR(MID($D9,FIND(".",$D9)+1,FIND(".",$D9,FIND(".",$D9)+1)-FIND(".",$D9)-1)&"月","")) -> 5月 | C9: 重庆市合川区云门街道云龙社区居民委员会(铁工厂还房建设项目)高压新装用电工程 | D9: 2026.5.13庆文公账收到新德润款项：云龙社区居民委员会 | E9: 新德润 | I9: =IF($H9="","",N($H9)*N($G9)) | J9: =IF($H9="","",N($H9)-N($I9)) | L9: =IF($A9="","",SUMIF($A$4:$A9,$A9,$J$4:$J9)-SUMIF($A$4:$A9,$A9,$K$4:$K9)) -> 0 | M9: =IF($H9="","",N($H9)) | O9: 43774.56 | P9: =IF($A9="","",SUMIF($A$4:$A9,$A9,$M$4:$M9)-SUMIF($A$4:$A9,$A9,$N$4:$N9)-SUMIF($A$4:$A9,$A9,$O$4:$O9)) -> 0 | T9: =IF($A9="","",SUMIF($A$4:$A9,$A9,$Q$4:$Q9)-SUMIF($A$4:$A9,$A9,$R$4:$R9)-SUMIF($A$4:$A9,$A9,$S$4:$S9)) -> 0 | V9: =IF(AND($C9="",COUNTA($D9:$H9,$K9,$N9:$O9,$Q9:$S9,$U9)=0),"",IF($C9="","⚠ 没填项目名称",IF($A9="⚠目录里没有","⚠ 项目名称在目录里找不到（先加到目录）",IF($A9="","⚠ 目录里这个项目没填简称",IF(ISTEXT($G9)+ISTEXT($H9)+ISTEXT($K9)+ISTEXT($N9)+ISTEXT($O9)+ISTEXT($Q9)+ISTEXT($R9)+ISTEXT($S9)>0,"⚠ 金额列里有文字，算不进合计",IF(N($G9)>=1,"⚠ 管理费点要填百分比，如 10%",IF(AND($D9<>"",$B9=""),"△ 摘要开头没写日期（如 2026.9.21），月份取不到",IF(AND(N($H9)<>0,COUNTIFS($A$4:$A$1003,$A9,$H$4:$H$1003,$H9,$D$4:$D$1003,LEFT($D9,9)&"*")>1),"△ 同一天同项目有一样的销售金额，看看是不是录重了","✓")))))))) -> ✓ | W9: =IF($A9="","",$A9&"#"&COUNTIF($A$4:$A9,$A9)) -> 云龙社区#4
A10: =IF($C10="","",IFERROR(VLOOKUP($C10,目录!$B:$C,2,0)&"","⚠目录里没有")) -> 合川瑞翔 | B10: =IF($D10="","",IFERROR(MID($D10,FIND(".",$D10)+1,FIND(".",$D10,FIND(".",$D10)+1)-FIND(".",$D10)-1)&"月","")) -> 6月 | C10: 高新区厂房及配套设施提质改造项目开票到瑞翔厂区电力土建(管廊)建设工程 | D10: 2026.6.17庆文开票给新德润：瑞翔厂区电力土建 | E10: 新德润 | F10: 1%专票 | H10: 100000 | I10: =IF($H10="","",N($H10)*N($G10)) -> 0 | J10: =IF($H10="","",N($H10)-N($I10)) -> 100000 | K10: 100000 | L10: =IF($A10="","",SUMIF($A$4:$A10,$A10,$J$4:$J10)-SUMIF($A$4:$A10,$A10,$K$4:$K10)) -> 0 | M10: =IF($H10="","",N($H10)) -> 100000 | P10: =IF($A10="","",SUMIF($A$4:$A10,$A10,$M$4:$M10)-SUMIF($A$4:$A10,$A10,$N$4:$N10)-SUMIF($A$4:$A10,$A10,$O$4:$O10)) -> 100000 | T10: =IF($A10="","",SUMIF($A$4:$A10,$A10,$Q$4:$Q10)-SUMIF($A$4:$A10,$A10,$R$4:$R10)-SUMIF($A$4:$A10,$A10,$S$4:$S10)) -> 0 | V10: =IF(AND($C10="",COUNTA($D10:$H10,$K10,$N10:$O10,$Q10:$S10,$U10)=0),"",IF($C10="","⚠ 没填项目名称",IF($A10="⚠目录里没有","⚠ 项目名称在目录里找不到（先加到目录）",IF($A10="","⚠ 目录里这个项目没填简称",IF(ISTEXT($G10)+ISTEXT($H10)+ISTEXT($K10)+ISTEXT($N10)+ISTEXT($O10)+ISTEXT($Q10)+ISTEXT($R10)+ISTEXT($S10)>0,"⚠ 金额列里有文字，算不进合计",IF(N($G10)>=1,"⚠ 管理费点要填百分比，如 10%",IF(AND($D10<>"",$B10=""),"△ 摘要开头没写日期（如 2026.9.21），月份取不到",IF(AND(N($H10)<>0,COUNTIFS($A$4:$A$1003,$A10,$H$4:$H$1003,$H10,$D$4:$D$1003,LEFT($D10,9)&"*")>1),"△ 同一天同项目有一样的销售金额，看看是不是录重了","✓")))))))) -> ✓ | W10: =IF($A10="","",$A10&"#"&COUNTIF($A$4:$A10,$A10)) -> 合川瑞翔#1
A11: =IF($C11="","",IFERROR(VLOOKUP($C11,目录!$B:$C,2,0)&"","⚠目录里没有")) -> 合川瑞翔 | B11: =IF($D11="","",IFERROR(MID($D11,FIND(".",$D11)+1,FIND(".",$D11,FIND(".",$D11)+1)-FIND(".",$D11)-1)&"月","")) -> 6月 | C11: 高新区厂房及配套设施提质改造项目开票到瑞翔厂区电力土建(管廊)建设工程 | D11: 2026.6.18庆文收到新德润打款：瑞翔厂区电力 | E11: 新德润 | I11: =IF($H11="","",N($H11)*N($G11)) | J11: =IF($H11="","",N($H11)-N($I11)) | L11: =IF($A11="","",SUMIF($A$4:$A11,$A11,$J$4:$J11)-SUMIF($A$4:$A11,$A11,$K$4:$K11)) -> 0 | M11: =IF($H11="","",N($H11)) | O11: 100000 | P11: =IF($A11="","",SUMIF($A$4:$A11,$A11,$M$4:$M11)-SUMIF($A$4:$A11,$A11,$N$4:$N11)-SUMIF($A$4:$A11,$A11,$O$4:$O11)) -> 0 | T11: =IF($A11="","",SUMIF($A$4:$A11,$A11,$Q$4:$Q11)-SUMIF($A$4:$A11,$A11,$R$4:$R11)-SUMIF($A$4:$A11,$A11,$S$4:$S11)) -> 0 | V11: =IF(AND($C11="",COUNTA($D11:$H11,$K11,$N11:$O11,$Q11:$S11,$U11)=0),"",IF($C11="","⚠ 没填项目名称",IF($A11="⚠目录里没有","⚠ 项目名称在目录里找不到（先加到目录）",IF($A11="","⚠ 目录里这个项目没填简称",IF(ISTEXT($G11)+ISTEXT($H11)+ISTEXT($K11)+ISTEXT($N11)+ISTEXT($O11)+ISTEXT($Q11)+ISTEXT($R11)+ISTEXT($S11)>0,"⚠ 金额列里有文字，算不进合计",IF(N($G11)>=1,"⚠ 管理费点要填百分比，如 10%",IF(AND($D11<>"",$B11=""),"△ 摘要开头没写日期（如 2026.9.21），月份取不到",IF(AND(N($H11)<>0,COUNTIFS($A$4:$A$1003,$A11,$H$4:$H$1003,$H11,$D$4:$D$1003,LEFT($D11,9)&"*")>1),"△ 同一天同项目有一样的销售金额，看看是不是录重了","✓")))))))) -> ✓ | W11: =IF($A11="","",$A11&"#"&COUNTIF($A$4:$A11,$A11)) -> 合川瑞翔#2
A12: =IF($C12="","",IFERROR(VLOOKUP($C12,目录!$B:$C,2,0)&"","⚠目录里没有")) -> 合川瑞翔 | B12: =IF($D12="","",IFERROR(MID($D12,FIND(".",$D12)+1,FIND(".",$D12,FIND(".",$D12)+1)-FIND(".",$D12)-1)&"月","")) -> 7月 | C12: 高新区厂房及配套设施提质改造项目开票到瑞翔厂区电力土建(管廊)建设工程 | D12: 2026.7.2朱氏水泥管件开票到新德润：瑞翔厂区电力土建 | E12: 新德润 | F12: 1%普票 | H12: 50200 | I12: =IF($H12="","",N($H12)*N($G12)) -> 0 | J12: =IF($H12="","",N($H12)-N($I12)) -> 50200 | K12: 50200 | L12: =IF($A12="","",SUMIF($A$4:$A12,$A12,$J$4:$J12)-SUMIF($A$4:$A12,$A12,$K$4:$K12)) -> 0 | M12: =IF($H12="","",N($H12)) -> 50200 | P12: =IF($A12="","",SUMIF($A$4:$A12,$A12,$M$4:$M12)-SUMIF($A$4:$A12,$A12,$N$4:$N12)-SUMIF($A$4:$A12,$A12,$O$4:$O12)) -> 50200 | T12: =IF($A12="","",SUMIF($A$4:$A12,$A12,$Q$4:$Q12)-SUMIF($A$4:$A12,$A12,$R$4:$R12)-SUMIF($A$4:$A12,$A12,$S$4:$S12)) -> 0 | V12: =IF(AND($C12="",COUNTA($D12:$H12,$K12,$N12:$O12,$Q12:$S12,$U12)=0),"",IF($C12="","⚠ 没填项目名称",IF($A12="⚠目录里没有","⚠ 项目名称在目录里找不到（先加到目录）",IF($A12="","⚠ 目录里这个项目没填简称",IF(ISTEXT($G12)+ISTEXT($H12)+ISTEXT($K12)+ISTEXT($N12)+ISTEXT($O12)+ISTEXT($Q12)+ISTEXT($R12)+ISTEXT($S12)>0,"⚠ 金额列里有文字，算不进合计",IF(N($G12)>=1,"⚠ 管理费点要填百分比，如 10%",IF(AND($D12<>"",$B12=""),"△ 摘要开头没写日期（如 2026.9.21），月份取不到",IF(AND(N($H12)<>0,COUNTIFS($A$4:$A$1003,$A12,$H$4:$H$1003,$H12,$D$4:$D$1003,LEFT($D12,9)&"*")>1),"△ 同一天同项目有一样的销售金额，看看是不是录重了","✓")))))))) -> ✓ | W12: =IF($A12="","",$A12&"#"&COUNTIF($A$4:$A12,$A12)) -> 合川瑞翔#3
A13: =IF($C13="","",IFERROR(VLOOKUP($C13,目录!$B:$C,2,0)&"","⚠目录里没有")) -> 合川瑞翔 | B13: =IF($D13="","",IFERROR(MID($D13,FIND(".",$D13)+1,FIND(".",$D13,FIND(".",$D13)+1)-FIND(".",$D13)-1)&"月","")) -> 7月 | C13: 高新区厂房及配套设施提质改造项目开票到瑞翔厂区电力土建(管廊)建设工程 | D13: 2026.7.6朱氏水泥管收到新德润：瑞翔厂区电力 | E13: 新德润 | I13: =IF($H13="","",N($H13)*N($G13)) | J13: =IF($H13="","",N($H13)-N($I13)) | L13: =IF($A13="","",SUMIF($A$4:$A13,$A13,$J$4:$J13)-SUMIF($A$4:$A13,$A13,$K$4:$K13)) -> 0 | M13: =IF($H13="","",N($H13)) | O13: 50200 | P13: =IF($A13="","",SUMIF($A$4:$A13,$A13,$M$4:$M13)-SUMIF($A$4:$A13,$A13,$N$4:$N13)-SUMIF($A$4:$A13,$A13,$O$4:$O13)) -> 0 | T13: =IF($A13="","",SUMIF($A$4:$A13,$A13,$Q$4:$Q13)-SUMIF($A$4:$A13,$A13,$R$4:$R13)-SUMIF($A$4:$A13,$A13,$S$4:$S13)) -> 0 | V13: =IF(AND($C13="",COUNTA($D13:$H13,$K13,$N13:$O13,$Q13:$S13,$U13)=0),"",IF($C13="","⚠ 没填项目名称",IF($A13="⚠目录里没有","⚠ 项目名称在目录里找不到（先加到目录）",IF($A13="","⚠ 目录里这个项目没填简称",IF(ISTEXT($G13)+ISTEXT($H13)+ISTEXT($K13)+ISTEXT($N13)+ISTEXT($O13)+ISTEXT($Q13)+ISTEXT($R13)+ISTEXT($S13)>0,"⚠ 金额列里有文字，算不进合计",IF(N($G13)>=1,"⚠ 管理费点要填百分比，如 10%",IF(AND($D13<>"",$B13=""),"△ 摘要开头没写日期（如 2026.9.21），月份取不到",IF(AND(N($H13)<>0,COUNTIFS($A$4:$A$1003,$A13,$H$4:$H$1003,$H13,$D$4:$D$1003,LEFT($D13,9)&"*")>1),"△ 同一天同项目有一样的销售金额，看看是不是录重了","✓")))))))) -> ✓ | W13: =IF($A13="","",$A13&"#"&COUNTIF($A$4:$A13,$A13)) -> 合川瑞翔#4
A14: =IF($C14="","",IFERROR(VLOOKUP($C14,目录!$B:$C,2,0)&"","⚠目录里没有")) -> 合川瑞翔 | B14: =IF($D14="","",IFERROR(MID($D14,FIND(".",$D14)+1,FIND(".",$D14,FIND(".",$D14)+1)-FIND(".",$D14)-1)&"月","")) -> 7月 | C14: 高新区厂房及配套设施提质改造项目开票到瑞翔厂区电力土建(管廊)建设工程 | D14: 2026.7.8庆文开票给新德润：瑞翔厂区电力土建 | E14: 新德润 | F14: 1%专票 | H14: 100000 | I14: =IF($H14="","",N($H14)*N($G14)) -> 0 | J14: =IF($H14="","",N($H14)-N($I14)) -> 100000 | K14: 100000 | L14: =IF($A14="","",SUMIF($A$4:$A14,$A14,$J$4:$J14)-SUMIF($A$4:$A14,$A14,$K$4:$K14)) -> 0 | M14: =IF($H14="","",N($H14)) -> 100000 | P14: =IF($A14="","",SUMIF($A$4:$A14,$A14,$M$4:$M14)-SUMIF($A$4:$A14,$A14,$N$4:$N14)-SUMIF($A$4:$A14,$A14,$O$4:$O14)) -> 100000 | T14: =IF($A14="","",SUMIF($A$4:$A14,$A14,$Q$4:$Q14)-SUMIF($A$4:$A14,$A14,$R$4:$R14)-SUMIF($A$4:$A14,$A14,$S$4:$S14)) -> 0 | V14: =IF(AND($C14="",COUNTA($D14:$H14,$K14,$N14:$O14,$Q14:$S14,$U14)=0),"",IF($C14="","⚠ 没填项目名称",IF($A14="⚠目录里没有","⚠ 项目名称在目录里找不到（先加到目录）",IF($A14="","⚠ 目录里这个项目没填简称",IF(ISTEXT($G14)+ISTEXT($H14)+ISTEXT($K14)+ISTEXT($N14)+ISTEXT($O14)+ISTEXT($Q14)+ISTEXT($R14)+ISTEXT($S14)>0,"⚠ 金额列里有文字，算不进合计",IF(N($G14)>=1,"⚠ 管理费点要填百分比，如 10%",IF(AND($D14<>"",$B14=""),"△ 摘要开头没写日期（如 2026.9.21），月份取不到",IF(AND(N($H14)<>0,COUNTIFS($A$4:$A$1003,$A14,$H$4:$H$1003,$H14,$D$4:$D$1003,LEFT($D14,9)&"*")>1),"△ 同一天同项目有一样的销售金额，看看是不是录重了","✓")))))))) -> ✓ | W14: =IF($A14="","",$A14&"#"&COUNTIF($A$4:$A14,$A14)) -> 合川瑞翔#5
A15: =IF($C15="","",IFERROR(VLOOKUP($C15,目录!$B:$C,2,0)&"","⚠目录里没有")) -> 合川瑞翔 | B15: =IF($D15="","",IFERROR(MID($D15,FIND(".",$D15)+1,FIND(".",$D15,FIND(".",$D15)+1)-FIND(".",$D15)-1)&"月","")) -> 7月 | C15: 高新区厂房及配套设施提质改造项目开票到瑞翔厂区电力土建(管廊)建设工程 | D15: 2026.7.9庆文收到新德润打款：瑞翔厂区电力 | E15: 新德润 | I15: =IF($H15="","",N($H15)*N($G15)) | J15: =IF($H15="","",N($H15)-N($I15)) | K15: 0 | L15: =IF($A15="","",SUMIF($A$4:$A15,$A15,$J$4:$J15)-SUMIF($A$4:$A15,$A15,$K$4:$K15)) -> 0 | M15: =IF($H15="","",N($H15)) | O15: 100000 | P15: =IF($A15="","",SUMIF($A$4:$A15,$A15,$M$4:$M15)-SUMIF($A$4:$A15,$A15,$N$4:$N15)-SUMIF($A$4:$A15,$A15,$O$4:$O15)) -> 0 | T15: =IF($A15="","",SUMIF($A$4:$A15,$A15,$Q$4:$Q15)-SUMIF($A$4:$A15,$A15,$R$4:$R15)-SUMIF($A$4:$A15,$A15,$S$4:$S15)) -> 0 | V15: =IF(AND($C15="",COUNTA($D15:$H15,$K15,$N15:$O15,$Q15:$S15,$U15)=0),"",IF($C15="","⚠ 没填项目名称",IF($A15="⚠目录里没有","⚠ 项目名称在目录里找不到（先加到目录）",IF($A15="","⚠ 目录里这个项目没填简称",IF(ISTEXT($G15)+ISTEXT($H15)+ISTEXT($K15)+ISTEXT($N15)+ISTEXT($O15)+ISTEXT($Q15)+ISTEXT($R15)+ISTEXT($S15)>0,"⚠ 金额列里有文字，算不进合计",IF(N($G15)>=1,"⚠ 管理费点要填百分比，如 10%",IF(AND($D15<>"",$B15=""),"△ 摘要开头没写日期（如 2026.9.21），月份取不到",IF(AND(N($H15)<>0,COUNTIFS($A$4:$A$1003,$A15,$H$4:$H$1003,$H15,$D$4:$D$1003,LEFT($D15,9)&"*")>1),"△ 同一天同项目有一样的销售金额，看看是不是录重了","✓")))))))) -> ✓ | W15: =IF($A15="","",$A15&"#"&COUNTIF($A$4:$A15,$A15)) -> 合川瑞翔#6
A16: =IF($C16="","",IFERROR(VLOOKUP($C16,目录!$B:$C,2,0)&"","⚠目录里没有")) -> 合川瑞翔 | B16: =IF($D16="","",IFERROR(MID($D16,FIND(".",$D16)+1,FIND(".",$D16,FIND(".",$D16)+1)-FIND(".",$D16)-1)&"月","")) -> 7月 | C16: 高新区厂房及配套设施提质改造项目开票到瑞翔厂区电力土建(管廊)建设工程 | D16: 2026.7.8铜桐桐建材开票到新德润：瑞翔厂区电力土建 | E16: 新德润 | F16: 1%普票 | H16: 49800 | I16: =IF($H16="","",N($H16)*N($G16)) -> 0 | J16: =IF($H16="","",N($H16)-N($I16)) -> 49800 | K16: 49800 | L16: =IF($A16="","",SUMIF($A$4:$A16,$A16,$J$4:$J16)-SUMIF($A$4:$A16,$A16,$K$4:$K16)) -> 0 | M16: =IF($H16="","",N($H16)) -> 49800 | P16: =IF($A16="","",SUMIF($A$4:$A16,$A16,$M$4:$M16)-SUMIF($A$4:$A16,$A16,$N$4:$N16)-SUMIF($A$4:$A16,$A16,$O$4:$O16)) -> 49800 | T16: =IF($A16="","",SUMIF($A$4:$A16,$A16,$Q$4:$Q16)-SUMIF($A$4:$A16,$A16,$R$4:$R16)-SUMIF($A$4:$A16,$A16,$S$4:$S16)) -> 0 | V16: =IF(AND($C16="",COUNTA($D16:$H16,$K16,$N16:$O16,$Q16:$S16,$U16)=0),"",IF($C16="","⚠ 没填项目名称",IF($A16="⚠目录里没有","⚠ 项目名称在目录里找不到（先加到目录）",IF($A16="","⚠ 目录里这个项目没填简称",IF(ISTEXT($G16)+ISTEXT($H16)+ISTEXT($K16)+ISTEXT($N16)+ISTEXT($O16)+ISTEXT($Q16)+ISTEXT($R16)+ISTEXT($S16)>0,"⚠ 金额列里有文字，算不进合计",IF(N($G16)>=1,"⚠ 管理费点要填百分比，如 10%",IF(AND($D16<>"",$B16=""),"△ 摘要开头没写日期（如 2026.9.21），月份取不到",IF(AND(N($H16)<>0,COUNTIFS($A$4:$A$1003,$A16,$H$4:$H$1003,$H16,$D$4:$D$1003,LEFT($D16,9)&"*")>1),"△ 同一天同项目有一样的销售金额，看看是不是录重了","✓")))))))) -> ✓ | W16: =IF($A16="","",$A16&"#"&COUNTIF($A$4:$A16,$A16)) -> 合川瑞翔#7
A17: =IF($C17="","",IFERROR(VLOOKUP($C17,目录!$B:$C,2,0)&"","⚠目录里没有")) -> 合川瑞翔 | B17: =IF($D17="","",IFERROR(MID($D17,FIND(".",$D17)+1,FIND(".",$D17,FIND(".",$D17)+1)-FIND(".",$D17)-1)&"月","")) -> 7月 | C17: 高新区厂房及配套设施提质改造项目开票到瑞翔厂区电力土建(管廊)建设工程 | D17: 2026.7.7号收到新德润打款给胡崇文：瑞翔厂区电力 | E17: 新德润 | I17: =IF($H17="","",N($H17)*N($G17)) | J17: =IF($H17="","",N($H17)-N($I17)) | K17: 0 | L17: =IF($A17="","",SUMIF($A$4:$A17,$A17,$J$4:$J17)-SUMIF($A$4:$A17,$A17,$K$4:$K17)) -> 0 | M17: =IF($H17="","",N($H17)) | O17: 49800 | P17: =IF($A17="","",SUMIF($A$4:$A17,$A17,$M$4:$M17)-SUMIF($A$4:$A17,$A17,$N$4:$N17)-SUMIF($A$4:$A17,$A17,$O$4:$O17)) -> 0 | T17: =IF($A17="","",SUMIF($A$4:$A17,$A17,$Q$4:$Q17)-SUMIF($A$4:$A17,$A17,$R$4:$R17)-SUMIF($A$4:$A17,$A17,$S$4:$S17)) -> 0 | V17: =IF(AND($C17="",COUNTA($D17:$H17,$K17,$N17:$O17,$Q17:$S17,$U17)=0),"",IF($C17="","⚠ 没填项目名称",IF($A17="⚠目录里没有","⚠ 项目名称在目录里找不到（先加到目录）",IF($A17="","⚠ 目录里这个项目没填简称",IF(ISTEXT($G17)+ISTEXT($H17)+ISTEXT($K17)+ISTEXT($N17)+ISTEXT($O17)+ISTEXT($Q17)+ISTEXT($R17)+ISTEXT($S17)>0,"⚠ 金额列里有文字，算不进合计",IF(N($G17)>=1,"⚠ 管理费点要填百分比，如 10%",IF(AND($D17<>"",$B17=""),"△ 摘要开头没写日期（如 2026.9.21），月份取不到",IF(AND(N($H17)<>0,COUNTIFS($A$4:$A$1003,$A17,$H$4:$H$1003,$H17,$D$4:$D$1003,LEFT($D17,9)&"*")>1),"△ 同一天同项目有一样的销售金额，看看是不是录重了","✓")))))))) -> ✓ | W17: =IF($A17="","",$A17&"#"&COUNTIF($A$4:$A17,$A17)) -> 合川瑞翔#8
A18: =IF($C18="","",IFERROR(VLOOKUP($C18,目录!$B:$C,2,0)&"","⚠目录里没有")) -> 合川瑞翔 | B18: =IF($D18="","",IFERROR(MID($D18,FIND(".",$D18)+1,FIND(".",$D18,FIND(".",$D18)+1)-FIND(".",$D18)-1)&"月","")) -> 7月 | C18: 高新区厂房及配套设施提质改造项目开票到瑞翔厂区电力土建(管廊)建设工程 | D18: 2026.7.13小溪建材开票到新德润：瑞翔厂区电力土建 | E18: 新德润 | F18: 13%专票 | H18: 50220 | I18: =IF($H18="","",N($H18)*N($G18)) -> 0 | J18: =IF($H18="","",N($H18)-N($I18)) -> 50220 | K18: 50220 | L18: =IF($A18="","",SUMIF($A$4:$A18,$A18,$J$4:$J18)-SUMIF($A$4:$A18,$A18,$K$4:$K18)) -> 0 | M18: =IF($H18="","",N($H18)) -> 50220 | P18: =IF($A18="","",SUMIF($A$4:$A18,$A18,$M$4:$M18)-SUMIF($A$4:$A18,$A18,$N$4:$N18)-SUMIF($A$4:$A18,$A18,$O$4:$O18)) -> 50220 | T18: =IF($A18="","",SUMIF($A$4:$A18,$A18,$Q$4:$Q18)-SUMIF($A$4:$A18,$A18,$R$4:$R18)-SUMIF($A$4:$A18,$A18,$S$4:$S18)) -> 0 | V18: =IF(AND($C18="",COUNTA($D18:$H18,$K18,$N18:$O18,$Q18:$S18,$U18)=0),"",IF($C18="","⚠ 没填项目名称",IF($A18="⚠目录里没有","⚠ 项目名称在目录里找不到（先加到目录）",IF($A18="","⚠ 目录里这个项目没填简称",IF(ISTEXT($G18)+ISTEXT($H18)+ISTEXT($K18)+ISTEXT($N18)+ISTEXT($O18)+ISTEXT($Q18)+ISTEXT($R18)+ISTEXT($S18)>0,"⚠ 金额列里有文字，算不进合计",IF(N($G18)>=1,"⚠ 管理费点要填百分比，如 10%",IF(AND($D18<>"",$B18=""),"△ 摘要开头没写日期（如 2026.9.21），月份取不到",IF(AND(N($H18)<>0,COUNTIFS($A$4:$A$1003,$A18,$H$4:$H$1003,$H18,$D$4:$D$1003,LEFT($D18,9)&"*")>1),"△ 同一天同项目有一样的销售金额，看看是不是录重了","✓")))))))) -> ✓ | W18: =IF($A18="","",$A18&"#"&COUNTIF($A$4:$A18,$A18)) -> 合川瑞翔#9
A19: =IF($C19="","",IFERROR(VLOOKUP($C19,目录!$B:$C,2,0)&"","⚠目录里没有")) -> 合川瑞翔 | B19: =IF($D19="","",IFERROR(MID($D19,FIND(".",$D19)+1,FIND(".",$D19,FIND(".",$D19)+1)-FIND(".",$D19)-1)&"月","")) -> 7月 | C19: 高新区厂房及配套设施提质改造项目开票到瑞翔厂区电力土建(管廊)建设工程 | D19: 2026.7.15小溪建材收到新德润打款：瑞翔厂区电力 | E19: 新德润 | I19: =IF($H19="","",N($H19)*N($G19)) | J19: =IF($H19="","",N($H19)-N($I19)) | L19: =IF($A19="","",SUMIF($A$4:$A19,$A19,$J$4:$J19)-SUMIF($A$4:$A19,$A19,$K$4:$K19)) -> 0 | M19: =IF($H19="","",N($H19)) | O19: 50220 | P19: =IF($A19="","",SUMIF($A$4:$A19,$A19,$M$4:$M19)-SUMIF($A$4:$A19,$A19,$N$4:$N19)-SUMIF($A$4:$A19,$A19,$O$4:$O19)) -> 0 | T19: =IF($A19="","",SUMIF($A$4:$A19,$A19,$Q$4:$Q19)-SUMIF($A$4:$A19,$A19,$R$4:$R19)-SUMIF($A$4:$A19,$A19,$S$4:$S19)) -> 0 | V19: =IF(AND($C19="",COUNTA($D19:$H19,$K19,$N19:$O19,$Q19:$S19,$U19)=0),"",IF($C19="","⚠ 没填项目名称",IF($A19="⚠目录里没有","⚠ 项目名称在目录里找不到（先加到目录）",IF($A19="","⚠ 目录里这个项目没填简称",IF(ISTEXT($G19)+ISTEXT($H19)+ISTEXT($K19)+ISTEXT($N19)+ISTEXT($O19)+ISTEXT($Q19)+ISTEXT($R19)+ISTEXT($S19)>0,"⚠ 金额列里有文字，算不进合计",IF(N($G19)>=1,"⚠ 管理费点要填百分比，如 10%",IF(AND($D19<>"",$B19=""),"△ 摘要开头没写日期（如 2026.9.21），月份取不到",IF(AND(N($H19)<>0,COUNTIFS($A$4:$A$1003,$A19,$H$4:$H$1003,$H19,$D$4:$D$1003,LEFT($D19,9)&"*")>1),"△ 同一天同项目有一样的销售金额，看看是不是录重了","✓")))))))) -> ✓ | W19: =IF($A19="","",$A19&"#"&COUNTIF($A$4:$A19,$A19)) -> 合川瑞翔#10
A20: =IF($C20="","",IFERROR(VLOOKUP($C20,目录!$B:$C,2,0)&"","⚠目录里没有")) -> 合川瑞翔 | B20: =IF($D20="","",IFERROR(MID($D20,FIND(".",$D20)+1,FIND(".",$D20,FIND(".",$D20)+1)-FIND(".",$D20)-1)&"月","")) -> 7月 | C20: 高新区厂房及配套设施提质改造项目开票到瑞翔厂区电力土建(管廊)建设工程 | D20: 2026.7.13旭承机械开票到新德润：瑞翔厂区电力土建 | E20: 新德润 | F20: 1%普票 | H20: 100000 | I20: =IF($H20="","",N($H20)*N($G20)) -> 0 | J20: =IF($H20="","",N($H20)-N($I20)) -> 100000 | K20: 100000 | L20: =IF($A20="","",SUMIF($A$4:$A20,$A20,$J$4:$J20)-SUMIF($A$4:$A20,$A20,$K$4:$K20)) -> 0 | M20: =IF($H20="","",N($H20)) -> 100000 | P20: =IF($A20="","",SUMIF($A$4:$A20,$A20,$M$4:$M20)-SUMIF($A$4:$A20,$A20,$N$4:$N20)-SUMIF($A$4:$A20,$A20,$O$4:$O20)) -> 100000 | T20: =IF($A20="","",SUMIF($A$4:$A20,$A20,$Q$4:$Q20)-SUMIF($A$4:$A20,$A20,$R$4:$R20)-SUMIF($A$4:$A20,$A20,$S$4:$S20)) -> 0 | V20: =IF(AND($C20="",COUNTA($D20:$H20,$K20,$N20:$O20,$Q20:$S20,$U20)=0),"",IF($C20="","⚠ 没填项目名称",IF($A20="⚠目录里没有","⚠ 项目名称在目录里找不到（先加到目录）",IF($A20="","⚠ 目录里这个项目没填简称",IF(ISTEXT($G20)+ISTEXT($H20)+ISTEXT($K20)+ISTEXT($N20)+ISTEXT($O20)+ISTEXT($Q20)+ISTEXT($R20)+ISTEXT($S20)>0,"⚠ 金额列里有文字，算不进合计",IF(N($G20)>=1,"⚠ 管理费点要填百分比，如 10%",IF(AND($D20<>"",$B20=""),"△ 摘要开头没写日期（如 2026.9.21），月份取不到",IF(AND(N($H20)<>0,COUNTIFS($A$4:$A$1003,$A20,$H$4:$H$1003,$H20,$D$4:$D$1003,LEFT($D20,9)&"*")>1),"△ 同一天同项目有一样的销售金额，看看是不是录重了","✓")))))))) -> ✓ | W20: =IF($A20="","",$A20&"#"&COUNTIF($A$4:$A20,$A20)) -> 合川瑞翔#11
A21: =IF($C21="","",IFERROR(VLOOKUP($C21,目录!$B:$C,2,0)&"","⚠目录里没有")) -> 合川瑞翔 | B21: =IF($D21="","",IFERROR(MID($D21,FIND(".",$D21)+1,FIND(".",$D21,FIND(".",$D21)+1)-FIND(".",$D21)-1)&"月","")) -> 7月 | C21: 高新区厂房及配套设施提质改造项目开票到瑞翔厂区电力土建(管廊)建设工程 | D21: 2026.7.15旭承机械收到新德润打款：瑞翔厂区电力土建 | E21: 新德润 | I21: =IF($H21="","",N($H21)*N($G21)) | J21: =IF($H21="","",N($H21)-N($I21)) | L21: =IF($A21="","",SUMIF($A$4:$A21,$A21,$J$4:$J21)-SUMIF($A$4:$A21,$A21,$K$4:$K21)) -> 0 | M21: =IF($H21="","",N($H21)) | O21: 100000 | P21: =IF($A21="","",SUMIF($A$4:$A21,$A21,$M$4:$M21)-SUMIF($A$4:$A21,$A21,$N$4:$N21)-SUMIF($A$4:$A21,$A21,$O$4:$O21)) -> 0 | T21: =IF($A21="","",SUMIF($A$4:$A21,$A21,$Q$4:$Q21)-SUMIF($A$4:$A21,$A21,$R$4:$R21)-SUMIF($A$4:$A21,$A21,$S$4:$S21)) -> 0 | V21: =IF(AND($C21="",COUNTA($D21:$H21,$K21,$N21:$O21,$Q21:$S21,$U21)=0),"",IF($C21="","⚠ 没填项目名称",IF($A21="⚠目录里没有","⚠ 项目名称在目录里找不到（先加到目录）",IF($A21="","⚠ 目录里这个项目没填简称",IF(ISTEXT($G21)+ISTEXT($H21)+ISTEXT($K21)+ISTEXT($N21)+ISTEXT($O21)+ISTEXT($Q21)+ISTEXT($R21)+ISTEXT($S21)>0,"⚠ 金额列里有文字，算不进合计",IF(N($G21)>=1,"⚠ 管理费点要填百分比，如 10%",IF(AND($D21<>"",$B21=""),"△ 摘要开头没写日期（如 2026.9.21），月份取不到",IF(AND(N($H21)<>0,COUNTIFS($A$4:$A$1003,$A21,$H$4:$H$1003,$H21,$D$4:$D$1003,LEFT($D21,9)&"*")>1),"△ 同一天同项目有一样的销售金额，看看是不是录重了","✓")))))))) -> ✓ | W21: =IF($A21="","",$A21&"#"&COUNTIF($A$4:$A21,$A21)) -> 合川瑞翔#12
A22: =IF($C22="","",IFERROR(VLOOKUP($C22,目录!$B:$C,2,0)&"","⚠目录里没有")) -> 合川瑞翔 | B22: =IF($D22="","",IFERROR(MID($D22,FIND(".",$D22)+1,FIND(".",$D22,FIND(".",$D22)+1)-FIND(".",$D22)-1)&"月","")) -> 7月 | C22: 高新区厂房及配套设施提质改造项目开票到瑞翔厂区电力土建(管廊)建设工程 | D22: 2026.7.14凯樽物资开票到新德润：瑞翔厂区电力土建 | E22: 新德润 | F22: 13%专票 | H22: 49780 | I22: =IF($H22="","",N($H22)*N($G22)) -> 0 | J22: =IF($H22="","",N($H22)-N($I22)) -> 49780 | K22: 49780 | L22: =IF($A22="","",SUMIF($A$4:$A22,$A22,$J$4:$J22)-SUMIF($A$4:$A22,$A22,$K$4:$K22)) -> 0 | M22: =IF($H22="","",N($H22)) -> 49780 | P22: =IF($A22="","",SUMIF($A$4:$A22,$A22,$M$4:$M22)-SUMIF($A$4:$A22,$A22,$N$4:$N22)-SUMIF($A$4:$A22,$A22,$O$4:$O22)) -> 49780 | T22: =IF($A22="","",SUMIF($A$4:$A22,$A22,$Q$4:$Q22)-SUMIF($A$4:$A22,$A22,$R$4:$R22)-SUMIF($A$4:$A22,$A22,$S$4:$S22)) -> 0 | V22: =IF(AND($C22="",COUNTA($D22:$H22,$K22,$N22:$O22,$Q22:$S22,$U22)=0),"",IF($C22="","⚠ 没填项目名称",IF($A22="⚠目录里没有","⚠ 项目名称在目录里找不到（先加到目录）",IF($A22="","⚠ 目录里这个项目没填简称",IF(ISTEXT($G22)+ISTEXT($H22)+ISTEXT($K22)+ISTEXT($N22)+ISTEXT($O22)+ISTEXT($Q22)+ISTEXT($R22)+ISTEXT($S22)>0,"⚠ 金额列里有文字，算不进合计",IF(N($G22)>=1,"⚠ 管理费点要填百分比，如 10%",IF(AND($D22<>"",$B22=""),"△ 摘要开头没写日期（如 2026.9.21），月份取不到",IF(AND(N($H22)<>0,COUNTIFS($A$4:$A$1003,$A22,$H$4:$H$1003,$H22,$D$4:$D$1003,LEFT($D22,9)&"*")>1),"△ 同一天同项目有一样的销售金额，看看是不是录重了","✓")))))))) -> ✓ | W22: =IF($A22="","",$A22&"#"&COUNTIF($A$4:$A22,$A22)) -> 合川瑞翔#13
A23: =IF($C23="","",IFERROR(VLOOKUP($C23,目录!$B:$C,2,0)&"","⚠目录里没有")) -> 合川瑞翔 | B23: =IF($D23="","",IFERROR(MID($D23,FIND(".",$D23)+1,FIND(".",$D23,FIND(".",$D23)+1)-FIND(".",$D23)-1)&"月","")) -> 7月 | C23: 高新区厂房及配套设施提质改造项目开票到瑞翔厂区电力土建(管廊)建设工程 | D23: 2026.7.15凯樽物资收到新德润打款：瑞翔厂区电力土建 | E23: 新德润 | I23: =IF($H23="","",N($H23)*N($G23)) | J23: =IF($H23="","",N($H23)-N($I23)) | L23: =IF($A23="","",SUMIF($A$4:$A23,$A23,$J$4:$J23)-SUMIF($A$4:$A23,$A23,$K$4:$K23)) -> 0 | M23: =IF($H23="","",N($H23)) | O23: 49780 | P23: =IF($A23="","",SUMIF($A$4:$A23,$A23,$M$4:$M23)-SUMIF($A$4:$A23,$A23,$N$4:$N23)-SUMIF($A$4:$A23,$A23,$O$4:$O23)) -> 0 | T23: =IF($A23="","",SUMIF($A$4:$A23,$A23,$Q$4:$Q23)-SUMIF($A$4:$A23,$A23,$R$4:$R23)-SUMIF($A$4:$A23,$A23,$S$4:$S23)) -> 0 | V23: =IF(AND($C23="",COUNTA($D23:$H23,$K23,$N23:$O23,$Q23:$S23,$U23)=0),"",IF($C23="","⚠ 没填项目名称",IF($A23="⚠目录里没有","⚠ 项目名称在目录里找不到（先加到目录）",IF($A23="","⚠ 目录里这个项目没填简称",IF(ISTEXT($G23)+ISTEXT($H23)+ISTEXT($K23)+ISTEXT($N23)+ISTEXT($O23)+ISTEXT($Q23)+ISTEXT($R23)+ISTEXT($S23)>0,"⚠ 金额列里有文字，算不进合计",IF(N($G23)>=1,"⚠ 管理费点要填百分比，如 10%",IF(AND($D23<>"",$B23=""),"△ 摘要开头没写日期（如 2026.9.21），月份取不到",IF(AND(N($H23)<>0,COUNTIFS($A$4:$A$1003,$A23,$H$4:$H$1003,$H23,$D$4:$D$1003,LEFT($D23,9)&"*")>1),"△ 同一天同项目有一样的销售金额，看看是不是录重了","✓")))))))) -> ✓ | W23: =IF($A23="","",$A23&"#"&COUNTIF($A$4:$A23,$A23)) -> 合川瑞翔#14
A24: =IF($C24="","",IFERROR(VLOOKUP($C24,目录!$B:$C,2,0)&"","⚠目录里没有")) -> 合川瑞翔 | B24: =IF($D24="","",IFERROR(MID($D24,FIND(".",$D24)+1,FIND(".",$D24,FIND(".",$D24)+1)-FIND(".",$D24)-1)&"月","")) -> 9月 | C24: 高新区厂房及配套设施提质改造项目开票到瑞翔厂区电力土建(管廊)建设工程 | D24: 2026.9.14新德润代胡崇文支付宜宾翠屏货款：42800-39473.83=3326.17 | E24: 新德润 | I24: =IF($H24="","",N($H24)*N($G24)) | J24: =IF($H24="","",N($H24)-N($I24)) | L24: =IF($A24="","",SUMIF($A$4:$A24,$A24,$J$4:$J24)-SUMIF($A$4:$A24,$A24,$K$4:$K24)) -> 0 | M24: =IF($H24="","",N($H24)) | O24: 3326.17 | P24: =IF($A24="","",SUMIF($A$4:$A24,$A24,$M$4:$M24)-SUMIF($A$4:$A24,$A24,$N$4:$N24)-SUMIF($A$4:$A24,$A24,$O$4:$O24)) -> -3326.17 | T24: =IF($A24="","",SUMIF($A$4:$A24,$A24,$Q$4:$Q24)-SUMIF($A$4:$A24,$A24,$R$4:$R24)-SUMIF($A$4:$A24,$A24,$S$4:$S24)) -> 0 | V24: =IF(AND($C24="",COUNTA($D24:$H24,$K24,$N24:$O24,$Q24:$S24,$U24)=0),"",IF($C24="","⚠ 没填项目名称",IF($A24="⚠目录里没有","⚠ 项目名称在目录里找不到（先加到目录）",IF($A24="","⚠ 目录里这个项目没填简称",IF(ISTEXT($G24)+ISTEXT($H24)+ISTEXT($K24)+ISTEXT($N24)+ISTEXT($O24)+ISTEXT($Q24)+ISTEXT($R24)+ISTEXT($S24)>0,"⚠ 金额列里有文字，算不进合计",IF(N($G24)>=1,"⚠ 管理费点要填百分比，如 10%",IF(AND($D24<>"",$B24=""),"△ 摘要开头没写日期（如 2026.9.21），月份取不到",IF(AND(N($H24)<>0,COUNTIFS($A$4:$A$1003,$A24,$H$4:$H$1003,$H24,$D$4:$D$1003,LEFT($D24,9)&"*")>1),"△ 同一天同项目有一样的销售金额，看看是不是录重了","✓")))))))) -> ✓ | W24: =IF($A24="","",$A24&"#"&COUNTIF($A$4:$A24,$A24)) -> 合川瑞翔#15
A25: =IF($C25="","",IFERROR(VLOOKUP($C25,目录!$B:$C,2,0)&"","⚠目录里没有")) -> 铜城2回、玉璟尚线、铁井一回、淮拦线4 | B25: =IF($D25="","",IFERROR(MID($D25,FIND(".",$D25)+1,FIND(".",$D25,FIND(".",$D25)+1)-FIND(".",$D25)-1)&"月","")) -> 6月 | C25: 重庆铜梁铜城2回金龙物业管理有限公司10kV业扩配套工程 | D25: 2026.6.24新德润开票民能：铜城2回，10%管理费 | E25: 民能 | F25: 3%专票 | G25: 0.1 | H25: 4002.66 | I25: =IF($H25="","",N($H25)*N($G25)) -> 400.266 | J25: =IF($H25="","",N($H25)-N($I25)) -> 3602.394 | L25: =IF($A25="","",SUMIF($A$4:$A25,$A25,$J$4:$J25)-SUMIF($A$4:$A25,$A25,$K$4:$K25)) -> 3602.394 | M25: =IF($H25="","",N($H25)) -> 4002.66 | P25: =IF($A25="","",SUMIF($A$4:$A25,$A25,$M$4:$M25)-SUMIF($A$4:$A25,$A25,$N$4:$N25)-SUMIF($A$4:$A25,$A25,$O$4:$O25)) -> 4002.66 | T25: =IF($A25="","",SUMIF($A$4:$A25,$A25,$Q$4:$Q25)-SUMIF($A$4:$A25,$A25,$R$4:$R25)-SUMIF($A$4:$A25,$A25,$S$4:$S25)) -> 0 | V25: =IF(AND($C25="",COUNTA($D25:$H25,$K25,$N25:$O25,$Q25:$S25,$U25)=0),"",IF($C25="","⚠ 没填项目名称",IF($A25="⚠目录里没有","⚠ 项目名称在目录里找不到（先加到目录）",IF($A25="","⚠ 目录里这个项目没填简称",IF(ISTEXT($G25)+ISTEXT($H25)+ISTEXT($K25)+ISTEXT($N25)+ISTEXT($O25)+ISTEXT($Q25)+ISTEXT($R25)+ISTEXT($S25)>0,"⚠ 金额列里有文字，算不进合计",IF(N($G25)>=1,"⚠ 管理费点要填百分比，如 10%",IF(AND($D25<>"",$B25=""),"△ 摘要开头没写日期（如 2026.9.21），月份取不到",IF(AND(N($H25)<>0,COUNTIFS($A$4:$A$1003,$A25,$H$4:$H$1003,$H25,$D$4:$D$1003,LEFT($D25,9)&"*")>1),"△ 同一天同项目有一样的销售金额，看看是不是录重了","✓")))))))) -> ✓ | W25: =IF($A25="","",$A25&"#"&COUNTIF($A$4:$A25,$A25)) -> 铜城2回、玉璟尚线、铁井一回、淮拦线4#1
A26: =IF($C26="","",IFERROR(VLOOKUP($C26,目录!$B:$C,2,0)&"","⚠目录里没有")) -> 铜城2回、玉璟尚线、铁井一回、淮拦线4 | B26: =IF($D26="","",IFERROR(MID($D26,FIND(".",$D26)+1,FIND(".",$D26,FIND(".",$D26)+1)-FIND(".",$D26)-1)&"月","")) -> 6月 | C26: 重庆铜梁玉璟尚线金龙物业管理有限公司10kV业扩配套工程 | D26: 2026.6.24新德润开票民能：玉璟尚线，10%管理费 | E26: 民能 | F26: 3%专票 | G26: 0.1 | H26: 13079.84 | I26: =IF($H26="","",N($H26)*N($G26)) -> 1307.984 | J26: =IF($H26="","",N($H26)-N($I26)) -> 11771.856 | L26: =IF($A26="","",SUMIF($A$4:$A26,$A26,$J$4:$J26)-SUMIF($A$4:$A26,$A26,$K$4:$K26)) -> 15374.25 | M26: =IF($H26="","",N($H26)) -> 13079.84 | P26: =IF($A26="","",SUMIF($A$4:$A26,$A26,$M$4:$M26)-SUMIF($A$4:$A26,$A26,$N$4:$N26)-SUMIF($A$4:$A26,$A26,$O$4:$O26)) -> 17082.5 | T26: =IF($A26="","",SUMIF($A$4:$A26,$A26,$Q$4:$Q26)-SUMIF($A$4:$A26,$A26,$R$4:$R26)-SUMIF($A$4:$A26,$A26,$S$4:$S26)) -> 0 | V26: =IF(AND($C26="",COUNTA($D26:$H26,$K26,$N26:$O26,$Q26:$S26,$U26)=0),"",IF($C26="","⚠ 没填项目名称",IF($A26="⚠目录里没有","⚠ 项目名称在目录里找不到（先加到目录）",IF($A26="","⚠ 目录里这个项目没填简称",IF(ISTEXT($G26)+ISTEXT($H26)+ISTEXT($K26)+ISTEXT($N26)+ISTEXT($O26)+ISTEXT($Q26)+ISTEXT($R26)+ISTEXT($S26)>0,"⚠ 金额列里有文字，算不进合计",IF(N($G26)>=1,"⚠ 管理费点要填百分比，如 10%",IF(AND($D26<>"",$B26=""),"△ 摘要开头没写日期（如 2026.9.21），月份取不到",IF(AND(N($H26)<>0,COUNTIFS($A$4:$A$1003,$A26,$H$4:$H$1003,$H26,$D$4:$D$1003,LEFT($D26,9)&"*")>1),"△ 同一天同项目有一样的销售金额，看看是不是录重了","✓")))))))) -> ✓ | W26: =IF($A26="","",$A26&"#"&COUNTIF($A$4:$A26,$A26)) -> 铜城2回、玉璟尚线、铁井一回、淮拦线4#2
A27: =IF($C27="","",IFERROR(VLOOKUP($C27,目录!$B:$C,2,0)&"","⚠目录里没有")) -> 铜城2回、玉璟尚线、铁井一回、淮拦线4 | B27: =IF($D27="","",IFERROR(MID($D27,FIND(".",$D27)+1,FIND(".",$D27,FIND(".",$D27)+1)-FIND(".",$D27)-1)&"月","")) -> 6月 | C27: 重庆铜梁铁井一回1#环网柜等6个10kV老旧环网柜改造工程(安装) | D27: 2026.6.24新德润开票民能：铁井一回1#环网柜，10%管理费 | E27: 民能 | F27: 3%专票 | G27: 0.1 | H27: 47546.28 | I27: =IF($H27="","",N($H27)*N($G27)) -> 4754.628 | J27: =IF($H27="","",N($H27)-N($I27)) -> 42791.652 | L27: =IF($A27="","",SUMIF($A$4:$A27,$A27,$J$4:$J27)-SUMIF($A$4:$A27,$A27,$K$4:$K27)) -> 58165.902 | M27: =IF($H27="","",N($H27)) -> 47546.28 | P27: =IF($A27="","",SUMIF($A$4:$A27,$A27,$M$4:$M27)-SUMIF($A$4:$A27,$A27,$N$4:$N27)-SUMIF($A$4:$A27,$A27,$O$4:$O27)) -> 64628.78 | T27: =IF($A27="","",SUMIF($A$4:$A27,$A27,$Q$4:$Q27)-SUMIF($A$4:$A27,$A27,$R$4:$R27)-SUMIF($A$4:$A27,$A27,$S$4:$S27)) -> 0 | V27: =IF(AND($C27="",COUNTA($D27:$H27,$K27,$N27:$O27,$Q27:$S27,$U27)=0),"",IF($C27="","⚠ 没填项目名称",IF($A27="⚠目录里没有","⚠ 项目名称在目录里找不到（先加到目录）",IF($A27="","⚠ 目录里这个项目没填简称",IF(ISTEXT($G27)+ISTEXT($H27)+ISTEXT($K27)+ISTEXT($N27)+ISTEXT($O27)+ISTEXT($Q27)+ISTEXT($R27)+ISTEXT($S27)>0,"⚠ 金额列里有文字，算不进合计",IF(N($G27)>=1,"⚠ 管理费点要填百分比，如 10%",IF(AND($D27<>"",$B27=""),"△ 摘要开头没写日期（如 2026.9.21），月份取不到",IF(AND(N($H27)<>0,COUNTIFS($A$4:$A$1003,$A27,$H$4:$H$1003,$H27,$D$4:$D$1003,LEFT($D27,9)&"*")>1),"△ 同一天同项目有一样的销售金额，看看是不是录重了","✓")))))))) -> ✓ | W27: =IF($A27="","",$A27&"#"&COUNTIF($A$4:$A27,$A27)) -> 铜城2回、玉璟尚线、铁井一回、淮拦线4#3
A28: =IF($C28="","",IFERROR(VLOOKUP($C28,目录!$B:$C,2,0)&"","⚠目录里没有")) -> 铜城2回、玉璟尚线、铁井一回、淮拦线4 | B28: =IF($D28="","",IFERROR(MID($D28,FIND(".",$D28)+1,FIND(".",$D28,FIND(".",$D28)+1)-FIND(".",$D28)-1)&"月","")) -> 6月 | C28: 重庆铜梁淮拦线4#环网柜等6个10kV老旧环网柜改造工程（安装） | D28: 2026.6.24新德润开票民能：淮拦线4#环网柜，10%管理费 | E28: 民能 | F28: 3%专票 | G28: 0.1 | H28: 56969.32 | I28: =IF($H28="","",N($H28)*N($G28)) -> 5696.932 | J28: =IF($H28="","",N($H28)-N($I28)) -> 51272.388 | L28: =IF($A28="","",SUMIF($A$4:$A28,$A28,$J$4:$J28)-SUMIF($A$4:$A28,$A28,$K$4:$K28)) -> 109438.29 | M28: =IF($H28="","",N($H28)) -> 56969.32 | P28: =IF($A28="","",SUMIF($A$4:$A28,$A28,$M$4:$M28)-SUMIF($A$4:$A28,$A28,$N$4:$N28)-SUMIF($A$4:$A28,$A28,$O$4:$O28)) -> 121598.1 | T28: =IF($A28="","",SUMIF($A$4:$A28,$A28,$Q$4:$Q28)-SUMIF($A$4:$A28,$A28,$R$4:$R28)-SUMIF($A$4:$A28,$A28,$S$4:$S28)) -> 0 | V28: =IF(AND($C28="",COUNTA($D28:$H28,$K28,$N28:$O28,$Q28:$S28,$U28)=0),"",IF($C28="","⚠ 没填项目名称",IF($A28="⚠目录里没有","⚠ 项目名称在目录里找不到（先加到目录）",IF($A28="","⚠ 目录里这个项目没填简称",IF(ISTEXT($G28)+ISTEXT($H28)+ISTEXT($K28)+ISTEXT($N28)+ISTEXT($O28)+ISTEXT($Q28)+ISTEXT($R28)+ISTEXT($S28)>0,"⚠ 金额列里有文字，算不进合计",IF(N($G28)>=1,"⚠ 管理费点要填百分比，如 10%",IF(AND($D28<>"",$B28=""),"△ 摘要开头没写日期（如 2026.9.21），月份取不到",IF(AND(N($H28)<>0,COUNTIFS($A$4:$A$1003,$A28,$H$4:$H$1003,$H28,$D$4:$D$1003,LEFT($D28,9)&"*")>1),"△ 同一天同项目有一样的销售金额，看看是不是录重了","✓")))))))) -> ✓ | W28: =IF($A28="","",$A28&"#"&COUNTIF($A$4:$A28,$A28)) -> 铜城2回、玉璟尚线、铁井一回、淮拦线4#4
A29: =IF($C29="","",IFERROR(VLOOKUP($C29,目录!$B:$C,2,0)&"","⚠目录里没有")) -> 铜城2回、玉璟尚线、铁井一回、淮拦线4 | B29: =IF($D29="","",IFERROR(MID($D29,FIND(".",$D29)+1,FIND(".",$D29,FIND(".",$D29)+1)-FIND(".",$D29)-1)&"月","")) -> 6月 | C29: 重庆铜梁淮拦线4#环网柜等6个10kV老旧环网柜改造工程（安装） | D29: 2026.6.23桐桐建材开票到新德润：淮拦、铁井、玉璟、铜城2回 | E29: 新德润 | F29: 1%普票 | I29: =IF($H29="","",N($H29)*N($G29)) | J29: =IF($H29="","",N($H29)-N($I29)) | K29: 67200 | L29: =IF($A29="","",SUMIF($A$4:$A29,$A29,$J$4:$J29)-SUMIF($A$4:$A29,$A29,$K$4:$K29)) -> 42238.29 | M29: =IF($H29="","",N($H29)) | P29: =IF($A29="","",SUMIF($A$4:$A29,$A29,$M$4:$M29)-SUMIF($A$4:$A29,$A29,$N$4:$N29)-SUMIF($A$4:$A29,$A29,$O$4:$O29)) -> 121598.1 | T29: =IF($A29="","",SUMIF($A$4:$A29,$A29,$Q$4:$Q29)-SUMIF($A$4:$A29,$A29,$R$4:$R29)-SUMIF($A$4:$A29,$A29,$S$4:$S29)) -> 0 | V29: =IF(AND($C29="",COUNTA($D29:$H29,$K29,$N29:$O29,$Q29:$S29,$U29)=0),"",IF($C29="","⚠ 没填项目名称",IF($A29="⚠目录里没有","⚠ 项目名称在目录里找不到（先加到目录）",IF($A29="","⚠ 目录里这个项目没填简称",IF(ISTEXT($G29)+ISTEXT($H29)+ISTEXT($K29)+ISTEXT($N29)+ISTEXT($O29)+ISTEXT($Q29)+ISTEXT($R29)+ISTEXT($S29)>0,"⚠ 金额列里有文字，算不进合计",IF(N($G29)>=1,"⚠ 管理费点要填百分比，如 10%",IF(AND($D29<>"",$B29=""),"△ 摘要开头没写日期（如 2026.9.21），月份取不到",IF(AND(N($H29)<>0,COUNTIFS($A$4:$A$1003,$A29,$H$4:$H$1003,$H29,$D$4:$D$1003,LEFT($D29,9)&"*")>1),"△ 同一天同项目有一样的销售金额，看看是不是录重了","✓")))))))) -> ✓ | W29: =IF($A29="","",$A29&"#"&COUNTIF($A$4:$A29,$A29)) -> 铜城2回、玉璟尚线、铁井一回、淮拦线4#5
A30: =IF($C30="","",IFERROR(VLOOKUP($C30,目录!$B:$C,2,0)&"","⚠目录里没有")) -> 铜城2回、玉璟尚线、铁井一回、淮拦线4 | B30: =IF($D30="","",IFERROR(MID($D30,FIND(".",$D30)+1,FIND(".",$D30,FIND(".",$D30)+1)-FIND(".",$D30)-1)&"月","")) -> 6月 | C30: 重庆铜梁淮拦线4#环网柜等6个10kV老旧环网柜改造工程（安装） | D30: 2026.6.24宜宾翠屏开票到新德润淮：淮拦、铁井、玉璟、铜城2回 | E30: 新德润 | F30: 1%普票 | I30: =IF($H30="","",N($H30)*N($G30)) | J30: =IF($H30="","",N($H30)-N($I30)) | K30: 42800 | L30: =IF($A30="","",SUMIF($A$4:$A30,$A30,$J$4:$J30)-SUMIF($A$4:$A30,$A30,$K$4:$K30)) -> -561.71 | M30: =IF($H30="","",N($H30)) | P30: =IF($A30="","",SUMIF($A$4:$A30,$A30,$M$4:$M30)-SUMIF($A$4:$A30,$A30,$N$4:$N30)-SUMIF($A$4:$A30,$A30,$O$4:$O30)) -> 121598.1 | T30: =IF($A30="","",SUMIF($A$4:$A30,$A30,$Q$4:$Q30)-SUMIF($A$4:$A30,$A30,$R$4:$R30)-SUMIF($A$4:$A30,$A30,$S$4:$S30)) -> 0 | V30: =IF(AND($C30="",COUNTA($D30:$H30,$K30,$N30:$O30,$Q30:$S30,$U30)=0),"",IF($C30="","⚠ 没填项目名称",IF($A30="⚠目录里没有","⚠ 项目名称在目录里找不到（先加到目录）",IF($A30="","⚠ 目录里这个项目没填简称",IF(ISTEXT($G30)+ISTEXT($H30)+ISTEXT($K30)+ISTEXT($N30)+ISTEXT($O30)+ISTEXT($Q30)+ISTEXT($R30)+ISTEXT($S30)>0,"⚠ 金额列里有文字，算不进合计",IF(N($G30)>=1,"⚠ 管理费点要填百分比，如 10%",IF(AND($D30<>"",$B30=""),"△ 摘要开头没写日期（如 2026.9.21），月份取不到",IF(AND(N($H30)<>0,COUNTIFS($A$4:$A$1003,$A30,$H$4:$H$1003,$H30,$D$4:$D$1003,LEFT($D30,9)&"*")>1),"△ 同一天同项目有一样的销售金额，看看是不是录重了","✓")))))))) -> ✓ | W30: =IF($A30="","",$A30&"#"&COUNTIF($A$4:$A30,$A30)) -> 铜城2回、玉璟尚线、铁井一回、淮拦线4#6
A31: =IF($C31="","",IFERROR(VLOOKUP($C31,目录!$B:$C,2,0)&"","⚠目录里没有")) -> 铜城2回、玉璟尚线、铁井一回、淮拦线4 | B31: =IF($D31="","",IFERROR(MID($D31,FIND(".",$D31)+1,FIND(".",$D31,FIND(".",$D31)+1)-FIND(".",$D31)-1)&"月","")) -> 9月 | C31: 重庆铜梁淮拦线4#环网柜等6个10kV老旧环网柜改造工程（安装） | D31: 2026.9.14新德润扣8月民能农民工工资个税 | E31: 新德润 | F31: 1%普票 | I31: =IF($H31="","",N($H31)*N($G31)) | J31: =IF($H31="","",N($H31)-N($I31)) | K31: 57000 | L31: =IF($A31="","",SUMIF($A$4:$A31,$A31,$J$4:$J31)-SUMIF($A$4:$A31,$A31,$K$4:$K31)) -> -57561.71 | M31: =IF($H31="","",N($H31)) | O31: 810 | P31: =IF($A31="","",SUMIF($A$4:$A31,$A31,$M$4:$M31)-SUMIF($A$4:$A31,$A31,$N$4:$N31)-SUMIF($A$4:$A31,$A31,$O$4:$O31)) -> 120788.1 | T31: =IF($A31="","",SUMIF($A$4:$A31,$A31,$Q$4:$Q31)-SUMIF($A$4:$A31,$A31,$R$4:$R31)-SUMIF($A$4:$A31,$A31,$S$4:$S31)) -> 0 | V31: =IF(AND($C31="",COUNTA($D31:$H31,$K31,$N31:$O31,$Q31:$S31,$U31)=0),"",IF($C31="","⚠ 没填项目名称",IF($A31="⚠目录里没有","⚠ 项目名称在目录里找不到（先加到目录）",IF($A31="","⚠ 目录里这个项目没填简称",IF(ISTEXT($G31)+ISTEXT($H31)+ISTEXT($K31)+ISTEXT($N31)+ISTEXT($O31)+ISTEXT($Q31)+ISTEXT($R31)+ISTEXT($S31)>0,"⚠ 金额列里有文字，算不进合计",IF(N($G31)>=1,"⚠ 管理费点要填百分比，如 10%",IF(AND($D31<>"",$B31=""),"△ 摘要开头没写日期（如 2026.9.21），月份取不到",IF(AND(N($H31)<>0,COUNTIFS($A$4:$A$1003,$A31,$H$4:$H$1003,$H31,$D$4:$D$1003,LEFT($D31,9)&"*")>1),"△ 同一天同项目有一样的销售金额，看看是不是录重了","✓")))))))) -> ✓ | W31: =IF($A31="","",$A31&"#"&COUNTIF($A$4:$A31,$A31)) -> 铜城2回、玉璟尚线、铁井一回、淮拦线4#7
A32: =IF($C32="","",IFERROR(VLOOKUP($C32,目录!$B:$C,2,0)&"","⚠目录里没有")) -> 铜城2回、玉璟尚线、铁井一回、淮拦线4 | B32: =IF($D32="","",IFERROR(MID($D32,FIND(".",$D32)+1,FIND(".",$D32,FIND(".",$D32)+1)-FIND(".",$D32)-1)&"月","")) -> 9月 | C32: 重庆铜梁铁井一回1#环网柜等6个10kV老旧环网柜改造工程(安装) | D32: 2026.9.14新德润扣8月民能农民工工资：铁井一回1 | E32: 新德润 | I32: =IF($H32="","",N($H32)*N($G32)) | J32: =IF($H32="","",N($H32)-N($I32)) | L32: =IF($A32="","",SUMIF($A$4:$A32,$A32,$J$4:$J32)-SUMIF($A$4:$A32,$A32,$K$4:$K32)) -> -57561.71 | M32: =IF($H32="","",N($H32)) | O32: 22000 | P32: =IF($A32="","",SUMIF($A$4:$A32,$A32,$M$4:$M32)-SUMIF($A$4:$A32,$A32,$N$4:$N32)-SUMIF($A$4:$A32,$A32,$O$4:$O32)) -> 98788.1 | T32: =IF($A32="","",SUMIF($A$4:$A32,$A32,$Q$4:$Q32)-SUMIF($A$4:$A32,$A32,$R$4:$R32)-SUMIF($A$4:$A32,$A32,$S$4:$S32)) -> 0 | V32: =IF(AND($C32="",COUNTA($D32:$H32,$K32,$N32:$O32,$Q32:$S32,$U32)=0),"",IF($C32="","⚠ 没填项目名称",IF($A32="⚠目录里没有","⚠ 项目名称在目录里找不到（先加到目录）",IF($A32="","⚠ 目录里这个项目没填简称",IF(ISTEXT($G32)+ISTEXT($H32)+ISTEXT($K32)+ISTEXT($N32)+ISTEXT($O32)+ISTEXT($Q32)+ISTEXT($R32)+ISTEXT($S32)>0,"⚠ 金额列里有文字，算不进合计",IF(N($G32)>=1,"⚠ 管理费点要填百分比，如 10%",IF(AND($D32<>"",$B32=""),"△ 摘要开头没写日期（如 2026.9.21），月份取不到",IF(AND(N($H32)<>0,COUNTIFS($A$4:$A$1003,$A32,$H$4:$H$1003,$H32,$D$4:$D$1003,LEFT($D32,9)&"*")>1),"△ 同一天同项目有一样的销售金额，看看是不是录重了","✓")))))))) -> ✓ | W32: =IF($A32="","",$A32&"#"&COUNTIF($A$4:$A32,$A32)) -> 铜城2回、玉璟尚线、铁井一回、淮拦线4#8
A33: =IF($C33="","",IFERROR(VLOOKUP($C33,目录!$B:$C,2,0)&"","⚠目录里没有")) -> 铜城2回、玉璟尚线、铁井一回、淮拦线4 | B33: =IF($D33="","",IFERROR(MID($D33,FIND(".",$D33)+1,FIND(".",$D33,FIND(".",$D33)+1)-FIND(".",$D33)-1)&"月","")) -> 9月 | C33: 重庆铜梁淮拦线4#环网柜等6个10kV老旧环网柜改造工程（安装） | D33: 2026.9.14新德润扣8月民能农民工工资：淮拦线4 | E33: 新德润 | I33: =IF($H33="","",N($H33)*N($G33)) | J33: =IF($H33="","",N($H33)-N($I33)) | L33: =IF($A33="","",SUMIF($A$4:$A33,$A33,$J$4:$J33)-SUMIF($A$4:$A33,$A33,$K$4:$K33)) -> -57561.71 | M33: =IF($H33="","",N($H33)) | O33: 27000 | P33: =IF($A33="","",SUMIF($A$4:$A33,$A33,$M$4:$M33)-SUMIF($A$4:$A33,$A33,$N$4:$N33)-SUMIF($A$4:$A33,$A33,$O$4:$O33)) -> 71788.1 | T33: =IF($A33="","",SUMIF($A$4:$A33,$A33,$Q$4:$Q33)-SUMIF($A$4:$A33,$A33,$R$4:$R33)-SUMIF($A$4:$A33,$A33,$S$4:$S33)) -> 0 | V33: =IF(AND($C33="",COUNTA($D33:$H33,$K33,$N33:$O33,$Q33:$S33,$U33)=0),"",IF($C33="","⚠ 没填项目名称",IF($A33="⚠目录里没有","⚠ 项目名称在目录里找不到（先加到目录）",IF($A33="","⚠ 目录里这个项目没填简称",IF(ISTEXT($G33)+ISTEXT($H33)+ISTEXT($K33)+ISTEXT($N33)+ISTEXT($O33)+ISTEXT($Q33)+ISTEXT($R33)+ISTEXT($S33)>0,"⚠ 金额列里有文字，算不进合计",IF(N($G33)>=1,"⚠ 管理费点要填百分比，如 10%",IF(AND($D33<>"",$B33=""),"△ 摘要开头没写日期（如 2026.9.21），月份取不到",IF(AND(N($H33)<>0,COUNTIFS($A$4:$A$1003,$A33,$H$4:$H$1003,$H33,$D$4:$D$1003,LEFT($D33,9)&"*")>1),"△ 同一天同项目有一样的销售金额，看看是不是录重了","✓")))))))) -> ✓ | W33: =IF($A33="","",$A33&"#"&COUNTIF($A$4:$A33,$A33)) -> 铜城2回、玉璟尚线、铁井一回、淮拦线4#9
A34: =IF($C34="","",IFERROR(VLOOKUP($C34,目录!$B:$C,2,0)&"","⚠目录里没有")) -> 铜城2回、玉璟尚线、铁井一回、淮拦线4 | B34: =IF($D34="","",IFERROR(MID($D34,FIND(".",$D34)+1,FIND(".",$D34,FIND(".",$D34)+1)-FIND(".",$D34)-1)&"月","")) -> 9月 | C34: 重庆铜梁铜城2回金龙物业管理有限公司10kV业扩配套工程 | D34: 2026.9.14新德润扣8月民能农民工工资：铜城2回 | E34: 新德润 | I34: =IF($H34="","",N($H34)*N($G34)) | J34: =IF($H34="","",N($H34)-N($I34)) | L34: =IF($A34="","",SUMIF($A$4:$A34,$A34,$J$4:$J34)-SUMIF($A$4:$A34,$A34,$K$4:$K34)) -> -57561.71 | M34: =IF($H34="","",N($H34)) | O34: 2000 | P34: =IF($A34="","",SUMIF($A$4:$A34,$A34,$M$4:$M34)-SUMIF($A$4:$A34,$A34,$N$4:$N34)-SUMIF($A$4:$A34,$A34,$O$4:$O34)) -> 69788.1 | T34: =IF($A34="","",SUMIF($A$4:$A34,$A34,$Q$4:$Q34)-SUMIF($A$4:$A34,$A34,$R$4:$R34)-SUMIF($A$4:$A34,$A34,$S$4:$S34)) -> 0 | V34: =IF(AND($C34="",COUNTA($D34:$H34,$K34,$N34:$O34,$Q34:$S34,$U34)=0),"",IF($C34="","⚠ 没填项目名称",IF($A34="⚠目录里没有","⚠ 项目名称在目录里找不到（先加到目录）",IF($A34="","⚠ 目录里这个项目没填简称",IF(ISTEXT($G34)+ISTEXT($H34)+ISTEXT($K34)+ISTEXT($N34)+ISTEXT($O34)+ISTEXT($Q34)+ISTEXT($R34)+ISTEXT($S34)>0,"⚠ 金额列里有文字，算不进合计",IF(N($G34)>=1,"⚠ 管理费点要填百分比，如 10%",IF(AND($D34<>"",$B34=""),"△ 摘要开头没写日期（如 2026.9.21），月份取不到",IF(AND(N($H34)<>0,COUNTIFS($A$4:$A$1003,$A34,$H$4:$H$1003,$H34,$D$4:$D$1003,LEFT($D34,9)&"*")>1),"△ 同一天同项目有一样的销售金额，看看是不是录重了","✓")))))))) -> ✓ | W34: =IF($A34="","",$A34&"#"&COUNTIF($A$4:$A34,$A34)) -> 铜城2回、玉璟尚线、铁井一回、淮拦线4#10
A35: =IF($C35="","",IFERROR(VLOOKUP($C35,目录!$B:$C,2,0)&"","⚠目录里没有")) -> 铜城2回、玉璟尚线、铁井一回、淮拦线4 | B35: =IF($D35="","",IFERROR(MID($D35,FIND(".",$D35)+1,FIND(".",$D35,FIND(".",$D35)+1)-FIND(".",$D35)-1)&"月","")) -> 9月 | C35: 重庆铜梁玉璟尚线金龙物业管理有限公司10kV业扩配套工程 | D35: 2026.9.14新德润扣8月民能农民工工资：玉璟尚线 | E35: 新德润 | I35: =IF($H35="","",N($H35)*N($G35)) | J35: =IF($H35="","",N($H35)-N($I35)) | L35: =IF($A35="","",SUMIF($A$4:$A35,$A35,$J$4:$J35)-SUMIF($A$4:$A35,$A35,$K$4:$K35)) -> -57561.71 | M35: =IF($H35="","",N($H35)) | O35: 6000 | P35: =IF($A35="","",SUMIF($A$4:$A35,$A35,$M$4:$M35)-SUMIF($A$4:$A35,$A35,$N$4:$N35)-SUMIF($A$4:$A35,$A35,$O$4:$O35)) -> 63788.1 | T35: =IF($A35="","",SUMIF($A$4:$A35,$A35,$Q$4:$Q35)-SUMIF($A$4:$A35,$A35,$R$4:$R35)-SUMIF($A$4:$A35,$A35,$S$4:$S35)) -> 0 | V35: =IF(AND($C35="",COUNTA($D35:$H35,$K35,$N35:$O35,$Q35:$S35,$U35)=0),"",IF($C35="","⚠ 没填项目名称",IF($A35="⚠目录里没有","⚠ 项目名称在目录里找不到（先加到目录）",IF($A35="","⚠ 目录里这个项目没填简称",IF(ISTEXT($G35)+ISTEXT($H35)+ISTEXT($K35)+ISTEXT($N35)+ISTEXT($O35)+ISTEXT($Q35)+ISTEXT($R35)+ISTEXT($S35)>0,"⚠ 金额列里有文字，算不进合计",IF(N($G35)>=1,"⚠ 管理费点要填百分比，如 10%",IF(AND($D35<>"",$B35=""),"△ 摘要开头没写日期（如 2026.9.21），月份取不到",IF(AND(N($H35)<>0,COUNTIFS($A$4:$A$1003,$A35,$H$4:$H$1003,$H35,$D$4:$D$1003,LEFT($D35,9)&"*")>1),"△ 同一天同项目有一样的销售金额，看看是不是录重了","✓")))))))) -> ✓ | W35: =IF($A35="","",$A35&"#"&COUNTIF($A$4:$A35,$A35)) -> 铜城2回、玉璟尚线、铁井一回、淮拦线4#11
A36: =IF($C36="","",IFERROR(VLOOKUP($C36,目录!$B:$C,2,0)&"","⚠目录里没有")) -> 铜城2回、玉璟尚线、铁井一回、淮拦线4 | B36: =IF($D36="","",IFERROR(MID($D36,FIND(".",$D36)+1,FIND(".",$D36,FIND(".",$D36)+1)-FIND(".",$D36)-1)&"月","")) -> 9月 | C36: 重庆铜梁淮拦线4#环网柜等6个10kV老旧环网柜改造工程（安装） | D36: 2026.9.14新德润扣工资残保金1.5% | E36: 新德润 | I36: =IF($H36="","",N($H36)*N($G36)) | J36: =IF($H36="","",N($H36)-N($I36)) | L36: =IF($A36="","",SUMIF($A$4:$A36,$A36,$J$4:$J36)-SUMIF($A$4:$A36,$A36,$K$4:$K36)) -> -57561.71 | M36: =IF($H36="","",N($H36)) | O36: 1823.97 | P36: =IF($A36="","",SUMIF($A$4:$A36,$A36,$M$4:$M36)-SUMIF($A$4:$A36,$A36,$N$4:$N36)-SUMIF($A$4:$A36,$A36,$O$4:$O36)) -> 61964.13 | T36: =IF($A36="","",SUMIF($A$4:$A36,$A36,$Q$4:$Q36)-SUMIF($A$4:$A36,$A36,$R$4:$R36)-SUMIF($A$4:$A36,$A36,$S$4:$S36)) -> 0 | V36: =IF(AND($C36="",COUNTA($D36:$H36,$K36,$N36:$O36,$Q36:$S36,$U36)=0),"",IF($C36="","⚠ 没填项目名称",IF($A36="⚠目录里没有","⚠ 项目名称在目录里找不到（先加到目录）",IF($A36="","⚠ 目录里这个项目没填简称",IF(ISTEXT($G36)+ISTEXT($H36)+ISTEXT($K36)+ISTEXT($N36)+ISTEXT($O36)+ISTEXT($Q36)+ISTEXT($R36)+ISTEXT($S36)>0,"⚠ 金额列里有文字，算不进合计",IF(N($G36)>=1,"⚠ 管理费点要填百分比，如 10%",IF(AND($D36<>"",$B36=""),"△ 摘要开头没写日期（如 2026.9.21），月份取不到",IF(AND(N($H36)<>0,COUNTIFS($A$4:$A$1003,$A36,$H$4:$H$1003,$H36,$D$4:$D$1003,LEFT($D36,9)&"*")>1),"△ 同一天同项目有一样的销售金额，看看是不是录重了","✓")))))))) -> ✓ | W36: =IF($A36="","",$A36&"#"&COUNTIF($A$4:$A36,$A36)) -> 铜城2回、玉璟尚线、铁井一回、淮拦线4#12
A37: =IF($C37="","",IFERROR(VLOOKUP($C37,目录!$B:$C,2,0)&"","⚠目录里没有")) -> 铜城2回、玉璟尚线、铁井一回、淮拦线4 | B37: =IF($D37="","",IFERROR(MID($D37,FIND(".",$D37)+1,FIND(".",$D37,FIND(".",$D37)+1)-FIND(".",$D37)-1)&"月","")) -> 9月 | C37: 重庆铜梁淮拦线4#环网柜等6个10kV老旧环网柜改造工程（安装） | D37: 2026.9.14新德润扣增值税3541.69，附加税425，印花税72.96 | E37: 新德润 | I37: =IF($H37="","",N($H37)*N($G37)) | J37: =IF($H37="","",N($H37)-N($I37)) | L37: =IF($A37="","",SUMIF($A$4:$A37,$A37,$J$4:$J37)-SUMIF($A$4:$A37,$A37,$K$4:$K37)) -> -57561.71 | M37: =IF($H37="","",N($H37)) | O37: =3541.69+425+72.96 -> 4039.65 | P37: =IF($A37="","",SUMIF($A$4:$A37,$A37,$M$4:$M37)-SUMIF($A$4:$A37,$A37,$N$4:$N37)-SUMIF($A$4:$A37,$A37,$O$4:$O37)) -> 57924.48 | T37: =IF($A37="","",SUMIF($A$4:$A37,$A37,$Q$4:$Q37)-SUMIF($A$4:$A37,$A37,$R$4:$R37)-SUMIF($A$4:$A37,$A37,$S$4:$S37)) -> 0 | V37: =IF(AND($C37="",COUNTA($D37:$H37,$K37,$N37:$O37,$Q37:$S37,$U37)=0),"",IF($C37="","⚠ 没填项目名称",IF($A37="⚠目录里没有","⚠ 项目名称在目录里找不到（先加到目录）",IF($A37="","⚠ 目录里这个项目没填简称",IF(ISTEXT($G37)+ISTEXT($H37)+ISTEXT($K37)+ISTEXT($N37)+ISTEXT($O37)+ISTEXT($Q37)+ISTEXT($R37)+ISTEXT($S37)>0,"⚠ 金额列里有文字，算不进合计",IF(N($G37)>=1,"⚠ 管理费点要填百分比，如 10%",IF(AND($D37<>"",$B37=""),"△ 摘要开头没写日期（如 2026.9.21），月份取不到",IF(AND(N($H37)<>0,COUNTIFS($A$4:$A$1003,$A37,$H$4:$H$1003,$H37,$D$4:$D$1003,LEFT($D37,9)&"*")>1),"△ 同一天同项目有一样的销售金额，看看是不是录重了","✓")))))))) -> ✓ | W37: =IF($A37="","",$A37&"#"&COUNTIF($A$4:$A37,$A37)) -> 铜城2回、玉璟尚线、铁井一回、淮拦线4#13
A38: =IF($C38="","",IFERROR(VLOOKUP($C38,目录!$B:$C,2,0)&"","⚠目录里没有")) -> 铜城2回、玉璟尚线、铁井一回、淮拦线4 | B38: =IF($D38="","",IFERROR(MID($D38,FIND(".",$D38)+1,FIND(".",$D38,FIND(".",$D38)+1)-FIND(".",$D38)-1)&"月","")) -> 9月 | C38: 重庆铜梁淮拦线4#环网柜等6个10kV老旧环网柜改造工程（安装） | D38: 2026.9.14新德润扣管理费 | E38: 新德润 | I38: =IF($H38="","",N($H38)*N($G38)) | J38: =IF($H38="","",N($H38)-N($I38)) | L38: =IF($A38="","",SUMIF($A$4:$A38,$A38,$J$4:$J38)-SUMIF($A$4:$A38,$A38,$K$4:$K38)) -> -57561.71 | M38: =IF($H38="","",N($H38)) | O38: 12159.81 | P38: =IF($A38="","",SUMIF($A$4:$A38,$A38,$M$4:$M38)-SUMIF($A$4:$A38,$A38,$N$4:$N38)-SUMIF($A$4:$A38,$A38,$O$4:$O38)) -> 45764.67 | T38: =IF($A38="","",SUMIF($A$4:$A38,$A38,$Q$4:$Q38)-SUMIF($A$4:$A38,$A38,$R$4:$R38)-SUMIF($A$4:$A38,$A38,$S$4:$S38)) -> 0 | V38: =IF(AND($C38="",COUNTA($D38:$H38,$K38,$N38:$O38,$Q38:$S38,$U38)=0),"",IF($C38="","⚠ 没填项目名称",IF($A38="⚠目录里没有","⚠ 项目名称在目录里找不到（先加到目录）",IF($A38="","⚠ 目录里这个项目没填简称",IF(ISTEXT($G38)+ISTEXT($H38)+ISTEXT($K38)+ISTEXT($N38)+ISTEXT($O38)+ISTEXT($Q38)+ISTEXT($R38)+ISTEXT($S38)>0,"⚠ 金额列里有文字，算不进合计",IF(N($G38)>=1,"⚠ 管理费点要填百分比，如 10%",IF(AND($D38<>"",$B38=""),"△ 摘要开头没写日期（如 2026.9.21），月份取不到",IF(AND(N($H38)<>0,COUNTIFS($A$4:$A$1003,$A38,$H$4:$H$1003,$H38,$D$4:$D$1003,LEFT($D38,9)&"*")>1),"△ 同一天同项目有一样的销售金额，看看是不是录重了","✓")))))))) -> ✓ | W38: =IF($A38="","",$A38&"#"&COUNTIF($A$4:$A38,$A38)) -> 铜城2回、玉璟尚线、铁井一回、淮拦线4#14
A39: =IF($C39="","",IFERROR(VLOOKUP($C39,目录!$B:$C,2,0)&"","⚠目录里没有")) -> 铜城2回、玉璟尚线、铁井一回、淮拦线4 | B39: =IF($D39="","",IFERROR(MID($D39,FIND(".",$D39)+1,FIND(".",$D39,FIND(".",$D39)+1)-FIND(".",$D39)-1)&"月","")) -> 9月 | C39: 重庆铜梁淮拦线4#环网柜等6个10kV老旧环网柜改造工程（安装） | D39: 2026.9.14新德润代胡崇文支付宜宾翠屏货款：42800-39473.83=3326.17 | E39: 新德润 | I39: =IF($H39="","",N($H39)*N($G39)) | J39: =IF($H39="","",N($H39)-N($I39)) | L39: =IF($A39="","",SUMIF($A$4:$A39,$A39,$J$4:$J39)-SUMIF($A$4:$A39,$A39,$K$4:$K39)) -> -57561.71 | M39: =IF($H39="","",N($H39)) | O39: 39473.83 | P39: =IF($A39="","",SUMIF($A$4:$A39,$A39,$M$4:$M39)-SUMIF($A$4:$A39,$A39,$N$4:$N39)-SUMIF($A$4:$A39,$A39,$O$4:$O39)) -> 6290.84 | T39: =IF($A39="","",SUMIF($A$4:$A39,$A39,$Q$4:$Q39)-SUMIF($A$4:$A39,$A39,$R$4:$R39)-SUMIF($A$4:$A39,$A39,$S$4:$S39)) -> 0 | V39: =IF(AND($C39="",COUNTA($D39:$H39,$K39,$N39:$O39,$Q39:$S39,$U39)=0),"",IF($C39="","⚠ 没填项目名称",IF($A39="⚠目录里没有","⚠ 项目名称在目录里找不到（先加到目录）",IF($A39="","⚠ 目录里这个项目没填简称",IF(ISTEXT($G39)+ISTEXT($H39)+ISTEXT($K39)+ISTEXT($N39)+ISTEXT($O39)+ISTEXT($Q39)+ISTEXT($R39)+ISTEXT($S39)>0,"⚠ 金额列里有文字，算不进合计",IF(N($G39)>=1,"⚠ 管理费点要填百分比，如 10%",IF(AND($D39<>"",$B39=""),"△ 摘要开头没写日期（如 2026.9.21），月份取不到",IF(AND(N($H39)<>0,COUNTIFS($A$4:$A$1003,$A39,$H$4:$H$1003,$H39,$D$4:$D$1003,LEFT($D39,9)&"*")>1),"△ 同一天同项目有一样的销售金额，看看是不是录重了","✓")))))))) -> ✓ | W39: =IF($A39="","",$A39&"#"&COUNTIF($A$4:$A39,$A39)) -> 铜城2回、玉璟尚线、铁井一回、淮拦线4#15
A40: =IF($C40="","",IFERROR(VLOOKUP($C40,目录!$B:$C,2,0)&"","⚠目录里没有")) -> 合川表计 | B40: =IF($D40="","",IFERROR(MID($D40,FIND(".",$D40)+1,FIND(".",$D40,FIND(".",$D40)+1)-FIND(".",$D40)-1)&"月","")) -> 6月 | C40: 国网重庆合川供电公司2026年用电信息采集系统建筑相关工程施工(包4) | D40: 2026.6.1张氏机电开票到新德润：合川表计项目 | E40: 新德润 | F40: 1%普票 | H40: 100000 | I40: =IF($H40="","",N($H40)*N($G40)) -> 0 | J40: =IF($H40="","",N($H40)-N($I40)) -> 100000 | K40: 100000 | L40: =IF($A40="","",SUMIF($A$4:$A40,$A40,$J$4:$J40)-SUMIF($A$4:$A40,$A40,$K$4:$K40)) -> 0 | M40: =IF($H40="","",N($H40)) -> 100000 | P40: =IF($A40="","",SUMIF($A$4:$A40,$A40,$M$4:$M40)-SUMIF($A$4:$A40,$A40,$N$4:$N40)-SUMIF($A$4:$A40,$A40,$O$4:$O40)) -> 100000 | T40: =IF($A40="","",SUMIF($A$4:$A40,$A40,$Q$4:$Q40)-SUMIF($A$4:$A40,$A40,$R$4:$R40)-SUMIF($A$4:$A40,$A40,$S$4:$S40)) -> 0 | V40: =IF(AND($C40="",COUNTA($D40:$H40,$K40,$N40:$O40,$Q40:$S40,$U40)=0),"",IF($C40="","⚠ 没填项目名称",IF($A40="⚠目录里没有","⚠ 项目名称在目录里找不到（先加到目录）",IF($A40="","⚠ 目录里这个项目没填简称",IF(ISTEXT($G40)+ISTEXT($H40)+ISTEXT($K40)+ISTEXT($N40)+ISTEXT($O40)+ISTEXT($Q40)+ISTEXT($R40)+ISTEXT($S40)>0,"⚠ 金额列里有文字，算不进合计",IF(N($G40)>=1,"⚠ 管理费点要填百分比，如 10%",IF(AND($D40<>"",$B40=""),"△ 摘要开头没写日期（如 2026.9.21），月份取不到",IF(AND(N($H40)<>0,COUNTIFS($A$4:$A$1003,$A40,$H$4:$H$1003,$H40,$D$4:$D$1003,LEFT($D40,9)&"*")>1),"△ 同一天同项目有一样的销售金额，看看是不是录重了","✓")))))))) -> ✓ | W40: =IF($A40="","",$A40&"#"&COUNTIF($A$4:$A40,$A40)) -> 合川表计#1
A41: =IF($C41="","",IFERROR(VLOOKUP($C41,目录!$B:$C,2,0)&"","⚠目录里没有")) -> 合川表计 | B41: =IF($D41="","",IFERROR(MID($D41,FIND(".",$D41)+1,FIND(".",$D41,FIND(".",$D41)+1)-FIND(".",$D41)-1)&"月","")) -> 7月 | C41: 国网重庆合川供电公司2026年用电信息采集系统建筑相关工程施工(包4) | D41: 2026.7.28冷氏五金开票到众聚能：合川表计项目 | E41: 众聚能 | F41: 3%普票 | H41: 50000 | I41: =IF($H41="","",N($H41)*N($G41)) -> 0 | J41: =IF($H41="","",N($H41)-N($I41)) -> 50000 | K41: 50000 | L41: =IF($A41="","",SUMIF($A$4:$A41,$A41,$J$4:$J41)-SUMIF($A$4:$A41,$A41,$K$4:$K41)) -> 0 | M41: =IF($H41="","",N($H41)) -> 50000 | P41: =IF($A41="","",SUMIF($A$4:$A41,$A41,$M$4:$M41)-SUMIF($A$4:$A41,$A41,$N$4:$N41)-SUMIF($A$4:$A41,$A41,$O$4:$O41)) -> 150000 | T41: =IF($A41="","",SUMIF($A$4:$A41,$A41,$Q$4:$Q41)-SUMIF($A$4:$A41,$A41,$R$4:$R41)-SUMIF($A$4:$A41,$A41,$S$4:$S41)) -> 0 | V41: =IF(AND($C41="",COUNTA($D41:$H41,$K41,$N41:$O41,$Q41:$S41,$U41)=0),"",IF($C41="","⚠ 没填项目名称",IF($A41="⚠目录里没有","⚠ 项目名称在目录里找不到（先加到目录）",IF($A41="","⚠ 目录里这个项目没填简称",IF(ISTEXT($G41)+ISTEXT($H41)+ISTEXT($K41)+ISTEXT($N41)+ISTEXT($O41)+ISTEXT($Q41)+ISTEXT($R41)+ISTEXT($S41)>0,"⚠ 金额列里有文字，算不进合计",IF(N($G41)>=1,"⚠ 管理费点要填百分比，如 10%",IF(AND($D41<>"",$B41=""),"△ 摘要开头没写日期（如 2026.9.21），月份取不到",IF(AND(N($H41)<>0,COUNTIFS($A$4:$A$1003,$A41,$H$4:$H$1003,$H41,$D$4:$D$1003,LEFT($D41,9)&"*")>1),"△ 同一天同项目有一样的销售金额，看看是不是录重了","✓")))))))) -> ✓ | W41: =IF($A41="","",$A41&"#"&COUNTIF($A$4:$A41,$A41)) -> 合川表计#2
A42: =IF($C42="","",IFERROR(VLOOKUP($C42,目录!$B:$C,2,0)&"","⚠目录里没有")) -> 合川表计 | B42: =IF($D42="","",IFERROR(MID($D42,FIND(".",$D42)+1,FIND(".",$D42,FIND(".",$D42)+1)-FIND(".",$D42)-1)&"月","")) -> 6月 | C42: 国网重庆合川供电公司2026年用电信息采集系统建筑相关工程施工(包4) | D42: 2026.6.5张氏机电收到新德润转款：合川表计项目 | E42: 新德润 | I42: =IF($H42="","",N($H42)*N($G42)) | J42: =IF($H42="","",N($H42)-N($I42)) | L42: =IF($A42="","",SUMIF($A$4:$A42,$A42,$J$4:$J42)-SUMIF($A$4:$A42,$A42,$K$4:$K42)) -> 0 | M42: =IF($H42="","",N($H42)) | O42: 100000 | P42: =IF($A42="","",SUMIF($A$4:$A42,$A42,$M$4:$M42)-SUMIF($A$4:$A42,$A42,$N$4:$N42)-SUMIF($A$4:$A42,$A42,$O$4:$O42)) -> 50000 | T42: =IF($A42="","",SUMIF($A$4:$A42,$A42,$Q$4:$Q42)-SUMIF($A$4:$A42,$A42,$R$4:$R42)-SUMIF($A$4:$A42,$A42,$S$4:$S42)) -> 0 | V42: =IF(AND($C42="",COUNTA($D42:$H42,$K42,$N42:$O42,$Q42:$S42,$U42)=0),"",IF($C42="","⚠ 没填项目名称",IF($A42="⚠目录里没有","⚠ 项目名称在目录里找不到（先加到目录）",IF($A42="","⚠ 目录里这个项目没填简称",IF(ISTEXT($G42)+ISTEXT($H42)+ISTEXT($K42)+ISTEXT($N42)+ISTEXT($O42)+ISTEXT($Q42)+ISTEXT($R42)+ISTEXT($S42)>0,"⚠ 金额列里有文字，算不进合计",IF(N($G42)>=1,"⚠ 管理费点要填百分比，如 10%",IF(AND($D42<>"",$B42=""),"△ 摘要开头没写日期（如 2026.9.21），月份取不到",IF(AND(N($H42)<>0,COUNTIFS($A$4:$A$1003,$A42,$H$4:$H$1003,$H42,$D$4:$D$1003,LEFT($D42,9)&"*")>1),"△ 同一天同项目有一样的销售金额，看看是不是录重了","✓")))))))) -> ✓ | W42: =IF($A42="","",$A42&"#"&COUNTIF($A$4:$A42,$A42)) -> 合川表计#3
A43: =IF($C43="","",IFERROR(VLOOKUP($C43,目录!$B:$C,2,0)&"","⚠目录里没有")) -> 合川表计 | B43: =IF($D43="","",IFERROR(MID($D43,FIND(".",$D43)+1,FIND(".",$D43,FIND(".",$D43)+1)-FIND(".",$D43)-1)&"月","")) -> 7月 | C43: 国网重庆合川供电公司2026年用电信息采集系统建筑相关工程施工(包4) | D43: 2026.7.31陈小琴（冷氏五金开）收到新德润打款：合川表计项目 | E43: 新德润 | I43: =IF($H43="","",N($H43)*N($G43)) | J43: =IF($H43="","",N($H43)-N($I43)) | L43: =IF($A43="","",SUMIF($A$4:$A43,$A43,$J$4:$J43)-SUMIF($A$4:$A43,$A43,$K$4:$K43)) -> 0 | M43: =IF($H43="","",N($H43)) | O43: 50000 | P43: =IF($A43="","",SUMIF($A$4:$A43,$A43,$M$4:$M43)-SUMIF($A$4:$A43,$A43,$N$4:$N43)-SUMIF($A$4:$A43,$A43,$O$4:$O43)) -> 0 | T43: =IF($A43="","",SUMIF($A$4:$A43,$A43,$Q$4:$Q43)-SUMIF($A$4:$A43,$A43,$R$4:$R43)-SUMIF($A$4:$A43,$A43,$S$4:$S43)) -> 0 | V43: =IF(AND($C43="",COUNTA($D43:$H43,$K43,$N43:$O43,$Q43:$S43,$U43)=0),"",IF($C43="","⚠ 没填项目名称",IF($A43="⚠目录里没有","⚠ 项目名称在目录里找不到（先加到目录）",IF($A43="","⚠ 目录里这个项目没填简称",IF(ISTEXT($G43)+ISTEXT($H43)+ISTEXT($K43)+ISTEXT($N43)+ISTEXT($O43)+ISTEXT($Q43)+ISTEXT($R43)+ISTEXT($S43)>0,"⚠ 金额列里有文字，算不进合计",IF(N($G43)>=1,"⚠ 管理费点要填百分比，如 10%",IF(AND($D43<>"",$B43=""),"△ 摘要开头没写日期（如 2026.9.21），月份取不到",IF(AND(N($H43)<>0,COUNTIFS($A$4:$A$1003,$A43,$H$4:$H$1003,$H43,$D$4:$D$1003,LEFT($D43,9)&"*")>1),"△ 同一天同项目有一样的销售金额，看看是不是录重了","✓")))))))) -> ✓ | W43: =IF($A43="","",$A43&"#"&COUNTIF($A$4:$A43,$A43)) -> 合川表计#4
A44: =IF($C44="","",IFERROR(VLOOKUP($C44,目录!$B:$C,2,0)&"","⚠目录里没有")) -> 合川表计 | B44: =IF($D44="","",IFERROR(MID($D44,FIND(".",$D44)+1,FIND(".",$D44,FIND(".",$D44)+1)-FIND(".",$D44)-1)&"月","")) -> 8月 | C44: 国网重庆合川供电公司2026年用电信息采集系统建筑相关工程施工(包4) | D44: 2026.8.21工资表给众聚能挂账：合川表计项目 | E44: 众聚能 | F44: 1%普票 | H44: 122000 | I44: =IF($H44="","",N($H44)*N($G44)) -> 0 | J44: =IF($H44="","",N($H44)-N($I44)) -> 122000 | K44: 122000 | L44: =IF($A44="","",SUMIF($A$4:$A44,$A44,$J$4:$J44)-SUMIF($A$4:$A44,$A44,$K$4:$K44)) -> 0 | M44: =IF($H44="","",N($H44)) -> 122000 | P44: =IF($A44="","",SUMIF($A$4:$A44,$A44,$M$4:$M44)-SUMIF($A$4:$A44,$A44,$N$4:$N44)-SUMIF($A$4:$A44,$A44,$O$4:$O44)) -> 122000 | T44: =IF($A44="","",SUMIF($A$4:$A44,$A44,$Q$4:$Q44)-SUMIF($A$4:$A44,$A44,$R$4:$R44)-SUMIF($A$4:$A44,$A44,$S$4:$S44)) -> 0 | V44: =IF(AND($C44="",COUNTA($D44:$H44,$K44,$N44:$O44,$Q44:$S44,$U44)=0),"",IF($C44="","⚠ 没填项目名称",IF($A44="⚠目录里没有","⚠ 项目名称在目录里找不到（先加到目录）",IF($A44="","⚠ 目录里这个项目没填简称",IF(ISTEXT($G44)+ISTEXT($H44)+ISTEXT($K44)+ISTEXT($N44)+ISTEXT($O44)+ISTEXT($Q44)+ISTEXT($R44)+ISTEXT($S44)>0,"⚠ 金额列里有文字，算不进合计",IF(N($G44)>=1,"⚠ 管理费点要填百分比，如 10%",IF(AND($D44<>"",$B44=""),"△ 摘要开头没写日期（如 2026.9.21），月份取不到",IF(AND(N($H44)<>0,COUNTIFS($A$4:$A$1003,$A44,$H$4:$H$1003,$H44,$D$4:$D$1003,LEFT($D44,9)&"*")>1),"△ 同一天同项目有一样的销售金额，看看是不是录重了","✓")))))))) -> ✓ | W44: =IF($A44="","",$A44&"#"&COUNTIF($A$4:$A44,$A44)) -> 合川表计#5
A45: =IF($C45="","",IFERROR(VLOOKUP($C45,目录!$B:$C,2,0)&"","⚠目录里没有")) -> 合川表计 | B45: =IF($D45="","",IFERROR(MID($D45,FIND(".",$D45)+1,FIND(".",$D45,FIND(".",$D45)+1)-FIND(".",$D45)-1)&"月","")) -> 8月 | C45: 国网重庆合川供电公司2026年用电信息采集系统建筑相关工程施工(包4) | D45: 2026.8.21众聚能代付工资：合川表计项目 | E45: 众聚能 | I45: =IF($H45="","",N($H45)*N($G45)) | J45: =IF($H45="","",N($H45)-N($I45)) | L45: =IF($A45="","",SUMIF($A$4:$A45,$A45,$J$4:$J45)-SUMIF($A$4:$A45,$A45,$K$4:$K45)) -> 0 | M45: =IF($H45="","",N($H45)) | O45: 122000 | P45: =IF($A45="","",SUMIF($A$4:$A45,$A45,$M$4:$M45)-SUMIF($A$4:$A45,$A45,$N$4:$N45)-SUMIF($A$4:$A45,$A45,$O$4:$O45)) -> 0 | T45: =IF($A45="","",SUMIF($A$4:$A45,$A45,$Q$4:$Q45)-SUMIF($A$4:$A45,$A45,$R$4:$R45)-SUMIF($A$4:$A45,$A45,$S$4:$S45)) -> 0 | V45: =IF(AND($C45="",COUNTA($D45:$H45,$K45,$N45:$O45,$Q45:$S45,$U45)=0),"",IF($C45="","⚠ 没填项目名称",IF($A45="⚠目录里没有","⚠ 项目名称在目录里找不到（先加到目录）",IF($A45="","⚠ 目录里这个项目没填简称",IF(ISTEXT($G45)+ISTEXT($H45)+ISTEXT($K45)+ISTEXT($N45)+ISTEXT($O45)+ISTEXT($Q45)+ISTEXT($R45)+ISTEXT($S45)>0,"⚠ 金额列里有文字，算不进合计",IF(N($G45)>=1,"⚠ 管理费点要填百分比，如 10%",IF(AND($D45<>"",$B45=""),"△ 摘要开头没写日期（如 2026.9.21），月份取不到",IF(AND(N($H45)<>0,COUNTIFS($A$4:$A$1003,$A45,$H$4:$H$1003,$H45,$D$4:$D$1003,LEFT($D45,9)&"*")>1),"△ 同一天同项目有一样的销售金额，看看是不是录重了","✓")))))))) -> ✓ | W45: =IF($A45="","",$A45&"#"&COUNTIF($A$4:$A45,$A45)) -> 合川表计#6
A46: =IF($C46="","",IFERROR(VLOOKUP($C46,目录!$B:$C,2,0)&"","⚠目录里没有")) -> 合川表计 | B46: =IF($D46="","",IFERROR(MID($D46,FIND(".",$D46)+1,FIND(".",$D46,FIND(".",$D46)+1)-FIND(".",$D46)-1)&"月","")) -> 8月 | C46: 国网重庆合川供电公司2026年用电信息采集系统建筑相关工程施工(包4) | D46: 2026.8.21工资表给腾泰挂账：合川表计项目 | E46: 腾泰 | F46: 1%普票 | H46: 78000 | I46: =IF($H46="","",N($H46)*N($G46)) -> 0 | J46: =IF($H46="","",N($H46)-N($I46)) -> 78000 | K46: 78000 | L46: =IF($A46="","",SUMIF($A$4:$A46,$A46,$J$4:$J46)-SUMIF($A$4:$A46,$A46,$K$4:$K46)) -> 0 | M46: =IF($H46="","",N($H46)) -> 78000 | P46: =IF($A46="","",SUMIF($A$4:$A46,$A46,$M$4:$M46)-SUMIF($A$4:$A46,$A46,$N$4:$N46)-SUMIF($A$4:$A46,$A46,$O$4:$O46)) -> 78000 | T46: =IF($A46="","",SUMIF($A$4:$A46,$A46,$Q$4:$Q46)-SUMIF($A$4:$A46,$A46,$R$4:$R46)-SUMIF($A$4:$A46,$A46,$S$4:$S46)) -> 0 | V46: =IF(AND($C46="",COUNTA($D46:$H46,$K46,$N46:$O46,$Q46:$S46,$U46)=0),"",IF($C46="","⚠ 没填项目名称",IF($A46="⚠目录里没有","⚠ 项目名称在目录里找不到（先加到目录）",IF($A46="","⚠ 目录里这个项目没填简称",IF(ISTEXT($G46)+ISTEXT($H46)+ISTEXT($K46)+ISTEXT($N46)+ISTEXT($O46)+ISTEXT($Q46)+ISTEXT($R46)+ISTEXT($S46)>0,"⚠ 金额列里有文字，算不进合计",IF(N($G46)>=1,"⚠ 管理费点要填百分比，如 10%",IF(AND($D46<>"",$B46=""),"△ 摘要开头没写日期（如 2026.9.21），月份取不到",IF(AND(N($H46)<>0,COUNTIFS($A$4:$A$1003,$A46,$H$4:$H$1003,$H46,$D$4:$D$1003,LEFT($D46,9)&"*")>1),"△ 同一天同项目有一样的销售金额，看看是不是录重了","✓")))))))) -> ✓ | W46: =IF($A46="","",$A46&"#"&COUNTIF($A$4:$A46,$A46)) -> 合川表计#7
A47: =IF($C47="","",IFERROR(VLOOKUP($C47,目录!$B:$C,2,0)&"","⚠目录里没有")) -> 合川表计 | B47: =IF($D47="","",IFERROR(MID($D47,FIND(".",$D47)+1,FIND(".",$D47,FIND(".",$D47)+1)-FIND(".",$D47)-1)&"月","")) -> 8月 | C47: 国网重庆合川供电公司2026年用电信息采集系统建筑相关工程施工(包4) | D47: 2026.8.21腾泰代付工资：合川表计项目 | E47: 腾泰 | I47: =IF($H47="","",N($H47)*N($G47)) | J47: =IF($H47="","",N($H47)-N($I47)) | L47: =IF($A47="","",SUMIF($A$4:$A47,$A47,$J$4:$J47)-SUMIF($A$4:$A47,$A47,$K$4:$K47)) -> 0 | M47: =IF($H47="","",N($H47)) | O47: 78000 | P47: =IF($A47="","",SUMIF($A$4:$A47,$A47,$M$4:$M47)-SUMIF($A$4:$A47,$A47,$N$4:$N47)-SUMIF($A$4:$A47,$A47,$O$4:$O47)) -> 0 | T47: =IF($A47="","",SUMIF($A$4:$A47,$A47,$Q$4:$Q47)-SUMIF($A$4:$A47,$A47,$R$4:$R47)-SUMIF($A$4:$A47,$A47,$S$4:$S47)) -> 0 | V47: =IF(AND($C47="",COUNTA($D47:$H47,$K47,$N47:$O47,$Q47:$S47,$U47)=0),"",IF($C47="","⚠ 没填项目名称",IF($A47="⚠目录里没有","⚠ 项目名称在目录里找不到（先加到目录）",IF($A47="","⚠ 目录里这个项目没填简称",IF(ISTEXT($G47)+ISTEXT($H47)+ISTEXT($K47)+ISTEXT($N47)+ISTEXT($O47)+ISTEXT($Q47)+ISTEXT($R47)+ISTEXT($S47)>0,"⚠ 金额列里有文字，算不进合计",IF(N($G47)>=1,"⚠ 管理费点要填百分比，如 10%",IF(AND($D47<>"",$B47=""),"△ 摘要开头没写日期（如 2026.9.21），月份取不到",IF(AND(N($H47)<>0,COUNTIFS($A$4:$A$1003,$A47,$H$4:$H$1003,$H47,$D$4:$D$1003,LEFT($D47,9)&"*")>1),"△ 同一天同项目有一样的销售金额，看看是不是录重了","✓")))))))) -> ✓ | W47: =IF($A47="","",$A47&"#"&COUNTIF($A$4:$A47,$A47)) -> 合川表计#8
A48: =IF($C48="","",IFERROR(VLOOKUP($C48,目录!$B:$C,2,0)&"","⚠目录里没有")) -> 合川表计 | B48: =IF($D48="","",IFERROR(MID($D48,FIND(".",$D48)+1,FIND(".",$D48,FIND(".",$D48)+1)-FIND(".",$D48)-1)&"月","")) -> 9月 | C48: 国网重庆合川供电公司2026年用电信息采集系统建筑相关工程施工(包4) | D48: 2026.9.14进源开给润德427712.65，提交15万工资（进源部分人工）：合川表计项目 | E48: 润德 | F48: 3%专票 | H48: 150000 | I48: =IF($H48="","",N($H48)*N($G48)) -> 0 | J48: =IF($H48="","",N($H48)-N($I48)) -> 150000 | K48: 150000 | L48: =IF($A48="","",SUMIF($A$4:$A48,$A48,$J$4:$J48)-SUMIF($A$4:$A48,$A48,$K$4:$K48)) -> 0 | M48: =IF($H48="","",N($H48)) -> 150000 | P48: =IF($A48="","",SUMIF($A$4:$A48,$A48,$M$4:$M48)-SUMIF($A$4:$A48,$A48,$N$4:$N48)-SUMIF($A$4:$A48,$A48,$O$4:$O48)) -> 150000 | T48: =IF($A48="","",SUMIF($A$4:$A48,$A48,$Q$4:$Q48)-SUMIF($A$4:$A48,$A48,$R$4:$R48)-SUMIF($A$4:$A48,$A48,$S$4:$S48)) -> 0 | V48: =IF(AND($C48="",COUNTA($D48:$H48,$K48,$N48:$O48,$Q48:$S48,$U48)=0),"",IF($C48="","⚠ 没填项目名称",IF($A48="⚠目录里没有","⚠ 项目名称在目录里找不到（先加到目录）",IF($A48="","⚠ 目录里这个项目没填简称",IF(ISTEXT($G48)+ISTEXT($H48)+ISTEXT($K48)+ISTEXT($N48)+ISTEXT($O48)+ISTEXT($Q48)+ISTEXT($R48)+ISTEXT($S48)>0,"⚠ 金额列里有文字，算不进合计",IF(N($G48)>=1,"⚠ 管理费点要填百分比，如 10%",IF(AND($D48<>"",$B48=""),"△ 摘要开头没写日期（如 2026.9.21），月份取不到",IF(AND(N($H48)<>0,COUNTIFS($A$4:$A$1003,$A48,$H$4:$H$1003,$H48,$D$4:$D$1003,LEFT($D48,9)&"*")>1),"△ 同一天同项目有一样的销售金额，看看是不是录重了","✓")))))))) -> ✓ | W48: =IF($A48="","",$A48&"#"&COUNTIF($A$4:$A48,$A48)) -> 合川表计#9
A49: =IF($C49="","",IFERROR(VLOOKUP($C49,目录!$B:$C,2,0)&"","⚠目录里没有")) -> 合川表计 | B49: =IF($D49="","",IFERROR(MID($D49,FIND(".",$D49)+1,FIND(".",$D49,FIND(".",$D49)+1)-FIND(".",$D49)-1)&"月","")) -> 9月 | C49: 国网重庆合川供电公司2026年用电信息采集系统建筑相关工程施工(包4) | D49: 2026.9.21维维对账提交腾泰工资：合川表计项目 | E49: 腾泰 | F49: 1%普票 | H49: 195460 | I49: =IF($H49="","",N($H49)*N($G49)) -> 0 | J49: =IF($H49="","",N($H49)-N($I49)) -> 195460 | K49: 195460 | L49: =IF($A49="","",SUMIF($A$4:$A49,$A49,$J$4:$J49)-SUMIF($A$4:$A49,$A49,$K$4:$K49)) -> 0 | M49: =IF($H49="","",N($H49)) -> 195460 | P49: =IF($A49="","",SUMIF($A$4:$A49,$A49,$M$4:$M49)-SUMIF($A$4:$A49,$A49,$N$4:$N49)-SUMIF($A$4:$A49,$A49,$O$4:$O49)) -> 345460 | T49: =IF($A49="","",SUMIF($A$4:$A49,$A49,$Q$4:$Q49)-SUMIF($A$4:$A49,$A49,$R$4:$R49)-SUMIF($A$4:$A49,$A49,$S$4:$S49)) -> 0 | V49: =IF(AND($C49="",COUNTA($D49:$H49,$K49,$N49:$O49,$Q49:$S49,$U49)=0),"",IF($C49="","⚠ 没填项目名称",IF($A49="⚠目录里没有","⚠ 项目名称在目录里找不到（先加到目录）",IF($A49="","⚠ 目录里这个项目没填简称",IF(ISTEXT($G49)+ISTEXT($H49)+ISTEXT($K49)+ISTEXT($N49)+ISTEXT($O49)+ISTEXT($Q49)+ISTEXT($R49)+ISTEXT($S49)>0,"⚠ 金额列里有文字，算不进合计",IF(N($G49)>=1,"⚠ 管理费点要填百分比，如 10%",IF(AND($D49<>"",$B49=""),"△ 摘要开头没写日期（如 2026.9.21），月份取不到",IF(AND(N($H49)<>0,COUNTIFS($A$4:$A$1003,$A49,$H$4:$H$1003,$H49,$D$4:$D$1003,LEFT($D49,9)&"*")>1),"△ 同一天同项目有一样的销售金额，看看是不是录重了","✓")))))))) -> ✓ | W49: =IF($A49="","",$A49&"#"&COUNTIF($A$4:$A49,$A49)) -> 合川表计#10
A50: =IF($C50="","",IFERROR(VLOOKUP($C50,目录!$B:$C,2,0)&"","⚠目录里没有")) -> 合川表计 | B50: =IF($D50="","",IFERROR(MID($D50,FIND(".",$D50)+1,FIND(".",$D50,FIND(".",$D50)+1)-FIND(".",$D50)-1)&"月","")) -> 9月 | C50: 国网重庆合川供电公司2026年用电信息采集系统建筑相关工程施工(包4) | D50: 2026.9.21何燕反馈提交10W工资表 | E50: 众聚能 | H50: 100000 | I50: =IF($H50="","",N($H50)*N($G50)) -> 0 | J50: =IF($H50="","",N($H50)-N($I50)) -> 100000 | K50: 100000 | L50: =IF($A50="","",SUMIF($A$4:$A50,$A50,$J$4:$J50)-SUMIF($A$4:$A50,$A50,$K$4:$K50)) -> 0 | M50: =IF($H50="","",N($H50)) -> 100000 | P50: =IF($A50="","",SUMIF($A$4:$A50,$A50,$M$4:$M50)-SUMIF($A$4:$A50,$A50,$N$4:$N50)-SUMIF($A$4:$A50,$A50,$O$4:$O50)) -> 445460 | T50: =IF($A50="","",SUMIF($A$4:$A50,$A50,$Q$4:$Q50)-SUMIF($A$4:$A50,$A50,$R$4:$R50)-SUMIF($A$4:$A50,$A50,$S$4:$S50)) -> 0 | V50: =IF(AND($C50="",COUNTA($D50:$H50,$K50,$N50:$O50,$Q50:$S50,$U50)=0),"",IF($C50="","⚠ 没填项目名称",IF($A50="⚠目录里没有","⚠ 项目名称在目录里找不到（先加到目录）",IF($A50="","⚠ 目录里这个项目没填简称",IF(ISTEXT($G50)+ISTEXT($H50)+ISTEXT($K50)+ISTEXT($N50)+ISTEXT($O50)+ISTEXT($Q50)+ISTEXT($R50)+ISTEXT($S50)>0,"⚠ 金额列里有文字，算不进合计",IF(N($G50)>=1,"⚠ 管理费点要填百分比，如 10%",IF(AND($D50<>"",$B50=""),"△ 摘要开头没写日期（如 2026.9.21），月份取不到",IF(AND(N($H50)<>0,COUNTIFS($A$4:$A$1003,$A50,$H$4:$H$1003,$H50,$D$4:$D$1003,LEFT($D50,9)&"*")>1),"△ 同一天同项目有一样的销售金额，看看是不是录重了","✓")))))))) -> △ 同一天同项目有一样的销售金额，看看是不是录重了 | W50: =IF($A50="","",$A50&"#"&COUNTIF($A$4:$A50,$A50)) -> 合川表计#11
A51: =IF($C51="","",IFERROR(VLOOKUP($C51,目录!$B:$C,2,0)&"","⚠目录里没有")) -> 合川表计 | B51: =IF($D51="","",IFERROR(MID($D51,FIND(".",$D51)+1,FIND(".",$D51,FIND(".",$D51)+1)-FIND(".",$D51)-1)&"月","")) -> 9月 | C51: 国网重庆合川供电公司2026年用电信息采集系统建筑相关工程施工(包4) | D51: 2026.9.21小温提供表计工资表给众聚能何燕挂账 | E51: 众聚能 | F51: 1%普票 | H51: 100000 | I51: =IF($H51="","",N($H51)*N($G51)) -> 0 | J51: =IF($H51="","",N($H51)-N($I51)) -> 100000 | L51: =IF($A51="","",SUMIF($A$4:$A51,$A51,$J$4:$J51)-SUMIF($A$4:$A51,$A51,$K$4:$K51)) -> 100000 | M51: =IF($H51="","",N($H51)) -> 100000 | P51: =IF($A51="","",SUMIF($A$4:$A51,$A51,$M$4:$M51)-SUMIF($A$4:$A51,$A51,$N$4:$N51)-SUMIF($A$4:$A51,$A51,$O$4:$O51)) -> 545460 | T51: =IF($A51="","",SUMIF($A$4:$A51,$A51,$Q$4:$Q51)-SUMIF($A$4:$A51,$A51,$R$4:$R51)-SUMIF($A$4:$A51,$A51,$S$4:$S51)) -> 0 | V51: =IF(AND($C51="",COUNTA($D51:$H51,$K51,$N51:$O51,$Q51:$S51,$U51)=0),"",IF($C51="","⚠ 没填项目名称",IF($A51="⚠目录里没有","⚠ 项目名称在目录里找不到（先加到目录）",IF($A51="","⚠ 目录里这个项目没填简称",IF(ISTEXT($G51)+ISTEXT($H51)+ISTEXT($K51)+ISTEXT($N51)+ISTEXT($O51)+ISTEXT($Q51)+ISTEXT($R51)+ISTEXT($S51)>0,"⚠ 金额列里有文字，算不进合计",IF(N($G51)>=1,"⚠ 管理费点要填百分比，如 10%",IF(AND($D51<>"",$B51=""),"△ 摘要开头没写日期（如 2026.9.21），月份取不到",IF(AND(N($H51)<>0,COUNTIFS($A$4:$A$1003,$A51,$H$4:$H$1003,$H51,$D$4:$D$1003,LEFT($D51,9)&"*")>1),"△ 同一天同项目有一样的销售金额，看看是不是录重了","✓")))))))) -> △ 同一天同项目有一样的销售金额，看看是不是录重了 | W51: =IF($A51="","",$A51&"#"&COUNTIF($A$4:$A51,$A51)) -> 合川表计#12
A52: =IF($C52="","",IFERROR(VLOOKUP($C52,目录!$B:$C,2,0)&"","⚠目录里没有")) -> 合川表计 | B52: =IF($D52="","",IFERROR(MID($D52,FIND(".",$D52)+1,FIND(".",$D52,FIND(".",$D52)+1)-FIND(".",$D52)-1)&"月","")) -> 5月 | C52: 国网重庆合川供电公司2026年用电信息采集系统建筑相关工程施工(包4) | D52: 2026.5.6/5.23代付合川表计工资 | I52: =IF($H52="","",N($H52)*N($G52)) | J52: =IF($H52="","",N($H52)-N($I52)) | L52: =IF($A52="","",SUMIF($A$4:$A52,$A52,$J$4:$J52)-SUMIF($A$4:$A52,$A52,$K$4:$K52)) -> 100000 | M52: =IF($H52="","",N($H52)) | P52: =IF($A52="","",SUMIF($A$4:$A52,$A52,$M$4:$M52)-SUMIF($A$4:$A52,$A52,$N$4:$N52)-SUMIF($A$4:$A52,$A52,$O$4:$O52)) -> 545460 | S52: 105000 | T52: =IF($A52="","",SUMIF($A$4:$A52,$A52,$Q$4:$Q52)-SUMIF($A$4:$A52,$A52,$R$4:$R52)-SUMIF($A$4:$A52,$A52,$S$4:$S52)) -> -105000 | V52: =IF(AND($C52="",COUNTA($D52:$H52,$K52,$N52:$O52,$Q52:$S52,$U52)=0),"",IF($C52="","⚠ 没填项目名称",IF($A52="⚠目录里没有","⚠ 项目名称在目录里找不到（先加到目录）",IF($A52="","⚠ 目录里这个项目没填简称",IF(ISTEXT($G52)+ISTEXT($H52)+ISTEXT($K52)+ISTEXT($N52)+ISTEXT($O52)+ISTEXT($Q52)+ISTEXT($R52)+ISTEXT($S52)>0,"⚠ 金额列里有文字，算不进合计",IF(N($G52)>=1,"⚠ 管理费点要填百分比，如 10%",IF(AND($D52<>"",$B52=""),"△ 摘要开头没写日期（如 2026.9.21），月份取不到",IF(AND(N($H52)<>0,COUNTIFS($A$4:$A$1003,$A52,$H$4:$H$1003,$H52,$D$4:$D$1003,LEFT($D52,9)&"*")>1),"△ 同一天同项目有一样的销售金额，看看是不是录重了","✓")))))))) -> ✓ | W52: =IF($A52="","",$A52&"#"&COUNTIF($A$4:$A52,$A52)) -> 合川表计#13
A53: =IF($C53="","",IFERROR(VLOOKUP($C53,目录!$B:$C,2,0)&"","⚠目录里没有")) -> 合川表计 | B53: =IF($D53="","",IFERROR(MID($D53,FIND(".",$D53)+1,FIND(".",$D53,FIND(".",$D53)+1)-FIND(".",$D53)-1)&"月","")) -> 5月 | C53: 国网重庆合川供电公司2026年用电信息采集系统建筑相关工程施工(包4) | D53: 2026.5.14伍勇军借支 | I53: =IF($H53="","",N($H53)*N($G53)) | J53: =IF($H53="","",N($H53)-N($I53)) | L53: =IF($A53="","",SUMIF($A$4:$A53,$A53,$J$4:$J53)-SUMIF($A$4:$A53,$A53,$K$4:$K53)) -> 100000 | M53: =IF($H53="","",N($H53)) | P53: =IF($A53="","",SUMIF($A$4:$A53,$A53,$M$4:$M53)-SUMIF($A$4:$A53,$A53,$N$4:$N53)-SUMIF($A$4:$A53,$A53,$O$4:$O53)) -> 545460 | S53: 20000 | T53: =IF($A53="","",SUMIF($A$4:$A53,$A53,$Q$4:$Q53)-SUMIF($A$4:$A53,$A53,$R$4:$R53)-SUMIF($A$4:$A53,$A53,$S$4:$S53)) -> -125000 | V53: =IF(AND($C53="",COUNTA($D53:$H53,$K53,$N53:$O53,$Q53:$S53,$U53)=0),"",IF($C53="","⚠ 没填项目名称",IF($A53="⚠目录里没有","⚠ 项目名称在目录里找不到（先加到目录）",IF($A53="","⚠ 目录里这个项目没填简称",IF(ISTEXT($G53)+ISTEXT($H53)+ISTEXT($K53)+ISTEXT($N53)+ISTEXT($O53)+ISTEXT($Q53)+ISTEXT($R53)+ISTEXT($S53)>0,"⚠ 金额列里有文字，算不进合计",IF(N($G53)>=1,"⚠ 管理费点要填百分比，如 10%",IF(AND($D53<>"",$B53=""),"△ 摘要开头没写日期（如 2026.9.21），月份取不到",IF(AND(N($H53)<>0,COUNTIFS($A$4:$A$1003,$A53,$H$4:$H$1003,$H53,$D$4:$D$1003,LEFT($D53,9)&"*")>1),"△ 同一天同项目有一样的销售金额，看看是不是录重了","✓")))))))) -> ✓ | W53: =IF($A53="","",$A53&"#"&COUNTIF($A$4:$A53,$A53)) -> 合川表计#14
A54: =IF($C54="","",IFERROR(VLOOKUP($C54,目录!$B:$C,2,0)&"","⚠目录里没有")) -> 合川表计 | B54: =IF($D54="","",IFERROR(MID($D54,FIND(".",$D54)+1,FIND(".",$D54,FIND(".",$D54)+1)-FIND(".",$D54)-1)&"月","")) -> 5月 | C54: 国网重庆合川供电公司2026年用电信息采集系统建筑相关工程施工(包4) | D54: 2026.5.27伍勇军借支 | I54: =IF($H54="","",N($H54)*N($G54)) | J54: =IF($H54="","",N($H54)-N($I54)) | L54: =IF($A54="","",SUMIF($A$4:$A54,$A54,$J$4:$J54)-SUMIF($A$4:$A54,$A54,$K$4:$K54)) -> 100000 | M54: =IF($H54="","",N($H54)) | P54: =IF($A54="","",SUMIF($A$4:$A54,$A54,$M$4:$M54)-SUMIF($A$4:$A54,$A54,$N$4:$N54)-SUMIF($A$4:$A54,$A54,$O$4:$O54)) -> 545460 | S54: 10000 | T54: =IF($A54="","",SUMIF($A$4:$A54,$A54,$Q$4:$Q54)-SUMIF($A$4:$A54,$A54,$R$4:$R54)-SUMIF($A$4:$A54,$A54,$S$4:$S54)) -> -135000 | V54: =IF(AND($C54="",COUNTA($D54:$H54,$K54,$N54:$O54,$Q54:$S54,$U54)=0),"",IF($C54="","⚠ 没填项目名称",IF($A54="⚠目录里没有","⚠ 项目名称在目录里找不到（先加到目录）",IF($A54="","⚠ 目录里这个项目没填简称",IF(ISTEXT($G54)+ISTEXT($H54)+ISTEXT($K54)+ISTEXT($N54)+ISTEXT($O54)+ISTEXT($Q54)+ISTEXT($R54)+ISTEXT($S54)>0,"⚠ 金额列里有文字，算不进合计",IF(N($G54)>=1,"⚠ 管理费点要填百分比，如 10%",IF(AND($D54<>"",$B54=""),"△ 摘要开头没写日期（如 2026.9.21），月份取不到",IF(AND(N($H54)<>0,COUNTIFS($A$4:$A$1003,$A54,$H$4:$H$1003,$H54,$D$4:$D$1003,LEFT($D54,9)&"*")>1),"△ 同一天同项目有一样的销售金额，看看是不是录重了","✓")))))))) -> ✓ | W54: =IF($A54="","",$A54&"#"&COUNTIF($A$4:$A54,$A54)) -> 合川表计#15
A55: =IF($C55="","",IFERROR(VLOOKUP($C55,目录!$B:$C,2,0)&"","⚠目录里没有")) -> 合川表计 | B55: =IF($D55="","",IFERROR(MID($D55,FIND(".",$D55)+1,FIND(".",$D55,FIND(".",$D55)+1)-FIND(".",$D55)-1)&"月","")) -> 6月 | C55: 国网重庆合川供电公司2026年用电信息采集系统建筑相关工程施工(包4) | D55: 2026.6.8代付合川表计工资 | I55: =IF($H55="","",N($H55)*N($G55)) | J55: =IF($H55="","",N($H55)-N($I55)) | L55: =IF($A55="","",SUMIF($A$4:$A55,$A55,$J$4:$J55)-SUMIF($A$4:$A55,$A55,$K$4:$K55)) -> 100000 | M55: =IF($H55="","",N($H55)) | P55: =IF($A55="","",SUMIF($A$4:$A55,$A55,$M$4:$M55)-SUMIF($A$4:$A55,$A55,$N$4:$N55)-SUMIF($A$4:$A55,$A55,$O$4:$O55)) -> 545460 | S55: 91200 | T55: =IF($A55="","",SUMIF($A$4:$A55,$A55,$Q$4:$Q55)-SUMIF($A$4:$A55,$A55,$R$4:$R55)-SUMIF($A$4:$A55,$A55,$S$4:$S55)) -> -226200 | V55: =IF(AND($C55="",COUNTA($D55:$H55,$K55,$N55:$O55,$Q55:$S55,$U55)=0),"",IF($C55="","⚠ 没填项目名称",IF($A55="⚠目录里没有","⚠ 项目名称在目录里找不到（先加到目录）",IF($A55="","⚠ 目录里这个项目没填简称",IF(ISTEXT($G55)+ISTEXT($H55)+ISTEXT($K55)+ISTEXT($N55)+ISTEXT($O55)+ISTEXT($Q55)+ISTEXT($R55)+ISTEXT($S55)>0,"⚠ 金额列里有文字，算不进合计",IF(N($G55)>=1,"⚠ 管理费点要填百分比，如 10%",IF(AND($D55<>"",$B55=""),"△ 摘要开头没写日期（如 2026.9.21），月份取不到",IF(AND(N($H55)<>0,COUNTIFS($A$4:$A$1003,$A55,$H$4:$H$1003,$H55,$D$4:$D$1003,LEFT($D55,9)&"*")>1),"△ 同一天同项目有一样的销售金额，看看是不是录重了","✓")))))))) -> ✓ | W55: =IF($A55="","",$A55&"#"&COUNTIF($A$4:$A55,$A55)) -> 合川表计#16
A56: =IF($C56="","",IFERROR(VLOOKUP($C56,目录!$B:$C,2,0)&"","⚠目录里没有")) -> 合川表计 | B56: =IF($D56="","",IFERROR(MID($D56,FIND(".",$D56)+1,FIND(".",$D56,FIND(".",$D56)+1)-FIND(".",$D56)-1)&"月","")) -> 6月 | C56: 国网重庆合川供电公司2026年用电信息采集系统建筑相关工程施工(包4) | D56: 2026.6.18/6.30代付合川表计工资 | I56: =IF($H56="","",N($H56)*N($G56)) | J56: =IF($H56="","",N($H56)-N($I56)) | L56: =IF($A56="","",SUMIF($A$4:$A56,$A56,$J$4:$J56)-SUMIF($A$4:$A56,$A56,$K$4:$K56)) -> 100000 | M56: =IF($H56="","",N($H56)) | P56: =IF($A56="","",SUMIF($A$4:$A56,$A56,$M$4:$M56)-SUMIF($A$4:$A56,$A56,$N$4:$N56)-SUMIF($A$4:$A56,$A56,$O$4:$O56)) -> 545460 | S56: 75943 | T56: =IF($A56="","",SUMIF($A$4:$A56,$A56,$Q$4:$Q56)-SUMIF($A$4:$A56,$A56,$R$4:$R56)-SUMIF($A$4:$A56,$A56,$S$4:$S56)) -> -302143 | V56: =IF(AND($C56="",COUNTA($D56:$H56,$K56,$N56:$O56,$Q56:$S56,$U56)=0),"",IF($C56="","⚠ 没填项目名称",IF($A56="⚠目录里没有","⚠ 项目名称在目录里找不到（先加到目录）",IF($A56="","⚠ 目录里这个项目没填简称",IF(ISTEXT($G56)+ISTEXT($H56)+ISTEXT($K56)+ISTEXT($N56)+ISTEXT($O56)+ISTEXT($Q56)+ISTEXT($R56)+ISTEXT($S56)>0,"⚠ 金额列里有文字，算不进合计",IF(N($G56)>=1,"⚠ 管理费点要填百分比，如 10%",IF(AND($D56<>"",$B56=""),"△ 摘要开头没写日期（如 2026.9.21），月份取不到",IF(AND(N($H56)<>0,COUNTIFS($A$4:$A$1003,$A56,$H$4:$H$1003,$H56,$D$4:$D$1003,LEFT($D56,9)&"*")>1),"△ 同一天同项目有一样的销售金额，看看是不是录重了","✓")))))))) -> ✓ | W56: =IF($A56="","",$A56&"#"&COUNTIF($A$4:$A56,$A56)) -> 合川表计#17
A57: =IF($C57="","",IFERROR(VLOOKUP($C57,目录!$B:$C,2,0)&"","⚠目录里没有")) -> 合川表计 | B57: =IF($D57="","",IFERROR(MID($D57,FIND(".",$D57)+1,FIND(".",$D57,FIND(".",$D57)+1)-FIND(".",$D57)-1)&"月","")) -> 7月 | C57: 国网重庆合川供电公司2026年用电信息采集系统建筑相关工程施工(包4) | D57: 2026.7.2代付伍建华合川表计工资 | I57: =IF($H57="","",N($H57)*N($G57)) | J57: =IF($H57="","",N($H57)-N($I57)) | L57: =IF($A57="","",SUMIF($A$4:$A57,$A57,$J$4:$J57)-SUMIF($A$4:$A57,$A57,$K$4:$K57)) -> 100000 | M57: =IF($H57="","",N($H57)) | P57: =IF($A57="","",SUMIF($A$4:$A57,$A57,$M$4:$M57)-SUMIF($A$4:$A57,$A57,$N$4:$N57)-SUMIF($A$4:$A57,$A57,$O$4:$O57)) -> 545460 | S57: 2000 | T57: =IF($A57="","",SUMIF($A$4:$A57,$A57,$Q$4:$Q57)-SUMIF($A$4:$A57,$A57,$R$4:$R57)-SUMIF($A$4:$A57,$A57,$S$4:$S57)) -> -304143 | V57: =IF(AND($C57="",COUNTA($D57:$H57,$K57,$N57:$O57,$Q57:$S57,$U57)=0),"",IF($C57="","⚠ 没填项目名称",IF($A57="⚠目录里没有","⚠ 项目名称在目录里找不到（先加到目录）",IF($A57="","⚠ 目录里这个项目没填简称",IF(ISTEXT($G57)+ISTEXT($H57)+ISTEXT($K57)+ISTEXT($N57)+ISTEXT($O57)+ISTEXT($Q57)+ISTEXT($R57)+ISTEXT($S57)>0,"⚠ 金额列里有文字，算不进合计",IF(N($G57)>=1,"⚠ 管理费点要填百分比，如 10%",IF(AND($D57<>"",$B57=""),"△ 摘要开头没写日期（如 2026.9.21），月份取不到",IF(AND(N($H57)<>0,COUNTIFS($A$4:$A$1003,$A57,$H$4:$H$1003,$H57,$D$4:$D$1003,LEFT($D57,9)&"*")>1),"△ 同一天同项目有一样的销售金额，看看是不是录重了","✓")))))))) -> ✓ | W57: =IF($A57="","",$A57&"#"&COUNTIF($A$4:$A57,$A57)) -> 合川表计#18
A58: =IF($C58="","",IFERROR(VLOOKUP($C58,目录!$B:$C,2,0)&"","⚠目录里没有")) -> 合川表计 | B58: =IF($D58="","",IFERROR(MID($D58,FIND(".",$D58)+1,FIND(".",$D58,FIND(".",$D58)+1)-FIND(".",$D58)-1)&"月","")) -> 7月 | C58: 国网重庆合川供电公司2026年用电信息采集系统建筑相关工程施工(包4) | D58: 2026.7.9代付伍建华合川表计工资 | I58: =IF($H58="","",N($H58)*N($G58)) | J58: =IF($H58="","",N($H58)-N($I58)) | L58: =IF($A58="","",SUMIF($A$4:$A58,$A58,$J$4:$J58)-SUMIF($A$4:$A58,$A58,$K$4:$K58)) -> 100000 | M58: =IF($H58="","",N($H58)) | P58: =IF($A58="","",SUMIF($A$4:$A58,$A58,$M$4:$M58)-SUMIF($A$4:$A58,$A58,$N$4:$N58)-SUMIF($A$4:$A58,$A58,$O$4:$O58)) -> 545460 | S58: 70000 | T58: =IF($A58="","",SUMIF($A$4:$A58,$A58,$Q$4:$Q58)-SUMIF($A$4:$A58,$A58,$R$4:$R58)-SUMIF($A$4:$A58,$A58,$S$4:$S58)) -> -374143 | V58: =IF(AND($C58="",COUNTA($D58:$H58,$K58,$N58:$O58,$Q58:$S58,$U58)=0),"",IF($C58="","⚠ 没填项目名称",IF($A58="⚠目录里没有","⚠ 项目名称在目录里找不到（先加到目录）",IF($A58="","⚠ 目录里这个项目没填简称",IF(ISTEXT($G58)+ISTEXT($H58)+ISTEXT($K58)+ISTEXT($N58)+ISTEXT($O58)+ISTEXT($Q58)+ISTEXT($R58)+ISTEXT($S58)>0,"⚠ 金额列里有文字，算不进合计",IF(N($G58)>=1,"⚠ 管理费点要填百分比，如 10%",IF(AND($D58<>"",$B58=""),"△ 摘要开头没写日期（如 2026.9.21），月份取不到",IF(AND(N($H58)<>0,COUNTIFS($A$4:$A$1003,$A58,$H$4:$H$1003,$H58,$D$4:$D$1003,LEFT($D58,9)&"*")>1),"△ 同一天同项目有一样的销售金额，看看是不是录重了","✓")))))))) -> ✓ | W58: =IF($A58="","",$A58&"#"&COUNTIF($A$4:$A58,$A58)) -> 合川表计#19
A59: =IF($C59="","",IFERROR(VLOOKUP($C59,目录!$B:$C,2,0)&"","⚠目录里没有")) -> 合川表计 | B59: =IF($D59="","",IFERROR(MID($D59,FIND(".",$D59)+1,FIND(".",$D59,FIND(".",$D59)+1)-FIND(".",$D59)-1)&"月","")) -> 7月 | C59: 国网重庆合川供电公司2026年用电信息采集系统建筑相关工程施工(包4) | D59: 2026.7.13代付伍建华合川表计工资 | I59: =IF($H59="","",N($H59)*N($G59)) | J59: =IF($H59="","",N($H59)-N($I59)) | L59: =IF($A59="","",SUMIF($A$4:$A59,$A59,$J$4:$J59)-SUMIF($A$4:$A59,$A59,$K$4:$K59)) -> 100000 | M59: =IF($H59="","",N($H59)) | P59: =IF($A59="","",SUMIF($A$4:$A59,$A59,$M$4:$M59)-SUMIF($A$4:$A59,$A59,$N$4:$N59)-SUMIF($A$4:$A59,$A59,$O$4:$O59)) -> 545460 | S59: 10000 | T59: =IF($A59="","",SUMIF($A$4:$A59,$A59,$Q$4:$Q59)-SUMIF($A$4:$A59,$A59,$R$4:$R59)-SUMIF($A$4:$A59,$A59,$S$4:$S59)) -> -384143 | V59: =IF(AND($C59="",COUNTA($D59:$H59,$K59,$N59:$O59,$Q59:$S59,$U59)=0),"",IF($C59="","⚠ 没填项目名称",IF($A59="⚠目录里没有","⚠ 项目名称在目录里找不到（先加到目录）",IF($A59="","⚠ 目录里这个项目没填简称",IF(ISTEXT($G59)+ISTEXT($H59)+ISTEXT($K59)+ISTEXT($N59)+ISTEXT($O59)+ISTEXT($Q59)+ISTEXT($R59)+ISTEXT($S59)>0,"⚠ 金额列里有文字，算不进合计",IF(N($G59)>=1,"⚠ 管理费点要填百分比，如 10%",IF(AND($D59<>"",$B59=""),"△ 摘要开头没写日期（如 2026.9.21），月份取不到",IF(AND(N($H59)<>0,COUNTIFS($A$4:$A$1003,$A59,$H$4:$H$1003,$H59,$D$4:$D$1003,LEFT($D59,9)&"*")>1),"△ 同一天同项目有一样的销售金额，看看是不是录重了","✓")))))))) -> ✓ | W59: =IF($A59="","",$A59&"#"&COUNTIF($A$4:$A59,$A59)) -> 合川表计#20
A60: =IF($C60="","",IFERROR(VLOOKUP($C60,目录!$B:$C,2,0)&"","⚠目录里没有")) -> 合川表计 | B60: =IF($D60="","",IFERROR(MID($D60,FIND(".",$D60)+1,FIND(".",$D60,FIND(".",$D60)+1)-FIND(".",$D60)-1)&"月","")) -> 7月 | C60: 国网重庆合川供电公司2026年用电信息采集系统建筑相关工程施工(包4) | D60: 2026.7.25代付伍建华合川表计工资 | I60: =IF($H60="","",N($H60)*N($G60)) | J60: =IF($H60="","",N($H60)-N($I60)) | L60: =IF($A60="","",SUMIF($A$4:$A60,$A60,$J$4:$J60)-SUMIF($A$4:$A60,$A60,$K$4:$K60)) -> 100000 | M60: =IF($H60="","",N($H60)) | P60: =IF($A60="","",SUMIF($A$4:$A60,$A60,$M$4:$M60)-SUMIF($A$4:$A60,$A60,$N$4:$N60)-SUMIF($A$4:$A60,$A60,$O$4:$O60)) -> 545460 | S60: 5000 | T60: =IF($A60="","",SUMIF($A$4:$A60,$A60,$Q$4:$Q60)-SUMIF($A$4:$A60,$A60,$R$4:$R60)-SUMIF($A$4:$A60,$A60,$S$4:$S60)) -> -389143 | V60: =IF(AND($C60="",COUNTA($D60:$H60,$K60,$N60:$O60,$Q60:$S60,$U60)=0),"",IF($C60="","⚠ 没填项目名称",IF($A60="⚠目录里没有","⚠ 项目名称在目录里找不到（先加到目录）",IF($A60="","⚠ 目录里这个项目没填简称",IF(ISTEXT($G60)+ISTEXT($H60)+ISTEXT($K60)+ISTEXT($N60)+ISTEXT($O60)+ISTEXT($Q60)+ISTEXT($R60)+ISTEXT($S60)>0,"⚠ 金额列里有文字，算不进合计",IF(N($G60)>=1,"⚠ 管理费点要填百分比，如 10%",IF(AND($D60<>"",$B60=""),"△ 摘要开头没写日期（如 2026.9.21），月份取不到",IF(AND(N($H60)<>0,COUNTIFS($A$4:$A$1003,$A60,$H$4:$H$1003,$H60,$D$4:$D$1003,LEFT($D60,9)&"*")>1),"△ 同一天同项目有一样的销售金额，看看是不是录重了","✓")))))))) -> ✓ | W60: =IF($A60="","",$A60&"#"&COUNTIF($A$4:$A60,$A60)) -> 合川表计#21
A61: =IF($C61="","",IFERROR(VLOOKUP($C61,目录!$B:$C,2,0)&"","⚠目录里没有")) -> 合川表计 | B61: =IF($D61="","",IFERROR(MID($D61,FIND(".",$D61)+1,FIND(".",$D61,FIND(".",$D61)+1)-FIND(".",$D61)-1)&"月","")) -> 7月 | C61: 国网重庆合川供电公司2026年用电信息采集系统建筑相关工程施工(包4) | D61: 2026.7.31支付伍建华合川表计工资 | I61: =IF($H61="","",N($H61)*N($G61)) | J61: =IF($H61="","",N($H61)-N($I61)) | L61: =IF($A61="","",SUMIF($A$4:$A61,$A61,$J$4:$J61)-SUMIF($A$4:$A61,$A61,$K$4:$K61)) -> 100000 | M61: =IF($H61="","",N($H61)) | P61: =IF($A61="","",SUMIF($A$4:$A61,$A61,$M$4:$M61)-SUMIF($A$4:$A61,$A61,$N$4:$N61)-SUMIF($A$4:$A61,$A61,$O$4:$O61)) -> 545460 | S61: 2000 | T61: =IF($A61="","",SUMIF($A$4:$A61,$A61,$Q$4:$Q61)-SUMIF($A$4:$A61,$A61,$R$4:$R61)-SUMIF($A$4:$A61,$A61,$S$4:$S61)) -> -391143 | V61: =IF(AND($C61="",COUNTA($D61:$H61,$K61,$N61:$O61,$Q61:$S61,$U61)=0),"",IF($C61="","⚠ 没填项目名称",IF($A61="⚠目录里没有","⚠ 项目名称在目录里找不到（先加到目录）",IF($A61="","⚠ 目录里这个项目没填简称",IF(ISTEXT($G61)+ISTEXT($H61)+ISTEXT($K61)+ISTEXT($N61)+ISTEXT($O61)+ISTEXT($Q61)+ISTEXT($R61)+ISTEXT($S61)>0,"⚠ 金额列里有文字，算不进合计",IF(N($G61)>=1,"⚠ 管理费点要填百分比，如 10%",IF(AND($D61<>"",$B61=""),"△ 摘要开头没写日期（如 2026.9.21），月份取不到",IF(AND(N($H61)<>0,COUNTIFS($A$4:$A$1003,$A61,$H$4:$H$1003,$H61,$D$4:$D$1003,LEFT($D61,9)&"*")>1),"△ 同一天同项目有一样的销售金额，看看是不是录重了","✓")))))))) -> ✓ | W61: =IF($A61="","",$A61&"#"&COUNTIF($A$4:$A61,$A61)) -> 合川表计#22
A62: =IF($C62="","",IFERROR(VLOOKUP($C62,目录!$B:$C,2,0)&"","⚠目录里没有")) -> 合川表计 | B62: =IF($D62="","",IFERROR(MID($D62,FIND(".",$D62)+1,FIND(".",$D62,FIND(".",$D62)+1)-FIND(".",$D62)-1)&"月","")) -> 8月 | C62: 国网重庆合川供电公司2026年用电信息采集系统建筑相关工程施工(包4) | D62: 2026.8.1支付伍建劳表计费用 | I62: =IF($H62="","",N($H62)*N($G62)) | J62: =IF($H62="","",N($H62)-N($I62)) | L62: =IF($A62="","",SUMIF($A$4:$A62,$A62,$J$4:$J62)-SUMIF($A$4:$A62,$A62,$K$4:$K62)) -> 100000 | M62: =IF($H62="","",N($H62)) | P62: =IF($A62="","",SUMIF($A$4:$A62,$A62,$M$4:$M62)-SUMIF($A$4:$A62,$A62,$N$4:$N62)-SUMIF($A$4:$A62,$A62,$O$4:$O62)) -> 545460 | S62: 8000 | T62: =IF($A62="","",SUMIF($A$4:$A62,$A62,$Q$4:$Q62)-SUMIF($A$4:$A62,$A62,$R$4:$R62)-SUMIF($A$4:$A62,$A62,$S$4:$S62)) -> -399143 | V62: =IF(AND($C62="",COUNTA($D62:$H62,$K62,$N62:$O62,$Q62:$S62,$U62)=0),"",IF($C62="","⚠ 没填项目名称",IF($A62="⚠目录里没有","⚠ 项目名称在目录里找不到（先加到目录）",IF($A62="","⚠ 目录里这个项目没填简称",IF(ISTEXT($G62)+ISTEXT($H62)+ISTEXT($K62)+ISTEXT($N62)+ISTEXT($O62)+ISTEXT($Q62)+ISTEXT($R62)+ISTEXT($S62)>0,"⚠ 金额列里有文字，算不进合计",IF(N($G62)>=1,"⚠ 管理费点要填百分比，如 10%",IF(AND($D62<>"",$B62=""),"△ 摘要开头没写日期（如 2026.9.21），月份取不到",IF(AND(N($H62)<>0,COUNTIFS($A$4:$A$1003,$A62,$H$4:$H$1003,$H62,$D$4:$D$1003,LEFT($D62,9)&"*")>1),"△ 同一天同项目有一样的销售金额，看看是不是录重了","✓")))))))) -> ✓ | W62: =IF($A62="","",$A62&"#"&COUNTIF($A$4:$A62,$A62)) -> 合川表计#23
A63: =IF($C63="","",IFERROR(VLOOKUP($C63,目录!$B:$C,2,0)&"","⚠目录里没有")) -> 合川表计 | B63: =IF($D63="","",IFERROR(MID($D63,FIND(".",$D63)+1,FIND(".",$D63,FIND(".",$D63)+1)-FIND(".",$D63)-1)&"月","")) -> 8月 | C63: 国网重庆合川供电公司2026年用电信息采集系统建筑相关工程施工(包4) | D63: 2026.8.6支付合川工资 | I63: =IF($H63="","",N($H63)*N($G63)) | J63: =IF($H63="","",N($H63)-N($I63)) | L63: =IF($A63="","",SUMIF($A$4:$A63,$A63,$J$4:$J63)-SUMIF($A$4:$A63,$A63,$K$4:$K63)) -> 100000 | M63: =IF($H63="","",N($H63)) | P63: =IF($A63="","",SUMIF($A$4:$A63,$A63,$M$4:$M63)-SUMIF($A$4:$A63,$A63,$N$4:$N63)-SUMIF($A$4:$A63,$A63,$O$4:$O63)) -> 545460 | S63: 6000 | T63: =IF($A63="","",SUMIF($A$4:$A63,$A63,$Q$4:$Q63)-SUMIF($A$4:$A63,$A63,$R$4:$R63)-SUMIF($A$4:$A63,$A63,$S$4:$S63)) -> -405143 | V63: =IF(AND($C63="",COUNTA($D63:$H63,$K63,$N63:$O63,$Q63:$S63,$U63)=0),"",IF($C63="","⚠ 没填项目名称",IF($A63="⚠目录里没有","⚠ 项目名称在目录里找不到（先加到目录）",IF($A63="","⚠ 目录里这个项目没填简称",IF(ISTEXT($G63)+ISTEXT($H63)+ISTEXT($K63)+ISTEXT($N63)+ISTEXT($O63)+ISTEXT($Q63)+ISTEXT($R63)+ISTEXT($S63)>0,"⚠ 金额列里有文字，算不进合计",IF(N($G63)>=1,"⚠ 管理费点要填百分比，如 10%",IF(AND($D63<>"",$B63=""),"△ 摘要开头没写日期（如 2026.9.21），月份取不到",IF(AND(N($H63)<>0,COUNTIFS($A$4:$A$1003,$A63,$H$4:$H$1003,$H63,$D$4:$D$1003,LEFT($D63,9)&"*")>1),"△ 同一天同项目有一样的销售金额，看看是不是录重了","✓")))))))) -> ✓ | W63: =IF($A63="","",$A63&"#"&COUNTIF($A$4:$A63,$A63)) -> 合川表计#24
... A81: =IF($C81="","",IFERROR(VLOOKUP($C81,目录!$B:$C,2,0)&"","⚠目录里没有")) -> 合川表计 | B81: =IF($D81="","",IFERROR(MID($D81,FIND(".",$D81)+1,FIND(".",$D81,FIND(".",$D81)+1)-FIND(".",$D81)-1)&"月","")) -> 9月 | C81: 国网重庆合川供电公司2026年用电信息采集系统建筑相关工程施工(包4) | D81: 2026.9.22胡崇文支付表计工资 | I81: =IF($H81="","",N($H81)*N($G81)) | J81: =IF($H81="","",N($H81)-N($I81)) | L81: =IF($A81="","",SUMIF($A$4:$A81,$A81,$J$4:$J81)-SUMIF($A$4:$A81,$A81,$K$4:$K81)) -> 100000 | M81: =IF($H81="","",N($H81)) | P81: =IF($A81="","",SUMIF($A$4:$A81,$A81,$M$4:$M81)-SUMIF($A$4:$A81,$A81,$N$4:$N81)-SUMIF($A$4:$A81,$A81,$O$4:$O81)) -> 545460 | S81: 10500 | T81: =IF($A81="","",SUMIF($A$4:$A81,$A81,$Q$4:$Q81)-SUMIF($A$4:$A81,$A81,$R$4:$R81)-SUMIF($A$4:$A81,$A81,$S$4:$S81)) -> -576643 | V81: =IF(AND($C81="",COUNTA($D81:$H81,$K81,$N81:$O81,$Q81:$S81,$U81)=0),"",IF($C81="","⚠ 没填项目名称",IF($A81="⚠目录里没有","⚠ 项目名称在目录里找不到（先加到目录）",IF($A81="","⚠ 目录里这个项目没填简称",IF(ISTEXT($G81)+ISTEXT($H81)+ISTEXT($K81)+ISTEXT($N81)+ISTEXT($O81)+ISTEXT($Q81)+ISTEXT($R81)+ISTEXT($S81)>0,"⚠ 金额列里有文字，算不进合计",IF(N($G81)>=1,"⚠ 管理费点要填百分比，如 10%",IF(AND($D81<>"",$B81=""),"△ 摘要开头没写日期（如 2026.9.21），月份取不到",IF(AND(N($H81)<>0,COUNTIFS($A$4:$A$1003,$A81,$H$4:$H$1003,$H81,$D$4:$D$1003,LEFT($D81,9)&"*")>1),"△ 同一天同项目有一样的销售金额，看看是不是录重了","✓")))))))) -> ✓ | W81: =IF($A81="","",$A81&"#"&COUNTIF($A$4:$A81,$A81)) -> 合川表计#42
A82: =IF($C82="","",IFERROR(VLOOKUP($C82,目录!$B:$C,2,0)&"","⚠目录里没有")) -> 蒲吕片区A段 | B82: =IF($D82="","",IFERROR(MID($D82,FIND(".",$D82)+1,FIND(".",$D82,FIND(".",$D82)+1)-FIND(".",$D82)-1)&"月","")) -> 2月 | C82: 铜梁区园区屋顶分布式光伏发电建设项目-蒲吕片区A段10千伏电力新建工程 | D82: 2026.2.9新德润开9%专票到民能：蒲吕片区A段10千伏电力新建 | E82: 民能 | F82: 9%专票 | G82: 0.15 | H82: 200000 | I82: =IF($H82="","",N($H82)*N($G82)) -> 30000 | J82: =IF($H82="","",N($H82)-N($I82)) -> 170000 | L82: =IF($A82="","",SUMIF($A$4:$A82,$A82,$J$4:$J82)-SUMIF($A$4:$A82,$A82,$K$4:$K82)) -> 170000 | M82: =IF($H82="","",N($H82)) -> 200000 | P82: =IF($A82="","",SUMIF($A$4:$A82,$A82,$M$4:$M82)-SUMIF($A$4:$A82,$A82,$N$4:$N82)-SUMIF($A$4:$A82,$A82,$O$4:$O82)) -> 200000 | T82: =IF($A82="","",SUMIF($A$4:$A82,$A82,$Q$4:$Q82)-SUMIF($A$4:$A82,$A82,$R$4:$R82)-SUMIF($A$4:$A82,$A82,$S$4:$S82)) -> 0 | V82: =IF(AND($C82="",COUNTA($D82:$H82,$K82,$N82:$O82,$Q82:$S82,$U82)=0),"",IF($C82="","⚠ 没填项目名称",IF($A82="⚠目录里没有","⚠ 项目名称在目录里找不到（先加到目录）",IF($A82="","⚠ 目录里这个项目没填简称",IF(ISTEXT($G82)+ISTEXT($H82)+ISTEXT($K82)+ISTEXT($N82)+ISTEXT($O82)+ISTEXT($Q82)+ISTEXT($R82)+ISTEXT($S82)>0,"⚠ 金额列里有文字，算不进合计",IF(N($G82)>=1,"⚠ 管理费点要填百分比，如 10%",IF(AND($D82<>"",$B82=""),"△ 摘要开头没写日期（如 2026.9.21），月份取不到",IF(AND(N($H82)<>0,COUNTIFS($A$4:$A$1003,$A82,$H$4:$H$1003,$H82,$D$4:$D$1003,LEFT($D82,9)&"*")>1),"△ 同一天同项目有一样的销售金额，看看是不是录重了","✓")))))))) -> ✓ | W82: =IF($A82="","",$A82&"#"&COUNTIF($A$4:$A82,$A82)) -> 蒲吕片区A段#1
A83: =IF($C83="","",IFERROR(VLOOKUP($C83,目录!$B:$C,2,0)&"","⚠目录里没有")) -> 蒲吕片区A段 | B83: =IF($D83="","",IFERROR(MID($D83,FIND(".",$D83)+1,FIND(".",$D83,FIND(".",$D83)+1)-FIND(".",$D83)-1)&"月","")) -> 9月 | C83: 铜梁区园区屋顶分布式光伏发电建设项目-蒲吕片区A段10千伏电力新建工程 | D83: 2026.9.1扣15%管理费 | E83: 民能 | F83: 9%专票 | G83: 0.15 | I83: =IF($H83="","",N($H83)*N($G83)) | J83: =IF($H83="","",N($H83)-N($I83)) | L83: =IF($A83="","",SUMIF($A$4:$A83,$A83,$J$4:$J83)-SUMIF($A$4:$A83,$A83,$K$4:$K83)) -> 170000 | M83: =IF($H83="","",N($H83)) | O83: 30000 | P83: =IF($A83="","",SUMIF($A$4:$A83,$A83,$M$4:$M83)-SUMIF($A$4:$A83,$A83,$N$4:$N83)-SUMIF($A$4:$A83,$A83,$O$4:$O83)) -> 170000 | T83: =IF($A83="","",SUMIF($A$4:$A83,$A83,$Q$4:$Q83)-SUMIF($A$4:$A83,$A83,$R$4:$R83)-SUMIF($A$4:$A83,$A83,$S$4:$S83)) -> 0 | V83: =IF(AND($C83="",COUNTA($D83:$H83,$K83,$N83:$O83,$Q83:$S83,$U83)=0),"",IF($C83="","⚠ 没填项目名称",IF($A83="⚠目录里没有","⚠ 项目名称在目录里找不到（先加到目录）",IF($A83="","⚠ 目录里这个项目没填简称",IF(ISTEXT($G83)+ISTEXT($H83)+ISTEXT($K83)+ISTEXT($N83)+ISTEXT($O83)+ISTEXT($Q83)+ISTEXT($R83)+ISTEXT($S83)>0,"⚠ 金额列里有文字，算不进合计",IF(N($G83)>=1,"⚠ 管理费点要填百分比，如 10%",IF(AND($D83<>"",$B83=""),"△ 摘要开头没写日期（如 2026.9.21），月份取不到",IF(AND(N($H83)<>0,COUNTIFS($A$4:$A$1003,$A83,$H$4:$H$1003,$H83,$D$4:$D$1003,LEFT($D83,9)&"*")>1),"△ 同一天同项目有一样的销售金额，看看是不是录重了","✓")))))))) -> ✓ | W83: =IF($A83="","",$A83&"#"&COUNTIF($A$4:$A83,$A83)) -> 蒲吕片区A段#2
A84: =IF($C84="","",IFERROR(VLOOKUP($C84,目录!$B:$C,2,0)&"","⚠目录里没有")) -> 蒲吕片区A段 | B84: =IF($D84="","",IFERROR(MID($D84,FIND(".",$D84)+1,FIND(".",$D84,FIND(".",$D84)+1)-FIND(".",$D84)-1)&"月","")) -> 9月 | C84: 铜梁区园区屋顶分布式光伏发电建设项目-蒲吕片区A段10千伏电力新建工程 | D84: 2026.9.1确认前期收到代发工资 | E84: 民能 | F84: 9%专票 | G84: 0.15 | I84: =IF($H84="","",N($H84)*N($G84)) | J84: =IF($H84="","",N($H84)-N($I84)) | K84: 200000 | L84: =IF($A84="","",SUMIF($A$4:$A84,$A84,$J$4:$J84)-SUMIF($A$4:$A84,$A84,$K$4:$K84)) -> -30000 | M84: =IF($H84="","",N($H84)) | O84: 200000 | P84: =IF($A84="","",SUMIF($A$4:$A84,$A84,$M$4:$M84)-SUMIF($A$4:$A84,$A84,$N$4:$N84)-SUMIF($A$4:$A84,$A84,$O$4:$O84)) -> -30000 | T84: =IF($A84="","",SUMIF($A$4:$A84,$A84,$Q$4:$Q84)-SUMIF($A$4:$A84,$A84,$R$4:$R84)-SUMIF($A$4:$A84,$A84,$S$4:$S84)) -> 0 | V84: =IF(AND($C84="",COUNTA($D84:$H84,$K84,$N84:$O84,$Q84:$S84,$U84)=0),"",IF($C84="","⚠ 没填项目名称",IF($A84="⚠目录里没有","⚠ 项目名称在目录里找不到（先加到目录）",IF($A84="","⚠ 目录里这个项目没填简称",IF(ISTEXT($G84)+ISTEXT($H84)+ISTEXT($K84)+ISTEXT($N84)+ISTEXT($O84)+ISTEXT($Q84)+ISTEXT($R84)+ISTEXT($S84)>0,"⚠ 金额列里有文字，算不进合计",IF(N($G84)>=1,"⚠ 管理费点要填百分比，如 10%",IF(AND($D84<>"",$B84=""),"△ 摘要开头没写日期（如 2026.9.21），月份取不到",IF(AND(N($H84)<>0,COUNTIFS($A$4:$A$1003,$A84,$H$4:$H$1003,$H84,$D$4:$D$1003,LEFT($D84,9)&"*")>1),"△ 同一天同项目有一样的销售金额，看看是不是录重了","✓")))))))) -> ✓ | W84: =IF($A84="","",$A84&"#"&COUNTIF($A$4:$A84,$A84)) -> 蒲吕片区A段#3
A85: =IF($C85="","",IFERROR(VLOOKUP($C85,目录!$B:$C,2,0)&"","⚠目录里没有")) -> 蒲吕片区A段 | B85: =IF($D85="","",IFERROR(MID($D85,FIND(".",$D85)+1,FIND(".",$D85,FIND(".",$D85)+1)-FIND(".",$D85)-1)&"月","")) -> 9月 | C85: 铜梁区园区屋顶分布式光伏发电建设项目-蒲吕片区A段10千伏电力新建工程 | D85: 2026.9.1确认扣9%增值税29253.77，附加科3510.45，印花税212.58，合计32976.8 | E85: 民能 | F85: 9%专票 | G85: 0.15 | I85: =IF($H85="","",N($H85)*N($G85)) | J85: =IF($H85="","",N($H85)-N($I85)) | K85: 32976.8 | L85: =IF($A85="","",SUMIF($A$4:$A85,$A85,$J$4:$J85)-SUMIF($A$4:$A85,$A85,$K$4:$K85)) -> -62976.8 | M85: =IF($H85="","",N($H85)) | O85: 32976.8 | P85: =IF($A85="","",SUMIF($A$4:$A85,$A85,$M$4:$M85)-SUMIF($A$4:$A85,$A85,$N$4:$N85)-SUMIF($A$4:$A85,$A85,$O$4:$O85)) -> -62976.8 | T85: =IF($A85="","",SUMIF($A$4:$A85,$A85,$Q$4:$Q85)-SUMIF($A$4:$A85,$A85,$R$4:$R85)-SUMIF($A$4:$A85,$A85,$S$4:$S85)) -> 0 | V85: =IF(AND($C85="",COUNTA($D85:$H85,$K85,$N85:$O85,$Q85:$S85,$U85)=0),"",IF($C85="","⚠ 没填项目名称",IF($A85="⚠目录里没有","⚠ 项目名称在目录里找不到（先加到目录）",IF($A85="","⚠ 目录里这个项目没填简称",IF(ISTEXT($G85)+ISTEXT($H85)+ISTEXT($K85)+ISTEXT($N85)+ISTEXT($O85)+ISTEXT($Q85)+ISTEXT($R85)+ISTEXT($S85)>0,"⚠ 金额列里有文字，算不进合计",IF(N($G85)>=1,"⚠ 管理费点要填百分比，如 10%",IF(AND($D85<>"",$B85=""),"△ 摘要开头没写日期（如 2026.9.21），月份取不到",IF(AND(N($H85)<>0,COUNTIFS($A$4:$A$1003,$A85,$H$4:$H$1003,$H85,$D$4:$D$1003,LEFT($D85,9)&"*")>1),"△ 同一天同项目有一样的销售金额，看看是不是录重了","✓")))))))) -> ✓ | W85: =IF($A85="","",$A85&"#"&COUNTIF($A$4:$A85,$A85)) -> 蒲吕片区A段#4
A86: =IF($C86="","",IFERROR(VLOOKUP($C86,目录!$B:$C,2,0)&"","⚠目录里没有")) -> 蒲吕片区A段 | B86: =IF($D86="","",IFERROR(MID($D86,FIND(".",$D86)+1,FIND(".",$D86,FIND(".",$D86)+1)-FIND(".",$D86)-1)&"月","")) -> 9月 | C86: 铜梁区园区屋顶分布式光伏发电建设项目-蒲吕片区A段10千伏电力新建工程 | D86: 2026.9.1扣残保金20W*1.5% | E86: 民能 | F86: 9%专票 | G86: 0.15 | I86: =IF($H86="","",N($H86)*N($G86)) | J86: =IF($H86="","",N($H86)-N($I86)) | K86: 3000 | L86: =IF($A86="","",SUMIF($A$4:$A86,$A86,$J$4:$J86)-SUMIF($A$4:$A86,$A86,$K$4:$K86)) -> -65976.8 | M86: =IF($H86="","",N($H86)) | O86: 3000 | P86: =IF($A86="","",SUMIF($A$4:$A86,$A86,$M$4:$M86)-SUMIF($A$4:$A86,$A86,$N$4:$N86)-SUMIF($A$4:$A86,$A86,$O$4:$O86)) -> -65976.8 | T86: =IF($A86="","",SUMIF($A$4:$A86,$A86,$Q$4:$Q86)-SUMIF($A$4:$A86,$A86,$R$4:$R86)-SUMIF($A$4:$A86,$A86,$S$4:$S86)) -> 0 | V86: =IF(AND($C86="",COUNTA($D86:$H86,$K86,$N86:$O86,$Q86:$S86,$U86)=0),"",IF($C86="","⚠ 没填项目名称",IF($A86="⚠目录里没有","⚠ 项目名称在目录里找不到（先加到目录）",IF($A86="","⚠ 目录里这个项目没填简称",IF(ISTEXT($G86)+ISTEXT($H86)+ISTEXT($K86)+ISTEXT($N86)+ISTEXT($O86)+ISTEXT($Q86)+ISTEXT($R86)+ISTEXT($S86)>0,"⚠ 金额列里有文字，算不进合计",IF(N($G86)>=1,"⚠ 管理费点要填百分比，如 10%",IF(AND($D86<>"",$B86=""),"△ 摘要开头没写日期（如 2026.9.21），月份取不到",IF(AND(N($H86)<>0,COUNTIFS($A$4:$A$1003,$A86,$H$4:$H$1003,$H86,$D$4:$D$1003,LEFT($D86,9)&"*")>1),"△ 同一天同项目有一样的销售金额，看看是不是录重了","✓")))))))) -> ✓ | W86: =IF($A86="","",$A86&"#"&COUNTIF($A$4:$A86,$A86)) -> 蒲吕片区A段#5
A87: =IF($C87="","",IFERROR(VLOOKUP($C87,目录!$B:$C,2,0)&"","⚠目录里没有")) -> 蒲吕片区A段 | B87: =IF($D87="","",IFERROR(MID($D87,FIND(".",$D87)+1,FIND(".",$D87,FIND(".",$D87)+1)-FIND(".",$D87)-1)&"月","")) -> 9月 | C87: 铜梁区园区屋顶分布式光伏发电建设项目-蒲吕片区A段10千伏电力新建工程 | D87: 2026.9.1扣个税 | E87: 民能 | F87: 9%专票 | G87: 0.15 | I87: =IF($H87="","",N($H87)*N($G87)) | J87: =IF($H87="","",N($H87)-N($I87)) | K87: 4950 | L87: =IF($A87="","",SUMIF($A$4:$A87,$A87,$J$4:$J87)-SUMIF($A$4:$A87,$A87,$K$4:$K87)) -> -70926.8 | M87: =IF($H87="","",N($H87)) | O87: 4950 | P87: =IF($A87="","",SUMIF($A$4:$A87,$A87,$M$4:$M87)-SUMIF($A$4:$A87,$A87,$N$4:$N87)-SUMIF($A$4:$A87,$A87,$O$4:$O87)) -> -70926.8 | T87: =IF($A87="","",SUMIF($A$4:$A87,$A87,$Q$4:$Q87)-SUMIF($A$4:$A87,$A87,$R$4:$R87)-SUMIF($A$4:$A87,$A87,$S$4:$S87)) -> 0 | V87: =IF(AND($C87="",COUNTA($D87:$H87,$K87,$N87:$O87,$Q87:$S87,$U87)=0),"",IF($C87="","⚠ 没填项目名称",IF($A87="⚠目录里没有","⚠ 项目名称在目录里找不到（先加到目录）",IF($A87="","⚠ 目录里这个项目没填简称",IF(ISTEXT($G87)+ISTEXT($H87)+ISTEXT($K87)+ISTEXT($N87)+ISTEXT($O87)+ISTEXT($Q87)+ISTEXT($R87)+ISTEXT($S87)>0,"⚠ 金额列里有文字，算不进合计",IF(N($G87)>=1,"⚠ 管理费点要填百分比，如 10%",IF(AND($D87<>"",$B87=""),"△ 摘要开头没写日期（如 2026.9.21），月份取不到",IF(AND(N($H87)<>0,COUNTIFS($A$4:$A$1003,$A87,$H$4:$H$1003,$H87,$D$4:$D$1003,LEFT($D87,9)&"*")>1),"△ 同一天同项目有一样的销售金额，看看是不是录重了","✓")))))))) -> ✓ | W87: =IF($A87="","",$A87&"#"&COUNTIF($A$4:$A87,$A87)) -> 蒲吕片区A段#6
A88: =IF($C88="","",IFERROR(VLOOKUP($C88,目录!$B:$C,2,0)&"","⚠目录里没有")) -> 蒲吕片区A段 | B88: =IF($D88="","",IFERROR(MID($D88,FIND(".",$D88)+1,FIND(".",$D88,FIND(".",$D88)+1)-FIND(".",$D88)-1)&"月","")) -> 9月 | C88: 铜梁区园区屋顶分布式光伏发电建设项目-蒲吕片区A段10千伏电力新建工程 | D88: 2026.9.1质保金354295.65*3% | E88: 民能 | F88: 9%专票 | G88: 0.15 | I88: =IF($H88="","",N($H88)*N($G88)) | J88: =IF($H88="","",N($H88)-N($I88)) | K88: 10628.87 | L88: =IF($A88="","",SUMIF($A$4:$A88,$A88,$J$4:$J88)-SUMIF($A$4:$A88,$A88,$K$4:$K88)) -> -81555.67 | M88: =IF($H88="","",N($H88)) | O88: 10628.87 | P88: =IF($A88="","",SUMIF($A$4:$A88,$A88,$M$4:$M88)-SUMIF($A$4:$A88,$A88,$N$4:$N88)-SUMIF($A$4:$A88,$A88,$O$4:$O88)) -> -81555.67 | T88: =IF($A88="","",SUMIF($A$4:$A88,$A88,$Q$4:$Q88)-SUMIF($A$4:$A88,$A88,$R$4:$R88)-SUMIF($A$4:$A88,$A88,$S$4:$S88)) -> 0 | V88: =IF(AND($C88="",COUNTA($D88:$H88,$K88,$N88:$O88,$Q88:$S88,$U88)=0),"",IF($C88="","⚠ 没填项目名称",IF($A88="⚠目录里没有","⚠ 项目名称在目录里找不到（先加到目录）",IF($A88="","⚠ 目录里这个项目没填简称",IF(ISTEXT($G88)+ISTEXT($H88)+ISTEXT($K88)+ISTEXT($N88)+ISTEXT($O88)+ISTEXT($Q88)+ISTEXT($R88)+ISTEXT($S88)>0,"⚠ 金额列里有文字，算不进合计",IF(N($G88)>=1,"⚠ 管理费点要填百分比，如 10%",IF(AND($D88<>"",$B88=""),"△ 摘要开头没写日期（如 2026.9.21），月份取不到",IF(AND(N($H88)<>0,COUNTIFS($A$4:$A$1003,$A88,$H$4:$H$1003,$H88,$D$4:$D$1003,LEFT($D88,9)&"*")>1),"△ 同一天同项目有一样的销售金额，看看是不是录重了","✓")))))))) -> ✓ | W88: =IF($A88="","",$A88&"#"&COUNTIF($A$4:$A88,$A88)) -> 蒲吕片区A段#7
A89: =IF($C89="","",IFERROR(VLOOKUP($C89,目录!$B:$C,2,0)&"","⚠目录里没有")) -> 蒲吕片区A段 | B89: =IF($D89="","",IFERROR(MID($D89,FIND(".",$D89)+1,FIND(".",$D89,FIND(".",$D89)+1)-FIND(".",$D89)-1)&"月","")) -> 9月 | C89: 铜梁区园区屋顶分布式光伏发电建设项目-蒲吕片区A段10千伏电力新建工程 | D89: 2026.9.4新德润开9%专票到民能：蒲吕片区A段10千伏电力新建 | E89: 民能 | F89: 9%专票 | G89: 0.15 | H89: 154295.65 | I89: =IF($H89="","",N($H89)*N($G89)) -> 23144.347 | J89: =IF($H89="","",N($H89)-N($I89)) -> 131151.3 | K89: 49595.632 | L89: =IF($A89="","",SUMIF($A$4:$A89,$A89,$J$4:$J89)-SUMIF($A$4:$A89,$A89,$K$4:$K89)) -> 0 | M89: =IF($H89="","",N($H89)) -> 154295.65 | O89: 23144.347 | P89: =IF($A89="","",SUMIF($A$4:$A89,$A89,$M$4:$M89)-SUMIF($A$4:$A89,$A89,$N$4:$N89)-SUMIF($A$4:$A89,$A89,$O$4:$O89)) -> 49595.632 | T89: =IF($A89="","",SUMIF($A$4:$A89,$A89,$Q$4:$Q89)-SUMIF($A$4:$A89,$A89,$R$4:$R89)-SUMIF($A$4:$A89,$A89,$S$4:$S89)) -> 0 | V89: =IF(AND($C89="",COUNTA($D89:$H89,$K89,$N89:$O89,$Q89:$S89,$U89)=0),"",IF($C89="","⚠ 没填项目名称",IF($A89="⚠目录里没有","⚠ 项目名称在目录里找不到（先加到目录）",IF($A89="","⚠ 目录里这个项目没填简称",IF(ISTEXT($G89)+ISTEXT($H89)+ISTEXT($K89)+ISTEXT($N89)+ISTEXT($O89)+ISTEXT($Q89)+ISTEXT($R89)+ISTEXT($S89)>0,"⚠ 金额列里有文字，算不进合计",IF(N($G89)>=1,"⚠ 管理费点要填百分比，如 10%",IF(AND($D89<>"",$B89=""),"△ 摘要开头没写日期（如 2026.9.21），月份取不到",IF(AND(N($H89)<>0,COUNTIFS($A$4:$A$1003,$A89,$H$4:$H$1003,$H89,$D$4:$D$1003,LEFT($D89,9)&"*")>1),"△ 同一天同项目有一样的销售金额，看看是不是录重了","✓")))))))) -> ✓ | W89: =IF($A89="","",$A89&"#"&COUNTIF($A$4:$A89,$A89)) -> 蒲吕片区A段#8
A90: =IF($C90="","",IFERROR(VLOOKUP($C90,目录!$B:$C,2,0)&"","⚠目录里没有")) | B90: =IF($D90="","",IFERROR(MID($D90,FIND(".",$D90)+1,FIND(".",$D90,FIND(".",$D90)+1)-FIND(".",$D90)-1)&"月","")) | I90: =IF($H90="","",N($H90)*N($G90)) | J90: =IF($H90="","",N($H90)-N($I90)) | L90: =IF($A90="","",SUMIF($A$4:$A90,$A90,$J$4:$J90)-SUMIF($A$4:$A90,$A90,$K$4:$K90)) | M90: =IF($H90="","",N($H90)) | P90: =IF($A90="","",SUMIF($A$4:$A90,$A90,$M$4:$M90)-SUMIF($A$4:$A90,$A90,$N$4:$N90)-SUMIF($A$4:$A90,$A90,$O$4:$O90)) | T90: =IF($A90="","",SUMIF($A$4:$A90,$A90,$Q$4:$Q90)-SUMIF($A$4:$A90,$A90,$R$4:$R90)-SUMIF($A$4:$A90,$A90,$S$4:$S90)) | V90: =IF(AND($C90="",COUNTA($D90:$H90,$K90,$N90:$O90,$Q90:$S90,$U90)=0),"",IF($C90="","⚠ 没填项目名称",IF($A90="⚠目录里没有","⚠ 项目名称在目录里找不到（先加到目录）",IF($A90="","⚠ 目录里这个项目没填简称",IF(ISTEXT($G90)+ISTEXT($H90)+ISTEXT($K90)+ISTEXT($N90)+ISTEXT($O90)+ISTEXT($Q90)+ISTEXT($R90)+ISTEXT($S90)>0,"⚠ 金额列里有文字，算不进合计",IF(N($G90)>=1,"⚠ 管理费点要填百分比，如 10%",IF(AND($D90<>"",$B90=""),"△ 摘要开头没写日期（如 2026.9.21），月份取不到",IF(AND(N($H90)<>0,COUNTIFS($A$4:$A$1003,$A90,$H$4:$H$1003,$H90,$D$4:$D$1003,LEFT($D90,9)&"*")>1),"△ 同一天同项目有一样的销售金额，看看是不是录重了","✓")))))))) | W90: =IF($A90="","",$A90&"#"&COUNTIF($A$4:$A90,$A90))
A91: =IF($C91="","",IFERROR(VLOOKUP($C91,目录!$B:$C,2,0)&"","⚠目录里没有")) | B91: =IF($D91="","",IFERROR(MID($D91,FIND(".",$D91)+1,FIND(".",$D91,FIND(".",$D91)+1)-FIND(".",$D91)-1)&"月","")) | I91: =IF($H91="","",N($H91)*N($G91)) | J91: =IF($H91="","",N($H91)-N($I91)) | L91: =IF($A91="","",SUMIF($A$4:$A91,$A91,$J$4:$J91)-SUMIF($A$4:$A91,$A91,$K$4:$K91)) | M91: =IF($H91="","",N($H91)) | P91: =IF($A91="","",SUMIF($A$4:$A91,$A91,$M$4:$M91)-SUMIF($A$4:$A91,$A91,$N$4:$N91)-SUMIF($A$4:$A91,$A91,$O$4:$O91)) | T91: =IF($A91="","",SUMIF($A$4:$A91,$A91,$Q$4:$Q91)-SUMIF($A$4:$A91,$A91,$R$4:$R91)-SUMIF($A$4:$A91,$A91,$S$4:$S91)) | V91: =IF(AND($C91="",COUNTA($D91:$H91,$K91,$N91:$O91,$Q91:$S91,$U91)=0),"",IF($C91="","⚠ 没填项目名称",IF($A91="⚠目录里没有","⚠ 项目名称在目录里找不到（先加到目录）",IF($A91="","⚠ 目录里这个项目没填简称",IF(ISTEXT($G91)+ISTEXT($H91)+ISTEXT($K91)+ISTEXT($N91)+ISTEXT($O91)+ISTEXT($Q91)+ISTEXT($R91)+ISTEXT($S91)>0,"⚠ 金额列里有文字，算不进合计",IF(N($G91)>=1,"⚠ 管理费点要填百分比，如 10%",IF(AND($D91<>"",$B91=""),"△ 摘要开头没写日期（如 2026.9.21），月份取不到",IF(AND(N($H91)<>0,COUNTIFS($A$4:$A$1003,$A91,$H$4:$H$1003,$H91,$D$4:$D$1003,LEFT($D91,9)&"*")>1),"△ 同一天同项目有一样的销售金额，看看是不是录重了","✓")))))))) | W91: =IF($A91="","",$A91&"#"&COUNTIF($A$4:$A91,$A91))
A92: =IF($C92="","",IFERROR(VLOOKUP($C92,目录!$B:$C,2,0)&"","⚠目录里没有")) | B92: =IF($D92="","",IFERROR(MID($D92,FIND(".",$D92)+1,FIND(".",$D92,FIND(".",$D92)+1)-FIND(".",$D92)-1)&"月","")) | I92: =IF($H92="","",N($H92)*N($G92)) | J92: =IF($H92="","",N($H92)-N($I92)) | L92: =IF($A92="","",SUMIF($A$4:$A92,$A92,$J$4:$J92)-SUMIF($A$4:$A92,$A92,$K$4:$K92)) | M92: =IF($H92="","",N($H92)) | P92: =IF($A92="","",SUMIF($A$4:$A92,$A92,$M$4:$M92)-SUMIF($A$4:$A92,$A92,$N$4:$N92)-SUMIF($A$4:$A92,$A92,$O$4:$O92)) | T92: =IF($A92="","",SUMIF($A$4:$A92,$A92,$Q$4:$Q92)-SUMIF($A$4:$A92,$A92,$R$4:$R92)-SUMIF($A$4:$A92,$A92,$S$4:$S92)) | V92: =IF(AND($C92="",COUNTA($D92:$H92,$K92,$N92:$O92,$Q92:$S92,$U92)=0),"",IF($C92="","⚠ 没填项目名称",IF($A92="⚠目录里没有","⚠ 项目名称在目录里找不到（先加到目录）",IF($A92="","⚠ 目录里这个项目没填简称",IF(ISTEXT($G92)+ISTEXT($H92)+ISTEXT($K92)+ISTEXT($N92)+ISTEXT($O92)+ISTEXT($Q92)+ISTEXT($R92)+ISTEXT($S92)>0,"⚠ 金额列里有文字，算不进合计",IF(N($G92)>=1,"⚠ 管理费点要填百分比，如 10%",IF(AND($D92<>"",$B92=""),"△ 摘要开头没写日期（如 2026.9.21），月份取不到",IF(AND(N($H92)<>0,COUNTIFS($A$4:$A$1003,$A92,$H$4:$H$1003,$H92,$D$4:$D$1003,LEFT($D92,9)&"*")>1),"△ 同一天同项目有一样的销售金额，看看是不是录重了","✓")))))))) | W92: =IF($A92="","",$A92&"#"&COUNTIF($A$4:$A92,$A92))
A93: =IF($C93="","",IFERROR(VLOOKUP($C93,目录!$B:$C,2,0)&"","⚠目录里没有")) | B93: =IF($D93="","",IFERROR(MID($D93,FIND(".",$D93)+1,FIND(".",$D93,FIND(".",$D93)+1)-FIND(".",$D93)-1)&"月","")) | I93: =IF($H93="","",N($H93)*N($G93)) | J93: =IF($H93="","",N($H93)-N($I93)) | L93: =IF($A93="","",SUMIF($A$4:$A93,$A93,$J$4:$J93)-SUMIF($A$4:$A93,$A93,$K$4:$K93)) | M93: =IF($H93="","",N($H93)) | P93: =IF($A93="","",SUMIF($A$4:$A93,$A93,$M$4:$M93)-SUMIF($A$4:$A93,$A93,$N$4:$N93)-SUMIF($A$4:$A93,$A93,$O$4:$O93)) | T93: =IF($A93="","",SUMIF($A$4:$A93,$A93,$Q$4:$Q93)-SUMIF($A$4:$A93,$A93,$R$4:$R93)-SUMIF($A$4:$A93,$A93,$S$4:$S93)) | V93: =IF(AND($C93="",COUNTA($D93:$H93,$K93,$N93:$O93,$Q93:$S93,$U93)=0),"",IF($C93="","⚠ 没填项目名称",IF($A93="⚠目录里没有","⚠ 项目名称在目录里找不到（先加到目录）",IF($A93="","⚠ 目录里这个项目没填简称",IF(ISTEXT($G93)+ISTEXT($H93)+ISTEXT($K93)+ISTEXT($N93)+ISTEXT($O93)+ISTEXT($Q93)+ISTEXT($R93)+ISTEXT($S93)>0,"⚠ 金额列里有文字，算不进合计",IF(N($G93)>=1,"⚠ 管理费点要填百分比，如 10%",IF(AND($D93<>"",$B93=""),"△ 摘要开头没写日期（如 2026.9.21），月份取不到",IF(AND(N($H93)<>0,COUNTIFS($A$4:$A$1003,$A93,$H$4:$H$1003,$H93,$D$4:$D$1003,LEFT($D93,9)&"*")>1),"△ 同一天同项目有一样的销售金额，看看是不是录重了","✓")))))))) | W93: =IF($A93="","",$A93&"#"&COUNTIF($A$4:$A93,$A93))
A94: =IF($C94="","",IFERROR(VLOOKUP($C94,目录!$B:$C,2,0)&"","⚠目录里没有")) | B94: =IF($D94="","",IFERROR(MID($D94,FIND(".",$D94)+1,FIND(".",$D94,FIND(".",$D94)+1)-FIND(".",$D94)-1)&"月","")) | I94: =IF($H94="","",N($H94)*N($G94)) | J94: =IF($H94="","",N($H94)-N($I94)) | L94: =IF($A94="","",SUMIF($A$4:$A94,$A94,$J$4:$J94)-SUMIF($A$4:$A94,$A94,$K$4:$K94)) | M94: =IF($H94="","",N($H94)) | P94: =IF($A94="","",SUMIF($A$4:$A94,$A94,$M$4:$M94)-SUMIF($A$4:$A94,$A94,$N$4:$N94)-SUMIF($A$4:$A94,$A94,$O$4:$O94)) | T94: =IF($A94="","",SUMIF($A$4:$A94,$A94,$Q$4:$Q94)-SUMIF($A$4:$A94,$A94,$R$4:$R94)-SUMIF($A$4:$A94,$A94,$S$4:$S94)) | V94: =IF(AND($C94="",COUNTA($D94:$H94,$K94,$N94:$O94,$Q94:$S94,$U94)=0),"",IF($C94="","⚠ 没填项目名称",IF($A94="⚠目录里没有","⚠ 项目名称在目录里找不到（先加到目录）",IF($A94="","⚠ 目录里这个项目没填简称",IF(ISTEXT($G94)+ISTEXT($H94)+ISTEXT($K94)+ISTEXT($N94)+ISTEXT($O94)+ISTEXT($Q94)+ISTEXT($R94)+ISTEXT($S94)>0,"⚠ 金额列里有文字，算不进合计",IF(N($G94)>=1,"⚠ 管理费点要填百分比，如 10%",IF(AND($D94<>"",$B94=""),"△ 摘要开头没写日期（如 2026.9.21），月份取不到",IF(AND(N($H94)<>0,COUNTIFS($A$4:$A$1003,$A94,$H$4:$H$1003,$H94,$D$4:$D$1003,LEFT($D94,9)&"*")>1),"△ 同一天同项目有一样的销售金额，看看是不是录重了","✓")))))))) | W94: =IF($A94="","",$A94&"#"&COUNTIF($A$4:$A94,$A94))
A95: =IF($C95="","",IFERROR(VLOOKUP($C95,目录!$B:$C,2,0)&"","⚠目录里没有")) | B95: =IF($D95="","",IFERROR(MID($D95,FIND(".",$D95)+1,FIND(".",$D95,FIND(".",$D95)+1)-FIND(".",$D95)-1)&"月","")) | I95: =IF($H95="","",N($H95)*N($G95)) | J95: =IF($H95="","",N($H95)-N($I95)) | L95: =IF($A95="","",SUMIF($A$4:$A95,$A95,$J$4:$J95)-SUMIF($A$4:$A95,$A95,$K$4:$K95)) | M95: =IF($H95="","",N($H95)) | P95: =IF($A95="","",SUMIF($A$4:$A95,$A95,$M$4:$M95)-SUMIF($A$4:$A95,$A95,$N$4:$N95)-SUMIF($A$4:$A95,$A95,$O$4:$O95)) | T95: =IF($A95="","",SUMIF($A$4:$A95,$A95,$Q$4:$Q95)-SUMIF($A$4:$A95,$A95,$R$4:$R95)-SUMIF($A$4:$A95,$A95,$S$4:$S95)) | V95: =IF(AND($C95="",COUNTA($D95:$H95,$K95,$N95:$O95,$Q95:$S95,$U95)=0),"",IF($C95="","⚠ 没填项目名称",IF($A95="⚠目录里没有","⚠ 项目名称在目录里找不到（先加到目录）",IF($A95="","⚠ 目录里这个项目没填简称",IF(ISTEXT($G95)+ISTEXT($H95)+ISTEXT($K95)+ISTEXT($N95)+ISTEXT($O95)+ISTEXT($Q95)+ISTEXT($R95)+ISTEXT($S95)>0,"⚠ 金额列里有文字，算不进合计",IF(N($G95)>=1,"⚠ 管理费点要填百分比，如 10%",IF(AND($D95<>"",$B95=""),"△ 摘要开头没写日期（如 2026.9.21），月份取不到",IF(AND(N($H95)<>0,COUNTIFS($A$4:$A$1003,$A95,$H$4:$H$1003,$H95,$D$4:$D$1003,LEFT($D95,9)&"*")>1),"△ 同一天同项目有一样的销售金额，看看是不是录重了","✓")))))))) | W95: =IF($A95="","",$A95&"#"&COUNTIF($A$4:$A95,$A95))
A96: =IF($C96="","",IFERROR(VLOOKUP($C96,目录!$B:$C,2,0)&"","⚠目录里没有")) | B96: =IF($D96="","",IFERROR(MID($D96,FIND(".",$D96)+1,FIND(".",$D96,FIND(".",$D96)+1)-FIND(".",$D96)-1)&"月","")) | I96: =IF($H96="","",N($H96)*N($G96)) | J96: =IF($H96="","",N($H96)-N($I96)) | L96: =IF($A96="","",SUMIF($A$4:$A96,$A96,$J$4:$J96)-SUMIF($A$4:$A96,$A96,$K$4:$K96)) | M96: =IF($H96="","",N($H96)) | P96: =IF($A96="","",SUMIF($A$4:$A96,$A96,$M$4:$M96)-SUMIF($A$4:$A96,$A96,$N$4:$N96)-SUMIF($A$4:$A96,$A96,$O$4:$O96)) | T96: =IF($A96="","",SUMIF($A$4:$A96,$A96,$Q$4:$Q96)-SUMIF($A$4:$A96,$A96,$R$4:$R96)-SUMIF($A$4:$A96,$A96,$S$4:$S96)) | V96: =IF(AND($C96="",COUNTA($D96:$H96,$K96,$N96:$O96,$Q96:$S96,$U96)=0),"",IF($C96="","⚠ 没填项目名称",IF($A96="⚠目录里没有","⚠ 项目名称在目录里找不到（先加到目录）",IF($A96="","⚠ 目录里这个项目没填简称",IF(ISTEXT($G96)+ISTEXT($H96)+ISTEXT($K96)+ISTEXT($N96)+ISTEXT($O96)+ISTEXT($Q96)+ISTEXT($R96)+ISTEXT($S96)>0,"⚠ 金额列里有文字，算不进合计",IF(N($G96)>=1,"⚠ 管理费点要填百分比，如 10%",IF(AND($D96<>"",$B96=""),"△ 摘要开头没写日期（如 2026.9.21），月份取不到",IF(AND(N($H96)<>0,COUNTIFS($A$4:$A$1003,$A96,$H$4:$H$1003,$H96,$D$4:$D$1003,LEFT($D96,9)&"*")>1),"△ 同一天同项目有一样的销售金额，看看是不是录重了","✓")))))))) | W96: =IF($A96="","",$A96&"#"&COUNTIF($A$4:$A96,$A96))
A97: =IF($C97="","",IFERROR(VLOOKUP($C97,目录!$B:$C,2,0)&"","⚠目录里没有")) | B97: =IF($D97="","",IFERROR(MID($D97,FIND(".",$D97)+1,FIND(".",$D97,FIND(".",$D97)+1)-FIND(".",$D97)-1)&"月","")) | I97: =IF($H97="","",N($H97)*N($G97)) | J97: =IF($H97="","",N($H97)-N($I97)) | L97: =IF($A97="","",SUMIF($A$4:$A97,$A97,$J$4:$J97)-SUMIF($A$4:$A97,$A97,$K$4:$K97)) | M97: =IF($H97="","",N($H97)) | P97: =IF($A97="","",SUMIF($A$4:$A97,$A97,$M$4:$M97)-SUMIF($A$4:$A97,$A97,$N$4:$N97)-SUMIF($A$4:$A97,$A97,$O$4:$O97)) | T97: =IF($A97="","",SUMIF($A$4:$A97,$A97,$Q$4:$Q97)-SUMIF($A$4:$A97,$A97,$R$4:$R97)-SUMIF($A$4:$A97,$A97,$S$4:$S97)) | V97: =IF(AND($C97="",COUNTA($D97:$H97,$K97,$N97:$O97,$Q97:$S97,$U97)=0),"",IF($C97="","⚠ 没填项目名称",IF($A97="⚠目录里没有","⚠ 项目名称在目录里找不到（先加到目录）",IF($A97="","⚠ 目录里这个项目没填简称",IF(ISTEXT($G97)+ISTEXT($H97)+ISTEXT($K97)+ISTEXT($N97)+ISTEXT($O97)+ISTEXT($Q97)+ISTEXT($R97)+ISTEXT($S97)>0,"⚠ 金额列里有文字，算不进合计",IF(N($G97)>=1,"⚠ 管理费点要填百分比，如 10%",IF(AND($D97<>"",$B97=""),"△ 摘要开头没写日期（如 2026.9.21），月份取不到",IF(AND(N($H97)<>0,COUNTIFS($A$4:$A$1003,$A97,$H$4:$H$1003,$H97,$D$4:$D$1003,LEFT($D97,9)&"*")>1),"△ 同一天同项目有一样的销售金额，看看是不是录重了","✓")))))))) | W97: =IF($A97="","",$A97&"#"&COUNTIF($A$4:$A97,$A97))
A98: =IF($C98="","",IFERROR(VLOOKUP($C98,目录!$B:$C,2,0)&"","⚠目录里没有")) | B98: =IF($D98="","",IFERROR(MID($D98,FIND(".",$D98)+1,FIND(".",$D98,FIND(".",$D98)+1)-FIND(".",$D98)-1)&"月","")) | I98: =IF($H98="","",N($H98)*N($G98)) | J98: =IF($H98="","",N($H98)-N($I98)) | L98: =IF($A98="","",SUMIF($A$4:$A98,$A98,$J$4:$J98)-SUMIF($A$4:$A98,$A98,$K$4:$K98)) | M98: =IF($H98="","",N($H98)) | P98: =IF($A98="","",SUMIF($A$4:$A98,$A98,$M$4:$M98)-SUMIF($A$4:$A98,$A98,$N$4:$N98)-SUMIF($A$4:$A98,$A98,$O$4:$O98)) | T98: =IF($A98="","",SUMIF($A$4:$A98,$A98,$Q$4:$Q98)-SUMIF($A$4:$A98,$A98,$R$4:$R98)-SUMIF($A$4:$A98,$A98,$S$4:$S98)) | V98: =IF(AND($C98="",COUNTA($D98:$H98,$K98,$N98:$O98,$Q98:$S98,$U98)=0),"",IF($C98="","⚠ 没填项目名称",IF($A98="⚠目录里没有","⚠ 项目名称在目录里找不到（先加到目录）",IF($A98="","⚠ 目录里这个项目没填简称",IF(ISTEXT($G98)+ISTEXT($H98)+ISTEXT($K98)+ISTEXT($N98)+ISTEXT($O98)+ISTEXT($Q98)+ISTEXT($R98)+ISTEXT($S98)>0,"⚠ 金额列里有文字，算不进合计",IF(N($G98)>=1,"⚠ 管理费点要填百分比，如 10%",IF(AND($D98<>"",$B98=""),"△ 摘要开头没写日期（如 2026.9.21），月份取不到",IF(AND(N($H98)<>0,COUNTIFS($A$4:$A$1003,$A98,$H$4:$H$1003,$H98,$D$4:$D$1003,LEFT($D98,9)&"*")>1),"△ 同一天同项目有一样的销售金额，看看是不是录重了","✓")))))))) | W98: =IF($A98="","",$A98&"#"&COUNTIF($A$4:$A98,$A98))
A99: =IF($C99="","",IFERROR(VLOOKUP($C99,目录!$B:$C,2,0)&"","⚠目录里没有")) | B99: =IF($D99="","",IFERROR(MID($D99,FIND(".",$D99)+1,FIND(".",$D99,FIND(".",$D99)+1)-FIND(".",$D99)-1)&"月","")) | I99: =IF($H99="","",N($H99)*N($G99)) | J99: =IF($H99="","",N($H99)-N($I99)) | L99: =IF($A99="","",SUMIF($A$4:$A99,$A99,$J$4:$J99)-SUMIF($A$4:$A99,$A99,$K$4:$K99)) | M99: =IF($H99="","",N($H99)) | P99: =IF($A99="","",SUMIF($A$4:$A99,$A99,$M$4:$M99)-SUMIF($A$4:$A99,$A99,$N$4:$N99)-SUMIF($A$4:$A99,$A99,$O$4:$O99)) | T99: =IF($A99="","",SUMIF($A$4:$A99,$A99,$Q$4:$Q99)-SUMIF($A$4:$A99,$A99,$R$4:$R99)-SUMIF($A$4:$A99,$A99,$S$4:$S99)) | V99: =IF(AND($C99="",COUNTA($D99:$H99,$K99,$N99:$O99,$Q99:$S99,$U99)=0),"",IF($C99="","⚠ 没填项目名称",IF($A99="⚠目录里没有","⚠ 项目名称在目录里找不到（先加到目录）",IF($A99="","⚠ 目录里这个项目没填简称",IF(ISTEXT($G99)+ISTEXT($H99)+ISTEXT($K99)+ISTEXT($N99)+ISTEXT($O99)+ISTEXT($Q99)+ISTEXT($R99)+ISTEXT($S99)>0,"⚠ 金额列里有文字，算不进合计",IF(N($G99)>=1,"⚠ 管理费点要填百分比，如 10%",IF(AND($D99<>"",$B99=""),"△ 摘要开头没写日期（如 2026.9.21），月份取不到",IF(AND(N($H99)<>0,COUNTIFS($A$4:$A$1003,$A99,$H$4:$H$1003,$H99,$D$4:$D$1003,LEFT($D99,9)&"*")>1),"△ 同一天同项目有一样的销售金额，看看是不是录重了","✓")))))))) | W99: =IF($A99="","",$A99&"#"&COUNTIF($A$4:$A99,$A99))
A100: =IF($C100="","",IFERROR(VLOOKUP($C100,目录!$B:$C,2,0)&"","⚠目录里没有")) | B100: =IF($D100="","",IFERROR(MID($D100,FIND(".",$D100)+1,FIND(".",$D100,FIND(".",$D100)+1)-FIND(".",$D100)-1)&"月","")) | I100: =IF($H100="","",N($H100)*N($G100)) | J100: =IF($H100="","",N($H100)-N($I100)) | L100: =IF($A100="","",SUMIF($A$4:$A100,$A100,$J$4:$J100)-SUMIF($A$4:$A100,$A100,$K$4:$K100)) | M100: =IF($H100="","",N($H100)) | P100: =IF($A100="","",SUMIF($A$4:$A100,$A100,$M$4:$M100)-SUMIF($A$4:$A100,$A100,$N$4:$N100)-SUMIF($A$4:$A100,$A100,$O$4:$O100)) | T100: =IF($A100="","",SUMIF($A$4:$A100,$A100,$Q$4:$Q100)-SUMIF($A$4:$A100,$A100,$R$4:$R100)-SUMIF($A$4:$A100,$A100,$S$4:$S100)) | V100: =IF(AND($C100="",COUNTA($D100:$H100,$K100,$N100:$O100,$Q100:$S100,$U100)=0),"",IF($C100="","⚠ 没填项目名称",IF($A100="⚠目录里没有","⚠ 项目名称在目录里找不到（先加到目录）",IF($A100="","⚠ 目录里这个项目没填简称",IF(ISTEXT($G100)+ISTEXT($H100)+ISTEXT($K100)+ISTEXT($N100)+ISTEXT($O100)+ISTEXT($Q100)+ISTEXT($R100)+ISTEXT($S100)>0,"⚠ 金额列里有文字，算不进合计",IF(N($G100)>=1,"⚠ 管理费点要填百分比，如 10%",IF(AND($D100<>"",$B100=""),"△ 摘要开头没写日期（如 2026.9.21），月份取不到",IF(AND(N($H100)<>0,COUNTIFS($A$4:$A$1003,$A100,$H$4:$H$1003,$H100,$D$4:$D$1003,LEFT($D100,9)&"*")>1),"△ 同一天同项目有一样的销售金额，看看是不是录重了","✓")))))))) | W100: =IF($A100="","",$A100&"#"&COUNTIF($A$4:$A100,$A100))
A101: =IF($C101="","",IFERROR(VLOOKUP($C101,目录!$B:$C,2,0)&"","⚠目录里没有")) | B101: =IF($D101="","",IFERROR(MID($D101,FIND(".",$D101)+1,FIND(".",$D101,FIND(".",$D101)+1)-FIND(".",$D101)-1)&"月","")) | I101: =IF($H101="","",N($H101)*N($G101)) | J101: =IF($H101="","",N($H101)-N($I101)) | L101: =IF($A101="","",SUMIF($A$4:$A101,$A101,$J$4:$J101)-SUMIF($A$4:$A101,$A101,$K$4:$K101)) | M101: =IF($H101="","",N($H101)) | P101: =IF($A101="","",SUMIF($A$4:$A101,$A101,$M$4:$M101)-SUMIF($A$4:$A101,$A101,$N$4:$N101)-SUMIF($A$4:$A101,$A101,$O$4:$O101)) | T101: =IF($A101="","",SUMIF($A$4:$A101,$A101,$Q$4:$Q101)-SUMIF($A$4:$A101,$A101,$R$4:$R101)-SUMIF($A$4:$A101,$A101,$S$4:$S101)) | V101: =IF(AND($C101="",COUNTA($D101:$H101,$K101,$N101:$O101,$Q101:$S101,$U101)=0),"",IF($C101="","⚠ 没填项目名称",IF($A101="⚠目录里没有","⚠ 项目名称在目录里找不到（先加到目录）",IF($A101="","⚠ 目录里这个项目没填简称",IF(ISTEXT($G101)+ISTEXT($H101)+ISTEXT($K101)+ISTEXT($N101)+ISTEXT($O101)+ISTEXT($Q101)+ISTEXT($R101)+ISTEXT($S101)>0,"⚠ 金额列里有文字，算不进合计",IF(N($G101)>=1,"⚠ 管理费点要填百分比，如 10%",IF(AND($D101<>"",$B101=""),"△ 摘要开头没写日期（如 2026.9.21），月份取不到",IF(AND(N($H101)<>0,COUNTIFS($A$4:$A$1003,$A101,$H$4:$H$1003,$H101,$D$4:$D$1003,LEFT($D101,9)&"*")>1),"△ 同一天同项目有一样的销售金额，看看是不是录重了","✓")))))))) | W101: =IF($A101="","",$A101&"#"&COUNTIF($A$4:$A101,$A101))
... A1003: =IF($C1003="","",IFERROR(VLOOKUP($C1003,目录!$B:$C,2,0)&"","⚠目录里没有")) | B1003: =IF($D1003="","",IFERROR(MID($D1003,FIND(".",$D1003)+1,FIND(".",$D1003,FIND(".",$D1003)+1)-FIND(".",$D1003)-1)&"月","")) | I1003: =IF($H1003="","",N($H1003)*N($G1003)) | J1003: =IF($H1003="","",N($H1003)-N($I1003)) | L1003: =IF($A1003="","",SUMIF($A$4:$A1003,$A1003,$J$4:$J1003)-SUMIF($A$4:$A1003,$A1003,$K$4:$K1003)) | M1003: =IF($H1003="","",N($H1003)) | P1003: =IF($A1003="","",SUMIF($A$4:$A1003,$A1003,$M$4:$M1003)-SUMIF($A$4:$A1003,$A1003,$N$4:$N1003)-SUMIF($A$4:$A1003,$A1003,$O$4:$O1003)) | T1003: =IF($A1003="","",SUMIF($A$4:$A1003,$A1003,$Q$4:$Q1003)-SUMIF($A$4:$A1003,$A1003,$R$4:$R1003)-SUMIF($A$4:$A1003,$A1003,$S$4:$S1003)) | V1003: =IF(AND($C1003="",COUNTA($D1003:$H1003,$K1003,$N1003:$O1003,$Q1003:$S1003,$U1003)=0),"",IF($C1003="","⚠ 没填项目名称",IF($A1003="⚠目录里没有","⚠ 项目名称在目录里找不到（先加到目录）",IF($A1003="","⚠ 目录里这个项目没填简称",IF(ISTEXT($G1003)+ISTEXT($H1003)+ISTEXT($K1003)+ISTEXT($N1003)+ISTEXT($O1003)+ISTEXT($Q1003)+ISTEXT($R1003)+ISTEXT($S1003)>0,"⚠ 金额列里有文字，算不进合计",IF(N($G1003)>=1,"⚠ 管理费点要填百分比，如 10%",IF(AND($D1003<>"",$B1003=""),"△ 摘要开头没写日期（如 2026.9.21），月份取不到",IF(AND(N($H1003)<>0,COUNTIFS($A$4:$A$1003,$A1003,$H$4:$H$1003,$H1003,$D$4:$D$1003,LEFT($D1003,9)&"*")>1),"△ 同一天同项目有一样的销售金额，看看是不是录重了","✓")))))))) | W1003: =IF($A1003="","",$A1003&"#"&COUNTIF($A$4:$A1003,$A1003))

Sheet 项目汇总
A1: 项目汇总
A2: 序号 | B2: 项目简称 （点开分表） | C2: 笔数 | D2: 最后一笔摘要 | E2: 销售金额 | F2: 管理费 | G2: 应开 成本票 | H2: 已开 成本票 | I2: 未开 成本票 | J2: 应收款 | K2: 质保金 | L2: 已收款 | M2: 未收款 | N2: 应付 工程款 | O2: 扣除 管理费 | P2: 已付 工程款 | Q2: 未付 工程款 | R2: 分表核对
A3: 合计 | E3: =SUM(E4:E53) -> 2206559.2 | F3: =SUM(F4:F53) -> 65304.158 | G3: =SUM(G4:G53) -> 2141255 | H3: =SUM(H4:H53) -> 2098816.7 | I3: =G3-H3 -> 42438.29 | J3: =SUM(J4:J53) -> 2206559.2 | K3: =SUM(K4:K53) -> 0 | L3: =SUM(L4:L53) -> 1500594.2 | M3: =J3-K3-L3 -> 705964.91 | N3: =SUM(N4:N53) -> 0 | O3: =SUM(O4:O53) -> 0 | P3: =SUM(P4:P53) -> 576643 | Q3: =N3-O3-P3 -> -576643 | R3: =IF(SUMPRODUCT(ABS(E3:Q3-发票统计!H3:T3))<0.01,"✓ 与发票统计合计一致","⚠ 与发票统计合计对不上：有行没归到项目，看发票统计 V 列") -> ✓ 与发票统计合计一致
A4: =IF($B4="","",ROWS(A$4:A4)) -> 1 | B4: =IFERROR(HYPERLINK("#'"&INDEX(目录!$C$3:$C$102,MATCH(ROWS(B$4:B4),目录!$F$3:$F$102,0))&"'!A1",INDEX(目录!$C$3:$C$102,MATCH(ROWS(B$4:B4),目录!$F$3:$F$102,0))),"") -> 淮阳站阳高线 | C4: =IF($B4="","",COUNTIF(发票统计!$A$4:$A$1003,$B4)) -> 2 | D4: =IF(N($C4)=0,"",INDEX(发票统计!$D$4:$D$1003,MATCH($B4&"#"&$C4,发票统计!$W$4:$W$1003,0))&"") -> 2026.3.25张氏机电-新德润：淮阳站阳高线 | E4: =IF($B4="","",SUMIF(发票统计!$A$4:$A$1003,$B4,发票统计!$H$4:$H$1003)) -> 107944.61 | F4: =IF($B4="","",SUMIF(发票统计!$A$4:$A$1003,$B4,发票统计!$I$4:$I$1003)) -> 0 | G4: =IF($B4="","",SUMIF(发票统计!$A$4:$A$1003,$B4,发票统计!$J$4:$J$1003)) -> 107944.61 | H4: =IF($B4="","",SUMIF(发票统计!$A$4:$A$1003,$B4,发票统计!$K$4:$K$1003)) -> 107944.61 | I4: =IF($B4="","",G4-H4) -> 0 | J4: =IF($B4="","",SUMIF(发票统计!$A$4:$A$1003,$B4,发票统计!$M$4:$M$1003)) -> 107944.61 | K4: =IF($B4="","",SUMIF(发票统计!$A$4:$A$1003,$B4,发票统计!$N$4:$N$1003)) -> 0 | L4: =IF($B4="","",SUMIF(发票统计!$A$4:$A$1003,$B4,发票统计!$O$4:$O$1003)) -> 0 | M4: =IF($B4="","",J4-K4-L4) -> 107944.61 | N4: =IF($B4="","",SUMIF(发票统计!$A$4:$A$1003,$B4,发票统计!$Q$4:$Q$1003)) -> 0 | O4: =IF($B4="","",SUMIF(发票统计!$A$4:$A$1003,$B4,发票统计!$R$4:$R$1003)) -> 0 | P4: =IF($B4="","",SUMIF(发票统计!$A$4:$A$1003,$B4,发票统计!$S$4:$S$1003)) -> 0 | Q4: =IF($B4="","",N4-O4-P4) -> 0 | R4: =IF($B4="","",IFERROR(IF(SUMPRODUCT(ABS(INDIRECT("'"&$B4&"'!H3:T3")-$E4:$Q4))<0.01,"✓","⚠ 分表合计对不上"),"⚠ 还没建分表")) -> ✓
A5: =IF($B5="","",ROWS(A$4:A5)) -> 2 | B5: =IFERROR(HYPERLINK("#'"&INDEX(目录!$C$3:$C$102,MATCH(ROWS(B$4:B5),目录!$F$3:$F$102,0))&"'!A1",INDEX(目录!$C$3:$C$102,MATCH(ROWS(B$4:B5),目录!$F$3:$F$102,0))),"") -> 云龙社区 | C5: =IF($B5="","",COUNTIF(发票统计!$A$4:$A$1003,$B5)) -> 4 | D5: =IF(N($C5)=0,"",INDEX(发票统计!$D$4:$D$1003,MATCH($B5&"#"&$C5,发票统计!$W$4:$W$1003,0))&"") -> 2026.5.13庆文公账收到新德润款项：云龙社区居民委员会 | E5: =IF($B5="","",SUMIF(发票统计!$A$4:$A$1003,$B5,发票统计!$H$4:$H$1003)) -> 227260.8 | F5: =IF($B5="","",SUMIF(发票统计!$A$4:$A$1003,$B5,发票统计!$I$4:$I$1003)) -> 0 | G5: =IF($B5="","",SUMIF(发票统计!$A$4:$A$1003,$B5,发票统计!$J$4:$J$1003)) -> 227260.8 | H5: =IF($B5="","",SUMIF(发票统计!$A$4:$A$1003,$B5,发票统计!$K$4:$K$1003)) -> 227260.8 | I5: =IF($B5="","",G5-H5) -> 0 | J5: =IF($B5="","",SUMIF(发票统计!$A$4:$A$1003,$B5,发票统计!$M$4:$M$1003)) -> 227260.8 | K5: =IF($B5="","",SUMIF(发票统计!$A$4:$A$1003,$B5,发票统计!$N$4:$N$1003)) -> 0 | L5: =IF($B5="","",SUMIF(发票统计!$A$4:$A$1003,$B5,发票统计!$O$4:$O$1003)) -> 227260.8 | M5: =IF($B5="","",J5-K5-L5) -> 0 | N5: =IF($B5="","",SUMIF(发票统计!$A$4:$A$1003,$B5,发票统计!$Q$4:$Q$1003)) -> 0 | O5: =IF($B5="","",SUMIF(发票统计!$A$4:$A$1003,$B5,发票统计!$R$4:$R$1003)) -> 0 | P5: =IF($B5="","",SUMIF(发票统计!$A$4:$A$1003,$B5,发票统计!$S$4:$S$1003)) -> 0 | Q5: =IF($B5="","",N5-O5-P5) -> 0 | R5: =IF($B5="","",IFERROR(IF(SUMPRODUCT(ABS(INDIRECT("'"&$B5&"'!H3:T3")-$E5:$Q5))<0.01,"✓","⚠ 分表合计对不上"),"⚠ 还没建分表")) -> ✓
A6: =IF($B6="","",ROWS(A$4:A6)) -> 3 | B6: =IFERROR(HYPERLINK("#'"&INDEX(目录!$C$3:$C$102,MATCH(ROWS(B$4:B6),目录!$F$3:$F$102,0))&"'!A1",INDEX(目录!$C$3:$C$102,MATCH(ROWS(B$4:B6),目录!$F$3:$F$102,0))),"") -> 合川瑞翔 | C6: =IF($B6="","",COUNTIF(发票统计!$A$4:$A$1003,$B6)) -> 15 | D6: =IF(N($C6)=0,"",INDEX(发票统计!$D$4:$D$1003,MATCH($B6&"#"&$C6,发票统计!$W$4:$W$1003,0))&"") -> 2026.9.14新德润代胡崇文支付宜宾翠屏货款：42800-39473.83=3326.17 | E6: =IF($B6="","",SUMIF(发票统计!$A$4:$A$1003,$B6,发票统计!$H$4:$H$1003)) -> 500000 | F6: =IF($B6="","",SUMIF(发票统计!$A$4:$A$1003,$B6,发票统计!$I$4:$I$1003)) -> 0 | G6: =IF($B6="","",SUMIF(发票统计!$A$4:$A$1003,$B6,发票统计!$J$4:$J$1003)) -> 500000 | H6: =IF($B6="","",SUMIF(发票统计!$A$4:$A$1003,$B6,发票统计!$K$4:$K$1003)) -> 500000 | I6: =IF($B6="","",G6-H6) -> 0 | J6: =IF($B6="","",SUMIF(发票统计!$A$4:$A$1003,$B6,发票统计!$M$4:$M$1003)) -> 500000 | K6: =IF($B6="","",SUMIF(发票统计!$A$4:$A$1003,$B6,发票统计!$N$4:$N$1003)) -> 0 | L6: =IF($B6="","",SUMIF(发票统计!$A$4:$A$1003,$B6,发票统计!$O$4:$O$1003)) -> 503326.17 | M6: =IF($B6="","",J6-K6-L6) -> -3326.17 | N6: =IF($B6="","",SUMIF(发票统计!$A$4:$A$1003,$B6,发票统计!$Q$4:$Q$1003)) -> 0 | O6: =IF($B6="","",SUMIF(发票统计!$A$4:$A$1003,$B6,发票统计!$R$4:$R$1003)) -> 0 | P6: =IF($B6="","",SUMIF(发票统计!$A$4:$A$1003,$B6,发票统计!$S$4:$S$1003)) -> 0 | Q6: =IF($B6="","",N6-O6-P6) -> 0 | R6: =IF($B6="","",IFERROR(IF(SUMPRODUCT(ABS(INDIRECT("'"&$B6&"'!H3:T3")-$E6:$Q6))<0.01,"✓","⚠ 分表合计对不上"),"⚠ 还没建分表")) -> ✓
A7: =IF($B7="","",ROWS(A$4:A7)) -> 4 | B7: =IFERROR(HYPERLINK("#'"&INDEX(目录!$C$3:$C$102,MATCH(ROWS(B$4:B7),目录!$F$3:$F$102,0))&"'!A1",INDEX(目录!$C$3:$C$102,MATCH(ROWS(B$4:B7),目录!$F$3:$F$102,0))),"") -> 铜城2回、玉璟尚线、铁井一回、淮拦线4 | C7: =IF($B7="","",COUNTIF(发票统计!$A$4:$A$1003,$B7)) -> 15 | D7: =IF(N($C7)=0,"",INDEX(发票统计!$D$4:$D$1003,MATCH($B7&"#"&$C7,发票统计!$W$4:$W$1003,0))&"") -> 2026.9.14新德润代胡崇文支付宜宾翠屏货款：42800-39473.83=3326.17 | E7: =IF($B7="","",SUMIF(发票统计!$A$4:$A$1003,$B7,发票统计!$H$4:$H$1003)) -> 121598.1 | F7: =IF($B7="","",SUMIF(发票统计!$A$4:$A$1003,$B7,发票统计!$I$4:$I$1003)) -> 12159.81 | G7: =IF($B7="","",SUMIF(发票统计!$A$4:$A$1003,$B7,发票统计!$J$4:$J$1003)) -> 109438.29 | H7: =IF($B7="","",SUMIF(发票统计!$A$4:$A$1003,$B7,发票统计!$K$4:$K$1003)) -> 167000 | I7: =IF($B7="","",G7-H7) -> -57561.71 | J7: =IF($B7="","",SUMIF(发票统计!$A$4:$A$1003,$B7,发票统计!$M$4:$M$1003)) -> 121598.1 | K7: =IF($B7="","",SUMIF(发票统计!$A$4:$A$1003,$B7,发票统计!$N$4:$N$1003)) -> 0 | L7: =IF($B7="","",SUMIF(发票统计!$A$4:$A$1003,$B7,发票统计!$O$4:$O$1003)) -> 115307.26 | M7: =IF($B7="","",J7-K7-L7) -> 6290.84 | N7: =IF($B7="","",SUMIF(发票统计!$A$4:$A$1003,$B7,发票统计!$Q$4:$Q$1003)) -> 0 | O7: =IF($B7="","",SUMIF(发票统计!$A$4:$A$1003,$B7,发票统计!$R$4:$R$1003)) -> 0 | P7: =IF($B7="","",SUMIF(发票统计!$A$4:$A$1003,$B7,发票统计!$S$4:$S$1003)) -> 0 | Q7: =IF($B7="","",N7-O7-P7) -> 0 | R7: =IF($B7="","",IFERROR(IF(SUMPRODUCT(ABS(INDIRECT("'"&$B7&"'!H3:T3")-$E7:$Q7))<0.01,"✓","⚠ 分表合计对不上"),"⚠ 还没建分表")) -> ✓
A8: =IF($B8="","",ROWS(A$4:A8)) -> 5 | B8: =IFERROR(HYPERLINK("#'"&INDEX(目录!$C$3:$C$102,MATCH(ROWS(B$4:B8),目录!$F$3:$F$102,0))&"'!A1",INDEX(目录!$C$3:$C$102,MATCH(ROWS(B$4:B8),目录!$F$3:$F$102,0))),"") -> 合川表计 | C8: =IF($B8="","",COUNTIF(发票统计!$A$4:$A$1003,$B8)) -> 42 | D8: =IF(N($C8)=0,"",INDEX(发票统计!$D$4:$D$1003,MATCH($B8&"#"&$C8,发票统计!$W$4:$W$1003,0))&"") -> 2026.9.22胡崇文支付表计工资 | E8: =IF($B8="","",SUMIF(发票统计!$A$4:$A$1003,$B8,发票统计!$H$4:$H$1003)) -> 895460 | F8: =IF($B8="","",SUMIF(发票统计!$A$4:$A$1003,$B8,发票统计!$I$4:$I$1003)) -> 0 | G8: =IF($B8="","",SUMIF(发票统计!$A$4:$A$1003,$B8,发票统计!$J$4:$J$1003)) -> 895460 | H8: =IF($B8="","",SUMIF(发票统计!$A$4:$A$1003,$B8,发票统计!$K$4:$K$1003)) -> 795460 | I8: =IF($B8="","",G8-H8) -> 100000 | J8: =IF($B8="","",SUMIF(发票统计!$A$4:$A$1003,$B8,发票统计!$M$4:$M$1003)) -> 895460 | K8: =IF($B8="","",SUMIF(发票统计!$A$4:$A$1003,$B8,发票统计!$N$4:$N$1003)) -> 0 | L8: =IF($B8="","",SUMIF(发票统计!$A$4:$A$1003,$B8,发票统计!$O$4:$O$1003)) -> 350000 | M8: =IF($B8="","",J8-K8-L8) -> 545460 | N8: =IF($B8="","",SUMIF(发票统计!$A$4:$A$1003,$B8,发票统计!$Q$4:$Q$1003)) -> 0 | O8: =IF($B8="","",SUMIF(发票统计!$A$4:$A$1003,$B8,发票统计!$R$4:$R$1003)) -> 0 | P8: =IF($B8="","",SUMIF(发票统计!$A$4:$A$1003,$B8,发票统计!$S$4:$S$1003)) -> 576643 | Q8: =IF($B8="","",N8-O8-P8) -> -576643 | R8: =IF($B8="","",IFERROR(IF(SUMPRODUCT(ABS(INDIRECT("'"&$B8&"'!H3:T3")-$E8:$Q8))<0.01,"✓","⚠ 分表合计对不上"),"⚠ 还没建分表")) -> ✓
A9: =IF($B9="","",ROWS(A$4:A9)) -> 6 | B9: =IFERROR(HYPERLINK("#'"&INDEX(目录!$C$3:$C$102,MATCH(ROWS(B$4:B9),目录!$F$3:$F$102,0))&"'!A1",INDEX(目录!$C$3:$C$102,MATCH(ROWS(B$4:B9),目录!$F$3:$F$102,0))),"") -> 蒲吕片区A段 | C9: =IF($B9="","",COUNTIF(发票统计!$A$4:$A$1003,$B9)) -> 8 | D9: =IF(N($C9)=0,"",INDEX(发票统计!$D$4:$D$1003,MATCH($B9&"#"&$C9,发票统计!$W$4:$W$1003,0))&"") -> 2026.9.4新德润开9%专票到民能：蒲吕片区A段10千伏电力新建 | E9: =IF($B9="","",SUMIF(发票统计!$A$4:$A$1003,$B9,发票统计!$H$4:$H$1003)) -> 354295.65 | F9: =IF($B9="","",SUMIF(发票统计!$A$4:$A$1003,$B9,发票统计!$I$4:$I$1003)) -> 53144.348 | G9: =IF($B9="","",SUMIF(发票统计!$A$4:$A$1003,$B9,发票统计!$J$4:$J$1003)) -> 301151.3 | H9: =IF($B9="","",SUMIF(发票统计!$A$4:$A$1003,$B9,发票统计!$K$4:$K$1003)) -> 301151.3 | I9: =IF($B9="","",G9-H9) -> 0 | J9: =IF($B9="","",SUMIF(发票统计!$A$4:$A$1003,$B9,发票统计!$M$4:$M$1003)) -> 354295.65 | K9: =IF($B9="","",SUMIF(发票统计!$A$4:$A$1003,$B9,发票统计!$N$4:$N$1003)) -> 0 | L9: =IF($B9="","",SUMIF(发票统计!$A$4:$A$1003,$B9,发票统计!$O$4:$O$1003)) -> 304700.02 | M9: =IF($B9="","",J9-K9-L9) -> 49595.632 | N9: =IF($B9="","",SUMIF(发票统计!$A$4:$A$1003,$B9,发票统计!$Q$4:$Q$1003)) -> 0 | O9: =IF($B9="","",SUMIF(发票统计!$A$4:$A$1003,$B9,发票统计!$R$4:$R$1003)) -> 0 | P9: =IF($B9="","",SUMIF(发票统计!$A$4:$A$1003,$B9,发票统计!$S$4:$S$1003)) -> 0 | Q9: =IF($B9="","",N9-O9-P9) -> 0 | R9: =IF($B9="","",IFERROR(IF(SUMPRODUCT(ABS(INDIRECT("'"&$B9&"'!H3:T3")-$E9:$Q9))<0.01,"✓","⚠ 分表合计对不上"),"⚠ 还没建分表")) -> ✓
A10: =IF($B10="","",ROWS(A$4:A10)) | B10: =IFERROR(HYPERLINK("#'"&INDEX(目录!$C$3:$C$102,MATCH(ROWS(B$4:B10),目录!$F$3:$F$102,0))&"'!A1",INDEX(目录!$C$3:$C$102,MATCH(ROWS(B$4:B10),目录!$F$3:$F$102,0))),"") | C10: =IF($B10="","",COUNTIF(发票统计!$A$4:$A$1003,$B10)) | D10: =IF(N($C10)=0,"",INDEX(发票统计!$D$4:$D$1003,MATCH($B10&"#"&$C10,发票统计!$W$4:$W$1003,0))&"") | E10: =IF($B10="","",SUMIF(发票统计!$A$4:$A$1003,$B10,发票统计!$H$4:$H$1003)) | F10: =IF($B10="","",SUMIF(发票统计!$A$4:$A$1003,$B10,发票统计!$I$4:$I$1003)) | G10: =IF($B10="","",SUMIF(发票统计!$A$4:$A$1003,$B10,发票统计!$J$4:$J$1003)) | H10: =IF($B10="","",SUMIF(发票统计!$A$4:$A$1003,$B10,发票统计!$K$4:$K$1003)) | I10: =IF($B10="","",G10-H10) | J10: =IF($B10="","",SUMIF(发票统计!$A$4:$A$1003,$B10,发票统计!$M$4:$M$1003)) | K10: =IF($B10="","",SUMIF(发票统计!$A$4:$A$1003,$B10,发票统计!$N$4:$N$1003)) | L10: =IF($B10="","",SUMIF(发票统计!$A$4:$A$1003,$B10,发票统计!$O$4:$O$1003)) | M10: =IF($B10="","",J10-K10-L10) | N10: =IF($B10="","",SUMIF(发票统计!$A$4:$A$1003,$B10,发票统计!$Q$4:$Q$1003)) | O10: =IF($B10="","",SUMIF(发票统计!$A$4:$A$1003,$B10,发票统计!$R$4:$R$1003)) | P10: =IF($B10="","",SUMIF(发票统计!$A$4:$A$1003,$B10,发票统计!$S$4:$S$1003)) | Q10: =IF($B10="","",N10-O10-P10) | R10: =IF($B10="","",IFERROR(IF(SUMPRODUCT(ABS(INDIRECT("'"&$B10&"'!H3:T3")-$E10:$Q10))<0.01,"✓","⚠ 分表合计对不上"),"⚠ 还没建分表"))
A11: =IF($B11="","",ROWS(A$4:A11)) | B11: =IFERROR(HYPERLINK("#'"&INDEX(目录!$C$3:$C$102,MATCH(ROWS(B$4:B11),目录!$F$3:$F$102,0))&"'!A1",INDEX(目录!$C$3:$C$102,MATCH(ROWS(B$4:B11),目录!$F$3:$F$102,0))),"") | C11: =IF($B11="","",COUNTIF(发票统计!$A$4:$A$1003,$B11)) | D11: =IF(N($C11)=0,"",INDEX(发票统计!$D$4:$D$1003,MATCH($B11&"#"&$C11,发票统计!$W$4:$W$1003,0))&"") | E11: =IF($B11="","",SUMIF(发票统计!$A$4:$A$1003,$B11,发票统计!$H$4:$H$1003)) | F11: =IF($B11="","",SUMIF(发票统计!$A$4:$A$1003,$B11,发票统计!$I$4:$I$1003)) | G11: =IF($B11="","",SUMIF(发票统计!$A$4:$A$1003,$B11,发票统计!$J$4:$J$1003)) | H11: =IF($B11="","",SUMIF(发票统计!$A$4:$A$1003,$B11,发票统计!$K$4:$K$1003)) | I11: =IF($B11="","",G11-H11) | J11: =IF($B11="","",SUMIF(发票统计!$A$4:$A$1003,$B11,发票统计!$M$4:$M$1003)) | K11: =IF($B11="","",SUMIF(发票统计!$A$4:$A$1003,$B11,发票统计!$N$4:$N$1003)) | L11: =IF($B11="","",SUMIF(发票统计!$A$4:$A$1003,$B11,发票统计!$O$4:$O$1003)) | M11: =IF($B11="","",J11-K11-L11) | N11: =IF($B11="","",SUMIF(发票统计!$A$4:$A$1003,$B11,发票统计!$Q$4:$Q$1003)) | O11: =IF($B11="","",SUMIF(发票统计!$A$4:$A$1003,$B11,发票统计!$R$4:$R$1003)) | P11: =IF($B11="","",SUMIF(发票统计!$A$4:$A$1003,$B11,发票统计!$S$4:$S$1003)) | Q11: =IF($B11="","",N11-O11-P11) | R11: =IF($B11="","",IFERROR(IF(SUMPRODUCT(ABS(INDIRECT("'"&$B11&"'!H3:T3")-$E11:$Q11))<0.01,"✓","⚠ 分表合计对不上"),"⚠ 还没建分表"))
A12: =IF($B12="","",ROWS(A$4:A12)) | B12: =IFERROR(HYPERLINK("#'"&INDEX(目录!$C$3:$C$102,MATCH(ROWS(B$4:B12),目录!$F$3:$F$102,0))&"'!A1",INDEX(目录!$C$3:$C$102,MATCH(ROWS(B$4:B12),目录!$F$3:$F$102,0))),"") | C12: =IF($B12="","",COUNTIF(发票统计!$A$4:$A$1003,$B12)) | D12: =IF(N($C12)=0,"",INDEX(发票统计!$D$4:$D$1003,MATCH($B12&"#"&$C12,发票统计!$W$4:$W$1003,0))&"") | E12: =IF($B12="","",SUMIF(发票统计!$A$4:$A$1003,$B12,发票统计!$H$4:$H$1003)) | F12: =IF($B12="","",SUMIF(发票统计!$A$4:$A$1003,$B12,发票统计!$I$4:$I$1003)) | G12: =IF($B12="","",SUMIF(发票统计!$A$4:$A$1003,$B12,发票统计!$J$4:$J$1003)) | H12: =IF($B12="","",SUMIF(发票统计!$A$4:$A$1003,$B12,发票统计!$K$4:$K$1003)) | I12: =IF($B12="","",G12-H12) | J12: =IF($B12="","",SUMIF(发票统计!$A$4:$A$1003,$B12,发票统计!$M$4:$M$1003)) | K12: =IF($B12="","",SUMIF(发票统计!$A$4:$A$1003,$B12,发票统计!$N$4:$N$1003)) | L12: =IF($B12="","",SUMIF(发票统计!$A$4:$A$1003,$B12,发票统计!$O$4:$O$1003)) | M12: =IF($B12="","",J12-K12-L12) | N12: =IF($B12="","",SUMIF(发票统计!$A$4:$A$1003,$B12,发票统计!$Q$4:$Q$1003)) | O12: =IF($B12="","",SUMIF(发票统计!$A$4:$A$1003,$B12,发票统计!$R$4:$R$1003)) | P12: =IF($B12="","",SUMIF(发票统计!$A$4:$A$1003,$B12,发票统计!$S$4:$S$1003)) | Q12: =IF($B12="","",N12-O12-P12) | R12: =IF($B12="","",IFERROR(IF(SUMPRODUCT(ABS(INDIRECT("'"&$B12&"'!H3:T3")-$E12:$Q12))<0.01,"✓","⚠ 分表合计对不上"),"⚠ 还没建分表"))
A13: =IF($B13="","",ROWS(A$4:A13)) | B13: =IFERROR(HYPERLINK("#'"&INDEX(目录!$C$3:$C$102,MATCH(ROWS(B$4:B13),目录!$F$3:$F$102,0))&"'!A1",INDEX(目录!$C$3:$C$102,MATCH(ROWS(B$4:B13),目录!$F$3:$F$102,0))),"") | C13: =IF($B13="","",COUNTIF(发票统计!$A$4:$A$1003,$B13)) | D13: =IF(N($C13)=0,"",INDEX(发票统计!$D$4:$D$1003,MATCH($B13&"#"&$C13,发票统计!$W$4:$W$1003,0))&"") | E13: =IF($B13="","",SUMIF(发票统计!$A$4:$A$1003,$B13,发票统计!$H$4:$H$1003)) | F13: =IF($B13="","",SUMIF(发票统计!$A$4:$A$1003,$B13,发票统计!$I$4:$I$1003)) | G13: =IF($B13="","",SUMIF(发票统计!$A$4:$A$1003,$B13,发票统计!$J$4:$J$1003)) | H13: =IF($B13="","",SUMIF(发票统计!$A$4:$A$1003,$B13,发票统计!$K$4:$K$1003)) | I13: =IF($B13="","",G13-H13) | J13: =IF($B13="","",SUMIF(发票统计!$A$4:$A$1003,$B13,发票统计!$M$4:$M$1003)) | K13: =IF($B13="","",SUMIF(发票统计!$A$4:$A$1003,$B13,发票统计!$N$4:$N$1003)) | L13: =IF($B13="","",SUMIF(发票统计!$A$4:$A$1003,$B13,发票统计!$O$4:$O$1003)) | M13: =IF($B13="","",J13-K13-L13) | N13: =IF($B13="","",SUMIF(发票统计!$A$4:$A$1003,$B13,发票统计!$Q$4:$Q$1003)) | O13: =IF($B13="","",SUMIF(发票统计!$A$4:$A$1003,$B13,发票统计!$R$4:$R$1003)) | P13: =IF($B13="","",SUMIF(发票统计!$A$4:$A$1003,$B13,发票统计!$S$4:$S$1003)) | Q13: =IF($B13="","",N13-O13-P13) | R13: =IF($B13="","",IFERROR(IF(SUMPRODUCT(ABS(INDIRECT("'"&$B13&"'!H3:T3")-$E13:$Q13))<0.01,"✓","⚠ 分表合计对不上"),"⚠ 还没建分表"))
A14: =IF($B14="","",ROWS(A$4:A14)) | B14: =IFERROR(HYPERLINK("#'"&INDEX(目录!$C$3:$C$102,MATCH(ROWS(B$4:B14),目录!$F$3:$F$102,0))&"'!A1",INDEX(目录!$C$3:$C$102,MATCH(ROWS(B$4:B14),目录!$F$3:$F$102,0))),"") | C14: =IF($B14="","",COUNTIF(发票统计!$A$4:$A$1003,$B14)) | D14: =IF(N($C14)=0,"",INDEX(发票统计!$D$4:$D$1003,MATCH($B14&"#"&$C14,发票统计!$W$4:$W$1003,0))&"") | E14: =IF($B14="","",SUMIF(发票统计!$A$4:$A$1003,$B14,发票统计!$H$4:$H$1003)) | F14: =IF($B14="","",SUMIF(发票统计!$A$4:$A$1003,$B14,发票统计!$I$4:$I$1003)) | G14: =IF($B14="","",SUMIF(发票统计!$A$4:$A$1003,$B14,发票统计!$J$4:$J$1003)) | H14: =IF($B14="","",SUMIF(发票统计!$A$4:$A$1003,$B14,发票统计!$K$4:$K$1003)) | I14: =IF($B14="","",G14-H14) | J14: =IF($B14="","",SUMIF(发票统计!$A$4:$A$1003,$B14,发票统计!$M$4:$M$1003)) | K14: =IF($B14="","",SUMIF(发票统计!$A$4:$A$1003,$B14,发票统计!$N$4:$N$1003)) | L14: =IF($B14="","",SUMIF(发票统计!$A$4:$A$1003,$B14,发票统计!$O$4:$O$1003)) | M14: =IF($B14="","",J14-K14-L14) | N14: =IF($B14="","",SUMIF(发票统计!$A$4:$A$1003,$B14,发票统计!$Q$4:$Q$1003)) | O14: =IF($B14="","",SUMIF(发票统计!$A$4:$A$1003,$B14,发票统计!$R$4:$R$1003)) | P14: =IF($B14="","",SUMIF(发票统计!$A$4:$A$1003,$B14,发票统计!$S$4:$S$1003)) | Q14: =IF($B14="","",N14-O14-P14) | R14: =IF($B14="","",IFERROR(IF(SUMPRODUCT(ABS(INDIRECT("'"&$B14&"'!H3:T3")-$E14:$Q14))<0.01,"✓","⚠ 分表合计对不上"),"⚠ 还没建分表"))
A15: =IF($B15="","",ROWS(A$4:A15)) | B15: =IFERROR(HYPERLINK("#'"&INDEX(目录!$C$3:$C$102,MATCH(ROWS(B$4:B15),目录!$F$3:$F$102,0))&"'!A1",INDEX(目录!$C$3:$C$102,MATCH(ROWS(B$4:B15),目录!$F$3:$F$102,0))),"") | C15: =IF($B15="","",COUNTIF(发票统计!$A$4:$A$1003,$B15)) | D15: =IF(N($C15)=0,"",INDEX(发票统计!$D$4:$D$1003,MATCH($B15&"#"&$C15,发票统计!$W$4:$W$1003,0))&"") | E15: =IF($B15="","",SUMIF(发票统计!$A$4:$A$1003,$B15,发票统计!$H$4:$H$1003)) | F15: =IF($B15="","",SUMIF(发票统计!$A$4:$A$1003,$B15,发票统计!$I$4:$I$1003)) | G15: =IF($B15="","",SUMIF(发票统计!$A$4:$A$1003,$B15,发票统计!$J$4:$J$1003)) | H15: =IF($B15="","",SUMIF(发票统计!$A$4:$A$1003,$B15,发票统计!$K$4:$K$1003)) | I15: =IF($B15="","",G15-H15) | J15: =IF($B15="","",SUMIF(发票统计!$A$4:$A$1003,$B15,发票统计!$M$4:$M$1003)) | K15: =IF($B15="","",SUMIF(发票统计!$A$4:$A$1003,$B15,发票统计!$N$4:$N$1003)) | L15: =IF($B15="","",SUMIF(发票统计!$A$4:$A$1003,$B15,发票统计!$O$4:$O$1003)) | M15: =IF($B15="","",J15-K15-L15) | N15: =IF($B15="","",SUMIF(发票统计!$A$4:$A$1003,$B15,发票统计!$Q$4:$Q$1003)) | O15: =IF($B15="","",SUMIF(发票统计!$A$4:$A$1003,$B15,发票统计!$R$4:$R$1003)) | P15: =IF($B15="","",SUMIF(发票统计!$A$4:$A$1003,$B15,发票统计!$S$4:$S$1003)) | Q15: =IF($B15="","",N15-O15-P15) | R15: =IF($B15="","",IFERROR(IF(SUMPRODUCT(ABS(INDIRECT("'"&$B15&"'!H3:T3")-$E15:$Q15))<0.01,"✓","⚠ 分表合计对不上"),"⚠ 还没建分表"))
... A53: =IF($B53="","",ROWS(A$4:A53)) | B53: =IFERROR(HYPERLINK("#'"&INDEX(目录!$C$3:$C$102,MATCH(ROWS(B$4:B53),目录!$F$3:$F$102,0))&"'!A1",INDEX(目录!$C$3:$C$102,MATCH(ROWS(B$4:B53),目录!$F$3:$F$102,0))),"") | C53: =IF($B53="","",COUNTIF(发票统计!$A$4:$A$1003,$B53)) | D53: =IF(N($C53)=0,"",INDEX(发票统计!$D$4:$D$1003,MATCH($B53&"#"&$C53,发票统计!$W$4:$W$1003,0))&"") | E53: =IF($B53="","",SUMIF(发票统计!$A$4:$A$1003,$B53,发票统计!$H$4:$H$1003)) | F53: =IF($B53="","",SUMIF(发票统计!$A$4:$A$1003,$B53,发票统计!$I$4:$I$1003)) | G53: =IF($B53="","",SUMIF(发票统计!$A$4:$A$1003,$B53,发票统计!$J$4:$J$1003)) | H53: =IF($B53="","",SUMIF(发票统计!$A$4:$A$1003,$B53,发票统计!$K$4:$K$1003)) | I53: =IF($B53="","",G53-H53) | J53: =IF($B53="","",SUMIF(发票统计!$A$4:$A$1003,$B53,发票统计!$M$4:$M$1003)) | K53: =IF($B53="","",SUMIF(发票统计!$A$4:$A$1003,$B53,发票统计!$N$4:$N$1003)) | L53: =IF($B53="","",SUMIF(发票统计!$A$4:$A$1003,$B53,发票统计!$O$4:$O$1003)) | M53: =IF($B53="","",J53-K53-L53) | N53: =IF($B53="","",SUMIF(发票统计!$A$4:$A$1003,$B53,发票统计!$Q$4:$Q$1003)) | O53: =IF($B53="","",SUMIF(发票统计!$A$4:$A$1003,$B53,发票统计!$R$4:$R$1003)) | P53: =IF($B53="","",SUMIF(发票统计!$A$4:$A$1003,$B53,发票统计!$S$4:$S$1003)) | Q53: =IF($B53="","",N53-O53-P53) | R53: =IF($B53="","",IFERROR(IF(SUMPRODUCT(ABS(INDIRECT("'"&$B53&"'!H3:T3")-$E53:$Q53))<0.01,"✓","⚠ 分表合计对不上"),"⚠ 还没建分表"))

Sheet 蒲吕片区A段
A1: 铜梁区园区屋顶分布式光伏发电建设项目-蒲吕片区A段10千伏电力新建工程
A2: 对账 单位 | B2: 月份 | C2: 项目 名称 | D2: 摘要 | E2: 收票 单位 | F2: 发票 性质 | G2: 管理 费点 | H2: 销售金额 | I2: 管理费 | J2: 应开 成本票 | K2: 已开 成本票 | L2: 未开 成本票 | M2: 应收款 | N2: 质保金 | O2: 已收款 | P2: 未收款 | Q2: 应付 工程款 | R2: 扣除 管理费 | S2: 已付 工程款 | T2: 未付 工程款 | U2: 备注 | V2: 本表项目简称 （自动取表名）
H3: =SUM(H4:H303) -> 354295.65 | I3: =SUM(I4:I303) -> 53144.348 | J3: =SUM(J4:J303) -> 301151.3 | K3: =SUM(K4:K303) -> 301151.3 | L3: =J3-K3 -> 0 | M3: =SUM(M4:M303) -> 354295.65 | N3: =SUM(N4:N303) -> 0 | O3: =SUM(O4:O303) -> 304700.02 | P3: =M3-N3-O3 -> 49595.633 | Q3: =SUM(Q4:Q303) -> 0 | R3: =SUM(R4:R303) -> 0 | S3: =SUM(S4:S303) -> 0 | T3: =Q3-R3-S3 -> 0 | V3: =IFERROR(MID(CELL("filename",$A$1),FIND("]",CELL("filename",$A$1))+1,99),IFERROR(SUBSTITUTE(MID(CELL("filename",$A$1),FIND("#$",CELL("filename",$A$1))+2,99),"'",""),"")) -> 蒲吕片区A段
A4: =IF($W4="","",INDEX(发票统计!A$4:A$1003,$W4)&"") -> 蒲吕片区A段 | B4: =IF($W4="","",INDEX(发票统计!B$4:B$1003,$W4)&"") -> 2月 | C4: =IF($W4="","",INDEX(发票统计!C$4:C$1003,$W4)&"") -> 铜梁区园区屋顶分布式光伏发电建设项目-蒲吕片区A段10千伏电力新建工程 | D4: =IF($W4="","",INDEX(发票统计!D$4:D$1003,$W4)&"") -> 2026.2.9新德润开9%专票到民能：蒲吕片区A段10千伏电力新建 | E4: =IF($W4="","",INDEX(发票统计!E$4:E$1003,$W4)&"") -> 民能 | F4: =IF($W4="","",INDEX(发票统计!F$4:F$1003,$W4)&"") -> 9%专票 | G4: =IF($W4="","",IF(INDEX(发票统计!G$4:G$1003,$W4)="","",INDEX(发票统计!G$4:G$1003,$W4))) -> 0.15 | H4: =IF($W4="","",N(INDEX(发票统计!H$4:H$1003,$W4))) -> 200000 | I4: =IF($W4="","",N(INDEX(发票统计!I$4:I$1003,$W4))) -> 30000 | J4: =IF($W4="","",N(INDEX(发票统计!J$4:J$1003,$W4))) -> 170000 | K4: =IF($W4="","",N(INDEX(发票统计!K$4:K$1003,$W4))) -> 0 | L4: =IF($W4="","",SUM(J$4:J4)-SUM(K$4:K4)) -> 170000 | M4: =IF($W4="","",N(INDEX(发票统计!M$4:M$1003,$W4))) -> 200000 | N4: =IF($W4="","",N(INDEX(发票统计!N$4:N$1003,$W4))) -> 0 | O4: =IF($W4="","",N(INDEX(发票统计!O$4:O$1003,$W4))) -> 0 | P4: =IF($W4="","",SUM(M$4:M4)-SUM(N$4:N4)-SUM(O$4:O4)) -> 200000 | Q4: =IF($W4="","",N(INDEX(发票统计!Q$4:Q$1003,$W4))) -> 0 | R4: =IF($W4="","",N(INDEX(发票统计!R$4:R$1003,$W4))) -> 0 | S4: =IF($W4="","",N(INDEX(发票统计!S$4:S$1003,$W4))) -> 0 | T4: =IF($W4="","",SUM(Q$4:Q4)-SUM(R$4:R4)-SUM(S$4:S4)) -> 0 | U4: =IF($W4="","",INDEX(发票统计!U$4:U$1003,$W4)&"") | V4: =IF($V$3="","⚠ 取不到表名，请在 V3 手填项目简称",IF(COUNTIF(发票统计!$A$4:$A$1003,$V$3)=0,"⚠ 发票统计里没有「"&$V$3&"」的行，表名要和目录里的简称一样",IF(COUNTIF(发票统计!$A$4:$A$1003,$V$3)>300,"⚠ 本项目超过 300 行，后面的没显示","共 "&COUNTIF(发票统计!$A$4:$A$1003,$V$3)&" 笔"))) -> 共 8 笔 | W4: =IF($V$3="","",IFERROR(MATCH($V$3&"#"&ROWS(W$4:W4),发票统计!$W$4:$W$1003,0),"")) -> 79
A5: =IF($W5="","",INDEX(发票统计!A$4:A$1003,$W5)&"") -> 蒲吕片区A段 | B5: =IF($W5="","",INDEX(发票统计!B$4:B$1003,$W5)&"") -> 9月 | C5: =IF($W5="","",INDEX(发票统计!C$4:C$1003,$W5)&"") -> 铜梁区园区屋顶分布式光伏发电建设项目-蒲吕片区A段10千伏电力新建工程 | D5: =IF($W5="","",INDEX(发票统计!D$4:D$1003,$W5)&"") -> 2026.9.1扣15%管理费 | E5: =IF($W5="","",INDEX(发票统计!E$4:E$1003,$W5)&"") -> 民能 | F5: =IF($W5="","",INDEX(发票统计!F$4:F$1003,$W5)&"") -> 9%专票 | G5: =IF($W5="","",IF(INDEX(发票统计!G$4:G$1003,$W5)="","",INDEX(发票统计!G$4:G$1003,$W5))) -> 0.15 | H5: =IF($W5="","",N(INDEX(发票统计!H$4:H$1003,$W5))) -> 0 | I5: =IF($W5="","",N(INDEX(发票统计!I$4:I$1003,$W5))) -> 0 | J5: =IF($W5="","",N(INDEX(发票统计!J$4:J$1003,$W5))) -> 0 | K5: =IF($W5="","",N(INDEX(发票统计!K$4:K$1003,$W5))) -> 0 | L5: =IF($W5="","",SUM(J$4:J5)-SUM(K$4:K5)) -> 170000 | M5: =IF($W5="","",N(INDEX(发票统计!M$4:M$1003,$W5))) -> 0 | N5: =IF($W5="","",N(INDEX(发票统计!N$4:N$1003,$W5))) -> 0 | O5: =IF($W5="","",N(INDEX(发票统计!O$4:O$1003,$W5))) -> 30000 | P5: =IF($W5="","",SUM(M$4:M5)-SUM(N$4:N5)-SUM(O$4:O5)) -> 170000 | Q5: =IF($W5="","",N(INDEX(发票统计!Q$4:Q$1003,$W5))) -> 0 | R5: =IF($W5="","",N(INDEX(发票统计!R$4:R$1003,$W5))) -> 0 | S5: =IF($W5="","",N(INDEX(发票统计!S$4:S$1003,$W5))) -> 0 | T5: =IF($W5="","",SUM(Q$4:Q5)-SUM(R$4:R5)-SUM(S$4:S5)) -> 0 | U5: =IF($W5="","",INDEX(发票统计!U$4:U$1003,$W5)&"") | W5: =IF($V$3="","",IFERROR(MATCH($V$3&"#"&ROWS(W$4:W5),发票统计!$W$4:$W$1003,0),"")) -> 80
A6: =IF($W6="","",INDEX(发票统计!A$4:A$1003,$W6)&"") -> 蒲吕片区A段 | B6: =IF($W6="","",INDEX(发票统计!B$4:B$1003,$W6)&"") -> 9月 | C6: =IF($W6="","",INDEX(发票统计!C$4:C$1003,$W6)&"") -> 铜梁区园区屋顶分布式光伏发电建设项目-蒲吕片区A段10千伏电力新建工程 | D6: =IF($W6="","",INDEX(发票统计!D$4:D$1003,$W6)&"") -> 2026.9.1确认前期收到代发工资 | E6: =IF($W6="","",INDEX(发票统计!E$4:E$1003,$W6)&"") -> 民能 | F6: =IF($W6="","",INDEX(发票统计!F$4:F$1003,$W6)&"") -> 9%专票 | G6: =IF($W6="","",IF(INDEX(发票统计!G$4:G$1003,$W6)="","",INDEX(发票统计!G$4:G$1003,$W6))) -> 0.15 | H6: =IF($W6="","",N(INDEX(发票统计!H$4:H$1003,$W6))) -> 0 | I6: =IF($W6="","",N(INDEX(发票统计!I$4:I$1003,$W6))) -> 0 | J6: =IF($W6="","",N(INDEX(发票统计!J$4:J$1003,$W6))) -> 0 | K6: =IF($W6="","",N(INDEX(发票统计!K$4:K$1003,$W6))) -> 200000 | L6: =IF($W6="","",SUM(J$4:J6)-SUM(K$4:K6)) -> -30000 | M6: =IF($W6="","",N(INDEX(发票统计!M$4:M$1003,$W6))) -> 0 | N6: =IF($W6="","",N(INDEX(发票统计!N$4:N$1003,$W6))) -> 0 | O6: =IF($W6="","",N(INDEX(发票统计!O$4:O$1003,$W6))) -> 200000 | P6: =IF($W6="","",SUM(M$4:M6)-SUM(N$4:N6)-SUM(O$4:O6)) -> -30000 | Q6: =IF($W6="","",N(INDEX(发票统计!Q$4:Q$1003,$W6))) -> 0 | R6: =IF($W6="","",N(INDEX(发票统计!R$4:R$1003,$W6))) -> 0 | S6: =IF($W6="","",N(INDEX(发票统计!S$4:S$1003,$W6))) -> 0 | T6: =IF($W6="","",SUM(Q$4:Q6)-SUM(R$4:R6)-SUM(S$4:S6)) -> 0 | U6: =IF($W6="","",INDEX(发票统计!U$4:U$1003,$W6)&"") | W6: =IF($V$3="","",IFERROR(MATCH($V$3&"#"&ROWS(W$4:W6),发票统计!$W$4:$W$1003,0),"")) -> 81
A7: =IF($W7="","",INDEX(发票统计!A$4:A$1003,$W7)&"") -> 蒲吕片区A段 | B7: =IF($W7="","",INDEX(发票统计!B$4:B$1003,$W7)&"") -> 9月 | C7: =IF($W7="","",INDEX(发票统计!C$4:C$1003,$W7)&"") -> 铜梁区园区屋顶分布式光伏发电建设项目-蒲吕片区A段10千伏电力新建工程 | D7: =IF($W7="","",INDEX(发票统计!D$4:D$1003,$W7)&"") -> 2026.9.1确认扣9%增值税29253.77，附加科3510.45，印花税212.58，合计32976.8 | E7: =IF($W7="","",INDEX(发票统计!E$4:E$1003,$W7)&"") -> 民能 | F7: =IF($W7="","",INDEX(发票统计!F$4:F$1003,$W7)&"") -> 9%专票 | G7: =IF($W7="","",IF(INDEX(发票统计!G$4:G$1003,$W7)="","",INDEX(发票统计!G$4:G$1003,$W7))) -> 0.15 | H7: =IF($W7="","",N(INDEX(发票统计!H$4:H$1003,$W7))) -> 0 | I7: =IF($W7="","",N(INDEX(发票统计!I$4:I$1003,$W7))) -> 0 | J7: =IF($W7="","",N(INDEX(发票统计!J$4:J$1003,$W7))) -> 0 | K7: =IF($W7="","",N(INDEX(发票统计!K$4:K$1003,$W7))) -> 32976.8 | L7: =IF($W7="","",SUM(J$4:J7)-SUM(K$4:K7)) -> -62976.8 | M7: =IF($W7="","",N(INDEX(发票统计!M$4:M$1003,$W7))) -> 0 | N7: =IF($W7="","",N(INDEX(发票统计!N$4:N$1003,$W7))) -> 0 | O7: =IF($W7="","",N(INDEX(发票统计!O$4:O$1003,$W7))) -> 32976.8 | P7: =IF($W7="","",SUM(M$4:M7)-SUM(N$4:N7)-SUM(O$4:O7)) -> -62976.8 | Q7: =IF($W7="","",N(INDEX(发票统计!Q$4:Q$1003,$W7))) -> 0 | R7: =IF($W7="","",N(INDEX(发票统计!R$4:R$1003,$W7))) -> 0 | S7: =IF($W7="","",N(INDEX(发票统计!S$4:S$1003,$W7))) -> 0 | T7: =IF($W7="","",SUM(Q$4:Q7)-SUM(R$4:R7)-SUM(S$4:S7)) -> 0 | U7: =IF($W7="","",INDEX(发票统计!U$4:U$1003,$W7)&"") | W7: =IF($V$3="","",IFERROR(MATCH($V$3&"#"&ROWS(W$4:W7),发票统计!$W$4:$W$1003,0),"")) -> 82
A8: =IF($W8="","",INDEX(发票统计!A$4:A$1003,$W8)&"") -> 蒲吕片区A段 | B8: =IF($W8="","",INDEX(发票统计!B$4:B$1003,$W8)&"") -> 9月 | C8: =IF($W8="","",INDEX(发票统计!C$4:C$1003,$W8)&"") -> 铜梁区园区屋顶分布式光伏发电建设项目-蒲吕片区A段10千伏电力新建工程 | D8: =IF($W8="","",INDEX(发票统计!D$4:D$1003,$W8)&"") -> 2026.9.1扣残保金20W*1.5% | E8: =IF($W8="","",INDEX(发票统计!E$4:E$1003,$W8)&"") -> 民能 | F8: =IF($W8="","",INDEX(发票统计!F$4:F$1003,$W8)&"") -> 9%专票 | G8: =IF($W8="","",IF(INDEX(发票统计!G$4:G$1003,$W8)="","",INDEX(发票统计!G$4:G$1003,$W8))) -> 0.15 | H8: =IF($W8="","",N(INDEX(发票统计!H$4:H$1003,$W8))) -> 0 | I8: =IF($W8="","",N(INDEX(发票统计!I$4:I$1003,$W8))) -> 0 | J8: =IF($W8="","",N(INDEX(发票统计!J$4:J$1003,$W8))) -> 0 | K8: =IF($W8="","",N(INDEX(发票统计!K$4:K$1003,$W8))) -> 3000 | L8: =IF($W8="","",SUM(J$4:J8)-SUM(K$4:K8)) -> -65976.8 | M8: =IF($W8="","",N(INDEX(发票统计!M$4:M$1003,$W8))) -> 0 | N8: =IF($W8="","",N(INDEX(发票统计!N$4:N$1003,$W8))) -> 0 | O8: =IF($W8="","",N(INDEX(发票统计!O$4:O$1003,$W8))) -> 3000 | P8: =IF($W8="","",SUM(M$4:M8)-SUM(N$4:N8)-SUM(O$4:O8)) -> -65976.8 | Q8: =IF($W8="","",N(INDEX(发票统计!Q$4:Q$1003,$W8))) -> 0 | R8: =IF($W8="","",N(INDEX(发票统计!R$4:R$1003,$W8))) -> 0 | S8: =IF($W8="","",N(INDEX(发票统计!S$4:S$1003,$W8))) -> 0 | T8: =IF($W8="","",SUM(Q$4:Q8)-SUM(R$4:R8)-SUM(S$4:S8)) -> 0 | U8: =IF($W8="","",INDEX(发票统计!U$4:U$1003,$W8)&"") | W8: =IF($V$3="","",IFERROR(MATCH($V$3&"#"&ROWS(W$4:W8),发票统计!$W$4:$W$1003,0),"")) -> 83
A9: =IF($W9="","",INDEX(发票统计!A$4:A$1003,$W9)&"") -> 蒲吕片区A段 | B9: =IF($W9="","",INDEX(发票统计!B$4:B$1003,$W9)&"") -> 9月 | C9: =IF($W9="","",INDEX(发票统计!C$4:C$1003,$W9)&"") -> 铜梁区园区屋顶分布式光伏发电建设项目-蒲吕片区A段10千伏电力新建工程 | D9: =IF($W9="","",INDEX(发票统计!D$4:D$1003,$W9)&"") -> 2026.9.1扣个税 | E9: =IF($W9="","",INDEX(发票统计!E$4:E$1003,$W9)&"") -> 民能 | F9: =IF($W9="","",INDEX(发票统计!F$4:F$1003,$W9)&"") -> 9%专票 | G9: =IF($W9="","",IF(INDEX(发票统计!G$4:G$1003,$W9)="","",INDEX(发票统计!G$4:G$1003,$W9))) -> 0.15 | H9: =IF($W9="","",N(INDEX(发票统计!H$4:H$1003,$W9))) -> 0 | I9: =IF($W9="","",N(INDEX(发票统计!I$4:I$1003,$W9))) -> 0 | J9: =IF($W9="","",N(INDEX(发票统计!J$4:J$1003,$W9))) -> 0 | K9: =IF($W9="","",N(INDEX(发票统计!K$4:K$1003,$W9))) -> 4950 | L9: =IF($W9="","",SUM(J$4:J9)-SUM(K$4:K9)) -> -70926.8 | M9: =IF($W9="","",N(INDEX(发票统计!M$4:M$1003,$W9))) -> 0 | N9: =IF($W9="","",N(INDEX(发票统计!N$4:N$1003,$W9))) -> 0 | O9: =IF($W9="","",N(INDEX(发票统计!O$4:O$1003,$W9))) -> 4950 | P9: =IF($W9="","",SUM(M$4:M9)-SUM(N$4:N9)-SUM(O$4:O9)) -> -70926.8 | Q9: =IF($W9="","",N(INDEX(发票统计!Q$4:Q$1003,$W9))) -> 0 | R9: =IF($W9="","",N(INDEX(发票统计!R$4:R$1003,$W9))) -> 0 | S9: =IF($W9="","",N(INDEX(发票统计!S$4:S$1003,$W9))) -> 0 | T9: =IF($W9="","",SUM(Q$4:Q9)-SUM(R$4:R9)-SUM(S$4:S9)) -> 0 | U9: =IF($W9="","",INDEX(发票统计!U$4:U$1003,$W9)&"") | W9: =IF($V$3="","",IFERROR(MATCH($V$3&"#"&ROWS(W$4:W9),发票统计!$W$4:$W$1003,0),"")) -> 84
A10: =IF($W10="","",INDEX(发票统计!A$4:A$1003,$W10)&"") -> 蒲吕片区A段 | B10: =IF($W10="","",INDEX(发票统计!B$4:B$1003,$W10)&"") -> 9月 | C10: =IF($W10="","",INDEX(发票统计!C$4:C$1003,$W10)&"") -> 铜梁区园区屋顶分布式光伏发电建设项目-蒲吕片区A段10千伏电力新建工程 | D10: =IF($W10="","",INDEX(发票统计!D$4:D$1003,$W10)&"") -> 2026.9.1质保金354295.65*3% | E10: =IF($W10="","",INDEX(发票统计!E$4:E$1003,$W10)&"") -> 民能 | F10: =IF($W10="","",INDEX(发票统计!F$4:F$1003,$W10)&"") -> 9%专票 | G10: =IF($W10="","",IF(INDEX(发票统计!G$4:G$1003,$W10)="","",INDEX(发票统计!G$4:G$1003,$W10))) -> 0.15 | H10: =IF($W10="","",N(INDEX(发票统计!H$4:H$1003,$W10))) -> 0 | I10: =IF($W10="","",N(INDEX(发票统计!I$4:I$1003,$W10))) -> 0 | J10: =IF($W10="","",N(INDEX(发票统计!J$4:J$1003,$W10))) -> 0 | K10: =IF($W10="","",N(INDEX(发票统计!K$4:K$1003,$W10))) -> 10628.87 | L10: =IF($W10="","",SUM(J$4:J10)-SUM(K$4:K10)) -> -81555.67 | M10: =IF($W10="","",N(INDEX(发票统计!M$4:M$1003,$W10))) -> 0 | N10: =IF($W10="","",N(INDEX(发票统计!N$4:N$1003,$W10))) -> 0 | O10: =IF($W10="","",N(INDEX(发票统计!O$4:O$1003,$W10))) -> 10628.87 | P10: =IF($W10="","",SUM(M$4:M10)-SUM(N$4:N10)-SUM(O$4:O10)) -> -81555.67 | Q10: =IF($W10="","",N(INDEX(发票统计!Q$4:Q$1003,$W10))) -> 0 | R10: =IF($W10="","",N(INDEX(发票统计!R$4:R$1003,$W10))) -> 0 | S10: =IF($W10="","",N(INDEX(发票统计!S$4:S$1003,$W10))) -> 0 | T10: =IF($W10="","",SUM(Q$4:Q10)-SUM(R$4:R10)-SUM(S$4:S10)) -> 0 | U10: =IF($W10="","",INDEX(发票统计!U$4:U$1003,$W10)&"") | W10: =IF($V$3="","",IFERROR(MATCH($V$3&"#"&ROWS(W$4:W10),发票统计!$W$4:$W$1003,0),"")) -> 85
A11: =IF($W11="","",INDEX(发票统计!A$4:A$1003,$W11)&"") -> 蒲吕片区A段 | B11: =IF($W11="","",INDEX(发票统计!B$4:B$1003,$W11)&"") -> 9月 | C11: =IF($W11="","",INDEX(发票统计!C$4:C$1003,$W11)&"") -> 铜梁区园区屋顶分布式光伏发电建设项目-蒲吕片区A段10千伏电力新建工程 | D11: =IF($W11="","",INDEX(发票统计!D$4:D$1003,$W11)&"") -> 2026.9.4新德润开9%专票到民能：蒲吕片区A段10千伏电力新建 | E11: =IF($W11="","",INDEX(发票统计!E$4:E$1003,$W11)&"") -> 民能 | F11: =IF($W11="","",INDEX(发票统计!F$4:F$1003,$W11)&"") -> 9%专票 | G11: =IF($W11="","",IF(INDEX(发票统计!G$4:G$1003,$W11)="","",INDEX(发票统计!G$4:G$1003,$W11))) -> 0.15 | H11: =IF($W11="","",N(INDEX(发票统计!H$4:H$1003,$W11))) -> 154295.65 | I11: =IF($W11="","",N(INDEX(发票统计!I$4:I$1003,$W11))) -> 23144.347 | J11: =IF($W11="","",N(INDEX(发票统计!J$4:J$1003,$W11))) -> 131151.3 | K11: =IF($W11="","",N(INDEX(发票统计!K$4:K$1003,$W11))) -> 49595.632 | L11: =IF($W11="","",SUM(J$4:J11)-SUM(K$4:K11)) -> 0 | M11: =IF($W11="","",N(INDEX(发票统计!M$4:M$1003,$W11))) -> 154295.65 | N11: =IF($W11="","",N(INDEX(发票统计!N$4:N$1003,$W11))) -> 0 | O11: =IF($W11="","",N(INDEX(发票统计!O$4:O$1003,$W11))) -> 23144.347 | P11: =IF($W11="","",SUM(M$4:M11)-SUM(N$4:N11)-SUM(O$4:O11)) -> 49595.633 | Q11: =IF($W11="","",N(INDEX(发票统计!Q$4:Q$1003,$W11))) -> 0 | R11: =IF($W11="","",N(INDEX(发票统计!R$4:R$1003,$W11))) -> 0 | S11: =IF($W11="","",N(INDEX(发票统计!S$4:S$1003,$W11))) -> 0 | T11: =IF($W11="","",SUM(Q$4:Q11)-SUM(R$4:R11)-SUM(S$4:S11)) -> 0 | U11: =IF($W11="","",INDEX(发票统计!U$4:U$1003,$W11)&"") | W11: =IF($V$3="","",IFERROR(MATCH($V$3&"#"&ROWS(W$4:W11),发票统计!$W$4:$W$1003,0),"")) -> 86
A12: =IF($W12="","",INDEX(发票统计!A$4:A$1003,$W12)&"") | B12: =IF($W12="","",INDEX(发票统计!B$4:B$1003,$W12)&"") | C12: =IF($W12="","",INDEX(发票统计!C$4:C$1003,$W12)&"") | D12: =IF($W12="","",INDEX(发票统计!D$4:D$1003,$W12)&"") | E12: =IF($W12="","",INDEX(发票统计!E$4:E$1003,$W12)&"") | F12: =IF($W12="","",INDEX(发票统计!F$4:F$1003,$W12)&"") | G12: =IF($W12="","",IF(INDEX(发票统计!G$4:G$1003,$W12)="","",INDEX(发票统计!G$4:G$1003,$W12))) | H12: =IF($W12="","",N(INDEX(发票统计!H$4:H$1003,$W12))) | I12: =IF($W12="","",N(INDEX(发票统计!I$4:I$1003,$W12))) | J12: =IF($W12="","",N(INDEX(发票统计!J$4:J$1003,$W12))) | K12: =IF($W12="","",N(INDEX(发票统计!K$4:K$1003,$W12))) | L12: =IF($W12="","",SUM(J$4:J12)-SUM(K$4:K12)) | M12: =IF($W12="","",N(INDEX(发票统计!M$4:M$1003,$W12))) | N12: =IF($W12="","",N(INDEX(发票统计!N$4:N$1003,$W12))) | O12: =IF($W12="","",N(INDEX(发票统计!O$4:O$1003,$W12))) | P12: =IF($W12="","",SUM(M$4:M12)-SUM(N$4:N12)-SUM(O$4:O12)) | Q12: =IF($W12="","",N(INDEX(发票统计!Q$4:Q$1003,$W12))) | R12: =IF($W12="","",N(INDEX(发票统计!R$4:R$1003,$W12))) | S12: =IF($W12="","",N(INDEX(发票统计!S$4:S$1003,$W12))) | T12: =IF($W12="","",SUM(Q$4:Q12)-SUM(R$4:R12)-SUM(S$4:S12)) | U12: =IF($W12="","",INDEX(发票统计!U$4:U$1003,$W12)&"") | W12: =IF($V$3="","",IFERROR(MATCH($V$3&"#"&ROWS(W$4:W12),发票统计!$W$4:$W$1003,0),""))
A13: =IF($W13="","",INDEX(发票统计!A$4:A$1003,$W13)&"") | B13: =IF($W13="","",INDEX(发票统计!B$4:B$1003,$W13)&"") | C13: =IF($W13="","",INDEX(发票统计!C$4:C$1003,$W13)&"") | D13: =IF($W13="","",INDEX(发票统计!D$4:D$1003,$W13)&"") | E13: =IF($W13="","",INDEX(发票统计!E$4:E$1003,$W13)&"") | F13: =IF($W13="","",INDEX(发票统计!F$4:F$1003,$W13)&"") | G13: =IF($W13="","",IF(INDEX(发票统计!G$4:G$1003,$W13)="","",INDEX(发票统计!G$4:G$1003,$W13))) | H13: =IF($W13="","",N(INDEX(发票统计!H$4:H$1003,$W13))) | I13: =IF($W13="","",N(INDEX(发票统计!I$4:I$1003,$W13))) | J13: =IF($W13="","",N(INDEX(发票统计!J$4:J$1003,$W13))) | K13: =IF($W13="","",N(INDEX(发票统计!K$4:K$1003,$W13))) | L13: =IF($W13="","",SUM(J$4:J13)-SUM(K$4:K13)) | M13: =IF($W13="","",N(INDEX(发票统计!M$4:M$1003,$W13))) | N13: =IF($W13="","",N(INDEX(发票统计!N$4:N$1003,$W13))) | O13: =IF($W13="","",N(INDEX(发票统计!O$4:O$1003,$W13))) | P13: =IF($W13="","",SUM(M$4:M13)-SUM(N$4:N13)-SUM(O$4:O13)) | Q13: =IF($W13="","",N(INDEX(发票统计!Q$4:Q$1003,$W13))) | R13: =IF($W13="","",N(INDEX(发票统计!R$4:R$1003,$W13))) | S13: =IF($W13="","",N(INDEX(发票统计!S$4:S$1003,$W13))) | T13: =IF($W13="","",SUM(Q$4:Q13)-SUM(R$4:R13)-SUM(S$4:S13)) | U13: =IF($W13="","",INDEX(发票统计!U$4:U$1003,$W13)&"") | W13: =IF($V$3="","",IFERROR(MATCH($V$3&"#"&ROWS(W$4:W13),发票统计!$W$4:$W$1003,0),""))
A14: =IF($W14="","",INDEX(发票统计!A$4:A$1003,$W14)&"") | B14: =IF($W14="","",INDEX(发票统计!B$4:B$1003,$W14)&"") | C14: =IF($W14="","",INDEX(发票统计!C$4:C$1003,$W14)&"") | D14: =IF($W14="","",INDEX(发票统计!D$4:D$1003,$W14)&"") | E14: =IF($W14="","",INDEX(发票统计!E$4:E$1003,$W14)&"") | F14: =IF($W14="","",INDEX(发票统计!F$4:F$1003,$W14)&"") | G14: =IF($W14="","",IF(INDEX(发票统计!G$4:G$1003,$W14)="","",INDEX(发票统计!G$4:G$1003,$W14))) | H14: =IF($W14="","",N(INDEX(发票统计!H$4:H$1003,$W14))) | I14: =IF($W14="","",N(INDEX(发票统计!I$4:I$1003,$W14))) | J14: =IF($W14="","",N(INDEX(发票统计!J$4:J$1003,$W14))) | K14: =IF($W14="","",N(INDEX(发票统计!K$4:K$1003,$W14))) | L14: =IF($W14="","",SUM(J$4:J14)-SUM(K$4:K14)) | M14: =IF($W14="","",N(INDEX(发票统计!M$4:M$1003,$W14))) | N14: =IF($W14="","",N(INDEX(发票统计!N$4:N$1003,$W14))) | O14: =IF($W14="","",N(INDEX(发票统计!O$4:O$1003,$W14))) | P14: =IF($W14="","",SUM(M$4:M14)-SUM(N$4:N14)-SUM(O$4:O14)) | Q14: =IF($W14="","",N(INDEX(发票统计!Q$4:Q$1003,$W14))) | R14: =IF($W14="","",N(INDEX(发票统计!R$4:R$1003,$W14))) | S14: =IF($W14="","",N(INDEX(发票统计!S$4:S$1003,$W14))) | T14: =IF($W14="","",SUM(Q$4:Q14)-SUM(R$4:R14)-SUM(S$4:S14)) | U14: =IF($W14="","",INDEX(发票统计!U$4:U$1003,$W14)&"") | W14: =IF($V$3="","",IFERROR(MATCH($V$3&"#"&ROWS(W$4:W14),发票统计!$W$4:$W$1003,0),""))
A15: =IF($W15="","",INDEX(发票统计!A$4:A$1003,$W15)&"") | B15: =IF($W15="","",INDEX(发票统计!B$4:B$1003,$W15)&"") | C15: =IF($W15="","",INDEX(发票统计!C$4:C$1003,$W15)&"") | D15: =IF($W15="","",INDEX(发票统计!D$4:D$1003,$W15)&"") | E15: =IF($W15="","",INDEX(发票统计!E$4:E$1003,$W15)&"") | F15: =IF($W15="","",INDEX(发票统计!F$4:F$1003,$W15)&"") | G15: =IF($W15="","",IF(INDEX(发票统计!G$4:G$1003,$W15)="","",INDEX(发票统计!G$4:G$1003,$W15))) | H15: =IF($W15="","",N(INDEX(发票统计!H$4:H$1003,$W15))) | I15: =IF($W15="","",N(INDEX(发票统计!I$4:I$1003,$W15))) | J15: =IF($W15="","",N(INDEX(发票统计!J$4:J$1003,$W15))) | K15: =IF($W15="","",N(INDEX(发票统计!K$4:K$1003,$W15))) | L15: =IF($W15="","",SUM(J$4:J15)-SUM(K$4:K15)) | M15: =IF($W15="","",N(INDEX(发票统计!M$4:M$1003,$W15))) | N15: =IF($W15="","",N(INDEX(发票统计!N$4:N$1003,$W15))) | O15: =IF($W15="","",N(INDEX(发票统计!O$4:O$1003,$W15))) | P15: =IF($W15="","",SUM(M$4:M15)-SUM(N$4:N15)-SUM(O$4:O15)) | Q15: =IF($W15="","",N(INDEX(发票统计!Q$4:Q$1003,$W15))) | R15: =IF($W15="","",N(INDEX(发票统计!R$4:R$1003,$W15))) | S15: =IF($W15="","",N(INDEX(发票统计!S$4:S$1003,$W15))) | T15: =IF($W15="","",SUM(Q$4:Q15)-SUM(R$4:R15)-SUM(S$4:S15)) | U15: =IF($W15="","",INDEX(发票统计!U$4:U$1003,$W15)&"") | W15: =IF($V$3="","",IFERROR(MATCH($V$3&"#"&ROWS(W$4:W15),发票统计!$W$4:$W$1003,0),""))
A16: =IF($W16="","",INDEX(发票统计!A$4:A$1003,$W16)&"") | B16: =IF($W16="","",INDEX(发票统计!B$4:B$1003,$W16)&"") | C16: =IF($W16="","",INDEX(发票统计!C$4:C$1003,$W16)&"") | D16: =IF($W16="","",INDEX(发票统计!D$4:D$1003,$W16)&"") | E16: =IF($W16="","",INDEX(发票统计!E$4:E$1003,$W16)&"") | F16: =IF($W16="","",INDEX(发票统计!F$4:F$1003,$W16)&"") | G16: =IF($W16="","",IF(INDEX(发票统计!G$4:G$1003,$W16)="","",INDEX(发票统计!G$4:G$1003,$W16))) | H16: =IF($W16="","",N(INDEX(发票统计!H$4:H$1003,$W16))) | I16: =IF($W16="","",N(INDEX(发票统计!I$4:I$1003,$W16))) | J16: =IF($W16="","",N(INDEX(发票统计!J$4:J$1003,$W16))) | K16: =IF($W16="","",N(INDEX(发票统计!K$4:K$1003,$W16))) | L16: =IF($W16="","",SUM(J$4:J16)-SUM(K$4:K16)) | M16: =IF($W16="","",N(INDEX(发票统计!M$4:M$1003,$W16))) | N16: =IF($W16="","",N(INDEX(发票统计!N$4:N$1003,$W16))) | O16: =IF($W16="","",N(INDEX(发票统计!O$4:O$1003,$W16))) | P16: =IF($W16="","",SUM(M$4:M16)-SUM(N$4:N16)-SUM(O$4:O16)) | Q16: =IF($W16="","",N(INDEX(发票统计!Q$4:Q$1003,$W16))) | R16: =IF($W16="","",N(INDEX(发票统计!R$4:R$1003,$W16))) | S16: =IF($W16="","",N(INDEX(发票统计!S$4:S$1003,$W16))) | T16: =IF($W16="","",SUM(Q$4:Q16)-SUM(R$4:R16)-SUM(S$4:S16)) | U16: =IF($W16="","",INDEX(发票统计!U$4:U$1003,$W16)&"") | W16: =IF($V$3="","",IFERROR(MATCH($V$3&"#"&ROWS(W$4:W16),发票统计!$W$4:$W$1003,0),""))
... A303: =IF($W303="","",INDEX(发票统计!A$4:A$1003,$W303)&"") | B303: =IF($W303="","",INDEX(发票统计!B$4:B$1003,$W303)&"") | C303: =IF($W303="","",INDEX(发票统计!C$4:C$1003,$W303)&"") | D303: =IF($W303="","",INDEX(发票统计!D$4:D$1003,$W303)&"") | E303: =IF($W303="","",INDEX(发票统计!E$4:E$1003,$W303)&"") | F303: =IF($W303="","",INDEX(发票统计!F$4:F$1003,$W303)&"") | G303: =IF($W303="","",IF(INDEX(发票统计!G$4:G$1003,$W303)="","",INDEX(发票统计!G$4:G$1003,$W303))) | H303: =IF($W303="","",N(INDEX(发票统计!H$4:H$1003,$W303))) | I303: =IF($W303="","",N(INDEX(发票统计!I$4:I$1003,$W303))) | J303: =IF($W303="","",N(INDEX(发票统计!J$4:J$1003,$W303))) | K303: =IF($W303="","",N(INDEX(发票统计!K$4:K$1003,$W303))) | L303: =IF($W303="","",SUM(J$4:J303)-SUM(K$4:K303)) | M303: =IF($W303="","",N(INDEX(发票统计!M$4:M$1003,$W303))) | N303: =IF($W303="","",N(INDEX(发票统计!N$4:N$1003,$W303))) | O303: =IF($W303="","",N(INDEX(发票统计!O$4:O$1003,$W303))) | P303: =IF($W303="","",SUM(M$4:M303)-SUM(N$4:N303)-SUM(O$4:O303)) | Q303: =IF($W303="","",N(INDEX(发票统计!Q$4:Q$1003,$W303))) | R303: =IF($W303="","",N(INDEX(发票统计!R$4:R$1003,$W303))) | S303: =IF($W303="","",N(INDEX(发票统计!S$4:S$1003,$W303))) | T303: =IF($W303="","",SUM(Q$4:Q303)-SUM(R$4:R303)-SUM(S$4:S303)) | U303: =IF($W303="","",INDEX(发票统计!U$4:U$1003,$W303)&"") | W303: =IF($V$3="","",IFERROR(MATCH($V$3&"#"&ROWS(W$4:W303),发票统计!$W$4:$W$1003,0),""))

Sheet 淮阳站阳高线
A1: 淮阳站阳高线
A2: 对账 单位 | B2: 月份 | C2: 项目 名称 | D2: 摘要 | E2: 收票 单位 | F2: 发票 性质 | G2: 管理 费点 | H2: 销售金额 | I2: 管理费 | J2: 应开 成本票 | K2: 已开 成本票 | L2: 未开 成本票 | M2: 应收款 | N2: 质保金 | O2: 已收款 | P2: 未收款 | Q2: 应付 工程款 | R2: 扣除 管理费 | S2: 已付 工程款 | T2: 未付 工程款 | U2: 备注 | V2: 本表项目简称 （自动取表名）
H3: =SUM(H4:H303) -> 107944.61 | I3: =SUM(I4:I303) -> 0 | J3: =SUM(J4:J303) -> 107944.61 | K3: =SUM(K4:K303) -> 107944.61 | L3: =J3-K3 -> 0 | M3: =SUM(M4:M303) -> 107944.61 | N3: =SUM(N4:N303) -> 0 | O3: =SUM(O4:O303) -> 0 | P3: =M3-N3-O3 -> 107944.61 | Q3: =SUM(Q4:Q303) -> 0 | R3: =SUM(R4:R303) -> 0 | S3: =SUM(S4:S303) -> 0 | T3: =Q3-R3-S3 -> 0 | V3: =IFERROR(MID(CELL("filename",$A$1),FIND("]",CELL("filename",$A$1))+1,99),IFERROR(SUBSTITUTE(MID(CELL("filename",$A$1),FIND("#$",CELL("filename",$A$1))+2,99),"'",""),"")) -> 淮阳站阳高线
A4: =IF($W4="","",INDEX(发票统计!A$4:A$1003,$W4)&"") -> 淮阳站阳高线 | B4: =IF($W4="","",INDEX(发票统计!B$4:B$1003,$W4)&"") -> 3月 | C4: =IF($W4="","",INDEX(发票统计!C$4:C$1003,$W4)&"") -> 重庆铜梁110kV淮阳站阳高线10kV配套送出工程（安装） | D4: =IF($W4="","",INDEX(发票统计!D$4:D$1003,$W4)&"") -> 2026.3.25新德润开票到民能：淮阳站阳高线 | E4: =IF($W4="","",INDEX(发票统计!E$4:E$1003,$W4)&"") -> 民能 | F4: =IF($W4="","",INDEX(发票统计!F$4:F$1003,$W4)&"") -> 3%专票 | G4: =IF($W4="","",IF(INDEX(发票统计!G$4:G$1003,$W4)="","",INDEX(发票统计!G$4:G$1003,$W4))) | H4: =IF($W4="","",N(INDEX(发票统计!H$4:H$1003,$W4))) -> 57824 | I4: =IF($W4="","",N(INDEX(发票统计!I$4:I$1003,$W4))) -> 0 | J4: =IF($W4="","",N(INDEX(发票统计!J$4:J$1003,$W4))) -> 57824 | K4: =IF($W4="","",N(INDEX(发票统计!K$4:K$1003,$W4))) -> 57824 | L4: =IF($W4="","",SUM(J$4:J4)-SUM(K$4:K4)) -> 0 | M4: =IF($W4="","",N(INDEX(发票统计!M$4:M$1003,$W4))) -> 57824 | N4: =IF($W4="","",N(INDEX(发票统计!N$4:N$1003,$W4))) -> 0 | O4: =IF($W4="","",N(INDEX(发票统计!O$4:O$1003,$W4))) -> 0 | P4: =IF($W4="","",SUM(M$4:M4)-SUM(N$4:N4)-SUM(O$4:O4)) -> 57824 | Q4: =IF($W4="","",N(INDEX(发票统计!Q$4:Q$1003,$W4))) -> 0 | R4: =IF($W4="","",N(INDEX(发票统计!R$4:R$1003,$W4))) -> 0 | S4: =IF($W4="","",N(INDEX(发票统计!S$4:S$1003,$W4))) -> 0 | T4: =IF($W4="","",SUM(Q$4:Q4)-SUM(R$4:R4)-SUM(S$4:S4)) -> 0 | U4: =IF($W4="","",INDEX(发票统计!U$4:U$1003,$W4)&"") | V4: =IF($V$3="","⚠ 取不到表名，请在 V3 手填项目简称",IF(COUNTIF(发票统计!$A$4:$A$1003,$V$3)=0,"⚠ 发票统计里没有「"&$V$3&"」的行，表名要和目录里的简称一样",IF(COUNTIF(发票统计!$A$4:$A$1003,$V$3)>300,"⚠ 本项目超过 300 行，后面的没显示","共 "&COUNTIF(发票统计!$A$4:$A$1003,$V$3)&" 笔"))) -> 共 2 笔 | W4: =IF($V$3="","",IFERROR(MATCH($V$3&"#"&ROWS(W$4:W4),发票统计!$W$4:$W$1003,0),"")) -> 1
A5: =IF($W5="","",INDEX(发票统计!A$4:A$1003,$W5)&"") -> 淮阳站阳高线 | B5: =IF($W5="","",INDEX(发票统计!B$4:B$1003,$W5)&"") -> 3月 | C5: =IF($W5="","",INDEX(发票统计!C$4:C$1003,$W5)&"") -> 重庆铜梁110kV淮阳站阳高线10kV配套送出工程（安装） | D5: =IF($W5="","",INDEX(发票统计!D$4:D$1003,$W5)&"") -> 2026.3.25张氏机电-新德润：淮阳站阳高线 | E5: =IF($W5="","",INDEX(发票统计!E$4:E$1003,$W5)&"") -> 新德润 | F5: =IF($W5="","",INDEX(发票统计!F$4:F$1003,$W5)&"") | G5: =IF($W5="","",IF(INDEX(发票统计!G$4:G$1003,$W5)="","",INDEX(发票统计!G$4:G$1003,$W5))) | H5: =IF($W5="","",N(INDEX(发票统计!H$4:H$1003,$W5))) -> 50120.61 | I5: =IF($W5="","",N(INDEX(发票统计!I$4:I$1003,$W5))) -> 0 | J5: =IF($W5="","",N(INDEX(发票统计!J$4:J$1003,$W5))) -> 50120.61 | K5: =IF($W5="","",N(INDEX(发票统计!K$4:K$1003,$W5))) -> 50120.61 | L5: =IF($W5="","",SUM(J$4:J5)-SUM(K$4:K5)) -> 0 | M5: =IF($W5="","",N(INDEX(发票统计!M$4:M$1003,$W5))) -> 50120.61 | N5: =IF($W5="","",N(INDEX(发票统计!N$4:N$1003,$W5))) -> 0 | O5: =IF($W5="","",N(INDEX(发票统计!O$4:O$1003,$W5))) -> 0 | P5: =IF($W5="","",SUM(M$4:M5)-SUM(N$4:N5)-SUM(O$4:O5)) -> 107944.61 | Q5: =IF($W5="","",N(INDEX(发票统计!Q$4:Q$1003,$W5))) -> 0 | R5: =IF($W5="","",N(INDEX(发票统计!R$4:R$1003,$W5))) -> 0 | S5: =IF($W5="","",N(INDEX(发票统计!S$4:S$1003,$W5))) -> 0 | T5: =IF($W5="","",SUM(Q$4:Q5)-SUM(R$4:R5)-SUM(S$4:S5)) -> 0 | U5: =IF($W5="","",INDEX(发票统计!U$4:U$1003,$W5)&"") | W5: =IF($V$3="","",IFERROR(MATCH($V$3&"#"&ROWS(W$4:W5),发票统计!$W$4:$W$1003,0),"")) -> 2
A6: =IF($W6="","",INDEX(发票统计!A$4:A$1003,$W6)&"") | B6: =IF($W6="","",INDEX(发票统计!B$4:B$1003,$W6)&"") | C6: =IF($W6="","",INDEX(发票统计!C$4:C$1003,$W6)&"") | D6: =IF($W6="","",INDEX(发票统计!D$4:D$1003,$W6)&"") | E6: =IF($W6="","",INDEX(发票统计!E$4:E$1003,$W6)&"") | F6: =IF($W6="","",INDEX(发票统计!F$4:F$1003,$W6)&"") | G6: =IF($W6="","",IF(INDEX(发票统计!G$4:G$1003,$W6)="","",INDEX(发票统计!G$4:G$1003,$W6))) | H6: =IF($W6="","",N(INDEX(发票统计!H$4:H$1003,$W6))) | I6: =IF($W6="","",N(INDEX(发票统计!I$4:I$1003,$W6))) | J6: =IF($W6="","",N(INDEX(发票统计!J$4:J$1003,$W6))) | K6: =IF($W6="","",N(INDEX(发票统计!K$4:K$1003,$W6))) | L6: =IF($W6="","",SUM(J$4:J6)-SUM(K$4:K6)) | M6: =IF($W6="","",N(INDEX(发票统计!M$4:M$1003,$W6))) | N6: =IF($W6="","",N(INDEX(发票统计!N$4:N$1003,$W6))) | O6: =IF($W6="","",N(INDEX(发票统计!O$4:O$1003,$W6))) | P6: =IF($W6="","",SUM(M$4:M6)-SUM(N$4:N6)-SUM(O$4:O6)) | Q6: =IF($W6="","",N(INDEX(发票统计!Q$4:Q$1003,$W6))) | R6: =IF($W6="","",N(INDEX(发票统计!R$4:R$1003,$W6))) | S6: =IF($W6="","",N(INDEX(发票统计!S$4:S$1003,$W6))) | T6: =IF($W6="","",SUM(Q$4:Q6)-SUM(R$4:R6)-SUM(S$4:S6)) | U6: =IF($W6="","",INDEX(发票统计!U$4:U$1003,$W6)&"") | W6: =IF($V$3="","",IFERROR(MATCH($V$3&"#"&ROWS(W$4:W6),发票统计!$W$4:$W$1003,0),""))
A7: =IF($W7="","",INDEX(发票统计!A$4:A$1003,$W7)&"") | B7: =IF($W7="","",INDEX(发票统计!B$4:B$1003,$W7)&"") | C7: =IF($W7="","",INDEX(发票统计!C$4:C$1003,$W7)&"") | D7: =IF($W7="","",INDEX(发票统计!D$4:D$1003,$W7)&"") | E7: =IF($W7="","",INDEX(发票统计!E$4:E$1003,$W7)&"") | F7: =IF($W7="","",INDEX(发票统计!F$4:F$1003,$W7)&"") | G7: =IF($W7="","",IF(INDEX(发票统计!G$4:G$1003,$W7)="","",INDEX(发票统计!G$4:G$1003,$W7))) | H7: =IF($W7="","",N(INDEX(发票统计!H$4:H$1003,$W7))) | I7: =IF($W7="","",N(INDEX(发票统计!I$4:I$1003,$W7))) | J7: =IF($W7="","",N(INDEX(发票统计!J$4:J$1003,$W7))) | K7: =IF($W7="","",N(INDEX(发票统计!K$4:K$1003,$W7))) | L7: =IF($W7="","",SUM(J$4:J7)-SUM(K$4:K7)) | M7: =IF($W7="","",N(INDEX(发票统计!M$4:M$1003,$W7))) | N7: =IF($W7="","",N(INDEX(发票统计!N$4:N$1003,$W7))) | O7: =IF($W7="","",N(INDEX(发票统计!O$4:O$1003,$W7))) | P7: =IF($W7="","",SUM(M$4:M7)-SUM(N$4:N7)-SUM(O$4:O7)) | Q7: =IF($W7="","",N(INDEX(发票统计!Q$4:Q$1003,$W7))) | R7: =IF($W7="","",N(INDEX(发票统计!R$4:R$1003,$W7))) | S7: =IF($W7="","",N(INDEX(发票统计!S$4:S$1003,$W7))) | T7: =IF($W7="","",SUM(Q$4:Q7)-SUM(R$4:R7)-SUM(S$4:S7)) | U7: =IF($W7="","",INDEX(发票统计!U$4:U$1003,$W7)&"") | W7: =IF($V$3="","",IFERROR(MATCH($V$3&"#"&ROWS(W$4:W7),发票统计!$W$4:$W$1003,0),""))
A8: =IF($W8="","",INDEX(发票统计!A$4:A$1003,$W8)&"") | B8: =IF($W8="","",INDEX(发票统计!B$4:B$1003,$W8)&"") | C8: =IF($W8="","",INDEX(发票统计!C$4:C$1003,$W8)&"") | D8: =IF($W8="","",INDEX(发票统计!D$4:D$1003,$W8)&"") | E8: =IF($W8="","",INDEX(发票统计!E$4:E$1003,$W8)&"") | F8: =IF($W8="","",INDEX(发票统计!F$4:F$1003,$W8)&"") | G8: =IF($W8="","",IF(INDEX(发票统计!G$4:G$1003,$W8)="","",INDEX(发票统计!G$4:G$1003,$W8))) | H8: =IF($W8="","",N(INDEX(发票统计!H$4:H$1003,$W8))) | I8: =IF($W8="","",N(INDEX(发票统计!I$4:I$1003,$W8))) | J8: =IF($W8="","",N(INDEX(发票统计!J$4:J$1003,$W8))) | K8: =IF($W8="","",N(INDEX(发票统计!K$4:K$1003,$W8))) | L8: =IF($W8="","",SUM(J$4:J8)-SUM(K$4:K8)) | M8: =IF($W8="","",N(INDEX(发票统计!M$4:M$1003,$W8))) | N8: =IF($W8="","",N(INDEX(发票统计!N$4:N$1003,$W8))) | O8: =IF($W8="","",N(INDEX(发票统计!O$4:O$1003,$W8))) | P8: =IF($W8="","",SUM(M$4:M8)-SUM(N$4:N8)-SUM(O$4:O8)) | Q8: =IF($W8="","",N(INDEX(发票统计!Q$4:Q$1003,$W8))) | R8: =IF($W8="","",N(INDEX(发票统计!R$4:R$1003,$W8))) | S8: =IF($W8="","",N(INDEX(发票统计!S$4:S$1003,$W8))) | T8: =IF($W8="","",SUM(Q$4:Q8)-SUM(R$4:R8)-SUM(S$4:S8)) | U8: =IF($W8="","",INDEX(发票统计!U$4:U$1003,$W8)&"") | W8: =IF($V$3="","",IFERROR(MATCH($V$3&"#"&ROWS(W$4:W8),发票统计!$W$4:$W$1003,0),""))
A9: =IF($W9="","",INDEX(发票统计!A$4:A$1003,$W9)&"") | B9: =IF($W9="","",INDEX(发票统计!B$4:B$1003,$W9)&"") | C9: =IF($W9="","",INDEX(发票统计!C$4:C$1003,$W9)&"") | D9: =IF($W9="","",INDEX(发票统计!D$4:D$1003,$W9)&"") | E9: =IF($W9="","",INDEX(发票统计!E$4:E$1003,$W9)&"") | F9: =IF($W9="","",INDEX(发票统计!F$4:F$1003,$W9)&"") | G9: =IF($W9="","",IF(INDEX(发票统计!G$4:G$1003,$W9)="","",INDEX(发票统计!G$4:G$1003,$W9))) | H9: =IF($W9="","",N(INDEX(发票统计!H$4:H$1003,$W9))) | I9: =IF($W9="","",N(INDEX(发票统计!I$4:I$1003,$W9))) | J9: =IF($W9="","",N(INDEX(发票统计!J$4:J$1003,$W9))) | K9: =IF($W9="","",N(INDEX(发票统计!K$4:K$1003,$W9))) | L9: =IF($W9="","",SUM(J$4:J9)-SUM(K$4:K9)) | M9: =IF($W9="","",N(INDEX(发票统计!M$4:M$1003,$W9))) | N9: =IF($W9="","",N(INDEX(发票统计!N$4:N$1003,$W9))) | O9: =IF($W9="","",N(INDEX(发票统计!O$4:O$1003,$W9))) | P9: =IF($W9="","",SUM(M$4:M9)-SUM(N$4:N9)-SUM(O$4:O9)) | Q9: =IF($W9="","",N(INDEX(发票统计!Q$4:Q$1003,$W9))) | R9: =IF($W9="","",N(INDEX(发票统计!R$4:R$1003,$W9))) | S9: =IF($W9="","",N(INDEX(发票统计!S$4:S$1003,$W9))) | T9: =IF($W9="","",SUM(Q$4:Q9)-SUM(R$4:R9)-SUM(S$4:S9)) | U9: =IF($W9="","",INDEX(发票统计!U$4:U$1003,$W9)&"") | W9: =IF($V$3="","",IFERROR(MATCH($V$3&"#"&ROWS(W$4:W9),发票统计!$W$4:$W$1003,0),""))
A10: =IF($W10="","",INDEX(发票统计!A$4:A$1003,$W10)&"") | B10: =IF($W10="","",INDEX(发票统计!B$4:B$1003,$W10)&"") | C10: =IF($W10="","",INDEX(发票统计!C$4:C$1003,$W10)&"") | D10: =IF($W10="","",INDEX(发票统计!D$4:D$1003,$W10)&"") | E10: =IF($W10="","",INDEX(发票统计!E$4:E$1003,$W10)&"") | F10: =IF($W10="","",INDEX(发票统计!F$4:F$1003,$W10)&"") | G10: =IF($W10="","",IF(INDEX(发票统计!G$4:G$1003,$W10)="","",INDEX(发票统计!G$4:G$1003,$W10))) | H10: =IF($W10="","",N(INDEX(发票统计!H$4:H$1003,$W10))) | I10: =IF($W10="","",N(INDEX(发票统计!I$4:I$1003,$W10))) | J10: =IF($W10="","",N(INDEX(发票统计!J$4:J$1003,$W10))) | K10: =IF($W10="","",N(INDEX(发票统计!K$4:K$1003,$W10))) | L10: =IF($W10="","",SUM(J$4:J10)-SUM(K$4:K10)) | M10: =IF($W10="","",N(INDEX(发票统计!M$4:M$1003,$W10))) | N10: =IF($W10="","",N(INDEX(发票统计!N$4:N$1003,$W10))) | O10: =IF($W10="","",N(INDEX(发票统计!O$4:O$1003,$W10))) | P10: =IF($W10="","",SUM(M$4:M10)-SUM(N$4:N10)-SUM(O$4:O10)) | Q10: =IF($W10="","",N(INDEX(发票统计!Q$4:Q$1003,$W10))) | R10: =IF($W10="","",N(INDEX(发票统计!R$4:R$1003,$W10))) | S10: =IF($W10="","",N(INDEX(发票统计!S$4:S$1003,$W10))) | T10: =IF($W10="","",SUM(Q$4:Q10)-SUM(R$4:R10)-SUM(S$4:S10)) | U10: =IF($W10="","",INDEX(发票统计!U$4:U$1003,$W10)&"") | W10: =IF($V$3="","",IFERROR(MATCH($V$3&"#"&ROWS(W$4:W10),发票统计!$W$4:$W$1003,0),""))
A11: =IF($W11="","",INDEX(发票统计!A$4:A$1003,$W11)&"") | B11: =IF($W11="","",INDEX(发票统计!B$4:B$1003,$W11)&"") | C11: =IF($W11="","",INDEX(发票统计!C$4:C$1003,$W11)&"") | D11: =IF($W11="","",INDEX(发票统计!D$4:D$1003,$W11)&"") | E11: =IF($W11="","",INDEX(发票统计!E$4:E$1003,$W11)&"") | F11: =IF($W11="","",INDEX(发票统计!F$4:F$1003,$W11)&"") | G11: =IF($W11="","",IF(INDEX(发票统计!G$4:G$1003,$W11)="","",INDEX(发票统计!G$4:G$1003,$W11))) | H11: =IF($W11="","",N(INDEX(发票统计!H$4:H$1003,$W11))) | I11: =IF($W11="","",N(INDEX(发票统计!I$4:I$1003,$W11))) | J11: =IF($W11="","",N(INDEX(发票统计!J$4:J$1003,$W11))) | K11: =IF($W11="","",N(INDEX(发票统计!K$4:K$1003,$W11))) | L11: =IF($W11="","",SUM(J$4:J11)-SUM(K$4:K11)) | M11: =IF($W11="","",N(INDEX(发票统计!M$4:M$1003,$W11))) | N11: =IF($W11="","",N(INDEX(发票统计!N$4:N$1003,$W11))) | O11: =IF($W11="","",N(INDEX(发票统计!O$4:O$1003,$W11))) | P11: =IF($W11="","",SUM(M$4:M11)-SUM(N$4:N11)-SUM(O$4:O11)) | Q11: =IF($W11="","",N(INDEX(发票统计!Q$4:Q$1003,$W11))) | R11: =IF($W11="","",N(INDEX(发票统计!R$4:R$1003,$W11))) | S11: =IF($W11="","",N(INDEX(发票统计!S$4:S$1003,$W11))) | T11: =IF($W11="","",SUM(Q$4:Q11)-SUM(R$4:R11)-SUM(S$4:S11)) | U11: =IF($W11="","",INDEX(发票统计!U$4:U$1003,$W11)&"") | W11: =IF($V$3="","",IFERROR(MATCH($V$3&"#"&ROWS(W$4:W11),发票统计!$W$4:$W$1003,0),""))
A12: =IF($W12="","",INDEX(发票统计!A$4:A$1003,$W12)&"") | B12: =IF($W12="","",INDEX(发票统计!B$4:B$1003,$W12)&"") | C12: =IF($W12="","",INDEX(发票统计!C$4:C$1003,$W12)&"") | D12: =IF($W12="","",INDEX(发票统计!D$4:D$1003,$W12)&"") | E12: =IF($W12="","",INDEX(发票统计!E$4:E$1003,$W12)&"") | F12: =IF($W12="","",INDEX(发票统计!F$4:F$1003,$W12)&"") | G12: =IF($W12="","",IF(INDEX(发票统计!G$4:G$1003,$W12)="","",INDEX(发票统计!G$4:G$1003,$W12))) | H12: =IF($W12="","",N(INDEX(发票统计!H$4:H$1003,$W12))) | I12: =IF($W12="","",N(INDEX(发票统计!I$4:I$1003,$W12))) | J12: =IF($W12="","",N(INDEX(发票统计!J$4:J$1003,$W12))) | K12: =IF($W12="","",N(INDEX(发票统计!K$4:K$1003,$W12))) | L12: =IF($W12="","",SUM(J$4:J12)-SUM(K$4:K12)) | M12: =IF($W12="","",N(INDEX(发票统计!M$4:M$1003,$W12))) | N12: =IF($W12="","",N(INDEX(发票统计!N$4:N$1003,$W12))) | O12: =IF($W12="","",N(INDEX(发票统计!O$4:O$1003,$W12))) | P12: =IF($W12="","",SUM(M$4:M12)-SUM(N$4:N12)-SUM(O$4:O12)) | Q12: =IF($W12="","",N(INDEX(发票统计!Q$4:Q$1003,$W12))) | R12: =IF($W12="","",N(INDEX(发票统计!R$4:R$1003,$W12))) | S12: =IF($W12="","",N(INDEX(发票统计!S$4:S$1003,$W12))) | T12: =IF($W12="","",SUM(Q$4:Q12)-SUM(R$4:R12)-SUM(S$4:S12)) | U12: =IF($W12="","",INDEX(发票统计!U$4:U$1003,$W12)&"") | W12: =IF($V$3="","",IFERROR(MATCH($V$3&"#"&ROWS(W$4:W12),发票统计!$W$4:$W$1003,0),""))
A13: =IF($W13="","",INDEX(发票统计!A$4:A$1003,$W13)&"") | B13: =IF($W13="","",INDEX(发票统计!B$4:B$1003,$W13)&"") | C13: =IF($W13="","",INDEX(发票统计!C$4:C$1003,$W13)&"") | D13: =IF($W13="","",INDEX(发票统计!D$4:D$1003,$W13)&"") | E13: =IF($W13="","",INDEX(发票统计!E$4:E$1003,$W13)&"") | F13: =IF($W13="","",INDEX(发票统计!F$4:F$1003,$W13)&"") | G13: =IF($W13="","",IF(INDEX(发票统计!G$4:G$1003,$W13)="","",INDEX(发票统计!G$4:G$1003,$W13))) | H13: =IF($W13="","",N(INDEX(发票统计!H$4:H$1003,$W13))) | I13: =IF($W13="","",N(INDEX(发票统计!I$4:I$1003,$W13))) | J13: =IF($W13="","",N(INDEX(发票统计!J$4:J$1003,$W13))) | K13: =IF($W13="","",N(INDEX(发票统计!K$4:K$1003,$W13))) | L13: =IF($W13="","",SUM(J$4:J13)-SUM(K$4:K13)) | M13: =IF($W13="","",N(INDEX(发票统计!M$4:M$1003,$W13))) | N13: =IF($W13="","",N(INDEX(发票统计!N$4:N$1003,$W13))) | O13: =IF($W13="","",N(INDEX(发票统计!O$4:O$1003,$W13))) | P13: =IF($W13="","",SUM(M$4:M13)-SUM(N$4:N13)-SUM(O$4:O13)) | Q13: =IF($W13="","",N(INDEX(发票统计!Q$4:Q$1003,$W13))) | R13: =IF($W13="","",N(INDEX(发票统计!R$4:R$1003,$W13))) | S13: =IF($W13="","",N(INDEX(发票统计!S$4:S$1003,$W13))) | T13: =IF($W13="","",SUM(Q$4:Q13)-SUM(R$4:R13)-SUM(S$4:S13)) | U13: =IF($W13="","",INDEX(发票统计!U$4:U$1003,$W13)&"") | W13: =IF($V$3="","",IFERROR(MATCH($V$3&"#"&ROWS(W$4:W13),发票统计!$W$4:$W$1003,0),""))
A14: =IF($W14="","",INDEX(发票统计!A$4:A$1003,$W14)&"") | B14: =IF($W14="","",INDEX(发票统计!B$4:B$1003,$W14)&"") | C14: =IF($W14="","",INDEX(发票统计!C$4:C$1003,$W14)&"") | D14: =IF($W14="","",INDEX(发票统计!D$4:D$1003,$W14)&"") | E14: =IF($W14="","",INDEX(发票统计!E$4:E$1003,$W14)&"") | F14: =IF($W14="","",INDEX(发票统计!F$4:F$1003,$W14)&"") | G14: =IF($W14="","",IF(INDEX(发票统计!G$4:G$1003,$W14)="","",INDEX(发票统计!G$4:G$1003,$W14))) | H14: =IF($W14="","",N(INDEX(发票统计!H$4:H$1003,$W14))) | I14: =IF($W14="","",N(INDEX(发票统计!I$4:I$1003,$W14))) | J14: =IF($W14="","",N(INDEX(发票统计!J$4:J$1003,$W14))) | K14: =IF($W14="","",N(INDEX(发票统计!K$4:K$1003,$W14))) | L14: =IF($W14="","",SUM(J$4:J14)-SUM(K$4:K14)) | M14: =IF($W14="","",N(INDEX(发票统计!M$4:M$1003,$W14))) | N14: =IF($W14="","",N(INDEX(发票统计!N$4:N$1003,$W14))) | O14: =IF($W14="","",N(INDEX(发票统计!O$4:O$1003,$W14))) | P14: =IF($W14="","",SUM(M$4:M14)-SUM(N$4:N14)-SUM(O$4:O14)) | Q14: =IF($W14="","",N(INDEX(发票统计!Q$4:Q$1003,$W14))) | R14: =IF($W14="","",N(INDEX(发票统计!R$4:R$1003,$W14))) | S14: =IF($W14="","",N(INDEX(发票统计!S$4:S$1003,$W14))) | T14: =IF($W14="","",SUM(Q$4:Q14)-SUM(R$4:R14)-SUM(S$4:S14)) | U14: =IF($W14="","",INDEX(发票统计!U$4:U$1003,$W14)&"") | W14: =IF($V$3="","",IFERROR(MATCH($V$3&"#"&ROWS(W$4:W14),发票统计!$W$4:$W$1003,0),""))
A15: =IF($W15="","",INDEX(发票统计!A$4:A$1003,$W15)&"") | B15: =IF($W15="","",INDEX(发票统计!B$4:B$1003,$W15)&"") | C15: =IF($W15="","",INDEX(发票统计!C$4:C$1003,$W15)&"") | D15: =IF($W15="","",INDEX(发票统计!D$4:D$1003,$W15)&"") | E15: =IF($W15="","",INDEX(发票统计!E$4:E$1003,$W15)&"") | F15: =IF($W15="","",INDEX(发票统计!F$4:F$1003,$W15)&"") | G15: =IF($W15="","",IF(INDEX(发票统计!G$4:G$1003,$W15)="","",INDEX(发票统计!G$4:G$1003,$W15))) | H15: =IF($W15="","",N(INDEX(发票统计!H$4:H$1003,$W15))) | I15: =IF($W15="","",N(INDEX(发票统计!I$4:I$1003,$W15))) | J15: =IF($W15="","",N(INDEX(发票统计!J$4:J$1003,$W15))) | K15: =IF($W15="","",N(INDEX(发票统计!K$4:K$1003,$W15))) | L15: =IF($W15="","",SUM(J$4:J15)-SUM(K$4:K15)) | M15: =IF($W15="","",N(INDEX(发票统计!M$4:M$1003,$W15))) | N15: =IF($W15="","",N(INDEX(发票统计!N$4:N$1003,$W15))) | O15: =IF($W15="","",N(INDEX(发票统计!O$4:O$1003,$W15))) | P15: =IF($W15="","",SUM(M$4:M15)-SUM(N$4:N15)-SUM(O$4:O15)) | Q15: =IF($W15="","",N(INDEX(发票统计!Q$4:Q$1003,$W15))) | R15: =IF($W15="","",N(INDEX(发票统计!R$4:R$1003,$W15))) | S15: =IF($W15="","",N(INDEX(发票统计!S$4:S$1003,$W15))) | T15: =IF($W15="","",SUM(Q$4:Q15)-SUM(R$4:R15)-SUM(S$4:S15)) | U15: =IF($W15="","",INDEX(发票统计!U$4:U$1003,$W15)&"") | W15: =IF($V$3="","",IFERROR(MATCH($V$3&"#"&ROWS(W$4:W15),发票统计!$W$4:$W$1003,0),""))
A16: =IF($W16="","",INDEX(发票统计!A$4:A$1003,$W16)&"") | B16: =IF($W16="","",INDEX(发票统计!B$4:B$1003,$W16)&"") | C16: =IF($W16="","",INDEX(发票统计!C$4:C$1003,$W16)&"") | D16: =IF($W16="","",INDEX(发票统计!D$4:D$1003,$W16)&"") | E16: =IF($W16="","",INDEX(发票统计!E$4:E$1003,$W16)&"") | F16: =IF($W16="","",INDEX(发票统计!F$4:F$1003,$W16)&"") | G16: =IF($W16="","",IF(INDEX(发票统计!G$4:G$1003,$W16)="","",INDEX(发票统计!G$4:G$1003,$W16))) | H16: =IF($W16="","",N(INDEX(发票统计!H$4:H$1003,$W16))) | I16: =IF($W16="","",N(INDEX(发票统计!I$4:I$1003,$W16))) | J16: =IF($W16="","",N(INDEX(发票统计!J$4:J$1003,$W16))) | K16: =IF($W16="","",N(INDEX(发票统计!K$4:K$1003,$W16))) | L16: =IF($W16="","",SUM(J$4:J16)-SUM(K$4:K16)) | M16: =IF($W16="","",N(INDEX(发票统计!M$4:M$1003,$W16))) | N16: =IF($W16="","",N(INDEX(发票统计!N$4:N$1003,$W16))) | O16: =IF($W16="","",N(INDEX(发票统计!O$4:O$1003,$W16))) | P16: =IF($W16="","",SUM(M$4:M16)-SUM(N$4:N16)-SUM(O$4:O16)) | Q16: =IF($W16="","",N(INDEX(发票统计!Q$4:Q$1003,$W16))) | R16: =IF($W16="","",N(INDEX(发票统计!R$4:R$1003,$W16))) | S16: =IF($W16="","",N(INDEX(发票统计!S$4:S$1003,$W16))) | T16: =IF($W16="","",SUM(Q$4:Q16)-SUM(R$4:R16)-SUM(S$4:S16)) | U16: =IF($W16="","",INDEX(发票统计!U$4:U$1003,$W16)&"") | W16: =IF($V$3="","",IFERROR(MATCH($V$3&"#"&ROWS(W$4:W16),发票统计!$W$4:$W$1003,0),""))
... A303: =IF($W303="","",INDEX(发票统计!A$4:A$1003,$W303)&"") | B303: =IF($W303="","",INDEX(发票统计!B$4:B$1003,$W303)&"") | C303: =IF($W303="","",INDEX(发票统计!C$4:C$1003,$W303)&"") | D303: =IF($W303="","",INDEX(发票统计!D$4:D$1003,$W303)&"") | E303: =IF($W303="","",INDEX(发票统计!E$4:E$1003,$W303)&"") | F303: =IF($W303="","",INDEX(发票统计!F$4:F$1003,$W303)&"") | G303: =IF($W303="","",IF(INDEX(发票统计!G$4:G$1003,$W303)="","",INDEX(发票统计!G$4:G$1003,$W303))) | H303: =IF($W303="","",N(INDEX(发票统计!H$4:H$1003,$W303))) | I303: =IF($W303="","",N(INDEX(发票统计!I$4:I$1003,$W303))) | J303: =IF($W303="","",N(INDEX(发票统计!J$4:J$1003,$W303))) | K303: =IF($W303="","",N(INDEX(发票统计!K$4:K$1003,$W303))) | L303: =IF($W303="","",SUM(J$4:J303)-SUM(K$4:K303)) | M303: =IF($W303="","",N(INDEX(发票统计!M$4:M$1003,$W303))) | N303: =IF($W303="","",N(INDEX(发票统计!N$4:N$1003,$W303))) | O303: =IF($W303="","",N(INDEX(发票统计!O$4:O$1003,$W303))) | P303: =IF($W303="","",SUM(M$4:M303)-SUM(N$4:N303)-SUM(O$4:O303)) | Q303: =IF($W303="","",N(INDEX(发票统计!Q$4:Q$1003,$W303))) | R303: =IF($W303="","",N(INDEX(发票统计!R$4:R$1003,$W303))) | S303: =IF($W303="","",N(INDEX(发票统计!S$4:S$1003,$W303))) | T303: =IF($W303="","",SUM(Q$4:Q303)-SUM(R$4:R303)-SUM(S$4:S303)) | U303: =IF($W303="","",INDEX(发票统计!U$4:U$1003,$W303)&"") | W303: =IF($V$3="","",IFERROR(MATCH($V$3&"#"&ROWS(W$4:W303),发票统计!$W$4:$W$1003,0),""))

Sheet 合川表计
A1: 合川表计项目
A2: 对账 单位 | B2: 月份 | C2: 项目 名称 | D2: 摘要 | E2: 收票 单位 | F2: 发票 性质 | G2: 管理 费点 | H2: 销售金额 | I2: 管理费 | J2: 应开 成本票 | K2: 已开 成本票 | L2: 未开 成本票 | M2: 应收款 | N2: 扣质保金 | O2: 已收款 | P2: 未收款 | Q2: 应付 工程款 | R2: 扣除 管理费 | S2: 已付 工程款 | T2: 未付 工程款 | U2: 备注 | V2: 本表项目简称 （自动取表名）
H3: =SUM(H4:H303) -> 895460 | I3: =SUM(I4:I303) -> 0 | J3: =SUM(J4:J303) -> 895460 | K3: =SUM(K4:K303) -> 795460 | L3: =J3-K3 -> 100000 | M3: =SUM(M4:M303) -> 895460 | N3: =SUM(N4:N303) -> 0 | O3: =SUM(O4:O303) -> 350000 | P3: =M3-N3-O3 -> 545460 | Q3: =SUM(Q4:Q303) -> 0 | R3: =SUM(R4:R303) -> 0 | S3: =SUM(S4:S303) -> 576643 | T3: =Q3-R3-S3 -> -576643 | V3: =IFERROR(MID(CELL("filename",$A$1),FIND("]",CELL("filename",$A$1))+1,99),IFERROR(SUBSTITUTE(MID(CELL("filename",$A$1),FIND("#$",CELL("filename",$A$1))+2,99),"'",""),"")) -> 合川表计
A4: =IF($W4="","",INDEX(发票统计!A$4:A$1003,$W4)&"") -> 合川表计 | B4: =IF($W4="","",INDEX(发票统计!B$4:B$1003,$W4)&"") -> 6月 | C4: =IF($W4="","",INDEX(发票统计!C$4:C$1003,$W4)&"") -> 国网重庆合川供电公司2026年用电信息采集系统建筑相关工程施工(包4) | D4: =IF($W4="","",INDEX(发票统计!D$4:D$1003,$W4)&"") -> 2026.6.1张氏机电开票到新德润：合川表计项目 | E4: =IF($W4="","",INDEX(发票统计!E$4:E$1003,$W4)&"") -> 新德润 | F4: =IF($W4="","",INDEX(发票统计!F$4:F$1003,$W4)&"") -> 1%普票 | G4: =IF($W4="","",IF(INDEX(发票统计!G$4:G$1003,$W4)="","",INDEX(发票统计!G$4:G$1003,$W4))) | H4: =IF($W4="","",N(INDEX(发票统计!H$4:H$1003,$W4))) -> 100000 | I4: =IF($W4="","",N(INDEX(发票统计!I$4:I$1003,$W4))) -> 0 | J4: =IF($W4="","",N(INDEX(发票统计!J$4:J$1003,$W4))) -> 100000 | K4: =IF($W4="","",N(INDEX(发票统计!K$4:K$1003,$W4))) -> 100000 | L4: =IF($W4="","",SUM(J$4:J4)-SUM(K$4:K4)) -> 0 | M4: =IF($W4="","",N(INDEX(发票统计!M$4:M$1003,$W4))) -> 100000 | N4: =IF($W4="","",N(INDEX(发票统计!N$4:N$1003,$W4))) -> 0 | O4: =IF($W4="","",N(INDEX(发票统计!O$4:O$1003,$W4))) -> 0 | P4: =IF($W4="","",SUM(M$4:M4)-SUM(N$4:N4)-SUM(O$4:O4)) -> 100000 | Q4: =IF($W4="","",N(INDEX(发票统计!Q$4:Q$1003,$W4))) -> 0 | R4: =IF($W4="","",N(INDEX(发票统计!R$4:R$1003,$W4))) -> 0 | S4: =IF($W4="","",N(INDEX(发票统计!S$4:S$1003,$W4))) -> 0 | T4: =IF($W4="","",SUM(Q$4:Q4)-SUM(R$4:R4)-SUM(S$4:S4)) -> 0 | U4: =IF($W4="","",INDEX(发票统计!U$4:U$1003,$W4)&"") | V4: =IF($V$3="","⚠ 取不到表名，请在 V3 手填项目简称",IF(COUNTIF(发票统计!$A$4:$A$1003,$V$3)=0,"⚠ 发票统计里没有「"&$V$3&"」的行，表名要和目录里的简称一样",IF(COUNTIF(发票统计!$A$4:$A$1003,$V$3)>300,"⚠ 本项目超过 300 行，后面的没显示","共 "&COUNTIF(发票统计!$A$4:$A$1003,$V$3)&" 笔"))) -> 共 42 笔 | W4: =IF($V$3="","",IFERROR(MATCH($V$3&"#"&ROWS(W$4:W4),发票统计!$W$4:$W$1003,0),"")) -> 37
A5: =IF($W5="","",INDEX(发票统计!A$4:A$1003,$W5)&"") -> 合川表计 | B5: =IF($W5="","",INDEX(发票统计!B$4:B$1003,$W5)&"") -> 7月 | C5: =IF($W5="","",INDEX(发票统计!C$4:C$1003,$W5)&"") -> 国网重庆合川供电公司2026年用电信息采集系统建筑相关工程施工(包4) | D5: =IF($W5="","",INDEX(发票统计!D$4:D$1003,$W5)&"") -> 2026.7.28冷氏五金开票到众聚能：合川表计项目 | E5: =IF($W5="","",INDEX(发票统计!E$4:E$1003,$W5)&"") -> 众聚能 | F5: =IF($W5="","",INDEX(发票统计!F$4:F$1003,$W5)&"") -> 3%普票 | G5: =IF($W5="","",IF(INDEX(发票统计!G$4:G$1003,$W5)="","",INDEX(发票统计!G$4:G$1003,$W5))) | H5: =IF($W5="","",N(INDEX(发票统计!H$4:H$1003,$W5))) -> 50000 | I5: =IF($W5="","",N(INDEX(发票统计!I$4:I$1003,$W5))) -> 0 | J5: =IF($W5="","",N(INDEX(发票统计!J$4:J$1003,$W5))) -> 50000 | K5: =IF($W5="","",N(INDEX(发票统计!K$4:K$1003,$W5))) -> 50000 | L5: =IF($W5="","",SUM(J$4:J5)-SUM(K$4:K5)) -> 0 | M5: =IF($W5="","",N(INDEX(发票统计!M$4:M$1003,$W5))) -> 50000 | N5: =IF($W5="","",N(INDEX(发票统计!N$4:N$1003,$W5))) -> 0 | O5: =IF($W5="","",N(INDEX(发票统计!O$4:O$1003,$W5))) -> 0 | P5: =IF($W5="","",SUM(M$4:M5)-SUM(N$4:N5)-SUM(O$4:O5)) -> 150000 | Q5: =IF($W5="","",N(INDEX(发票统计!Q$4:Q$1003,$W5))) -> 0 | R5: =IF($W5="","",N(INDEX(发票统计!R$4:R$1003,$W5))) -> 0 | S5: =IF($W5="","",N(INDEX(发票统计!S$4:S$1003,$W5))) -> 0 | T5: =IF($W5="","",SUM(Q$4:Q5)-SUM(R$4:R5)-SUM(S$4:S5)) -> 0 | U5: =IF($W5="","",INDEX(发票统计!U$4:U$1003,$W5)&"") | W5: =IF($V$3="","",IFERROR(MATCH($V$3&"#"&ROWS(W$4:W5),发票统计!$W$4:$W$1003,0),"")) -> 38
A6: =IF($W6="","",INDEX(发票统计!A$4:A$1003,$W6)&"") -> 合川表计 | B6: =IF($W6="","",INDEX(发票统计!B$4:B$1003,$W6)&"") -> 6月 | C6: =IF($W6="","",INDEX(发票统计!C$4:C$1003,$W6)&"") -> 国网重庆合川供电公司2026年用电信息采集系统建筑相关工程施工(包4) | D6: =IF($W6="","",INDEX(发票统计!D$4:D$1003,$W6)&"") -> 2026.6.5张氏机电收到新德润转款：合川表计项目 | E6: =IF($W6="","",INDEX(发票统计!E$4:E$1003,$W6)&"") -> 新德润 | F6: =IF($W6="","",INDEX(发票统计!F$4:F$1003,$W6)&"") | G6: =IF($W6="","",IF(INDEX(发票统计!G$4:G$1003,$W6)="","",INDEX(发票统计!G$4:G$1003,$W6))) | H6: =IF($W6="","",N(INDEX(发票统计!H$4:H$1003,$W6))) -> 0 | I6: =IF($W6="","",N(INDEX(发票统计!I$4:I$1003,$W6))) -> 0 | J6: =IF($W6="","",N(INDEX(发票统计!J$4:J$1003,$W6))) -> 0 | K6: =IF($W6="","",N(INDEX(发票统计!K$4:K$1003,$W6))) -> 0 | L6: =IF($W6="","",SUM(J$4:J6)-SUM(K$4:K6)) -> 0 | M6: =IF($W6="","",N(INDEX(发票统计!M$4:M$1003,$W6))) -> 0 | N6: =IF($W6="","",N(INDEX(发票统计!N$4:N$1003,$W6))) -> 0 | O6: =IF($W6="","",N(INDEX(发票统计!O$4:O$1003,$W6))) -> 100000 | P6: =IF($W6="","",SUM(M$4:M6)-SUM(N$4:N6)-SUM(O$4:O6)) -> 50000 | Q6: =IF($W6="","",N(INDEX(发票统计!Q$4:Q$1003,$W6))) -> 0 | R6: =IF($W6="","",N(INDEX(发票统计!R$4:R$1003,$W6))) -> 0 | S6: =IF($W6="","",N(INDEX(发票统计!S$4:S$1003,$W6))) -> 0 | T6: =IF($W6="","",SUM(Q$4:Q6)-SUM(R$4:R6)-SUM(S$4:S6)) -> 0 | U6: =IF($W6="","",INDEX(发票统计!U$4:U$1003,$W6)&"") | W6: =IF($V$3="","",IFERROR(MATCH($V$3&"#"&ROWS(W$4:W6),发票统计!$W$4:$W$1003,0),"")) -> 39
A7: =IF($W7="","",INDEX(发票统计!A$4:A$1003,$W7)&"") -> 合川表计 | B7: =IF($W7="","",INDEX(发票统计!B$4:B$1003,$W7)&"") -> 7月 | C7: =IF($W7="","",INDEX(发票统计!C$4:C$1003,$W7)&"") -> 国网重庆合川供电公司2026年用电信息采集系统建筑相关工程施工(包4) | D7: =IF($W7="","",INDEX(发票统计!D$4:D$1003,$W7)&"") -> 2026.7.31陈小琴（冷氏五金开）收到新德润打款：合川表计项目 | E7: =IF($W7="","",INDEX(发票统计!E$4:E$1003,$W7)&"") -> 新德润 | F7: =IF($W7="","",INDEX(发票统计!F$4:F$1003,$W7)&"") | G7: =IF($W7="","",IF(INDEX(发票统计!G$4:G$1003,$W7)="","",INDEX(发票统计!G$4:G$1003,$W7))) | H7: =IF($W7="","",N(INDEX(发票统计!H$4:H$1003,$W7))) -> 0 | I7: =IF($W7="","",N(INDEX(发票统计!I$4:I$1003,$W7))) -> 0 | J7: =IF($W7="","",N(INDEX(发票统计!J$4:J$1003,$W7))) -> 0 | K7: =IF($W7="","",N(INDEX(发票统计!K$4:K$1003,$W7))) -> 0 | L7: =IF($W7="","",SUM(J$4:J7)-SUM(K$4:K7)) -> 0 | M7: =IF($W7="","",N(INDEX(发票统计!M$4:M$1003,$W7))) -> 0 | N7: =IF($W7="","",N(INDEX(发票统计!N$4:N$1003,$W7))) -> 0 | O7: =IF($W7="","",N(INDEX(发票统计!O$4:O$1003,$W7))) -> 50000 | P7: =IF($W7="","",SUM(M$4:M7)-SUM(N$4:N7)-SUM(O$4:O7)) -> 0 | Q7: =IF($W7="","",N(INDEX(发票统计!Q$4:Q$1003,$W7))) -> 0 | R7: =IF($W7="","",N(INDEX(发票统计!R$4:R$1003,$W7))) -> 0 | S7: =IF($W7="","",N(INDEX(发票统计!S$4:S$1003,$W7))) -> 0 | T7: =IF($W7="","",SUM(Q$4:Q7)-SUM(R$4:R7)-SUM(S$4:S7)) -> 0 | U7: =IF($W7="","",INDEX(发票统计!U$4:U$1003,$W7)&"") | W7: =IF($V$3="","",IFERROR(MATCH($V$3&"#"&ROWS(W$4:W7),发票统计!$W$4:$W$1003,0),"")) -> 40
A8: =IF($W8="","",INDEX(发票统计!A$4:A$1003,$W8)&"") -> 合川表计 | B8: =IF($W8="","",INDEX(发票统计!B$4:B$1003,$W8)&"") -> 8月 | C8: =IF($W8="","",INDEX(发票统计!C$4:C$1003,$W8)&"") -> 国网重庆合川供电公司2026年用电信息采集系统建筑相关工程施工(包4) | D8: =IF($W8="","",INDEX(发票统计!D$4:D$1003,$W8)&"") -> 2026.8.21工资表给众聚能挂账：合川表计项目 | E8: =IF($W8="","",INDEX(发票统计!E$4:E$1003,$W8)&"") -> 众聚能 | F8: =IF($W8="","",INDEX(发票统计!F$4:F$1003,$W8)&"") -> 1%普票 | G8: =IF($W8="","",IF(INDEX(发票统计!G$4:G$1003,$W8)="","",INDEX(发票统计!G$4:G$1003,$W8))) | H8: =IF($W8="","",N(INDEX(发票统计!H$4:H$1003,$W8))) -> 122000 | I8: =IF($W8="","",N(INDEX(发票统计!I$4:I$1003,$W8))) -> 0 | J8: =IF($W8="","",N(INDEX(发票统计!J$4:J$1003,$W8))) -> 122000 | K8: =IF($W8="","",N(INDEX(发票统计!K$4:K$1003,$W8))) -> 122000 | L8: =IF($W8="","",SUM(J$4:J8)-SUM(K$4:K8)) -> 0 | M8: =IF($W8="","",N(INDEX(发票统计!M$4:M$1003,$W8))) -> 122000 | N8: =IF($W8="","",N(INDEX(发票统计!N$4:N$1003,$W8))) -> 0 | O8: =IF($W8="","",N(INDEX(发票统计!O$4:O$1003,$W8))) -> 0 | P8: =IF($W8="","",SUM(M$4:M8)-SUM(N$4:N8)-SUM(O$4:O8)) -> 122000 | Q8: =IF($W8="","",N(INDEX(发票统计!Q$4:Q$1003,$W8))) -> 0 | R8: =IF($W8="","",N(INDEX(发票统计!R$4:R$1003,$W8))) -> 0 | S8: =IF($W8="","",N(INDEX(发票统计!S$4:S$1003,$W8))) -> 0 | T8: =IF($W8="","",SUM(Q$4:Q8)-SUM(R$4:R8)-SUM(S$4:S8)) -> 0 | U8: =IF($W8="","",INDEX(发票统计!U$4:U$1003,$W8)&"") | W8: =IF($V$3="","",IFERROR(MATCH($V$3&"#"&ROWS(W$4:W8),发票统计!$W$4:$W$1003,0),"")) -> 41
A9: =IF($W9="","",INDEX(发票统计!A$4:A$1003,$W9)&"") -> 合川表计 | B9: =IF($W9="","",INDEX(发票统计!B$4:B$1003,$W9)&"") -> 8月 | C9: =IF($W9="","",INDEX(发票统计!C$4:C$1003,$W9)&"") -> 国网重庆合川供电公司2026年用电信息采集系统建筑相关工程施工(包4) | D9: =IF($W9="","",INDEX(发票统计!D$4:D$1003,$W9)&"") -> 2026.8.21众聚能代付工资：合川表计项目 | E9: =IF($W9="","",INDEX(发票统计!E$4:E$1003,$W9)&"") -> 众聚能 | F9: =IF($W9="","",INDEX(发票统计!F$4:F$1003,$W9)&"") | G9: =IF($W9="","",IF(INDEX(发票统计!G$4:G$1003,$W9)="","",INDEX(发票统计!G$4:G$1003,$W9))) | H9: =IF($W9="","",N(INDEX(发票统计!H$4:H$1003,$W9))) -> 0 | I9: =IF($W9="","",N(INDEX(发票统计!I$4:I$1003,$W9))) -> 0 | J9: =IF($W9="","",N(INDEX(发票统计!J$4:J$1003,$W9))) -> 0 | K9: =IF($W9="","",N(INDEX(发票统计!K$4:K$1003,$W9))) -> 0 | L9: =IF($W9="","",SUM(J$4:J9)-SUM(K$4:K9)) -> 0 | M9: =IF($W9="","",N(INDEX(发票统计!M$4:M$1003,$W9))) -> 0 | N9: =IF($W9="","",N(INDEX(发票统计!N$4:N$1003,$W9))) -> 0 | O9: =IF($W9="","",N(INDEX(发票统计!O$4:O$1003,$W9))) -> 122000 | P9: =IF($W9="","",SUM(M$4:M9)-SUM(N$4:N9)-SUM(O$4:O9)) -> 0 | Q9: =IF($W9="","",N(INDEX(发票统计!Q$4:Q$1003,$W9))) -> 0 | R9: =IF($W9="","",N(INDEX(发票统计!R$4:R$1003,$W9))) -> 0 | S9: =IF($W9="","",N(INDEX(发票统计!S$4:S$1003,$W9))) -> 0 | T9: =IF($W9="","",SUM(Q$4:Q9)-SUM(R$4:R9)-SUM(S$4:S9)) -> 0 | U9: =IF($W9="","",INDEX(发票统计!U$4:U$1003,$W9)&"") | W9: =IF($V$3="","",IFERROR(MATCH($V$3&"#"&ROWS(W$4:W9),发票统计!$W$4:$W$1003,0),"")) -> 42
A10: =IF($W10="","",INDEX(发票统计!A$4:A$1003,$W10)&"") -> 合川表计 | B10: =IF($W10="","",INDEX(发票统计!B$4:B$1003,$W10)&"") -> 8月 | C10: =IF($W10="","",INDEX(发票统计!C$4:C$1003,$W10)&"") -> 国网重庆合川供电公司2026年用电信息采集系统建筑相关工程施工(包4) | D10: =IF($W10="","",INDEX(发票统计!D$4:D$1003,$W10)&"") -> 2026.8.21工资表给腾泰挂账：合川表计项目 | E10: =IF($W10="","",INDEX(发票统计!E$4:E$1003,$W10)&"") -> 腾泰 | F10: =IF($W10="","",INDEX(发票统计!F$4:F$1003,$W10)&"") -> 1%普票 | G10: =IF($W10="","",IF(INDEX(发票统计!G$4:G$1003,$W10)="","",INDEX(发票统计!G$4:G$1003,$W10))) | H10: =IF($W10="","",N(INDEX(发票统计!H$4:H$1003,$W10))) -> 78000 | I10: =IF($W10="","",N(INDEX(发票统计!I$4:I$1003,$W10))) -> 0 | J10: =IF($W10="","",N(INDEX(发票统计!J$4:J$1003,$W10))) -> 78000 | K10: =IF($W10="","",N(INDEX(发票统计!K$4:K$1003,$W10))) -> 78000 | L10: =IF($W10="","",SUM(J$4:J10)-SUM(K$4:K10)) -> 0 | M10: =IF($W10="","",N(INDEX(发票统计!M$4:M$1003,$W10))) -> 78000 | N10: =IF($W10="","",N(INDEX(发票统计!N$4:N$1003,$W10))) -> 0 | O10: =IF($W10="","",N(INDEX(发票统计!O$4:O$1003,$W10))) -> 0 | P10: =IF($W10="","",SUM(M$4:M10)-SUM(N$4:N10)-SUM(O$4:O10)) -> 78000 | Q10: =IF($W10="","",N(INDEX(发票统计!Q$4:Q$1003,$W10))) -> 0 | R10: =IF($W10="","",N(INDEX(发票统计!R$4:R$1003,$W10))) -> 0 | S10: =IF($W10="","",N(INDEX(发票统计!S$4:S$1003,$W10))) -> 0 | T10: =IF($W10="","",SUM(Q$4:Q10)-SUM(R$4:R10)-SUM(S$4:S10)) -> 0 | U10: =IF($W10="","",INDEX(发票统计!U$4:U$1003,$W10)&"") | W10: =IF($V$3="","",IFERROR(MATCH($V$3&"#"&ROWS(W$4:W10),发票统计!$W$4:$W$1003,0),"")) -> 43
A11: =IF($W11="","",INDEX(发票统计!A$4:A$1003,$W11)&"") -> 合川表计 | B11: =IF($W11="","",INDEX(发票统计!B$4:B$1003,$W11)&"") -> 8月 | C11: =IF($W11="","",INDEX(发票统计!C$4:C$1003,$W11)&"") -> 国网重庆合川供电公司2026年用电信息采集系统建筑相关工程施工(包4) | D11: =IF($W11="","",INDEX(发票统计!D$4:D$1003,$W11)&"") -> 2026.8.21腾泰代付工资：合川表计项目 | E11: =IF($W11="","",INDEX(发票统计!E$4:E$1003,$W11)&"") -> 腾泰 | F11: =IF($W11="","",INDEX(发票统计!F$4:F$1003,$W11)&"") | G11: =IF($W11="","",IF(INDEX(发票统计!G$4:G$1003,$W11)="","",INDEX(发票统计!G$4:G$1003,$W11))) | H11: =IF($W11="","",N(INDEX(发票统计!H$4:H$1003,$W11))) -> 0 | I11: =IF($W11="","",N(INDEX(发票统计!I$4:I$1003,$W11))) -> 0 | J11: =IF($W11="","",N(INDEX(发票统计!J$4:J$1003,$W11))) -> 0 | K11: =IF($W11="","",N(INDEX(发票统计!K$4:K$1003,$W11))) -> 0 | L11: =IF($W11="","",SUM(J$4:J11)-SUM(K$4:K11)) -> 0 | M11: =IF($W11="","",N(INDEX(发票统计!M$4:M$1003,$W11))) -> 0 | N11: =IF($W11="","",N(INDEX(发票统计!N$4:N$1003,$W11))) -> 0 | O11: =IF($W11="","",N(INDEX(发票统计!O$4:O$1003,$W11))) -> 78000 | P11: =IF($W11="","",SUM(M$4:M11)-SUM(N$4:N11)-SUM(O$4:O11)) -> 0 | Q11: =IF($W11="","",N(INDEX(发票统计!Q$4:Q$1003,$W11))) -> 0 | R11: =IF($W11="","",N(INDEX(发票统计!R$4:R$1003,$W11))) -> 0 | S11: =IF($W11="","",N(INDEX(发票统计!S$4:S$1003,$W11))) -> 0 | T11: =IF($W11="","",SUM(Q$4:Q11)-SUM(R$4:R11)-SUM(S$4:S11)) -> 0 | U11: =IF($W11="","",INDEX(发票统计!U$4:U$1003,$W11)&"") | W11: =IF($V$3="","",IFERROR(MATCH($V$3&"#"&ROWS(W$4:W11),发票统计!$W$4:$W$1003,0),"")) -> 44
A12: =IF($W12="","",INDEX(发票统计!A$4:A$1003,$W12)&"") -> 合川表计 | B12: =IF($W12="","",INDEX(发票统计!B$4:B$1003,$W12)&"") -> 9月 | C12: =IF($W12="","",INDEX(发票统计!C$4:C$1003,$W12)&"") -> 国网重庆合川供电公司2026年用电信息采集系统建筑相关工程施工(包4) | D12: =IF($W12="","",INDEX(发票统计!D$4:D$1003,$W12)&"") -> 2026.9.14进源开给润德427712.65，提交15万工资（进源部分人工）：合川表计项目 | E12: =IF($W12="","",INDEX(发票统计!E$4:E$1003,$W12)&"") -> 润德 | F12: =IF($W12="","",INDEX(发票统计!F$4:F$1003,$W12)&"") -> 3%专票 | G12: =IF($W12="","",IF(INDEX(发票统计!G$4:G$1003,$W12)="","",INDEX(发票统计!G$4:G$1003,$W12))) | H12: =IF($W12="","",N(INDEX(发票统计!H$4:H$1003,$W12))) -> 150000 | I12: =IF($W12="","",N(INDEX(发票统计!I$4:I$1003,$W12))) -> 0 | J12: =IF($W12="","",N(INDEX(发票统计!J$4:J$1003,$W12))) -> 150000 | K12: =IF($W12="","",N(INDEX(发票统计!K$4:K$1003,$W12))) -> 150000 | L12: =IF($W12="","",SUM(J$4:J12)-SUM(K$4:K12)) -> 0 | M12: =IF($W12="","",N(INDEX(发票统计!M$4:M$1003,$W12))) -> 150000 | N12: =IF($W12="","",N(INDEX(发票统计!N$4:N$1003,$W12))) -> 0 | O12: =IF($W12="","",N(INDEX(发票统计!O$4:O$1003,$W12))) -> 0 | P12: =IF($W12="","",SUM(M$4:M12)-SUM(N$4:N12)-SUM(O$4:O12)) -> 150000 | Q12: =IF($W12="","",N(INDEX(发票统计!Q$4:Q$1003,$W12))) -> 0 | R12: =IF($W12="","",N(INDEX(发票统计!R$4:R$1003,$W12))) -> 0 | S12: =IF($W12="","",N(INDEX(发票统计!S$4:S$1003,$W12))) -> 0 | T12: =IF($W12="","",SUM(Q$4:Q12)-SUM(R$4:R12)-SUM(S$4:S12)) -> 0 | U12: =IF($W12="","",INDEX(发票统计!U$4:U$1003,$W12)&"") | W12: =IF($V$3="","",IFERROR(MATCH($V$3&"#"&ROWS(W$4:W12),发票统计!$W$4:$W$1003,0),"")) -> 45
A13: =IF($W13="","",INDEX(发票统计!A$4:A$1003,$W13)&"") -> 合川表计 | B13: =IF($W13="","",INDEX(发票统计!B$4:B$1003,$W13)&"") -> 9月 | C13: =IF($W13="","",INDEX(发票统计!C$4:C$1003,$W13)&"") -> 国网重庆合川供电公司2026年用电信息采集系统建筑相关工程施工(包4) | D13: =IF($W13="","",INDEX(发票统计!D$4:D$1003,$W13)&"") -> 2026.9.21维维对账提交腾泰工资：合川表计项目 | E13: =IF($W13="","",INDEX(发票统计!E$4:E$1003,$W13)&"") -> 腾泰 | F13: =IF($W13="","",INDEX(发票统计!F$4:F$1003,$W13)&"") -> 1%普票 | G13: =IF($W13="","",IF(INDEX(发票统计!G$4:G$1003,$W13)="","",INDEX(发票统计!G$4:G$1003,$W13))) | H13: =IF($W13="","",N(INDEX(发票统计!H$4:H$1003,$W13))) -> 195460 | I13: =IF($W13="","",N(INDEX(发票统计!I$4:I$1003,$W13))) -> 0 | J13: =IF($W13="","",N(INDEX(发票统计!J$4:J$1003,$W13))) -> 195460 | K13: =IF($W13="","",N(INDEX(发票统计!K$4:K$1003,$W13))) -> 195460 | L13: =IF($W13="","",SUM(J$4:J13)-SUM(K$4:K13)) -> 0 | M13: =IF($W13="","",N(INDEX(发票统计!M$4:M$1003,$W13))) -> 195460 | N13: =IF($W13="","",N(INDEX(发票统计!N$4:N$1003,$W13))) -> 0 | O13: =IF($W13="","",N(INDEX(发票统计!O$4:O$1003,$W13))) -> 0 | P13: =IF($W13="","",SUM(M$4:M13)-SUM(N$4:N13)-SUM(O$4:O13)) -> 345460 | Q13: =IF($W13="","",N(INDEX(发票统计!Q$4:Q$1003,$W13))) -> 0 | R13: =IF($W13="","",N(INDEX(发票统计!R$4:R$1003,$W13))) -> 0 | S13: =IF($W13="","",N(INDEX(发票统计!S$4:S$1003,$W13))) -> 0 | T13: =IF($W13="","",SUM(Q$4:Q13)-SUM(R$4:R13)-SUM(S$4:S13)) -> 0 | U13: =IF($W13="","",INDEX(发票统计!U$4:U$1003,$W13)&"") | W13: =IF($V$3="","",IFERROR(MATCH($V$3&"#"&ROWS(W$4:W13),发票统计!$W$4:$W$1003,0),"")) -> 46
A14: =IF($W14="","",INDEX(发票统计!A$4:A$1003,$W14)&"") -> 合川表计 | B14: =IF($W14="","",INDEX(发票统计!B$4:B$1003,$W14)&"") -> 9月 | C14: =IF($W14="","",INDEX(发票统计!C$4:C$1003,$W14)&"") -> 国网重庆合川供电公司2026年用电信息采集系统建筑相关工程施工(包4) | D14: =IF($W14="","",INDEX(发票统计!D$4:D$1003,$W14)&"") -> 2026.9.21何燕反馈提交10W工资表 | E14: =IF($W14="","",INDEX(发票统计!E$4:E$1003,$W14)&"") -> 众聚能 | F14: =IF($W14="","",INDEX(发票统计!F$4:F$1003,$W14)&"") | G14: =IF($W14="","",IF(INDEX(发票统计!G$4:G$1003,$W14)="","",INDEX(发票统计!G$4:G$1003,$W14))) | H14: =IF($W14="","",N(INDEX(发票统计!H$4:H$1003,$W14))) -> 100000 | I14: =IF($W14="","",N(INDEX(发票统计!I$4:I$1003,$W14))) -> 0 | J14: =IF($W14="","",N(INDEX(发票统计!J$4:J$1003,$W14))) -> 100000 | K14: =IF($W14="","",N(INDEX(发票统计!K$4:K$1003,$W14))) -> 100000 | L14: =IF($W14="","",SUM(J$4:J14)-SUM(K$4:K14)) -> 0 | M14: =IF($W14="","",N(INDEX(发票统计!M$4:M$1003,$W14))) -> 100000 | N14: =IF($W14="","",N(INDEX(发票统计!N$4:N$1003,$W14))) -> 0 | O14: =IF($W14="","",N(INDEX(发票统计!O$4:O$1003,$W14))) -> 0 | P14: =IF($W14="","",SUM(M$4:M14)-SUM(N$4:N14)-SUM(O$4:O14)) -> 445460 | Q14: =IF($W14="","",N(INDEX(发票统计!Q$4:Q$1003,$W14))) -> 0 | R14: =IF($W14="","",N(INDEX(发票统计!R$4:R$1003,$W14))) -> 0 | S14: =IF($W14="","",N(INDEX(发票统计!S$4:S$1003,$W14))) -> 0 | T14: =IF($W14="","",SUM(Q$4:Q14)-SUM(R$4:R14)-SUM(S$4:S14)) -> 0 | U14: =IF($W14="","",INDEX(发票统计!U$4:U$1003,$W14)&"") | W14: =IF($V$3="","",IFERROR(MATCH($V$3&"#"&ROWS(W$4:W14),发票统计!$W$4:$W$1003,0),"")) -> 47
A15: =IF($W15="","",INDEX(发票统计!A$4:A$1003,$W15)&"") -> 合川表计 | B15: =IF($W15="","",INDEX(发票统计!B$4:B$1003,$W15)&"") -> 9月 | C15: =IF($W15="","",INDEX(发票统计!C$4:C$1003,$W15)&"") -> 国网重庆合川供电公司2026年用电信息采集系统建筑相关工程施工(包4) | D15: =IF($W15="","",INDEX(发票统计!D$4:D$1003,$W15)&"") -> 2026.9.21小温提供表计工资表给众聚能何燕挂账 | E15: =IF($W15="","",INDEX(发票统计!E$4:E$1003,$W15)&"") -> 众聚能 | F15: =IF($W15="","",INDEX(发票统计!F$4:F$1003,$W15)&"") -> 1%普票 | G15: =IF($W15="","",IF(INDEX(发票统计!G$4:G$1003,$W15)="","",INDEX(发票统计!G$4:G$1003,$W15))) | H15: =IF($W15="","",N(INDEX(发票统计!H$4:H$1003,$W15))) -> 100000 | I15: =IF($W15="","",N(INDEX(发票统计!I$4:I$1003,$W15))) -> 0 | J15: =IF($W15="","",N(INDEX(发票统计!J$4:J$1003,$W15))) -> 100000 | K15: =IF($W15="","",N(INDEX(发票统计!K$4:K$1003,$W15))) -> 0 | L15: =IF($W15="","",SUM(J$4:J15)-SUM(K$4:K15)) -> 100000 | M15: =IF($W15="","",N(INDEX(发票统计!M$4:M$1003,$W15))) -> 100000 | N15: =IF($W15="","",N(INDEX(发票统计!N$4:N$1003,$W15))) -> 0 | O15: =IF($W15="","",N(INDEX(发票统计!O$4:O$1003,$W15))) -> 0 | P15: =IF($W15="","",SUM(M$4:M15)-SUM(N$4:N15)-SUM(O$4:O15)) -> 545460 | Q15: =IF($W15="","",N(INDEX(发票统计!Q$4:Q$1003,$W15))) -> 0 | R15: =IF($W15="","",N(INDEX(发票统计!R$4:R$1003,$W15))) -> 0 | S15: =IF($W15="","",N(INDEX(发票统计!S$4:S$1003,$W15))) -> 0 | T15: =IF($W15="","",SUM(Q$4:Q15)-SUM(R$4:R15)-SUM(S$4:S15)) -> 0 | U15: =IF($W15="","",INDEX(发票统计!U$4:U$1003,$W15)&"") | W15: =IF($V$3="","",IFERROR(MATCH($V$3&"#"&ROWS(W$4:W15),发票统计!$W$4:$W$1003,0),"")) -> 48
A16: =IF($W16="","",INDEX(发票统计!A$4:A$1003,$W16)&"") -> 合川表计 | B16: =IF($W16="","",INDEX(发票统计!B$4:B$1003,$W16)&"") -> 5月 | C16: =IF($W16="","",INDEX(发票统计!C$4:C$1003,$W16)&"") -> 国网重庆合川供电公司2026年用电信息采集系统建筑相关工程施工(包4) | D16: =IF($W16="","",INDEX(发票统计!D$4:D$1003,$W16)&"") -> 2026.5.6/5.23代付合川表计工资 | E16: =IF($W16="","",INDEX(发票统计!E$4:E$1003,$W16)&"") | F16: =IF($W16="","",INDEX(发票统计!F$4:F$1003,$W16)&"") | G16: =IF($W16="","",IF(INDEX(发票统计!G$4:G$1003,$W16)="","",INDEX(发票统计!G$4:G$1003,$W16))) | H16: =IF($W16="","",N(INDEX(发票统计!H$4:H$1003,$W16))) -> 0 | I16: =IF($W16="","",N(INDEX(发票统计!I$4:I$1003,$W16))) -> 0 | J16: =IF($W16="","",N(INDEX(发票统计!J$4:J$1003,$W16))) -> 0 | K16: =IF($W16="","",N(INDEX(发票统计!K$4:K$1003,$W16))) -> 0 | L16: =IF($W16="","",SUM(J$4:J16)-SUM(K$4:K16)) -> 100000 | M16: =IF($W16="","",N(INDEX(发票统计!M$4:M$1003,$W16))) -> 0 | N16: =IF($W16="","",N(INDEX(发票统计!N$4:N$1003,$W16))) -> 0 | O16: =IF($W16="","",N(INDEX(发票统计!O$4:O$1003,$W16))) -> 0 | P16: =IF($W16="","",SUM(M$4:M16)-SUM(N$4:N16)-SUM(O$4:O16)) -> 545460 | Q16: =IF($W16="","",N(INDEX(发票统计!Q$4:Q$1003,$W16))) -> 0 | R16: =IF($W16="","",N(INDEX(发票统计!R$4:R$1003,$W16))) -> 0 | S16: =IF($W16="","",N(INDEX(发票统计!S$4:S$1003,$W16))) -> 105000 | T16: =IF($W16="","",SUM(Q$4:Q16)-SUM(R$4:R16)-SUM(S$4:S16)) -> -105000 | U16: =IF($W16="","",INDEX(发票统计!U$4:U$1003,$W16)&"") | W16: =IF($V$3="","",IFERROR(MATCH($V$3&"#"&ROWS(W$4:W16),发票统计!$W$4:$W$1003,0),"")) -> 49
... A303: =IF($W303="","",INDEX(发票统计!A$4:A$1003,$W303)&"") | B303: =IF($W303="","",INDEX(发票统计!B$4:B$1003,$W303)&"") | C303: =IF($W303="","",INDEX(发票统计!C$4:C$1003,$W303)&"") | D303: =IF($W303="","",INDEX(发票统计!D$4:D$1003,$W303)&"") | E303: =IF($W303="","",INDEX(发票统计!E$4:E$1003,$W303)&"") | F303: =IF($W303="","",INDEX(发票统计!F$4:F$1003,$W303)&"") | G303: =IF($W303="","",IF(INDEX(发票统计!G$4:G$1003,$W303)="","",INDEX(发票统计!G$4:G$1003,$W303))) | H303: =IF($W303="","",N(INDEX(发票统计!H$4:H$1003,$W303))) | I303: =IF($W303="","",N(INDEX(发票统计!I$4:I$1003,$W303))) | J303: =IF($W303="","",N(INDEX(发票统计!J$4:J$1003,$W303))) | K303: =IF($W303="","",N(INDEX(发票统计!K$4:K$1003,$W303))) | L303: =IF($W303="","",SUM(J$4:J303)-SUM(K$4:K303)) | M303: =IF($W303="","",N(INDEX(发票统计!M$4:M$1003,$W303))) | N303: =IF($W303="","",N(INDEX(发票统计!N$4:N$1003,$W303))) | O303: =IF($W303="","",N(INDEX(发票统计!O$4:O$1003,$W303))) | P303: =IF($W303="","",SUM(M$4:M303)-SUM(N$4:N303)-SUM(O$4:O303)) | Q303: =IF($W303="","",N(INDEX(发票统计!Q$4:Q$1003,$W303))) | R303: =IF($W303="","",N(INDEX(发票统计!R$4:R$1003,$W303))) | S303: =IF($W303="","",N(INDEX(发票统计!S$4:S$1003,$W303))) | T303: =IF($W303="","",SUM(Q$4:Q303)-SUM(R$4:R303)-SUM(S$4:S303)) | U303: =IF($W303="","",INDEX(发票统计!U$4:U$1003,$W303)&"") | W303: =IF($V$3="","",IFERROR(MATCH($V$3&"#"&ROWS(W$4:W303),发票统计!$W$4:$W$1003,0),""))

Sheet 云龙社区
A1: 云门街道云龙社区居民委员会(铁工厂还房建设项目)高压新装用电工程
A2: 对账 单位 | B2: 月份 | C2: 项目 名称 | D2: 摘要 | E2: 收票 单位 | F2: 发票 性质 | G2: 管理 费点 | H2: 销售金额 | I2: 管理费 | J2: 应开 成本票 | K2: 已开 成本票 | L2: 未开 成本票 | M2: 应收款 | N2: 质保金 | O2: 已收款 | P2: 未收款 | Q2: 应付 工程款 | R2: 扣除 管理费 | S2: 已付 工程款 | T2: 未付 工程款 | U2: 备注 | V2: 本表项目简称 （自动取表名）
H3: =SUM(H4:H303) -> 227260.8 | I3: =SUM(I4:I303) -> 0 | J3: =SUM(J4:J303) -> 227260.8 | K3: =SUM(K4:K303) -> 227260.8 | L3: =J3-K3 -> 0 | M3: =SUM(M4:M303) -> 227260.8 | N3: =SUM(N4:N303) -> 0 | O3: =SUM(O4:O303) -> 227260.8 | P3: =M3-N3-O3 -> 0 | Q3: =SUM(Q4:Q303) -> 0 | R3: =SUM(R4:R303) -> 0 | S3: =SUM(S4:S303) -> 0 | T3: =Q3-R3-S3 -> 0 | V3: =IFERROR(MID(CELL("filename",$A$1),FIND("]",CELL("filename",$A$1))+1,99),IFERROR(SUBSTITUTE(MID(CELL("filename",$A$1),FIND("#$",CELL("filename",$A$1))+2,99),"'",""),"")) -> 云龙社区
A4: =IF($W4="","",INDEX(发票统计!A$4:A$1003,$W4)&"") -> 云龙社区 | B4: =IF($W4="","",INDEX(发票统计!B$4:B$1003,$W4)&"") -> 4月 | C4: =IF($W4="","",INDEX(发票统计!C$4:C$1003,$W4)&"") -> 重庆市合川区云门街道云龙社区居民委员会(铁工厂还房建设项目)高压新装用电工程 | D4: =IF($W4="","",INDEX(发票统计!D$4:D$1003,$W4)&"") -> 2026.4.28庆文开票给新德润：云龙社区居民委员会 | E4: =IF($W4="","",INDEX(发票统计!E$4:E$1003,$W4)&"") -> 新德润 | F4: =IF($W4="","",INDEX(发票统计!F$4:F$1003,$W4)&"") -> 3%专票 | G4: =IF($W4="","",IF(INDEX(发票统计!G$4:G$1003,$W4)="","",INDEX(发票统计!G$4:G$1003,$W4))) | H4: =IF($W4="","",N(INDEX(发票统计!H$4:H$1003,$W4))) -> 183486.24 | I4: =IF($W4="","",N(INDEX(发票统计!I$4:I$1003,$W4))) -> 0 | J4: =IF($W4="","",N(INDEX(发票统计!J$4:J$1003,$W4))) -> 183486.24 | K4: =IF($W4="","",N(INDEX(发票统计!K$4:K$1003,$W4))) -> 183486.24 | L4: =IF($W4="","",SUM(J$4:J4)-SUM(K$4:K4)) -> 0 | M4: =IF($W4="","",N(INDEX(发票统计!M$4:M$1003,$W4))) -> 183486.24 | N4: =IF($W4="","",N(INDEX(发票统计!N$4:N$1003,$W4))) -> 0 | O4: =IF($W4="","",N(INDEX(发票统计!O$4:O$1003,$W4))) -> 0 | P4: =IF($W4="","",SUM(M$4:M4)-SUM(N$4:N4)-SUM(O$4:O4)) -> 183486.24 | Q4: =IF($W4="","",N(INDEX(发票统计!Q$4:Q$1003,$W4))) -> 0 | R4: =IF($W4="","",N(INDEX(发票统计!R$4:R$1003,$W4))) -> 0 | S4: =IF($W4="","",N(INDEX(发票统计!S$4:S$1003,$W4))) -> 0 | T4: =IF($W4="","",SUM(Q$4:Q4)-SUM(R$4:R4)-SUM(S$4:S4)) -> 0 | U4: =IF($W4="","",INDEX(发票统计!U$4:U$1003,$W4)&"") | V4: =IF($V$3="","⚠ 取不到表名，请在 V3 手填项目简称",IF(COUNTIF(发票统计!$A$4:$A$1003,$V$3)=0,"⚠ 发票统计里没有「"&$V$3&"」的行，表名要和目录里的简称一样",IF(COUNTIF(发票统计!$A$4:$A$1003,$V$3)>300,"⚠ 本项目超过 300 行，后面的没显示","共 "&COUNTIF(发票统计!$A$4:$A$1003,$V$3)&" 笔"))) -> 共 4 笔 | W4: =IF($V$3="","",IFERROR(MATCH($V$3&"#"&ROWS(W$4:W4),发票统计!$W$4:$W$1003,0),"")) -> 3
A5: =IF($W5="","",INDEX(发票统计!A$4:A$1003,$W5)&"") -> 云龙社区 | B5: =IF($W5="","",INDEX(发票统计!B$4:B$1003,$W5)&"") -> 4月 | C5: =IF($W5="","",INDEX(发票统计!C$4:C$1003,$W5)&"") -> 重庆市合川区云门街道云龙社区居民委员会(铁工厂还房建设项目)高压新装用电工程 | D5: =IF($W5="","",INDEX(发票统计!D$4:D$1003,$W5)&"") -> 2026.4.30莨富收到新德润款项：云龙社区居民委员会 | E5: =IF($W5="","",INDEX(发票统计!E$4:E$1003,$W5)&"") -> 新德润 | F5: =IF($W5="","",INDEX(发票统计!F$4:F$1003,$W5)&"") | G5: =IF($W5="","",IF(INDEX(发票统计!G$4:G$1003,$W5)="","",INDEX(发票统计!G$4:G$1003,$W5))) | H5: =IF($W5="","",N(INDEX(发票统计!H$4:H$1003,$W5))) -> 0 | I5: =IF($W5="","",N(INDEX(发票统计!I$4:I$1003,$W5))) -> 0 | J5: =IF($W5="","",N(INDEX(发票统计!J$4:J$1003,$W5))) -> 0 | K5: =IF($W5="","",N(INDEX(发票统计!K$4:K$1003,$W5))) -> 0 | L5: =IF($W5="","",SUM(J$4:J5)-SUM(K$4:K5)) -> 0 | M5: =IF($W5="","",N(INDEX(发票统计!M$4:M$1003,$W5))) -> 0 | N5: =IF($W5="","",N(INDEX(发票统计!N$4:N$1003,$W5))) -> 0 | O5: =IF($W5="","",N(INDEX(发票统计!O$4:O$1003,$W5))) -> 183486.24 | P5: =IF($W5="","",SUM(M$4:M5)-SUM(N$4:N5)-SUM(O$4:O5)) -> 0 | Q5: =IF($W5="","",N(INDEX(发票统计!Q$4:Q$1003,$W5))) -> 0 | R5: =IF($W5="","",N(INDEX(发票统计!R$4:R$1003,$W5))) -> 0 | S5: =IF($W5="","",N(INDEX(发票统计!S$4:S$1003,$W5))) -> 0 | T5: =IF($W5="","",SUM(Q$4:Q5)-SUM(R$4:R5)-SUM(S$4:S5)) -> 0 | U5: =IF($W5="","",INDEX(发票统计!U$4:U$1003,$W5)&"") | W5: =IF($V$3="","",IFERROR(MATCH($V$3&"#"&ROWS(W$4:W5),发票统计!$W$4:$W$1003,0),"")) -> 4
A6: =IF($W6="","",INDEX(发票统计!A$4:A$1003,$W6)&"") -> 云龙社区 | B6: =IF($W6="","",INDEX(发票统计!B$4:B$1003,$W6)&"") -> 5月 | C6: =IF($W6="","",INDEX(发票统计!C$4:C$1003,$W6)&"") -> 重庆市合川区云门街道云龙社区居民委员会(铁工厂还房建设项目)高压新装用电工程 | D6: =IF($W6="","",INDEX(发票统计!D$4:D$1003,$W6)&"") -> 2026.5.7庆文开票给新德润：云龙社区居民委员会 | E6: =IF($W6="","",INDEX(发票统计!E$4:E$1003,$W6)&"") -> 新德润 | F6: =IF($W6="","",INDEX(发票统计!F$4:F$1003,$W6)&"") -> 3%专票 | G6: =IF($W6="","",IF(INDEX(发票统计!G$4:G$1003,$W6)="","",INDEX(发票统计!G$4:G$1003,$W6))) | H6: =IF($W6="","",N(INDEX(发票统计!H$4:H$1003,$W6))) -> 43774.56 | I6: =IF($W6="","",N(INDEX(发票统计!I$4:I$1003,$W6))) -> 0 | J6: =IF($W6="","",N(INDEX(发票统计!J$4:J$1003,$W6))) -> 43774.56 | K6: =IF($W6="","",N(INDEX(发票统计!K$4:K$1003,$W6))) -> 43774.56 | L6: =IF($W6="","",SUM(J$4:J6)-SUM(K$4:K6)) -> 0 | M6: =IF($W6="","",N(INDEX(发票统计!M$4:M$1003,$W6))) -> 43774.56 | N6: =IF($W6="","",N(INDEX(发票统计!N$4:N$1003,$W6))) -> 0 | O6: =IF($W6="","",N(INDEX(发票统计!O$4:O$1003,$W6))) -> 0 | P6: =IF($W6="","",SUM(M$4:M6)-SUM(N$4:N6)-SUM(O$4:O6)) -> 43774.56 | Q6: =IF($W6="","",N(INDEX(发票统计!Q$4:Q$1003,$W6))) -> 0 | R6: =IF($W6="","",N(INDEX(发票统计!R$4:R$1003,$W6))) -> 0 | S6: =IF($W6="","",N(INDEX(发票统计!S$4:S$1003,$W6))) -> 0 | T6: =IF($W6="","",SUM(Q$4:Q6)-SUM(R$4:R6)-SUM(S$4:S6)) -> 0 | U6: =IF($W6="","",INDEX(发票统计!U$4:U$1003,$W6)&"") | W6: =IF($V$3="","",IFERROR(MATCH($V$3&"#"&ROWS(W$4:W6),发票统计!$W$4:$W$1003,0),"")) -> 5
A7: =IF($W7="","",INDEX(发票统计!A$4:A$1003,$W7)&"") -> 云龙社区 | B7: =IF($W7="","",INDEX(发票统计!B$4:B$1003,$W7)&"") -> 5月 | C7: =IF($W7="","",INDEX(发票统计!C$4:C$1003,$W7)&"") -> 重庆市合川区云门街道云龙社区居民委员会(铁工厂还房建设项目)高压新装用电工程 | D7: =IF($W7="","",INDEX(发票统计!D$4:D$1003,$W7)&"") -> 2026.5.13庆文公账收到新德润款项：云龙社区居民委员会 | E7: =IF($W7="","",INDEX(发票统计!E$4:E$1003,$W7)&"") -> 新德润 | F7: =IF($W7="","",INDEX(发票统计!F$4:F$1003,$W7)&"") | G7: =IF($W7="","",IF(INDEX(发票统计!G$4:G$1003,$W7)="","",INDEX(发票统计!G$4:G$1003,$W7))) | H7: =IF($W7="","",N(INDEX(发票统计!H$4:H$1003,$W7))) -> 0 | I7: =IF($W7="","",N(INDEX(发票统计!I$4:I$1003,$W7))) -> 0 | J7: =IF($W7="","",N(INDEX(发票统计!J$4:J$1003,$W7))) -> 0 | K7: =IF($W7="","",N(INDEX(发票统计!K$4:K$1003,$W7))) -> 0 | L7: =IF($W7="","",SUM(J$4:J7)-SUM(K$4:K7)) -> 0 | M7: =IF($W7="","",N(INDEX(发票统计!M$4:M$1003,$W7))) -> 0 | N7: =IF($W7="","",N(INDEX(发票统计!N$4:N$1003,$W7))) -> 0 | O7: =IF($W7="","",N(INDEX(发票统计!O$4:O$1003,$W7))) -> 43774.56 | P7: =IF($W7="","",SUM(M$4:M7)-SUM(N$4:N7)-SUM(O$4:O7)) -> 0 | Q7: =IF($W7="","",N(INDEX(发票统计!Q$4:Q$1003,$W7))) -> 0 | R7: =IF($W7="","",N(INDEX(发票统计!R$4:R$1003,$W7))) -> 0 | S7: =IF($W7="","",N(INDEX(发票统计!S$4:S$1003,$W7))) -> 0 | T7: =IF($W7="","",SUM(Q$4:Q7)-SUM(R$4:R7)-SUM(S$4:S7)) -> 0 | U7: =IF($W7="","",INDEX(发票统计!U$4:U$1003,$W7)&"") | W7: =IF($V$3="","",IFERROR(MATCH($V$3&"#"&ROWS(W$4:W7),发票统计!$W$4:$W$1003,0),"")) -> 6
A8: =IF($W8="","",INDEX(发票统计!A$4:A$1003,$W8)&"") | B8: =IF($W8="","",INDEX(发票统计!B$4:B$1003,$W8)&"") | C8: =IF($W8="","",INDEX(发票统计!C$4:C$1003,$W8)&"") | D8: =IF($W8="","",INDEX(发票统计!D$4:D$1003,$W8)&"") | E8: =IF($W8="","",INDEX(发票统计!E$4:E$1003,$W8)&"") | F8: =IF($W8="","",INDEX(发票统计!F$4:F$1003,$W8)&"") | G8: =IF($W8="","",IF(INDEX(发票统计!G$4:G$1003,$W8)="","",INDEX(发票统计!G$4:G$1003,$W8))) | H8: =IF($W8="","",N(INDEX(发票统计!H$4:H$1003,$W8))) | I8: =IF($W8="","",N(INDEX(发票统计!I$4:I$1003,$W8))) | J8: =IF($W8="","",N(INDEX(发票统计!J$4:J$1003,$W8))) | K8: =IF($W8="","",N(INDEX(发票统计!K$4:K$1003,$W8))) | L8: =IF($W8="","",SUM(J$4:J8)-SUM(K$4:K8)) | M8: =IF($W8="","",N(INDEX(发票统计!M$4:M$1003,$W8))) | N8: =IF($W8="","",N(INDEX(发票统计!N$4:N$1003,$W8))) | O8: =IF($W8="","",N(INDEX(发票统计!O$4:O$1003,$W8))) | P8: =IF($W8="","",SUM(M$4:M8)-SUM(N$4:N8)-SUM(O$4:O8)) | Q8: =IF($W8="","",N(INDEX(发票统计!Q$4:Q$1003,$W8))) | R8: =IF($W8="","",N(INDEX(发票统计!R$4:R$1003,$W8))) | S8: =IF($W8="","",N(INDEX(发票统计!S$4:S$1003,$W8))) | T8: =IF($W8="","",SUM(Q$4:Q8)-SUM(R$4:R8)-SUM(S$4:S8)) | U8: =IF($W8="","",INDEX(发票统计!U$4:U$1003,$W8)&"") | W8: =IF($V$3="","",IFERROR(MATCH($V$3&"#"&ROWS(W$4:W8),发票统计!$W$4:$W$1003,0),""))
