Workbook
Name 账户表: 基础资料!$A$4:$A$13
Name 账户期初: 基础资料!$A$4:$B$13
Name 客户表: 基础资料!$E$4:$E$253
Name 供应商表: 基础资料!$G$4:$G$153
Name 类别表: 基础资料!$I$4:$I$83
Name 类别归属: 基础资料!$I$4:$J$83
Name 归属表: 基础资料!$L$4:$L$23
Name 人员表: 基础资料!$N$4:$N$53
Name 项目类型表: 基础资料!$P$4:$P$15
Name 材料类别表: 基础资料!$R$4:$R$15
Name 材料归属: 基础资料!$R$4:$S$15
Name 工作类型表: 基础资料!$U$4:$U$17
Name 工作归属: 基础资料!$U$4:$V$17
Name 单位表: 基础资料!$X$4:$X$33
Name 往来单位表: 基础资料!$Z$4:$Z$403
Name 收支表: 基础资料!$AB$4:$AB$7
Name 外叫表: 基础资料!$AD$4:$AD$7
Name 项目名表: 项目台账!$B$4:$B$403

Sheet 使用说明
A1: 广告公司项目管理系统 · 使用说明
A2: 全公司一个文件。各人只管自己那张录入表，绿色标签的核算表全是公式，不用填也别删。
A3: 一、谁填哪一张表
A4: 岗位 | B4: 表名 | C4: 填什么
A5: 业务 / 下单 | B5: 项目台账 | C5: 接到单就开一行：项目名、客户、合同额、下单日期。做完了把「完工日期」填上——利润表就是按这个日期确认收入的。
A6: 设计 / 下单 | B6: 订单明细 | C6: 按件报价的客户（一次几十个标牌那种）在这里逐项登记，金额自动汇总进项目台账。整单包死的项目不用填这张。
A7: 采购 | B7: 采购单 | C7: 买的每一笔材料：供应商、项目、主材还是辅材、数量单价。金额自动算。
A8: 设计 / 制作 / 安装 | B8: 生产安装 | C8: 设计费、制作工时、安装工时、加班、外叫小工、吊车租车，按项目登记。
A9: 财务 / 出纳 | B9: 资金日记账 | C9: 五个账户（支付宝、平安银行、中信银行、微信1、微信2）所有进出都记这一张，右边自动结出该账户的即时余额。
A11: 二、三条规则，记住就不会乱
A12: 规则 1 | B12: 成本从哪来 | C12: 项目成本 = 采购单 + 生产安装 + 日记账里选了成本类别的支出。三个来源相加，所以同一笔钱只能记在其中一个地方。
A13: 规则 2 | B13: 别把一笔钱记两次 | C13: 登过采购单的料，出纳付钱时「费用类别」要选『付供应商货款』（它不计成本）；没登采购单的零星开支（配送费、运费、餐费），出纳直接选成本类别即可，不用再补采购单。
A14: 规则 3 | B14: 收入按完工确认 | C14: 利润表的营业收入 = 当月填了「完工日期」的项目合同额，成本也跟着那个月走，这样毛利才配得上。没完工的项目算「在制」，不进利润表。长期客户（比如东尼电子）建议按月建一个项目，月底填完工日期。
A15: 账户互转 | B15: 记两行 | C15: 从支付宝转到平安银行：支付宝记一行支出、平安银行记一行收入，两行的费用类别都选『账户互转』，它不进利润表。
A17: 三、颜色和符号
A18: 淡黄色格子 | B18: 请填写 | C18: 这是要人填的。
A19: 灰色格子 | B19: 公式自动算 | C19: 别手动改，改了就断了。整列往下都有公式，新增数据直接往下填即可。
A20: ※ 开头的红字 | B20: 有问题 | C20: 「核对」列会自己挑毛病：项目不在台账、类别没选、收支金额对不上、可能和采购单重复。看到红的就去改。
A22: 四、录入体检（活的，随时看这里）
A23: 检查项 | B23: 数值 | C23: 说明
A24: 日记账还没分类的笔数 | C24: =COUNTIF(资金日记账!$E:$E,"待分类") | D24: 这些笔的费用类别请挑一个，否则不进利润表
A25: 对应金额（收+支） | C25: =ROUND(SUMIF(资金日记账!$E:$E,"待分类",资金日记账!$J:$J)+SUMIF(资金日记账!$E:$E,"待分类",资金日记账!$K:$K),2)
A26: 成本类支出没填项目的笔数 | C26: =COUNTIF(资金日记账!$P:$P,"※成本类支出没填项目") | D26: 补上项目名，这些钱就能进对应项目的成本，利润表也就准了
A27: 对应金额 | C27: =ROUND(SUMIFS(资金日记账!$K:$K,资金日记账!$P:$P,"※成本类支出没填项目"),2)
A28: 还没填完工日期的项目数 | C28: =COUNTIFS(项目台账!$B$4:$B$403,"<>",项目台账!$J$4:$J$403,"") | D28: 这些项目的收入和成本都还没进利润表
A29: 这些项目的合同额 | C29: =ROUND(SUMIFS(项目台账!$M$4:$M$403,项目台账!$B$4:$B$403,"<>",项目台账!$J$4:$J$403,""),2)
A30: 日记账其它红字提示笔数 | C30: =COUNTIF(资金日记账!$P:$P,"※*")-COUNTIF(资金日记账!$P:$P,"※成本类支出没填项目") | D30: 去【资金日记账】最后一列看
A31: 采购单有红字提示的笔数 | C31: =COUNTIF(采购单!$N:$N,"※*")
A32: 生产安装有红字提示的笔数 | C32: =COUNTIF(生产安装!$M:$M,"※*")
A33: 项目台账有红字提示的条数 | C33: =COUNTIF(项目台账!$S:$S,"※*")
A34: 订单明细项目对不上的条数 | C34: =COUNTIF(订单明细!$J:$J,"※*")
A36: 五、一眼看家底
A37: 五个账户余额合计 | C37: =账户余额!$E$14
A38: 客户还欠我们（应收） | C38: =项目核算!$K$4
A39: 我们还欠供应商（应付） | C39: =供应商对账!$F$4
A40: 在制项目已投入成本 | C40: =利润表!$B$34
A41: 本年累计毛利 | C41: =利润表!$N$17
A42: 本年累计净利 | C42: =利润表!$N$27
A44: 六、这份表是怎么从旧表搬过来的
A45: · 旧文件 22 张表全部取过来了：940 行日记帐、17 张项目表、东尼电子和 Sheet1 两张制作清单、综合汇总表。
A46: · 17 张项目表的成本一分不差地拆进了【采购单】和【生产安装】，逐张核对过（详见 说明.md）。
A47: · 日记帐前半段（3~4 月）原来手工分过类，照搬；后半段是微信账单原样粘贴，只有摘要，
A48: 按关键字能认出来的自动归了类，认不出的一律标「待分类」，没有瞎猜。请按上面「体检」里的笔数去补。
A49: · 项目名做了归并：兰溪牛肉面=兰溪手擀面、津华钢铁=德清津华钢铁、巴比贝克=芭比贝克…… 完整对照表在 说明.md。
A50: · 「织里店-炳秀」这类写法拆成了 项目=织里店、往来单位=炳秀。
A51: · 完工日期只给「钱已经收齐」的项目补了，其余留空，请自己填——它直接决定利润表哪个月确认收入。

Sheet 基础资料
A1: 基础资料 · 所有下拉菜单的来源
A2: 要加客户、加供应商、加人，就在这里往下接着写，别留空行。改了这里，所有表的下拉菜单立刻跟着变。
A3: 资金账户 | B3: 期初余额 | E3: 客户名称 | G3: 供应商名称 | I3: 费用类别 | J3: 归属大类 | L3: 归属大类清单 | N3: 人员 | P3: 项目类型 | R3: 材料类别 | S3: 成本归属 | U3: 工作类型 | V3: 成本归属 | X3: 计量单位 | Z3: 往来单位(自动合并) | AB3: 收支方向 | AD3: 是否外叫
A4: 支付宝 | B4: 0 | E4: 南浔美食城 | G4: 炳秀 | I4: 项目收款 | J4: 收款-项目 | L4: 收款-项目 | N4: 杨德 | P4: 门头招牌 | R4: 主材 | S4: 成本-主材 | U4: 设计费 | V4: 成本-人工 | X4: 个 | Z4: =IF(ROW()-3<=COUNTA($E$4:$E$253),INDEX($E$4:$E$253,ROW()-3),IF(ROW()-3-COUNTA($E$4:$E$253)<=COUNTA($G$4:$G$153),INDEX($G$4:$G$153,ROW()-3-COUNTA($E$4:$E$253)),"")) | AB4: 收入 | AD4: 自有员工
A5: 平安银行 | B5: 0 | E5: 德清津华钢铁 | G5: 付久华 | I5: 预收定金 | J5: 收款-项目 | L5: 收入-其他 | N5: 凌宇 | P5: 发光字/灯箱 | R5: 外发加工 | S5: 成本-主材 | U5: 制作工时 | V5: 成本-人工 | X5: 套 | Z5: =IF(ROW()-3<=COUNTA($E$4:$E$253),INDEX($E$4:$E$253,ROW()-3),IF(ROW()-3-COUNTA($E$4:$E$253)<=COUNTA($G$4:$G$153),INDEX($G$4:$G$153,ROW()-3-COUNTA($E$4:$E$253)),"")) | AB5: 支出 | AD5: 外叫
A6: 中信银行 | B6: 0 | E6: 兰溪手擀面 | G6: 货拉拉 | I6: 退还客户款 | J6: 收款-项目 | L6: 成本-主材 | N6: 章凡 | P6: 亮化工程 | R6: 辅材 | S6: 成本-辅材 | U6: 安装工时 | V6: 成本-人工 | X6: 块 | Z6: =IF(ROW()-3<=COUNTA($E$4:$E$253),INDEX($E$4:$E$253,ROW()-3),IF(ROW()-3-COUNTA($E$4:$E$253)<=COUNTA($G$4:$G$153),INDEX($G$4:$G$153,ROW()-3-COUNTA($E$4:$E$253)),""))
A7: 微信1 | B7: 0 | E7: 莫盾服饰 | G7: 拼多多 | I7: 零星物料销售 | J7: 收入-其他 | L7: 成本-辅材 | N7: 徐可欣 | P7: 室内标识 | R7: 五金耗材 | S7: 成本-辅材 | U7: 加班费 | V7: 成本-人工 | X7: 张 | Z7: =IF(ROW()-3<=COUNTA($E$4:$E$253),INDEX($E$4:$E$253,ROW()-3),IF(ROW()-3-COUNTA($E$4:$E$253)<=COUNTA($G$4:$G$153),INDEX($G$4:$G$153,ROW()-3-COUNTA($E$4:$E$253)),""))
A8: 微信2 | B8: 0 | E8: 君澜服饰 | G8: 顺丰速运 | I8: 设计费收入 | J8: 收入-其他 | L8: 成本-人工 | N8: 老姚 | P8: 广告物料 | R8: 其他材料 | S8: 成本-其他 | U8: 外叫小工 | V8: 成本-人工 | X8: 米 | Z8: =IF(ROW()-3<=COUNTA($E$4:$E$253),INDEX($E$4:$E$253,ROW()-3),IF(ROW()-3-COUNTA($E$4:$E$253)<=COUNTA($G$4:$G$153),INDEX($G$4:$G$153,ROW()-3-COUNTA($E$4:$E$253)),""))
A9: 现金 | B9: 0 | E9: 芭比贝克 | G9: 盛世大瑞 | I9: 其他收入 | J9: 收入-其他 | L9: 成本-车运 | N9: 小章 | P9: 车贴喷绘 | U9: 其他人工 | V9: 成本-人工 | X9: 平方 | Z9: =IF(ROW()-3<=COUNTA($E$4:$E$253),INDEX($E$4:$E$253,ROW()-3),IF(ROW()-3-COUNTA($E$4:$E$253)<=COUNTA($G$4:$G$153),INDEX($G$4:$G$153,ROW()-3-COUNTA($E$4:$E$253)),""))
E10: 铁柱烧烤店 | G10: 淘宝 | I10: 主材采购 | J10: 成本-主材 | L10: 成本-其他 | N10: 小姜 | P10: 维修保养 | U10: 吊车/租车 | V10: 成本-车运 | X10: 根 | Z10: =IF(ROW()-3<=COUNTA($E$4:$E$253),INDEX($E$4:$E$253,ROW()-3),IF(ROW()-3-COUNTA($E$4:$E$253)<=COUNTA($G$4:$G$153),INDEX($G$4:$G$153,ROW()-3-COUNTA($E$4:$E$253)),""))
E11: 钟管熟食店 | G11: 安吉鑫龙 | I11: 外发加工 | J11: 成本-主材 | L11: 费用-管理 | P11: 其他 | U11: 运费/搬运 | V11: 成本-车运 | X11: 条 | Z11: =IF(ROW()-3<=COUNTA($E$4:$E$253),INDEX($E$4:$E$253,ROW()-3),IF(ROW()-3-COUNTA($E$4:$E$253)<=COUNTA($G$4:$G$153),INDEX($G$4:$G$153,ROW()-3-COUNTA($E$4:$E$253)),""))
E12: 螺有名灯箱门头 | G12: 章凡 | I12: 辅材采购 | J12: 成本-辅材 | L12: 费用-销售 | X12: 箱 | Z12: =IF(ROW()-3<=COUNTA($E$4:$E$253),INDEX($E$4:$E$253,ROW()-3),IF(ROW()-3-COUNTA($E$4:$E$253)<=COUNTA($G$4:$G$153),INDEX($G$4:$G$153,ROW()-3-COUNTA($E$4:$E$253)),""))
E13: 汕味杏花室内项目 | G13: 浩智蚀刻标识标牌 | I13: 网购材料耗材 | J13: 成本-辅材 | L13: 费用-财务 | X13: 桶 | Z13: =IF(ROW()-3<=COUNTA($E$4:$E$253),INDEX($E$4:$E$253,ROW()-3),IF(ROW()-3-COUNTA($E$4:$E$253)<=COUNTA($G$4:$G$153),INDEX($G$4:$G$153,ROW()-3-COUNTA($E$4:$E$253)),""))
E14: 双林面馆-滨河路 | G14: 天津货拉拉科技有限 | I14: 五金耗材 | J14: 成本-辅材 | L14: 其他-营业外收入 | X14: 支 | Z14: =IF(ROW()-3<=COUNTA($E$4:$E$253),INDEX($E$4:$E$253,ROW()-3),IF(ROW()-3-COUNTA($E$4:$E$253)<=COUNTA($G$4:$G$153),INDEX($G$4:$G$153,ROW()-3-COUNTA($E$4:$E$253)),""))
E15: 梓灿软装 | G15: 一利钢材 | I15: 设计费 | J15: 成本-人工 | L15: 其他-营业外支出 | X15: 卷 | Z15: =IF(ROW()-3<=COUNTA($E$4:$E$253),INDEX($E$4:$E$253,ROW()-3),IF(ROW()-3-COUNTA($E$4:$E$253)<=COUNTA($G$4:$G$153),INDEX($G$4:$G$153,ROW()-3-COUNTA($E$4:$E$253)),""))
E16: 长颈鹿庄园 | G16: 小王加工厂 | I16: 制作工资 | J16: 成本-人工 | L16: 往来-货款 | X16: 工 | Z16: =IF(ROW()-3<=COUNTA($E$4:$E$253),INDEX($E$4:$E$253,ROW()-3),IF(ROW()-3-COUNTA($E$4:$E$253)<=COUNTA($G$4:$G$153),INDEX($G$4:$G$153,ROW()-3-COUNTA($E$4:$E$253)),""))
E17: 国智校服 | G17: 甄铭 | I17: 安装工资 | J17: 成本-人工 | L17: 往来-借贷 | X17: 天 | Z17: =IF(ROW()-3<=COUNTA($E$4:$E$253),INDEX($E$4:$E$253,ROW()-3),IF(ROW()-3-COUNTA($E$4:$E$253)<=COUNTA($G$4:$G$153),INDEX($G$4:$G$153,ROW()-3-COUNTA($E$4:$E$253)),""))
E18: 民盛生鲜店 | G18: 小王 | I18: 加班费 | J18: 成本-人工 | L18: 内部转账 | X18: 次 | Z18: =IF(ROW()-3<=COUNTA($E$4:$E$253),INDEX($E$4:$E$253,ROW()-3),IF(ROW()-3-COUNTA($E$4:$E$253)<=COUNTA($G$4:$G$153),INDEX($G$4:$G$153,ROW()-3-COUNTA($E$4:$E$253)),""))
E19: 饺子店 | G19: 水尚 | I19: 外叫小工 | J19: 成本-人工 | X19: 趟 | Z19: =IF(ROW()-3<=COUNTA($E$4:$E$253),INDEX($E$4:$E$253,ROW()-3),IF(ROW()-3-COUNTA($E$4:$E$253)<=COUNTA($G$4:$G$153),INDEX($G$4:$G$153,ROW()-3-COUNTA($E$4:$E$253)),""))
E20: 睿芯行 | G20: 杭州杜邦软膜 | I20: 运费/快递费 | J20: 成本-车运 | X20: 项 | Z20: =IF(ROW()-3<=COUNTA($E$4:$E$253),INDEX($E$4:$E$253,ROW()-3),IF(ROW()-3-COUNTA($E$4:$E$253)<=COUNTA($G$4:$G$153),INDEX($G$4:$G$153,ROW()-3-COUNTA($E$4:$E$253)),""))
E21: 东尼新能源 | G21: 浙江孚泰 | I21: 车费/油费/过路费 | J21: 成本-车运 | X21: 批 | Z21: =IF(ROW()-3<=COUNTA($E$4:$E$253),INDEX($E$4:$E$253,ROW()-3),IF(ROW()-3-COUNTA($E$4:$E$253)<=COUNTA($G$4:$G$153),INDEX($G$4:$G$153,ROW()-3-COUNTA($E$4:$E$253)),""))
E22: 盛昊篷车 | G22: 吉祥铝板吴玲芳 | I22: 吊车/租车费 | J22: 成本-车运 | X22: 台 | Z22: =IF(ROW()-3<=COUNTA($E$4:$E$253),INDEX($E$4:$E$253,ROW()-3),IF(ROW()-3-COUNTA($E$4:$E$253)<=COUNTA($G$4:$G$153),INDEX($G$4:$G$153,ROW()-3-COUNTA($E$4:$E$253)),""))
E23: 付炳秀配送 | G23: 上达铝板 | I23: 项目餐费补助 | J23: 成本-其他 | X23: 组 | Z23: =IF(ROW()-3<=COUNTA($E$4:$E$253),INDEX($E$4:$E$253,ROW()-3),IF(ROW()-3-COUNTA($E$4:$E$253)<=COUNTA($G$4:$G$153),INDEX($G$4:$G$153,ROW()-3-COUNTA($E$4:$E$253)),""))
E24: 万达kvv | G24: 北京京邦达贸易有限 | I24: 其他直接费用 | J24: 成本-其他 | X24: m² | Z24: =IF(ROW()-3<=COUNTA($E$4:$E$253),INDEX($E$4:$E$253,ROW()-3),IF(ROW()-3-COUNTA($E$4:$E$253)<=COUNTA($G$4:$G$153),INDEX($G$4:$G$153,ROW()-3-COUNTA($E$4:$E$253)),""))
E25: 织里店 | G25: 外叫租赁 | I25: 员工工资 | J25: 费用-管理 | X25: 千克 | Z25: =IF(ROW()-3<=COUNTA($E$4:$E$253),INDEX($E$4:$E$253,ROW()-3),IF(ROW()-3-COUNTA($E$4:$E$253)<=COUNTA($G$4:$G$153),INDEX($G$4:$G$153,ROW()-3-COUNTA($E$4:$E$253)),""))
E26: 高恒荣熟食店 | G26: 匠心 | I26: 社保公积金 | J26: 费用-管理 | Z26: =IF(ROW()-3<=COUNTA($E$4:$E$253),INDEX($E$4:$E$253,ROW()-3),IF(ROW()-3-COUNTA($E$4:$E$253)<=COUNTA($G$4:$G$153),INDEX($G$4:$G$153,ROW()-3-COUNTA($E$4:$E$253)),""))
E27: 卓越桌球 | G27: 杭州水尚装饰 | I27: 房租水电 | J27: 费用-管理 | Z27: =IF(ROW()-3<=COUNTA($E$4:$E$253),INDEX($E$4:$E$253,ROW()-3),IF(ROW()-3-COUNTA($E$4:$E$253)<=COUNTA($G$4:$G$153),INDEX($G$4:$G$153,ROW()-3-COUNTA($E$4:$E$253)),""))
E28: 东尼电子 | G28: 点工 | I28: 办公用品 | J28: 费用-管理 | Z28: =IF(ROW()-3<=COUNTA($E$4:$E$253),INDEX($E$4:$E$253,ROW()-3),IF(ROW()-3-COUNTA($E$4:$E$253)<=COUNTA($G$4:$G$153),INDEX($G$4:$G$153,ROW()-3-COUNTA($E$4:$E$253)),""))
E29: 犇腾牛排 | G29: 灯箱哥 | I29: 通讯费 | J29: 费用-管理 | Z29: =IF(ROW()-3<=COUNTA($E$4:$E$253),INDEX($E$4:$E$253,ROW()-3),IF(ROW()-3-COUNTA($E$4:$E$253)<=COUNTA($G$4:$G$153),INDEX($G$4:$G$153,ROW()-3-COUNTA($E$4:$E$253)),""))
E30: 校服基地 | G30: 1.71*5.61 | I30: 差旅费 | J30: 费用-管理 | Z30: =IF(ROW()-3<=COUNTA($E$4:$E$253),INDEX($E$4:$E$253,ROW()-3),IF(ROW()-3-COUNTA($E$4:$E$253)<=COUNTA($G$4:$G$153),INDEX($G$4:$G$153,ROW()-3-COUNTA($E$4:$E$253)),""))
E31: 德清钟管菜市场 | G31: 武帝 | I31: 业务招待/餐费 | J31: 费用-管理 | Z31: =IF(ROW()-3<=COUNTA($E$4:$E$253),INDEX($E$4:$E$253,ROW()-3),IF(ROW()-3-COUNTA($E$4:$E$253)<=COUNTA($G$4:$G$153),INDEX($G$4:$G$153,ROW()-3-COUNTA($E$4:$E$253)),""))
E32: 中交 | G32: 泰发五金 | I32: 团建费 | J32: 费用-管理 | Z32: =IF(ROW()-3<=COUNTA($E$4:$E$253),INDEX($E$4:$E$253,ROW()-3),IF(ROW()-3-COUNTA($E$4:$E$253)<=COUNTA($G$4:$G$153),INDEX($G$4:$G$153,ROW()-3-COUNTA($E$4:$E$253)),""))
E33: vip宠物乐园 | G33: 周学峰 | I33: 车辆费用(非项目) | J33: 费用-管理 | Z33: =IF(ROW()-3<=COUNTA($E$4:$E$253),INDEX($E$4:$E$253,ROW()-3),IF(ROW()-3-COUNTA($E$4:$E$253)<=COUNTA($G$4:$G$153),INDEX($G$4:$G$153,ROW()-3-COUNTA($E$4:$E$253)),""))
E34: 安吉车贴项目 | G34: 顺丰快递费 | I34: 税金 | J34: 费用-管理 | Z34: =IF(ROW()-3<=COUNTA($E$4:$E$253),INDEX($E$4:$E$253,ROW()-3),IF(ROW()-3-COUNTA($E$4:$E$253)<=COUNTA($G$4:$G$153),INDEX($G$4:$G$153,ROW()-3-COUNTA($E$4:$E$253)),""))
E35: 最爱潘多拉ktv | G35: 吴玲芳 | I35: 其他管理费用 | J35: 费用-管理 | Z35: =IF(ROW()-3<=COUNTA($E$4:$E$253),INDEX($E$4:$E$253,ROW()-3),IF(ROW()-3-COUNTA($E$4:$E$253)<=COUNTA($G$4:$G$153),INDEX($G$4:$G$153,ROW()-3-COUNTA($E$4:$E$253)),""))
E36: 小谷姐姐 | G36: 津华钢铁张总 | I36: 广告推广 | J36: 费用-销售 | Z36: =IF(ROW()-3<=COUNTA($E$4:$E$253),INDEX($E$4:$E$253,ROW()-3),IF(ROW()-3-COUNTA($E$4:$E$253)<=COUNTA($G$4:$G$153),INDEX($G$4:$G$153,ROW()-3-COUNTA($E$4:$E$253)),""))
E37: 每甜 | G37: 220V不防水区块65 | I37: 平台服务费 | J37: 费用-销售 | Z37: =IF(ROW()-3<=COUNTA($E$4:$E$253),INDEX($E$4:$E$253,ROW()-3),IF(ROW()-3-COUNTA($E$4:$E$253)<=COUNTA($G$4:$G$153),INDEX($G$4:$G$153,ROW()-3-COUNTA($E$4:$E$253)),""))
... E54: 凤姐早餐店 | G54: 货拉拉运费 | I54: 营业外支出 | J54: 其他-营业外支出 | Z54: =IF(ROW()-3<=COUNTA($E$4:$E$253),INDEX($E$4:$E$253,ROW()-3),IF(ROW()-3-COUNTA($E$4:$E$253)<=COUNTA($G$4:$G$153),INDEX($G$4:$G$153,ROW()-3-COUNTA($E$4:$E$253)),""))
E55: 焰燃烧烤 | G55: 温州五金 | I55: 待分类 | Z55: =IF(ROW()-3<=COUNTA($E$4:$E$253),INDEX($E$4:$E$253,ROW()-3),IF(ROW()-3-COUNTA($E$4:$E$253)<=COUNTA($G$4:$G$153),INDEX($G$4:$G$153,ROW()-3-COUNTA($E$4:$E$253)),""))
E56: 湖岸漫食 | G56: 京东货拉拉运费 | Z56: =IF(ROW()-3<=COUNTA($E$4:$E$253),INDEX($E$4:$E$253,ROW()-3),IF(ROW()-3-COUNTA($E$4:$E$253)<=COUNTA($G$4:$G$153),INDEX($G$4:$G$153,ROW()-3-COUNTA($E$4:$E$253)),""))
E57: 万达荣泰 | G57: 铝板运费 | Z57: =IF(ROW()-3<=COUNTA($E$4:$E$253),INDEX($E$4:$E$253,ROW()-3),IF(ROW()-3-COUNTA($E$4:$E$253)<=COUNTA($G$4:$G$153),INDEX($G$4:$G$153,ROW()-3-COUNTA($E$4:$E$253)),""))
E58: 玖味卤味 | G58: 万马不锈钢牌 | Z58: =IF(ROW()-3<=COUNTA($E$4:$E$253),INDEX($E$4:$E$253,ROW()-3),IF(ROW()-3-COUNTA($E$4:$E$253)<=COUNTA($G$4:$G$153),INDEX($G$4:$G$153,ROW()-3-COUNTA($E$4:$E$253)),""))
E59: 焰燃烧烤店 | G59: 永康五金百货 | Z59: =IF(ROW()-3<=COUNTA($E$4:$E$253),INDEX($E$4:$E$253,ROW()-3),IF(ROW()-3-COUNTA($E$4:$E$253)<=COUNTA($G$4:$G$153),INDEX($G$4:$G$153,ROW()-3-COUNTA($E$4:$E$253)),""))
E60: 东北烧烤大转盘店 | G60: 杭州炳秀德清配送王赛辉 | Z60: =IF(ROW()-3<=COUNTA($E$4:$E$253),INDEX($E$4:$E$253,ROW()-3),IF(ROW()-3-COUNTA($E$4:$E$253)<=COUNTA($G$4:$G$153),INDEX($G$4:$G$153,ROW()-3-COUNTA($E$4:$E$253)),""))
E61: 创艺装饰 | Z61: =IF(ROW()-3<=COUNTA($E$4:$E$253),INDEX($E$4:$E$253,ROW()-3),IF(ROW()-3-COUNTA($E$4:$E$253)<=COUNTA($G$4:$G$153),INDEX($G$4:$G$153,ROW()-3-COUNTA($E$4:$E$253)),""))
E62: 坚蛋健身 | Z62: =IF(ROW()-3<=COUNTA($E$4:$E$253),INDEX($E$4:$E$253,ROW()-3),IF(ROW()-3-COUNTA($E$4:$E$253)<=COUNTA($G$4:$G$153),INDEX($G$4:$G$153,ROW()-3-COUNTA($E$4:$E$253)),""))
E63: 许多多超市 | Z63: =IF(ROW()-3<=COUNTA($E$4:$E$253),INDEX($E$4:$E$253,ROW()-3),IF(ROW()-3-COUNTA($E$4:$E$253)<=COUNTA($G$4:$G$153),INDEX($G$4:$G$153,ROW()-3-COUNTA($E$4:$E$253)),""))
E64: 圣薇依儿 | Z64: =IF(ROW()-3<=COUNTA($E$4:$E$253),INDEX($E$4:$E$253,ROW()-3),IF(ROW()-3-COUNTA($E$4:$E$253)<=COUNTA($G$4:$G$153),INDEX($G$4:$G$153,ROW()-3-COUNTA($E$4:$E$253)),""))
E65: 浙江戴纳 | Z65: =IF(ROW()-3<=COUNTA($E$4:$E$253),INDEX($E$4:$E$253,ROW()-3),IF(ROW()-3-COUNTA($E$4:$E$253)<=COUNTA($G$4:$G$153),INDEX($G$4:$G$153,ROW()-3-COUNTA($E$4:$E$253)),""))
E66: 纳载智能 | Z66: =IF(ROW()-3<=COUNTA($E$4:$E$253),INDEX($E$4:$E$253,ROW()-3),IF(ROW()-3-COUNTA($E$4:$E$253)<=COUNTA($G$4:$G$153),INDEX($G$4:$G$153,ROW()-3-COUNTA($E$4:$E$253)),""))
E67: 瑞佳装饰 | Z67: =IF(ROW()-3<=COUNTA($E$4:$E$253),INDEX($E$4:$E$253,ROW()-3),IF(ROW()-3-COUNTA($E$4:$E$253)<=COUNTA($G$4:$G$153),INDEX($G$4:$G$153,ROW()-3-COUNTA($E$4:$E$253)),""))
E68: 启航烟酒 | Z68: =IF(ROW()-3<=COUNTA($E$4:$E$253),INDEX($E$4:$E$253,ROW()-3),IF(ROW()-3-COUNTA($E$4:$E$253)<=COUNTA($G$4:$G$153),INDEX($G$4:$G$153,ROW()-3-COUNTA($E$4:$E$253)),""))
E69: 全球购 | Z69: =IF(ROW()-3<=COUNTA($E$4:$E$253),INDEX($E$4:$E$253,ROW()-3),IF(ROW()-3-COUNTA($E$4:$E$253)<=COUNTA($G$4:$G$153),INDEX($G$4:$G$153,ROW()-3-COUNTA($E$4:$E$253)),""))
E70: 安格斯烤串 | Z70: =IF(ROW()-3<=COUNTA($E$4:$E$253),INDEX($E$4:$E$253,ROW()-3),IF(ROW()-3-COUNTA($E$4:$E$253)<=COUNTA($G$4:$G$153),INDEX($G$4:$G$153,ROW()-3-COUNTA($E$4:$E$253)),""))
E71: 行一文化 | Z71: =IF(ROW()-3<=COUNTA($E$4:$E$253),INDEX($E$4:$E$253,ROW()-3),IF(ROW()-3-COUNTA($E$4:$E$253)<=COUNTA($G$4:$G$153),INDEX($G$4:$G$153,ROW()-3-COUNTA($E$4:$E$253)),""))
E72: 安格斯牛肉串 | Z72: =IF(ROW()-3<=COUNTA($E$4:$E$253),INDEX($E$4:$E$253,ROW()-3),IF(ROW()-3-COUNTA($E$4:$E$253)<=COUNTA($G$4:$G$153),INDEX($G$4:$G$153,ROW()-3-COUNTA($E$4:$E$253)),""))
... E87: nook咖啡店 | Z87: =IF(ROW()-3<=COUNTA($E$4:$E$253),INDEX($E$4:$E$253,ROW()-3),IF(ROW()-3-COUNTA($E$4:$E$253)<=COUNTA($G$4:$G$153),INDEX($G$4:$G$153,ROW()-3-COUNTA($E$4:$E$253)),""))
Z88: =IF(ROW()-3<=COUNTA($E$4:$E$253),INDEX($E$4:$E$253,ROW()-3),IF(ROW()-3-COUNTA($E$4:$E$253)<=COUNTA($G$4:$G$153),INDEX($G$4:$G$153,ROW()-3-COUNTA($E$4:$E$253)),""))
Z89: =IF(ROW()-3<=COUNTA($E$4:$E$253),INDEX($E$4:$E$253,ROW()-3),IF(ROW()-3-COUNTA($E$4:$E$253)<=COUNTA($G$4:$G$153),INDEX($G$4:$G$153,ROW()-3-COUNTA($E$4:$E$253)),""))
Z90: =IF(ROW()-3<=COUNTA($E$4:$E$253),INDEX($E$4:$E$253,ROW()-3),IF(ROW()-3-COUNTA($E$4:$E$253)<=COUNTA($G$4:$G$153),INDEX($G$4:$G$153,ROW()-3-COUNTA($E$4:$E$253)),""))
Z91: =IF(ROW()-3<=COUNTA($E$4:$E$253),INDEX($E$4:$E$253,ROW()-3),IF(ROW()-3-COUNTA($E$4:$E$253)<=COUNTA($G$4:$G$153),INDEX($G$4:$G$153,ROW()-3-COUNTA($E$4:$E$253)),""))
Z92: =IF(ROW()-3<=COUNTA($E$4:$E$253),INDEX($E$4:$E$253,ROW()-3),IF(ROW()-3-COUNTA($E$4:$E$253)<=COUNTA($G$4:$G$153),INDEX($G$4:$G$153,ROW()-3-COUNTA($E$4:$E$253)),""))
Z93: =IF(ROW()-3<=COUNTA($E$4:$E$253),INDEX($E$4:$E$253,ROW()-3),IF(ROW()-3-COUNTA($E$4:$E$253)<=COUNTA($G$4:$G$153),INDEX($G$4:$G$153,ROW()-3-COUNTA($E$4:$E$253)),""))
Z94: =IF(ROW()-3<=COUNTA($E$4:$E$253),INDEX($E$4:$E$253,ROW()-3),IF(ROW()-3-COUNTA($E$4:$E$253)<=COUNTA($G$4:$G$153),INDEX($G$4:$G$153,ROW()-3-COUNTA($E$4:$E$253)),""))
Z95: =IF(ROW()-3<=COUNTA($E$4:$E$253),INDEX($E$4:$E$253,ROW()-3),IF(ROW()-3-COUNTA($E$4:$E$253)<=COUNTA($G$4:$G$153),INDEX($G$4:$G$153,ROW()-3-COUNTA($E$4:$E$253)),""))
Z96: =IF(ROW()-3<=COUNTA($E$4:$E$253),INDEX($E$4:$E$253,ROW()-3),IF(ROW()-3-COUNTA($E$4:$E$253)<=COUNTA($G$4:$G$153),INDEX($G$4:$G$153,ROW()-3-COUNTA($E$4:$E$253)),""))
Z97: =IF(ROW()-3<=COUNTA($E$4:$E$253),INDEX($E$4:$E$253,ROW()-3),IF(ROW()-3-COUNTA($E$4:$E$253)<=COUNTA($G$4:$G$153),INDEX($G$4:$G$153,ROW()-3-COUNTA($E$4:$E$253)),""))
Z98: =IF(ROW()-3<=COUNTA($E$4:$E$253),INDEX($E$4:$E$253,ROW()-3),IF(ROW()-3-COUNTA($E$4:$E$253)<=COUNTA($G$4:$G$153),INDEX($G$4:$G$153,ROW()-3-COUNTA($E$4:$E$253)),""))
Z99: =IF(ROW()-3<=COUNTA($E$4:$E$253),INDEX($E$4:$E$253,ROW()-3),IF(ROW()-3-COUNTA($E$4:$E$253)<=COUNTA($G$4:$G$153),INDEX($G$4:$G$153,ROW()-3-COUNTA($E$4:$E$253)),""))
... Z403: =IF(ROW()-3<=COUNTA($E$4:$E$253),INDEX($E$4:$E$253,ROW()-3),IF(ROW()-3-COUNTA($E$4:$E$253)<=COUNTA($G$4:$G$153),INDEX($G$4:$G$153,ROW()-3-COUNTA($E$4:$E$253)),""))

Sheet 项目台账
A1: 项目台账 · 业务 / 下单岗位填
A2: 接到单就开一行。做完了一定要填「完工日期」——利润表就是按这个日期把收入和成本算进当月的。
A3: 项目编号 | B3: 项目名称 ★ | C3: 客户名称 ★ | D3: 项目类型 | E3: 负责人 | F3: 下单日期 ★ | G3: 设计完成 | H3: 制作完成 | I3: 安装完成 | J3: 完工日期 ★ (确认收入) | K3: 合同额 (整单包死) | L3: 订单明细额 (自动) | M3: 合同总额 | N3: 期初已收 (导入用) | O3: 已收款 | P3: 未收款 | Q3: 状态 | R3: 备注 | S3: 核对
A4: =IF($B4="","","P"&TEXT(ROW()-3,"000")) | B4: 南浔美食城 | C4: 南浔美食城 | D4: 门头招牌 | F4: 46043 | K4: 42294 | L4: =IF($B4="","",ROUND(SUMIF(订单明细!$C:$C,$B4,订单明细!$I:$I),2)) | M4: =IF($B4="","",ROUND(N($K4)+N($L4),2)) | N4: 20000 | O4: =IF($B4="","",ROUND(N($N4)+SUMIFS(资金日记账!$J$4:$J$2503,资金日记账!$G$4:$G$2503,$B4,资金日记账!$F$4:$F$2503,"收款-项目")-SUMIFS(资金日记账!$K$4:$K$2503,资金日记账!$G$4:$G$2503,$B4,资金日记账!$F$4:$F$2503,"收款-项目"),2)) | P4: =IF($B4="","",ROUND($M4-$O4,2)) | Q4: =IF($B4="","",IF(AND($J4<>"",ROUND($P4,2)<=0),"已完工·已结清",IF($J4<>"","已完工·还有尾款",IF($I4<>"","已安装",IF($H4<>"","已制作",IF($G4<>"","设计完成","已下单")))))) | R4: 来源：1-南浔美食城 | S4: =IF($B4="","",IF(COUNTIF($B$4:$B$403,$B4)>1,"※项目名重复了",IF(AND($C4<>"",ISNA(MATCH($C4,客户表,0))),"※客户不在基础资料里",IF(AND($J4<>"",$F4<>"",$J4<$F4),"※完工日期早于下单日期",""))))
A5: =IF($B5="","","P"&TEXT(ROW()-3,"000")) | B5: 德清津华钢铁 | C5: 德清津华钢铁 | D5: 门头招牌 | F5: 46060 | J5: 46082 | K5: 11000 | L5: =IF($B5="","",ROUND(SUMIF(订单明细!$C:$C,$B5,订单明细!$I:$I),2)) | M5: =IF($B5="","",ROUND(N($K5)+N($L5),2)) | N5: 11000 | O5: =IF($B5="","",ROUND(N($N5)+SUMIFS(资金日记账!$J$4:$J$2503,资金日记账!$G$4:$G$2503,$B5,资金日记账!$F$4:$F$2503,"收款-项目")-SUMIFS(资金日记账!$K$4:$K$2503,资金日记账!$G$4:$G$2503,$B5,资金日记账!$F$4:$F$2503,"收款-项目"),2)) | P5: =IF($B5="","",ROUND($M5-$O5,2)) | Q5: =IF($B5="","",IF(AND($J5<>"",ROUND($P5,2)<=0),"已完工·已结清",IF($J5<>"","已完工·还有尾款",IF($I5<>"","已安装",IF($H5<>"","已制作",IF($G5<>"","设计完成","已下单")))))) | R5: 来源：2-德清津华钢铁 | S5: =IF($B5="","",IF(COUNTIF($B$4:$B$403,$B5)>1,"※项目名重复了",IF(AND($C5<>"",ISNA(MATCH($C5,客户表,0))),"※客户不在基础资料里",IF(AND($J5<>"",$F5<>"",$J5<$F5),"※完工日期早于下单日期",""))))
A6: =IF($B6="","","P"&TEXT(ROW()-3,"000")) | B6: 兰溪手擀面 | C6: 兰溪手擀面 | D6: 门头招牌 | F6: 46083 | J6: 46083 | K6: 1400 | L6: =IF($B6="","",ROUND(SUMIF(订单明细!$C:$C,$B6,订单明细!$I:$I),2)) | M6: =IF($B6="","",ROUND(N($K6)+N($L6),2)) | O6: =IF($B6="","",ROUND(N($N6)+SUMIFS(资金日记账!$J$4:$J$2503,资金日记账!$G$4:$G$2503,$B6,资金日记账!$F$4:$F$2503,"收款-项目")-SUMIFS(资金日记账!$K$4:$K$2503,资金日记账!$G$4:$G$2503,$B6,资金日记账!$F$4:$F$2503,"收款-项目"),2)) | P6: =IF($B6="","",ROUND($M6-$O6,2)) | Q6: =IF($B6="","",IF(AND($J6<>"",ROUND($P6,2)<=0),"已完工·已结清",IF($J6<>"","已完工·还有尾款",IF($I6<>"","已安装",IF($H6<>"","已制作",IF($G6<>"","设计完成","已下单")))))) | R6: 来源：3-兰溪手擀面 | S6: =IF($B6="","",IF(COUNTIF($B$4:$B$403,$B6)>1,"※项目名重复了",IF(AND($C6<>"",ISNA(MATCH($C6,客户表,0))),"※客户不在基础资料里",IF(AND($J6<>"",$F6<>"",$J6<$F6),"※完工日期早于下单日期",""))))
A7: =IF($B7="","","P"&TEXT(ROW()-3,"000")) | B7: 莫盾服饰 | C7: 莫盾服饰 | D7: 门头招牌 | K7: 12623 | L7: =IF($B7="","",ROUND(SUMIF(订单明细!$C:$C,$B7,订单明细!$I:$I),2)) | M7: =IF($B7="","",ROUND(N($K7)+N($L7),2)) | O7: =IF($B7="","",ROUND(N($N7)+SUMIFS(资金日记账!$J$4:$J$2503,资金日记账!$G$4:$G$2503,$B7,资金日记账!$F$4:$F$2503,"收款-项目")-SUMIFS(资金日记账!$K$4:$K$2503,资金日记账!$G$4:$G$2503,$B7,资金日记账!$F$4:$F$2503,"收款-项目"),2)) | P7: =IF($B7="","",ROUND($M7-$O7,2)) | Q7: =IF($B7="","",IF(AND($J7<>"",ROUND($P7,2)<=0),"已完工·已结清",IF($J7<>"","已完工·还有尾款",IF($I7<>"","已安装",IF($H7<>"","已制作",IF($G7<>"","设计完成","已下单")))))) | R7: 来源：4-莫盾服饰 | S7: =IF($B7="","",IF(COUNTIF($B$4:$B$403,$B7)>1,"※项目名重复了",IF(AND($C7<>"",ISNA(MATCH($C7,客户表,0))),"※客户不在基础资料里",IF(AND($J7<>"",$F7<>"",$J7<$F7),"※完工日期早于下单日期",""))))
A8: =IF($B8="","","P"&TEXT(ROW()-3,"000")) | B8: 君澜服饰 | C8: 君澜服饰 | D8: 门头招牌 | F8: 46106 | K8: 9350 | L8: =IF($B8="","",ROUND(SUMIF(订单明细!$C:$C,$B8,订单明细!$I:$I),2)) | M8: =IF($B8="","",ROUND(N($K8)+N($L8),2)) | O8: =IF($B8="","",ROUND(N($N8)+SUMIFS(资金日记账!$J$4:$J$2503,资金日记账!$G$4:$G$2503,$B8,资金日记账!$F$4:$F$2503,"收款-项目")-SUMIFS(资金日记账!$K$4:$K$2503,资金日记账!$G$4:$G$2503,$B8,资金日记账!$F$4:$F$2503,"收款-项目"),2)) | P8: =IF($B8="","",ROUND($M8-$O8,2)) | Q8: =IF($B8="","",IF(AND($J8<>"",ROUND($P8,2)<=0),"已完工·已结清",IF($J8<>"","已完工·还有尾款",IF($I8<>"","已安装",IF($H8<>"","已制作",IF($G8<>"","设计完成","已下单")))))) | R8: 来源：5-君澜服饰 | S8: =IF($B8="","",IF(COUNTIF($B$4:$B$403,$B8)>1,"※项目名重复了",IF(AND($C8<>"",ISNA(MATCH($C8,客户表,0))),"※客户不在基础资料里",IF(AND($J8<>"",$F8<>"",$J8<$F8),"※完工日期早于下单日期",""))))
A9: =IF($B9="","","P"&TEXT(ROW()-3,"000")) | B9: 芭比贝克 | C9: 芭比贝克 | D9: 门头招牌 | F9: 46082 | J9: 46128 | K9: 820 | L9: =IF($B9="","",ROUND(SUMIF(订单明细!$C:$C,$B9,订单明细!$I:$I),2)) | M9: =IF($B9="","",ROUND(N($K9)+N($L9),2)) | O9: =IF($B9="","",ROUND(N($N9)+SUMIFS(资金日记账!$J$4:$J$2503,资金日记账!$G$4:$G$2503,$B9,资金日记账!$F$4:$F$2503,"收款-项目")-SUMIFS(资金日记账!$K$4:$K$2503,资金日记账!$G$4:$G$2503,$B9,资金日记账!$F$4:$F$2503,"收款-项目"),2)) | P9: =IF($B9="","",ROUND($M9-$O9,2)) | Q9: =IF($B9="","",IF(AND($J9<>"",ROUND($P9,2)<=0),"已完工·已结清",IF($J9<>"","已完工·还有尾款",IF($I9<>"","已安装",IF($H9<>"","已制作",IF($G9<>"","设计完成","已下单")))))) | R9: 来源：6-芭比贝克1 | S9: =IF($B9="","",IF(COUNTIF($B$4:$B$403,$B9)>1,"※项目名重复了",IF(AND($C9<>"",ISNA(MATCH($C9,客户表,0))),"※客户不在基础资料里",IF(AND($J9<>"",$F9<>"",$J9<$F9),"※完工日期早于下单日期",""))))
A10: =IF($B10="","","P"&TEXT(ROW()-3,"000")) | B10: 铁柱烧烤店 | C10: 铁柱烧烤店 | D10: 门头招牌 | F10: 46100 | J10: 46139 | K10: 7800 | L10: =IF($B10="","",ROUND(SUMIF(订单明细!$C:$C,$B10,订单明细!$I:$I),2)) | M10: =IF($B10="","",ROUND(N($K10)+N($L10),2)) | O10: =IF($B10="","",ROUND(N($N10)+SUMIFS(资金日记账!$J$4:$J$2503,资金日记账!$G$4:$G$2503,$B10,资金日记账!$F$4:$F$2503,"收款-项目")-SUMIFS(资金日记账!$K$4:$K$2503,资金日记账!$G$4:$G$2503,$B10,资金日记账!$F$4:$F$2503,"收款-项目"),2)) | P10: =IF($B10="","",ROUND($M10-$O10,2)) | Q10: =IF($B10="","",IF(AND($J10<>"",ROUND($P10,2)<=0),"已完工·已结清",IF($J10<>"","已完工·还有尾款",IF($I10<>"","已安装",IF($H10<>"","已制作",IF($G10<>"","设计完成","已下单")))))) | R10: 来源：7-铁柱烧烤店 | S10: =IF($B10="","",IF(COUNTIF($B$4:$B$403,$B10)>1,"※项目名重复了",IF(AND($C10<>"",ISNA(MATCH($C10,客户表,0))),"※客户不在基础资料里",IF(AND($J10<>"",$F10<>"",$J10<$F10),"※完工日期早于下单日期",""))))
A11: =IF($B11="","","P"&TEXT(ROW()-3,"000")) | B11: 钟管熟食店 | C11: 钟管熟食店 | D11: 门头招牌 | F11: 46084 | J11: 46084 | K11: 24000 | L11: =IF($B11="","",ROUND(SUMIF(订单明细!$C:$C,$B11,订单明细!$I:$I),2)) | M11: =IF($B11="","",ROUND(N($K11)+N($L11),2)) | N11: 24000 | O11: =IF($B11="","",ROUND(N($N11)+SUMIFS(资金日记账!$J$4:$J$2503,资金日记账!$G$4:$G$2503,$B11,资金日记账!$F$4:$F$2503,"收款-项目")-SUMIFS(资金日记账!$K$4:$K$2503,资金日记账!$G$4:$G$2503,$B11,资金日记账!$F$4:$F$2503,"收款-项目"),2)) | P11: =IF($B11="","",ROUND($M11-$O11,2)) | Q11: =IF($B11="","",IF(AND($J11<>"",ROUND($P11,2)<=0),"已完工·已结清",IF($J11<>"","已完工·还有尾款",IF($I11<>"","已安装",IF($H11<>"","已制作",IF($G11<>"","设计完成","已下单")))))) | R11: 来源：8-钟管熟食店 | S11: =IF($B11="","",IF(COUNTIF($B$4:$B$403,$B11)>1,"※项目名重复了",IF(AND($C11<>"",ISNA(MATCH($C11,客户表,0))),"※客户不在基础资料里",IF(AND($J11<>"",$F11<>"",$J11<$F11),"※完工日期早于下单日期",""))))
A12: =IF($B12="","","P"&TEXT(ROW()-3,"000")) | B12: 螺有名灯箱门头 | C12: 螺有名灯箱门头 | D12: 门头招牌 | F12: 46100 | J12: 46100 | K12: 1314 | L12: =IF($B12="","",ROUND(SUMIF(订单明细!$C:$C,$B12,订单明细!$I:$I),2)) | M12: =IF($B12="","",ROUND(N($K12)+N($L12),2)) | N12: 1314 | O12: =IF($B12="","",ROUND(N($N12)+SUMIFS(资金日记账!$J$4:$J$2503,资金日记账!$G$4:$G$2503,$B12,资金日记账!$F$4:$F$2503,"收款-项目")-SUMIFS(资金日记账!$K$4:$K$2503,资金日记账!$G$4:$G$2503,$B12,资金日记账!$F$4:$F$2503,"收款-项目"),2)) | P12: =IF($B12="","",ROUND($M12-$O12,2)) | Q12: =IF($B12="","",IF(AND($J12<>"",ROUND($P12,2)<=0),"已完工·已结清",IF($J12<>"","已完工·还有尾款",IF($I12<>"","已安装",IF($H12<>"","已制作",IF($G12<>"","设计完成","已下单")))))) | R12: 来源：9-螺有名灯箱门头 | S12: =IF($B12="","",IF(COUNTIF($B$4:$B$403,$B12)>1,"※项目名重复了",IF(AND($C12<>"",ISNA(MATCH($C12,客户表,0))),"※客户不在基础资料里",IF(AND($J12<>"",$F12<>"",$J12<$F12),"※完工日期早于下单日期",""))))
A13: =IF($B13="","","P"&TEXT(ROW()-3,"000")) | B13: 汕味杏花室内项目 | C13: 汕味杏花室内项目 | D13: 门头招牌 | F13: 46102 | J13: 46120 | K13: 5665.5 | L13: =IF($B13="","",ROUND(SUMIF(订单明细!$C:$C,$B13,订单明细!$I:$I),2)) | M13: =IF($B13="","",ROUND(N($K13)+N($L13),2)) | N13: 3000 | O13: =IF($B13="","",ROUND(N($N13)+SUMIFS(资金日记账!$J$4:$J$2503,资金日记账!$G$4:$G$2503,$B13,资金日记账!$F$4:$F$2503,"收款-项目")-SUMIFS(资金日记账!$K$4:$K$2503,资金日记账!$G$4:$G$2503,$B13,资金日记账!$F$4:$F$2503,"收款-项目"),2)) | P13: =IF($B13="","",ROUND($M13-$O13,2)) | Q13: =IF($B13="","",IF(AND($J13<>"",ROUND($P13,2)<=0),"已完工·已结清",IF($J13<>"","已完工·还有尾款",IF($I13<>"","已安装",IF($H13<>"","已制作",IF($G13<>"","设计完成","已下单")))))) | R13: 来源：10-汕味杏花室内项目 | S13: =IF($B13="","",IF(COUNTIF($B$4:$B$403,$B13)>1,"※项目名重复了",IF(AND($C13<>"",ISNA(MATCH($C13,客户表,0))),"※客户不在基础资料里",IF(AND($J13<>"",$F13<>"",$J13<$F13),"※完工日期早于下单日期",""))))
A14: =IF($B14="","","P"&TEXT(ROW()-3,"000")) | B14: 双林面馆-滨河路 | C14: 双林面馆-滨河路 | D14: 门头招牌 | F14: 46086 | K14: 4400 | L14: =IF($B14="","",ROUND(SUMIF(订单明细!$C:$C,$B14,订单明细!$I:$I),2)) | M14: =IF($B14="","",ROUND(N($K14)+N($L14),2)) | N14: 1700 | O14: =IF($B14="","",ROUND(N($N14)+SUMIFS(资金日记账!$J$4:$J$2503,资金日记账!$G$4:$G$2503,$B14,资金日记账!$F$4:$F$2503,"收款-项目")-SUMIFS(资金日记账!$K$4:$K$2503,资金日记账!$G$4:$G$2503,$B14,资金日记账!$F$4:$F$2503,"收款-项目"),2)) | P14: =IF($B14="","",ROUND($M14-$O14,2)) | Q14: =IF($B14="","",IF(AND($J14<>"",ROUND($P14,2)<=0),"已完工·已结清",IF($J14<>"","已完工·还有尾款",IF($I14<>"","已安装",IF($H14<>"","已制作",IF($G14<>"","设计完成","已下单")))))) | R14: 来源：11-双林面馆-滨河路 | S14: =IF($B14="","",IF(COUNTIF($B$4:$B$403,$B14)>1,"※项目名重复了",IF(AND($C14<>"",ISNA(MATCH($C14,客户表,0))),"※客户不在基础资料里",IF(AND($J14<>"",$F14<>"",$J14<$F14),"※完工日期早于下单日期",""))))
A15: =IF($B15="","","P"&TEXT(ROW()-3,"000")) | B15: 梓灿软装 | C15: 梓灿软装 | D15: 门头招牌 | F15: 46102 | K15: 3400 | L15: =IF($B15="","",ROUND(SUMIF(订单明细!$C:$C,$B15,订单明细!$I:$I),2)) | M15: =IF($B15="","",ROUND(N($K15)+N($L15),2)) | O15: =IF($B15="","",ROUND(N($N15)+SUMIFS(资金日记账!$J$4:$J$2503,资金日记账!$G$4:$G$2503,$B15,资金日记账!$F$4:$F$2503,"收款-项目")-SUMIFS(资金日记账!$K$4:$K$2503,资金日记账!$G$4:$G$2503,$B15,资金日记账!$F$4:$F$2503,"收款-项目"),2)) | P15: =IF($B15="","",ROUND($M15-$O15,2)) | Q15: =IF($B15="","",IF(AND($J15<>"",ROUND($P15,2)<=0),"已完工·已结清",IF($J15<>"","已完工·还有尾款",IF($I15<>"","已安装",IF($H15<>"","已制作",IF($G15<>"","设计完成","已下单")))))) | R15: 来源：12-梓灿软装 | S15: =IF($B15="","",IF(COUNTIF($B$4:$B$403,$B15)>1,"※项目名重复了",IF(AND($C15<>"",ISNA(MATCH($C15,客户表,0))),"※客户不在基础资料里",IF(AND($J15<>"",$F15<>"",$J15<$F15),"※完工日期早于下单日期",""))))
A16: =IF($B16="","","P"&TEXT(ROW()-3,"000")) | B16: 长颈鹿庄园 | C16: 长颈鹿庄园 | D16: 门头招牌 | F16: 46083 | J16: 46112 | K16: 4050 | L16: =IF($B16="","",ROUND(SUMIF(订单明细!$C:$C,$B16,订单明细!$I:$I),2)) | M16: =IF($B16="","",ROUND(N($K16)+N($L16),2)) | O16: =IF($B16="","",ROUND(N($N16)+SUMIFS(资金日记账!$J$4:$J$2503,资金日记账!$G$4:$G$2503,$B16,资金日记账!$F$4:$F$2503,"收款-项目")-SUMIFS(资金日记账!$K$4:$K$2503,资金日记账!$G$4:$G$2503,$B16,资金日记账!$F$4:$F$2503,"收款-项目"),2)) | P16: =IF($B16="","",ROUND($M16-$O16,2)) | Q16: =IF($B16="","",IF(AND($J16<>"",ROUND($P16,2)<=0),"已完工·已结清",IF($J16<>"","已完工·还有尾款",IF($I16<>"","已安装",IF($H16<>"","已制作",IF($G16<>"","设计完成","已下单")))))) | R16: 来源：13-长颈鹿庄园 | S16: =IF($B16="","",IF(COUNTIF($B$4:$B$403,$B16)>1,"※项目名重复了",IF(AND($C16<>"",ISNA(MATCH($C16,客户表,0))),"※客户不在基础资料里",IF(AND($J16<>"",$F16<>"",$J16<$F16),"※完工日期早于下单日期",""))))
A17: =IF($B17="","","P"&TEXT(ROW()-3,"000")) | B17: 国智校服 | C17: 国智校服 | D17: 门头招牌 | F17: 46083 | K17: 4904.2 | L17: =IF($B17="","",ROUND(SUMIF(订单明细!$C:$C,$B17,订单明细!$I:$I),2)) | M17: =IF($B17="","",ROUND(N($K17)+N($L17),2)) | O17: =IF($B17="","",ROUND(N($N17)+SUMIFS(资金日记账!$J$4:$J$2503,资金日记账!$G$4:$G$2503,$B17,资金日记账!$F$4:$F$2503,"收款-项目")-SUMIFS(资金日记账!$K$4:$K$2503,资金日记账!$G$4:$G$2503,$B17,资金日记账!$F$4:$F$2503,"收款-项目"),2)) | P17: =IF($B17="","",ROUND($M17-$O17,2)) | Q17: =IF($B17="","",IF(AND($J17<>"",ROUND($P17,2)<=0),"已完工·已结清",IF($J17<>"","已完工·还有尾款",IF($I17<>"","已安装",IF($H17<>"","已制作",IF($G17<>"","设计完成","已下单")))))) | R17: 来源：14-国智校服 | S17: =IF($B17="","",IF(COUNTIF($B$4:$B$403,$B17)>1,"※项目名重复了",IF(AND($C17<>"",ISNA(MATCH($C17,客户表,0))),"※客户不在基础资料里",IF(AND($J17<>"",$F17<>"",$J17<$F17),"※完工日期早于下单日期",""))))
A18: =IF($B18="","","P"&TEXT(ROW()-3,"000")) | B18: 民盛生鲜店 | C18: 民盛生鲜店 | D18: 门头招牌 | F18: 46107 | J18: 46129 | K18: 2000 | L18: =IF($B18="","",ROUND(SUMIF(订单明细!$C:$C,$B18,订单明细!$I:$I),2)) | M18: =IF($B18="","",ROUND(N($K18)+N($L18),2)) | O18: =IF($B18="","",ROUND(N($N18)+SUMIFS(资金日记账!$J$4:$J$2503,资金日记账!$G$4:$G$2503,$B18,资金日记账!$F$4:$F$2503,"收款-项目")-SUMIFS(资金日记账!$K$4:$K$2503,资金日记账!$G$4:$G$2503,$B18,资金日记账!$F$4:$F$2503,"收款-项目"),2)) | P18: =IF($B18="","",ROUND($M18-$O18,2)) | Q18: =IF($B18="","",IF(AND($J18<>"",ROUND($P18,2)<=0),"已完工·已结清",IF($J18<>"","已完工·还有尾款",IF($I18<>"","已安装",IF($H18<>"","已制作",IF($G18<>"","设计完成","已下单")))))) | R18: 来源：15-民盛生鲜店 | S18: =IF($B18="","",IF(COUNTIF($B$4:$B$403,$B18)>1,"※项目名重复了",IF(AND($C18<>"",ISNA(MATCH($C18,客户表,0))),"※客户不在基础资料里",IF(AND($J18<>"",$F18<>"",$J18<$F18),"※完工日期早于下单日期",""))))
A19: =IF($B19="","","P"&TEXT(ROW()-3,"000")) | B19: 饺子店 | C19: 饺子店 | D19: 门头招牌 | F19: 46108 | J19: 46119 | K19: 1928 | L19: =IF($B19="","",ROUND(SUMIF(订单明细!$C:$C,$B19,订单明细!$I:$I),2)) | M19: =IF($B19="","",ROUND(N($K19)+N($L19),2)) | O19: =IF($B19="","",ROUND(N($N19)+SUMIFS(资金日记账!$J$4:$J$2503,资金日记账!$G$4:$G$2503,$B19,资金日记账!$F$4:$F$2503,"收款-项目")-SUMIFS(资金日记账!$K$4:$K$2503,资金日记账!$G$4:$G$2503,$B19,资金日记账!$F$4:$F$2503,"收款-项目"),2)) | P19: =IF($B19="","",ROUND($M19-$O19,2)) | Q19: =IF($B19="","",IF(AND($J19<>"",ROUND($P19,2)<=0),"已完工·已结清",IF($J19<>"","已完工·还有尾款",IF($I19<>"","已安装",IF($H19<>"","已制作",IF($G19<>"","设计完成","已下单")))))) | R19: 来源：16-饺子店 | S19: =IF($B19="","",IF(COUNTIF($B$4:$B$403,$B19)>1,"※项目名重复了",IF(AND($C19<>"",ISNA(MATCH($C19,客户表,0))),"※客户不在基础资料里",IF(AND($J19<>"",$F19<>"",$J19<$F19),"※完工日期早于下单日期",""))))
A20: =IF($B20="","","P"&TEXT(ROW()-3,"000")) | B20: 睿芯行 | C20: 睿芯行 | D20: 门头招牌 | F20: 46108 | K20: 39800 | L20: =IF($B20="","",ROUND(SUMIF(订单明细!$C:$C,$B20,订单明细!$I:$I),2)) | M20: =IF($B20="","",ROUND(N($K20)+N($L20),2)) | N20: 19800 | O20: =IF($B20="","",ROUND(N($N20)+SUMIFS(资金日记账!$J$4:$J$2503,资金日记账!$G$4:$G$2503,$B20,资金日记账!$F$4:$F$2503,"收款-项目")-SUMIFS(资金日记账!$K$4:$K$2503,资金日记账!$G$4:$G$2503,$B20,资金日记账!$F$4:$F$2503,"收款-项目"),2)) | P20: =IF($B20="","",ROUND($M20-$O20,2)) | Q20: =IF($B20="","",IF(AND($J20<>"",ROUND($P20,2)<=0),"已完工·已结清",IF($J20<>"","已完工·还有尾款",IF($I20<>"","已安装",IF($H20<>"","已制作",IF($G20<>"","设计完成","已下单")))))) | R20: 来源：17-睿芯行 | S20: =IF($B20="","",IF(COUNTIF($B$4:$B$403,$B20)>1,"※项目名重复了",IF(AND($C20<>"",ISNA(MATCH($C20,客户表,0))),"※客户不在基础资料里",IF(AND($J20<>"",$F20<>"",$J20<$F20),"※完工日期早于下单日期",""))))
A21: =IF($B21="","","P"&TEXT(ROW()-3,"000")) | B21: 东尼电子26.3-4 | C21: 东尼新能源 | D21: 门头招牌 | F21: 46087 | J21: 46106 | L21: =IF($B21="","",ROUND(SUMIF(订单明细!$C:$C,$B21,订单明细!$I:$I),2)) | M21: =IF($B21="","",ROUND(N($K21)+N($L21),2)) | O21: =IF($B21="","",ROUND(N($N21)+SUMIFS(资金日记账!$J$4:$J$2503,资金日记账!$G$4:$G$2503,$B21,资金日记账!$F$4:$F$2503,"收款-项目")-SUMIFS(资金日记账!$K$4:$K$2503,资金日记账!$G$4:$G$2503,$B21,资金日记账!$F$4:$F$2503,"收款-项目"),2)) | P21: =IF($B21="","",ROUND($M21-$O21,2)) | Q21: =IF($B21="","",IF(AND($J21<>"",ROUND($P21,2)<=0),"已完工·已结清",IF($J21<>"","已完工·还有尾款",IF($I21<>"","已安装",IF($H21<>"","已制作",IF($G21<>"","设计完成","已下单")))))) | R21: 原「东尼电子」制作清单 | S21: =IF($B21="","",IF(COUNTIF($B$4:$B$403,$B21)>1,"※项目名重复了",IF(AND($C21<>"",ISNA(MATCH($C21,客户表,0))),"※客户不在基础资料里",IF(AND($J21<>"",$F21<>"",$J21<$F21),"※完工日期早于下单日期",""))))
A22: =IF($B22="","","P"&TEXT(ROW()-3,"000")) | B22: 东尼电子26.5 | C22: 东尼新能源 | D22: 门头招牌 | F22: 46148 | J22: 46169 | L22: =IF($B22="","",ROUND(SUMIF(订单明细!$C:$C,$B22,订单明细!$I:$I),2)) | M22: =IF($B22="","",ROUND(N($K22)+N($L22),2)) | O22: =IF($B22="","",ROUND(N($N22)+SUMIFS(资金日记账!$J$4:$J$2503,资金日记账!$G$4:$G$2503,$B22,资金日记账!$F$4:$F$2503,"收款-项目")-SUMIFS(资金日记账!$K$4:$K$2503,资金日记账!$G$4:$G$2503,$B22,资金日记账!$F$4:$F$2503,"收款-项目"),2)) | P22: =IF($B22="","",ROUND($M22-$O22,2)) | Q22: =IF($B22="","",IF(AND($J22<>"",ROUND($P22,2)<=0),"已完工·已结清",IF($J22<>"","已完工·还有尾款",IF($I22<>"","已安装",IF($H22<>"","已制作",IF($G22<>"","设计完成","已下单")))))) | R22: 原「Sheet1」制作清单 | S22: =IF($B22="","",IF(COUNTIF($B$4:$B$403,$B22)>1,"※项目名重复了",IF(AND($C22<>"",ISNA(MATCH($C22,客户表,0))),"※客户不在基础资料里",IF(AND($J22<>"",$F22<>"",$J22<$F22),"※完工日期早于下单日期",""))))
A23: =IF($B23="","","P"&TEXT(ROW()-3,"000")) | B23: 盛昊篷车 | C23: 盛昊篷车 | D23: 门头招牌 | F23: 46079 | L23: =IF($B23="","",ROUND(SUMIF(订单明细!$C:$C,$B23,订单明细!$I:$I),2)) | M23: =IF($B23="","",ROUND(N($K23)+N($L23),2)) | O23: =IF($B23="","",ROUND(N($N23)+SUMIFS(资金日记账!$J$4:$J$2503,资金日记账!$G$4:$G$2503,$B23,资金日记账!$F$4:$F$2503,"收款-项目")-SUMIFS(资金日记账!$K$4:$K$2503,资金日记账!$G$4:$G$2503,$B23,资金日记账!$F$4:$F$2503,"收款-项目"),2)) | P23: =IF($B23="","",ROUND($M23-$O23,2)) | Q23: =IF($B23="","",IF(AND($J23<>"",ROUND($P23,2)<=0),"已完工·已结清",IF($J23<>"","已完工·还有尾款",IF($I23<>"","已安装",IF($H23<>"","已制作",IF($G23<>"","设计完成","已下单")))))) | S23: =IF($B23="","",IF(COUNTIF($B$4:$B$403,$B23)>1,"※项目名重复了",IF(AND($C23<>"",ISNA(MATCH($C23,客户表,0))),"※客户不在基础资料里",IF(AND($J23<>"",$F23<>"",$J23<$F23),"※完工日期早于下单日期",""))))
A24: =IF($B24="","","P"&TEXT(ROW()-3,"000")) | B24: 付炳秀配送 | C24: 付炳秀配送 | D24: 门头招牌 | F24: 46080 | L24: =IF($B24="","",ROUND(SUMIF(订单明细!$C:$C,$B24,订单明细!$I:$I),2)) | M24: =IF($B24="","",ROUND(N($K24)+N($L24),2)) | O24: =IF($B24="","",ROUND(N($N24)+SUMIFS(资金日记账!$J$4:$J$2503,资金日记账!$G$4:$G$2503,$B24,资金日记账!$F$4:$F$2503,"收款-项目")-SUMIFS(资金日记账!$K$4:$K$2503,资金日记账!$G$4:$G$2503,$B24,资金日记账!$F$4:$F$2503,"收款-项目"),2)) | P24: =IF($B24="","",ROUND($M24-$O24,2)) | Q24: =IF($B24="","",IF(AND($J24<>"",ROUND($P24,2)<=0),"已完工·已结清",IF($J24<>"","已完工·还有尾款",IF($I24<>"","已安装",IF($H24<>"","已制作",IF($G24<>"","设计完成","已下单")))))) | S24: =IF($B24="","",IF(COUNTIF($B$4:$B$403,$B24)>1,"※项目名重复了",IF(AND($C24<>"",ISNA(MATCH($C24,客户表,0))),"※客户不在基础资料里",IF(AND($J24<>"",$F24<>"",$J24<$F24),"※完工日期早于下单日期",""))))
A25: =IF($B25="","","P"&TEXT(ROW()-3,"000")) | B25: 万达kvv | C25: 万达kvv | D25: 门头招牌 | F25: 46083 | L25: =IF($B25="","",ROUND(SUMIF(订单明细!$C:$C,$B25,订单明细!$I:$I),2)) | M25: =IF($B25="","",ROUND(N($K25)+N($L25),2)) | O25: =IF($B25="","",ROUND(N($N25)+SUMIFS(资金日记账!$J$4:$J$2503,资金日记账!$G$4:$G$2503,$B25,资金日记账!$F$4:$F$2503,"收款-项目")-SUMIFS(资金日记账!$K$4:$K$2503,资金日记账!$G$4:$G$2503,$B25,资金日记账!$F$4:$F$2503,"收款-项目"),2)) | P25: =IF($B25="","",ROUND($M25-$O25,2)) | Q25: =IF($B25="","",IF(AND($J25<>"",ROUND($P25,2)<=0),"已完工·已结清",IF($J25<>"","已完工·还有尾款",IF($I25<>"","已安装",IF($H25<>"","已制作",IF($G25<>"","设计完成","已下单")))))) | S25: =IF($B25="","",IF(COUNTIF($B$4:$B$403,$B25)>1,"※项目名重复了",IF(AND($C25<>"",ISNA(MATCH($C25,客户表,0))),"※客户不在基础资料里",IF(AND($J25<>"",$F25<>"",$J25<$F25),"※完工日期早于下单日期",""))))
A26: =IF($B26="","","P"&TEXT(ROW()-3,"000")) | B26: 织里店 | C26: 织里店 | D26: 门头招牌 | F26: 46084 | L26: =IF($B26="","",ROUND(SUMIF(订单明细!$C:$C,$B26,订单明细!$I:$I),2)) | M26: =IF($B26="","",ROUND(N($K26)+N($L26),2)) | O26: =IF($B26="","",ROUND(N($N26)+SUMIFS(资金日记账!$J$4:$J$2503,资金日记账!$G$4:$G$2503,$B26,资金日记账!$F$4:$F$2503,"收款-项目")-SUMIFS(资金日记账!$K$4:$K$2503,资金日记账!$G$4:$G$2503,$B26,资金日记账!$F$4:$F$2503,"收款-项目"),2)) | P26: =IF($B26="","",ROUND($M26-$O26,2)) | Q26: =IF($B26="","",IF(AND($J26<>"",ROUND($P26,2)<=0),"已完工·已结清",IF($J26<>"","已完工·还有尾款",IF($I26<>"","已安装",IF($H26<>"","已制作",IF($G26<>"","设计完成","已下单")))))) | S26: =IF($B26="","",IF(COUNTIF($B$4:$B$403,$B26)>1,"※项目名重复了",IF(AND($C26<>"",ISNA(MATCH($C26,客户表,0))),"※客户不在基础资料里",IF(AND($J26<>"",$F26<>"",$J26<$F26),"※完工日期早于下单日期",""))))
A27: =IF($B27="","","P"&TEXT(ROW()-3,"000")) | B27: 高恒荣熟食店 | C27: 高恒荣熟食店 | D27: 门头招牌 | F27: 46084 | L27: =IF($B27="","",ROUND(SUMIF(订单明细!$C:$C,$B27,订单明细!$I:$I),2)) | M27: =IF($B27="","",ROUND(N($K27)+N($L27),2)) | O27: =IF($B27="","",ROUND(N($N27)+SUMIFS(资金日记账!$J$4:$J$2503,资金日记账!$G$4:$G$2503,$B27,资金日记账!$F$4:$F$2503,"收款-项目")-SUMIFS(资金日记账!$K$4:$K$2503,资金日记账!$G$4:$G$2503,$B27,资金日记账!$F$4:$F$2503,"收款-项目"),2)) | P27: =IF($B27="","",ROUND($M27-$O27,2)) | Q27: =IF($B27="","",IF(AND($J27<>"",ROUND($P27,2)<=0),"已完工·已结清",IF($J27<>"","已完工·还有尾款",IF($I27<>"","已安装",IF($H27<>"","已制作",IF($G27<>"","设计完成","已下单")))))) | S27: =IF($B27="","",IF(COUNTIF($B$4:$B$403,$B27)>1,"※项目名重复了",IF(AND($C27<>"",ISNA(MATCH($C27,客户表,0))),"※客户不在基础资料里",IF(AND($J27<>"",$F27<>"",$J27<$F27),"※完工日期早于下单日期",""))))
A28: =IF($B28="","","P"&TEXT(ROW()-3,"000")) | B28: 卓越桌球 | C28: 卓越桌球 | D28: 门头招牌 | F28: 46085 | L28: =IF($B28="","",ROUND(SUMIF(订单明细!$C:$C,$B28,订单明细!$I:$I),2)) | M28: =IF($B28="","",ROUND(N($K28)+N($L28),2)) | O28: =IF($B28="","",ROUND(N($N28)+SUMIFS(资金日记账!$J$4:$J$2503,资金日记账!$G$4:$G$2503,$B28,资金日记账!$F$4:$F$2503,"收款-项目")-SUMIFS(资金日记账!$K$4:$K$2503,资金日记账!$G$4:$G$2503,$B28,资金日记账!$F$4:$F$2503,"收款-项目"),2)) | P28: =IF($B28="","",ROUND($M28-$O28,2)) | Q28: =IF($B28="","",IF(AND($J28<>"",ROUND($P28,2)<=0),"已完工·已结清",IF($J28<>"","已完工·还有尾款",IF($I28<>"","已安装",IF($H28<>"","已制作",IF($G28<>"","设计完成","已下单")))))) | S28: =IF($B28="","",IF(COUNTIF($B$4:$B$403,$B28)>1,"※项目名重复了",IF(AND($C28<>"",ISNA(MATCH($C28,客户表,0))),"※客户不在基础资料里",IF(AND($J28<>"",$F28<>"",$J28<$F28),"※完工日期早于下单日期",""))))
A29: =IF($B29="","","P"&TEXT(ROW()-3,"000")) | B29: 东尼电子 | C29: 东尼电子 | D29: 门头招牌 | F29: 46085 | L29: =IF($B29="","",ROUND(SUMIF(订单明细!$C:$C,$B29,订单明细!$I:$I),2)) | M29: =IF($B29="","",ROUND(N($K29)+N($L29),2)) | O29: =IF($B29="","",ROUND(N($N29)+SUMIFS(资金日记账!$J$4:$J$2503,资金日记账!$G$4:$G$2503,$B29,资金日记账!$F$4:$F$2503,"收款-项目")-SUMIFS(资金日记账!$K$4:$K$2503,资金日记账!$G$4:$G$2503,$B29,资金日记账!$F$4:$F$2503,"收款-项目"),2)) | P29: =IF($B29="","",ROUND($M29-$O29,2)) | Q29: =IF($B29="","",IF(AND($J29<>"",ROUND($P29,2)<=0),"已完工·已结清",IF($J29<>"","已完工·还有尾款",IF($I29<>"","已安装",IF($H29<>"","已制作",IF($G29<>"","设计完成","已下单")))))) | S29: =IF($B29="","",IF(COUNTIF($B$4:$B$403,$B29)>1,"※项目名重复了",IF(AND($C29<>"",ISNA(MATCH($C29,客户表,0))),"※客户不在基础资料里",IF(AND($J29<>"",$F29<>"",$J29<$F29),"※完工日期早于下单日期",""))))
A30: =IF($B30="","","P"&TEXT(ROW()-3,"000")) | B30: 犇腾牛排 | C30: 犇腾牛排 | D30: 门头招牌 | F30: 46088 | L30: =IF($B30="","",ROUND(SUMIF(订单明细!$C:$C,$B30,订单明细!$I:$I),2)) | M30: =IF($B30="","",ROUND(N($K30)+N($L30),2)) | O30: =IF($B30="","",ROUND(N($N30)+SUMIFS(资金日记账!$J$4:$J$2503,资金日记账!$G$4:$G$2503,$B30,资金日记账!$F$4:$F$2503,"收款-项目")-SUMIFS(资金日记账!$K$4:$K$2503,资金日记账!$G$4:$G$2503,$B30,资金日记账!$F$4:$F$2503,"收款-项目"),2)) | P30: =IF($B30="","",ROUND($M30-$O30,2)) | Q30: =IF($B30="","",IF(AND($J30<>"",ROUND($P30,2)<=0),"已完工·已结清",IF($J30<>"","已完工·还有尾款",IF($I30<>"","已安装",IF($H30<>"","已制作",IF($G30<>"","设计完成","已下单")))))) | S30: =IF($B30="","",IF(COUNTIF($B$4:$B$403,$B30)>1,"※项目名重复了",IF(AND($C30<>"",ISNA(MATCH($C30,客户表,0))),"※客户不在基础资料里",IF(AND($J30<>"",$F30<>"",$J30<$F30),"※完工日期早于下单日期",""))))
A31: =IF($B31="","","P"&TEXT(ROW()-3,"000")) | B31: 校服基地 | C31: 校服基地 | D31: 门头招牌 | F31: 46090 | L31: =IF($B31="","",ROUND(SUMIF(订单明细!$C:$C,$B31,订单明细!$I:$I),2)) | M31: =IF($B31="","",ROUND(N($K31)+N($L31),2)) | O31: =IF($B31="","",ROUND(N($N31)+SUMIFS(资金日记账!$J$4:$J$2503,资金日记账!$G$4:$G$2503,$B31,资金日记账!$F$4:$F$2503,"收款-项目")-SUMIFS(资金日记账!$K$4:$K$2503,资金日记账!$G$4:$G$2503,$B31,资金日记账!$F$4:$F$2503,"收款-项目"),2)) | P31: =IF($B31="","",ROUND($M31-$O31,2)) | Q31: =IF($B31="","",IF(AND($J31<>"",ROUND($P31,2)<=0),"已完工·已结清",IF($J31<>"","已完工·还有尾款",IF($I31<>"","已安装",IF($H31<>"","已制作",IF($G31<>"","设计完成","已下单")))))) | S31: =IF($B31="","",IF(COUNTIF($B$4:$B$403,$B31)>1,"※项目名重复了",IF(AND($C31<>"",ISNA(MATCH($C31,客户表,0))),"※客户不在基础资料里",IF(AND($J31<>"",$F31<>"",$J31<$F31),"※完工日期早于下单日期",""))))
A32: =IF($B32="","","P"&TEXT(ROW()-3,"000")) | B32: 德清钟管菜市场 | C32: 德清钟管菜市场 | D32: 门头招牌 | F32: 46090 | L32: =IF($B32="","",ROUND(SUMIF(订单明细!$C:$C,$B32,订单明细!$I:$I),2)) | M32: =IF($B32="","",ROUND(N($K32)+N($L32),2)) | O32: =IF($B32="","",ROUND(N($N32)+SUMIFS(资金日记账!$J$4:$J$2503,资金日记账!$G$4:$G$2503,$B32,资金日记账!$F$4:$F$2503,"收款-项目")-SUMIFS(资金日记账!$K$4:$K$2503,资金日记账!$G$4:$G$2503,$B32,资金日记账!$F$4:$F$2503,"收款-项目"),2)) | P32: =IF($B32="","",ROUND($M32-$O32,2)) | Q32: =IF($B32="","",IF(AND($J32<>"",ROUND($P32,2)<=0),"已完工·已结清",IF($J32<>"","已完工·还有尾款",IF($I32<>"","已安装",IF($H32<>"","已制作",IF($G32<>"","设计完成","已下单")))))) | S32: =IF($B32="","",IF(COUNTIF($B$4:$B$403,$B32)>1,"※项目名重复了",IF(AND($C32<>"",ISNA(MATCH($C32,客户表,0))),"※客户不在基础资料里",IF(AND($J32<>"",$F32<>"",$J32<$F32),"※完工日期早于下单日期",""))))
A33: =IF($B33="","","P"&TEXT(ROW()-3,"000")) | B33: 中交 | C33: 中交 | D33: 门头招牌 | F33: 46092 | L33: =IF($B33="","",ROUND(SUMIF(订单明细!$C:$C,$B33,订单明细!$I:$I),2)) | M33: =IF($B33="","",ROUND(N($K33)+N($L33),2)) | O33: =IF($B33="","",ROUND(N($N33)+SUMIFS(资金日记账!$J$4:$J$2503,资金日记账!$G$4:$G$2503,$B33,资金日记账!$F$4:$F$2503,"收款-项目")-SUMIFS(资金日记账!$K$4:$K$2503,资金日记账!$G$4:$G$2503,$B33,资金日记账!$F$4:$F$2503,"收款-项目"),2)) | P33: =IF($B33="","",ROUND($M33-$O33,2)) | Q33: =IF($B33="","",IF(AND($J33<>"",ROUND($P33,2)<=0),"已完工·已结清",IF($J33<>"","已完工·还有尾款",IF($I33<>"","已安装",IF($H33<>"","已制作",IF($G33<>"","设计完成","已下单")))))) | S33: =IF($B33="","",IF(COUNTIF($B$4:$B$403,$B33)>1,"※项目名重复了",IF(AND($C33<>"",ISNA(MATCH($C33,客户表,0))),"※客户不在基础资料里",IF(AND($J33<>"",$F33<>"",$J33<$F33),"※完工日期早于下单日期",""))))
A34: =IF($B34="","","P"&TEXT(ROW()-3,"000")) | B34: vip宠物乐园 | C34: vip宠物乐园 | D34: 门头招牌 | F34: 46093 | L34: =IF($B34="","",ROUND(SUMIF(订单明细!$C:$C,$B34,订单明细!$I:$I),2)) | M34: =IF($B34="","",ROUND(N($K34)+N($L34),2)) | O34: =IF($B34="","",ROUND(N($N34)+SUMIFS(资金日记账!$J$4:$J$2503,资金日记账!$G$4:$G$2503,$B34,资金日记账!$F$4:$F$2503,"收款-项目")-SUMIFS(资金日记账!$K$4:$K$2503,资金日记账!$G$4:$G$2503,$B34,资金日记账!$F$4:$F$2503,"收款-项目"),2)) | P34: =IF($B34="","",ROUND($M34-$O34,2)) | Q34: =IF($B34="","",IF(AND($J34<>"",ROUND($P34,2)<=0),"已完工·已结清",IF($J34<>"","已完工·还有尾款",IF($I34<>"","已安装",IF($H34<>"","已制作",IF($G34<>"","设计完成","已下单")))))) | S34: =IF($B34="","",IF(COUNTIF($B$4:$B$403,$B34)>1,"※项目名重复了",IF(AND($C34<>"",ISNA(MATCH($C34,客户表,0))),"※客户不在基础资料里",IF(AND($J34<>"",$F34<>"",$J34<$F34),"※完工日期早于下单日期",""))))
... A88: =IF($B88="","","P"&TEXT(ROW()-3,"000")) | B88: nook咖啡店 | C88: nook咖啡店 | D88: 门头招牌 | F88: 46186 | L88: =IF($B88="","",ROUND(SUMIF(订单明细!$C:$C,$B88,订单明细!$I:$I),2)) | M88: =IF($B88="","",ROUND(N($K88)+N($L88),2)) | O88: =IF($B88="","",ROUND(N($N88)+SUMIFS(资金日记账!$J$4:$J$2503,资金日记账!$G$4:$G$2503,$B88,资金日记账!$F$4:$F$2503,"收款-项目")-SUMIFS(资金日记账!$K$4:$K$2503,资金日记账!$G$4:$G$2503,$B88,资金日记账!$F$4:$F$2503,"收款-项目"),2)) | P88: =IF($B88="","",ROUND($M88-$O88,2)) | Q88: =IF($B88="","",IF(AND($J88<>"",ROUND($P88,2)<=0),"已完工·已结清",IF($J88<>"","已完工·还有尾款",IF($I88<>"","已安装",IF($H88<>"","已制作",IF($G88<>"","设计完成","已下单")))))) | S88: =IF($B88="","",IF(COUNTIF($B$4:$B$403,$B88)>1,"※项目名重复了",IF(AND($C88<>"",ISNA(MATCH($C88,客户表,0))),"※客户不在基础资料里",IF(AND($J88<>"",$F88<>"",$J88<$F88),"※完工日期早于下单日期",""))))
A89: =IF($B89="","","P"&TEXT(ROW()-3,"000")) | L89: =IF($B89="","",ROUND(SUMIF(订单明细!$C:$C,$B89,订单明细!$I:$I),2)) | M89: =IF($B89="","",ROUND(N($K89)+N($L89),2)) | O89: =IF($B89="","",ROUND(N($N89)+SUMIFS(资金日记账!$J$4:$J$2503,资金日记账!$G$4:$G$2503,$B89,资金日记账!$F$4:$F$2503,"收款-项目")-SUMIFS(资金日记账!$K$4:$K$2503,资金日记账!$G$4:$G$2503,$B89,资金日记账!$F$4:$F$2503,"收款-项目"),2)) | P89: =IF($B89="","",ROUND($M89-$O89,2)) | Q89: =IF($B89="","",IF(AND($J89<>"",ROUND($P89,2)<=0),"已完工·已结清",IF($J89<>"","已完工·还有尾款",IF($I89<>"","已安装",IF($H89<>"","已制作",IF($G89<>"","设计完成","已下单")))))) | S89: =IF($B89="","",IF(COUNTIF($B$4:$B$403,$B89)>1,"※项目名重复了",IF(AND($C89<>"",ISNA(MATCH($C89,客户表,0))),"※客户不在基础资料里",IF(AND($J89<>"",$F89<>"",$J89<$F89),"※完工日期早于下单日期",""))))
A90: =IF($B90="","","P"&TEXT(ROW()-3,"000")) | L90: =IF($B90="","",ROUND(SUMIF(订单明细!$C:$C,$B90,订单明细!$I:$I),2)) | M90: =IF($B90="","",ROUND(N($K90)+N($L90),2)) | O90: =IF($B90="","",ROUND(N($N90)+SUMIFS(资金日记账!$J$4:$J$2503,资金日记账!$G$4:$G$2503,$B90,资金日记账!$F$4:$F$2503,"收款-项目")-SUMIFS(资金日记账!$K$4:$K$2503,资金日记账!$G$4:$G$2503,$B90,资金日记账!$F$4:$F$2503,"收款-项目"),2)) | P90: =IF($B90="","",ROUND($M90-$O90,2)) | Q90: =IF($B90="","",IF(AND($J90<>"",ROUND($P90,2)<=0),"已完工·已结清",IF($J90<>"","已完工·还有尾款",IF($I90<>"","已安装",IF($H90<>"","已制作",IF($G90<>"","设计完成","已下单")))))) | S90: =IF($B90="","",IF(COUNTIF($B$4:$B$403,$B90)>1,"※项目名重复了",IF(AND($C90<>"",ISNA(MATCH($C90,客户表,0))),"※客户不在基础资料里",IF(AND($J90<>"",$F90<>"",$J90<$F90),"※完工日期早于下单日期",""))))
A91: =IF($B91="","","P"&TEXT(ROW()-3,"000")) | L91: =IF($B91="","",ROUND(SUMIF(订单明细!$C:$C,$B91,订单明细!$I:$I),2)) | M91: =IF($B91="","",ROUND(N($K91)+N($L91),2)) | O91: =IF($B91="","",ROUND(N($N91)+SUMIFS(资金日记账!$J$4:$J$2503,资金日记账!$G$4:$G$2503,$B91,资金日记账!$F$4:$F$2503,"收款-项目")-SUMIFS(资金日记账!$K$4:$K$2503,资金日记账!$G$4:$G$2503,$B91,资金日记账!$F$4:$F$2503,"收款-项目"),2)) | P91: =IF($B91="","",ROUND($M91-$O91,2)) | Q91: =IF($B91="","",IF(AND($J91<>"",ROUND($P91,2)<=0),"已完工·已结清",IF($J91<>"","已完工·还有尾款",IF($I91<>"","已安装",IF($H91<>"","已制作",IF($G91<>"","设计完成","已下单")))))) | S91: =IF($B91="","",IF(COUNTIF($B$4:$B$403,$B91)>1,"※项目名重复了",IF(AND($C91<>"",ISNA(MATCH($C91,客户表,0))),"※客户不在基础资料里",IF(AND($J91<>"",$F91<>"",$J91<$F91),"※完工日期早于下单日期",""))))
A92: =IF($B92="","","P"&TEXT(ROW()-3,"000")) | L92: =IF($B92="","",ROUND(SUMIF(订单明细!$C:$C,$B92,订单明细!$I:$I),2)) | M92: =IF($B92="","",ROUND(N($K92)+N($L92),2)) | O92: =IF($B92="","",ROUND(N($N92)+SUMIFS(资金日记账!$J$4:$J$2503,资金日记账!$G$4:$G$2503,$B92,资金日记账!$F$4:$F$2503,"收款-项目")-SUMIFS(资金日记账!$K$4:$K$2503,资金日记账!$G$4:$G$2503,$B92,资金日记账!$F$4:$F$2503,"收款-项目"),2)) | P92: =IF($B92="","",ROUND($M92-$O92,2)) | Q92: =IF($B92="","",IF(AND($J92<>"",ROUND($P92,2)<=0),"已完工·已结清",IF($J92<>"","已完工·还有尾款",IF($I92<>"","已安装",IF($H92<>"","已制作",IF($G92<>"","设计完成","已下单")))))) | S92: =IF($B92="","",IF(COUNTIF($B$4:$B$403,$B92)>1,"※项目名重复了",IF(AND($C92<>"",ISNA(MATCH($C92,客户表,0))),"※客户不在基础资料里",IF(AND($J92<>"",$F92<>"",$J92<$F92),"※完工日期早于下单日期",""))))
A93: =IF($B93="","","P"&TEXT(ROW()-3,"000")) | L93: =IF($B93="","",ROUND(SUMIF(订单明细!$C:$C,$B93,订单明细!$I:$I),2)) | M93: =IF($B93="","",ROUND(N($K93)+N($L93),2)) | O93: =IF($B93="","",ROUND(N($N93)+SUMIFS(资金日记账!$J$4:$J$2503,资金日记账!$G$4:$G$2503,$B93,资金日记账!$F$4:$F$2503,"收款-项目")-SUMIFS(资金日记账!$K$4:$K$2503,资金日记账!$G$4:$G$2503,$B93,资金日记账!$F$4:$F$2503,"收款-项目"),2)) | P93: =IF($B93="","",ROUND($M93-$O93,2)) | Q93: =IF($B93="","",IF(AND($J93<>"",ROUND($P93,2)<=0),"已完工·已结清",IF($J93<>"","已完工·还有尾款",IF($I93<>"","已安装",IF($H93<>"","已制作",IF($G93<>"","设计完成","已下单")))))) | S93: =IF($B93="","",IF(COUNTIF($B$4:$B$403,$B93)>1,"※项目名重复了",IF(AND($C93<>"",ISNA(MATCH($C93,客户表,0))),"※客户不在基础资料里",IF(AND($J93<>"",$F93<>"",$J93<$F93),"※完工日期早于下单日期",""))))
A94: =IF($B94="","","P"&TEXT(ROW()-3,"000")) | L94: =IF($B94="","",ROUND(SUMIF(订单明细!$C:$C,$B94,订单明细!$I:$I),2)) | M94: =IF($B94="","",ROUND(N($K94)+N($L94),2)) | O94: =IF($B94="","",ROUND(N($N94)+SUMIFS(资金日记账!$J$4:$J$2503,资金日记账!$G$4:$G$2503,$B94,资金日记账!$F$4:$F$2503,"收款-项目")-SUMIFS(资金日记账!$K$4:$K$2503,资金日记账!$G$4:$G$2503,$B94,资金日记账!$F$4:$F$2503,"收款-项目"),2)) | P94: =IF($B94="","",ROUND($M94-$O94,2)) | Q94: =IF($B94="","",IF(AND($J94<>"",ROUND($P94,2)<=0),"已完工·已结清",IF($J94<>"","已完工·还有尾款",IF($I94<>"","已安装",IF($H94<>"","已制作",IF($G94<>"","设计完成","已下单")))))) | S94: =IF($B94="","",IF(COUNTIF($B$4:$B$403,$B94)>1,"※项目名重复了",IF(AND($C94<>"",ISNA(MATCH($C94,客户表,0))),"※客户不在基础资料里",IF(AND($J94<>"",$F94<>"",$J94<$F94),"※完工日期早于下单日期",""))))
A95: =IF($B95="","","P"&TEXT(ROW()-3,"000")) | L95: =IF($B95="","",ROUND(SUMIF(订单明细!$C:$C,$B95,订单明细!$I:$I),2)) | M95: =IF($B95="","",ROUND(N($K95)+N($L95),2)) | O95: =IF($B95="","",ROUND(N($N95)+SUMIFS(资金日记账!$J$4:$J$2503,资金日记账!$G$4:$G$2503,$B95,资金日记账!$F$4:$F$2503,"收款-项目")-SUMIFS(资金日记账!$K$4:$K$2503,资金日记账!$G$4:$G$2503,$B95,资金日记账!$F$4:$F$2503,"收款-项目"),2)) | P95: =IF($B95="","",ROUND($M95-$O95,2)) | Q95: =IF($B95="","",IF(AND($J95<>"",ROUND($P95,2)<=0),"已完工·已结清",IF($J95<>"","已完工·还有尾款",IF($I95<>"","已安装",IF($H95<>"","已制作",IF($G95<>"","设计完成","已下单")))))) | S95: =IF($B95="","",IF(COUNTIF($B$4:$B$403,$B95)>1,"※项目名重复了",IF(AND($C95<>"",ISNA(MATCH($C95,客户表,0))),"※客户不在基础资料里",IF(AND($J95<>"",$F95<>"",$J95<$F95),"※完工日期早于下单日期",""))))
A96: =IF($B96="","","P"&TEXT(ROW()-3,"000")) | L96: =IF($B96="","",ROUND(SUMIF(订单明细!$C:$C,$B96,订单明细!$I:$I),2)) | M96: =IF($B96="","",ROUND(N($K96)+N($L96),2)) | O96: =IF($B96="","",ROUND(N($N96)+SUMIFS(资金日记账!$J$4:$J$2503,资金日记账!$G$4:$G$2503,$B96,资金日记账!$F$4:$F$2503,"收款-项目")-SUMIFS(资金日记账!$K$4:$K$2503,资金日记账!$G$4:$G$2503,$B96,资金日记账!$F$4:$F$2503,"收款-项目"),2)) | P96: =IF($B96="","",ROUND($M96-$O96,2)) | Q96: =IF($B96="","",IF(AND($J96<>"",ROUND($P96,2)<=0),"已完工·已结清",IF($J96<>"","已完工·还有尾款",IF($I96<>"","已安装",IF($H96<>"","已制作",IF($G96<>"","设计完成","已下单")))))) | S96: =IF($B96="","",IF(COUNTIF($B$4:$B$403,$B96)>1,"※项目名重复了",IF(AND($C96<>"",ISNA(MATCH($C96,客户表,0))),"※客户不在基础资料里",IF(AND($J96<>"",$F96<>"",$J96<$F96),"※完工日期早于下单日期",""))))
A97: =IF($B97="","","P"&TEXT(ROW()-3,"000")) | L97: =IF($B97="","",ROUND(SUMIF(订单明细!$C:$C,$B97,订单明细!$I:$I),2)) | M97: =IF($B97="","",ROUND(N($K97)+N($L97),2)) | O97: =IF($B97="","",ROUND(N($N97)+SUMIFS(资金日记账!$J$4:$J$2503,资金日记账!$G$4:$G$2503,$B97,资金日记账!$F$4:$F$2503,"收款-项目")-SUMIFS(资金日记账!$K$4:$K$2503,资金日记账!$G$4:$G$2503,$B97,资金日记账!$F$4:$F$2503,"收款-项目"),2)) | P97: =IF($B97="","",ROUND($M97-$O97,2)) | Q97: =IF($B97="","",IF(AND($J97<>"",ROUND($P97,2)<=0),"已完工·已结清",IF($J97<>"","已完工·还有尾款",IF($I97<>"","已安装",IF($H97<>"","已制作",IF($G97<>"","设计完成","已下单")))))) | S97: =IF($B97="","",IF(COUNTIF($B$4:$B$403,$B97)>1,"※项目名重复了",IF(AND($C97<>"",ISNA(MATCH($C97,客户表,0))),"※客户不在基础资料里",IF(AND($J97<>"",$F97<>"",$J97<$F97),"※完工日期早于下单日期",""))))
A98: =IF($B98="","","P"&TEXT(ROW()-3,"000")) | L98: =IF($B98="","",ROUND(SUMIF(订单明细!$C:$C,$B98,订单明细!$I:$I),2)) | M98: =IF($B98="","",ROUND(N($K98)+N($L98),2)) | O98: =IF($B98="","",ROUND(N($N98)+SUMIFS(资金日记账!$J$4:$J$2503,资金日记账!$G$4:$G$2503,$B98,资金日记账!$F$4:$F$2503,"收款-项目")-SUMIFS(资金日记账!$K$4:$K$2503,资金日记账!$G$4:$G$2503,$B98,资金日记账!$F$4:$F$2503,"收款-项目"),2)) | P98: =IF($B98="","",ROUND($M98-$O98,2)) | Q98: =IF($B98="","",IF(AND($J98<>"",ROUND($P98,2)<=0),"已完工·已结清",IF($J98<>"","已完工·还有尾款",IF($I98<>"","已安装",IF($H98<>"","已制作",IF($G98<>"","设计完成","已下单")))))) | S98: =IF($B98="","",IF(COUNTIF($B$4:$B$403,$B98)>1,"※项目名重复了",IF(AND($C98<>"",ISNA(MATCH($C98,客户表,0))),"※客户不在基础资料里",IF(AND($J98<>"",$F98<>"",$J98<$F98),"※完工日期早于下单日期",""))))
A99: =IF($B99="","","P"&TEXT(ROW()-3,"000")) | L99: =IF($B99="","",ROUND(SUMIF(订单明细!$C:$C,$B99,订单明细!$I:$I),2)) | M99: =IF($B99="","",ROUND(N($K99)+N($L99),2)) | O99: =IF($B99="","",ROUND(N($N99)+SUMIFS(资金日记账!$J$4:$J$2503,资金日记账!$G$4:$G$2503,$B99,资金日记账!$F$4:$F$2503,"收款-项目")-SUMIFS(资金日记账!$K$4:$K$2503,资金日记账!$G$4:$G$2503,$B99,资金日记账!$F$4:$F$2503,"收款-项目"),2)) | P99: =IF($B99="","",ROUND($M99-$O99,2)) | Q99: =IF($B99="","",IF(AND($J99<>"",ROUND($P99,2)<=0),"已完工·已结清",IF($J99<>"","已完工·还有尾款",IF($I99<>"","已安装",IF($H99<>"","已制作",IF($G99<>"","设计完成","已下单")))))) | S99: =IF($B99="","",IF(COUNTIF($B$4:$B$403,$B99)>1,"※项目名重复了",IF(AND($C99<>"",ISNA(MATCH($C99,客户表,0))),"※客户不在基础资料里",IF(AND($J99<>"",$F99<>"",$J99<$F99),"※完工日期早于下单日期",""))))
A100: =IF($B100="","","P"&TEXT(ROW()-3,"000")) | L100: =IF($B100="","",ROUND(SUMIF(订单明细!$C:$C,$B100,订单明细!$I:$I),2)) | M100: =IF($B100="","",ROUND(N($K100)+N($L100),2)) | O100: =IF($B100="","",ROUND(N($N100)+SUMIFS(资金日记账!$J$4:$J$2503,资金日记账!$G$4:$G$2503,$B100,资金日记账!$F$4:$F$2503,"收款-项目")-SUMIFS(资金日记账!$K$4:$K$2503,资金日记账!$G$4:$G$2503,$B100,资金日记账!$F$4:$F$2503,"收款-项目"),2)) | P100: =IF($B100="","",ROUND($M100-$O100,2)) | Q100: =IF($B100="","",IF(AND($J100<>"",ROUND($P100,2)<=0),"已完工·已结清",IF($J100<>"","已完工·还有尾款",IF($I100<>"","已安装",IF($H100<>"","已制作",IF($G100<>"","设计完成","已下单")))))) | S100: =IF($B100="","",IF(COUNTIF($B$4:$B$403,$B100)>1,"※项目名重复了",IF(AND($C100<>"",ISNA(MATCH($C100,客户表,0))),"※客户不在基础资料里",IF(AND($J100<>"",$F100<>"",$J100<$F100),"※完工日期早于下单日期",""))))
... A403: =IF($B403="","","P"&TEXT(ROW()-3,"000")) | L403: =IF($B403="","",ROUND(SUMIF(订单明细!$C:$C,$B403,订单明细!$I:$I),2)) | M403: =IF($B403="","",ROUND(N($K403)+N($L403),2)) | O403: =IF($B403="","",ROUND(N($N403)+SUMIFS(资金日记账!$J$4:$J$2503,资金日记账!$G$4:$G$2503,$B403,资金日记账!$F$4:$F$2503,"收款-项目")-SUMIFS(资金日记账!$K$4:$K$2503,资金日记账!$G$4:$G$2503,$B403,资金日记账!$F$4:$F$2503,"收款-项目"),2)) | P403: =IF($B403="","",ROUND($M403-$O403,2)) | Q403: =IF($B403="","",IF(AND($J403<>"",ROUND($P403,2)<=0),"已完工·已结清",IF($J403<>"","已完工·还有尾款",IF($I403<>"","已安装",IF($H403<>"","已制作",IF($G403<>"","设计完成","已下单")))))) | S403: =IF($B403="","",IF(COUNTIF($B$4:$B$403,$B403)>1,"※项目名重复了",IF(AND($C403<>"",ISNA(MATCH($C403,客户表,0))),"※客户不在基础资料里",IF(AND($J403<>"",$F403<>"",$J403<$F403),"※完工日期早于下单日期",""))))

Sheet 订单明细
A1: 订单明细 · 按件报价的客户用（下单 / 设计岗位填）
A2: 一次几十个标牌那种客户在这里逐项登记，金额会自动加进【项目台账】的「订单明细额」。整单包死的项目不用填这张表。
A3: 序号 | B3: 下单日期 ★ | C3: 项目名称 ★ | D3: 品名 ★ | E3: 规格 | F3: 单位 | G3: 数量 | H3: 单价 | I3: 金额 | J3: 客户 | K3: 备注
A4: =IF($C4="","",ROW()-3) | B4: 46087 | C4: 东尼电子26.3-4 | D4: 作业表单放置处 | E4: 15*3cm | F4: 张 | G4: 50 | H4: 1 | I4: =IF($C4="","",ROUND(IF($G4="",1,$G4)*N($H4),2)) | J4: =IF($C4="","",IFERROR(VLOOKUP($C4,项目台账!$B:$C,2,0),"※项目不在项目台账里"))
A5: =IF($C5="","",ROW()-3) | B5: 46087 | C5: 东尼电子26.3-4 | D5: 准文件放置处 | E5: 15*3cm | F5: 张 | G5: 50 | H5: 1 | I5: =IF($C5="","",ROUND(IF($G5="",1,$G5)*N($H5),2)) | J5: =IF($C5="","",IFERROR(VLOOKUP($C5,项目台账!$B:$C,2,0),"※项目不在项目台账里"))
A6: =IF($C6="","",ROW()-3) | B6: 46087 | C6: 东尼电子26.3-4 | D6: 标识牌（物料专用通道） | E6: 40*80 | F6: 块 | G6: 4 | H6: 40 | I6: =IF($C6="","",ROUND(IF($G6="",1,$G6)*N($H6),2)) | J6: =IF($C6="","",IFERROR(VLOOKUP($C6,项目台账!$B:$C,2,0),"※项目不在项目台账里"))
A7: =IF($C7="","",ROW()-3) | B7: 46095 | C7: 东尼电子26.3-4 | D7: 玻璃磨砂膜 | E7: 指定尺寸 | F7: 平方 | G7: 51.705 | H7: 35 | I7: =IF($C7="","",ROUND(IF($G7="",1,$G7)*N($H7),2)) | J7: =IF($C7="","",IFERROR(VLOOKUP($C7,项目台账!$B:$C,2,0),"※项目不在项目台账里"))
A8: =IF($C8="","",ROW()-3) | B8: 46095 | C8: 东尼电子26.3-4 | D8: 安装费 | E8: - | F8: 次 | G8: 1 | H8: 600 | I8: =IF($C8="","",ROUND(IF($G8="",1,$G8)*N($H8),2)) | J8: =IF($C8="","",IFERROR(VLOOKUP($C8,项目台账!$B:$C,2,0),"※项目不在项目台账里"))
A9: =IF($C9="","",ROW()-3) | B9: 46095 | C9: 东尼电子26.3-4 | D9: 告示牌（道路施工） | E9: 40cm*80cm | F9: 块 | G9: 2 | H9: 20 | I9: =IF($C9="","",ROUND(IF($G9="",1,$G9)*N($H9),2)) | J9: =IF($C9="","",IFERROR(VLOOKUP($C9,项目台账!$B:$C,2,0),"※项目不在项目台账里"))
A10: =IF($C10="","",ROW()-3) | B10: 46099 | C10: 东尼电子26.3-4 | D10: 斜纹贴（点检表放置处 | E10: :20*5cm | F10: 张 | G10: 100 | H10: 2 | I10: =IF($C10="","",ROUND(IF($G10="",1,$G10)*N($H10),2)) | J10: =IF($C10="","",IFERROR(VLOOKUP($C10,项目台账!$B:$C,2,0),"※项目不在项目台账里"))
A11: =IF($C11="","",ROW()-3) | B11: 46099 | C11: 东尼电子26.3-4 | D11: 斜纹贴（SOP作业指导书放置处） | E11: 20*5cm | F11: 张 | G11: 80 | H11: 2 | I11: =IF($C11="","",ROUND(IF($G11="",1,$G11)*N($H11),2)) | J11: =IF($C11="","",IFERROR(VLOOKUP($C11,项目台账!$B:$C,2,0),"※项目不在项目台账里"))
A12: =IF($C12="","",ROW()-3) | B12: 46104 | C12: 东尼电子26.3-4 | D12: 斜纹贴（点检表放置处） | E12: 20*3cm | F12: 张 | G12: 100 | H12: 2 | I12: =IF($C12="","",ROUND(IF($G12="",1,$G12)*N($H12),2)) | J12: =IF($C12="","",IFERROR(VLOOKUP($C12,项目台账!$B:$C,2,0),"※项目不在项目台账里"))
A13: =IF($C13="","",ROW()-3) | B13: 46104 | C13: 东尼电子26.3-4 | D13: 斜纹贴（SOP作业指导书放置处） | E13: 20*3cm | F13: 张 | G13: 100 | H13: 2 | I13: =IF($C13="","",ROUND(IF($G13="",1,$G13)*N($H13),2)) | J13: =IF($C13="","",IFERROR(VLOOKUP($C13,项目台账!$B:$C,2,0),"※项目不在项目台账里"))
A14: =IF($C14="","",ROW()-3) | B14: 46104 | C14: 东尼电子26.3-4 | D14: 当心夹手 | E14: 10*6cm | F14: 张 | G14: 50 | H14: 2 | I14: =IF($C14="","",ROUND(IF($G14="",1,$G14)*N($H14),2)) | J14: =IF($C14="","",IFERROR(VLOOKUP($C14,项目台账!$B:$C,2,0),"※项目不在项目台账里"))
A15: =IF($C15="","",ROW()-3) | B15: 46104 | C15: 东尼电子26.3-4 | D15: 机器运转时禁止开门 | E15: 10*6cm | F15: 张 | G15: 50 | H15: 2 | I15: =IF($C15="","",ROUND(IF($G15="",1,$G15)*N($H15),2)) | J15: =IF($C15="","",IFERROR(VLOOKUP($C15,项目台账!$B:$C,2,0),"※项目不在项目台账里"))
... A38: =IF($C38="","",ROW()-3) | B38: 46104 | C38: 东尼电子26.3-4 | D38: 注意压接面向 | E38: 10*6cm | F38: 张 | G38: 20 | H38: 2 | I38: =IF($C38="","",ROUND(IF($G38="",1,$G38)*N($H38),2)) | J38: =IF($C38="","",IFERROR(VLOOKUP($C38,项目台账!$B:$C,2,0),"※项目不在项目台账里"))
A39: =IF($C39="","",ROW()-3) | B39: 46106 | C39: 东尼电子26.3-4 | D39: 号码牌 | E39: - | F39: 张 | G39: 190 | H39: 1.85 | I39: =IF($C39="","",ROUND(IF($G39="",1,$G39)*N($H39),2)) | J39: =IF($C39="","",IFERROR(VLOOKUP($C39,项目台账!$B:$C,2,0),"※项目不在项目台账里")) | K39: 待打拔产品放置处*30 待专检产品放置处*30 打拔毕产品放置处*30 待包装产品放置处*30
A40: =IF($C40="","",ROW()-3) | B40: 46106 | C40: 东尼电子26.3-4 | D40: 斜纹贴纸（待专检产品放置处、 | E40: 28*5cm | F40: 张 | G40: 120 | H40: 2 | I40: =IF($C40="","",ROUND(IF($G40="",1,$G40)*N($H40),2)) | J40: =IF($C40="","",IFERROR(VLOOKUP($C40,项目台账!$B:$C,2,0),"※项目不在项目台账里"))
A41: =IF($C41="","",ROW()-3) | B41: 46106 | C41: 东尼电子26.3-4 | D41: 标识牌（阀体保养室） | E41: 42*30cm | F41: 块 | G41: 1 | H41: 20 | I41: =IF($C41="","",ROUND(IF($G41="",1,$G41)*N($H41),2)) | J41: =IF($C41="","",IFERROR(VLOOKUP($C41,项目台账!$B:$C,2,0),"※项目不在项目台账里"))
A42: =IF($C42="","",ROW()-3) | B42: 46148 | C42: 东尼电子26.5 | D42: 贴纸（宿舍值日表) | E42: A4户外防水贴纸 | F42: 张 | G42: 330 | H42: 3 | I42: =IF($C42="","",ROUND(IF($G42="",1,$G42)*N($H42),2)) | J42: =IF($C42="","",IFERROR(VLOOKUP($C42,项目台账!$B:$C,2,0),"※项目不在项目台账里"))
A43: =IF($C43="","",ROW()-3) | B43: 46148 | C43: 东尼电子26.5 | D43: 超透彩白彩 | E43: 高50CM 宽70CM | F43: 张 | G43: 2 | H43: 16 | I43: =IF($C43="","",ROUND(IF($G43="",1,$G43)*N($H43),2)) | J43: =IF($C43="","",IFERROR(VLOOKUP($C43,项目台账!$B:$C,2,0),"※项目不在项目台账里"))
A44: =IF($C44="","",ROW()-3) | B44: 46150 | C44: 东尼电子26.5 | D44: 标识牌（固定车位、请勿占用） | E44: 不锈钢 10*70 | F44: 块 | G44: 17 | I44: =IF($C44="","",ROUND(IF($G44="",1,$G44)*N($H44),2)) | J44: =IF($C44="","",IFERROR(VLOOKUP($C44,项目台账!$B:$C,2,0),"※项目不在项目台账里"))
A45: =IF($C45="","",ROW()-3) | B45: 46150 | C45: 东尼电子26.5 | D45: 斜纹贴纸（通风口 禁止遮挡） | E45: 210*150mm | F45: 张 | G45: 50 | H45: 3 | I45: =IF($C45="","",ROUND(IF($G45="",1,$G45)*N($H45),2)) | J45: =IF($C45="","",IFERROR(VLOOKUP($C45,项目台账!$B:$C,2,0),"※项目不在项目台账里"))
A46: =IF($C46="","",ROW()-3) | B46: 46154 | C46: 东尼电子26.5 | D46: 标识牌（异常反馈机制） | E46: 29cmX5cm 1mm亚克力+背胶 | F46: 张 | G46: 30 | H46: 4.2 | I46: =IF($C46="","",ROUND(IF($G46="",1,$G46)*N($H46),2)) | J46: =IF($C46="","",IFERROR(VLOOKUP($C46,项目台账!$B:$C,2,0),"※项目不在项目台账里"))
A47: =IF($C47="","",ROW()-3) | B47: 46154 | C47: 东尼电子26.5 | D47: 标识牌（细心点检） | E47: :14cmX3cm 1mm亚克力+背胶 | F47: 张 | G47: 30 | H47: 1.5 | I47: =IF($C47="","",ROUND(IF($G47="",1,$G47)*N($H47),2)) | J47: =IF($C47="","",IFERROR(VLOOKUP($C47,项目台账!$B:$C,2,0),"※项目不在项目台账里"))
A48: =IF($C48="","",ROW()-3) | B48: 46154 | C48: 东尼电子26.5 | D48: 标识（卷帘门下严禁站人和堆物） | E48: 宽20cm*高80cm 2mm亚克力+背胶 | F48: 张 | G48: 3 | H48: 60 | I48: =IF($C48="","",ROUND(IF($G48="",1,$G48)*N($H48),2)) | J48: =IF($C48="","",IFERROR(VLOOKUP($C48,项目台账!$B:$C,2,0),"※项目不在项目台账里"))
A49: =IF($C49="","",ROW()-3) | B49: 46160 | C49: 东尼电子26.5 | D49: 设备编码标签 | E49: 65*30mm 2mm亚克力+背胶 | F49: 张 | G49: 6 | H49: 1.5 | I49: =IF($C49="","",ROUND(IF($G49="",1,$G49)*N($H49),2)) | J49: =IF($C49="","",IFERROR(VLOOKUP($C49,项目台账!$B:$C,2,0),"※项目不在项目台账里"))
A50: =IF($C50="","",ROW()-3) | B50: 46160 | C50: 东尼电子26.5 | D50: 设备验收合格标签 | E50: 75*23mm 2mm亚克力+背胶 | F50: 张 | G50: 6 | H50: 1.5 | I50: =IF($C50="","",ROUND(IF($G50="",1,$G50)*N($H50),2)) | J50: =IF($C50="","",IFERROR(VLOOKUP($C50,项目台账!$B:$C,2,0),"※项目不在项目台账里"))
A51: =IF($C51="","",ROW()-3) | B51: 46160 | C51: 东尼电子26.5 | D51: 背胶贴膜 | E51: 30*40cm | F51: 块 | G51: 12 | H51: 6 | I51: =IF($C51="","",ROUND(IF($G51="",1,$G51)*N($H51),2)) | J51: =IF($C51="","",IFERROR(VLOOKUP($C51,项目台账!$B:$C,2,0),"※项目不在项目台账里"))
A52: =IF($C52="","",ROW()-3) | B52: 46161 | C52: 东尼电子26.5 | D52: 标识牌（FPCA-课线边物料仓） | E52: 42*30cm | F52: 块 | G52: 1 | H52: 20 | I52: =IF($C52="","",ROUND(IF($G52="",1,$G52)*N($H52),2)) | J52: =IF($C52="","",IFERROR(VLOOKUP($C52,项目台账!$B:$C,2,0),"※项目不在项目台账里"))
A53: =IF($C53="","",ROW()-3) | B53: 46162 | C53: 东尼电子26.5 | D53: 标识牌（专注做事） | E53: 110X200cm 5mm雪弗板覆钢化膜 包安装 | F53: 块 | G53: 1 | H53: 540 | I53: =IF($C53="","",ROUND(IF($G53="",1,$G53)*N($H53),2)) | J53: =IF($C53="","",IFERROR(VLOOKUP($C53,项目台账!$B:$C,2,0),"※项目不在项目台账里"))
A54: =IF($C54="","",ROW()-3) | B54: 46163 | C54: 东尼电子26.5 | D54: 标识牌（连廊通行须知） | E54: 8mmpvc板 0.6*0.9m | F54: 块 | G54: 2 | H54: 60 | I54: =IF($C54="","",ROUND(IF($G54="",1,$G54)*N($H54),2)) | J54: =IF($C54="","",IFERROR(VLOOKUP($C54,项目台账!$B:$C,2,0),"※项目不在项目台账里"))
A55: =IF($C55="","",ROW()-3) | B55: 46167 | C55: 东尼电子26.5 | D55: 斜纹背胶贴（人行通道、推车通道） | E55: 239*30cm | F55: 张 | G55: 2 | H55: 20 | I55: =IF($C55="","",ROUND(IF($G55="",1,$G55)*N($H55),2)) | J55: =IF($C55="","",IFERROR(VLOOKUP($C55,项目台账!$B:$C,2,0),"※项目不在项目台账里"))
A56: =IF($C56="","",ROW()-3) | B56: 46169 | C56: 东尼电子26.5 | D56: 横幅 | E56: 220*50cm | F56: 条 | G56: 1 | H56: 15 | I56: =IF($C56="","",ROUND(IF($G56="",1,$G56)*N($H56),2)) | J56: =IF($C56="","",IFERROR(VLOOKUP($C56,项目台账!$B:$C,2,0),"※项目不在项目台账里"))
... A58: =IF($C58="","",ROW()-3) | B58: 46169 | C58: 东尼电子26.5 | D58: 斜纹背胶贴（人行通道、推车通道） | E58: 239*30cm | F58: 张 | G58: 2 | H58: 20 | I58: =IF($C58="","",ROUND(IF($G58="",1,$G58)*N($H58),2)) | J58: =IF($C58="","",IFERROR(VLOOKUP($C58,项目台账!$B:$C,2,0),"※项目不在项目台账里"))
A59: =IF($C59="","",ROW()-3) | I59: =IF($C59="","",ROUND(IF($G59="",1,$G59)*N($H59),2)) | J59: =IF($C59="","",IFERROR(VLOOKUP($C59,项目台账!$B:$C,2,0),"※项目不在项目台账里"))
A60: =IF($C60="","",ROW()-3) | I60: =IF($C60="","",ROUND(IF($G60="",1,$G60)*N($H60),2)) | J60: =IF($C60="","",IFERROR(VLOOKUP($C60,项目台账!$B:$C,2,0),"※项目不在项目台账里"))
A61: =IF($C61="","",ROW()-3) | I61: =IF($C61="","",ROUND(IF($G61="",1,$G61)*N($H61),2)) | J61: =IF($C61="","",IFERROR(VLOOKUP($C61,项目台账!$B:$C,2,0),"※项目不在项目台账里"))
A62: =IF($C62="","",ROW()-3) | I62: =IF($C62="","",ROUND(IF($G62="",1,$G62)*N($H62),2)) | J62: =IF($C62="","",IFERROR(VLOOKUP($C62,项目台账!$B:$C,2,0),"※项目不在项目台账里"))
A63: =IF($C63="","",ROW()-3) | I63: =IF($C63="","",ROUND(IF($G63="",1,$G63)*N($H63),2)) | J63: =IF($C63="","",IFERROR(VLOOKUP($C63,项目台账!$B:$C,2,0),"※项目不在项目台账里"))
A64: =IF($C64="","",ROW()-3) | I64: =IF($C64="","",ROUND(IF($G64="",1,$G64)*N($H64),2)) | J64: =IF($C64="","",IFERROR(VLOOKUP($C64,项目台账!$B:$C,2,0),"※项目不在项目台账里"))
A65: =IF($C65="","",ROW()-3) | I65: =IF($C65="","",ROUND(IF($G65="",1,$G65)*N($H65),2)) | J65: =IF($C65="","",IFERROR(VLOOKUP($C65,项目台账!$B:$C,2,0),"※项目不在项目台账里"))
A66: =IF($C66="","",ROW()-3) | I66: =IF($C66="","",ROUND(IF($G66="",1,$G66)*N($H66),2)) | J66: =IF($C66="","",IFERROR(VLOOKUP($C66,项目台账!$B:$C,2,0),"※项目不在项目台账里"))
A67: =IF($C67="","",ROW()-3) | I67: =IF($C67="","",ROUND(IF($G67="",1,$G67)*N($H67),2)) | J67: =IF($C67="","",IFERROR(VLOOKUP($C67,项目台账!$B:$C,2,0),"※项目不在项目台账里"))
A68: =IF($C68="","",ROW()-3) | I68: =IF($C68="","",ROUND(IF($G68="",1,$G68)*N($H68),2)) | J68: =IF($C68="","",IFERROR(VLOOKUP($C68,项目台账!$B:$C,2,0),"※项目不在项目台账里"))
A69: =IF($C69="","",ROW()-3) | I69: =IF($C69="","",ROUND(IF($G69="",1,$G69)*N($H69),2)) | J69: =IF($C69="","",IFERROR(VLOOKUP($C69,项目台账!$B:$C,2,0),"※项目不在项目台账里"))
A70: =IF($C70="","",ROW()-3) | I70: =IF($C70="","",ROUND(IF($G70="",1,$G70)*N($H70),2)) | J70: =IF($C70="","",IFERROR(VLOOKUP($C70,项目台账!$B:$C,2,0),"※项目不在项目台账里"))
... A1503: =IF($C1503="","",ROW()-3) | I1503: =IF($C1503="","",ROUND(IF($G1503="",1,$G1503)*N($H1503),2)) | J1503: =IF($C1503="","",IFERROR(VLOOKUP($C1503,项目台账!$B:$C,2,0),"※项目不在项目台账里"))

Sheet 采购单
A1: 采购单 · 采购岗位填
A2: 买的每一笔材料都记一行。注意：登过这里的料，出纳付钱时费用类别要选『付供应商货款』，不然成本会算两遍。
A3: 序号 | B3: 采购日期 ★ | C3: 供应商 ★ | D3: 项目名称 ★ | E3: 材料类别 ★ | F3: 成本归属 | G3: 品名 ★ | H3: 规格 | I3: 单位 | J3: 数量 | K3: 单价 | L3: 金额 | M3: 备注 | N3: 核对
A4: =IF($D4="","",ROW()-3) | B4: 46043 | C4: 炳秀 | D4: 南浔美食城 | E4: 主材 | F4: =IF($D4="","",IFERROR(VLOOKUP($E4,材料归属,2,0),"※材料类别没选")) | G4: 7.5*7.5黑边灯箱型材 | I4: 米 | J4: 146 | K4: 10 | L4: =IF($D4="","",ROUND(IF($J4="",1,$J4)*N($K4),2)) | M4: 原表·主材 | N4: =IF($D4="","",IF(ISNA(MATCH($D4,项目名表,0)),"※项目不在项目台账里",IF($F4="※材料类别没选","※材料类别没选",IF(AND($C4<>"",ISNA(MATCH($C4,供应商表,0))),"※供应商不在基础资料里",""))))
A5: =IF($D5="","",ROW()-3) | B5: 46043 | D5: 南浔美食城 | E5: 主材 | F5: =IF($D5="","",IFERROR(VLOOKUP($E5,材料归属,2,0),"※材料类别没选")) | G5: 25*25方管 | I5: 根 | J5: 29 | K5: 19 | L5: =IF($D5="","",ROUND(IF($J5="",1,$J5)*N($K5),2)) | M5: 原表·主材 | N5: =IF($D5="","",IF(ISNA(MATCH($D5,项目名表,0)),"※项目不在项目台账里",IF($F5="※材料类别没选","※材料类别没选",IF(AND($C5<>"",ISNA(MATCH($C5,供应商表,0))),"※供应商不在基础资料里",""))))
A6: =IF($D6="","",ROW()-3) | B6: 46043 | D6: 南浔美食城 | E6: 主材 | F6: =IF($D6="","",IFERROR(VLOOKUP($E6,材料归属,2,0),"※材料类别没选")) | G6: 反光背板 | I6: 张 | J6: 58 | K6: 19 | L6: =IF($D6="","",ROUND(IF($J6="",1,$J6)*N($K6),2)) | M6: 原表·主材 | N6: =IF($D6="","",IF(ISNA(MATCH($D6,项目名表,0)),"※项目不在项目台账里",IF($F6="※材料类别没选","※材料类别没选",IF(AND($C6<>"",ISNA(MATCH($C6,供应商表,0))),"※供应商不在基础资料里",""))))
A7: =IF($D7="","",ROW()-3) | B7: 46043 | D7: 南浔美食城 | E7: 主材 | F7: =IF($D7="","",IFERROR(VLOOKUP($E7,材料归属,2,0),"※材料类别没选")) | G7: 3000K区块 | I7: 箱 | J7: 500 | K7: 1 | L7: =IF($D7="","",ROUND(IF($J7="",1,$J7)*N($K7),2)) | M7: 原表·主材 | N7: =IF($D7="","",IF(ISNA(MATCH($D7,项目名表,0)),"※项目不在项目台账里",IF($F7="※材料类别没选","※材料类别没选",IF(AND($C7<>"",ISNA(MATCH($C7,供应商表,0))),"※供应商不在基础资料里",""))))
A8: =IF($D8="","",ROW()-3) | B8: 46043 | D8: 南浔美食城 | E8: 主材 | F8: =IF($D8="","",IFERROR(VLOOKUP($E8,材料归属,2,0),"※材料类别没选")) | G8: 7.5*7.5黑边灯箱型材 | I8: 米 | J8: 75 | K8: 10 | L8: =IF($D8="","",ROUND(IF($J8="",1,$J8)*N($K8),2)) | M8: 原表·主材 | N8: =IF($D8="","",IF(ISNA(MATCH($D8,项目名表,0)),"※项目不在项目台账里",IF($F8="※材料类别没选","※材料类别没选",IF(AND($C8<>"",ISNA(MATCH($C8,供应商表,0))),"※供应商不在基础资料里",""))))
A9: =IF($D9="","",ROW()-3) | B9: 46043 | D9: 南浔美食城 | E9: 辅材 | F9: =IF($D9="","",IFERROR(VLOOKUP($E9,材料归属,2,0),"※材料类别没选")) | G9: 12V/10000K灯条 | I9: 根 | J9: 100 | K9: 1.5 | L9: =IF($D9="","",ROUND(IF($J9="",1,$J9)*N($K9),2)) | M9: 原表·辅材 | N9: =IF($D9="","",IF(ISNA(MATCH($D9,项目名表,0)),"※项目不在项目台账里",IF($F9="※材料类别没选","※材料类别没选",IF(AND($C9<>"",ISNA(MATCH($C9,供应商表,0))),"※供应商不在基础资料里",""))))
A10: =IF($D10="","",ROW()-3) | B10: 46043 | D10: 南浔美食城 | E10: 辅材 | F10: =IF($D10="","",IFERROR(VLOOKUP($E10,材料归属,2,0),"※材料类别没选")) | G10: 辅材 | J10: 1 | K10: 500 | L10: =IF($D10="","",ROUND(IF($J10="",1,$J10)*N($K10),2)) | M10: 原表·辅材 | N10: =IF($D10="","",IF(ISNA(MATCH($D10,项目名表,0)),"※项目不在项目台账里",IF($F10="※材料类别没选","※材料类别没选",IF(AND($C10<>"",ISNA(MATCH($C10,供应商表,0))),"※供应商不在基础资料里",""))))
A11: =IF($D11="","",ROW()-3) | B11: 46060 | C11: 一利钢材 | D11: 德清津华钢铁 | E11: 主材 | F11: =IF($D11="","",IFERROR(VLOOKUP($E11,材料归属,2,0),"※材料类别没选")) | G11: 3*3*1.2镀锌方管 | I11: 根 | J11: 25 | K11: 23.52 | L11: =IF($D11="","",ROUND(IF($J11="",1,$J11)*N($K11),2)) | M11: 原表·主材 | N11: =IF($D11="","",IF(ISNA(MATCH($D11,项目名表,0)),"※项目不在项目台账里",IF($F11="※材料类别没选","※材料类别没选",IF(AND($C11<>"",ISNA(MATCH($C11,供应商表,0))),"※供应商不在基础资料里",""))))
A12: =IF($D12="","",ROW()-3) | B12: 46060 | C12: 一利钢材 | D12: 德清津华钢铁 | E12: 主材 | F12: =IF($D12="","",IFERROR(VLOOKUP($E12,材料归属,2,0),"※材料类别没选")) | G12: 4*4*2镀锌角铁 | I12: 根 | J12: 1 | K12: 60 | L12: =IF($D12="","",ROUND(IF($J12="",1,$J12)*N($K12),2)) | M12: 原表·主材 | N12: =IF($D12="","",IF(ISNA(MATCH($D12,项目名表,0)),"※项目不在项目台账里",IF($F12="※材料类别没选","※材料类别没选",IF(AND($C12<>"",ISNA(MATCH($C12,供应商表,0))),"※供应商不在基础资料里",""))))
A13: =IF($D13="","",ROW()-3) | B13: 46060 | C13: 小王加工厂 | D13: 德清津华钢铁 | E13: 主材 | F13: =IF($D13="","",IFERROR(VLOOKUP($E13,材料归属,2,0),"※材料类别没选")) | G13: 550喷绘布 | I13: m² | J13: 184.97 | K13: 8 | L13: =IF($D13="","",ROUND(IF($J13="",1,$J13)*N($K13),2)) | M13: 原表·主材 | N13: =IF($D13="","",IF(ISNA(MATCH($D13,项目名表,0)),"※项目不在项目台账里",IF($F13="※材料类别没选","※材料类别没选",IF(AND($C13<>"",ISNA(MATCH($C13,供应商表,0))),"※供应商不在基础资料里",""))))
A14: =IF($D14="","",ROW()-3) | B14: 46060 | C14: 小王加工厂 | D14: 德清津华钢铁 | E14: 主材 | F14: =IF($D14="","",IFERROR(VLOOKUP($E14,材料归属,2,0),"※材料类别没选")) | G14: 550喷绘布 | I14: m² | J14: 75.43 | K14: 6 | L14: =IF($D14="","",ROUND(IF($J14="",1,$J14)*N($K14),2)) | M14: 原表·主材 | N14: =IF($D14="","",IF(ISNA(MATCH($D14,项目名表,0)),"※项目不在项目台账里",IF($F14="※材料类别没选","※材料类别没选",IF(AND($C14<>"",ISNA(MATCH($C14,供应商表,0))),"※供应商不在基础资料里",""))))
A15: =IF($D15="","",ROW()-3) | B15: 46060 | D15: 德清津华钢铁 | E15: 辅材 | F15: =IF($D15="","",IFERROR(VLOOKUP($E15,材料归属,2,0),"※材料类别没选")) | G15: 车辆+辅材 | I15: 趟 | J15: 1 | K15: 200 | L15: =IF($D15="","",ROUND(IF($J15="",1,$J15)*N($K15),2)) | M15: 原表·辅材 | N15: =IF($D15="","",IF(ISNA(MATCH($D15,项目名表,0)),"※项目不在项目台账里",IF($F15="※材料类别没选","※材料类别没选",IF(AND($C15<>"",ISNA(MATCH($C15,供应商表,0))),"※供应商不在基础资料里",""))))
A16: =IF($D16="","",ROW()-3) | B16: 46083 | C16: 匠心 | D16: 兰溪手擀面 | E16: 主材 | F16: =IF($D16="","",IFERROR(VLOOKUP($E16,材料归属,2,0),"※材料类别没选")) | G16: 发光字 | I16: 套 | J16: 1 | K16: 440 | L16: =IF($D16="","",ROUND(IF($J16="",1,$J16)*N($K16),2)) | M16: 原表·主材 | N16: =IF($D16="","",IF(ISNA(MATCH($D16,项目名表,0)),"※项目不在项目台账里",IF($F16="※材料类别没选","※材料类别没选",IF(AND($C16<>"",ISNA(MATCH($C16,供应商表,0))),"※供应商不在基础资料里",""))))
A17: =IF($D17="","",ROW()-3) | B17: 46083 | D17: 兰溪手擀面 | E17: 辅材 | F17: =IF($D17="","",IFERROR(VLOOKUP($E17,材料归属,2,0),"※材料类别没选")) | G17: 辅材+车辆 | I17: 1 | J17: 1 | K17: 100 | L17: =IF($D17="","",ROUND(IF($J17="",1,$J17)*N($K17),2)) | M17: 原表·辅材 | N17: =IF($D17="","",IF(ISNA(MATCH($D17,项目名表,0)),"※项目不在项目台账里",IF($F17="※材料类别没选","※材料类别没选",IF(AND($C17<>"",ISNA(MATCH($C17,供应商表,0))),"※供应商不在基础资料里",""))))
A18: =IF($D18="","",ROW()-3) | C18: 杭州水尚装饰 | D18: 莫盾服饰 | E18: 主材 | F18: =IF($D18="","",IFERROR(VLOOKUP($E18,材料归属,2,0),"※材料类别没选")) | G18: 烫边软膜 | I18: m² | J18: 34.713 | K18: 20 | L18: =IF($D18="","",ROUND(IF($J18="",1,$J18)*N($K18),2)) | M18: 原表·主材 | N18: =IF($D18="","",IF(ISNA(MATCH($D18,项目名表,0)),"※项目不在项目台账里",IF($F18="※材料类别没选","※材料类别没选",IF(AND($C18<>"",ISNA(MATCH($C18,供应商表,0))),"※供应商不在基础资料里",""))))
A19: =IF($D19="","",ROW()-3) | D19: 莫盾服饰 | E19: 主材 | F19: =IF($D19="","",IFERROR(VLOOKUP($E19,材料归属,2,0),"※材料类别没选")) | G19: 室内6000K区块 | I19: 块 | J19: 750 | K19: 1 | L19: =IF($D19="","",ROUND(IF($J19="",1,$J19)*N($K19),2)) | M19: 原表·主材 | N19: =IF($D19="","",IF(ISNA(MATCH($D19,项目名表,0)),"※项目不在项目台账里",IF($F19="※材料类别没选","※材料类别没选",IF(AND($C19<>"",ISNA(MATCH($C19,供应商表,0))),"※供应商不在基础资料里",""))))
A20: =IF($D20="","",ROW()-3) | D20: 莫盾服饰 | E20: 主材 | F20: =IF($D20="","",IFERROR(VLOOKUP($E20,材料归属,2,0),"※材料类别没选")) | G20: 烫边软膜专用铝型材 | I20: 米 | J20: 25.38 | K20: 8 | L20: =IF($D20="","",ROUND(IF($J20="",1,$J20)*N($K20),2)) | M20: 原表·主材 | N20: =IF($D20="","",IF(ISNA(MATCH($D20,项目名表,0)),"※项目不在项目台账里",IF($F20="※材料类别没选","※材料类别没选",IF(AND($C20<>"",ISNA(MATCH($C20,供应商表,0))),"※供应商不在基础资料里",""))))
A21: =IF($D21="","",ROW()-3) | D21: 莫盾服饰 | E21: 主材 | F21: =IF($D21="","",IFERROR(VLOOKUP($E21,材料归属,2,0),"※材料类别没选")) | G21: 发光字埋线 | I21: 套 | J21: 2 | K21: 200 | L21: =IF($D21="","",ROUND(IF($J21="",1,$J21)*N($K21),2)) | M21: 原表·主材 | N21: =IF($D21="","",IF(ISNA(MATCH($D21,项目名表,0)),"※项目不在项目台账里",IF($F21="※材料类别没选","※材料类别没选",IF(AND($C21<>"",ISNA(MATCH($C21,供应商表,0))),"※供应商不在基础资料里",""))))
A22: =IF($D22="","",ROW()-3) | C22: 盛世大瑞 | D22: 莫盾服饰 | E22: 主材 | F22: =IF($D22="","",IFERROR(VLOOKUP($E22,材料归属,2,0),"※材料类别没选")) | G22: 发光字 | I22: 套 | J22: 2 | K22: 1300 | L22: =IF($D22="","",ROUND(IF($J22="",1,$J22)*N($K22),2)) | M22: 原表·主材 | N22: =IF($D22="","",IF(ISNA(MATCH($D22,项目名表,0)),"※项目不在项目台账里",IF($F22="※材料类别没选","※材料类别没选",IF(AND($C22<>"",ISNA(MATCH($C22,供应商表,0))),"※供应商不在基础资料里",""))))
A23: =IF($D23="","",ROW()-3) | D23: 莫盾服饰 | E23: 辅材 | F23: =IF($D23="","",IFERROR(VLOOKUP($E23,材料归属,2,0),"※材料类别没选")) | G23: 车辆+辅材 | I23: 趟 | J23: 2 | K23: 100 | L23: =IF($D23="","",ROUND(IF($J23="",1,$J23)*N($K23),2)) | M23: 原表·辅材 | N23: =IF($D23="","",IF(ISNA(MATCH($D23,项目名表,0)),"※项目不在项目台账里",IF($F23="※材料类别没选","※材料类别没选",IF(AND($C23<>"",ISNA(MATCH($C23,供应商表,0))),"※供应商不在基础资料里",""))))
A24: =IF($D24="","",ROW()-3) | B24: 46106 | C24: 甄铭 | D24: 君澜服饰 | E24: 主材 | F24: =IF($D24="","",IFERROR(VLOOKUP($E24,材料归属,2,0),"※材料类别没选")) | G24: 发光字 | I24: 套 | J24: 1 | K24: 244 | L24: =IF($D24="","",ROUND(IF($J24="",1,$J24)*N($K24),2)) | M24: 原表·主材 | N24: =IF($D24="","",IF(ISNA(MATCH($D24,项目名表,0)),"※项目不在项目台账里",IF($F24="※材料类别没选","※材料类别没选",IF(AND($C24<>"",ISNA(MATCH($C24,供应商表,0))),"※供应商不在基础资料里",""))))
A25: =IF($D25="","",ROW()-3) | B25: 46106 | C25: 甄铭 | D25: 君澜服饰 | E25: 主材 | F25: =IF($D25="","",IFERROR(VLOOKUP($E25,材料归属,2,0),"※材料类别没选")) | G25: 发光字 | I25: 套 | J25: 1 | K25: 362 | L25: =IF($D25="","",ROUND(IF($J25="",1,$J25)*N($K25),2)) | M25: 原表·主材 | N25: =IF($D25="","",IF(ISNA(MATCH($D25,项目名表,0)),"※项目不在项目台账里",IF($F25="※材料类别没选","※材料类别没选",IF(AND($C25<>"",ISNA(MATCH($C25,供应商表,0))),"※供应商不在基础资料里",""))))
A26: =IF($D26="","",ROW()-3) | B26: 46106 | C26: 炳秀 | D26: 君澜服饰 | E26: 主材 | F26: =IF($D26="","",IFERROR(VLOOKUP($E26,材料归属,2,0),"※材料类别没选")) | G26: 软膜 | J26: 1 | K26: 244 | L26: =IF($D26="","",ROUND(IF($J26="",1,$J26)*N($K26),2)) | M26: 原表·主材 | N26: =IF($D26="","",IF(ISNA(MATCH($D26,项目名表,0)),"※项目不在项目台账里",IF($F26="※材料类别没选","※材料类别没选",IF(AND($C26<>"",ISNA(MATCH($C26,供应商表,0))),"※供应商不在基础资料里",""))))
A27: =IF($D27="","",ROW()-3) | B27: 46106 | C27: 小王 | D27: 君澜服饰 | E27: 主材 | F27: =IF($D27="","",IFERROR(VLOOKUP($E27,材料归属,2,0),"※材料类别没选")) | G27: 2cmpvc字 | J27: 2 | K27: 150 | L27: =IF($D27="","",ROUND(IF($J27="",1,$J27)*N($K27),2)) | M27: 原表·主材 | N27: =IF($D27="","",IF(ISNA(MATCH($D27,项目名表,0)),"※项目不在项目台账里",IF($F27="※材料类别没选","※材料类别没选",IF(AND($C27<>"",ISNA(MATCH($C27,供应商表,0))),"※供应商不在基础资料里",""))))
A28: =IF($D28="","",ROW()-3) | B28: 46106 | C28: 水尚 | D28: 君澜服饰 | E28: 主材 | F28: =IF($D28="","",IFERROR(VLOOKUP($E28,材料归属,2,0),"※材料类别没选")) | G28: 烫边软膜 | J28: 1 | K28: 214 | L28: =IF($D28="","",ROUND(IF($J28="",1,$J28)*N($K28),2)) | M28: 原表·主材 | N28: =IF($D28="","",IF(ISNA(MATCH($D28,项目名表,0)),"※项目不在项目台账里",IF($F28="※材料类别没选","※材料类别没选",IF(AND($C28<>"",ISNA(MATCH($C28,供应商表,0))),"※供应商不在基础资料里",""))))
A29: =IF($D29="","",ROW()-3) | B29: 46106 | C29: 水尚 | D29: 君澜服饰 | E29: 主材 | F29: =IF($D29="","",IFERROR(VLOOKUP($E29,材料归属,2,0),"※材料类别没选")) | G29: 烫边软膜 | J29: 1 | K29: 38 | L29: =IF($D29="","",ROUND(IF($J29="",1,$J29)*N($K29),2)) | M29: 原表·主材 | N29: =IF($D29="","",IF(ISNA(MATCH($D29,项目名表,0)),"※项目不在项目台账里",IF($F29="※材料类别没选","※材料类别没选",IF(AND($C29<>"",ISNA(MATCH($C29,供应商表,0))),"※供应商不在基础资料里",""))))
A30: =IF($D30="","",ROW()-3) | B30: 46106 | D30: 君澜服饰 | E30: 辅材 | F30: =IF($D30="","",IFERROR(VLOOKUP($E30,材料归属,2,0),"※材料类别没选")) | G30: 安装工资 | I30: 工 | J30: 2 | K30: 450 | L30: =IF($D30="","",ROUND(IF($J30="",1,$J30)*N($K30),2)) | M30: 原表·辅材 | N30: =IF($D30="","",IF(ISNA(MATCH($D30,项目名表,0)),"※项目不在项目台账里",IF($F30="※材料类别没选","※材料类别没选",IF(AND($C30<>"",ISNA(MATCH($C30,供应商表,0))),"※供应商不在基础资料里",""))))
A31: =IF($D31="","",ROW()-3) | B31: 46082 | D31: 芭比贝克 | E31: 主材 | F31: =IF($D31="","",IFERROR(VLOOKUP($E31,材料归属,2,0),"※材料类别没选")) | G31: 7.5CM灯箱型材 | I31: 米 | J31: 13.08 | K31: 8 | L31: =IF($D31="","",ROUND(IF($J31="",1,$J31)*N($K31),2)) | M31: 原表·主材 | N31: =IF($D31="","",IF(ISNA(MATCH($D31,项目名表,0)),"※项目不在项目台账里",IF($F31="※材料类别没选","※材料类别没选",IF(AND($C31<>"",ISNA(MATCH($C31,供应商表,0))),"※供应商不在基础资料里",""))))
A32: =IF($D32="","",ROW()-3) | B32: 46082 | D32: 芭比贝克 | E32: 主材 | F32: =IF($D32="","",IFERROR(VLOOKUP($E32,材料归属,2,0),"※材料类别没选")) | G32: 软膜 | I32: m² | J32: 4.2 | K32: 9 | L32: =IF($D32="","",ROUND(IF($J32="",1,$J32)*N($K32),2)) | M32: 原表·主材 | N32: =IF($D32="","",IF(ISNA(MATCH($D32,项目名表,0)),"※项目不在项目台账里",IF($F32="※材料类别没选","※材料类别没选",IF(AND($C32<>"",ISNA(MATCH($C32,供应商表,0))),"※供应商不在基础资料里",""))))
A33: =IF($D33="","",ROW()-3) | B33: 46082 | D33: 芭比贝克 | E33: 主材 | F33: =IF($D33="","",IFERROR(VLOOKUP($E33,材料归属,2,0),"※材料类别没选")) | G33: 灯条 | I33: 根 | J33: 24 | K33: 1.5 | L33: =IF($D33="","",ROUND(IF($J33="",1,$J33)*N($K33),2)) | M33: 原表·主材 | N33: =IF($D33="","",IF(ISNA(MATCH($D33,项目名表,0)),"※项目不在项目台账里",IF($F33="※材料类别没选","※材料类别没选",IF(AND($C33<>"",ISNA(MATCH($C33,供应商表,0))),"※供应商不在基础资料里",""))))
A34: =IF($D34="","",ROW()-3) | B34: 46082 | D34: 芭比贝克 | E34: 主材 | F34: =IF($D34="","",IFERROR(VLOOKUP($E34,材料归属,2,0),"※材料类别没选")) | G34: 背板 | I34: 张 | J34: 2 | K34: 23 | L34: =IF($D34="","",ROUND(IF($J34="",1,$J34)*N($K34),2)) | M34: 原表·主材 | N34: =IF($D34="","",IF(ISNA(MATCH($D34,项目名表,0)),"※项目不在项目台账里",IF($F34="※材料类别没选","※材料类别没选",IF(AND($C34<>"",ISNA(MATCH($C34,供应商表,0))),"※供应商不在基础资料里",""))))
A35: =IF($D35="","",ROW()-3) | B35: 46100 | C35: 灯箱哥 | D35: 铁柱烧烤店 | E35: 主材 | F35: =IF($D35="","",IFERROR(VLOOKUP($E35,材料归属,2,0),"※材料类别没选")) | G35: 3m布 | I35: 张 | J35: 1 | K35: 741 | L35: =IF($D35="","",ROUND(IF($J35="",1,$J35)*N($K35),2)) | M35: 原表·主材 | N35: =IF($D35="","",IF(ISNA(MATCH($D35,项目名表,0)),"※项目不在项目台账里",IF($F35="※材料类别没选","※材料类别没选",IF(AND($C35<>"",ISNA(MATCH($C35,供应商表,0))),"※供应商不在基础资料里",""))))
A36: =IF($D36="","",ROW()-3) | B36: 46100 | D36: 铁柱烧烤店 | E36: 主材 | F36: =IF($D36="","",IFERROR(VLOOKUP($E36,材料归属,2,0),"※材料类别没选")) | G36: 2*4方管 | I36: 根 | J36: 13 | K36: 28 | L36: =IF($D36="","",ROUND(IF($J36="",1,$J36)*N($K36),2)) | M36: 原表·主材 | N36: =IF($D36="","",IF(ISNA(MATCH($D36,项目名表,0)),"※项目不在项目台账里",IF($F36="※材料类别没选","※材料类别没选",IF(AND($C36<>"",ISNA(MATCH($C36,供应商表,0))),"※供应商不在基础资料里",""))))
A37: =IF($D37="","",ROW()-3) | B37: 46100 | D37: 铁柱烧烤店 | E37: 主材 | F37: =IF($D37="","",IFERROR(VLOOKUP($E37,材料归属,2,0),"※材料类别没选")) | G37: 3*3方管 | I37: 根 | J37: 6 | K37: 25 | L37: =IF($D37="","",ROUND(IF($J37="",1,$J37)*N($K37),2)) | M37: 原表·主材 | N37: =IF($D37="","",IF(ISNA(MATCH($D37,项目名表,0)),"※项目不在项目台账里",IF($F37="※材料类别没选","※材料类别没选",IF(AND($C37<>"",ISNA(MATCH($C37,供应商表,0))),"※供应商不在基础资料里",""))))
A38: =IF($D38="","",ROW()-3) | B38: 46100 | D38: 铁柱烧烤店 | E38: 主材 | F38: =IF($D38="","",IFERROR(VLOOKUP($E38,材料归属,2,0),"※材料类别没选")) | G38: 3mm铝塑板 | I38: 张 | J38: 2 | K38: 65 | L38: =IF($D38="","",ROUND(IF($J38="",1,$J38)*N($K38),2)) | M38: 原表·主材 | N38: =IF($D38="","",IF(ISNA(MATCH($D38,项目名表,0)),"※项目不在项目台账里",IF($F38="※材料类别没选","※材料类别没选",IF(AND($C38<>"",ISNA(MATCH($C38,供应商表,0))),"※供应商不在基础资料里",""))))
A39: =IF($D39="","",ROW()-3) | B39: 46100 | D39: 铁柱烧烤店 | E39: 主材 | F39: =IF($D39="","",IFERROR(VLOOKUP($E39,材料归属,2,0),"※材料类别没选")) | G39: 不锈钢包边 | I39: 米 | J39: 28.42 | K39: 10.1 | L39: =IF($D39="","",ROUND(IF($J39="",1,$J39)*N($K39),2)) | M39: 原表·主材 | N39: =IF($D39="","",IF(ISNA(MATCH($D39,项目名表,0)),"※项目不在项目台账里",IF($F39="※材料类别没选","※材料类别没选",IF(AND($C39<>"",ISNA(MATCH($C39,供应商表,0))),"※供应商不在基础资料里",""))))
A40: =IF($D40="","",ROW()-3) | B40: 46100 | D40: 铁柱烧烤店 | E40: 主材 | F40: =IF($D40="","",IFERROR(VLOOKUP($E40,材料归属,2,0),"※材料类别没选")) | G40: 防雨区块 | I40: 块 | J40: 480 | K40: 1.6 | L40: =IF($D40="","",ROUND(IF($J40="",1,$J40)*N($K40),2)) | M40: 原表·主材 | N40: =IF($D40="","",IF(ISNA(MATCH($D40,项目名表,0)),"※项目不在项目台账里",IF($F40="※材料类别没选","※材料类别没选",IF(AND($C40<>"",ISNA(MATCH($C40,供应商表,0))),"※供应商不在基础资料里",""))))
A41: =IF($D41="","",ROW()-3) | B41: 46100 | D41: 铁柱烧烤店 | E41: 主材 | F41: =IF($D41="","",IFERROR(VLOOKUP($E41,材料归属,2,0),"※材料类别没选")) | G41: 8mmpvc板 | I41: 张 | J41: 8 | K41: 40 | L41: =IF($D41="","",ROUND(IF($J41="",1,$J41)*N($K41),2)) | M41: 原表·主材 | N41: =IF($D41="","",IF(ISNA(MATCH($D41,项目名表,0)),"※项目不在项目台账里",IF($F41="※材料类别没选","※材料类别没选",IF(AND($C41<>"",ISNA(MATCH($C41,供应商表,0))),"※供应商不在基础资料里",""))))
A42: =IF($D42="","",ROW()-3) | B42: 46100 | D42: 铁柱烧烤店 | E42: 辅材 | F42: =IF($D42="","",IFERROR(VLOOKUP($E42,材料归属,2,0),"※材料类别没选")) | G42: 辅材+车辆 | I42: 趟 | J42: 2 | K42: 150 | L42: =IF($D42="","",ROUND(IF($J42="",1,$J42)*N($K42),2)) | M42: 原表·辅材 | N42: =IF($D42="","",IF(ISNA(MATCH($D42,项目名表,0)),"※项目不在项目台账里",IF($F42="※材料类别没选","※材料类别没选",IF(AND($C42<>"",ISNA(MATCH($C42,供应商表,0))),"※供应商不在基础资料里",""))))
A43: =IF($D43="","",ROW()-3) | B43: 46084 | C43: 盛世大瑞 | D43: 钟管熟食店 | E43: 主材 | F43: =IF($D43="","",IFERROR(VLOOKUP($E43,材料归属,2,0),"※材料类别没选")) | G43: 发光字 | I43: 套 | J43: 1 | K43: 1425 | L43: =IF($D43="","",ROUND(IF($J43="",1,$J43)*N($K43),2)) | M43: 原表·主材 | N43: =IF($D43="","",IF(ISNA(MATCH($D43,项目名表,0)),"※项目不在项目台账里",IF($F43="※材料类别没选","※材料类别没选",IF(AND($C43<>"",ISNA(MATCH($C43,供应商表,0))),"※供应商不在基础资料里",""))))
A44: =IF($D44="","",ROW()-3) | B44: 46084 | D44: 钟管熟食店 | E44: 主材 | F44: =IF($D44="","",IFERROR(VLOOKUP($E44,材料归属,2,0),"※材料类别没选")) | G44: 铝塑板 | I44: 张 | J44: 24 | K44: 90 | L44: =IF($D44="","",ROUND(IF($J44="",1,$J44)*N($K44),2)) | M44: 原表·主材 | N44: =IF($D44="","",IF(ISNA(MATCH($D44,项目名表,0)),"※项目不在项目台账里",IF($F44="※材料类别没选","※材料类别没选",IF(AND($C44<>"",ISNA(MATCH($C44,供应商表,0))),"※供应商不在基础资料里",""))))
A45: =IF($D45="","",ROW()-3) | B45: 46084 | D45: 钟管熟食店 | E45: 主材 | F45: =IF($D45="","",IFERROR(VLOOKUP($E45,材料归属,2,0),"※材料类别没选")) | G45: 4*4方管 | I45: 根 | J45: 6 | K45: 60 | L45: =IF($D45="","",ROUND(IF($J45="",1,$J45)*N($K45),2)) | M45: 原表·主材 | N45: =IF($D45="","",IF(ISNA(MATCH($D45,项目名表,0)),"※项目不在项目台账里",IF($F45="※材料类别没选","※材料类别没选",IF(AND($C45<>"",ISNA(MATCH($C45,供应商表,0))),"※供应商不在基础资料里",""))))
A46: =IF($D46="","",ROW()-3) | B46: 46084 | D46: 钟管熟食店 | E46: 主材 | F46: =IF($D46="","",IFERROR(VLOOKUP($E46,材料归属,2,0),"※材料类别没选")) | G46: 2*4方管 | J46: 14 | K46: 28 | L46: =IF($D46="","",ROUND(IF($J46="",1,$J46)*N($K46),2)) | M46: 原表·主材 | N46: =IF($D46="","",IF(ISNA(MATCH($D46,项目名表,0)),"※项目不在项目台账里",IF($F46="※材料类别没选","※材料类别没选",IF(AND($C46<>"",ISNA(MATCH($C46,供应商表,0))),"※供应商不在基础资料里",""))))
A47: =IF($D47="","",ROW()-3) | B47: 46084 | D47: 钟管熟食店 | E47: 主材 | F47: =IF($D47="","",IFERROR(VLOOKUP($E47,材料归属,2,0),"※材料类别没选")) | G47: 2*4方管 | J47: 25 | K47: 27 | L47: =IF($D47="","",ROUND(IF($J47="",1,$J47)*N($K47),2)) | M47: 原表·主材 | N47: =IF($D47="","",IF(ISNA(MATCH($D47,项目名表,0)),"※项目不在项目台账里",IF($F47="※材料类别没选","※材料类别没选",IF(AND($C47<>"",ISNA(MATCH($C47,供应商表,0))),"※供应商不在基础资料里",""))))
A48: =IF($D48="","",ROW()-3) | B48: 46084 | D48: 钟管熟食店 | E48: 主材 | F48: =IF($D48="","",IFERROR(VLOOKUP($E48,材料归属,2,0),"※材料类别没选")) | G48: 3*3方管 | J48: 10 | K48: 24 | L48: =IF($D48="","",ROUND(IF($J48="",1,$J48)*N($K48),2)) | M48: 原表·主材 | N48: =IF($D48="","",IF(ISNA(MATCH($D48,项目名表,0)),"※项目不在项目台账里",IF($F48="※材料类别没选","※材料类别没选",IF(AND($C48<>"",ISNA(MATCH($C48,供应商表,0))),"※供应商不在基础资料里",""))))
A49: =IF($D49="","",ROW()-3) | B49: 46084 | D49: 钟管熟食店 | E49: 主材 | F49: =IF($D49="","",IFERROR(VLOOKUP($E49,材料归属,2,0),"※材料类别没选")) | G49: 4*4角码 | I49: 只 | J49: 50 | K49: 0.7 | L49: =IF($D49="","",ROUND(IF($J49="",1,$J49)*N($K49),2)) | M49: 原表·主材 | N49: =IF($D49="","",IF(ISNA(MATCH($D49,项目名表,0)),"※项目不在项目台账里",IF($F49="※材料类别没选","※材料类别没选",IF(AND($C49<>"",ISNA(MATCH($C49,供应商表,0))),"※供应商不在基础资料里",""))))
A50: =IF($D50="","",ROW()-3) | B50: 46084 | D50: 钟管熟食店 | E50: 主材 | F50: =IF($D50="","",IFERROR(VLOOKUP($E50,材料归属,2,0),"※材料类别没选")) | G50: 5*5角码 | I50: 只 | J50: 50 | K50: 1 | L50: =IF($D50="","",ROUND(IF($J50="",1,$J50)*N($K50),2)) | M50: 原表·主材 | N50: =IF($D50="","",IF(ISNA(MATCH($D50,项目名表,0)),"※项目不在项目台账里",IF($F50="※材料类别没选","※材料类别没选",IF(AND($C50<>"",ISNA(MATCH($C50,供应商表,0))),"※供应商不在基础资料里",""))))
A51: =IF($D51="","",ROW()-3) | B51: 46084 | D51: 钟管熟食店 | E51: 主材 | F51: =IF($D51="","",IFERROR(VLOOKUP($E51,材料归属,2,0),"※材料类别没选")) | G51: 超薄灯箱（80*65） | I51: 块 | J51: 6 | K51: 136 | L51: =IF($D51="","",ROUND(IF($J51="",1,$J51)*N($K51),2)) | M51: 原表·主材 | N51: =IF($D51="","",IF(ISNA(MATCH($D51,项目名表,0)),"※项目不在项目台账里",IF($F51="※材料类别没选","※材料类别没选",IF(AND($C51<>"",ISNA(MATCH($C51,供应商表,0))),"※供应商不在基础资料里",""))))
A52: =IF($D52="","",ROW()-3) | B52: 46084 | D52: 钟管熟食店 | E52: 辅材 | F52: =IF($D52="","",IFERROR(VLOOKUP($E52,材料归属,2,0),"※材料类别没选")) | G52: 筒灯 | I52: 只 | J52: 8 | K52: 15 | L52: =IF($D52="","",ROUND(IF($J52="",1,$J52)*N($K52),2)) | M52: 原表·辅材 | N52: =IF($D52="","",IF(ISNA(MATCH($D52,项目名表,0)),"※项目不在项目台账里",IF($F52="※材料类别没选","※材料类别没选",IF(AND($C52<>"",ISNA(MATCH($C52,供应商表,0))),"※供应商不在基础资料里",""))))
A53: =IF($D53="","",ROW()-3) | B53: 46084 | D53: 钟管熟食店 | E53: 辅材 | F53: =IF($D53="","",IFERROR(VLOOKUP($E53,材料归属,2,0),"※材料类别没选")) | G53: 双面胶 | I53: 箱 | J53: 1 | K53: 120 | L53: =IF($D53="","",ROUND(IF($J53="",1,$J53)*N($K53),2)) | M53: 原表·辅材 | N53: =IF($D53="","",IF(ISNA(MATCH($D53,项目名表,0)),"※项目不在项目台账里",IF($F53="※材料类别没选","※材料类别没选",IF(AND($C53<>"",ISNA(MATCH($C53,供应商表,0))),"※供应商不在基础资料里",""))))
A54: =IF($D54="","",ROW()-3) | B54: 46084 | D54: 钟管熟食店 | E54: 辅材 | F54: =IF($D54="","",IFERROR(VLOOKUP($E54,材料归属,2,0),"※材料类别没选")) | G54: 结构胶 | I54: 箱 | J54: 1 | K54: 190 | L54: =IF($D54="","",ROUND(IF($J54="",1,$J54)*N($K54),2)) | M54: 原表·辅材 | N54: =IF($D54="","",IF(ISNA(MATCH($D54,项目名表,0)),"※项目不在项目台账里",IF($F54="※材料类别没选","※材料类别没选",IF(AND($C54<>"",ISNA(MATCH($C54,供应商表,0))),"※供应商不在基础资料里",""))))
A55: =IF($D55="","",ROW()-3) | B55: 46084 | D55: 钟管熟食店 | E55: 辅材 | F55: =IF($D55="","",IFERROR(VLOOKUP($E55,材料归属,2,0),"※材料类别没选")) | G55: 12防雨电源 | I55: 台 | J55: 4 | K55: 30 | L55: =IF($D55="","",ROUND(IF($J55="",1,$J55)*N($K55),2)) | M55: 原表·辅材 | N55: =IF($D55="","",IF(ISNA(MATCH($D55,项目名表,0)),"※项目不在项目台账里",IF($F55="※材料类别没选","※材料类别没选",IF(AND($C55<>"",ISNA(MATCH($C55,供应商表,0))),"※供应商不在基础资料里",""))))
A56: =IF($D56="","",ROW()-3) | B56: 46084 | D56: 钟管熟食店 | E56: 辅材 | F56: =IF($D56="","",IFERROR(VLOOKUP($E56,材料归属,2,0),"※材料类别没选")) | G56: 24防雨电源 | I56: 台 | J56: 2 | K56: 30 | L56: =IF($D56="","",ROUND(IF($J56="",1,$J56)*N($K56),2)) | M56: 原表·辅材 | N56: =IF($D56="","",IF(ISNA(MATCH($D56,项目名表,0)),"※项目不在项目台账里",IF($F56="※材料类别没选","※材料类别没选",IF(AND($C56<>"",ISNA(MATCH($C56,供应商表,0))),"※供应商不在基础资料里",""))))
A57: =IF($D57="","",ROW()-3) | B57: 46084 | D57: 钟管熟食店 | E57: 辅材 | F57: =IF($D57="","",IFERROR(VLOOKUP($E57,材料归属,2,0),"※材料类别没选")) | G57: 车辆+辅材 | J57: 2 | K57: 200 | L57: =IF($D57="","",ROUND(IF($J57="",1,$J57)*N($K57),2)) | M57: 原表·辅材 | N57: =IF($D57="","",IF(ISNA(MATCH($D57,项目名表,0)),"※项目不在项目台账里",IF($F57="※材料类别没选","※材料类别没选",IF(AND($C57<>"",ISNA(MATCH($C57,供应商表,0))),"※供应商不在基础资料里",""))))
A58: =IF($D58="","",ROW()-3) | B58: 46100 | D58: 螺有名灯箱门头 | E58: 主材 | F58: =IF($D58="","",IFERROR(VLOOKUP($E58,材料归属,2,0),"※材料类别没选")) | G58: 7.5CM黑色型材 | I58: 米 | J58: 10.9 | K58: 8 | L58: =IF($D58="","",ROUND(IF($J58="",1,$J58)*N($K58),2)) | M58: 原表·主材 | N58: =IF($D58="","",IF(ISNA(MATCH($D58,项目名表,0)),"※项目不在项目台账里",IF($F58="※材料类别没选","※材料类别没选",IF(AND($C58<>"",ISNA(MATCH($C58,供应商表,0))),"※供应商不在基础资料里",""))))
A59: =IF($D59="","",ROW()-3) | B59: 46100 | D59: 螺有名灯箱门头 | E59: 主材 | F59: =IF($D59="","",IFERROR(VLOOKUP($E59,材料归属,2,0),"※材料类别没选")) | G59: 反光板 | I59: 张 | J59: 3 | K59: 20 | L59: =IF($D59="","",ROUND(IF($J59="",1,$J59)*N($K59),2)) | M59: 原表·主材 | N59: =IF($D59="","",IF(ISNA(MATCH($D59,项目名表,0)),"※项目不在项目台账里",IF($F59="※材料类别没选","※材料类别没选",IF(AND($C59<>"",ISNA(MATCH($C59,供应商表,0))),"※供应商不在基础资料里",""))))
A60: =IF($D60="","",ROW()-3) | B60: 46100 | D60: 螺有名灯箱门头 | E60: 主材 | F60: =IF($D60="","",IFERROR(VLOOKUP($E60,材料归属,2,0),"※材料类别没选")) | G60: 220V防雨灯条 | I60: 条 | J60: 36 | K60: 2.4 | L60: =IF($D60="","",ROUND(IF($J60="",1,$J60)*N($K60),2)) | M60: 原表·主材 | N60: =IF($D60="","",IF(ISNA(MATCH($D60,项目名表,0)),"※项目不在项目台账里",IF($F60="※材料类别没选","※材料类别没选",IF(AND($C60<>"",ISNA(MATCH($C60,供应商表,0))),"※供应商不在基础资料里",""))))
A61: =IF($D61="","",ROW()-3) | B61: 46100 | C61: 炳秀 | D61: 螺有名灯箱门头 | E61: 主材 | F61: =IF($D61="","",IFERROR(VLOOKUP($E61,材料归属,2,0),"※材料类别没选")) | G61: 软膜 | I61: 张 | J61: 1 | K61: 59 | L61: =IF($D61="","",ROUND(IF($J61="",1,$J61)*N($K61),2)) | M61: 原表·主材 | N61: =IF($D61="","",IF(ISNA(MATCH($D61,项目名表,0)),"※项目不在项目台账里",IF($F61="※材料类别没选","※材料类别没选",IF(AND($C61<>"",ISNA(MATCH($C61,供应商表,0))),"※供应商不在基础资料里",""))))
A62: =IF($D62="","",ROW()-3) | B62: 46100 | D62: 螺有名灯箱门头 | E62: 辅材 | F62: =IF($D62="","",IFERROR(VLOOKUP($E62,材料归属,2,0),"※材料类别没选")) | G62: 辅材+车辆 | I62: 趟 | J62: 1 | K62: 100 | L62: =IF($D62="","",ROUND(IF($J62="",1,$J62)*N($K62),2)) | M62: 原表·辅材 | N62: =IF($D62="","",IF(ISNA(MATCH($D62,项目名表,0)),"※项目不在项目台账里",IF($F62="※材料类别没选","※材料类别没选",IF(AND($C62<>"",ISNA(MATCH($C62,供应商表,0))),"※供应商不在基础资料里",""))))
A63: =IF($D63="","",ROW()-3) | B63: 46102 | D63: 汕味杏花室内项目 | E63: 主材 | F63: =IF($D63="","",IFERROR(VLOOKUP($E63,材料归属,2,0),"※材料类别没选")) | G63: 6.5cm黑色室内软膜灯箱型材 | I63: 米 | J63: 30.1 | K63: 10 | L63: =IF($D63="","",ROUND(IF($J63="",1,$J63)*N($K63),2)) | M63: 原表·主材 | N63: =IF($D63="","",IF(ISNA(MATCH($D63,项目名表,0)),"※项目不在项目台账里",IF($F63="※材料类别没选","※材料类别没选",IF(AND($C63<>"",ISNA(MATCH($C63,供应商表,0))),"※供应商不在基础资料里",""))))
A64: =IF($D64="","",ROW()-3) | B64: 46102 | D64: 汕味杏花室内项目 | E64: 主材 | F64: =IF($D64="","",IFERROR(VLOOKUP($E64,材料归属,2,0),"※材料类别没选")) | G64: 发光字 | I64: 套 | J64: 1 | K64: 705 | L64: =IF($D64="","",ROUND(IF($J64="",1,$J64)*N($K64),2)) | M64: 原表·主材 | N64: =IF($D64="","",IF(ISNA(MATCH($D64,项目名表,0)),"※项目不在项目台账里",IF($F64="※材料类别没选","※材料类别没选",IF(AND($C64<>"",ISNA(MATCH($C64,供应商表,0))),"※供应商不在基础资料里",""))))
A65: =IF($D65="","",ROW()-3) | B65: 46102 | D65: 汕味杏花室内项目 | E65: 主材 | F65: =IF($D65="","",IFERROR(VLOOKUP($E65,材料归属,2,0),"※材料类别没选")) | G65: 软膜 | I65: m² | J65: 1 | K65: 48 | L65: =IF($D65="","",ROUND(IF($J65="",1,$J65)*N($K65),2)) | M65: 原表·主材 原表数量0.0×单价117.0，与金额对不上，已按金额入账 | N65: =IF($D65="","",IF(ISNA(MATCH($D65,项目名表,0)),"※项目不在项目台账里",IF($F65="※材料类别没选","※材料类别没选",IF(AND($C65<>"",ISNA(MATCH($C65,供应商表,0))),"※供应商不在基础资料里",""))))
A66: =IF($D66="","",ROW()-3) | B66: 46102 | D66: 汕味杏花室内项目 | E66: 主材 | F66: =IF($D66="","",IFERROR(VLOOKUP($E66,材料归属,2,0),"※材料类别没选")) | G66: 室外亚克力灯箱 | I66: 套 | J66: 1 | K66: 740 | L66: =IF($D66="","",ROUND(IF($J66="",1,$J66)*N($K66),2)) | M66: 原表·主材 原表数量2.0×单价740.0，与金额对不上，已按金额入账 | N66: =IF($D66="","",IF(ISNA(MATCH($D66,项目名表,0)),"※项目不在项目台账里",IF($F66="※材料类别没选","※材料类别没选",IF(AND($C66<>"",ISNA(MATCH($C66,供应商表,0))),"※供应商不在基础资料里",""))))
A67: =IF($D67="","",ROW()-3) | B67: 46102 | D67: 汕味杏花室内项目 | E67: 主材 | F67: =IF($D67="","",IFERROR(VLOOKUP($E67,材料归属,2,0),"※材料类别没选")) | G67: PVC板 | I67: 块 | J67: 7 | K67: 25 | L67: =IF($D67="","",ROUND(IF($J67="",1,$J67)*N($K67),2)) | M67: 原表·主材 | N67: =IF($D67="","",IF(ISNA(MATCH($D67,项目名表,0)),"※项目不在项目台账里",IF($F67="※材料类别没选","※材料类别没选",IF(AND($C67<>"",ISNA(MATCH($C67,供应商表,0))),"※供应商不在基础资料里",""))))
A68: =IF($D68="","",ROW()-3) | B68: 46102 | D68: 汕味杏花室内项目 | E68: 主材 | F68: =IF($D68="","",IFERROR(VLOOKUP($E68,材料归属,2,0),"※材料类别没选")) | G68: 2.2mm亚克力覆8mm雪弗板 | J68: 1 | K68: 681 | L68: =IF($D68="","",ROUND(IF($J68="",1,$J68)*N($K68),2)) | M68: 原表·主材 | N68: =IF($D68="","",IF(ISNA(MATCH($D68,项目名表,0)),"※项目不在项目台账里",IF($F68="※材料类别没选","※材料类别没选",IF(AND($C68<>"",ISNA(MATCH($C68,供应商表,0))),"※供应商不在基础资料里",""))))
A69: =IF($D69="","",ROW()-3) | B69: 46102 | D69: 汕味杏花室内项目 | E69: 主材 | F69: =IF($D69="","",IFERROR(VLOOKUP($E69,材料归属,2,0),"※材料类别没选")) | G69: 2.2mm亚克力覆8mm雪弗板 | J69: 1 | K69: 35.2 | L69: =IF($D69="","",ROUND(IF($J69="",1,$J69)*N($K69),2)) | M69: 原表·主材 | N69: =IF($D69="","",IF(ISNA(MATCH($D69,项目名表,0)),"※项目不在项目台账里",IF($F69="※材料类别没选","※材料类别没选",IF(AND($C69<>"",ISNA(MATCH($C69,供应商表,0))),"※供应商不在基础资料里",""))))
A70: =IF($D70="","",ROW()-3) | B70: 46102 | D70: 汕味杏花室内项目 | E70: 主材 | F70: =IF($D70="","",IFERROR(VLOOKUP($E70,材料归属,2,0),"※材料类别没选")) | G70: 写真 | J70: 2 | K70: 6.24 | L70: =IF($D70="","",ROUND(IF($J70="",1,$J70)*N($K70),2)) | M70: 原表·主材 | N70: =IF($D70="","",IF(ISNA(MATCH($D70,项目名表,0)),"※项目不在项目台账里",IF($F70="※材料类别没选","※材料类别没选",IF(AND($C70<>"",ISNA(MATCH($C70,供应商表,0))),"※供应商不在基础资料里",""))))
A71: =IF($D71="","",ROW()-3) | B71: 46102 | D71: 汕味杏花室内项目 | E71: 主材 | F71: =IF($D71="","",IFERROR(VLOOKUP($E71,材料归属,2,0),"※材料类别没选")) | G71: 写真 | J71: 2 | K71: 30 | L71: =IF($D71="","",ROUND(IF($J71="",1,$J71)*N($K71),2)) | M71: 原表·主材 | N71: =IF($D71="","",IF(ISNA(MATCH($D71,项目名表,0)),"※项目不在项目台账里",IF($F71="※材料类别没选","※材料类别没选",IF(AND($C71<>"",ISNA(MATCH($C71,供应商表,0))),"※供应商不在基础资料里",""))))
A72: =IF($D72="","",ROW()-3) | B72: 46102 | D72: 汕味杏花室内项目 | E72: 辅材 | F72: =IF($D72="","",IFERROR(VLOOKUP($E72,材料归属,2,0),"※材料类别没选")) | G72: 车辆+辅材 | I72: 趟 | J72: 2 | K72: 100 | L72: =IF($D72="","",ROUND(IF($J72="",1,$J72)*N($K72),2)) | M72: 原表·辅材 | N72: =IF($D72="","",IF(ISNA(MATCH($D72,项目名表,0)),"※项目不在项目台账里",IF($F72="※材料类别没选","※材料类别没选",IF(AND($C72<>"",ISNA(MATCH($C72,供应商表,0))),"※供应商不在基础资料里",""))))
A73: =IF($D73="","",ROW()-3) | B73: 46102 | D73: 汕味杏花室内项目 | E73: 辅材 | F73: =IF($D73="","",IFERROR(VLOOKUP($E73,材料归属,2,0),"※材料类别没选")) | G73: 室内灯条 | I73: 条 | J73: 75 | K73: 1.65 | L73: =IF($D73="","",ROUND(IF($J73="",1,$J73)*N($K73),2)) | M73: 原表·辅材 | N73: =IF($D73="","",IF(ISNA(MATCH($D73,项目名表,0)),"※项目不在项目台账里",IF($F73="※材料类别没选","※材料类别没选",IF(AND($C73<>"",ISNA(MATCH($C73,供应商表,0))),"※供应商不在基础资料里",""))))
A74: =IF($D74="","",ROW()-3) | B74: 46102 | D74: 汕味杏花室内项目 | E74: 辅材 | F74: =IF($D74="","",IFERROR(VLOOKUP($E74,材料归属,2,0),"※材料类别没选")) | G74: 12v室内电源 | I74: 块 | J74: 1 | K74: 30 | L74: =IF($D74="","",ROUND(IF($J74="",1,$J74)*N($K74),2)) | M74: 原表·辅材 | N74: =IF($D74="","",IF(ISNA(MATCH($D74,项目名表,0)),"※项目不在项目台账里",IF($F74="※材料类别没选","※材料类别没选",IF(AND($C74<>"",ISNA(MATCH($C74,供应商表,0))),"※供应商不在基础资料里",""))))
A75: =IF($D75="","",ROW()-3) | B75: 46102 | D75: 汕味杏花室内项目 | E75: 辅材 | F75: =IF($D75="","",IFERROR(VLOOKUP($E75,材料归属,2,0),"※材料类别没选")) | G75: 腰条 | I75: 米 | J75: 1 | K75: 48 | L75: =IF($D75="","",ROUND(IF($J75="",1,$J75)*N($K75),2)) | M75: 原表·辅材 | N75: =IF($D75="","",IF(ISNA(MATCH($D75,项目名表,0)),"※项目不在项目台账里",IF($F75="※材料类别没选","※材料类别没选",IF(AND($C75<>"",ISNA(MATCH($C75,供应商表,0))),"※供应商不在基础资料里",""))))
A76: =IF($D76="","",ROW()-3) | B76: 46086 | D76: 双林面馆-滨河路 | E76: 主材 | F76: =IF($D76="","",IFERROR(VLOOKUP($E76,材料归属,2,0),"※材料类别没选")) | G76: 7.5黑色型材 | I76: 米 | J76: 28.94 | K76: 10 | L76: =IF($D76="","",ROUND(IF($J76="",1,$J76)*N($K76),2)) | M76: 原表·主材 | N76: =IF($D76="","",IF(ISNA(MATCH($D76,项目名表,0)),"※项目不在项目台账里",IF($F76="※材料类别没选","※材料类别没选",IF(AND($C76<>"",ISNA(MATCH($C76,供应商表,0))),"※供应商不在基础资料里",""))))
A77: =IF($D77="","",ROW()-3) | B77: 46086 | D77: 双林面馆-滨河路 | E77: 主材 | F77: =IF($D77="","",IFERROR(VLOOKUP($E77,材料归属,2,0),"※材料类别没选")) | G77: 2.5*2.5钢管 | I77: 根 | J77: 5 | K77: 19 | L77: =IF($D77="","",ROUND(IF($J77="",1,$J77)*N($K77),2)) | M77: 原表·主材 | N77: =IF($D77="","",IF(ISNA(MATCH($D77,项目名表,0)),"※项目不在项目台账里",IF($F77="※材料类别没选","※材料类别没选",IF(AND($C77<>"",ISNA(MATCH($C77,供应商表,0))),"※供应商不在基础资料里",""))))
A78: =IF($D78="","",ROW()-3) | B78: 46086 | D78: 双林面馆-滨河路 | E78: 主材 | F78: =IF($D78="","",IFERROR(VLOOKUP($E78,材料归属,2,0),"※材料类别没选")) | G78: 背板 | I78: 张 | J78: 5 | K78: 20 | L78: =IF($D78="","",ROUND(IF($J78="",1,$J78)*N($K78),2)) | M78: 原表·主材 | N78: =IF($D78="","",IF(ISNA(MATCH($D78,项目名表,0)),"※项目不在项目台账里",IF($F78="※材料类别没选","※材料类别没选",IF(AND($C78<>"",ISNA(MATCH($C78,供应商表,0))),"※供应商不在基础资料里",""))))
A79: =IF($D79="","",ROW()-3) | B79: 46086 | D79: 双林面馆-滨河路 | E79: 主材 | F79: =IF($D79="","",IFERROR(VLOOKUP($E79,材料归属,2,0),"※材料类别没选")) | G79: 软膜 | I79: 张 | J79: 1 | K79: 115 | L79: =IF($D79="","",ROUND(IF($J79="",1,$J79)*N($K79),2)) | M79: 原表·主材 | N79: =IF($D79="","",IF(ISNA(MATCH($D79,项目名表,0)),"※项目不在项目台账里",IF($F79="※材料类别没选","※材料类别没选",IF(AND($C79<>"",ISNA(MATCH($C79,供应商表,0))),"※供应商不在基础资料里",""))))
A80: =IF($D80="","",ROW()-3) | B80: 46086 | D80: 双林面馆-滨河路 | E80: 辅材 | F80: =IF($D80="","",IFERROR(VLOOKUP($E80,材料归属,2,0),"※材料类别没选")) | G80: 220v室外防雨灯条 | I80: 条 | J80: 55 | K80: 2.4 | L80: =IF($D80="","",ROUND(IF($J80="",1,$J80)*N($K80),2)) | M80: 原表·辅材 | N80: =IF($D80="","",IF(ISNA(MATCH($D80,项目名表,0)),"※项目不在项目台账里",IF($F80="※材料类别没选","※材料类别没选",IF(AND($C80<>"",ISNA(MATCH($C80,供应商表,0))),"※供应商不在基础资料里",""))))
A81: =IF($D81="","",ROW()-3) | B81: 46086 | D81: 双林面馆-滨河路 | E81: 辅材 | F81: =IF($D81="","",IFERROR(VLOOKUP($E81,材料归属,2,0),"※材料类别没选")) | G81: 220v室内灯条 | I81: 条 | J81: 15 | K81: 1.65 | L81: =IF($D81="","",ROUND(IF($J81="",1,$J81)*N($K81),2)) | M81: 原表·辅材 | N81: =IF($D81="","",IF(ISNA(MATCH($D81,项目名表,0)),"※项目不在项目台账里",IF($F81="※材料类别没选","※材料类别没选",IF(AND($C81<>"",ISNA(MATCH($C81,供应商表,0))),"※供应商不在基础资料里",""))))
A82: =IF($D82="","",ROW()-3) | B82: 46086 | D82: 双林面馆-滨河路 | E82: 辅材 | F82: =IF($D82="","",IFERROR(VLOOKUP($E82,材料归属,2,0),"※材料类别没选")) | G82: 辅材+车辆 | I82: 趟 | J82: 1 | K82: 100 | L82: =IF($D82="","",ROUND(IF($J82="",1,$J82)*N($K82),2)) | M82: 原表·辅材 | N82: =IF($D82="","",IF(ISNA(MATCH($D82,项目名表,0)),"※项目不在项目台账里",IF($F82="※材料类别没选","※材料类别没选",IF(AND($C82<>"",ISNA(MATCH($C82,供应商表,0))),"※供应商不在基础资料里",""))))
A83: =IF($D83="","",ROW()-3) | B83: 46102 | D83: 梓灿软装 | E83: 主材 | F83: =IF($D83="","",IFERROR(VLOOKUP($E83,材料归属,2,0),"※材料类别没选")) | G83: 铝塑板 | I83: 张 | J83: 5 | K83: 90 | L83: =IF($D83="","",ROUND(IF($J83="",1,$J83)*N($K83),2)) | M83: 原表·主材 | N83: =IF($D83="","",IF(ISNA(MATCH($D83,项目名表,0)),"※项目不在项目台账里",IF($F83="※材料类别没选","※材料类别没选",IF(AND($C83<>"",ISNA(MATCH($C83,供应商表,0))),"※供应商不在基础资料里",""))))
A84: =IF($D84="","",ROW()-3) | B84: 46102 | C84: 盛世大瑞 | D84: 梓灿软装 | E84: 主材 | F84: =IF($D84="","",IFERROR(VLOOKUP($E84,材料归属,2,0),"※材料类别没选")) | G84: 发光字 | I84: 套 | J84: 1 | K84: 559 | L84: =IF($D84="","",ROUND(IF($J84="",1,$J84)*N($K84),2)) | M84: 原表·主材 | N84: =IF($D84="","",IF(ISNA(MATCH($D84,项目名表,0)),"※项目不在项目台账里",IF($F84="※材料类别没选","※材料类别没选",IF(AND($C84<>"",ISNA(MATCH($C84,供应商表,0))),"※供应商不在基础资料里",""))))
A85: =IF($D85="","",ROW()-3) | B85: 46102 | D85: 梓灿软装 | E85: 辅材 | F85: =IF($D85="","",IFERROR(VLOOKUP($E85,材料归属,2,0),"※材料类别没选")) | G85: 结构胶 | I85: 支 | J85: 5 | K85: 15 | L85: =IF($D85="","",ROUND(IF($J85="",1,$J85)*N($K85),2)) | M85: 原表·辅材 | N85: =IF($D85="","",IF(ISNA(MATCH($D85,项目名表,0)),"※项目不在项目台账里",IF($F85="※材料类别没选","※材料类别没选",IF(AND($C85<>"",ISNA(MATCH($C85,供应商表,0))),"※供应商不在基础资料里",""))))
A86: =IF($D86="","",ROW()-3) | B86: 46102 | D86: 梓灿软装 | E86: 辅材 | F86: =IF($D86="","",IFERROR(VLOOKUP($E86,材料归属,2,0),"※材料类别没选")) | G86: 双面胶 | I86: 包 | J86: 4 | K86: 5 | L86: =IF($D86="","",ROUND(IF($J86="",1,$J86)*N($K86),2)) | M86: 原表·辅材 | N86: =IF($D86="","",IF(ISNA(MATCH($D86,项目名表,0)),"※项目不在项目台账里",IF($F86="※材料类别没选","※材料类别没选",IF(AND($C86<>"",ISNA(MATCH($C86,供应商表,0))),"※供应商不在基础资料里",""))))
A87: =IF($D87="","",ROW()-3) | B87: 46083 | C87: 盛世大瑞 | D87: 长颈鹿庄园 | E87: 主材 | F87: =IF($D87="","",IFERROR(VLOOKUP($E87,材料归属,2,0),"※材料类别没选")) | G87: 发光字灯箱 | I87: 套 | J87: 1 | K87: 506 | L87: =IF($D87="","",ROUND(IF($J87="",1,$J87)*N($K87),2)) | M87: 原表·主材 | N87: =IF($D87="","",IF(ISNA(MATCH($D87,项目名表,0)),"※项目不在项目台账里",IF($F87="※材料类别没选","※材料类别没选",IF(AND($C87<>"",ISNA(MATCH($C87,供应商表,0))),"※供应商不在基础资料里",""))))
A88: =IF($D88="","",ROW()-3) | B88: 46083 | D88: 长颈鹿庄园 | E88: 主材 | F88: =IF($D88="","",IFERROR(VLOOKUP($E88,材料归属,2,0),"※材料类别没选")) | G88: 写真 | J88: 2 | K88: 5.4 | L88: =IF($D88="","",ROUND(IF($J88="",1,$J88)*N($K88),2)) | M88: 原表·主材 | N88: =IF($D88="","",IF(ISNA(MATCH($D88,项目名表,0)),"※项目不在项目台账里",IF($F88="※材料类别没选","※材料类别没选",IF(AND($C88<>"",ISNA(MATCH($C88,供应商表,0))),"※供应商不在基础资料里",""))))
A89: =IF($D89="","",ROW()-3) | B89: 46083 | D89: 长颈鹿庄园 | E89: 主材 | F89: =IF($D89="","",IFERROR(VLOOKUP($E89,材料归属,2,0),"※材料类别没选")) | G89: 写真覆亮膜 | J89: 26.8 | K89: 10 | L89: =IF($D89="","",ROUND(IF($J89="",1,$J89)*N($K89),2)) | M89: 原表·主材 | N89: =IF($D89="","",IF(ISNA(MATCH($D89,项目名表,0)),"※项目不在项目台账里",IF($F89="※材料类别没选","※材料类别没选",IF(AND($C89<>"",ISNA(MATCH($C89,供应商表,0))),"※供应商不在基础资料里",""))))
A90: =IF($D90="","",ROW()-3) | B90: 46083 | D90: 长颈鹿庄园 | E90: 主材 | F90: =IF($D90="","",IFERROR(VLOOKUP($E90,材料归属,2,0),"※材料类别没选")) | G90: 异形雪弗板覆钢化膜 | J90: 1 | K90: 280 | L90: =IF($D90="","",ROUND(IF($J90="",1,$J90)*N($K90),2)) | M90: 原表·主材 | N90: =IF($D90="","",IF(ISNA(MATCH($D90,项目名表,0)),"※项目不在项目台账里",IF($F90="※材料类别没选","※材料类别没选",IF(AND($C90<>"",ISNA(MATCH($C90,供应商表,0))),"※供应商不在基础资料里",""))))
A91: =IF($D91="","",ROW()-3) | B91: 46083 | D91: 长颈鹿庄园 | E91: 辅材 | F91: =IF($D91="","",IFERROR(VLOOKUP($E91,材料归属,2,0),"※材料类别没选")) | G91: 车辆+辅材 | I91: 趟 | J91: 1.5 | K91: 200 | L91: =IF($D91="","",ROUND(IF($J91="",1,$J91)*N($K91),2)) | M91: 原表·辅材 | N91: =IF($D91="","",IF(ISNA(MATCH($D91,项目名表,0)),"※项目不在项目台账里",IF($F91="※材料类别没选","※材料类别没选",IF(AND($C91<>"",ISNA(MATCH($C91,供应商表,0))),"※供应商不在基础资料里",""))))
A92: =IF($D92="","",ROW()-3) | B92: 46083 | C92: 盛世大瑞 | D92: 国智校服 | E92: 主材 | F92: =IF($D92="","",IFERROR(VLOOKUP($E92,材料归属,2,0),"※材料类别没选")) | G92: 镀锌板烤漆指路牌 | I92: 套 | J92: 1 | K92: 1010 | L92: =IF($D92="","",ROUND(IF($J92="",1,$J92)*N($K92),2)) | M92: 原表·主材 | N92: =IF($D92="","",IF(ISNA(MATCH($D92,项目名表,0)),"※项目不在项目台账里",IF($F92="※材料类别没选","※材料类别没选",IF(AND($C92<>"",ISNA(MATCH($C92,供应商表,0))),"※供应商不在基础资料里",""))))
A93: =IF($D93="","",ROW()-3) | B93: 46083 | D93: 国智校服 | E93: 主材 | F93: =IF($D93="","",IFERROR(VLOOKUP($E93,材料归属,2,0),"※材料类别没选")) | G93: 黄钛金牌子 | I93: 套 | J93: 1 | K93: 85 | L93: =IF($D93="","",ROUND(IF($J93="",1,$J93)*N($K93),2)) | M93: 原表·主材 | N93: =IF($D93="","",IF(ISNA(MATCH($D93,项目名表,0)),"※项目不在项目台账里",IF($F93="※材料类别没选","※材料类别没选",IF(AND($C93<>"",ISNA(MATCH($C93,供应商表,0))),"※供应商不在基础资料里",""))))
A94: =IF($D94="","",ROW()-3) | B94: 46083 | D94: 国智校服 | E94: 主材 | F94: =IF($D94="","",IFERROR(VLOOKUP($E94,材料归属,2,0),"※材料类别没选")) | G94: 室内pvc字 | I94: 套 | J94: 1 | K94: 300 | L94: =IF($D94="","",ROUND(IF($J94="",1,$J94)*N($K94),2)) | M94: 原表·主材 | N94: =IF($D94="","",IF(ISNA(MATCH($D94,项目名表,0)),"※项目不在项目台账里",IF($F94="※材料类别没选","※材料类别没选",IF(AND($C94<>"",ISNA(MATCH($C94,供应商表,0))),"※供应商不在基础资料里",""))))
A95: =IF($D95="","",ROW()-3) | B95: 46083 | D95: 国智校服 | E95: 辅材 | F95: =IF($D95="","",IFERROR(VLOOKUP($E95,材料归属,2,0),"※材料类别没选")) | G95: 车辆+辅材 | I95: 趟 | J95: 1.5 | K95: 200 | L95: =IF($D95="","",ROUND(IF($J95="",1,$J95)*N($K95),2)) | M95: 原表·辅材 | N95: =IF($D95="","",IF(ISNA(MATCH($D95,项目名表,0)),"※项目不在项目台账里",IF($F95="※材料类别没选","※材料类别没选",IF(AND($C95<>"",ISNA(MATCH($C95,供应商表,0))),"※供应商不在基础资料里",""))))
A96: =IF($D96="","",ROW()-3) | B96: 46107 | C96: 1.71*5.61 | D96: 民盛生鲜店 | E96: 主材 | F96: =IF($D96="","",IFERROR(VLOOKUP($E96,材料归属,2,0),"※材料类别没选")) | G96: 门头软膜灯箱 | I96: m² | J96: 1 | K96: 86 | L96: =IF($D96="","",ROUND(IF($J96="",1,$J96)*N($K96),2)) | M96: 原表·主材 原表数量9.6×单价9.0，与金额对不上，已按金额入账 | N96: =IF($D96="","",IF(ISNA(MATCH($D96,项目名表,0)),"※项目不在项目台账里",IF($F96="※材料类别没选","※材料类别没选",IF(AND($C96<>"",ISNA(MATCH($C96,供应商表,0))),"※供应商不在基础资料里",""))))
A97: =IF($D97="","",ROW()-3) | B97: 46107 | D97: 民盛生鲜店 | E97: 主材 | F97: =IF($D97="","",IFERROR(VLOOKUP($E97,材料归属,2,0),"※材料类别没选")) | G97: 7.5型材 | I97: 米 | J97: 12 | K97: 14.64 | L97: =IF($D97="","",ROUND(IF($J97="",1,$J97)*N($K97),2)) | M97: 原表·主材 | N97: =IF($D97="","",IF(ISNA(MATCH($D97,项目名表,0)),"※项目不在项目台账里",IF($F97="※材料类别没选","※材料类别没选",IF(AND($C97<>"",ISNA(MATCH($C97,供应商表,0))),"※供应商不在基础资料里",""))))
A98: =IF($D98="","",ROW()-3) | B98: 46107 | D98: 民盛生鲜店 | E98: 主材 | F98: =IF($D98="","",IFERROR(VLOOKUP($E98,材料归属,2,0),"※材料类别没选")) | G98: 防雨灯条 | I98: 根 | J98: 72 | K98: 2.5 | L98: =IF($D98="","",ROUND(IF($J98="",1,$J98)*N($K98),2)) | M98: 原表·主材 | N98: =IF($D98="","",IF(ISNA(MATCH($D98,项目名表,0)),"※项目不在项目台账里",IF($F98="※材料类别没选","※材料类别没选",IF(AND($C98<>"",ISNA(MATCH($C98,供应商表,0))),"※供应商不在基础资料里",""))))
A99: =IF($D99="","",ROW()-3) | B99: 46107 | D99: 民盛生鲜店 | E99: 主材 | F99: =IF($D99="","",IFERROR(VLOOKUP($E99,材料归属,2,0),"※材料类别没选")) | G99: 车辆+辅材 | I99: 趟 | J99: 1 | K99: 150 | L99: =IF($D99="","",ROUND(IF($J99="",1,$J99)*N($K99),2)) | M99: 原表·主材 | N99: =IF($D99="","",IF(ISNA(MATCH($D99,项目名表,0)),"※项目不在项目台账里",IF($F99="※材料类别没选","※材料类别没选",IF(AND($C99<>"",ISNA(MATCH($C99,供应商表,0))),"※供应商不在基础资料里",""))))
A100: =IF($D100="","",ROW()-3) | B100: 46107 | D100: 民盛生鲜店 | E100: 主材 | F100: =IF($D100="","",IFERROR(VLOOKUP($E100,材料归属,2,0),"※材料类别没选")) | G100: 反光板 | I100: 张 | J100: 4 | K100: 22 | L100: =IF($D100="","",ROUND(IF($J100="",1,$J100)*N($K100),2)) | M100: 原表·主材 | N100: =IF($D100="","",IF(ISNA(MATCH($D100,项目名表,0)),"※项目不在项目台账里",IF($F100="※材料类别没选","※材料类别没选",IF(AND($C100<>"",ISNA(MATCH($C100,供应商表,0))),"※供应商不在基础资料里",""))))
...

Sheet 生产安装
A1: 生产安装 · 设计 / 制作 / 安装岗位填
A2: 设计费、制作工时、安装工时、加班、外叫小工、吊车租车都记这里，按项目分开记，会自动进项目成本。
A3: 序号 | B3: 日期 ★ | C3: 项目名称 ★ | D3: 工作类型 ★ | E3: 成本归属 | F3: 人员 / 班组 | G3: 单位 | H3: 数量 | I3: 单价 | J3: 金额 | K3: 自有/外叫 | L3: 备注 | M3: 核对
A4: =IF($C4="","",ROW()-3) | B4: 46043 | C4: 南浔美食城 | D4: 安装工时 | E4: =IF($C4="","",IFERROR(VLOOKUP($D4,工作归属,2,0),"※工作类型没选")) | G4: 工 | H4: 12 | I4: 450 | J4: =IF($C4="","",ROUND(IF($H4="",1,$H4)*N($I4),2)) | L4: 原表·人工 | M4: =IF($C4="","",IF(ISNA(MATCH($C4,项目名表,0)),"※项目不在项目台账里",IF($E4="※工作类型没选","※工作类型没选","")))
A5: =IF($C5="","",ROW()-3) | B5: 46043 | C5: 南浔美食城 | D5: 吊车/租车 | E5: =IF($C5="","",IFERROR(VLOOKUP($D5,工作归属,2,0),"※工作类型没选")) | G5: 趟 | H5: 6 | I5: 100 | J5: =IF($C5="","",ROUND(IF($H5="",1,$H5)*N($I5),2)) | L5: 原表·小车费 | M5: =IF($C5="","",IF(ISNA(MATCH($C5,项目名表,0)),"※项目不在项目台账里",IF($E5="※工作类型没选","※工作类型没选","")))
A6: =IF($C6="","",ROW()-3) | B6: 46060 | C6: 德清津华钢铁 | D6: 安装工时 | E6: =IF($C6="","",IFERROR(VLOOKUP($D6,工作归属,2,0),"※工作类型没选")) | G6: 工 | H6: 2 | I6: 450 | J6: =IF($C6="","",ROUND(IF($H6="",1,$H6)*N($I6),2)) | L6: 原表·人工 | M6: =IF($C6="","",IF(ISNA(MATCH($C6,项目名表,0)),"※项目不在项目台账里",IF($E6="※工作类型没选","※工作类型没选","")))
A7: =IF($C7="","",ROW()-3) | B7: 46060 | C7: 德清津华钢铁 | D7: 加班费 | E7: =IF($C7="","",IFERROR(VLOOKUP($D7,工作归属,2,0),"※工作类型没选")) | G7: 小时 | H7: 6 | I7: 50 | J7: =IF($C7="","",ROUND(IF($H7="",1,$H7)*N($I7),2)) | L7: 原表·人工 | M7: =IF($C7="","",IF(ISNA(MATCH($C7,项目名表,0)),"※项目不在项目台账里",IF($E7="※工作类型没选","※工作类型没选","")))
A8: =IF($C8="","",ROW()-3) | B8: 46060 | C8: 德清津华钢铁 | D8: 外叫小工 | E8: =IF($C8="","",IFERROR(VLOOKUP($D8,工作归属,2,0),"※工作类型没选")) | G8: 工 | H8: 2 | I8: 350 | J8: =IF($C8="","",ROUND(IF($H8="",1,$H8)*N($I8),2)) | L8: 原表·人工 | M8: =IF($C8="","",IF(ISNA(MATCH($C8,项目名表,0)),"※项目不在项目台账里",IF($E8="※工作类型没选","※工作类型没选","")))
A9: =IF($C9="","",ROW()-3) | B9: 46060 | C9: 德清津华钢铁 | D9: 加班费 | E9: =IF($C9="","",IFERROR(VLOOKUP($D9,工作归属,2,0),"※工作类型没选")) | G9: 小时 | H9: 6 | I9: 50 | J9: =IF($C9="","",ROUND(IF($H9="",1,$H9)*N($I9),2)) | L9: 原表·人工 | M9: =IF($C9="","",IF(ISNA(MATCH($C9,项目名表,0)),"※项目不在项目台账里",IF($E9="※工作类型没选","※工作类型没选","")))
A10: =IF($C10="","",ROW()-3) | B10: 46060 | C10: 德清津华钢铁 | D10: 运费/搬运 | E10: =IF($C10="","",IFERROR(VLOOKUP($D10,工作归属,2,0),"※工作类型没选")) | F10: 杨德 | G10: 趟 | H10: 1 | I10: 68.11 | J10: =IF($C10="","",ROUND(IF($H10="",1,$H10)*N($I10),2)) | L10: 原表·运费/快递费 | M10: =IF($C10="","",IF(ISNA(MATCH($C10,项目名表,0)),"※项目不在项目台账里",IF($E10="※工作类型没选","※工作类型没选","")))
A11: =IF($C11="","",ROW()-3) | B11: 46060 | C11: 德清津华钢铁 | D11: 吊车/租车 | E11: =IF($C11="","",IFERROR(VLOOKUP($D11,工作归属,2,0),"※工作类型没选")) | F11: 杨德 | G11: 趟 | H11: 2 | I11: 23 | J11: =IF($C11="","",ROUND(IF($H11="",1,$H11)*N($I11),2)) | L11: 原表·交通费/过路费 | M11: =IF($C11="","",IF(ISNA(MATCH($C11,项目名表,0)),"※项目不在项目台账里",IF($E11="※工作类型没选","※工作类型没选","")))
A12: =IF($C12="","",ROW()-3) | B12: 46060 | C12: 德清津华钢铁 | D12: 吊车/租车 | E12: =IF($C12="","",IFERROR(VLOOKUP($D12,工作归属,2,0),"※工作类型没选")) | F12: 外叫租赁 | G12: 天 | H12: 1 | I12: 800 | J12: =IF($C12="","",ROUND(IF($H12="",1,$H12)*N($I12),2)) | L12: 原表·吊车费 | M12: =IF($C12="","",IF(ISNA(MATCH($C12,项目名表,0)),"※项目不在项目台账里",IF($E12="※工作类型没选","※工作类型没选","")))
A13: =IF($C13="","",ROW()-3) | B13: 46060 | C13: 德清津华钢铁 | D13: 吊车/租车 | E13: =IF($C13="","",IFERROR(VLOOKUP($D13,工作归属,2,0),"※工作类型没选")) | F13: 杨德 | G13: 次 | H13: 1 | I13: 200 | J13: =IF($C13="","",ROUND(IF($H13="",1,$H13)*N($I13),2)) | L13: 原表·小车费 | M13: =IF($C13="","",IF(ISNA(MATCH($C13,项目名表,0)),"※项目不在项目台账里",IF($E13="※工作类型没选","※工作类型没选","")))
A14: =IF($C14="","",ROW()-3) | B14: 46060 | C14: 德清津华钢铁 | D14: 其他人工 | E14: =IF($C14="","",IFERROR(VLOOKUP($D14,工作归属,2,0),"※工作类型没选")) | F14: 杨德 | G14: 人 | H14: 2 | I14: 18 | J14: =IF($C14="","",ROUND(IF($H14="",1,$H14)*N($I14),2)) | L14: 原表·其它补助 | M14: =IF($C14="","",IF(ISNA(MATCH($C14,项目名表,0)),"※项目不在项目台账里",IF($E14="※工作类型没选","※工作类型没选","")))
A15: =IF($C15="","",ROW()-3) | B15: 46083 | C15: 兰溪手擀面 | D15: 安装工时 | E15: =IF($C15="","",IFERROR(VLOOKUP($D15,工作归属,2,0),"※工作类型没选")) | G15: 工 | H15: 1 | I15: 400 | J15: =IF($C15="","",ROUND(IF($H15="",1,$H15)*N($I15),2)) | L15: 原表·人工 | M15: =IF($C15="","",IF(ISNA(MATCH($C15,项目名表,0)),"※项目不在项目台账里",IF($E15="※工作类型没选","※工作类型没选","")))
A16: =IF($C16="","",ROW()-3) | C16: 莫盾服饰 | D16: 安装工时 | E16: =IF($C16="","",IFERROR(VLOOKUP($D16,工作归属,2,0),"※工作类型没选")) | F16: 点工 | G16: 工 | H16: 4 | I16: 400 | J16: =IF($C16="","",ROUND(IF($H16="",1,$H16)*N($I16),2)) | L16: 原表·人工 | M16: =IF($C16="","",IF(ISNA(MATCH($C16,项目名表,0)),"※项目不在项目台账里",IF($E16="※工作类型没选","※工作类型没选","")))
A17: =IF($C17="","",ROW()-3) | B17: 46106 | C17: 君澜服饰 | D17: 加班费 | E17: =IF($C17="","",IFERROR(VLOOKUP($D17,工作归属,2,0),"※工作类型没选")) | G17: 小时 | H17: 6 | I17: 50 | J17: =IF($C17="","",ROUND(IF($H17="",1,$H17)*N($I17),2)) | L17: 原表·人工 | M17: =IF($C17="","",IF(ISNA(MATCH($C17,项目名表,0)),"※项目不在项目台账里",IF($E17="※工作类型没选","※工作类型没选","")))
A18: =IF($C18="","",ROW()-3) | B18: 46106 | C18: 君澜服饰 | D18: 外叫小工 | E18: =IF($C18="","",IFERROR(VLOOKUP($D18,工作归属,2,0),"※工作类型没选")) | G18: 工 | H18: 2 | I18: 350 | J18: =IF($C18="","",ROUND(IF($H18="",1,$H18)*N($I18),2)) | L18: 原表·人工 | M18: =IF($C18="","",IF(ISNA(MATCH($C18,项目名表,0)),"※项目不在项目台账里",IF($E18="※工作类型没选","※工作类型没选","")))
A19: =IF($C19="","",ROW()-3) | B19: 46106 | C19: 君澜服饰 | D19: 加班费 | E19: =IF($C19="","",IFERROR(VLOOKUP($D19,工作归属,2,0),"※工作类型没选")) | G19: 小时 | H19: 6 | I19: 50 | J19: =IF($C19="","",ROUND(IF($H19="",1,$H19)*N($I19),2)) | L19: 原表·人工 | M19: =IF($C19="","",IF(ISNA(MATCH($C19,项目名表,0)),"※项目不在项目台账里",IF($E19="※工作类型没选","※工作类型没选","")))
A20: =IF($C20="","",ROW()-3) | B20: 46082 | C20: 芭比贝克 | D20: 安装工时 | E20: =IF($C20="","",IFERROR(VLOOKUP($D20,工作归属,2,0),"※工作类型没选")) | G20: 工 | H20: 1 | I20: 350 | J20: =IF($C20="","",ROUND(IF($H20="",1,$H20)*N($I20),2)) | L20: 原表·人工 | M20: =IF($C20="","",IF(ISNA(MATCH($C20,项目名表,0)),"※项目不在项目台账里",IF($E20="※工作类型没选","※工作类型没选","")))
A21: =IF($C21="","",ROW()-3) | B21: 46100 | C21: 铁柱烧烤店 | D21: 安装工时 | E21: =IF($C21="","",IFERROR(VLOOKUP($D21,工作归属,2,0),"※工作类型没选")) | G21: 工 | H21: 3 | I21: 400 | J21: =IF($C21="","",ROUND(IF($H21="",1,$H21)*N($I21),2)) | L21: 原表·人工 | M21: =IF($C21="","",IF(ISNA(MATCH($C21,项目名表,0)),"※项目不在项目台账里",IF($E21="※工作类型没选","※工作类型没选","")))
A22: =IF($C22="","",ROW()-3) | B22: 46100 | C22: 铁柱烧烤店 | D22: 加班费 | E22: =IF($C22="","",IFERROR(VLOOKUP($D22,工作归属,2,0),"※工作类型没选")) | G22: 小时 | H22: 6 | I22: 50 | J22: =IF($C22="","",ROUND(IF($H22="",1,$H22)*N($I22),2)) | L22: 原表·人工 | M22: =IF($C22="","",IF(ISNA(MATCH($C22,项目名表,0)),"※项目不在项目台账里",IF($E22="※工作类型没选","※工作类型没选","")))
A23: =IF($C23="","",ROW()-3) | B23: 46084 | C23: 钟管熟食店 | D23: 安装工时 | E23: =IF($C23="","",IFERROR(VLOOKUP($D23,工作归属,2,0),"※工作类型没选")) | H23: 1 | I23: 8500 | J23: =IF($C23="","",ROUND(IF($H23="",1,$H23)*N($I23),2)) | L23: 原表·人工 | M23: =IF($C23="","",IF(ISNA(MATCH($C23,项目名表,0)),"※项目不在项目台账里",IF($E23="※工作类型没选","※工作类型没选","")))
A24: =IF($C24="","",ROW()-3) | B24: 46100 | C24: 螺有名灯箱门头 | D24: 安装工时 | E24: =IF($C24="","",IFERROR(VLOOKUP($D24,工作归属,2,0),"※工作类型没选")) | G24: 工 | H24: 1 | I24: 400 | J24: =IF($C24="","",ROUND(IF($H24="",1,$H24)*N($I24),2)) | L24: 原表·人工 | M24: =IF($C24="","",IF(ISNA(MATCH($C24,项目名表,0)),"※项目不在项目台账里",IF($E24="※工作类型没选","※工作类型没选","")))
A25: =IF($C25="","",ROW()-3) | B25: 46102 | C25: 汕味杏花室内项目 | D25: 安装工时 | E25: =IF($C25="","",IFERROR(VLOOKUP($D25,工作归属,2,0),"※工作类型没选")) | G25: 工 | H25: 2 | I25: 400 | J25: =IF($C25="","",ROUND(IF($H25="",1,$H25)*N($I25),2)) | L25: 原表·人工 | M25: =IF($C25="","",IF(ISNA(MATCH($C25,项目名表,0)),"※项目不在项目台账里",IF($E25="※工作类型没选","※工作类型没选","")))
A26: =IF($C26="","",ROW()-3) | B26: 46086 | C26: 双林面馆-滨河路 | D26: 安装工时 | E26: =IF($C26="","",IFERROR(VLOOKUP($D26,工作归属,2,0),"※工作类型没选")) | G26: 工 | H26: 2 | I26: 400 | J26: =IF($C26="","",ROUND(IF($H26="",1,$H26)*N($I26),2)) | L26: 原表·人工 | M26: =IF($C26="","",IF(ISNA(MATCH($C26,项目名表,0)),"※项目不在项目台账里",IF($E26="※工作类型没选","※工作类型没选","")))
A27: =IF($C27="","",ROW()-3) | B27: 46102 | C27: 梓灿软装 | D27: 安装工时 | E27: =IF($C27="","",IFERROR(VLOOKUP($D27,工作归属,2,0),"※工作类型没选")) | G27: 工 | H27: 1 | I27: 1200 | J27: =IF($C27="","",ROUND(IF($H27="",1,$H27)*N($I27),2)) | L27: 原表·人工 | M27: =IF($C27="","",IF(ISNA(MATCH($C27,项目名表,0)),"※项目不在项目台账里",IF($E27="※工作类型没选","※工作类型没选","")))
A28: =IF($C28="","",ROW()-3) | B28: 46083 | C28: 长颈鹿庄园 | D28: 安装工时 | E28: =IF($C28="","",IFERROR(VLOOKUP($D28,工作归属,2,0),"※工作类型没选")) | G28: 工 | H28: 2.5 | I28: 400 | J28: =IF($C28="","",ROUND(IF($H28="",1,$H28)*N($I28),2)) | L28: 原表·人工 | M28: =IF($C28="","",IF(ISNA(MATCH($C28,项目名表,0)),"※项目不在项目台账里",IF($E28="※工作类型没选","※工作类型没选","")))
A29: =IF($C29="","",ROW()-3) | B29: 46083 | C29: 国智校服 | D29: 安装工时 | E29: =IF($C29="","",IFERROR(VLOOKUP($D29,工作归属,2,0),"※工作类型没选")) | G29: 工 | H29: 2.5 | I29: 400 | J29: =IF($C29="","",ROUND(IF($H29="",1,$H29)*N($I29),2)) | L29: 原表·人工 | M29: =IF($C29="","",IF(ISNA(MATCH($C29,项目名表,0)),"※项目不在项目台账里",IF($E29="※工作类型没选","※工作类型没选","")))
A30: =IF($C30="","",ROW()-3) | B30: 46108 | C30: 睿芯行 | D30: 外叫小工 | E30: =IF($C30="","",IFERROR(VLOOKUP($D30,工作归属,2,0),"※工作类型没选")) | G30: 工 | H30: 9 | I30: 350 | J30: =IF($C30="","",ROUND(IF($H30="",1,$H30)*N($I30),2)) | L30: 原表·人工 | M30: =IF($C30="","",IF(ISNA(MATCH($C30,项目名表,0)),"※项目不在项目台账里",IF($E30="※工作类型没选","※工作类型没选","")))
A31: =IF($C31="","",ROW()-3) | E31: =IF($C31="","",IFERROR(VLOOKUP($D31,工作归属,2,0),"※工作类型没选")) | J31: =IF($C31="","",ROUND(IF($H31="",1,$H31)*N($I31),2)) | M31: =IF($C31="","",IF(ISNA(MATCH($C31,项目名表,0)),"※项目不在项目台账里",IF($E31="※工作类型没选","※工作类型没选","")))
A32: =IF($C32="","",ROW()-3) | E32: =IF($C32="","",IFERROR(VLOOKUP($D32,工作归属,2,0),"※工作类型没选")) | J32: =IF($C32="","",ROUND(IF($H32="",1,$H32)*N($I32),2)) | M32: =IF($C32="","",IF(ISNA(MATCH($C32,项目名表,0)),"※项目不在项目台账里",IF($E32="※工作类型没选","※工作类型没选","")))
A33: =IF($C33="","",ROW()-3) | E33: =IF($C33="","",IFERROR(VLOOKUP($D33,工作归属,2,0),"※工作类型没选")) | J33: =IF($C33="","",ROUND(IF($H33="",1,$H33)*N($I33),2)) | M33: =IF($C33="","",IF(ISNA(MATCH($C33,项目名表,0)),"※项目不在项目台账里",IF($E33="※工作类型没选","※工作类型没选","")))
A34: =IF($C34="","",ROW()-3) | E34: =IF($C34="","",IFERROR(VLOOKUP($D34,工作归属,2,0),"※工作类型没选")) | J34: =IF($C34="","",ROUND(IF($H34="",1,$H34)*N($I34),2)) | M34: =IF($C34="","",IF(ISNA(MATCH($C34,项目名表,0)),"※项目不在项目台账里",IF($E34="※工作类型没选","※工作类型没选","")))
A35: =IF($C35="","",ROW()-3) | E35: =IF($C35="","",IFERROR(VLOOKUP($D35,工作归属,2,0),"※工作类型没选")) | J35: =IF($C35="","",ROUND(IF($H35="",1,$H35)*N($I35),2)) | M35: =IF($C35="","",IF(ISNA(MATCH($C35,项目名表,0)),"※项目不在项目台账里",IF($E35="※工作类型没选","※工作类型没选","")))
A36: =IF($C36="","",ROW()-3) | E36: =IF($C36="","",IFERROR(VLOOKUP($D36,工作归属,2,0),"※工作类型没选")) | J36: =IF($C36="","",ROUND(IF($H36="",1,$H36)*N($I36),2)) | M36: =IF($C36="","",IF(ISNA(MATCH($C36,项目名表,0)),"※项目不在项目台账里",IF($E36="※工作类型没选","※工作类型没选","")))
A37: =IF($C37="","",ROW()-3) | E37: =IF($C37="","",IFERROR(VLOOKUP($D37,工作归属,2,0),"※工作类型没选")) | J37: =IF($C37="","",ROUND(IF($H37="",1,$H37)*N($I37),2)) | M37: =IF($C37="","",IF(ISNA(MATCH($C37,项目名表,0)),"※项目不在项目台账里",IF($E37="※工作类型没选","※工作类型没选","")))
A38: =IF($C38="","",ROW()-3) | E38: =IF($C38="","",IFERROR(VLOOKUP($D38,工作归属,2,0),"※工作类型没选")) | J38: =IF($C38="","",ROUND(IF($H38="",1,$H38)*N($I38),2)) | M38: =IF($C38="","",IF(ISNA(MATCH($C38,项目名表,0)),"※项目不在项目台账里",IF($E38="※工作类型没选","※工作类型没选","")))
A39: =IF($C39="","",ROW()-3) | E39: =IF($C39="","",IFERROR(VLOOKUP($D39,工作归属,2,0),"※工作类型没选")) | J39: =IF($C39="","",ROUND(IF($H39="",1,$H39)*N($I39),2)) | M39: =IF($C39="","",IF(ISNA(MATCH($C39,项目名表,0)),"※项目不在项目台账里",IF($E39="※工作类型没选","※工作类型没选","")))
A40: =IF($C40="","",ROW()-3) | E40: =IF($C40="","",IFERROR(VLOOKUP($D40,工作归属,2,0),"※工作类型没选")) | J40: =IF($C40="","",ROUND(IF($H40="",1,$H40)*N($I40),2)) | M40: =IF($C40="","",IF(ISNA(MATCH($C40,项目名表,0)),"※项目不在项目台账里",IF($E40="※工作类型没选","※工作类型没选","")))
A41: =IF($C41="","",ROW()-3) | E41: =IF($C41="","",IFERROR(VLOOKUP($D41,工作归属,2,0),"※工作类型没选")) | J41: =IF($C41="","",ROUND(IF($H41="",1,$H41)*N($I41),2)) | M41: =IF($C41="","",IF(ISNA(MATCH($C41,项目名表,0)),"※项目不在项目台账里",IF($E41="※工作类型没选","※工作类型没选","")))
A42: =IF($C42="","",ROW()-3) | E42: =IF($C42="","",IFERROR(VLOOKUP($D42,工作归属,2,0),"※工作类型没选")) | J42: =IF($C42="","",ROUND(IF($H42="",1,$H42)*N($I42),2)) | M42: =IF($C42="","",IF(ISNA(MATCH($C42,项目名表,0)),"※项目不在项目台账里",IF($E42="※工作类型没选","※工作类型没选","")))
... A1203: =IF($C1203="","",ROW()-3) | E1203: =IF($C1203="","",IFERROR(VLOOKUP($D1203,工作归属,2,0),"※工作类型没选")) | J1203: =IF($C1203="","",ROUND(IF($H1203="",1,$H1203)*N($I1203),2)) | M1203: =IF($C1203="","",IF(ISNA(MATCH($C1203,项目名表,0)),"※项目不在项目台账里",IF($E1203="※工作类型没选","※工作类型没选","")))

Sheet 资金日记账
A1: 资金日记账 · 出纳填（五个账户混在一起记）
A2: 五个账户的钱都记这一张，按日期顺着往下记就行。L 列自动结出「这个账户」当时的余额，M 列是全部账户合计。账户之间互转记两行（转出一行支出、转入一行收入），类别都选『账户互转』。
A3: 序号 | B3: 日期 ★ | C3: 账户 ★ | D3: 收/支 ★ | E3: 费用类别 ★ | F3: 归属大类 | G3: 项目名称 | H3: 往来单位 | I3: 摘要 ★ | J3: 收入金额 | K3: 支出金额 | L3: 本账户余额 | M3: 全账户合计 | N3: 经手人 | O3: 备注 | P3: 核对
A4: =IF($B4="","",ROW()-3) | C4: 微信1 | D4: 收入 | E4: 待分类 | F4: =IF($E4="","",IFERROR(VLOOKUP($E4,类别归属,2,0),"※类别不在基础资料里")) | G4: 盛昊篷车 | I4: 二维码收款 | J4: 282 | L4: =IF($C4="","",ROUND(IFERROR(VLOOKUP($C4,账户期初,2,0),0)+SUMIFS($J$4:J4,$C$4:C4,$C4)-SUMIFS($K$4:K4,$C$4:C4,$C4),2)) | M4: =IF($C4="","",ROUND(SUM(基础资料!$B$4:$B$13)+SUM($J$4:J4)-SUM($K$4:K4),2)) | P4: =IF($B4="","",IF($F4="※类别不在基础资料里","※费用类别不在基础资料里",IF(AND(N($J4)=0,N($K4)=0),"※这行没填金额",IF(AND(N($J4)>0,N($K4)>0),"※收入和支出不能同一行都填",IF(AND($D4="收入",N($J4)=0),"※收入行要填收入金额",IF(AND($D4="支出",N($K4)=0),"※支出行要填支出金额",IF(AND($C4<>"",ISNA(MATCH($C4,账户表,0))),"※账户不在基础资料里",IF(AND($G4<>"",ISNA(MATCH($G4,项目名表,0))),"※项目不在项目台账里",IF(AND(LEFT($F4,3)="成本-",$G4=""),"※成本类支出没填项目",IF(AND(LEFT($F4,3)="成本-",$H4<>"",N($K4)>0,COUNTIFS(采购单!$B:$B,$B4,采购单!$C:$C,$H4,采购单!$L:$L,$K4)>0),"※这笔可能和采购单重复了",""))))))))))
A5: =IF($B5="","",ROW()-3) | B5: 46079 | C5: 微信1 | D5: 收入 | E5: 待分类 | F5: =IF($E5="","",IFERROR(VLOOKUP($E5,类别归属,2,0),"※类别不在基础资料里")) | G5: 盛昊篷车 | I5: 二维码收款 | J5: 190 | L5: =IF($C5="","",ROUND(IFERROR(VLOOKUP($C5,账户期初,2,0),0)+SUMIFS($J$4:J5,$C$4:C5,$C5)-SUMIFS($K$4:K5,$C$4:C5,$C5),2)) | M5: =IF($C5="","",ROUND(SUM(基础资料!$B$4:$B$13)+SUM($J$4:J5)-SUM($K$4:K5),2)) | P5: =IF($B5="","",IF($F5="※类别不在基础资料里","※费用类别不在基础资料里",IF(AND(N($J5)=0,N($K5)=0),"※这行没填金额",IF(AND(N($J5)>0,N($K5)>0),"※收入和支出不能同一行都填",IF(AND($D5="收入",N($J5)=0),"※收入行要填收入金额",IF(AND($D5="支出",N($K5)=0),"※支出行要填支出金额",IF(AND($C5<>"",ISNA(MATCH($C5,账户表,0))),"※账户不在基础资料里",IF(AND($G5<>"",ISNA(MATCH($G5,项目名表,0))),"※项目不在项目台账里",IF(AND(LEFT($F5,3)="成本-",$G5=""),"※成本类支出没填项目",IF(AND(LEFT($F5,3)="成本-",$H5<>"",N($K5)>0,COUNTIFS(采购单!$B:$B,$B5,采购单!$C:$C,$H5,采购单!$L:$L,$K5)>0),"※这笔可能和采购单重复了",""))))))))))
A6: =IF($B6="","",ROW()-3) | B6: 46080 | C6: 微信1 | D6: 支出 | E6: 主材采购 | F6: =IF($E6="","",IFERROR(VLOOKUP($E6,类别归属,2,0),"※类别不在基础资料里")) | H6: 泰发五金 | I6: 付泰发五金 | K6: 45 | L6: =IF($C6="","",ROUND(IFERROR(VLOOKUP($C6,账户期初,2,0),0)+SUMIFS($J$4:J6,$C$4:C6,$C6)-SUMIFS($K$4:K6,$C$4:C6,$C6),2)) | M6: =IF($C6="","",ROUND(SUM(基础资料!$B$4:$B$13)+SUM($J$4:J6)-SUM($K$4:K6),2)) | O6: 焊把钳、接头 | P6: =IF($B6="","",IF($F6="※类别不在基础资料里","※费用类别不在基础资料里",IF(AND(N($J6)=0,N($K6)=0),"※这行没填金额",IF(AND(N($J6)>0,N($K6)>0),"※收入和支出不能同一行都填",IF(AND($D6="收入",N($J6)=0),"※收入行要填收入金额",IF(AND($D6="支出",N($K6)=0),"※支出行要填支出金额",IF(AND($C6<>"",ISNA(MATCH($C6,账户表,0))),"※账户不在基础资料里",IF(AND($G6<>"",ISNA(MATCH($G6,项目名表,0))),"※项目不在项目台账里",IF(AND(LEFT($F6,3)="成本-",$G6=""),"※成本类支出没填项目",IF(AND(LEFT($F6,3)="成本-",$H6<>"",N($K6)>0,COUNTIFS(采购单!$B:$B,$B6,采购单!$C:$C,$H6,采购单!$L:$L,$K6)>0),"※这笔可能和采购单重复了",""))))))))))
A7: =IF($B7="","",ROW()-3) | B7: 46080 | C7: 微信1 | D7: 支出 | E7: 运费/快递费 | F7: =IF($E7="","",IFERROR(VLOOKUP($E7,类别归属,2,0),"※类别不在基础资料里")) | G7: 付炳秀配送 | H7: 炳秀 | I7: 付炳秀 | K7: 330 | L7: =IF($C7="","",ROUND(IFERROR(VLOOKUP($C7,账户期初,2,0),0)+SUMIFS($J$4:J7,$C$4:C7,$C7)-SUMIFS($K$4:K7,$C$4:C7,$C7),2)) | M7: =IF($C7="","",ROUND(SUM(基础资料!$B$4:$B$13)+SUM($J$4:J7)-SUM($K$4:K7),2)) | P7: =IF($B7="","",IF($F7="※类别不在基础资料里","※费用类别不在基础资料里",IF(AND(N($J7)=0,N($K7)=0),"※这行没填金额",IF(AND(N($J7)>0,N($K7)>0),"※收入和支出不能同一行都填",IF(AND($D7="收入",N($J7)=0),"※收入行要填收入金额",IF(AND($D7="支出",N($K7)=0),"※支出行要填支出金额",IF(AND($C7<>"",ISNA(MATCH($C7,账户表,0))),"※账户不在基础资料里",IF(AND($G7<>"",ISNA(MATCH($G7,项目名表,0))),"※项目不在项目台账里",IF(AND(LEFT($F7,3)="成本-",$G7=""),"※成本类支出没填项目",IF(AND(LEFT($F7,3)="成本-",$H7<>"",N($K7)>0,COUNTIFS(采购单!$B:$B,$B7,采购单!$C:$C,$H7,采购单!$L:$L,$K7)>0),"※这笔可能和采购单重复了",""))))))))))
A8: =IF($B8="","",ROW()-3) | C8: 微信1 | D8: 支出 | E8: 运费/快递费 | F8: =IF($E8="","",IFERROR(VLOOKUP($E8,类别归属,2,0),"※类别不在基础资料里")) | H8: 炳秀 | I8: 付炳秀配送 | K8: 10 | L8: =IF($C8="","",ROUND(IFERROR(VLOOKUP($C8,账户期初,2,0),0)+SUMIFS($J$4:J8,$C$4:C8,$C8)-SUMIFS($K$4:K8,$C$4:C8,$C8),2)) | M8: =IF($C8="","",ROUND(SUM(基础资料!$B$4:$B$13)+SUM($J$4:J8)-SUM($K$4:K8),2)) | P8: =IF($B8="","",IF($F8="※类别不在基础资料里","※费用类别不在基础资料里",IF(AND(N($J8)=0,N($K8)=0),"※这行没填金额",IF(AND(N($J8)>0,N($K8)>0),"※收入和支出不能同一行都填",IF(AND($D8="收入",N($J8)=0),"※收入行要填收入金额",IF(AND($D8="支出",N($K8)=0),"※支出行要填支出金额",IF(AND($C8<>"",ISNA(MATCH($C8,账户表,0))),"※账户不在基础资料里",IF(AND($G8<>"",ISNA(MATCH($G8,项目名表,0))),"※项目不在项目台账里",IF(AND(LEFT($F8,3)="成本-",$G8=""),"※成本类支出没填项目",IF(AND(LEFT($F8,3)="成本-",$H8<>"",N($K8)>0,COUNTIFS(采购单!$B:$B,$B8,采购单!$C:$C,$H8,采购单!$L:$L,$K8)>0),"※这笔可能和采购单重复了",""))))))))))
A9: =IF($B9="","",ROW()-3) | B9: 46082 | C9: 微信1 | D9: 收入 | E9: 项目收款 | F9: =IF($E9="","",IFERROR(VLOOKUP($E9,类别归属,2,0),"※类别不在基础资料里")) | G9: 芭比贝克 | I9: 叶永红 | J9: 400 | L9: =IF($C9="","",ROUND(IFERROR(VLOOKUP($C9,账户期初,2,0),0)+SUMIFS($J$4:J9,$C$4:C9,$C9)-SUMIFS($K$4:K9,$C$4:C9,$C9),2)) | M9: =IF($C9="","",ROUND(SUM(基础资料!$B$4:$B$13)+SUM($J$4:J9)-SUM($K$4:K9),2)) | P9: =IF($B9="","",IF($F9="※类别不在基础资料里","※费用类别不在基础资料里",IF(AND(N($J9)=0,N($K9)=0),"※这行没填金额",IF(AND(N($J9)>0,N($K9)>0),"※收入和支出不能同一行都填",IF(AND($D9="收入",N($J9)=0),"※收入行要填收入金额",IF(AND($D9="支出",N($K9)=0),"※支出行要填支出金额",IF(AND($C9<>"",ISNA(MATCH($C9,账户表,0))),"※账户不在基础资料里",IF(AND($G9<>"",ISNA(MATCH($G9,项目名表,0))),"※项目不在项目台账里",IF(AND(LEFT($F9,3)="成本-",$G9=""),"※成本类支出没填项目",IF(AND(LEFT($F9,3)="成本-",$H9<>"",N($K9)>0,COUNTIFS(采购单!$B:$B,$B9,采购单!$C:$C,$H9,采购单!$L:$L,$K9)>0),"※这笔可能和采购单重复了",""))))))))))
A10: =IF($B10="","",ROW()-3) | B10: 46083 | C10: 微信1 | D10: 收入 | E10: 项目收款 | F10: =IF($E10="","",IFERROR(VLOOKUP($E10,类别归属,2,0),"※类别不在基础资料里")) | G10: 兰溪手擀面 | I10: 收兰溪牛肉拉面 | J10: 1400 | L10: =IF($C10="","",ROUND(IFERROR(VLOOKUP($C10,账户期初,2,0),0)+SUMIFS($J$4:J10,$C$4:C10,$C10)-SUMIFS($K$4:K10,$C$4:C10,$C10),2)) | M10: =IF($C10="","",ROUND(SUM(基础资料!$B$4:$B$13)+SUM($J$4:J10)-SUM($K$4:K10),2)) | P10: =IF($B10="","",IF($F10="※类别不在基础资料里","※费用类别不在基础资料里",IF(AND(N($J10)=0,N($K10)=0),"※这行没填金额",IF(AND(N($J10)>0,N($K10)>0),"※收入和支出不能同一行都填",IF(AND($D10="收入",N($J10)=0),"※收入行要填收入金额",IF(AND($D10="支出",N($K10)=0),"※支出行要填支出金额",IF(AND($C10<>"",ISNA(MATCH($C10,账户表,0))),"※账户不在基础资料里",IF(AND($G10<>"",ISNA(MATCH($G10,项目名表,0))),"※项目不在项目台账里",IF(AND(LEFT($F10,3)="成本-",$G10=""),"※成本类支出没填项目",IF(AND(LEFT($F10,3)="成本-",$H10<>"",N($K10)>0,COUNTIFS(采购单!$B:$B,$B10,采购单!$C:$C,$H10,采购单!$L:$L,$K10)>0),"※这笔可能和采购单重复了",""))))))))))
A11: =IF($B11="","",ROW()-3) | B11: 46083 | C11: 微信1 | D11: 收入 | E11: 零星物料销售 | F11: =IF($E11="","",IFERROR(VLOOKUP($E11,类别归属,2,0),"※类别不在基础资料里")) | G11: 万达kvv | I11: 万达-KVV乔金鑫 | J11: 68 | L11: =IF($C11="","",ROUND(IFERROR(VLOOKUP($C11,账户期初,2,0),0)+SUMIFS($J$4:J11,$C$4:C11,$C11)-SUMIFS($K$4:K11,$C$4:C11,$C11),2)) | M11: =IF($C11="","",ROUND(SUM(基础资料!$B$4:$B$13)+SUM($J$4:J11)-SUM($K$4:K11),2)) | P11: =IF($B11="","",IF($F11="※类别不在基础资料里","※费用类别不在基础资料里",IF(AND(N($J11)=0,N($K11)=0),"※这行没填金额",IF(AND(N($J11)>0,N($K11)>0),"※收入和支出不能同一行都填",IF(AND($D11="收入",N($J11)=0),"※收入行要填收入金额",IF(AND($D11="支出",N($K11)=0),"※支出行要填支出金额",IF(AND($C11<>"",ISNA(MATCH($C11,账户表,0))),"※账户不在基础资料里",IF(AND($G11<>"",ISNA(MATCH($G11,项目名表,0))),"※项目不在项目台账里",IF(AND(LEFT($F11,3)="成本-",$G11=""),"※成本类支出没填项目",IF(AND(LEFT($F11,3)="成本-",$H11<>"",N($K11)>0,COUNTIFS(采购单!$B:$B,$B11,采购单!$C:$C,$H11,采购单!$L:$L,$K11)>0),"※这笔可能和采购单重复了",""))))))))))
A12: =IF($B12="","",ROW()-3) | B12: 46083 | C12: 微信1 | D12: 支出 | E12: 运费/快递费 | F12: =IF($E12="","",IFERROR(VLOOKUP($E12,类别归属,2,0),"※类别不在基础资料里")) | G12: 芭比贝克 | H12: 炳秀 | I12: 付炳秀配送 | K12: 38 | L12: =IF($C12="","",ROUND(IFERROR(VLOOKUP($C12,账户期初,2,0),0)+SUMIFS($J$4:J12,$C$4:C12,$C12)-SUMIFS($K$4:K12,$C$4:C12,$C12),2)) | M12: =IF($C12="","",ROUND(SUM(基础资料!$B$4:$B$13)+SUM($J$4:J12)-SUM($K$4:K12),2)) | P12: =IF($B12="","",IF($F12="※类别不在基础资料里","※费用类别不在基础资料里",IF(AND(N($J12)=0,N($K12)=0),"※这行没填金额",IF(AND(N($J12)>0,N($K12)>0),"※收入和支出不能同一行都填",IF(AND($D12="收入",N($J12)=0),"※收入行要填收入金额",IF(AND($D12="支出",N($K12)=0),"※支出行要填支出金额",IF(AND($C12<>"",ISNA(MATCH($C12,账户表,0))),"※账户不在基础资料里",IF(AND($G12<>"",ISNA(MATCH($G12,项目名表,0))),"※项目不在项目台账里",IF(AND(LEFT($F12,3)="成本-",$G12=""),"※成本类支出没填项目",IF(AND(LEFT($F12,3)="成本-",$H12<>"",N($K12)>0,COUNTIFS(采购单!$B:$B,$B12,采购单!$C:$C,$H12,采购单!$L:$L,$K12)>0),"※这笔可能和采购单重复了",""))))))))))
A13: =IF($B13="","",ROW()-3) | B13: 46084 | C13: 微信1 | D13: 支出 | E13: 安装工资 | F13: =IF($E13="","",IFERROR(VLOOKUP($E13,类别归属,2,0),"※类别不在基础资料里")) | I13: 付章凡预支工资 | K13: 1000 | L13: =IF($C13="","",ROUND(IFERROR(VLOOKUP($C13,账户期初,2,0),0)+SUMIFS($J$4:J13,$C$4:C13,$C13)-SUMIFS($K$4:K13,$C$4:C13,$C13),2)) | M13: =IF($C13="","",ROUND(SUM(基础资料!$B$4:$B$13)+SUM($J$4:J13)-SUM($K$4:K13),2)) | P13: =IF($B13="","",IF($F13="※类别不在基础资料里","※费用类别不在基础资料里",IF(AND(N($J13)=0,N($K13)=0),"※这行没填金额",IF(AND(N($J13)>0,N($K13)>0),"※收入和支出不能同一行都填",IF(AND($D13="收入",N($J13)=0),"※收入行要填收入金额",IF(AND($D13="支出",N($K13)=0),"※支出行要填支出金额",IF(AND($C13<>"",ISNA(MATCH($C13,账户表,0))),"※账户不在基础资料里",IF(AND($G13<>"",ISNA(MATCH($G13,项目名表,0))),"※项目不在项目台账里",IF(AND(LEFT($F13,3)="成本-",$G13=""),"※成本类支出没填项目",IF(AND(LEFT($F13,3)="成本-",$H13<>"",N($K13)>0,COUNTIFS(采购单!$B:$B,$B13,采购单!$C:$C,$H13,采购单!$L:$L,$K13)>0),"※这笔可能和采购单重复了",""))))))))))
A14: =IF($B14="","",ROW()-3) | B14: 46084 | C14: 微信1 | D14: 支出 | E14: 运费/快递费 | F14: =IF($E14="","",IFERROR(VLOOKUP($E14,类别归属,2,0),"※类别不在基础资料里")) | G14: 万达kvv | H14: 炳秀 | I14: 付炳秀配送 | K14: 10 | L14: =IF($C14="","",ROUND(IFERROR(VLOOKUP($C14,账户期初,2,0),0)+SUMIFS($J$4:J14,$C$4:C14,$C14)-SUMIFS($K$4:K14,$C$4:C14,$C14),2)) | M14: =IF($C14="","",ROUND(SUM(基础资料!$B$4:$B$13)+SUM($J$4:J14)-SUM($K$4:K14),2)) | O14: 95 | P14: =IF($B14="","",IF($F14="※类别不在基础资料里","※费用类别不在基础资料里",IF(AND(N($J14)=0,N($K14)=0),"※这行没填金额",IF(AND(N($J14)>0,N($K14)>0),"※收入和支出不能同一行都填",IF(AND($D14="收入",N($J14)=0),"※收入行要填收入金额",IF(AND($D14="支出",N($K14)=0),"※支出行要填支出金额",IF(AND($C14<>"",ISNA(MATCH($C14,账户表,0))),"※账户不在基础资料里",IF(AND($G14<>"",ISNA(MATCH($G14,项目名表,0))),"※项目不在项目台账里",IF(AND(LEFT($F14,3)="成本-",$G14=""),"※成本类支出没填项目",IF(AND(LEFT($F14,3)="成本-",$H14<>"",N($K14)>0,COUNTIFS(采购单!$B:$B,$B14,采购单!$C:$C,$H14,采购单!$L:$L,$K14)>0),"※这笔可能和采购单重复了",""))))))))))
A15: =IF($B15="","",ROW()-3) | B15: 46084 | C15: 微信1 | D15: 支出 | E15: 运费/快递费 | F15: =IF($E15="","",IFERROR(VLOOKUP($E15,类别归属,2,0),"※类别不在基础资料里")) | G15: 万达kvv | H15: 炳秀 | I15: 付炳秀配送 | K15: 5 | L15: =IF($C15="","",ROUND(IFERROR(VLOOKUP($C15,账户期初,2,0),0)+SUMIFS($J$4:J15,$C$4:C15,$C15)-SUMIFS($K$4:K15,$C$4:C15,$C15),2)) | M15: =IF($C15="","",ROUND(SUM(基础资料!$B$4:$B$13)+SUM($J$4:J15)-SUM($K$4:K15),2)) | P15: =IF($B15="","",IF($F15="※类别不在基础资料里","※费用类别不在基础资料里",IF(AND(N($J15)=0,N($K15)=0),"※这行没填金额",IF(AND(N($J15)>0,N($K15)>0),"※收入和支出不能同一行都填",IF(AND($D15="收入",N($J15)=0),"※收入行要填收入金额",IF(AND($D15="支出",N($K15)=0),"※支出行要填支出金额",IF(AND($C15<>"",ISNA(MATCH($C15,账户表,0))),"※账户不在基础资料里",IF(AND($G15<>"",ISNA(MATCH($G15,项目名表,0))),"※项目不在项目台账里",IF(AND(LEFT($F15,3)="成本-",$G15=""),"※成本类支出没填项目",IF(AND(LEFT($F15,3)="成本-",$H15<>"",N($K15)>0,COUNTIFS(采购单!$B:$B,$B15,采购单!$C:$C,$H15,采购单!$L:$L,$K15)>0),"※这笔可能和采购单重复了",""))))))))))
A16: =IF($B16="","",ROW()-3) | B16: 46084 | C16: 微信1 | D16: 支出 | E16: 运费/快递费 | F16: =IF($E16="","",IFERROR(VLOOKUP($E16,类别归属,2,0),"※类别不在基础资料里")) | G16: 织里店 | H16: 炳秀 | I16: 付炳秀配送 | K16: 80 | L16: =IF($C16="","",ROUND(IFERROR(VLOOKUP($C16,账户期初,2,0),0)+SUMIFS($J$4:J16,$C$4:C16,$C16)-SUMIFS($K$4:K16,$C$4:C16,$C16),2)) | M16: =IF($C16="","",ROUND(SUM(基础资料!$B$4:$B$13)+SUM($J$4:J16)-SUM($K$4:K16),2)) | P16: =IF($B16="","",IF($F16="※类别不在基础资料里","※费用类别不在基础资料里",IF(AND(N($J16)=0,N($K16)=0),"※这行没填金额",IF(AND(N($J16)>0,N($K16)>0),"※收入和支出不能同一行都填",IF(AND($D16="收入",N($J16)=0),"※收入行要填收入金额",IF(AND($D16="支出",N($K16)=0),"※支出行要填支出金额",IF(AND($C16<>"",ISNA(MATCH($C16,账户表,0))),"※账户不在基础资料里",IF(AND($G16<>"",ISNA(MATCH($G16,项目名表,0))),"※项目不在项目台账里",IF(AND(LEFT($F16,3)="成本-",$G16=""),"※成本类支出没填项目",IF(AND(LEFT($F16,3)="成本-",$H16<>"",N($K16)>0,COUNTIFS(采购单!$B:$B,$B16,采购单!$C:$C,$H16,采购单!$L:$L,$K16)>0),"※这笔可能和采购单重复了",""))))))))))
A17: =IF($B17="","",ROW()-3) | B17: 46084 | C17: 微信1 | D17: 收入 | E17: 项目收款 | F17: =IF($E17="","",IFERROR(VLOOKUP($E17,类别归属,2,0),"※类别不在基础资料里")) | G17: 高恒荣熟食店 | I17: 收木森装饰公司-波 | J17: 8000 | L17: =IF($C17="","",ROUND(IFERROR(VLOOKUP($C17,账户期初,2,0),0)+SUMIFS($J$4:J17,$C$4:C17,$C17)-SUMIFS($K$4:K17,$C$4:C17,$C17),2)) | M17: =IF($C17="","",ROUND(SUM(基础资料!$B$4:$B$13)+SUM($J$4:J17)-SUM($K$4:K17),2)) | P17: =IF($B17="","",IF($F17="※类别不在基础资料里","※费用类别不在基础资料里",IF(AND(N($J17)=0,N($K17)=0),"※这行没填金额",IF(AND(N($J17)>0,N($K17)>0),"※收入和支出不能同一行都填",IF(AND($D17="收入",N($J17)=0),"※收入行要填收入金额",IF(AND($D17="支出",N($K17)=0),"※支出行要填支出金额",IF(AND($C17<>"",ISNA(MATCH($C17,账户表,0))),"※账户不在基础资料里",IF(AND($G17<>"",ISNA(MATCH($G17,项目名表,0))),"※项目不在项目台账里",IF(AND(LEFT($F17,3)="成本-",$G17=""),"※成本类支出没填项目",IF(AND(LEFT($F17,3)="成本-",$H17<>"",N($K17)>0,COUNTIFS(采购单!$B:$B,$B17,采购单!$C:$C,$H17,采购单!$L:$L,$K17)>0),"※这笔可能和采购单重复了",""))))))))))
A18: =IF($B18="","",ROW()-3) | B18: 46084 | C18: 微信1 | D18: 支出 | E18: 借出款 | F18: =IF($E18="","",IFERROR(VLOOKUP($E18,类别归属,2,0),"※类别不在基础资料里")) | H18: 往来款 | I18: 付给付久华(3.6退2000+付1000买方管） | K18: 3000 | L18: =IF($C18="","",ROUND(IFERROR(VLOOKUP($C18,账户期初,2,0),0)+SUMIFS($J$4:J18,$C$4:C18,$C18)-SUMIFS($K$4:K18,$C$4:C18,$C18),2)) | M18: =IF($C18="","",ROUND(SUM(基础资料!$B$4:$B$13)+SUM($J$4:J18)-SUM($K$4:K18),2)) | P18: =IF($B18="","",IF($F18="※类别不在基础资料里","※费用类别不在基础资料里",IF(AND(N($J18)=0,N($K18)=0),"※这行没填金额",IF(AND(N($J18)>0,N($K18)>0),"※收入和支出不能同一行都填",IF(AND($D18="收入",N($J18)=0),"※收入行要填收入金额",IF(AND($D18="支出",N($K18)=0),"※支出行要填支出金额",IF(AND($C18<>"",ISNA(MATCH($C18,账户表,0))),"※账户不在基础资料里",IF(AND($G18<>"",ISNA(MATCH($G18,项目名表,0))),"※项目不在项目台账里",IF(AND(LEFT($F18,3)="成本-",$G18=""),"※成本类支出没填项目",IF(AND(LEFT($F18,3)="成本-",$H18<>"",N($K18)>0,COUNTIFS(采购单!$B:$B,$B18,采购单!$C:$C,$H18,采购单!$L:$L,$K18)>0),"※这笔可能和采购单重复了",""))))))))))
A19: =IF($B19="","",ROW()-3) | B19: 46084 | C19: 微信1 | D19: 支出 | E19: 团建费 | F19: =IF($E19="","",IFERROR(VLOOKUP($E19,类别归属,2,0),"※类别不在基础资料里")) | I19: 付团建费 | K19: 376 | L19: =IF($C19="","",ROUND(IFERROR(VLOOKUP($C19,账户期初,2,0),0)+SUMIFS($J$4:J19,$C$4:C19,$C19)-SUMIFS($K$4:K19,$C$4:C19,$C19),2)) | M19: =IF($C19="","",ROUND(SUM(基础资料!$B$4:$B$13)+SUM($J$4:J19)-SUM($K$4:K19),2)) | P19: =IF($B19="","",IF($F19="※类别不在基础资料里","※费用类别不在基础资料里",IF(AND(N($J19)=0,N($K19)=0),"※这行没填金额",IF(AND(N($J19)>0,N($K19)>0),"※收入和支出不能同一行都填",IF(AND($D19="收入",N($J19)=0),"※收入行要填收入金额",IF(AND($D19="支出",N($K19)=0),"※支出行要填支出金额",IF(AND($C19<>"",ISNA(MATCH($C19,账户表,0))),"※账户不在基础资料里",IF(AND($G19<>"",ISNA(MATCH($G19,项目名表,0))),"※项目不在项目台账里",IF(AND(LEFT($F19,3)="成本-",$G19=""),"※成本类支出没填项目",IF(AND(LEFT($F19,3)="成本-",$H19<>"",N($K19)>0,COUNTIFS(采购单!$B:$B,$B19,采购单!$C:$C,$H19,采购单!$L:$L,$K19)>0),"※这笔可能和采购单重复了",""))))))))))
A20: =IF($B20="","",ROW()-3) | B20: 46084 | C20: 微信1 | D20: 支出 | E20: 团建费 | F20: =IF($E20="","",IFERROR(VLOOKUP($E20,类别归属,2,0),"※类别不在基础资料里")) | I20: 付冠鸿餐饮团建-押金（已收回） | J20: 50 | K20: 50 | L20: =IF($C20="","",ROUND(IFERROR(VLOOKUP($C20,账户期初,2,0),0)+SUMIFS($J$4:J20,$C$4:C20,$C20)-SUMIFS($K$4:K20,$C$4:C20,$C20),2)) | M20: =IF($C20="","",ROUND(SUM(基础资料!$B$4:$B$13)+SUM($J$4:J20)-SUM($K$4:K20),2)) | P20: =IF($B20="","",IF($F20="※类别不在基础资料里","※费用类别不在基础资料里",IF(AND(N($J20)=0,N($K20)=0),"※这行没填金额",IF(AND(N($J20)>0,N($K20)>0),"※收入和支出不能同一行都填",IF(AND($D20="收入",N($J20)=0),"※收入行要填收入金额",IF(AND($D20="支出",N($K20)=0),"※支出行要填支出金额",IF(AND($C20<>"",ISNA(MATCH($C20,账户表,0))),"※账户不在基础资料里",IF(AND($G20<>"",ISNA(MATCH($G20,项目名表,0))),"※项目不在项目台账里",IF(AND(LEFT($F20,3)="成本-",$G20=""),"※成本类支出没填项目",IF(AND(LEFT($F20,3)="成本-",$H20<>"",N($K20)>0,COUNTIFS(采购单!$B:$B,$B20,采购单!$C:$C,$H20,采购单!$L:$L,$K20)>0),"※这笔可能和采购单重复了",""))))))))))
A21: =IF($B21="","",ROW()-3) | B21: 46085 | C21: 微信1 | D21: 支出 | E21: 主材采购 | F21: =IF($E21="","",IFERROR(VLOOKUP($E21,类别归属,2,0),"※类别不在基础资料里")) | G21: 高恒荣熟食店 | I21: 付采购长城板-杭州丽彩（常俊山） | K21: 725 | L21: =IF($C21="","",ROUND(IFERROR(VLOOKUP($C21,账户期初,2,0),0)+SUMIFS($J$4:J21,$C$4:C21,$C21)-SUMIFS($K$4:K21,$C$4:C21,$C21),2)) | M21: =IF($C21="","",ROUND(SUM(基础资料!$B$4:$B$13)+SUM($J$4:J21)-SUM($K$4:K21),2)) | P21: =IF($B21="","",IF($F21="※类别不在基础资料里","※费用类别不在基础资料里",IF(AND(N($J21)=0,N($K21)=0),"※这行没填金额",IF(AND(N($J21)>0,N($K21)>0),"※收入和支出不能同一行都填",IF(AND($D21="收入",N($J21)=0),"※收入行要填收入金额",IF(AND($D21="支出",N($K21)=0),"※支出行要填支出金额",IF(AND($C21<>"",ISNA(MATCH($C21,账户表,0))),"※账户不在基础资料里",IF(AND($G21<>"",ISNA(MATCH($G21,项目名表,0))),"※项目不在项目台账里",IF(AND(LEFT($F21,3)="成本-",$G21=""),"※成本类支出没填项目",IF(AND(LEFT($F21,3)="成本-",$H21<>"",N($K21)>0,COUNTIFS(采购单!$B:$B,$B21,采购单!$C:$C,$H21,采购单!$L:$L,$K21)>0),"※这笔可能和采购单重复了",""))))))))))
A22: =IF($B22="","",ROW()-3) | B22: 46085 | C22: 微信1 | D22: 支出 | E22: 运费/快递费 | F22: =IF($E22="","",IFERROR(VLOOKUP($E22,类别归属,2,0),"※类别不在基础资料里")) | G22: 织里店 | H22: 炳秀 | I22: 付炳秀配送 | K22: 55 | L22: =IF($C22="","",ROUND(IFERROR(VLOOKUP($C22,账户期初,2,0),0)+SUMIFS($J$4:J22,$C$4:C22,$C22)-SUMIFS($K$4:K22,$C$4:C22,$C22),2)) | M22: =IF($C22="","",ROUND(SUM(基础资料!$B$4:$B$13)+SUM($J$4:J22)-SUM($K$4:K22),2)) | P22: =IF($B22="","",IF($F22="※类别不在基础资料里","※费用类别不在基础资料里",IF(AND(N($J22)=0,N($K22)=0),"※这行没填金额",IF(AND(N($J22)>0,N($K22)>0),"※收入和支出不能同一行都填",IF(AND($D22="收入",N($J22)=0),"※收入行要填收入金额",IF(AND($D22="支出",N($K22)=0),"※支出行要填支出金额",IF(AND($C22<>"",ISNA(MATCH($C22,账户表,0))),"※账户不在基础资料里",IF(AND($G22<>"",ISNA(MATCH($G22,项目名表,0))),"※项目不在项目台账里",IF(AND(LEFT($F22,3)="成本-",$G22=""),"※成本类支出没填项目",IF(AND(LEFT($F22,3)="成本-",$H22<>"",N($K22)>0,COUNTIFS(采购单!$B:$B,$B22,采购单!$C:$C,$H22,采购单!$L:$L,$K22)>0),"※这笔可能和采购单重复了",""))))))))))
A23: =IF($B23="","",ROW()-3) | B23: 46085 | C23: 微信1 | D23: 支出 | E23: 运费/快递费 | F23: =IF($E23="","",IFERROR(VLOOKUP($E23,类别归属,2,0),"※类别不在基础资料里")) | G23: 卓越桌球 | H23: 炳秀 | I23: 付炳秀配送 | K23: 17 | L23: =IF($C23="","",ROUND(IFERROR(VLOOKUP($C23,账户期初,2,0),0)+SUMIFS($J$4:J23,$C$4:C23,$C23)-SUMIFS($K$4:K23,$C$4:C23,$C23),2)) | M23: =IF($C23="","",ROUND(SUM(基础资料!$B$4:$B$13)+SUM($J$4:J23)-SUM($K$4:K23),2)) | P23: =IF($B23="","",IF($F23="※类别不在基础资料里","※费用类别不在基础资料里",IF(AND(N($J23)=0,N($K23)=0),"※这行没填金额",IF(AND(N($J23)>0,N($K23)>0),"※收入和支出不能同一行都填",IF(AND($D23="收入",N($J23)=0),"※收入行要填收入金额",IF(AND($D23="支出",N($K23)=0),"※支出行要填支出金额",IF(AND($C23<>"",ISNA(MATCH($C23,账户表,0))),"※账户不在基础资料里",IF(AND($G23<>"",ISNA(MATCH($G23,项目名表,0))),"※项目不在项目台账里",IF(AND(LEFT($F23,3)="成本-",$G23=""),"※成本类支出没填项目",IF(AND(LEFT($F23,3)="成本-",$H23<>"",N($K23)>0,COUNTIFS(采购单!$B:$B,$B23,采购单!$C:$C,$H23,采购单!$L:$L,$K23)>0),"※这笔可能和采购单重复了",""))))))))))
A24: =IF($B24="","",ROW()-3) | B24: 46085 | C24: 微信1 | D24: 支出 | E24: 运费/快递费 | F24: =IF($E24="","",IFERROR(VLOOKUP($E24,类别归属,2,0),"※类别不在基础资料里")) | G24: 东尼电子 | H24: 炳秀 | I24: 付炳秀配送 | K24: 39 | L24: =IF($C24="","",ROUND(IFERROR(VLOOKUP($C24,账户期初,2,0),0)+SUMIFS($J$4:J24,$C$4:C24,$C24)-SUMIFS($K$4:K24,$C$4:C24,$C24),2)) | M24: =IF($C24="","",ROUND(SUM(基础资料!$B$4:$B$13)+SUM($J$4:J24)-SUM($K$4:K24),2)) | P24: =IF($B24="","",IF($F24="※类别不在基础资料里","※费用类别不在基础资料里",IF(AND(N($J24)=0,N($K24)=0),"※这行没填金额",IF(AND(N($J24)>0,N($K24)>0),"※收入和支出不能同一行都填",IF(AND($D24="收入",N($J24)=0),"※收入行要填收入金额",IF(AND($D24="支出",N($K24)=0),"※支出行要填支出金额",IF(AND($C24<>"",ISNA(MATCH($C24,账户表,0))),"※账户不在基础资料里",IF(AND($G24<>"",ISNA(MATCH($G24,项目名表,0))),"※项目不在项目台账里",IF(AND(LEFT($F24,3)="成本-",$G24=""),"※成本类支出没填项目",IF(AND(LEFT($F24,3)="成本-",$H24<>"",N($K24)>0,COUNTIFS(采购单!$B:$B,$B24,采购单!$C:$C,$H24,采购单!$L:$L,$K24)>0),"※这笔可能和采购单重复了",""))))))))))
A25: =IF($B25="","",ROW()-3) | B25: 46085 | C25: 微信1 | D25: 支出 | E25: 其他管理费用 | F25: =IF($E25="","",IFERROR(VLOOKUP($E25,类别归属,2,0),"※类别不在基础资料里")) | I25: 付杨德报销费用 | K25: 1216 | L25: =IF($C25="","",ROUND(IFERROR(VLOOKUP($C25,账户期初,2,0),0)+SUMIFS($J$4:J25,$C$4:C25,$C25)-SUMIFS($K$4:K25,$C$4:C25,$C25),2)) | M25: =IF($C25="","",ROUND(SUM(基础资料!$B$4:$B$13)+SUM($J$4:J25)-SUM($K$4:K25),2)) | P25: =IF($B25="","",IF($F25="※类别不在基础资料里","※费用类别不在基础资料里",IF(AND(N($J25)=0,N($K25)=0),"※这行没填金额",IF(AND(N($J25)>0,N($K25)>0),"※收入和支出不能同一行都填",IF(AND($D25="收入",N($J25)=0),"※收入行要填收入金额",IF(AND($D25="支出",N($K25)=0),"※支出行要填支出金额",IF(AND($C25<>"",ISNA(MATCH($C25,账户表,0))),"※账户不在基础资料里",IF(AND($G25<>"",ISNA(MATCH($G25,项目名表,0))),"※项目不在项目台账里",IF(AND(LEFT($F25,3)="成本-",$G25=""),"※成本类支出没填项目",IF(AND(LEFT($F25,3)="成本-",$H25<>"",N($K25)>0,COUNTIFS(采购单!$B:$B,$B25,采购单!$C:$C,$H25,采购单!$L:$L,$K25)>0),"※这笔可能和采购单重复了",""))))))))))
A26: =IF($B26="","",ROW()-3) | B26: 46086 | C26: 微信1 | D26: 支出 | E26: 主材采购 | F26: =IF($E26="","",IFERROR(VLOOKUP($E26,类别归属,2,0),"※类别不在基础资料里")) | I26: 付杭州杜邦纸-软膜 | K26: 520 | L26: =IF($C26="","",ROUND(IFERROR(VLOOKUP($C26,账户期初,2,0),0)+SUMIFS($J$4:J26,$C$4:C26,$C26)-SUMIFS($K$4:K26,$C$4:C26,$C26),2)) | M26: =IF($C26="","",ROUND(SUM(基础资料!$B$4:$B$13)+SUM($J$4:J26)-SUM($K$4:K26),2)) | P26: =IF($B26="","",IF($F26="※类别不在基础资料里","※费用类别不在基础资料里",IF(AND(N($J26)=0,N($K26)=0),"※这行没填金额",IF(AND(N($J26)>0,N($K26)>0),"※收入和支出不能同一行都填",IF(AND($D26="收入",N($J26)=0),"※收入行要填收入金额",IF(AND($D26="支出",N($K26)=0),"※支出行要填支出金额",IF(AND($C26<>"",ISNA(MATCH($C26,账户表,0))),"※账户不在基础资料里",IF(AND($G26<>"",ISNA(MATCH($G26,项目名表,0))),"※项目不在项目台账里",IF(AND(LEFT($F26,3)="成本-",$G26=""),"※成本类支出没填项目",IF(AND(LEFT($F26,3)="成本-",$H26<>"",N($K26)>0,COUNTIFS(采购单!$B:$B,$B26,采购单!$C:$C,$H26,采购单!$L:$L,$K26)>0),"※这笔可能和采购单重复了",""))))))))))
A27: =IF($B27="","",ROW()-3) | B27: 46086 | C27: 微信1 | D27: 支出 | E27: 主材采购 | F27: =IF($E27="","",IFERROR(VLOOKUP($E27,类别归属,2,0),"※类别不在基础资料里")) | G27: 东尼电子 | I27: 付采购呗彩-LED发光屏 | K27: 1580 | L27: =IF($C27="","",ROUND(IFERROR(VLOOKUP($C27,账户期初,2,0),0)+SUMIFS($J$4:J27,$C$4:C27,$C27)-SUMIFS($K$4:K27,$C$4:C27,$C27),2)) | M27: =IF($C27="","",ROUND(SUM(基础资料!$B$4:$B$13)+SUM($J$4:J27)-SUM($K$4:K27),2)) | O27: 应该是东尼的 | P27: =IF($B27="","",IF($F27="※类别不在基础资料里","※费用类别不在基础资料里",IF(AND(N($J27)=0,N($K27)=0),"※这行没填金额",IF(AND(N($J27)>0,N($K27)>0),"※收入和支出不能同一行都填",IF(AND($D27="收入",N($J27)=0),"※收入行要填收入金额",IF(AND($D27="支出",N($K27)=0),"※支出行要填支出金额",IF(AND($C27<>"",ISNA(MATCH($C27,账户表,0))),"※账户不在基础资料里",IF(AND($G27<>"",ISNA(MATCH($G27,项目名表,0))),"※项目不在项目台账里",IF(AND(LEFT($F27,3)="成本-",$G27=""),"※成本类支出没填项目",IF(AND(LEFT($F27,3)="成本-",$H27<>"",N($K27)>0,COUNTIFS(采购单!$B:$B,$B27,采购单!$C:$C,$H27,采购单!$L:$L,$K27)>0),"※这笔可能和采购单重复了",""))))))))))
A28: =IF($B28="","",ROW()-3) | B28: 46086 | C28: 微信1 | D28: 支出 | E28: 运费/快递费 | F28: =IF($E28="","",IFERROR(VLOOKUP($E28,类别归属,2,0),"※类别不在基础资料里")) | G28: 织里店 | H28: 炳秀 | I28: 付炳秀配送 | K28: 9 | L28: =IF($C28="","",ROUND(IFERROR(VLOOKUP($C28,账户期初,2,0),0)+SUMIFS($J$4:J28,$C$4:C28,$C28)-SUMIFS($K$4:K28,$C$4:C28,$C28),2)) | M28: =IF($C28="","",ROUND(SUM(基础资料!$B$4:$B$13)+SUM($J$4:J28)-SUM($K$4:K28),2)) | P28: =IF($B28="","",IF($F28="※类别不在基础资料里","※费用类别不在基础资料里",IF(AND(N($J28)=0,N($K28)=0),"※这行没填金额",IF(AND(N($J28)>0,N($K28)>0),"※收入和支出不能同一行都填",IF(AND($D28="收入",N($J28)=0),"※收入行要填收入金额",IF(AND($D28="支出",N($K28)=0),"※支出行要填支出金额",IF(AND($C28<>"",ISNA(MATCH($C28,账户表,0))),"※账户不在基础资料里",IF(AND($G28<>"",ISNA(MATCH($G28,项目名表,0))),"※项目不在项目台账里",IF(AND(LEFT($F28,3)="成本-",$G28=""),"※成本类支出没填项目",IF(AND(LEFT($F28,3)="成本-",$H28<>"",N($K28)>0,COUNTIFS(采购单!$B:$B,$B28,采购单!$C:$C,$H28,采购单!$L:$L,$K28)>0),"※这笔可能和采购单重复了",""))))))))))
A29: =IF($B29="","",ROW()-3) | B29: 46086 | C29: 微信1 | D29: 支出 | E29: 通讯费 | F29: =IF($E29="","",IFERROR(VLOOKUP($E29,类别归属,2,0),"※类别不在基础资料里")) | I29: 付中国移动话费 | K29: 50 | L29: =IF($C29="","",ROUND(IFERROR(VLOOKUP($C29,账户期初,2,0),0)+SUMIFS($J$4:J29,$C$4:C29,$C29)-SUMIFS($K$4:K29,$C$4:C29,$C29),2)) | M29: =IF($C29="","",ROUND(SUM(基础资料!$B$4:$B$13)+SUM($J$4:J29)-SUM($K$4:K29),2)) | P29: =IF($B29="","",IF($F29="※类别不在基础资料里","※费用类别不在基础资料里",IF(AND(N($J29)=0,N($K29)=0),"※这行没填金额",IF(AND(N($J29)>0,N($K29)>0),"※收入和支出不能同一行都填",IF(AND($D29="收入",N($J29)=0),"※收入行要填收入金额",IF(AND($D29="支出",N($K29)=0),"※支出行要填支出金额",IF(AND($C29<>"",ISNA(MATCH($C29,账户表,0))),"※账户不在基础资料里",IF(AND($G29<>"",ISNA(MATCH($G29,项目名表,0))),"※项目不在项目台账里",IF(AND(LEFT($F29,3)="成本-",$G29=""),"※成本类支出没填项目",IF(AND(LEFT($F29,3)="成本-",$H29<>"",N($K29)>0,COUNTIFS(采购单!$B:$B,$B29,采购单!$C:$C,$H29,采购单!$L:$L,$K29)>0),"※这笔可能和采购单重复了",""))))))))))
A30: =IF($B30="","",ROW()-3) | B30: 46087 | C30: 微信1 | D30: 收入 | E30: 收回借出款 | F30: =IF($E30="","",IFERROR(VLOOKUP($E30,类别归属,2,0),"※类别不在基础资料里")) | H30: 往来款 | I30: 收付久华 | J30: 2000 | L30: =IF($C30="","",ROUND(IFERROR(VLOOKUP($C30,账户期初,2,0),0)+SUMIFS($J$4:J30,$C$4:C30,$C30)-SUMIFS($K$4:K30,$C$4:C30,$C30),2)) | M30: =IF($C30="","",ROUND(SUM(基础资料!$B$4:$B$13)+SUM($J$4:J30)-SUM($K$4:K30),2)) | O30: 3.6止凌实存3235 | P30: =IF($B30="","",IF($F30="※类别不在基础资料里","※费用类别不在基础资料里",IF(AND(N($J30)=0,N($K30)=0),"※这行没填金额",IF(AND(N($J30)>0,N($K30)>0),"※收入和支出不能同一行都填",IF(AND($D30="收入",N($J30)=0),"※收入行要填收入金额",IF(AND($D30="支出",N($K30)=0),"※支出行要填支出金额",IF(AND($C30<>"",ISNA(MATCH($C30,账户表,0))),"※账户不在基础资料里",IF(AND($G30<>"",ISNA(MATCH($G30,项目名表,0))),"※项目不在项目台账里",IF(AND(LEFT($F30,3)="成本-",$G30=""),"※成本类支出没填项目",IF(AND(LEFT($F30,3)="成本-",$H30<>"",N($K30)>0,COUNTIFS(采购单!$B:$B,$B30,采购单!$C:$C,$H30,采购单!$L:$L,$K30)>0),"※这笔可能和采购单重复了",""))))))))))
A31: =IF($B31="","",ROW()-3) | B31: 46087 | C31: 微信1 | D31: 支出 | E31: 运费/快递费 | F31: =IF($E31="","",IFERROR(VLOOKUP($E31,类别归属,2,0),"※类别不在基础资料里")) | G31: 织里店 | H31: 炳秀 | I31: 付炳秀配送 | K31: 55 | L31: =IF($C31="","",ROUND(IFERROR(VLOOKUP($C31,账户期初,2,0),0)+SUMIFS($J$4:J31,$C$4:C31,$C31)-SUMIFS($K$4:K31,$C$4:C31,$C31),2)) | M31: =IF($C31="","",ROUND(SUM(基础资料!$B$4:$B$13)+SUM($J$4:J31)-SUM($K$4:K31),2)) | P31: =IF($B31="","",IF($F31="※类别不在基础资料里","※费用类别不在基础资料里",IF(AND(N($J31)=0,N($K31)=0),"※这行没填金额",IF(AND(N($J31)>0,N($K31)>0),"※收入和支出不能同一行都填",IF(AND($D31="收入",N($J31)=0),"※收入行要填收入金额",IF(AND($D31="支出",N($K31)=0),"※支出行要填支出金额",IF(AND($C31<>"",ISNA(MATCH($C31,账户表,0))),"※账户不在基础资料里",IF(AND($G31<>"",ISNA(MATCH($G31,项目名表,0))),"※项目不在项目台账里",IF(AND(LEFT($F31,3)="成本-",$G31=""),"※成本类支出没填项目",IF(AND(LEFT($F31,3)="成本-",$H31<>"",N($K31)>0,COUNTIFS(采购单!$B:$B,$B31,采购单!$C:$C,$H31,采购单!$L:$L,$K31)>0),"※这笔可能和采购单重复了",""))))))))))
A32: =IF($B32="","",ROW()-3) | B32: 46087 | C32: 微信1 | D32: 收入 | E32: 零星物料销售 | F32: =IF($E32="","",IFERROR(VLOOKUP($E32,类别归属,2,0),"※类别不在基础资料里")) | G32: 万达kvv | I32: 万达-KVV乔金鑫 | J32: 40 | L32: =IF($C32="","",ROUND(IFERROR(VLOOKUP($C32,账户期初,2,0),0)+SUMIFS($J$4:J32,$C$4:C32,$C32)-SUMIFS($K$4:K32,$C$4:C32,$C32),2)) | M32: =IF($C32="","",ROUND(SUM(基础资料!$B$4:$B$13)+SUM($J$4:J32)-SUM($K$4:K32),2)) | P32: =IF($B32="","",IF($F32="※类别不在基础资料里","※费用类别不在基础资料里",IF(AND(N($J32)=0,N($K32)=0),"※这行没填金额",IF(AND(N($J32)>0,N($K32)>0),"※收入和支出不能同一行都填",IF(AND($D32="收入",N($J32)=0),"※收入行要填收入金额",IF(AND($D32="支出",N($K32)=0),"※支出行要填支出金额",IF(AND($C32<>"",ISNA(MATCH($C32,账户表,0))),"※账户不在基础资料里",IF(AND($G32<>"",ISNA(MATCH($G32,项目名表,0))),"※项目不在项目台账里",IF(AND(LEFT($F32,3)="成本-",$G32=""),"※成本类支出没填项目",IF(AND(LEFT($F32,3)="成本-",$H32<>"",N($K32)>0,COUNTIFS(采购单!$B:$B,$B32,采购单!$C:$C,$H32,采购单!$L:$L,$K32)>0),"※这笔可能和采购单重复了",""))))))))))
A33: =IF($B33="","",ROW()-3) | B33: 46088 | C33: 微信1 | D33: 收入 | E33: 项目收款 | F33: =IF($E33="","",IFERROR(VLOOKUP($E33,类别归属,2,0),"※类别不在基础资料里")) | G33: 高恒荣熟食店 | I33: 收德清木森 | J33: 4500 | L33: =IF($C33="","",ROUND(IFERROR(VLOOKUP($C33,账户期初,2,0),0)+SUMIFS($J$4:J33,$C$4:C33,$C33)-SUMIFS($K$4:K33,$C$4:C33,$C33),2)) | M33: =IF($C33="","",ROUND(SUM(基础资料!$B$4:$B$13)+SUM($J$4:J33)-SUM($K$4:K33),2)) | P33: =IF($B33="","",IF($F33="※类别不在基础资料里","※费用类别不在基础资料里",IF(AND(N($J33)=0,N($K33)=0),"※这行没填金额",IF(AND(N($J33)>0,N($K33)>0),"※收入和支出不能同一行都填",IF(AND($D33="收入",N($J33)=0),"※收入行要填收入金额",IF(AND($D33="支出",N($K33)=0),"※支出行要填支出金额",IF(AND($C33<>"",ISNA(MATCH($C33,账户表,0))),"※账户不在基础资料里",IF(AND($G33<>"",ISNA(MATCH($G33,项目名表,0))),"※项目不在项目台账里",IF(AND(LEFT($F33,3)="成本-",$G33=""),"※成本类支出没填项目",IF(AND(LEFT($F33,3)="成本-",$H33<>"",N($K33)>0,COUNTIFS(采购单!$B:$B,$B33,采购单!$C:$C,$H33,采购单!$L:$L,$K33)>0),"※这笔可能和采购单重复了",""))))))))))
A34: =IF($B34="","",ROW()-3) | B34: 46088 | C34: 微信1 | D34: 支出 | E34: 主材采购 | F34: =IF($E34="","",IFERROR(VLOOKUP($E34,类别归属,2,0),"※类别不在基础资料里")) | I34: 荣盛钢材镀锌角铁4*4（6*60） | K34: 360 | L34: =IF($C34="","",ROUND(IFERROR(VLOOKUP($C34,账户期初,2,0),0)+SUMIFS($J$4:J34,$C$4:C34,$C34)-SUMIFS($K$4:K34,$C$4:C34,$C34),2)) | M34: =IF($C34="","",ROUND(SUM(基础资料!$B$4:$B$13)+SUM($J$4:J34)-SUM($K$4:K34),2)) | P34: =IF($B34="","",IF($F34="※类别不在基础资料里","※费用类别不在基础资料里",IF(AND(N($J34)=0,N($K34)=0),"※这行没填金额",IF(AND(N($J34)>0,N($K34)>0),"※收入和支出不能同一行都填",IF(AND($D34="收入",N($J34)=0),"※收入行要填收入金额",IF(AND($D34="支出",N($K34)=0),"※支出行要填支出金额",IF(AND($C34<>"",ISNA(MATCH($C34,账户表,0))),"※账户不在基础资料里",IF(AND($G34<>"",ISNA(MATCH($G34,项目名表,0))),"※项目不在项目台账里",IF(AND(LEFT($F34,3)="成本-",$G34=""),"※成本类支出没填项目",IF(AND(LEFT($F34,3)="成本-",$H34<>"",N($K34)>0,COUNTIFS(采购单!$B:$B,$B34,采购单!$C:$C,$H34,采购单!$L:$L,$K34)>0),"※这笔可能和采购单重复了",""))))))))))
A35: =IF($B35="","",ROW()-3) | B35: 46088 | C35: 微信1 | D35: 支出 | E35: 运费/快递费 | F35: =IF($E35="","",IFERROR(VLOOKUP($E35,类别归属,2,0),"※类别不在基础资料里")) | G35: 犇腾牛排 | H35: 炳秀 | I35: 付炳秀配送 | K35: 28 | L35: =IF($C35="","",ROUND(IFERROR(VLOOKUP($C35,账户期初,2,0),0)+SUMIFS($J$4:J35,$C$4:C35,$C35)-SUMIFS($K$4:K35,$C$4:C35,$C35),2)) | M35: =IF($C35="","",ROUND(SUM(基础资料!$B$4:$B$13)+SUM($J$4:J35)-SUM($K$4:K35),2)) | P35: =IF($B35="","",IF($F35="※类别不在基础资料里","※费用类别不在基础资料里",IF(AND(N($J35)=0,N($K35)=0),"※这行没填金额",IF(AND(N($J35)>0,N($K35)>0),"※收入和支出不能同一行都填",IF(AND($D35="收入",N($J35)=0),"※收入行要填收入金额",IF(AND($D35="支出",N($K35)=0),"※支出行要填支出金额",IF(AND($C35<>"",ISNA(MATCH($C35,账户表,0))),"※账户不在基础资料里",IF(AND($G35<>"",ISNA(MATCH($G35,项目名表,0))),"※项目不在项目台账里",IF(AND(LEFT($F35,3)="成本-",$G35=""),"※成本类支出没填项目",IF(AND(LEFT($F35,3)="成本-",$H35<>"",N($K35)>0,COUNTIFS(采购单!$B:$B,$B35,采购单!$C:$C,$H35,采购单!$L:$L,$K35)>0),"※这笔可能和采购单重复了",""))))))))))
A36: =IF($B36="","",ROW()-3) | B36: 46088 | C36: 微信1 | D36: 支出 | E36: 主材采购 | F36: =IF($E36="","",IFERROR(VLOOKUP($E36,类别归属,2,0),"※类别不在基础资料里")) | G36: 高恒荣熟食店 | I36: 付南浔优丰建材-415中国红铝塑板 | K36: 1260 | L36: =IF($C36="","",ROUND(IFERROR(VLOOKUP($C36,账户期初,2,0),0)+SUMIFS($J$4:J36,$C$4:C36,$C36)-SUMIFS($K$4:K36,$C$4:C36,$C36),2)) | M36: =IF($C36="","",ROUND(SUM(基础资料!$B$4:$B$13)+SUM($J$4:J36)-SUM($K$4:K36),2)) | P36: =IF($B36="","",IF($F36="※类别不在基础资料里","※费用类别不在基础资料里",IF(AND(N($J36)=0,N($K36)=0),"※这行没填金额",IF(AND(N($J36)>0,N($K36)>0),"※收入和支出不能同一行都填",IF(AND($D36="收入",N($J36)=0),"※收入行要填收入金额",IF(AND($D36="支出",N($K36)=0),"※支出行要填支出金额",IF(AND($C36<>"",ISNA(MATCH($C36,账户表,0))),"※账户不在基础资料里",IF(AND($G36<>"",ISNA(MATCH($G36,项目名表,0))),"※项目不在项目台账里",IF(AND(LEFT($F36,3)="成本-",$G36=""),"※成本类支出没填项目",IF(AND(LEFT($F36,3)="成本-",$H36<>"",N($K36)>0,COUNTIFS(采购单!$B:$B,$B36,采购单!$C:$C,$H36,采购单!$L:$L,$K36)>0),"※这笔可能和采购单重复了",""))))))))))
A37: =IF($B37="","",ROW()-3) | B37: 46089 | C37: 微信1 | D37: 支出 | E37: 主材采购 | F37: =IF($E37="","",IFERROR(VLOOKUP($E37,类别归属,2,0),"※类别不在基础资料里")) | G37: 高恒荣熟食店 | I37: 镀锌方管2*4（14*28） | K37: 392 | L37: =IF($C37="","",ROUND(IFERROR(VLOOKUP($C37,账户期初,2,0),0)+SUMIFS($J$4:J37,$C$4:C37,$C37)-SUMIFS($K$4:K37,$C$4:C37,$C37),2)) | M37: =IF($C37="","",ROUND(SUM(基础资料!$B$4:$B$13)+SUM($J$4:J37)-SUM($K$4:K37),2)) | P37: =IF($B37="","",IF($F37="※类别不在基础资料里","※费用类别不在基础资料里",IF(AND(N($J37)=0,N($K37)=0),"※这行没填金额",IF(AND(N($J37)>0,N($K37)>0),"※收入和支出不能同一行都填",IF(AND($D37="收入",N($J37)=0),"※收入行要填收入金额",IF(AND($D37="支出",N($K37)=0),"※支出行要填支出金额",IF(AND($C37<>"",ISNA(MATCH($C37,账户表,0))),"※账户不在基础资料里",IF(AND($G37<>"",ISNA(MATCH($G37,项目名表,0))),"※项目不在项目台账里",IF(AND(LEFT($F37,3)="成本-",$G37=""),"※成本类支出没填项目",IF(AND(LEFT($F37,3)="成本-",$H37<>"",N($K37)>0,COUNTIFS(采购单!$B:$B,$B37,采购单!$C:$C,$H37,采购单!$L:$L,$K37)>0),"※这笔可能和采购单重复了",""))))))))))
A38: =IF($B38="","",ROW()-3) | B38: 46089 | C38: 微信1 | D38: 支出 | E38: 运费/快递费 | F38: =IF($E38="","",IFERROR(VLOOKUP($E38,类别归属,2,0),"※类别不在基础资料里")) | G38: 织里店 | H38: 炳秀 | I38: 付炳秀配送 | K38: 40 | L38: =IF($C38="","",ROUND(IFERROR(VLOOKUP($C38,账户期初,2,0),0)+SUMIFS($J$4:J38,$C$4:C38,$C38)-SUMIFS($K$4:K38,$C$4:C38,$C38),2)) | M38: =IF($C38="","",ROUND(SUM(基础资料!$B$4:$B$13)+SUM($J$4:J38)-SUM($K$4:K38),2)) | P38: =IF($B38="","",IF($F38="※类别不在基础资料里","※费用类别不在基础资料里",IF(AND(N($J38)=0,N($K38)=0),"※这行没填金额",IF(AND(N($J38)>0,N($K38)>0),"※收入和支出不能同一行都填",IF(AND($D38="收入",N($J38)=0),"※收入行要填收入金额",IF(AND($D38="支出",N($K38)=0),"※支出行要填支出金额",IF(AND($C38<>"",ISNA(MATCH($C38,账户表,0))),"※账户不在基础资料里",IF(AND($G38<>"",ISNA(MATCH($G38,项目名表,0))),"※项目不在项目台账里",IF(AND(LEFT($F38,3)="成本-",$G38=""),"※成本类支出没填项目",IF(AND(LEFT($F38,3)="成本-",$H38<>"",N($K38)>0,COUNTIFS(采购单!$B:$B,$B38,采购单!$C:$C,$H38,采购单!$L:$L,$K38)>0),"※这笔可能和采购单重复了",""))))))))))
A39: =IF($B39="","",ROW()-3) | B39: 46089 | C39: 微信1 | D39: 支出 | E39: 主材采购 | F39: =IF($E39="","",IFERROR(VLOOKUP($E39,类别归属,2,0),"※类别不在基础资料里")) | G39: 高恒荣熟食店 | H39: 周学峰 | I39: 付周学峰 | K39: 40 | L39: =IF($C39="","",ROUND(IFERROR(VLOOKUP($C39,账户期初,2,0),0)+SUMIFS($J$4:J39,$C$4:C39,$C39)-SUMIFS($K$4:K39,$C$4:C39,$C39),2)) | M39: =IF($C39="","",ROUND(SUM(基础资料!$B$4:$B$13)+SUM($J$4:J39)-SUM($K$4:K39),2)) | O39: 红色结构胶 | P39: =IF($B39="","",IF($F39="※类别不在基础资料里","※费用类别不在基础资料里",IF(AND(N($J39)=0,N($K39)=0),"※这行没填金额",IF(AND(N($J39)>0,N($K39)>0),"※收入和支出不能同一行都填",IF(AND($D39="收入",N($J39)=0),"※收入行要填收入金额",IF(AND($D39="支出",N($K39)=0),"※支出行要填支出金额",IF(AND($C39<>"",ISNA(MATCH($C39,账户表,0))),"※账户不在基础资料里",IF(AND($G39<>"",ISNA(MATCH($G39,项目名表,0))),"※项目不在项目台账里",IF(AND(LEFT($F39,3)="成本-",$G39=""),"※成本类支出没填项目",IF(AND(LEFT($F39,3)="成本-",$H39<>"",N($K39)>0,COUNTIFS(采购单!$B:$B,$B39,采购单!$C:$C,$H39,采购单!$L:$L,$K39)>0),"※这笔可能和采购单重复了",""))))))))))
A40: =IF($B40="","",ROW()-3) | B40: 46090 | C40: 微信1 | D40: 支出 | E40: 通讯费 | F40: =IF($E40="","",IFERROR(VLOOKUP($E40,类别归属,2,0),"※类别不在基础资料里")) | I40: 电话费充值 | K40: 50 | L40: =IF($C40="","",ROUND(IFERROR(VLOOKUP($C40,账户期初,2,0),0)+SUMIFS($J$4:J40,$C$4:C40,$C40)-SUMIFS($K$4:K40,$C$4:C40,$C40),2)) | M40: =IF($C40="","",ROUND(SUM(基础资料!$B$4:$B$13)+SUM($J$4:J40)-SUM($K$4:K40),2)) | O40: 杨德本次报销 1027.2 | P40: =IF($B40="","",IF($F40="※类别不在基础资料里","※费用类别不在基础资料里",IF(AND(N($J40)=0,N($K40)=0),"※这行没填金额",IF(AND(N($J40)>0,N($K40)>0),"※收入和支出不能同一行都填",IF(AND($D40="收入",N($J40)=0),"※收入行要填收入金额",IF(AND($D40="支出",N($K40)=0),"※支出行要填支出金额",IF(AND($C40<>"",ISNA(MATCH($C40,账户表,0))),"※账户不在基础资料里",IF(AND($G40<>"",ISNA(MATCH($G40,项目名表,0))),"※项目不在项目台账里",IF(AND(LEFT($F40,3)="成本-",$G40=""),"※成本类支出没填项目",IF(AND(LEFT($F40,3)="成本-",$H40<>"",N($K40)>0,COUNTIFS(采购单!$B:$B,$B40,采购单!$C:$C,$H40,采购单!$L:$L,$K40)>0),"※这笔可能和采购单重复了",""))))))))))
A41: =IF($B41="","",ROW()-3) | B41: 46090 | C41: 微信1 | D41: 支出 | E41: 运费/快递费 | F41: =IF($E41="","",IFERROR(VLOOKUP($E41,类别归属,2,0),"※类别不在基础资料里")) | G41: 校服基地 | H41: 顺丰快递费 | I41: 顺丰快递费 | K41: 28 | L41: =IF($C41="","",ROUND(IFERROR(VLOOKUP($C41,账户期初,2,0),0)+SUMIFS($J$4:J41,$C$4:C41,$C41)-SUMIFS($K$4:K41,$C$4:C41,$C41),2)) | M41: =IF($C41="","",ROUND(SUM(基础资料!$B$4:$B$13)+SUM($J$4:J41)-SUM($K$4:K41),2)) | P41: =IF($B41="","",IF($F41="※类别不在基础资料里","※费用类别不在基础资料里",IF(AND(N($J41)=0,N($K41)=0),"※这行没填金额",IF(AND(N($J41)>0,N($K41)>0),"※收入和支出不能同一行都填",IF(AND($D41="收入",N($J41)=0),"※收入行要填收入金额",IF(AND($D41="支出",N($K41)=0),"※支出行要填支出金额",IF(AND($C41<>"",ISNA(MATCH($C41,账户表,0))),"※账户不在基础资料里",IF(AND($G41<>"",ISNA(MATCH($G41,项目名表,0))),"※项目不在项目台账里",IF(AND(LEFT($F41,3)="成本-",$G41=""),"※成本类支出没填项目",IF(AND(LEFT($F41,3)="成本-",$H41<>"",N($K41)>0,COUNTIFS(采购单!$B:$B,$B41,采购单!$C:$C,$H41,采购单!$L:$L,$K41)>0),"※这笔可能和采购单重复了",""))))))))))
A42: =IF($B42="","",ROW()-3) | B42: 46090 | C42: 微信1 | D42: 支出 | E42: 其他管理费用 | F42: =IF($E42="","",IFERROR(VLOOKUP($E42,类别归属,2,0),"※类别不在基础资料里")) | G42: 南浔美食城 | I42: 2mm镀锌钢丝绳200米 | K42: 160 | L42: =IF($C42="","",ROUND(IFERROR(VLOOKUP($C42,账户期初,2,0),0)+SUMIFS($J$4:J42,$C$4:C42,$C42)-SUMIFS($K$4:K42,$C$4:C42,$C42),2)) | M42: =IF($C42="","",ROUND(SUM(基础资料!$B$4:$B$13)+SUM($J$4:J42)-SUM($K$4:K42),2)) | P42: =IF($B42="","",IF($F42="※类别不在基础资料里","※费用类别不在基础资料里",IF(AND(N($J42)=0,N($K42)=0),"※这行没填金额",IF(AND(N($J42)>0,N($K42)>0),"※收入和支出不能同一行都填",IF(AND($D42="收入",N($J42)=0),"※收入行要填收入金额",IF(AND($D42="支出",N($K42)=0),"※支出行要填支出金额",IF(AND($C42<>"",ISNA(MATCH($C42,账户表,0))),"※账户不在基础资料里",IF(AND($G42<>"",ISNA(MATCH($G42,项目名表,0))),"※项目不在项目台账里",IF(AND(LEFT($F42,3)="成本-",$G42=""),"※成本类支出没填项目",IF(AND(LEFT($F42,3)="成本-",$H42<>"",N($K42)>0,COUNTIFS(采购单!$B:$B,$B42,采购单!$C:$C,$H42,采购单!$L:$L,$K42)>0),"※这笔可能和采购单重复了",""))))))))))
A43: =IF($B43="","",ROW()-3) | B43: 46090 | C43: 微信1 | D43: 支出 | E43: 其他管理费用 | F43: =IF($E43="","",IFERROR(VLOOKUP($E43,类别归属,2,0),"※类别不在基础资料里")) | G43: 德清钟管菜市场 | I43: 结构胶1箱 | K43: 190 | L43: =IF($C43="","",ROUND(IFERROR(VLOOKUP($C43,账户期初,2,0),0)+SUMIFS($J$4:J43,$C$4:C43,$C43)-SUMIFS($K$4:K43,$C$4:C43,$C43),2)) | M43: =IF($C43="","",ROUND(SUM(基础资料!$B$4:$B$13)+SUM($J$4:J43)-SUM($K$4:K43),2)) | P43: =IF($B43="","",IF($F43="※类别不在基础资料里","※费用类别不在基础资料里",IF(AND(N($J43)=0,N($K43)=0),"※这行没填金额",IF(AND(N($J43)>0,N($K43)>0),"※收入和支出不能同一行都填",IF(AND($D43="收入",N($J43)=0),"※收入行要填收入金额",IF(AND($D43="支出",N($K43)=0),"※支出行要填支出金额",IF(AND($C43<>"",ISNA(MATCH($C43,账户表,0))),"※账户不在基础资料里",IF(AND($G43<>"",ISNA(MATCH($G43,项目名表,0))),"※项目不在项目台账里",IF(AND(LEFT($F43,3)="成本-",$G43=""),"※成本类支出没填项目",IF(AND(LEFT($F43,3)="成本-",$H43<>"",N($K43)>0,COUNTIFS(采购单!$B:$B,$B43,采购单!$C:$C,$H43,采购单!$L:$L,$K43)>0),"※这笔可能和采购单重复了",""))))))))))
A44: =IF($B44="","",ROW()-3) | B44: 46090 | C44: 微信1 | D44: 支出 | E44: 其他管理费用 | F44: =IF($E44="","",IFERROR(VLOOKUP($E44,类别归属,2,0),"※类别不在基础资料里")) | G44: 校服基地 | I44: 打车费 | K44: 17.2 | L44: =IF($C44="","",ROUND(IFERROR(VLOOKUP($C44,账户期初,2,0),0)+SUMIFS($J$4:J44,$C$4:C44,$C44)-SUMIFS($K$4:K44,$C$4:C44,$C44),2)) | M44: =IF($C44="","",ROUND(SUM(基础资料!$B$4:$B$13)+SUM($J$4:J44)-SUM($K$4:K44),2)) | P44: =IF($B44="","",IF($F44="※类别不在基础资料里","※费用类别不在基础资料里",IF(AND(N($J44)=0,N($K44)=0),"※这行没填金额",IF(AND(N($J44)>0,N($K44)>0),"※收入和支出不能同一行都填",IF(AND($D44="收入",N($J44)=0),"※收入行要填收入金额",IF(AND($D44="支出",N($K44)=0),"※支出行要填支出金额",IF(AND($C44<>"",ISNA(MATCH($C44,账户表,0))),"※账户不在基础资料里",IF(AND($G44<>"",ISNA(MATCH($G44,项目名表,0))),"※项目不在项目台账里",IF(AND(LEFT($F44,3)="成本-",$G44=""),"※成本类支出没填项目",IF(AND(LEFT($F44,3)="成本-",$H44<>"",N($K44)>0,COUNTIFS(采购单!$B:$B,$B44,采购单!$C:$C,$H44,采购单!$L:$L,$K44)>0),"※这笔可能和采购单重复了",""))))))))))
A45: =IF($B45="","",ROW()-3) | B45: 46090 | C45: 微信1 | D45: 支出 | E45: 其他管理费用 | F45: =IF($E45="","",IFERROR(VLOOKUP($E45,类别归属,2,0),"※类别不在基础资料里")) | G45: 德清钟管菜市场 | I45: 筒灯6500K120mm8只 | K45: 120 | L45: =IF($C45="","",ROUND(IFERROR(VLOOKUP($C45,账户期初,2,0),0)+SUMIFS($J$4:J45,$C$4:C45,$C45)-SUMIFS($K$4:K45,$C$4:C45,$C45),2)) | M45: =IF($C45="","",ROUND(SUM(基础资料!$B$4:$B$13)+SUM($J$4:J45)-SUM($K$4:K45),2)) | P45: =IF($B45="","",IF($F45="※类别不在基础资料里","※费用类别不在基础资料里",IF(AND(N($J45)=0,N($K45)=0),"※这行没填金额",IF(AND(N($J45)>0,N($K45)>0),"※收入和支出不能同一行都填",IF(AND($D45="收入",N($J45)=0),"※收入行要填收入金额",IF(AND($D45="支出",N($K45)=0),"※支出行要填支出金额",IF(AND($C45<>"",ISNA(MATCH($C45,账户表,0))),"※账户不在基础资料里",IF(AND($G45<>"",ISNA(MATCH($G45,项目名表,0))),"※项目不在项目台账里",IF(AND(LEFT($F45,3)="成本-",$G45=""),"※成本类支出没填项目",IF(AND(LEFT($F45,3)="成本-",$H45<>"",N($K45)>0,COUNTIFS(采购单!$B:$B,$B45,采购单!$C:$C,$H45,采购单!$L:$L,$K45)>0),"※这笔可能和采购单重复了",""))))))))))
A46: =IF($B46="","",ROW()-3) | B46: 46090 | C46: 微信1 | D46: 支出 | E46: 其他管理费用 | F46: =IF($E46="","",IFERROR(VLOOKUP($E46,类别归属,2,0),"※类别不在基础资料里")) | G46: 德清钟管菜市场 | I46: 双面胶一箱 | K46: 120 | L46: =IF($C46="","",ROUND(IFERROR(VLOOKUP($C46,账户期初,2,0),0)+SUMIFS($J$4:J46,$C$4:C46,$C46)-SUMIFS($K$4:K46,$C$4:C46,$C46),2)) | M46: =IF($C46="","",ROUND(SUM(基础资料!$B$4:$B$13)+SUM($J$4:J46)-SUM($K$4:K46),2)) | P46: =IF($B46="","",IF($F46="※类别不在基础资料里","※费用类别不在基础资料里",IF(AND(N($J46)=0,N($K46)=0),"※这行没填金额",IF(AND(N($J46)>0,N($K46)>0),"※收入和支出不能同一行都填",IF(AND($D46="收入",N($J46)=0),"※收入行要填收入金额",IF(AND($D46="支出",N($K46)=0),"※支出行要填支出金额",IF(AND($C46<>"",ISNA(MATCH($C46,账户表,0))),"※账户不在基础资料里",IF(AND($G46<>"",ISNA(MATCH($G46,项目名表,0))),"※项目不在项目台账里",IF(AND(LEFT($F46,3)="成本-",$G46=""),"※成本类支出没填项目",IF(AND(LEFT($F46,3)="成本-",$H46<>"",N($K46)>0,COUNTIFS(采购单!$B:$B,$B46,采购单!$C:$C,$H46,采购单!$L:$L,$K46)>0),"※这笔可能和采购单重复了",""))))))))))
A47: =IF($B47="","",ROW()-3) | B47: 46090 | C47: 微信1 | D47: 支出 | E47: 其他管理费用 | F47: =IF($E47="","",IFERROR(VLOOKUP($E47,类别归属,2,0),"※类别不在基础资料里")) | G47: 德清钟管菜市场 | I47: 10mm阻燃版2张 | K47: 130 | L47: =IF($C47="","",ROUND(IFERROR(VLOOKUP($C47,账户期初,2,0),0)+SUMIFS($J$4:J47,$C$4:C47,$C47)-SUMIFS($K$4:K47,$C$4:C47,$C47),2)) | M47: =IF($C47="","",ROUND(SUM(基础资料!$B$4:$B$13)+SUM($J$4:J47)-SUM($K$4:K47),2)) | P47: =IF($B47="","",IF($F47="※类别不在基础资料里","※费用类别不在基础资料里",IF(AND(N($J47)=0,N($K47)=0),"※这行没填金额",IF(AND(N($J47)>0,N($K47)>0),"※收入和支出不能同一行都填",IF(AND($D47="收入",N($J47)=0),"※收入行要填收入金额",IF(AND($D47="支出",N($K47)=0),"※支出行要填支出金额",IF(AND($C47<>"",ISNA(MATCH($C47,账户表,0))),"※账户不在基础资料里",IF(AND($G47<>"",ISNA(MATCH($G47,项目名表,0))),"※项目不在项目台账里",IF(AND(LEFT($F47,3)="成本-",$G47=""),"※成本类支出没填项目",IF(AND(LEFT($F47,3)="成本-",$H47<>"",N($K47)>0,COUNTIFS(采购单!$B:$B,$B47,采购单!$C:$C,$H47,采购单!$L:$L,$K47)>0),"※这笔可能和采购单重复了",""))))))))))
A48: =IF($B48="","",ROW()-3) | B48: 46090 | C48: 微信1 | D48: 支出 | E48: 车费/油费/过路费 | F48: =IF($E48="","",IFERROR(VLOOKUP($E48,类别归属,2,0),"※类别不在基础资料里")) | G48: 德清钟管菜市场 | I48: 高速费 | K48: 12 | L48: =IF($C48="","",ROUND(IFERROR(VLOOKUP($C48,账户期初,2,0),0)+SUMIFS($J$4:J48,$C$4:C48,$C48)-SUMIFS($K$4:K48,$C$4:C48,$C48),2)) | M48: =IF($C48="","",ROUND(SUM(基础资料!$B$4:$B$13)+SUM($J$4:J48)-SUM($K$4:K48),2)) | P48: =IF($B48="","",IF($F48="※类别不在基础资料里","※费用类别不在基础资料里",IF(AND(N($J48)=0,N($K48)=0),"※这行没填金额",IF(AND(N($J48)>0,N($K48)>0),"※收入和支出不能同一行都填",IF(AND($D48="收入",N($J48)=0),"※收入行要填收入金额",IF(AND($D48="支出",N($K48)=0),"※支出行要填支出金额",IF(AND($C48<>"",ISNA(MATCH($C48,账户表,0))),"※账户不在基础资料里",IF(AND($G48<>"",ISNA(MATCH($G48,项目名表,0))),"※项目不在项目台账里",IF(AND(LEFT($F48,3)="成本-",$G48=""),"※成本类支出没填项目",IF(AND(LEFT($F48,3)="成本-",$H48<>"",N($K48)>0,COUNTIFS(采购单!$B:$B,$B48,采购单!$C:$C,$H48,采购单!$L:$L,$K48)>0),"※这笔可能和采购单重复了",""))))))))))
A49: =IF($B49="","",ROW()-3) | B49: 46090 | C49: 微信1 | D49: 支出 | E49: 车费/油费/过路费 | F49: =IF($E49="","",IFERROR(VLOOKUP($E49,类别归属,2,0),"※类别不在基础资料里")) | I49: 312加油 | K49: 200 | L49: =IF($C49="","",ROUND(IFERROR(VLOOKUP($C49,账户期初,2,0),0)+SUMIFS($J$4:J49,$C$4:C49,$C49)-SUMIFS($K$4:K49,$C$4:C49,$C49),2)) | M49: =IF($C49="","",ROUND(SUM(基础资料!$B$4:$B$13)+SUM($J$4:J49)-SUM($K$4:K49),2)) | P49: =IF($B49="","",IF($F49="※类别不在基础资料里","※费用类别不在基础资料里",IF(AND(N($J49)=0,N($K49)=0),"※这行没填金额",IF(AND(N($J49)>0,N($K49)>0),"※收入和支出不能同一行都填",IF(AND($D49="收入",N($J49)=0),"※收入行要填收入金额",IF(AND($D49="支出",N($K49)=0),"※支出行要填支出金额",IF(AND($C49<>"",ISNA(MATCH($C49,账户表,0))),"※账户不在基础资料里",IF(AND($G49<>"",ISNA(MATCH($G49,项目名表,0))),"※项目不在项目台账里",IF(AND(LEFT($F49,3)="成本-",$G49=""),"※成本类支出没填项目",IF(AND(LEFT($F49,3)="成本-",$H49<>"",N($K49)>0,COUNTIFS(采购单!$B:$B,$B49,采购单!$C:$C,$H49,采购单!$L:$L,$K49)>0),"※这笔可能和采购单重复了",""))))))))))
A50: =IF($B50="","",ROW()-3) | B50: 46090 | C50: 微信1 | D50: 支出 | E50: 主材采购 | F50: =IF($E50="","",IFERROR(VLOOKUP($E50,类别归属,2,0),"※类别不在基础资料里")) | G50: 高恒荣熟食店 | H50: 吴玲芳 | I50: 付吴玲芳 | K50: 900 | L50: =IF($C50="","",ROUND(IFERROR(VLOOKUP($C50,账户期初,2,0),0)+SUMIFS($J$4:J50,$C$4:C50,$C50)-SUMIFS($K$4:K50,$C$4:C50,$C50),2)) | M50: =IF($C50="","",ROUND(SUM(基础资料!$B$4:$B$13)+SUM($J$4:J50)-SUM($K$4:K50),2)) | P50: =IF($B50="","",IF($F50="※类别不在基础资料里","※费用类别不在基础资料里",IF(AND(N($J50)=0,N($K50)=0),"※这行没填金额",IF(AND(N($J50)>0,N($K50)>0),"※收入和支出不能同一行都填",IF(AND($D50="收入",N($J50)=0),"※收入行要填收入金额",IF(AND($D50="支出",N($K50)=0),"※支出行要填支出金额",IF(AND($C50<>"",ISNA(MATCH($C50,账户表,0))),"※账户不在基础资料里",IF(AND($G50<>"",ISNA(MATCH($G50,项目名表,0))),"※项目不在项目台账里",IF(AND(LEFT($F50,3)="成本-",$G50=""),"※成本类支出没填项目",IF(AND(LEFT($F50,3)="成本-",$H50<>"",N($K50)>0,COUNTIFS(采购单!$B:$B,$B50,采购单!$C:$C,$H50,采购单!$L:$L,$K50)>0),"※这笔可能和采购单重复了",""))))))))))
A51: =IF($B51="","",ROW()-3) | B51: 46090 | C51: 微信1 | D51: 支出 | E51: 运费/快递费 | F51: =IF($E51="","",IFERROR(VLOOKUP($E51,类别归属,2,0),"※类别不在基础资料里")) | G51: 织里店 | H51: 炳秀 | I51: 付炳秀配送 | K51: 62 | L51: =IF($C51="","",ROUND(IFERROR(VLOOKUP($C51,账户期初,2,0),0)+SUMIFS($J$4:J51,$C$4:C51,$C51)-SUMIFS($K$4:K51,$C$4:C51,$C51),2)) | M51: =IF($C51="","",ROUND(SUM(基础资料!$B$4:$B$13)+SUM($J$4:J51)-SUM($K$4:K51),2)) | P51: =IF($B51="","",IF($F51="※类别不在基础资料里","※费用类别不在基础资料里",IF(AND(N($J51)=0,N($K51)=0),"※这行没填金额",IF(AND(N($J51)>0,N($K51)>0),"※收入和支出不能同一行都填",IF(AND($D51="收入",N($J51)=0),"※收入行要填收入金额",IF(AND($D51="支出",N($K51)=0),"※支出行要填支出金额",IF(AND($C51<>"",ISNA(MATCH($C51,账户表,0))),"※账户不在基础资料里",IF(AND($G51<>"",ISNA(MATCH($G51,项目名表,0))),"※项目不在项目台账里",IF(AND(LEFT($F51,3)="成本-",$G51=""),"※成本类支出没填项目",IF(AND(LEFT($F51,3)="成本-",$H51<>"",N($K51)>0,COUNTIFS(采购单!$B:$B,$B51,采购单!$C:$C,$H51,采购单!$L:$L,$K51)>0),"※这笔可能和采购单重复了",""))))))))))
A52: =IF($B52="","",ROW()-3) | B52: 46090 | C52: 微信1 | D52: 收入 | E52: 零星物料销售 | F52: =IF($E52="","",IFERROR(VLOOKUP($E52,类别归属,2,0),"※类别不在基础资料里")) | I52: 锅贴菜单-收阿 | J52: 30 | L52: =IF($C52="","",ROUND(IFERROR(VLOOKUP($C52,账户期初,2,0),0)+SUMIFS($J$4:J52,$C$4:C52,$C52)-SUMIFS($K$4:K52,$C$4:C52,$C52),2)) | M52: =IF($C52="","",ROUND(SUM(基础资料!$B$4:$B$13)+SUM($J$4:J52)-SUM($K$4:K52),2)) | P52: =IF($B52="","",IF($F52="※类别不在基础资料里","※费用类别不在基础资料里",IF(AND(N($J52)=0,N($K52)=0),"※这行没填金额",IF(AND(N($J52)>0,N($K52)>0),"※收入和支出不能同一行都填",IF(AND($D52="收入",N($J52)=0),"※收入行要填收入金额",IF(AND($D52="支出",N($K52)=0),"※支出行要填支出金额",IF(AND($C52<>"",ISNA(MATCH($C52,账户表,0))),"※账户不在基础资料里",IF(AND($G52<>"",ISNA(MATCH($G52,项目名表,0))),"※项目不在项目台账里",IF(AND(LEFT($F52,3)="成本-",$G52=""),"※成本类支出没填项目",IF(AND(LEFT($F52,3)="成本-",$H52<>"",N($K52)>0,COUNTIFS(采购单!$B:$B,$B52,采购单!$C:$C,$H52,采购单!$L:$L,$K52)>0),"※这笔可能和采购单重复了",""))))))))))
A53: =IF($B53="","",ROW()-3) | B53: 46082 | C53: 微信1 | D53: 支出 | E53: 主材采购 | F53: =IF($E53="","",IFERROR(VLOOKUP($E53,类别归属,2,0),"※类别不在基础资料里")) | G53: 德清津华钢铁 | H53: 津华钢铁张总 | I53: 付津华钢铁张总 | K53: 2000 | L53: =IF($C53="","",ROUND(IFERROR(VLOOKUP($C53,账户期初,2,0),0)+SUMIFS($J$4:J53,$C$4:C53,$C53)-SUMIFS($K$4:K53,$C$4:C53,$C53),2)) | M53: =IF($C53="","",ROUND(SUM(基础资料!$B$4:$B$13)+SUM($J$4:J53)-SUM($K$4:K53),2)) | P53: =IF($B53="","",IF($F53="※类别不在基础资料里","※费用类别不在基础资料里",IF(AND(N($J53)=0,N($K53)=0),"※这行没填金额",IF(AND(N($J53)>0,N($K53)>0),"※收入和支出不能同一行都填",IF(AND($D53="收入",N($J53)=0),"※收入行要填收入金额",IF(AND($D53="支出",N($K53)=0),"※支出行要填支出金额",IF(AND($C53<>"",ISNA(MATCH($C53,账户表,0))),"※账户不在基础资料里",IF(AND($G53<>"",ISNA(MATCH($G53,项目名表,0))),"※项目不在项目台账里",IF(AND(LEFT($F53,3)="成本-",$G53=""),"※成本类支出没填项目",IF(AND(LEFT($F53,3)="成本-",$H53<>"",N($K53)>0,COUNTIFS(采购单!$B:$B,$B53,采购单!$C:$C,$H53,采购单!$L:$L,$K53)>0),"※这笔可能和采购单重复了",""))))))))))
A54: =IF($B54="","",ROW()-3) | B54: 46082 | C54: 微信1 | D54: 收入 | E54: 收回借出款 | F54: =IF($E54="","",IFERROR(VLOOKUP($E54,类别归属,2,0),"※类别不在基础资料里")) | H54: 往来款 | I54: 收付久华借3000-2000还款 | J54: 2000 | L54: =IF($C54="","",ROUND(IFERROR(VLOOKUP($C54,账户期初,2,0),0)+SUMIFS($J$4:J54,$C$4:C54,$C54)-SUMIFS($K$4:K54,$C$4:C54,$C54),2)) | M54: =IF($C54="","",ROUND(SUM(基础资料!$B$4:$B$13)+SUM($J$4:J54)-SUM($K$4:K54),2)) | P54: =IF($B54="","",IF($F54="※类别不在基础资料里","※费用类别不在基础资料里",IF(AND(N($J54)=0,N($K54)=0),"※这行没填金额",IF(AND(N($J54)>0,N($K54)>0),"※收入和支出不能同一行都填",IF(AND($D54="收入",N($J54)=0),"※收入行要填收入金额",IF(AND($D54="支出",N($K54)=0),"※支出行要填支出金额",IF(AND($C54<>"",ISNA(MATCH($C54,账户表,0))),"※账户不在基础资料里",IF(AND($G54<>"",ISNA(MATCH($G54,项目名表,0))),"※项目不在项目台账里",IF(AND(LEFT($F54,3)="成本-",$G54=""),"※成本类支出没填项目",IF(AND(LEFT($F54,3)="成本-",$H54<>"",N($K54)>0,COUNTIFS(采购单!$B:$B,$B54,采购单!$C:$C,$H54,采购单!$L:$L,$K54)>0),"※这笔可能和采购单重复了",""))))))))))
A55: =IF($B55="","",ROW()-3) | B55: 46082 | C55: 微信1 | D55: 支出 | E55: 运费/快递费 | F55: =IF($E55="","",IFERROR(VLOOKUP($E55,类别归属,2,0),"※类别不在基础资料里")) | G55: 织里店 | H55: 炳秀 | I55: 付炳秀配送 | K55: 94 | L55: =IF($C55="","",ROUND(IFERROR(VLOOKUP($C55,账户期初,2,0),0)+SUMIFS($J$4:J55,$C$4:C55,$C55)-SUMIFS($K$4:K55,$C$4:C55,$C55),2)) | M55: =IF($C55="","",ROUND(SUM(基础资料!$B$4:$B$13)+SUM($J$4:J55)-SUM($K$4:K55),2)) | P55: =IF($B55="","",IF($F55="※类别不在基础资料里","※费用类别不在基础资料里",IF(AND(N($J55)=0,N($K55)=0),"※这行没填金额",IF(AND(N($J55)>0,N($K55)>0),"※收入和支出不能同一行都填",IF(AND($D55="收入",N($J55)=0),"※收入行要填收入金额",IF(AND($D55="支出",N($K55)=0),"※支出行要填支出金额",IF(AND($C55<>"",ISNA(MATCH($C55,账户表,0))),"※账户不在基础资料里",IF(AND($G55<>"",ISNA(MATCH($G55,项目名表,0))),"※项目不在项目台账里",IF(AND(LEFT($F55,3)="成本-",$G55=""),"※成本类支出没填项目",IF(AND(LEFT($F55,3)="成本-",$H55<>"",N($K55)>0,COUNTIFS(采购单!$B:$B,$B55,采购单!$C:$C,$H55,采购单!$L:$L,$K55)>0),"※这笔可能和采购单重复了",""))))))))))
A56: =IF($B56="","",ROW()-3) | B56: 46082 | C56: 微信1 | D56: 支出 | E56: 运费/快递费 | F56: =IF($E56="","",IFERROR(VLOOKUP($E56,类别归属,2,0),"※类别不在基础资料里")) | G56: 犇腾牛排 | H56: 炳秀 | I56: 付炳秀配送 | K56: 5 | L56: =IF($C56="","",ROUND(IFERROR(VLOOKUP($C56,账户期初,2,0),0)+SUMIFS($J$4:J56,$C$4:C56,$C56)-SUMIFS($K$4:K56,$C$4:C56,$C56),2)) | M56: =IF($C56="","",ROUND(SUM(基础资料!$B$4:$B$13)+SUM($J$4:J56)-SUM($K$4:K56),2)) | P56: =IF($B56="","",IF($F56="※类别不在基础资料里","※费用类别不在基础资料里",IF(AND(N($J56)=0,N($K56)=0),"※这行没填金额",IF(AND(N($J56)>0,N($K56)>0),"※收入和支出不能同一行都填",IF(AND($D56="收入",N($J56)=0),"※收入行要填收入金额",IF(AND($D56="支出",N($K56)=0),"※支出行要填支出金额",IF(AND($C56<>"",ISNA(MATCH($C56,账户表,0))),"※账户不在基础资料里",IF(AND($G56<>"",ISNA(MATCH($G56,项目名表,0))),"※项目不在项目台账里",IF(AND(LEFT($F56,3)="成本-",$G56=""),"※成本类支出没填项目",IF(AND(LEFT($F56,3)="成本-",$H56<>"",N($K56)>0,COUNTIFS(采购单!$B:$B,$B56,采购单!$C:$C,$H56,采购单!$L:$L,$K56)>0),"※这笔可能和采购单重复了",""))))))))))
A57: =IF($B57="","",ROW()-3) | B57: 46082 | C57: 微信1 | D57: 支出 | E57: 运费/快递费 | F57: =IF($E57="","",IFERROR(VLOOKUP($E57,类别归属,2,0),"※类别不在基础资料里")) | G57: 犇腾牛排 | H57: 炳秀 | I57: 付炳秀配送 | K57: 23 | L57: =IF($C57="","",ROUND(IFERROR(VLOOKUP($C57,账户期初,2,0),0)+SUMIFS($J$4:J57,$C$4:C57,$C57)-SUMIFS($K$4:K57,$C$4:C57,$C57),2)) | M57: =IF($C57="","",ROUND(SUM(基础资料!$B$4:$B$13)+SUM($J$4:J57)-SUM($K$4:K57),2)) | P57: =IF($B57="","",IF($F57="※类别不在基础资料里","※费用类别不在基础资料里",IF(AND(N($J57)=0,N($K57)=0),"※这行没填金额",IF(AND(N($J57)>0,N($K57)>0),"※收入和支出不能同一行都填",IF(AND($D57="收入",N($J57)=0),"※收入行要填收入金额",IF(AND($D57="支出",N($K57)=0),"※支出行要填支出金额",IF(AND($C57<>"",ISNA(MATCH($C57,账户表,0))),"※账户不在基础资料里",IF(AND($G57<>"",ISNA(MATCH($G57,项目名表,0))),"※项目不在项目台账里",IF(AND(LEFT($F57,3)="成本-",$G57=""),"※成本类支出没填项目",IF(AND(LEFT($F57,3)="成本-",$H57<>"",N($K57)>0,COUNTIFS(采购单!$B:$B,$B57,采购单!$C:$C,$H57,采购单!$L:$L,$K57)>0),"※这笔可能和采购单重复了",""))))))))))
A58: =IF($B58="","",ROW()-3) | B58: 46082 | C58: 微信1 | D58: 支出 | E58: 主材采购 | F58: =IF($E58="","",IFERROR(VLOOKUP($E58,类别归属,2,0),"※类别不在基础资料里")) | G58: 高恒荣熟食店 | I58: 付杨老头电焊-钟管门头彩钢瓦雨棚 | K58: 270 | L58: =IF($C58="","",ROUND(IFERROR(VLOOKUP($C58,账户期初,2,0),0)+SUMIFS($J$4:J58,$C$4:C58,$C58)-SUMIFS($K$4:K58,$C$4:C58,$C58),2)) | M58: =IF($C58="","",ROUND(SUM(基础资料!$B$4:$B$13)+SUM($J$4:J58)-SUM($K$4:K58),2)) | P58: =IF($B58="","",IF($F58="※类别不在基础资料里","※费用类别不在基础资料里",IF(AND(N($J58)=0,N($K58)=0),"※这行没填金额",IF(AND(N($J58)>0,N($K58)>0),"※收入和支出不能同一行都填",IF(AND($D58="收入",N($J58)=0),"※收入行要填收入金额",IF(AND($D58="支出",N($K58)=0),"※支出行要填支出金额",IF(AND($C58<>"",ISNA(MATCH($C58,账户表,0))),"※账户不在基础资料里",IF(AND($G58<>"",ISNA(MATCH($G58,项目名表,0))),"※项目不在项目台账里",IF(AND(LEFT($F58,3)="成本-",$G58=""),"※成本类支出没填项目",IF(AND(LEFT($F58,3)="成本-",$H58<>"",N($K58)>0,COUNTIFS(采购单!$B:$B,$B58,采购单!$C:$C,$H58,采购单!$L:$L,$K58)>0),"※这笔可能和采购单重复了",""))))))))))
A59: =IF($B59="","",ROW()-3) | B59: 46092 | C59: 微信1 | D59: 支出 | E59: 主材采购 | F59: =IF($E59="","",IFERROR(VLOOKUP($E59,类别归属,2,0),"※类别不在基础资料里")) | G59: 东尼电子 | I59: 付杨采购东尼LED屏反场运费200元 | K59: 200 | L59: =IF($C59="","",ROUND(IFERROR(VLOOKUP($C59,账户期初,2,0),0)+SUMIFS($J$4:J59,$C$4:C59,$C59)-SUMIFS($K$4:K59,$C$4:C59,$C59),2)) | M59: =IF($C59="","",ROUND(SUM(基础资料!$B$4:$B$13)+SUM($J$4:J59)-SUM($K$4:K59),2)) | P59: =IF($B59="","",IF($F59="※类别不在基础资料里","※费用类别不在基础资料里",IF(AND(N($J59)=0,N($K59)=0),"※这行没填金额",IF(AND(N($J59)>0,N($K59)>0),"※收入和支出不能同一行都填",IF(AND($D59="收入",N($J59)=0),"※收入行要填收入金额",IF(AND($D59="支出",N($K59)=0),"※支出行要填支出金额",IF(AND($C59<>"",ISNA(MATCH($C59,账户表,0))),"※账户不在基础资料里",IF(AND($G59<>"",ISNA(MATCH($G59,项目名表,0))),"※项目不在项目台账里",IF(AND(LEFT($F59,3)="成本-",$G59=""),"※成本类支出没填项目",IF(AND(LEFT($F59,3)="成本-",$H59<>"",N($K59)>0,COUNTIFS(采购单!$B:$B,$B59,采购单!$C:$C,$H59,采购单!$L:$L,$K59)>0),"※这笔可能和采购单重复了",""))))))))))
A60: =IF($B60="","",ROW()-3) | B60: 46092 | C60: 微信1 | D60: 支出 | E60: 运费/快递费 | F60: =IF($E60="","",IFERROR(VLOOKUP($E60,类别归属,2,0),"※类别不在基础资料里")) | G60: 织里店 | H60: 炳秀 | I60: 付炳秀配送 | K60: 137 | L60: =IF($C60="","",ROUND(IFERROR(VLOOKUP($C60,账户期初,2,0),0)+SUMIFS($J$4:J60,$C$4:C60,$C60)-SUMIFS($K$4:K60,$C$4:C60,$C60),2)) | M60: =IF($C60="","",ROUND(SUM(基础资料!$B$4:$B$13)+SUM($J$4:J60)-SUM($K$4:K60),2)) | P60: =IF($B60="","",IF($F60="※类别不在基础资料里","※费用类别不在基础资料里",IF(AND(N($J60)=0,N($K60)=0),"※这行没填金额",IF(AND(N($J60)>0,N($K60)>0),"※收入和支出不能同一行都填",IF(AND($D60="收入",N($J60)=0),"※收入行要填收入金额",IF(AND($D60="支出",N($K60)=0),"※支出行要填支出金额",IF(AND($C60<>"",ISNA(MATCH($C60,账户表,0))),"※账户不在基础资料里",IF(AND($G60<>"",ISNA(MATCH($G60,项目名表,0))),"※项目不在项目台账里",IF(AND(LEFT($F60,3)="成本-",$G60=""),"※成本类支出没填项目",IF(AND(LEFT($F60,3)="成本-",$H60<>"",N($K60)>0,COUNTIFS(采购单!$B:$B,$B60,采购单!$C:$C,$H60,采购单!$L:$L,$K60)>0),"※这笔可能和采购单重复了",""))))))))))
A61: =IF($B61="","",ROW()-3) | B61: 46092 | C61: 微信1 | D61: 支出 | E61: 运费/快递费 | F61: =IF($E61="","",IFERROR(VLOOKUP($E61,类别归属,2,0),"※类别不在基础资料里")) | G61: 中交 | H61: 炳秀 | I61: 付炳秀配送 | K61: 6 | L61: =IF($C61="","",ROUND(IFERROR(VLOOKUP($C61,账户期初,2,0),0)+SUMIFS($J$4:J61,$C$4:C61,$C61)-SUMIFS($K$4:K61,$C$4:C61,$C61),2)) | M61: =IF($C61="","",ROUND(SUM(基础资料!$B$4:$B$13)+SUM($J$4:J61)-SUM($K$4:K61),2)) | P61: =IF($B61="","",IF($F61="※类别不在基础资料里","※费用类别不在基础资料里",IF(AND(N($J61)=0,N($K61)=0),"※这行没填金额",IF(AND(N($J61)>0,N($K61)>0),"※收入和支出不能同一行都填",IF(AND($D61="收入",N($J61)=0),"※收入行要填收入金额",IF(AND($D61="支出",N($K61)=0),"※支出行要填支出金额",IF(AND($C61<>"",ISNA(MATCH($C61,账户表,0))),"※账户不在基础资料里",IF(AND($G61<>"",ISNA(MATCH($G61,项目名表,0))),"※项目不在项目台账里",IF(AND(LEFT($F61,3)="成本-",$G61=""),"※成本类支出没填项目",IF(AND(LEFT($F61,3)="成本-",$H61<>"",N($K61)>0,COUNTIFS(采购单!$B:$B,$B61,采购单!$C:$C,$H61,采购单!$L:$L,$K61)>0),"※这笔可能和采购单重复了",""))))))))))
A62: =IF($B62="","",ROW()-3) | B62: 46092 | C62: 微信1 | D62: 收入 | E62: 项目收款 | F62: =IF($E62="","",IFERROR(VLOOKUP($E62,类别归属,2,0),"※类别不在基础资料里")) | G62: 双林面馆-滨河路 | I62: 双林面馆定金-钱多多 | J62: 1000 | L62: =IF($C62="","",ROUND(IFERROR(VLOOKUP($C62,账户期初,2,0),0)+SUMIFS($J$4:J62,$C$4:C62,$C62)-SUMIFS($K$4:K62,$C$4:C62,$C62),2)) | M62: =IF($C62="","",ROUND(SUM(基础资料!$B$4:$B$13)+SUM($J$4:J62)-SUM($K$4:K62),2)) | P62: =IF($B62="","",IF($F62="※类别不在基础资料里","※费用类别不在基础资料里",IF(AND(N($J62)=0,N($K62)=0),"※这行没填金额",IF(AND(N($J62)>0,N($K62)>0),"※收入和支出不能同一行都填",IF(AND($D62="收入",N($J62)=0),"※收入行要填收入金额",IF(AND($D62="支出",N($K62)=0),"※支出行要填支出金额",IF(AND($C62<>"",ISNA(MATCH($C62,账户表,0))),"※账户不在基础资料里",IF(AND($G62<>"",ISNA(MATCH($G62,项目名表,0))),"※项目不在项目台账里",IF(AND(LEFT($F62,3)="成本-",$G62=""),"※成本类支出没填项目",IF(AND(LEFT($F62,3)="成本-",$H62<>"",N($K62)>0,COUNTIFS(采购单!$B:$B,$B62,采购单!$C:$C,$H62,采购单!$L:$L,$K62)>0),"※这笔可能和采购单重复了",""))))))))))
A63: =IF($B63="","",ROW()-3) | B63: 46092 | C63: 微信1 | D63: 支出 | E63: 主材采购 | F63: =IF($E63="","",IFERROR(VLOOKUP($E63,类别归属,2,0),"※类别不在基础资料里")) | I63: 外叫零时工南浔古镇450+450+450+津华钢铁450 | K63: 1900 | L63: =IF($C63="","",ROUND(IFERROR(VLOOKUP($C63,账户期初,2,0),0)+SUMIFS($J$4:J63,$C$4:C63,$C63)-SUMIFS($K$4:K63,$C$4:C63,$C63),2)) | M63: =IF($C63="","",ROUND(SUM(基础资料!$B$4:$B$13)+SUM($J$4:J63)-SUM($K$4:K63),2)) | P63: =IF($B63="","",IF($F63="※类别不在基础资料里","※费用类别不在基础资料里",IF(AND(N($J63)=0,N($K63)=0),"※这行没填金额",IF(AND(N($J63)>0,N($K63)>0),"※收入和支出不能同一行都填",IF(AND($D63="收入",N($J63)=0),"※收入行要填收入金额",IF(AND($D63="支出",N($K63)=0),"※支出行要填支出金额",IF(AND($C63<>"",ISNA(MATCH($C63,账户表,0))),"※账户不在基础资料里",IF(AND($G63<>"",ISNA(MATCH($G63,项目名表,0))),"※项目不在项目台账里",IF(AND(LEFT($F63,3)="成本-",$G63=""),"※成本类支出没填项目",IF(AND(LEFT($F63,3)="成本-",$H63<>"",N($K63)>0,COUNTIFS(采购单!$B:$B,$B63,采购单!$C:$C,$H63,采购单!$L:$L,$K63)>0),"※这笔可能和采购单重复了",""))))))))))
A64: =IF($B64="","",ROW()-3) | B64: 46093 | C64: 微信1 | D64: 支出 | E64: 运费/快递费 | F64: =IF($E64="","",IFERROR(VLOOKUP($E64,类别归属,2,0),"※类别不在基础资料里")) | G64: 织里店 | H64: 炳秀 | I64: 付炳秀配送 | K64: 545 | L64: =IF($C64="","",ROUND(IFERROR(VLOOKUP($C64,账户期初,2,0),0)+SUMIFS($J$4:J64,$C$4:C64,$C64)-SUMIFS($K$4:K64,$C$4:C64,$C64),2)) | M64: =IF($C64="","",ROUND(SUM(基础资料!$B$4:$B$13)+SUM($J$4:J64)-SUM($K$4:K64),2)) | O64: 668 | P64: =IF($B64="","",IF($F64="※类别不在基础资料里","※费用类别不在基础资料里",IF(AND(N($J64)=0,N($K64)=0),"※这行没填金额",IF(AND(N($J64)>0,N($K64)>0),"※收入和支出不能同一行都填",IF(AND($D64="收入",N($J64)=0),"※收入行要填收入金额",IF(AND($D64="支出",N($K64)=0),"※支出行要填支出金额",IF(AND($C64<>"",ISNA(MATCH($C64,账户表,0))),"※账户不在基础资料里",IF(AND($G64<>"",ISNA(MATCH($G64,项目名表,0))),"※项目不在项目台账里",IF(AND(LEFT($F64,3)="成本-",$G64=""),"※成本类支出没填项目",IF(AND(LEFT($F64,3)="成本-",$H64<>"",N($K64)>0,COUNTIFS(采购单!$B:$B,$B64,采购单!$C:$C,$H64,采购单!$L:$L,$K64)>0),"※这笔可能和采购单重复了",""))))))))))
A65: =IF($B65="","",ROW()-3) | B65: 46093 | C65: 微信1 | D65: 支出 | E65: 运费/快递费 | F65: =IF($E65="","",IFERROR(VLOOKUP($E65,类别归属,2,0),"※类别不在基础资料里")) | G65: vip宠物乐园 | H65: 炳秀 | I65: 付炳秀配送 | K65: 8 | L65: =IF($C65="","",ROUND(IFERROR(VLOOKUP($C65,账户期初,2,0),0)+SUMIFS($J$4:J65,$C$4:C65,$C65)-SUMIFS($K$4:K65,$C$4:C65,$C65),2)) | M65: =IF($C65="","",ROUND(SUM(基础资料!$B$4:$B$13)+SUM($J$4:J65)-SUM($K$4:K65),2)) | P65: =IF($B65="","",IF($F65="※类别不在基础资料里","※费用类别不在基础资料里",IF(AND(N($J65)=0,N($K65)=0),"※这行没填金额",IF(AND(N($J65)>0,N($K65)>0),"※收入和支出不能同一行都填",IF(AND($D65="收入",N($J65)=0),"※收入行要填收入金额",IF(AND($D65="支出",N($K65)=0),"※支出行要填支出金额",IF(AND($C65<>"",ISNA(MATCH($C65,账户表,0))),"※账户不在基础资料里",IF(AND($G65<>"",ISNA(MATCH($G65,项目名表,0))),"※项目不在项目台账里",IF(AND(LEFT($F65,3)="成本-",$G65=""),"※成本类支出没填项目",IF(AND(LEFT($F65,3)="成本-",$H65<>"",N($K65)>0,COUNTIFS(采购单!$B:$B,$B65,采购单!$C:$C,$H65,采购单!$L:$L,$K65)>0),"※这笔可能和采购单重复了",""))))))))))
A66: =IF($B66="","",ROW()-3) | B66: 46093 | C66: 微信1 | D66: 支出 | E66: 运费/快递费 | F66: =IF($E66="","",IFERROR(VLOOKUP($E66,类别归属,2,0),"※类别不在基础资料里")) | G66: 双林面馆-滨河路 | H66: 炳秀 | I66: 付炳秀配送 | K66: 115 | L66: =IF($C66="","",ROUND(IFERROR(VLOOKUP($C66,账户期初,2,0),0)+SUMIFS($J$4:J66,$C$4:C66,$C66)-SUMIFS($K$4:K66,$C$4:C66,$C66),2)) | M66: =IF($C66="","",ROUND(SUM(基础资料!$B$4:$B$13)+SUM($J$4:J66)-SUM($K$4:K66),2)) | P66: =IF($B66="","",IF($F66="※类别不在基础资料里","※费用类别不在基础资料里",IF(AND(N($J66)=0,N($K66)=0),"※这行没填金额",IF(AND(N($J66)>0,N($K66)>0),"※收入和支出不能同一行都填",IF(AND($D66="收入",N($J66)=0),"※收入行要填收入金额",IF(AND($D66="支出",N($K66)=0),"※支出行要填支出金额",IF(AND($C66<>"",ISNA(MATCH($C66,账户表,0))),"※账户不在基础资料里",IF(AND($G66<>"",ISNA(MATCH($G66,项目名表,0))),"※项目不在项目台账里",IF(AND(LEFT($F66,3)="成本-",$G66=""),"※成本类支出没填项目",IF(AND(LEFT($F66,3)="成本-",$H66<>"",N($K66)>0,COUNTIFS(采购单!$B:$B,$B66,采购单!$C:$C,$H66,采购单!$L:$L,$K66)>0),"※这笔可能和采购单重复了",""))))))))))
A67: =IF($B67="","",ROW()-3) | B67: 46093 | C67: 微信1 | D67: 支出 | E67: 借出款 | F67: =IF($E67="","",IFERROR(VLOOKUP($E67,类别归属,2,0),"※类别不在基础资料里")) | H67: 章凡 | I67: 付章凡预支工资 | K67: 1000 | L67: =IF($C67="","",ROUND(IFERROR(VLOOKUP($C67,账户期初,2,0),0)+SUMIFS($J$4:J67,$C$4:C67,$C67)-SUMIFS($K$4:K67,$C$4:C67,$C67),2)) | M67: =IF($C67="","",ROUND(SUM(基础资料!$B$4:$B$13)+SUM($J$4:J67)-SUM($K$4:K67),2)) | P67: =IF($B67="","",IF($F67="※类别不在基础资料里","※费用类别不在基础资料里",IF(AND(N($J67)=0,N($K67)=0),"※这行没填金额",IF(AND(N($J67)>0,N($K67)>0),"※收入和支出不能同一行都填",IF(AND($D67="收入",N($J67)=0),"※收入行要填收入金额",IF(AND($D67="支出",N($K67)=0),"※支出行要填支出金额",IF(AND($C67<>"",ISNA(MATCH($C67,账户表,0))),"※账户不在基础资料里",IF(AND($G67<>"",ISNA(MATCH($G67,项目名表,0))),"※项目不在项目台账里",IF(AND(LEFT($F67,3)="成本-",$G67=""),"※成本类支出没填项目",IF(AND(LEFT($F67,3)="成本-",$H67<>"",N($K67)>0,COUNTIFS(采购单!$B:$B,$B67,采购单!$C:$C,$H67,采购单!$L:$L,$K67)>0),"※这笔可能和采购单重复了",""))))))))))
A68: =IF($B68="","",ROW()-3) | B68: 46094 | C68: 微信1 | D68: 支出 | E68: 主材采购 | F68: =IF($E68="","",IFERROR(VLOOKUP($E68,类别归属,2,0),"※类别不在基础资料里")) | H68: 220V不防水区块65 | I68: 220V不防水区块65（补LED屏星蓝光电） | K68: 187 | L68: =IF($C68="","",ROUND(IFERROR(VLOOKUP($C68,账户期初,2,0),0)+SUMIFS($J$4:J68,$C$4:C68,$C68)-SUMIFS($K$4:K68,$C$4:C68,$C68),2)) | M68: =IF($C68="","",ROUND(SUM(基础资料!$B$4:$B$13)+SUM($J$4:J68)-SUM($K$4:K68),2)) | O68: 750片*0.75，，-500*0.75 | P68: =IF($B68="","",IF($F68="※类别不在基础资料里","※费用类别不在基础资料里",IF(AND(N($J68)=0,N($K68)=0),"※这行没填金额",IF(AND(N($J68)>0,N($K68)>0),"※收入和支出不能同一行都填",IF(AND($D68="收入",N($J68)=0),"※收入行要填收入金额",IF(AND($D68="支出",N($K68)=0),"※支出行要填支出金额",IF(AND($C68<>"",ISNA(MATCH($C68,账户表,0))),"※账户不在基础资料里",IF(AND($G68<>"",ISNA(MATCH($G68,项目名表,0))),"※项目不在项目台账里",IF(AND(LEFT($F68,3)="成本-",$G68=""),"※成本类支出没填项目",IF(AND(LEFT($F68,3)="成本-",$H68<>"",N($K68)>0,COUNTIFS(采购单!$B:$B,$B68,采购单!$C:$C,$H68,采购单!$L:$L,$K68)>0),"※这笔可能和采购单重复了",""))))))))))
A69: =IF($B69="","",ROW()-3) | B69: 46094 | C69: 微信1 | D69: 支出 | E69: 其他直接费用 | F69: =IF($E69="","",IFERROR(VLOOKUP($E69,类别归属,2,0),"※类别不在基础资料里")) | G69: 高恒荣熟食店 | I69: 杨买玻璃胶嘴 | K69: 1 | L69: =IF($C69="","",ROUND(IFERROR(VLOOKUP($C69,账户期初,2,0),0)+SUMIFS($J$4:J69,$C$4:C69,$C69)-SUMIFS($K$4:K69,$C$4:C69,$C69),2)) | M69: =IF($C69="","",ROUND(SUM(基础资料!$B$4:$B$13)+SUM($J$4:J69)-SUM($K$4:K69),2)) | P69: =IF($B69="","",IF($F69="※类别不在基础资料里","※费用类别不在基础资料里",IF(AND(N($J69)=0,N($K69)=0),"※这行没填金额",IF(AND(N($J69)>0,N($K69)>0),"※收入和支出不能同一行都填",IF(AND($D69="收入",N($J69)=0),"※收入行要填收入金额",IF(AND($D69="支出",N($K69)=0),"※支出行要填支出金额",IF(AND($C69<>"",ISNA(MATCH($C69,账户表,0))),"※账户不在基础资料里",IF(AND($G69<>"",ISNA(MATCH($G69,项目名表,0))),"※项目不在项目台账里",IF(AND(LEFT($F69,3)="成本-",$G69=""),"※成本类支出没填项目",IF(AND(LEFT($F69,3)="成本-",$H69<>"",N($K69)>0,COUNTIFS(采购单!$B:$B,$B69,采购单!$C:$C,$H69,采购单!$L:$L,$K69)>0),"※这笔可能和采购单重复了",""))))))))))
A70: =IF($B70="","",ROW()-3) | B70: 46095 | C70: 微信1 | D70: 收入 | E70: 项目收款 | F70: =IF($E70="","",IFERROR(VLOOKUP($E70,类别归属,2,0),"※类别不在基础资料里")) | G70: 高恒荣熟食店 | I70: 收尾款-木森装饰公司-波 | J70: 10000 | L70: =IF($C70="","",ROUND(IFERROR(VLOOKUP($C70,账户期初,2,0),0)+SUMIFS($J$4:J70,$C$4:C70,$C70)-SUMIFS($K$4:K70,$C$4:C70,$C70),2)) | M70: =IF($C70="","",ROUND(SUM(基础资料!$B$4:$B$13)+SUM($J$4:J70)-SUM($K$4:K70),2)) | P70: =IF($B70="","",IF($F70="※类别不在基础资料里","※费用类别不在基础资料里",IF(AND(N($J70)=0,N($K70)=0),"※这行没填金额",IF(AND(N($J70)>0,N($K70)>0),"※收入和支出不能同一行都填",IF(AND($D70="收入",N($J70)=0),"※收入行要填收入金额",IF(AND($D70="支出",N($K70)=0),"※支出行要填支出金额",IF(AND($C70<>"",ISNA(MATCH($C70,账户表,0))),"※账户不在基础资料里",IF(AND($G70<>"",ISNA(MATCH($G70,项目名表,0))),"※项目不在项目台账里",IF(AND(LEFT($F70,3)="成本-",$G70=""),"※成本类支出没填项目",IF(AND(LEFT($F70,3)="成本-",$H70<>"",N($K70)>0,COUNTIFS(采购单!$B:$B,$B70,采购单!$C:$C,$H70,采购单!$L:$L,$K70)>0),"※这笔可能和采购单重复了",""))))))))))
A71: =IF($B71="","",ROW()-3) | B71: 46095 | C71: 微信1 | D71: 支出 | E71: 车费/油费/过路费 | F71: =IF($E71="","",IFERROR(VLOOKUP($E71,类别归属,2,0),"※类别不在基础资料里")) | G71: 安吉车贴项目 | I71: 高速费 | K71: 33 | L71: =IF($C71="","",ROUND(IFERROR(VLOOKUP($C71,账户期初,2,0),0)+SUMIFS($J$4:J71,$C$4:C71,$C71)-SUMIFS($K$4:K71,$C$4:C71,$C71),2)) | M71: =IF($C71="","",ROUND(SUM(基础资料!$B$4:$B$13)+SUM($J$4:J71)-SUM($K$4:K71),2)) | O71: 杨德 本次报销 345.4 | P71: =IF($B71="","",IF($F71="※类别不在基础资料里","※费用类别不在基础资料里",IF(AND(N($J71)=0,N($K71)=0),"※这行没填金额",IF(AND(N($J71)>0,N($K71)>0),"※收入和支出不能同一行都填",IF(AND($D71="收入",N($J71)=0),"※收入行要填收入金额",IF(AND($D71="支出",N($K71)=0),"※支出行要填支出金额",IF(AND($C71<>"",ISNA(MATCH($C71,账户表,0))),"※账户不在基础资料里",IF(AND($G71<>"",ISNA(MATCH($G71,项目名表,0))),"※项目不在项目台账里",IF(AND(LEFT($F71,3)="成本-",$G71=""),"※成本类支出没填项目",IF(AND(LEFT($F71,3)="成本-",$H71<>"",N($K71)>0,COUNTIFS(采购单!$B:$B,$B71,采购单!$C:$C,$H71,采购单!$L:$L,$K71)>0),"※这笔可能和采购单重复了",""))))))))))
A72: =IF($B72="","",ROW()-3) | B72: 46095 | C72: 微信1 | D72: 支出 | E72: 车费/油费/过路费 | F72: =IF($E72="","",IFERROR(VLOOKUP($E72,类别归属,2,0),"※类别不在基础资料里")) | G72: 安吉车贴项目 | I72: 312加油 | K72: 200 | L72: =IF($C72="","",ROUND(IFERROR(VLOOKUP($C72,账户期初,2,0),0)+SUMIFS($J$4:J72,$C$4:C72,$C72)-SUMIFS($K$4:K72,$C$4:C72,$C72),2)) | M72: =IF($C72="","",ROUND(SUM(基础资料!$B$4:$B$13)+SUM($J$4:J72)-SUM($K$4:K72),2)) | P72: =IF($B72="","",IF($F72="※类别不在基础资料里","※费用类别不在基础资料里",IF(AND(N($J72)=0,N($K72)=0),"※这行没填金额",IF(AND(N($J72)>0,N($K72)>0),"※收入和支出不能同一行都填",IF(AND($D72="收入",N($J72)=0),"※收入行要填收入金额",IF(AND($D72="支出",N($K72)=0),"※支出行要填支出金额",IF(AND($C72<>"",ISNA(MATCH($C72,账户表,0))),"※账户不在基础资料里",IF(AND($G72<>"",ISNA(MATCH($G72,项目名表,0))),"※项目不在项目台账里",IF(AND(LEFT($F72,3)="成本-",$G72=""),"※成本类支出没填项目",IF(AND(LEFT($F72,3)="成本-",$H72<>"",N($K72)>0,COUNTIFS(采购单!$B:$B,$B72,采购单!$C:$C,$H72,采购单!$L:$L,$K72)>0),"※这笔可能和采购单重复了",""))))))))))
A73: =IF($B73="","",ROW()-3) | B73: 46095 | C73: 微信1 | D73: 支出 | E73: 车费/油费/过路费 | F73: =IF($E73="","",IFERROR(VLOOKUP($E73,类别归属,2,0),"※类别不在基础资料里")) | G73: 安吉车贴项目 | I73: 高速费 | K73: 32 | L73: =IF($C73="","",ROUND(IFERROR(VLOOKUP($C73,账户期初,2,0),0)+SUMIFS($J$4:J73,$C$4:C73,$C73)-SUMIFS($K$4:K73,$C$4:C73,$C73),2)) | M73: =IF($C73="","",ROUND(SUM(基础资料!$B$4:$B$13)+SUM($J$4:J73)-SUM($K$4:K73),2)) | P73: =IF($B73="","",IF($F73="※类别不在基础资料里","※费用类别不在基础资料里",IF(AND(N($J73)=0,N($K73)=0),"※这行没填金额",IF(AND(N($J73)>0,N($K73)>0),"※收入和支出不能同一行都填",IF(AND($D73="收入",N($J73)=0),"※收入行要填收入金额",IF(AND($D73="支出",N($K73)=0),"※支出行要填支出金额",IF(AND($C73<>"",ISNA(MATCH($C73,账户表,0))),"※账户不在基础资料里",IF(AND($G73<>"",ISNA(MATCH($G73,项目名表,0))),"※项目不在项目台账里",IF(AND(LEFT($F73,3)="成本-",$G73=""),"※成本类支出没填项目",IF(AND(LEFT($F73,3)="成本-",$H73<>"",N($K73)>0,COUNTIFS(采购单!$B:$B,$B73,采购单!$C:$C,$H73,采购单!$L:$L,$K73)>0),"※这笔可能和采购单重复了",""))))))))))
A74: =IF($B74="","",ROW()-3) | B74: 46095 | C74: 微信1 | D74: 支出 | E74: 其他管理费用 | F74: =IF($E74="","",IFERROR(VLOOKUP($E74,类别归属,2,0),"※类别不在基础资料里")) | I74: 7.5米卷尺2把 | K74: 18.8 | L74: =IF($C74="","",ROUND(IFERROR(VLOOKUP($C74,账户期初,2,0),0)+SUMIFS($J$4:J74,$C$4:C74,$C74)-SUMIFS($K$4:K74,$C$4:C74,$C74),2)) | M74: =IF($C74="","",ROUND(SUM(基础资料!$B$4:$B$13)+SUM($J$4:J74)-SUM($K$4:K74),2)) | P74: =IF($B74="","",IF($F74="※类别不在基础资料里","※费用类别不在基础资料里",IF(AND(N($J74)=0,N($K74)=0),"※这行没填金额",IF(AND(N($J74)>0,N($K74)>0),"※收入和支出不能同一行都填",IF(AND($D74="收入",N($J74)=0),"※收入行要填收入金额",IF(AND($D74="支出",N($K74)=0),"※支出行要填支出金额",IF(AND($C74<>"",ISNA(MATCH($C74,账户表,0))),"※账户不在基础资料里",IF(AND($G74<>"",ISNA(MATCH($G74,项目名表,0))),"※项目不在项目台账里",IF(AND(LEFT($F74,3)="成本-",$G74=""),"※成本类支出没填项目",IF(AND(LEFT($F74,3)="成本-",$H74<>"",N($K74)>0,COUNTIFS(采购单!$B:$B,$B74,采购单!$C:$C,$H74,采购单!$L:$L,$K74)>0),"※这笔可能和采购单重复了",""))))))))))
A75: =IF($B75="","",ROW()-3) | B75: 46095 | C75: 微信1 | D75: 支出 | E75: 其他管理费用 | F75: =IF($E75="","",IFERROR(VLOOKUP($E75,类别归属,2,0),"※类别不在基础资料里")) | I75: 10米卷尺2把 | K75: 26.8 | L75: =IF($C75="","",ROUND(IFERROR(VLOOKUP($C75,账户期初,2,0),0)+SUMIFS($J$4:J75,$C$4:C75,$C75)-SUMIFS($K$4:K75,$C$4:C75,$C75),2)) | M75: =IF($C75="","",ROUND(SUM(基础资料!$B$4:$B$13)+SUM($J$4:J75)-SUM($K$4:K75),2)) | P75: =IF($B75="","",IF($F75="※类别不在基础资料里","※费用类别不在基础资料里",IF(AND(N($J75)=0,N($K75)=0),"※这行没填金额",IF(AND(N($J75)>0,N($K75)>0),"※收入和支出不能同一行都填",IF(AND($D75="收入",N($J75)=0),"※收入行要填收入金额",IF(AND($D75="支出",N($K75)=0),"※支出行要填支出金额",IF(AND($C75<>"",ISNA(MATCH($C75,账户表,0))),"※账户不在基础资料里",IF(AND($G75<>"",ISNA(MATCH($G75,项目名表,0))),"※项目不在项目台账里",IF(AND(LEFT($F75,3)="成本-",$G75=""),"※成本类支出没填项目",IF(AND(LEFT($F75,3)="成本-",$H75<>"",N($K75)>0,COUNTIFS(采购单!$B:$B,$B75,采购单!$C:$C,$H75,采购单!$L:$L,$K75)>0),"※这笔可能和采购单重复了",""))))))))))
A76: =IF($B76="","",ROW()-3) | B76: 46095 | C76: 微信1 | D76: 支出 | E76: 其他管理费用 | F76: =IF($E76="","",IFERROR(VLOOKUP($E76,类别归属,2,0),"※类别不在基础资料里")) | I76: 透明胶带 | K76: 34.8 | L76: =IF($C76="","",ROUND(IFERROR(VLOOKUP($C76,账户期初,2,0),0)+SUMIFS($J$4:J76,$C$4:C76,$C76)-SUMIFS($K$4:K76,$C$4:C76,$C76),2)) | M76: =IF($C76="","",ROUND(SUM(基础资料!$B$4:$B$13)+SUM($J$4:J76)-SUM($K$4:K76),2)) | P76: =IF($B76="","",IF($F76="※类别不在基础资料里","※费用类别不在基础资料里",IF(AND(N($J76)=0,N($K76)=0),"※这行没填金额",IF(AND(N($J76)>0,N($K76)>0),"※收入和支出不能同一行都填",IF(AND($D76="收入",N($J76)=0),"※收入行要填收入金额",IF(AND($D76="支出",N($K76)=0),"※支出行要填支出金额",IF(AND($C76<>"",ISNA(MATCH($C76,账户表,0))),"※账户不在基础资料里",IF(AND($G76<>"",ISNA(MATCH($G76,项目名表,0))),"※项目不在项目台账里",IF(AND(LEFT($F76,3)="成本-",$G76=""),"※成本类支出没填项目",IF(AND(LEFT($F76,3)="成本-",$H76<>"",N($K76)>0,COUNTIFS(采购单!$B:$B,$B76,采购单!$C:$C,$H76,采购单!$L:$L,$K76)>0),"※这笔可能和采购单重复了",""))))))))))
A77: =IF($B77="","",ROW()-3) | B77: 46095 | C77: 微信1 | D77: 支出 | E77: 运费/快递费 | F77: =IF($E77="","",IFERROR(VLOOKUP($E77,类别归属,2,0),"※类别不在基础资料里")) | G77: 织里店 | H77: 炳秀 | I77: 付炳秀配送 | K77: 91 | L77: =IF($C77="","",ROUND(IFERROR(VLOOKUP($C77,账户期初,2,0),0)+SUMIFS($J$4:J77,$C$4:C77,$C77)-SUMIFS($K$4:K77,$C$4:C77,$C77),2)) | M77: =IF($C77="","",ROUND(SUM(基础资料!$B$4:$B$13)+SUM($J$4:J77)-SUM($K$4:K77),2)) | O77: 99 | P77: =IF($B77="","",IF($F77="※类别不在基础资料里","※费用类别不在基础资料里",IF(AND(N($J77)=0,N($K77)=0),"※这行没填金额",IF(AND(N($J77)>0,N($K77)>0),"※收入和支出不能同一行都填",IF(AND($D77="收入",N($J77)=0),"※收入行要填收入金额",IF(AND($D77="支出",N($K77)=0),"※支出行要填支出金额",IF(AND($C77<>"",ISNA(MATCH($C77,账户表,0))),"※账户不在基础资料里",IF(AND($G77<>"",ISNA(MATCH($G77,项目名表,0))),"※项目不在项目台账里",IF(AND(LEFT($F77,3)="成本-",$G77=""),"※成本类支出没填项目",IF(AND(LEFT($F77,3)="成本-",$H77<>"",N($K77)>0,COUNTIFS(采购单!$B:$B,$B77,采购单!$C:$C,$H77,采购单!$L:$L,$K77)>0),"※这笔可能和采购单重复了",""))))))))))
A78: =IF($B78="","",ROW()-3) | B78: 46095 | C78: 微信1 | D78: 支出 | E78: 运费/快递费 | F78: =IF($E78="","",IFERROR(VLOOKUP($E78,类别归属,2,0),"※类别不在基础资料里")) | G78: 犇腾牛排 | H78: 炳秀 | I78: 付炳秀配送 | K78: 8 | L78: =IF($C78="","",ROUND(IFERROR(VLOOKUP($C78,账户期初,2,0),0)+SUMIFS($J$4:J78,$C$4:C78,$C78)-SUMIFS($K$4:K78,$C$4:C78,$C78),2)) | M78: =IF($C78="","",ROUND(SUM(基础资料!$B$4:$B$13)+SUM($J$4:J78)-SUM($K$4:K78),2)) | P78: =IF($B78="","",IF($F78="※类别不在基础资料里","※费用类别不在基础资料里",IF(AND(N($J78)=0,N($K78)=0),"※这行没填金额",IF(AND(N($J78)>0,N($K78)>0),"※收入和支出不能同一行都填",IF(AND($D78="收入",N($J78)=0),"※收入行要填收入金额",IF(AND($D78="支出",N($K78)=0),"※支出行要填支出金额",IF(AND($C78<>"",ISNA(MATCH($C78,账户表,0))),"※账户不在基础资料里",IF(AND($G78<>"",ISNA(MATCH($G78,项目名表,0))),"※项目不在项目台账里",IF(AND(LEFT($F78,3)="成本-",$G78=""),"※成本类支出没填项目",IF(AND(LEFT($F78,3)="成本-",$H78<>"",N($K78)>0,COUNTIFS(采购单!$B:$B,$B78,采购单!$C:$C,$H78,采购单!$L:$L,$K78)>0),"※这笔可能和采购单重复了",""))))))))))
A79: =IF($B79="","",ROW()-3) | B79: 46096 | C79: 微信1 | D79: 支出 | E79: 主材采购 | F79: =IF($E79="","",IFERROR(VLOOKUP($E79,类别归属,2,0),"※类别不在基础资料里")) | G79: 中交 | I79: 付拉斯金2个-海天钛金-中交金属牌 | K79: 216 | L79: =IF($C79="","",ROUND(IFERROR(VLOOKUP($C79,账户期初,2,0),0)+SUMIFS($J$4:J79,$C$4:C79,$C79)-SUMIFS($K$4:K79,$C$4:C79,$C79),2)) | M79: =IF($C79="","",ROUND(SUM(基础资料!$B$4:$B$13)+SUM($J$4:J79)-SUM($K$4:K79),2)) | P79: =IF($B79="","",IF($F79="※类别不在基础资料里","※费用类别不在基础资料里",IF(AND(N($J79)=0,N($K79)=0),"※这行没填金额",IF(AND(N($J79)>0,N($K79)>0),"※收入和支出不能同一行都填",IF(AND($D79="收入",N($J79)=0),"※收入行要填收入金额",IF(AND($D79="支出",N($K79)=0),"※支出行要填支出金额",IF(AND($C79<>"",ISNA(MATCH($C79,账户表,0))),"※账户不在基础资料里",IF(AND($G79<>"",ISNA(MATCH($G79,项目名表,0))),"※项目不在项目台账里",IF(AND(LEFT($F79,3)="成本-",$G79=""),"※成本类支出没填项目",IF(AND(LEFT($F79,3)="成本-",$H79<>"",N($K79)>0,COUNTIFS(采购单!$B:$B,$B79,采购单!$C:$C,$H79,采购单!$L:$L,$K79)>0),"※这笔可能和采购单重复了",""))))))))))
A80: =IF($B80="","",ROW()-3) | B80: 46096 | C80: 微信1 | D80: 支出 | E80: 其他管理费用 | F80: =IF($E80="","",IFERROR(VLOOKUP($E80,类别归属,2,0),"※类别不在基础资料里")) | G80: 东尼电子 | I80: 付运费 | K80: 105 | L80: =IF($C80="","",ROUND(IFERROR(VLOOKUP($C80,账户期初,2,0),0)+SUMIFS($J$4:J80,$C$4:C80,$C80)-SUMIFS($K$4:K80,$C$4:C80,$C80),2)) | M80: =IF($C80="","",ROUND(SUM(基础资料!$B$4:$B$13)+SUM($J$4:J80)-SUM($K$4:K80),2)) | P80: =IF($B80="","",IF($F80="※类别不在基础资料里","※费用类别不在基础资料里",IF(AND(N($J80)=0,N($K80)=0),"※这行没填金额",IF(AND(N($J80)>0,N($K80)>0),"※收入和支出不能同一行都填",IF(AND($D80="收入",N($J80)=0),"※收入行要填收入金额",IF(AND($D80="支出",N($K80)=0),"※支出行要填支出金额",IF(AND($C80<>"",ISNA(MATCH($C80,账户表,0))),"※账户不在基础资料里",IF(AND($G80<>"",ISNA(MATCH($G80,项目名表,0))),"※项目不在项目台账里",IF(AND(LEFT($F80,3)="成本-",$G80=""),"※成本类支出没填项目",IF(AND(LEFT($F80,3)="成本-",$H80<>"",N($K80)>0,COUNTIFS(采购单!$B:$B,$B80,采购单!$C:$C,$H80,采购单!$L:$L,$K80)>0),"※这笔可能和采购单重复了",""))))))))))
A81: =IF($B81="","",ROW()-3) | B81: 46096 | C81: 微信1 | D81: 支出 | E81: 运费/快递费 | F81: =IF($E81="","",IFERROR(VLOOKUP($E81,类别归属,2,0),"※类别不在基础资料里")) | G81: 织里店 | H81: 炳秀 | I81: 付炳秀配送 | K81: 197 | L81: =IF($C81="","",ROUND(IFERROR(VLOOKUP($C81,账户期初,2,0),0)+SUMIFS($J$4:J81,$C$4:C81,$C81)-SUMIFS($K$4:K81,$C$4:C81,$C81),2)) | M81: =IF($C81="","",ROUND(SUM(基础资料!$B$4:$B$13)+SUM($J$4:J81)-SUM($K$4:K81),2)) | P81: =IF($B81="","",IF($F81="※类别不在基础资料里","※费用类别不在基础资料里",IF(AND(N($J81)=0,N($K81)=0),"※这行没填金额",IF(AND(N($J81)>0,N($K81)>0),"※收入和支出不能同一行都填",IF(AND($D81="收入",N($J81)=0),"※收入行要填收入金额",IF(AND($D81="支出",N($K81)=0),"※支出行要填支出金额",IF(AND($C81<>"",ISNA(MATCH($C81,账户表,0))),"※账户不在基础资料里",IF(AND($G81<>"",ISNA(MATCH($G81,项目名表,0))),"※项目不在项目台账里",IF(AND(LEFT($F81,3)="成本-",$G81=""),"※成本类支出没填项目",IF(AND(LEFT($F81,3)="成本-",$H81<>"",N($K81)>0,COUNTIFS(采购单!$B:$B,$B81,采购单!$C:$C,$H81,采购单!$L:$L,$K81)>0),"※这笔可能和采购单重复了",""))))))))))
A82: =IF($B82="","",ROW()-3) | B82: 46097 | C82: 微信1 | D82: 支出 | E82: 借出款 | F82: =IF($E82="","",IFERROR(VLOOKUP($E82,类别归属,2,0),"※类别不在基础资料里")) | H82: 往来款 | I82: 付给付久华 | K82: 4000 | L82: =IF($C82="","",ROUND(IFERROR(VLOOKUP($C82,账户期初,2,0),0)+SUMIFS($J$4:J82,$C$4:C82,$C82)-SUMIFS($K$4:K82,$C$4:C82,$C82),2)) | M82: =IF($C82="","",ROUND(SUM(基础资料!$B$4:$B$13)+SUM($J$4:J82)-SUM($K$4:K82),2)) | P82: =IF($B82="","",IF($F82="※类别不在基础资料里","※费用类别不在基础资料里",IF(AND(N($J82)=0,N($K82)=0),"※这行没填金额",IF(AND(N($J82)>0,N($K82)>0),"※收入和支出不能同一行都填",IF(AND($D82="收入",N($J82)=0),"※收入行要填收入金额",IF(AND($D82="支出",N($K82)=0),"※支出行要填支出金额",IF(AND($C82<>"",ISNA(MATCH($C82,账户表,0))),"※账户不在基础资料里",IF(AND($G82<>"",ISNA(MATCH($G82,项目名表,0))),"※项目不在项目台账里",IF(AND(LEFT($F82,3)="成本-",$G82=""),"※成本类支出没填项目",IF(AND(LEFT($F82,3)="成本-",$H82<>"",N($K82)>0,COUNTIFS(采购单!$B:$B,$B82,采购单!$C:$C,$H82,采购单!$L:$L,$K82)>0),"※这笔可能和采购单重复了",""))))))))))
A83: =IF($B83="","",ROW()-3) | B83: 46097 | C83: 微信1 | D83: 支出 | E83: 借出款 | F83: =IF($E83="","",IFERROR(VLOOKUP($E83,类别归属,2,0),"※类别不在基础资料里")) | G83: 织里店 | H83: 钮 | I83: 付鑫鑫30*30镀锌方管4*26=104元国威拼包 | K83: 100 | L83: =IF($C83="","",ROUND(IFERROR(VLOOKUP($C83,账户期初,2,0),0)+SUMIFS($J$4:J83,$C$4:C83,$C83)-SUMIFS($K$4:K83,$C$4:C83,$C83),2)) | M83: =IF($C83="","",ROUND(SUM(基础资料!$B$4:$B$13)+SUM($J$4:J83)-SUM($K$4:K83),2)) | P83: =IF($B83="","",IF($F83="※类别不在基础资料里","※费用类别不在基础资料里",IF(AND(N($J83)=0,N($K83)=0),"※这行没填金额",IF(AND(N($J83)>0,N($K83)>0),"※收入和支出不能同一行都填",IF(AND($D83="收入",N($J83)=0),"※收入行要填收入金额",IF(AND($D83="支出",N($K83)=0),"※支出行要填支出金额",IF(AND($C83<>"",ISNA(MATCH($C83,账户表,0))),"※账户不在基础资料里",IF(AND($G83<>"",ISNA(MATCH($G83,项目名表,0))),"※项目不在项目台账里",IF(AND(LEFT($F83,3)="成本-",$G83=""),"※成本类支出没填项目",IF(AND(LEFT($F83,3)="成本-",$H83<>"",N($K83)>0,COUNTIFS(采购单!$B:$B,$B83,采购单!$C:$C,$H83,采购单!$L:$L,$K83)>0),"※这笔可能和采购单重复了",""))))))))))
A84: =IF($B84="","",ROW()-3) | B84: 46097 | C84: 微信1 | D84: 收入 | E84: 零星物料销售 | F84: =IF($E84="","",IFERROR(VLOOKUP($E84,类别归属,2,0),"※类别不在基础资料里")) | G84: 万达kvv | I84: 收万达KVV乔金鑫 | J84: 70 | L84: =IF($C84="","",ROUND(IFERROR(VLOOKUP($C84,账户期初,2,0),0)+SUMIFS($J$4:J84,$C$4:C84,$C84)-SUMIFS($K$4:K84,$C$4:C84,$C84),2)) | M84: =IF($C84="","",ROUND(SUM(基础资料!$B$4:$B$13)+SUM($J$4:J84)-SUM($K$4:K84),2)) | P84: =IF($B84="","",IF($F84="※类别不在基础资料里","※费用类别不在基础资料里",IF(AND(N($J84)=0,N($K84)=0),"※这行没填金额",IF(AND(N($J84)>0,N($K84)>0),"※收入和支出不能同一行都填",IF(AND($D84="收入",N($J84)=0),"※收入行要填收入金额",IF(AND($D84="支出",N($K84)=0),"※支出行要填支出金额",IF(AND($C84<>"",ISNA(MATCH($C84,账户表,0))),"※账户不在基础资料里",IF(AND($G84<>"",ISNA(MATCH($G84,项目名表,0))),"※项目不在项目台账里",IF(AND(LEFT($F84,3)="成本-",$G84=""),"※成本类支出没填项目",IF(AND(LEFT($F84,3)="成本-",$H84<>"",N($K84)>0,COUNTIFS(采购单!$B:$B,$B84,采购单!$C:$C,$H84,采购单!$L:$L,$K84)>0),"※这笔可能和采购单重复了",""))))))))))
A85: =IF($B85="","",ROW()-3) | B85: 46097 | C85: 微信1 | D85: 支出 | E85: 运费/快递费 | F85: =IF($E85="","",IFERROR(VLOOKUP($E85,类别归属,2,0),"※类别不在基础资料里")) | G85: 万达kvv | H85: 炳秀 | I85: 付炳秀配送 | K85: 13 | L85: =IF($C85="","",ROUND(IFERROR(VLOOKUP($C85,账户期初,2,0),0)+SUMIFS($J$4:J85,$C$4:C85,$C85)-SUMIFS($K$4:K85,$C$4:C85,$C85),2)) | M85: =IF($C85="","",ROUND(SUM(基础资料!$B$4:$B$13)+SUM($J$4:J85)-SUM($K$4:K85),2)) | O85: 58 | P85: =IF($B85="","",IF($F85="※类别不在基础资料里","※费用类别不在基础资料里",IF(AND(N($J85)=0,N($K85)=0),"※这行没填金额",IF(AND(N($J85)>0,N($K85)>0),"※收入和支出不能同一行都填",IF(AND($D85="收入",N($J85)=0),"※收入行要填收入金额",IF(AND($D85="支出",N($K85)=0),"※支出行要填支出金额",IF(AND($C85<>"",ISNA(MATCH($C85,账户表,0))),"※账户不在基础资料里",IF(AND($G85<>"",ISNA(MATCH($G85,项目名表,0))),"※项目不在项目台账里",IF(AND(LEFT($F85,3)="成本-",$G85=""),"※成本类支出没填项目",IF(AND(LEFT($F85,3)="成本-",$H85<>"",N($K85)>0,COUNTIFS(采购单!$B:$B,$B85,采购单!$C:$C,$H85,采购单!$L:$L,$K85)>0),"※这笔可能和采购单重复了",""))))))))))
A86: =IF($B86="","",ROW()-3) | B86: 46097 | C86: 微信1 | D86: 支出 | E86: 运费/快递费 | F86: =IF($E86="","",IFERROR(VLOOKUP($E86,类别归属,2,0),"※类别不在基础资料里")) | G86: 织里店 | H86: 炳秀 | I86: 付炳秀配送 | K86: 45 | L86: =IF($C86="","",ROUND(IFERROR(VLOOKUP($C86,账户期初,2,0),0)+SUMIFS($J$4:J86,$C$4:C86,$C86)-SUMIFS($K$4:K86,$C$4:C86,$C86),2)) | M86: =IF($C86="","",ROUND(SUM(基础资料!$B$4:$B$13)+SUM($J$4:J86)-SUM($K$4:K86),2)) | P86: =IF($B86="","",IF($F86="※类别不在基础资料里","※费用类别不在基础资料里",IF(AND(N($J86)=0,N($K86)=0),"※这行没填金额",IF(AND(N($J86)>0,N($K86)>0),"※收入和支出不能同一行都填",IF(AND($D86="收入",N($J86)=0),"※收入行要填收入金额",IF(AND($D86="支出",N($K86)=0),"※支出行要填支出金额",IF(AND($C86<>"",ISNA(MATCH($C86,账户表,0))),"※账户不在基础资料里",IF(AND($G86<>"",ISNA(MATCH($G86,项目名表,0))),"※项目不在项目台账里",IF(AND(LEFT($F86,3)="成本-",$G86=""),"※成本类支出没填项目",IF(AND(LEFT($F86,3)="成本-",$H86<>"",N($K86)>0,COUNTIFS(采购单!$B:$B,$B86,采购单!$C:$C,$H86,采购单!$L:$L,$K86)>0),"※这笔可能和采购单重复了",""))))))))))
A87: =IF($B87="","",ROW()-3) | B87: 46097 | C87: 微信1 | D87: 支出 | E87: 借出款 | F87: =IF($E87="","",IFERROR(VLOOKUP($E87,类别归属,2,0),"※类别不在基础资料里")) | I87: 买桶装水 8*10+20*2空桶押金（40元） | K87: 120 | L87: =IF($C87="","",ROUND(IFERROR(VLOOKUP($C87,账户期初,2,0),0)+SUMIFS($J$4:J87,$C$4:C87,$C87)-SUMIFS($K$4:K87,$C$4:C87,$C87),2)) | M87: =IF($C87="","",ROUND(SUM(基础资料!$B$4:$B$13)+SUM($J$4:J87)-SUM($K$4:K87),2)) | P87: =IF($B87="","",IF($F87="※类别不在基础资料里","※费用类别不在基础资料里",IF(AND(N($J87)=0,N($K87)=0),"※这行没填金额",IF(AND(N($J87)>0,N($K87)>0),"※收入和支出不能同一行都填",IF(AND($D87="收入",N($J87)=0),"※收入行要填收入金额",IF(AND($D87="支出",N($K87)=0),"※支出行要填支出金额",IF(AND($C87<>"",ISNA(MATCH($C87,账户表,0))),"※账户不在基础资料里",IF(AND($G87<>"",ISNA(MATCH($G87,项目名表,0))),"※项目不在项目台账里",IF(AND(LEFT($F87,3)="成本-",$G87=""),"※成本类支出没填项目",IF(AND(LEFT($F87,3)="成本-",$H87<>"",N($K87)>0,COUNTIFS(采购单!$B:$B,$B87,采购单!$C:$C,$H87,采购单!$L:$L,$K87)>0),"※这笔可能和采购单重复了",""))))))))))
A88: =IF($B88="","",ROW()-3) | B88: 46098 | C88: 微信1 | D88: 收入 | E88: 项目收款 | F88: =IF($E88="","",IFERROR(VLOOKUP($E88,类别归属,2,0),"※类别不在基础资料里")) | G88: 最爱潘多拉ktv | I88: 应实收浩然如歌362（已付514） | J88: 514 | L88: =IF($C88="","",ROUND(IFERROR(VLOOKUP($C88,账户期初,2,0),0)+SUMIFS($J$4:J88,$C$4:C88,$C88)-SUMIFS($K$4:K88,$C$4:C88,$C88),2)) | M88: =IF($C88="","",ROUND(SUM(基础资料!$B$4:$B$13)+SUM($J$4:J88)-SUM($K$4:K88),2)) | P88: =IF($B88="","",IF($F88="※类别不在基础资料里","※费用类别不在基础资料里",IF(AND(N($J88)=0,N($K88)=0),"※这行没填金额",IF(AND(N($J88)>0,N($K88)>0),"※收入和支出不能同一行都填",IF(AND($D88="收入",N($J88)=0),"※收入行要填收入金额",IF(AND($D88="支出",N($K88)=0),"※支出行要填支出金额",IF(AND($C88<>"",ISNA(MATCH($C88,账户表,0))),"※账户不在基础资料里",IF(AND($G88<>"",ISNA(MATCH($G88,项目名表,0))),"※项目不在项目台账里",IF(AND(LEFT($F88,3)="成本-",$G88=""),"※成本类支出没填项目",IF(AND(LEFT($F88,3)="成本-",$H88<>"",N($K88)>0,COUNTIFS(采购单!$B:$B,$B88,采购单!$C:$C,$H88,采购单!$L:$L,$K88)>0),"※这笔可能和采购单重复了",""))))))))))
A89: =IF($B89="","",ROW()-3) | B89: 46098 | C89: 微信1 | D89: 支出 | E89: 主材采购 | F89: =IF($E89="","",IFERROR(VLOOKUP($E89,类别归属,2,0),"※类别不在基础资料里")) | G89: 最爱潘多拉ktv | I89: 退回多收浩然如歌付款514-152=362 | K89: 152 | L89: =IF($C89="","",ROUND(IFERROR(VLOOKUP($C89,账户期初,2,0),0)+SUMIFS($J$4:J89,$C$4:C89,$C89)-SUMIFS($K$4:K89,$C$4:C89,$C89),2)) | M89: =IF($C89="","",ROUND(SUM(基础资料!$B$4:$B$13)+SUM($J$4:J89)-SUM($K$4:K89),2)) | P89: =IF($B89="","",IF($F89="※类别不在基础资料里","※费用类别不在基础资料里",IF(AND(N($J89)=0,N($K89)=0),"※这行没填金额",IF(AND(N($J89)>0,N($K89)>0),"※收入和支出不能同一行都填",IF(AND($D89="收入",N($J89)=0),"※收入行要填收入金额",IF(AND($D89="支出",N($K89)=0),"※支出行要填支出金额",IF(AND($C89<>"",ISNA(MATCH($C89,账户表,0))),"※账户不在基础资料里",IF(AND($G89<>"",ISNA(MATCH($G89,项目名表,0))),"※项目不在项目台账里",IF(AND(LEFT($F89,3)="成本-",$G89=""),"※成本类支出没填项目",IF(AND(LEFT($F89,3)="成本-",$H89<>"",N($K89)>0,COUNTIFS(采购单!$B:$B,$B89,采购单!$C:$C,$H89,采购单!$L:$L,$K89)>0),"※这笔可能和采购单重复了",""))))))))))
A90: =IF($B90="","",ROW()-3) | B90: 46097 | C90: 微信1 | D90: 支出 | E90: 车费/油费/过路费 | F90: =IF($E90="","",IFERROR(VLOOKUP($E90,类别归属,2,0),"※类别不在基础资料里")) | G90: 小谷姐姐 | I90: 应付章凡垫付停车费 | K90: 67 | L90: =IF($C90="","",ROUND(IFERROR(VLOOKUP($C90,账户期初,2,0),0)+SUMIFS($J$4:J90,$C$4:C90,$C90)-SUMIFS($K$4:K90,$C$4:C90,$C90),2)) | M90: =IF($C90="","",ROUND(SUM(基础资料!$B$4:$B$13)+SUM($J$4:J90)-SUM($K$4:K90),2)) | O90: 中交、潮汕火锅、每甜 | P90: =IF($B90="","",IF($F90="※类别不在基础资料里","※费用类别不在基础资料里",IF(AND(N($J90)=0,N($K90)=0),"※这行没填金额",IF(AND(N($J90)>0,N($K90)>0),"※收入和支出不能同一行都填",IF(AND($D90="收入",N($J90)=0),"※收入行要填收入金额",IF(AND($D90="支出",N($K90)=0),"※支出行要填支出金额",IF(AND($C90<>"",ISNA(MATCH($C90,账户表,0))),"※账户不在基础资料里",IF(AND($G90<>"",ISNA(MATCH($G90,项目名表,0))),"※项目不在项目台账里",IF(AND(LEFT($F90,3)="成本-",$G90=""),"※成本类支出没填项目",IF(AND(LEFT($F90,3)="成本-",$H90<>"",N($K90)>0,COUNTIFS(采购单!$B:$B,$B90,采购单!$C:$C,$H90,采购单!$L:$L,$K90)>0),"※这笔可能和采购单重复了",""))))))))))
A91: =IF($B91="","",ROW()-3) | B91: 46098 | C91: 微信1 | D91: 支出 | E91: 运费/快递费 | F91: =IF($E91="","",IFERROR(VLOOKUP($E91,类别归属,2,0),"※类别不在基础资料里")) | G91: 织里店 | H91: 炳秀 | I91: 付炳秀配送 | K91: 18 | L91: =IF($C91="","",ROUND(IFERROR(VLOOKUP($C91,账户期初,2,0),0)+SUMIFS($J$4:J91,$C$4:C91,$C91)-SUMIFS($K$4:K91,$C$4:C91,$C91),2)) | M91: =IF($C91="","",ROUND(SUM(基础资料!$B$4:$B$13)+SUM($J$4:J91)-SUM($K$4:K91),2)) | P91: =IF($B91="","",IF($F91="※类别不在基础资料里","※费用类别不在基础资料里",IF(AND(N($J91)=0,N($K91)=0),"※这行没填金额",IF(AND(N($J91)>0,N($K91)>0),"※收入和支出不能同一行都填",IF(AND($D91="收入",N($J91)=0),"※收入行要填收入金额",IF(AND($D91="支出",N($K91)=0),"※支出行要填支出金额",IF(AND($C91<>"",ISNA(MATCH($C91,账户表,0))),"※账户不在基础资料里",IF(AND($G91<>"",ISNA(MATCH($G91,项目名表,0))),"※项目不在项目台账里",IF(AND(LEFT($F91,3)="成本-",$G91=""),"※成本类支出没填项目",IF(AND(LEFT($F91,3)="成本-",$H91<>"",N($K91)>0,COUNTIFS(采购单!$B:$B,$B91,采购单!$C:$C,$H91,采购单!$L:$L,$K91)>0),"※这笔可能和采购单重复了",""))))))))))
A92: =IF($B92="","",ROW()-3) | B92: 46099 | C92: 微信1 | D92: 支出 | E92: 其他管理费用 | F92: =IF($E92="","",IFERROR(VLOOKUP($E92,类别归属,2,0),"※类别不在基础资料里")) | G92: 德清钟管菜市场 | I92: 中国红结构胶2支 | K92: 24 | L92: =IF($C92="","",ROUND(IFERROR(VLOOKUP($C92,账户期初,2,0),0)+SUMIFS($J$4:J92,$C$4:C92,$C92)-SUMIFS($K$4:K92,$C$4:C92,$C92),2)) | M92: =IF($C92="","",ROUND(SUM(基础资料!$B$4:$B$13)+SUM($J$4:J92)-SUM($K$4:K92),2)) | O92: 本次杨德 报销660.5 | P92: =IF($B92="","",IF($F92="※类别不在基础资料里","※费用类别不在基础资料里",IF(AND(N($J92)=0,N($K92)=0),"※这行没填金额",IF(AND(N($J92)>0,N($K92)>0),"※收入和支出不能同一行都填",IF(AND($D92="收入",N($J92)=0),"※收入行要填收入金额",IF(AND($D92="支出",N($K92)=0),"※支出行要填支出金额",IF(AND($C92<>"",ISNA(MATCH($C92,账户表,0))),"※账户不在基础资料里",IF(AND($G92<>"",ISNA(MATCH($G92,项目名表,0))),"※项目不在项目台账里",IF(AND(LEFT($F92,3)="成本-",$G92=""),"※成本类支出没填项目",IF(AND(LEFT($F92,3)="成本-",$H92<>"",N($K92)>0,COUNTIFS(采购单!$B:$B,$B92,采购单!$C:$C,$H92,采购单!$L:$L,$K92)>0),"※这笔可能和采购单重复了",""))))))))))
A93: =IF($B93="","",ROW()-3) | B93: 46099 | C93: 微信1 | D93: 支出 | E93: 车费/油费/过路费 | F93: =IF($E93="","",IFERROR(VLOOKUP($E93,类别归属,2,0),"※类别不在基础资料里")) | G93: 安吉车贴项目 | I93: 312加油 | K93: 200 | L93: =IF($C93="","",ROUND(IFERROR(VLOOKUP($C93,账户期初,2,0),0)+SUMIFS($J$4:J93,$C$4:C93,$C93)-SUMIFS($K$4:K93,$C$4:C93,$C93),2)) | M93: =IF($C93="","",ROUND(SUM(基础资料!$B$4:$B$13)+SUM($J$4:J93)-SUM($K$4:K93),2)) | P93: =IF($B93="","",IF($F93="※类别不在基础资料里","※费用类别不在基础资料里",IF(AND(N($J93)=0,N($K93)=0),"※这行没填金额",IF(AND(N($J93)>0,N($K93)>0),"※收入和支出不能同一行都填",IF(AND($D93="收入",N($J93)=0),"※收入行要填收入金额",IF(AND($D93="支出",N($K93)=0),"※支出行要填支出金额",IF(AND($C93<>"",ISNA(MATCH($C93,账户表,0))),"※账户不在基础资料里",IF(AND($G93<>"",ISNA(MATCH($G93,项目名表,0))),"※项目不在项目台账里",IF(AND(LEFT($F93,3)="成本-",$G93=""),"※成本类支出没填项目",IF(AND(LEFT($F93,3)="成本-",$H93<>"",N($K93)>0,COUNTIFS(采购单!$B:$B,$B93,采购单!$C:$C,$H93,采购单!$L:$L,$K93)>0),"※这笔可能和采购单重复了",""))))))))))
A94: =IF($B94="","",ROW()-3) | B94: 46099 | C94: 微信1 | D94: 支出 | E94: 车费/油费/过路费 | F94: =IF($E94="","",IFERROR(VLOOKUP($E94,类别归属,2,0),"※类别不在基础资料里")) | G94: 安吉车贴项目 | I94: 高速费（来回） | K94: 64 | L94: =IF($C94="","",ROUND(IFERROR(VLOOKUP($C94,账户期初,2,0),0)+SUMIFS($J$4:J94,$C$4:C94,$C94)-SUMIFS($K$4:K94,$C$4:C94,$C94),2)) | M94: =IF($C94="","",ROUND(SUM(基础资料!$B$4:$B$13)+SUM($J$4:J94)-SUM($K$4:K94),2)) | P94: =IF($B94="","",IF($F94="※类别不在基础资料里","※费用类别不在基础资料里",IF(AND(N($J94)=0,N($K94)=0),"※这行没填金额",IF(AND(N($J94)>0,N($K94)>0),"※收入和支出不能同一行都填",IF(AND($D94="收入",N($J94)=0),"※收入行要填收入金额",IF(AND($D94="支出",N($K94)=0),"※支出行要填支出金额",IF(AND($C94<>"",ISNA(MATCH($C94,账户表,0))),"※账户不在基础资料里",IF(AND($G94<>"",ISNA(MATCH($G94,项目名表,0))),"※项目不在项目台账里",IF(AND(LEFT($F94,3)="成本-",$G94=""),"※成本类支出没填项目",IF(AND(LEFT($F94,3)="成本-",$H94<>"",N($K94)>0,COUNTIFS(采购单!$B:$B,$B94,采购单!$C:$C,$H94,采购单!$L:$L,$K94)>0),"※这笔可能和采购单重复了",""))))))))))
A95: =IF($B95="","",ROW()-3) | B95: 46099 | C95: 微信1 | D95: 支出 | E95: 其他管理费用 | F95: =IF($E95="","",IFERROR(VLOOKUP($E95,类别归属,2,0),"※类别不在基础资料里")) | G95: 安吉车贴项目 | I95: 刮板5块 | K95: 35 | L95: =IF($C95="","",ROUND(IFERROR(VLOOKUP($C95,账户期初,2,0),0)+SUMIFS($J$4:J95,$C$4:C95,$C95)-SUMIFS($K$4:K95,$C$4:C95,$C95),2)) | M95: =IF($C95="","",ROUND(SUM(基础资料!$B$4:$B$13)+SUM($J$4:J95)-SUM($K$4:K95),2)) | P95: =IF($B95="","",IF($F95="※类别不在基础资料里","※费用类别不在基础资料里",IF(AND(N($J95)=0,N($K95)=0),"※这行没填金额",IF(AND(N($J95)>0,N($K95)>0),"※收入和支出不能同一行都填",IF(AND($D95="收入",N($J95)=0),"※收入行要填收入金额",IF(AND($D95="支出",N($K95)=0),"※支出行要填支出金额",IF(AND($C95<>"",ISNA(MATCH($C95,账户表,0))),"※账户不在基础资料里",IF(AND($G95<>"",ISNA(MATCH($G95,项目名表,0))),"※项目不在项目台账里",IF(AND(LEFT($F95,3)="成本-",$G95=""),"※成本类支出没填项目",IF(AND(LEFT($F95,3)="成本-",$H95<>"",N($K95)>0,COUNTIFS(采购单!$B:$B,$B95,采购单!$C:$C,$H95,采购单!$L:$L,$K95)>0),"※这笔可能和采购单重复了",""))))))))))
A96: =IF($B96="","",ROW()-3) | B96: 46099 | C96: 微信1 | D96: 支出 | E96: 车费/油费/过路费 | F96: =IF($E96="","",IFERROR(VLOOKUP($E96,类别归属,2,0),"※类别不在基础资料里")) | I96: 停车费 | K96: 12.5 | L96: =IF($C96="","",ROUND(IFERROR(VLOOKUP($C96,账户期初,2,0),0)+SUMIFS($J$4:J96,$C$4:C96,$C96)-SUMIFS($K$4:K96,$C$4:C96,$C96),2)) | M96: =IF($C96="","",ROUND(SUM(基础资料!$B$4:$B$13)+SUM($J$4:J96)-SUM($K$4:K96),2)) | P96: =IF($B96="","",IF($F96="※类别不在基础资料里","※费用类别不在基础资料里",IF(AND(N($J96)=0,N($K96)=0),"※这行没填金额",IF(AND(N($J96)>0,N($K96)>0),"※收入和支出不能同一行都填",IF(AND($D96="收入",N($J96)=0),"※收入行要填收入金额",IF(AND($D96="支出",N($K96)=0),"※支出行要填支出金额",IF(AND($C96<>"",ISNA(MATCH($C96,账户表,0))),"※账户不在基础资料里",IF(AND($G96<>"",ISNA(MATCH($G96,项目名表,0))),"※项目不在项目台账里",IF(AND(LEFT($F96,3)="成本-",$G96=""),"※成本类支出没填项目",IF(AND(LEFT($F96,3)="成本-",$H96<>"",N($K96)>0,COUNTIFS(采购单!$B:$B,$B96,采购单!$C:$C,$H96,采购单!$L:$L,$K96)>0),"※这笔可能和采购单重复了",""))))))))))
