Workbook

Sheet 使用说明
A1: 公司 LOGO （选中本区域插入图片） | C1: =IF(使用说明!$B$2="","",使用说明!$B$2&" ")&"研发费用归集与分摊台账（2026年度） 使用说明" -> 研发费用归集与分摊台账（2026年度） 使用说明
A2: 企业名称： | F2: ← 填一次，全表标题自动带出
A4: 一、适用范围
B5: 本台账适用于以泡棉发泡成型、泡棉与PET基材贴合（复合）、分切/模切为主要工艺，产品应用于3C电子与新能源汽车板块的企业。
B6: 针对研发人员、仪器设备与无形资产在研发与生产之间“混合使用”的情形，按工时法进行费用分配，形成《费用分配说明》及计算证据材料，满足高新技术企业认定、研发费用加计扣除等对“从事研发活动的人员（含外聘人员）和用于研发活动的仪器、设备、无形资产的费用分配说明（包括工作使用情况记录及费用分配计算证据材料）”的资料要求。
A7: 二、核算原则
B8: ① 按月核算、按年汇总：每月末由研发人员填报工时，财务据以计算分摊，年末自动汇总；
B9: ② 人员人工费用：当月某项目应分摊人工费 = 该人员当月总薪酬（含工资、社保、公积金、外聘劳务费）×（该项目研发工时 ÷ 该人员当月总工时）；
B10: ③ 仪器设备折旧/使用费：当月某项目应分摊设备费 = 该设备当月折旧额（或租赁费）×（该项目使用工时 ÷ 该设备当月总运行工时）；
B11: ④ 无形资产摊销：当月某项目应分摊的摊销额 = 该无形资产当月摊销额 ×（该项目使用工时 ÷ 该资产当月总使用工时），由研发按月填报无形资产使用工时；
B12: ⑤ 研发专用人员/设备/无形资产记录全额工时；研发生产共用的记录实际投入研发的工时；
B13: ⑥ 未分配至研发项目的部分，全额计入生产成本，做到“研发与生产各归其位、合计不重不漏”。
B14: ⑦ 数据来源：薪酬数据源自月度工资表；折旧数据源自月度固定资产折旧明细表；摊销数据源自无形资产摊销表。
A15: 三、每月操作流程（5步）
B16: 第1步 基础维护 | C16: 在【项目清单】【人员名册】【资产台账】中维护当期在研项目、研发人员（含外聘）、研发与生产共用的设备及无形资产。基础信息只需变动时维护。
B17: 第2步 工时填报 | C17: 研发部门于次月3日前完成《研发人员工时分配表》《仪器、设备工时分配表》《无形资产工时分配表》填报（签批用纸质表见【附表1】【附表2】【附表3】），经项目负责人、部门负责人签字确认后交财务。签字件为“工作使用情况记录”原始证据，须装订留存。
B18: 第3步 数据录入 | C18: 财务将签批后的工时录入【研发人员工时分配表】与【仪器设备工时分配表】。注意“工时校验”列必须为0（红色即为不平）。研发专用人员/设备的“非研发工时”应填0。
B19: 第4步 费用分摊 | C19: 在【研发人员工时费用分配表】录入当月薪酬构成；在【仪器设备工时费用分配表】核对当月折旧/租赁金额；在【无形资产费用分配表】核对当月摊销额。三表的各项目分摊金额均按对应工时占比自动计算。【其他研发费用】按需登记直接投入等费用（选填）。
B20: 第5步 汇总复核 | C20: 查看【月度归集汇总】与【年度汇总】（含表四勾稽校验，差异须为0），与研发支出辅助账、财务账核对一致；同步更新【指标监测】中的收入与人数，跟踪三项高企指标；年末打印【费用分配说明】签章存档。
A21: 四、本台账与《研发费用归集》制表要求的对应关系
B22: 指标监测 | C22: 《各项指标监测》—— 科技人员占比≥10%、研发费用占销售收入比例（＜5000万≥5%／5000万~2亿≥4%／＞2亿≥3%）、高新收入占比≥60%。对应页签：【指标监测】
B23: 人员人工 | C23: 《研发人员工时分配表》研发按月填报 → 【研发人员工时分配表】；《研发人员工时费用分配表》财务按月按项目核算、按年汇总 → 【研发人员工时费用分配表】
B24: 仪器设备 | C24: 《仪器、设备工时分配表》研发按月填报 → 【仪器设备工时分配表】；《仪器、设备工时费用分配表》财务按月按项目核算、按年汇总 → 【仪器设备工时费用分配表】
B25: 无形资产 | C25: 《无形资产工时分配表》研发按月填报 → 【无形资产工时分配表】；《无形资产费用分配表》财务按月按项目核算、按年汇总 → 【无形资产费用分配表】
A26: 五、单元格颜色约定
C27: 浅黄底 = 需人工录入 | D27: 由研发/财务填写的原始数据
C28: 浅灰底 = 公式自动计算 | D28: 请勿手工覆盖，改动会破坏勾稽关系
C29: 浅蓝底 = 合计/汇总行 | D29: 自动生成，用于与账面核对
A31: 六、留存备查资料清单（应对“费用分配说明”核查）
B32: 1. 本台账电子版（按年一个文件）及打印的【月度归集汇总】【年度汇总】；
B33: 2. 经签批的《研发人员工时分配表》《仪器、设备工时分配表》《无形资产工时分配表》原件（附表1、附表2、附表3）；
B34: 3. 《研发人员与设备费用分配说明》（本文件【费用分配说明】页，加盖公章）；
B35: 4. 研发人员名册、劳动合同/外聘劳务合同、当月工资表及社保公积金缴纳凭证；
B36: 5. 设备固定资产卡片、折旧计提表、租赁合同及付款凭证，无形资产摊销表；
B37: 6. 研发项目立项决议文件、项目计划书、阶段性研发记录（配方试验记录、贴合/分切工艺试验记录、检测报告等）；
B38: 7. 研发支出辅助账及与财务账、纳税申报表的核对说明。
B40: 提示：各录入表首行标有“★示例”的行为填写示范，正式使用前请整行删除，以免混入统计。

Sheet 指标监测
A1: 公司 LOGO （选中本区域插入图片） | C1: =IF(使用说明!$B$2="","",使用说明!$B$2&" ")&"一、高新技术企业各项指标监测表（2026年度）" -> 一、高新技术企业各项指标监测表（2026年度）
A2: 监测口径：①科技人员占当年职工总数比例不低于10%；②研发费用占销售收入比例——销售收入＜5000万元的不低于5%，5000万元～2亿元的不低于4%，超过2亿元的不低于3%（本表按销售收入自动判定适用档次）；③高新技术产品（服务）收入占同期总收入比例不低于60%。浅黄底单元格需人工录入（数据取自财务报表及人事台账），研发费用自动取自【年度汇总】。
A4: 表一 年度指标达标测算
A5: 指标项目 | C5: 数值 | D5: 标准要求 | E5: 是否达标 | F5: 说明
A6: 当年职工总数（人） | F6: 在职职工月平均人数，与社保缴纳人数、工资表人数一致
A7: 其中：科技人员数（人） | D7: =COUNTIF(人员名册!$H$4:$H$53,"是") -> 4 | F7: 左侧“标准要求”列为【人员名册】中标记“是否科技人员=是”的统计参考值，实际以人事台账为准
A8: 科技人员占比 | C8: =IF($C$6=0,"",$C$7/$C$6) | D8: 不低于10% | E8: =IF($C$8="","",IF($C$8>=0.1,"√ 达标","✗ 未达标")) | F8: 累计实际工作满183天以上的研发人员及相关技术人员
A9: 当年销售收入（元） | F9: 取自利润表“营业收入”中的销售（营业）收入，用于研发费用占比测算
A10: 当年研发费用总额（元） | C10: =年度汇总!$O$16 -> 126067.89 | D10: 自动取数 | F10: 自动取自【年度汇总】表一合计，须与研发支出辅助账、纳税申报一致
A11: 适用研发费用比例标准 | C11: =IF($C$9=0,"",IF($C$9<50000000,0.05,IF($C$9<=200000000,0.04,0.03))) | D11: 按销售收入自动分档 | F11: ＜5000万→5%；5000万～2亿→4%；＞2亿→3%
A12: 研发费用占销售收入比例 | C12: =IF($C$9=0,"",$C$10/$C$9) | D12: =IF($C$11="","",$C$11) | E12: =IF(OR($C$12="",$C$11=""),"",IF($C$12>=$C$11,"√ 达标","✗ 未达标")) | F12: 近三个会计年度分别测算；企业成立不足三年的按实际经营年限计算
A13: 当年总收入（元） | F13: 收入总额减去不征税收入后的余额
A14: 高新技术产品（服务）收入（元） | F14: 对应主要产品（服务）：3C电子用泡棉/复合材料、新能源汽车电池用缓冲阻燃材料等
A15: 高新收入占比 | C15: =IF($C$13=0,"",$C$14/$C$13) | D15: 不低于60% | E15: =IF($C$15="","",IF($C$15>=0.6,"√ 达标","✗ 未达标")) | F15: 高新技术产品（服务）收入占同期总收入比例
A17: 表二 分月监测（收入与研发费用累计进度）
A18: 年月 | B18: 当月销售收入 (元) | C18: 当月高新技术产品 (服务)收入(元) | D18: 当月总收入 (元) | E18: 当月研发费用 (元,自动) | F18: 累计销售收入 (元) | G18: 累计研发费用 (元) | H18: 累计研发费用 占销售收入比例 | I18: 累计高新收入 占总收入比例 | J18: 预警提示
A19: 2026-01 | E19: =月度归集汇总!$K$14 -> 0 | F19: =SUM($B$19:B19) -> 0 | G19: =SUM($E$19:E19) -> 0 | H19: =IF($F19=0,"",$G19/$F19) | I19: =IF(SUM($D$19:D19)=0,"",SUM($C$19:C19)/SUM($D$19:D19)) | J19: =IF(OR($H19="",$C$11=""),"",IF($H19<$C$11,"⚠ 研发费用占比低于标准","√ 正常"))
A20: 2026-02 | E20: =月度归集汇总!$K$25 -> 0 | F20: =SUM($B$19:B20) -> 0 | G20: =SUM($E$19:E20) -> 0 | H20: =IF($F20=0,"",$G20/$F20) | I20: =IF(SUM($D$19:D20)=0,"",SUM($C$19:C20)/SUM($D$19:D20)) | J20: =IF(OR($H20="",$C$11=""),"",IF($H20<$C$11,"⚠ 研发费用占比低于标准","√ 正常"))
A21: 2026-03 | E21: =月度归集汇总!$K$36 -> 0 | F21: =SUM($B$19:B21) -> 0 | G21: =SUM($E$19:E21) -> 0 | H21: =IF($F21=0,"",$G21/$F21) | I21: =IF(SUM($D$19:D21)=0,"",SUM($C$19:C21)/SUM($D$19:D21)) | J21: =IF(OR($H21="",$C$11=""),"",IF($H21<$C$11,"⚠ 研发费用占比低于标准","√ 正常"))
A22: 2026-04 | E22: =月度归集汇总!$K$47 -> 0 | F22: =SUM($B$19:B22) -> 0 | G22: =SUM($E$19:E22) -> 0 | H22: =IF($F22=0,"",$G22/$F22) | I22: =IF(SUM($D$19:D22)=0,"",SUM($C$19:C22)/SUM($D$19:D22)) | J22: =IF(OR($H22="",$C$11=""),"",IF($H22<$C$11,"⚠ 研发费用占比低于标准","√ 正常"))
A23: 2026-05 | E23: =月度归集汇总!$K$58 -> 0 | F23: =SUM($B$19:B23) -> 0 | G23: =SUM($E$19:E23) -> 0 | H23: =IF($F23=0,"",$G23/$F23) | I23: =IF(SUM($D$19:D23)=0,"",SUM($C$19:C23)/SUM($D$19:D23)) | J23: =IF(OR($H23="",$C$11=""),"",IF($H23<$C$11,"⚠ 研发费用占比低于标准","√ 正常"))
A24: 2026-06 | E24: =月度归集汇总!$K$69 -> 0 | F24: =SUM($B$19:B24) -> 0 | G24: =SUM($E$19:E24) -> 0 | H24: =IF($F24=0,"",$G24/$F24) | I24: =IF(SUM($D$19:D24)=0,"",SUM($C$19:C24)/SUM($D$19:D24)) | J24: =IF(OR($H24="",$C$11=""),"",IF($H24<$C$11,"⚠ 研发费用占比低于标准","√ 正常"))
A25: 2026-07 | E25: =月度归集汇总!$K$80 -> 0 | F25: =SUM($B$19:B25) -> 0 | G25: =SUM($E$19:E25) -> 0 | H25: =IF($F25=0,"",$G25/$F25) | I25: =IF(SUM($D$19:D25)=0,"",SUM($C$19:C25)/SUM($D$19:D25)) | J25: =IF(OR($H25="",$C$11=""),"",IF($H25<$C$11,"⚠ 研发费用占比低于标准","√ 正常"))
A26: 2026-08 | E26: =月度归集汇总!$K$91 -> 0 | F26: =SUM($B$19:B26) -> 0 | G26: =SUM($E$19:E26) -> 0 | H26: =IF($F26=0,"",$G26/$F26) | I26: =IF(SUM($D$19:D26)=0,"",SUM($C$19:C26)/SUM($D$19:D26)) | J26: =IF(OR($H26="",$C$11=""),"",IF($H26<$C$11,"⚠ 研发费用占比低于标准","√ 正常"))
A27: 2026-09 | E27: =月度归集汇总!$K$102 -> 126067.89 | F27: =SUM($B$19:B27) -> 0 | G27: =SUM($E$19:E27) -> 126067.89 | H27: =IF($F27=0,"",$G27/$F27) | I27: =IF(SUM($D$19:D27)=0,"",SUM($C$19:C27)/SUM($D$19:D27)) | J27: =IF(OR($H27="",$C$11=""),"",IF($H27<$C$11,"⚠ 研发费用占比低于标准","√ 正常"))
A28: 2026-10 | E28: =月度归集汇总!$K$113 -> 0 | F28: =SUM($B$19:B28) -> 0 | G28: =SUM($E$19:E28) -> 126067.89 | H28: =IF($F28=0,"",$G28/$F28) | I28: =IF(SUM($D$19:D28)=0,"",SUM($C$19:C28)/SUM($D$19:D28)) | J28: =IF(OR($H28="",$C$11=""),"",IF($H28<$C$11,"⚠ 研发费用占比低于标准","√ 正常"))
A29: 2026-11 | E29: =月度归集汇总!$K$124 -> 0 | F29: =SUM($B$19:B29) -> 0 | G29: =SUM($E$19:E29) -> 126067.89 | H29: =IF($F29=0,"",$G29/$F29) | I29: =IF(SUM($D$19:D29)=0,"",SUM($C$19:C29)/SUM($D$19:D29)) | J29: =IF(OR($H29="",$C$11=""),"",IF($H29<$C$11,"⚠ 研发费用占比低于标准","√ 正常"))
A30: 2026-12 | E30: =月度归集汇总!$K$135 -> 0 | F30: =SUM($B$19:B30) -> 0 | G30: =SUM($E$19:E30) -> 126067.89 | H30: =IF($F30=0,"",$G30/$F30) | I30: =IF(SUM($D$19:D30)=0,"",SUM($C$19:C30)/SUM($D$19:D30)) | J30: =IF(OR($H30="",$C$11=""),"",IF($H30<$C$11,"⚠ 研发费用占比低于标准","√ 正常"))
A31: 全年合计 | B31: =ROUND(SUM(B19:B30),2) -> 0 | C31: =ROUND(SUM(C19:C30),2) -> 0 | D31: =ROUND(SUM(D19:D30),2) -> 0 | E31: =ROUND(SUM(E19:E30),2) -> 126067.89 | H31: =IF($B31=0,"",$E31/$B31) | I31: =IF($D31=0,"",$C31/$D31)
A33: 提示：表二“当月研发费用”自动取自【月度归集汇总】各月合计；销售收入、高新技术产品收入、总收入需按月从财务系统取数填列，便于全年动态监测研发费用投入强度，避免年末突击。

Sheet 项目清单
A1: 公司 LOGO （选中本区域插入图片） | C1: =IF(使用说明!$B$2="","",使用说明!$B$2&" ")&"二、研发项目清单（2026年度）" -> 二、研发项目清单（2026年度）
A2: 填写说明：项目编号 RD01～RD10 为全表引用主键，请勿改动编号本身；项目名称、板块等可自由维护，编号顺序不可打乱。通常一个年度应有 5～10 个研发项目（至少 5 个），未使用的编号留空即可，不影响各表计算。
A3: 序号 | B3: 项目编号 | C3: 研发项目名称 | D3: 应用板块 | E3: 主要工艺环节 | F3: 立项日期 | G3: 计划结题日期 | H3: 项目负责人 | I3: 项目状态 | J3: 备注
A4: 1 | B4: RD01 | C4: 高回弹低压缩永久变形3C用聚氨酯泡棉开发 | D4: 3C电子 | E4: 发泡成型 | F4: 2026-01-05 | G4: 2026-12-20 | I4: 在研
A5: 2 | B5: RD02 | C5: 动力电池模组用高阻燃缓冲泡棉研发 | D5: 新能源汽车 | E5: 发泡成型 | F5: 2026-01-05 | G5: 2026-12-20 | I5: 在研
A6: 3 | B6: RD03 | C6: 泡棉与PET基材无溶剂贴合工艺开发 | D6: 通用 | E6: PET贴合 | F6: 2026-02-01 | G6: 2026-11-30 | I6: 在研
A7: 4 | B7: RD04 | C7: 超薄泡棉高精度分切及毛边控制技术研究 | D7: 3C电子 | E7: 分切 | F7: 2026-03-01 | G7: 2026-12-31 | I7: 在研
A8: 5 | B8: RD05 | C8: 新能源汽车电池包用导热缓冲复合材料开发 | D8: 新能源汽车 | E8: PET贴合 | F8: 2026-03-01 | G8: 2027-02-28 | I8: 在研
A9: 6 | B9: RD06 | C9: 3C电子用超薄黑色遮光泡棉制备技术 | D9: 3C电子 | E9: 发泡成型 | I9: 在研
A10: 7 | B10: RD07 | C10: 环保型水性胶泡棉贴合技术开发 | D10: 通用 | E10: PET贴合 | I10: 在研
A11: 8 | B11: RD08 | C11: 泡棉模切自动化在线检测技术研究 | D11: 3C电子 | E11: 模切 | I11: 在研
A12: 9 | B12: RD09
A13: 10 | B13: RD10

Sheet 人员名册
A1: 公司 LOGO （选中本区域插入图片） | C1: =IF(使用说明!$B$2="","",使用说明!$B$2&" ")&"三、研发人员名册（含外聘人员）" -> 三、研发人员名册（含外聘人员）
A2: 填写说明：①工号为工时表引用主键，须唯一且不可重复；②“人员使用性质”区分研发专用与研发生产共用——研发专用人员在工时表中记录全额工时，研发生产共用人员记录实际投入研发的工时；③外聘人员“人员类别”选“外聘”，其劳务费在【研发人员工时费用分配表】的“外聘劳务费”列填列；④“是否科技人员”用于高新技术企业科技人员占比（不低于10%）指标监测。
A3: 序号 | B3: 工号 | C3: 姓名 | D3: 所属部门 | E3: 岗位/承担研发任务 | F3: 人员类别 | G3: 人员使用性质 | H3: 是否科技人员 | I3: 入职/合作日期 | J3: 备注
A4: 1 | B4: YF001 | C4: （示例）张工 | D4: 研发中心 | E4: 配方工程师 | F4: 在职 | G4: 研发专用 | H4: 是 | J4: ★示例行，请删除
A5: 2 | B5: YF002 | C5: （示例）李工 | D5: 研发中心 | E5: 工艺工程师 | F5: 在职 | G5: 研发专用 | H5: 是 | J5: ★示例行，请删除
A6: 3 | B6: YF003 | C6: （示例）王工 | D6: 生产部 | E6: 贴合技师（研发生产共用） | F6: 在职 | G6: 研发生产共用 | H6: 是 | J6: ★示例行，请删除
A7: 4 | B7: WP001 | C7: （示例）赵博 | D7: 外聘专家 | E7: 高分子材料顾问 | F7: 外聘 | G7: 研发生产共用 | H7: 是 | J7: ★示例行，请删除
A8: 5
A9: 6
A10: 7
A11: 8
A12: 9
A13: 10
A14: 11
A15: 12
A16: 13
A17: 14
A18: 15
A19: 16
... A53: 50

Sheet 资产台账
A1: 公司 LOGO （选中本区域插入图片） | C1: =IF(使用说明!$B$2="","",使用说明!$B$2&" ")&"四、研发用仪器设备及无形资产台账（含研发生产共用资产）" -> 四、研发用仪器设备及无形资产台账（含研发生产共用资产）
A2: 填写说明：资产编号为工时表引用主键，须唯一。“月折旧/摊销/租赁额”按财务实际计提数填列，【仪器设备工时费用分配表】表将自动取数（当月实际不同可在该表直接覆盖）。研发与生产共用的设备必须登记，其研发使用工时在【仪器设备工时分配表】中据实填报（研发专用设备记录全额运行工时）；无形资产（配方模拟软件、专利/专有技术等）同样登记，其使用工时在【无形资产工时分配表】中据实填报，摊销额按使用工时占比分摊。数据来源：月度固定资产折旧明细表 / 月度无形资产摊销表。
A3: 序号 | B3: 资产编号 | C3: 资产名称 | D3: 资产类别 | E3: 规格型号 | F3: 所属工序 | G3: 取得日期 | H3: 原值(元) | I3: 预计使用年限(年) | J3: 月折旧/摊销/租赁额(元) | K3: 费用类型 | L3: 资产使用性质 | M3: 存放地点 | N3: 备注
A4: 1 | B4: SB001 | C4: （示例）连续发泡生产线 | D4: 设备 | E4: FP-2000 | F4: 发泡成型 | G4: 2023-06-15 | H4: 1800000 | I4: 10 | J4: 15000 | K4: 折旧 | L4: 研发生产共用 | N4: ★示例行，请删除
A5: 2 | B5: SB002 | C5: （示例）自动贴合复合机 | D5: 设备 | E5: LM-1300 | F5: PET贴合 | G5: 2024-03-20 | H5: 960000 | I5: 10 | J5: 8000 | K5: 折旧 | L5: 研发生产共用 | N5: ★示例行，请删除
A6: 3 | B6: SB003 | C6: （示例）高精度分切机 | D6: 设备 | E6: SL-800 | F6: 分切 | G6: 2024-09-10 | H6: 620000 | I6: 10 | J6: 5166.67 | K6: 折旧 | L6: 研发生产共用 | N6: ★示例行，请删除
A7: 4 | B7: SB004 | C7: （示例）万能材料试验机 | D7: 设备 | E7: UTM-50 | F7: 检测试验 | G7: 2025-01-12 | H7: 180000 | I7: 5 | J7: 3000 | K7: 折旧 | L7: 研发生产共用 | N7: ★示例行，请删除
A8: 5 | B8: SB005 | C8: （示例）租入激光模切设备 | D8: 设备 | E8: LD-600 | F8: 模切 | G8: 2026-01-01 | H8: 0 | I8: 0 | J8: 12000 | K8: 租赁费 | L8: 研发生产共用 | N8: ★示例行，请删除
A9: 6 | B9: WX001 | C9: （示例）泡棉配方模拟软件 | D9: 无形资产 | E9: V3.0 | F9: 研发通用 | G9: 2025-05-06 | H9: 240000 | I9: 5 | J9: 4000 | K9: 摊销 | L9: 研发专用 | N9: ★示例行，请删除
A10: 7
A11: 8
A12: 9
A13: 10
A14: 11
A15: 12
A16: 13
A17: 14
A18: 15
A19: 16
A20: 17
A21: 18
... A53: 50

Sheet 研发人员工时分配表
A1: 公司 LOGO （选中本区域插入图片） | C1: =IF(使用说明!$B$2="","",使用说明!$B$2&" ")&"五、《研发人员工时分配表》（研发部门按月填报，2026年度）" -> 五、《研发人员工时分配表》（研发部门按月填报，2026年度）
A2: 录入说明：①由研发部门按月填报，依据经签批的《附表1-研发人员工时分配表(签批用)》逐人逐月录入；②“当月出勤总工时”为该人当月全部有效工作工时（含加班）；③研发专用人员记录全额工时（非研发工时填0），研发生产共用人员按实际投入分别记录研发工时与非研发（生产）工时；④“工时校验”须为0，显示红色表示总工时与明细不平，须更正后方可分摊；⑤同一人当月只填一行；⑥灰底列为公式自动计算，请勿覆盖。
A3: 年月 (YYYY-MM) | B3: 工号 | C3: 姓名 | D3: 所属部门 | E3: 人员类别 | F3: 当月出勤 总工时 | G3: 非研发工时 (生产及其他) | H3: 各研发项目分配工时（小时） | R3: 研发工时 合计 | S3: 工时校验 (须为0) | T3: 研发工时 占比 | U3: 本月主要研发工作内容 | V3: 备注
H4: =项目清单!$B$4 -> RD01 | I4: =项目清单!$B$5 -> RD02 | J4: =项目清单!$B$6 -> RD03 | K4: =项目清单!$B$7 -> RD04 | L4: =项目清单!$B$8 -> RD05 | M4: =项目清单!$B$9 -> RD06 | N4: =项目清单!$B$10 -> RD07 | O4: =项目清单!$B$11 -> RD08 | P4: =项目清单!$B$12 -> RD09 | Q4: =项目清单!$B$13 -> RD10
H5: =IF(H4="","",IFERROR(VLOOKUP(H4,项目清单!$B$4:$C$13,2,0)&"","")) -> 高回弹低压缩永久变形3C用聚氨酯泡棉开发 | I5: =IF(I4="","",IFERROR(VLOOKUP(I4,项目清单!$B$4:$C$13,2,0)&"","")) -> 动力电池模组用高阻燃缓冲泡棉研发 | J5: =IF(J4="","",IFERROR(VLOOKUP(J4,项目清单!$B$4:$C$13,2,0)&"","")) -> 泡棉与PET基材无溶剂贴合工艺开发 | K5: =IF(K4="","",IFERROR(VLOOKUP(K4,项目清单!$B$4:$C$13,2,0)&"","")) -> 超薄泡棉高精度分切及毛边控制技术研究 | L5: =IF(L4="","",IFERROR(VLOOKUP(L4,项目清单!$B$4:$C$13,2,0)&"","")) -> 新能源汽车电池包用导热缓冲复合材料开发 | M5: =IF(M4="","",IFERROR(VLOOKUP(M4,项目清单!$B$4:$C$13,2,0)&"","")) -> 3C电子用超薄黑色遮光泡棉制备技术 | N5: =IF(N4="","",IFERROR(VLOOKUP(N4,项目清单!$B$4:$C$13,2,0)&"","")) -> 环保型水性胶泡棉贴合技术开发 | O5: =IF(O4="","",IFERROR(VLOOKUP(O4,项目清单!$B$4:$C$13,2,0)&"","")) -> 泡棉模切自动化在线检测技术研究 | ... Q5: =IF(Q4="","",IFERROR(VLOOKUP(Q4,项目清单!$B$4:$C$13,2,0)&"","")) | W5: 匹配主键(勿删)
A6: 2026-09 | B6: YF001 | C6: =IF($B6="","",IFERROR(VLOOKUP($B6,人员名册!$B$4:$G$53,2,0)&"","名册中未登记")) -> （示例）张工 | D6: =IF($B6="","",IFERROR(VLOOKUP($B6,人员名册!$B$4:$G$53,3,0)&"","")) -> 研发中心 | E6: =IF($B6="","",IFERROR(VLOOKUP($B6,人员名册!$B$4:$G$53,5,0)&"","")) -> 在职 | F6: 176 | G6: 16 | H6: 100 | I6: 60 | R6: =IF($A6="","",SUM(H6:Q6)) -> 160 | S6: =IF($A6="","",ROUND($F6-$G6-$R6,2)) -> 0 | T6: =IF(OR($A6="",$F6=0),"",$R6/$F6) -> 0.90909091 | U6: 完成低压变形泡棉配方第3轮小试及压缩永久变形验证 | V6: ★示例行，请删除 | W6: =IF($A6="","",$A6&"|"&$B6) -> 2026-09|YF001
A7: 2026-09 | B7: YF003 | C7: =IF($B7="","",IFERROR(VLOOKUP($B7,人员名册!$B$4:$G$53,2,0)&"","名册中未登记")) -> （示例）王工 | D7: =IF($B7="","",IFERROR(VLOOKUP($B7,人员名册!$B$4:$G$53,3,0)&"","")) -> 生产部 | E7: =IF($B7="","",IFERROR(VLOOKUP($B7,人员名册!$B$4:$G$53,5,0)&"","")) -> 在职 | F7: 176 | G7: 120 | J7: 36 | L7: 20 | R7: =IF($A7="","",SUM(H7:Q7)) -> 56 | S7: =IF($A7="","",ROUND($F7-$G7-$R7,2)) -> 0 | T7: =IF(OR($A7="",$F7=0),"",$R7/$F7) -> 0.31818182 | U7: 无溶剂贴合线速与胶量匹配试验（研发生产共用岗位） | V7: ★示例行，请删除 | W7: =IF($A7="","",$A7&"|"&$B7) -> 2026-09|YF003
A8: 2026-09 | B8: WP001 | C8: =IF($B8="","",IFERROR(VLOOKUP($B8,人员名册!$B$4:$G$53,2,0)&"","名册中未登记")) -> （示例）赵博 | D8: =IF($B8="","",IFERROR(VLOOKUP($B8,人员名册!$B$4:$G$53,3,0)&"","")) -> 外聘专家 | E8: =IF($B8="","",IFERROR(VLOOKUP($B8,人员名册!$B$4:$G$53,5,0)&"","")) -> 外聘 | F8: 80 | G8: 0 | I8: 50 | L8: 30 | R8: =IF($A8="","",SUM(H8:Q8)) -> 80 | S8: =IF($A8="","",ROUND($F8-$G8-$R8,2)) -> 0 | T8: =IF(OR($A8="",$F8=0),"",$R8/$F8) -> 1 | U8: 外聘专家：阻燃体系选型指导与试验方案评审 | V8: ★示例行，请删除 | W8: =IF($A8="","",$A8&"|"&$B8) -> 2026-09|WP001
C9: =IF($B9="","",IFERROR(VLOOKUP($B9,人员名册!$B$4:$G$53,2,0)&"","名册中未登记")) | D9: =IF($B9="","",IFERROR(VLOOKUP($B9,人员名册!$B$4:$G$53,3,0)&"","")) | E9: =IF($B9="","",IFERROR(VLOOKUP($B9,人员名册!$B$4:$G$53,5,0)&"","")) | R9: =IF($A9="","",SUM(H9:Q9)) | S9: =IF($A9="","",ROUND($F9-$G9-$R9,2)) | T9: =IF(OR($A9="",$F9=0),"",$R9/$F9) | W9: =IF($A9="","",$A9&"|"&$B9)
C10: =IF($B10="","",IFERROR(VLOOKUP($B10,人员名册!$B$4:$G$53,2,0)&"","名册中未登记")) | D10: =IF($B10="","",IFERROR(VLOOKUP($B10,人员名册!$B$4:$G$53,3,0)&"","")) | E10: =IF($B10="","",IFERROR(VLOOKUP($B10,人员名册!$B$4:$G$53,5,0)&"","")) | R10: =IF($A10="","",SUM(H10:Q10)) | S10: =IF($A10="","",ROUND($F10-$G10-$R10,2)) | T10: =IF(OR($A10="",$F10=0),"",$R10/$F10) | W10: =IF($A10="","",$A10&"|"&$B10)
C11: =IF($B11="","",IFERROR(VLOOKUP($B11,人员名册!$B$4:$G$53,2,0)&"","名册中未登记")) | D11: =IF($B11="","",IFERROR(VLOOKUP($B11,人员名册!$B$4:$G$53,3,0)&"","")) | E11: =IF($B11="","",IFERROR(VLOOKUP($B11,人员名册!$B$4:$G$53,5,0)&"","")) | R11: =IF($A11="","",SUM(H11:Q11)) | S11: =IF($A11="","",ROUND($F11-$G11-$R11,2)) | T11: =IF(OR($A11="",$F11=0),"",$R11/$F11) | W11: =IF($A11="","",$A11&"|"&$B11)
C12: =IF($B12="","",IFERROR(VLOOKUP($B12,人员名册!$B$4:$G$53,2,0)&"","名册中未登记")) | D12: =IF($B12="","",IFERROR(VLOOKUP($B12,人员名册!$B$4:$G$53,3,0)&"","")) | E12: =IF($B12="","",IFERROR(VLOOKUP($B12,人员名册!$B$4:$G$53,5,0)&"","")) | R12: =IF($A12="","",SUM(H12:Q12)) | S12: =IF($A12="","",ROUND($F12-$G12-$R12,2)) | T12: =IF(OR($A12="",$F12=0),"",$R12/$F12) | W12: =IF($A12="","",$A12&"|"&$B12)
C13: =IF($B13="","",IFERROR(VLOOKUP($B13,人员名册!$B$4:$G$53,2,0)&"","名册中未登记")) | D13: =IF($B13="","",IFERROR(VLOOKUP($B13,人员名册!$B$4:$G$53,3,0)&"","")) | E13: =IF($B13="","",IFERROR(VLOOKUP($B13,人员名册!$B$4:$G$53,5,0)&"","")) | R13: =IF($A13="","",SUM(H13:Q13)) | S13: =IF($A13="","",ROUND($F13-$G13-$R13,2)) | T13: =IF(OR($A13="",$F13=0),"",$R13/$F13) | W13: =IF($A13="","",$A13&"|"&$B13)
C14: =IF($B14="","",IFERROR(VLOOKUP($B14,人员名册!$B$4:$G$53,2,0)&"","名册中未登记")) | D14: =IF($B14="","",IFERROR(VLOOKUP($B14,人员名册!$B$4:$G$53,3,0)&"","")) | E14: =IF($B14="","",IFERROR(VLOOKUP($B14,人员名册!$B$4:$G$53,5,0)&"","")) | R14: =IF($A14="","",SUM(H14:Q14)) | S14: =IF($A14="","",ROUND($F14-$G14-$R14,2)) | T14: =IF(OR($A14="",$F14=0),"",$R14/$F14) | W14: =IF($A14="","",$A14&"|"&$B14)
C15: =IF($B15="","",IFERROR(VLOOKUP($B15,人员名册!$B$4:$G$53,2,0)&"","名册中未登记")) | D15: =IF($B15="","",IFERROR(VLOOKUP($B15,人员名册!$B$4:$G$53,3,0)&"","")) | E15: =IF($B15="","",IFERROR(VLOOKUP($B15,人员名册!$B$4:$G$53,5,0)&"","")) | R15: =IF($A15="","",SUM(H15:Q15)) | S15: =IF($A15="","",ROUND($F15-$G15-$R15,2)) | T15: =IF(OR($A15="",$F15=0),"",$R15/$F15) | W15: =IF($A15="","",$A15&"|"&$B15)
C16: =IF($B16="","",IFERROR(VLOOKUP($B16,人员名册!$B$4:$G$53,2,0)&"","名册中未登记")) | D16: =IF($B16="","",IFERROR(VLOOKUP($B16,人员名册!$B$4:$G$53,3,0)&"","")) | E16: =IF($B16="","",IFERROR(VLOOKUP($B16,人员名册!$B$4:$G$53,5,0)&"","")) | R16: =IF($A16="","",SUM(H16:Q16)) | S16: =IF($A16="","",ROUND($F16-$G16-$R16,2)) | T16: =IF(OR($A16="",$F16=0),"",$R16/$F16) | W16: =IF($A16="","",$A16&"|"&$B16)
C17: =IF($B17="","",IFERROR(VLOOKUP($B17,人员名册!$B$4:$G$53,2,0)&"","名册中未登记")) | D17: =IF($B17="","",IFERROR(VLOOKUP($B17,人员名册!$B$4:$G$53,3,0)&"","")) | E17: =IF($B17="","",IFERROR(VLOOKUP($B17,人员名册!$B$4:$G$53,5,0)&"","")) | R17: =IF($A17="","",SUM(H17:Q17)) | S17: =IF($A17="","",ROUND($F17-$G17-$R17,2)) | T17: =IF(OR($A17="",$F17=0),"",$R17/$F17) | W17: =IF($A17="","",$A17&"|"&$B17)
C18: =IF($B18="","",IFERROR(VLOOKUP($B18,人员名册!$B$4:$G$53,2,0)&"","名册中未登记")) | D18: =IF($B18="","",IFERROR(VLOOKUP($B18,人员名册!$B$4:$G$53,3,0)&"","")) | E18: =IF($B18="","",IFERROR(VLOOKUP($B18,人员名册!$B$4:$G$53,5,0)&"","")) | R18: =IF($A18="","",SUM(H18:Q18)) | S18: =IF($A18="","",ROUND($F18-$G18-$R18,2)) | T18: =IF(OR($A18="",$F18=0),"",$R18/$F18) | W18: =IF($A18="","",$A18&"|"&$B18)
C19: =IF($B19="","",IFERROR(VLOOKUP($B19,人员名册!$B$4:$G$53,2,0)&"","名册中未登记")) | D19: =IF($B19="","",IFERROR(VLOOKUP($B19,人员名册!$B$4:$G$53,3,0)&"","")) | E19: =IF($B19="","",IFERROR(VLOOKUP($B19,人员名册!$B$4:$G$53,5,0)&"","")) | R19: =IF($A19="","",SUM(H19:Q19)) | S19: =IF($A19="","",ROUND($F19-$G19-$R19,2)) | T19: =IF(OR($A19="",$F19=0),"",$R19/$F19) | W19: =IF($A19="","",$A19&"|"&$B19)
C20: =IF($B20="","",IFERROR(VLOOKUP($B20,人员名册!$B$4:$G$53,2,0)&"","名册中未登记")) | D20: =IF($B20="","",IFERROR(VLOOKUP($B20,人员名册!$B$4:$G$53,3,0)&"","")) | E20: =IF($B20="","",IFERROR(VLOOKUP($B20,人员名册!$B$4:$G$53,5,0)&"","")) | R20: =IF($A20="","",SUM(H20:Q20)) | S20: =IF($A20="","",ROUND($F20-$G20-$R20,2)) | T20: =IF(OR($A20="",$F20=0),"",$R20/$F20) | W20: =IF($A20="","",$A20&"|"&$B20)
... C245: =IF($B245="","",IFERROR(VLOOKUP($B245,人员名册!$B$4:$G$53,2,0)&"","名册中未登记")) | D245: =IF($B245="","",IFERROR(VLOOKUP($B245,人员名册!$B$4:$G$53,3,0)&"","")) | E245: =IF($B245="","",IFERROR(VLOOKUP($B245,人员名册!$B$4:$G$53,5,0)&"","")) | R245: =IF($A245="","",SUM(H245:Q245)) | S245: =IF($A245="","",ROUND($F245-$G245-$R245,2)) | T245: =IF(OR($A245="",$F245=0),"",$R245/$F245) | W245: =IF($A245="","",$A245&"|"&$B245)

Sheet 研发人员工时费用分配表
A1: 公司 LOGO （选中本区域插入图片） | C1: =IF(使用说明!$B$2="","",使用说明!$B$2&" ")&"六、《研发人员工时费用分配表》（财务按月按项目核算、按年汇总，2026年度）" -> 六、《研发人员工时费用分配表》（财务按月按项目核算、按年汇总，2026年度）
A2: 计算依据：当月某项目应分摊人工费 = 该人员当月总薪酬（含工资、社保、公积金、外聘劳务费）×（该项目研发工时 ÷ 该人员当月总工时）。数据来源：薪酬数据源自【月度工资表】及社保公积金缴费凭证。录入说明：只需录入 A~I 列（年月、工号及薪酬构成；外聘人员在“外聘劳务费”列填列）；工时及各项目分摊金额由《研发人员工时分配表》按“年月+工号”自动匹配取数。请关注末列“数据校验”，出现⚠提示须先更正工时分配表。
A3: 年月 (YYYY-MM) | B3: 工号 | C3: 姓名 | D3: 人员类别 | E3: 工资薪金 (元) | F3: 社保 (单位承担,元) | G3: 公积金 (单位承担,元) | H3: 外聘劳务费 (元) | I3: 其他人工支出 (元) | J3: 当月薪酬合计 (元) | K3: 当月总工时 | L3: 研发工时合计 | M3: 研发工时占比 (分摊系数) | N3: 各研发项目分摊人工费用（元） | X3: 研发人工费 小计(元) | Y3: 计入生产成本的 人工费(元) | Z3: 数据校验
N4: =项目清单!$B$4 -> RD01 | O4: =项目清单!$B$5 -> RD02 | P4: =项目清单!$B$6 -> RD03 | Q4: =项目清单!$B$7 -> RD04 | R4: =项目清单!$B$8 -> RD05 | S4: =项目清单!$B$9 -> RD06 | T4: =项目清单!$B$10 -> RD07 | U4: =项目清单!$B$11 -> RD08 | V4: =项目清单!$B$12 -> RD09 | W4: =项目清单!$B$13 -> RD10
N5: =IF(N4="","",IFERROR(VLOOKUP(N4,项目清单!$B$4:$C$13,2,0)&"","")) -> 高回弹低压缩永久变形3C用聚氨酯泡棉开发 | O5: =IF(O4="","",IFERROR(VLOOKUP(O4,项目清单!$B$4:$C$13,2,0)&"","")) -> 动力电池模组用高阻燃缓冲泡棉研发 | P5: =IF(P4="","",IFERROR(VLOOKUP(P4,项目清单!$B$4:$C$13,2,0)&"","")) -> 泡棉与PET基材无溶剂贴合工艺开发 | Q5: =IF(Q4="","",IFERROR(VLOOKUP(Q4,项目清单!$B$4:$C$13,2,0)&"","")) -> 超薄泡棉高精度分切及毛边控制技术研究 | R5: =IF(R4="","",IFERROR(VLOOKUP(R4,项目清单!$B$4:$C$13,2,0)&"","")) -> 新能源汽车电池包用导热缓冲复合材料开发 | S5: =IF(S4="","",IFERROR(VLOOKUP(S4,项目清单!$B$4:$C$13,2,0)&"","")) -> 3C电子用超薄黑色遮光泡棉制备技术 | T5: =IF(T4="","",IFERROR(VLOOKUP(T4,项目清单!$B$4:$C$13,2,0)&"","")) -> 环保型水性胶泡棉贴合技术开发 | U5: =IF(U4="","",IFERROR(VLOOKUP(U4,项目清单!$B$4:$C$13,2,0)&"","")) -> 泡棉模切自动化在线检测技术研究 | ... W5: =IF(W4="","",IFERROR(VLOOKUP(W4,项目清单!$B$4:$C$13,2,0)&"","")) | AA5: 匹配行号(勿删) | AB5: 重复计数(勿删)
A6: 2026-09 | B6: YF001 | C6: =IF($B6="","",IFERROR(VLOOKUP($B6,人员名册!$B$4:$G$53,2,0)&"","名册中未登记")) -> （示例）张工 | D6: =IF($B6="","",IFERROR(VLOOKUP($B6,人员名册!$B$4:$G$53,5,0)&"","")) -> 在职 | E6: 15000 | F6: 3900 | G6: 1800 | H6: 0 | I6: 1200 | J6: =IF($A6="","",ROUND(SUM(E6:I6),2)) -> 21900 | K6: =IF(OR($A6="",$AA6=0),0,INDEX(研发人员工时分配表!$F$6:$F$245,$AA6)) -> 176 | L6: =IF(OR($A6="",$AA6=0),0,INDEX(研发人员工时分配表!$R$6:$R$245,$AA6)) -> 160 | M6: =IF(OR($A6="",$K6=0),"",$L6/$K6) -> 0.90909091 | N6: =IF(OR($A6="",$K6=0),"",ROUND($J6*INDEX(研发人员工时分配表!$H$6:$H$245,$AA6)/$K6,2)) -> 12443.18 | O6: =IF(OR($A6="",$K6=0),"",ROUND($J6*INDEX(研发人员工时分配表!$I$6:$I$245,$AA6)/$K6,2)) -> 7465.91 | P6: =IF(OR($A6="",$K6=0),"",ROUND($J6*INDEX(研发人员工时分配表!$J$6:$J$245,$AA6)/$K6,2)) -> 0 | Q6: =IF(OR($A6="",$K6=0),"",ROUND($J6*INDEX(研发人员工时分配表!$K$6:$K$245,$AA6)/$K6,2)) -> 0 | R6: =IF(OR($A6="",$K6=0),"",ROUND($J6*INDEX(研发人员工时分配表!$L$6:$L$245,$AA6)/$K6,2)) -> 0 | S6: =IF(OR($A6="",$K6=0),"",ROUND($J6*INDEX(研发人员工时分配表!$M$6:$M$245,$AA6)/$K6,2)) -> 0 | T6: =IF(OR($A6="",$K6=0),"",ROUND($J6*INDEX(研发人员工时分配表!$N$6:$N$245,$AA6)/$K6,2)) -> 0 | U6: =IF(OR($A6="",$K6=0),"",ROUND($J6*INDEX(研发人员工时分配表!$O$6:$O$245,$AA6)/$K6,2)) -> 0 | V6: =IF(OR($A6="",$K6=0),"",ROUND($J6*INDEX(研发人员工时分配表!$P$6:$P$245,$AA6)/$K6,2)) -> 0 | W6: =IF(OR($A6="",$K6=0),"",ROUND($J6*INDEX(研发人员工时分配表!$Q$6:$Q$245,$AA6)/$K6,2)) -> 0 | X6: =IF($A6="","",ROUND(SUM(N6:W6),2)) -> 19909.09 | Y6: =IF($A6="","",ROUND($J6-X6,2)) -> 1990.91 | Z6: =IF($A6="","",IF($AA6=0,"⚠ 工时分配表无此人当月记录",IF($AB6>1,"⚠ 工时分配表存在重复行","√ 正常"))) -> √ 正常 | AA6: =IF($A6="",0,IFERROR(MATCH($A6&"|"&$B6,研发人员工时分配表!$W$6:$W$245,0),0)) -> 1 | AB6: =IF($A6="",0,COUNTIFS(研发人员工时分配表!$A$6:$A$245,$A6,研发人员工时分配表!$B$6:$B$245,$B6)) -> 1
A7: 2026-09 | B7: YF003 | C7: =IF($B7="","",IFERROR(VLOOKUP($B7,人员名册!$B$4:$G$53,2,0)&"","名册中未登记")) -> （示例）王工 | D7: =IF($B7="","",IFERROR(VLOOKUP($B7,人员名册!$B$4:$G$53,5,0)&"","")) -> 在职 | E7: 9000 | F7: 2340 | G7: 1080 | H7: 0 | I7: 600 | J7: =IF($A7="","",ROUND(SUM(E7:I7),2)) -> 13020 | K7: =IF(OR($A7="",$AA7=0),0,INDEX(研发人员工时分配表!$F$6:$F$245,$AA7)) -> 176 | L7: =IF(OR($A7="",$AA7=0),0,INDEX(研发人员工时分配表!$R$6:$R$245,$AA7)) -> 56 | M7: =IF(OR($A7="",$K7=0),"",$L7/$K7) -> 0.31818182 | N7: =IF(OR($A7="",$K7=0),"",ROUND($J7*INDEX(研发人员工时分配表!$H$6:$H$245,$AA7)/$K7,2)) -> 0 | O7: =IF(OR($A7="",$K7=0),"",ROUND($J7*INDEX(研发人员工时分配表!$I$6:$I$245,$AA7)/$K7,2)) -> 0 | P7: =IF(OR($A7="",$K7=0),"",ROUND($J7*INDEX(研发人员工时分配表!$J$6:$J$245,$AA7)/$K7,2)) -> 2663.18 | Q7: =IF(OR($A7="",$K7=0),"",ROUND($J7*INDEX(研发人员工时分配表!$K$6:$K$245,$AA7)/$K7,2)) -> 0 | R7: =IF(OR($A7="",$K7=0),"",ROUND($J7*INDEX(研发人员工时分配表!$L$6:$L$245,$AA7)/$K7,2)) -> 1479.55 | S7: =IF(OR($A7="",$K7=0),"",ROUND($J7*INDEX(研发人员工时分配表!$M$6:$M$245,$AA7)/$K7,2)) -> 0 | T7: =IF(OR($A7="",$K7=0),"",ROUND($J7*INDEX(研发人员工时分配表!$N$6:$N$245,$AA7)/$K7,2)) -> 0 | U7: =IF(OR($A7="",$K7=0),"",ROUND($J7*INDEX(研发人员工时分配表!$O$6:$O$245,$AA7)/$K7,2)) -> 0 | V7: =IF(OR($A7="",$K7=0),"",ROUND($J7*INDEX(研发人员工时分配表!$P$6:$P$245,$AA7)/$K7,2)) -> 0 | W7: =IF(OR($A7="",$K7=0),"",ROUND($J7*INDEX(研发人员工时分配表!$Q$6:$Q$245,$AA7)/$K7,2)) -> 0 | X7: =IF($A7="","",ROUND(SUM(N7:W7),2)) -> 4142.73 | Y7: =IF($A7="","",ROUND($J7-X7,2)) -> 8877.27 | Z7: =IF($A7="","",IF($AA7=0,"⚠ 工时分配表无此人当月记录",IF($AB7>1,"⚠ 工时分配表存在重复行","√ 正常"))) -> √ 正常 | AA7: =IF($A7="",0,IFERROR(MATCH($A7&"|"&$B7,研发人员工时分配表!$W$6:$W$245,0),0)) -> 2 | AB7: =IF($A7="",0,COUNTIFS(研发人员工时分配表!$A$6:$A$245,$A7,研发人员工时分配表!$B$6:$B$245,$B7)) -> 1
A8: 2026-09 | B8: WP001 | C8: =IF($B8="","",IFERROR(VLOOKUP($B8,人员名册!$B$4:$G$53,2,0)&"","名册中未登记")) -> （示例）赵博 | D8: =IF($B8="","",IFERROR(VLOOKUP($B8,人员名册!$B$4:$G$53,5,0)&"","")) -> 外聘 | E8: 0 | F8: 0 | G8: 0 | H8: 30000 | I8: 0 | J8: =IF($A8="","",ROUND(SUM(E8:I8),2)) -> 30000 | K8: =IF(OR($A8="",$AA8=0),0,INDEX(研发人员工时分配表!$F$6:$F$245,$AA8)) -> 80 | L8: =IF(OR($A8="",$AA8=0),0,INDEX(研发人员工时分配表!$R$6:$R$245,$AA8)) -> 80 | M8: =IF(OR($A8="",$K8=0),"",$L8/$K8) -> 1 | N8: =IF(OR($A8="",$K8=0),"",ROUND($J8*INDEX(研发人员工时分配表!$H$6:$H$245,$AA8)/$K8,2)) -> 0 | O8: =IF(OR($A8="",$K8=0),"",ROUND($J8*INDEX(研发人员工时分配表!$I$6:$I$245,$AA8)/$K8,2)) -> 18750 | P8: =IF(OR($A8="",$K8=0),"",ROUND($J8*INDEX(研发人员工时分配表!$J$6:$J$245,$AA8)/$K8,2)) -> 0 | Q8: =IF(OR($A8="",$K8=0),"",ROUND($J8*INDEX(研发人员工时分配表!$K$6:$K$245,$AA8)/$K8,2)) -> 0 | R8: =IF(OR($A8="",$K8=0),"",ROUND($J8*INDEX(研发人员工时分配表!$L$6:$L$245,$AA8)/$K8,2)) -> 11250 | S8: =IF(OR($A8="",$K8=0),"",ROUND($J8*INDEX(研发人员工时分配表!$M$6:$M$245,$AA8)/$K8,2)) -> 0 | T8: =IF(OR($A8="",$K8=0),"",ROUND($J8*INDEX(研发人员工时分配表!$N$6:$N$245,$AA8)/$K8,2)) -> 0 | U8: =IF(OR($A8="",$K8=0),"",ROUND($J8*INDEX(研发人员工时分配表!$O$6:$O$245,$AA8)/$K8,2)) -> 0 | V8: =IF(OR($A8="",$K8=0),"",ROUND($J8*INDEX(研发人员工时分配表!$P$6:$P$245,$AA8)/$K8,2)) -> 0 | W8: =IF(OR($A8="",$K8=0),"",ROUND($J8*INDEX(研发人员工时分配表!$Q$6:$Q$245,$AA8)/$K8,2)) -> 0 | X8: =IF($A8="","",ROUND(SUM(N8:W8),2)) -> 30000 | Y8: =IF($A8="","",ROUND($J8-X8,2)) -> 0 | Z8: =IF($A8="","",IF($AA8=0,"⚠ 工时分配表无此人当月记录",IF($AB8>1,"⚠ 工时分配表存在重复行","√ 正常"))) -> √ 正常 | AA8: =IF($A8="",0,IFERROR(MATCH($A8&"|"&$B8,研发人员工时分配表!$W$6:$W$245,0),0)) -> 3 | AB8: =IF($A8="",0,COUNTIFS(研发人员工时分配表!$A$6:$A$245,$A8,研发人员工时分配表!$B$6:$B$245,$B8)) -> 1
C9: =IF($B9="","",IFERROR(VLOOKUP($B9,人员名册!$B$4:$G$53,2,0)&"","名册中未登记")) | D9: =IF($B9="","",IFERROR(VLOOKUP($B9,人员名册!$B$4:$G$53,5,0)&"","")) | J9: =IF($A9="","",ROUND(SUM(E9:I9),2)) | K9: =IF(OR($A9="",$AA9=0),0,INDEX(研发人员工时分配表!$F$6:$F$245,$AA9)) -> 0 | L9: =IF(OR($A9="",$AA9=0),0,INDEX(研发人员工时分配表!$R$6:$R$245,$AA9)) -> 0 | M9: =IF(OR($A9="",$K9=0),"",$L9/$K9) | N9: =IF(OR($A9="",$K9=0),"",ROUND($J9*INDEX(研发人员工时分配表!$H$6:$H$245,$AA9)/$K9,2)) | O9: =IF(OR($A9="",$K9=0),"",ROUND($J9*INDEX(研发人员工时分配表!$I$6:$I$245,$AA9)/$K9,2)) | P9: =IF(OR($A9="",$K9=0),"",ROUND($J9*INDEX(研发人员工时分配表!$J$6:$J$245,$AA9)/$K9,2)) | Q9: =IF(OR($A9="",$K9=0),"",ROUND($J9*INDEX(研发人员工时分配表!$K$6:$K$245,$AA9)/$K9,2)) | R9: =IF(OR($A9="",$K9=0),"",ROUND($J9*INDEX(研发人员工时分配表!$L$6:$L$245,$AA9)/$K9,2)) | S9: =IF(OR($A9="",$K9=0),"",ROUND($J9*INDEX(研发人员工时分配表!$M$6:$M$245,$AA9)/$K9,2)) | T9: =IF(OR($A9="",$K9=0),"",ROUND($J9*INDEX(研发人员工时分配表!$N$6:$N$245,$AA9)/$K9,2)) | U9: =IF(OR($A9="",$K9=0),"",ROUND($J9*INDEX(研发人员工时分配表!$O$6:$O$245,$AA9)/$K9,2)) | V9: =IF(OR($A9="",$K9=0),"",ROUND($J9*INDEX(研发人员工时分配表!$P$6:$P$245,$AA9)/$K9,2)) | W9: =IF(OR($A9="",$K9=0),"",ROUND($J9*INDEX(研发人员工时分配表!$Q$6:$Q$245,$AA9)/$K9,2)) | X9: =IF($A9="","",ROUND(SUM(N9:W9),2)) | Y9: =IF($A9="","",ROUND($J9-X9,2)) | Z9: =IF($A9="","",IF($AA9=0,"⚠ 工时分配表无此人当月记录",IF($AB9>1,"⚠ 工时分配表存在重复行","√ 正常"))) | AA9: =IF($A9="",0,IFERROR(MATCH($A9&"|"&$B9,研发人员工时分配表!$W$6:$W$245,0),0)) -> 0 | AB9: =IF($A9="",0,COUNTIFS(研发人员工时分配表!$A$6:$A$245,$A9,研发人员工时分配表!$B$6:$B$245,$B9)) -> 0
C10: =IF($B10="","",IFERROR(VLOOKUP($B10,人员名册!$B$4:$G$53,2,0)&"","名册中未登记")) | D10: =IF($B10="","",IFERROR(VLOOKUP($B10,人员名册!$B$4:$G$53,5,0)&"","")) | J10: =IF($A10="","",ROUND(SUM(E10:I10),2)) | K10: =IF(OR($A10="",$AA10=0),0,INDEX(研发人员工时分配表!$F$6:$F$245,$AA10)) -> 0 | L10: =IF(OR($A10="",$AA10=0),0,INDEX(研发人员工时分配表!$R$6:$R$245,$AA10)) -> 0 | M10: =IF(OR($A10="",$K10=0),"",$L10/$K10) | N10: =IF(OR($A10="",$K10=0),"",ROUND($J10*INDEX(研发人员工时分配表!$H$6:$H$245,$AA10)/$K10,2)) | O10: =IF(OR($A10="",$K10=0),"",ROUND($J10*INDEX(研发人员工时分配表!$I$6:$I$245,$AA10)/$K10,2)) | P10: =IF(OR($A10="",$K10=0),"",ROUND($J10*INDEX(研发人员工时分配表!$J$6:$J$245,$AA10)/$K10,2)) | Q10: =IF(OR($A10="",$K10=0),"",ROUND($J10*INDEX(研发人员工时分配表!$K$6:$K$245,$AA10)/$K10,2)) | R10: =IF(OR($A10="",$K10=0),"",ROUND($J10*INDEX(研发人员工时分配表!$L$6:$L$245,$AA10)/$K10,2)) | S10: =IF(OR($A10="",$K10=0),"",ROUND($J10*INDEX(研发人员工时分配表!$M$6:$M$245,$AA10)/$K10,2)) | T10: =IF(OR($A10="",$K10=0),"",ROUND($J10*INDEX(研发人员工时分配表!$N$6:$N$245,$AA10)/$K10,2)) | U10: =IF(OR($A10="",$K10=0),"",ROUND($J10*INDEX(研发人员工时分配表!$O$6:$O$245,$AA10)/$K10,2)) | V10: =IF(OR($A10="",$K10=0),"",ROUND($J10*INDEX(研发人员工时分配表!$P$6:$P$245,$AA10)/$K10,2)) | W10: =IF(OR($A10="",$K10=0),"",ROUND($J10*INDEX(研发人员工时分配表!$Q$6:$Q$245,$AA10)/$K10,2)) | X10: =IF($A10="","",ROUND(SUM(N10:W10),2)) | Y10: =IF($A10="","",ROUND($J10-X10,2)) | Z10: =IF($A10="","",IF($AA10=0,"⚠ 工时分配表无此人当月记录",IF($AB10>1,"⚠ 工时分配表存在重复行","√ 正常"))) | AA10: =IF($A10="",0,IFERROR(MATCH($A10&"|"&$B10,研发人员工时分配表!$W$6:$W$245,0),0)) -> 0 | AB10: =IF($A10="",0,COUNTIFS(研发人员工时分配表!$A$6:$A$245,$A10,研发人员工时分配表!$B$6:$B$245,$B10)) -> 0
C11: =IF($B11="","",IFERROR(VLOOKUP($B11,人员名册!$B$4:$G$53,2,0)&"","名册中未登记")) | D11: =IF($B11="","",IFERROR(VLOOKUP($B11,人员名册!$B$4:$G$53,5,0)&"","")) | J11: =IF($A11="","",ROUND(SUM(E11:I11),2)) | K11: =IF(OR($A11="",$AA11=0),0,INDEX(研发人员工时分配表!$F$6:$F$245,$AA11)) -> 0 | L11: =IF(OR($A11="",$AA11=0),0,INDEX(研发人员工时分配表!$R$6:$R$245,$AA11)) -> 0 | M11: =IF(OR($A11="",$K11=0),"",$L11/$K11) | N11: =IF(OR($A11="",$K11=0),"",ROUND($J11*INDEX(研发人员工时分配表!$H$6:$H$245,$AA11)/$K11,2)) | O11: =IF(OR($A11="",$K11=0),"",ROUND($J11*INDEX(研发人员工时分配表!$I$6:$I$245,$AA11)/$K11,2)) | P11: =IF(OR($A11="",$K11=0),"",ROUND($J11*INDEX(研发人员工时分配表!$J$6:$J$245,$AA11)/$K11,2)) | Q11: =IF(OR($A11="",$K11=0),"",ROUND($J11*INDEX(研发人员工时分配表!$K$6:$K$245,$AA11)/$K11,2)) | R11: =IF(OR($A11="",$K11=0),"",ROUND($J11*INDEX(研发人员工时分配表!$L$6:$L$245,$AA11)/$K11,2)) | S11: =IF(OR($A11="",$K11=0),"",ROUND($J11*INDEX(研发人员工时分配表!$M$6:$M$245,$AA11)/$K11,2)) | T11: =IF(OR($A11="",$K11=0),"",ROUND($J11*INDEX(研发人员工时分配表!$N$6:$N$245,$AA11)/$K11,2)) | U11: =IF(OR($A11="",$K11=0),"",ROUND($J11*INDEX(研发人员工时分配表!$O$6:$O$245,$AA11)/$K11,2)) | V11: =IF(OR($A11="",$K11=0),"",ROUND($J11*INDEX(研发人员工时分配表!$P$6:$P$245,$AA11)/$K11,2)) | W11: =IF(OR($A11="",$K11=0),"",ROUND($J11*INDEX(研发人员工时分配表!$Q$6:$Q$245,$AA11)/$K11,2)) | X11: =IF($A11="","",ROUND(SUM(N11:W11),2)) | Y11: =IF($A11="","",ROUND($J11-X11,2)) | Z11: =IF($A11="","",IF($AA11=0,"⚠ 工时分配表无此人当月记录",IF($AB11>1,"⚠ 工时分配表存在重复行","√ 正常"))) | AA11: =IF($A11="",0,IFERROR(MATCH($A11&"|"&$B11,研发人员工时分配表!$W$6:$W$245,0),0)) -> 0 | AB11: =IF($A11="",0,COUNTIFS(研发人员工时分配表!$A$6:$A$245,$A11,研发人员工时分配表!$B$6:$B$245,$B11)) -> 0
C12: =IF($B12="","",IFERROR(VLOOKUP($B12,人员名册!$B$4:$G$53,2,0)&"","名册中未登记")) | D12: =IF($B12="","",IFERROR(VLOOKUP($B12,人员名册!$B$4:$G$53,5,0)&"","")) | J12: =IF($A12="","",ROUND(SUM(E12:I12),2)) | K12: =IF(OR($A12="",$AA12=0),0,INDEX(研发人员工时分配表!$F$6:$F$245,$AA12)) -> 0 | L12: =IF(OR($A12="",$AA12=0),0,INDEX(研发人员工时分配表!$R$6:$R$245,$AA12)) -> 0 | M12: =IF(OR($A12="",$K12=0),"",$L12/$K12) | N12: =IF(OR($A12="",$K12=0),"",ROUND($J12*INDEX(研发人员工时分配表!$H$6:$H$245,$AA12)/$K12,2)) | O12: =IF(OR($A12="",$K12=0),"",ROUND($J12*INDEX(研发人员工时分配表!$I$6:$I$245,$AA12)/$K12,2)) | P12: =IF(OR($A12="",$K12=0),"",ROUND($J12*INDEX(研发人员工时分配表!$J$6:$J$245,$AA12)/$K12,2)) | Q12: =IF(OR($A12="",$K12=0),"",ROUND($J12*INDEX(研发人员工时分配表!$K$6:$K$245,$AA12)/$K12,2)) | R12: =IF(OR($A12="",$K12=0),"",ROUND($J12*INDEX(研发人员工时分配表!$L$6:$L$245,$AA12)/$K12,2)) | S12: =IF(OR($A12="",$K12=0),"",ROUND($J12*INDEX(研发人员工时分配表!$M$6:$M$245,$AA12)/$K12,2)) | T12: =IF(OR($A12="",$K12=0),"",ROUND($J12*INDEX(研发人员工时分配表!$N$6:$N$245,$AA12)/$K12,2)) | U12: =IF(OR($A12="",$K12=0),"",ROUND($J12*INDEX(研发人员工时分配表!$O$6:$O$245,$AA12)/$K12,2)) | V12: =IF(OR($A12="",$K12=0),"",ROUND($J12*INDEX(研发人员工时分配表!$P$6:$P$245,$AA12)/$K12,2)) | W12: =IF(OR($A12="",$K12=0),"",ROUND($J12*INDEX(研发人员工时分配表!$Q$6:$Q$245,$AA12)/$K12,2)) | X12: =IF($A12="","",ROUND(SUM(N12:W12),2)) | Y12: =IF($A12="","",ROUND($J12-X12,2)) | Z12: =IF($A12="","",IF($AA12=0,"⚠ 工时分配表无此人当月记录",IF($AB12>1,"⚠ 工时分配表存在重复行","√ 正常"))) | AA12: =IF($A12="",0,IFERROR(MATCH($A12&"|"&$B12,研发人员工时分配表!$W$6:$W$245,0),0)) -> 0 | AB12: =IF($A12="",0,COUNTIFS(研发人员工时分配表!$A$6:$A$245,$A12,研发人员工时分配表!$B$6:$B$245,$B12)) -> 0
C13: =IF($B13="","",IFERROR(VLOOKUP($B13,人员名册!$B$4:$G$53,2,0)&"","名册中未登记")) | D13: =IF($B13="","",IFERROR(VLOOKUP($B13,人员名册!$B$4:$G$53,5,0)&"","")) | J13: =IF($A13="","",ROUND(SUM(E13:I13),2)) | K13: =IF(OR($A13="",$AA13=0),0,INDEX(研发人员工时分配表!$F$6:$F$245,$AA13)) -> 0 | L13: =IF(OR($A13="",$AA13=0),0,INDEX(研发人员工时分配表!$R$6:$R$245,$AA13)) -> 0 | M13: =IF(OR($A13="",$K13=0),"",$L13/$K13) | N13: =IF(OR($A13="",$K13=0),"",ROUND($J13*INDEX(研发人员工时分配表!$H$6:$H$245,$AA13)/$K13,2)) | O13: =IF(OR($A13="",$K13=0),"",ROUND($J13*INDEX(研发人员工时分配表!$I$6:$I$245,$AA13)/$K13,2)) | P13: =IF(OR($A13="",$K13=0),"",ROUND($J13*INDEX(研发人员工时分配表!$J$6:$J$245,$AA13)/$K13,2)) | Q13: =IF(OR($A13="",$K13=0),"",ROUND($J13*INDEX(研发人员工时分配表!$K$6:$K$245,$AA13)/$K13,2)) | R13: =IF(OR($A13="",$K13=0),"",ROUND($J13*INDEX(研发人员工时分配表!$L$6:$L$245,$AA13)/$K13,2)) | S13: =IF(OR($A13="",$K13=0),"",ROUND($J13*INDEX(研发人员工时分配表!$M$6:$M$245,$AA13)/$K13,2)) | T13: =IF(OR($A13="",$K13=0),"",ROUND($J13*INDEX(研发人员工时分配表!$N$6:$N$245,$AA13)/$K13,2)) | U13: =IF(OR($A13="",$K13=0),"",ROUND($J13*INDEX(研发人员工时分配表!$O$6:$O$245,$AA13)/$K13,2)) | V13: =IF(OR($A13="",$K13=0),"",ROUND($J13*INDEX(研发人员工时分配表!$P$6:$P$245,$AA13)/$K13,2)) | W13: =IF(OR($A13="",$K13=0),"",ROUND($J13*INDEX(研发人员工时分配表!$Q$6:$Q$245,$AA13)/$K13,2)) | X13: =IF($A13="","",ROUND(SUM(N13:W13),2)) | Y13: =IF($A13="","",ROUND($J13-X13,2)) | Z13: =IF($A13="","",IF($AA13=0,"⚠ 工时分配表无此人当月记录",IF($AB13>1,"⚠ 工时分配表存在重复行","√ 正常"))) | AA13: =IF($A13="",0,IFERROR(MATCH($A13&"|"&$B13,研发人员工时分配表!$W$6:$W$245,0),0)) -> 0 | AB13: =IF($A13="",0,COUNTIFS(研发人员工时分配表!$A$6:$A$245,$A13,研发人员工时分配表!$B$6:$B$245,$B13)) -> 0
C14: =IF($B14="","",IFERROR(VLOOKUP($B14,人员名册!$B$4:$G$53,2,0)&"","名册中未登记")) | D14: =IF($B14="","",IFERROR(VLOOKUP($B14,人员名册!$B$4:$G$53,5,0)&"","")) | J14: =IF($A14="","",ROUND(SUM(E14:I14),2)) | K14: =IF(OR($A14="",$AA14=0),0,INDEX(研发人员工时分配表!$F$6:$F$245,$AA14)) -> 0 | L14: =IF(OR($A14="",$AA14=0),0,INDEX(研发人员工时分配表!$R$6:$R$245,$AA14)) -> 0 | M14: =IF(OR($A14="",$K14=0),"",$L14/$K14) | N14: =IF(OR($A14="",$K14=0),"",ROUND($J14*INDEX(研发人员工时分配表!$H$6:$H$245,$AA14)/$K14,2)) | O14: =IF(OR($A14="",$K14=0),"",ROUND($J14*INDEX(研发人员工时分配表!$I$6:$I$245,$AA14)/$K14,2)) | P14: =IF(OR($A14="",$K14=0),"",ROUND($J14*INDEX(研发人员工时分配表!$J$6:$J$245,$AA14)/$K14,2)) | Q14: =IF(OR($A14="",$K14=0),"",ROUND($J14*INDEX(研发人员工时分配表!$K$6:$K$245,$AA14)/$K14,2)) | R14: =IF(OR($A14="",$K14=0),"",ROUND($J14*INDEX(研发人员工时分配表!$L$6:$L$245,$AA14)/$K14,2)) | S14: =IF(OR($A14="",$K14=0),"",ROUND($J14*INDEX(研发人员工时分配表!$M$6:$M$245,$AA14)/$K14,2)) | T14: =IF(OR($A14="",$K14=0),"",ROUND($J14*INDEX(研发人员工时分配表!$N$6:$N$245,$AA14)/$K14,2)) | U14: =IF(OR($A14="",$K14=0),"",ROUND($J14*INDEX(研发人员工时分配表!$O$6:$O$245,$AA14)/$K14,2)) | V14: =IF(OR($A14="",$K14=0),"",ROUND($J14*INDEX(研发人员工时分配表!$P$6:$P$245,$AA14)/$K14,2)) | W14: =IF(OR($A14="",$K14=0),"",ROUND($J14*INDEX(研发人员工时分配表!$Q$6:$Q$245,$AA14)/$K14,2)) | X14: =IF($A14="","",ROUND(SUM(N14:W14),2)) | Y14: =IF($A14="","",ROUND($J14-X14,2)) | Z14: =IF($A14="","",IF($AA14=0,"⚠ 工时分配表无此人当月记录",IF($AB14>1,"⚠ 工时分配表存在重复行","√ 正常"))) | AA14: =IF($A14="",0,IFERROR(MATCH($A14&"|"&$B14,研发人员工时分配表!$W$6:$W$245,0),0)) -> 0 | AB14: =IF($A14="",0,COUNTIFS(研发人员工时分配表!$A$6:$A$245,$A14,研发人员工时分配表!$B$6:$B$245,$B14)) -> 0
C15: =IF($B15="","",IFERROR(VLOOKUP($B15,人员名册!$B$4:$G$53,2,0)&"","名册中未登记")) | D15: =IF($B15="","",IFERROR(VLOOKUP($B15,人员名册!$B$4:$G$53,5,0)&"","")) | J15: =IF($A15="","",ROUND(SUM(E15:I15),2)) | K15: =IF(OR($A15="",$AA15=0),0,INDEX(研发人员工时分配表!$F$6:$F$245,$AA15)) -> 0 | L15: =IF(OR($A15="",$AA15=0),0,INDEX(研发人员工时分配表!$R$6:$R$245,$AA15)) -> 0 | M15: =IF(OR($A15="",$K15=0),"",$L15/$K15) | N15: =IF(OR($A15="",$K15=0),"",ROUND($J15*INDEX(研发人员工时分配表!$H$6:$H$245,$AA15)/$K15,2)) | O15: =IF(OR($A15="",$K15=0),"",ROUND($J15*INDEX(研发人员工时分配表!$I$6:$I$245,$AA15)/$K15,2)) | P15: =IF(OR($A15="",$K15=0),"",ROUND($J15*INDEX(研发人员工时分配表!$J$6:$J$245,$AA15)/$K15,2)) | Q15: =IF(OR($A15="",$K15=0),"",ROUND($J15*INDEX(研发人员工时分配表!$K$6:$K$245,$AA15)/$K15,2)) | R15: =IF(OR($A15="",$K15=0),"",ROUND($J15*INDEX(研发人员工时分配表!$L$6:$L$245,$AA15)/$K15,2)) | S15: =IF(OR($A15="",$K15=0),"",ROUND($J15*INDEX(研发人员工时分配表!$M$6:$M$245,$AA15)/$K15,2)) | T15: =IF(OR($A15="",$K15=0),"",ROUND($J15*INDEX(研发人员工时分配表!$N$6:$N$245,$AA15)/$K15,2)) | U15: =IF(OR($A15="",$K15=0),"",ROUND($J15*INDEX(研发人员工时分配表!$O$6:$O$245,$AA15)/$K15,2)) | V15: =IF(OR($A15="",$K15=0),"",ROUND($J15*INDEX(研发人员工时分配表!$P$6:$P$245,$AA15)/$K15,2)) | W15: =IF(OR($A15="",$K15=0),"",ROUND($J15*INDEX(研发人员工时分配表!$Q$6:$Q$245,$AA15)/$K15,2)) | X15: =IF($A15="","",ROUND(SUM(N15:W15),2)) | Y15: =IF($A15="","",ROUND($J15-X15,2)) | Z15: =IF($A15="","",IF($AA15=0,"⚠ 工时分配表无此人当月记录",IF($AB15>1,"⚠ 工时分配表存在重复行","√ 正常"))) | AA15: =IF($A15="",0,IFERROR(MATCH($A15&"|"&$B15,研发人员工时分配表!$W$6:$W$245,0),0)) -> 0 | AB15: =IF($A15="",0,COUNTIFS(研发人员工时分配表!$A$6:$A$245,$A15,研发人员工时分配表!$B$6:$B$245,$B15)) -> 0
C16: =IF($B16="","",IFERROR(VLOOKUP($B16,人员名册!$B$4:$G$53,2,0)&"","名册中未登记")) | D16: =IF($B16="","",IFERROR(VLOOKUP($B16,人员名册!$B$4:$G$53,5,0)&"","")) | J16: =IF($A16="","",ROUND(SUM(E16:I16),2)) | K16: =IF(OR($A16="",$AA16=0),0,INDEX(研发人员工时分配表!$F$6:$F$245,$AA16)) -> 0 | L16: =IF(OR($A16="",$AA16=0),0,INDEX(研发人员工时分配表!$R$6:$R$245,$AA16)) -> 0 | M16: =IF(OR($A16="",$K16=0),"",$L16/$K16) | N16: =IF(OR($A16="",$K16=0),"",ROUND($J16*INDEX(研发人员工时分配表!$H$6:$H$245,$AA16)/$K16,2)) | O16: =IF(OR($A16="",$K16=0),"",ROUND($J16*INDEX(研发人员工时分配表!$I$6:$I$245,$AA16)/$K16,2)) | P16: =IF(OR($A16="",$K16=0),"",ROUND($J16*INDEX(研发人员工时分配表!$J$6:$J$245,$AA16)/$K16,2)) | Q16: =IF(OR($A16="",$K16=0),"",ROUND($J16*INDEX(研发人员工时分配表!$K$6:$K$245,$AA16)/$K16,2)) | R16: =IF(OR($A16="",$K16=0),"",ROUND($J16*INDEX(研发人员工时分配表!$L$6:$L$245,$AA16)/$K16,2)) | S16: =IF(OR($A16="",$K16=0),"",ROUND($J16*INDEX(研发人员工时分配表!$M$6:$M$245,$AA16)/$K16,2)) | T16: =IF(OR($A16="",$K16=0),"",ROUND($J16*INDEX(研发人员工时分配表!$N$6:$N$245,$AA16)/$K16,2)) | U16: =IF(OR($A16="",$K16=0),"",ROUND($J16*INDEX(研发人员工时分配表!$O$6:$O$245,$AA16)/$K16,2)) | V16: =IF(OR($A16="",$K16=0),"",ROUND($J16*INDEX(研发人员工时分配表!$P$6:$P$245,$AA16)/$K16,2)) | W16: =IF(OR($A16="",$K16=0),"",ROUND($J16*INDEX(研发人员工时分配表!$Q$6:$Q$245,$AA16)/$K16,2)) | X16: =IF($A16="","",ROUND(SUM(N16:W16),2)) | Y16: =IF($A16="","",ROUND($J16-X16,2)) | Z16: =IF($A16="","",IF($AA16=0,"⚠ 工时分配表无此人当月记录",IF($AB16>1,"⚠ 工时分配表存在重复行","√ 正常"))) | AA16: =IF($A16="",0,IFERROR(MATCH($A16&"|"&$B16,研发人员工时分配表!$W$6:$W$245,0),0)) -> 0 | AB16: =IF($A16="",0,COUNTIFS(研发人员工时分配表!$A$6:$A$245,$A16,研发人员工时分配表!$B$6:$B$245,$B16)) -> 0
C17: =IF($B17="","",IFERROR(VLOOKUP($B17,人员名册!$B$4:$G$53,2,0)&"","名册中未登记")) | D17: =IF($B17="","",IFERROR(VLOOKUP($B17,人员名册!$B$4:$G$53,5,0)&"","")) | J17: =IF($A17="","",ROUND(SUM(E17:I17),2)) | K17: =IF(OR($A17="",$AA17=0),0,INDEX(研发人员工时分配表!$F$6:$F$245,$AA17)) -> 0 | L17: =IF(OR($A17="",$AA17=0),0,INDEX(研发人员工时分配表!$R$6:$R$245,$AA17)) -> 0 | M17: =IF(OR($A17="",$K17=0),"",$L17/$K17) | N17: =IF(OR($A17="",$K17=0),"",ROUND($J17*INDEX(研发人员工时分配表!$H$6:$H$245,$AA17)/$K17,2)) | O17: =IF(OR($A17="",$K17=0),"",ROUND($J17*INDEX(研发人员工时分配表!$I$6:$I$245,$AA17)/$K17,2)) | P17: =IF(OR($A17="",$K17=0),"",ROUND($J17*INDEX(研发人员工时分配表!$J$6:$J$245,$AA17)/$K17,2)) | Q17: =IF(OR($A17="",$K17=0),"",ROUND($J17*INDEX(研发人员工时分配表!$K$6:$K$245,$AA17)/$K17,2)) | R17: =IF(OR($A17="",$K17=0),"",ROUND($J17*INDEX(研发人员工时分配表!$L$6:$L$245,$AA17)/$K17,2)) | S17: =IF(OR($A17="",$K17=0),"",ROUND($J17*INDEX(研发人员工时分配表!$M$6:$M$245,$AA17)/$K17,2)) | T17: =IF(OR($A17="",$K17=0),"",ROUND($J17*INDEX(研发人员工时分配表!$N$6:$N$245,$AA17)/$K17,2)) | U17: =IF(OR($A17="",$K17=0),"",ROUND($J17*INDEX(研发人员工时分配表!$O$6:$O$245,$AA17)/$K17,2)) | V17: =IF(OR($A17="",$K17=0),"",ROUND($J17*INDEX(研发人员工时分配表!$P$6:$P$245,$AA17)/$K17,2)) | W17: =IF(OR($A17="",$K17=0),"",ROUND($J17*INDEX(研发人员工时分配表!$Q$6:$Q$245,$AA17)/$K17,2)) | X17: =IF($A17="","",ROUND(SUM(N17:W17),2)) | Y17: =IF($A17="","",ROUND($J17-X17,2)) | Z17: =IF($A17="","",IF($AA17=0,"⚠ 工时分配表无此人当月记录",IF($AB17>1,"⚠ 工时分配表存在重复行","√ 正常"))) | AA17: =IF($A17="",0,IFERROR(MATCH($A17&"|"&$B17,研发人员工时分配表!$W$6:$W$245,0),0)) -> 0 | AB17: =IF($A17="",0,COUNTIFS(研发人员工时分配表!$A$6:$A$245,$A17,研发人员工时分配表!$B$6:$B$245,$B17)) -> 0
C18: =IF($B18="","",IFERROR(VLOOKUP($B18,人员名册!$B$4:$G$53,2,0)&"","名册中未登记")) | D18: =IF($B18="","",IFERROR(VLOOKUP($B18,人员名册!$B$4:$G$53,5,0)&"","")) | J18: =IF($A18="","",ROUND(SUM(E18:I18),2)) | K18: =IF(OR($A18="",$AA18=0),0,INDEX(研发人员工时分配表!$F$6:$F$245,$AA18)) -> 0 | L18: =IF(OR($A18="",$AA18=0),0,INDEX(研发人员工时分配表!$R$6:$R$245,$AA18)) -> 0 | M18: =IF(OR($A18="",$K18=0),"",$L18/$K18) | N18: =IF(OR($A18="",$K18=0),"",ROUND($J18*INDEX(研发人员工时分配表!$H$6:$H$245,$AA18)/$K18,2)) | O18: =IF(OR($A18="",$K18=0),"",ROUND($J18*INDEX(研发人员工时分配表!$I$6:$I$245,$AA18)/$K18,2)) | P18: =IF(OR($A18="",$K18=0),"",ROUND($J18*INDEX(研发人员工时分配表!$J$6:$J$245,$AA18)/$K18,2)) | Q18: =IF(OR($A18="",$K18=0),"",ROUND($J18*INDEX(研发人员工时分配表!$K$6:$K$245,$AA18)/$K18,2)) | R18: =IF(OR($A18="",$K18=0),"",ROUND($J18*INDEX(研发人员工时分配表!$L$6:$L$245,$AA18)/$K18,2)) | S18: =IF(OR($A18="",$K18=0),"",ROUND($J18*INDEX(研发人员工时分配表!$M$6:$M$245,$AA18)/$K18,2)) | T18: =IF(OR($A18="",$K18=0),"",ROUND($J18*INDEX(研发人员工时分配表!$N$6:$N$245,$AA18)/$K18,2)) | U18: =IF(OR($A18="",$K18=0),"",ROUND($J18*INDEX(研发人员工时分配表!$O$6:$O$245,$AA18)/$K18,2)) | V18: =IF(OR($A18="",$K18=0),"",ROUND($J18*INDEX(研发人员工时分配表!$P$6:$P$245,$AA18)/$K18,2)) | W18: =IF(OR($A18="",$K18=0),"",ROUND($J18*INDEX(研发人员工时分配表!$Q$6:$Q$245,$AA18)/$K18,2)) | X18: =IF($A18="","",ROUND(SUM(N18:W18),2)) | Y18: =IF($A18="","",ROUND($J18-X18,2)) | Z18: =IF($A18="","",IF($AA18=0,"⚠ 工时分配表无此人当月记录",IF($AB18>1,"⚠ 工时分配表存在重复行","√ 正常"))) | AA18: =IF($A18="",0,IFERROR(MATCH($A18&"|"&$B18,研发人员工时分配表!$W$6:$W$245,0),0)) -> 0 | AB18: =IF($A18="",0,COUNTIFS(研发人员工时分配表!$A$6:$A$245,$A18,研发人员工时分配表!$B$6:$B$245,$B18)) -> 0
C19: =IF($B19="","",IFERROR(VLOOKUP($B19,人员名册!$B$4:$G$53,2,0)&"","名册中未登记")) | D19: =IF($B19="","",IFERROR(VLOOKUP($B19,人员名册!$B$4:$G$53,5,0)&"","")) | J19: =IF($A19="","",ROUND(SUM(E19:I19),2)) | K19: =IF(OR($A19="",$AA19=0),0,INDEX(研发人员工时分配表!$F$6:$F$245,$AA19)) -> 0 | L19: =IF(OR($A19="",$AA19=0),0,INDEX(研发人员工时分配表!$R$6:$R$245,$AA19)) -> 0 | M19: =IF(OR($A19="",$K19=0),"",$L19/$K19) | N19: =IF(OR($A19="",$K19=0),"",ROUND($J19*INDEX(研发人员工时分配表!$H$6:$H$245,$AA19)/$K19,2)) | O19: =IF(OR($A19="",$K19=0),"",ROUND($J19*INDEX(研发人员工时分配表!$I$6:$I$245,$AA19)/$K19,2)) | P19: =IF(OR($A19="",$K19=0),"",ROUND($J19*INDEX(研发人员工时分配表!$J$6:$J$245,$AA19)/$K19,2)) | Q19: =IF(OR($A19="",$K19=0),"",ROUND($J19*INDEX(研发人员工时分配表!$K$6:$K$245,$AA19)/$K19,2)) | R19: =IF(OR($A19="",$K19=0),"",ROUND($J19*INDEX(研发人员工时分配表!$L$6:$L$245,$AA19)/$K19,2)) | S19: =IF(OR($A19="",$K19=0),"",ROUND($J19*INDEX(研发人员工时分配表!$M$6:$M$245,$AA19)/$K19,2)) | T19: =IF(OR($A19="",$K19=0),"",ROUND($J19*INDEX(研发人员工时分配表!$N$6:$N$245,$AA19)/$K19,2)) | U19: =IF(OR($A19="",$K19=0),"",ROUND($J19*INDEX(研发人员工时分配表!$O$6:$O$245,$AA19)/$K19,2)) | V19: =IF(OR($A19="",$K19=0),"",ROUND($J19*INDEX(研发人员工时分配表!$P$6:$P$245,$AA19)/$K19,2)) | W19: =IF(OR($A19="",$K19=0),"",ROUND($J19*INDEX(研发人员工时分配表!$Q$6:$Q$245,$AA19)/$K19,2)) | X19: =IF($A19="","",ROUND(SUM(N19:W19),2)) | Y19: =IF($A19="","",ROUND($J19-X19,2)) | Z19: =IF($A19="","",IF($AA19=0,"⚠ 工时分配表无此人当月记录",IF($AB19>1,"⚠ 工时分配表存在重复行","√ 正常"))) | AA19: =IF($A19="",0,IFERROR(MATCH($A19&"|"&$B19,研发人员工时分配表!$W$6:$W$245,0),0)) -> 0 | AB19: =IF($A19="",0,COUNTIFS(研发人员工时分配表!$A$6:$A$245,$A19,研发人员工时分配表!$B$6:$B$245,$B19)) -> 0
C20: =IF($B20="","",IFERROR(VLOOKUP($B20,人员名册!$B$4:$G$53,2,0)&"","名册中未登记")) | D20: =IF($B20="","",IFERROR(VLOOKUP($B20,人员名册!$B$4:$G$53,5,0)&"","")) | J20: =IF($A20="","",ROUND(SUM(E20:I20),2)) | K20: =IF(OR($A20="",$AA20=0),0,INDEX(研发人员工时分配表!$F$6:$F$245,$AA20)) -> 0 | L20: =IF(OR($A20="",$AA20=0),0,INDEX(研发人员工时分配表!$R$6:$R$245,$AA20)) -> 0 | M20: =IF(OR($A20="",$K20=0),"",$L20/$K20) | N20: =IF(OR($A20="",$K20=0),"",ROUND($J20*INDEX(研发人员工时分配表!$H$6:$H$245,$AA20)/$K20,2)) | O20: =IF(OR($A20="",$K20=0),"",ROUND($J20*INDEX(研发人员工时分配表!$I$6:$I$245,$AA20)/$K20,2)) | P20: =IF(OR($A20="",$K20=0),"",ROUND($J20*INDEX(研发人员工时分配表!$J$6:$J$245,$AA20)/$K20,2)) | Q20: =IF(OR($A20="",$K20=0),"",ROUND($J20*INDEX(研发人员工时分配表!$K$6:$K$245,$AA20)/$K20,2)) | R20: =IF(OR($A20="",$K20=0),"",ROUND($J20*INDEX(研发人员工时分配表!$L$6:$L$245,$AA20)/$K20,2)) | S20: =IF(OR($A20="",$K20=0),"",ROUND($J20*INDEX(研发人员工时分配表!$M$6:$M$245,$AA20)/$K20,2)) | T20: =IF(OR($A20="",$K20=0),"",ROUND($J20*INDEX(研发人员工时分配表!$N$6:$N$245,$AA20)/$K20,2)) | U20: =IF(OR($A20="",$K20=0),"",ROUND($J20*INDEX(研发人员工时分配表!$O$6:$O$245,$AA20)/$K20,2)) | V20: =IF(OR($A20="",$K20=0),"",ROUND($J20*INDEX(研发人员工时分配表!$P$6:$P$245,$AA20)/$K20,2)) | W20: =IF(OR($A20="",$K20=0),"",ROUND($J20*INDEX(研发人员工时分配表!$Q$6:$Q$245,$AA20)/$K20,2)) | X20: =IF($A20="","",ROUND(SUM(N20:W20),2)) | Y20: =IF($A20="","",ROUND($J20-X20,2)) | Z20: =IF($A20="","",IF($AA20=0,"⚠ 工时分配表无此人当月记录",IF($AB20>1,"⚠ 工时分配表存在重复行","√ 正常"))) | AA20: =IF($A20="",0,IFERROR(MATCH($A20&"|"&$B20,研发人员工时分配表!$W$6:$W$245,0),0)) -> 0 | AB20: =IF($A20="",0,COUNTIFS(研发人员工时分配表!$A$6:$A$245,$A20,研发人员工时分配表!$B$6:$B$245,$B20)) -> 0
... C245: =IF($B245="","",IFERROR(VLOOKUP($B245,人员名册!$B$4:$G$53,2,0)&"","名册中未登记")) | D245: =IF($B245="","",IFERROR(VLOOKUP($B245,人员名册!$B$4:$G$53,5,0)&"","")) | J245: =IF($A245="","",ROUND(SUM(E245:I245),2)) | K245: =IF(OR($A245="",$AA245=0),0,INDEX(研发人员工时分配表!$F$6:$F$245,$AA245)) -> 0 | L245: =IF(OR($A245="",$AA245=0),0,INDEX(研发人员工时分配表!$R$6:$R$245,$AA245)) -> 0 | M245: =IF(OR($A245="",$K245=0),"",$L245/$K245) | N245: =IF(OR($A245="",$K245=0),"",ROUND($J245*INDEX(研发人员工时分配表!$H$6:$H$245,$AA245)/$K245,2)) | O245: =IF(OR($A245="",$K245=0),"",ROUND($J245*INDEX(研发人员工时分配表!$I$6:$I$245,$AA245)/$K245,2)) | P245: =IF(OR($A245="",$K245=0),"",ROUND($J245*INDEX(研发人员工时分配表!$J$6:$J$245,$AA245)/$K245,2)) | Q245: =IF(OR($A245="",$K245=0),"",ROUND($J245*INDEX(研发人员工时分配表!$K$6:$K$245,$AA245)/$K245,2)) | R245: =IF(OR($A245="",$K245=0),"",ROUND($J245*INDEX(研发人员工时分配表!$L$6:$L$245,$AA245)/$K245,2)) | S245: =IF(OR($A245="",$K245=0),"",ROUND($J245*INDEX(研发人员工时分配表!$M$6:$M$245,$AA245)/$K245,2)) | T245: =IF(OR($A245="",$K245=0),"",ROUND($J245*INDEX(研发人员工时分配表!$N$6:$N$245,$AA245)/$K245,2)) | U245: =IF(OR($A245="",$K245=0),"",ROUND($J245*INDEX(研发人员工时分配表!$O$6:$O$245,$AA245)/$K245,2)) | V245: =IF(OR($A245="",$K245=0),"",ROUND($J245*INDEX(研发人员工时分配表!$P$6:$P$245,$AA245)/$K245,2)) | W245: =IF(OR($A245="",$K245=0),"",ROUND($J245*INDEX(研发人员工时分配表!$Q$6:$Q$245,$AA245)/$K245,2)) | X245: =IF($A245="","",ROUND(SUM(N245:W245),2)) | Y245: =IF($A245="","",ROUND($J245-X245,2)) | Z245: =IF($A245="","",IF($AA245=0,"⚠ 工时分配表无此人当月记录",IF($AB245>1,"⚠ 工时分配表存在重复行","√ 正常"))) | AA245: =IF($A245="",0,IFERROR(MATCH($A245&"|"&$B245,研发人员工时分配表!$W$6:$W$245,0),0)) -> 0 | AB245: =IF($A245="",0,COUNTIFS(研发人员工时分配表!$A$6:$A$245,$A245,研发人员工时分配表!$B$6:$B$245,$B245)) -> 0

Sheet 仪器设备工时分配表
A1: 公司 LOGO （选中本区域插入图片） | C1: =IF(使用说明!$B$2="","",使用说明!$B$2&" ")&"七、《仪器、设备工时分配表》（研发部门按月填报，2026年度）" -> 七、《仪器、设备工时分配表》（研发部门按月填报，2026年度）
A2: 录入说明：①由研发部门/设备管理员按月填报，依据经签批的《附表2-仪器设备工时分配表(签批用)》录入；②“当月总运行(使用)工时”为该设备当月实际运行总工时（生产+研发），是分摊的分母，须与设备点检表、生产报工记录一致；③研发专用设备记录全额运行工时（非研发使用工时填0），研发生产共用设备按实际使用分别记录；④本表只登记“设备”类资产，无形资产不在此填报（其摊销在【无形资产费用分配表】中按人工工时比例分摊）；⑤同一设备当月只填一行；⑥“工时校验”须为0。
A3: 年月 (YYYY-MM) | B3: 资产编号 | C3: 资产名称 | D3: 资产类别 | E3: 所属工序 | F3: 当月总运行 (使用)工时 | G3: 非研发使用工时 (生产及其他) | H3: 各研发项目使用工时（小时） | R3: 研发使用 工时合计 | S3: 工时校验 (须为0) | T3: 研发使用 占比 | U3: 备注
H4: =项目清单!$B$4 -> RD01 | I4: =项目清单!$B$5 -> RD02 | J4: =项目清单!$B$6 -> RD03 | K4: =项目清单!$B$7 -> RD04 | L4: =项目清单!$B$8 -> RD05 | M4: =项目清单!$B$9 -> RD06 | N4: =项目清单!$B$10 -> RD07 | O4: =项目清单!$B$11 -> RD08 | P4: =项目清单!$B$12 -> RD09 | Q4: =项目清单!$B$13 -> RD10
H5: =IF(H4="","",IFERROR(VLOOKUP(H4,项目清单!$B$4:$C$13,2,0)&"","")) -> 高回弹低压缩永久变形3C用聚氨酯泡棉开发 | I5: =IF(I4="","",IFERROR(VLOOKUP(I4,项目清单!$B$4:$C$13,2,0)&"","")) -> 动力电池模组用高阻燃缓冲泡棉研发 | J5: =IF(J4="","",IFERROR(VLOOKUP(J4,项目清单!$B$4:$C$13,2,0)&"","")) -> 泡棉与PET基材无溶剂贴合工艺开发 | K5: =IF(K4="","",IFERROR(VLOOKUP(K4,项目清单!$B$4:$C$13,2,0)&"","")) -> 超薄泡棉高精度分切及毛边控制技术研究 | L5: =IF(L4="","",IFERROR(VLOOKUP(L4,项目清单!$B$4:$C$13,2,0)&"","")) -> 新能源汽车电池包用导热缓冲复合材料开发 | M5: =IF(M4="","",IFERROR(VLOOKUP(M4,项目清单!$B$4:$C$13,2,0)&"","")) -> 3C电子用超薄黑色遮光泡棉制备技术 | N5: =IF(N4="","",IFERROR(VLOOKUP(N4,项目清单!$B$4:$C$13,2,0)&"","")) -> 环保型水性胶泡棉贴合技术开发 | O5: =IF(O4="","",IFERROR(VLOOKUP(O4,项目清单!$B$4:$C$13,2,0)&"","")) -> 泡棉模切自动化在线检测技术研究 | ... Q5: =IF(Q4="","",IFERROR(VLOOKUP(Q4,项目清单!$B$4:$C$13,2,0)&"","")) | V5: 匹配主键(勿删)
A6: 2026-09 | B6: SB001 | C6: =IF($B6="","",IFERROR(VLOOKUP($B6,资产台账!$B$4:$N$53,2,0)&"","台账中未登记")) -> （示例）连续发泡生产线 | D6: =IF($B6="","",IFERROR(VLOOKUP($B6,资产台账!$B$4:$N$53,3,0)&"","")) -> 设备 | E6: =IF($B6="","",IFERROR(VLOOKUP($B6,资产台账!$B$4:$N$53,5,0)&"","")) -> 发泡成型 | F6: 320 | G6: 260 | H6: 40 | I6: 20 | R6: =IF($A6="","",SUM(H6:Q6)) -> 60 | S6: =IF($A6="","",ROUND($F6-$G6-$R6,2)) -> 0 | T6: =IF(OR($A6="",$F6=0),"",$R6/$F6) -> 0.1875 | U6: ★示例行，请删除 | V6: =IF($A6="","",$A6&"|"&$B6) -> 2026-09|SB001
A7: 2026-09 | B7: SB002 | C7: =IF($B7="","",IFERROR(VLOOKUP($B7,资产台账!$B$4:$N$53,2,0)&"","台账中未登记")) -> （示例）自动贴合复合机 | D7: =IF($B7="","",IFERROR(VLOOKUP($B7,资产台账!$B$4:$N$53,3,0)&"","")) -> 设备 | E7: =IF($B7="","",IFERROR(VLOOKUP($B7,资产台账!$B$4:$N$53,5,0)&"","")) -> PET贴合 | F7: 300 | G7: 240 | J7: 40 | L7: 20 | R7: =IF($A7="","",SUM(H7:Q7)) -> 60 | S7: =IF($A7="","",ROUND($F7-$G7-$R7,2)) -> 0 | T7: =IF(OR($A7="",$F7=0),"",$R7/$F7) -> 0.2 | U7: ★示例行，请删除 | V7: =IF($A7="","",$A7&"|"&$B7) -> 2026-09|SB002
A8: 2026-09 | B8: SB003 | C8: =IF($B8="","",IFERROR(VLOOKUP($B8,资产台账!$B$4:$N$53,2,0)&"","台账中未登记")) -> （示例）高精度分切机 | D8: =IF($B8="","",IFERROR(VLOOKUP($B8,资产台账!$B$4:$N$53,3,0)&"","")) -> 设备 | E8: =IF($B8="","",IFERROR(VLOOKUP($B8,资产台账!$B$4:$N$53,5,0)&"","")) -> 分切 | F8: 280 | G8: 250 | K8: 30 | R8: =IF($A8="","",SUM(H8:Q8)) -> 30 | S8: =IF($A8="","",ROUND($F8-$G8-$R8,2)) -> 0 | T8: =IF(OR($A8="",$F8=0),"",$R8/$F8) -> 0.10714286 | U8: ★示例行，请删除 | V8: =IF($A8="","",$A8&"|"&$B8) -> 2026-09|SB003
A9: 2026-09 | B9: SB005 | C9: =IF($B9="","",IFERROR(VLOOKUP($B9,资产台账!$B$4:$N$53,2,0)&"","台账中未登记")) -> （示例）租入激光模切设备 | D9: =IF($B9="","",IFERROR(VLOOKUP($B9,资产台账!$B$4:$N$53,3,0)&"","")) -> 设备 | E9: =IF($B9="","",IFERROR(VLOOKUP($B9,资产台账!$B$4:$N$53,5,0)&"","")) -> 模切 | F9: 120 | G9: 0 | I9: 70 | L9: 50 | R9: =IF($A9="","",SUM(H9:Q9)) -> 120 | S9: =IF($A9="","",ROUND($F9-$G9-$R9,2)) -> 0 | T9: =IF(OR($A9="",$F9=0),"",$R9/$F9) -> 1 | U9: ★示例行，请删除 | V9: =IF($A9="","",$A9&"|"&$B9) -> 2026-09|SB005
C10: =IF($B10="","",IFERROR(VLOOKUP($B10,资产台账!$B$4:$N$53,2,0)&"","台账中未登记")) | D10: =IF($B10="","",IFERROR(VLOOKUP($B10,资产台账!$B$4:$N$53,3,0)&"","")) | E10: =IF($B10="","",IFERROR(VLOOKUP($B10,资产台账!$B$4:$N$53,5,0)&"","")) | R10: =IF($A10="","",SUM(H10:Q10)) | S10: =IF($A10="","",ROUND($F10-$G10-$R10,2)) | T10: =IF(OR($A10="",$F10=0),"",$R10/$F10) | V10: =IF($A10="","",$A10&"|"&$B10)
C11: =IF($B11="","",IFERROR(VLOOKUP($B11,资产台账!$B$4:$N$53,2,0)&"","台账中未登记")) | D11: =IF($B11="","",IFERROR(VLOOKUP($B11,资产台账!$B$4:$N$53,3,0)&"","")) | E11: =IF($B11="","",IFERROR(VLOOKUP($B11,资产台账!$B$4:$N$53,5,0)&"","")) | R11: =IF($A11="","",SUM(H11:Q11)) | S11: =IF($A11="","",ROUND($F11-$G11-$R11,2)) | T11: =IF(OR($A11="",$F11=0),"",$R11/$F11) | V11: =IF($A11="","",$A11&"|"&$B11)
C12: =IF($B12="","",IFERROR(VLOOKUP($B12,资产台账!$B$4:$N$53,2,0)&"","台账中未登记")) | D12: =IF($B12="","",IFERROR(VLOOKUP($B12,资产台账!$B$4:$N$53,3,0)&"","")) | E12: =IF($B12="","",IFERROR(VLOOKUP($B12,资产台账!$B$4:$N$53,5,0)&"","")) | R12: =IF($A12="","",SUM(H12:Q12)) | S12: =IF($A12="","",ROUND($F12-$G12-$R12,2)) | T12: =IF(OR($A12="",$F12=0),"",$R12/$F12) | V12: =IF($A12="","",$A12&"|"&$B12)
C13: =IF($B13="","",IFERROR(VLOOKUP($B13,资产台账!$B$4:$N$53,2,0)&"","台账中未登记")) | D13: =IF($B13="","",IFERROR(VLOOKUP($B13,资产台账!$B$4:$N$53,3,0)&"","")) | E13: =IF($B13="","",IFERROR(VLOOKUP($B13,资产台账!$B$4:$N$53,5,0)&"","")) | R13: =IF($A13="","",SUM(H13:Q13)) | S13: =IF($A13="","",ROUND($F13-$G13-$R13,2)) | T13: =IF(OR($A13="",$F13=0),"",$R13/$F13) | V13: =IF($A13="","",$A13&"|"&$B13)
C14: =IF($B14="","",IFERROR(VLOOKUP($B14,资产台账!$B$4:$N$53,2,0)&"","台账中未登记")) | D14: =IF($B14="","",IFERROR(VLOOKUP($B14,资产台账!$B$4:$N$53,3,0)&"","")) | E14: =IF($B14="","",IFERROR(VLOOKUP($B14,资产台账!$B$4:$N$53,5,0)&"","")) | R14: =IF($A14="","",SUM(H14:Q14)) | S14: =IF($A14="","",ROUND($F14-$G14-$R14,2)) | T14: =IF(OR($A14="",$F14=0),"",$R14/$F14) | V14: =IF($A14="","",$A14&"|"&$B14)
C15: =IF($B15="","",IFERROR(VLOOKUP($B15,资产台账!$B$4:$N$53,2,0)&"","台账中未登记")) | D15: =IF($B15="","",IFERROR(VLOOKUP($B15,资产台账!$B$4:$N$53,3,0)&"","")) | E15: =IF($B15="","",IFERROR(VLOOKUP($B15,资产台账!$B$4:$N$53,5,0)&"","")) | R15: =IF($A15="","",SUM(H15:Q15)) | S15: =IF($A15="","",ROUND($F15-$G15-$R15,2)) | T15: =IF(OR($A15="",$F15=0),"",$R15/$F15) | V15: =IF($A15="","",$A15&"|"&$B15)
C16: =IF($B16="","",IFERROR(VLOOKUP($B16,资产台账!$B$4:$N$53,2,0)&"","台账中未登记")) | D16: =IF($B16="","",IFERROR(VLOOKUP($B16,资产台账!$B$4:$N$53,3,0)&"","")) | E16: =IF($B16="","",IFERROR(VLOOKUP($B16,资产台账!$B$4:$N$53,5,0)&"","")) | R16: =IF($A16="","",SUM(H16:Q16)) | S16: =IF($A16="","",ROUND($F16-$G16-$R16,2)) | T16: =IF(OR($A16="",$F16=0),"",$R16/$F16) | V16: =IF($A16="","",$A16&"|"&$B16)
C17: =IF($B17="","",IFERROR(VLOOKUP($B17,资产台账!$B$4:$N$53,2,0)&"","台账中未登记")) | D17: =IF($B17="","",IFERROR(VLOOKUP($B17,资产台账!$B$4:$N$53,3,0)&"","")) | E17: =IF($B17="","",IFERROR(VLOOKUP($B17,资产台账!$B$4:$N$53,5,0)&"","")) | R17: =IF($A17="","",SUM(H17:Q17)) | S17: =IF($A17="","",ROUND($F17-$G17-$R17,2)) | T17: =IF(OR($A17="",$F17=0),"",$R17/$F17) | V17: =IF($A17="","",$A17&"|"&$B17)
C18: =IF($B18="","",IFERROR(VLOOKUP($B18,资产台账!$B$4:$N$53,2,0)&"","台账中未登记")) | D18: =IF($B18="","",IFERROR(VLOOKUP($B18,资产台账!$B$4:$N$53,3,0)&"","")) | E18: =IF($B18="","",IFERROR(VLOOKUP($B18,资产台账!$B$4:$N$53,5,0)&"","")) | R18: =IF($A18="","",SUM(H18:Q18)) | S18: =IF($A18="","",ROUND($F18-$G18-$R18,2)) | T18: =IF(OR($A18="",$F18=0),"",$R18/$F18) | V18: =IF($A18="","",$A18&"|"&$B18)
C19: =IF($B19="","",IFERROR(VLOOKUP($B19,资产台账!$B$4:$N$53,2,0)&"","台账中未登记")) | D19: =IF($B19="","",IFERROR(VLOOKUP($B19,资产台账!$B$4:$N$53,3,0)&"","")) | E19: =IF($B19="","",IFERROR(VLOOKUP($B19,资产台账!$B$4:$N$53,5,0)&"","")) | R19: =IF($A19="","",SUM(H19:Q19)) | S19: =IF($A19="","",ROUND($F19-$G19-$R19,2)) | T19: =IF(OR($A19="",$F19=0),"",$R19/$F19) | V19: =IF($A19="","",$A19&"|"&$B19)
C20: =IF($B20="","",IFERROR(VLOOKUP($B20,资产台账!$B$4:$N$53,2,0)&"","台账中未登记")) | D20: =IF($B20="","",IFERROR(VLOOKUP($B20,资产台账!$B$4:$N$53,3,0)&"","")) | E20: =IF($B20="","",IFERROR(VLOOKUP($B20,资产台账!$B$4:$N$53,5,0)&"","")) | R20: =IF($A20="","",SUM(H20:Q20)) | S20: =IF($A20="","",ROUND($F20-$G20-$R20,2)) | T20: =IF(OR($A20="",$F20=0),"",$R20/$F20) | V20: =IF($A20="","",$A20&"|"&$B20)
C21: =IF($B21="","",IFERROR(VLOOKUP($B21,资产台账!$B$4:$N$53,2,0)&"","台账中未登记")) | D21: =IF($B21="","",IFERROR(VLOOKUP($B21,资产台账!$B$4:$N$53,3,0)&"","")) | E21: =IF($B21="","",IFERROR(VLOOKUP($B21,资产台账!$B$4:$N$53,5,0)&"","")) | R21: =IF($A21="","",SUM(H21:Q21)) | S21: =IF($A21="","",ROUND($F21-$G21-$R21,2)) | T21: =IF(OR($A21="",$F21=0),"",$R21/$F21) | V21: =IF($A21="","",$A21&"|"&$B21)
... C245: =IF($B245="","",IFERROR(VLOOKUP($B245,资产台账!$B$4:$N$53,2,0)&"","台账中未登记")) | D245: =IF($B245="","",IFERROR(VLOOKUP($B245,资产台账!$B$4:$N$53,3,0)&"","")) | E245: =IF($B245="","",IFERROR(VLOOKUP($B245,资产台账!$B$4:$N$53,5,0)&"","")) | R245: =IF($A245="","",SUM(H245:Q245)) | S245: =IF($A245="","",ROUND($F245-$G245-$R245,2)) | T245: =IF(OR($A245="",$F245=0),"",$R245/$F245) | V245: =IF($A245="","",$A245&"|"&$B245)

Sheet 仪器设备工时费用分配表
A1: 公司 LOGO （选中本区域插入图片） | C1: =IF(使用说明!$B$2="","",使用说明!$B$2&" ")&"八、《仪器、设备工时费用分配表》（财务按月按项目核算、按年汇总，2026年度）" -> 八、《仪器、设备工时费用分配表》（财务按月按项目核算、按年汇总，2026年度）
A2: 计算依据：当月某项目应分摊设备费 = 该设备当月折旧额（或租赁费）×（该项目使用工时 ÷ 该设备当月总运行工时）。数据来源：折旧数据源自【月度固定资产折旧明细表】。录入说明：只需录入 A、B 两列（年月、资产编号，仅登记“设备”类资产）；F列“当月折旧/租赁额”自动取自【资产台账】，当月实际计提数不同时可直接覆盖填写，但须与折旧明细表一致。请关注末列“数据校验”。
A3: 年月 (YYYY-MM) | B3: 资产编号 | C3: 资产名称 | D3: 资产类别 | E3: 费用类型 | F3: 当月折旧/ 租赁额(元) | G3: 当月总运行 (使用)工时 | H3: 研发使用 工时合计 | I3: 研发使用占比 (分摊系数) | J3: 各研发项目分摊折旧/租赁费用（元） | T3: 研发费用 小计(元) | U3: 计入生产成本的 折旧费用(元) | V3: 数据校验
J4: =项目清单!$B$4 -> RD01 | K4: =项目清单!$B$5 -> RD02 | L4: =项目清单!$B$6 -> RD03 | M4: =项目清单!$B$7 -> RD04 | N4: =项目清单!$B$8 -> RD05 | O4: =项目清单!$B$9 -> RD06 | P4: =项目清单!$B$10 -> RD07 | Q4: =项目清单!$B$11 -> RD08 | R4: =项目清单!$B$12 -> RD09 | S4: =项目清单!$B$13 -> RD10
J5: =IF(J4="","",IFERROR(VLOOKUP(J4,项目清单!$B$4:$C$13,2,0)&"","")) -> 高回弹低压缩永久变形3C用聚氨酯泡棉开发 | K5: =IF(K4="","",IFERROR(VLOOKUP(K4,项目清单!$B$4:$C$13,2,0)&"","")) -> 动力电池模组用高阻燃缓冲泡棉研发 | L5: =IF(L4="","",IFERROR(VLOOKUP(L4,项目清单!$B$4:$C$13,2,0)&"","")) -> 泡棉与PET基材无溶剂贴合工艺开发 | M5: =IF(M4="","",IFERROR(VLOOKUP(M4,项目清单!$B$4:$C$13,2,0)&"","")) -> 超薄泡棉高精度分切及毛边控制技术研究 | N5: =IF(N4="","",IFERROR(VLOOKUP(N4,项目清单!$B$4:$C$13,2,0)&"","")) -> 新能源汽车电池包用导热缓冲复合材料开发 | O5: =IF(O4="","",IFERROR(VLOOKUP(O4,项目清单!$B$4:$C$13,2,0)&"","")) -> 3C电子用超薄黑色遮光泡棉制备技术 | P5: =IF(P4="","",IFERROR(VLOOKUP(P4,项目清单!$B$4:$C$13,2,0)&"","")) -> 环保型水性胶泡棉贴合技术开发 | Q5: =IF(Q4="","",IFERROR(VLOOKUP(Q4,项目清单!$B$4:$C$13,2,0)&"","")) -> 泡棉模切自动化在线检测技术研究 | ... S5: =IF(S4="","",IFERROR(VLOOKUP(S4,项目清单!$B$4:$C$13,2,0)&"","")) | W5: 匹配行号(勿删) | X5: 重复计数(勿删)
A6: 2026-09 | B6: SB001 | C6: =IF($B6="","",IFERROR(VLOOKUP($B6,资产台账!$B$4:$N$53,2,0)&"","台账中未登记")) -> （示例）连续发泡生产线 | D6: =IF($B6="","",IFERROR(VLOOKUP($B6,资产台账!$B$4:$N$53,3,0)&"","")) -> 设备 | E6: =IF($B6="","",IFERROR(VLOOKUP($B6,资产台账!$B$4:$N$53,10,0)&"","")) -> 折旧 | F6: =IF($B6="","",IFERROR(VLOOKUP($B6,资产台账!$B$4:$N$53,9,0),0)) -> 15000 | G6: =IF(OR($A6="",$W6=0),0,INDEX(仪器设备工时分配表!$F$6:$F$245,$W6)) -> 320 | H6: =IF(OR($A6="",$W6=0),0,INDEX(仪器设备工时分配表!$R$6:$R$245,$W6)) -> 60 | I6: =IF(OR($A6="",$G6=0),"",$H6/$G6) -> 0.1875 | J6: =IF(OR($A6="",$G6=0),"",ROUND($F6*INDEX(仪器设备工时分配表!$H$6:$H$245,$W6)/$G6,2)) -> 1875 | K6: =IF(OR($A6="",$G6=0),"",ROUND($F6*INDEX(仪器设备工时分配表!$I$6:$I$245,$W6)/$G6,2)) -> 937.5 | L6: =IF(OR($A6="",$G6=0),"",ROUND($F6*INDEX(仪器设备工时分配表!$J$6:$J$245,$W6)/$G6,2)) -> 0 | M6: =IF(OR($A6="",$G6=0),"",ROUND($F6*INDEX(仪器设备工时分配表!$K$6:$K$245,$W6)/$G6,2)) -> 0 | N6: =IF(OR($A6="",$G6=0),"",ROUND($F6*INDEX(仪器设备工时分配表!$L$6:$L$245,$W6)/$G6,2)) -> 0 | O6: =IF(OR($A6="",$G6=0),"",ROUND($F6*INDEX(仪器设备工时分配表!$M$6:$M$245,$W6)/$G6,2)) -> 0 | P6: =IF(OR($A6="",$G6=0),"",ROUND($F6*INDEX(仪器设备工时分配表!$N$6:$N$245,$W6)/$G6,2)) -> 0 | Q6: =IF(OR($A6="",$G6=0),"",ROUND($F6*INDEX(仪器设备工时分配表!$O$6:$O$245,$W6)/$G6,2)) -> 0 | R6: =IF(OR($A6="",$G6=0),"",ROUND($F6*INDEX(仪器设备工时分配表!$P$6:$P$245,$W6)/$G6,2)) -> 0 | S6: =IF(OR($A6="",$G6=0),"",ROUND($F6*INDEX(仪器设备工时分配表!$Q$6:$Q$245,$W6)/$G6,2)) -> 0 | T6: =IF($A6="","",ROUND(SUM(J6:S6),2)) -> 2812.5 | U6: =IF($A6="","",ROUND($F6-T6,2)) -> 12187.5 | V6: =IF($A6="","",IF($D6="无形资产","⚠ 无形资产请在无形资产费用分配表登记",IF($W6=0,"⚠ 工时分配表无此资产当月记录",IF($X6>1,"⚠ 工时分配表存在重复行","√ 正常")))) -> √ 正常 | W6: =IF($A6="",0,IFERROR(MATCH($A6&"|"&$B6,仪器设备工时分配表!$V$6:$V$245,0),0)) -> 1 | X6: =IF($A6="",0,COUNTIFS(仪器设备工时分配表!$A$6:$A$245,$A6,仪器设备工时分配表!$B$6:$B$245,$B6)) -> 1
A7: 2026-09 | B7: SB002 | C7: =IF($B7="","",IFERROR(VLOOKUP($B7,资产台账!$B$4:$N$53,2,0)&"","台账中未登记")) -> （示例）自动贴合复合机 | D7: =IF($B7="","",IFERROR(VLOOKUP($B7,资产台账!$B$4:$N$53,3,0)&"","")) -> 设备 | E7: =IF($B7="","",IFERROR(VLOOKUP($B7,资产台账!$B$4:$N$53,10,0)&"","")) -> 折旧 | F7: =IF($B7="","",IFERROR(VLOOKUP($B7,资产台账!$B$4:$N$53,9,0),0)) -> 8000 | G7: =IF(OR($A7="",$W7=0),0,INDEX(仪器设备工时分配表!$F$6:$F$245,$W7)) -> 300 | H7: =IF(OR($A7="",$W7=0),0,INDEX(仪器设备工时分配表!$R$6:$R$245,$W7)) -> 60 | I7: =IF(OR($A7="",$G7=0),"",$H7/$G7) -> 0.2 | J7: =IF(OR($A7="",$G7=0),"",ROUND($F7*INDEX(仪器设备工时分配表!$H$6:$H$245,$W7)/$G7,2)) -> 0 | K7: =IF(OR($A7="",$G7=0),"",ROUND($F7*INDEX(仪器设备工时分配表!$I$6:$I$245,$W7)/$G7,2)) -> 0 | L7: =IF(OR($A7="",$G7=0),"",ROUND($F7*INDEX(仪器设备工时分配表!$J$6:$J$245,$W7)/$G7,2)) -> 1066.67 | M7: =IF(OR($A7="",$G7=0),"",ROUND($F7*INDEX(仪器设备工时分配表!$K$6:$K$245,$W7)/$G7,2)) -> 0 | N7: =IF(OR($A7="",$G7=0),"",ROUND($F7*INDEX(仪器设备工时分配表!$L$6:$L$245,$W7)/$G7,2)) -> 533.33 | O7: =IF(OR($A7="",$G7=0),"",ROUND($F7*INDEX(仪器设备工时分配表!$M$6:$M$245,$W7)/$G7,2)) -> 0 | P7: =IF(OR($A7="",$G7=0),"",ROUND($F7*INDEX(仪器设备工时分配表!$N$6:$N$245,$W7)/$G7,2)) -> 0 | Q7: =IF(OR($A7="",$G7=0),"",ROUND($F7*INDEX(仪器设备工时分配表!$O$6:$O$245,$W7)/$G7,2)) -> 0 | R7: =IF(OR($A7="",$G7=0),"",ROUND($F7*INDEX(仪器设备工时分配表!$P$6:$P$245,$W7)/$G7,2)) -> 0 | S7: =IF(OR($A7="",$G7=0),"",ROUND($F7*INDEX(仪器设备工时分配表!$Q$6:$Q$245,$W7)/$G7,2)) -> 0 | T7: =IF($A7="","",ROUND(SUM(J7:S7),2)) -> 1600 | U7: =IF($A7="","",ROUND($F7-T7,2)) -> 6400 | V7: =IF($A7="","",IF($D7="无形资产","⚠ 无形资产请在无形资产费用分配表登记",IF($W7=0,"⚠ 工时分配表无此资产当月记录",IF($X7>1,"⚠ 工时分配表存在重复行","√ 正常")))) -> √ 正常 | W7: =IF($A7="",0,IFERROR(MATCH($A7&"|"&$B7,仪器设备工时分配表!$V$6:$V$245,0),0)) -> 2 | X7: =IF($A7="",0,COUNTIFS(仪器设备工时分配表!$A$6:$A$245,$A7,仪器设备工时分配表!$B$6:$B$245,$B7)) -> 1
A8: 2026-09 | B8: SB003 | C8: =IF($B8="","",IFERROR(VLOOKUP($B8,资产台账!$B$4:$N$53,2,0)&"","台账中未登记")) -> （示例）高精度分切机 | D8: =IF($B8="","",IFERROR(VLOOKUP($B8,资产台账!$B$4:$N$53,3,0)&"","")) -> 设备 | E8: =IF($B8="","",IFERROR(VLOOKUP($B8,资产台账!$B$4:$N$53,10,0)&"","")) -> 折旧 | F8: =IF($B8="","",IFERROR(VLOOKUP($B8,资产台账!$B$4:$N$53,9,0),0)) -> 5166.67 | G8: =IF(OR($A8="",$W8=0),0,INDEX(仪器设备工时分配表!$F$6:$F$245,$W8)) -> 280 | H8: =IF(OR($A8="",$W8=0),0,INDEX(仪器设备工时分配表!$R$6:$R$245,$W8)) -> 30 | I8: =IF(OR($A8="",$G8=0),"",$H8/$G8) -> 0.10714286 | J8: =IF(OR($A8="",$G8=0),"",ROUND($F8*INDEX(仪器设备工时分配表!$H$6:$H$245,$W8)/$G8,2)) -> 0 | K8: =IF(OR($A8="",$G8=0),"",ROUND($F8*INDEX(仪器设备工时分配表!$I$6:$I$245,$W8)/$G8,2)) -> 0 | L8: =IF(OR($A8="",$G8=0),"",ROUND($F8*INDEX(仪器设备工时分配表!$J$6:$J$245,$W8)/$G8,2)) -> 0 | M8: =IF(OR($A8="",$G8=0),"",ROUND($F8*INDEX(仪器设备工时分配表!$K$6:$K$245,$W8)/$G8,2)) -> 553.57 | N8: =IF(OR($A8="",$G8=0),"",ROUND($F8*INDEX(仪器设备工时分配表!$L$6:$L$245,$W8)/$G8,2)) -> 0 | O8: =IF(OR($A8="",$G8=0),"",ROUND($F8*INDEX(仪器设备工时分配表!$M$6:$M$245,$W8)/$G8,2)) -> 0 | P8: =IF(OR($A8="",$G8=0),"",ROUND($F8*INDEX(仪器设备工时分配表!$N$6:$N$245,$W8)/$G8,2)) -> 0 | Q8: =IF(OR($A8="",$G8=0),"",ROUND($F8*INDEX(仪器设备工时分配表!$O$6:$O$245,$W8)/$G8,2)) -> 0 | R8: =IF(OR($A8="",$G8=0),"",ROUND($F8*INDEX(仪器设备工时分配表!$P$6:$P$245,$W8)/$G8,2)) -> 0 | S8: =IF(OR($A8="",$G8=0),"",ROUND($F8*INDEX(仪器设备工时分配表!$Q$6:$Q$245,$W8)/$G8,2)) -> 0 | T8: =IF($A8="","",ROUND(SUM(J8:S8),2)) -> 553.57 | U8: =IF($A8="","",ROUND($F8-T8,2)) -> 4613.1 | V8: =IF($A8="","",IF($D8="无形资产","⚠ 无形资产请在无形资产费用分配表登记",IF($W8=0,"⚠ 工时分配表无此资产当月记录",IF($X8>1,"⚠ 工时分配表存在重复行","√ 正常")))) -> √ 正常 | W8: =IF($A8="",0,IFERROR(MATCH($A8&"|"&$B8,仪器设备工时分配表!$V$6:$V$245,0),0)) -> 3 | X8: =IF($A8="",0,COUNTIFS(仪器设备工时分配表!$A$6:$A$245,$A8,仪器设备工时分配表!$B$6:$B$245,$B8)) -> 1
A9: 2026-09 | B9: SB005 | C9: =IF($B9="","",IFERROR(VLOOKUP($B9,资产台账!$B$4:$N$53,2,0)&"","台账中未登记")) -> （示例）租入激光模切设备 | D9: =IF($B9="","",IFERROR(VLOOKUP($B9,资产台账!$B$4:$N$53,3,0)&"","")) -> 设备 | E9: =IF($B9="","",IFERROR(VLOOKUP($B9,资产台账!$B$4:$N$53,10,0)&"","")) -> 租赁费 | F9: =IF($B9="","",IFERROR(VLOOKUP($B9,资产台账!$B$4:$N$53,9,0),0)) -> 12000 | G9: =IF(OR($A9="",$W9=0),0,INDEX(仪器设备工时分配表!$F$6:$F$245,$W9)) -> 120 | H9: =IF(OR($A9="",$W9=0),0,INDEX(仪器设备工时分配表!$R$6:$R$245,$W9)) -> 120 | I9: =IF(OR($A9="",$G9=0),"",$H9/$G9) -> 1 | J9: =IF(OR($A9="",$G9=0),"",ROUND($F9*INDEX(仪器设备工时分配表!$H$6:$H$245,$W9)/$G9,2)) -> 0 | K9: =IF(OR($A9="",$G9=0),"",ROUND($F9*INDEX(仪器设备工时分配表!$I$6:$I$245,$W9)/$G9,2)) -> 7000 | L9: =IF(OR($A9="",$G9=0),"",ROUND($F9*INDEX(仪器设备工时分配表!$J$6:$J$245,$W9)/$G9,2)) -> 0 | M9: =IF(OR($A9="",$G9=0),"",ROUND($F9*INDEX(仪器设备工时分配表!$K$6:$K$245,$W9)/$G9,2)) -> 0 | N9: =IF(OR($A9="",$G9=0),"",ROUND($F9*INDEX(仪器设备工时分配表!$L$6:$L$245,$W9)/$G9,2)) -> 5000 | O9: =IF(OR($A9="",$G9=0),"",ROUND($F9*INDEX(仪器设备工时分配表!$M$6:$M$245,$W9)/$G9,2)) -> 0 | P9: =IF(OR($A9="",$G9=0),"",ROUND($F9*INDEX(仪器设备工时分配表!$N$6:$N$245,$W9)/$G9,2)) -> 0 | Q9: =IF(OR($A9="",$G9=0),"",ROUND($F9*INDEX(仪器设备工时分配表!$O$6:$O$245,$W9)/$G9,2)) -> 0 | R9: =IF(OR($A9="",$G9=0),"",ROUND($F9*INDEX(仪器设备工时分配表!$P$6:$P$245,$W9)/$G9,2)) -> 0 | S9: =IF(OR($A9="",$G9=0),"",ROUND($F9*INDEX(仪器设备工时分配表!$Q$6:$Q$245,$W9)/$G9,2)) -> 0 | T9: =IF($A9="","",ROUND(SUM(J9:S9),2)) -> 12000 | U9: =IF($A9="","",ROUND($F9-T9,2)) -> 0 | V9: =IF($A9="","",IF($D9="无形资产","⚠ 无形资产请在无形资产费用分配表登记",IF($W9=0,"⚠ 工时分配表无此资产当月记录",IF($X9>1,"⚠ 工时分配表存在重复行","√ 正常")))) -> √ 正常 | W9: =IF($A9="",0,IFERROR(MATCH($A9&"|"&$B9,仪器设备工时分配表!$V$6:$V$245,0),0)) -> 4 | X9: =IF($A9="",0,COUNTIFS(仪器设备工时分配表!$A$6:$A$245,$A9,仪器设备工时分配表!$B$6:$B$245,$B9)) -> 1
C10: =IF($B10="","",IFERROR(VLOOKUP($B10,资产台账!$B$4:$N$53,2,0)&"","台账中未登记")) | D10: =IF($B10="","",IFERROR(VLOOKUP($B10,资产台账!$B$4:$N$53,3,0)&"","")) | E10: =IF($B10="","",IFERROR(VLOOKUP($B10,资产台账!$B$4:$N$53,10,0)&"","")) | F10: =IF($B10="","",IFERROR(VLOOKUP($B10,资产台账!$B$4:$N$53,9,0),0)) | G10: =IF(OR($A10="",$W10=0),0,INDEX(仪器设备工时分配表!$F$6:$F$245,$W10)) -> 0 | H10: =IF(OR($A10="",$W10=0),0,INDEX(仪器设备工时分配表!$R$6:$R$245,$W10)) -> 0 | I10: =IF(OR($A10="",$G10=0),"",$H10/$G10) | J10: =IF(OR($A10="",$G10=0),"",ROUND($F10*INDEX(仪器设备工时分配表!$H$6:$H$245,$W10)/$G10,2)) | K10: =IF(OR($A10="",$G10=0),"",ROUND($F10*INDEX(仪器设备工时分配表!$I$6:$I$245,$W10)/$G10,2)) | L10: =IF(OR($A10="",$G10=0),"",ROUND($F10*INDEX(仪器设备工时分配表!$J$6:$J$245,$W10)/$G10,2)) | M10: =IF(OR($A10="",$G10=0),"",ROUND($F10*INDEX(仪器设备工时分配表!$K$6:$K$245,$W10)/$G10,2)) | N10: =IF(OR($A10="",$G10=0),"",ROUND($F10*INDEX(仪器设备工时分配表!$L$6:$L$245,$W10)/$G10,2)) | O10: =IF(OR($A10="",$G10=0),"",ROUND($F10*INDEX(仪器设备工时分配表!$M$6:$M$245,$W10)/$G10,2)) | P10: =IF(OR($A10="",$G10=0),"",ROUND($F10*INDEX(仪器设备工时分配表!$N$6:$N$245,$W10)/$G10,2)) | Q10: =IF(OR($A10="",$G10=0),"",ROUND($F10*INDEX(仪器设备工时分配表!$O$6:$O$245,$W10)/$G10,2)) | R10: =IF(OR($A10="",$G10=0),"",ROUND($F10*INDEX(仪器设备工时分配表!$P$6:$P$245,$W10)/$G10,2)) | S10: =IF(OR($A10="",$G10=0),"",ROUND($F10*INDEX(仪器设备工时分配表!$Q$6:$Q$245,$W10)/$G10,2)) | T10: =IF($A10="","",ROUND(SUM(J10:S10),2)) | U10: =IF($A10="","",ROUND($F10-T10,2)) | V10: =IF($A10="","",IF($D10="无形资产","⚠ 无形资产请在无形资产费用分配表登记",IF($W10=0,"⚠ 工时分配表无此资产当月记录",IF($X10>1,"⚠ 工时分配表存在重复行","√ 正常")))) | W10: =IF($A10="",0,IFERROR(MATCH($A10&"|"&$B10,仪器设备工时分配表!$V$6:$V$245,0),0)) -> 0 | X10: =IF($A10="",0,COUNTIFS(仪器设备工时分配表!$A$6:$A$245,$A10,仪器设备工时分配表!$B$6:$B$245,$B10)) -> 0
C11: =IF($B11="","",IFERROR(VLOOKUP($B11,资产台账!$B$4:$N$53,2,0)&"","台账中未登记")) | D11: =IF($B11="","",IFERROR(VLOOKUP($B11,资产台账!$B$4:$N$53,3,0)&"","")) | E11: =IF($B11="","",IFERROR(VLOOKUP($B11,资产台账!$B$4:$N$53,10,0)&"","")) | F11: =IF($B11="","",IFERROR(VLOOKUP($B11,资产台账!$B$4:$N$53,9,0),0)) | G11: =IF(OR($A11="",$W11=0),0,INDEX(仪器设备工时分配表!$F$6:$F$245,$W11)) -> 0 | H11: =IF(OR($A11="",$W11=0),0,INDEX(仪器设备工时分配表!$R$6:$R$245,$W11)) -> 0 | I11: =IF(OR($A11="",$G11=0),"",$H11/$G11) | J11: =IF(OR($A11="",$G11=0),"",ROUND($F11*INDEX(仪器设备工时分配表!$H$6:$H$245,$W11)/$G11,2)) | K11: =IF(OR($A11="",$G11=0),"",ROUND($F11*INDEX(仪器设备工时分配表!$I$6:$I$245,$W11)/$G11,2)) | L11: =IF(OR($A11="",$G11=0),"",ROUND($F11*INDEX(仪器设备工时分配表!$J$6:$J$245,$W11)/$G11,2)) | M11: =IF(OR($A11="",$G11=0),"",ROUND($F11*INDEX(仪器设备工时分配表!$K$6:$K$245,$W11)/$G11,2)) | N11: =IF(OR($A11="",$G11=0),"",ROUND($F11*INDEX(仪器设备工时分配表!$L$6:$L$245,$W11)/$G11,2)) | O11: =IF(OR($A11="",$G11=0),"",ROUND($F11*INDEX(仪器设备工时分配表!$M$6:$M$245,$W11)/$G11,2)) | P11: =IF(OR($A11="",$G11=0),"",ROUND($F11*INDEX(仪器设备工时分配表!$N$6:$N$245,$W11)/$G11,2)) | Q11: =IF(OR($A11="",$G11=0),"",ROUND($F11*INDEX(仪器设备工时分配表!$O$6:$O$245,$W11)/$G11,2)) | R11: =IF(OR($A11="",$G11=0),"",ROUND($F11*INDEX(仪器设备工时分配表!$P$6:$P$245,$W11)/$G11,2)) | S11: =IF(OR($A11="",$G11=0),"",ROUND($F11*INDEX(仪器设备工时分配表!$Q$6:$Q$245,$W11)/$G11,2)) | T11: =IF($A11="","",ROUND(SUM(J11:S11),2)) | U11: =IF($A11="","",ROUND($F11-T11,2)) | V11: =IF($A11="","",IF($D11="无形资产","⚠ 无形资产请在无形资产费用分配表登记",IF($W11=0,"⚠ 工时分配表无此资产当月记录",IF($X11>1,"⚠ 工时分配表存在重复行","√ 正常")))) | W11: =IF($A11="",0,IFERROR(MATCH($A11&"|"&$B11,仪器设备工时分配表!$V$6:$V$245,0),0)) -> 0 | X11: =IF($A11="",0,COUNTIFS(仪器设备工时分配表!$A$6:$A$245,$A11,仪器设备工时分配表!$B$6:$B$245,$B11)) -> 0
C12: =IF($B12="","",IFERROR(VLOOKUP($B12,资产台账!$B$4:$N$53,2,0)&"","台账中未登记")) | D12: =IF($B12="","",IFERROR(VLOOKUP($B12,资产台账!$B$4:$N$53,3,0)&"","")) | E12: =IF($B12="","",IFERROR(VLOOKUP($B12,资产台账!$B$4:$N$53,10,0)&"","")) | F12: =IF($B12="","",IFERROR(VLOOKUP($B12,资产台账!$B$4:$N$53,9,0),0)) | G12: =IF(OR($A12="",$W12=0),0,INDEX(仪器设备工时分配表!$F$6:$F$245,$W12)) -> 0 | H12: =IF(OR($A12="",$W12=0),0,INDEX(仪器设备工时分配表!$R$6:$R$245,$W12)) -> 0 | I12: =IF(OR($A12="",$G12=0),"",$H12/$G12) | J12: =IF(OR($A12="",$G12=0),"",ROUND($F12*INDEX(仪器设备工时分配表!$H$6:$H$245,$W12)/$G12,2)) | K12: =IF(OR($A12="",$G12=0),"",ROUND($F12*INDEX(仪器设备工时分配表!$I$6:$I$245,$W12)/$G12,2)) | L12: =IF(OR($A12="",$G12=0),"",ROUND($F12*INDEX(仪器设备工时分配表!$J$6:$J$245,$W12)/$G12,2)) | M12: =IF(OR($A12="",$G12=0),"",ROUND($F12*INDEX(仪器设备工时分配表!$K$6:$K$245,$W12)/$G12,2)) | N12: =IF(OR($A12="",$G12=0),"",ROUND($F12*INDEX(仪器设备工时分配表!$L$6:$L$245,$W12)/$G12,2)) | O12: =IF(OR($A12="",$G12=0),"",ROUND($F12*INDEX(仪器设备工时分配表!$M$6:$M$245,$W12)/$G12,2)) | P12: =IF(OR($A12="",$G12=0),"",ROUND($F12*INDEX(仪器设备工时分配表!$N$6:$N$245,$W12)/$G12,2)) | Q12: =IF(OR($A12="",$G12=0),"",ROUND($F12*INDEX(仪器设备工时分配表!$O$6:$O$245,$W12)/$G12,2)) | R12: =IF(OR($A12="",$G12=0),"",ROUND($F12*INDEX(仪器设备工时分配表!$P$6:$P$245,$W12)/$G12,2)) | S12: =IF(OR($A12="",$G12=0),"",ROUND($F12*INDEX(仪器设备工时分配表!$Q$6:$Q$245,$W12)/$G12,2)) | T12: =IF($A12="","",ROUND(SUM(J12:S12),2)) | U12: =IF($A12="","",ROUND($F12-T12,2)) | V12: =IF($A12="","",IF($D12="无形资产","⚠ 无形资产请在无形资产费用分配表登记",IF($W12=0,"⚠ 工时分配表无此资产当月记录",IF($X12>1,"⚠ 工时分配表存在重复行","√ 正常")))) | W12: =IF($A12="",0,IFERROR(MATCH($A12&"|"&$B12,仪器设备工时分配表!$V$6:$V$245,0),0)) -> 0 | X12: =IF($A12="",0,COUNTIFS(仪器设备工时分配表!$A$6:$A$245,$A12,仪器设备工时分配表!$B$6:$B$245,$B12)) -> 0
C13: =IF($B13="","",IFERROR(VLOOKUP($B13,资产台账!$B$4:$N$53,2,0)&"","台账中未登记")) | D13: =IF($B13="","",IFERROR(VLOOKUP($B13,资产台账!$B$4:$N$53,3,0)&"","")) | E13: =IF($B13="","",IFERROR(VLOOKUP($B13,资产台账!$B$4:$N$53,10,0)&"","")) | F13: =IF($B13="","",IFERROR(VLOOKUP($B13,资产台账!$B$4:$N$53,9,0),0)) | G13: =IF(OR($A13="",$W13=0),0,INDEX(仪器设备工时分配表!$F$6:$F$245,$W13)) -> 0 | H13: =IF(OR($A13="",$W13=0),0,INDEX(仪器设备工时分配表!$R$6:$R$245,$W13)) -> 0 | I13: =IF(OR($A13="",$G13=0),"",$H13/$G13) | J13: =IF(OR($A13="",$G13=0),"",ROUND($F13*INDEX(仪器设备工时分配表!$H$6:$H$245,$W13)/$G13,2)) | K13: =IF(OR($A13="",$G13=0),"",ROUND($F13*INDEX(仪器设备工时分配表!$I$6:$I$245,$W13)/$G13,2)) | L13: =IF(OR($A13="",$G13=0),"",ROUND($F13*INDEX(仪器设备工时分配表!$J$6:$J$245,$W13)/$G13,2)) | M13: =IF(OR($A13="",$G13=0),"",ROUND($F13*INDEX(仪器设备工时分配表!$K$6:$K$245,$W13)/$G13,2)) | N13: =IF(OR($A13="",$G13=0),"",ROUND($F13*INDEX(仪器设备工时分配表!$L$6:$L$245,$W13)/$G13,2)) | O13: =IF(OR($A13="",$G13=0),"",ROUND($F13*INDEX(仪器设备工时分配表!$M$6:$M$245,$W13)/$G13,2)) | P13: =IF(OR($A13="",$G13=0),"",ROUND($F13*INDEX(仪器设备工时分配表!$N$6:$N$245,$W13)/$G13,2)) | Q13: =IF(OR($A13="",$G13=0),"",ROUND($F13*INDEX(仪器设备工时分配表!$O$6:$O$245,$W13)/$G13,2)) | R13: =IF(OR($A13="",$G13=0),"",ROUND($F13*INDEX(仪器设备工时分配表!$P$6:$P$245,$W13)/$G13,2)) | S13: =IF(OR($A13="",$G13=0),"",ROUND($F13*INDEX(仪器设备工时分配表!$Q$6:$Q$245,$W13)/$G13,2)) | T13: =IF($A13="","",ROUND(SUM(J13:S13),2)) | U13: =IF($A13="","",ROUND($F13-T13,2)) | V13: =IF($A13="","",IF($D13="无形资产","⚠ 无形资产请在无形资产费用分配表登记",IF($W13=0,"⚠ 工时分配表无此资产当月记录",IF($X13>1,"⚠ 工时分配表存在重复行","√ 正常")))) | W13: =IF($A13="",0,IFERROR(MATCH($A13&"|"&$B13,仪器设备工时分配表!$V$6:$V$245,0),0)) -> 0 | X13: =IF($A13="",0,COUNTIFS(仪器设备工时分配表!$A$6:$A$245,$A13,仪器设备工时分配表!$B$6:$B$245,$B13)) -> 0
C14: =IF($B14="","",IFERROR(VLOOKUP($B14,资产台账!$B$4:$N$53,2,0)&"","台账中未登记")) | D14: =IF($B14="","",IFERROR(VLOOKUP($B14,资产台账!$B$4:$N$53,3,0)&"","")) | E14: =IF($B14="","",IFERROR(VLOOKUP($B14,资产台账!$B$4:$N$53,10,0)&"","")) | F14: =IF($B14="","",IFERROR(VLOOKUP($B14,资产台账!$B$4:$N$53,9,0),0)) | G14: =IF(OR($A14="",$W14=0),0,INDEX(仪器设备工时分配表!$F$6:$F$245,$W14)) -> 0 | H14: =IF(OR($A14="",$W14=0),0,INDEX(仪器设备工时分配表!$R$6:$R$245,$W14)) -> 0 | I14: =IF(OR($A14="",$G14=0),"",$H14/$G14) | J14: =IF(OR($A14="",$G14=0),"",ROUND($F14*INDEX(仪器设备工时分配表!$H$6:$H$245,$W14)/$G14,2)) | K14: =IF(OR($A14="",$G14=0),"",ROUND($F14*INDEX(仪器设备工时分配表!$I$6:$I$245,$W14)/$G14,2)) | L14: =IF(OR($A14="",$G14=0),"",ROUND($F14*INDEX(仪器设备工时分配表!$J$6:$J$245,$W14)/$G14,2)) | M14: =IF(OR($A14="",$G14=0),"",ROUND($F14*INDEX(仪器设备工时分配表!$K$6:$K$245,$W14)/$G14,2)) | N14: =IF(OR($A14="",$G14=0),"",ROUND($F14*INDEX(仪器设备工时分配表!$L$6:$L$245,$W14)/$G14,2)) | O14: =IF(OR($A14="",$G14=0),"",ROUND($F14*INDEX(仪器设备工时分配表!$M$6:$M$245,$W14)/$G14,2)) | P14: =IF(OR($A14="",$G14=0),"",ROUND($F14*INDEX(仪器设备工时分配表!$N$6:$N$245,$W14)/$G14,2)) | Q14: =IF(OR($A14="",$G14=0),"",ROUND($F14*INDEX(仪器设备工时分配表!$O$6:$O$245,$W14)/$G14,2)) | R14: =IF(OR($A14="",$G14=0),"",ROUND($F14*INDEX(仪器设备工时分配表!$P$6:$P$245,$W14)/$G14,2)) | S14: =IF(OR($A14="",$G14=0),"",ROUND($F14*INDEX(仪器设备工时分配表!$Q$6:$Q$245,$W14)/$G14,2)) | T14: =IF($A14="","",ROUND(SUM(J14:S14),2)) | U14: =IF($A14="","",ROUND($F14-T14,2)) | V14: =IF($A14="","",IF($D14="无形资产","⚠ 无形资产请在无形资产费用分配表登记",IF($W14=0,"⚠ 工时分配表无此资产当月记录",IF($X14>1,"⚠ 工时分配表存在重复行","√ 正常")))) | W14: =IF($A14="",0,IFERROR(MATCH($A14&"|"&$B14,仪器设备工时分配表!$V$6:$V$245,0),0)) -> 0 | X14: =IF($A14="",0,COUNTIFS(仪器设备工时分配表!$A$6:$A$245,$A14,仪器设备工时分配表!$B$6:$B$245,$B14)) -> 0
C15: =IF($B15="","",IFERROR(VLOOKUP($B15,资产台账!$B$4:$N$53,2,0)&"","台账中未登记")) | D15: =IF($B15="","",IFERROR(VLOOKUP($B15,资产台账!$B$4:$N$53,3,0)&"","")) | E15: =IF($B15="","",IFERROR(VLOOKUP($B15,资产台账!$B$4:$N$53,10,0)&"","")) | F15: =IF($B15="","",IFERROR(VLOOKUP($B15,资产台账!$B$4:$N$53,9,0),0)) | G15: =IF(OR($A15="",$W15=0),0,INDEX(仪器设备工时分配表!$F$6:$F$245,$W15)) -> 0 | H15: =IF(OR($A15="",$W15=0),0,INDEX(仪器设备工时分配表!$R$6:$R$245,$W15)) -> 0 | I15: =IF(OR($A15="",$G15=0),"",$H15/$G15) | J15: =IF(OR($A15="",$G15=0),"",ROUND($F15*INDEX(仪器设备工时分配表!$H$6:$H$245,$W15)/$G15,2)) | K15: =IF(OR($A15="",$G15=0),"",ROUND($F15*INDEX(仪器设备工时分配表!$I$6:$I$245,$W15)/$G15,2)) | L15: =IF(OR($A15="",$G15=0),"",ROUND($F15*INDEX(仪器设备工时分配表!$J$6:$J$245,$W15)/$G15,2)) | M15: =IF(OR($A15="",$G15=0),"",ROUND($F15*INDEX(仪器设备工时分配表!$K$6:$K$245,$W15)/$G15,2)) | N15: =IF(OR($A15="",$G15=0),"",ROUND($F15*INDEX(仪器设备工时分配表!$L$6:$L$245,$W15)/$G15,2)) | O15: =IF(OR($A15="",$G15=0),"",ROUND($F15*INDEX(仪器设备工时分配表!$M$6:$M$245,$W15)/$G15,2)) | P15: =IF(OR($A15="",$G15=0),"",ROUND($F15*INDEX(仪器设备工时分配表!$N$6:$N$245,$W15)/$G15,2)) | Q15: =IF(OR($A15="",$G15=0),"",ROUND($F15*INDEX(仪器设备工时分配表!$O$6:$O$245,$W15)/$G15,2)) | R15: =IF(OR($A15="",$G15=0),"",ROUND($F15*INDEX(仪器设备工时分配表!$P$6:$P$245,$W15)/$G15,2)) | S15: =IF(OR($A15="",$G15=0),"",ROUND($F15*INDEX(仪器设备工时分配表!$Q$6:$Q$245,$W15)/$G15,2)) | T15: =IF($A15="","",ROUND(SUM(J15:S15),2)) | U15: =IF($A15="","",ROUND($F15-T15,2)) | V15: =IF($A15="","",IF($D15="无形资产","⚠ 无形资产请在无形资产费用分配表登记",IF($W15=0,"⚠ 工时分配表无此资产当月记录",IF($X15>1,"⚠ 工时分配表存在重复行","√ 正常")))) | W15: =IF($A15="",0,IFERROR(MATCH($A15&"|"&$B15,仪器设备工时分配表!$V$6:$V$245,0),0)) -> 0 | X15: =IF($A15="",0,COUNTIFS(仪器设备工时分配表!$A$6:$A$245,$A15,仪器设备工时分配表!$B$6:$B$245,$B15)) -> 0
C16: =IF($B16="","",IFERROR(VLOOKUP($B16,资产台账!$B$4:$N$53,2,0)&"","台账中未登记")) | D16: =IF($B16="","",IFERROR(VLOOKUP($B16,资产台账!$B$4:$N$53,3,0)&"","")) | E16: =IF($B16="","",IFERROR(VLOOKUP($B16,资产台账!$B$4:$N$53,10,0)&"","")) | F16: =IF($B16="","",IFERROR(VLOOKUP($B16,资产台账!$B$4:$N$53,9,0),0)) | G16: =IF(OR($A16="",$W16=0),0,INDEX(仪器设备工时分配表!$F$6:$F$245,$W16)) -> 0 | H16: =IF(OR($A16="",$W16=0),0,INDEX(仪器设备工时分配表!$R$6:$R$245,$W16)) -> 0 | I16: =IF(OR($A16="",$G16=0),"",$H16/$G16) | J16: =IF(OR($A16="",$G16=0),"",ROUND($F16*INDEX(仪器设备工时分配表!$H$6:$H$245,$W16)/$G16,2)) | K16: =IF(OR($A16="",$G16=0),"",ROUND($F16*INDEX(仪器设备工时分配表!$I$6:$I$245,$W16)/$G16,2)) | L16: =IF(OR($A16="",$G16=0),"",ROUND($F16*INDEX(仪器设备工时分配表!$J$6:$J$245,$W16)/$G16,2)) | M16: =IF(OR($A16="",$G16=0),"",ROUND($F16*INDEX(仪器设备工时分配表!$K$6:$K$245,$W16)/$G16,2)) | N16: =IF(OR($A16="",$G16=0),"",ROUND($F16*INDEX(仪器设备工时分配表!$L$6:$L$245,$W16)/$G16,2)) | O16: =IF(OR($A16="",$G16=0),"",ROUND($F16*INDEX(仪器设备工时分配表!$M$6:$M$245,$W16)/$G16,2)) | P16: =IF(OR($A16="",$G16=0),"",ROUND($F16*INDEX(仪器设备工时分配表!$N$6:$N$245,$W16)/$G16,2)) | Q16: =IF(OR($A16="",$G16=0),"",ROUND($F16*INDEX(仪器设备工时分配表!$O$6:$O$245,$W16)/$G16,2)) | R16: =IF(OR($A16="",$G16=0),"",ROUND($F16*INDEX(仪器设备工时分配表!$P$6:$P$245,$W16)/$G16,2)) | S16: =IF(OR($A16="",$G16=0),"",ROUND($F16*INDEX(仪器设备工时分配表!$Q$6:$Q$245,$W16)/$G16,2)) | T16: =IF($A16="","",ROUND(SUM(J16:S16),2)) | U16: =IF($A16="","",ROUND($F16-T16,2)) | V16: =IF($A16="","",IF($D16="无形资产","⚠ 无形资产请在无形资产费用分配表登记",IF($W16=0,"⚠ 工时分配表无此资产当月记录",IF($X16>1,"⚠ 工时分配表存在重复行","√ 正常")))) | W16: =IF($A16="",0,IFERROR(MATCH($A16&"|"&$B16,仪器设备工时分配表!$V$6:$V$245,0),0)) -> 0 | X16: =IF($A16="",0,COUNTIFS(仪器设备工时分配表!$A$6:$A$245,$A16,仪器设备工时分配表!$B$6:$B$245,$B16)) -> 0
C17: =IF($B17="","",IFERROR(VLOOKUP($B17,资产台账!$B$4:$N$53,2,0)&"","台账中未登记")) | D17: =IF($B17="","",IFERROR(VLOOKUP($B17,资产台账!$B$4:$N$53,3,0)&"","")) | E17: =IF($B17="","",IFERROR(VLOOKUP($B17,资产台账!$B$4:$N$53,10,0)&"","")) | F17: =IF($B17="","",IFERROR(VLOOKUP($B17,资产台账!$B$4:$N$53,9,0),0)) | G17: =IF(OR($A17="",$W17=0),0,INDEX(仪器设备工时分配表!$F$6:$F$245,$W17)) -> 0 | H17: =IF(OR($A17="",$W17=0),0,INDEX(仪器设备工时分配表!$R$6:$R$245,$W17)) -> 0 | I17: =IF(OR($A17="",$G17=0),"",$H17/$G17) | J17: =IF(OR($A17="",$G17=0),"",ROUND($F17*INDEX(仪器设备工时分配表!$H$6:$H$245,$W17)/$G17,2)) | K17: =IF(OR($A17="",$G17=0),"",ROUND($F17*INDEX(仪器设备工时分配表!$I$6:$I$245,$W17)/$G17,2)) | L17: =IF(OR($A17="",$G17=0),"",ROUND($F17*INDEX(仪器设备工时分配表!$J$6:$J$245,$W17)/$G17,2)) | M17: =IF(OR($A17="",$G17=0),"",ROUND($F17*INDEX(仪器设备工时分配表!$K$6:$K$245,$W17)/$G17,2)) | N17: =IF(OR($A17="",$G17=0),"",ROUND($F17*INDEX(仪器设备工时分配表!$L$6:$L$245,$W17)/$G17,2)) | O17: =IF(OR($A17="",$G17=0),"",ROUND($F17*INDEX(仪器设备工时分配表!$M$6:$M$245,$W17)/$G17,2)) | P17: =IF(OR($A17="",$G17=0),"",ROUND($F17*INDEX(仪器设备工时分配表!$N$6:$N$245,$W17)/$G17,2)) | Q17: =IF(OR($A17="",$G17=0),"",ROUND($F17*INDEX(仪器设备工时分配表!$O$6:$O$245,$W17)/$G17,2)) | R17: =IF(OR($A17="",$G17=0),"",ROUND($F17*INDEX(仪器设备工时分配表!$P$6:$P$245,$W17)/$G17,2)) | S17: =IF(OR($A17="",$G17=0),"",ROUND($F17*INDEX(仪器设备工时分配表!$Q$6:$Q$245,$W17)/$G17,2)) | T17: =IF($A17="","",ROUND(SUM(J17:S17),2)) | U17: =IF($A17="","",ROUND($F17-T17,2)) | V17: =IF($A17="","",IF($D17="无形资产","⚠ 无形资产请在无形资产费用分配表登记",IF($W17=0,"⚠ 工时分配表无此资产当月记录",IF($X17>1,"⚠ 工时分配表存在重复行","√ 正常")))) | W17: =IF($A17="",0,IFERROR(MATCH($A17&"|"&$B17,仪器设备工时分配表!$V$6:$V$245,0),0)) -> 0 | X17: =IF($A17="",0,COUNTIFS(仪器设备工时分配表!$A$6:$A$245,$A17,仪器设备工时分配表!$B$6:$B$245,$B17)) -> 0
C18: =IF($B18="","",IFERROR(VLOOKUP($B18,资产台账!$B$4:$N$53,2,0)&"","台账中未登记")) | D18: =IF($B18="","",IFERROR(VLOOKUP($B18,资产台账!$B$4:$N$53,3,0)&"","")) | E18: =IF($B18="","",IFERROR(VLOOKUP($B18,资产台账!$B$4:$N$53,10,0)&"","")) | F18: =IF($B18="","",IFERROR(VLOOKUP($B18,资产台账!$B$4:$N$53,9,0),0)) | G18: =IF(OR($A18="",$W18=0),0,INDEX(仪器设备工时分配表!$F$6:$F$245,$W18)) -> 0 | H18: =IF(OR($A18="",$W18=0),0,INDEX(仪器设备工时分配表!$R$6:$R$245,$W18)) -> 0 | I18: =IF(OR($A18="",$G18=0),"",$H18/$G18) | J18: =IF(OR($A18="",$G18=0),"",ROUND($F18*INDEX(仪器设备工时分配表!$H$6:$H$245,$W18)/$G18,2)) | K18: =IF(OR($A18="",$G18=0),"",ROUND($F18*INDEX(仪器设备工时分配表!$I$6:$I$245,$W18)/$G18,2)) | L18: =IF(OR($A18="",$G18=0),"",ROUND($F18*INDEX(仪器设备工时分配表!$J$6:$J$245,$W18)/$G18,2)) | M18: =IF(OR($A18="",$G18=0),"",ROUND($F18*INDEX(仪器设备工时分配表!$K$6:$K$245,$W18)/$G18,2)) | N18: =IF(OR($A18="",$G18=0),"",ROUND($F18*INDEX(仪器设备工时分配表!$L$6:$L$245,$W18)/$G18,2)) | O18: =IF(OR($A18="",$G18=0),"",ROUND($F18*INDEX(仪器设备工时分配表!$M$6:$M$245,$W18)/$G18,2)) | P18: =IF(OR($A18="",$G18=0),"",ROUND($F18*INDEX(仪器设备工时分配表!$N$6:$N$245,$W18)/$G18,2)) | Q18: =IF(OR($A18="",$G18=0),"",ROUND($F18*INDEX(仪器设备工时分配表!$O$6:$O$245,$W18)/$G18,2)) | R18: =IF(OR($A18="",$G18=0),"",ROUND($F18*INDEX(仪器设备工时分配表!$P$6:$P$245,$W18)/$G18,2)) | S18: =IF(OR($A18="",$G18=0),"",ROUND($F18*INDEX(仪器设备工时分配表!$Q$6:$Q$245,$W18)/$G18,2)) | T18: =IF($A18="","",ROUND(SUM(J18:S18),2)) | U18: =IF($A18="","",ROUND($F18-T18,2)) | V18: =IF($A18="","",IF($D18="无形资产","⚠ 无形资产请在无形资产费用分配表登记",IF($W18=0,"⚠ 工时分配表无此资产当月记录",IF($X18>1,"⚠ 工时分配表存在重复行","√ 正常")))) | W18: =IF($A18="",0,IFERROR(MATCH($A18&"|"&$B18,仪器设备工时分配表!$V$6:$V$245,0),0)) -> 0 | X18: =IF($A18="",0,COUNTIFS(仪器设备工时分配表!$A$6:$A$245,$A18,仪器设备工时分配表!$B$6:$B$245,$B18)) -> 0
C19: =IF($B19="","",IFERROR(VLOOKUP($B19,资产台账!$B$4:$N$53,2,0)&"","台账中未登记")) | D19: =IF($B19="","",IFERROR(VLOOKUP($B19,资产台账!$B$4:$N$53,3,0)&"","")) | E19: =IF($B19="","",IFERROR(VLOOKUP($B19,资产台账!$B$4:$N$53,10,0)&"","")) | F19: =IF($B19="","",IFERROR(VLOOKUP($B19,资产台账!$B$4:$N$53,9,0),0)) | G19: =IF(OR($A19="",$W19=0),0,INDEX(仪器设备工时分配表!$F$6:$F$245,$W19)) -> 0 | H19: =IF(OR($A19="",$W19=0),0,INDEX(仪器设备工时分配表!$R$6:$R$245,$W19)) -> 0 | I19: =IF(OR($A19="",$G19=0),"",$H19/$G19) | J19: =IF(OR($A19="",$G19=0),"",ROUND($F19*INDEX(仪器设备工时分配表!$H$6:$H$245,$W19)/$G19,2)) | K19: =IF(OR($A19="",$G19=0),"",ROUND($F19*INDEX(仪器设备工时分配表!$I$6:$I$245,$W19)/$G19,2)) | L19: =IF(OR($A19="",$G19=0),"",ROUND($F19*INDEX(仪器设备工时分配表!$J$6:$J$245,$W19)/$G19,2)) | M19: =IF(OR($A19="",$G19=0),"",ROUND($F19*INDEX(仪器设备工时分配表!$K$6:$K$245,$W19)/$G19,2)) | N19: =IF(OR($A19="",$G19=0),"",ROUND($F19*INDEX(仪器设备工时分配表!$L$6:$L$245,$W19)/$G19,2)) | O19: =IF(OR($A19="",$G19=0),"",ROUND($F19*INDEX(仪器设备工时分配表!$M$6:$M$245,$W19)/$G19,2)) | P19: =IF(OR($A19="",$G19=0),"",ROUND($F19*INDEX(仪器设备工时分配表!$N$6:$N$245,$W19)/$G19,2)) | Q19: =IF(OR($A19="",$G19=0),"",ROUND($F19*INDEX(仪器设备工时分配表!$O$6:$O$245,$W19)/$G19,2)) | R19: =IF(OR($A19="",$G19=0),"",ROUND($F19*INDEX(仪器设备工时分配表!$P$6:$P$245,$W19)/$G19,2)) | S19: =IF(OR($A19="",$G19=0),"",ROUND($F19*INDEX(仪器设备工时分配表!$Q$6:$Q$245,$W19)/$G19,2)) | T19: =IF($A19="","",ROUND(SUM(J19:S19),2)) | U19: =IF($A19="","",ROUND($F19-T19,2)) | V19: =IF($A19="","",IF($D19="无形资产","⚠ 无形资产请在无形资产费用分配表登记",IF($W19=0,"⚠ 工时分配表无此资产当月记录",IF($X19>1,"⚠ 工时分配表存在重复行","√ 正常")))) | W19: =IF($A19="",0,IFERROR(MATCH($A19&"|"&$B19,仪器设备工时分配表!$V$6:$V$245,0),0)) -> 0 | X19: =IF($A19="",0,COUNTIFS(仪器设备工时分配表!$A$6:$A$245,$A19,仪器设备工时分配表!$B$6:$B$245,$B19)) -> 0
C20: =IF($B20="","",IFERROR(VLOOKUP($B20,资产台账!$B$4:$N$53,2,0)&"","台账中未登记")) | D20: =IF($B20="","",IFERROR(VLOOKUP($B20,资产台账!$B$4:$N$53,3,0)&"","")) | E20: =IF($B20="","",IFERROR(VLOOKUP($B20,资产台账!$B$4:$N$53,10,0)&"","")) | F20: =IF($B20="","",IFERROR(VLOOKUP($B20,资产台账!$B$4:$N$53,9,0),0)) | G20: =IF(OR($A20="",$W20=0),0,INDEX(仪器设备工时分配表!$F$6:$F$245,$W20)) -> 0 | H20: =IF(OR($A20="",$W20=0),0,INDEX(仪器设备工时分配表!$R$6:$R$245,$W20)) -> 0 | I20: =IF(OR($A20="",$G20=0),"",$H20/$G20) | J20: =IF(OR($A20="",$G20=0),"",ROUND($F20*INDEX(仪器设备工时分配表!$H$6:$H$245,$W20)/$G20,2)) | K20: =IF(OR($A20="",$G20=0),"",ROUND($F20*INDEX(仪器设备工时分配表!$I$6:$I$245,$W20)/$G20,2)) | L20: =IF(OR($A20="",$G20=0),"",ROUND($F20*INDEX(仪器设备工时分配表!$J$6:$J$245,$W20)/$G20,2)) | M20: =IF(OR($A20="",$G20=0),"",ROUND($F20*INDEX(仪器设备工时分配表!$K$6:$K$245,$W20)/$G20,2)) | N20: =IF(OR($A20="",$G20=0),"",ROUND($F20*INDEX(仪器设备工时分配表!$L$6:$L$245,$W20)/$G20,2)) | O20: =IF(OR($A20="",$G20=0),"",ROUND($F20*INDEX(仪器设备工时分配表!$M$6:$M$245,$W20)/$G20,2)) | P20: =IF(OR($A20="",$G20=0),"",ROUND($F20*INDEX(仪器设备工时分配表!$N$6:$N$245,$W20)/$G20,2)) | Q20: =IF(OR($A20="",$G20=0),"",ROUND($F20*INDEX(仪器设备工时分配表!$O$6:$O$245,$W20)/$G20,2)) | R20: =IF(OR($A20="",$G20=0),"",ROUND($F20*INDEX(仪器设备工时分配表!$P$6:$P$245,$W20)/$G20,2)) | S20: =IF(OR($A20="",$G20=0),"",ROUND($F20*INDEX(仪器设备工时分配表!$Q$6:$Q$245,$W20)/$G20,2)) | T20: =IF($A20="","",ROUND(SUM(J20:S20),2)) | U20: =IF($A20="","",ROUND($F20-T20,2)) | V20: =IF($A20="","",IF($D20="无形资产","⚠ 无形资产请在无形资产费用分配表登记",IF($W20=0,"⚠ 工时分配表无此资产当月记录",IF($X20>1,"⚠ 工时分配表存在重复行","√ 正常")))) | W20: =IF($A20="",0,IFERROR(MATCH($A20&"|"&$B20,仪器设备工时分配表!$V$6:$V$245,0),0)) -> 0 | X20: =IF($A20="",0,COUNTIFS(仪器设备工时分配表!$A$6:$A$245,$A20,仪器设备工时分配表!$B$6:$B$245,$B20)) -> 0
C21: =IF($B21="","",IFERROR(VLOOKUP($B21,资产台账!$B$4:$N$53,2,0)&"","台账中未登记")) | D21: =IF($B21="","",IFERROR(VLOOKUP($B21,资产台账!$B$4:$N$53,3,0)&"","")) | E21: =IF($B21="","",IFERROR(VLOOKUP($B21,资产台账!$B$4:$N$53,10,0)&"","")) | F21: =IF($B21="","",IFERROR(VLOOKUP($B21,资产台账!$B$4:$N$53,9,0),0)) | G21: =IF(OR($A21="",$W21=0),0,INDEX(仪器设备工时分配表!$F$6:$F$245,$W21)) -> 0 | H21: =IF(OR($A21="",$W21=0),0,INDEX(仪器设备工时分配表!$R$6:$R$245,$W21)) -> 0 | I21: =IF(OR($A21="",$G21=0),"",$H21/$G21) | J21: =IF(OR($A21="",$G21=0),"",ROUND($F21*INDEX(仪器设备工时分配表!$H$6:$H$245,$W21)/$G21,2)) | K21: =IF(OR($A21="",$G21=0),"",ROUND($F21*INDEX(仪器设备工时分配表!$I$6:$I$245,$W21)/$G21,2)) | L21: =IF(OR($A21="",$G21=0),"",ROUND($F21*INDEX(仪器设备工时分配表!$J$6:$J$245,$W21)/$G21,2)) | M21: =IF(OR($A21="",$G21=0),"",ROUND($F21*INDEX(仪器设备工时分配表!$K$6:$K$245,$W21)/$G21,2)) | N21: =IF(OR($A21="",$G21=0),"",ROUND($F21*INDEX(仪器设备工时分配表!$L$6:$L$245,$W21)/$G21,2)) | O21: =IF(OR($A21="",$G21=0),"",ROUND($F21*INDEX(仪器设备工时分配表!$M$6:$M$245,$W21)/$G21,2)) | P21: =IF(OR($A21="",$G21=0),"",ROUND($F21*INDEX(仪器设备工时分配表!$N$6:$N$245,$W21)/$G21,2)) | Q21: =IF(OR($A21="",$G21=0),"",ROUND($F21*INDEX(仪器设备工时分配表!$O$6:$O$245,$W21)/$G21,2)) | R21: =IF(OR($A21="",$G21=0),"",ROUND($F21*INDEX(仪器设备工时分配表!$P$6:$P$245,$W21)/$G21,2)) | S21: =IF(OR($A21="",$G21=0),"",ROUND($F21*INDEX(仪器设备工时分配表!$Q$6:$Q$245,$W21)/$G21,2)) | T21: =IF($A21="","",ROUND(SUM(J21:S21),2)) | U21: =IF($A21="","",ROUND($F21-T21,2)) | V21: =IF($A21="","",IF($D21="无形资产","⚠ 无形资产请在无形资产费用分配表登记",IF($W21=0,"⚠ 工时分配表无此资产当月记录",IF($X21>1,"⚠ 工时分配表存在重复行","√ 正常")))) | W21: =IF($A21="",0,IFERROR(MATCH($A21&"|"&$B21,仪器设备工时分配表!$V$6:$V$245,0),0)) -> 0 | X21: =IF($A21="",0,COUNTIFS(仪器设备工时分配表!$A$6:$A$245,$A21,仪器设备工时分配表!$B$6:$B$245,$B21)) -> 0
... C245: =IF($B245="","",IFERROR(VLOOKUP($B245,资产台账!$B$4:$N$53,2,0)&"","台账中未登记")) | D245: =IF($B245="","",IFERROR(VLOOKUP($B245,资产台账!$B$4:$N$53,3,0)&"","")) | E245: =IF($B245="","",IFERROR(VLOOKUP($B245,资产台账!$B$4:$N$53,10,0)&"","")) | F245: =IF($B245="","",IFERROR(VLOOKUP($B245,资产台账!$B$4:$N$53,9,0),0)) | G245: =IF(OR($A245="",$W245=0),0,INDEX(仪器设备工时分配表!$F$6:$F$245,$W245)) -> 0 | H245: =IF(OR($A245="",$W245=0),0,INDEX(仪器设备工时分配表!$R$6:$R$245,$W245)) -> 0 | I245: =IF(OR($A245="",$G245=0),"",$H245/$G245) | J245: =IF(OR($A245="",$G245=0),"",ROUND($F245*INDEX(仪器设备工时分配表!$H$6:$H$245,$W245)/$G245,2)) | K245: =IF(OR($A245="",$G245=0),"",ROUND($F245*INDEX(仪器设备工时分配表!$I$6:$I$245,$W245)/$G245,2)) | L245: =IF(OR($A245="",$G245=0),"",ROUND($F245*INDEX(仪器设备工时分配表!$J$6:$J$245,$W245)/$G245,2)) | M245: =IF(OR($A245="",$G245=0),"",ROUND($F245*INDEX(仪器设备工时分配表!$K$6:$K$245,$W245)/$G245,2)) | N245: =IF(OR($A245="",$G245=0),"",ROUND($F245*INDEX(仪器设备工时分配表!$L$6:$L$245,$W245)/$G245,2)) | O245: =IF(OR($A245="",$G245=0),"",ROUND($F245*INDEX(仪器设备工时分配表!$M$6:$M$245,$W245)/$G245,2)) | P245: =IF(OR($A245="",$G245=0),"",ROUND($F245*INDEX(仪器设备工时分配表!$N$6:$N$245,$W245)/$G245,2)) | Q245: =IF(OR($A245="",$G245=0),"",ROUND($F245*INDEX(仪器设备工时分配表!$O$6:$O$245,$W245)/$G245,2)) | R245: =IF(OR($A245="",$G245=0),"",ROUND($F245*INDEX(仪器设备工时分配表!$P$6:$P$245,$W245)/$G245,2)) | S245: =IF(OR($A245="",$G245=0),"",ROUND($F245*INDEX(仪器设备工时分配表!$Q$6:$Q$245,$W245)/$G245,2)) | T245: =IF($A245="","",ROUND(SUM(J245:S245),2)) | U245: =IF($A245="","",ROUND($F245-T245,2)) | V245: =IF($A245="","",IF($D245="无形资产","⚠ 无形资产请在无形资产费用分配表登记",IF($W245=0,"⚠ 工时分配表无此资产当月记录",IF($X245>1,"⚠ 工时分配表存在重复行","√ 正常")))) | W245: =IF($A245="",0,IFERROR(MATCH($A245&"|"&$B245,仪器设备工时分配表!$V$6:$V$245,0),0)) -> 0 | X245: =IF($A245="",0,COUNTIFS(仪器设备工时分配表!$A$6:$A$245,$A245,仪器设备工时分配表!$B$6:$B$245,$B245)) -> 0

Sheet 无形资产工时分配表
A1: 公司 LOGO （选中本区域插入图片） | C1: =IF(使用说明!$B$2="","",使用说明!$B$2&" ")&"九、《无形资产工时分配表》（研发部门按月填报，2026年度）" -> 九、《无形资产工时分配表》（研发部门按月填报，2026年度）
A2: 录入说明：①由研发部门按月填报，依据经签批的《附表3-无形资产工时分配表(签批用)》录入；②“当月总使用工时”为该无形资产（如配方模拟软件、专利技术、专有技术等）当月实际使用总工时（生产+研发），是分摊的分母；③研发专用无形资产记录全额使用工时（非研发使用工时填0），研发生产共用的按实际使用分别记录；④同一资产当月只填一行；⑤“工时校验”须为0，显示红色表示不平，须更正后方可分摊。
A3: 年月 (YYYY-MM) | B3: 资产编号 | C3: 无形资产名称 | D3: 资产类别 | E3: 所属工序/用途 | F3: 当月总使用 工时 | G3: 非研发使用工时 (生产及其他) | H3: 各研发项目使用工时（小时） | R3: 研发使用 工时合计 | S3: 工时校验 (须为0) | T3: 研发使用 占比 | U3: 备注
H4: =项目清单!$B$4 -> RD01 | I4: =项目清单!$B$5 -> RD02 | J4: =项目清单!$B$6 -> RD03 | K4: =项目清单!$B$7 -> RD04 | L4: =项目清单!$B$8 -> RD05 | M4: =项目清单!$B$9 -> RD06 | N4: =项目清单!$B$10 -> RD07 | O4: =项目清单!$B$11 -> RD08 | P4: =项目清单!$B$12 -> RD09 | Q4: =项目清单!$B$13 -> RD10
H5: =IF(H4="","",IFERROR(VLOOKUP(H4,项目清单!$B$4:$C$13,2,0)&"","")) -> 高回弹低压缩永久变形3C用聚氨酯泡棉开发 | I5: =IF(I4="","",IFERROR(VLOOKUP(I4,项目清单!$B$4:$C$13,2,0)&"","")) -> 动力电池模组用高阻燃缓冲泡棉研发 | J5: =IF(J4="","",IFERROR(VLOOKUP(J4,项目清单!$B$4:$C$13,2,0)&"","")) -> 泡棉与PET基材无溶剂贴合工艺开发 | K5: =IF(K4="","",IFERROR(VLOOKUP(K4,项目清单!$B$4:$C$13,2,0)&"","")) -> 超薄泡棉高精度分切及毛边控制技术研究 | L5: =IF(L4="","",IFERROR(VLOOKUP(L4,项目清单!$B$4:$C$13,2,0)&"","")) -> 新能源汽车电池包用导热缓冲复合材料开发 | M5: =IF(M4="","",IFERROR(VLOOKUP(M4,项目清单!$B$4:$C$13,2,0)&"","")) -> 3C电子用超薄黑色遮光泡棉制备技术 | N5: =IF(N4="","",IFERROR(VLOOKUP(N4,项目清单!$B$4:$C$13,2,0)&"","")) -> 环保型水性胶泡棉贴合技术开发 | O5: =IF(O4="","",IFERROR(VLOOKUP(O4,项目清单!$B$4:$C$13,2,0)&"","")) -> 泡棉模切自动化在线检测技术研究 | ... Q5: =IF(Q4="","",IFERROR(VLOOKUP(Q4,项目清单!$B$4:$C$13,2,0)&"","")) | V5: 匹配主键(勿删)
A6: 2026-09 | B6: WX001 | C6: =IF($B6="","",IFERROR(VLOOKUP($B6,资产台账!$B$4:$N$53,2,0)&"","台账中未登记")) -> （示例）泡棉配方模拟软件 | D6: =IF($B6="","",IFERROR(VLOOKUP($B6,资产台账!$B$4:$N$53,3,0)&"","")) -> 无形资产 | E6: =IF($B6="","",IFERROR(VLOOKUP($B6,资产台账!$B$4:$N$53,5,0)&"","")) -> 研发通用 | F6: 160 | G6: 0 | H6: 60 | I6: 60 | L6: 40 | R6: =IF($A6="","",SUM(H6:Q6)) -> 160 | S6: =IF($A6="","",ROUND($F6-$G6-$R6,2)) -> 0 | T6: =IF(OR($A6="",$F6=0),"",$R6/$F6) -> 1 | U6: ★示例行，请删除 | V6: =IF($A6="","",$A6&"|"&$B6) -> 2026-09|WX001
C7: =IF($B7="","",IFERROR(VLOOKUP($B7,资产台账!$B$4:$N$53,2,0)&"","台账中未登记")) | D7: =IF($B7="","",IFERROR(VLOOKUP($B7,资产台账!$B$4:$N$53,3,0)&"","")) | E7: =IF($B7="","",IFERROR(VLOOKUP($B7,资产台账!$B$4:$N$53,5,0)&"","")) | R7: =IF($A7="","",SUM(H7:Q7)) | S7: =IF($A7="","",ROUND($F7-$G7-$R7,2)) | T7: =IF(OR($A7="",$F7=0),"",$R7/$F7) | V7: =IF($A7="","",$A7&"|"&$B7)
C8: =IF($B8="","",IFERROR(VLOOKUP($B8,资产台账!$B$4:$N$53,2,0)&"","台账中未登记")) | D8: =IF($B8="","",IFERROR(VLOOKUP($B8,资产台账!$B$4:$N$53,3,0)&"","")) | E8: =IF($B8="","",IFERROR(VLOOKUP($B8,资产台账!$B$4:$N$53,5,0)&"","")) | R8: =IF($A8="","",SUM(H8:Q8)) | S8: =IF($A8="","",ROUND($F8-$G8-$R8,2)) | T8: =IF(OR($A8="",$F8=0),"",$R8/$F8) | V8: =IF($A8="","",$A8&"|"&$B8)
C9: =IF($B9="","",IFERROR(VLOOKUP($B9,资产台账!$B$4:$N$53,2,0)&"","台账中未登记")) | D9: =IF($B9="","",IFERROR(VLOOKUP($B9,资产台账!$B$4:$N$53,3,0)&"","")) | E9: =IF($B9="","",IFERROR(VLOOKUP($B9,资产台账!$B$4:$N$53,5,0)&"","")) | R9: =IF($A9="","",SUM(H9:Q9)) | S9: =IF($A9="","",ROUND($F9-$G9-$R9,2)) | T9: =IF(OR($A9="",$F9=0),"",$R9/$F9) | V9: =IF($A9="","",$A9&"|"&$B9)
C10: =IF($B10="","",IFERROR(VLOOKUP($B10,资产台账!$B$4:$N$53,2,0)&"","台账中未登记")) | D10: =IF($B10="","",IFERROR(VLOOKUP($B10,资产台账!$B$4:$N$53,3,0)&"","")) | E10: =IF($B10="","",IFERROR(VLOOKUP($B10,资产台账!$B$4:$N$53,5,0)&"","")) | R10: =IF($A10="","",SUM(H10:Q10)) | S10: =IF($A10="","",ROUND($F10-$G10-$R10,2)) | T10: =IF(OR($A10="",$F10=0),"",$R10/$F10) | V10: =IF($A10="","",$A10&"|"&$B10)
C11: =IF($B11="","",IFERROR(VLOOKUP($B11,资产台账!$B$4:$N$53,2,0)&"","台账中未登记")) | D11: =IF($B11="","",IFERROR(VLOOKUP($B11,资产台账!$B$4:$N$53,3,0)&"","")) | E11: =IF($B11="","",IFERROR(VLOOKUP($B11,资产台账!$B$4:$N$53,5,0)&"","")) | R11: =IF($A11="","",SUM(H11:Q11)) | S11: =IF($A11="","",ROUND($F11-$G11-$R11,2)) | T11: =IF(OR($A11="",$F11=0),"",$R11/$F11) | V11: =IF($A11="","",$A11&"|"&$B11)
C12: =IF($B12="","",IFERROR(VLOOKUP($B12,资产台账!$B$4:$N$53,2,0)&"","台账中未登记")) | D12: =IF($B12="","",IFERROR(VLOOKUP($B12,资产台账!$B$4:$N$53,3,0)&"","")) | E12: =IF($B12="","",IFERROR(VLOOKUP($B12,资产台账!$B$4:$N$53,5,0)&"","")) | R12: =IF($A12="","",SUM(H12:Q12)) | S12: =IF($A12="","",ROUND($F12-$G12-$R12,2)) | T12: =IF(OR($A12="",$F12=0),"",$R12/$F12) | V12: =IF($A12="","",$A12&"|"&$B12)
C13: =IF($B13="","",IFERROR(VLOOKUP($B13,资产台账!$B$4:$N$53,2,0)&"","台账中未登记")) | D13: =IF($B13="","",IFERROR(VLOOKUP($B13,资产台账!$B$4:$N$53,3,0)&"","")) | E13: =IF($B13="","",IFERROR(VLOOKUP($B13,资产台账!$B$4:$N$53,5,0)&"","")) | R13: =IF($A13="","",SUM(H13:Q13)) | S13: =IF($A13="","",ROUND($F13-$G13-$R13,2)) | T13: =IF(OR($A13="",$F13=0),"",$R13/$F13) | V13: =IF($A13="","",$A13&"|"&$B13)
C14: =IF($B14="","",IFERROR(VLOOKUP($B14,资产台账!$B$4:$N$53,2,0)&"","台账中未登记")) | D14: =IF($B14="","",IFERROR(VLOOKUP($B14,资产台账!$B$4:$N$53,3,0)&"","")) | E14: =IF($B14="","",IFERROR(VLOOKUP($B14,资产台账!$B$4:$N$53,5,0)&"","")) | R14: =IF($A14="","",SUM(H14:Q14)) | S14: =IF($A14="","",ROUND($F14-$G14-$R14,2)) | T14: =IF(OR($A14="",$F14=0),"",$R14/$F14) | V14: =IF($A14="","",$A14&"|"&$B14)
C15: =IF($B15="","",IFERROR(VLOOKUP($B15,资产台账!$B$4:$N$53,2,0)&"","台账中未登记")) | D15: =IF($B15="","",IFERROR(VLOOKUP($B15,资产台账!$B$4:$N$53,3,0)&"","")) | E15: =IF($B15="","",IFERROR(VLOOKUP($B15,资产台账!$B$4:$N$53,5,0)&"","")) | R15: =IF($A15="","",SUM(H15:Q15)) | S15: =IF($A15="","",ROUND($F15-$G15-$R15,2)) | T15: =IF(OR($A15="",$F15=0),"",$R15/$F15) | V15: =IF($A15="","",$A15&"|"&$B15)
C16: =IF($B16="","",IFERROR(VLOOKUP($B16,资产台账!$B$4:$N$53,2,0)&"","台账中未登记")) | D16: =IF($B16="","",IFERROR(VLOOKUP($B16,资产台账!$B$4:$N$53,3,0)&"","")) | E16: =IF($B16="","",IFERROR(VLOOKUP($B16,资产台账!$B$4:$N$53,5,0)&"","")) | R16: =IF($A16="","",SUM(H16:Q16)) | S16: =IF($A16="","",ROUND($F16-$G16-$R16,2)) | T16: =IF(OR($A16="",$F16=0),"",$R16/$F16) | V16: =IF($A16="","",$A16&"|"&$B16)
C17: =IF($B17="","",IFERROR(VLOOKUP($B17,资产台账!$B$4:$N$53,2,0)&"","台账中未登记")) | D17: =IF($B17="","",IFERROR(VLOOKUP($B17,资产台账!$B$4:$N$53,3,0)&"","")) | E17: =IF($B17="","",IFERROR(VLOOKUP($B17,资产台账!$B$4:$N$53,5,0)&"","")) | R17: =IF($A17="","",SUM(H17:Q17)) | S17: =IF($A17="","",ROUND($F17-$G17-$R17,2)) | T17: =IF(OR($A17="",$F17=0),"",$R17/$F17) | V17: =IF($A17="","",$A17&"|"&$B17)
C18: =IF($B18="","",IFERROR(VLOOKUP($B18,资产台账!$B$4:$N$53,2,0)&"","台账中未登记")) | D18: =IF($B18="","",IFERROR(VLOOKUP($B18,资产台账!$B$4:$N$53,3,0)&"","")) | E18: =IF($B18="","",IFERROR(VLOOKUP($B18,资产台账!$B$4:$N$53,5,0)&"","")) | R18: =IF($A18="","",SUM(H18:Q18)) | S18: =IF($A18="","",ROUND($F18-$G18-$R18,2)) | T18: =IF(OR($A18="",$F18=0),"",$R18/$F18) | V18: =IF($A18="","",$A18&"|"&$B18)
... C125: =IF($B125="","",IFERROR(VLOOKUP($B125,资产台账!$B$4:$N$53,2,0)&"","台账中未登记")) | D125: =IF($B125="","",IFERROR(VLOOKUP($B125,资产台账!$B$4:$N$53,3,0)&"","")) | E125: =IF($B125="","",IFERROR(VLOOKUP($B125,资产台账!$B$4:$N$53,5,0)&"","")) | R125: =IF($A125="","",SUM(H125:Q125)) | S125: =IF($A125="","",ROUND($F125-$G125-$R125,2)) | T125: =IF(OR($A125="",$F125=0),"",$R125/$F125) | V125: =IF($A125="","",$A125&"|"&$B125)

Sheet 无形资产费用分配表
A1: 公司 LOGO （选中本区域插入图片） | C1: =IF(使用说明!$B$2="","",使用说明!$B$2&" ")&"十、《无形资产费用分配表》（财务按月按项目核算、按年汇总，2026年度）" -> 十、《无形资产费用分配表》（财务按月按项目核算、按年汇总，2026年度）
A2: 计算依据：当月某项目应分摊的无形资产摊销额 = 该无形资产当月摊销额 ×（该项目使用工时 ÷ 该资产当月总使用工时）。数据来源：摊销数据源自【月度无形资产摊销表】。录入说明：只需录入 A、B 两列（年月、资产编号）；F列“当月摊销额”自动取自【资产台账】，当月实际摊销数不同时可直接覆盖填写；工时及分摊金额由《无形资产工时分配表》按“年月+资产编号”自动匹配取数。
A3: 年月 (YYYY-MM) | B3: 资产编号 | C3: 无形资产名称 | D3: 资产类别 | E3: 费用类型 | F3: 当月摊销额 (元) | G3: 当月总使用 工时 | H3: 研发使用 工时合计 | I3: 研发使用占比 (分摊系数) | J3: 各研发项目分摊无形资产摊销额（元） | T3: 研发摊销费用 小计(元) | U3: 计入生产成本的 摊销额(元) | V3: 数据校验
J4: =项目清单!$B$4 -> RD01 | K4: =项目清单!$B$5 -> RD02 | L4: =项目清单!$B$6 -> RD03 | M4: =项目清单!$B$7 -> RD04 | N4: =项目清单!$B$8 -> RD05 | O4: =项目清单!$B$9 -> RD06 | P4: =项目清单!$B$10 -> RD07 | Q4: =项目清单!$B$11 -> RD08 | R4: =项目清单!$B$12 -> RD09 | S4: =项目清单!$B$13 -> RD10
J5: =IF(J4="","",IFERROR(VLOOKUP(J4,项目清单!$B$4:$C$13,2,0)&"","")) -> 高回弹低压缩永久变形3C用聚氨酯泡棉开发 | K5: =IF(K4="","",IFERROR(VLOOKUP(K4,项目清单!$B$4:$C$13,2,0)&"","")) -> 动力电池模组用高阻燃缓冲泡棉研发 | L5: =IF(L4="","",IFERROR(VLOOKUP(L4,项目清单!$B$4:$C$13,2,0)&"","")) -> 泡棉与PET基材无溶剂贴合工艺开发 | M5: =IF(M4="","",IFERROR(VLOOKUP(M4,项目清单!$B$4:$C$13,2,0)&"","")) -> 超薄泡棉高精度分切及毛边控制技术研究 | N5: =IF(N4="","",IFERROR(VLOOKUP(N4,项目清单!$B$4:$C$13,2,0)&"","")) -> 新能源汽车电池包用导热缓冲复合材料开发 | O5: =IF(O4="","",IFERROR(VLOOKUP(O4,项目清单!$B$4:$C$13,2,0)&"","")) -> 3C电子用超薄黑色遮光泡棉制备技术 | P5: =IF(P4="","",IFERROR(VLOOKUP(P4,项目清单!$B$4:$C$13,2,0)&"","")) -> 环保型水性胶泡棉贴合技术开发 | Q5: =IF(Q4="","",IFERROR(VLOOKUP(Q4,项目清单!$B$4:$C$13,2,0)&"","")) -> 泡棉模切自动化在线检测技术研究 | ... S5: =IF(S4="","",IFERROR(VLOOKUP(S4,项目清单!$B$4:$C$13,2,0)&"","")) | W5: 匹配行号(勿删) | X5: 重复计数(勿删)
A6: 2026-09 | B6: WX001 | C6: =IF($B6="","",IFERROR(VLOOKUP($B6,资产台账!$B$4:$N$53,2,0)&"","台账中未登记")) -> （示例）泡棉配方模拟软件 | D6: =IF($B6="","",IFERROR(VLOOKUP($B6,资产台账!$B$4:$N$53,3,0)&"","")) -> 无形资产 | E6: =IF($B6="","",IFERROR(VLOOKUP($B6,资产台账!$B$4:$N$53,10,0)&"","")) -> 摊销 | F6: =IF($B6="","",IFERROR(VLOOKUP($B6,资产台账!$B$4:$N$53,9,0),0)) -> 4000 | G6: =IF(OR($A6="",$W6=0),0,INDEX(无形资产工时分配表!$F$6:$F$125,$W6)) -> 160 | H6: =IF(OR($A6="",$W6=0),0,INDEX(无形资产工时分配表!$R$6:$R$125,$W6)) -> 160 | I6: =IF(OR($A6="",$G6=0),"",$H6/$G6) -> 1 | J6: =IF(OR($A6="",$G6=0),"",ROUND($F6*INDEX(无形资产工时分配表!$H$6:$H$125,$W6)/$G6,2)) -> 1500 | K6: =IF(OR($A6="",$G6=0),"",ROUND($F6*INDEX(无形资产工时分配表!$I$6:$I$125,$W6)/$G6,2)) -> 1500 | L6: =IF(OR($A6="",$G6=0),"",ROUND($F6*INDEX(无形资产工时分配表!$J$6:$J$125,$W6)/$G6,2)) -> 0 | M6: =IF(OR($A6="",$G6=0),"",ROUND($F6*INDEX(无形资产工时分配表!$K$6:$K$125,$W6)/$G6,2)) -> 0 | N6: =IF(OR($A6="",$G6=0),"",ROUND($F6*INDEX(无形资产工时分配表!$L$6:$L$125,$W6)/$G6,2)) -> 1000 | O6: =IF(OR($A6="",$G6=0),"",ROUND($F6*INDEX(无形资产工时分配表!$M$6:$M$125,$W6)/$G6,2)) -> 0 | P6: =IF(OR($A6="",$G6=0),"",ROUND($F6*INDEX(无形资产工时分配表!$N$6:$N$125,$W6)/$G6,2)) -> 0 | Q6: =IF(OR($A6="",$G6=0),"",ROUND($F6*INDEX(无形资产工时分配表!$O$6:$O$125,$W6)/$G6,2)) -> 0 | R6: =IF(OR($A6="",$G6=0),"",ROUND($F6*INDEX(无形资产工时分配表!$P$6:$P$125,$W6)/$G6,2)) -> 0 | S6: =IF(OR($A6="",$G6=0),"",ROUND($F6*INDEX(无形资产工时分配表!$Q$6:$Q$125,$W6)/$G6,2)) -> 0 | T6: =IF($A6="","",ROUND(SUM(J6:S6),2)) -> 4000 | U6: =IF($A6="","",ROUND($F6-T6,2)) -> 0 | V6: =IF($A6="","",IF($D6="设备","⚠ 设备请在仪器设备工时费用分配表登记",IF($W6=0,"⚠ 工时分配表无此资产当月记录",IF($X6>1,"⚠ 工时分配表存在重复行","√ 正常")))) -> √ 正常 | W6: =IF($A6="",0,IFERROR(MATCH($A6&"|"&$B6,无形资产工时分配表!$V$6:$V$125,0),0)) -> 1 | X6: =IF($A6="",0,COUNTIFS(无形资产工时分配表!$A$6:$A$125,$A6,无形资产工时分配表!$B$6:$B$125,$B6)) -> 1
C7: =IF($B7="","",IFERROR(VLOOKUP($B7,资产台账!$B$4:$N$53,2,0)&"","台账中未登记")) | D7: =IF($B7="","",IFERROR(VLOOKUP($B7,资产台账!$B$4:$N$53,3,0)&"","")) | E7: =IF($B7="","",IFERROR(VLOOKUP($B7,资产台账!$B$4:$N$53,10,0)&"","")) | F7: =IF($B7="","",IFERROR(VLOOKUP($B7,资产台账!$B$4:$N$53,9,0),0)) | G7: =IF(OR($A7="",$W7=0),0,INDEX(无形资产工时分配表!$F$6:$F$125,$W7)) -> 0 | H7: =IF(OR($A7="",$W7=0),0,INDEX(无形资产工时分配表!$R$6:$R$125,$W7)) -> 0 | I7: =IF(OR($A7="",$G7=0),"",$H7/$G7) | J7: =IF(OR($A7="",$G7=0),"",ROUND($F7*INDEX(无形资产工时分配表!$H$6:$H$125,$W7)/$G7,2)) | K7: =IF(OR($A7="",$G7=0),"",ROUND($F7*INDEX(无形资产工时分配表!$I$6:$I$125,$W7)/$G7,2)) | L7: =IF(OR($A7="",$G7=0),"",ROUND($F7*INDEX(无形资产工时分配表!$J$6:$J$125,$W7)/$G7,2)) | M7: =IF(OR($A7="",$G7=0),"",ROUND($F7*INDEX(无形资产工时分配表!$K$6:$K$125,$W7)/$G7,2)) | N7: =IF(OR($A7="",$G7=0),"",ROUND($F7*INDEX(无形资产工时分配表!$L$6:$L$125,$W7)/$G7,2)) | O7: =IF(OR($A7="",$G7=0),"",ROUND($F7*INDEX(无形资产工时分配表!$M$6:$M$125,$W7)/$G7,2)) | P7: =IF(OR($A7="",$G7=0),"",ROUND($F7*INDEX(无形资产工时分配表!$N$6:$N$125,$W7)/$G7,2)) | Q7: =IF(OR($A7="",$G7=0),"",ROUND($F7*INDEX(无形资产工时分配表!$O$6:$O$125,$W7)/$G7,2)) | R7: =IF(OR($A7="",$G7=0),"",ROUND($F7*INDEX(无形资产工时分配表!$P$6:$P$125,$W7)/$G7,2)) | S7: =IF(OR($A7="",$G7=0),"",ROUND($F7*INDEX(无形资产工时分配表!$Q$6:$Q$125,$W7)/$G7,2)) | T7: =IF($A7="","",ROUND(SUM(J7:S7),2)) | U7: =IF($A7="","",ROUND($F7-T7,2)) | V7: =IF($A7="","",IF($D7="设备","⚠ 设备请在仪器设备工时费用分配表登记",IF($W7=0,"⚠ 工时分配表无此资产当月记录",IF($X7>1,"⚠ 工时分配表存在重复行","√ 正常")))) | W7: =IF($A7="",0,IFERROR(MATCH($A7&"|"&$B7,无形资产工时分配表!$V$6:$V$125,0),0)) -> 0 | X7: =IF($A7="",0,COUNTIFS(无形资产工时分配表!$A$6:$A$125,$A7,无形资产工时分配表!$B$6:$B$125,$B7)) -> 0
C8: =IF($B8="","",IFERROR(VLOOKUP($B8,资产台账!$B$4:$N$53,2,0)&"","台账中未登记")) | D8: =IF($B8="","",IFERROR(VLOOKUP($B8,资产台账!$B$4:$N$53,3,0)&"","")) | E8: =IF($B8="","",IFERROR(VLOOKUP($B8,资产台账!$B$4:$N$53,10,0)&"","")) | F8: =IF($B8="","",IFERROR(VLOOKUP($B8,资产台账!$B$4:$N$53,9,0),0)) | G8: =IF(OR($A8="",$W8=0),0,INDEX(无形资产工时分配表!$F$6:$F$125,$W8)) -> 0 | H8: =IF(OR($A8="",$W8=0),0,INDEX(无形资产工时分配表!$R$6:$R$125,$W8)) -> 0 | I8: =IF(OR($A8="",$G8=0),"",$H8/$G8) | J8: =IF(OR($A8="",$G8=0),"",ROUND($F8*INDEX(无形资产工时分配表!$H$6:$H$125,$W8)/$G8,2)) | K8: =IF(OR($A8="",$G8=0),"",ROUND($F8*INDEX(无形资产工时分配表!$I$6:$I$125,$W8)/$G8,2)) | L8: =IF(OR($A8="",$G8=0),"",ROUND($F8*INDEX(无形资产工时分配表!$J$6:$J$125,$W8)/$G8,2)) | M8: =IF(OR($A8="",$G8=0),"",ROUND($F8*INDEX(无形资产工时分配表!$K$6:$K$125,$W8)/$G8,2)) | N8: =IF(OR($A8="",$G8=0),"",ROUND($F8*INDEX(无形资产工时分配表!$L$6:$L$125,$W8)/$G8,2)) | O8: =IF(OR($A8="",$G8=0),"",ROUND($F8*INDEX(无形资产工时分配表!$M$6:$M$125,$W8)/$G8,2)) | P8: =IF(OR($A8="",$G8=0),"",ROUND($F8*INDEX(无形资产工时分配表!$N$6:$N$125,$W8)/$G8,2)) | Q8: =IF(OR($A8="",$G8=0),"",ROUND($F8*INDEX(无形资产工时分配表!$O$6:$O$125,$W8)/$G8,2)) | R8: =IF(OR($A8="",$G8=0),"",ROUND($F8*INDEX(无形资产工时分配表!$P$6:$P$125,$W8)/$G8,2)) | S8: =IF(OR($A8="",$G8=0),"",ROUND($F8*INDEX(无形资产工时分配表!$Q$6:$Q$125,$W8)/$G8,2)) | T8: =IF($A8="","",ROUND(SUM(J8:S8),2)) | U8: =IF($A8="","",ROUND($F8-T8,2)) | V8: =IF($A8="","",IF($D8="设备","⚠ 设备请在仪器设备工时费用分配表登记",IF($W8=0,"⚠ 工时分配表无此资产当月记录",IF($X8>1,"⚠ 工时分配表存在重复行","√ 正常")))) | W8: =IF($A8="",0,IFERROR(MATCH($A8&"|"&$B8,无形资产工时分配表!$V$6:$V$125,0),0)) -> 0 | X8: =IF($A8="",0,COUNTIFS(无形资产工时分配表!$A$6:$A$125,$A8,无形资产工时分配表!$B$6:$B$125,$B8)) -> 0
C9: =IF($B9="","",IFERROR(VLOOKUP($B9,资产台账!$B$4:$N$53,2,0)&"","台账中未登记")) | D9: =IF($B9="","",IFERROR(VLOOKUP($B9,资产台账!$B$4:$N$53,3,0)&"","")) | E9: =IF($B9="","",IFERROR(VLOOKUP($B9,资产台账!$B$4:$N$53,10,0)&"","")) | F9: =IF($B9="","",IFERROR(VLOOKUP($B9,资产台账!$B$4:$N$53,9,0),0)) | G9: =IF(OR($A9="",$W9=0),0,INDEX(无形资产工时分配表!$F$6:$F$125,$W9)) -> 0 | H9: =IF(OR($A9="",$W9=0),0,INDEX(无形资产工时分配表!$R$6:$R$125,$W9)) -> 0 | I9: =IF(OR($A9="",$G9=0),"",$H9/$G9) | J9: =IF(OR($A9="",$G9=0),"",ROUND($F9*INDEX(无形资产工时分配表!$H$6:$H$125,$W9)/$G9,2)) | K9: =IF(OR($A9="",$G9=0),"",ROUND($F9*INDEX(无形资产工时分配表!$I$6:$I$125,$W9)/$G9,2)) | L9: =IF(OR($A9="",$G9=0),"",ROUND($F9*INDEX(无形资产工时分配表!$J$6:$J$125,$W9)/$G9,2)) | M9: =IF(OR($A9="",$G9=0),"",ROUND($F9*INDEX(无形资产工时分配表!$K$6:$K$125,$W9)/$G9,2)) | N9: =IF(OR($A9="",$G9=0),"",ROUND($F9*INDEX(无形资产工时分配表!$L$6:$L$125,$W9)/$G9,2)) | O9: =IF(OR($A9="",$G9=0),"",ROUND($F9*INDEX(无形资产工时分配表!$M$6:$M$125,$W9)/$G9,2)) | P9: =IF(OR($A9="",$G9=0),"",ROUND($F9*INDEX(无形资产工时分配表!$N$6:$N$125,$W9)/$G9,2)) | Q9: =IF(OR($A9="",$G9=0),"",ROUND($F9*INDEX(无形资产工时分配表!$O$6:$O$125,$W9)/$G9,2)) | R9: =IF(OR($A9="",$G9=0),"",ROUND($F9*INDEX(无形资产工时分配表!$P$6:$P$125,$W9)/$G9,2)) | S9: =IF(OR($A9="",$G9=0),"",ROUND($F9*INDEX(无形资产工时分配表!$Q$6:$Q$125,$W9)/$G9,2)) | T9: =IF($A9="","",ROUND(SUM(J9:S9),2)) | U9: =IF($A9="","",ROUND($F9-T9,2)) | V9: =IF($A9="","",IF($D9="设备","⚠ 设备请在仪器设备工时费用分配表登记",IF($W9=0,"⚠ 工时分配表无此资产当月记录",IF($X9>1,"⚠ 工时分配表存在重复行","√ 正常")))) | W9: =IF($A9="",0,IFERROR(MATCH($A9&"|"&$B9,无形资产工时分配表!$V$6:$V$125,0),0)) -> 0 | X9: =IF($A9="",0,COUNTIFS(无形资产工时分配表!$A$6:$A$125,$A9,无形资产工时分配表!$B$6:$B$125,$B9)) -> 0
C10: =IF($B10="","",IFERROR(VLOOKUP($B10,资产台账!$B$4:$N$53,2,0)&"","台账中未登记")) | D10: =IF($B10="","",IFERROR(VLOOKUP($B10,资产台账!$B$4:$N$53,3,0)&"","")) | E10: =IF($B10="","",IFERROR(VLOOKUP($B10,资产台账!$B$4:$N$53,10,0)&"","")) | F10: =IF($B10="","",IFERROR(VLOOKUP($B10,资产台账!$B$4:$N$53,9,0),0)) | G10: =IF(OR($A10="",$W10=0),0,INDEX(无形资产工时分配表!$F$6:$F$125,$W10)) -> 0 | H10: =IF(OR($A10="",$W10=0),0,INDEX(无形资产工时分配表!$R$6:$R$125,$W10)) -> 0 | I10: =IF(OR($A10="",$G10=0),"",$H10/$G10) | J10: =IF(OR($A10="",$G10=0),"",ROUND($F10*INDEX(无形资产工时分配表!$H$6:$H$125,$W10)/$G10,2)) | K10: =IF(OR($A10="",$G10=0),"",ROUND($F10*INDEX(无形资产工时分配表!$I$6:$I$125,$W10)/$G10,2)) | L10: =IF(OR($A10="",$G10=0),"",ROUND($F10*INDEX(无形资产工时分配表!$J$6:$J$125,$W10)/$G10,2)) | M10: =IF(OR($A10="",$G10=0),"",ROUND($F10*INDEX(无形资产工时分配表!$K$6:$K$125,$W10)/$G10,2)) | N10: =IF(OR($A10="",$G10=0),"",ROUND($F10*INDEX(无形资产工时分配表!$L$6:$L$125,$W10)/$G10,2)) | O10: =IF(OR($A10="",$G10=0),"",ROUND($F10*INDEX(无形资产工时分配表!$M$6:$M$125,$W10)/$G10,2)) | P10: =IF(OR($A10="",$G10=0),"",ROUND($F10*INDEX(无形资产工时分配表!$N$6:$N$125,$W10)/$G10,2)) | Q10: =IF(OR($A10="",$G10=0),"",ROUND($F10*INDEX(无形资产工时分配表!$O$6:$O$125,$W10)/$G10,2)) | R10: =IF(OR($A10="",$G10=0),"",ROUND($F10*INDEX(无形资产工时分配表!$P$6:$P$125,$W10)/$G10,2)) | S10: =IF(OR($A10="",$G10=0),"",ROUND($F10*INDEX(无形资产工时分配表!$Q$6:$Q$125,$W10)/$G10,2)) | T10: =IF($A10="","",ROUND(SUM(J10:S10),2)) | U10: =IF($A10="","",ROUND($F10-T10,2)) | V10: =IF($A10="","",IF($D10="设备","⚠ 设备请在仪器设备工时费用分配表登记",IF($W10=0,"⚠ 工时分配表无此资产当月记录",IF($X10>1,"⚠ 工时分配表存在重复行","√ 正常")))) | W10: =IF($A10="",0,IFERROR(MATCH($A10&"|"&$B10,无形资产工时分配表!$V$6:$V$125,0),0)) -> 0 | X10: =IF($A10="",0,COUNTIFS(无形资产工时分配表!$A$6:$A$125,$A10,无形资产工时分配表!$B$6:$B$125,$B10)) -> 0
C11: =IF($B11="","",IFERROR(VLOOKUP($B11,资产台账!$B$4:$N$53,2,0)&"","台账中未登记")) | D11: =IF($B11="","",IFERROR(VLOOKUP($B11,资产台账!$B$4:$N$53,3,0)&"","")) | E11: =IF($B11="","",IFERROR(VLOOKUP($B11,资产台账!$B$4:$N$53,10,0)&"","")) | F11: =IF($B11="","",IFERROR(VLOOKUP($B11,资产台账!$B$4:$N$53,9,0),0)) | G11: =IF(OR($A11="",$W11=0),0,INDEX(无形资产工时分配表!$F$6:$F$125,$W11)) -> 0 | H11: =IF(OR($A11="",$W11=0),0,INDEX(无形资产工时分配表!$R$6:$R$125,$W11)) -> 0 | I11: =IF(OR($A11="",$G11=0),"",$H11/$G11) | J11: =IF(OR($A11="",$G11=0),"",ROUND($F11*INDEX(无形资产工时分配表!$H$6:$H$125,$W11)/$G11,2)) | K11: =IF(OR($A11="",$G11=0),"",ROUND($F11*INDEX(无形资产工时分配表!$I$6:$I$125,$W11)/$G11,2)) | L11: =IF(OR($A11="",$G11=0),"",ROUND($F11*INDEX(无形资产工时分配表!$J$6:$J$125,$W11)/$G11,2)) | M11: =IF(OR($A11="",$G11=0),"",ROUND($F11*INDEX(无形资产工时分配表!$K$6:$K$125,$W11)/$G11,2)) | N11: =IF(OR($A11="",$G11=0),"",ROUND($F11*INDEX(无形资产工时分配表!$L$6:$L$125,$W11)/$G11,2)) | O11: =IF(OR($A11="",$G11=0),"",ROUND($F11*INDEX(无形资产工时分配表!$M$6:$M$125,$W11)/$G11,2)) | P11: =IF(OR($A11="",$G11=0),"",ROUND($F11*INDEX(无形资产工时分配表!$N$6:$N$125,$W11)/$G11,2)) | Q11: =IF(OR($A11="",$G11=0),"",ROUND($F11*INDEX(无形资产工时分配表!$O$6:$O$125,$W11)/$G11,2)) | R11: =IF(OR($A11="",$G11=0),"",ROUND($F11*INDEX(无形资产工时分配表!$P$6:$P$125,$W11)/$G11,2)) | S11: =IF(OR($A11="",$G11=0),"",ROUND($F11*INDEX(无形资产工时分配表!$Q$6:$Q$125,$W11)/$G11,2)) | T11: =IF($A11="","",ROUND(SUM(J11:S11),2)) | U11: =IF($A11="","",ROUND($F11-T11,2)) | V11: =IF($A11="","",IF($D11="设备","⚠ 设备请在仪器设备工时费用分配表登记",IF($W11=0,"⚠ 工时分配表无此资产当月记录",IF($X11>1,"⚠ 工时分配表存在重复行","√ 正常")))) | W11: =IF($A11="",0,IFERROR(MATCH($A11&"|"&$B11,无形资产工时分配表!$V$6:$V$125,0),0)) -> 0 | X11: =IF($A11="",0,COUNTIFS(无形资产工时分配表!$A$6:$A$125,$A11,无形资产工时分配表!$B$6:$B$125,$B11)) -> 0
C12: =IF($B12="","",IFERROR(VLOOKUP($B12,资产台账!$B$4:$N$53,2,0)&"","台账中未登记")) | D12: =IF($B12="","",IFERROR(VLOOKUP($B12,资产台账!$B$4:$N$53,3,0)&"","")) | E12: =IF($B12="","",IFERROR(VLOOKUP($B12,资产台账!$B$4:$N$53,10,0)&"","")) | F12: =IF($B12="","",IFERROR(VLOOKUP($B12,资产台账!$B$4:$N$53,9,0),0)) | G12: =IF(OR($A12="",$W12=0),0,INDEX(无形资产工时分配表!$F$6:$F$125,$W12)) -> 0 | H12: =IF(OR($A12="",$W12=0),0,INDEX(无形资产工时分配表!$R$6:$R$125,$W12)) -> 0 | I12: =IF(OR($A12="",$G12=0),"",$H12/$G12) | J12: =IF(OR($A12="",$G12=0),"",ROUND($F12*INDEX(无形资产工时分配表!$H$6:$H$125,$W12)/$G12,2)) | K12: =IF(OR($A12="",$G12=0),"",ROUND($F12*INDEX(无形资产工时分配表!$I$6:$I$125,$W12)/$G12,2)) | L12: =IF(OR($A12="",$G12=0),"",ROUND($F12*INDEX(无形资产工时分配表!$J$6:$J$125,$W12)/$G12,2)) | M12: =IF(OR($A12="",$G12=0),"",ROUND($F12*INDEX(无形资产工时分配表!$K$6:$K$125,$W12)/$G12,2)) | N12: =IF(OR($A12="",$G12=0),"",ROUND($F12*INDEX(无形资产工时分配表!$L$6:$L$125,$W12)/$G12,2)) | O12: =IF(OR($A12="",$G12=0),"",ROUND($F12*INDEX(无形资产工时分配表!$M$6:$M$125,$W12)/$G12,2)) | P12: =IF(OR($A12="",$G12=0),"",ROUND($F12*INDEX(无形资产工时分配表!$N$6:$N$125,$W12)/$G12,2)) | Q12: =IF(OR($A12="",$G12=0),"",ROUND($F12*INDEX(无形资产工时分配表!$O$6:$O$125,$W12)/$G12,2)) | R12: =IF(OR($A12="",$G12=0),"",ROUND($F12*INDEX(无形资产工时分配表!$P$6:$P$125,$W12)/$G12,2)) | S12: =IF(OR($A12="",$G12=0),"",ROUND($F12*INDEX(无形资产工时分配表!$Q$6:$Q$125,$W12)/$G12,2)) | T12: =IF($A12="","",ROUND(SUM(J12:S12),2)) | U12: =IF($A12="","",ROUND($F12-T12,2)) | V12: =IF($A12="","",IF($D12="设备","⚠ 设备请在仪器设备工时费用分配表登记",IF($W12=0,"⚠ 工时分配表无此资产当月记录",IF($X12>1,"⚠ 工时分配表存在重复行","√ 正常")))) | W12: =IF($A12="",0,IFERROR(MATCH($A12&"|"&$B12,无形资产工时分配表!$V$6:$V$125,0),0)) -> 0 | X12: =IF($A12="",0,COUNTIFS(无形资产工时分配表!$A$6:$A$125,$A12,无形资产工时分配表!$B$6:$B$125,$B12)) -> 0
C13: =IF($B13="","",IFERROR(VLOOKUP($B13,资产台账!$B$4:$N$53,2,0)&"","台账中未登记")) | D13: =IF($B13="","",IFERROR(VLOOKUP($B13,资产台账!$B$4:$N$53,3,0)&"","")) | E13: =IF($B13="","",IFERROR(VLOOKUP($B13,资产台账!$B$4:$N$53,10,0)&"","")) | F13: =IF($B13="","",IFERROR(VLOOKUP($B13,资产台账!$B$4:$N$53,9,0),0)) | G13: =IF(OR($A13="",$W13=0),0,INDEX(无形资产工时分配表!$F$6:$F$125,$W13)) -> 0 | H13: =IF(OR($A13="",$W13=0),0,INDEX(无形资产工时分配表!$R$6:$R$125,$W13)) -> 0 | I13: =IF(OR($A13="",$G13=0),"",$H13/$G13) | J13: =IF(OR($A13="",$G13=0),"",ROUND($F13*INDEX(无形资产工时分配表!$H$6:$H$125,$W13)/$G13,2)) | K13: =IF(OR($A13="",$G13=0),"",ROUND($F13*INDEX(无形资产工时分配表!$I$6:$I$125,$W13)/$G13,2)) | L13: =IF(OR($A13="",$G13=0),"",ROUND($F13*INDEX(无形资产工时分配表!$J$6:$J$125,$W13)/$G13,2)) | M13: =IF(OR($A13="",$G13=0),"",ROUND($F13*INDEX(无形资产工时分配表!$K$6:$K$125,$W13)/$G13,2)) | N13: =IF(OR($A13="",$G13=0),"",ROUND($F13*INDEX(无形资产工时分配表!$L$6:$L$125,$W13)/$G13,2)) | O13: =IF(OR($A13="",$G13=0),"",ROUND($F13*INDEX(无形资产工时分配表!$M$6:$M$125,$W13)/$G13,2)) | P13: =IF(OR($A13="",$G13=0),"",ROUND($F13*INDEX(无形资产工时分配表!$N$6:$N$125,$W13)/$G13,2)) | Q13: =IF(OR($A13="",$G13=0),"",ROUND($F13*INDEX(无形资产工时分配表!$O$6:$O$125,$W13)/$G13,2)) | R13: =IF(OR($A13="",$G13=0),"",ROUND($F13*INDEX(无形资产工时分配表!$P$6:$P$125,$W13)/$G13,2)) | S13: =IF(OR($A13="",$G13=0),"",ROUND($F13*INDEX(无形资产工时分配表!$Q$6:$Q$125,$W13)/$G13,2)) | T13: =IF($A13="","",ROUND(SUM(J13:S13),2)) | U13: =IF($A13="","",ROUND($F13-T13,2)) | V13: =IF($A13="","",IF($D13="设备","⚠ 设备请在仪器设备工时费用分配表登记",IF($W13=0,"⚠ 工时分配表无此资产当月记录",IF($X13>1,"⚠ 工时分配表存在重复行","√ 正常")))) | W13: =IF($A13="",0,IFERROR(MATCH($A13&"|"&$B13,无形资产工时分配表!$V$6:$V$125,0),0)) -> 0 | X13: =IF($A13="",0,COUNTIFS(无形资产工时分配表!$A$6:$A$125,$A13,无形资产工时分配表!$B$6:$B$125,$B13)) -> 0
C14: =IF($B14="","",IFERROR(VLOOKUP($B14,资产台账!$B$4:$N$53,2,0)&"","台账中未登记")) | D14: =IF($B14="","",IFERROR(VLOOKUP($B14,资产台账!$B$4:$N$53,3,0)&"","")) | E14: =IF($B14="","",IFERROR(VLOOKUP($B14,资产台账!$B$4:$N$53,10,0)&"","")) | F14: =IF($B14="","",IFERROR(VLOOKUP($B14,资产台账!$B$4:$N$53,9,0),0)) | G14: =IF(OR($A14="",$W14=0),0,INDEX(无形资产工时分配表!$F$6:$F$125,$W14)) -> 0 | H14: =IF(OR($A14="",$W14=0),0,INDEX(无形资产工时分配表!$R$6:$R$125,$W14)) -> 0 | I14: =IF(OR($A14="",$G14=0),"",$H14/$G14) | J14: =IF(OR($A14="",$G14=0),"",ROUND($F14*INDEX(无形资产工时分配表!$H$6:$H$125,$W14)/$G14,2)) | K14: =IF(OR($A14="",$G14=0),"",ROUND($F14*INDEX(无形资产工时分配表!$I$6:$I$125,$W14)/$G14,2)) | L14: =IF(OR($A14="",$G14=0),"",ROUND($F14*INDEX(无形资产工时分配表!$J$6:$J$125,$W14)/$G14,2)) | M14: =IF(OR($A14="",$G14=0),"",ROUND($F14*INDEX(无形资产工时分配表!$K$6:$K$125,$W14)/$G14,2)) | N14: =IF(OR($A14="",$G14=0),"",ROUND($F14*INDEX(无形资产工时分配表!$L$6:$L$125,$W14)/$G14,2)) | O14: =IF(OR($A14="",$G14=0),"",ROUND($F14*INDEX(无形资产工时分配表!$M$6:$M$125,$W14)/$G14,2)) | P14: =IF(OR($A14="",$G14=0),"",ROUND($F14*INDEX(无形资产工时分配表!$N$6:$N$125,$W14)/$G14,2)) | Q14: =IF(OR($A14="",$G14=0),"",ROUND($F14*INDEX(无形资产工时分配表!$O$6:$O$125,$W14)/$G14,2)) | R14: =IF(OR($A14="",$G14=0),"",ROUND($F14*INDEX(无形资产工时分配表!$P$6:$P$125,$W14)/$G14,2)) | S14: =IF(OR($A14="",$G14=0),"",ROUND($F14*INDEX(无形资产工时分配表!$Q$6:$Q$125,$W14)/$G14,2)) | T14: =IF($A14="","",ROUND(SUM(J14:S14),2)) | U14: =IF($A14="","",ROUND($F14-T14,2)) | V14: =IF($A14="","",IF($D14="设备","⚠ 设备请在仪器设备工时费用分配表登记",IF($W14=0,"⚠ 工时分配表无此资产当月记录",IF($X14>1,"⚠ 工时分配表存在重复行","√ 正常")))) | W14: =IF($A14="",0,IFERROR(MATCH($A14&"|"&$B14,无形资产工时分配表!$V$6:$V$125,0),0)) -> 0 | X14: =IF($A14="",0,COUNTIFS(无形资产工时分配表!$A$6:$A$125,$A14,无形资产工时分配表!$B$6:$B$125,$B14)) -> 0
C15: =IF($B15="","",IFERROR(VLOOKUP($B15,资产台账!$B$4:$N$53,2,0)&"","台账中未登记")) | D15: =IF($B15="","",IFERROR(VLOOKUP($B15,资产台账!$B$4:$N$53,3,0)&"","")) | E15: =IF($B15="","",IFERROR(VLOOKUP($B15,资产台账!$B$4:$N$53,10,0)&"","")) | F15: =IF($B15="","",IFERROR(VLOOKUP($B15,资产台账!$B$4:$N$53,9,0),0)) | G15: =IF(OR($A15="",$W15=0),0,INDEX(无形资产工时分配表!$F$6:$F$125,$W15)) -> 0 | H15: =IF(OR($A15="",$W15=0),0,INDEX(无形资产工时分配表!$R$6:$R$125,$W15)) -> 0 | I15: =IF(OR($A15="",$G15=0),"",$H15/$G15) | J15: =IF(OR($A15="",$G15=0),"",ROUND($F15*INDEX(无形资产工时分配表!$H$6:$H$125,$W15)/$G15,2)) | K15: =IF(OR($A15="",$G15=0),"",ROUND($F15*INDEX(无形资产工时分配表!$I$6:$I$125,$W15)/$G15,2)) | L15: =IF(OR($A15="",$G15=0),"",ROUND($F15*INDEX(无形资产工时分配表!$J$6:$J$125,$W15)/$G15,2)) | M15: =IF(OR($A15="",$G15=0),"",ROUND($F15*INDEX(无形资产工时分配表!$K$6:$K$125,$W15)/$G15,2)) | N15: =IF(OR($A15="",$G15=0),"",ROUND($F15*INDEX(无形资产工时分配表!$L$6:$L$125,$W15)/$G15,2)) | O15: =IF(OR($A15="",$G15=0),"",ROUND($F15*INDEX(无形资产工时分配表!$M$6:$M$125,$W15)/$G15,2)) | P15: =IF(OR($A15="",$G15=0),"",ROUND($F15*INDEX(无形资产工时分配表!$N$6:$N$125,$W15)/$G15,2)) | Q15: =IF(OR($A15="",$G15=0),"",ROUND($F15*INDEX(无形资产工时分配表!$O$6:$O$125,$W15)/$G15,2)) | R15: =IF(OR($A15="",$G15=0),"",ROUND($F15*INDEX(无形资产工时分配表!$P$6:$P$125,$W15)/$G15,2)) | S15: =IF(OR($A15="",$G15=0),"",ROUND($F15*INDEX(无形资产工时分配表!$Q$6:$Q$125,$W15)/$G15,2)) | T15: =IF($A15="","",ROUND(SUM(J15:S15),2)) | U15: =IF($A15="","",ROUND($F15-T15,2)) | V15: =IF($A15="","",IF($D15="设备","⚠ 设备请在仪器设备工时费用分配表登记",IF($W15=0,"⚠ 工时分配表无此资产当月记录",IF($X15>1,"⚠ 工时分配表存在重复行","√ 正常")))) | W15: =IF($A15="",0,IFERROR(MATCH($A15&"|"&$B15,无形资产工时分配表!$V$6:$V$125,0),0)) -> 0 | X15: =IF($A15="",0,COUNTIFS(无形资产工时分配表!$A$6:$A$125,$A15,无形资产工时分配表!$B$6:$B$125,$B15)) -> 0
C16: =IF($B16="","",IFERROR(VLOOKUP($B16,资产台账!$B$4:$N$53,2,0)&"","台账中未登记")) | D16: =IF($B16="","",IFERROR(VLOOKUP($B16,资产台账!$B$4:$N$53,3,0)&"","")) | E16: =IF($B16="","",IFERROR(VLOOKUP($B16,资产台账!$B$4:$N$53,10,0)&"","")) | F16: =IF($B16="","",IFERROR(VLOOKUP($B16,资产台账!$B$4:$N$53,9,0),0)) | G16: =IF(OR($A16="",$W16=0),0,INDEX(无形资产工时分配表!$F$6:$F$125,$W16)) -> 0 | H16: =IF(OR($A16="",$W16=0),0,INDEX(无形资产工时分配表!$R$6:$R$125,$W16)) -> 0 | I16: =IF(OR($A16="",$G16=0),"",$H16/$G16) | J16: =IF(OR($A16="",$G16=0),"",ROUND($F16*INDEX(无形资产工时分配表!$H$6:$H$125,$W16)/$G16,2)) | K16: =IF(OR($A16="",$G16=0),"",ROUND($F16*INDEX(无形资产工时分配表!$I$6:$I$125,$W16)/$G16,2)) | L16: =IF(OR($A16="",$G16=0),"",ROUND($F16*INDEX(无形资产工时分配表!$J$6:$J$125,$W16)/$G16,2)) | M16: =IF(OR($A16="",$G16=0),"",ROUND($F16*INDEX(无形资产工时分配表!$K$6:$K$125,$W16)/$G16,2)) | N16: =IF(OR($A16="",$G16=0),"",ROUND($F16*INDEX(无形资产工时分配表!$L$6:$L$125,$W16)/$G16,2)) | O16: =IF(OR($A16="",$G16=0),"",ROUND($F16*INDEX(无形资产工时分配表!$M$6:$M$125,$W16)/$G16,2)) | P16: =IF(OR($A16="",$G16=0),"",ROUND($F16*INDEX(无形资产工时分配表!$N$6:$N$125,$W16)/$G16,2)) | Q16: =IF(OR($A16="",$G16=0),"",ROUND($F16*INDEX(无形资产工时分配表!$O$6:$O$125,$W16)/$G16,2)) | R16: =IF(OR($A16="",$G16=0),"",ROUND($F16*INDEX(无形资产工时分配表!$P$6:$P$125,$W16)/$G16,2)) | S16: =IF(OR($A16="",$G16=0),"",ROUND($F16*INDEX(无形资产工时分配表!$Q$6:$Q$125,$W16)/$G16,2)) | T16: =IF($A16="","",ROUND(SUM(J16:S16),2)) | U16: =IF($A16="","",ROUND($F16-T16,2)) | V16: =IF($A16="","",IF($D16="设备","⚠ 设备请在仪器设备工时费用分配表登记",IF($W16=0,"⚠ 工时分配表无此资产当月记录",IF($X16>1,"⚠ 工时分配表存在重复行","√ 正常")))) | W16: =IF($A16="",0,IFERROR(MATCH($A16&"|"&$B16,无形资产工时分配表!$V$6:$V$125,0),0)) -> 0 | X16: =IF($A16="",0,COUNTIFS(无形资产工时分配表!$A$6:$A$125,$A16,无形资产工时分配表!$B$6:$B$125,$B16)) -> 0
C17: =IF($B17="","",IFERROR(VLOOKUP($B17,资产台账!$B$4:$N$53,2,0)&"","台账中未登记")) | D17: =IF($B17="","",IFERROR(VLOOKUP($B17,资产台账!$B$4:$N$53,3,0)&"","")) | E17: =IF($B17="","",IFERROR(VLOOKUP($B17,资产台账!$B$4:$N$53,10,0)&"","")) | F17: =IF($B17="","",IFERROR(VLOOKUP($B17,资产台账!$B$4:$N$53,9,0),0)) | G17: =IF(OR($A17="",$W17=0),0,INDEX(无形资产工时分配表!$F$6:$F$125,$W17)) -> 0 | H17: =IF(OR($A17="",$W17=0),0,INDEX(无形资产工时分配表!$R$6:$R$125,$W17)) -> 0 | I17: =IF(OR($A17="",$G17=0),"",$H17/$G17) | J17: =IF(OR($A17="",$G17=0),"",ROUND($F17*INDEX(无形资产工时分配表!$H$6:$H$125,$W17)/$G17,2)) | K17: =IF(OR($A17="",$G17=0),"",ROUND($F17*INDEX(无形资产工时分配表!$I$6:$I$125,$W17)/$G17,2)) | L17: =IF(OR($A17="",$G17=0),"",ROUND($F17*INDEX(无形资产工时分配表!$J$6:$J$125,$W17)/$G17,2)) | M17: =IF(OR($A17="",$G17=0),"",ROUND($F17*INDEX(无形资产工时分配表!$K$6:$K$125,$W17)/$G17,2)) | N17: =IF(OR($A17="",$G17=0),"",ROUND($F17*INDEX(无形资产工时分配表!$L$6:$L$125,$W17)/$G17,2)) | O17: =IF(OR($A17="",$G17=0),"",ROUND($F17*INDEX(无形资产工时分配表!$M$6:$M$125,$W17)/$G17,2)) | P17: =IF(OR($A17="",$G17=0),"",ROUND($F17*INDEX(无形资产工时分配表!$N$6:$N$125,$W17)/$G17,2)) | Q17: =IF(OR($A17="",$G17=0),"",ROUND($F17*INDEX(无形资产工时分配表!$O$6:$O$125,$W17)/$G17,2)) | R17: =IF(OR($A17="",$G17=0),"",ROUND($F17*INDEX(无形资产工时分配表!$P$6:$P$125,$W17)/$G17,2)) | S17: =IF(OR($A17="",$G17=0),"",ROUND($F17*INDEX(无形资产工时分配表!$Q$6:$Q$125,$W17)/$G17,2)) | T17: =IF($A17="","",ROUND(SUM(J17:S17),2)) | U17: =IF($A17="","",ROUND($F17-T17,2)) | V17: =IF($A17="","",IF($D17="设备","⚠ 设备请在仪器设备工时费用分配表登记",IF($W17=0,"⚠ 工时分配表无此资产当月记录",IF($X17>1,"⚠ 工时分配表存在重复行","√ 正常")))) | W17: =IF($A17="",0,IFERROR(MATCH($A17&"|"&$B17,无形资产工时分配表!$V$6:$V$125,0),0)) -> 0 | X17: =IF($A17="",0,COUNTIFS(无形资产工时分配表!$A$6:$A$125,$A17,无形资产工时分配表!$B$6:$B$125,$B17)) -> 0
C18: =IF($B18="","",IFERROR(VLOOKUP($B18,资产台账!$B$4:$N$53,2,0)&"","台账中未登记")) | D18: =IF($B18="","",IFERROR(VLOOKUP($B18,资产台账!$B$4:$N$53,3,0)&"","")) | E18: =IF($B18="","",IFERROR(VLOOKUP($B18,资产台账!$B$4:$N$53,10,0)&"","")) | F18: =IF($B18="","",IFERROR(VLOOKUP($B18,资产台账!$B$4:$N$53,9,0),0)) | G18: =IF(OR($A18="",$W18=0),0,INDEX(无形资产工时分配表!$F$6:$F$125,$W18)) -> 0 | H18: =IF(OR($A18="",$W18=0),0,INDEX(无形资产工时分配表!$R$6:$R$125,$W18)) -> 0 | I18: =IF(OR($A18="",$G18=0),"",$H18/$G18) | J18: =IF(OR($A18="",$G18=0),"",ROUND($F18*INDEX(无形资产工时分配表!$H$6:$H$125,$W18)/$G18,2)) | K18: =IF(OR($A18="",$G18=0),"",ROUND($F18*INDEX(无形资产工时分配表!$I$6:$I$125,$W18)/$G18,2)) | L18: =IF(OR($A18="",$G18=0),"",ROUND($F18*INDEX(无形资产工时分配表!$J$6:$J$125,$W18)/$G18,2)) | M18: =IF(OR($A18="",$G18=0),"",ROUND($F18*INDEX(无形资产工时分配表!$K$6:$K$125,$W18)/$G18,2)) | N18: =IF(OR($A18="",$G18=0),"",ROUND($F18*INDEX(无形资产工时分配表!$L$6:$L$125,$W18)/$G18,2)) | O18: =IF(OR($A18="",$G18=0),"",ROUND($F18*INDEX(无形资产工时分配表!$M$6:$M$125,$W18)/$G18,2)) | P18: =IF(OR($A18="",$G18=0),"",ROUND($F18*INDEX(无形资产工时分配表!$N$6:$N$125,$W18)/$G18,2)) | Q18: =IF(OR($A18="",$G18=0),"",ROUND($F18*INDEX(无形资产工时分配表!$O$6:$O$125,$W18)/$G18,2)) | R18: =IF(OR($A18="",$G18=0),"",ROUND($F18*INDEX(无形资产工时分配表!$P$6:$P$125,$W18)/$G18,2)) | S18: =IF(OR($A18="",$G18=0),"",ROUND($F18*INDEX(无形资产工时分配表!$Q$6:$Q$125,$W18)/$G18,2)) | T18: =IF($A18="","",ROUND(SUM(J18:S18),2)) | U18: =IF($A18="","",ROUND($F18-T18,2)) | V18: =IF($A18="","",IF($D18="设备","⚠ 设备请在仪器设备工时费用分配表登记",IF($W18=0,"⚠ 工时分配表无此资产当月记录",IF($X18>1,"⚠ 工时分配表存在重复行","√ 正常")))) | W18: =IF($A18="",0,IFERROR(MATCH($A18&"|"&$B18,无形资产工时分配表!$V$6:$V$125,0),0)) -> 0 | X18: =IF($A18="",0,COUNTIFS(无形资产工时分配表!$A$6:$A$125,$A18,无形资产工时分配表!$B$6:$B$125,$B18)) -> 0
... C125: =IF($B125="","",IFERROR(VLOOKUP($B125,资产台账!$B$4:$N$53,2,0)&"","台账中未登记")) | D125: =IF($B125="","",IFERROR(VLOOKUP($B125,资产台账!$B$4:$N$53,3,0)&"","")) | E125: =IF($B125="","",IFERROR(VLOOKUP($B125,资产台账!$B$4:$N$53,10,0)&"","")) | F125: =IF($B125="","",IFERROR(VLOOKUP($B125,资产台账!$B$4:$N$53,9,0),0)) | G125: =IF(OR($A125="",$W125=0),0,INDEX(无形资产工时分配表!$F$6:$F$125,$W125)) -> 0 | H125: =IF(OR($A125="",$W125=0),0,INDEX(无形资产工时分配表!$R$6:$R$125,$W125)) -> 0 | I125: =IF(OR($A125="",$G125=0),"",$H125/$G125) | J125: =IF(OR($A125="",$G125=0),"",ROUND($F125*INDEX(无形资产工时分配表!$H$6:$H$125,$W125)/$G125,2)) | K125: =IF(OR($A125="",$G125=0),"",ROUND($F125*INDEX(无形资产工时分配表!$I$6:$I$125,$W125)/$G125,2)) | L125: =IF(OR($A125="",$G125=0),"",ROUND($F125*INDEX(无形资产工时分配表!$J$6:$J$125,$W125)/$G125,2)) | M125: =IF(OR($A125="",$G125=0),"",ROUND($F125*INDEX(无形资产工时分配表!$K$6:$K$125,$W125)/$G125,2)) | N125: =IF(OR($A125="",$G125=0),"",ROUND($F125*INDEX(无形资产工时分配表!$L$6:$L$125,$W125)/$G125,2)) | O125: =IF(OR($A125="",$G125=0),"",ROUND($F125*INDEX(无形资产工时分配表!$M$6:$M$125,$W125)/$G125,2)) | P125: =IF(OR($A125="",$G125=0),"",ROUND($F125*INDEX(无形资产工时分配表!$N$6:$N$125,$W125)/$G125,2)) | Q125: =IF(OR($A125="",$G125=0),"",ROUND($F125*INDEX(无形资产工时分配表!$O$6:$O$125,$W125)/$G125,2)) | R125: =IF(OR($A125="",$G125=0),"",ROUND($F125*INDEX(无形资产工时分配表!$P$6:$P$125,$W125)/$G125,2)) | S125: =IF(OR($A125="",$G125=0),"",ROUND($F125*INDEX(无形资产工时分配表!$Q$6:$Q$125,$W125)/$G125,2)) | T125: =IF($A125="","",ROUND(SUM(J125:S125),2)) | U125: =IF($A125="","",ROUND($F125-T125,2)) | V125: =IF($A125="","",IF($D125="设备","⚠ 设备请在仪器设备工时费用分配表登记",IF($W125=0,"⚠ 工时分配表无此资产当月记录",IF($X125>1,"⚠ 工时分配表存在重复行","√ 正常")))) | W125: =IF($A125="",0,IFERROR(MATCH($A125&"|"&$B125,无形资产工时分配表!$V$6:$V$125,0),0)) -> 0 | X125: =IF($A125="",0,COUNTIFS(无形资产工时分配表!$A$6:$A$125,$A125,无形资产工时分配表!$B$6:$B$125,$B125)) -> 0

Sheet 其他研发费用
A1: 公司 LOGO （选中本区域插入图片） | C1: =IF(使用说明!$B$2="","",使用说明!$B$2&" ")&"十一、其他研发费用登记表（直接投入/设计费/其他相关费用/委外研发） —— 选填" -> 十一、其他研发费用登记表（直接投入/设计费/其他相关费用/委外研发） —— 选填
A2: 填写说明：本表用于登记除人工费、折旧摊销外可直接归属到项目的研发费用（如试验用泡棉原料、PET基材、胶粘剂、燃料动力、样品模具、委外检测与委托研发等），逐笔登记并注明凭证号，自动汇总至【月度归集汇总】。费用类别请从下拉菜单选择，口径与研发费用加计扣除政策一致。
A3: 年月 | B3: 项目编号 | C3: 研发项目名称 | D3: 费用类别 | E3: 费用内容摘要 | F3: 金额(元) | G3: 记账凭证号 | H3: 备注
A4: 2026-09 | B4: RD02 | C4: =IF($B4="","",IFERROR(VLOOKUP($B4,项目清单!$B$4:$C$13,2,0)&"","清单中未登记")) -> 动力电池模组用高阻燃缓冲泡棉研发 | D4: 直接投入费用 | E4: 无卤阻燃母粒及试验用聚醚多元醇（第3批小试） | F4: 12600 | G4: 记-09-0186 | H4: ★示例行，请删除
A5: 2026-09 | B5: RD03 | C5: =IF($B5="","",IFERROR(VLOOKUP($B5,项目清单!$B$4:$C$13,2,0)&"","清单中未登记")) -> 泡棉与PET基材无溶剂贴合工艺开发 | D5: 委托外部研发费用 | E5: 委托XX大学开展无溶剂贴合剥离强度机理测试 | F5: 30000 | G5: 记-09-0212 | H5: ★示例行，请删除
A6: 2026-09 | B6: RD04 | C6: =IF($B6="","",IFERROR(VLOOKUP($B6,项目清单!$B$4:$C$13,2,0)&"","清单中未登记")) -> 超薄泡棉高精度分切及毛边控制技术研究 | D6: 直接投入费用 | E6: 分切刀具试验损耗及试切PET复合泡棉料带 | F6: 8450 | G6: 记-09-0233 | H6: ★示例行，请删除
C7: =IF($B7="","",IFERROR(VLOOKUP($B7,项目清单!$B$4:$C$13,2,0)&"","清单中未登记"))
C8: =IF($B8="","",IFERROR(VLOOKUP($B8,项目清单!$B$4:$C$13,2,0)&"","清单中未登记"))
C9: =IF($B9="","",IFERROR(VLOOKUP($B9,项目清单!$B$4:$C$13,2,0)&"","清单中未登记"))
C10: =IF($B10="","",IFERROR(VLOOKUP($B10,项目清单!$B$4:$C$13,2,0)&"","清单中未登记"))
C11: =IF($B11="","",IFERROR(VLOOKUP($B11,项目清单!$B$4:$C$13,2,0)&"","清单中未登记"))
C12: =IF($B12="","",IFERROR(VLOOKUP($B12,项目清单!$B$4:$C$13,2,0)&"","清单中未登记"))
C13: =IF($B13="","",IFERROR(VLOOKUP($B13,项目清单!$B$4:$C$13,2,0)&"","清单中未登记"))
C14: =IF($B14="","",IFERROR(VLOOKUP($B14,项目清单!$B$4:$C$13,2,0)&"","清单中未登记"))
C15: =IF($B15="","",IFERROR(VLOOKUP($B15,项目清单!$B$4:$C$13,2,0)&"","清单中未登记"))
C16: =IF($B16="","",IFERROR(VLOOKUP($B16,项目清单!$B$4:$C$13,2,0)&"","清单中未登记"))
C17: =IF($B17="","",IFERROR(VLOOKUP($B17,项目清单!$B$4:$C$13,2,0)&"","清单中未登记"))
C18: =IF($B18="","",IFERROR(VLOOKUP($B18,项目清单!$B$4:$C$13,2,0)&"","清单中未登记"))
... C153: =IF($B153="","",IFERROR(VLOOKUP($B153,项目清单!$B$4:$C$13,2,0)&"","清单中未登记"))

Sheet 月度归集汇总
A1: 公司 LOGO （选中本区域插入图片） | C1: =IF(使用说明!$B$2="","",使用说明!$B$2&" ")&"十二、研发费用月度归集汇总表（2026年度，按项目·按月）" -> 十二、研发费用月度归集汇总表（2026年度，按项目·按月）
A2: 本表全部为公式自动汇总，请勿手工修改。费用类别口径与《研发费用加计扣除》一致，可直接与研发支出辅助账、“研发支出”科目明细账逐月核对。末两列同步列示当月归集的研发人员工时与设备使用工时，作为费用分配的量化依据。
A3: 年月 | B3: 项目编号 | C3: 研发项目名称 | D3: 人员人工费用 | E3: 折旧费用 | F3: 无形资产摊销 | G3: 直接投入费用 | H3: 新产品设计费等 | I3: 其他相关费用 | J3: 委托外部研发费用 | K3: 本月研发费用合计 | L3: 研发人员工时 (小时) | M3: 设备使用工时 (小时)
A4: 2026-01 | B4: =项目清单!$B$4 -> RD01 | C4: =IF($B4="","",IFERROR(VLOOKUP($B4,项目清单!$B$4:$C$13,2,0)&"","")) -> 高回弹低压缩永久变形3C用聚氨酯泡棉开发 | D4: =SUMIFS(研发人员工时费用分配表!$N$6:$N$245,研发人员工时费用分配表!$A$6:$A$245,$A4) -> 0 | E4: =SUMIFS(仪器设备工时费用分配表!$J$6:$J$245,仪器设备工时费用分配表!$A$6:$A$245,$A4,仪器设备工时费用分配表!$D$6:$D$245,"设备") -> 0 | F4: =SUMIFS(无形资产费用分配表!$J$6:$J$125,无形资产费用分配表!$A$6:$A$125,$A4) -> 0 | G4: =SUMIFS(其他研发费用!$F$4:$F$153,其他研发费用!$A$4:$A$153,$A4,其他研发费用!$B$4:$B$153,$B4,其他研发费用!$D$4:$D$153,"直接投入费用") -> 0 | H4: =SUMIFS(其他研发费用!$F$4:$F$153,其他研发费用!$A$4:$A$153,$A4,其他研发费用!$B$4:$B$153,$B4,其他研发费用!$D$4:$D$153,"新产品设计费等") -> 0 | I4: =SUMIFS(其他研发费用!$F$4:$F$153,其他研发费用!$A$4:$A$153,$A4,其他研发费用!$B$4:$B$153,$B4,其他研发费用!$D$4:$D$153,"其他相关费用") -> 0 | J4: =SUMIFS(其他研发费用!$F$4:$F$153,其他研发费用!$A$4:$A$153,$A4,其他研发费用!$B$4:$B$153,$B4,其他研发费用!$D$4:$D$153,"委托外部研发费用") -> 0 | K4: =ROUND(SUM(D4:J4),2) -> 0 | L4: =SUMIFS(研发人员工时分配表!$H$6:$H$245,研发人员工时分配表!$A$6:$A$245,$A4) -> 0 | M4: =SUMIFS(仪器设备工时分配表!$H$6:$H$245,仪器设备工时分配表!$A$6:$A$245,$A4) -> 0
A5: 2026-01 | B5: =项目清单!$B$5 -> RD02 | C5: =IF($B5="","",IFERROR(VLOOKUP($B5,项目清单!$B$4:$C$13,2,0)&"","")) -> 动力电池模组用高阻燃缓冲泡棉研发 | D5: =SUMIFS(研发人员工时费用分配表!$O$6:$O$245,研发人员工时费用分配表!$A$6:$A$245,$A5) -> 0 | E5: =SUMIFS(仪器设备工时费用分配表!$K$6:$K$245,仪器设备工时费用分配表!$A$6:$A$245,$A5,仪器设备工时费用分配表!$D$6:$D$245,"设备") -> 0 | F5: =SUMIFS(无形资产费用分配表!$K$6:$K$125,无形资产费用分配表!$A$6:$A$125,$A5) -> 0 | G5: =SUMIFS(其他研发费用!$F$4:$F$153,其他研发费用!$A$4:$A$153,$A5,其他研发费用!$B$4:$B$153,$B5,其他研发费用!$D$4:$D$153,"直接投入费用") -> 0 | H5: =SUMIFS(其他研发费用!$F$4:$F$153,其他研发费用!$A$4:$A$153,$A5,其他研发费用!$B$4:$B$153,$B5,其他研发费用!$D$4:$D$153,"新产品设计费等") -> 0 | I5: =SUMIFS(其他研发费用!$F$4:$F$153,其他研发费用!$A$4:$A$153,$A5,其他研发费用!$B$4:$B$153,$B5,其他研发费用!$D$4:$D$153,"其他相关费用") -> 0 | J5: =SUMIFS(其他研发费用!$F$4:$F$153,其他研发费用!$A$4:$A$153,$A5,其他研发费用!$B$4:$B$153,$B5,其他研发费用!$D$4:$D$153,"委托外部研发费用") -> 0 | K5: =ROUND(SUM(D5:J5),2) -> 0 | L5: =SUMIFS(研发人员工时分配表!$I$6:$I$245,研发人员工时分配表!$A$6:$A$245,$A5) -> 0 | M5: =SUMIFS(仪器设备工时分配表!$I$6:$I$245,仪器设备工时分配表!$A$6:$A$245,$A5) -> 0
A6: 2026-01 | B6: =项目清单!$B$6 -> RD03 | C6: =IF($B6="","",IFERROR(VLOOKUP($B6,项目清单!$B$4:$C$13,2,0)&"","")) -> 泡棉与PET基材无溶剂贴合工艺开发 | D6: =SUMIFS(研发人员工时费用分配表!$P$6:$P$245,研发人员工时费用分配表!$A$6:$A$245,$A6) -> 0 | E6: =SUMIFS(仪器设备工时费用分配表!$L$6:$L$245,仪器设备工时费用分配表!$A$6:$A$245,$A6,仪器设备工时费用分配表!$D$6:$D$245,"设备") -> 0 | F6: =SUMIFS(无形资产费用分配表!$L$6:$L$125,无形资产费用分配表!$A$6:$A$125,$A6) -> 0 | G6: =SUMIFS(其他研发费用!$F$4:$F$153,其他研发费用!$A$4:$A$153,$A6,其他研发费用!$B$4:$B$153,$B6,其他研发费用!$D$4:$D$153,"直接投入费用") -> 0 | H6: =SUMIFS(其他研发费用!$F$4:$F$153,其他研发费用!$A$4:$A$153,$A6,其他研发费用!$B$4:$B$153,$B6,其他研发费用!$D$4:$D$153,"新产品设计费等") -> 0 | I6: =SUMIFS(其他研发费用!$F$4:$F$153,其他研发费用!$A$4:$A$153,$A6,其他研发费用!$B$4:$B$153,$B6,其他研发费用!$D$4:$D$153,"其他相关费用") -> 0 | J6: =SUMIFS(其他研发费用!$F$4:$F$153,其他研发费用!$A$4:$A$153,$A6,其他研发费用!$B$4:$B$153,$B6,其他研发费用!$D$4:$D$153,"委托外部研发费用") -> 0 | K6: =ROUND(SUM(D6:J6),2) -> 0 | L6: =SUMIFS(研发人员工时分配表!$J$6:$J$245,研发人员工时分配表!$A$6:$A$245,$A6) -> 0 | M6: =SUMIFS(仪器设备工时分配表!$J$6:$J$245,仪器设备工时分配表!$A$6:$A$245,$A6) -> 0
A7: 2026-01 | B7: =项目清单!$B$7 -> RD04 | C7: =IF($B7="","",IFERROR(VLOOKUP($B7,项目清单!$B$4:$C$13,2,0)&"","")) -> 超薄泡棉高精度分切及毛边控制技术研究 | D7: =SUMIFS(研发人员工时费用分配表!$Q$6:$Q$245,研发人员工时费用分配表!$A$6:$A$245,$A7) -> 0 | E7: =SUMIFS(仪器设备工时费用分配表!$M$6:$M$245,仪器设备工时费用分配表!$A$6:$A$245,$A7,仪器设备工时费用分配表!$D$6:$D$245,"设备") -> 0 | F7: =SUMIFS(无形资产费用分配表!$M$6:$M$125,无形资产费用分配表!$A$6:$A$125,$A7) -> 0 | G7: =SUMIFS(其他研发费用!$F$4:$F$153,其他研发费用!$A$4:$A$153,$A7,其他研发费用!$B$4:$B$153,$B7,其他研发费用!$D$4:$D$153,"直接投入费用") -> 0 | H7: =SUMIFS(其他研发费用!$F$4:$F$153,其他研发费用!$A$4:$A$153,$A7,其他研发费用!$B$4:$B$153,$B7,其他研发费用!$D$4:$D$153,"新产品设计费等") -> 0 | I7: =SUMIFS(其他研发费用!$F$4:$F$153,其他研发费用!$A$4:$A$153,$A7,其他研发费用!$B$4:$B$153,$B7,其他研发费用!$D$4:$D$153,"其他相关费用") -> 0 | J7: =SUMIFS(其他研发费用!$F$4:$F$153,其他研发费用!$A$4:$A$153,$A7,其他研发费用!$B$4:$B$153,$B7,其他研发费用!$D$4:$D$153,"委托外部研发费用") -> 0 | K7: =ROUND(SUM(D7:J7),2) -> 0 | L7: =SUMIFS(研发人员工时分配表!$K$6:$K$245,研发人员工时分配表!$A$6:$A$245,$A7) -> 0 | M7: =SUMIFS(仪器设备工时分配表!$K$6:$K$245,仪器设备工时分配表!$A$6:$A$245,$A7) -> 0
A8: 2026-01 | B8: =项目清单!$B$8 -> RD05 | C8: =IF($B8="","",IFERROR(VLOOKUP($B8,项目清单!$B$4:$C$13,2,0)&"","")) -> 新能源汽车电池包用导热缓冲复合材料开发 | D8: =SUMIFS(研发人员工时费用分配表!$R$6:$R$245,研发人员工时费用分配表!$A$6:$A$245,$A8) -> 0 | E8: =SUMIFS(仪器设备工时费用分配表!$N$6:$N$245,仪器设备工时费用分配表!$A$6:$A$245,$A8,仪器设备工时费用分配表!$D$6:$D$245,"设备") -> 0 | F8: =SUMIFS(无形资产费用分配表!$N$6:$N$125,无形资产费用分配表!$A$6:$A$125,$A8) -> 0 | G8: =SUMIFS(其他研发费用!$F$4:$F$153,其他研发费用!$A$4:$A$153,$A8,其他研发费用!$B$4:$B$153,$B8,其他研发费用!$D$4:$D$153,"直接投入费用") -> 0 | H8: =SUMIFS(其他研发费用!$F$4:$F$153,其他研发费用!$A$4:$A$153,$A8,其他研发费用!$B$4:$B$153,$B8,其他研发费用!$D$4:$D$153,"新产品设计费等") -> 0 | I8: =SUMIFS(其他研发费用!$F$4:$F$153,其他研发费用!$A$4:$A$153,$A8,其他研发费用!$B$4:$B$153,$B8,其他研发费用!$D$4:$D$153,"其他相关费用") -> 0 | J8: =SUMIFS(其他研发费用!$F$4:$F$153,其他研发费用!$A$4:$A$153,$A8,其他研发费用!$B$4:$B$153,$B8,其他研发费用!$D$4:$D$153,"委托外部研发费用") -> 0 | K8: =ROUND(SUM(D8:J8),2) -> 0 | L8: =SUMIFS(研发人员工时分配表!$L$6:$L$245,研发人员工时分配表!$A$6:$A$245,$A8) -> 0 | M8: =SUMIFS(仪器设备工时分配表!$L$6:$L$245,仪器设备工时分配表!$A$6:$A$245,$A8) -> 0
A9: 2026-01 | B9: =项目清单!$B$9 -> RD06 | C9: =IF($B9="","",IFERROR(VLOOKUP($B9,项目清单!$B$4:$C$13,2,0)&"","")) -> 3C电子用超薄黑色遮光泡棉制备技术 | D9: =SUMIFS(研发人员工时费用分配表!$S$6:$S$245,研发人员工时费用分配表!$A$6:$A$245,$A9) -> 0 | E9: =SUMIFS(仪器设备工时费用分配表!$O$6:$O$245,仪器设备工时费用分配表!$A$6:$A$245,$A9,仪器设备工时费用分配表!$D$6:$D$245,"设备") -> 0 | F9: =SUMIFS(无形资产费用分配表!$O$6:$O$125,无形资产费用分配表!$A$6:$A$125,$A9) -> 0 | G9: =SUMIFS(其他研发费用!$F$4:$F$153,其他研发费用!$A$4:$A$153,$A9,其他研发费用!$B$4:$B$153,$B9,其他研发费用!$D$4:$D$153,"直接投入费用") -> 0 | H9: =SUMIFS(其他研发费用!$F$4:$F$153,其他研发费用!$A$4:$A$153,$A9,其他研发费用!$B$4:$B$153,$B9,其他研发费用!$D$4:$D$153,"新产品设计费等") -> 0 | I9: =SUMIFS(其他研发费用!$F$4:$F$153,其他研发费用!$A$4:$A$153,$A9,其他研发费用!$B$4:$B$153,$B9,其他研发费用!$D$4:$D$153,"其他相关费用") -> 0 | J9: =SUMIFS(其他研发费用!$F$4:$F$153,其他研发费用!$A$4:$A$153,$A9,其他研发费用!$B$4:$B$153,$B9,其他研发费用!$D$4:$D$153,"委托外部研发费用") -> 0 | K9: =ROUND(SUM(D9:J9),2) -> 0 | L9: =SUMIFS(研发人员工时分配表!$M$6:$M$245,研发人员工时分配表!$A$6:$A$245,$A9) -> 0 | M9: =SUMIFS(仪器设备工时分配表!$M$6:$M$245,仪器设备工时分配表!$A$6:$A$245,$A9) -> 0
A10: 2026-01 | B10: =项目清单!$B$10 -> RD07 | C10: =IF($B10="","",IFERROR(VLOOKUP($B10,项目清单!$B$4:$C$13,2,0)&"","")) -> 环保型水性胶泡棉贴合技术开发 | D10: =SUMIFS(研发人员工时费用分配表!$T$6:$T$245,研发人员工时费用分配表!$A$6:$A$245,$A10) -> 0 | E10: =SUMIFS(仪器设备工时费用分配表!$P$6:$P$245,仪器设备工时费用分配表!$A$6:$A$245,$A10,仪器设备工时费用分配表!$D$6:$D$245,"设备") -> 0 | F10: =SUMIFS(无形资产费用分配表!$P$6:$P$125,无形资产费用分配表!$A$6:$A$125,$A10) -> 0 | G10: =SUMIFS(其他研发费用!$F$4:$F$153,其他研发费用!$A$4:$A$153,$A10,其他研发费用!$B$4:$B$153,$B10,其他研发费用!$D$4:$D$153,"直接投入费用") -> 0 | H10: =SUMIFS(其他研发费用!$F$4:$F$153,其他研发费用!$A$4:$A$153,$A10,其他研发费用!$B$4:$B$153,$B10,其他研发费用!$D$4:$D$153,"新产品设计费等") -> 0 | I10: =SUMIFS(其他研发费用!$F$4:$F$153,其他研发费用!$A$4:$A$153,$A10,其他研发费用!$B$4:$B$153,$B10,其他研发费用!$D$4:$D$153,"其他相关费用") -> 0 | J10: =SUMIFS(其他研发费用!$F$4:$F$153,其他研发费用!$A$4:$A$153,$A10,其他研发费用!$B$4:$B$153,$B10,其他研发费用!$D$4:$D$153,"委托外部研发费用") -> 0 | K10: =ROUND(SUM(D10:J10),2) -> 0 | L10: =SUMIFS(研发人员工时分配表!$N$6:$N$245,研发人员工时分配表!$A$6:$A$245,$A10) -> 0 | M10: =SUMIFS(仪器设备工时分配表!$N$6:$N$245,仪器设备工时分配表!$A$6:$A$245,$A10) -> 0
A11: 2026-01 | B11: =项目清单!$B$11 -> RD08 | C11: =IF($B11="","",IFERROR(VLOOKUP($B11,项目清单!$B$4:$C$13,2,0)&"","")) -> 泡棉模切自动化在线检测技术研究 | D11: =SUMIFS(研发人员工时费用分配表!$U$6:$U$245,研发人员工时费用分配表!$A$6:$A$245,$A11) -> 0 | E11: =SUMIFS(仪器设备工时费用分配表!$Q$6:$Q$245,仪器设备工时费用分配表!$A$6:$A$245,$A11,仪器设备工时费用分配表!$D$6:$D$245,"设备") -> 0 | F11: =SUMIFS(无形资产费用分配表!$Q$6:$Q$125,无形资产费用分配表!$A$6:$A$125,$A11) -> 0 | G11: =SUMIFS(其他研发费用!$F$4:$F$153,其他研发费用!$A$4:$A$153,$A11,其他研发费用!$B$4:$B$153,$B11,其他研发费用!$D$4:$D$153,"直接投入费用") -> 0 | H11: =SUMIFS(其他研发费用!$F$4:$F$153,其他研发费用!$A$4:$A$153,$A11,其他研发费用!$B$4:$B$153,$B11,其他研发费用!$D$4:$D$153,"新产品设计费等") -> 0 | I11: =SUMIFS(其他研发费用!$F$4:$F$153,其他研发费用!$A$4:$A$153,$A11,其他研发费用!$B$4:$B$153,$B11,其他研发费用!$D$4:$D$153,"其他相关费用") -> 0 | J11: =SUMIFS(其他研发费用!$F$4:$F$153,其他研发费用!$A$4:$A$153,$A11,其他研发费用!$B$4:$B$153,$B11,其他研发费用!$D$4:$D$153,"委托外部研发费用") -> 0 | K11: =ROUND(SUM(D11:J11),2) -> 0 | L11: =SUMIFS(研发人员工时分配表!$O$6:$O$245,研发人员工时分配表!$A$6:$A$245,$A11) -> 0 | M11: =SUMIFS(仪器设备工时分配表!$O$6:$O$245,仪器设备工时分配表!$A$6:$A$245,$A11) -> 0
A12: 2026-01 | B12: =项目清单!$B$12 -> RD09 | C12: =IF($B12="","",IFERROR(VLOOKUP($B12,项目清单!$B$4:$C$13,2,0)&"","")) | D12: =SUMIFS(研发人员工时费用分配表!$V$6:$V$245,研发人员工时费用分配表!$A$6:$A$245,$A12) -> 0 | E12: =SUMIFS(仪器设备工时费用分配表!$R$6:$R$245,仪器设备工时费用分配表!$A$6:$A$245,$A12,仪器设备工时费用分配表!$D$6:$D$245,"设备") -> 0 | F12: =SUMIFS(无形资产费用分配表!$R$6:$R$125,无形资产费用分配表!$A$6:$A$125,$A12) -> 0 | G12: =SUMIFS(其他研发费用!$F$4:$F$153,其他研发费用!$A$4:$A$153,$A12,其他研发费用!$B$4:$B$153,$B12,其他研发费用!$D$4:$D$153,"直接投入费用") -> 0 | H12: =SUMIFS(其他研发费用!$F$4:$F$153,其他研发费用!$A$4:$A$153,$A12,其他研发费用!$B$4:$B$153,$B12,其他研发费用!$D$4:$D$153,"新产品设计费等") -> 0 | I12: =SUMIFS(其他研发费用!$F$4:$F$153,其他研发费用!$A$4:$A$153,$A12,其他研发费用!$B$4:$B$153,$B12,其他研发费用!$D$4:$D$153,"其他相关费用") -> 0 | J12: =SUMIFS(其他研发费用!$F$4:$F$153,其他研发费用!$A$4:$A$153,$A12,其他研发费用!$B$4:$B$153,$B12,其他研发费用!$D$4:$D$153,"委托外部研发费用") -> 0 | K12: =ROUND(SUM(D12:J12),2) -> 0 | L12: =SUMIFS(研发人员工时分配表!$P$6:$P$245,研发人员工时分配表!$A$6:$A$245,$A12) -> 0 | M12: =SUMIFS(仪器设备工时分配表!$P$6:$P$245,仪器设备工时分配表!$A$6:$A$245,$A12) -> 0
A13: 2026-01 | B13: =项目清单!$B$13 -> RD10 | C13: =IF($B13="","",IFERROR(VLOOKUP($B13,项目清单!$B$4:$C$13,2,0)&"","")) | D13: =SUMIFS(研发人员工时费用分配表!$W$6:$W$245,研发人员工时费用分配表!$A$6:$A$245,$A13) -> 0 | E13: =SUMIFS(仪器设备工时费用分配表!$S$6:$S$245,仪器设备工时费用分配表!$A$6:$A$245,$A13,仪器设备工时费用分配表!$D$6:$D$245,"设备") -> 0 | F13: =SUMIFS(无形资产费用分配表!$S$6:$S$125,无形资产费用分配表!$A$6:$A$125,$A13) -> 0 | G13: =SUMIFS(其他研发费用!$F$4:$F$153,其他研发费用!$A$4:$A$153,$A13,其他研发费用!$B$4:$B$153,$B13,其他研发费用!$D$4:$D$153,"直接投入费用") -> 0 | H13: =SUMIFS(其他研发费用!$F$4:$F$153,其他研发费用!$A$4:$A$153,$A13,其他研发费用!$B$4:$B$153,$B13,其他研发费用!$D$4:$D$153,"新产品设计费等") -> 0 | I13: =SUMIFS(其他研发费用!$F$4:$F$153,其他研发费用!$A$4:$A$153,$A13,其他研发费用!$B$4:$B$153,$B13,其他研发费用!$D$4:$D$153,"其他相关费用") -> 0 | J13: =SUMIFS(其他研发费用!$F$4:$F$153,其他研发费用!$A$4:$A$153,$A13,其他研发费用!$B$4:$B$153,$B13,其他研发费用!$D$4:$D$153,"委托外部研发费用") -> 0 | K13: =ROUND(SUM(D13:J13),2) -> 0 | L13: =SUMIFS(研发人员工时分配表!$Q$6:$Q$245,研发人员工时分配表!$A$6:$A$245,$A13) -> 0 | M13: =SUMIFS(仪器设备工时分配表!$Q$6:$Q$245,仪器设备工时分配表!$A$6:$A$245,$A13) -> 0
A14: 2026-01 | C14: 本月合计 | D14: =ROUND(SUM(D4:D13),2) -> 0 | E14: =ROUND(SUM(E4:E13),2) -> 0 | F14: =ROUND(SUM(F4:F13),2) -> 0 | G14: =ROUND(SUM(G4:G13),2) -> 0 | H14: =ROUND(SUM(H4:H13),2) -> 0 | I14: =ROUND(SUM(I4:I13),2) -> 0 | J14: =ROUND(SUM(J4:J13),2) -> 0 | K14: =ROUND(SUM(K4:K13),2) -> 0 | ... M14: =ROUND(SUM(M4:M13),2) -> 0
A15: 2026-02 | B15: =项目清单!$B$4 -> RD01 | C15: =IF($B15="","",IFERROR(VLOOKUP($B15,项目清单!$B$4:$C$13,2,0)&"","")) -> 高回弹低压缩永久变形3C用聚氨酯泡棉开发 | D15: =SUMIFS(研发人员工时费用分配表!$N$6:$N$245,研发人员工时费用分配表!$A$6:$A$245,$A15) -> 0 | E15: =SUMIFS(仪器设备工时费用分配表!$J$6:$J$245,仪器设备工时费用分配表!$A$6:$A$245,$A15,仪器设备工时费用分配表!$D$6:$D$245,"设备") -> 0 | F15: =SUMIFS(无形资产费用分配表!$J$6:$J$125,无形资产费用分配表!$A$6:$A$125,$A15) -> 0 | G15: =SUMIFS(其他研发费用!$F$4:$F$153,其他研发费用!$A$4:$A$153,$A15,其他研发费用!$B$4:$B$153,$B15,其他研发费用!$D$4:$D$153,"直接投入费用") -> 0 | H15: =SUMIFS(其他研发费用!$F$4:$F$153,其他研发费用!$A$4:$A$153,$A15,其他研发费用!$B$4:$B$153,$B15,其他研发费用!$D$4:$D$153,"新产品设计费等") -> 0 | I15: =SUMIFS(其他研发费用!$F$4:$F$153,其他研发费用!$A$4:$A$153,$A15,其他研发费用!$B$4:$B$153,$B15,其他研发费用!$D$4:$D$153,"其他相关费用") -> 0 | J15: =SUMIFS(其他研发费用!$F$4:$F$153,其他研发费用!$A$4:$A$153,$A15,其他研发费用!$B$4:$B$153,$B15,其他研发费用!$D$4:$D$153,"委托外部研发费用") -> 0 | K15: =ROUND(SUM(D15:J15),2) -> 0 | L15: =SUMIFS(研发人员工时分配表!$H$6:$H$245,研发人员工时分配表!$A$6:$A$245,$A15) -> 0 | M15: =SUMIFS(仪器设备工时分配表!$H$6:$H$245,仪器设备工时分配表!$A$6:$A$245,$A15) -> 0
A16: 2026-02 | B16: =项目清单!$B$5 -> RD02 | C16: =IF($B16="","",IFERROR(VLOOKUP($B16,项目清单!$B$4:$C$13,2,0)&"","")) -> 动力电池模组用高阻燃缓冲泡棉研发 | D16: =SUMIFS(研发人员工时费用分配表!$O$6:$O$245,研发人员工时费用分配表!$A$6:$A$245,$A16) -> 0 | E16: =SUMIFS(仪器设备工时费用分配表!$K$6:$K$245,仪器设备工时费用分配表!$A$6:$A$245,$A16,仪器设备工时费用分配表!$D$6:$D$245,"设备") -> 0 | F16: =SUMIFS(无形资产费用分配表!$K$6:$K$125,无形资产费用分配表!$A$6:$A$125,$A16) -> 0 | G16: =SUMIFS(其他研发费用!$F$4:$F$153,其他研发费用!$A$4:$A$153,$A16,其他研发费用!$B$4:$B$153,$B16,其他研发费用!$D$4:$D$153,"直接投入费用") -> 0 | H16: =SUMIFS(其他研发费用!$F$4:$F$153,其他研发费用!$A$4:$A$153,$A16,其他研发费用!$B$4:$B$153,$B16,其他研发费用!$D$4:$D$153,"新产品设计费等") -> 0 | I16: =SUMIFS(其他研发费用!$F$4:$F$153,其他研发费用!$A$4:$A$153,$A16,其他研发费用!$B$4:$B$153,$B16,其他研发费用!$D$4:$D$153,"其他相关费用") -> 0 | J16: =SUMIFS(其他研发费用!$F$4:$F$153,其他研发费用!$A$4:$A$153,$A16,其他研发费用!$B$4:$B$153,$B16,其他研发费用!$D$4:$D$153,"委托外部研发费用") -> 0 | K16: =ROUND(SUM(D16:J16),2) -> 0 | L16: =SUMIFS(研发人员工时分配表!$I$6:$I$245,研发人员工时分配表!$A$6:$A$245,$A16) -> 0 | M16: =SUMIFS(仪器设备工时分配表!$I$6:$I$245,仪器设备工时分配表!$A$6:$A$245,$A16) -> 0
A17: 2026-02 | B17: =项目清单!$B$6 -> RD03 | C17: =IF($B17="","",IFERROR(VLOOKUP($B17,项目清单!$B$4:$C$13,2,0)&"","")) -> 泡棉与PET基材无溶剂贴合工艺开发 | D17: =SUMIFS(研发人员工时费用分配表!$P$6:$P$245,研发人员工时费用分配表!$A$6:$A$245,$A17) -> 0 | E17: =SUMIFS(仪器设备工时费用分配表!$L$6:$L$245,仪器设备工时费用分配表!$A$6:$A$245,$A17,仪器设备工时费用分配表!$D$6:$D$245,"设备") -> 0 | F17: =SUMIFS(无形资产费用分配表!$L$6:$L$125,无形资产费用分配表!$A$6:$A$125,$A17) -> 0 | G17: =SUMIFS(其他研发费用!$F$4:$F$153,其他研发费用!$A$4:$A$153,$A17,其他研发费用!$B$4:$B$153,$B17,其他研发费用!$D$4:$D$153,"直接投入费用") -> 0 | H17: =SUMIFS(其他研发费用!$F$4:$F$153,其他研发费用!$A$4:$A$153,$A17,其他研发费用!$B$4:$B$153,$B17,其他研发费用!$D$4:$D$153,"新产品设计费等") -> 0 | I17: =SUMIFS(其他研发费用!$F$4:$F$153,其他研发费用!$A$4:$A$153,$A17,其他研发费用!$B$4:$B$153,$B17,其他研发费用!$D$4:$D$153,"其他相关费用") -> 0 | J17: =SUMIFS(其他研发费用!$F$4:$F$153,其他研发费用!$A$4:$A$153,$A17,其他研发费用!$B$4:$B$153,$B17,其他研发费用!$D$4:$D$153,"委托外部研发费用") -> 0 | K17: =ROUND(SUM(D17:J17),2) -> 0 | L17: =SUMIFS(研发人员工时分配表!$J$6:$J$245,研发人员工时分配表!$A$6:$A$245,$A17) -> 0 | M17: =SUMIFS(仪器设备工时分配表!$J$6:$J$245,仪器设备工时分配表!$A$6:$A$245,$A17) -> 0
A18: 2026-02 | B18: =项目清单!$B$7 -> RD04 | C18: =IF($B18="","",IFERROR(VLOOKUP($B18,项目清单!$B$4:$C$13,2,0)&"","")) -> 超薄泡棉高精度分切及毛边控制技术研究 | D18: =SUMIFS(研发人员工时费用分配表!$Q$6:$Q$245,研发人员工时费用分配表!$A$6:$A$245,$A18) -> 0 | E18: =SUMIFS(仪器设备工时费用分配表!$M$6:$M$245,仪器设备工时费用分配表!$A$6:$A$245,$A18,仪器设备工时费用分配表!$D$6:$D$245,"设备") -> 0 | F18: =SUMIFS(无形资产费用分配表!$M$6:$M$125,无形资产费用分配表!$A$6:$A$125,$A18) -> 0 | G18: =SUMIFS(其他研发费用!$F$4:$F$153,其他研发费用!$A$4:$A$153,$A18,其他研发费用!$B$4:$B$153,$B18,其他研发费用!$D$4:$D$153,"直接投入费用") -> 0 | H18: =SUMIFS(其他研发费用!$F$4:$F$153,其他研发费用!$A$4:$A$153,$A18,其他研发费用!$B$4:$B$153,$B18,其他研发费用!$D$4:$D$153,"新产品设计费等") -> 0 | I18: =SUMIFS(其他研发费用!$F$4:$F$153,其他研发费用!$A$4:$A$153,$A18,其他研发费用!$B$4:$B$153,$B18,其他研发费用!$D$4:$D$153,"其他相关费用") -> 0 | J18: =SUMIFS(其他研发费用!$F$4:$F$153,其他研发费用!$A$4:$A$153,$A18,其他研发费用!$B$4:$B$153,$B18,其他研发费用!$D$4:$D$153,"委托外部研发费用") -> 0 | K18: =ROUND(SUM(D18:J18),2) -> 0 | L18: =SUMIFS(研发人员工时分配表!$K$6:$K$245,研发人员工时分配表!$A$6:$A$245,$A18) -> 0 | M18: =SUMIFS(仪器设备工时分配表!$K$6:$K$245,仪器设备工时分配表!$A$6:$A$245,$A18) -> 0
A19: 2026-02 | B19: =项目清单!$B$8 -> RD05 | C19: =IF($B19="","",IFERROR(VLOOKUP($B19,项目清单!$B$4:$C$13,2,0)&"","")) -> 新能源汽车电池包用导热缓冲复合材料开发 | D19: =SUMIFS(研发人员工时费用分配表!$R$6:$R$245,研发人员工时费用分配表!$A$6:$A$245,$A19) -> 0 | E19: =SUMIFS(仪器设备工时费用分配表!$N$6:$N$245,仪器设备工时费用分配表!$A$6:$A$245,$A19,仪器设备工时费用分配表!$D$6:$D$245,"设备") -> 0 | F19: =SUMIFS(无形资产费用分配表!$N$6:$N$125,无形资产费用分配表!$A$6:$A$125,$A19) -> 0 | G19: =SUMIFS(其他研发费用!$F$4:$F$153,其他研发费用!$A$4:$A$153,$A19,其他研发费用!$B$4:$B$153,$B19,其他研发费用!$D$4:$D$153,"直接投入费用") -> 0 | H19: =SUMIFS(其他研发费用!$F$4:$F$153,其他研发费用!$A$4:$A$153,$A19,其他研发费用!$B$4:$B$153,$B19,其他研发费用!$D$4:$D$153,"新产品设计费等") -> 0 | I19: =SUMIFS(其他研发费用!$F$4:$F$153,其他研发费用!$A$4:$A$153,$A19,其他研发费用!$B$4:$B$153,$B19,其他研发费用!$D$4:$D$153,"其他相关费用") -> 0 | J19: =SUMIFS(其他研发费用!$F$4:$F$153,其他研发费用!$A$4:$A$153,$A19,其他研发费用!$B$4:$B$153,$B19,其他研发费用!$D$4:$D$153,"委托外部研发费用") -> 0 | K19: =ROUND(SUM(D19:J19),2) -> 0 | L19: =SUMIFS(研发人员工时分配表!$L$6:$L$245,研发人员工时分配表!$A$6:$A$245,$A19) -> 0 | M19: =SUMIFS(仪器设备工时分配表!$L$6:$L$245,仪器设备工时分配表!$A$6:$A$245,$A19) -> 0
A20: 2026-02 | B20: =项目清单!$B$9 -> RD06 | C20: =IF($B20="","",IFERROR(VLOOKUP($B20,项目清单!$B$4:$C$13,2,0)&"","")) -> 3C电子用超薄黑色遮光泡棉制备技术 | D20: =SUMIFS(研发人员工时费用分配表!$S$6:$S$245,研发人员工时费用分配表!$A$6:$A$245,$A20) -> 0 | E20: =SUMIFS(仪器设备工时费用分配表!$O$6:$O$245,仪器设备工时费用分配表!$A$6:$A$245,$A20,仪器设备工时费用分配表!$D$6:$D$245,"设备") -> 0 | F20: =SUMIFS(无形资产费用分配表!$O$6:$O$125,无形资产费用分配表!$A$6:$A$125,$A20) -> 0 | G20: =SUMIFS(其他研发费用!$F$4:$F$153,其他研发费用!$A$4:$A$153,$A20,其他研发费用!$B$4:$B$153,$B20,其他研发费用!$D$4:$D$153,"直接投入费用") -> 0 | H20: =SUMIFS(其他研发费用!$F$4:$F$153,其他研发费用!$A$4:$A$153,$A20,其他研发费用!$B$4:$B$153,$B20,其他研发费用!$D$4:$D$153,"新产品设计费等") -> 0 | I20: =SUMIFS(其他研发费用!$F$4:$F$153,其他研发费用!$A$4:$A$153,$A20,其他研发费用!$B$4:$B$153,$B20,其他研发费用!$D$4:$D$153,"其他相关费用") -> 0 | J20: =SUMIFS(其他研发费用!$F$4:$F$153,其他研发费用!$A$4:$A$153,$A20,其他研发费用!$B$4:$B$153,$B20,其他研发费用!$D$4:$D$153,"委托外部研发费用") -> 0 | K20: =ROUND(SUM(D20:J20),2) -> 0 | L20: =SUMIFS(研发人员工时分配表!$M$6:$M$245,研发人员工时分配表!$A$6:$A$245,$A20) -> 0 | M20: =SUMIFS(仪器设备工时分配表!$M$6:$M$245,仪器设备工时分配表!$A$6:$A$245,$A20) -> 0
A21: 2026-02 | B21: =项目清单!$B$10 -> RD07 | C21: =IF($B21="","",IFERROR(VLOOKUP($B21,项目清单!$B$4:$C$13,2,0)&"","")) -> 环保型水性胶泡棉贴合技术开发 | D21: =SUMIFS(研发人员工时费用分配表!$T$6:$T$245,研发人员工时费用分配表!$A$6:$A$245,$A21) -> 0 | E21: =SUMIFS(仪器设备工时费用分配表!$P$6:$P$245,仪器设备工时费用分配表!$A$6:$A$245,$A21,仪器设备工时费用分配表!$D$6:$D$245,"设备") -> 0 | F21: =SUMIFS(无形资产费用分配表!$P$6:$P$125,无形资产费用分配表!$A$6:$A$125,$A21) -> 0 | G21: =SUMIFS(其他研发费用!$F$4:$F$153,其他研发费用!$A$4:$A$153,$A21,其他研发费用!$B$4:$B$153,$B21,其他研发费用!$D$4:$D$153,"直接投入费用") -> 0 | H21: =SUMIFS(其他研发费用!$F$4:$F$153,其他研发费用!$A$4:$A$153,$A21,其他研发费用!$B$4:$B$153,$B21,其他研发费用!$D$4:$D$153,"新产品设计费等") -> 0 | I21: =SUMIFS(其他研发费用!$F$4:$F$153,其他研发费用!$A$4:$A$153,$A21,其他研发费用!$B$4:$B$153,$B21,其他研发费用!$D$4:$D$153,"其他相关费用") -> 0 | J21: =SUMIFS(其他研发费用!$F$4:$F$153,其他研发费用!$A$4:$A$153,$A21,其他研发费用!$B$4:$B$153,$B21,其他研发费用!$D$4:$D$153,"委托外部研发费用") -> 0 | K21: =ROUND(SUM(D21:J21),2) -> 0 | L21: =SUMIFS(研发人员工时分配表!$N$6:$N$245,研发人员工时分配表!$A$6:$A$245,$A21) -> 0 | M21: =SUMIFS(仪器设备工时分配表!$N$6:$N$245,仪器设备工时分配表!$A$6:$A$245,$A21) -> 0
A22: 2026-02 | B22: =项目清单!$B$11 -> RD08 | C22: =IF($B22="","",IFERROR(VLOOKUP($B22,项目清单!$B$4:$C$13,2,0)&"","")) -> 泡棉模切自动化在线检测技术研究 | D22: =SUMIFS(研发人员工时费用分配表!$U$6:$U$245,研发人员工时费用分配表!$A$6:$A$245,$A22) -> 0 | E22: =SUMIFS(仪器设备工时费用分配表!$Q$6:$Q$245,仪器设备工时费用分配表!$A$6:$A$245,$A22,仪器设备工时费用分配表!$D$6:$D$245,"设备") -> 0 | F22: =SUMIFS(无形资产费用分配表!$Q$6:$Q$125,无形资产费用分配表!$A$6:$A$125,$A22) -> 0 | G22: =SUMIFS(其他研发费用!$F$4:$F$153,其他研发费用!$A$4:$A$153,$A22,其他研发费用!$B$4:$B$153,$B22,其他研发费用!$D$4:$D$153,"直接投入费用") -> 0 | H22: =SUMIFS(其他研发费用!$F$4:$F$153,其他研发费用!$A$4:$A$153,$A22,其他研发费用!$B$4:$B$153,$B22,其他研发费用!$D$4:$D$153,"新产品设计费等") -> 0 | I22: =SUMIFS(其他研发费用!$F$4:$F$153,其他研发费用!$A$4:$A$153,$A22,其他研发费用!$B$4:$B$153,$B22,其他研发费用!$D$4:$D$153,"其他相关费用") -> 0 | J22: =SUMIFS(其他研发费用!$F$4:$F$153,其他研发费用!$A$4:$A$153,$A22,其他研发费用!$B$4:$B$153,$B22,其他研发费用!$D$4:$D$153,"委托外部研发费用") -> 0 | K22: =ROUND(SUM(D22:J22),2) -> 0 | L22: =SUMIFS(研发人员工时分配表!$O$6:$O$245,研发人员工时分配表!$A$6:$A$245,$A22) -> 0 | M22: =SUMIFS(仪器设备工时分配表!$O$6:$O$245,仪器设备工时分配表!$A$6:$A$245,$A22) -> 0
A23: 2026-02 | B23: =项目清单!$B$12 -> RD09 | C23: =IF($B23="","",IFERROR(VLOOKUP($B23,项目清单!$B$4:$C$13,2,0)&"","")) | D23: =SUMIFS(研发人员工时费用分配表!$V$6:$V$245,研发人员工时费用分配表!$A$6:$A$245,$A23) -> 0 | E23: =SUMIFS(仪器设备工时费用分配表!$R$6:$R$245,仪器设备工时费用分配表!$A$6:$A$245,$A23,仪器设备工时费用分配表!$D$6:$D$245,"设备") -> 0 | F23: =SUMIFS(无形资产费用分配表!$R$6:$R$125,无形资产费用分配表!$A$6:$A$125,$A23) -> 0 | G23: =SUMIFS(其他研发费用!$F$4:$F$153,其他研发费用!$A$4:$A$153,$A23,其他研发费用!$B$4:$B$153,$B23,其他研发费用!$D$4:$D$153,"直接投入费用") -> 0 | H23: =SUMIFS(其他研发费用!$F$4:$F$153,其他研发费用!$A$4:$A$153,$A23,其他研发费用!$B$4:$B$153,$B23,其他研发费用!$D$4:$D$153,"新产品设计费等") -> 0 | I23: =SUMIFS(其他研发费用!$F$4:$F$153,其他研发费用!$A$4:$A$153,$A23,其他研发费用!$B$4:$B$153,$B23,其他研发费用!$D$4:$D$153,"其他相关费用") -> 0 | J23: =SUMIFS(其他研发费用!$F$4:$F$153,其他研发费用!$A$4:$A$153,$A23,其他研发费用!$B$4:$B$153,$B23,其他研发费用!$D$4:$D$153,"委托外部研发费用") -> 0 | K23: =ROUND(SUM(D23:J23),2) -> 0 | L23: =SUMIFS(研发人员工时分配表!$P$6:$P$245,研发人员工时分配表!$A$6:$A$245,$A23) -> 0 | M23: =SUMIFS(仪器设备工时分配表!$P$6:$P$245,仪器设备工时分配表!$A$6:$A$245,$A23) -> 0
A24: 2026-02 | B24: =项目清单!$B$13 -> RD10 | C24: =IF($B24="","",IFERROR(VLOOKUP($B24,项目清单!$B$4:$C$13,2,0)&"","")) | D24: =SUMIFS(研发人员工时费用分配表!$W$6:$W$245,研发人员工时费用分配表!$A$6:$A$245,$A24) -> 0 | E24: =SUMIFS(仪器设备工时费用分配表!$S$6:$S$245,仪器设备工时费用分配表!$A$6:$A$245,$A24,仪器设备工时费用分配表!$D$6:$D$245,"设备") -> 0 | F24: =SUMIFS(无形资产费用分配表!$S$6:$S$125,无形资产费用分配表!$A$6:$A$125,$A24) -> 0 | G24: =SUMIFS(其他研发费用!$F$4:$F$153,其他研发费用!$A$4:$A$153,$A24,其他研发费用!$B$4:$B$153,$B24,其他研发费用!$D$4:$D$153,"直接投入费用") -> 0 | H24: =SUMIFS(其他研发费用!$F$4:$F$153,其他研发费用!$A$4:$A$153,$A24,其他研发费用!$B$4:$B$153,$B24,其他研发费用!$D$4:$D$153,"新产品设计费等") -> 0 | I24: =SUMIFS(其他研发费用!$F$4:$F$153,其他研发费用!$A$4:$A$153,$A24,其他研发费用!$B$4:$B$153,$B24,其他研发费用!$D$4:$D$153,"其他相关费用") -> 0 | J24: =SUMIFS(其他研发费用!$F$4:$F$153,其他研发费用!$A$4:$A$153,$A24,其他研发费用!$B$4:$B$153,$B24,其他研发费用!$D$4:$D$153,"委托外部研发费用") -> 0 | K24: =ROUND(SUM(D24:J24),2) -> 0 | L24: =SUMIFS(研发人员工时分配表!$Q$6:$Q$245,研发人员工时分配表!$A$6:$A$245,$A24) -> 0 | M24: =SUMIFS(仪器设备工时分配表!$Q$6:$Q$245,仪器设备工时分配表!$A$6:$A$245,$A24) -> 0
A25: 2026-02 | C25: 本月合计 | D25: =ROUND(SUM(D15:D24),2) -> 0 | E25: =ROUND(SUM(E15:E24),2) -> 0 | F25: =ROUND(SUM(F15:F24),2) -> 0 | G25: =ROUND(SUM(G15:G24),2) -> 0 | H25: =ROUND(SUM(H15:H24),2) -> 0 | I25: =ROUND(SUM(I15:I24),2) -> 0 | J25: =ROUND(SUM(J15:J24),2) -> 0 | K25: =ROUND(SUM(K15:K24),2) -> 0 | ... M25: =ROUND(SUM(M15:M24),2) -> 0
A26: 2026-03 | B26: =项目清单!$B$4 -> RD01 | C26: =IF($B26="","",IFERROR(VLOOKUP($B26,项目清单!$B$4:$C$13,2,0)&"","")) -> 高回弹低压缩永久变形3C用聚氨酯泡棉开发 | D26: =SUMIFS(研发人员工时费用分配表!$N$6:$N$245,研发人员工时费用分配表!$A$6:$A$245,$A26) -> 0 | E26: =SUMIFS(仪器设备工时费用分配表!$J$6:$J$245,仪器设备工时费用分配表!$A$6:$A$245,$A26,仪器设备工时费用分配表!$D$6:$D$245,"设备") -> 0 | F26: =SUMIFS(无形资产费用分配表!$J$6:$J$125,无形资产费用分配表!$A$6:$A$125,$A26) -> 0 | G26: =SUMIFS(其他研发费用!$F$4:$F$153,其他研发费用!$A$4:$A$153,$A26,其他研发费用!$B$4:$B$153,$B26,其他研发费用!$D$4:$D$153,"直接投入费用") -> 0 | H26: =SUMIFS(其他研发费用!$F$4:$F$153,其他研发费用!$A$4:$A$153,$A26,其他研发费用!$B$4:$B$153,$B26,其他研发费用!$D$4:$D$153,"新产品设计费等") -> 0 | I26: =SUMIFS(其他研发费用!$F$4:$F$153,其他研发费用!$A$4:$A$153,$A26,其他研发费用!$B$4:$B$153,$B26,其他研发费用!$D$4:$D$153,"其他相关费用") -> 0 | J26: =SUMIFS(其他研发费用!$F$4:$F$153,其他研发费用!$A$4:$A$153,$A26,其他研发费用!$B$4:$B$153,$B26,其他研发费用!$D$4:$D$153,"委托外部研发费用") -> 0 | K26: =ROUND(SUM(D26:J26),2) -> 0 | L26: =SUMIFS(研发人员工时分配表!$H$6:$H$245,研发人员工时分配表!$A$6:$A$245,$A26) -> 0 | M26: =SUMIFS(仪器设备工时分配表!$H$6:$H$245,仪器设备工时分配表!$A$6:$A$245,$A26) -> 0
A27: 2026-03 | B27: =项目清单!$B$5 -> RD02 | C27: =IF($B27="","",IFERROR(VLOOKUP($B27,项目清单!$B$4:$C$13,2,0)&"","")) -> 动力电池模组用高阻燃缓冲泡棉研发 | D27: =SUMIFS(研发人员工时费用分配表!$O$6:$O$245,研发人员工时费用分配表!$A$6:$A$245,$A27) -> 0 | E27: =SUMIFS(仪器设备工时费用分配表!$K$6:$K$245,仪器设备工时费用分配表!$A$6:$A$245,$A27,仪器设备工时费用分配表!$D$6:$D$245,"设备") -> 0 | F27: =SUMIFS(无形资产费用分配表!$K$6:$K$125,无形资产费用分配表!$A$6:$A$125,$A27) -> 0 | G27: =SUMIFS(其他研发费用!$F$4:$F$153,其他研发费用!$A$4:$A$153,$A27,其他研发费用!$B$4:$B$153,$B27,其他研发费用!$D$4:$D$153,"直接投入费用") -> 0 | H27: =SUMIFS(其他研发费用!$F$4:$F$153,其他研发费用!$A$4:$A$153,$A27,其他研发费用!$B$4:$B$153,$B27,其他研发费用!$D$4:$D$153,"新产品设计费等") -> 0 | I27: =SUMIFS(其他研发费用!$F$4:$F$153,其他研发费用!$A$4:$A$153,$A27,其他研发费用!$B$4:$B$153,$B27,其他研发费用!$D$4:$D$153,"其他相关费用") -> 0 | J27: =SUMIFS(其他研发费用!$F$4:$F$153,其他研发费用!$A$4:$A$153,$A27,其他研发费用!$B$4:$B$153,$B27,其他研发费用!$D$4:$D$153,"委托外部研发费用") -> 0 | K27: =ROUND(SUM(D27:J27),2) -> 0 | L27: =SUMIFS(研发人员工时分配表!$I$6:$I$245,研发人员工时分配表!$A$6:$A$245,$A27) -> 0 | M27: =SUMIFS(仪器设备工时分配表!$I$6:$I$245,仪器设备工时分配表!$A$6:$A$245,$A27) -> 0
A28: 2026-03 | B28: =项目清单!$B$6 -> RD03 | C28: =IF($B28="","",IFERROR(VLOOKUP($B28,项目清单!$B$4:$C$13,2,0)&"","")) -> 泡棉与PET基材无溶剂贴合工艺开发 | D28: =SUMIFS(研发人员工时费用分配表!$P$6:$P$245,研发人员工时费用分配表!$A$6:$A$245,$A28) -> 0 | E28: =SUMIFS(仪器设备工时费用分配表!$L$6:$L$245,仪器设备工时费用分配表!$A$6:$A$245,$A28,仪器设备工时费用分配表!$D$6:$D$245,"设备") -> 0 | F28: =SUMIFS(无形资产费用分配表!$L$6:$L$125,无形资产费用分配表!$A$6:$A$125,$A28) -> 0 | G28: =SUMIFS(其他研发费用!$F$4:$F$153,其他研发费用!$A$4:$A$153,$A28,其他研发费用!$B$4:$B$153,$B28,其他研发费用!$D$4:$D$153,"直接投入费用") -> 0 | H28: =SUMIFS(其他研发费用!$F$4:$F$153,其他研发费用!$A$4:$A$153,$A28,其他研发费用!$B$4:$B$153,$B28,其他研发费用!$D$4:$D$153,"新产品设计费等") -> 0 | I28: =SUMIFS(其他研发费用!$F$4:$F$153,其他研发费用!$A$4:$A$153,$A28,其他研发费用!$B$4:$B$153,$B28,其他研发费用!$D$4:$D$153,"其他相关费用") -> 0 | J28: =SUMIFS(其他研发费用!$F$4:$F$153,其他研发费用!$A$4:$A$153,$A28,其他研发费用!$B$4:$B$153,$B28,其他研发费用!$D$4:$D$153,"委托外部研发费用") -> 0 | K28: =ROUND(SUM(D28:J28),2) -> 0 | L28: =SUMIFS(研发人员工时分配表!$J$6:$J$245,研发人员工时分配表!$A$6:$A$245,$A28) -> 0 | M28: =SUMIFS(仪器设备工时分配表!$J$6:$J$245,仪器设备工时分配表!$A$6:$A$245,$A28) -> 0
A29: 2026-03 | B29: =项目清单!$B$7 -> RD04 | C29: =IF($B29="","",IFERROR(VLOOKUP($B29,项目清单!$B$4:$C$13,2,0)&"","")) -> 超薄泡棉高精度分切及毛边控制技术研究 | D29: =SUMIFS(研发人员工时费用分配表!$Q$6:$Q$245,研发人员工时费用分配表!$A$6:$A$245,$A29) -> 0 | E29: =SUMIFS(仪器设备工时费用分配表!$M$6:$M$245,仪器设备工时费用分配表!$A$6:$A$245,$A29,仪器设备工时费用分配表!$D$6:$D$245,"设备") -> 0 | F29: =SUMIFS(无形资产费用分配表!$M$6:$M$125,无形资产费用分配表!$A$6:$A$125,$A29) -> 0 | G29: =SUMIFS(其他研发费用!$F$4:$F$153,其他研发费用!$A$4:$A$153,$A29,其他研发费用!$B$4:$B$153,$B29,其他研发费用!$D$4:$D$153,"直接投入费用") -> 0 | H29: =SUMIFS(其他研发费用!$F$4:$F$153,其他研发费用!$A$4:$A$153,$A29,其他研发费用!$B$4:$B$153,$B29,其他研发费用!$D$4:$D$153,"新产品设计费等") -> 0 | I29: =SUMIFS(其他研发费用!$F$4:$F$153,其他研发费用!$A$4:$A$153,$A29,其他研发费用!$B$4:$B$153,$B29,其他研发费用!$D$4:$D$153,"其他相关费用") -> 0 | J29: =SUMIFS(其他研发费用!$F$4:$F$153,其他研发费用!$A$4:$A$153,$A29,其他研发费用!$B$4:$B$153,$B29,其他研发费用!$D$4:$D$153,"委托外部研发费用") -> 0 | K29: =ROUND(SUM(D29:J29),2) -> 0 | L29: =SUMIFS(研发人员工时分配表!$K$6:$K$245,研发人员工时分配表!$A$6:$A$245,$A29) -> 0 | M29: =SUMIFS(仪器设备工时分配表!$K$6:$K$245,仪器设备工时分配表!$A$6:$A$245,$A29) -> 0
A30: 2026-03 | B30: =项目清单!$B$8 -> RD05 | C30: =IF($B30="","",IFERROR(VLOOKUP($B30,项目清单!$B$4:$C$13,2,0)&"","")) -> 新能源汽车电池包用导热缓冲复合材料开发 | D30: =SUMIFS(研发人员工时费用分配表!$R$6:$R$245,研发人员工时费用分配表!$A$6:$A$245,$A30) -> 0 | E30: =SUMIFS(仪器设备工时费用分配表!$N$6:$N$245,仪器设备工时费用分配表!$A$6:$A$245,$A30,仪器设备工时费用分配表!$D$6:$D$245,"设备") -> 0 | F30: =SUMIFS(无形资产费用分配表!$N$6:$N$125,无形资产费用分配表!$A$6:$A$125,$A30) -> 0 | G30: =SUMIFS(其他研发费用!$F$4:$F$153,其他研发费用!$A$4:$A$153,$A30,其他研发费用!$B$4:$B$153,$B30,其他研发费用!$D$4:$D$153,"直接投入费用") -> 0 | H30: =SUMIFS(其他研发费用!$F$4:$F$153,其他研发费用!$A$4:$A$153,$A30,其他研发费用!$B$4:$B$153,$B30,其他研发费用!$D$4:$D$153,"新产品设计费等") -> 0 | I30: =SUMIFS(其他研发费用!$F$4:$F$153,其他研发费用!$A$4:$A$153,$A30,其他研发费用!$B$4:$B$153,$B30,其他研发费用!$D$4:$D$153,"其他相关费用") -> 0 | J30: =SUMIFS(其他研发费用!$F$4:$F$153,其他研发费用!$A$4:$A$153,$A30,其他研发费用!$B$4:$B$153,$B30,其他研发费用!$D$4:$D$153,"委托外部研发费用") -> 0 | K30: =ROUND(SUM(D30:J30),2) -> 0 | L30: =SUMIFS(研发人员工时分配表!$L$6:$L$245,研发人员工时分配表!$A$6:$A$245,$A30) -> 0 | M30: =SUMIFS(仪器设备工时分配表!$L$6:$L$245,仪器设备工时分配表!$A$6:$A$245,$A30) -> 0
A31: 2026-03 | B31: =项目清单!$B$9 -> RD06 | C31: =IF($B31="","",IFERROR(VLOOKUP($B31,项目清单!$B$4:$C$13,2,0)&"","")) -> 3C电子用超薄黑色遮光泡棉制备技术 | D31: =SUMIFS(研发人员工时费用分配表!$S$6:$S$245,研发人员工时费用分配表!$A$6:$A$245,$A31) -> 0 | E31: =SUMIFS(仪器设备工时费用分配表!$O$6:$O$245,仪器设备工时费用分配表!$A$6:$A$245,$A31,仪器设备工时费用分配表!$D$6:$D$245,"设备") -> 0 | F31: =SUMIFS(无形资产费用分配表!$O$6:$O$125,无形资产费用分配表!$A$6:$A$125,$A31) -> 0 | G31: =SUMIFS(其他研发费用!$F$4:$F$153,其他研发费用!$A$4:$A$153,$A31,其他研发费用!$B$4:$B$153,$B31,其他研发费用!$D$4:$D$153,"直接投入费用") -> 0 | H31: =SUMIFS(其他研发费用!$F$4:$F$153,其他研发费用!$A$4:$A$153,$A31,其他研发费用!$B$4:$B$153,$B31,其他研发费用!$D$4:$D$153,"新产品设计费等") -> 0 | I31: =SUMIFS(其他研发费用!$F$4:$F$153,其他研发费用!$A$4:$A$153,$A31,其他研发费用!$B$4:$B$153,$B31,其他研发费用!$D$4:$D$153,"其他相关费用") -> 0 | J31: =SUMIFS(其他研发费用!$F$4:$F$153,其他研发费用!$A$4:$A$153,$A31,其他研发费用!$B$4:$B$153,$B31,其他研发费用!$D$4:$D$153,"委托外部研发费用") -> 0 | K31: =ROUND(SUM(D31:J31),2) -> 0 | L31: =SUMIFS(研发人员工时分配表!$M$6:$M$245,研发人员工时分配表!$A$6:$A$245,$A31) -> 0 | M31: =SUMIFS(仪器设备工时分配表!$M$6:$M$245,仪器设备工时分配表!$A$6:$A$245,$A31) -> 0
A32: 2026-03 | B32: =项目清单!$B$10 -> RD07 | C32: =IF($B32="","",IFERROR(VLOOKUP($B32,项目清单!$B$4:$C$13,2,0)&"","")) -> 环保型水性胶泡棉贴合技术开发 | D32: =SUMIFS(研发人员工时费用分配表!$T$6:$T$245,研发人员工时费用分配表!$A$6:$A$245,$A32) -> 0 | E32: =SUMIFS(仪器设备工时费用分配表!$P$6:$P$245,仪器设备工时费用分配表!$A$6:$A$245,$A32,仪器设备工时费用分配表!$D$6:$D$245,"设备") -> 0 | F32: =SUMIFS(无形资产费用分配表!$P$6:$P$125,无形资产费用分配表!$A$6:$A$125,$A32) -> 0 | G32: =SUMIFS(其他研发费用!$F$4:$F$153,其他研发费用!$A$4:$A$153,$A32,其他研发费用!$B$4:$B$153,$B32,其他研发费用!$D$4:$D$153,"直接投入费用") -> 0 | H32: =SUMIFS(其他研发费用!$F$4:$F$153,其他研发费用!$A$4:$A$153,$A32,其他研发费用!$B$4:$B$153,$B32,其他研发费用!$D$4:$D$153,"新产品设计费等") -> 0 | I32: =SUMIFS(其他研发费用!$F$4:$F$153,其他研发费用!$A$4:$A$153,$A32,其他研发费用!$B$4:$B$153,$B32,其他研发费用!$D$4:$D$153,"其他相关费用") -> 0 | J32: =SUMIFS(其他研发费用!$F$4:$F$153,其他研发费用!$A$4:$A$153,$A32,其他研发费用!$B$4:$B$153,$B32,其他研发费用!$D$4:$D$153,"委托外部研发费用") -> 0 | K32: =ROUND(SUM(D32:J32),2) -> 0 | L32: =SUMIFS(研发人员工时分配表!$N$6:$N$245,研发人员工时分配表!$A$6:$A$245,$A32) -> 0 | M32: =SUMIFS(仪器设备工时分配表!$N$6:$N$245,仪器设备工时分配表!$A$6:$A$245,$A32) -> 0
A33: 2026-03 | B33: =项目清单!$B$11 -> RD08 | C33: =IF($B33="","",IFERROR(VLOOKUP($B33,项目清单!$B$4:$C$13,2,0)&"","")) -> 泡棉模切自动化在线检测技术研究 | D33: =SUMIFS(研发人员工时费用分配表!$U$6:$U$245,研发人员工时费用分配表!$A$6:$A$245,$A33) -> 0 | E33: =SUMIFS(仪器设备工时费用分配表!$Q$6:$Q$245,仪器设备工时费用分配表!$A$6:$A$245,$A33,仪器设备工时费用分配表!$D$6:$D$245,"设备") -> 0 | F33: =SUMIFS(无形资产费用分配表!$Q$6:$Q$125,无形资产费用分配表!$A$6:$A$125,$A33) -> 0 | G33: =SUMIFS(其他研发费用!$F$4:$F$153,其他研发费用!$A$4:$A$153,$A33,其他研发费用!$B$4:$B$153,$B33,其他研发费用!$D$4:$D$153,"直接投入费用") -> 0 | H33: =SUMIFS(其他研发费用!$F$4:$F$153,其他研发费用!$A$4:$A$153,$A33,其他研发费用!$B$4:$B$153,$B33,其他研发费用!$D$4:$D$153,"新产品设计费等") -> 0 | I33: =SUMIFS(其他研发费用!$F$4:$F$153,其他研发费用!$A$4:$A$153,$A33,其他研发费用!$B$4:$B$153,$B33,其他研发费用!$D$4:$D$153,"其他相关费用") -> 0 | J33: =SUMIFS(其他研发费用!$F$4:$F$153,其他研发费用!$A$4:$A$153,$A33,其他研发费用!$B$4:$B$153,$B33,其他研发费用!$D$4:$D$153,"委托外部研发费用") -> 0 | K33: =ROUND(SUM(D33:J33),2) -> 0 | L33: =SUMIFS(研发人员工时分配表!$O$6:$O$245,研发人员工时分配表!$A$6:$A$245,$A33) -> 0 | M33: =SUMIFS(仪器设备工时分配表!$O$6:$O$245,仪器设备工时分配表!$A$6:$A$245,$A33) -> 0
A34: 2026-03 | B34: =项目清单!$B$12 -> RD09 | C34: =IF($B34="","",IFERROR(VLOOKUP($B34,项目清单!$B$4:$C$13,2,0)&"","")) | D34: =SUMIFS(研发人员工时费用分配表!$V$6:$V$245,研发人员工时费用分配表!$A$6:$A$245,$A34) -> 0 | E34: =SUMIFS(仪器设备工时费用分配表!$R$6:$R$245,仪器设备工时费用分配表!$A$6:$A$245,$A34,仪器设备工时费用分配表!$D$6:$D$245,"设备") -> 0 | F34: =SUMIFS(无形资产费用分配表!$R$6:$R$125,无形资产费用分配表!$A$6:$A$125,$A34) -> 0 | G34: =SUMIFS(其他研发费用!$F$4:$F$153,其他研发费用!$A$4:$A$153,$A34,其他研发费用!$B$4:$B$153,$B34,其他研发费用!$D$4:$D$153,"直接投入费用") -> 0 | H34: =SUMIFS(其他研发费用!$F$4:$F$153,其他研发费用!$A$4:$A$153,$A34,其他研发费用!$B$4:$B$153,$B34,其他研发费用!$D$4:$D$153,"新产品设计费等") -> 0 | I34: =SUMIFS(其他研发费用!$F$4:$F$153,其他研发费用!$A$4:$A$153,$A34,其他研发费用!$B$4:$B$153,$B34,其他研发费用!$D$4:$D$153,"其他相关费用") -> 0 | J34: =SUMIFS(其他研发费用!$F$4:$F$153,其他研发费用!$A$4:$A$153,$A34,其他研发费用!$B$4:$B$153,$B34,其他研发费用!$D$4:$D$153,"委托外部研发费用") -> 0 | K34: =ROUND(SUM(D34:J34),2) -> 0 | L34: =SUMIFS(研发人员工时分配表!$P$6:$P$245,研发人员工时分配表!$A$6:$A$245,$A34) -> 0 | M34: =SUMIFS(仪器设备工时分配表!$P$6:$P$245,仪器设备工时分配表!$A$6:$A$245,$A34) -> 0
A35: 2026-03 | B35: =项目清单!$B$13 -> RD10 | C35: =IF($B35="","",IFERROR(VLOOKUP($B35,项目清单!$B$4:$C$13,2,0)&"","")) | D35: =SUMIFS(研发人员工时费用分配表!$W$6:$W$245,研发人员工时费用分配表!$A$6:$A$245,$A35) -> 0 | E35: =SUMIFS(仪器设备工时费用分配表!$S$6:$S$245,仪器设备工时费用分配表!$A$6:$A$245,$A35,仪器设备工时费用分配表!$D$6:$D$245,"设备") -> 0 | F35: =SUMIFS(无形资产费用分配表!$S$6:$S$125,无形资产费用分配表!$A$6:$A$125,$A35) -> 0 | G35: =SUMIFS(其他研发费用!$F$4:$F$153,其他研发费用!$A$4:$A$153,$A35,其他研发费用!$B$4:$B$153,$B35,其他研发费用!$D$4:$D$153,"直接投入费用") -> 0 | H35: =SUMIFS(其他研发费用!$F$4:$F$153,其他研发费用!$A$4:$A$153,$A35,其他研发费用!$B$4:$B$153,$B35,其他研发费用!$D$4:$D$153,"新产品设计费等") -> 0 | I35: =SUMIFS(其他研发费用!$F$4:$F$153,其他研发费用!$A$4:$A$153,$A35,其他研发费用!$B$4:$B$153,$B35,其他研发费用!$D$4:$D$153,"其他相关费用") -> 0 | J35: =SUMIFS(其他研发费用!$F$4:$F$153,其他研发费用!$A$4:$A$153,$A35,其他研发费用!$B$4:$B$153,$B35,其他研发费用!$D$4:$D$153,"委托外部研发费用") -> 0 | K35: =ROUND(SUM(D35:J35),2) -> 0 | L35: =SUMIFS(研发人员工时分配表!$Q$6:$Q$245,研发人员工时分配表!$A$6:$A$245,$A35) -> 0 | M35: =SUMIFS(仪器设备工时分配表!$Q$6:$Q$245,仪器设备工时分配表!$A$6:$A$245,$A35) -> 0
A36: 2026-03 | C36: 本月合计 | D36: =ROUND(SUM(D26:D35),2) -> 0 | E36: =ROUND(SUM(E26:E35),2) -> 0 | F36: =ROUND(SUM(F26:F35),2) -> 0 | G36: =ROUND(SUM(G26:G35),2) -> 0 | H36: =ROUND(SUM(H26:H35),2) -> 0 | I36: =ROUND(SUM(I26:I35),2) -> 0 | J36: =ROUND(SUM(J26:J35),2) -> 0 | K36: =ROUND(SUM(K26:K35),2) -> 0 | ... M36: =ROUND(SUM(M26:M35),2) -> 0
A37: 2026-04 | B37: =项目清单!$B$4 -> RD01 | C37: =IF($B37="","",IFERROR(VLOOKUP($B37,项目清单!$B$4:$C$13,2,0)&"","")) -> 高回弹低压缩永久变形3C用聚氨酯泡棉开发 | D37: =SUMIFS(研发人员工时费用分配表!$N$6:$N$245,研发人员工时费用分配表!$A$6:$A$245,$A37) -> 0 | E37: =SUMIFS(仪器设备工时费用分配表!$J$6:$J$245,仪器设备工时费用分配表!$A$6:$A$245,$A37,仪器设备工时费用分配表!$D$6:$D$245,"设备") -> 0 | F37: =SUMIFS(无形资产费用分配表!$J$6:$J$125,无形资产费用分配表!$A$6:$A$125,$A37) -> 0 | G37: =SUMIFS(其他研发费用!$F$4:$F$153,其他研发费用!$A$4:$A$153,$A37,其他研发费用!$B$4:$B$153,$B37,其他研发费用!$D$4:$D$153,"直接投入费用") -> 0 | H37: =SUMIFS(其他研发费用!$F$4:$F$153,其他研发费用!$A$4:$A$153,$A37,其他研发费用!$B$4:$B$153,$B37,其他研发费用!$D$4:$D$153,"新产品设计费等") -> 0 | I37: =SUMIFS(其他研发费用!$F$4:$F$153,其他研发费用!$A$4:$A$153,$A37,其他研发费用!$B$4:$B$153,$B37,其他研发费用!$D$4:$D$153,"其他相关费用") -> 0 | J37: =SUMIFS(其他研发费用!$F$4:$F$153,其他研发费用!$A$4:$A$153,$A37,其他研发费用!$B$4:$B$153,$B37,其他研发费用!$D$4:$D$153,"委托外部研发费用") -> 0 | K37: =ROUND(SUM(D37:J37),2) -> 0 | L37: =SUMIFS(研发人员工时分配表!$H$6:$H$245,研发人员工时分配表!$A$6:$A$245,$A37) -> 0 | M37: =SUMIFS(仪器设备工时分配表!$H$6:$H$245,仪器设备工时分配表!$A$6:$A$245,$A37) -> 0
A38: 2026-04 | B38: =项目清单!$B$5 -> RD02 | C38: =IF($B38="","",IFERROR(VLOOKUP($B38,项目清单!$B$4:$C$13,2,0)&"","")) -> 动力电池模组用高阻燃缓冲泡棉研发 | D38: =SUMIFS(研发人员工时费用分配表!$O$6:$O$245,研发人员工时费用分配表!$A$6:$A$245,$A38) -> 0 | E38: =SUMIFS(仪器设备工时费用分配表!$K$6:$K$245,仪器设备工时费用分配表!$A$6:$A$245,$A38,仪器设备工时费用分配表!$D$6:$D$245,"设备") -> 0 | F38: =SUMIFS(无形资产费用分配表!$K$6:$K$125,无形资产费用分配表!$A$6:$A$125,$A38) -> 0 | G38: =SUMIFS(其他研发费用!$F$4:$F$153,其他研发费用!$A$4:$A$153,$A38,其他研发费用!$B$4:$B$153,$B38,其他研发费用!$D$4:$D$153,"直接投入费用") -> 0 | H38: =SUMIFS(其他研发费用!$F$4:$F$153,其他研发费用!$A$4:$A$153,$A38,其他研发费用!$B$4:$B$153,$B38,其他研发费用!$D$4:$D$153,"新产品设计费等") -> 0 | I38: =SUMIFS(其他研发费用!$F$4:$F$153,其他研发费用!$A$4:$A$153,$A38,其他研发费用!$B$4:$B$153,$B38,其他研发费用!$D$4:$D$153,"其他相关费用") -> 0 | J38: =SUMIFS(其他研发费用!$F$4:$F$153,其他研发费用!$A$4:$A$153,$A38,其他研发费用!$B$4:$B$153,$B38,其他研发费用!$D$4:$D$153,"委托外部研发费用") -> 0 | K38: =ROUND(SUM(D38:J38),2) -> 0 | L38: =SUMIFS(研发人员工时分配表!$I$6:$I$245,研发人员工时分配表!$A$6:$A$245,$A38) -> 0 | M38: =SUMIFS(仪器设备工时分配表!$I$6:$I$245,仪器设备工时分配表!$A$6:$A$245,$A38) -> 0
A39: 2026-04 | B39: =项目清单!$B$6 -> RD03 | C39: =IF($B39="","",IFERROR(VLOOKUP($B39,项目清单!$B$4:$C$13,2,0)&"","")) -> 泡棉与PET基材无溶剂贴合工艺开发 | D39: =SUMIFS(研发人员工时费用分配表!$P$6:$P$245,研发人员工时费用分配表!$A$6:$A$245,$A39) -> 0 | E39: =SUMIFS(仪器设备工时费用分配表!$L$6:$L$245,仪器设备工时费用分配表!$A$6:$A$245,$A39,仪器设备工时费用分配表!$D$6:$D$245,"设备") -> 0 | F39: =SUMIFS(无形资产费用分配表!$L$6:$L$125,无形资产费用分配表!$A$6:$A$125,$A39) -> 0 | G39: =SUMIFS(其他研发费用!$F$4:$F$153,其他研发费用!$A$4:$A$153,$A39,其他研发费用!$B$4:$B$153,$B39,其他研发费用!$D$4:$D$153,"直接投入费用") -> 0 | H39: =SUMIFS(其他研发费用!$F$4:$F$153,其他研发费用!$A$4:$A$153,$A39,其他研发费用!$B$4:$B$153,$B39,其他研发费用!$D$4:$D$153,"新产品设计费等") -> 0 | I39: =SUMIFS(其他研发费用!$F$4:$F$153,其他研发费用!$A$4:$A$153,$A39,其他研发费用!$B$4:$B$153,$B39,其他研发费用!$D$4:$D$153,"其他相关费用") -> 0 | J39: =SUMIFS(其他研发费用!$F$4:$F$153,其他研发费用!$A$4:$A$153,$A39,其他研发费用!$B$4:$B$153,$B39,其他研发费用!$D$4:$D$153,"委托外部研发费用") -> 0 | K39: =ROUND(SUM(D39:J39),2) -> 0 | L39: =SUMIFS(研发人员工时分配表!$J$6:$J$245,研发人员工时分配表!$A$6:$A$245,$A39) -> 0 | M39: =SUMIFS(仪器设备工时分配表!$J$6:$J$245,仪器设备工时分配表!$A$6:$A$245,$A39) -> 0
A40: 2026-04 | B40: =项目清单!$B$7 -> RD04 | C40: =IF($B40="","",IFERROR(VLOOKUP($B40,项目清单!$B$4:$C$13,2,0)&"","")) -> 超薄泡棉高精度分切及毛边控制技术研究 | D40: =SUMIFS(研发人员工时费用分配表!$Q$6:$Q$245,研发人员工时费用分配表!$A$6:$A$245,$A40) -> 0 | E40: =SUMIFS(仪器设备工时费用分配表!$M$6:$M$245,仪器设备工时费用分配表!$A$6:$A$245,$A40,仪器设备工时费用分配表!$D$6:$D$245,"设备") -> 0 | F40: =SUMIFS(无形资产费用分配表!$M$6:$M$125,无形资产费用分配表!$A$6:$A$125,$A40) -> 0 | G40: =SUMIFS(其他研发费用!$F$4:$F$153,其他研发费用!$A$4:$A$153,$A40,其他研发费用!$B$4:$B$153,$B40,其他研发费用!$D$4:$D$153,"直接投入费用") -> 0 | H40: =SUMIFS(其他研发费用!$F$4:$F$153,其他研发费用!$A$4:$A$153,$A40,其他研发费用!$B$4:$B$153,$B40,其他研发费用!$D$4:$D$153,"新产品设计费等") -> 0 | I40: =SUMIFS(其他研发费用!$F$4:$F$153,其他研发费用!$A$4:$A$153,$A40,其他研发费用!$B$4:$B$153,$B40,其他研发费用!$D$4:$D$153,"其他相关费用") -> 0 | J40: =SUMIFS(其他研发费用!$F$4:$F$153,其他研发费用!$A$4:$A$153,$A40,其他研发费用!$B$4:$B$153,$B40,其他研发费用!$D$4:$D$153,"委托外部研发费用") -> 0 | K40: =ROUND(SUM(D40:J40),2) -> 0 | L40: =SUMIFS(研发人员工时分配表!$K$6:$K$245,研发人员工时分配表!$A$6:$A$245,$A40) -> 0 | M40: =SUMIFS(仪器设备工时分配表!$K$6:$K$245,仪器设备工时分配表!$A$6:$A$245,$A40) -> 0
A41: 2026-04 | B41: =项目清单!$B$8 -> RD05 | C41: =IF($B41="","",IFERROR(VLOOKUP($B41,项目清单!$B$4:$C$13,2,0)&"","")) -> 新能源汽车电池包用导热缓冲复合材料开发 | D41: =SUMIFS(研发人员工时费用分配表!$R$6:$R$245,研发人员工时费用分配表!$A$6:$A$245,$A41) -> 0 | E41: =SUMIFS(仪器设备工时费用分配表!$N$6:$N$245,仪器设备工时费用分配表!$A$6:$A$245,$A41,仪器设备工时费用分配表!$D$6:$D$245,"设备") -> 0 | F41: =SUMIFS(无形资产费用分配表!$N$6:$N$125,无形资产费用分配表!$A$6:$A$125,$A41) -> 0 | G41: =SUMIFS(其他研发费用!$F$4:$F$153,其他研发费用!$A$4:$A$153,$A41,其他研发费用!$B$4:$B$153,$B41,其他研发费用!$D$4:$D$153,"直接投入费用") -> 0 | H41: =SUMIFS(其他研发费用!$F$4:$F$153,其他研发费用!$A$4:$A$153,$A41,其他研发费用!$B$4:$B$153,$B41,其他研发费用!$D$4:$D$153,"新产品设计费等") -> 0 | I41: =SUMIFS(其他研发费用!$F$4:$F$153,其他研发费用!$A$4:$A$153,$A41,其他研发费用!$B$4:$B$153,$B41,其他研发费用!$D$4:$D$153,"其他相关费用") -> 0 | J41: =SUMIFS(其他研发费用!$F$4:$F$153,其他研发费用!$A$4:$A$153,$A41,其他研发费用!$B$4:$B$153,$B41,其他研发费用!$D$4:$D$153,"委托外部研发费用") -> 0 | K41: =ROUND(SUM(D41:J41),2) -> 0 | L41: =SUMIFS(研发人员工时分配表!$L$6:$L$245,研发人员工时分配表!$A$6:$A$245,$A41) -> 0 | M41: =SUMIFS(仪器设备工时分配表!$L$6:$L$245,仪器设备工时分配表!$A$6:$A$245,$A41) -> 0
A42: 2026-04 | B42: =项目清单!$B$9 -> RD06 | C42: =IF($B42="","",IFERROR(VLOOKUP($B42,项目清单!$B$4:$C$13,2,0)&"","")) -> 3C电子用超薄黑色遮光泡棉制备技术 | D42: =SUMIFS(研发人员工时费用分配表!$S$6:$S$245,研发人员工时费用分配表!$A$6:$A$245,$A42) -> 0 | E42: =SUMIFS(仪器设备工时费用分配表!$O$6:$O$245,仪器设备工时费用分配表!$A$6:$A$245,$A42,仪器设备工时费用分配表!$D$6:$D$245,"设备") -> 0 | F42: =SUMIFS(无形资产费用分配表!$O$6:$O$125,无形资产费用分配表!$A$6:$A$125,$A42) -> 0 | G42: =SUMIFS(其他研发费用!$F$4:$F$153,其他研发费用!$A$4:$A$153,$A42,其他研发费用!$B$4:$B$153,$B42,其他研发费用!$D$4:$D$153,"直接投入费用") -> 0 | H42: =SUMIFS(其他研发费用!$F$4:$F$153,其他研发费用!$A$4:$A$153,$A42,其他研发费用!$B$4:$B$153,$B42,其他研发费用!$D$4:$D$153,"新产品设计费等") -> 0 | I42: =SUMIFS(其他研发费用!$F$4:$F$153,其他研发费用!$A$4:$A$153,$A42,其他研发费用!$B$4:$B$153,$B42,其他研发费用!$D$4:$D$153,"其他相关费用") -> 0 | J42: =SUMIFS(其他研发费用!$F$4:$F$153,其他研发费用!$A$4:$A$153,$A42,其他研发费用!$B$4:$B$153,$B42,其他研发费用!$D$4:$D$153,"委托外部研发费用") -> 0 | K42: =ROUND(SUM(D42:J42),2) -> 0 | L42: =SUMIFS(研发人员工时分配表!$M$6:$M$245,研发人员工时分配表!$A$6:$A$245,$A42) -> 0 | M42: =SUMIFS(仪器设备工时分配表!$M$6:$M$245,仪器设备工时分配表!$A$6:$A$245,$A42) -> 0
A43: 2026-04 | B43: =项目清单!$B$10 -> RD07 | C43: =IF($B43="","",IFERROR(VLOOKUP($B43,项目清单!$B$4:$C$13,2,0)&"","")) -> 环保型水性胶泡棉贴合技术开发 | D43: =SUMIFS(研发人员工时费用分配表!$T$6:$T$245,研发人员工时费用分配表!$A$6:$A$245,$A43) -> 0 | E43: =SUMIFS(仪器设备工时费用分配表!$P$6:$P$245,仪器设备工时费用分配表!$A$6:$A$245,$A43,仪器设备工时费用分配表!$D$6:$D$245,"设备") -> 0 | F43: =SUMIFS(无形资产费用分配表!$P$6:$P$125,无形资产费用分配表!$A$6:$A$125,$A43) -> 0 | G43: =SUMIFS(其他研发费用!$F$4:$F$153,其他研发费用!$A$4:$A$153,$A43,其他研发费用!$B$4:$B$153,$B43,其他研发费用!$D$4:$D$153,"直接投入费用") -> 0 | H43: =SUMIFS(其他研发费用!$F$4:$F$153,其他研发费用!$A$4:$A$153,$A43,其他研发费用!$B$4:$B$153,$B43,其他研发费用!$D$4:$D$153,"新产品设计费等") -> 0 | I43: =SUMIFS(其他研发费用!$F$4:$F$153,其他研发费用!$A$4:$A$153,$A43,其他研发费用!$B$4:$B$153,$B43,其他研发费用!$D$4:$D$153,"其他相关费用") -> 0 | J43: =SUMIFS(其他研发费用!$F$4:$F$153,其他研发费用!$A$4:$A$153,$A43,其他研发费用!$B$4:$B$153,$B43,其他研发费用!$D$4:$D$153,"委托外部研发费用") -> 0 | K43: =ROUND(SUM(D43:J43),2) -> 0 | L43: =SUMIFS(研发人员工时分配表!$N$6:$N$245,研发人员工时分配表!$A$6:$A$245,$A43) -> 0 | M43: =SUMIFS(仪器设备工时分配表!$N$6:$N$245,仪器设备工时分配表!$A$6:$A$245,$A43) -> 0
A44: 2026-04 | B44: =项目清单!$B$11 -> RD08 | C44: =IF($B44="","",IFERROR(VLOOKUP($B44,项目清单!$B$4:$C$13,2,0)&"","")) -> 泡棉模切自动化在线检测技术研究 | D44: =SUMIFS(研发人员工时费用分配表!$U$6:$U$245,研发人员工时费用分配表!$A$6:$A$245,$A44) -> 0 | E44: =SUMIFS(仪器设备工时费用分配表!$Q$6:$Q$245,仪器设备工时费用分配表!$A$6:$A$245,$A44,仪器设备工时费用分配表!$D$6:$D$245,"设备") -> 0 | F44: =SUMIFS(无形资产费用分配表!$Q$6:$Q$125,无形资产费用分配表!$A$6:$A$125,$A44) -> 0 | G44: =SUMIFS(其他研发费用!$F$4:$F$153,其他研发费用!$A$4:$A$153,$A44,其他研发费用!$B$4:$B$153,$B44,其他研发费用!$D$4:$D$153,"直接投入费用") -> 0 | H44: =SUMIFS(其他研发费用!$F$4:$F$153,其他研发费用!$A$4:$A$153,$A44,其他研发费用!$B$4:$B$153,$B44,其他研发费用!$D$4:$D$153,"新产品设计费等") -> 0 | I44: =SUMIFS(其他研发费用!$F$4:$F$153,其他研发费用!$A$4:$A$153,$A44,其他研发费用!$B$4:$B$153,$B44,其他研发费用!$D$4:$D$153,"其他相关费用") -> 0 | J44: =SUMIFS(其他研发费用!$F$4:$F$153,其他研发费用!$A$4:$A$153,$A44,其他研发费用!$B$4:$B$153,$B44,其他研发费用!$D$4:$D$153,"委托外部研发费用") -> 0 | K44: =ROUND(SUM(D44:J44),2) -> 0 | L44: =SUMIFS(研发人员工时分配表!$O$6:$O$245,研发人员工时分配表!$A$6:$A$245,$A44) -> 0 | M44: =SUMIFS(仪器设备工时分配表!$O$6:$O$245,仪器设备工时分配表!$A$6:$A$245,$A44) -> 0
A45: 2026-04 | B45: =项目清单!$B$12 -> RD09 | C45: =IF($B45="","",IFERROR(VLOOKUP($B45,项目清单!$B$4:$C$13,2,0)&"","")) | D45: =SUMIFS(研发人员工时费用分配表!$V$6:$V$245,研发人员工时费用分配表!$A$6:$A$245,$A45) -> 0 | E45: =SUMIFS(仪器设备工时费用分配表!$R$6:$R$245,仪器设备工时费用分配表!$A$6:$A$245,$A45,仪器设备工时费用分配表!$D$6:$D$245,"设备") -> 0 | F45: =SUMIFS(无形资产费用分配表!$R$6:$R$125,无形资产费用分配表!$A$6:$A$125,$A45) -> 0 | G45: =SUMIFS(其他研发费用!$F$4:$F$153,其他研发费用!$A$4:$A$153,$A45,其他研发费用!$B$4:$B$153,$B45,其他研发费用!$D$4:$D$153,"直接投入费用") -> 0 | H45: =SUMIFS(其他研发费用!$F$4:$F$153,其他研发费用!$A$4:$A$153,$A45,其他研发费用!$B$4:$B$153,$B45,其他研发费用!$D$4:$D$153,"新产品设计费等") -> 0 | I45: =SUMIFS(其他研发费用!$F$4:$F$153,其他研发费用!$A$4:$A$153,$A45,其他研发费用!$B$4:$B$153,$B45,其他研发费用!$D$4:$D$153,"其他相关费用") -> 0 | J45: =SUMIFS(其他研发费用!$F$4:$F$153,其他研发费用!$A$4:$A$153,$A45,其他研发费用!$B$4:$B$153,$B45,其他研发费用!$D$4:$D$153,"委托外部研发费用") -> 0 | K45: =ROUND(SUM(D45:J45),2) -> 0 | L45: =SUMIFS(研发人员工时分配表!$P$6:$P$245,研发人员工时分配表!$A$6:$A$245,$A45) -> 0 | M45: =SUMIFS(仪器设备工时分配表!$P$6:$P$245,仪器设备工时分配表!$A$6:$A$245,$A45) -> 0
A46: 2026-04 | B46: =项目清单!$B$13 -> RD10 | C46: =IF($B46="","",IFERROR(VLOOKUP($B46,项目清单!$B$4:$C$13,2,0)&"","")) | D46: =SUMIFS(研发人员工时费用分配表!$W$6:$W$245,研发人员工时费用分配表!$A$6:$A$245,$A46) -> 0 | E46: =SUMIFS(仪器设备工时费用分配表!$S$6:$S$245,仪器设备工时费用分配表!$A$6:$A$245,$A46,仪器设备工时费用分配表!$D$6:$D$245,"设备") -> 0 | F46: =SUMIFS(无形资产费用分配表!$S$6:$S$125,无形资产费用分配表!$A$6:$A$125,$A46) -> 0 | G46: =SUMIFS(其他研发费用!$F$4:$F$153,其他研发费用!$A$4:$A$153,$A46,其他研发费用!$B$4:$B$153,$B46,其他研发费用!$D$4:$D$153,"直接投入费用") -> 0 | H46: =SUMIFS(其他研发费用!$F$4:$F$153,其他研发费用!$A$4:$A$153,$A46,其他研发费用!$B$4:$B$153,$B46,其他研发费用!$D$4:$D$153,"新产品设计费等") -> 0 | I46: =SUMIFS(其他研发费用!$F$4:$F$153,其他研发费用!$A$4:$A$153,$A46,其他研发费用!$B$4:$B$153,$B46,其他研发费用!$D$4:$D$153,"其他相关费用") -> 0 | J46: =SUMIFS(其他研发费用!$F$4:$F$153,其他研发费用!$A$4:$A$153,$A46,其他研发费用!$B$4:$B$153,$B46,其他研发费用!$D$4:$D$153,"委托外部研发费用") -> 0 | K46: =ROUND(SUM(D46:J46),2) -> 0 | L46: =SUMIFS(研发人员工时分配表!$Q$6:$Q$245,研发人员工时分配表!$A$6:$A$245,$A46) -> 0 | M46: =SUMIFS(仪器设备工时分配表!$Q$6:$Q$245,仪器设备工时分配表!$A$6:$A$245,$A46) -> 0
A47: 2026-04 | C47: 本月合计 | D47: =ROUND(SUM(D37:D46),2) -> 0 | E47: =ROUND(SUM(E37:E46),2) -> 0 | F47: =ROUND(SUM(F37:F46),2) -> 0 | G47: =ROUND(SUM(G37:G46),2) -> 0 | H47: =ROUND(SUM(H37:H46),2) -> 0 | I47: =ROUND(SUM(I37:I46),2) -> 0 | J47: =ROUND(SUM(J37:J46),2) -> 0 | K47: =ROUND(SUM(K37:K46),2) -> 0 | ... M47: =ROUND(SUM(M37:M46),2) -> 0
A48: 2026-05 | B48: =项目清单!$B$4 -> RD01 | C48: =IF($B48="","",IFERROR(VLOOKUP($B48,项目清单!$B$4:$C$13,2,0)&"","")) -> 高回弹低压缩永久变形3C用聚氨酯泡棉开发 | D48: =SUMIFS(研发人员工时费用分配表!$N$6:$N$245,研发人员工时费用分配表!$A$6:$A$245,$A48) -> 0 | E48: =SUMIFS(仪器设备工时费用分配表!$J$6:$J$245,仪器设备工时费用分配表!$A$6:$A$245,$A48,仪器设备工时费用分配表!$D$6:$D$245,"设备") -> 0 | F48: =SUMIFS(无形资产费用分配表!$J$6:$J$125,无形资产费用分配表!$A$6:$A$125,$A48) -> 0 | G48: =SUMIFS(其他研发费用!$F$4:$F$153,其他研发费用!$A$4:$A$153,$A48,其他研发费用!$B$4:$B$153,$B48,其他研发费用!$D$4:$D$153,"直接投入费用") -> 0 | H48: =SUMIFS(其他研发费用!$F$4:$F$153,其他研发费用!$A$4:$A$153,$A48,其他研发费用!$B$4:$B$153,$B48,其他研发费用!$D$4:$D$153,"新产品设计费等") -> 0 | I48: =SUMIFS(其他研发费用!$F$4:$F$153,其他研发费用!$A$4:$A$153,$A48,其他研发费用!$B$4:$B$153,$B48,其他研发费用!$D$4:$D$153,"其他相关费用") -> 0 | J48: =SUMIFS(其他研发费用!$F$4:$F$153,其他研发费用!$A$4:$A$153,$A48,其他研发费用!$B$4:$B$153,$B48,其他研发费用!$D$4:$D$153,"委托外部研发费用") -> 0 | K48: =ROUND(SUM(D48:J48),2) -> 0 | L48: =SUMIFS(研发人员工时分配表!$H$6:$H$245,研发人员工时分配表!$A$6:$A$245,$A48) -> 0 | M48: =SUMIFS(仪器设备工时分配表!$H$6:$H$245,仪器设备工时分配表!$A$6:$A$245,$A48) -> 0
A49: 2026-05 | B49: =项目清单!$B$5 -> RD02 | C49: =IF($B49="","",IFERROR(VLOOKUP($B49,项目清单!$B$4:$C$13,2,0)&"","")) -> 动力电池模组用高阻燃缓冲泡棉研发 | D49: =SUMIFS(研发人员工时费用分配表!$O$6:$O$245,研发人员工时费用分配表!$A$6:$A$245,$A49) -> 0 | E49: =SUMIFS(仪器设备工时费用分配表!$K$6:$K$245,仪器设备工时费用分配表!$A$6:$A$245,$A49,仪器设备工时费用分配表!$D$6:$D$245,"设备") -> 0 | F49: =SUMIFS(无形资产费用分配表!$K$6:$K$125,无形资产费用分配表!$A$6:$A$125,$A49) -> 0 | G49: =SUMIFS(其他研发费用!$F$4:$F$153,其他研发费用!$A$4:$A$153,$A49,其他研发费用!$B$4:$B$153,$B49,其他研发费用!$D$4:$D$153,"直接投入费用") -> 0 | H49: =SUMIFS(其他研发费用!$F$4:$F$153,其他研发费用!$A$4:$A$153,$A49,其他研发费用!$B$4:$B$153,$B49,其他研发费用!$D$4:$D$153,"新产品设计费等") -> 0 | I49: =SUMIFS(其他研发费用!$F$4:$F$153,其他研发费用!$A$4:$A$153,$A49,其他研发费用!$B$4:$B$153,$B49,其他研发费用!$D$4:$D$153,"其他相关费用") -> 0 | J49: =SUMIFS(其他研发费用!$F$4:$F$153,其他研发费用!$A$4:$A$153,$A49,其他研发费用!$B$4:$B$153,$B49,其他研发费用!$D$4:$D$153,"委托外部研发费用") -> 0 | K49: =ROUND(SUM(D49:J49),2) -> 0 | L49: =SUMIFS(研发人员工时分配表!$I$6:$I$245,研发人员工时分配表!$A$6:$A$245,$A49) -> 0 | M49: =SUMIFS(仪器设备工时分配表!$I$6:$I$245,仪器设备工时分配表!$A$6:$A$245,$A49) -> 0
A50: 2026-05 | B50: =项目清单!$B$6 -> RD03 | C50: =IF($B50="","",IFERROR(VLOOKUP($B50,项目清单!$B$4:$C$13,2,0)&"","")) -> 泡棉与PET基材无溶剂贴合工艺开发 | D50: =SUMIFS(研发人员工时费用分配表!$P$6:$P$245,研发人员工时费用分配表!$A$6:$A$245,$A50) -> 0 | E50: =SUMIFS(仪器设备工时费用分配表!$L$6:$L$245,仪器设备工时费用分配表!$A$6:$A$245,$A50,仪器设备工时费用分配表!$D$6:$D$245,"设备") -> 0 | F50: =SUMIFS(无形资产费用分配表!$L$6:$L$125,无形资产费用分配表!$A$6:$A$125,$A50) -> 0 | G50: =SUMIFS(其他研发费用!$F$4:$F$153,其他研发费用!$A$4:$A$153,$A50,其他研发费用!$B$4:$B$153,$B50,其他研发费用!$D$4:$D$153,"直接投入费用") -> 0 | H50: =SUMIFS(其他研发费用!$F$4:$F$153,其他研发费用!$A$4:$A$153,$A50,其他研发费用!$B$4:$B$153,$B50,其他研发费用!$D$4:$D$153,"新产品设计费等") -> 0 | I50: =SUMIFS(其他研发费用!$F$4:$F$153,其他研发费用!$A$4:$A$153,$A50,其他研发费用!$B$4:$B$153,$B50,其他研发费用!$D$4:$D$153,"其他相关费用") -> 0 | J50: =SUMIFS(其他研发费用!$F$4:$F$153,其他研发费用!$A$4:$A$153,$A50,其他研发费用!$B$4:$B$153,$B50,其他研发费用!$D$4:$D$153,"委托外部研发费用") -> 0 | K50: =ROUND(SUM(D50:J50),2) -> 0 | L50: =SUMIFS(研发人员工时分配表!$J$6:$J$245,研发人员工时分配表!$A$6:$A$245,$A50) -> 0 | M50: =SUMIFS(仪器设备工时分配表!$J$6:$J$245,仪器设备工时分配表!$A$6:$A$245,$A50) -> 0
A51: 2026-05 | B51: =项目清单!$B$7 -> RD04 | C51: =IF($B51="","",IFERROR(VLOOKUP($B51,项目清单!$B$4:$C$13,2,0)&"","")) -> 超薄泡棉高精度分切及毛边控制技术研究 | D51: =SUMIFS(研发人员工时费用分配表!$Q$6:$Q$245,研发人员工时费用分配表!$A$6:$A$245,$A51) -> 0 | E51: =SUMIFS(仪器设备工时费用分配表!$M$6:$M$245,仪器设备工时费用分配表!$A$6:$A$245,$A51,仪器设备工时费用分配表!$D$6:$D$245,"设备") -> 0 | F51: =SUMIFS(无形资产费用分配表!$M$6:$M$125,无形资产费用分配表!$A$6:$A$125,$A51) -> 0 | G51: =SUMIFS(其他研发费用!$F$4:$F$153,其他研发费用!$A$4:$A$153,$A51,其他研发费用!$B$4:$B$153,$B51,其他研发费用!$D$4:$D$153,"直接投入费用") -> 0 | H51: =SUMIFS(其他研发费用!$F$4:$F$153,其他研发费用!$A$4:$A$153,$A51,其他研发费用!$B$4:$B$153,$B51,其他研发费用!$D$4:$D$153,"新产品设计费等") -> 0 | I51: =SUMIFS(其他研发费用!$F$4:$F$153,其他研发费用!$A$4:$A$153,$A51,其他研发费用!$B$4:$B$153,$B51,其他研发费用!$D$4:$D$153,"其他相关费用") -> 0 | J51: =SUMIFS(其他研发费用!$F$4:$F$153,其他研发费用!$A$4:$A$153,$A51,其他研发费用!$B$4:$B$153,$B51,其他研发费用!$D$4:$D$153,"委托外部研发费用") -> 0 | K51: =ROUND(SUM(D51:J51),2) -> 0 | L51: =SUMIFS(研发人员工时分配表!$K$6:$K$245,研发人员工时分配表!$A$6:$A$245,$A51) -> 0 | M51: =SUMIFS(仪器设备工时分配表!$K$6:$K$245,仪器设备工时分配表!$A$6:$A$245,$A51) -> 0
A52: 2026-05 | B52: =项目清单!$B$8 -> RD05 | C52: =IF($B52="","",IFERROR(VLOOKUP($B52,项目清单!$B$4:$C$13,2,0)&"","")) -> 新能源汽车电池包用导热缓冲复合材料开发 | D52: =SUMIFS(研发人员工时费用分配表!$R$6:$R$245,研发人员工时费用分配表!$A$6:$A$245,$A52) -> 0 | E52: =SUMIFS(仪器设备工时费用分配表!$N$6:$N$245,仪器设备工时费用分配表!$A$6:$A$245,$A52,仪器设备工时费用分配表!$D$6:$D$245,"设备") -> 0 | F52: =SUMIFS(无形资产费用分配表!$N$6:$N$125,无形资产费用分配表!$A$6:$A$125,$A52) -> 0 | G52: =SUMIFS(其他研发费用!$F$4:$F$153,其他研发费用!$A$4:$A$153,$A52,其他研发费用!$B$4:$B$153,$B52,其他研发费用!$D$4:$D$153,"直接投入费用") -> 0 | H52: =SUMIFS(其他研发费用!$F$4:$F$153,其他研发费用!$A$4:$A$153,$A52,其他研发费用!$B$4:$B$153,$B52,其他研发费用!$D$4:$D$153,"新产品设计费等") -> 0 | I52: =SUMIFS(其他研发费用!$F$4:$F$153,其他研发费用!$A$4:$A$153,$A52,其他研发费用!$B$4:$B$153,$B52,其他研发费用!$D$4:$D$153,"其他相关费用") -> 0 | J52: =SUMIFS(其他研发费用!$F$4:$F$153,其他研发费用!$A$4:$A$153,$A52,其他研发费用!$B$4:$B$153,$B52,其他研发费用!$D$4:$D$153,"委托外部研发费用") -> 0 | K52: =ROUND(SUM(D52:J52),2) -> 0 | L52: =SUMIFS(研发人员工时分配表!$L$6:$L$245,研发人员工时分配表!$A$6:$A$245,$A52) -> 0 | M52: =SUMIFS(仪器设备工时分配表!$L$6:$L$245,仪器设备工时分配表!$A$6:$A$245,$A52) -> 0
A53: 2026-05 | B53: =项目清单!$B$9 -> RD06 | C53: =IF($B53="","",IFERROR(VLOOKUP($B53,项目清单!$B$4:$C$13,2,0)&"","")) -> 3C电子用超薄黑色遮光泡棉制备技术 | D53: =SUMIFS(研发人员工时费用分配表!$S$6:$S$245,研发人员工时费用分配表!$A$6:$A$245,$A53) -> 0 | E53: =SUMIFS(仪器设备工时费用分配表!$O$6:$O$245,仪器设备工时费用分配表!$A$6:$A$245,$A53,仪器设备工时费用分配表!$D$6:$D$245,"设备") -> 0 | F53: =SUMIFS(无形资产费用分配表!$O$6:$O$125,无形资产费用分配表!$A$6:$A$125,$A53) -> 0 | G53: =SUMIFS(其他研发费用!$F$4:$F$153,其他研发费用!$A$4:$A$153,$A53,其他研发费用!$B$4:$B$153,$B53,其他研发费用!$D$4:$D$153,"直接投入费用") -> 0 | H53: =SUMIFS(其他研发费用!$F$4:$F$153,其他研发费用!$A$4:$A$153,$A53,其他研发费用!$B$4:$B$153,$B53,其他研发费用!$D$4:$D$153,"新产品设计费等") -> 0 | I53: =SUMIFS(其他研发费用!$F$4:$F$153,其他研发费用!$A$4:$A$153,$A53,其他研发费用!$B$4:$B$153,$B53,其他研发费用!$D$4:$D$153,"其他相关费用") -> 0 | J53: =SUMIFS(其他研发费用!$F$4:$F$153,其他研发费用!$A$4:$A$153,$A53,其他研发费用!$B$4:$B$153,$B53,其他研发费用!$D$4:$D$153,"委托外部研发费用") -> 0 | K53: =ROUND(SUM(D53:J53),2) -> 0 | L53: =SUMIFS(研发人员工时分配表!$M$6:$M$245,研发人员工时分配表!$A$6:$A$245,$A53) -> 0 | M53: =SUMIFS(仪器设备工时分配表!$M$6:$M$245,仪器设备工时分配表!$A$6:$A$245,$A53) -> 0
A54: 2026-05 | B54: =项目清单!$B$10 -> RD07 | C54: =IF($B54="","",IFERROR(VLOOKUP($B54,项目清单!$B$4:$C$13,2,0)&"","")) -> 环保型水性胶泡棉贴合技术开发 | D54: =SUMIFS(研发人员工时费用分配表!$T$6:$T$245,研发人员工时费用分配表!$A$6:$A$245,$A54) -> 0 | E54: =SUMIFS(仪器设备工时费用分配表!$P$6:$P$245,仪器设备工时费用分配表!$A$6:$A$245,$A54,仪器设备工时费用分配表!$D$6:$D$245,"设备") -> 0 | F54: =SUMIFS(无形资产费用分配表!$P$6:$P$125,无形资产费用分配表!$A$6:$A$125,$A54) -> 0 | G54: =SUMIFS(其他研发费用!$F$4:$F$153,其他研发费用!$A$4:$A$153,$A54,其他研发费用!$B$4:$B$153,$B54,其他研发费用!$D$4:$D$153,"直接投入费用") -> 0 | H54: =SUMIFS(其他研发费用!$F$4:$F$153,其他研发费用!$A$4:$A$153,$A54,其他研发费用!$B$4:$B$153,$B54,其他研发费用!$D$4:$D$153,"新产品设计费等") -> 0 | I54: =SUMIFS(其他研发费用!$F$4:$F$153,其他研发费用!$A$4:$A$153,$A54,其他研发费用!$B$4:$B$153,$B54,其他研发费用!$D$4:$D$153,"其他相关费用") -> 0 | J54: =SUMIFS(其他研发费用!$F$4:$F$153,其他研发费用!$A$4:$A$153,$A54,其他研发费用!$B$4:$B$153,$B54,其他研发费用!$D$4:$D$153,"委托外部研发费用") -> 0 | K54: =ROUND(SUM(D54:J54),2) -> 0 | L54: =SUMIFS(研发人员工时分配表!$N$6:$N$245,研发人员工时分配表!$A$6:$A$245,$A54) -> 0 | M54: =SUMIFS(仪器设备工时分配表!$N$6:$N$245,仪器设备工时分配表!$A$6:$A$245,$A54) -> 0
A55: 2026-05 | B55: =项目清单!$B$11 -> RD08 | C55: =IF($B55="","",IFERROR(VLOOKUP($B55,项目清单!$B$4:$C$13,2,0)&"","")) -> 泡棉模切自动化在线检测技术研究 | D55: =SUMIFS(研发人员工时费用分配表!$U$6:$U$245,研发人员工时费用分配表!$A$6:$A$245,$A55) -> 0 | E55: =SUMIFS(仪器设备工时费用分配表!$Q$6:$Q$245,仪器设备工时费用分配表!$A$6:$A$245,$A55,仪器设备工时费用分配表!$D$6:$D$245,"设备") -> 0 | F55: =SUMIFS(无形资产费用分配表!$Q$6:$Q$125,无形资产费用分配表!$A$6:$A$125,$A55) -> 0 | G55: =SUMIFS(其他研发费用!$F$4:$F$153,其他研发费用!$A$4:$A$153,$A55,其他研发费用!$B$4:$B$153,$B55,其他研发费用!$D$4:$D$153,"直接投入费用") -> 0 | H55: =SUMIFS(其他研发费用!$F$4:$F$153,其他研发费用!$A$4:$A$153,$A55,其他研发费用!$B$4:$B$153,$B55,其他研发费用!$D$4:$D$153,"新产品设计费等") -> 0 | I55: =SUMIFS(其他研发费用!$F$4:$F$153,其他研发费用!$A$4:$A$153,$A55,其他研发费用!$B$4:$B$153,$B55,其他研发费用!$D$4:$D$153,"其他相关费用") -> 0 | J55: =SUMIFS(其他研发费用!$F$4:$F$153,其他研发费用!$A$4:$A$153,$A55,其他研发费用!$B$4:$B$153,$B55,其他研发费用!$D$4:$D$153,"委托外部研发费用") -> 0 | K55: =ROUND(SUM(D55:J55),2) -> 0 | L55: =SUMIFS(研发人员工时分配表!$O$6:$O$245,研发人员工时分配表!$A$6:$A$245,$A55) -> 0 | M55: =SUMIFS(仪器设备工时分配表!$O$6:$O$245,仪器设备工时分配表!$A$6:$A$245,$A55) -> 0
A56: 2026-05 | B56: =项目清单!$B$12 -> RD09 | C56: =IF($B56="","",IFERROR(VLOOKUP($B56,项目清单!$B$4:$C$13,2,0)&"","")) | D56: =SUMIFS(研发人员工时费用分配表!$V$6:$V$245,研发人员工时费用分配表!$A$6:$A$245,$A56) -> 0 | E56: =SUMIFS(仪器设备工时费用分配表!$R$6:$R$245,仪器设备工时费用分配表!$A$6:$A$245,$A56,仪器设备工时费用分配表!$D$6:$D$245,"设备") -> 0 | F56: =SUMIFS(无形资产费用分配表!$R$6:$R$125,无形资产费用分配表!$A$6:$A$125,$A56) -> 0 | G56: =SUMIFS(其他研发费用!$F$4:$F$153,其他研发费用!$A$4:$A$153,$A56,其他研发费用!$B$4:$B$153,$B56,其他研发费用!$D$4:$D$153,"直接投入费用") -> 0 | H56: =SUMIFS(其他研发费用!$F$4:$F$153,其他研发费用!$A$4:$A$153,$A56,其他研发费用!$B$4:$B$153,$B56,其他研发费用!$D$4:$D$153,"新产品设计费等") -> 0 | I56: =SUMIFS(其他研发费用!$F$4:$F$153,其他研发费用!$A$4:$A$153,$A56,其他研发费用!$B$4:$B$153,$B56,其他研发费用!$D$4:$D$153,"其他相关费用") -> 0 | J56: =SUMIFS(其他研发费用!$F$4:$F$153,其他研发费用!$A$4:$A$153,$A56,其他研发费用!$B$4:$B$153,$B56,其他研发费用!$D$4:$D$153,"委托外部研发费用") -> 0 | K56: =ROUND(SUM(D56:J56),2) -> 0 | L56: =SUMIFS(研发人员工时分配表!$P$6:$P$245,研发人员工时分配表!$A$6:$A$245,$A56) -> 0 | M56: =SUMIFS(仪器设备工时分配表!$P$6:$P$245,仪器设备工时分配表!$A$6:$A$245,$A56) -> 0
A57: 2026-05 | B57: =项目清单!$B$13 -> RD10 | C57: =IF($B57="","",IFERROR(VLOOKUP($B57,项目清单!$B$4:$C$13,2,0)&"","")) | D57: =SUMIFS(研发人员工时费用分配表!$W$6:$W$245,研发人员工时费用分配表!$A$6:$A$245,$A57) -> 0 | E57: =SUMIFS(仪器设备工时费用分配表!$S$6:$S$245,仪器设备工时费用分配表!$A$6:$A$245,$A57,仪器设备工时费用分配表!$D$6:$D$245,"设备") -> 0 | F57: =SUMIFS(无形资产费用分配表!$S$6:$S$125,无形资产费用分配表!$A$6:$A$125,$A57) -> 0 | G57: =SUMIFS(其他研发费用!$F$4:$F$153,其他研发费用!$A$4:$A$153,$A57,其他研发费用!$B$4:$B$153,$B57,其他研发费用!$D$4:$D$153,"直接投入费用") -> 0 | H57: =SUMIFS(其他研发费用!$F$4:$F$153,其他研发费用!$A$4:$A$153,$A57,其他研发费用!$B$4:$B$153,$B57,其他研发费用!$D$4:$D$153,"新产品设计费等") -> 0 | I57: =SUMIFS(其他研发费用!$F$4:$F$153,其他研发费用!$A$4:$A$153,$A57,其他研发费用!$B$4:$B$153,$B57,其他研发费用!$D$4:$D$153,"其他相关费用") -> 0 | J57: =SUMIFS(其他研发费用!$F$4:$F$153,其他研发费用!$A$4:$A$153,$A57,其他研发费用!$B$4:$B$153,$B57,其他研发费用!$D$4:$D$153,"委托外部研发费用") -> 0 | K57: =ROUND(SUM(D57:J57),2) -> 0 | L57: =SUMIFS(研发人员工时分配表!$Q$6:$Q$245,研发人员工时分配表!$A$6:$A$245,$A57) -> 0 | M57: =SUMIFS(仪器设备工时分配表!$Q$6:$Q$245,仪器设备工时分配表!$A$6:$A$245,$A57) -> 0
A58: 2026-05 | C58: 本月合计 | D58: =ROUND(SUM(D48:D57),2) -> 0 | E58: =ROUND(SUM(E48:E57),2) -> 0 | F58: =ROUND(SUM(F48:F57),2) -> 0 | G58: =ROUND(SUM(G48:G57),2) -> 0 | H58: =ROUND(SUM(H48:H57),2) -> 0 | I58: =ROUND(SUM(I48:I57),2) -> 0 | J58: =ROUND(SUM(J48:J57),2) -> 0 | K58: =ROUND(SUM(K48:K57),2) -> 0 | ... M58: =ROUND(SUM(M48:M57),2) -> 0
A59: 2026-06 | B59: =项目清单!$B$4 -> RD01 | C59: =IF($B59="","",IFERROR(VLOOKUP($B59,项目清单!$B$4:$C$13,2,0)&"","")) -> 高回弹低压缩永久变形3C用聚氨酯泡棉开发 | D59: =SUMIFS(研发人员工时费用分配表!$N$6:$N$245,研发人员工时费用分配表!$A$6:$A$245,$A59) -> 0 | E59: =SUMIFS(仪器设备工时费用分配表!$J$6:$J$245,仪器设备工时费用分配表!$A$6:$A$245,$A59,仪器设备工时费用分配表!$D$6:$D$245,"设备") -> 0 | F59: =SUMIFS(无形资产费用分配表!$J$6:$J$125,无形资产费用分配表!$A$6:$A$125,$A59) -> 0 | G59: =SUMIFS(其他研发费用!$F$4:$F$153,其他研发费用!$A$4:$A$153,$A59,其他研发费用!$B$4:$B$153,$B59,其他研发费用!$D$4:$D$153,"直接投入费用") -> 0 | H59: =SUMIFS(其他研发费用!$F$4:$F$153,其他研发费用!$A$4:$A$153,$A59,其他研发费用!$B$4:$B$153,$B59,其他研发费用!$D$4:$D$153,"新产品设计费等") -> 0 | I59: =SUMIFS(其他研发费用!$F$4:$F$153,其他研发费用!$A$4:$A$153,$A59,其他研发费用!$B$4:$B$153,$B59,其他研发费用!$D$4:$D$153,"其他相关费用") -> 0 | J59: =SUMIFS(其他研发费用!$F$4:$F$153,其他研发费用!$A$4:$A$153,$A59,其他研发费用!$B$4:$B$153,$B59,其他研发费用!$D$4:$D$153,"委托外部研发费用") -> 0 | K59: =ROUND(SUM(D59:J59),2) -> 0 | L59: =SUMIFS(研发人员工时分配表!$H$6:$H$245,研发人员工时分配表!$A$6:$A$245,$A59) -> 0 | M59: =SUMIFS(仪器设备工时分配表!$H$6:$H$245,仪器设备工时分配表!$A$6:$A$245,$A59) -> 0
A60: 2026-06 | B60: =项目清单!$B$5 -> RD02 | C60: =IF($B60="","",IFERROR(VLOOKUP($B60,项目清单!$B$4:$C$13,2,0)&"","")) -> 动力电池模组用高阻燃缓冲泡棉研发 | D60: =SUMIFS(研发人员工时费用分配表!$O$6:$O$245,研发人员工时费用分配表!$A$6:$A$245,$A60) -> 0 | E60: =SUMIFS(仪器设备工时费用分配表!$K$6:$K$245,仪器设备工时费用分配表!$A$6:$A$245,$A60,仪器设备工时费用分配表!$D$6:$D$245,"设备") -> 0 | F60: =SUMIFS(无形资产费用分配表!$K$6:$K$125,无形资产费用分配表!$A$6:$A$125,$A60) -> 0 | G60: =SUMIFS(其他研发费用!$F$4:$F$153,其他研发费用!$A$4:$A$153,$A60,其他研发费用!$B$4:$B$153,$B60,其他研发费用!$D$4:$D$153,"直接投入费用") -> 0 | H60: =SUMIFS(其他研发费用!$F$4:$F$153,其他研发费用!$A$4:$A$153,$A60,其他研发费用!$B$4:$B$153,$B60,其他研发费用!$D$4:$D$153,"新产品设计费等") -> 0 | I60: =SUMIFS(其他研发费用!$F$4:$F$153,其他研发费用!$A$4:$A$153,$A60,其他研发费用!$B$4:$B$153,$B60,其他研发费用!$D$4:$D$153,"其他相关费用") -> 0 | J60: =SUMIFS(其他研发费用!$F$4:$F$153,其他研发费用!$A$4:$A$153,$A60,其他研发费用!$B$4:$B$153,$B60,其他研发费用!$D$4:$D$153,"委托外部研发费用") -> 0 | K60: =ROUND(SUM(D60:J60),2) -> 0 | L60: =SUMIFS(研发人员工时分配表!$I$6:$I$245,研发人员工时分配表!$A$6:$A$245,$A60) -> 0 | M60: =SUMIFS(仪器设备工时分配表!$I$6:$I$245,仪器设备工时分配表!$A$6:$A$245,$A60) -> 0
A61: 2026-06 | B61: =项目清单!$B$6 -> RD03 | C61: =IF($B61="","",IFERROR(VLOOKUP($B61,项目清单!$B$4:$C$13,2,0)&"","")) -> 泡棉与PET基材无溶剂贴合工艺开发 | D61: =SUMIFS(研发人员工时费用分配表!$P$6:$P$245,研发人员工时费用分配表!$A$6:$A$245,$A61) -> 0 | E61: =SUMIFS(仪器设备工时费用分配表!$L$6:$L$245,仪器设备工时费用分配表!$A$6:$A$245,$A61,仪器设备工时费用分配表!$D$6:$D$245,"设备") -> 0 | F61: =SUMIFS(无形资产费用分配表!$L$6:$L$125,无形资产费用分配表!$A$6:$A$125,$A61) -> 0 | G61: =SUMIFS(其他研发费用!$F$4:$F$153,其他研发费用!$A$4:$A$153,$A61,其他研发费用!$B$4:$B$153,$B61,其他研发费用!$D$4:$D$153,"直接投入费用") -> 0 | H61: =SUMIFS(其他研发费用!$F$4:$F$153,其他研发费用!$A$4:$A$153,$A61,其他研发费用!$B$4:$B$153,$B61,其他研发费用!$D$4:$D$153,"新产品设计费等") -> 0 | I61: =SUMIFS(其他研发费用!$F$4:$F$153,其他研发费用!$A$4:$A$153,$A61,其他研发费用!$B$4:$B$153,$B61,其他研发费用!$D$4:$D$153,"其他相关费用") -> 0 | J61: =SUMIFS(其他研发费用!$F$4:$F$153,其他研发费用!$A$4:$A$153,$A61,其他研发费用!$B$4:$B$153,$B61,其他研发费用!$D$4:$D$153,"委托外部研发费用") -> 0 | K61: =ROUND(SUM(D61:J61),2) -> 0 | L61: =SUMIFS(研发人员工时分配表!$J$6:$J$245,研发人员工时分配表!$A$6:$A$245,$A61) -> 0 | M61: =SUMIFS(仪器设备工时分配表!$J$6:$J$245,仪器设备工时分配表!$A$6:$A$245,$A61) -> 0
A62: 2026-06 | B62: =项目清单!$B$7 -> RD04 | C62: =IF($B62="","",IFERROR(VLOOKUP($B62,项目清单!$B$4:$C$13,2,0)&"","")) -> 超薄泡棉高精度分切及毛边控制技术研究 | D62: =SUMIFS(研发人员工时费用分配表!$Q$6:$Q$245,研发人员工时费用分配表!$A$6:$A$245,$A62) -> 0 | E62: =SUMIFS(仪器设备工时费用分配表!$M$6:$M$245,仪器设备工时费用分配表!$A$6:$A$245,$A62,仪器设备工时费用分配表!$D$6:$D$245,"设备") -> 0 | F62: =SUMIFS(无形资产费用分配表!$M$6:$M$125,无形资产费用分配表!$A$6:$A$125,$A62) -> 0 | G62: =SUMIFS(其他研发费用!$F$4:$F$153,其他研发费用!$A$4:$A$153,$A62,其他研发费用!$B$4:$B$153,$B62,其他研发费用!$D$4:$D$153,"直接投入费用") -> 0 | H62: =SUMIFS(其他研发费用!$F$4:$F$153,其他研发费用!$A$4:$A$153,$A62,其他研发费用!$B$4:$B$153,$B62,其他研发费用!$D$4:$D$153,"新产品设计费等") -> 0 | I62: =SUMIFS(其他研发费用!$F$4:$F$153,其他研发费用!$A$4:$A$153,$A62,其他研发费用!$B$4:$B$153,$B62,其他研发费用!$D$4:$D$153,"其他相关费用") -> 0 | J62: =SUMIFS(其他研发费用!$F$4:$F$153,其他研发费用!$A$4:$A$153,$A62,其他研发费用!$B$4:$B$153,$B62,其他研发费用!$D$4:$D$153,"委托外部研发费用") -> 0 | K62: =ROUND(SUM(D62:J62),2) -> 0 | L62: =SUMIFS(研发人员工时分配表!$K$6:$K$245,研发人员工时分配表!$A$6:$A$245,$A62) -> 0 | M62: =SUMIFS(仪器设备工时分配表!$K$6:$K$245,仪器设备工时分配表!$A$6:$A$245,$A62) -> 0
A63: 2026-06 | B63: =项目清单!$B$8 -> RD05 | C63: =IF($B63="","",IFERROR(VLOOKUP($B63,项目清单!$B$4:$C$13,2,0)&"","")) -> 新能源汽车电池包用导热缓冲复合材料开发 | D63: =SUMIFS(研发人员工时费用分配表!$R$6:$R$245,研发人员工时费用分配表!$A$6:$A$245,$A63) -> 0 | E63: =SUMIFS(仪器设备工时费用分配表!$N$6:$N$245,仪器设备工时费用分配表!$A$6:$A$245,$A63,仪器设备工时费用分配表!$D$6:$D$245,"设备") -> 0 | F63: =SUMIFS(无形资产费用分配表!$N$6:$N$125,无形资产费用分配表!$A$6:$A$125,$A63) -> 0 | G63: =SUMIFS(其他研发费用!$F$4:$F$153,其他研发费用!$A$4:$A$153,$A63,其他研发费用!$B$4:$B$153,$B63,其他研发费用!$D$4:$D$153,"直接投入费用") -> 0 | H63: =SUMIFS(其他研发费用!$F$4:$F$153,其他研发费用!$A$4:$A$153,$A63,其他研发费用!$B$4:$B$153,$B63,其他研发费用!$D$4:$D$153,"新产品设计费等") -> 0 | I63: =SUMIFS(其他研发费用!$F$4:$F$153,其他研发费用!$A$4:$A$153,$A63,其他研发费用!$B$4:$B$153,$B63,其他研发费用!$D$4:$D$153,"其他相关费用") -> 0 | J63: =SUMIFS(其他研发费用!$F$4:$F$153,其他研发费用!$A$4:$A$153,$A63,其他研发费用!$B$4:$B$153,$B63,其他研发费用!$D$4:$D$153,"委托外部研发费用") -> 0 | K63: =ROUND(SUM(D63:J63),2) -> 0 | L63: =SUMIFS(研发人员工时分配表!$L$6:$L$245,研发人员工时分配表!$A$6:$A$245,$A63) -> 0 | M63: =SUMIFS(仪器设备工时分配表!$L$6:$L$245,仪器设备工时分配表!$A$6:$A$245,$A63) -> 0
A64: 2026-06 | B64: =项目清单!$B$9 -> RD06 | C64: =IF($B64="","",IFERROR(VLOOKUP($B64,项目清单!$B$4:$C$13,2,0)&"","")) -> 3C电子用超薄黑色遮光泡棉制备技术 | D64: =SUMIFS(研发人员工时费用分配表!$S$6:$S$245,研发人员工时费用分配表!$A$6:$A$245,$A64) -> 0 | E64: =SUMIFS(仪器设备工时费用分配表!$O$6:$O$245,仪器设备工时费用分配表!$A$6:$A$245,$A64,仪器设备工时费用分配表!$D$6:$D$245,"设备") -> 0 | F64: =SUMIFS(无形资产费用分配表!$O$6:$O$125,无形资产费用分配表!$A$6:$A$125,$A64) -> 0 | G64: =SUMIFS(其他研发费用!$F$4:$F$153,其他研发费用!$A$4:$A$153,$A64,其他研发费用!$B$4:$B$153,$B64,其他研发费用!$D$4:$D$153,"直接投入费用") -> 0 | H64: =SUMIFS(其他研发费用!$F$4:$F$153,其他研发费用!$A$4:$A$153,$A64,其他研发费用!$B$4:$B$153,$B64,其他研发费用!$D$4:$D$153,"新产品设计费等") -> 0 | I64: =SUMIFS(其他研发费用!$F$4:$F$153,其他研发费用!$A$4:$A$153,$A64,其他研发费用!$B$4:$B$153,$B64,其他研发费用!$D$4:$D$153,"其他相关费用") -> 0 | J64: =SUMIFS(其他研发费用!$F$4:$F$153,其他研发费用!$A$4:$A$153,$A64,其他研发费用!$B$4:$B$153,$B64,其他研发费用!$D$4:$D$153,"委托外部研发费用") -> 0 | K64: =ROUND(SUM(D64:J64),2) -> 0 | L64: =SUMIFS(研发人员工时分配表!$M$6:$M$245,研发人员工时分配表!$A$6:$A$245,$A64) -> 0 | M64: =SUMIFS(仪器设备工时分配表!$M$6:$M$245,仪器设备工时分配表!$A$6:$A$245,$A64) -> 0
A65: 2026-06 | B65: =项目清单!$B$10 -> RD07 | C65: =IF($B65="","",IFERROR(VLOOKUP($B65,项目清单!$B$4:$C$13,2,0)&"","")) -> 环保型水性胶泡棉贴合技术开发 | D65: =SUMIFS(研发人员工时费用分配表!$T$6:$T$245,研发人员工时费用分配表!$A$6:$A$245,$A65) -> 0 | E65: =SUMIFS(仪器设备工时费用分配表!$P$6:$P$245,仪器设备工时费用分配表!$A$6:$A$245,$A65,仪器设备工时费用分配表!$D$6:$D$245,"设备") -> 0 | F65: =SUMIFS(无形资产费用分配表!$P$6:$P$125,无形资产费用分配表!$A$6:$A$125,$A65) -> 0 | G65: =SUMIFS(其他研发费用!$F$4:$F$153,其他研发费用!$A$4:$A$153,$A65,其他研发费用!$B$4:$B$153,$B65,其他研发费用!$D$4:$D$153,"直接投入费用") -> 0 | H65: =SUMIFS(其他研发费用!$F$4:$F$153,其他研发费用!$A$4:$A$153,$A65,其他研发费用!$B$4:$B$153,$B65,其他研发费用!$D$4:$D$153,"新产品设计费等") -> 0 | I65: =SUMIFS(其他研发费用!$F$4:$F$153,其他研发费用!$A$4:$A$153,$A65,其他研发费用!$B$4:$B$153,$B65,其他研发费用!$D$4:$D$153,"其他相关费用") -> 0 | J65: =SUMIFS(其他研发费用!$F$4:$F$153,其他研发费用!$A$4:$A$153,$A65,其他研发费用!$B$4:$B$153,$B65,其他研发费用!$D$4:$D$153,"委托外部研发费用") -> 0 | K65: =ROUND(SUM(D65:J65),2) -> 0 | L65: =SUMIFS(研发人员工时分配表!$N$6:$N$245,研发人员工时分配表!$A$6:$A$245,$A65) -> 0 | M65: =SUMIFS(仪器设备工时分配表!$N$6:$N$245,仪器设备工时分配表!$A$6:$A$245,$A65) -> 0
A66: 2026-06 | B66: =项目清单!$B$11 -> RD08 | C66: =IF($B66="","",IFERROR(VLOOKUP($B66,项目清单!$B$4:$C$13,2,0)&"","")) -> 泡棉模切自动化在线检测技术研究 | D66: =SUMIFS(研发人员工时费用分配表!$U$6:$U$245,研发人员工时费用分配表!$A$6:$A$245,$A66) -> 0 | E66: =SUMIFS(仪器设备工时费用分配表!$Q$6:$Q$245,仪器设备工时费用分配表!$A$6:$A$245,$A66,仪器设备工时费用分配表!$D$6:$D$245,"设备") -> 0 | F66: =SUMIFS(无形资产费用分配表!$Q$6:$Q$125,无形资产费用分配表!$A$6:$A$125,$A66) -> 0 | G66: =SUMIFS(其他研发费用!$F$4:$F$153,其他研发费用!$A$4:$A$153,$A66,其他研发费用!$B$4:$B$153,$B66,其他研发费用!$D$4:$D$153,"直接投入费用") -> 0 | H66: =SUMIFS(其他研发费用!$F$4:$F$153,其他研发费用!$A$4:$A$153,$A66,其他研发费用!$B$4:$B$153,$B66,其他研发费用!$D$4:$D$153,"新产品设计费等") -> 0 | I66: =SUMIFS(其他研发费用!$F$4:$F$153,其他研发费用!$A$4:$A$153,$A66,其他研发费用!$B$4:$B$153,$B66,其他研发费用!$D$4:$D$153,"其他相关费用") -> 0 | J66: =SUMIFS(其他研发费用!$F$4:$F$153,其他研发费用!$A$4:$A$153,$A66,其他研发费用!$B$4:$B$153,$B66,其他研发费用!$D$4:$D$153,"委托外部研发费用") -> 0 | K66: =ROUND(SUM(D66:J66),2) -> 0 | L66: =SUMIFS(研发人员工时分配表!$O$6:$O$245,研发人员工时分配表!$A$6:$A$245,$A66) -> 0 | M66: =SUMIFS(仪器设备工时分配表!$O$6:$O$245,仪器设备工时分配表!$A$6:$A$245,$A66) -> 0
A67: 2026-06 | B67: =项目清单!$B$12 -> RD09 | C67: =IF($B67="","",IFERROR(VLOOKUP($B67,项目清单!$B$4:$C$13,2,0)&"","")) | D67: =SUMIFS(研发人员工时费用分配表!$V$6:$V$245,研发人员工时费用分配表!$A$6:$A$245,$A67) -> 0 | E67: =SUMIFS(仪器设备工时费用分配表!$R$6:$R$245,仪器设备工时费用分配表!$A$6:$A$245,$A67,仪器设备工时费用分配表!$D$6:$D$245,"设备") -> 0 | F67: =SUMIFS(无形资产费用分配表!$R$6:$R$125,无形资产费用分配表!$A$6:$A$125,$A67) -> 0 | G67: =SUMIFS(其他研发费用!$F$4:$F$153,其他研发费用!$A$4:$A$153,$A67,其他研发费用!$B$4:$B$153,$B67,其他研发费用!$D$4:$D$153,"直接投入费用") -> 0 | H67: =SUMIFS(其他研发费用!$F$4:$F$153,其他研发费用!$A$4:$A$153,$A67,其他研发费用!$B$4:$B$153,$B67,其他研发费用!$D$4:$D$153,"新产品设计费等") -> 0 | I67: =SUMIFS(其他研发费用!$F$4:$F$153,其他研发费用!$A$4:$A$153,$A67,其他研发费用!$B$4:$B$153,$B67,其他研发费用!$D$4:$D$153,"其他相关费用") -> 0 | J67: =SUMIFS(其他研发费用!$F$4:$F$153,其他研发费用!$A$4:$A$153,$A67,其他研发费用!$B$4:$B$153,$B67,其他研发费用!$D$4:$D$153,"委托外部研发费用") -> 0 | K67: =ROUND(SUM(D67:J67),2) -> 0 | L67: =SUMIFS(研发人员工时分配表!$P$6:$P$245,研发人员工时分配表!$A$6:$A$245,$A67) -> 0 | M67: =SUMIFS(仪器设备工时分配表!$P$6:$P$245,仪器设备工时分配表!$A$6:$A$245,$A67) -> 0
A68: 2026-06 | B68: =项目清单!$B$13 -> RD10 | C68: =IF($B68="","",IFERROR(VLOOKUP($B68,项目清单!$B$4:$C$13,2,0)&"","")) | D68: =SUMIFS(研发人员工时费用分配表!$W$6:$W$245,研发人员工时费用分配表!$A$6:$A$245,$A68) -> 0 | E68: =SUMIFS(仪器设备工时费用分配表!$S$6:$S$245,仪器设备工时费用分配表!$A$6:$A$245,$A68,仪器设备工时费用分配表!$D$6:$D$245,"设备") -> 0 | F68: =SUMIFS(无形资产费用分配表!$S$6:$S$125,无形资产费用分配表!$A$6:$A$125,$A68) -> 0 | G68: =SUMIFS(其他研发费用!$F$4:$F$153,其他研发费用!$A$4:$A$153,$A68,其他研发费用!$B$4:$B$153,$B68,其他研发费用!$D$4:$D$153,"直接投入费用") -> 0 | H68: =SUMIFS(其他研发费用!$F$4:$F$153,其他研发费用!$A$4:$A$153,$A68,其他研发费用!$B$4:$B$153,$B68,其他研发费用!$D$4:$D$153,"新产品设计费等") -> 0 | I68: =SUMIFS(其他研发费用!$F$4:$F$153,其他研发费用!$A$4:$A$153,$A68,其他研发费用!$B$4:$B$153,$B68,其他研发费用!$D$4:$D$153,"其他相关费用") -> 0 | J68: =SUMIFS(其他研发费用!$F$4:$F$153,其他研发费用!$A$4:$A$153,$A68,其他研发费用!$B$4:$B$153,$B68,其他研发费用!$D$4:$D$153,"委托外部研发费用") -> 0 | K68: =ROUND(SUM(D68:J68),2) -> 0 | L68: =SUMIFS(研发人员工时分配表!$Q$6:$Q$245,研发人员工时分配表!$A$6:$A$245,$A68) -> 0 | M68: =SUMIFS(仪器设备工时分配表!$Q$6:$Q$245,仪器设备工时分配表!$A$6:$A$245,$A68) -> 0
A69: 2026-06 | C69: 本月合计 | D69: =ROUND(SUM(D59:D68),2) -> 0 | E69: =ROUND(SUM(E59:E68),2) -> 0 | F69: =ROUND(SUM(F59:F68),2) -> 0 | G69: =ROUND(SUM(G59:G68),2) -> 0 | H69: =ROUND(SUM(H59:H68),2) -> 0 | I69: =ROUND(SUM(I59:I68),2) -> 0 | J69: =ROUND(SUM(J59:J68),2) -> 0 | K69: =ROUND(SUM(K59:K68),2) -> 0 | ... M69: =ROUND(SUM(M59:M68),2) -> 0
A70: 2026-07 | B70: =项目清单!$B$4 -> RD01 | C70: =IF($B70="","",IFERROR(VLOOKUP($B70,项目清单!$B$4:$C$13,2,0)&"","")) -> 高回弹低压缩永久变形3C用聚氨酯泡棉开发 | D70: =SUMIFS(研发人员工时费用分配表!$N$6:$N$245,研发人员工时费用分配表!$A$6:$A$245,$A70) -> 0 | E70: =SUMIFS(仪器设备工时费用分配表!$J$6:$J$245,仪器设备工时费用分配表!$A$6:$A$245,$A70,仪器设备工时费用分配表!$D$6:$D$245,"设备") -> 0 | F70: =SUMIFS(无形资产费用分配表!$J$6:$J$125,无形资产费用分配表!$A$6:$A$125,$A70) -> 0 | G70: =SUMIFS(其他研发费用!$F$4:$F$153,其他研发费用!$A$4:$A$153,$A70,其他研发费用!$B$4:$B$153,$B70,其他研发费用!$D$4:$D$153,"直接投入费用") -> 0 | H70: =SUMIFS(其他研发费用!$F$4:$F$153,其他研发费用!$A$4:$A$153,$A70,其他研发费用!$B$4:$B$153,$B70,其他研发费用!$D$4:$D$153,"新产品设计费等") -> 0 | I70: =SUMIFS(其他研发费用!$F$4:$F$153,其他研发费用!$A$4:$A$153,$A70,其他研发费用!$B$4:$B$153,$B70,其他研发费用!$D$4:$D$153,"其他相关费用") -> 0 | J70: =SUMIFS(其他研发费用!$F$4:$F$153,其他研发费用!$A$4:$A$153,$A70,其他研发费用!$B$4:$B$153,$B70,其他研发费用!$D$4:$D$153,"委托外部研发费用") -> 0 | K70: =ROUND(SUM(D70:J70),2) -> 0 | L70: =SUMIFS(研发人员工时分配表!$H$6:$H$245,研发人员工时分配表!$A$6:$A$245,$A70) -> 0 | M70: =SUMIFS(仪器设备工时分配表!$H$6:$H$245,仪器设备工时分配表!$A$6:$A$245,$A70) -> 0
A71: 2026-07 | B71: =项目清单!$B$5 -> RD02 | C71: =IF($B71="","",IFERROR(VLOOKUP($B71,项目清单!$B$4:$C$13,2,0)&"","")) -> 动力电池模组用高阻燃缓冲泡棉研发 | D71: =SUMIFS(研发人员工时费用分配表!$O$6:$O$245,研发人员工时费用分配表!$A$6:$A$245,$A71) -> 0 | E71: =SUMIFS(仪器设备工时费用分配表!$K$6:$K$245,仪器设备工时费用分配表!$A$6:$A$245,$A71,仪器设备工时费用分配表!$D$6:$D$245,"设备") -> 0 | F71: =SUMIFS(无形资产费用分配表!$K$6:$K$125,无形资产费用分配表!$A$6:$A$125,$A71) -> 0 | G71: =SUMIFS(其他研发费用!$F$4:$F$153,其他研发费用!$A$4:$A$153,$A71,其他研发费用!$B$4:$B$153,$B71,其他研发费用!$D$4:$D$153,"直接投入费用") -> 0 | H71: =SUMIFS(其他研发费用!$F$4:$F$153,其他研发费用!$A$4:$A$153,$A71,其他研发费用!$B$4:$B$153,$B71,其他研发费用!$D$4:$D$153,"新产品设计费等") -> 0 | I71: =SUMIFS(其他研发费用!$F$4:$F$153,其他研发费用!$A$4:$A$153,$A71,其他研发费用!$B$4:$B$153,$B71,其他研发费用!$D$4:$D$153,"其他相关费用") -> 0 | J71: =SUMIFS(其他研发费用!$F$4:$F$153,其他研发费用!$A$4:$A$153,$A71,其他研发费用!$B$4:$B$153,$B71,其他研发费用!$D$4:$D$153,"委托外部研发费用") -> 0 | K71: =ROUND(SUM(D71:J71),2) -> 0 | L71: =SUMIFS(研发人员工时分配表!$I$6:$I$245,研发人员工时分配表!$A$6:$A$245,$A71) -> 0 | M71: =SUMIFS(仪器设备工时分配表!$I$6:$I$245,仪器设备工时分配表!$A$6:$A$245,$A71) -> 0
A72: 2026-07 | B72: =项目清单!$B$6 -> RD03 | C72: =IF($B72="","",IFERROR(VLOOKUP($B72,项目清单!$B$4:$C$13,2,0)&"","")) -> 泡棉与PET基材无溶剂贴合工艺开发 | D72: =SUMIFS(研发人员工时费用分配表!$P$6:$P$245,研发人员工时费用分配表!$A$6:$A$245,$A72) -> 0 | E72: =SUMIFS(仪器设备工时费用分配表!$L$6:$L$245,仪器设备工时费用分配表!$A$6:$A$245,$A72,仪器设备工时费用分配表!$D$6:$D$245,"设备") -> 0 | F72: =SUMIFS(无形资产费用分配表!$L$6:$L$125,无形资产费用分配表!$A$6:$A$125,$A72) -> 0 | G72: =SUMIFS(其他研发费用!$F$4:$F$153,其他研发费用!$A$4:$A$153,$A72,其他研发费用!$B$4:$B$153,$B72,其他研发费用!$D$4:$D$153,"直接投入费用") -> 0 | H72: =SUMIFS(其他研发费用!$F$4:$F$153,其他研发费用!$A$4:$A$153,$A72,其他研发费用!$B$4:$B$153,$B72,其他研发费用!$D$4:$D$153,"新产品设计费等") -> 0 | I72: =SUMIFS(其他研发费用!$F$4:$F$153,其他研发费用!$A$4:$A$153,$A72,其他研发费用!$B$4:$B$153,$B72,其他研发费用!$D$4:$D$153,"其他相关费用") -> 0 | J72: =SUMIFS(其他研发费用!$F$4:$F$153,其他研发费用!$A$4:$A$153,$A72,其他研发费用!$B$4:$B$153,$B72,其他研发费用!$D$4:$D$153,"委托外部研发费用") -> 0 | K72: =ROUND(SUM(D72:J72),2) -> 0 | L72: =SUMIFS(研发人员工时分配表!$J$6:$J$245,研发人员工时分配表!$A$6:$A$245,$A72) -> 0 | M72: =SUMIFS(仪器设备工时分配表!$J$6:$J$245,仪器设备工时分配表!$A$6:$A$245,$A72) -> 0
A73: 2026-07 | B73: =项目清单!$B$7 -> RD04 | C73: =IF($B73="","",IFERROR(VLOOKUP($B73,项目清单!$B$4:$C$13,2,0)&"","")) -> 超薄泡棉高精度分切及毛边控制技术研究 | D73: =SUMIFS(研发人员工时费用分配表!$Q$6:$Q$245,研发人员工时费用分配表!$A$6:$A$245,$A73) -> 0 | E73: =SUMIFS(仪器设备工时费用分配表!$M$6:$M$245,仪器设备工时费用分配表!$A$6:$A$245,$A73,仪器设备工时费用分配表!$D$6:$D$245,"设备") -> 0 | F73: =SUMIFS(无形资产费用分配表!$M$6:$M$125,无形资产费用分配表!$A$6:$A$125,$A73) -> 0 | G73: =SUMIFS(其他研发费用!$F$4:$F$153,其他研发费用!$A$4:$A$153,$A73,其他研发费用!$B$4:$B$153,$B73,其他研发费用!$D$4:$D$153,"直接投入费用") -> 0 | H73: =SUMIFS(其他研发费用!$F$4:$F$153,其他研发费用!$A$4:$A$153,$A73,其他研发费用!$B$4:$B$153,$B73,其他研发费用!$D$4:$D$153,"新产品设计费等") -> 0 | I73: =SUMIFS(其他研发费用!$F$4:$F$153,其他研发费用!$A$4:$A$153,$A73,其他研发费用!$B$4:$B$153,$B73,其他研发费用!$D$4:$D$153,"其他相关费用") -> 0 | J73: =SUMIFS(其他研发费用!$F$4:$F$153,其他研发费用!$A$4:$A$153,$A73,其他研发费用!$B$4:$B$153,$B73,其他研发费用!$D$4:$D$153,"委托外部研发费用") -> 0 | K73: =ROUND(SUM(D73:J73),2) -> 0 | L73: =SUMIFS(研发人员工时分配表!$K$6:$K$245,研发人员工时分配表!$A$6:$A$245,$A73) -> 0 | M73: =SUMIFS(仪器设备工时分配表!$K$6:$K$245,仪器设备工时分配表!$A$6:$A$245,$A73) -> 0
A74: 2026-07 | B74: =项目清单!$B$8 -> RD05 | C74: =IF($B74="","",IFERROR(VLOOKUP($B74,项目清单!$B$4:$C$13,2,0)&"","")) -> 新能源汽车电池包用导热缓冲复合材料开发 | D74: =SUMIFS(研发人员工时费用分配表!$R$6:$R$245,研发人员工时费用分配表!$A$6:$A$245,$A74) -> 0 | E74: =SUMIFS(仪器设备工时费用分配表!$N$6:$N$245,仪器设备工时费用分配表!$A$6:$A$245,$A74,仪器设备工时费用分配表!$D$6:$D$245,"设备") -> 0 | F74: =SUMIFS(无形资产费用分配表!$N$6:$N$125,无形资产费用分配表!$A$6:$A$125,$A74) -> 0 | G74: =SUMIFS(其他研发费用!$F$4:$F$153,其他研发费用!$A$4:$A$153,$A74,其他研发费用!$B$4:$B$153,$B74,其他研发费用!$D$4:$D$153,"直接投入费用") -> 0 | H74: =SUMIFS(其他研发费用!$F$4:$F$153,其他研发费用!$A$4:$A$153,$A74,其他研发费用!$B$4:$B$153,$B74,其他研发费用!$D$4:$D$153,"新产品设计费等") -> 0 | I74: =SUMIFS(其他研发费用!$F$4:$F$153,其他研发费用!$A$4:$A$153,$A74,其他研发费用!$B$4:$B$153,$B74,其他研发费用!$D$4:$D$153,"其他相关费用") -> 0 | J74: =SUMIFS(其他研发费用!$F$4:$F$153,其他研发费用!$A$4:$A$153,$A74,其他研发费用!$B$4:$B$153,$B74,其他研发费用!$D$4:$D$153,"委托外部研发费用") -> 0 | K74: =ROUND(SUM(D74:J74),2) -> 0 | L74: =SUMIFS(研发人员工时分配表!$L$6:$L$245,研发人员工时分配表!$A$6:$A$245,$A74) -> 0 | M74: =SUMIFS(仪器设备工时分配表!$L$6:$L$245,仪器设备工时分配表!$A$6:$A$245,$A74) -> 0
A75: 2026-07 | B75: =项目清单!$B$9 -> RD06 | C75: =IF($B75="","",IFERROR(VLOOKUP($B75,项目清单!$B$4:$C$13,2,0)&"","")) -> 3C电子用超薄黑色遮光泡棉制备技术 | D75: =SUMIFS(研发人员工时费用分配表!$S$6:$S$245,研发人员工时费用分配表!$A$6:$A$245,$A75) -> 0 | E75: =SUMIFS(仪器设备工时费用分配表!$O$6:$O$245,仪器设备工时费用分配表!$A$6:$A$245,$A75,仪器设备工时费用分配表!$D$6:$D$245,"设备") -> 0 | F75: =SUMIFS(无形资产费用分配表!$O$6:$O$125,无形资产费用分配表!$A$6:$A$125,$A75) -> 0 | G75: =SUMIFS(其他研发费用!$F$4:$F$153,其他研发费用!$A$4:$A$153,$A75,其他研发费用!$B$4:$B$153,$B75,其他研发费用!$D$4:$D$153,"直接投入费用") -> 0 | H75: =SUMIFS(其他研发费用!$F$4:$F$153,其他研发费用!$A$4:$A$153,$A75,其他研发费用!$B$4:$B$153,$B75,其他研发费用!$D$4:$D$153,"新产品设计费等") -> 0 | I75: =SUMIFS(其他研发费用!$F$4:$F$153,其他研发费用!$A$4:$A$153,$A75,其他研发费用!$B$4:$B$153,$B75,其他研发费用!$D$4:$D$153,"其他相关费用") -> 0 | J75: =SUMIFS(其他研发费用!$F$4:$F$153,其他研发费用!$A$4:$A$153,$A75,其他研发费用!$B$4:$B$153,$B75,其他研发费用!$D$4:$D$153,"委托外部研发费用") -> 0 | K75: =ROUND(SUM(D75:J75),2) -> 0 | L75: =SUMIFS(研发人员工时分配表!$M$6:$M$245,研发人员工时分配表!$A$6:$A$245,$A75) -> 0 | M75: =SUMIFS(仪器设备工时分配表!$M$6:$M$245,仪器设备工时分配表!$A$6:$A$245,$A75) -> 0
A76: 2026-07 | B76: =项目清单!$B$10 -> RD07 | C76: =IF($B76="","",IFERROR(VLOOKUP($B76,项目清单!$B$4:$C$13,2,0)&"","")) -> 环保型水性胶泡棉贴合技术开发 | D76: =SUMIFS(研发人员工时费用分配表!$T$6:$T$245,研发人员工时费用分配表!$A$6:$A$245,$A76) -> 0 | E76: =SUMIFS(仪器设备工时费用分配表!$P$6:$P$245,仪器设备工时费用分配表!$A$6:$A$245,$A76,仪器设备工时费用分配表!$D$6:$D$245,"设备") -> 0 | F76: =SUMIFS(无形资产费用分配表!$P$6:$P$125,无形资产费用分配表!$A$6:$A$125,$A76) -> 0 | G76: =SUMIFS(其他研发费用!$F$4:$F$153,其他研发费用!$A$4:$A$153,$A76,其他研发费用!$B$4:$B$153,$B76,其他研发费用!$D$4:$D$153,"直接投入费用") -> 0 | H76: =SUMIFS(其他研发费用!$F$4:$F$153,其他研发费用!$A$4:$A$153,$A76,其他研发费用!$B$4:$B$153,$B76,其他研发费用!$D$4:$D$153,"新产品设计费等") -> 0 | I76: =SUMIFS(其他研发费用!$F$4:$F$153,其他研发费用!$A$4:$A$153,$A76,其他研发费用!$B$4:$B$153,$B76,其他研发费用!$D$4:$D$153,"其他相关费用") -> 0 | J76: =SUMIFS(其他研发费用!$F$4:$F$153,其他研发费用!$A$4:$A$153,$A76,其他研发费用!$B$4:$B$153,$B76,其他研发费用!$D$4:$D$153,"委托外部研发费用") -> 0 | K76: =ROUND(SUM(D76:J76),2) -> 0 | L76: =SUMIFS(研发人员工时分配表!$N$6:$N$245,研发人员工时分配表!$A$6:$A$245,$A76) -> 0 | M76: =SUMIFS(仪器设备工时分配表!$N$6:$N$245,仪器设备工时分配表!$A$6:$A$245,$A76) -> 0
A77: 2026-07 | B77: =项目清单!$B$11 -> RD08 | C77: =IF($B77="","",IFERROR(VLOOKUP($B77,项目清单!$B$4:$C$13,2,0)&"","")) -> 泡棉模切自动化在线检测技术研究 | D77: =SUMIFS(研发人员工时费用分配表!$U$6:$U$245,研发人员工时费用分配表!$A$6:$A$245,$A77) -> 0 | E77: =SUMIFS(仪器设备工时费用分配表!$Q$6:$Q$245,仪器设备工时费用分配表!$A$6:$A$245,$A77,仪器设备工时费用分配表!$D$6:$D$245,"设备") -> 0 | F77: =SUMIFS(无形资产费用分配表!$Q$6:$Q$125,无形资产费用分配表!$A$6:$A$125,$A77) -> 0 | G77: =SUMIFS(其他研发费用!$F$4:$F$153,其他研发费用!$A$4:$A$153,$A77,其他研发费用!$B$4:$B$153,$B77,其他研发费用!$D$4:$D$153,"直接投入费用") -> 0 | H77: =SUMIFS(其他研发费用!$F$4:$F$153,其他研发费用!$A$4:$A$153,$A77,其他研发费用!$B$4:$B$153,$B77,其他研发费用!$D$4:$D$153,"新产品设计费等") -> 0 | I77: =SUMIFS(其他研发费用!$F$4:$F$153,其他研发费用!$A$4:$A$153,$A77,其他研发费用!$B$4:$B$153,$B77,其他研发费用!$D$4:$D$153,"其他相关费用") -> 0 | J77: =SUMIFS(其他研发费用!$F$4:$F$153,其他研发费用!$A$4:$A$153,$A77,其他研发费用!$B$4:$B$153,$B77,其他研发费用!$D$4:$D$153,"委托外部研发费用") -> 0 | K77: =ROUND(SUM(D77:J77),2) -> 0 | L77: =SUMIFS(研发人员工时分配表!$O$6:$O$245,研发人员工时分配表!$A$6:$A$245,$A77) -> 0 | M77: =SUMIFS(仪器设备工时分配表!$O$6:$O$245,仪器设备工时分配表!$A$6:$A$245,$A77) -> 0
A78: 2026-07 | B78: =项目清单!$B$12 -> RD09 | C78: =IF($B78="","",IFERROR(VLOOKUP($B78,项目清单!$B$4:$C$13,2,0)&"","")) | D78: =SUMIFS(研发人员工时费用分配表!$V$6:$V$245,研发人员工时费用分配表!$A$6:$A$245,$A78) -> 0 | E78: =SUMIFS(仪器设备工时费用分配表!$R$6:$R$245,仪器设备工时费用分配表!$A$6:$A$245,$A78,仪器设备工时费用分配表!$D$6:$D$245,"设备") -> 0 | F78: =SUMIFS(无形资产费用分配表!$R$6:$R$125,无形资产费用分配表!$A$6:$A$125,$A78) -> 0 | G78: =SUMIFS(其他研发费用!$F$4:$F$153,其他研发费用!$A$4:$A$153,$A78,其他研发费用!$B$4:$B$153,$B78,其他研发费用!$D$4:$D$153,"直接投入费用") -> 0 | H78: =SUMIFS(其他研发费用!$F$4:$F$153,其他研发费用!$A$4:$A$153,$A78,其他研发费用!$B$4:$B$153,$B78,其他研发费用!$D$4:$D$153,"新产品设计费等") -> 0 | I78: =SUMIFS(其他研发费用!$F$4:$F$153,其他研发费用!$A$4:$A$153,$A78,其他研发费用!$B$4:$B$153,$B78,其他研发费用!$D$4:$D$153,"其他相关费用") -> 0 | J78: =SUMIFS(其他研发费用!$F$4:$F$153,其他研发费用!$A$4:$A$153,$A78,其他研发费用!$B$4:$B$153,$B78,其他研发费用!$D$4:$D$153,"委托外部研发费用") -> 0 | K78: =ROUND(SUM(D78:J78),2) -> 0 | L78: =SUMIFS(研发人员工时分配表!$P$6:$P$245,研发人员工时分配表!$A$6:$A$245,$A78) -> 0 | M78: =SUMIFS(仪器设备工时分配表!$P$6:$P$245,仪器设备工时分配表!$A$6:$A$245,$A78) -> 0
A79: 2026-07 | B79: =项目清单!$B$13 -> RD10 | C79: =IF($B79="","",IFERROR(VLOOKUP($B79,项目清单!$B$4:$C$13,2,0)&"","")) | D79: =SUMIFS(研发人员工时费用分配表!$W$6:$W$245,研发人员工时费用分配表!$A$6:$A$245,$A79) -> 0 | E79: =SUMIFS(仪器设备工时费用分配表!$S$6:$S$245,仪器设备工时费用分配表!$A$6:$A$245,$A79,仪器设备工时费用分配表!$D$6:$D$245,"设备") -> 0 | F79: =SUMIFS(无形资产费用分配表!$S$6:$S$125,无形资产费用分配表!$A$6:$A$125,$A79) -> 0 | G79: =SUMIFS(其他研发费用!$F$4:$F$153,其他研发费用!$A$4:$A$153,$A79,其他研发费用!$B$4:$B$153,$B79,其他研发费用!$D$4:$D$153,"直接投入费用") -> 0 | H79: =SUMIFS(其他研发费用!$F$4:$F$153,其他研发费用!$A$4:$A$153,$A79,其他研发费用!$B$4:$B$153,$B79,其他研发费用!$D$4:$D$153,"新产品设计费等") -> 0 | I79: =SUMIFS(其他研发费用!$F$4:$F$153,其他研发费用!$A$4:$A$153,$A79,其他研发费用!$B$4:$B$153,$B79,其他研发费用!$D$4:$D$153,"其他相关费用") -> 0 | J79: =SUMIFS(其他研发费用!$F$4:$F$153,其他研发费用!$A$4:$A$153,$A79,其他研发费用!$B$4:$B$153,$B79,其他研发费用!$D$4:$D$153,"委托外部研发费用") -> 0 | K79: =ROUND(SUM(D79:J79),2) -> 0 | L79: =SUMIFS(研发人员工时分配表!$Q$6:$Q$245,研发人员工时分配表!$A$6:$A$245,$A79) -> 0 | M79: =SUMIFS(仪器设备工时分配表!$Q$6:$Q$245,仪器设备工时分配表!$A$6:$A$245,$A79) -> 0
A80: 2026-07 | C80: 本月合计 | D80: =ROUND(SUM(D70:D79),2) -> 0 | E80: =ROUND(SUM(E70:E79),2) -> 0 | F80: =ROUND(SUM(F70:F79),2) -> 0 | G80: =ROUND(SUM(G70:G79),2) -> 0 | H80: =ROUND(SUM(H70:H79),2) -> 0 | I80: =ROUND(SUM(I70:I79),2) -> 0 | J80: =ROUND(SUM(J70:J79),2) -> 0 | K80: =ROUND(SUM(K70:K79),2) -> 0 | ... M80: =ROUND(SUM(M70:M79),2) -> 0
A81: 2026-08 | B81: =项目清单!$B$4 -> RD01 | C81: =IF($B81="","",IFERROR(VLOOKUP($B81,项目清单!$B$4:$C$13,2,0)&"","")) -> 高回弹低压缩永久变形3C用聚氨酯泡棉开发 | D81: =SUMIFS(研发人员工时费用分配表!$N$6:$N$245,研发人员工时费用分配表!$A$6:$A$245,$A81) -> 0 | E81: =SUMIFS(仪器设备工时费用分配表!$J$6:$J$245,仪器设备工时费用分配表!$A$6:$A$245,$A81,仪器设备工时费用分配表!$D$6:$D$245,"设备") -> 0 | F81: =SUMIFS(无形资产费用分配表!$J$6:$J$125,无形资产费用分配表!$A$6:$A$125,$A81) -> 0 | G81: =SUMIFS(其他研发费用!$F$4:$F$153,其他研发费用!$A$4:$A$153,$A81,其他研发费用!$B$4:$B$153,$B81,其他研发费用!$D$4:$D$153,"直接投入费用") -> 0 | H81: =SUMIFS(其他研发费用!$F$4:$F$153,其他研发费用!$A$4:$A$153,$A81,其他研发费用!$B$4:$B$153,$B81,其他研发费用!$D$4:$D$153,"新产品设计费等") -> 0 | I81: =SUMIFS(其他研发费用!$F$4:$F$153,其他研发费用!$A$4:$A$153,$A81,其他研发费用!$B$4:$B$153,$B81,其他研发费用!$D$4:$D$153,"其他相关费用") -> 0 | J81: =SUMIFS(其他研发费用!$F$4:$F$153,其他研发费用!$A$4:$A$153,$A81,其他研发费用!$B$4:$B$153,$B81,其他研发费用!$D$4:$D$153,"委托外部研发费用") -> 0 | K81: =ROUND(SUM(D81:J81),2) -> 0 | L81: =SUMIFS(研发人员工时分配表!$H$6:$H$245,研发人员工时分配表!$A$6:$A$245,$A81) -> 0 | M81: =SUMIFS(仪器设备工时分配表!$H$6:$H$245,仪器设备工时分配表!$A$6:$A$245,$A81) -> 0
A82: 2026-08 | B82: =项目清单!$B$5 -> RD02 | C82: =IF($B82="","",IFERROR(VLOOKUP($B82,项目清单!$B$4:$C$13,2,0)&"","")) -> 动力电池模组用高阻燃缓冲泡棉研发 | D82: =SUMIFS(研发人员工时费用分配表!$O$6:$O$245,研发人员工时费用分配表!$A$6:$A$245,$A82) -> 0 | E82: =SUMIFS(仪器设备工时费用分配表!$K$6:$K$245,仪器设备工时费用分配表!$A$6:$A$245,$A82,仪器设备工时费用分配表!$D$6:$D$245,"设备") -> 0 | F82: =SUMIFS(无形资产费用分配表!$K$6:$K$125,无形资产费用分配表!$A$6:$A$125,$A82) -> 0 | G82: =SUMIFS(其他研发费用!$F$4:$F$153,其他研发费用!$A$4:$A$153,$A82,其他研发费用!$B$4:$B$153,$B82,其他研发费用!$D$4:$D$153,"直接投入费用") -> 0 | H82: =SUMIFS(其他研发费用!$F$4:$F$153,其他研发费用!$A$4:$A$153,$A82,其他研发费用!$B$4:$B$153,$B82,其他研发费用!$D$4:$D$153,"新产品设计费等") -> 0 | I82: =SUMIFS(其他研发费用!$F$4:$F$153,其他研发费用!$A$4:$A$153,$A82,其他研发费用!$B$4:$B$153,$B82,其他研发费用!$D$4:$D$153,"其他相关费用") -> 0 | J82: =SUMIFS(其他研发费用!$F$4:$F$153,其他研发费用!$A$4:$A$153,$A82,其他研发费用!$B$4:$B$153,$B82,其他研发费用!$D$4:$D$153,"委托外部研发费用") -> 0 | K82: =ROUND(SUM(D82:J82),2) -> 0 | L82: =SUMIFS(研发人员工时分配表!$I$6:$I$245,研发人员工时分配表!$A$6:$A$245,$A82) -> 0 | M82: =SUMIFS(仪器设备工时分配表!$I$6:$I$245,仪器设备工时分配表!$A$6:$A$245,$A82) -> 0
A83: 2026-08 | B83: =项目清单!$B$6 -> RD03 | C83: =IF($B83="","",IFERROR(VLOOKUP($B83,项目清单!$B$4:$C$13,2,0)&"","")) -> 泡棉与PET基材无溶剂贴合工艺开发 | D83: =SUMIFS(研发人员工时费用分配表!$P$6:$P$245,研发人员工时费用分配表!$A$6:$A$245,$A83) -> 0 | E83: =SUMIFS(仪器设备工时费用分配表!$L$6:$L$245,仪器设备工时费用分配表!$A$6:$A$245,$A83,仪器设备工时费用分配表!$D$6:$D$245,"设备") -> 0 | F83: =SUMIFS(无形资产费用分配表!$L$6:$L$125,无形资产费用分配表!$A$6:$A$125,$A83) -> 0 | G83: =SUMIFS(其他研发费用!$F$4:$F$153,其他研发费用!$A$4:$A$153,$A83,其他研发费用!$B$4:$B$153,$B83,其他研发费用!$D$4:$D$153,"直接投入费用") -> 0 | H83: =SUMIFS(其他研发费用!$F$4:$F$153,其他研发费用!$A$4:$A$153,$A83,其他研发费用!$B$4:$B$153,$B83,其他研发费用!$D$4:$D$153,"新产品设计费等") -> 0 | I83: =SUMIFS(其他研发费用!$F$4:$F$153,其他研发费用!$A$4:$A$153,$A83,其他研发费用!$B$4:$B$153,$B83,其他研发费用!$D$4:$D$153,"其他相关费用") -> 0 | J83: =SUMIFS(其他研发费用!$F$4:$F$153,其他研发费用!$A$4:$A$153,$A83,其他研发费用!$B$4:$B$153,$B83,其他研发费用!$D$4:$D$153,"委托外部研发费用") -> 0 | K83: =ROUND(SUM(D83:J83),2) -> 0 | L83: =SUMIFS(研发人员工时分配表!$J$6:$J$245,研发人员工时分配表!$A$6:$A$245,$A83) -> 0 | M83: =SUMIFS(仪器设备工时分配表!$J$6:$J$245,仪器设备工时分配表!$A$6:$A$245,$A83) -> 0
A84: 2026-08 | B84: =项目清单!$B$7 -> RD04 | C84: =IF($B84="","",IFERROR(VLOOKUP($B84,项目清单!$B$4:$C$13,2,0)&"","")) -> 超薄泡棉高精度分切及毛边控制技术研究 | D84: =SUMIFS(研发人员工时费用分配表!$Q$6:$Q$245,研发人员工时费用分配表!$A$6:$A$245,$A84) -> 0 | E84: =SUMIFS(仪器设备工时费用分配表!$M$6:$M$245,仪器设备工时费用分配表!$A$6:$A$245,$A84,仪器设备工时费用分配表!$D$6:$D$245,"设备") -> 0 | F84: =SUMIFS(无形资产费用分配表!$M$6:$M$125,无形资产费用分配表!$A$6:$A$125,$A84) -> 0 | G84: =SUMIFS(其他研发费用!$F$4:$F$153,其他研发费用!$A$4:$A$153,$A84,其他研发费用!$B$4:$B$153,$B84,其他研发费用!$D$4:$D$153,"直接投入费用") -> 0 | H84: =SUMIFS(其他研发费用!$F$4:$F$153,其他研发费用!$A$4:$A$153,$A84,其他研发费用!$B$4:$B$153,$B84,其他研发费用!$D$4:$D$153,"新产品设计费等") -> 0 | I84: =SUMIFS(其他研发费用!$F$4:$F$153,其他研发费用!$A$4:$A$153,$A84,其他研发费用!$B$4:$B$153,$B84,其他研发费用!$D$4:$D$153,"其他相关费用") -> 0 | J84: =SUMIFS(其他研发费用!$F$4:$F$153,其他研发费用!$A$4:$A$153,$A84,其他研发费用!$B$4:$B$153,$B84,其他研发费用!$D$4:$D$153,"委托外部研发费用") -> 0 | K84: =ROUND(SUM(D84:J84),2) -> 0 | L84: =SUMIFS(研发人员工时分配表!$K$6:$K$245,研发人员工时分配表!$A$6:$A$245,$A84) -> 0 | M84: =SUMIFS(仪器设备工时分配表!$K$6:$K$245,仪器设备工时分配表!$A$6:$A$245,$A84) -> 0
