Workbook

Sheet 使用说明
A1: 更多财务实操模板，可自行搜索抖音/视频号：老财务的实操笔记
A3: 【老财务实操自用｜初级版财务台账模板】
A4: 作者：老财务的实操笔记
A5: ——————————————————————————
A6: 适用对象：小微企业、个体工商户、小规模纳税人、商贸服务类等
A7: 版本说明
A8: 本套为**通用基础初级版**，满足税务管理、费用报销、收支登记、票据管理等
A9: 可根据行业属性、业务规模、升级定制版。
A11: 模板清单，持续更新
A12: 1、应收账款风险预警表
A13: 2、日常经营情况汇总表
A14: 3、进项台帐自动查重表
... A47: 老财务自用模板｜禁止外传、倒卖、商用

Sheet 基础资料
A1: 账户 | C1: 支出业务类别 | E1: 客户 | F1: 客户期初余额 | G1: 供应商 | H1: 供应商期初余额
A2: 泰溢农行 | C2: 供应商 | E2: 成都蓉港商业发展有限公司 | G2: 成都鑫鑫向喜商贸有限公司
A3: 泰溢招行 | E3: 成都市双流区公共资源交易服务中心 | G3: 成都统一企业食品有限公司
A4: 趣点购浦发 | C4: 办公费 | E4: 陈金刚 | G4: 陈金刚
A5: 雅安趣点购农行 | C5: 水费 | E5: 成都空港公园城市绿道建设投资有限公司 | G5: 成都勤献食品有限公司
C6: 电费 | E6: 客户5 | G6: 武汉小麦便利科技有限公司
C7: 伙食费 | E7: 客户6 | G7: 供应商6
C8: 工资 | E8: 客户7 | G8: 供应商7
C9: 租赁费 | E9: 客户8 | G9: 供应商8
C10: 差旅费 | E10: 客户9 | G10: 供应商9
C11: 业务招待费 | E11: 客户10 | G11: 供应商10
C12: 车辆费用 | E12: 客户11 | G12: 供应商11
C13: 银行手续费 | E13: 客户12 | G13: 供应商12
C14: 税费 | E14: 客户13 | G14: 供应商13
C15: 设备款
C16: 投标保证金
C17: 合同履约保证金
C18: 借款
C19: 场地租金

Sheet 数据录入
A1: 多帐户收支登记表
F2: 收入总额 | G2: 支出总额 | H2: 账户余额
F3: =SUBTOTAL(109,$F$4:$F$9999) -> 0 | G3: =SUBTOTAL(109,$G$4:$G$9999) -> 733050 | H3: =SUBTOTAL(109,$H$5:$H$18)+F3-G3 -> -733050
A4: 序号 | B4: 日期 | C4: 公司账户 | D4: 支出业务类别 | E4: 摘要内容 | F4: 收入 | G4: 支出 | H4: 账户余额 | I4: 客户 | J4: 供应商 | K4: 月份
A5: =IF(B5="","",COUNTA($B$5:B5)) -> 1 | B5: 46174 | C5: 现金 | E5: 期初余额 | H5: 0 | K5: =IF($B5="","",--TEXT($B5,"yyyymm")) -> 202606
A6: =IF(B6="","",COUNTA($B$5:B6)) -> 2 | B6: 46174 | C6: 微信 | E6: 期初余额 | H6: 0 | K6: =IF($B6="","",--TEXT($B6,"yyyymm")) -> 202606
A7: =IF(B7="","",COUNTA($B$5:B7)) -> 3 | B7: 46174 | C7: 趣点购浦发 | E7: 期初余额 | H7: 0 | K7: =IF($B7="","",--TEXT($B7,"yyyymm")) -> 202606
A8: =IF(B8="","",COUNTA($B$5:B8)) -> 4 | B8: 46174 | C8: 民生 | E8: 期初余额 | H8: 0 | K8: =IF($B8="","",--TEXT($B8,"yyyymm")) -> 202606
A9: =IF(B9="","",COUNTA($B$5:B9)) -> 5 | B9: 46174 | C9: 建行 | E9: 期初余额 | H9: 0 | K9: =IF($B9="","",--TEXT($B9,"yyyymm")) -> 202606
A10: =IF(B10="","",COUNTA($B$5:B10)) -> 6 | B10: 46174 | C10: 农行 | E10: 期初余额 | H10: 0 | K10: =IF($B10="","",--TEXT($B10,"yyyymm")) -> 202606
A11: =IF(B11="","",COUNTA($B$5:B11)) -> 7 | B11: 46174 | C11: 中行 | E11: 期初余额 | H11: 0 | K11: =IF($B11="","",--TEXT($B11,"yyyymm")) -> 202606
A12: =IF(B12="","",COUNTA($B$5:B12)) -> 8 | B12: 46174 | C12: 支付宝 | E12: 期初余额 | H12: 0 | K12: =IF($B12="","",--TEXT($B12,"yyyymm")) -> 202606
A13: =IF(B13="","",COUNTA($B$5:B13)) -> 9 | B13: 46174 | C13: 农商行 | E13: 期初余额 | H13: 0 | K13: =IF($B13="","",--TEXT($B13,"yyyymm")) -> 202606
A14: =IF(B14="","",COUNTA($B$5:B14)) -> 10 | B14: 46174 | C14: 备用 | E14: 期初余额 | H14: 0 | K14: =IF($B14="","",--TEXT($B14,"yyyymm")) -> 202606
A15: =IF(B15="","",COUNTA($B$5:B15)) -> 11 | B15: 46174 | C15: 备用1 | E15: 期初余额 | H15: 0 | K15: =IF($B15="","",--TEXT($B15,"yyyymm")) -> 202606
A16: =IF(B16="","",COUNTA($B$5:B16)) -> 12 | B16: 46174 | C16: 备用2 | E16: 期初余额 | H16: 0 | K16: =IF($B16="","",--TEXT($B16,"yyyymm")) -> 202606
... A18: =IF(B18="","",COUNTA($B$5:B18)) -> 14 | B18: 46174 | C18: 备用4 | E18: 期初余额 | H18: 0 | K18: =IF($B18="","",--TEXT($B18,"yyyymm")) -> 202606
A19: =IF(B19="","",COUNTA($B$5:B19)) -> 15 | B19: 46127 | C19: 趣点购浦发 | E19: 银行变更资料 | F19: 200 | H19: =IFERROR(VLOOKUP($C19,$C$5:$H$18,6,0)+SUMIF($C$19:$C19,$C19,$F$19:$F19)-SUMIF($C$19:$C19,$C19,$G$19:$G19),"") -> 200 | K19: =IF($B19="","",--TEXT($B19,"yyyymm")) -> 202604
A20: =IF(B20="","",COUNTA($B$5:B20)) -> 16 | B20: 46127 | C20: 趣点购浦发 | D20: 银行手续费 | E20: 公司手机银行服务年费 | G20: 43.12 | H20: =IFERROR(VLOOKUP($C20,$C$5:$H$18,6,0)+SUMIF($C$19:$C20,$C20,$F$19:$F20)-SUMIF($C$19:$C20,$C20,$G$19:$G20),"") -> 156.88 | K20: =IF($B20="","",--TEXT($B20,"yyyymm")) -> 202604
A21: =IF(B21="","",COUNTA($B$5:B21)) -> 17 | B21: 46127 | C21: 趣点购浦发 | D21: 银行手续费 | E21: 帐户信息变更 | G21: 16 | H21: =IFERROR(VLOOKUP($C21,$C$5:$H$18,6,0)+SUMIF($C$19:$C21,$C21,$F$19:$F21)-SUMIF($C$19:$C21,$C21,$G$19:$G21),"") -> 140.88 | K21: =IF($B21="","",--TEXT($B21,"yyyymm")) -> 202604
A22: =IF(B22="","",COUNTA($B$5:B22)) -> 18 | B22: 46127 | C22: 趣点购浦发 | D22: 银行手续费 | E22: 印鉴变更 | G22: 10 | H22: =IFERROR(VLOOKUP($C22,$C$5:$H$18,6,0)+SUMIF($C$19:$C22,$C22,$F$19:$F22)-SUMIF($C$19:$C22,$C22,$G$19:$G22),"") -> 130.88 | K22: =IF($B22="","",--TEXT($B22,"yyyymm")) -> 202604
A23: =IF(B23="","",COUNTA($B$5:B23)) -> 19 | B23: 46128 | C23: 趣点购浦发 | D23: 银行手续费 | E23: 公司网银服务年费,公司手机银行服务年费,公司网银数字证书(2张) | G23: 130.88 | H23: =IFERROR(VLOOKUP($C23,$C$5:$H$18,6,0)+SUMIF($C$19:$C23,$C23,$F$19:$F23)-SUMIF($C$19:$C23,$C23,$G$19:$G23),"") -> 0 | K23: =IF($B23="","",--TEXT($B23,"yyyymm")) -> 202604
A24: =IF(B24="","",COUNTA($B$5:B24)) -> 20 | B24: 46129 | C24: 趣点购浦发 | E24: 入股金 | F24: 10000 | H24: =IFERROR(VLOOKUP($C24,$C$5:$H$18,6,0)+SUMIF($C$19:$C24,$C24,$F$19:$F24)-SUMIF($C$19:$C24,$C24,$G$19:$G24),"") -> 10000 | K24: =IF($B24="","",--TEXT($B24,"yyyymm")) -> 202604
A25: =IF(B25="","",COUNTA($B$5:B25)) -> 21 | B25: 46129 | C25: 趣点购浦发 | D25: 银行手续费 | E25: 公司网银数字证书(2张) | G25: 19.12 | H25: =IFERROR(VLOOKUP($C25,$C$5:$H$18,6,0)+SUMIF($C$19:$C25,$C25,$F$19:$F25)-SUMIF($C$19:$C25,$C25,$G$19:$G25),"") -> 9980.88 | K25: =IF($B25="","",--TEXT($B25,"yyyymm")) -> 202604
A26: =IF(B26="","",COUNTA($B$5:B26)) -> 22 | B26: 46129 | C26: 趣点购浦发 | D26: 银行手续费 | E26: 单位结算卡年费金卡 | G26: 100 | H26: =IFERROR(VLOOKUP($C26,$C$5:$H$18,6,0)+SUMIF($C$19:$C26,$C26,$F$19:$F26)-SUMIF($C$19:$C26,$C26,$G$19:$G26),"") -> 9880.88 | K26: =IF($B26="","",--TEXT($B26,"yyyymm")) -> 202604
A27: =IF(B27="","",COUNTA($B$5:B27)) -> 23 | B27: 46136 | C27: 趣点购浦发 | D27: 办公费 | E27: 四川CA电子签名认证证书申请验证 | G27: 0.05 | H27: =IFERROR(VLOOKUP($C27,$C$5:$H$18,6,0)+SUMIF($C$19:$C27,$C27,$F$19:$F27)-SUMIF($C$19:$C27,$C27,$G$19:$G27),"") -> 9880.83 | K27: =IF($B27="","",--TEXT($B27,"yyyymm")) -> 202604
A28: =IF(B28="","",COUNTA($B$5:B28)) -> 24 | B28: 46136 | C28: 趣点购浦发 | D28: 银行手续费 | E28: 网银互联汇出手续费 | G28: 4.5 | H28: =IFERROR(VLOOKUP($C28,$C$5:$H$18,6,0)+SUMIF($C$19:$C28,$C28,$F$19:$F28)-SUMIF($C$19:$C28,$C28,$G$19:$G28),"") -> 9876.33 | K28: =IF($B28="","",--TEXT($B28,"yyyymm")) -> 202604
A29: =IF(B29="","",COUNTA($B$5:B29)) -> 25 | B29: 46140 | C29: 趣点购浦发 | E29: 四川CA电子签名认证证书申请验证退款 | F29: 0.05 | H29: =IFERROR(VLOOKUP($C29,$C$5:$H$18,6,0)+SUMIF($C$19:$C29,$C29,$F$19:$F29)-SUMIF($C$19:$C29,$C29,$G$19:$G29),"") -> 9876.38 | K29: =IF($B29="","",--TEXT($B29,"yyyymm")) -> 202604
A30: =IF(B30="","",COUNTA($B$5:B30)) -> 26 | B30: 46142 | C30: 趣点购浦发 | E30: 入股金 | F30: 70000 | H30: =IFERROR(VLOOKUP($C30,$C$5:$H$18,6,0)+SUMIF($C$19:$C30,$C30,$F$19:$F30)-SUMIF($C$19:$C30,$C30,$G$19:$G30),"") -> 79876.38 | K30: =IF($B30="","",--TEXT($B30,"yyyymm")) -> 202604
A31: =IF(B31="","",COUNTA($B$5:B31)) -> 27 | B31: 46142 | C31: 趣点购浦发 | E31: 入股金 | F31: 50000 | H31: =IFERROR(VLOOKUP($C31,$C$5:$H$18,6,0)+SUMIF($C$19:$C31,$C31,$F$19:$F31)-SUMIF($C$19:$C31,$C31,$G$19:$G31),"") -> 129876.38 | K31: =IF($B31="","",--TEXT($B31,"yyyymm")) -> 202604
A32: =IF(B32="","",COUNTA($B$5:B32)) -> 28 | B32: 46142 | C32: 趣点购浦发 | E32: 雅安趣点购农行互转趣点购浦发 | F32: 20500 | H32: =IFERROR(VLOOKUP($C32,$C$5:$H$18,6,0)+SUMIF($C$19:$C32,$C32,$F$19:$F32)-SUMIF($C$19:$C32,$C32,$G$19:$G32),"") -> 150376.38 | K32: =IF($B32="","",--TEXT($B32,"yyyymm")) -> 202604
A33: =IF(B33="","",COUNTA($B$5:B33)) -> 29 | B33: 46142 | C33: 趣点购浦发 | D33: 往来款 | E33: 脉动货款 | G33: 150000 | H33: =IFERROR(VLOOKUP($C33,$C$5:$H$18,6,0)+SUMIF($C$19:$C33,$C33,$F$19:$F33)-SUMIF($C$19:$C33,$C33,$G$19:$G33),"") -> 376.38 | J33: 成都鑫鑫向喜商贸有限公司 | K33: =IF($B33="","",--TEXT($B33,"yyyymm")) -> 202604
A34: =IF(B34="","",COUNTA($B$5:B34)) -> 30 | B34: 46142 | C34: 趣点购浦发 | D34: 银行手续费 | E34: 网银互联汇出手续费 | G34: 15 | H34: =IFERROR(VLOOKUP($C34,$C$5:$H$18,6,0)+SUMIF($C$19:$C34,$C34,$F$19:$F34)-SUMIF($C$19:$C34,$C34,$G$19:$G34),"") -> 361.38 | K34: =IF($B34="","",--TEXT($B34,"yyyymm")) -> 202604
A35: =IF(B35="","",COUNTA($B$5:B35)) -> 31 | B35: 46146 | C35: 趣点购浦发 | E35: 入股金 | F35: 90000 | H35: =IFERROR(VLOOKUP($C35,$C$5:$H$18,6,0)+SUMIF($C$19:$C35,$C35,$F$19:$F35)-SUMIF($C$19:$C35,$C35,$G$19:$G35),"") -> 90361.38 | K35: =IF($B35="","",--TEXT($B35,"yyyymm")) -> 202605
A36: =IF(B36="","",COUNTA($B$5:B36)) -> 32 | B36: 46146 | C36: 趣点购浦发 | D36: 往来款 | E36: 脉动货款 | G36: 82400 | H36: =IFERROR(VLOOKUP($C36,$C$5:$H$18,6,0)+SUMIF($C$19:$C36,$C36,$F$19:$F36)-SUMIF($C$19:$C36,$C36,$G$19:$G36),"") -> 7961.38 | J36: 成都鑫鑫向喜商贸有限公司 | K36: =IF($B36="","",--TEXT($B36,"yyyymm")) -> 202605
A37: =IF(B37="","",COUNTA($B$5:B37)) -> 33 | B37: 46146 | C37: 趣点购浦发 | D37: 银行手续费 | E37: 网银互联汇出手续费 | G37: 9 | H37: =IFERROR(VLOOKUP($C37,$C$5:$H$18,6,0)+SUMIF($C$19:$C37,$C37,$F$19:$F37)-SUMIF($C$19:$C37,$C37,$G$19:$G37),"") -> 7952.38 | K37: =IF($B37="","",--TEXT($B37,"yyyymm")) -> 202605
A38: =IF(B38="","",COUNTA($B$5:B38)) -> 34 | B38: 46151 | C38: 趣点购浦发 | D38: 税费 | E38: 缴税 | G38: 450 | H38: =IFERROR(VLOOKUP($C38,$C$5:$H$18,6,0)+SUMIF($C$19:$C38,$C38,$F$19:$F38)-SUMIF($C$19:$C38,$C38,$G$19:$G38),"") -> 7502.38 | K38: =IF($B38="","",--TEXT($B38,"yyyymm")) -> 202605
A39: =IF(B39="","",COUNTA($B$5:B39)) -> 35 | B39: 46154 | C39: 趣点购浦发 | D39: 工资 | E39: 陈樨 | G39: 4500 | H39: =IFERROR(VLOOKUP($C39,$C$5:$H$18,6,0)+SUMIF($C$19:$C39,$C39,$F$19:$F39)-SUMIF($C$19:$C39,$C39,$G$19:$G39),"") -> 3002.38 | K39: =IF($B39="","",--TEXT($B39,"yyyymm")) -> 202605
A40: =IF(B40="","",COUNTA($B$5:B40)) -> 36 | B40: 46154 | C40: 趣点购浦发 | D40: 银行手续费 | E40: 网银互联汇出手续费 | G40: 4.5 | H40: =IFERROR(VLOOKUP($C40,$C$5:$H$18,6,0)+SUMIF($C$19:$C40,$C40,$F$19:$F40)-SUMIF($C$19:$C40,$C40,$G$19:$G40),"") -> 2997.88 | K40: =IF($B40="","",--TEXT($B40,"yyyymm")) -> 202605
A41: =IF(B41="","",COUNTA($B$5:B41)) -> 37 | B41: 46158 | C41: 趣点购浦发 | E41: 入股金 | F41: 30000 | H41: =IFERROR(VLOOKUP($C41,$C$5:$H$18,6,0)+SUMIF($C$19:$C41,$C41,$F$19:$F41)-SUMIF($C$19:$C41,$C41,$G$19:$G41),"") -> 32997.88 | K41: =IF($B41="","",--TEXT($B41,"yyyymm")) -> 202605
A42: =IF(B42="","",COUNTA($B$5:B42)) -> 38 | B42: 46162 | C42: 趣点购浦发 | E42: 入股金 | F42: 20000 | H42: =IFERROR(VLOOKUP($C42,$C$5:$H$18,6,0)+SUMIF($C$19:$C42,$C42,$F$19:$F42)-SUMIF($C$19:$C42,$C42,$G$19:$G42),"") -> 52997.88 | K42: =IF($B42="","",--TEXT($B42,"yyyymm")) -> 202605
A43: =IF(B43="","",COUNTA($B$5:B43)) -> 39 | B43: 46162 | C43: 趣点购浦发 | D43: 设备款 | E43: 购买售货机合同款 | G43: 44400 | H43: =IFERROR(VLOOKUP($C43,$C$5:$H$18,6,0)+SUMIF($C$19:$C43,$C43,$F$19:$F43)-SUMIF($C$19:$C43,$C43,$G$19:$G43),"") -> 8597.88 | K43: =IF($B43="","",--TEXT($B43,"yyyymm")) -> 202605
A44: =IF(B44="","",COUNTA($B$5:B44)) -> 40 | B44: 46162 | C44: 趣点购浦发 | D44: 银行手续费 | E44: 网银互联汇出手续费 | G44: 9 | H44: =IFERROR(VLOOKUP($C44,$C$5:$H$18,6,0)+SUMIF($C$19:$C44,$C44,$F$19:$F44)-SUMIF($C$19:$C44,$C44,$G$19:$G44),"") -> 8588.88 | K44: =IF($B44="","",--TEXT($B44,"yyyymm")) -> 202605
A45: =IF(B45="","",COUNTA($B$5:B45)) -> 41 | B45: 46163 | C45: 趣点购浦发 | E45: 超市营业款 | F45: 9088 | H45: =IFERROR(VLOOKUP($C45,$C$5:$H$18,6,0)+SUMIF($C$19:$C45,$C45,$F$19:$F45)-SUMIF($C$19:$C45,$C45,$G$19:$G45),"") -> 17676.88 | K45: =IF($B45="","",--TEXT($B45,"yyyymm")) -> 202605
A46: =IF(B46="","",COUNTA($B$5:B46)) -> 42 | B46: 46164 | C46: 趣点购浦发 | E46: 超市营业款 | F46: 9383.96 | H46: =IFERROR(VLOOKUP($C46,$C$5:$H$18,6,0)+SUMIF($C$19:$C46,$C46,$F$19:$F46)-SUMIF($C$19:$C46,$C46,$G$19:$G46),"") -> 27060.84 | K46: =IF($B46="","",--TEXT($B46,"yyyymm")) -> 202605
A47: =IF(B47="","",COUNTA($B$5:B47)) -> 43 | B47: 46164 | C47: 趣点购浦发 | E47: 入股金 | F47: 180000 | H47: =IFERROR(VLOOKUP($C47,$C$5:$H$18,6,0)+SUMIF($C$19:$C47,$C47,$F$19:$F47)-SUMIF($C$19:$C47,$C47,$G$19:$G47),"") -> 207060.84 | K47: =IF($B47="","",--TEXT($B47,"yyyymm")) -> 202605
A48: =IF(B48="","",COUNTA($B$5:B48)) -> 44 | B48: 46164 | C48: 趣点购浦发 | D48: 投标保证金 | E48: 2026年轨道交通自助零售机场地经营项目1标段 | G48: 50000 | H48: =IFERROR(VLOOKUP($C48,$C$5:$H$18,6,0)+SUMIF($C$19:$C48,$C48,$F$19:$F48)-SUMIF($C$19:$C48,$C48,$G$19:$G48),"") -> 157060.84 | I48: 成都蓉港商业发展有限公司 | K48: =IF($B48="","",--TEXT($B48,"yyyymm")) -> 202605
A49: =IF(B49="","",COUNTA($B$5:B49)) -> 45 | B49: 46164 | C49: 趣点购浦发 | D49: 银行手续费 | E49: 网银互联汇出手续费 | G49: 0.9 | H49: =IFERROR(VLOOKUP($C49,$C$5:$H$18,6,0)+SUMIF($C$19:$C49,$C49,$F$19:$F49)-SUMIF($C$19:$C49,$C49,$G$19:$G49),"") -> 157059.94 | K49: =IF($B49="","",--TEXT($B49,"yyyymm")) -> 202605
A50: =IF(B50="","",COUNTA($B$5:B50)) -> 46 | B50: 46164 | C50: 趣点购浦发 | D50: 投标保证金 | E50: 2026年轨道交通自助零售机场地经营项目2标段 | G50: 50000 | H50: =IFERROR(VLOOKUP($C50,$C$5:$H$18,6,0)+SUMIF($C$19:$C50,$C50,$F$19:$F50)-SUMIF($C$19:$C50,$C50,$G$19:$G50),"") -> 107059.94 | I50: 成都蓉港商业发展有限公司 | K50: =IF($B50="","",--TEXT($B50,"yyyymm")) -> 202605
A51: =IF(B51="","",COUNTA($B$5:B51)) -> 47 | B51: 46164 | C51: 趣点购浦发 | D51: 银行手续费 | E51: 网银互联汇出手续费 | G51: 0.9 | H51: =IFERROR(VLOOKUP($C51,$C$5:$H$18,6,0)+SUMIF($C$19:$C51,$C51,$F$19:$F51)-SUMIF($C$19:$C51,$C51,$G$19:$G51),"") -> 107059.04 | K51: =IF($B51="","",--TEXT($B51,"yyyymm")) -> 202605
A52: =IF(B52="","",COUNTA($B$5:B52)) -> 48 | B52: 46164 | C52: 趣点购浦发 | D52: 投标保证金 | E52: 2026年轨道交通自助零售机场地经营项目3标段 | G52: 50000 | H52: =IFERROR(VLOOKUP($C52,$C$5:$H$18,6,0)+SUMIF($C$19:$C52,$C52,$F$19:$F52)-SUMIF($C$19:$C52,$C52,$G$19:$G52),"") -> 57059.04 | I52: 成都蓉港商业发展有限公司 | K52: =IF($B52="","",--TEXT($B52,"yyyymm")) -> 202605
A53: =IF(B53="","",COUNTA($B$5:B53)) -> 49 | B53: 46164 | C53: 趣点购浦发 | D53: 银行手续费 | E53: 网银互联汇出手续费 | G53: 0.9 | H53: =IFERROR(VLOOKUP($C53,$C$5:$H$18,6,0)+SUMIF($C$19:$C53,$C53,$F$19:$F53)-SUMIF($C$19:$C53,$C53,$G$19:$G53),"") -> 57058.14 | K53: =IF($B53="","",--TEXT($B53,"yyyymm")) -> 202605
A54: =IF(B54="","",COUNTA($B$5:B54)) -> 50 | B54: 46165 | C54: 趣点购浦发 | E54: 超市营业款 | F54: 8368.85 | H54: =IFERROR(VLOOKUP($C54,$C$5:$H$18,6,0)+SUMIF($C$19:$C54,$C54,$F$19:$F54)-SUMIF($C$19:$C54,$C54,$G$19:$G54),"") -> 65426.99 | K54: =IF($B54="","",--TEXT($B54,"yyyymm")) -> 202605
A55: =IF(B55="","",COUNTA($B$5:B55)) -> 51 | B55: 46165 | C55: 趣点购浦发 | D55: 投标保证金 | E55: 2026年轨道交通自助零售机场地经营项目4标段 | G55: 50000 | H55: =IFERROR(VLOOKUP($C55,$C$5:$H$18,6,0)+SUMIF($C$19:$C55,$C55,$F$19:$F55)-SUMIF($C$19:$C55,$C55,$G$19:$G55),"") -> 15426.99 | K55: =IF($B55="","",--TEXT($B55,"yyyymm")) -> 202605
A56: =IF(B56="","",COUNTA($B$5:B56)) -> 52 | B56: 46165 | C56: 趣点购浦发 | D56: 银行手续费 | E56: 网银互联汇出手续费 | G56: 0.9 | H56: =IFERROR(VLOOKUP($C56,$C$5:$H$18,6,0)+SUMIF($C$19:$C56,$C56,$F$19:$F56)-SUMIF($C$19:$C56,$C56,$G$19:$G56),"") -> 15426.09 | K56: =IF($B56="","",--TEXT($B56,"yyyymm")) -> 202605
A57: =IF(B57="","",COUNTA($B$5:B57)) -> 53 | B57: 46166 | C57: 趣点购浦发 | E57: 超市营业款 | F57: 6442.95 | H57: =IFERROR(VLOOKUP($C57,$C$5:$H$18,6,0)+SUMIF($C$19:$C57,$C57,$F$19:$F57)-SUMIF($C$19:$C57,$C57,$G$19:$G57),"") -> 21869.04 | K57: =IF($B57="","",--TEXT($B57,"yyyymm")) -> 202605
A58: =IF(B58="","",COUNTA($B$5:B58)) -> 54 | B58: 46167 | C58: 趣点购浦发 | E58: 超市营业款 | F58: 6494.62 | H58: =IFERROR(VLOOKUP($C58,$C$5:$H$18,6,0)+SUMIF($C$19:$C58,$C58,$F$19:$F58)-SUMIF($C$19:$C58,$C58,$G$19:$G58),"") -> 28363.66 | K58: =IF($B58="","",--TEXT($B58,"yyyymm")) -> 202605
A59: =IF(B59="","",COUNTA($B$5:B59)) -> 55 | B59: 46167 | C59: 趣点购浦发 | D59: 税费 | E59: 缴税 | G59: 16.25 | H59: =IFERROR(VLOOKUP($C59,$C$5:$H$18,6,0)+SUMIF($C$19:$C59,$C59,$F$19:$F59)-SUMIF($C$19:$C59,$C59,$G$19:$G59),"") -> 28347.41 | K59: =IF($B59="","",--TEXT($B59,"yyyymm")) -> 202605
A60: =IF(B60="","",COUNTA($B$5:B60)) -> 56 | B60: 46168 | C60: 趣点购浦发 | E60: 超市营业款 | F60: 9286.7 | H60: =IFERROR(VLOOKUP($C60,$C$5:$H$18,6,0)+SUMIF($C$19:$C60,$C60,$F$19:$F60)-SUMIF($C$19:$C60,$C60,$G$19:$G60),"") -> 37634.11 | K60: =IF($B60="","",--TEXT($B60,"yyyymm")) -> 202605
A61: =IF(B61="","",COUNTA($B$5:B61)) -> 57 | B61: 46168 | C61: 趣点购浦发 | D61: 车辆费用 | E61: 川A2L3N6车辆保费 | G61: 2276 | H61: =IFERROR(VLOOKUP($C61,$C$5:$H$18,6,0)+SUMIF($C$19:$C61,$C61,$F$19:$F61)-SUMIF($C$19:$C61,$C61,$G$19:$G61),"") -> 35358.11 | K61: =IF($B61="","",--TEXT($B61,"yyyymm")) -> 202605
A62: =IF(B62="","",COUNTA($B$5:B62)) -> 58 | B62: 46168 | C62: 趣点购浦发 | D62: 银行手续费 | E62: 网银互联汇出手续费 | G62: 4.5 | H62: =IFERROR(VLOOKUP($C62,$C$5:$H$18,6,0)+SUMIF($C$19:$C62,$C62,$F$19:$F62)-SUMIF($C$19:$C62,$C62,$G$19:$G62),"") -> 35353.61 | K62: =IF($B62="","",--TEXT($B62,"yyyymm")) -> 202605
A63: =IF(B63="","",COUNTA($B$5:B63)) -> 59 | B63: 46168 | C63: 趣点购浦发 | D63: 税费 | E63: 缴税 | G63: 1605.56 | H63: =IFERROR(VLOOKUP($C63,$C$5:$H$18,6,0)+SUMIF($C$19:$C63,$C63,$F$19:$F63)-SUMIF($C$19:$C63,$C63,$G$19:$G63),"") -> 33748.05 | K63: =IF($B63="","",--TEXT($B63,"yyyymm")) -> 202605
A64: =IF(B64="","",COUNTA($B$5:B64)) -> 60 | B64: 46169 | C64: 趣点购浦发 | E64: 超市营业款 | F64: 9388.54 | H64: =IFERROR(VLOOKUP($C64,$C$5:$H$18,6,0)+SUMIF($C$19:$C64,$C64,$F$19:$F64)-SUMIF($C$19:$C64,$C64,$G$19:$G64),"") -> 43136.59 | K64: =IF($B64="","",--TEXT($B64,"yyyymm")) -> 202605
A65: =IF(B65="","",COUNTA($B$5:B65)) -> 61 | B65: 46170 | C65: 趣点购浦发 | E65: 超市营业款 | F65: 8734.59 | H65: =IFERROR(VLOOKUP($C65,$C$5:$H$18,6,0)+SUMIF($C$19:$C65,$C65,$F$19:$F65)-SUMIF($C$19:$C65,$C65,$G$19:$G65),"") -> 51871.18 | K65: =IF($B65="","",--TEXT($B65,"yyyymm")) -> 202605
A66: =IF(B66="","",COUNTA($B$5:B66)) -> 62 | B66: 46170 | C66: 趣点购浦发 | D66: 税费 | E66: 缴税 | G66: 3928.18 | H66: =IFERROR(VLOOKUP($C66,$C$5:$H$18,6,0)+SUMIF($C$19:$C66,$C66,$F$19:$F66)-SUMIF($C$19:$C66,$C66,$G$19:$G66),"") -> 47943 | K66: =IF($B66="","",--TEXT($B66,"yyyymm")) -> 202605
A67: =IF(B67="","",COUNTA($B$5:B67)) -> 63 | B67: 46171 | C67: 趣点购浦发 | E67: 超市营业款 | F67: 7792.68 | H67: =IFERROR(VLOOKUP($C67,$C$5:$H$18,6,0)+SUMIF($C$19:$C67,$C67,$F$19:$F67)-SUMIF($C$19:$C67,$C67,$G$19:$G67),"") -> 55735.68 | K67: =IF($B67="","",--TEXT($B67,"yyyymm")) -> 202605
A68: =IF(B68="","",COUNTA($B$5:B68)) -> 64 | B68: 46171 | C68: 趣点购浦发 | E68: 微信支付认证3457 | F68: 0.01 | H68: =IFERROR(VLOOKUP($C68,$C$5:$H$18,6,0)+SUMIF($C$19:$C68,$C68,$F$19:$F68)-SUMIF($C$19:$C68,$C68,$G$19:$G68),"") -> 55735.69 | K68: =IF($B68="","",--TEXT($B68,"yyyymm")) -> 202605
A69: =IF(B69="","",COUNTA($B$5:B69)) -> 65 | B69: 46172 | C69: 趣点购浦发 | E69: 超市营业款 | F69: 7862.46 | H69: =IFERROR(VLOOKUP($C69,$C$5:$H$18,6,0)+SUMIF($C$19:$C69,$C69,$F$19:$F69)-SUMIF($C$19:$C69,$C69,$G$19:$G69),"") -> 63598.15 | K69: =IF($B69="","",--TEXT($B69,"yyyymm")) -> 202605
A70: =IF(B70="","",COUNTA($B$5:B70)) -> 66 | B70: 46173 | C70: 趣点购浦发 | E70: 超市营业款 | F70: 5853.65 | H70: =IFERROR(VLOOKUP($C70,$C$5:$H$18,6,0)+SUMIF($C$19:$C70,$C70,$F$19:$F70)-SUMIF($C$19:$C70,$C70,$G$19:$G70),"") -> 69451.8 | K70: =IF($B70="","",--TEXT($B70,"yyyymm")) -> 202605
A71: =IF(B71="","",COUNTA($B$5:B71)) -> 67 | B71: 46174 | C71: 趣点购浦发 | E71: 超市营业款 | F71: 6293.37 | H71: =IFERROR(VLOOKUP($C71,$C$5:$H$18,6,0)+SUMIF($C$19:$C71,$C71,$F$19:$F71)-SUMIF($C$19:$C71,$C71,$G$19:$G71),"") -> 75745.17 | K71: =IF($B71="","",--TEXT($B71,"yyyymm")) -> 202606
A72: =IF(B72="","",COUNTA($B$5:B72)) -> 68 | B72: 46175 | C72: 趣点购浦发 | E72: 超市营业款 | F72: 10119.3 | H72: =IFERROR(VLOOKUP($C72,$C$5:$H$18,6,0)+SUMIF($C$19:$C72,$C72,$F$19:$F72)-SUMIF($C$19:$C72,$C72,$G$19:$G72),"") -> 85864.47 | K72: =IF($B72="","",--TEXT($B72,"yyyymm")) -> 202606
A73: =IF(B73="","",COUNTA($B$5:B73)) -> 69 | B73: 46176 | C73: 趣点购浦发 | E73: 超市营业款 | F73: 8231.16 | H73: =IFERROR(VLOOKUP($C73,$C$5:$H$18,6,0)+SUMIF($C$19:$C73,$C73,$F$19:$F73)-SUMIF($C$19:$C73,$C73,$G$19:$G73),"") -> 94095.63 | K73: =IF($B73="","",--TEXT($B73,"yyyymm")) -> 202606
A74: =IF(B74="","",COUNTA($B$5:B74)) -> 70 | B74: 46177 | C74: 趣点购浦发 | E74: 超市营业款 | F74: 10664.18 | H74: =IFERROR(VLOOKUP($C74,$C$5:$H$18,6,0)+SUMIF($C$19:$C74,$C74,$F$19:$F74)-SUMIF($C$19:$C74,$C74,$G$19:$G74),"") -> 104759.81 | K74: =IF($B74="","",--TEXT($B74,"yyyymm")) -> 202606
A75: =IF(B75="","",COUNTA($B$5:B75)) -> 71 | B75: 46178 | C75: 趣点购浦发 | E75: 超市营业款 | F75: 11964.7 | H75: =IFERROR(VLOOKUP($C75,$C$5:$H$18,6,0)+SUMIF($C$19:$C75,$C75,$F$19:$F75)-SUMIF($C$19:$C75,$C75,$G$19:$G75),"") -> 116724.51 | K75: =IF($B75="","",--TEXT($B75,"yyyymm")) -> 202606
A76: =IF(B76="","",COUNTA($B$5:B76)) -> 72 | B76: 46179 | C76: 趣点购浦发 | E76: 超市营业款 | F76: 8657.94 | H76: =IFERROR(VLOOKUP($C76,$C$5:$H$18,6,0)+SUMIF($C$19:$C76,$C76,$F$19:$F76)-SUMIF($C$19:$C76,$C76,$G$19:$G76),"") -> 125382.45 | K76: =IF($B76="","",--TEXT($B76,"yyyymm")) -> 202606
A77: =IF(B77="","",COUNTA($B$5:B77)) -> 73 | B77: 46180 | C77: 趣点购浦发 | E77: 超市营业款 | F77: 5883.69 | H77: =IFERROR(VLOOKUP($C77,$C$5:$H$18,6,0)+SUMIF($C$19:$C77,$C77,$F$19:$F77)-SUMIF($C$19:$C77,$C77,$G$19:$G77),"") -> 131266.14 | K77: =IF($B77="","",--TEXT($B77,"yyyymm")) -> 202606
A78: =IF(B78="","",COUNTA($B$5:B78)) -> 74 | B78: 46181 | C78: 趣点购浦发 | E78: 超市营业款 | F78: 5556.97 | H78: =IFERROR(VLOOKUP($C78,$C$5:$H$18,6,0)+SUMIF($C$19:$C78,$C78,$F$19:$F78)-SUMIF($C$19:$C78,$C78,$G$19:$G78),"") -> 136823.11 | K78: =IF($B78="","",--TEXT($B78,"yyyymm")) -> 202606
... A83: =IF(B83="","",COUNTA($B$5:B83)) -> 79 | B83: 46186 | C83: 趣点购浦发 | E83: 超市营业款 | F83: 8344.59 | H83: =IFERROR(VLOOKUP($C83,$C$5:$H$18,6,0)+SUMIF($C$19:$C83,$C83,$F$19:$F83)-SUMIF($C$19:$C83,$C83,$G$19:$G83),"") -> 179882.93 | K83: =IF($B83="","",--TEXT($B83,"yyyymm")) -> 202606
A84: =IF(B84="","",COUNTA($B$5:B84)) -> 80 | B84: 46186 | C84: 趣点购浦发 | D84: 工资 | E84: 陈樨 | G84: 4000 | H84: =IFERROR(VLOOKUP($C84,$C$5:$H$18,6,0)+SUMIF($C$19:$C84,$C84,$F$19:$F84)-SUMIF($C$19:$C84,$C84,$G$19:$G84),"") -> 175882.93 | K84: =IF($B84="","",--TEXT($B84,"yyyymm")) -> 202606
A85: =IF(B85="","",COUNTA($B$5:B85)) -> 81 | B85: 46186 | C85: 趣点购浦发 | D85: 银行手续费 | E85: 网银互联汇出手续费 | G85: 4.5 | H85: =IFERROR(VLOOKUP($C85,$C$5:$H$18,6,0)+SUMIF($C$19:$C85,$C85,$F$19:$F85)-SUMIF($C$19:$C85,$C85,$G$19:$G85),"") -> 175878.43 | K85: =IF($B85="","",--TEXT($B85,"yyyymm")) -> 202606
A86: =IF(B86="","",COUNTA($B$5:B86)) -> 82 | B86: 46187 | C86: 趣点购浦发 | E86: 超市营业款 | F86: 6178.11 | H86: =IFERROR(VLOOKUP($C86,$C$5:$H$18,6,0)+SUMIF($C$19:$C86,$C86,$F$19:$F86)-SUMIF($C$19:$C86,$C86,$G$19:$G86),"") -> 182056.54 | K86: =IF($B86="","",--TEXT($B86,"yyyymm")) -> 202606
A87: =IF(B87="","",COUNTA($B$5:B87)) -> 83 | B87: 46188 | C87: 趣点购浦发 | E87: 超市营业款 | F87: 6441.22 | H87: =IFERROR(VLOOKUP($C87,$C$5:$H$18,6,0)+SUMIF($C$19:$C87,$C87,$F$19:$F87)-SUMIF($C$19:$C87,$C87,$G$19:$G87),"") -> 188497.76 | K87: =IF($B87="","",--TEXT($B87,"yyyymm")) -> 202606
A88: =IF(B88="","",COUNTA($B$5:B88)) -> 84 | B88: 46188 | C88: 趣点购浦发 | D88: 税费 | E88: 缴税 | G88: 40 | H88: =IFERROR(VLOOKUP($C88,$C$5:$H$18,6,0)+SUMIF($C$19:$C88,$C88,$F$19:$F88)-SUMIF($C$19:$C88,$C88,$G$19:$G88),"") -> 188457.76 | K88: =IF($B88="","",--TEXT($B88,"yyyymm")) -> 202606
A89: =IF(B89="","",COUNTA($B$5:B89)) -> 85 | B89: 46188 | C89: 趣点购浦发 | D89: 税费 | E89: 缴税 | G89: 450 | H89: =IFERROR(VLOOKUP($C89,$C$5:$H$18,6,0)+SUMIF($C$19:$C89,$C89,$F$19:$F89)-SUMIF($C$19:$C89,$C89,$G$19:$G89),"") -> 188007.76 | K89: =IF($B89="","",--TEXT($B89,"yyyymm")) -> 202606
A90: =IF(B90="","",COUNTA($B$5:B90)) -> 86 | B90: 46189 | C90: 趣点购浦发 | E90: 超市营业款 | F90: 8915.36 | H90: =IFERROR(VLOOKUP($C90,$C$5:$H$18,6,0)+SUMIF($C$19:$C90,$C90,$F$19:$F90)-SUMIF($C$19:$C90,$C90,$G$19:$G90),"") -> 196923.12 | K90: =IF($B90="","",--TEXT($B90,"yyyymm")) -> 202606
A91: =IF(B91="","",COUNTA($B$5:B91)) -> 87 | B91: 46190 | C91: 趣点购浦发 | E91: 超市营业款 | F91: 8244.76 | H91: =IFERROR(VLOOKUP($C91,$C$5:$H$18,6,0)+SUMIF($C$19:$C91,$C91,$F$19:$F91)-SUMIF($C$19:$C91,$C91,$G$19:$G91),"") -> 205167.88 | K91: =IF($B91="","",--TEXT($B91,"yyyymm")) -> 202606
A92: =IF(B92="","",COUNTA($B$5:B92)) -> 88 | B92: 46190 | C92: 趣点购浦发 | E92: 微信支付认证5708 | F92: 0.01 | H92: =IFERROR(VLOOKUP($C92,$C$5:$H$18,6,0)+SUMIF($C$19:$C92,$C92,$F$19:$F92)-SUMIF($C$19:$C92,$C92,$G$19:$G92),"") -> 205167.89 | K92: =IF($B92="","",--TEXT($B92,"yyyymm")) -> 202606
A93: =IF(B93="","",COUNTA($B$5:B93)) -> 89 | B93: 46190 | C93: 趣点购浦发 | E93: 入股金 | F93: 400000 | H93: =IFERROR(VLOOKUP($C93,$C$5:$H$18,6,0)+SUMIF($C$19:$C93,$C93,$F$19:$F93)-SUMIF($C$19:$C93,$C93,$G$19:$G93),"") -> 605167.89 | K93: =IF($B93="","",--TEXT($B93,"yyyymm")) -> 202606
A94: =IF(B94="","",COUNTA($B$5:B94)) -> 90 | B94: 46191 | C94: 趣点购浦发 | E94: 超市营业款 | F94: 7872.11 | H94: =IFERROR(VLOOKUP($C94,$C$5:$H$18,6,0)+SUMIF($C$19:$C94,$C94,$F$19:$F94)-SUMIF($C$19:$C94,$C94,$G$19:$G94),"") -> 613040 | K94: =IF($B94="","",--TEXT($B94,"yyyymm")) -> 202606
A95: =IF(B95="","",COUNTA($B$5:B95)) -> 91 | B95: 46192 | C95: 趣点购浦发 | E95: 超市营业款 | F95: 8137.49 | H95: =IFERROR(VLOOKUP($C95,$C$5:$H$18,6,0)+SUMIF($C$19:$C95,$C95,$F$19:$F95)-SUMIF($C$19:$C95,$C95,$G$19:$G95),"") -> 621177.49 | K95: =IF($B95="","",--TEXT($B95,"yyyymm")) -> 202606
A96: =IF(B96="","",COUNTA($B$5:B96)) -> 92 | B96: 46193 | C96: 趣点购浦发 | E96: 超市营业款 | F96: 3985.05 | H96: =IFERROR(VLOOKUP($C96,$C$5:$H$18,6,0)+SUMIF($C$19:$C96,$C96,$F$19:$F96)-SUMIF($C$19:$C96,$C96,$G$19:$G96),"") -> 625162.54 | K96: =IF($B96="","",--TEXT($B96,"yyyymm")) -> 202606
A97: =IF(B97="","",COUNTA($B$5:B97)) -> 93 | B97: 46194 | C97: 趣点购浦发 | E97: 活期存款结息 | F97: 7.65 | H97: =IFERROR(VLOOKUP($C97,$C$5:$H$18,6,0)+SUMIF($C$19:$C97,$C97,$F$19:$F97)-SUMIF($C$19:$C97,$C97,$G$19:$G97),"") -> 625170.19 | K97: =IF($B97="","",--TEXT($B97,"yyyymm")) -> 202606
A98: =IF(B98="","",COUNTA($B$5:B98)) -> 94 | B98: 46194 | C98: 趣点购浦发 | E98: 超市营业款 | F98: 3890.63 | H98: =IFERROR(VLOOKUP($C98,$C$5:$H$18,6,0)+SUMIF($C$19:$C98,$C98,$F$19:$F98)-SUMIF($C$19:$C98,$C98,$G$19:$G98),"") -> 629060.82 | K98: =IF($B98="","",--TEXT($B98,"yyyymm")) -> 202606
A99: =IF(B99="","",COUNTA($B$5:B99)) -> 95 | B99: 46195 | C99: 趣点购浦发 | E99: 超市营业款 | F99: 4835.04 | H99: =IFERROR(VLOOKUP($C99,$C$5:$H$18,6,0)+SUMIF($C$19:$C99,$C99,$F$19:$F99)-SUMIF($C$19:$C99,$C99,$G$19:$G99),"") -> 633895.86 | K99: =IF($B99="","",--TEXT($B99,"yyyymm")) -> 202606
A100: =IF(B100="","",COUNTA($B$5:B100)) -> 96 | B100: 46195 | C100: 趣点购浦发 | E100: 企业实名认证专用，金额请勿泄露 | F100: 0.45 | H100: =IFERROR(VLOOKUP($C100,$C$5:$H$18,6,0)+SUMIF($C$19:$C100,$C100,$F$19:$F100)-SUMIF($C$19:$C100,$C100,$G$19:$G100),"") -> 633896.31 | K100: =IF($B100="","",--TEXT($B100,"yyyymm")) -> 202606
A101: =IF(B101="","",COUNTA($B$5:B101)) -> 97 | B101: 46195 | C101: 趣点购浦发 | D101: 合同履约保证金 | E101: 饮料合同保证金 | G101: 5000 | H101: =IFERROR(VLOOKUP($C101,$C$5:$H$18,6,0)+SUMIF($C$19:$C101,$C101,$F$19:$F101)-SUMIF($C$19:$C101,$C101,$G$19:$G101),"") -> 628896.31 | J101: 成都统一企业食品有限公司 | K101: =IF($B101="","",--TEXT($B101,"yyyymm")) -> 202606
A102: =IF(B102="","",COUNTA($B$5:B102)) -> 98 | B102: 46195 | C102: 趣点购浦发 | D102: 银行手续费 | E102: 网银互联汇出手续费 | G102: 4.5 | H102: =IFERROR(VLOOKUP($C102,$C$5:$H$18,6,0)+SUMIF($C$19:$C102,$C102,$F$19:$F102)-SUMIF($C$19:$C102,$C102,$G$19:$G102),"") -> 628891.81 | K102: =IF($B102="","",--TEXT($B102,"yyyymm")) -> 202606
A103: =IF(B103="","",COUNTA($B$5:B103)) -> 99 | B103: 46196 | C103: 趣点购浦发 | E103: 超市营业款 | F103: 9298.21 | H103: =IFERROR(VLOOKUP($C103,$C$5:$H$18,6,0)+SUMIF($C$19:$C103,$C103,$F$19:$F103)-SUMIF($C$19:$C103,$C103,$G$19:$G103),"") -> 638190.02 | K103: =IF($B103="","",--TEXT($B103,"yyyymm")) -> 202606
A104: =IF(B104="","",COUNTA($B$5:B104)) -> 100 | B104: 46197 | C104: 趣点购浦发 | E104: 超市营业款 | F104: 9069.14 | H104: =IFERROR(VLOOKUP($C104,$C$5:$H$18,6,0)+SUMIF($C$19:$C104,$C104,$F$19:$F104)-SUMIF($C$19:$C104,$C104,$G$19:$G104),"") -> 647259.16 | K104: =IF($B104="","",--TEXT($B104,"yyyymm")) -> 202606
A105: =IF(B105="","",COUNTA($B$5:B105)) -> 101 | B105: 46197 | C105: 趣点购浦发 | E105: 借款-陈金刚 | F105: 260000 | H105: =IFERROR(VLOOKUP($C105,$C$5:$H$18,6,0)+SUMIF($C$19:$C105,$C105,$F$19:$F105)-SUMIF($C$19:$C105,$C105,$G$19:$G105),"") -> 907259.16 | K105: =IF($B105="","",--TEXT($B105,"yyyymm")) -> 202606
...

Sheet 投标和合同履约保证金统计
A1: 保证金收款 / 付款统计（按起止日期）
A2: 开始日期 | B2: 46023 | C2: 结束日期 | D2: 46387 | F2: 期初余款 | G2: =SUMIFS(数据录入!$F$5:$F$4999,$Q$5:$Q$4999,1,数据录入!$B$5:$B$4999,"<"&$B$2)-SUMIFS(数据录入!$G$5:$G$4999,$Q$5:$Q$4999,1,数据录入!$B$5:$B$4999,"<"&$B$2)
A3: 说明：修改黄色起止日期即可查询。明细自动提取「数据录入」中业务类别为投标保证金 / 合同履约保证金，或摘要含“保证金”的收付记录；往来单位取自客户与供应商（见「基础资料」）。余额＝期初余款＋收款－付款，负数表示保证金已付出、尚未收回。 | F3: 期间收入 | G3: =SUMIFS(数据录入!$F$5:$F$4999,$Q$5:$Q$4999,1,数据录入!$B$5:$B$4999,">="&$B$2,数据录入!$B$5:$B$4999,"<="&$D$2)
F4: 期间付款 | G4: =SUMIFS(数据录入!$G$5:$G$4999,$Q$5:$Q$4999,1,数据录入!$B$5:$B$4999,">="&$B$2,数据录入!$B$5:$B$4999,"<="&$D$2) | Q4: 保证金标记 | R4: 期内序号
F5: 期末余额 | G5: =G2+G3-G4 | K5: 其他（未指定往来单位） | L5: =$G$2-SUM($L$8:$L$107) | M5: =$G$3-SUM($M$8:$M$107) | N5: =$G$4-SUM($N$8:$N$107) | O5: =L5+M5-N5 | Q5: =IF(数据录入!$B5="",0,IF(OR(数据录入!$D5="投标保证金",数据录入!$D5="合同履约保证金",ISNUMBER(FIND("保证金",数据录入!$E5))),1,0)) | R5: =IF(AND($Q5=1,数据录入!$B5>=$B$2,数据录入!$B5<=$D$2),N(R4)+1,N(R4))
A6: =IF(MAX($R$5:$R$4999)>500,"※ 期间保证金记录超过 500 条，明细仅显示前 500 条，请缩小查询区间或向下复制明细公式。","") | K6: 合计 | L6: =L5+SUM($L$8:$L$107) | M6: =M5+SUM($M$8:$M$107) | N6: =N5+SUM($N$8:$N$107) | O6: =L6+M6-N6 | Q6: =IF(数据录入!$B6="",0,IF(OR(数据录入!$D6="投标保证金",数据录入!$D6="合同履约保证金",ISNUMBER(FIND("保证金",数据录入!$E6))),1,0)) | R6: =IF(AND($Q6=1,数据录入!$B6>=$B$2,数据录入!$B6<=$D$2),N(R5)+1,N(R5))
A7: 日期 | B7: 账户 | C7: 类型 | D7: 往来单位 | E7: 摘要 | F7: 收入金额 | G7: 付款金额 | H7: 余额 | J7: 序 | K7: 往来单位 | L7: 期初余款 | M7: 期间收款 | N7: 期间付款 | O7: 期末余额 | Q7: =IF(数据录入!$B7="",0,IF(OR(数据录入!$D7="投标保证金",数据录入!$D7="合同履约保证金",ISNUMBER(FIND("保证金",数据录入!$E7))),1,0)) | R7: =IF(AND($Q7=1,数据录入!$B7>=$B$2,数据录入!$B7<=$D$2),N(R6)+1,N(R6)) | S7: 明细定位 | U7: 往来单位候选 | V7: 有效标记 | W7: 往来单位序号
A8: =IF($S8="","",INDEX(数据录入!$B$5:$B$4999,$S8)) | B8: =IF($S8="","",INDEX(数据录入!$C$5:$C$4999,$S8)&"") | C8: =IF($S8="","",IF(N($F8)>0,"收款",IF(N($G8)>0,"付款",""))) | D8: =IF($S8="","",IF((INDEX(数据录入!$I$5:$I$4999,$S8)&"")<>"",INDEX(数据录入!$I$5:$I$4999,$S8)&"",INDEX(数据录入!$J$5:$J$4999,$S8)&"")) | E8: =IF($S8="","",INDEX(数据录入!$E$5:$E$4999,$S8)&"") | F8: =IF($S8="","",N(INDEX(数据录入!$F$5:$F$4999,$S8))) | G8: =IF($S8="","",N(INDEX(数据录入!$G$5:$G$4999,$S8))) | H8: =IF($S8="","",$G$2+SUM($F$8:$F8)-SUM($G$8:$G8)) | J8: =IF($K8="","",1) | K8: =IFERROR(INDEX($U$8:$U$107,MATCH(1,$W$8:$W$107,0)),"") | L8: =IF($K8="","",(SUMIFS(数据录入!$F$5:$F$4999,$Q$5:$Q$4999,1,数据录入!$B$5:$B$4999,"<"&$B$2,数据录入!$I$5:$I$4999,$K8)+SUMIFS(数据录入!$F$5:$F$4999,$Q$5:$Q$4999,1,数据录入!$B$5:$B$4999,"<"&$B$2,数据录入!$J$5:$J$4999,$K8))-(SUMIFS(数据录入!$G$5:$G$4999,$Q$5:$Q$4999,1,数据录入!$B$5:$B$4999,"<"&$B$2,数据录入!$I$5:$I$4999,$K8)+SUMIFS(数据录入!$G$5:$G$4999,$Q$5:$Q$4999,1,数据录入!$B$5:$B$4999,"<"&$B$2,数据录入!$J$5:$J$4999,$K8))) | M8: =IF($K8="","",SUMIFS(数据录入!$F$5:$F$4999,$Q$5:$Q$4999,1,数据录入!$B$5:$B$4999,">="&$B$2,数据录入!$B$5:$B$4999,"<="&$D$2,数据录入!$I$5:$I$4999,$K8)+SUMIFS(数据录入!$F$5:$F$4999,$Q$5:$Q$4999,1,数据录入!$B$5:$B$4999,">="&$B$2,数据录入!$B$5:$B$4999,"<="&$D$2,数据录入!$J$5:$J$4999,$K8)) | N8: =IF($K8="","",SUMIFS(数据录入!$G$5:$G$4999,$Q$5:$Q$4999,1,数据录入!$B$5:$B$4999,">="&$B$2,数据录入!$B$5:$B$4999,"<="&$D$2,数据录入!$I$5:$I$4999,$K8)+SUMIFS(数据录入!$G$5:$G$4999,$Q$5:$Q$4999,1,数据录入!$B$5:$B$4999,">="&$B$2,数据录入!$B$5:$B$4999,"<="&$D$2,数据录入!$J$5:$J$4999,$K8)) | O8: =IF($K8="","",L8+M8-N8) | Q8: =IF(数据录入!$B8="",0,IF(OR(数据录入!$D8="投标保证金",数据录入!$D8="合同履约保证金",ISNUMBER(FIND("保证金",数据录入!$E8))),1,0)) | R8: =IF(AND($Q8=1,数据录入!$B8>=$B$2,数据录入!$B8<=$D$2),N(R7)+1,N(R7)) | S8: =IFERROR(MATCH(1,$R$5:$R$4999,0),"") | U8: =IFERROR(IF(1<=50,INDEX(基础资料!$E$2:$E$51,1)&"",INDEX(基础资料!$G$2:$G$51,1-50)&""),"") | V8: =IF($U8="",0,IF(AND(1>50,COUNTIF(基础资料!$E$2:$E$51,$U8)>0),0,1)) | W8: =IF($V8=1,N(W7)+1,N(W7))
A9: =IF($S9="","",INDEX(数据录入!$B$5:$B$4999,$S9)) | B9: =IF($S9="","",INDEX(数据录入!$C$5:$C$4999,$S9)&"") | C9: =IF($S9="","",IF(N($F9)>0,"收款",IF(N($G9)>0,"付款",""))) | D9: =IF($S9="","",IF((INDEX(数据录入!$I$5:$I$4999,$S9)&"")<>"",INDEX(数据录入!$I$5:$I$4999,$S9)&"",INDEX(数据录入!$J$5:$J$4999,$S9)&"")) | E9: =IF($S9="","",INDEX(数据录入!$E$5:$E$4999,$S9)&"") | F9: =IF($S9="","",N(INDEX(数据录入!$F$5:$F$4999,$S9))) | G9: =IF($S9="","",N(INDEX(数据录入!$G$5:$G$4999,$S9))) | H9: =IF($S9="","",$G$2+SUM($F$8:$F9)-SUM($G$8:$G9)) | J9: =IF($K9="","",2) | K9: =IFERROR(INDEX($U$8:$U$107,MATCH(2,$W$8:$W$107,0)),"") | L9: =IF($K9="","",(SUMIFS(数据录入!$F$5:$F$4999,$Q$5:$Q$4999,1,数据录入!$B$5:$B$4999,"<"&$B$2,数据录入!$I$5:$I$4999,$K9)+SUMIFS(数据录入!$F$5:$F$4999,$Q$5:$Q$4999,1,数据录入!$B$5:$B$4999,"<"&$B$2,数据录入!$J$5:$J$4999,$K9))-(SUMIFS(数据录入!$G$5:$G$4999,$Q$5:$Q$4999,1,数据录入!$B$5:$B$4999,"<"&$B$2,数据录入!$I$5:$I$4999,$K9)+SUMIFS(数据录入!$G$5:$G$4999,$Q$5:$Q$4999,1,数据录入!$B$5:$B$4999,"<"&$B$2,数据录入!$J$5:$J$4999,$K9))) | M9: =IF($K9="","",SUMIFS(数据录入!$F$5:$F$4999,$Q$5:$Q$4999,1,数据录入!$B$5:$B$4999,">="&$B$2,数据录入!$B$5:$B$4999,"<="&$D$2,数据录入!$I$5:$I$4999,$K9)+SUMIFS(数据录入!$F$5:$F$4999,$Q$5:$Q$4999,1,数据录入!$B$5:$B$4999,">="&$B$2,数据录入!$B$5:$B$4999,"<="&$D$2,数据录入!$J$5:$J$4999,$K9)) | N9: =IF($K9="","",SUMIFS(数据录入!$G$5:$G$4999,$Q$5:$Q$4999,1,数据录入!$B$5:$B$4999,">="&$B$2,数据录入!$B$5:$B$4999,"<="&$D$2,数据录入!$I$5:$I$4999,$K9)+SUMIFS(数据录入!$G$5:$G$4999,$Q$5:$Q$4999,1,数据录入!$B$5:$B$4999,">="&$B$2,数据录入!$B$5:$B$4999,"<="&$D$2,数据录入!$J$5:$J$4999,$K9)) | O9: =IF($K9="","",L9+M9-N9) | Q9: =IF(数据录入!$B9="",0,IF(OR(数据录入!$D9="投标保证金",数据录入!$D9="合同履约保证金",ISNUMBER(FIND("保证金",数据录入!$E9))),1,0)) | R9: =IF(AND($Q9=1,数据录入!$B9>=$B$2,数据录入!$B9<=$D$2),N(R8)+1,N(R8)) | S9: =IFERROR(MATCH(2,$R$5:$R$4999,0),"") | U9: =IFERROR(IF(2<=50,INDEX(基础资料!$E$2:$E$51,2)&"",INDEX(基础资料!$G$2:$G$51,2-50)&""),"") | V9: =IF($U9="",0,IF(AND(2>50,COUNTIF(基础资料!$E$2:$E$51,$U9)>0),0,1)) | W9: =IF($V9=1,N(W8)+1,N(W8))
A10: =IF($S10="","",INDEX(数据录入!$B$5:$B$4999,$S10)) | B10: =IF($S10="","",INDEX(数据录入!$C$5:$C$4999,$S10)&"") | C10: =IF($S10="","",IF(N($F10)>0,"收款",IF(N($G10)>0,"付款",""))) | D10: =IF($S10="","",IF((INDEX(数据录入!$I$5:$I$4999,$S10)&"")<>"",INDEX(数据录入!$I$5:$I$4999,$S10)&"",INDEX(数据录入!$J$5:$J$4999,$S10)&"")) | E10: =IF($S10="","",INDEX(数据录入!$E$5:$E$4999,$S10)&"") | F10: =IF($S10="","",N(INDEX(数据录入!$F$5:$F$4999,$S10))) | G10: =IF($S10="","",N(INDEX(数据录入!$G$5:$G$4999,$S10))) | H10: =IF($S10="","",$G$2+SUM($F$8:$F10)-SUM($G$8:$G10)) | J10: =IF($K10="","",3) | K10: =IFERROR(INDEX($U$8:$U$107,MATCH(3,$W$8:$W$107,0)),"") | L10: =IF($K10="","",(SUMIFS(数据录入!$F$5:$F$4999,$Q$5:$Q$4999,1,数据录入!$B$5:$B$4999,"<"&$B$2,数据录入!$I$5:$I$4999,$K10)+SUMIFS(数据录入!$F$5:$F$4999,$Q$5:$Q$4999,1,数据录入!$B$5:$B$4999,"<"&$B$2,数据录入!$J$5:$J$4999,$K10))-(SUMIFS(数据录入!$G$5:$G$4999,$Q$5:$Q$4999,1,数据录入!$B$5:$B$4999,"<"&$B$2,数据录入!$I$5:$I$4999,$K10)+SUMIFS(数据录入!$G$5:$G$4999,$Q$5:$Q$4999,1,数据录入!$B$5:$B$4999,"<"&$B$2,数据录入!$J$5:$J$4999,$K10))) | M10: =IF($K10="","",SUMIFS(数据录入!$F$5:$F$4999,$Q$5:$Q$4999,1,数据录入!$B$5:$B$4999,">="&$B$2,数据录入!$B$5:$B$4999,"<="&$D$2,数据录入!$I$5:$I$4999,$K10)+SUMIFS(数据录入!$F$5:$F$4999,$Q$5:$Q$4999,1,数据录入!$B$5:$B$4999,">="&$B$2,数据录入!$B$5:$B$4999,"<="&$D$2,数据录入!$J$5:$J$4999,$K10)) | N10: =IF($K10="","",SUMIFS(数据录入!$G$5:$G$4999,$Q$5:$Q$4999,1,数据录入!$B$5:$B$4999,">="&$B$2,数据录入!$B$5:$B$4999,"<="&$D$2,数据录入!$I$5:$I$4999,$K10)+SUMIFS(数据录入!$G$5:$G$4999,$Q$5:$Q$4999,1,数据录入!$B$5:$B$4999,">="&$B$2,数据录入!$B$5:$B$4999,"<="&$D$2,数据录入!$J$5:$J$4999,$K10)) | O10: =IF($K10="","",L10+M10-N10) | Q10: =IF(数据录入!$B10="",0,IF(OR(数据录入!$D10="投标保证金",数据录入!$D10="合同履约保证金",ISNUMBER(FIND("保证金",数据录入!$E10))),1,0)) | R10: =IF(AND($Q10=1,数据录入!$B10>=$B$2,数据录入!$B10<=$D$2),N(R9)+1,N(R9)) | S10: =IFERROR(MATCH(3,$R$5:$R$4999,0),"") | U10: =IFERROR(IF(3<=50,INDEX(基础资料!$E$2:$E$51,3)&"",INDEX(基础资料!$G$2:$G$51,3-50)&""),"") | V10: =IF($U10="",0,IF(AND(3>50,COUNTIF(基础资料!$E$2:$E$51,$U10)>0),0,1)) | W10: =IF($V10=1,N(W9)+1,N(W9))
A11: =IF($S11="","",INDEX(数据录入!$B$5:$B$4999,$S11)) | B11: =IF($S11="","",INDEX(数据录入!$C$5:$C$4999,$S11)&"") | C11: =IF($S11="","",IF(N($F11)>0,"收款",IF(N($G11)>0,"付款",""))) | D11: =IF($S11="","",IF((INDEX(数据录入!$I$5:$I$4999,$S11)&"")<>"",INDEX(数据录入!$I$5:$I$4999,$S11)&"",INDEX(数据录入!$J$5:$J$4999,$S11)&"")) | E11: =IF($S11="","",INDEX(数据录入!$E$5:$E$4999,$S11)&"") | F11: =IF($S11="","",N(INDEX(数据录入!$F$5:$F$4999,$S11))) | G11: =IF($S11="","",N(INDEX(数据录入!$G$5:$G$4999,$S11))) | H11: =IF($S11="","",$G$2+SUM($F$8:$F11)-SUM($G$8:$G11)) | J11: =IF($K11="","",4) | K11: =IFERROR(INDEX($U$8:$U$107,MATCH(4,$W$8:$W$107,0)),"") | L11: =IF($K11="","",(SUMIFS(数据录入!$F$5:$F$4999,$Q$5:$Q$4999,1,数据录入!$B$5:$B$4999,"<"&$B$2,数据录入!$I$5:$I$4999,$K11)+SUMIFS(数据录入!$F$5:$F$4999,$Q$5:$Q$4999,1,数据录入!$B$5:$B$4999,"<"&$B$2,数据录入!$J$5:$J$4999,$K11))-(SUMIFS(数据录入!$G$5:$G$4999,$Q$5:$Q$4999,1,数据录入!$B$5:$B$4999,"<"&$B$2,数据录入!$I$5:$I$4999,$K11)+SUMIFS(数据录入!$G$5:$G$4999,$Q$5:$Q$4999,1,数据录入!$B$5:$B$4999,"<"&$B$2,数据录入!$J$5:$J$4999,$K11))) | M11: =IF($K11="","",SUMIFS(数据录入!$F$5:$F$4999,$Q$5:$Q$4999,1,数据录入!$B$5:$B$4999,">="&$B$2,数据录入!$B$5:$B$4999,"<="&$D$2,数据录入!$I$5:$I$4999,$K11)+SUMIFS(数据录入!$F$5:$F$4999,$Q$5:$Q$4999,1,数据录入!$B$5:$B$4999,">="&$B$2,数据录入!$B$5:$B$4999,"<="&$D$2,数据录入!$J$5:$J$4999,$K11)) | N11: =IF($K11="","",SUMIFS(数据录入!$G$5:$G$4999,$Q$5:$Q$4999,1,数据录入!$B$5:$B$4999,">="&$B$2,数据录入!$B$5:$B$4999,"<="&$D$2,数据录入!$I$5:$I$4999,$K11)+SUMIFS(数据录入!$G$5:$G$4999,$Q$5:$Q$4999,1,数据录入!$B$5:$B$4999,">="&$B$2,数据录入!$B$5:$B$4999,"<="&$D$2,数据录入!$J$5:$J$4999,$K11)) | O11: =IF($K11="","",L11+M11-N11) | Q11: =IF(数据录入!$B11="",0,IF(OR(数据录入!$D11="投标保证金",数据录入!$D11="合同履约保证金",ISNUMBER(FIND("保证金",数据录入!$E11))),1,0)) | R11: =IF(AND($Q11=1,数据录入!$B11>=$B$2,数据录入!$B11<=$D$2),N(R10)+1,N(R10)) | S11: =IFERROR(MATCH(4,$R$5:$R$4999,0),"") | U11: =IFERROR(IF(4<=50,INDEX(基础资料!$E$2:$E$51,4)&"",INDEX(基础资料!$G$2:$G$51,4-50)&""),"") | V11: =IF($U11="",0,IF(AND(4>50,COUNTIF(基础资料!$E$2:$E$51,$U11)>0),0,1)) | W11: =IF($V11=1,N(W10)+1,N(W10))
A12: =IF($S12="","",INDEX(数据录入!$B$5:$B$4999,$S12)) | B12: =IF($S12="","",INDEX(数据录入!$C$5:$C$4999,$S12)&"") | C12: =IF($S12="","",IF(N($F12)>0,"收款",IF(N($G12)>0,"付款",""))) | D12: =IF($S12="","",IF((INDEX(数据录入!$I$5:$I$4999,$S12)&"")<>"",INDEX(数据录入!$I$5:$I$4999,$S12)&"",INDEX(数据录入!$J$5:$J$4999,$S12)&"")) | E12: =IF($S12="","",INDEX(数据录入!$E$5:$E$4999,$S12)&"") | F12: =IF($S12="","",N(INDEX(数据录入!$F$5:$F$4999,$S12))) | G12: =IF($S12="","",N(INDEX(数据录入!$G$5:$G$4999,$S12))) | H12: =IF($S12="","",$G$2+SUM($F$8:$F12)-SUM($G$8:$G12)) | J12: =IF($K12="","",5) | K12: =IFERROR(INDEX($U$8:$U$107,MATCH(5,$W$8:$W$107,0)),"") | L12: =IF($K12="","",(SUMIFS(数据录入!$F$5:$F$4999,$Q$5:$Q$4999,1,数据录入!$B$5:$B$4999,"<"&$B$2,数据录入!$I$5:$I$4999,$K12)+SUMIFS(数据录入!$F$5:$F$4999,$Q$5:$Q$4999,1,数据录入!$B$5:$B$4999,"<"&$B$2,数据录入!$J$5:$J$4999,$K12))-(SUMIFS(数据录入!$G$5:$G$4999,$Q$5:$Q$4999,1,数据录入!$B$5:$B$4999,"<"&$B$2,数据录入!$I$5:$I$4999,$K12)+SUMIFS(数据录入!$G$5:$G$4999,$Q$5:$Q$4999,1,数据录入!$B$5:$B$4999,"<"&$B$2,数据录入!$J$5:$J$4999,$K12))) | M12: =IF($K12="","",SUMIFS(数据录入!$F$5:$F$4999,$Q$5:$Q$4999,1,数据录入!$B$5:$B$4999,">="&$B$2,数据录入!$B$5:$B$4999,"<="&$D$2,数据录入!$I$5:$I$4999,$K12)+SUMIFS(数据录入!$F$5:$F$4999,$Q$5:$Q$4999,1,数据录入!$B$5:$B$4999,">="&$B$2,数据录入!$B$5:$B$4999,"<="&$D$2,数据录入!$J$5:$J$4999,$K12)) | N12: =IF($K12="","",SUMIFS(数据录入!$G$5:$G$4999,$Q$5:$Q$4999,1,数据录入!$B$5:$B$4999,">="&$B$2,数据录入!$B$5:$B$4999,"<="&$D$2,数据录入!$I$5:$I$4999,$K12)+SUMIFS(数据录入!$G$5:$G$4999,$Q$5:$Q$4999,1,数据录入!$B$5:$B$4999,">="&$B$2,数据录入!$B$5:$B$4999,"<="&$D$2,数据录入!$J$5:$J$4999,$K12)) | O12: =IF($K12="","",L12+M12-N12) | Q12: =IF(数据录入!$B12="",0,IF(OR(数据录入!$D12="投标保证金",数据录入!$D12="合同履约保证金",ISNUMBER(FIND("保证金",数据录入!$E12))),1,0)) | R12: =IF(AND($Q12=1,数据录入!$B12>=$B$2,数据录入!$B12<=$D$2),N(R11)+1,N(R11)) | S12: =IFERROR(MATCH(5,$R$5:$R$4999,0),"") | U12: =IFERROR(IF(5<=50,INDEX(基础资料!$E$2:$E$51,5)&"",INDEX(基础资料!$G$2:$G$51,5-50)&""),"") | V12: =IF($U12="",0,IF(AND(5>50,COUNTIF(基础资料!$E$2:$E$51,$U12)>0),0,1)) | W12: =IF($V12=1,N(W11)+1,N(W11))
A13: =IF($S13="","",INDEX(数据录入!$B$5:$B$4999,$S13)) | B13: =IF($S13="","",INDEX(数据录入!$C$5:$C$4999,$S13)&"") | C13: =IF($S13="","",IF(N($F13)>0,"收款",IF(N($G13)>0,"付款",""))) | D13: =IF($S13="","",IF((INDEX(数据录入!$I$5:$I$4999,$S13)&"")<>"",INDEX(数据录入!$I$5:$I$4999,$S13)&"",INDEX(数据录入!$J$5:$J$4999,$S13)&"")) | E13: =IF($S13="","",INDEX(数据录入!$E$5:$E$4999,$S13)&"") | F13: =IF($S13="","",N(INDEX(数据录入!$F$5:$F$4999,$S13))) | G13: =IF($S13="","",N(INDEX(数据录入!$G$5:$G$4999,$S13))) | H13: =IF($S13="","",$G$2+SUM($F$8:$F13)-SUM($G$8:$G13)) | J13: =IF($K13="","",6) | K13: =IFERROR(INDEX($U$8:$U$107,MATCH(6,$W$8:$W$107,0)),"") | L13: =IF($K13="","",(SUMIFS(数据录入!$F$5:$F$4999,$Q$5:$Q$4999,1,数据录入!$B$5:$B$4999,"<"&$B$2,数据录入!$I$5:$I$4999,$K13)+SUMIFS(数据录入!$F$5:$F$4999,$Q$5:$Q$4999,1,数据录入!$B$5:$B$4999,"<"&$B$2,数据录入!$J$5:$J$4999,$K13))-(SUMIFS(数据录入!$G$5:$G$4999,$Q$5:$Q$4999,1,数据录入!$B$5:$B$4999,"<"&$B$2,数据录入!$I$5:$I$4999,$K13)+SUMIFS(数据录入!$G$5:$G$4999,$Q$5:$Q$4999,1,数据录入!$B$5:$B$4999,"<"&$B$2,数据录入!$J$5:$J$4999,$K13))) | M13: =IF($K13="","",SUMIFS(数据录入!$F$5:$F$4999,$Q$5:$Q$4999,1,数据录入!$B$5:$B$4999,">="&$B$2,数据录入!$B$5:$B$4999,"<="&$D$2,数据录入!$I$5:$I$4999,$K13)+SUMIFS(数据录入!$F$5:$F$4999,$Q$5:$Q$4999,1,数据录入!$B$5:$B$4999,">="&$B$2,数据录入!$B$5:$B$4999,"<="&$D$2,数据录入!$J$5:$J$4999,$K13)) | N13: =IF($K13="","",SUMIFS(数据录入!$G$5:$G$4999,$Q$5:$Q$4999,1,数据录入!$B$5:$B$4999,">="&$B$2,数据录入!$B$5:$B$4999,"<="&$D$2,数据录入!$I$5:$I$4999,$K13)+SUMIFS(数据录入!$G$5:$G$4999,$Q$5:$Q$4999,1,数据录入!$B$5:$B$4999,">="&$B$2,数据录入!$B$5:$B$4999,"<="&$D$2,数据录入!$J$5:$J$4999,$K13)) | O13: =IF($K13="","",L13+M13-N13) | Q13: =IF(数据录入!$B13="",0,IF(OR(数据录入!$D13="投标保证金",数据录入!$D13="合同履约保证金",ISNUMBER(FIND("保证金",数据录入!$E13))),1,0)) | R13: =IF(AND($Q13=1,数据录入!$B13>=$B$2,数据录入!$B13<=$D$2),N(R12)+1,N(R12)) | S13: =IFERROR(MATCH(6,$R$5:$R$4999,0),"") | U13: =IFERROR(IF(6<=50,INDEX(基础资料!$E$2:$E$51,6)&"",INDEX(基础资料!$G$2:$G$51,6-50)&""),"") | V13: =IF($U13="",0,IF(AND(6>50,COUNTIF(基础资料!$E$2:$E$51,$U13)>0),0,1)) | W13: =IF($V13=1,N(W12)+1,N(W12))
A14: =IF($S14="","",INDEX(数据录入!$B$5:$B$4999,$S14)) | B14: =IF($S14="","",INDEX(数据录入!$C$5:$C$4999,$S14)&"") | C14: =IF($S14="","",IF(N($F14)>0,"收款",IF(N($G14)>0,"付款",""))) | D14: =IF($S14="","",IF((INDEX(数据录入!$I$5:$I$4999,$S14)&"")<>"",INDEX(数据录入!$I$5:$I$4999,$S14)&"",INDEX(数据录入!$J$5:$J$4999,$S14)&"")) | E14: =IF($S14="","",INDEX(数据录入!$E$5:$E$4999,$S14)&"") | F14: =IF($S14="","",N(INDEX(数据录入!$F$5:$F$4999,$S14))) | G14: =IF($S14="","",N(INDEX(数据录入!$G$5:$G$4999,$S14))) | H14: =IF($S14="","",$G$2+SUM($F$8:$F14)-SUM($G$8:$G14)) | J14: =IF($K14="","",7) | K14: =IFERROR(INDEX($U$8:$U$107,MATCH(7,$W$8:$W$107,0)),"") | L14: =IF($K14="","",(SUMIFS(数据录入!$F$5:$F$4999,$Q$5:$Q$4999,1,数据录入!$B$5:$B$4999,"<"&$B$2,数据录入!$I$5:$I$4999,$K14)+SUMIFS(数据录入!$F$5:$F$4999,$Q$5:$Q$4999,1,数据录入!$B$5:$B$4999,"<"&$B$2,数据录入!$J$5:$J$4999,$K14))-(SUMIFS(数据录入!$G$5:$G$4999,$Q$5:$Q$4999,1,数据录入!$B$5:$B$4999,"<"&$B$2,数据录入!$I$5:$I$4999,$K14)+SUMIFS(数据录入!$G$5:$G$4999,$Q$5:$Q$4999,1,数据录入!$B$5:$B$4999,"<"&$B$2,数据录入!$J$5:$J$4999,$K14))) | M14: =IF($K14="","",SUMIFS(数据录入!$F$5:$F$4999,$Q$5:$Q$4999,1,数据录入!$B$5:$B$4999,">="&$B$2,数据录入!$B$5:$B$4999,"<="&$D$2,数据录入!$I$5:$I$4999,$K14)+SUMIFS(数据录入!$F$5:$F$4999,$Q$5:$Q$4999,1,数据录入!$B$5:$B$4999,">="&$B$2,数据录入!$B$5:$B$4999,"<="&$D$2,数据录入!$J$5:$J$4999,$K14)) | N14: =IF($K14="","",SUMIFS(数据录入!$G$5:$G$4999,$Q$5:$Q$4999,1,数据录入!$B$5:$B$4999,">="&$B$2,数据录入!$B$5:$B$4999,"<="&$D$2,数据录入!$I$5:$I$4999,$K14)+SUMIFS(数据录入!$G$5:$G$4999,$Q$5:$Q$4999,1,数据录入!$B$5:$B$4999,">="&$B$2,数据录入!$B$5:$B$4999,"<="&$D$2,数据录入!$J$5:$J$4999,$K14)) | O14: =IF($K14="","",L14+M14-N14) | Q14: =IF(数据录入!$B14="",0,IF(OR(数据录入!$D14="投标保证金",数据录入!$D14="合同履约保证金",ISNUMBER(FIND("保证金",数据录入!$E14))),1,0)) | R14: =IF(AND($Q14=1,数据录入!$B14>=$B$2,数据录入!$B14<=$D$2),N(R13)+1,N(R13)) | S14: =IFERROR(MATCH(7,$R$5:$R$4999,0),"") | U14: =IFERROR(IF(7<=50,INDEX(基础资料!$E$2:$E$51,7)&"",INDEX(基础资料!$G$2:$G$51,7-50)&""),"") | V14: =IF($U14="",0,IF(AND(7>50,COUNTIF(基础资料!$E$2:$E$51,$U14)>0),0,1)) | W14: =IF($V14=1,N(W13)+1,N(W13))
A15: =IF($S15="","",INDEX(数据录入!$B$5:$B$4999,$S15)) | B15: =IF($S15="","",INDEX(数据录入!$C$5:$C$4999,$S15)&"") | C15: =IF($S15="","",IF(N($F15)>0,"收款",IF(N($G15)>0,"付款",""))) | D15: =IF($S15="","",IF((INDEX(数据录入!$I$5:$I$4999,$S15)&"")<>"",INDEX(数据录入!$I$5:$I$4999,$S15)&"",INDEX(数据录入!$J$5:$J$4999,$S15)&"")) | E15: =IF($S15="","",INDEX(数据录入!$E$5:$E$4999,$S15)&"") | F15: =IF($S15="","",N(INDEX(数据录入!$F$5:$F$4999,$S15))) | G15: =IF($S15="","",N(INDEX(数据录入!$G$5:$G$4999,$S15))) | H15: =IF($S15="","",$G$2+SUM($F$8:$F15)-SUM($G$8:$G15)) | J15: =IF($K15="","",8) | K15: =IFERROR(INDEX($U$8:$U$107,MATCH(8,$W$8:$W$107,0)),"") | L15: =IF($K15="","",(SUMIFS(数据录入!$F$5:$F$4999,$Q$5:$Q$4999,1,数据录入!$B$5:$B$4999,"<"&$B$2,数据录入!$I$5:$I$4999,$K15)+SUMIFS(数据录入!$F$5:$F$4999,$Q$5:$Q$4999,1,数据录入!$B$5:$B$4999,"<"&$B$2,数据录入!$J$5:$J$4999,$K15))-(SUMIFS(数据录入!$G$5:$G$4999,$Q$5:$Q$4999,1,数据录入!$B$5:$B$4999,"<"&$B$2,数据录入!$I$5:$I$4999,$K15)+SUMIFS(数据录入!$G$5:$G$4999,$Q$5:$Q$4999,1,数据录入!$B$5:$B$4999,"<"&$B$2,数据录入!$J$5:$J$4999,$K15))) | M15: =IF($K15="","",SUMIFS(数据录入!$F$5:$F$4999,$Q$5:$Q$4999,1,数据录入!$B$5:$B$4999,">="&$B$2,数据录入!$B$5:$B$4999,"<="&$D$2,数据录入!$I$5:$I$4999,$K15)+SUMIFS(数据录入!$F$5:$F$4999,$Q$5:$Q$4999,1,数据录入!$B$5:$B$4999,">="&$B$2,数据录入!$B$5:$B$4999,"<="&$D$2,数据录入!$J$5:$J$4999,$K15)) | N15: =IF($K15="","",SUMIFS(数据录入!$G$5:$G$4999,$Q$5:$Q$4999,1,数据录入!$B$5:$B$4999,">="&$B$2,数据录入!$B$5:$B$4999,"<="&$D$2,数据录入!$I$5:$I$4999,$K15)+SUMIFS(数据录入!$G$5:$G$4999,$Q$5:$Q$4999,1,数据录入!$B$5:$B$4999,">="&$B$2,数据录入!$B$5:$B$4999,"<="&$D$2,数据录入!$J$5:$J$4999,$K15)) | O15: =IF($K15="","",L15+M15-N15) | Q15: =IF(数据录入!$B15="",0,IF(OR(数据录入!$D15="投标保证金",数据录入!$D15="合同履约保证金",ISNUMBER(FIND("保证金",数据录入!$E15))),1,0)) | R15: =IF(AND($Q15=1,数据录入!$B15>=$B$2,数据录入!$B15<=$D$2),N(R14)+1,N(R14)) | S15: =IFERROR(MATCH(8,$R$5:$R$4999,0),"") | U15: =IFERROR(IF(8<=50,INDEX(基础资料!$E$2:$E$51,8)&"",INDEX(基础资料!$G$2:$G$51,8-50)&""),"") | V15: =IF($U15="",0,IF(AND(8>50,COUNTIF(基础资料!$E$2:$E$51,$U15)>0),0,1)) | W15: =IF($V15=1,N(W14)+1,N(W14))
A16: =IF($S16="","",INDEX(数据录入!$B$5:$B$4999,$S16)) | B16: =IF($S16="","",INDEX(数据录入!$C$5:$C$4999,$S16)&"") | C16: =IF($S16="","",IF(N($F16)>0,"收款",IF(N($G16)>0,"付款",""))) | D16: =IF($S16="","",IF((INDEX(数据录入!$I$5:$I$4999,$S16)&"")<>"",INDEX(数据录入!$I$5:$I$4999,$S16)&"",INDEX(数据录入!$J$5:$J$4999,$S16)&"")) | E16: =IF($S16="","",INDEX(数据录入!$E$5:$E$4999,$S16)&"") | F16: =IF($S16="","",N(INDEX(数据录入!$F$5:$F$4999,$S16))) | G16: =IF($S16="","",N(INDEX(数据录入!$G$5:$G$4999,$S16))) | H16: =IF($S16="","",$G$2+SUM($F$8:$F16)-SUM($G$8:$G16)) | J16: =IF($K16="","",9) | K16: =IFERROR(INDEX($U$8:$U$107,MATCH(9,$W$8:$W$107,0)),"") | L16: =IF($K16="","",(SUMIFS(数据录入!$F$5:$F$4999,$Q$5:$Q$4999,1,数据录入!$B$5:$B$4999,"<"&$B$2,数据录入!$I$5:$I$4999,$K16)+SUMIFS(数据录入!$F$5:$F$4999,$Q$5:$Q$4999,1,数据录入!$B$5:$B$4999,"<"&$B$2,数据录入!$J$5:$J$4999,$K16))-(SUMIFS(数据录入!$G$5:$G$4999,$Q$5:$Q$4999,1,数据录入!$B$5:$B$4999,"<"&$B$2,数据录入!$I$5:$I$4999,$K16)+SUMIFS(数据录入!$G$5:$G$4999,$Q$5:$Q$4999,1,数据录入!$B$5:$B$4999,"<"&$B$2,数据录入!$J$5:$J$4999,$K16))) | M16: =IF($K16="","",SUMIFS(数据录入!$F$5:$F$4999,$Q$5:$Q$4999,1,数据录入!$B$5:$B$4999,">="&$B$2,数据录入!$B$5:$B$4999,"<="&$D$2,数据录入!$I$5:$I$4999,$K16)+SUMIFS(数据录入!$F$5:$F$4999,$Q$5:$Q$4999,1,数据录入!$B$5:$B$4999,">="&$B$2,数据录入!$B$5:$B$4999,"<="&$D$2,数据录入!$J$5:$J$4999,$K16)) | N16: =IF($K16="","",SUMIFS(数据录入!$G$5:$G$4999,$Q$5:$Q$4999,1,数据录入!$B$5:$B$4999,">="&$B$2,数据录入!$B$5:$B$4999,"<="&$D$2,数据录入!$I$5:$I$4999,$K16)+SUMIFS(数据录入!$G$5:$G$4999,$Q$5:$Q$4999,1,数据录入!$B$5:$B$4999,">="&$B$2,数据录入!$B$5:$B$4999,"<="&$D$2,数据录入!$J$5:$J$4999,$K16)) | O16: =IF($K16="","",L16+M16-N16) | Q16: =IF(数据录入!$B16="",0,IF(OR(数据录入!$D16="投标保证金",数据录入!$D16="合同履约保证金",ISNUMBER(FIND("保证金",数据录入!$E16))),1,0)) | R16: =IF(AND($Q16=1,数据录入!$B16>=$B$2,数据录入!$B16<=$D$2),N(R15)+1,N(R15)) | S16: =IFERROR(MATCH(9,$R$5:$R$4999,0),"") | U16: =IFERROR(IF(9<=50,INDEX(基础资料!$E$2:$E$51,9)&"",INDEX(基础资料!$G$2:$G$51,9-50)&""),"") | V16: =IF($U16="",0,IF(AND(9>50,COUNTIF(基础资料!$E$2:$E$51,$U16)>0),0,1)) | W16: =IF($V16=1,N(W15)+1,N(W15))
A17: =IF($S17="","",INDEX(数据录入!$B$5:$B$4999,$S17)) | B17: =IF($S17="","",INDEX(数据录入!$C$5:$C$4999,$S17)&"") | C17: =IF($S17="","",IF(N($F17)>0,"收款",IF(N($G17)>0,"付款",""))) | D17: =IF($S17="","",IF((INDEX(数据录入!$I$5:$I$4999,$S17)&"")<>"",INDEX(数据录入!$I$5:$I$4999,$S17)&"",INDEX(数据录入!$J$5:$J$4999,$S17)&"")) | E17: =IF($S17="","",INDEX(数据录入!$E$5:$E$4999,$S17)&"") | F17: =IF($S17="","",N(INDEX(数据录入!$F$5:$F$4999,$S17))) | G17: =IF($S17="","",N(INDEX(数据录入!$G$5:$G$4999,$S17))) | H17: =IF($S17="","",$G$2+SUM($F$8:$F17)-SUM($G$8:$G17)) | J17: =IF($K17="","",10) | K17: =IFERROR(INDEX($U$8:$U$107,MATCH(10,$W$8:$W$107,0)),"") | L17: =IF($K17="","",(SUMIFS(数据录入!$F$5:$F$4999,$Q$5:$Q$4999,1,数据录入!$B$5:$B$4999,"<"&$B$2,数据录入!$I$5:$I$4999,$K17)+SUMIFS(数据录入!$F$5:$F$4999,$Q$5:$Q$4999,1,数据录入!$B$5:$B$4999,"<"&$B$2,数据录入!$J$5:$J$4999,$K17))-(SUMIFS(数据录入!$G$5:$G$4999,$Q$5:$Q$4999,1,数据录入!$B$5:$B$4999,"<"&$B$2,数据录入!$I$5:$I$4999,$K17)+SUMIFS(数据录入!$G$5:$G$4999,$Q$5:$Q$4999,1,数据录入!$B$5:$B$4999,"<"&$B$2,数据录入!$J$5:$J$4999,$K17))) | M17: =IF($K17="","",SUMIFS(数据录入!$F$5:$F$4999,$Q$5:$Q$4999,1,数据录入!$B$5:$B$4999,">="&$B$2,数据录入!$B$5:$B$4999,"<="&$D$2,数据录入!$I$5:$I$4999,$K17)+SUMIFS(数据录入!$F$5:$F$4999,$Q$5:$Q$4999,1,数据录入!$B$5:$B$4999,">="&$B$2,数据录入!$B$5:$B$4999,"<="&$D$2,数据录入!$J$5:$J$4999,$K17)) | N17: =IF($K17="","",SUMIFS(数据录入!$G$5:$G$4999,$Q$5:$Q$4999,1,数据录入!$B$5:$B$4999,">="&$B$2,数据录入!$B$5:$B$4999,"<="&$D$2,数据录入!$I$5:$I$4999,$K17)+SUMIFS(数据录入!$G$5:$G$4999,$Q$5:$Q$4999,1,数据录入!$B$5:$B$4999,">="&$B$2,数据录入!$B$5:$B$4999,"<="&$D$2,数据录入!$J$5:$J$4999,$K17)) | O17: =IF($K17="","",L17+M17-N17) | Q17: =IF(数据录入!$B17="",0,IF(OR(数据录入!$D17="投标保证金",数据录入!$D17="合同履约保证金",ISNUMBER(FIND("保证金",数据录入!$E17))),1,0)) | R17: =IF(AND($Q17=1,数据录入!$B17>=$B$2,数据录入!$B17<=$D$2),N(R16)+1,N(R16)) | S17: =IFERROR(MATCH(10,$R$5:$R$4999,0),"") | U17: =IFERROR(IF(10<=50,INDEX(基础资料!$E$2:$E$51,10)&"",INDEX(基础资料!$G$2:$G$51,10-50)&""),"") | V17: =IF($U17="",0,IF(AND(10>50,COUNTIF(基础资料!$E$2:$E$51,$U17)>0),0,1)) | W17: =IF($V17=1,N(W16)+1,N(W16))
A18: =IF($S18="","",INDEX(数据录入!$B$5:$B$4999,$S18)) | B18: =IF($S18="","",INDEX(数据录入!$C$5:$C$4999,$S18)&"") | C18: =IF($S18="","",IF(N($F18)>0,"收款",IF(N($G18)>0,"付款",""))) | D18: =IF($S18="","",IF((INDEX(数据录入!$I$5:$I$4999,$S18)&"")<>"",INDEX(数据录入!$I$5:$I$4999,$S18)&"",INDEX(数据录入!$J$5:$J$4999,$S18)&"")) | E18: =IF($S18="","",INDEX(数据录入!$E$5:$E$4999,$S18)&"") | F18: =IF($S18="","",N(INDEX(数据录入!$F$5:$F$4999,$S18))) | G18: =IF($S18="","",N(INDEX(数据录入!$G$5:$G$4999,$S18))) | H18: =IF($S18="","",$G$2+SUM($F$8:$F18)-SUM($G$8:$G18)) | J18: =IF($K18="","",11) | K18: =IFERROR(INDEX($U$8:$U$107,MATCH(11,$W$8:$W$107,0)),"") | L18: =IF($K18="","",(SUMIFS(数据录入!$F$5:$F$4999,$Q$5:$Q$4999,1,数据录入!$B$5:$B$4999,"<"&$B$2,数据录入!$I$5:$I$4999,$K18)+SUMIFS(数据录入!$F$5:$F$4999,$Q$5:$Q$4999,1,数据录入!$B$5:$B$4999,"<"&$B$2,数据录入!$J$5:$J$4999,$K18))-(SUMIFS(数据录入!$G$5:$G$4999,$Q$5:$Q$4999,1,数据录入!$B$5:$B$4999,"<"&$B$2,数据录入!$I$5:$I$4999,$K18)+SUMIFS(数据录入!$G$5:$G$4999,$Q$5:$Q$4999,1,数据录入!$B$5:$B$4999,"<"&$B$2,数据录入!$J$5:$J$4999,$K18))) | M18: =IF($K18="","",SUMIFS(数据录入!$F$5:$F$4999,$Q$5:$Q$4999,1,数据录入!$B$5:$B$4999,">="&$B$2,数据录入!$B$5:$B$4999,"<="&$D$2,数据录入!$I$5:$I$4999,$K18)+SUMIFS(数据录入!$F$5:$F$4999,$Q$5:$Q$4999,1,数据录入!$B$5:$B$4999,">="&$B$2,数据录入!$B$5:$B$4999,"<="&$D$2,数据录入!$J$5:$J$4999,$K18)) | N18: =IF($K18="","",SUMIFS(数据录入!$G$5:$G$4999,$Q$5:$Q$4999,1,数据录入!$B$5:$B$4999,">="&$B$2,数据录入!$B$5:$B$4999,"<="&$D$2,数据录入!$I$5:$I$4999,$K18)+SUMIFS(数据录入!$G$5:$G$4999,$Q$5:$Q$4999,1,数据录入!$B$5:$B$4999,">="&$B$2,数据录入!$B$5:$B$4999,"<="&$D$2,数据录入!$J$5:$J$4999,$K18)) | O18: =IF($K18="","",L18+M18-N18) | Q18: =IF(数据录入!$B18="",0,IF(OR(数据录入!$D18="投标保证金",数据录入!$D18="合同履约保证金",ISNUMBER(FIND("保证金",数据录入!$E18))),1,0)) | R18: =IF(AND($Q18=1,数据录入!$B18>=$B$2,数据录入!$B18<=$D$2),N(R17)+1,N(R17)) | S18: =IFERROR(MATCH(11,$R$5:$R$4999,0),"") | U18: =IFERROR(IF(11<=50,INDEX(基础资料!$E$2:$E$51,11)&"",INDEX(基础资料!$G$2:$G$51,11-50)&""),"") | V18: =IF($U18="",0,IF(AND(11>50,COUNTIF(基础资料!$E$2:$E$51,$U18)>0),0,1)) | W18: =IF($V18=1,N(W17)+1,N(W17))
A19: =IF($S19="","",INDEX(数据录入!$B$5:$B$4999,$S19)) | B19: =IF($S19="","",INDEX(数据录入!$C$5:$C$4999,$S19)&"") | C19: =IF($S19="","",IF(N($F19)>0,"收款",IF(N($G19)>0,"付款",""))) | D19: =IF($S19="","",IF((INDEX(数据录入!$I$5:$I$4999,$S19)&"")<>"",INDEX(数据录入!$I$5:$I$4999,$S19)&"",INDEX(数据录入!$J$5:$J$4999,$S19)&"")) | E19: =IF($S19="","",INDEX(数据录入!$E$5:$E$4999,$S19)&"") | F19: =IF($S19="","",N(INDEX(数据录入!$F$5:$F$4999,$S19))) | G19: =IF($S19="","",N(INDEX(数据录入!$G$5:$G$4999,$S19))) | H19: =IF($S19="","",$G$2+SUM($F$8:$F19)-SUM($G$8:$G19)) | J19: =IF($K19="","",12) | K19: =IFERROR(INDEX($U$8:$U$107,MATCH(12,$W$8:$W$107,0)),"") | L19: =IF($K19="","",(SUMIFS(数据录入!$F$5:$F$4999,$Q$5:$Q$4999,1,数据录入!$B$5:$B$4999,"<"&$B$2,数据录入!$I$5:$I$4999,$K19)+SUMIFS(数据录入!$F$5:$F$4999,$Q$5:$Q$4999,1,数据录入!$B$5:$B$4999,"<"&$B$2,数据录入!$J$5:$J$4999,$K19))-(SUMIFS(数据录入!$G$5:$G$4999,$Q$5:$Q$4999,1,数据录入!$B$5:$B$4999,"<"&$B$2,数据录入!$I$5:$I$4999,$K19)+SUMIFS(数据录入!$G$5:$G$4999,$Q$5:$Q$4999,1,数据录入!$B$5:$B$4999,"<"&$B$2,数据录入!$J$5:$J$4999,$K19))) | M19: =IF($K19="","",SUMIFS(数据录入!$F$5:$F$4999,$Q$5:$Q$4999,1,数据录入!$B$5:$B$4999,">="&$B$2,数据录入!$B$5:$B$4999,"<="&$D$2,数据录入!$I$5:$I$4999,$K19)+SUMIFS(数据录入!$F$5:$F$4999,$Q$5:$Q$4999,1,数据录入!$B$5:$B$4999,">="&$B$2,数据录入!$B$5:$B$4999,"<="&$D$2,数据录入!$J$5:$J$4999,$K19)) | N19: =IF($K19="","",SUMIFS(数据录入!$G$5:$G$4999,$Q$5:$Q$4999,1,数据录入!$B$5:$B$4999,">="&$B$2,数据录入!$B$5:$B$4999,"<="&$D$2,数据录入!$I$5:$I$4999,$K19)+SUMIFS(数据录入!$G$5:$G$4999,$Q$5:$Q$4999,1,数据录入!$B$5:$B$4999,">="&$B$2,数据录入!$B$5:$B$4999,"<="&$D$2,数据录入!$J$5:$J$4999,$K19)) | O19: =IF($K19="","",L19+M19-N19) | Q19: =IF(数据录入!$B19="",0,IF(OR(数据录入!$D19="投标保证金",数据录入!$D19="合同履约保证金",ISNUMBER(FIND("保证金",数据录入!$E19))),1,0)) | R19: =IF(AND($Q19=1,数据录入!$B19>=$B$2,数据录入!$B19<=$D$2),N(R18)+1,N(R18)) | S19: =IFERROR(MATCH(12,$R$5:$R$4999,0),"") | U19: =IFERROR(IF(12<=50,INDEX(基础资料!$E$2:$E$51,12)&"",INDEX(基础资料!$G$2:$G$51,12-50)&""),"") | V19: =IF($U19="",0,IF(AND(12>50,COUNTIF(基础资料!$E$2:$E$51,$U19)>0),0,1)) | W19: =IF($V19=1,N(W18)+1,N(W18))
A20: =IF($S20="","",INDEX(数据录入!$B$5:$B$4999,$S20)) | B20: =IF($S20="","",INDEX(数据录入!$C$5:$C$4999,$S20)&"") | C20: =IF($S20="","",IF(N($F20)>0,"收款",IF(N($G20)>0,"付款",""))) | D20: =IF($S20="","",IF((INDEX(数据录入!$I$5:$I$4999,$S20)&"")<>"",INDEX(数据录入!$I$5:$I$4999,$S20)&"",INDEX(数据录入!$J$5:$J$4999,$S20)&"")) | E20: =IF($S20="","",INDEX(数据录入!$E$5:$E$4999,$S20)&"") | F20: =IF($S20="","",N(INDEX(数据录入!$F$5:$F$4999,$S20))) | G20: =IF($S20="","",N(INDEX(数据录入!$G$5:$G$4999,$S20))) | H20: =IF($S20="","",$G$2+SUM($F$8:$F20)-SUM($G$8:$G20)) | J20: =IF($K20="","",13) | K20: =IFERROR(INDEX($U$8:$U$107,MATCH(13,$W$8:$W$107,0)),"") | L20: =IF($K20="","",(SUMIFS(数据录入!$F$5:$F$4999,$Q$5:$Q$4999,1,数据录入!$B$5:$B$4999,"<"&$B$2,数据录入!$I$5:$I$4999,$K20)+SUMIFS(数据录入!$F$5:$F$4999,$Q$5:$Q$4999,1,数据录入!$B$5:$B$4999,"<"&$B$2,数据录入!$J$5:$J$4999,$K20))-(SUMIFS(数据录入!$G$5:$G$4999,$Q$5:$Q$4999,1,数据录入!$B$5:$B$4999,"<"&$B$2,数据录入!$I$5:$I$4999,$K20)+SUMIFS(数据录入!$G$5:$G$4999,$Q$5:$Q$4999,1,数据录入!$B$5:$B$4999,"<"&$B$2,数据录入!$J$5:$J$4999,$K20))) | M20: =IF($K20="","",SUMIFS(数据录入!$F$5:$F$4999,$Q$5:$Q$4999,1,数据录入!$B$5:$B$4999,">="&$B$2,数据录入!$B$5:$B$4999,"<="&$D$2,数据录入!$I$5:$I$4999,$K20)+SUMIFS(数据录入!$F$5:$F$4999,$Q$5:$Q$4999,1,数据录入!$B$5:$B$4999,">="&$B$2,数据录入!$B$5:$B$4999,"<="&$D$2,数据录入!$J$5:$J$4999,$K20)) | N20: =IF($K20="","",SUMIFS(数据录入!$G$5:$G$4999,$Q$5:$Q$4999,1,数据录入!$B$5:$B$4999,">="&$B$2,数据录入!$B$5:$B$4999,"<="&$D$2,数据录入!$I$5:$I$4999,$K20)+SUMIFS(数据录入!$G$5:$G$4999,$Q$5:$Q$4999,1,数据录入!$B$5:$B$4999,">="&$B$2,数据录入!$B$5:$B$4999,"<="&$D$2,数据录入!$J$5:$J$4999,$K20)) | O20: =IF($K20="","",L20+M20-N20) | Q20: =IF(数据录入!$B20="",0,IF(OR(数据录入!$D20="投标保证金",数据录入!$D20="合同履约保证金",ISNUMBER(FIND("保证金",数据录入!$E20))),1,0)) | R20: =IF(AND($Q20=1,数据录入!$B20>=$B$2,数据录入!$B20<=$D$2),N(R19)+1,N(R19)) | S20: =IFERROR(MATCH(13,$R$5:$R$4999,0),"") | U20: =IFERROR(IF(13<=50,INDEX(基础资料!$E$2:$E$51,13)&"",INDEX(基础资料!$G$2:$G$51,13-50)&""),"") | V20: =IF($U20="",0,IF(AND(13>50,COUNTIF(基础资料!$E$2:$E$51,$U20)>0),0,1)) | W20: =IF($V20=1,N(W19)+1,N(W19))
A21: =IF($S21="","",INDEX(数据录入!$B$5:$B$4999,$S21)) | B21: =IF($S21="","",INDEX(数据录入!$C$5:$C$4999,$S21)&"") | C21: =IF($S21="","",IF(N($F21)>0,"收款",IF(N($G21)>0,"付款",""))) | D21: =IF($S21="","",IF((INDEX(数据录入!$I$5:$I$4999,$S21)&"")<>"",INDEX(数据录入!$I$5:$I$4999,$S21)&"",INDEX(数据录入!$J$5:$J$4999,$S21)&"")) | E21: =IF($S21="","",INDEX(数据录入!$E$5:$E$4999,$S21)&"") | F21: =IF($S21="","",N(INDEX(数据录入!$F$5:$F$4999,$S21))) | G21: =IF($S21="","",N(INDEX(数据录入!$G$5:$G$4999,$S21))) | H21: =IF($S21="","",$G$2+SUM($F$8:$F21)-SUM($G$8:$G21)) | J21: =IF($K21="","",14) | K21: =IFERROR(INDEX($U$8:$U$107,MATCH(14,$W$8:$W$107,0)),"") | L21: =IF($K21="","",(SUMIFS(数据录入!$F$5:$F$4999,$Q$5:$Q$4999,1,数据录入!$B$5:$B$4999,"<"&$B$2,数据录入!$I$5:$I$4999,$K21)+SUMIFS(数据录入!$F$5:$F$4999,$Q$5:$Q$4999,1,数据录入!$B$5:$B$4999,"<"&$B$2,数据录入!$J$5:$J$4999,$K21))-(SUMIFS(数据录入!$G$5:$G$4999,$Q$5:$Q$4999,1,数据录入!$B$5:$B$4999,"<"&$B$2,数据录入!$I$5:$I$4999,$K21)+SUMIFS(数据录入!$G$5:$G$4999,$Q$5:$Q$4999,1,数据录入!$B$5:$B$4999,"<"&$B$2,数据录入!$J$5:$J$4999,$K21))) | M21: =IF($K21="","",SUMIFS(数据录入!$F$5:$F$4999,$Q$5:$Q$4999,1,数据录入!$B$5:$B$4999,">="&$B$2,数据录入!$B$5:$B$4999,"<="&$D$2,数据录入!$I$5:$I$4999,$K21)+SUMIFS(数据录入!$F$5:$F$4999,$Q$5:$Q$4999,1,数据录入!$B$5:$B$4999,">="&$B$2,数据录入!$B$5:$B$4999,"<="&$D$2,数据录入!$J$5:$J$4999,$K21)) | N21: =IF($K21="","",SUMIFS(数据录入!$G$5:$G$4999,$Q$5:$Q$4999,1,数据录入!$B$5:$B$4999,">="&$B$2,数据录入!$B$5:$B$4999,"<="&$D$2,数据录入!$I$5:$I$4999,$K21)+SUMIFS(数据录入!$G$5:$G$4999,$Q$5:$Q$4999,1,数据录入!$B$5:$B$4999,">="&$B$2,数据录入!$B$5:$B$4999,"<="&$D$2,数据录入!$J$5:$J$4999,$K21)) | O21: =IF($K21="","",L21+M21-N21) | Q21: =IF(数据录入!$B21="",0,IF(OR(数据录入!$D21="投标保证金",数据录入!$D21="合同履约保证金",ISNUMBER(FIND("保证金",数据录入!$E21))),1,0)) | R21: =IF(AND($Q21=1,数据录入!$B21>=$B$2,数据录入!$B21<=$D$2),N(R20)+1,N(R20)) | S21: =IFERROR(MATCH(14,$R$5:$R$4999,0),"") | U21: =IFERROR(IF(14<=50,INDEX(基础资料!$E$2:$E$51,14)&"",INDEX(基础资料!$G$2:$G$51,14-50)&""),"") | V21: =IF($U21="",0,IF(AND(14>50,COUNTIF(基础资料!$E$2:$E$51,$U21)>0),0,1)) | W21: =IF($V21=1,N(W20)+1,N(W20))
A22: =IF($S22="","",INDEX(数据录入!$B$5:$B$4999,$S22)) | B22: =IF($S22="","",INDEX(数据录入!$C$5:$C$4999,$S22)&"") | C22: =IF($S22="","",IF(N($F22)>0,"收款",IF(N($G22)>0,"付款",""))) | D22: =IF($S22="","",IF((INDEX(数据录入!$I$5:$I$4999,$S22)&"")<>"",INDEX(数据录入!$I$5:$I$4999,$S22)&"",INDEX(数据录入!$J$5:$J$4999,$S22)&"")) | E22: =IF($S22="","",INDEX(数据录入!$E$5:$E$4999,$S22)&"") | F22: =IF($S22="","",N(INDEX(数据录入!$F$5:$F$4999,$S22))) | G22: =IF($S22="","",N(INDEX(数据录入!$G$5:$G$4999,$S22))) | H22: =IF($S22="","",$G$2+SUM($F$8:$F22)-SUM($G$8:$G22)) | J22: =IF($K22="","",15) | K22: =IFERROR(INDEX($U$8:$U$107,MATCH(15,$W$8:$W$107,0)),"") | L22: =IF($K22="","",(SUMIFS(数据录入!$F$5:$F$4999,$Q$5:$Q$4999,1,数据录入!$B$5:$B$4999,"<"&$B$2,数据录入!$I$5:$I$4999,$K22)+SUMIFS(数据录入!$F$5:$F$4999,$Q$5:$Q$4999,1,数据录入!$B$5:$B$4999,"<"&$B$2,数据录入!$J$5:$J$4999,$K22))-(SUMIFS(数据录入!$G$5:$G$4999,$Q$5:$Q$4999,1,数据录入!$B$5:$B$4999,"<"&$B$2,数据录入!$I$5:$I$4999,$K22)+SUMIFS(数据录入!$G$5:$G$4999,$Q$5:$Q$4999,1,数据录入!$B$5:$B$4999,"<"&$B$2,数据录入!$J$5:$J$4999,$K22))) | M22: =IF($K22="","",SUMIFS(数据录入!$F$5:$F$4999,$Q$5:$Q$4999,1,数据录入!$B$5:$B$4999,">="&$B$2,数据录入!$B$5:$B$4999,"<="&$D$2,数据录入!$I$5:$I$4999,$K22)+SUMIFS(数据录入!$F$5:$F$4999,$Q$5:$Q$4999,1,数据录入!$B$5:$B$4999,">="&$B$2,数据录入!$B$5:$B$4999,"<="&$D$2,数据录入!$J$5:$J$4999,$K22)) | N22: =IF($K22="","",SUMIFS(数据录入!$G$5:$G$4999,$Q$5:$Q$4999,1,数据录入!$B$5:$B$4999,">="&$B$2,数据录入!$B$5:$B$4999,"<="&$D$2,数据录入!$I$5:$I$4999,$K22)+SUMIFS(数据录入!$G$5:$G$4999,$Q$5:$Q$4999,1,数据录入!$B$5:$B$4999,">="&$B$2,数据录入!$B$5:$B$4999,"<="&$D$2,数据录入!$J$5:$J$4999,$K22)) | O22: =IF($K22="","",L22+M22-N22) | Q22: =IF(数据录入!$B22="",0,IF(OR(数据录入!$D22="投标保证金",数据录入!$D22="合同履约保证金",ISNUMBER(FIND("保证金",数据录入!$E22))),1,0)) | R22: =IF(AND($Q22=1,数据录入!$B22>=$B$2,数据录入!$B22<=$D$2),N(R21)+1,N(R21)) | S22: =IFERROR(MATCH(15,$R$5:$R$4999,0),"") | U22: =IFERROR(IF(15<=50,INDEX(基础资料!$E$2:$E$51,15)&"",INDEX(基础资料!$G$2:$G$51,15-50)&""),"") | V22: =IF($U22="",0,IF(AND(15>50,COUNTIF(基础资料!$E$2:$E$51,$U22)>0),0,1)) | W22: =IF($V22=1,N(W21)+1,N(W21))
A23: =IF($S23="","",INDEX(数据录入!$B$5:$B$4999,$S23)) | B23: =IF($S23="","",INDEX(数据录入!$C$5:$C$4999,$S23)&"") | C23: =IF($S23="","",IF(N($F23)>0,"收款",IF(N($G23)>0,"付款",""))) | D23: =IF($S23="","",IF((INDEX(数据录入!$I$5:$I$4999,$S23)&"")<>"",INDEX(数据录入!$I$5:$I$4999,$S23)&"",INDEX(数据录入!$J$5:$J$4999,$S23)&"")) | E23: =IF($S23="","",INDEX(数据录入!$E$5:$E$4999,$S23)&"") | F23: =IF($S23="","",N(INDEX(数据录入!$F$5:$F$4999,$S23))) | G23: =IF($S23="","",N(INDEX(数据录入!$G$5:$G$4999,$S23))) | H23: =IF($S23="","",$G$2+SUM($F$8:$F23)-SUM($G$8:$G23)) | J23: =IF($K23="","",16) | K23: =IFERROR(INDEX($U$8:$U$107,MATCH(16,$W$8:$W$107,0)),"") | L23: =IF($K23="","",(SUMIFS(数据录入!$F$5:$F$4999,$Q$5:$Q$4999,1,数据录入!$B$5:$B$4999,"<"&$B$2,数据录入!$I$5:$I$4999,$K23)+SUMIFS(数据录入!$F$5:$F$4999,$Q$5:$Q$4999,1,数据录入!$B$5:$B$4999,"<"&$B$2,数据录入!$J$5:$J$4999,$K23))-(SUMIFS(数据录入!$G$5:$G$4999,$Q$5:$Q$4999,1,数据录入!$B$5:$B$4999,"<"&$B$2,数据录入!$I$5:$I$4999,$K23)+SUMIFS(数据录入!$G$5:$G$4999,$Q$5:$Q$4999,1,数据录入!$B$5:$B$4999,"<"&$B$2,数据录入!$J$5:$J$4999,$K23))) | M23: =IF($K23="","",SUMIFS(数据录入!$F$5:$F$4999,$Q$5:$Q$4999,1,数据录入!$B$5:$B$4999,">="&$B$2,数据录入!$B$5:$B$4999,"<="&$D$2,数据录入!$I$5:$I$4999,$K23)+SUMIFS(数据录入!$F$5:$F$4999,$Q$5:$Q$4999,1,数据录入!$B$5:$B$4999,">="&$B$2,数据录入!$B$5:$B$4999,"<="&$D$2,数据录入!$J$5:$J$4999,$K23)) | N23: =IF($K23="","",SUMIFS(数据录入!$G$5:$G$4999,$Q$5:$Q$4999,1,数据录入!$B$5:$B$4999,">="&$B$2,数据录入!$B$5:$B$4999,"<="&$D$2,数据录入!$I$5:$I$4999,$K23)+SUMIFS(数据录入!$G$5:$G$4999,$Q$5:$Q$4999,1,数据录入!$B$5:$B$4999,">="&$B$2,数据录入!$B$5:$B$4999,"<="&$D$2,数据录入!$J$5:$J$4999,$K23)) | O23: =IF($K23="","",L23+M23-N23) | Q23: =IF(数据录入!$B23="",0,IF(OR(数据录入!$D23="投标保证金",数据录入!$D23="合同履约保证金",ISNUMBER(FIND("保证金",数据录入!$E23))),1,0)) | R23: =IF(AND($Q23=1,数据录入!$B23>=$B$2,数据录入!$B23<=$D$2),N(R22)+1,N(R22)) | S23: =IFERROR(MATCH(16,$R$5:$R$4999,0),"") | U23: =IFERROR(IF(16<=50,INDEX(基础资料!$E$2:$E$51,16)&"",INDEX(基础资料!$G$2:$G$51,16-50)&""),"") | V23: =IF($U23="",0,IF(AND(16>50,COUNTIF(基础资料!$E$2:$E$51,$U23)>0),0,1)) | W23: =IF($V23=1,N(W22)+1,N(W22))
A24: =IF($S24="","",INDEX(数据录入!$B$5:$B$4999,$S24)) | B24: =IF($S24="","",INDEX(数据录入!$C$5:$C$4999,$S24)&"") | C24: =IF($S24="","",IF(N($F24)>0,"收款",IF(N($G24)>0,"付款",""))) | D24: =IF($S24="","",IF((INDEX(数据录入!$I$5:$I$4999,$S24)&"")<>"",INDEX(数据录入!$I$5:$I$4999,$S24)&"",INDEX(数据录入!$J$5:$J$4999,$S24)&"")) | E24: =IF($S24="","",INDEX(数据录入!$E$5:$E$4999,$S24)&"") | F24: =IF($S24="","",N(INDEX(数据录入!$F$5:$F$4999,$S24))) | G24: =IF($S24="","",N(INDEX(数据录入!$G$5:$G$4999,$S24))) | H24: =IF($S24="","",$G$2+SUM($F$8:$F24)-SUM($G$8:$G24)) | J24: =IF($K24="","",17) | K24: =IFERROR(INDEX($U$8:$U$107,MATCH(17,$W$8:$W$107,0)),"") | L24: =IF($K24="","",(SUMIFS(数据录入!$F$5:$F$4999,$Q$5:$Q$4999,1,数据录入!$B$5:$B$4999,"<"&$B$2,数据录入!$I$5:$I$4999,$K24)+SUMIFS(数据录入!$F$5:$F$4999,$Q$5:$Q$4999,1,数据录入!$B$5:$B$4999,"<"&$B$2,数据录入!$J$5:$J$4999,$K24))-(SUMIFS(数据录入!$G$5:$G$4999,$Q$5:$Q$4999,1,数据录入!$B$5:$B$4999,"<"&$B$2,数据录入!$I$5:$I$4999,$K24)+SUMIFS(数据录入!$G$5:$G$4999,$Q$5:$Q$4999,1,数据录入!$B$5:$B$4999,"<"&$B$2,数据录入!$J$5:$J$4999,$K24))) | M24: =IF($K24="","",SUMIFS(数据录入!$F$5:$F$4999,$Q$5:$Q$4999,1,数据录入!$B$5:$B$4999,">="&$B$2,数据录入!$B$5:$B$4999,"<="&$D$2,数据录入!$I$5:$I$4999,$K24)+SUMIFS(数据录入!$F$5:$F$4999,$Q$5:$Q$4999,1,数据录入!$B$5:$B$4999,">="&$B$2,数据录入!$B$5:$B$4999,"<="&$D$2,数据录入!$J$5:$J$4999,$K24)) | N24: =IF($K24="","",SUMIFS(数据录入!$G$5:$G$4999,$Q$5:$Q$4999,1,数据录入!$B$5:$B$4999,">="&$B$2,数据录入!$B$5:$B$4999,"<="&$D$2,数据录入!$I$5:$I$4999,$K24)+SUMIFS(数据录入!$G$5:$G$4999,$Q$5:$Q$4999,1,数据录入!$B$5:$B$4999,">="&$B$2,数据录入!$B$5:$B$4999,"<="&$D$2,数据录入!$J$5:$J$4999,$K24)) | O24: =IF($K24="","",L24+M24-N24) | Q24: =IF(数据录入!$B24="",0,IF(OR(数据录入!$D24="投标保证金",数据录入!$D24="合同履约保证金",ISNUMBER(FIND("保证金",数据录入!$E24))),1,0)) | R24: =IF(AND($Q24=1,数据录入!$B24>=$B$2,数据录入!$B24<=$D$2),N(R23)+1,N(R23)) | S24: =IFERROR(MATCH(17,$R$5:$R$4999,0),"") | U24: =IFERROR(IF(17<=50,INDEX(基础资料!$E$2:$E$51,17)&"",INDEX(基础资料!$G$2:$G$51,17-50)&""),"") | V24: =IF($U24="",0,IF(AND(17>50,COUNTIF(基础资料!$E$2:$E$51,$U24)>0),0,1)) | W24: =IF($V24=1,N(W23)+1,N(W23))
A25: =IF($S25="","",INDEX(数据录入!$B$5:$B$4999,$S25)) | B25: =IF($S25="","",INDEX(数据录入!$C$5:$C$4999,$S25)&"") | C25: =IF($S25="","",IF(N($F25)>0,"收款",IF(N($G25)>0,"付款",""))) | D25: =IF($S25="","",IF((INDEX(数据录入!$I$5:$I$4999,$S25)&"")<>"",INDEX(数据录入!$I$5:$I$4999,$S25)&"",INDEX(数据录入!$J$5:$J$4999,$S25)&"")) | E25: =IF($S25="","",INDEX(数据录入!$E$5:$E$4999,$S25)&"") | F25: =IF($S25="","",N(INDEX(数据录入!$F$5:$F$4999,$S25))) | G25: =IF($S25="","",N(INDEX(数据录入!$G$5:$G$4999,$S25))) | H25: =IF($S25="","",$G$2+SUM($F$8:$F25)-SUM($G$8:$G25)) | J25: =IF($K25="","",18) | K25: =IFERROR(INDEX($U$8:$U$107,MATCH(18,$W$8:$W$107,0)),"") | L25: =IF($K25="","",(SUMIFS(数据录入!$F$5:$F$4999,$Q$5:$Q$4999,1,数据录入!$B$5:$B$4999,"<"&$B$2,数据录入!$I$5:$I$4999,$K25)+SUMIFS(数据录入!$F$5:$F$4999,$Q$5:$Q$4999,1,数据录入!$B$5:$B$4999,"<"&$B$2,数据录入!$J$5:$J$4999,$K25))-(SUMIFS(数据录入!$G$5:$G$4999,$Q$5:$Q$4999,1,数据录入!$B$5:$B$4999,"<"&$B$2,数据录入!$I$5:$I$4999,$K25)+SUMIFS(数据录入!$G$5:$G$4999,$Q$5:$Q$4999,1,数据录入!$B$5:$B$4999,"<"&$B$2,数据录入!$J$5:$J$4999,$K25))) | M25: =IF($K25="","",SUMIFS(数据录入!$F$5:$F$4999,$Q$5:$Q$4999,1,数据录入!$B$5:$B$4999,">="&$B$2,数据录入!$B$5:$B$4999,"<="&$D$2,数据录入!$I$5:$I$4999,$K25)+SUMIFS(数据录入!$F$5:$F$4999,$Q$5:$Q$4999,1,数据录入!$B$5:$B$4999,">="&$B$2,数据录入!$B$5:$B$4999,"<="&$D$2,数据录入!$J$5:$J$4999,$K25)) | N25: =IF($K25="","",SUMIFS(数据录入!$G$5:$G$4999,$Q$5:$Q$4999,1,数据录入!$B$5:$B$4999,">="&$B$2,数据录入!$B$5:$B$4999,"<="&$D$2,数据录入!$I$5:$I$4999,$K25)+SUMIFS(数据录入!$G$5:$G$4999,$Q$5:$Q$4999,1,数据录入!$B$5:$B$4999,">="&$B$2,数据录入!$B$5:$B$4999,"<="&$D$2,数据录入!$J$5:$J$4999,$K25)) | O25: =IF($K25="","",L25+M25-N25) | Q25: =IF(数据录入!$B25="",0,IF(OR(数据录入!$D25="投标保证金",数据录入!$D25="合同履约保证金",ISNUMBER(FIND("保证金",数据录入!$E25))),1,0)) | R25: =IF(AND($Q25=1,数据录入!$B25>=$B$2,数据录入!$B25<=$D$2),N(R24)+1,N(R24)) | S25: =IFERROR(MATCH(18,$R$5:$R$4999,0),"") | U25: =IFERROR(IF(18<=50,INDEX(基础资料!$E$2:$E$51,18)&"",INDEX(基础资料!$G$2:$G$51,18-50)&""),"") | V25: =IF($U25="",0,IF(AND(18>50,COUNTIF(基础资料!$E$2:$E$51,$U25)>0),0,1)) | W25: =IF($V25=1,N(W24)+1,N(W24))
A26: =IF($S26="","",INDEX(数据录入!$B$5:$B$4999,$S26)) | B26: =IF($S26="","",INDEX(数据录入!$C$5:$C$4999,$S26)&"") | C26: =IF($S26="","",IF(N($F26)>0,"收款",IF(N($G26)>0,"付款",""))) | D26: =IF($S26="","",IF((INDEX(数据录入!$I$5:$I$4999,$S26)&"")<>"",INDEX(数据录入!$I$5:$I$4999,$S26)&"",INDEX(数据录入!$J$5:$J$4999,$S26)&"")) | E26: =IF($S26="","",INDEX(数据录入!$E$5:$E$4999,$S26)&"") | F26: =IF($S26="","",N(INDEX(数据录入!$F$5:$F$4999,$S26))) | G26: =IF($S26="","",N(INDEX(数据录入!$G$5:$G$4999,$S26))) | H26: =IF($S26="","",$G$2+SUM($F$8:$F26)-SUM($G$8:$G26)) | J26: =IF($K26="","",19) | K26: =IFERROR(INDEX($U$8:$U$107,MATCH(19,$W$8:$W$107,0)),"") | L26: =IF($K26="","",(SUMIFS(数据录入!$F$5:$F$4999,$Q$5:$Q$4999,1,数据录入!$B$5:$B$4999,"<"&$B$2,数据录入!$I$5:$I$4999,$K26)+SUMIFS(数据录入!$F$5:$F$4999,$Q$5:$Q$4999,1,数据录入!$B$5:$B$4999,"<"&$B$2,数据录入!$J$5:$J$4999,$K26))-(SUMIFS(数据录入!$G$5:$G$4999,$Q$5:$Q$4999,1,数据录入!$B$5:$B$4999,"<"&$B$2,数据录入!$I$5:$I$4999,$K26)+SUMIFS(数据录入!$G$5:$G$4999,$Q$5:$Q$4999,1,数据录入!$B$5:$B$4999,"<"&$B$2,数据录入!$J$5:$J$4999,$K26))) | M26: =IF($K26="","",SUMIFS(数据录入!$F$5:$F$4999,$Q$5:$Q$4999,1,数据录入!$B$5:$B$4999,">="&$B$2,数据录入!$B$5:$B$4999,"<="&$D$2,数据录入!$I$5:$I$4999,$K26)+SUMIFS(数据录入!$F$5:$F$4999,$Q$5:$Q$4999,1,数据录入!$B$5:$B$4999,">="&$B$2,数据录入!$B$5:$B$4999,"<="&$D$2,数据录入!$J$5:$J$4999,$K26)) | N26: =IF($K26="","",SUMIFS(数据录入!$G$5:$G$4999,$Q$5:$Q$4999,1,数据录入!$B$5:$B$4999,">="&$B$2,数据录入!$B$5:$B$4999,"<="&$D$2,数据录入!$I$5:$I$4999,$K26)+SUMIFS(数据录入!$G$5:$G$4999,$Q$5:$Q$4999,1,数据录入!$B$5:$B$4999,">="&$B$2,数据录入!$B$5:$B$4999,"<="&$D$2,数据录入!$J$5:$J$4999,$K26)) | O26: =IF($K26="","",L26+M26-N26) | Q26: =IF(数据录入!$B26="",0,IF(OR(数据录入!$D26="投标保证金",数据录入!$D26="合同履约保证金",ISNUMBER(FIND("保证金",数据录入!$E26))),1,0)) | R26: =IF(AND($Q26=1,数据录入!$B26>=$B$2,数据录入!$B26<=$D$2),N(R25)+1,N(R25)) | S26: =IFERROR(MATCH(19,$R$5:$R$4999,0),"") | U26: =IFERROR(IF(19<=50,INDEX(基础资料!$E$2:$E$51,19)&"",INDEX(基础资料!$G$2:$G$51,19-50)&""),"") | V26: =IF($U26="",0,IF(AND(19>50,COUNTIF(基础资料!$E$2:$E$51,$U26)>0),0,1)) | W26: =IF($V26=1,N(W25)+1,N(W25))
A27: =IF($S27="","",INDEX(数据录入!$B$5:$B$4999,$S27)) | B27: =IF($S27="","",INDEX(数据录入!$C$5:$C$4999,$S27)&"") | C27: =IF($S27="","",IF(N($F27)>0,"收款",IF(N($G27)>0,"付款",""))) | D27: =IF($S27="","",IF((INDEX(数据录入!$I$5:$I$4999,$S27)&"")<>"",INDEX(数据录入!$I$5:$I$4999,$S27)&"",INDEX(数据录入!$J$5:$J$4999,$S27)&"")) | E27: =IF($S27="","",INDEX(数据录入!$E$5:$E$4999,$S27)&"") | F27: =IF($S27="","",N(INDEX(数据录入!$F$5:$F$4999,$S27))) | G27: =IF($S27="","",N(INDEX(数据录入!$G$5:$G$4999,$S27))) | H27: =IF($S27="","",$G$2+SUM($F$8:$F27)-SUM($G$8:$G27)) | J27: =IF($K27="","",20) | K27: =IFERROR(INDEX($U$8:$U$107,MATCH(20,$W$8:$W$107,0)),"") | L27: =IF($K27="","",(SUMIFS(数据录入!$F$5:$F$4999,$Q$5:$Q$4999,1,数据录入!$B$5:$B$4999,"<"&$B$2,数据录入!$I$5:$I$4999,$K27)+SUMIFS(数据录入!$F$5:$F$4999,$Q$5:$Q$4999,1,数据录入!$B$5:$B$4999,"<"&$B$2,数据录入!$J$5:$J$4999,$K27))-(SUMIFS(数据录入!$G$5:$G$4999,$Q$5:$Q$4999,1,数据录入!$B$5:$B$4999,"<"&$B$2,数据录入!$I$5:$I$4999,$K27)+SUMIFS(数据录入!$G$5:$G$4999,$Q$5:$Q$4999,1,数据录入!$B$5:$B$4999,"<"&$B$2,数据录入!$J$5:$J$4999,$K27))) | M27: =IF($K27="","",SUMIFS(数据录入!$F$5:$F$4999,$Q$5:$Q$4999,1,数据录入!$B$5:$B$4999,">="&$B$2,数据录入!$B$5:$B$4999,"<="&$D$2,数据录入!$I$5:$I$4999,$K27)+SUMIFS(数据录入!$F$5:$F$4999,$Q$5:$Q$4999,1,数据录入!$B$5:$B$4999,">="&$B$2,数据录入!$B$5:$B$4999,"<="&$D$2,数据录入!$J$5:$J$4999,$K27)) | N27: =IF($K27="","",SUMIFS(数据录入!$G$5:$G$4999,$Q$5:$Q$4999,1,数据录入!$B$5:$B$4999,">="&$B$2,数据录入!$B$5:$B$4999,"<="&$D$2,数据录入!$I$5:$I$4999,$K27)+SUMIFS(数据录入!$G$5:$G$4999,$Q$5:$Q$4999,1,数据录入!$B$5:$B$4999,">="&$B$2,数据录入!$B$5:$B$4999,"<="&$D$2,数据录入!$J$5:$J$4999,$K27)) | O27: =IF($K27="","",L27+M27-N27) | Q27: =IF(数据录入!$B27="",0,IF(OR(数据录入!$D27="投标保证金",数据录入!$D27="合同履约保证金",ISNUMBER(FIND("保证金",数据录入!$E27))),1,0)) | R27: =IF(AND($Q27=1,数据录入!$B27>=$B$2,数据录入!$B27<=$D$2),N(R26)+1,N(R26)) | S27: =IFERROR(MATCH(20,$R$5:$R$4999,0),"") | U27: =IFERROR(IF(20<=50,INDEX(基础资料!$E$2:$E$51,20)&"",INDEX(基础资料!$G$2:$G$51,20-50)&""),"") | V27: =IF($U27="",0,IF(AND(20>50,COUNTIF(基础资料!$E$2:$E$51,$U27)>0),0,1)) | W27: =IF($V27=1,N(W26)+1,N(W26))
A28: =IF($S28="","",INDEX(数据录入!$B$5:$B$4999,$S28)) | B28: =IF($S28="","",INDEX(数据录入!$C$5:$C$4999,$S28)&"") | C28: =IF($S28="","",IF(N($F28)>0,"收款",IF(N($G28)>0,"付款",""))) | D28: =IF($S28="","",IF((INDEX(数据录入!$I$5:$I$4999,$S28)&"")<>"",INDEX(数据录入!$I$5:$I$4999,$S28)&"",INDEX(数据录入!$J$5:$J$4999,$S28)&"")) | E28: =IF($S28="","",INDEX(数据录入!$E$5:$E$4999,$S28)&"") | F28: =IF($S28="","",N(INDEX(数据录入!$F$5:$F$4999,$S28))) | G28: =IF($S28="","",N(INDEX(数据录入!$G$5:$G$4999,$S28))) | H28: =IF($S28="","",$G$2+SUM($F$8:$F28)-SUM($G$8:$G28)) | J28: =IF($K28="","",21) | K28: =IFERROR(INDEX($U$8:$U$107,MATCH(21,$W$8:$W$107,0)),"") | L28: =IF($K28="","",(SUMIFS(数据录入!$F$5:$F$4999,$Q$5:$Q$4999,1,数据录入!$B$5:$B$4999,"<"&$B$2,数据录入!$I$5:$I$4999,$K28)+SUMIFS(数据录入!$F$5:$F$4999,$Q$5:$Q$4999,1,数据录入!$B$5:$B$4999,"<"&$B$2,数据录入!$J$5:$J$4999,$K28))-(SUMIFS(数据录入!$G$5:$G$4999,$Q$5:$Q$4999,1,数据录入!$B$5:$B$4999,"<"&$B$2,数据录入!$I$5:$I$4999,$K28)+SUMIFS(数据录入!$G$5:$G$4999,$Q$5:$Q$4999,1,数据录入!$B$5:$B$4999,"<"&$B$2,数据录入!$J$5:$J$4999,$K28))) | M28: =IF($K28="","",SUMIFS(数据录入!$F$5:$F$4999,$Q$5:$Q$4999,1,数据录入!$B$5:$B$4999,">="&$B$2,数据录入!$B$5:$B$4999,"<="&$D$2,数据录入!$I$5:$I$4999,$K28)+SUMIFS(数据录入!$F$5:$F$4999,$Q$5:$Q$4999,1,数据录入!$B$5:$B$4999,">="&$B$2,数据录入!$B$5:$B$4999,"<="&$D$2,数据录入!$J$5:$J$4999,$K28)) | N28: =IF($K28="","",SUMIFS(数据录入!$G$5:$G$4999,$Q$5:$Q$4999,1,数据录入!$B$5:$B$4999,">="&$B$2,数据录入!$B$5:$B$4999,"<="&$D$2,数据录入!$I$5:$I$4999,$K28)+SUMIFS(数据录入!$G$5:$G$4999,$Q$5:$Q$4999,1,数据录入!$B$5:$B$4999,">="&$B$2,数据录入!$B$5:$B$4999,"<="&$D$2,数据录入!$J$5:$J$4999,$K28)) | O28: =IF($K28="","",L28+M28-N28) | Q28: =IF(数据录入!$B28="",0,IF(OR(数据录入!$D28="投标保证金",数据录入!$D28="合同履约保证金",ISNUMBER(FIND("保证金",数据录入!$E28))),1,0)) | R28: =IF(AND($Q28=1,数据录入!$B28>=$B$2,数据录入!$B28<=$D$2),N(R27)+1,N(R27)) | S28: =IFERROR(MATCH(21,$R$5:$R$4999,0),"") | U28: =IFERROR(IF(21<=50,INDEX(基础资料!$E$2:$E$51,21)&"",INDEX(基础资料!$G$2:$G$51,21-50)&""),"") | V28: =IF($U28="",0,IF(AND(21>50,COUNTIF(基础资料!$E$2:$E$51,$U28)>0),0,1)) | W28: =IF($V28=1,N(W27)+1,N(W27))
A29: =IF($S29="","",INDEX(数据录入!$B$5:$B$4999,$S29)) | B29: =IF($S29="","",INDEX(数据录入!$C$5:$C$4999,$S29)&"") | C29: =IF($S29="","",IF(N($F29)>0,"收款",IF(N($G29)>0,"付款",""))) | D29: =IF($S29="","",IF((INDEX(数据录入!$I$5:$I$4999,$S29)&"")<>"",INDEX(数据录入!$I$5:$I$4999,$S29)&"",INDEX(数据录入!$J$5:$J$4999,$S29)&"")) | E29: =IF($S29="","",INDEX(数据录入!$E$5:$E$4999,$S29)&"") | F29: =IF($S29="","",N(INDEX(数据录入!$F$5:$F$4999,$S29))) | G29: =IF($S29="","",N(INDEX(数据录入!$G$5:$G$4999,$S29))) | H29: =IF($S29="","",$G$2+SUM($F$8:$F29)-SUM($G$8:$G29)) | J29: =IF($K29="","",22) | K29: =IFERROR(INDEX($U$8:$U$107,MATCH(22,$W$8:$W$107,0)),"") | L29: =IF($K29="","",(SUMIFS(数据录入!$F$5:$F$4999,$Q$5:$Q$4999,1,数据录入!$B$5:$B$4999,"<"&$B$2,数据录入!$I$5:$I$4999,$K29)+SUMIFS(数据录入!$F$5:$F$4999,$Q$5:$Q$4999,1,数据录入!$B$5:$B$4999,"<"&$B$2,数据录入!$J$5:$J$4999,$K29))-(SUMIFS(数据录入!$G$5:$G$4999,$Q$5:$Q$4999,1,数据录入!$B$5:$B$4999,"<"&$B$2,数据录入!$I$5:$I$4999,$K29)+SUMIFS(数据录入!$G$5:$G$4999,$Q$5:$Q$4999,1,数据录入!$B$5:$B$4999,"<"&$B$2,数据录入!$J$5:$J$4999,$K29))) | M29: =IF($K29="","",SUMIFS(数据录入!$F$5:$F$4999,$Q$5:$Q$4999,1,数据录入!$B$5:$B$4999,">="&$B$2,数据录入!$B$5:$B$4999,"<="&$D$2,数据录入!$I$5:$I$4999,$K29)+SUMIFS(数据录入!$F$5:$F$4999,$Q$5:$Q$4999,1,数据录入!$B$5:$B$4999,">="&$B$2,数据录入!$B$5:$B$4999,"<="&$D$2,数据录入!$J$5:$J$4999,$K29)) | N29: =IF($K29="","",SUMIFS(数据录入!$G$5:$G$4999,$Q$5:$Q$4999,1,数据录入!$B$5:$B$4999,">="&$B$2,数据录入!$B$5:$B$4999,"<="&$D$2,数据录入!$I$5:$I$4999,$K29)+SUMIFS(数据录入!$G$5:$G$4999,$Q$5:$Q$4999,1,数据录入!$B$5:$B$4999,">="&$B$2,数据录入!$B$5:$B$4999,"<="&$D$2,数据录入!$J$5:$J$4999,$K29)) | O29: =IF($K29="","",L29+M29-N29) | Q29: =IF(数据录入!$B29="",0,IF(OR(数据录入!$D29="投标保证金",数据录入!$D29="合同履约保证金",ISNUMBER(FIND("保证金",数据录入!$E29))),1,0)) | R29: =IF(AND($Q29=1,数据录入!$B29>=$B$2,数据录入!$B29<=$D$2),N(R28)+1,N(R28)) | S29: =IFERROR(MATCH(22,$R$5:$R$4999,0),"") | U29: =IFERROR(IF(22<=50,INDEX(基础资料!$E$2:$E$51,22)&"",INDEX(基础资料!$G$2:$G$51,22-50)&""),"") | V29: =IF($U29="",0,IF(AND(22>50,COUNTIF(基础资料!$E$2:$E$51,$U29)>0),0,1)) | W29: =IF($V29=1,N(W28)+1,N(W28))
A30: =IF($S30="","",INDEX(数据录入!$B$5:$B$4999,$S30)) | B30: =IF($S30="","",INDEX(数据录入!$C$5:$C$4999,$S30)&"") | C30: =IF($S30="","",IF(N($F30)>0,"收款",IF(N($G30)>0,"付款",""))) | D30: =IF($S30="","",IF((INDEX(数据录入!$I$5:$I$4999,$S30)&"")<>"",INDEX(数据录入!$I$5:$I$4999,$S30)&"",INDEX(数据录入!$J$5:$J$4999,$S30)&"")) | E30: =IF($S30="","",INDEX(数据录入!$E$5:$E$4999,$S30)&"") | F30: =IF($S30="","",N(INDEX(数据录入!$F$5:$F$4999,$S30))) | G30: =IF($S30="","",N(INDEX(数据录入!$G$5:$G$4999,$S30))) | H30: =IF($S30="","",$G$2+SUM($F$8:$F30)-SUM($G$8:$G30)) | J30: =IF($K30="","",23) | K30: =IFERROR(INDEX($U$8:$U$107,MATCH(23,$W$8:$W$107,0)),"") | L30: =IF($K30="","",(SUMIFS(数据录入!$F$5:$F$4999,$Q$5:$Q$4999,1,数据录入!$B$5:$B$4999,"<"&$B$2,数据录入!$I$5:$I$4999,$K30)+SUMIFS(数据录入!$F$5:$F$4999,$Q$5:$Q$4999,1,数据录入!$B$5:$B$4999,"<"&$B$2,数据录入!$J$5:$J$4999,$K30))-(SUMIFS(数据录入!$G$5:$G$4999,$Q$5:$Q$4999,1,数据录入!$B$5:$B$4999,"<"&$B$2,数据录入!$I$5:$I$4999,$K30)+SUMIFS(数据录入!$G$5:$G$4999,$Q$5:$Q$4999,1,数据录入!$B$5:$B$4999,"<"&$B$2,数据录入!$J$5:$J$4999,$K30))) | M30: =IF($K30="","",SUMIFS(数据录入!$F$5:$F$4999,$Q$5:$Q$4999,1,数据录入!$B$5:$B$4999,">="&$B$2,数据录入!$B$5:$B$4999,"<="&$D$2,数据录入!$I$5:$I$4999,$K30)+SUMIFS(数据录入!$F$5:$F$4999,$Q$5:$Q$4999,1,数据录入!$B$5:$B$4999,">="&$B$2,数据录入!$B$5:$B$4999,"<="&$D$2,数据录入!$J$5:$J$4999,$K30)) | N30: =IF($K30="","",SUMIFS(数据录入!$G$5:$G$4999,$Q$5:$Q$4999,1,数据录入!$B$5:$B$4999,">="&$B$2,数据录入!$B$5:$B$4999,"<="&$D$2,数据录入!$I$5:$I$4999,$K30)+SUMIFS(数据录入!$G$5:$G$4999,$Q$5:$Q$4999,1,数据录入!$B$5:$B$4999,">="&$B$2,数据录入!$B$5:$B$4999,"<="&$D$2,数据录入!$J$5:$J$4999,$K30)) | O30: =IF($K30="","",L30+M30-N30) | Q30: =IF(数据录入!$B30="",0,IF(OR(数据录入!$D30="投标保证金",数据录入!$D30="合同履约保证金",ISNUMBER(FIND("保证金",数据录入!$E30))),1,0)) | R30: =IF(AND($Q30=1,数据录入!$B30>=$B$2,数据录入!$B30<=$D$2),N(R29)+1,N(R29)) | S30: =IFERROR(MATCH(23,$R$5:$R$4999,0),"") | U30: =IFERROR(IF(23<=50,INDEX(基础资料!$E$2:$E$51,23)&"",INDEX(基础资料!$G$2:$G$51,23-50)&""),"") | V30: =IF($U30="",0,IF(AND(23>50,COUNTIF(基础资料!$E$2:$E$51,$U30)>0),0,1)) | W30: =IF($V30=1,N(W29)+1,N(W29))
A31: =IF($S31="","",INDEX(数据录入!$B$5:$B$4999,$S31)) | B31: =IF($S31="","",INDEX(数据录入!$C$5:$C$4999,$S31)&"") | C31: =IF($S31="","",IF(N($F31)>0,"收款",IF(N($G31)>0,"付款",""))) | D31: =IF($S31="","",IF((INDEX(数据录入!$I$5:$I$4999,$S31)&"")<>"",INDEX(数据录入!$I$5:$I$4999,$S31)&"",INDEX(数据录入!$J$5:$J$4999,$S31)&"")) | E31: =IF($S31="","",INDEX(数据录入!$E$5:$E$4999,$S31)&"") | F31: =IF($S31="","",N(INDEX(数据录入!$F$5:$F$4999,$S31))) | G31: =IF($S31="","",N(INDEX(数据录入!$G$5:$G$4999,$S31))) | H31: =IF($S31="","",$G$2+SUM($F$8:$F31)-SUM($G$8:$G31)) | J31: =IF($K31="","",24) | K31: =IFERROR(INDEX($U$8:$U$107,MATCH(24,$W$8:$W$107,0)),"") | L31: =IF($K31="","",(SUMIFS(数据录入!$F$5:$F$4999,$Q$5:$Q$4999,1,数据录入!$B$5:$B$4999,"<"&$B$2,数据录入!$I$5:$I$4999,$K31)+SUMIFS(数据录入!$F$5:$F$4999,$Q$5:$Q$4999,1,数据录入!$B$5:$B$4999,"<"&$B$2,数据录入!$J$5:$J$4999,$K31))-(SUMIFS(数据录入!$G$5:$G$4999,$Q$5:$Q$4999,1,数据录入!$B$5:$B$4999,"<"&$B$2,数据录入!$I$5:$I$4999,$K31)+SUMIFS(数据录入!$G$5:$G$4999,$Q$5:$Q$4999,1,数据录入!$B$5:$B$4999,"<"&$B$2,数据录入!$J$5:$J$4999,$K31))) | M31: =IF($K31="","",SUMIFS(数据录入!$F$5:$F$4999,$Q$5:$Q$4999,1,数据录入!$B$5:$B$4999,">="&$B$2,数据录入!$B$5:$B$4999,"<="&$D$2,数据录入!$I$5:$I$4999,$K31)+SUMIFS(数据录入!$F$5:$F$4999,$Q$5:$Q$4999,1,数据录入!$B$5:$B$4999,">="&$B$2,数据录入!$B$5:$B$4999,"<="&$D$2,数据录入!$J$5:$J$4999,$K31)) | N31: =IF($K31="","",SUMIFS(数据录入!$G$5:$G$4999,$Q$5:$Q$4999,1,数据录入!$B$5:$B$4999,">="&$B$2,数据录入!$B$5:$B$4999,"<="&$D$2,数据录入!$I$5:$I$4999,$K31)+SUMIFS(数据录入!$G$5:$G$4999,$Q$5:$Q$4999,1,数据录入!$B$5:$B$4999,">="&$B$2,数据录入!$B$5:$B$4999,"<="&$D$2,数据录入!$J$5:$J$4999,$K31)) | O31: =IF($K31="","",L31+M31-N31) | Q31: =IF(数据录入!$B31="",0,IF(OR(数据录入!$D31="投标保证金",数据录入!$D31="合同履约保证金",ISNUMBER(FIND("保证金",数据录入!$E31))),1,0)) | R31: =IF(AND($Q31=1,数据录入!$B31>=$B$2,数据录入!$B31<=$D$2),N(R30)+1,N(R30)) | S31: =IFERROR(MATCH(24,$R$5:$R$4999,0),"") | U31: =IFERROR(IF(24<=50,INDEX(基础资料!$E$2:$E$51,24)&"",INDEX(基础资料!$G$2:$G$51,24-50)&""),"") | V31: =IF($U31="",0,IF(AND(24>50,COUNTIF(基础资料!$E$2:$E$51,$U31)>0),0,1)) | W31: =IF($V31=1,N(W30)+1,N(W30))
A32: =IF($S32="","",INDEX(数据录入!$B$5:$B$4999,$S32)) | B32: =IF($S32="","",INDEX(数据录入!$C$5:$C$4999,$S32)&"") | C32: =IF($S32="","",IF(N($F32)>0,"收款",IF(N($G32)>0,"付款",""))) | D32: =IF($S32="","",IF((INDEX(数据录入!$I$5:$I$4999,$S32)&"")<>"",INDEX(数据录入!$I$5:$I$4999,$S32)&"",INDEX(数据录入!$J$5:$J$4999,$S32)&"")) | E32: =IF($S32="","",INDEX(数据录入!$E$5:$E$4999,$S32)&"") | F32: =IF($S32="","",N(INDEX(数据录入!$F$5:$F$4999,$S32))) | G32: =IF($S32="","",N(INDEX(数据录入!$G$5:$G$4999,$S32))) | H32: =IF($S32="","",$G$2+SUM($F$8:$F32)-SUM($G$8:$G32)) | J32: =IF($K32="","",25) | K32: =IFERROR(INDEX($U$8:$U$107,MATCH(25,$W$8:$W$107,0)),"") | L32: =IF($K32="","",(SUMIFS(数据录入!$F$5:$F$4999,$Q$5:$Q$4999,1,数据录入!$B$5:$B$4999,"<"&$B$2,数据录入!$I$5:$I$4999,$K32)+SUMIFS(数据录入!$F$5:$F$4999,$Q$5:$Q$4999,1,数据录入!$B$5:$B$4999,"<"&$B$2,数据录入!$J$5:$J$4999,$K32))-(SUMIFS(数据录入!$G$5:$G$4999,$Q$5:$Q$4999,1,数据录入!$B$5:$B$4999,"<"&$B$2,数据录入!$I$5:$I$4999,$K32)+SUMIFS(数据录入!$G$5:$G$4999,$Q$5:$Q$4999,1,数据录入!$B$5:$B$4999,"<"&$B$2,数据录入!$J$5:$J$4999,$K32))) | M32: =IF($K32="","",SUMIFS(数据录入!$F$5:$F$4999,$Q$5:$Q$4999,1,数据录入!$B$5:$B$4999,">="&$B$2,数据录入!$B$5:$B$4999,"<="&$D$2,数据录入!$I$5:$I$4999,$K32)+SUMIFS(数据录入!$F$5:$F$4999,$Q$5:$Q$4999,1,数据录入!$B$5:$B$4999,">="&$B$2,数据录入!$B$5:$B$4999,"<="&$D$2,数据录入!$J$5:$J$4999,$K32)) | N32: =IF($K32="","",SUMIFS(数据录入!$G$5:$G$4999,$Q$5:$Q$4999,1,数据录入!$B$5:$B$4999,">="&$B$2,数据录入!$B$5:$B$4999,"<="&$D$2,数据录入!$I$5:$I$4999,$K32)+SUMIFS(数据录入!$G$5:$G$4999,$Q$5:$Q$4999,1,数据录入!$B$5:$B$4999,">="&$B$2,数据录入!$B$5:$B$4999,"<="&$D$2,数据录入!$J$5:$J$4999,$K32)) | O32: =IF($K32="","",L32+M32-N32) | Q32: =IF(数据录入!$B32="",0,IF(OR(数据录入!$D32="投标保证金",数据录入!$D32="合同履约保证金",ISNUMBER(FIND("保证金",数据录入!$E32))),1,0)) | R32: =IF(AND($Q32=1,数据录入!$B32>=$B$2,数据录入!$B32<=$D$2),N(R31)+1,N(R31)) | S32: =IFERROR(MATCH(25,$R$5:$R$4999,0),"") | U32: =IFERROR(IF(25<=50,INDEX(基础资料!$E$2:$E$51,25)&"",INDEX(基础资料!$G$2:$G$51,25-50)&""),"") | V32: =IF($U32="",0,IF(AND(25>50,COUNTIF(基础资料!$E$2:$E$51,$U32)>0),0,1)) | W32: =IF($V32=1,N(W31)+1,N(W31))
A33: =IF($S33="","",INDEX(数据录入!$B$5:$B$4999,$S33)) | B33: =IF($S33="","",INDEX(数据录入!$C$5:$C$4999,$S33)&"") | C33: =IF($S33="","",IF(N($F33)>0,"收款",IF(N($G33)>0,"付款",""))) | D33: =IF($S33="","",IF((INDEX(数据录入!$I$5:$I$4999,$S33)&"")<>"",INDEX(数据录入!$I$5:$I$4999,$S33)&"",INDEX(数据录入!$J$5:$J$4999,$S33)&"")) | E33: =IF($S33="","",INDEX(数据录入!$E$5:$E$4999,$S33)&"") | F33: =IF($S33="","",N(INDEX(数据录入!$F$5:$F$4999,$S33))) | G33: =IF($S33="","",N(INDEX(数据录入!$G$5:$G$4999,$S33))) | H33: =IF($S33="","",$G$2+SUM($F$8:$F33)-SUM($G$8:$G33)) | J33: =IF($K33="","",26) | K33: =IFERROR(INDEX($U$8:$U$107,MATCH(26,$W$8:$W$107,0)),"") | L33: =IF($K33="","",(SUMIFS(数据录入!$F$5:$F$4999,$Q$5:$Q$4999,1,数据录入!$B$5:$B$4999,"<"&$B$2,数据录入!$I$5:$I$4999,$K33)+SUMIFS(数据录入!$F$5:$F$4999,$Q$5:$Q$4999,1,数据录入!$B$5:$B$4999,"<"&$B$2,数据录入!$J$5:$J$4999,$K33))-(SUMIFS(数据录入!$G$5:$G$4999,$Q$5:$Q$4999,1,数据录入!$B$5:$B$4999,"<"&$B$2,数据录入!$I$5:$I$4999,$K33)+SUMIFS(数据录入!$G$5:$G$4999,$Q$5:$Q$4999,1,数据录入!$B$5:$B$4999,"<"&$B$2,数据录入!$J$5:$J$4999,$K33))) | M33: =IF($K33="","",SUMIFS(数据录入!$F$5:$F$4999,$Q$5:$Q$4999,1,数据录入!$B$5:$B$4999,">="&$B$2,数据录入!$B$5:$B$4999,"<="&$D$2,数据录入!$I$5:$I$4999,$K33)+SUMIFS(数据录入!$F$5:$F$4999,$Q$5:$Q$4999,1,数据录入!$B$5:$B$4999,">="&$B$2,数据录入!$B$5:$B$4999,"<="&$D$2,数据录入!$J$5:$J$4999,$K33)) | N33: =IF($K33="","",SUMIFS(数据录入!$G$5:$G$4999,$Q$5:$Q$4999,1,数据录入!$B$5:$B$4999,">="&$B$2,数据录入!$B$5:$B$4999,"<="&$D$2,数据录入!$I$5:$I$4999,$K33)+SUMIFS(数据录入!$G$5:$G$4999,$Q$5:$Q$4999,1,数据录入!$B$5:$B$4999,">="&$B$2,数据录入!$B$5:$B$4999,"<="&$D$2,数据录入!$J$5:$J$4999,$K33)) | O33: =IF($K33="","",L33+M33-N33) | Q33: =IF(数据录入!$B33="",0,IF(OR(数据录入!$D33="投标保证金",数据录入!$D33="合同履约保证金",ISNUMBER(FIND("保证金",数据录入!$E33))),1,0)) | R33: =IF(AND($Q33=1,数据录入!$B33>=$B$2,数据录入!$B33<=$D$2),N(R32)+1,N(R32)) | S33: =IFERROR(MATCH(26,$R$5:$R$4999,0),"") | U33: =IFERROR(IF(26<=50,INDEX(基础资料!$E$2:$E$51,26)&"",INDEX(基础资料!$G$2:$G$51,26-50)&""),"") | V33: =IF($U33="",0,IF(AND(26>50,COUNTIF(基础资料!$E$2:$E$51,$U33)>0),0,1)) | W33: =IF($V33=1,N(W32)+1,N(W32))
A34: =IF($S34="","",INDEX(数据录入!$B$5:$B$4999,$S34)) | B34: =IF($S34="","",INDEX(数据录入!$C$5:$C$4999,$S34)&"") | C34: =IF($S34="","",IF(N($F34)>0,"收款",IF(N($G34)>0,"付款",""))) | D34: =IF($S34="","",IF((INDEX(数据录入!$I$5:$I$4999,$S34)&"")<>"",INDEX(数据录入!$I$5:$I$4999,$S34)&"",INDEX(数据录入!$J$5:$J$4999,$S34)&"")) | E34: =IF($S34="","",INDEX(数据录入!$E$5:$E$4999,$S34)&"") | F34: =IF($S34="","",N(INDEX(数据录入!$F$5:$F$4999,$S34))) | G34: =IF($S34="","",N(INDEX(数据录入!$G$5:$G$4999,$S34))) | H34: =IF($S34="","",$G$2+SUM($F$8:$F34)-SUM($G$8:$G34)) | J34: =IF($K34="","",27) | K34: =IFERROR(INDEX($U$8:$U$107,MATCH(27,$W$8:$W$107,0)),"") | L34: =IF($K34="","",(SUMIFS(数据录入!$F$5:$F$4999,$Q$5:$Q$4999,1,数据录入!$B$5:$B$4999,"<"&$B$2,数据录入!$I$5:$I$4999,$K34)+SUMIFS(数据录入!$F$5:$F$4999,$Q$5:$Q$4999,1,数据录入!$B$5:$B$4999,"<"&$B$2,数据录入!$J$5:$J$4999,$K34))-(SUMIFS(数据录入!$G$5:$G$4999,$Q$5:$Q$4999,1,数据录入!$B$5:$B$4999,"<"&$B$2,数据录入!$I$5:$I$4999,$K34)+SUMIFS(数据录入!$G$5:$G$4999,$Q$5:$Q$4999,1,数据录入!$B$5:$B$4999,"<"&$B$2,数据录入!$J$5:$J$4999,$K34))) | M34: =IF($K34="","",SUMIFS(数据录入!$F$5:$F$4999,$Q$5:$Q$4999,1,数据录入!$B$5:$B$4999,">="&$B$2,数据录入!$B$5:$B$4999,"<="&$D$2,数据录入!$I$5:$I$4999,$K34)+SUMIFS(数据录入!$F$5:$F$4999,$Q$5:$Q$4999,1,数据录入!$B$5:$B$4999,">="&$B$2,数据录入!$B$5:$B$4999,"<="&$D$2,数据录入!$J$5:$J$4999,$K34)) | N34: =IF($K34="","",SUMIFS(数据录入!$G$5:$G$4999,$Q$5:$Q$4999,1,数据录入!$B$5:$B$4999,">="&$B$2,数据录入!$B$5:$B$4999,"<="&$D$2,数据录入!$I$5:$I$4999,$K34)+SUMIFS(数据录入!$G$5:$G$4999,$Q$5:$Q$4999,1,数据录入!$B$5:$B$4999,">="&$B$2,数据录入!$B$5:$B$4999,"<="&$D$2,数据录入!$J$5:$J$4999,$K34)) | O34: =IF($K34="","",L34+M34-N34) | Q34: =IF(数据录入!$B34="",0,IF(OR(数据录入!$D34="投标保证金",数据录入!$D34="合同履约保证金",ISNUMBER(FIND("保证金",数据录入!$E34))),1,0)) | R34: =IF(AND($Q34=1,数据录入!$B34>=$B$2,数据录入!$B34<=$D$2),N(R33)+1,N(R33)) | S34: =IFERROR(MATCH(27,$R$5:$R$4999,0),"") | U34: =IFERROR(IF(27<=50,INDEX(基础资料!$E$2:$E$51,27)&"",INDEX(基础资料!$G$2:$G$51,27-50)&""),"") | V34: =IF($U34="",0,IF(AND(27>50,COUNTIF(基础资料!$E$2:$E$51,$U34)>0),0,1)) | W34: =IF($V34=1,N(W33)+1,N(W33))
A35: =IF($S35="","",INDEX(数据录入!$B$5:$B$4999,$S35)) | B35: =IF($S35="","",INDEX(数据录入!$C$5:$C$4999,$S35)&"") | C35: =IF($S35="","",IF(N($F35)>0,"收款",IF(N($G35)>0,"付款",""))) | D35: =IF($S35="","",IF((INDEX(数据录入!$I$5:$I$4999,$S35)&"")<>"",INDEX(数据录入!$I$5:$I$4999,$S35)&"",INDEX(数据录入!$J$5:$J$4999,$S35)&"")) | E35: =IF($S35="","",INDEX(数据录入!$E$5:$E$4999,$S35)&"") | F35: =IF($S35="","",N(INDEX(数据录入!$F$5:$F$4999,$S35))) | G35: =IF($S35="","",N(INDEX(数据录入!$G$5:$G$4999,$S35))) | H35: =IF($S35="","",$G$2+SUM($F$8:$F35)-SUM($G$8:$G35)) | J35: =IF($K35="","",28) | K35: =IFERROR(INDEX($U$8:$U$107,MATCH(28,$W$8:$W$107,0)),"") | L35: =IF($K35="","",(SUMIFS(数据录入!$F$5:$F$4999,$Q$5:$Q$4999,1,数据录入!$B$5:$B$4999,"<"&$B$2,数据录入!$I$5:$I$4999,$K35)+SUMIFS(数据录入!$F$5:$F$4999,$Q$5:$Q$4999,1,数据录入!$B$5:$B$4999,"<"&$B$2,数据录入!$J$5:$J$4999,$K35))-(SUMIFS(数据录入!$G$5:$G$4999,$Q$5:$Q$4999,1,数据录入!$B$5:$B$4999,"<"&$B$2,数据录入!$I$5:$I$4999,$K35)+SUMIFS(数据录入!$G$5:$G$4999,$Q$5:$Q$4999,1,数据录入!$B$5:$B$4999,"<"&$B$2,数据录入!$J$5:$J$4999,$K35))) | M35: =IF($K35="","",SUMIFS(数据录入!$F$5:$F$4999,$Q$5:$Q$4999,1,数据录入!$B$5:$B$4999,">="&$B$2,数据录入!$B$5:$B$4999,"<="&$D$2,数据录入!$I$5:$I$4999,$K35)+SUMIFS(数据录入!$F$5:$F$4999,$Q$5:$Q$4999,1,数据录入!$B$5:$B$4999,">="&$B$2,数据录入!$B$5:$B$4999,"<="&$D$2,数据录入!$J$5:$J$4999,$K35)) | N35: =IF($K35="","",SUMIFS(数据录入!$G$5:$G$4999,$Q$5:$Q$4999,1,数据录入!$B$5:$B$4999,">="&$B$2,数据录入!$B$5:$B$4999,"<="&$D$2,数据录入!$I$5:$I$4999,$K35)+SUMIFS(数据录入!$G$5:$G$4999,$Q$5:$Q$4999,1,数据录入!$B$5:$B$4999,">="&$B$2,数据录入!$B$5:$B$4999,"<="&$D$2,数据录入!$J$5:$J$4999,$K35)) | O35: =IF($K35="","",L35+M35-N35) | Q35: =IF(数据录入!$B35="",0,IF(OR(数据录入!$D35="投标保证金",数据录入!$D35="合同履约保证金",ISNUMBER(FIND("保证金",数据录入!$E35))),1,0)) | R35: =IF(AND($Q35=1,数据录入!$B35>=$B$2,数据录入!$B35<=$D$2),N(R34)+1,N(R34)) | S35: =IFERROR(MATCH(28,$R$5:$R$4999,0),"") | U35: =IFERROR(IF(28<=50,INDEX(基础资料!$E$2:$E$51,28)&"",INDEX(基础资料!$G$2:$G$51,28-50)&""),"") | V35: =IF($U35="",0,IF(AND(28>50,COUNTIF(基础资料!$E$2:$E$51,$U35)>0),0,1)) | W35: =IF($V35=1,N(W34)+1,N(W34))
A36: =IF($S36="","",INDEX(数据录入!$B$5:$B$4999,$S36)) | B36: =IF($S36="","",INDEX(数据录入!$C$5:$C$4999,$S36)&"") | C36: =IF($S36="","",IF(N($F36)>0,"收款",IF(N($G36)>0,"付款",""))) | D36: =IF($S36="","",IF((INDEX(数据录入!$I$5:$I$4999,$S36)&"")<>"",INDEX(数据录入!$I$5:$I$4999,$S36)&"",INDEX(数据录入!$J$5:$J$4999,$S36)&"")) | E36: =IF($S36="","",INDEX(数据录入!$E$5:$E$4999,$S36)&"") | F36: =IF($S36="","",N(INDEX(数据录入!$F$5:$F$4999,$S36))) | G36: =IF($S36="","",N(INDEX(数据录入!$G$5:$G$4999,$S36))) | H36: =IF($S36="","",$G$2+SUM($F$8:$F36)-SUM($G$8:$G36)) | J36: =IF($K36="","",29) | K36: =IFERROR(INDEX($U$8:$U$107,MATCH(29,$W$8:$W$107,0)),"") | L36: =IF($K36="","",(SUMIFS(数据录入!$F$5:$F$4999,$Q$5:$Q$4999,1,数据录入!$B$5:$B$4999,"<"&$B$2,数据录入!$I$5:$I$4999,$K36)+SUMIFS(数据录入!$F$5:$F$4999,$Q$5:$Q$4999,1,数据录入!$B$5:$B$4999,"<"&$B$2,数据录入!$J$5:$J$4999,$K36))-(SUMIFS(数据录入!$G$5:$G$4999,$Q$5:$Q$4999,1,数据录入!$B$5:$B$4999,"<"&$B$2,数据录入!$I$5:$I$4999,$K36)+SUMIFS(数据录入!$G$5:$G$4999,$Q$5:$Q$4999,1,数据录入!$B$5:$B$4999,"<"&$B$2,数据录入!$J$5:$J$4999,$K36))) | M36: =IF($K36="","",SUMIFS(数据录入!$F$5:$F$4999,$Q$5:$Q$4999,1,数据录入!$B$5:$B$4999,">="&$B$2,数据录入!$B$5:$B$4999,"<="&$D$2,数据录入!$I$5:$I$4999,$K36)+SUMIFS(数据录入!$F$5:$F$4999,$Q$5:$Q$4999,1,数据录入!$B$5:$B$4999,">="&$B$2,数据录入!$B$5:$B$4999,"<="&$D$2,数据录入!$J$5:$J$4999,$K36)) | N36: =IF($K36="","",SUMIFS(数据录入!$G$5:$G$4999,$Q$5:$Q$4999,1,数据录入!$B$5:$B$4999,">="&$B$2,数据录入!$B$5:$B$4999,"<="&$D$2,数据录入!$I$5:$I$4999,$K36)+SUMIFS(数据录入!$G$5:$G$4999,$Q$5:$Q$4999,1,数据录入!$B$5:$B$4999,">="&$B$2,数据录入!$B$5:$B$4999,"<="&$D$2,数据录入!$J$5:$J$4999,$K36)) | O36: =IF($K36="","",L36+M36-N36) | Q36: =IF(数据录入!$B36="",0,IF(OR(数据录入!$D36="投标保证金",数据录入!$D36="合同履约保证金",ISNUMBER(FIND("保证金",数据录入!$E36))),1,0)) | R36: =IF(AND($Q36=1,数据录入!$B36>=$B$2,数据录入!$B36<=$D$2),N(R35)+1,N(R35)) | S36: =IFERROR(MATCH(29,$R$5:$R$4999,0),"") | U36: =IFERROR(IF(29<=50,INDEX(基础资料!$E$2:$E$51,29)&"",INDEX(基础资料!$G$2:$G$51,29-50)&""),"") | V36: =IF($U36="",0,IF(AND(29>50,COUNTIF(基础资料!$E$2:$E$51,$U36)>0),0,1)) | W36: =IF($V36=1,N(W35)+1,N(W35))
A37: =IF($S37="","",INDEX(数据录入!$B$5:$B$4999,$S37)) | B37: =IF($S37="","",INDEX(数据录入!$C$5:$C$4999,$S37)&"") | C37: =IF($S37="","",IF(N($F37)>0,"收款",IF(N($G37)>0,"付款",""))) | D37: =IF($S37="","",IF((INDEX(数据录入!$I$5:$I$4999,$S37)&"")<>"",INDEX(数据录入!$I$5:$I$4999,$S37)&"",INDEX(数据录入!$J$5:$J$4999,$S37)&"")) | E37: =IF($S37="","",INDEX(数据录入!$E$5:$E$4999,$S37)&"") | F37: =IF($S37="","",N(INDEX(数据录入!$F$5:$F$4999,$S37))) | G37: =IF($S37="","",N(INDEX(数据录入!$G$5:$G$4999,$S37))) | H37: =IF($S37="","",$G$2+SUM($F$8:$F37)-SUM($G$8:$G37)) | J37: =IF($K37="","",30) | K37: =IFERROR(INDEX($U$8:$U$107,MATCH(30,$W$8:$W$107,0)),"") | L37: =IF($K37="","",(SUMIFS(数据录入!$F$5:$F$4999,$Q$5:$Q$4999,1,数据录入!$B$5:$B$4999,"<"&$B$2,数据录入!$I$5:$I$4999,$K37)+SUMIFS(数据录入!$F$5:$F$4999,$Q$5:$Q$4999,1,数据录入!$B$5:$B$4999,"<"&$B$2,数据录入!$J$5:$J$4999,$K37))-(SUMIFS(数据录入!$G$5:$G$4999,$Q$5:$Q$4999,1,数据录入!$B$5:$B$4999,"<"&$B$2,数据录入!$I$5:$I$4999,$K37)+SUMIFS(数据录入!$G$5:$G$4999,$Q$5:$Q$4999,1,数据录入!$B$5:$B$4999,"<"&$B$2,数据录入!$J$5:$J$4999,$K37))) | M37: =IF($K37="","",SUMIFS(数据录入!$F$5:$F$4999,$Q$5:$Q$4999,1,数据录入!$B$5:$B$4999,">="&$B$2,数据录入!$B$5:$B$4999,"<="&$D$2,数据录入!$I$5:$I$4999,$K37)+SUMIFS(数据录入!$F$5:$F$4999,$Q$5:$Q$4999,1,数据录入!$B$5:$B$4999,">="&$B$2,数据录入!$B$5:$B$4999,"<="&$D$2,数据录入!$J$5:$J$4999,$K37)) | N37: =IF($K37="","",SUMIFS(数据录入!$G$5:$G$4999,$Q$5:$Q$4999,1,数据录入!$B$5:$B$4999,">="&$B$2,数据录入!$B$5:$B$4999,"<="&$D$2,数据录入!$I$5:$I$4999,$K37)+SUMIFS(数据录入!$G$5:$G$4999,$Q$5:$Q$4999,1,数据录入!$B$5:$B$4999,">="&$B$2,数据录入!$B$5:$B$4999,"<="&$D$2,数据录入!$J$5:$J$4999,$K37)) | O37: =IF($K37="","",L37+M37-N37) | Q37: =IF(数据录入!$B37="",0,IF(OR(数据录入!$D37="投标保证金",数据录入!$D37="合同履约保证金",ISNUMBER(FIND("保证金",数据录入!$E37))),1,0)) | R37: =IF(AND($Q37=1,数据录入!$B37>=$B$2,数据录入!$B37<=$D$2),N(R36)+1,N(R36)) | S37: =IFERROR(MATCH(30,$R$5:$R$4999,0),"") | U37: =IFERROR(IF(30<=50,INDEX(基础资料!$E$2:$E$51,30)&"",INDEX(基础资料!$G$2:$G$51,30-50)&""),"") | V37: =IF($U37="",0,IF(AND(30>50,COUNTIF(基础资料!$E$2:$E$51,$U37)>0),0,1)) | W37: =IF($V37=1,N(W36)+1,N(W36))
A38: =IF($S38="","",INDEX(数据录入!$B$5:$B$4999,$S38)) | B38: =IF($S38="","",INDEX(数据录入!$C$5:$C$4999,$S38)&"") | C38: =IF($S38="","",IF(N($F38)>0,"收款",IF(N($G38)>0,"付款",""))) | D38: =IF($S38="","",IF((INDEX(数据录入!$I$5:$I$4999,$S38)&"")<>"",INDEX(数据录入!$I$5:$I$4999,$S38)&"",INDEX(数据录入!$J$5:$J$4999,$S38)&"")) | E38: =IF($S38="","",INDEX(数据录入!$E$5:$E$4999,$S38)&"") | F38: =IF($S38="","",N(INDEX(数据录入!$F$5:$F$4999,$S38))) | G38: =IF($S38="","",N(INDEX(数据录入!$G$5:$G$4999,$S38))) | H38: =IF($S38="","",$G$2+SUM($F$8:$F38)-SUM($G$8:$G38)) | J38: =IF($K38="","",31) | K38: =IFERROR(INDEX($U$8:$U$107,MATCH(31,$W$8:$W$107,0)),"") | L38: =IF($K38="","",(SUMIFS(数据录入!$F$5:$F$4999,$Q$5:$Q$4999,1,数据录入!$B$5:$B$4999,"<"&$B$2,数据录入!$I$5:$I$4999,$K38)+SUMIFS(数据录入!$F$5:$F$4999,$Q$5:$Q$4999,1,数据录入!$B$5:$B$4999,"<"&$B$2,数据录入!$J$5:$J$4999,$K38))-(SUMIFS(数据录入!$G$5:$G$4999,$Q$5:$Q$4999,1,数据录入!$B$5:$B$4999,"<"&$B$2,数据录入!$I$5:$I$4999,$K38)+SUMIFS(数据录入!$G$5:$G$4999,$Q$5:$Q$4999,1,数据录入!$B$5:$B$4999,"<"&$B$2,数据录入!$J$5:$J$4999,$K38))) | M38: =IF($K38="","",SUMIFS(数据录入!$F$5:$F$4999,$Q$5:$Q$4999,1,数据录入!$B$5:$B$4999,">="&$B$2,数据录入!$B$5:$B$4999,"<="&$D$2,数据录入!$I$5:$I$4999,$K38)+SUMIFS(数据录入!$F$5:$F$4999,$Q$5:$Q$4999,1,数据录入!$B$5:$B$4999,">="&$B$2,数据录入!$B$5:$B$4999,"<="&$D$2,数据录入!$J$5:$J$4999,$K38)) | N38: =IF($K38="","",SUMIFS(数据录入!$G$5:$G$4999,$Q$5:$Q$4999,1,数据录入!$B$5:$B$4999,">="&$B$2,数据录入!$B$5:$B$4999,"<="&$D$2,数据录入!$I$5:$I$4999,$K38)+SUMIFS(数据录入!$G$5:$G$4999,$Q$5:$Q$4999,1,数据录入!$B$5:$B$4999,">="&$B$2,数据录入!$B$5:$B$4999,"<="&$D$2,数据录入!$J$5:$J$4999,$K38)) | O38: =IF($K38="","",L38+M38-N38) | Q38: =IF(数据录入!$B38="",0,IF(OR(数据录入!$D38="投标保证金",数据录入!$D38="合同履约保证金",ISNUMBER(FIND("保证金",数据录入!$E38))),1,0)) | R38: =IF(AND($Q38=1,数据录入!$B38>=$B$2,数据录入!$B38<=$D$2),N(R37)+1,N(R37)) | S38: =IFERROR(MATCH(31,$R$5:$R$4999,0),"") | U38: =IFERROR(IF(31<=50,INDEX(基础资料!$E$2:$E$51,31)&"",INDEX(基础资料!$G$2:$G$51,31-50)&""),"") | V38: =IF($U38="",0,IF(AND(31>50,COUNTIF(基础资料!$E$2:$E$51,$U38)>0),0,1)) | W38: =IF($V38=1,N(W37)+1,N(W37))
A39: =IF($S39="","",INDEX(数据录入!$B$5:$B$4999,$S39)) | B39: =IF($S39="","",INDEX(数据录入!$C$5:$C$4999,$S39)&"") | C39: =IF($S39="","",IF(N($F39)>0,"收款",IF(N($G39)>0,"付款",""))) | D39: =IF($S39="","",IF((INDEX(数据录入!$I$5:$I$4999,$S39)&"")<>"",INDEX(数据录入!$I$5:$I$4999,$S39)&"",INDEX(数据录入!$J$5:$J$4999,$S39)&"")) | E39: =IF($S39="","",INDEX(数据录入!$E$5:$E$4999,$S39)&"") | F39: =IF($S39="","",N(INDEX(数据录入!$F$5:$F$4999,$S39))) | G39: =IF($S39="","",N(INDEX(数据录入!$G$5:$G$4999,$S39))) | H39: =IF($S39="","",$G$2+SUM($F$8:$F39)-SUM($G$8:$G39)) | J39: =IF($K39="","",32) | K39: =IFERROR(INDEX($U$8:$U$107,MATCH(32,$W$8:$W$107,0)),"") | L39: =IF($K39="","",(SUMIFS(数据录入!$F$5:$F$4999,$Q$5:$Q$4999,1,数据录入!$B$5:$B$4999,"<"&$B$2,数据录入!$I$5:$I$4999,$K39)+SUMIFS(数据录入!$F$5:$F$4999,$Q$5:$Q$4999,1,数据录入!$B$5:$B$4999,"<"&$B$2,数据录入!$J$5:$J$4999,$K39))-(SUMIFS(数据录入!$G$5:$G$4999,$Q$5:$Q$4999,1,数据录入!$B$5:$B$4999,"<"&$B$2,数据录入!$I$5:$I$4999,$K39)+SUMIFS(数据录入!$G$5:$G$4999,$Q$5:$Q$4999,1,数据录入!$B$5:$B$4999,"<"&$B$2,数据录入!$J$5:$J$4999,$K39))) | M39: =IF($K39="","",SUMIFS(数据录入!$F$5:$F$4999,$Q$5:$Q$4999,1,数据录入!$B$5:$B$4999,">="&$B$2,数据录入!$B$5:$B$4999,"<="&$D$2,数据录入!$I$5:$I$4999,$K39)+SUMIFS(数据录入!$F$5:$F$4999,$Q$5:$Q$4999,1,数据录入!$B$5:$B$4999,">="&$B$2,数据录入!$B$5:$B$4999,"<="&$D$2,数据录入!$J$5:$J$4999,$K39)) | N39: =IF($K39="","",SUMIFS(数据录入!$G$5:$G$4999,$Q$5:$Q$4999,1,数据录入!$B$5:$B$4999,">="&$B$2,数据录入!$B$5:$B$4999,"<="&$D$2,数据录入!$I$5:$I$4999,$K39)+SUMIFS(数据录入!$G$5:$G$4999,$Q$5:$Q$4999,1,数据录入!$B$5:$B$4999,">="&$B$2,数据录入!$B$5:$B$4999,"<="&$D$2,数据录入!$J$5:$J$4999,$K39)) | O39: =IF($K39="","",L39+M39-N39) | Q39: =IF(数据录入!$B39="",0,IF(OR(数据录入!$D39="投标保证金",数据录入!$D39="合同履约保证金",ISNUMBER(FIND("保证金",数据录入!$E39))),1,0)) | R39: =IF(AND($Q39=1,数据录入!$B39>=$B$2,数据录入!$B39<=$D$2),N(R38)+1,N(R38)) | S39: =IFERROR(MATCH(32,$R$5:$R$4999,0),"") | U39: =IFERROR(IF(32<=50,INDEX(基础资料!$E$2:$E$51,32)&"",INDEX(基础资料!$G$2:$G$51,32-50)&""),"") | V39: =IF($U39="",0,IF(AND(32>50,COUNTIF(基础资料!$E$2:$E$51,$U39)>0),0,1)) | W39: =IF($V39=1,N(W38)+1,N(W38))
A40: =IF($S40="","",INDEX(数据录入!$B$5:$B$4999,$S40)) | B40: =IF($S40="","",INDEX(数据录入!$C$5:$C$4999,$S40)&"") | C40: =IF($S40="","",IF(N($F40)>0,"收款",IF(N($G40)>0,"付款",""))) | D40: =IF($S40="","",IF((INDEX(数据录入!$I$5:$I$4999,$S40)&"")<>"",INDEX(数据录入!$I$5:$I$4999,$S40)&"",INDEX(数据录入!$J$5:$J$4999,$S40)&"")) | E40: =IF($S40="","",INDEX(数据录入!$E$5:$E$4999,$S40)&"") | F40: =IF($S40="","",N(INDEX(数据录入!$F$5:$F$4999,$S40))) | G40: =IF($S40="","",N(INDEX(数据录入!$G$5:$G$4999,$S40))) | H40: =IF($S40="","",$G$2+SUM($F$8:$F40)-SUM($G$8:$G40)) | J40: =IF($K40="","",33) | K40: =IFERROR(INDEX($U$8:$U$107,MATCH(33,$W$8:$W$107,0)),"") | L40: =IF($K40="","",(SUMIFS(数据录入!$F$5:$F$4999,$Q$5:$Q$4999,1,数据录入!$B$5:$B$4999,"<"&$B$2,数据录入!$I$5:$I$4999,$K40)+SUMIFS(数据录入!$F$5:$F$4999,$Q$5:$Q$4999,1,数据录入!$B$5:$B$4999,"<"&$B$2,数据录入!$J$5:$J$4999,$K40))-(SUMIFS(数据录入!$G$5:$G$4999,$Q$5:$Q$4999,1,数据录入!$B$5:$B$4999,"<"&$B$2,数据录入!$I$5:$I$4999,$K40)+SUMIFS(数据录入!$G$5:$G$4999,$Q$5:$Q$4999,1,数据录入!$B$5:$B$4999,"<"&$B$2,数据录入!$J$5:$J$4999,$K40))) | M40: =IF($K40="","",SUMIFS(数据录入!$F$5:$F$4999,$Q$5:$Q$4999,1,数据录入!$B$5:$B$4999,">="&$B$2,数据录入!$B$5:$B$4999,"<="&$D$2,数据录入!$I$5:$I$4999,$K40)+SUMIFS(数据录入!$F$5:$F$4999,$Q$5:$Q$4999,1,数据录入!$B$5:$B$4999,">="&$B$2,数据录入!$B$5:$B$4999,"<="&$D$2,数据录入!$J$5:$J$4999,$K40)) | N40: =IF($K40="","",SUMIFS(数据录入!$G$5:$G$4999,$Q$5:$Q$4999,1,数据录入!$B$5:$B$4999,">="&$B$2,数据录入!$B$5:$B$4999,"<="&$D$2,数据录入!$I$5:$I$4999,$K40)+SUMIFS(数据录入!$G$5:$G$4999,$Q$5:$Q$4999,1,数据录入!$B$5:$B$4999,">="&$B$2,数据录入!$B$5:$B$4999,"<="&$D$2,数据录入!$J$5:$J$4999,$K40)) | O40: =IF($K40="","",L40+M40-N40) | Q40: =IF(数据录入!$B40="",0,IF(OR(数据录入!$D40="投标保证金",数据录入!$D40="合同履约保证金",ISNUMBER(FIND("保证金",数据录入!$E40))),1,0)) | R40: =IF(AND($Q40=1,数据录入!$B40>=$B$2,数据录入!$B40<=$D$2),N(R39)+1,N(R39)) | S40: =IFERROR(MATCH(33,$R$5:$R$4999,0),"") | U40: =IFERROR(IF(33<=50,INDEX(基础资料!$E$2:$E$51,33)&"",INDEX(基础资料!$G$2:$G$51,33-50)&""),"") | V40: =IF($U40="",0,IF(AND(33>50,COUNTIF(基础资料!$E$2:$E$51,$U40)>0),0,1)) | W40: =IF($V40=1,N(W39)+1,N(W39))
A41: =IF($S41="","",INDEX(数据录入!$B$5:$B$4999,$S41)) | B41: =IF($S41="","",INDEX(数据录入!$C$5:$C$4999,$S41)&"") | C41: =IF($S41="","",IF(N($F41)>0,"收款",IF(N($G41)>0,"付款",""))) | D41: =IF($S41="","",IF((INDEX(数据录入!$I$5:$I$4999,$S41)&"")<>"",INDEX(数据录入!$I$5:$I$4999,$S41)&"",INDEX(数据录入!$J$5:$J$4999,$S41)&"")) | E41: =IF($S41="","",INDEX(数据录入!$E$5:$E$4999,$S41)&"") | F41: =IF($S41="","",N(INDEX(数据录入!$F$5:$F$4999,$S41))) | G41: =IF($S41="","",N(INDEX(数据录入!$G$5:$G$4999,$S41))) | H41: =IF($S41="","",$G$2+SUM($F$8:$F41)-SUM($G$8:$G41)) | J41: =IF($K41="","",34) | K41: =IFERROR(INDEX($U$8:$U$107,MATCH(34,$W$8:$W$107,0)),"") | L41: =IF($K41="","",(SUMIFS(数据录入!$F$5:$F$4999,$Q$5:$Q$4999,1,数据录入!$B$5:$B$4999,"<"&$B$2,数据录入!$I$5:$I$4999,$K41)+SUMIFS(数据录入!$F$5:$F$4999,$Q$5:$Q$4999,1,数据录入!$B$5:$B$4999,"<"&$B$2,数据录入!$J$5:$J$4999,$K41))-(SUMIFS(数据录入!$G$5:$G$4999,$Q$5:$Q$4999,1,数据录入!$B$5:$B$4999,"<"&$B$2,数据录入!$I$5:$I$4999,$K41)+SUMIFS(数据录入!$G$5:$G$4999,$Q$5:$Q$4999,1,数据录入!$B$5:$B$4999,"<"&$B$2,数据录入!$J$5:$J$4999,$K41))) | M41: =IF($K41="","",SUMIFS(数据录入!$F$5:$F$4999,$Q$5:$Q$4999,1,数据录入!$B$5:$B$4999,">="&$B$2,数据录入!$B$5:$B$4999,"<="&$D$2,数据录入!$I$5:$I$4999,$K41)+SUMIFS(数据录入!$F$5:$F$4999,$Q$5:$Q$4999,1,数据录入!$B$5:$B$4999,">="&$B$2,数据录入!$B$5:$B$4999,"<="&$D$2,数据录入!$J$5:$J$4999,$K41)) | N41: =IF($K41="","",SUMIFS(数据录入!$G$5:$G$4999,$Q$5:$Q$4999,1,数据录入!$B$5:$B$4999,">="&$B$2,数据录入!$B$5:$B$4999,"<="&$D$2,数据录入!$I$5:$I$4999,$K41)+SUMIFS(数据录入!$G$5:$G$4999,$Q$5:$Q$4999,1,数据录入!$B$5:$B$4999,">="&$B$2,数据录入!$B$5:$B$4999,"<="&$D$2,数据录入!$J$5:$J$4999,$K41)) | O41: =IF($K41="","",L41+M41-N41) | Q41: =IF(数据录入!$B41="",0,IF(OR(数据录入!$D41="投标保证金",数据录入!$D41="合同履约保证金",ISNUMBER(FIND("保证金",数据录入!$E41))),1,0)) | R41: =IF(AND($Q41=1,数据录入!$B41>=$B$2,数据录入!$B41<=$D$2),N(R40)+1,N(R40)) | S41: =IFERROR(MATCH(34,$R$5:$R$4999,0),"") | U41: =IFERROR(IF(34<=50,INDEX(基础资料!$E$2:$E$51,34)&"",INDEX(基础资料!$G$2:$G$51,34-50)&""),"") | V41: =IF($U41="",0,IF(AND(34>50,COUNTIF(基础资料!$E$2:$E$51,$U41)>0),0,1)) | W41: =IF($V41=1,N(W40)+1,N(W40))
A42: =IF($S42="","",INDEX(数据录入!$B$5:$B$4999,$S42)) | B42: =IF($S42="","",INDEX(数据录入!$C$5:$C$4999,$S42)&"") | C42: =IF($S42="","",IF(N($F42)>0,"收款",IF(N($G42)>0,"付款",""))) | D42: =IF($S42="","",IF((INDEX(数据录入!$I$5:$I$4999,$S42)&"")<>"",INDEX(数据录入!$I$5:$I$4999,$S42)&"",INDEX(数据录入!$J$5:$J$4999,$S42)&"")) | E42: =IF($S42="","",INDEX(数据录入!$E$5:$E$4999,$S42)&"") | F42: =IF($S42="","",N(INDEX(数据录入!$F$5:$F$4999,$S42))) | G42: =IF($S42="","",N(INDEX(数据录入!$G$5:$G$4999,$S42))) | H42: =IF($S42="","",$G$2+SUM($F$8:$F42)-SUM($G$8:$G42)) | J42: =IF($K42="","",35) | K42: =IFERROR(INDEX($U$8:$U$107,MATCH(35,$W$8:$W$107,0)),"") | L42: =IF($K42="","",(SUMIFS(数据录入!$F$5:$F$4999,$Q$5:$Q$4999,1,数据录入!$B$5:$B$4999,"<"&$B$2,数据录入!$I$5:$I$4999,$K42)+SUMIFS(数据录入!$F$5:$F$4999,$Q$5:$Q$4999,1,数据录入!$B$5:$B$4999,"<"&$B$2,数据录入!$J$5:$J$4999,$K42))-(SUMIFS(数据录入!$G$5:$G$4999,$Q$5:$Q$4999,1,数据录入!$B$5:$B$4999,"<"&$B$2,数据录入!$I$5:$I$4999,$K42)+SUMIFS(数据录入!$G$5:$G$4999,$Q$5:$Q$4999,1,数据录入!$B$5:$B$4999,"<"&$B$2,数据录入!$J$5:$J$4999,$K42))) | M42: =IF($K42="","",SUMIFS(数据录入!$F$5:$F$4999,$Q$5:$Q$4999,1,数据录入!$B$5:$B$4999,">="&$B$2,数据录入!$B$5:$B$4999,"<="&$D$2,数据录入!$I$5:$I$4999,$K42)+SUMIFS(数据录入!$F$5:$F$4999,$Q$5:$Q$4999,1,数据录入!$B$5:$B$4999,">="&$B$2,数据录入!$B$5:$B$4999,"<="&$D$2,数据录入!$J$5:$J$4999,$K42)) | N42: =IF($K42="","",SUMIFS(数据录入!$G$5:$G$4999,$Q$5:$Q$4999,1,数据录入!$B$5:$B$4999,">="&$B$2,数据录入!$B$5:$B$4999,"<="&$D$2,数据录入!$I$5:$I$4999,$K42)+SUMIFS(数据录入!$G$5:$G$4999,$Q$5:$Q$4999,1,数据录入!$B$5:$B$4999,">="&$B$2,数据录入!$B$5:$B$4999,"<="&$D$2,数据录入!$J$5:$J$4999,$K42)) | O42: =IF($K42="","",L42+M42-N42) | Q42: =IF(数据录入!$B42="",0,IF(OR(数据录入!$D42="投标保证金",数据录入!$D42="合同履约保证金",ISNUMBER(FIND("保证金",数据录入!$E42))),1,0)) | R42: =IF(AND($Q42=1,数据录入!$B42>=$B$2,数据录入!$B42<=$D$2),N(R41)+1,N(R41)) | S42: =IFERROR(MATCH(35,$R$5:$R$4999,0),"") | U42: =IFERROR(IF(35<=50,INDEX(基础资料!$E$2:$E$51,35)&"",INDEX(基础资料!$G$2:$G$51,35-50)&""),"") | V42: =IF($U42="",0,IF(AND(35>50,COUNTIF(基础资料!$E$2:$E$51,$U42)>0),0,1)) | W42: =IF($V42=1,N(W41)+1,N(W41))
A43: =IF($S43="","",INDEX(数据录入!$B$5:$B$4999,$S43)) | B43: =IF($S43="","",INDEX(数据录入!$C$5:$C$4999,$S43)&"") | C43: =IF($S43="","",IF(N($F43)>0,"收款",IF(N($G43)>0,"付款",""))) | D43: =IF($S43="","",IF((INDEX(数据录入!$I$5:$I$4999,$S43)&"")<>"",INDEX(数据录入!$I$5:$I$4999,$S43)&"",INDEX(数据录入!$J$5:$J$4999,$S43)&"")) | E43: =IF($S43="","",INDEX(数据录入!$E$5:$E$4999,$S43)&"") | F43: =IF($S43="","",N(INDEX(数据录入!$F$5:$F$4999,$S43))) | G43: =IF($S43="","",N(INDEX(数据录入!$G$5:$G$4999,$S43))) | H43: =IF($S43="","",$G$2+SUM($F$8:$F43)-SUM($G$8:$G43)) | J43: =IF($K43="","",36) | K43: =IFERROR(INDEX($U$8:$U$107,MATCH(36,$W$8:$W$107,0)),"") | L43: =IF($K43="","",(SUMIFS(数据录入!$F$5:$F$4999,$Q$5:$Q$4999,1,数据录入!$B$5:$B$4999,"<"&$B$2,数据录入!$I$5:$I$4999,$K43)+SUMIFS(数据录入!$F$5:$F$4999,$Q$5:$Q$4999,1,数据录入!$B$5:$B$4999,"<"&$B$2,数据录入!$J$5:$J$4999,$K43))-(SUMIFS(数据录入!$G$5:$G$4999,$Q$5:$Q$4999,1,数据录入!$B$5:$B$4999,"<"&$B$2,数据录入!$I$5:$I$4999,$K43)+SUMIFS(数据录入!$G$5:$G$4999,$Q$5:$Q$4999,1,数据录入!$B$5:$B$4999,"<"&$B$2,数据录入!$J$5:$J$4999,$K43))) | M43: =IF($K43="","",SUMIFS(数据录入!$F$5:$F$4999,$Q$5:$Q$4999,1,数据录入!$B$5:$B$4999,">="&$B$2,数据录入!$B$5:$B$4999,"<="&$D$2,数据录入!$I$5:$I$4999,$K43)+SUMIFS(数据录入!$F$5:$F$4999,$Q$5:$Q$4999,1,数据录入!$B$5:$B$4999,">="&$B$2,数据录入!$B$5:$B$4999,"<="&$D$2,数据录入!$J$5:$J$4999,$K43)) | N43: =IF($K43="","",SUMIFS(数据录入!$G$5:$G$4999,$Q$5:$Q$4999,1,数据录入!$B$5:$B$4999,">="&$B$2,数据录入!$B$5:$B$4999,"<="&$D$2,数据录入!$I$5:$I$4999,$K43)+SUMIFS(数据录入!$G$5:$G$4999,$Q$5:$Q$4999,1,数据录入!$B$5:$B$4999,">="&$B$2,数据录入!$B$5:$B$4999,"<="&$D$2,数据录入!$J$5:$J$4999,$K43)) | O43: =IF($K43="","",L43+M43-N43) | Q43: =IF(数据录入!$B43="",0,IF(OR(数据录入!$D43="投标保证金",数据录入!$D43="合同履约保证金",ISNUMBER(FIND("保证金",数据录入!$E43))),1,0)) | R43: =IF(AND($Q43=1,数据录入!$B43>=$B$2,数据录入!$B43<=$D$2),N(R42)+1,N(R42)) | S43: =IFERROR(MATCH(36,$R$5:$R$4999,0),"") | U43: =IFERROR(IF(36<=50,INDEX(基础资料!$E$2:$E$51,36)&"",INDEX(基础资料!$G$2:$G$51,36-50)&""),"") | V43: =IF($U43="",0,IF(AND(36>50,COUNTIF(基础资料!$E$2:$E$51,$U43)>0),0,1)) | W43: =IF($V43=1,N(W42)+1,N(W42))
A44: =IF($S44="","",INDEX(数据录入!$B$5:$B$4999,$S44)) | B44: =IF($S44="","",INDEX(数据录入!$C$5:$C$4999,$S44)&"") | C44: =IF($S44="","",IF(N($F44)>0,"收款",IF(N($G44)>0,"付款",""))) | D44: =IF($S44="","",IF((INDEX(数据录入!$I$5:$I$4999,$S44)&"")<>"",INDEX(数据录入!$I$5:$I$4999,$S44)&"",INDEX(数据录入!$J$5:$J$4999,$S44)&"")) | E44: =IF($S44="","",INDEX(数据录入!$E$5:$E$4999,$S44)&"") | F44: =IF($S44="","",N(INDEX(数据录入!$F$5:$F$4999,$S44))) | G44: =IF($S44="","",N(INDEX(数据录入!$G$5:$G$4999,$S44))) | H44: =IF($S44="","",$G$2+SUM($F$8:$F44)-SUM($G$8:$G44)) | J44: =IF($K44="","",37) | K44: =IFERROR(INDEX($U$8:$U$107,MATCH(37,$W$8:$W$107,0)),"") | L44: =IF($K44="","",(SUMIFS(数据录入!$F$5:$F$4999,$Q$5:$Q$4999,1,数据录入!$B$5:$B$4999,"<"&$B$2,数据录入!$I$5:$I$4999,$K44)+SUMIFS(数据录入!$F$5:$F$4999,$Q$5:$Q$4999,1,数据录入!$B$5:$B$4999,"<"&$B$2,数据录入!$J$5:$J$4999,$K44))-(SUMIFS(数据录入!$G$5:$G$4999,$Q$5:$Q$4999,1,数据录入!$B$5:$B$4999,"<"&$B$2,数据录入!$I$5:$I$4999,$K44)+SUMIFS(数据录入!$G$5:$G$4999,$Q$5:$Q$4999,1,数据录入!$B$5:$B$4999,"<"&$B$2,数据录入!$J$5:$J$4999,$K44))) | M44: =IF($K44="","",SUMIFS(数据录入!$F$5:$F$4999,$Q$5:$Q$4999,1,数据录入!$B$5:$B$4999,">="&$B$2,数据录入!$B$5:$B$4999,"<="&$D$2,数据录入!$I$5:$I$4999,$K44)+SUMIFS(数据录入!$F$5:$F$4999,$Q$5:$Q$4999,1,数据录入!$B$5:$B$4999,">="&$B$2,数据录入!$B$5:$B$4999,"<="&$D$2,数据录入!$J$5:$J$4999,$K44)) | N44: =IF($K44="","",SUMIFS(数据录入!$G$5:$G$4999,$Q$5:$Q$4999,1,数据录入!$B$5:$B$4999,">="&$B$2,数据录入!$B$5:$B$4999,"<="&$D$2,数据录入!$I$5:$I$4999,$K44)+SUMIFS(数据录入!$G$5:$G$4999,$Q$5:$Q$4999,1,数据录入!$B$5:$B$4999,">="&$B$2,数据录入!$B$5:$B$4999,"<="&$D$2,数据录入!$J$5:$J$4999,$K44)) | O44: =IF($K44="","",L44+M44-N44) | Q44: =IF(数据录入!$B44="",0,IF(OR(数据录入!$D44="投标保证金",数据录入!$D44="合同履约保证金",ISNUMBER(FIND("保证金",数据录入!$E44))),1,0)) | R44: =IF(AND($Q44=1,数据录入!$B44>=$B$2,数据录入!$B44<=$D$2),N(R43)+1,N(R43)) | S44: =IFERROR(MATCH(37,$R$5:$R$4999,0),"") | U44: =IFERROR(IF(37<=50,INDEX(基础资料!$E$2:$E$51,37)&"",INDEX(基础资料!$G$2:$G$51,37-50)&""),"") | V44: =IF($U44="",0,IF(AND(37>50,COUNTIF(基础资料!$E$2:$E$51,$U44)>0),0,1)) | W44: =IF($V44=1,N(W43)+1,N(W43))
A45: =IF($S45="","",INDEX(数据录入!$B$5:$B$4999,$S45)) | B45: =IF($S45="","",INDEX(数据录入!$C$5:$C$4999,$S45)&"") | C45: =IF($S45="","",IF(N($F45)>0,"收款",IF(N($G45)>0,"付款",""))) | D45: =IF($S45="","",IF((INDEX(数据录入!$I$5:$I$4999,$S45)&"")<>"",INDEX(数据录入!$I$5:$I$4999,$S45)&"",INDEX(数据录入!$J$5:$J$4999,$S45)&"")) | E45: =IF($S45="","",INDEX(数据录入!$E$5:$E$4999,$S45)&"") | F45: =IF($S45="","",N(INDEX(数据录入!$F$5:$F$4999,$S45))) | G45: =IF($S45="","",N(INDEX(数据录入!$G$5:$G$4999,$S45))) | H45: =IF($S45="","",$G$2+SUM($F$8:$F45)-SUM($G$8:$G45)) | J45: =IF($K45="","",38) | K45: =IFERROR(INDEX($U$8:$U$107,MATCH(38,$W$8:$W$107,0)),"") | L45: =IF($K45="","",(SUMIFS(数据录入!$F$5:$F$4999,$Q$5:$Q$4999,1,数据录入!$B$5:$B$4999,"<"&$B$2,数据录入!$I$5:$I$4999,$K45)+SUMIFS(数据录入!$F$5:$F$4999,$Q$5:$Q$4999,1,数据录入!$B$5:$B$4999,"<"&$B$2,数据录入!$J$5:$J$4999,$K45))-(SUMIFS(数据录入!$G$5:$G$4999,$Q$5:$Q$4999,1,数据录入!$B$5:$B$4999,"<"&$B$2,数据录入!$I$5:$I$4999,$K45)+SUMIFS(数据录入!$G$5:$G$4999,$Q$5:$Q$4999,1,数据录入!$B$5:$B$4999,"<"&$B$2,数据录入!$J$5:$J$4999,$K45))) | M45: =IF($K45="","",SUMIFS(数据录入!$F$5:$F$4999,$Q$5:$Q$4999,1,数据录入!$B$5:$B$4999,">="&$B$2,数据录入!$B$5:$B$4999,"<="&$D$2,数据录入!$I$5:$I$4999,$K45)+SUMIFS(数据录入!$F$5:$F$4999,$Q$5:$Q$4999,1,数据录入!$B$5:$B$4999,">="&$B$2,数据录入!$B$5:$B$4999,"<="&$D$2,数据录入!$J$5:$J$4999,$K45)) | N45: =IF($K45="","",SUMIFS(数据录入!$G$5:$G$4999,$Q$5:$Q$4999,1,数据录入!$B$5:$B$4999,">="&$B$2,数据录入!$B$5:$B$4999,"<="&$D$2,数据录入!$I$5:$I$4999,$K45)+SUMIFS(数据录入!$G$5:$G$4999,$Q$5:$Q$4999,1,数据录入!$B$5:$B$4999,">="&$B$2,数据录入!$B$5:$B$4999,"<="&$D$2,数据录入!$J$5:$J$4999,$K45)) | O45: =IF($K45="","",L45+M45-N45) | Q45: =IF(数据录入!$B45="",0,IF(OR(数据录入!$D45="投标保证金",数据录入!$D45="合同履约保证金",ISNUMBER(FIND("保证金",数据录入!$E45))),1,0)) | R45: =IF(AND($Q45=1,数据录入!$B45>=$B$2,数据录入!$B45<=$D$2),N(R44)+1,N(R44)) | S45: =IFERROR(MATCH(38,$R$5:$R$4999,0),"") | U45: =IFERROR(IF(38<=50,INDEX(基础资料!$E$2:$E$51,38)&"",INDEX(基础资料!$G$2:$G$51,38-50)&""),"") | V45: =IF($U45="",0,IF(AND(38>50,COUNTIF(基础资料!$E$2:$E$51,$U45)>0),0,1)) | W45: =IF($V45=1,N(W44)+1,N(W44))
A46: =IF($S46="","",INDEX(数据录入!$B$5:$B$4999,$S46)) | B46: =IF($S46="","",INDEX(数据录入!$C$5:$C$4999,$S46)&"") | C46: =IF($S46="","",IF(N($F46)>0,"收款",IF(N($G46)>0,"付款",""))) | D46: =IF($S46="","",IF((INDEX(数据录入!$I$5:$I$4999,$S46)&"")<>"",INDEX(数据录入!$I$5:$I$4999,$S46)&"",INDEX(数据录入!$J$5:$J$4999,$S46)&"")) | E46: =IF($S46="","",INDEX(数据录入!$E$5:$E$4999,$S46)&"") | F46: =IF($S46="","",N(INDEX(数据录入!$F$5:$F$4999,$S46))) | G46: =IF($S46="","",N(INDEX(数据录入!$G$5:$G$4999,$S46))) | H46: =IF($S46="","",$G$2+SUM($F$8:$F46)-SUM($G$8:$G46)) | J46: =IF($K46="","",39) | K46: =IFERROR(INDEX($U$8:$U$107,MATCH(39,$W$8:$W$107,0)),"") | L46: =IF($K46="","",(SUMIFS(数据录入!$F$5:$F$4999,$Q$5:$Q$4999,1,数据录入!$B$5:$B$4999,"<"&$B$2,数据录入!$I$5:$I$4999,$K46)+SUMIFS(数据录入!$F$5:$F$4999,$Q$5:$Q$4999,1,数据录入!$B$5:$B$4999,"<"&$B$2,数据录入!$J$5:$J$4999,$K46))-(SUMIFS(数据录入!$G$5:$G$4999,$Q$5:$Q$4999,1,数据录入!$B$5:$B$4999,"<"&$B$2,数据录入!$I$5:$I$4999,$K46)+SUMIFS(数据录入!$G$5:$G$4999,$Q$5:$Q$4999,1,数据录入!$B$5:$B$4999,"<"&$B$2,数据录入!$J$5:$J$4999,$K46))) | M46: =IF($K46="","",SUMIFS(数据录入!$F$5:$F$4999,$Q$5:$Q$4999,1,数据录入!$B$5:$B$4999,">="&$B$2,数据录入!$B$5:$B$4999,"<="&$D$2,数据录入!$I$5:$I$4999,$K46)+SUMIFS(数据录入!$F$5:$F$4999,$Q$5:$Q$4999,1,数据录入!$B$5:$B$4999,">="&$B$2,数据录入!$B$5:$B$4999,"<="&$D$2,数据录入!$J$5:$J$4999,$K46)) | N46: =IF($K46="","",SUMIFS(数据录入!$G$5:$G$4999,$Q$5:$Q$4999,1,数据录入!$B$5:$B$4999,">="&$B$2,数据录入!$B$5:$B$4999,"<="&$D$2,数据录入!$I$5:$I$4999,$K46)+SUMIFS(数据录入!$G$5:$G$4999,$Q$5:$Q$4999,1,数据录入!$B$5:$B$4999,">="&$B$2,数据录入!$B$5:$B$4999,"<="&$D$2,数据录入!$J$5:$J$4999,$K46)) | O46: =IF($K46="","",L46+M46-N46) | Q46: =IF(数据录入!$B46="",0,IF(OR(数据录入!$D46="投标保证金",数据录入!$D46="合同履约保证金",ISNUMBER(FIND("保证金",数据录入!$E46))),1,0)) | R46: =IF(AND($Q46=1,数据录入!$B46>=$B$2,数据录入!$B46<=$D$2),N(R45)+1,N(R45)) | S46: =IFERROR(MATCH(39,$R$5:$R$4999,0),"") | U46: =IFERROR(IF(39<=50,INDEX(基础资料!$E$2:$E$51,39)&"",INDEX(基础资料!$G$2:$G$51,39-50)&""),"") | V46: =IF($U46="",0,IF(AND(39>50,COUNTIF(基础资料!$E$2:$E$51,$U46)>0),0,1)) | W46: =IF($V46=1,N(W45)+1,N(W45))
A47: =IF($S47="","",INDEX(数据录入!$B$5:$B$4999,$S47)) | B47: =IF($S47="","",INDEX(数据录入!$C$5:$C$4999,$S47)&"") | C47: =IF($S47="","",IF(N($F47)>0,"收款",IF(N($G47)>0,"付款",""))) | D47: =IF($S47="","",IF((INDEX(数据录入!$I$5:$I$4999,$S47)&"")<>"",INDEX(数据录入!$I$5:$I$4999,$S47)&"",INDEX(数据录入!$J$5:$J$4999,$S47)&"")) | E47: =IF($S47="","",INDEX(数据录入!$E$5:$E$4999,$S47)&"") | F47: =IF($S47="","",N(INDEX(数据录入!$F$5:$F$4999,$S47))) | G47: =IF($S47="","",N(INDEX(数据录入!$G$5:$G$4999,$S47))) | H47: =IF($S47="","",$G$2+SUM($F$8:$F47)-SUM($G$8:$G47)) | J47: =IF($K47="","",40) | K47: =IFERROR(INDEX($U$8:$U$107,MATCH(40,$W$8:$W$107,0)),"") | L47: =IF($K47="","",(SUMIFS(数据录入!$F$5:$F$4999,$Q$5:$Q$4999,1,数据录入!$B$5:$B$4999,"<"&$B$2,数据录入!$I$5:$I$4999,$K47)+SUMIFS(数据录入!$F$5:$F$4999,$Q$5:$Q$4999,1,数据录入!$B$5:$B$4999,"<"&$B$2,数据录入!$J$5:$J$4999,$K47))-(SUMIFS(数据录入!$G$5:$G$4999,$Q$5:$Q$4999,1,数据录入!$B$5:$B$4999,"<"&$B$2,数据录入!$I$5:$I$4999,$K47)+SUMIFS(数据录入!$G$5:$G$4999,$Q$5:$Q$4999,1,数据录入!$B$5:$B$4999,"<"&$B$2,数据录入!$J$5:$J$4999,$K47))) | M47: =IF($K47="","",SUMIFS(数据录入!$F$5:$F$4999,$Q$5:$Q$4999,1,数据录入!$B$5:$B$4999,">="&$B$2,数据录入!$B$5:$B$4999,"<="&$D$2,数据录入!$I$5:$I$4999,$K47)+SUMIFS(数据录入!$F$5:$F$4999,$Q$5:$Q$4999,1,数据录入!$B$5:$B$4999,">="&$B$2,数据录入!$B$5:$B$4999,"<="&$D$2,数据录入!$J$5:$J$4999,$K47)) | N47: =IF($K47="","",SUMIFS(数据录入!$G$5:$G$4999,$Q$5:$Q$4999,1,数据录入!$B$5:$B$4999,">="&$B$2,数据录入!$B$5:$B$4999,"<="&$D$2,数据录入!$I$5:$I$4999,$K47)+SUMIFS(数据录入!$G$5:$G$4999,$Q$5:$Q$4999,1,数据录入!$B$5:$B$4999,">="&$B$2,数据录入!$B$5:$B$4999,"<="&$D$2,数据录入!$J$5:$J$4999,$K47)) | O47: =IF($K47="","",L47+M47-N47) | Q47: =IF(数据录入!$B47="",0,IF(OR(数据录入!$D47="投标保证金",数据录入!$D47="合同履约保证金",ISNUMBER(FIND("保证金",数据录入!$E47))),1,0)) | R47: =IF(AND($Q47=1,数据录入!$B47>=$B$2,数据录入!$B47<=$D$2),N(R46)+1,N(R46)) | S47: =IFERROR(MATCH(40,$R$5:$R$4999,0),"") | U47: =IFERROR(IF(40<=50,INDEX(基础资料!$E$2:$E$51,40)&"",INDEX(基础资料!$G$2:$G$51,40-50)&""),"") | V47: =IF($U47="",0,IF(AND(40>50,COUNTIF(基础资料!$E$2:$E$51,$U47)>0),0,1)) | W47: =IF($V47=1,N(W46)+1,N(W46))
A48: =IF($S48="","",INDEX(数据录入!$B$5:$B$4999,$S48)) | B48: =IF($S48="","",INDEX(数据录入!$C$5:$C$4999,$S48)&"") | C48: =IF($S48="","",IF(N($F48)>0,"收款",IF(N($G48)>0,"付款",""))) | D48: =IF($S48="","",IF((INDEX(数据录入!$I$5:$I$4999,$S48)&"")<>"",INDEX(数据录入!$I$5:$I$4999,$S48)&"",INDEX(数据录入!$J$5:$J$4999,$S48)&"")) | E48: =IF($S48="","",INDEX(数据录入!$E$5:$E$4999,$S48)&"") | F48: =IF($S48="","",N(INDEX(数据录入!$F$5:$F$4999,$S48))) | G48: =IF($S48="","",N(INDEX(数据录入!$G$5:$G$4999,$S48))) | H48: =IF($S48="","",$G$2+SUM($F$8:$F48)-SUM($G$8:$G48)) | J48: =IF($K48="","",41) | K48: =IFERROR(INDEX($U$8:$U$107,MATCH(41,$W$8:$W$107,0)),"") | L48: =IF($K48="","",(SUMIFS(数据录入!$F$5:$F$4999,$Q$5:$Q$4999,1,数据录入!$B$5:$B$4999,"<"&$B$2,数据录入!$I$5:$I$4999,$K48)+SUMIFS(数据录入!$F$5:$F$4999,$Q$5:$Q$4999,1,数据录入!$B$5:$B$4999,"<"&$B$2,数据录入!$J$5:$J$4999,$K48))-(SUMIFS(数据录入!$G$5:$G$4999,$Q$5:$Q$4999,1,数据录入!$B$5:$B$4999,"<"&$B$2,数据录入!$I$5:$I$4999,$K48)+SUMIFS(数据录入!$G$5:$G$4999,$Q$5:$Q$4999,1,数据录入!$B$5:$B$4999,"<"&$B$2,数据录入!$J$5:$J$4999,$K48))) | M48: =IF($K48="","",SUMIFS(数据录入!$F$5:$F$4999,$Q$5:$Q$4999,1,数据录入!$B$5:$B$4999,">="&$B$2,数据录入!$B$5:$B$4999,"<="&$D$2,数据录入!$I$5:$I$4999,$K48)+SUMIFS(数据录入!$F$5:$F$4999,$Q$5:$Q$4999,1,数据录入!$B$5:$B$4999,">="&$B$2,数据录入!$B$5:$B$4999,"<="&$D$2,数据录入!$J$5:$J$4999,$K48)) | N48: =IF($K48="","",SUMIFS(数据录入!$G$5:$G$4999,$Q$5:$Q$4999,1,数据录入!$B$5:$B$4999,">="&$B$2,数据录入!$B$5:$B$4999,"<="&$D$2,数据录入!$I$5:$I$4999,$K48)+SUMIFS(数据录入!$G$5:$G$4999,$Q$5:$Q$4999,1,数据录入!$B$5:$B$4999,">="&$B$2,数据录入!$B$5:$B$4999,"<="&$D$2,数据录入!$J$5:$J$4999,$K48)) | O48: =IF($K48="","",L48+M48-N48) | Q48: =IF(数据录入!$B48="",0,IF(OR(数据录入!$D48="投标保证金",数据录入!$D48="合同履约保证金",ISNUMBER(FIND("保证金",数据录入!$E48))),1,0)) | R48: =IF(AND($Q48=1,数据录入!$B48>=$B$2,数据录入!$B48<=$D$2),N(R47)+1,N(R47)) | S48: =IFERROR(MATCH(41,$R$5:$R$4999,0),"") | U48: =IFERROR(IF(41<=50,INDEX(基础资料!$E$2:$E$51,41)&"",INDEX(基础资料!$G$2:$G$51,41-50)&""),"") | V48: =IF($U48="",0,IF(AND(41>50,COUNTIF(基础资料!$E$2:$E$51,$U48)>0),0,1)) | W48: =IF($V48=1,N(W47)+1,N(W47))
A49: =IF($S49="","",INDEX(数据录入!$B$5:$B$4999,$S49)) | B49: =IF($S49="","",INDEX(数据录入!$C$5:$C$4999,$S49)&"") | C49: =IF($S49="","",IF(N($F49)>0,"收款",IF(N($G49)>0,"付款",""))) | D49: =IF($S49="","",IF((INDEX(数据录入!$I$5:$I$4999,$S49)&"")<>"",INDEX(数据录入!$I$5:$I$4999,$S49)&"",INDEX(数据录入!$J$5:$J$4999,$S49)&"")) | E49: =IF($S49="","",INDEX(数据录入!$E$5:$E$4999,$S49)&"") | F49: =IF($S49="","",N(INDEX(数据录入!$F$5:$F$4999,$S49))) | G49: =IF($S49="","",N(INDEX(数据录入!$G$5:$G$4999,$S49))) | H49: =IF($S49="","",$G$2+SUM($F$8:$F49)-SUM($G$8:$G49)) | J49: =IF($K49="","",42) | K49: =IFERROR(INDEX($U$8:$U$107,MATCH(42,$W$8:$W$107,0)),"") | L49: =IF($K49="","",(SUMIFS(数据录入!$F$5:$F$4999,$Q$5:$Q$4999,1,数据录入!$B$5:$B$4999,"<"&$B$2,数据录入!$I$5:$I$4999,$K49)+SUMIFS(数据录入!$F$5:$F$4999,$Q$5:$Q$4999,1,数据录入!$B$5:$B$4999,"<"&$B$2,数据录入!$J$5:$J$4999,$K49))-(SUMIFS(数据录入!$G$5:$G$4999,$Q$5:$Q$4999,1,数据录入!$B$5:$B$4999,"<"&$B$2,数据录入!$I$5:$I$4999,$K49)+SUMIFS(数据录入!$G$5:$G$4999,$Q$5:$Q$4999,1,数据录入!$B$5:$B$4999,"<"&$B$2,数据录入!$J$5:$J$4999,$K49))) | M49: =IF($K49="","",SUMIFS(数据录入!$F$5:$F$4999,$Q$5:$Q$4999,1,数据录入!$B$5:$B$4999,">="&$B$2,数据录入!$B$5:$B$4999,"<="&$D$2,数据录入!$I$5:$I$4999,$K49)+SUMIFS(数据录入!$F$5:$F$4999,$Q$5:$Q$4999,1,数据录入!$B$5:$B$4999,">="&$B$2,数据录入!$B$5:$B$4999,"<="&$D$2,数据录入!$J$5:$J$4999,$K49)) | N49: =IF($K49="","",SUMIFS(数据录入!$G$5:$G$4999,$Q$5:$Q$4999,1,数据录入!$B$5:$B$4999,">="&$B$2,数据录入!$B$5:$B$4999,"<="&$D$2,数据录入!$I$5:$I$4999,$K49)+SUMIFS(数据录入!$G$5:$G$4999,$Q$5:$Q$4999,1,数据录入!$B$5:$B$4999,">="&$B$2,数据录入!$B$5:$B$4999,"<="&$D$2,数据录入!$J$5:$J$4999,$K49)) | O49: =IF($K49="","",L49+M49-N49) | Q49: =IF(数据录入!$B49="",0,IF(OR(数据录入!$D49="投标保证金",数据录入!$D49="合同履约保证金",ISNUMBER(FIND("保证金",数据录入!$E49))),1,0)) | R49: =IF(AND($Q49=1,数据录入!$B49>=$B$2,数据录入!$B49<=$D$2),N(R48)+1,N(R48)) | S49: =IFERROR(MATCH(42,$R$5:$R$4999,0),"") | U49: =IFERROR(IF(42<=50,INDEX(基础资料!$E$2:$E$51,42)&"",INDEX(基础资料!$G$2:$G$51,42-50)&""),"") | V49: =IF($U49="",0,IF(AND(42>50,COUNTIF(基础资料!$E$2:$E$51,$U49)>0),0,1)) | W49: =IF($V49=1,N(W48)+1,N(W48))
A50: =IF($S50="","",INDEX(数据录入!$B$5:$B$4999,$S50)) | B50: =IF($S50="","",INDEX(数据录入!$C$5:$C$4999,$S50)&"") | C50: =IF($S50="","",IF(N($F50)>0,"收款",IF(N($G50)>0,"付款",""))) | D50: =IF($S50="","",IF((INDEX(数据录入!$I$5:$I$4999,$S50)&"")<>"",INDEX(数据录入!$I$5:$I$4999,$S50)&"",INDEX(数据录入!$J$5:$J$4999,$S50)&"")) | E50: =IF($S50="","",INDEX(数据录入!$E$5:$E$4999,$S50)&"") | F50: =IF($S50="","",N(INDEX(数据录入!$F$5:$F$4999,$S50))) | G50: =IF($S50="","",N(INDEX(数据录入!$G$5:$G$4999,$S50))) | H50: =IF($S50="","",$G$2+SUM($F$8:$F50)-SUM($G$8:$G50)) | J50: =IF($K50="","",43) | K50: =IFERROR(INDEX($U$8:$U$107,MATCH(43,$W$8:$W$107,0)),"") | L50: =IF($K50="","",(SUMIFS(数据录入!$F$5:$F$4999,$Q$5:$Q$4999,1,数据录入!$B$5:$B$4999,"<"&$B$2,数据录入!$I$5:$I$4999,$K50)+SUMIFS(数据录入!$F$5:$F$4999,$Q$5:$Q$4999,1,数据录入!$B$5:$B$4999,"<"&$B$2,数据录入!$J$5:$J$4999,$K50))-(SUMIFS(数据录入!$G$5:$G$4999,$Q$5:$Q$4999,1,数据录入!$B$5:$B$4999,"<"&$B$2,数据录入!$I$5:$I$4999,$K50)+SUMIFS(数据录入!$G$5:$G$4999,$Q$5:$Q$4999,1,数据录入!$B$5:$B$4999,"<"&$B$2,数据录入!$J$5:$J$4999,$K50))) | M50: =IF($K50="","",SUMIFS(数据录入!$F$5:$F$4999,$Q$5:$Q$4999,1,数据录入!$B$5:$B$4999,">="&$B$2,数据录入!$B$5:$B$4999,"<="&$D$2,数据录入!$I$5:$I$4999,$K50)+SUMIFS(数据录入!$F$5:$F$4999,$Q$5:$Q$4999,1,数据录入!$B$5:$B$4999,">="&$B$2,数据录入!$B$5:$B$4999,"<="&$D$2,数据录入!$J$5:$J$4999,$K50)) | N50: =IF($K50="","",SUMIFS(数据录入!$G$5:$G$4999,$Q$5:$Q$4999,1,数据录入!$B$5:$B$4999,">="&$B$2,数据录入!$B$5:$B$4999,"<="&$D$2,数据录入!$I$5:$I$4999,$K50)+SUMIFS(数据录入!$G$5:$G$4999,$Q$5:$Q$4999,1,数据录入!$B$5:$B$4999,">="&$B$2,数据录入!$B$5:$B$4999,"<="&$D$2,数据录入!$J$5:$J$4999,$K50)) | O50: =IF($K50="","",L50+M50-N50) | Q50: =IF(数据录入!$B50="",0,IF(OR(数据录入!$D50="投标保证金",数据录入!$D50="合同履约保证金",ISNUMBER(FIND("保证金",数据录入!$E50))),1,0)) | R50: =IF(AND($Q50=1,数据录入!$B50>=$B$2,数据录入!$B50<=$D$2),N(R49)+1,N(R49)) | S50: =IFERROR(MATCH(43,$R$5:$R$4999,0),"") | U50: =IFERROR(IF(43<=50,INDEX(基础资料!$E$2:$E$51,43)&"",INDEX(基础资料!$G$2:$G$51,43-50)&""),"") | V50: =IF($U50="",0,IF(AND(43>50,COUNTIF(基础资料!$E$2:$E$51,$U50)>0),0,1)) | W50: =IF($V50=1,N(W49)+1,N(W49))
A51: =IF($S51="","",INDEX(数据录入!$B$5:$B$4999,$S51)) | B51: =IF($S51="","",INDEX(数据录入!$C$5:$C$4999,$S51)&"") | C51: =IF($S51="","",IF(N($F51)>0,"收款",IF(N($G51)>0,"付款",""))) | D51: =IF($S51="","",IF((INDEX(数据录入!$I$5:$I$4999,$S51)&"")<>"",INDEX(数据录入!$I$5:$I$4999,$S51)&"",INDEX(数据录入!$J$5:$J$4999,$S51)&"")) | E51: =IF($S51="","",INDEX(数据录入!$E$5:$E$4999,$S51)&"") | F51: =IF($S51="","",N(INDEX(数据录入!$F$5:$F$4999,$S51))) | G51: =IF($S51="","",N(INDEX(数据录入!$G$5:$G$4999,$S51))) | H51: =IF($S51="","",$G$2+SUM($F$8:$F51)-SUM($G$8:$G51)) | J51: =IF($K51="","",44) | K51: =IFERROR(INDEX($U$8:$U$107,MATCH(44,$W$8:$W$107,0)),"") | L51: =IF($K51="","",(SUMIFS(数据录入!$F$5:$F$4999,$Q$5:$Q$4999,1,数据录入!$B$5:$B$4999,"<"&$B$2,数据录入!$I$5:$I$4999,$K51)+SUMIFS(数据录入!$F$5:$F$4999,$Q$5:$Q$4999,1,数据录入!$B$5:$B$4999,"<"&$B$2,数据录入!$J$5:$J$4999,$K51))-(SUMIFS(数据录入!$G$5:$G$4999,$Q$5:$Q$4999,1,数据录入!$B$5:$B$4999,"<"&$B$2,数据录入!$I$5:$I$4999,$K51)+SUMIFS(数据录入!$G$5:$G$4999,$Q$5:$Q$4999,1,数据录入!$B$5:$B$4999,"<"&$B$2,数据录入!$J$5:$J$4999,$K51))) | M51: =IF($K51="","",SUMIFS(数据录入!$F$5:$F$4999,$Q$5:$Q$4999,1,数据录入!$B$5:$B$4999,">="&$B$2,数据录入!$B$5:$B$4999,"<="&$D$2,数据录入!$I$5:$I$4999,$K51)+SUMIFS(数据录入!$F$5:$F$4999,$Q$5:$Q$4999,1,数据录入!$B$5:$B$4999,">="&$B$2,数据录入!$B$5:$B$4999,"<="&$D$2,数据录入!$J$5:$J$4999,$K51)) | N51: =IF($K51="","",SUMIFS(数据录入!$G$5:$G$4999,$Q$5:$Q$4999,1,数据录入!$B$5:$B$4999,">="&$B$2,数据录入!$B$5:$B$4999,"<="&$D$2,数据录入!$I$5:$I$4999,$K51)+SUMIFS(数据录入!$G$5:$G$4999,$Q$5:$Q$4999,1,数据录入!$B$5:$B$4999,">="&$B$2,数据录入!$B$5:$B$4999,"<="&$D$2,数据录入!$J$5:$J$4999,$K51)) | O51: =IF($K51="","",L51+M51-N51) | Q51: =IF(数据录入!$B51="",0,IF(OR(数据录入!$D51="投标保证金",数据录入!$D51="合同履约保证金",ISNUMBER(FIND("保证金",数据录入!$E51))),1,0)) | R51: =IF(AND($Q51=1,数据录入!$B51>=$B$2,数据录入!$B51<=$D$2),N(R50)+1,N(R50)) | S51: =IFERROR(MATCH(44,$R$5:$R$4999,0),"") | U51: =IFERROR(IF(44<=50,INDEX(基础资料!$E$2:$E$51,44)&"",INDEX(基础资料!$G$2:$G$51,44-50)&""),"") | V51: =IF($U51="",0,IF(AND(44>50,COUNTIF(基础资料!$E$2:$E$51,$U51)>0),0,1)) | W51: =IF($V51=1,N(W50)+1,N(W50))
A52: =IF($S52="","",INDEX(数据录入!$B$5:$B$4999,$S52)) | B52: =IF($S52="","",INDEX(数据录入!$C$5:$C$4999,$S52)&"") | C52: =IF($S52="","",IF(N($F52)>0,"收款",IF(N($G52)>0,"付款",""))) | D52: =IF($S52="","",IF((INDEX(数据录入!$I$5:$I$4999,$S52)&"")<>"",INDEX(数据录入!$I$5:$I$4999,$S52)&"",INDEX(数据录入!$J$5:$J$4999,$S52)&"")) | E52: =IF($S52="","",INDEX(数据录入!$E$5:$E$4999,$S52)&"") | F52: =IF($S52="","",N(INDEX(数据录入!$F$5:$F$4999,$S52))) | G52: =IF($S52="","",N(INDEX(数据录入!$G$5:$G$4999,$S52))) | H52: =IF($S52="","",$G$2+SUM($F$8:$F52)-SUM($G$8:$G52)) | J52: =IF($K52="","",45) | K52: =IFERROR(INDEX($U$8:$U$107,MATCH(45,$W$8:$W$107,0)),"") | L52: =IF($K52="","",(SUMIFS(数据录入!$F$5:$F$4999,$Q$5:$Q$4999,1,数据录入!$B$5:$B$4999,"<"&$B$2,数据录入!$I$5:$I$4999,$K52)+SUMIFS(数据录入!$F$5:$F$4999,$Q$5:$Q$4999,1,数据录入!$B$5:$B$4999,"<"&$B$2,数据录入!$J$5:$J$4999,$K52))-(SUMIFS(数据录入!$G$5:$G$4999,$Q$5:$Q$4999,1,数据录入!$B$5:$B$4999,"<"&$B$2,数据录入!$I$5:$I$4999,$K52)+SUMIFS(数据录入!$G$5:$G$4999,$Q$5:$Q$4999,1,数据录入!$B$5:$B$4999,"<"&$B$2,数据录入!$J$5:$J$4999,$K52))) | M52: =IF($K52="","",SUMIFS(数据录入!$F$5:$F$4999,$Q$5:$Q$4999,1,数据录入!$B$5:$B$4999,">="&$B$2,数据录入!$B$5:$B$4999,"<="&$D$2,数据录入!$I$5:$I$4999,$K52)+SUMIFS(数据录入!$F$5:$F$4999,$Q$5:$Q$4999,1,数据录入!$B$5:$B$4999,">="&$B$2,数据录入!$B$5:$B$4999,"<="&$D$2,数据录入!$J$5:$J$4999,$K52)) | N52: =IF($K52="","",SUMIFS(数据录入!$G$5:$G$4999,$Q$5:$Q$4999,1,数据录入!$B$5:$B$4999,">="&$B$2,数据录入!$B$5:$B$4999,"<="&$D$2,数据录入!$I$5:$I$4999,$K52)+SUMIFS(数据录入!$G$5:$G$4999,$Q$5:$Q$4999,1,数据录入!$B$5:$B$4999,">="&$B$2,数据录入!$B$5:$B$4999,"<="&$D$2,数据录入!$J$5:$J$4999,$K52)) | O52: =IF($K52="","",L52+M52-N52) | Q52: =IF(数据录入!$B52="",0,IF(OR(数据录入!$D52="投标保证金",数据录入!$D52="合同履约保证金",ISNUMBER(FIND("保证金",数据录入!$E52))),1,0)) | R52: =IF(AND($Q52=1,数据录入!$B52>=$B$2,数据录入!$B52<=$D$2),N(R51)+1,N(R51)) | S52: =IFERROR(MATCH(45,$R$5:$R$4999,0),"") | U52: =IFERROR(IF(45<=50,INDEX(基础资料!$E$2:$E$51,45)&"",INDEX(基础资料!$G$2:$G$51,45-50)&""),"") | V52: =IF($U52="",0,IF(AND(45>50,COUNTIF(基础资料!$E$2:$E$51,$U52)>0),0,1)) | W52: =IF($V52=1,N(W51)+1,N(W51))
A53: =IF($S53="","",INDEX(数据录入!$B$5:$B$4999,$S53)) | B53: =IF($S53="","",INDEX(数据录入!$C$5:$C$4999,$S53)&"") | C53: =IF($S53="","",IF(N($F53)>0,"收款",IF(N($G53)>0,"付款",""))) | D53: =IF($S53="","",IF((INDEX(数据录入!$I$5:$I$4999,$S53)&"")<>"",INDEX(数据录入!$I$5:$I$4999,$S53)&"",INDEX(数据录入!$J$5:$J$4999,$S53)&"")) | E53: =IF($S53="","",INDEX(数据录入!$E$5:$E$4999,$S53)&"") | F53: =IF($S53="","",N(INDEX(数据录入!$F$5:$F$4999,$S53))) | G53: =IF($S53="","",N(INDEX(数据录入!$G$5:$G$4999,$S53))) | H53: =IF($S53="","",$G$2+SUM($F$8:$F53)-SUM($G$8:$G53)) | J53: =IF($K53="","",46) | K53: =IFERROR(INDEX($U$8:$U$107,MATCH(46,$W$8:$W$107,0)),"") | L53: =IF($K53="","",(SUMIFS(数据录入!$F$5:$F$4999,$Q$5:$Q$4999,1,数据录入!$B$5:$B$4999,"<"&$B$2,数据录入!$I$5:$I$4999,$K53)+SUMIFS(数据录入!$F$5:$F$4999,$Q$5:$Q$4999,1,数据录入!$B$5:$B$4999,"<"&$B$2,数据录入!$J$5:$J$4999,$K53))-(SUMIFS(数据录入!$G$5:$G$4999,$Q$5:$Q$4999,1,数据录入!$B$5:$B$4999,"<"&$B$2,数据录入!$I$5:$I$4999,$K53)+SUMIFS(数据录入!$G$5:$G$4999,$Q$5:$Q$4999,1,数据录入!$B$5:$B$4999,"<"&$B$2,数据录入!$J$5:$J$4999,$K53))) | M53: =IF($K53="","",SUMIFS(数据录入!$F$5:$F$4999,$Q$5:$Q$4999,1,数据录入!$B$5:$B$4999,">="&$B$2,数据录入!$B$5:$B$4999,"<="&$D$2,数据录入!$I$5:$I$4999,$K53)+SUMIFS(数据录入!$F$5:$F$4999,$Q$5:$Q$4999,1,数据录入!$B$5:$B$4999,">="&$B$2,数据录入!$B$5:$B$4999,"<="&$D$2,数据录入!$J$5:$J$4999,$K53)) | N53: =IF($K53="","",SUMIFS(数据录入!$G$5:$G$4999,$Q$5:$Q$4999,1,数据录入!$B$5:$B$4999,">="&$B$2,数据录入!$B$5:$B$4999,"<="&$D$2,数据录入!$I$5:$I$4999,$K53)+SUMIFS(数据录入!$G$5:$G$4999,$Q$5:$Q$4999,1,数据录入!$B$5:$B$4999,">="&$B$2,数据录入!$B$5:$B$4999,"<="&$D$2,数据录入!$J$5:$J$4999,$K53)) | O53: =IF($K53="","",L53+M53-N53) | Q53: =IF(数据录入!$B53="",0,IF(OR(数据录入!$D53="投标保证金",数据录入!$D53="合同履约保证金",ISNUMBER(FIND("保证金",数据录入!$E53))),1,0)) | R53: =IF(AND($Q53=1,数据录入!$B53>=$B$2,数据录入!$B53<=$D$2),N(R52)+1,N(R52)) | S53: =IFERROR(MATCH(46,$R$5:$R$4999,0),"") | U53: =IFERROR(IF(46<=50,INDEX(基础资料!$E$2:$E$51,46)&"",INDEX(基础资料!$G$2:$G$51,46-50)&""),"") | V53: =IF($U53="",0,IF(AND(46>50,COUNTIF(基础资料!$E$2:$E$51,$U53)>0),0,1)) | W53: =IF($V53=1,N(W52)+1,N(W52))
A54: =IF($S54="","",INDEX(数据录入!$B$5:$B$4999,$S54)) | B54: =IF($S54="","",INDEX(数据录入!$C$5:$C$4999,$S54)&"") | C54: =IF($S54="","",IF(N($F54)>0,"收款",IF(N($G54)>0,"付款",""))) | D54: =IF($S54="","",IF((INDEX(数据录入!$I$5:$I$4999,$S54)&"")<>"",INDEX(数据录入!$I$5:$I$4999,$S54)&"",INDEX(数据录入!$J$5:$J$4999,$S54)&"")) | E54: =IF($S54="","",INDEX(数据录入!$E$5:$E$4999,$S54)&"") | F54: =IF($S54="","",N(INDEX(数据录入!$F$5:$F$4999,$S54))) | G54: =IF($S54="","",N(INDEX(数据录入!$G$5:$G$4999,$S54))) | H54: =IF($S54="","",$G$2+SUM($F$8:$F54)-SUM($G$8:$G54)) | J54: =IF($K54="","",47) | K54: =IFERROR(INDEX($U$8:$U$107,MATCH(47,$W$8:$W$107,0)),"") | L54: =IF($K54="","",(SUMIFS(数据录入!$F$5:$F$4999,$Q$5:$Q$4999,1,数据录入!$B$5:$B$4999,"<"&$B$2,数据录入!$I$5:$I$4999,$K54)+SUMIFS(数据录入!$F$5:$F$4999,$Q$5:$Q$4999,1,数据录入!$B$5:$B$4999,"<"&$B$2,数据录入!$J$5:$J$4999,$K54))-(SUMIFS(数据录入!$G$5:$G$4999,$Q$5:$Q$4999,1,数据录入!$B$5:$B$4999,"<"&$B$2,数据录入!$I$5:$I$4999,$K54)+SUMIFS(数据录入!$G$5:$G$4999,$Q$5:$Q$4999,1,数据录入!$B$5:$B$4999,"<"&$B$2,数据录入!$J$5:$J$4999,$K54))) | M54: =IF($K54="","",SUMIFS(数据录入!$F$5:$F$4999,$Q$5:$Q$4999,1,数据录入!$B$5:$B$4999,">="&$B$2,数据录入!$B$5:$B$4999,"<="&$D$2,数据录入!$I$5:$I$4999,$K54)+SUMIFS(数据录入!$F$5:$F$4999,$Q$5:$Q$4999,1,数据录入!$B$5:$B$4999,">="&$B$2,数据录入!$B$5:$B$4999,"<="&$D$2,数据录入!$J$5:$J$4999,$K54)) | N54: =IF($K54="","",SUMIFS(数据录入!$G$5:$G$4999,$Q$5:$Q$4999,1,数据录入!$B$5:$B$4999,">="&$B$2,数据录入!$B$5:$B$4999,"<="&$D$2,数据录入!$I$5:$I$4999,$K54)+SUMIFS(数据录入!$G$5:$G$4999,$Q$5:$Q$4999,1,数据录入!$B$5:$B$4999,">="&$B$2,数据录入!$B$5:$B$4999,"<="&$D$2,数据录入!$J$5:$J$4999,$K54)) | O54: =IF($K54="","",L54+M54-N54) | Q54: =IF(数据录入!$B54="",0,IF(OR(数据录入!$D54="投标保证金",数据录入!$D54="合同履约保证金",ISNUMBER(FIND("保证金",数据录入!$E54))),1,0)) | R54: =IF(AND($Q54=1,数据录入!$B54>=$B$2,数据录入!$B54<=$D$2),N(R53)+1,N(R53)) | S54: =IFERROR(MATCH(47,$R$5:$R$4999,0),"") | U54: =IFERROR(IF(47<=50,INDEX(基础资料!$E$2:$E$51,47)&"",INDEX(基础资料!$G$2:$G$51,47-50)&""),"") | V54: =IF($U54="",0,IF(AND(47>50,COUNTIF(基础资料!$E$2:$E$51,$U54)>0),0,1)) | W54: =IF($V54=1,N(W53)+1,N(W53))
A55: =IF($S55="","",INDEX(数据录入!$B$5:$B$4999,$S55)) | B55: =IF($S55="","",INDEX(数据录入!$C$5:$C$4999,$S55)&"") | C55: =IF($S55="","",IF(N($F55)>0,"收款",IF(N($G55)>0,"付款",""))) | D55: =IF($S55="","",IF((INDEX(数据录入!$I$5:$I$4999,$S55)&"")<>"",INDEX(数据录入!$I$5:$I$4999,$S55)&"",INDEX(数据录入!$J$5:$J$4999,$S55)&"")) | E55: =IF($S55="","",INDEX(数据录入!$E$5:$E$4999,$S55)&"") | F55: =IF($S55="","",N(INDEX(数据录入!$F$5:$F$4999,$S55))) | G55: =IF($S55="","",N(INDEX(数据录入!$G$5:$G$4999,$S55))) | H55: =IF($S55="","",$G$2+SUM($F$8:$F55)-SUM($G$8:$G55)) | J55: =IF($K55="","",48) | K55: =IFERROR(INDEX($U$8:$U$107,MATCH(48,$W$8:$W$107,0)),"") | L55: =IF($K55="","",(SUMIFS(数据录入!$F$5:$F$4999,$Q$5:$Q$4999,1,数据录入!$B$5:$B$4999,"<"&$B$2,数据录入!$I$5:$I$4999,$K55)+SUMIFS(数据录入!$F$5:$F$4999,$Q$5:$Q$4999,1,数据录入!$B$5:$B$4999,"<"&$B$2,数据录入!$J$5:$J$4999,$K55))-(SUMIFS(数据录入!$G$5:$G$4999,$Q$5:$Q$4999,1,数据录入!$B$5:$B$4999,"<"&$B$2,数据录入!$I$5:$I$4999,$K55)+SUMIFS(数据录入!$G$5:$G$4999,$Q$5:$Q$4999,1,数据录入!$B$5:$B$4999,"<"&$B$2,数据录入!$J$5:$J$4999,$K55))) | M55: =IF($K55="","",SUMIFS(数据录入!$F$5:$F$4999,$Q$5:$Q$4999,1,数据录入!$B$5:$B$4999,">="&$B$2,数据录入!$B$5:$B$4999,"<="&$D$2,数据录入!$I$5:$I$4999,$K55)+SUMIFS(数据录入!$F$5:$F$4999,$Q$5:$Q$4999,1,数据录入!$B$5:$B$4999,">="&$B$2,数据录入!$B$5:$B$4999,"<="&$D$2,数据录入!$J$5:$J$4999,$K55)) | N55: =IF($K55="","",SUMIFS(数据录入!$G$5:$G$4999,$Q$5:$Q$4999,1,数据录入!$B$5:$B$4999,">="&$B$2,数据录入!$B$5:$B$4999,"<="&$D$2,数据录入!$I$5:$I$4999,$K55)+SUMIFS(数据录入!$G$5:$G$4999,$Q$5:$Q$4999,1,数据录入!$B$5:$B$4999,">="&$B$2,数据录入!$B$5:$B$4999,"<="&$D$2,数据录入!$J$5:$J$4999,$K55)) | O55: =IF($K55="","",L55+M55-N55) | Q55: =IF(数据录入!$B55="",0,IF(OR(数据录入!$D55="投标保证金",数据录入!$D55="合同履约保证金",ISNUMBER(FIND("保证金",数据录入!$E55))),1,0)) | R55: =IF(AND($Q55=1,数据录入!$B55>=$B$2,数据录入!$B55<=$D$2),N(R54)+1,N(R54)) | S55: =IFERROR(MATCH(48,$R$5:$R$4999,0),"") | U55: =IFERROR(IF(48<=50,INDEX(基础资料!$E$2:$E$51,48)&"",INDEX(基础资料!$G$2:$G$51,48-50)&""),"") | V55: =IF($U55="",0,IF(AND(48>50,COUNTIF(基础资料!$E$2:$E$51,$U55)>0),0,1)) | W55: =IF($V55=1,N(W54)+1,N(W54))
A56: =IF($S56="","",INDEX(数据录入!$B$5:$B$4999,$S56)) | B56: =IF($S56="","",INDEX(数据录入!$C$5:$C$4999,$S56)&"") | C56: =IF($S56="","",IF(N($F56)>0,"收款",IF(N($G56)>0,"付款",""))) | D56: =IF($S56="","",IF((INDEX(数据录入!$I$5:$I$4999,$S56)&"")<>"",INDEX(数据录入!$I$5:$I$4999,$S56)&"",INDEX(数据录入!$J$5:$J$4999,$S56)&"")) | E56: =IF($S56="","",INDEX(数据录入!$E$5:$E$4999,$S56)&"") | F56: =IF($S56="","",N(INDEX(数据录入!$F$5:$F$4999,$S56))) | G56: =IF($S56="","",N(INDEX(数据录入!$G$5:$G$4999,$S56))) | H56: =IF($S56="","",$G$2+SUM($F$8:$F56)-SUM($G$8:$G56)) | J56: =IF($K56="","",49) | K56: =IFERROR(INDEX($U$8:$U$107,MATCH(49,$W$8:$W$107,0)),"") | L56: =IF($K56="","",(SUMIFS(数据录入!$F$5:$F$4999,$Q$5:$Q$4999,1,数据录入!$B$5:$B$4999,"<"&$B$2,数据录入!$I$5:$I$4999,$K56)+SUMIFS(数据录入!$F$5:$F$4999,$Q$5:$Q$4999,1,数据录入!$B$5:$B$4999,"<"&$B$2,数据录入!$J$5:$J$4999,$K56))-(SUMIFS(数据录入!$G$5:$G$4999,$Q$5:$Q$4999,1,数据录入!$B$5:$B$4999,"<"&$B$2,数据录入!$I$5:$I$4999,$K56)+SUMIFS(数据录入!$G$5:$G$4999,$Q$5:$Q$4999,1,数据录入!$B$5:$B$4999,"<"&$B$2,数据录入!$J$5:$J$4999,$K56))) | M56: =IF($K56="","",SUMIFS(数据录入!$F$5:$F$4999,$Q$5:$Q$4999,1,数据录入!$B$5:$B$4999,">="&$B$2,数据录入!$B$5:$B$4999,"<="&$D$2,数据录入!$I$5:$I$4999,$K56)+SUMIFS(数据录入!$F$5:$F$4999,$Q$5:$Q$4999,1,数据录入!$B$5:$B$4999,">="&$B$2,数据录入!$B$5:$B$4999,"<="&$D$2,数据录入!$J$5:$J$4999,$K56)) | N56: =IF($K56="","",SUMIFS(数据录入!$G$5:$G$4999,$Q$5:$Q$4999,1,数据录入!$B$5:$B$4999,">="&$B$2,数据录入!$B$5:$B$4999,"<="&$D$2,数据录入!$I$5:$I$4999,$K56)+SUMIFS(数据录入!$G$5:$G$4999,$Q$5:$Q$4999,1,数据录入!$B$5:$B$4999,">="&$B$2,数据录入!$B$5:$B$4999,"<="&$D$2,数据录入!$J$5:$J$4999,$K56)) | O56: =IF($K56="","",L56+M56-N56) | Q56: =IF(数据录入!$B56="",0,IF(OR(数据录入!$D56="投标保证金",数据录入!$D56="合同履约保证金",ISNUMBER(FIND("保证金",数据录入!$E56))),1,0)) | R56: =IF(AND($Q56=1,数据录入!$B56>=$B$2,数据录入!$B56<=$D$2),N(R55)+1,N(R55)) | S56: =IFERROR(MATCH(49,$R$5:$R$4999,0),"") | U56: =IFERROR(IF(49<=50,INDEX(基础资料!$E$2:$E$51,49)&"",INDEX(基础资料!$G$2:$G$51,49-50)&""),"") | V56: =IF($U56="",0,IF(AND(49>50,COUNTIF(基础资料!$E$2:$E$51,$U56)>0),0,1)) | W56: =IF($V56=1,N(W55)+1,N(W55))
A57: =IF($S57="","",INDEX(数据录入!$B$5:$B$4999,$S57)) | B57: =IF($S57="","",INDEX(数据录入!$C$5:$C$4999,$S57)&"") | C57: =IF($S57="","",IF(N($F57)>0,"收款",IF(N($G57)>0,"付款",""))) | D57: =IF($S57="","",IF((INDEX(数据录入!$I$5:$I$4999,$S57)&"")<>"",INDEX(数据录入!$I$5:$I$4999,$S57)&"",INDEX(数据录入!$J$5:$J$4999,$S57)&"")) | E57: =IF($S57="","",INDEX(数据录入!$E$5:$E$4999,$S57)&"") | F57: =IF($S57="","",N(INDEX(数据录入!$F$5:$F$4999,$S57))) | G57: =IF($S57="","",N(INDEX(数据录入!$G$5:$G$4999,$S57))) | H57: =IF($S57="","",$G$2+SUM($F$8:$F57)-SUM($G$8:$G57)) | J57: =IF($K57="","",50) | K57: =IFERROR(INDEX($U$8:$U$107,MATCH(50,$W$8:$W$107,0)),"") | L57: =IF($K57="","",(SUMIFS(数据录入!$F$5:$F$4999,$Q$5:$Q$4999,1,数据录入!$B$5:$B$4999,"<"&$B$2,数据录入!$I$5:$I$4999,$K57)+SUMIFS(数据录入!$F$5:$F$4999,$Q$5:$Q$4999,1,数据录入!$B$5:$B$4999,"<"&$B$2,数据录入!$J$5:$J$4999,$K57))-(SUMIFS(数据录入!$G$5:$G$4999,$Q$5:$Q$4999,1,数据录入!$B$5:$B$4999,"<"&$B$2,数据录入!$I$5:$I$4999,$K57)+SUMIFS(数据录入!$G$5:$G$4999,$Q$5:$Q$4999,1,数据录入!$B$5:$B$4999,"<"&$B$2,数据录入!$J$5:$J$4999,$K57))) | M57: =IF($K57="","",SUMIFS(数据录入!$F$5:$F$4999,$Q$5:$Q$4999,1,数据录入!$B$5:$B$4999,">="&$B$2,数据录入!$B$5:$B$4999,"<="&$D$2,数据录入!$I$5:$I$4999,$K57)+SUMIFS(数据录入!$F$5:$F$4999,$Q$5:$Q$4999,1,数据录入!$B$5:$B$4999,">="&$B$2,数据录入!$B$5:$B$4999,"<="&$D$2,数据录入!$J$5:$J$4999,$K57)) | N57: =IF($K57="","",SUMIFS(数据录入!$G$5:$G$4999,$Q$5:$Q$4999,1,数据录入!$B$5:$B$4999,">="&$B$2,数据录入!$B$5:$B$4999,"<="&$D$2,数据录入!$I$5:$I$4999,$K57)+SUMIFS(数据录入!$G$5:$G$4999,$Q$5:$Q$4999,1,数据录入!$B$5:$B$4999,">="&$B$2,数据录入!$B$5:$B$4999,"<="&$D$2,数据录入!$J$5:$J$4999,$K57)) | O57: =IF($K57="","",L57+M57-N57) | Q57: =IF(数据录入!$B57="",0,IF(OR(数据录入!$D57="投标保证金",数据录入!$D57="合同履约保证金",ISNUMBER(FIND("保证金",数据录入!$E57))),1,0)) | R57: =IF(AND($Q57=1,数据录入!$B57>=$B$2,数据录入!$B57<=$D$2),N(R56)+1,N(R56)) | S57: =IFERROR(MATCH(50,$R$5:$R$4999,0),"") | U57: =IFERROR(IF(50<=50,INDEX(基础资料!$E$2:$E$51,50)&"",INDEX(基础资料!$G$2:$G$51,50-50)&""),"") | V57: =IF($U57="",0,IF(AND(50>50,COUNTIF(基础资料!$E$2:$E$51,$U57)>0),0,1)) | W57: =IF($V57=1,N(W56)+1,N(W56))
A58: =IF($S58="","",INDEX(数据录入!$B$5:$B$4999,$S58)) | B58: =IF($S58="","",INDEX(数据录入!$C$5:$C$4999,$S58)&"") | C58: =IF($S58="","",IF(N($F58)>0,"收款",IF(N($G58)>0,"付款",""))) | D58: =IF($S58="","",IF((INDEX(数据录入!$I$5:$I$4999,$S58)&"")<>"",INDEX(数据录入!$I$5:$I$4999,$S58)&"",INDEX(数据录入!$J$5:$J$4999,$S58)&"")) | E58: =IF($S58="","",INDEX(数据录入!$E$5:$E$4999,$S58)&"") | F58: =IF($S58="","",N(INDEX(数据录入!$F$5:$F$4999,$S58))) | G58: =IF($S58="","",N(INDEX(数据录入!$G$5:$G$4999,$S58))) | H58: =IF($S58="","",$G$2+SUM($F$8:$F58)-SUM($G$8:$G58)) | J58: =IF($K58="","",51) | K58: =IFERROR(INDEX($U$8:$U$107,MATCH(51,$W$8:$W$107,0)),"") | L58: =IF($K58="","",(SUMIFS(数据录入!$F$5:$F$4999,$Q$5:$Q$4999,1,数据录入!$B$5:$B$4999,"<"&$B$2,数据录入!$I$5:$I$4999,$K58)+SUMIFS(数据录入!$F$5:$F$4999,$Q$5:$Q$4999,1,数据录入!$B$5:$B$4999,"<"&$B$2,数据录入!$J$5:$J$4999,$K58))-(SUMIFS(数据录入!$G$5:$G$4999,$Q$5:$Q$4999,1,数据录入!$B$5:$B$4999,"<"&$B$2,数据录入!$I$5:$I$4999,$K58)+SUMIFS(数据录入!$G$5:$G$4999,$Q$5:$Q$4999,1,数据录入!$B$5:$B$4999,"<"&$B$2,数据录入!$J$5:$J$4999,$K58))) | M58: =IF($K58="","",SUMIFS(数据录入!$F$5:$F$4999,$Q$5:$Q$4999,1,数据录入!$B$5:$B$4999,">="&$B$2,数据录入!$B$5:$B$4999,"<="&$D$2,数据录入!$I$5:$I$4999,$K58)+SUMIFS(数据录入!$F$5:$F$4999,$Q$5:$Q$4999,1,数据录入!$B$5:$B$4999,">="&$B$2,数据录入!$B$5:$B$4999,"<="&$D$2,数据录入!$J$5:$J$4999,$K58)) | N58: =IF($K58="","",SUMIFS(数据录入!$G$5:$G$4999,$Q$5:$Q$4999,1,数据录入!$B$5:$B$4999,">="&$B$2,数据录入!$B$5:$B$4999,"<="&$D$2,数据录入!$I$5:$I$4999,$K58)+SUMIFS(数据录入!$G$5:$G$4999,$Q$5:$Q$4999,1,数据录入!$B$5:$B$4999,">="&$B$2,数据录入!$B$5:$B$4999,"<="&$D$2,数据录入!$J$5:$J$4999,$K58)) | O58: =IF($K58="","",L58+M58-N58) | Q58: =IF(数据录入!$B58="",0,IF(OR(数据录入!$D58="投标保证金",数据录入!$D58="合同履约保证金",ISNUMBER(FIND("保证金",数据录入!$E58))),1,0)) | R58: =IF(AND($Q58=1,数据录入!$B58>=$B$2,数据录入!$B58<=$D$2),N(R57)+1,N(R57)) | S58: =IFERROR(MATCH(51,$R$5:$R$4999,0),"") | U58: =IFERROR(IF(51<=50,INDEX(基础资料!$E$2:$E$51,51)&"",INDEX(基础资料!$G$2:$G$51,51-50)&""),"") | V58: =IF($U58="",0,IF(AND(51>50,COUNTIF(基础资料!$E$2:$E$51,$U58)>0),0,1)) | W58: =IF($V58=1,N(W57)+1,N(W57))
A59: =IF($S59="","",INDEX(数据录入!$B$5:$B$4999,$S59)) | B59: =IF($S59="","",INDEX(数据录入!$C$5:$C$4999,$S59)&"") | C59: =IF($S59="","",IF(N($F59)>0,"收款",IF(N($G59)>0,"付款",""))) | D59: =IF($S59="","",IF((INDEX(数据录入!$I$5:$I$4999,$S59)&"")<>"",INDEX(数据录入!$I$5:$I$4999,$S59)&"",INDEX(数据录入!$J$5:$J$4999,$S59)&"")) | E59: =IF($S59="","",INDEX(数据录入!$E$5:$E$4999,$S59)&"") | F59: =IF($S59="","",N(INDEX(数据录入!$F$5:$F$4999,$S59))) | G59: =IF($S59="","",N(INDEX(数据录入!$G$5:$G$4999,$S59))) | H59: =IF($S59="","",$G$2+SUM($F$8:$F59)-SUM($G$8:$G59)) | J59: =IF($K59="","",52) | K59: =IFERROR(INDEX($U$8:$U$107,MATCH(52,$W$8:$W$107,0)),"") | L59: =IF($K59="","",(SUMIFS(数据录入!$F$5:$F$4999,$Q$5:$Q$4999,1,数据录入!$B$5:$B$4999,"<"&$B$2,数据录入!$I$5:$I$4999,$K59)+SUMIFS(数据录入!$F$5:$F$4999,$Q$5:$Q$4999,1,数据录入!$B$5:$B$4999,"<"&$B$2,数据录入!$J$5:$J$4999,$K59))-(SUMIFS(数据录入!$G$5:$G$4999,$Q$5:$Q$4999,1,数据录入!$B$5:$B$4999,"<"&$B$2,数据录入!$I$5:$I$4999,$K59)+SUMIFS(数据录入!$G$5:$G$4999,$Q$5:$Q$4999,1,数据录入!$B$5:$B$4999,"<"&$B$2,数据录入!$J$5:$J$4999,$K59))) | M59: =IF($K59="","",SUMIFS(数据录入!$F$5:$F$4999,$Q$5:$Q$4999,1,数据录入!$B$5:$B$4999,">="&$B$2,数据录入!$B$5:$B$4999,"<="&$D$2,数据录入!$I$5:$I$4999,$K59)+SUMIFS(数据录入!$F$5:$F$4999,$Q$5:$Q$4999,1,数据录入!$B$5:$B$4999,">="&$B$2,数据录入!$B$5:$B$4999,"<="&$D$2,数据录入!$J$5:$J$4999,$K59)) | N59: =IF($K59="","",SUMIFS(数据录入!$G$5:$G$4999,$Q$5:$Q$4999,1,数据录入!$B$5:$B$4999,">="&$B$2,数据录入!$B$5:$B$4999,"<="&$D$2,数据录入!$I$5:$I$4999,$K59)+SUMIFS(数据录入!$G$5:$G$4999,$Q$5:$Q$4999,1,数据录入!$B$5:$B$4999,">="&$B$2,数据录入!$B$5:$B$4999,"<="&$D$2,数据录入!$J$5:$J$4999,$K59)) | O59: =IF($K59="","",L59+M59-N59) | Q59: =IF(数据录入!$B59="",0,IF(OR(数据录入!$D59="投标保证金",数据录入!$D59="合同履约保证金",ISNUMBER(FIND("保证金",数据录入!$E59))),1,0)) | R59: =IF(AND($Q59=1,数据录入!$B59>=$B$2,数据录入!$B59<=$D$2),N(R58)+1,N(R58)) | S59: =IFERROR(MATCH(52,$R$5:$R$4999,0),"") | U59: =IFERROR(IF(52<=50,INDEX(基础资料!$E$2:$E$51,52)&"",INDEX(基础资料!$G$2:$G$51,52-50)&""),"") | V59: =IF($U59="",0,IF(AND(52>50,COUNTIF(基础资料!$E$2:$E$51,$U59)>0),0,1)) | W59: =IF($V59=1,N(W58)+1,N(W58))
A60: =IF($S60="","",INDEX(数据录入!$B$5:$B$4999,$S60)) | B60: =IF($S60="","",INDEX(数据录入!$C$5:$C$4999,$S60)&"") | C60: =IF($S60="","",IF(N($F60)>0,"收款",IF(N($G60)>0,"付款",""))) | D60: =IF($S60="","",IF((INDEX(数据录入!$I$5:$I$4999,$S60)&"")<>"",INDEX(数据录入!$I$5:$I$4999,$S60)&"",INDEX(数据录入!$J$5:$J$4999,$S60)&"")) | E60: =IF($S60="","",INDEX(数据录入!$E$5:$E$4999,$S60)&"") | F60: =IF($S60="","",N(INDEX(数据录入!$F$5:$F$4999,$S60))) | G60: =IF($S60="","",N(INDEX(数据录入!$G$5:$G$4999,$S60))) | H60: =IF($S60="","",$G$2+SUM($F$8:$F60)-SUM($G$8:$G60)) | J60: =IF($K60="","",53) | K60: =IFERROR(INDEX($U$8:$U$107,MATCH(53,$W$8:$W$107,0)),"") | L60: =IF($K60="","",(SUMIFS(数据录入!$F$5:$F$4999,$Q$5:$Q$4999,1,数据录入!$B$5:$B$4999,"<"&$B$2,数据录入!$I$5:$I$4999,$K60)+SUMIFS(数据录入!$F$5:$F$4999,$Q$5:$Q$4999,1,数据录入!$B$5:$B$4999,"<"&$B$2,数据录入!$J$5:$J$4999,$K60))-(SUMIFS(数据录入!$G$5:$G$4999,$Q$5:$Q$4999,1,数据录入!$B$5:$B$4999,"<"&$B$2,数据录入!$I$5:$I$4999,$K60)+SUMIFS(数据录入!$G$5:$G$4999,$Q$5:$Q$4999,1,数据录入!$B$5:$B$4999,"<"&$B$2,数据录入!$J$5:$J$4999,$K60))) | M60: =IF($K60="","",SUMIFS(数据录入!$F$5:$F$4999,$Q$5:$Q$4999,1,数据录入!$B$5:$B$4999,">="&$B$2,数据录入!$B$5:$B$4999,"<="&$D$2,数据录入!$I$5:$I$4999,$K60)+SUMIFS(数据录入!$F$5:$F$4999,$Q$5:$Q$4999,1,数据录入!$B$5:$B$4999,">="&$B$2,数据录入!$B$5:$B$4999,"<="&$D$2,数据录入!$J$5:$J$4999,$K60)) | N60: =IF($K60="","",SUMIFS(数据录入!$G$5:$G$4999,$Q$5:$Q$4999,1,数据录入!$B$5:$B$4999,">="&$B$2,数据录入!$B$5:$B$4999,"<="&$D$2,数据录入!$I$5:$I$4999,$K60)+SUMIFS(数据录入!$G$5:$G$4999,$Q$5:$Q$4999,1,数据录入!$B$5:$B$4999,">="&$B$2,数据录入!$B$5:$B$4999,"<="&$D$2,数据录入!$J$5:$J$4999,$K60)) | O60: =IF($K60="","",L60+M60-N60) | Q60: =IF(数据录入!$B60="",0,IF(OR(数据录入!$D60="投标保证金",数据录入!$D60="合同履约保证金",ISNUMBER(FIND("保证金",数据录入!$E60))),1,0)) | R60: =IF(AND($Q60=1,数据录入!$B60>=$B$2,数据录入!$B60<=$D$2),N(R59)+1,N(R59)) | S60: =IFERROR(MATCH(53,$R$5:$R$4999,0),"") | U60: =IFERROR(IF(53<=50,INDEX(基础资料!$E$2:$E$51,53)&"",INDEX(基础资料!$G$2:$G$51,53-50)&""),"") | V60: =IF($U60="",0,IF(AND(53>50,COUNTIF(基础资料!$E$2:$E$51,$U60)>0),0,1)) | W60: =IF($V60=1,N(W59)+1,N(W59))
A61: =IF($S61="","",INDEX(数据录入!$B$5:$B$4999,$S61)) | B61: =IF($S61="","",INDEX(数据录入!$C$5:$C$4999,$S61)&"") | C61: =IF($S61="","",IF(N($F61)>0,"收款",IF(N($G61)>0,"付款",""))) | D61: =IF($S61="","",IF((INDEX(数据录入!$I$5:$I$4999,$S61)&"")<>"",INDEX(数据录入!$I$5:$I$4999,$S61)&"",INDEX(数据录入!$J$5:$J$4999,$S61)&"")) | E61: =IF($S61="","",INDEX(数据录入!$E$5:$E$4999,$S61)&"") | F61: =IF($S61="","",N(INDEX(数据录入!$F$5:$F$4999,$S61))) | G61: =IF($S61="","",N(INDEX(数据录入!$G$5:$G$4999,$S61))) | H61: =IF($S61="","",$G$2+SUM($F$8:$F61)-SUM($G$8:$G61)) | J61: =IF($K61="","",54) | K61: =IFERROR(INDEX($U$8:$U$107,MATCH(54,$W$8:$W$107,0)),"") | L61: =IF($K61="","",(SUMIFS(数据录入!$F$5:$F$4999,$Q$5:$Q$4999,1,数据录入!$B$5:$B$4999,"<"&$B$2,数据录入!$I$5:$I$4999,$K61)+SUMIFS(数据录入!$F$5:$F$4999,$Q$5:$Q$4999,1,数据录入!$B$5:$B$4999,"<"&$B$2,数据录入!$J$5:$J$4999,$K61))-(SUMIFS(数据录入!$G$5:$G$4999,$Q$5:$Q$4999,1,数据录入!$B$5:$B$4999,"<"&$B$2,数据录入!$I$5:$I$4999,$K61)+SUMIFS(数据录入!$G$5:$G$4999,$Q$5:$Q$4999,1,数据录入!$B$5:$B$4999,"<"&$B$2,数据录入!$J$5:$J$4999,$K61))) | M61: =IF($K61="","",SUMIFS(数据录入!$F$5:$F$4999,$Q$5:$Q$4999,1,数据录入!$B$5:$B$4999,">="&$B$2,数据录入!$B$5:$B$4999,"<="&$D$2,数据录入!$I$5:$I$4999,$K61)+SUMIFS(数据录入!$F$5:$F$4999,$Q$5:$Q$4999,1,数据录入!$B$5:$B$4999,">="&$B$2,数据录入!$B$5:$B$4999,"<="&$D$2,数据录入!$J$5:$J$4999,$K61)) | N61: =IF($K61="","",SUMIFS(数据录入!$G$5:$G$4999,$Q$5:$Q$4999,1,数据录入!$B$5:$B$4999,">="&$B$2,数据录入!$B$5:$B$4999,"<="&$D$2,数据录入!$I$5:$I$4999,$K61)+SUMIFS(数据录入!$G$5:$G$4999,$Q$5:$Q$4999,1,数据录入!$B$5:$B$4999,">="&$B$2,数据录入!$B$5:$B$4999,"<="&$D$2,数据录入!$J$5:$J$4999,$K61)) | O61: =IF($K61="","",L61+M61-N61) | Q61: =IF(数据录入!$B61="",0,IF(OR(数据录入!$D61="投标保证金",数据录入!$D61="合同履约保证金",ISNUMBER(FIND("保证金",数据录入!$E61))),1,0)) | R61: =IF(AND($Q61=1,数据录入!$B61>=$B$2,数据录入!$B61<=$D$2),N(R60)+1,N(R60)) | S61: =IFERROR(MATCH(54,$R$5:$R$4999,0),"") | U61: =IFERROR(IF(54<=50,INDEX(基础资料!$E$2:$E$51,54)&"",INDEX(基础资料!$G$2:$G$51,54-50)&""),"") | V61: =IF($U61="",0,IF(AND(54>50,COUNTIF(基础资料!$E$2:$E$51,$U61)>0),0,1)) | W61: =IF($V61=1,N(W60)+1,N(W60))
A62: =IF($S62="","",INDEX(数据录入!$B$5:$B$4999,$S62)) | B62: =IF($S62="","",INDEX(数据录入!$C$5:$C$4999,$S62)&"") | C62: =IF($S62="","",IF(N($F62)>0,"收款",IF(N($G62)>0,"付款",""))) | D62: =IF($S62="","",IF((INDEX(数据录入!$I$5:$I$4999,$S62)&"")<>"",INDEX(数据录入!$I$5:$I$4999,$S62)&"",INDEX(数据录入!$J$5:$J$4999,$S62)&"")) | E62: =IF($S62="","",INDEX(数据录入!$E$5:$E$4999,$S62)&"") | F62: =IF($S62="","",N(INDEX(数据录入!$F$5:$F$4999,$S62))) | G62: =IF($S62="","",N(INDEX(数据录入!$G$5:$G$4999,$S62))) | H62: =IF($S62="","",$G$2+SUM($F$8:$F62)-SUM($G$8:$G62)) | J62: =IF($K62="","",55) | K62: =IFERROR(INDEX($U$8:$U$107,MATCH(55,$W$8:$W$107,0)),"") | L62: =IF($K62="","",(SUMIFS(数据录入!$F$5:$F$4999,$Q$5:$Q$4999,1,数据录入!$B$5:$B$4999,"<"&$B$2,数据录入!$I$5:$I$4999,$K62)+SUMIFS(数据录入!$F$5:$F$4999,$Q$5:$Q$4999,1,数据录入!$B$5:$B$4999,"<"&$B$2,数据录入!$J$5:$J$4999,$K62))-(SUMIFS(数据录入!$G$5:$G$4999,$Q$5:$Q$4999,1,数据录入!$B$5:$B$4999,"<"&$B$2,数据录入!$I$5:$I$4999,$K62)+SUMIFS(数据录入!$G$5:$G$4999,$Q$5:$Q$4999,1,数据录入!$B$5:$B$4999,"<"&$B$2,数据录入!$J$5:$J$4999,$K62))) | M62: =IF($K62="","",SUMIFS(数据录入!$F$5:$F$4999,$Q$5:$Q$4999,1,数据录入!$B$5:$B$4999,">="&$B$2,数据录入!$B$5:$B$4999,"<="&$D$2,数据录入!$I$5:$I$4999,$K62)+SUMIFS(数据录入!$F$5:$F$4999,$Q$5:$Q$4999,1,数据录入!$B$5:$B$4999,">="&$B$2,数据录入!$B$5:$B$4999,"<="&$D$2,数据录入!$J$5:$J$4999,$K62)) | N62: =IF($K62="","",SUMIFS(数据录入!$G$5:$G$4999,$Q$5:$Q$4999,1,数据录入!$B$5:$B$4999,">="&$B$2,数据录入!$B$5:$B$4999,"<="&$D$2,数据录入!$I$5:$I$4999,$K62)+SUMIFS(数据录入!$G$5:$G$4999,$Q$5:$Q$4999,1,数据录入!$B$5:$B$4999,">="&$B$2,数据录入!$B$5:$B$4999,"<="&$D$2,数据录入!$J$5:$J$4999,$K62)) | O62: =IF($K62="","",L62+M62-N62) | Q62: =IF(数据录入!$B62="",0,IF(OR(数据录入!$D62="投标保证金",数据录入!$D62="合同履约保证金",ISNUMBER(FIND("保证金",数据录入!$E62))),1,0)) | R62: =IF(AND($Q62=1,数据录入!$B62>=$B$2,数据录入!$B62<=$D$2),N(R61)+1,N(R61)) | S62: =IFERROR(MATCH(55,$R$5:$R$4999,0),"") | U62: =IFERROR(IF(55<=50,INDEX(基础资料!$E$2:$E$51,55)&"",INDEX(基础资料!$G$2:$G$51,55-50)&""),"") | V62: =IF($U62="",0,IF(AND(55>50,COUNTIF(基础资料!$E$2:$E$51,$U62)>0),0,1)) | W62: =IF($V62=1,N(W61)+1,N(W61))
A63: =IF($S63="","",INDEX(数据录入!$B$5:$B$4999,$S63)) | B63: =IF($S63="","",INDEX(数据录入!$C$5:$C$4999,$S63)&"") | C63: =IF($S63="","",IF(N($F63)>0,"收款",IF(N($G63)>0,"付款",""))) | D63: =IF($S63="","",IF((INDEX(数据录入!$I$5:$I$4999,$S63)&"")<>"",INDEX(数据录入!$I$5:$I$4999,$S63)&"",INDEX(数据录入!$J$5:$J$4999,$S63)&"")) | E63: =IF($S63="","",INDEX(数据录入!$E$5:$E$4999,$S63)&"") | F63: =IF($S63="","",N(INDEX(数据录入!$F$5:$F$4999,$S63))) | G63: =IF($S63="","",N(INDEX(数据录入!$G$5:$G$4999,$S63))) | H63: =IF($S63="","",$G$2+SUM($F$8:$F63)-SUM($G$8:$G63)) | J63: =IF($K63="","",56) | K63: =IFERROR(INDEX($U$8:$U$107,MATCH(56,$W$8:$W$107,0)),"") | L63: =IF($K63="","",(SUMIFS(数据录入!$F$5:$F$4999,$Q$5:$Q$4999,1,数据录入!$B$5:$B$4999,"<"&$B$2,数据录入!$I$5:$I$4999,$K63)+SUMIFS(数据录入!$F$5:$F$4999,$Q$5:$Q$4999,1,数据录入!$B$5:$B$4999,"<"&$B$2,数据录入!$J$5:$J$4999,$K63))-(SUMIFS(数据录入!$G$5:$G$4999,$Q$5:$Q$4999,1,数据录入!$B$5:$B$4999,"<"&$B$2,数据录入!$I$5:$I$4999,$K63)+SUMIFS(数据录入!$G$5:$G$4999,$Q$5:$Q$4999,1,数据录入!$B$5:$B$4999,"<"&$B$2,数据录入!$J$5:$J$4999,$K63))) | M63: =IF($K63="","",SUMIFS(数据录入!$F$5:$F$4999,$Q$5:$Q$4999,1,数据录入!$B$5:$B$4999,">="&$B$2,数据录入!$B$5:$B$4999,"<="&$D$2,数据录入!$I$5:$I$4999,$K63)+SUMIFS(数据录入!$F$5:$F$4999,$Q$5:$Q$4999,1,数据录入!$B$5:$B$4999,">="&$B$2,数据录入!$B$5:$B$4999,"<="&$D$2,数据录入!$J$5:$J$4999,$K63)) | N63: =IF($K63="","",SUMIFS(数据录入!$G$5:$G$4999,$Q$5:$Q$4999,1,数据录入!$B$5:$B$4999,">="&$B$2,数据录入!$B$5:$B$4999,"<="&$D$2,数据录入!$I$5:$I$4999,$K63)+SUMIFS(数据录入!$G$5:$G$4999,$Q$5:$Q$4999,1,数据录入!$B$5:$B$4999,">="&$B$2,数据录入!$B$5:$B$4999,"<="&$D$2,数据录入!$J$5:$J$4999,$K63)) | O63: =IF($K63="","",L63+M63-N63) | Q63: =IF(数据录入!$B63="",0,IF(OR(数据录入!$D63="投标保证金",数据录入!$D63="合同履约保证金",ISNUMBER(FIND("保证金",数据录入!$E63))),1,0)) | R63: =IF(AND($Q63=1,数据录入!$B63>=$B$2,数据录入!$B63<=$D$2),N(R62)+1,N(R62)) | S63: =IFERROR(MATCH(56,$R$5:$R$4999,0),"") | U63: =IFERROR(IF(56<=50,INDEX(基础资料!$E$2:$E$51,56)&"",INDEX(基础资料!$G$2:$G$51,56-50)&""),"") | V63: =IF($U63="",0,IF(AND(56>50,COUNTIF(基础资料!$E$2:$E$51,$U63)>0),0,1)) | W63: =IF($V63=1,N(W62)+1,N(W62))
A64: =IF($S64="","",INDEX(数据录入!$B$5:$B$4999,$S64)) | B64: =IF($S64="","",INDEX(数据录入!$C$5:$C$4999,$S64)&"") | C64: =IF($S64="","",IF(N($F64)>0,"收款",IF(N($G64)>0,"付款",""))) | D64: =IF($S64="","",IF((INDEX(数据录入!$I$5:$I$4999,$S64)&"")<>"",INDEX(数据录入!$I$5:$I$4999,$S64)&"",INDEX(数据录入!$J$5:$J$4999,$S64)&"")) | E64: =IF($S64="","",INDEX(数据录入!$E$5:$E$4999,$S64)&"") | F64: =IF($S64="","",N(INDEX(数据录入!$F$5:$F$4999,$S64))) | G64: =IF($S64="","",N(INDEX(数据录入!$G$5:$G$4999,$S64))) | H64: =IF($S64="","",$G$2+SUM($F$8:$F64)-SUM($G$8:$G64)) | J64: =IF($K64="","",57) | K64: =IFERROR(INDEX($U$8:$U$107,MATCH(57,$W$8:$W$107,0)),"") | L64: =IF($K64="","",(SUMIFS(数据录入!$F$5:$F$4999,$Q$5:$Q$4999,1,数据录入!$B$5:$B$4999,"<"&$B$2,数据录入!$I$5:$I$4999,$K64)+SUMIFS(数据录入!$F$5:$F$4999,$Q$5:$Q$4999,1,数据录入!$B$5:$B$4999,"<"&$B$2,数据录入!$J$5:$J$4999,$K64))-(SUMIFS(数据录入!$G$5:$G$4999,$Q$5:$Q$4999,1,数据录入!$B$5:$B$4999,"<"&$B$2,数据录入!$I$5:$I$4999,$K64)+SUMIFS(数据录入!$G$5:$G$4999,$Q$5:$Q$4999,1,数据录入!$B$5:$B$4999,"<"&$B$2,数据录入!$J$5:$J$4999,$K64))) | M64: =IF($K64="","",SUMIFS(数据录入!$F$5:$F$4999,$Q$5:$Q$4999,1,数据录入!$B$5:$B$4999,">="&$B$2,数据录入!$B$5:$B$4999,"<="&$D$2,数据录入!$I$5:$I$4999,$K64)+SUMIFS(数据录入!$F$5:$F$4999,$Q$5:$Q$4999,1,数据录入!$B$5:$B$4999,">="&$B$2,数据录入!$B$5:$B$4999,"<="&$D$2,数据录入!$J$5:$J$4999,$K64)) | N64: =IF($K64="","",SUMIFS(数据录入!$G$5:$G$4999,$Q$5:$Q$4999,1,数据录入!$B$5:$B$4999,">="&$B$2,数据录入!$B$5:$B$4999,"<="&$D$2,数据录入!$I$5:$I$4999,$K64)+SUMIFS(数据录入!$G$5:$G$4999,$Q$5:$Q$4999,1,数据录入!$B$5:$B$4999,">="&$B$2,数据录入!$B$5:$B$4999,"<="&$D$2,数据录入!$J$5:$J$4999,$K64)) | O64: =IF($K64="","",L64+M64-N64) | Q64: =IF(数据录入!$B64="",0,IF(OR(数据录入!$D64="投标保证金",数据录入!$D64="合同履约保证金",ISNUMBER(FIND("保证金",数据录入!$E64))),1,0)) | R64: =IF(AND($Q64=1,数据录入!$B64>=$B$2,数据录入!$B64<=$D$2),N(R63)+1,N(R63)) | S64: =IFERROR(MATCH(57,$R$5:$R$4999,0),"") | U64: =IFERROR(IF(57<=50,INDEX(基础资料!$E$2:$E$51,57)&"",INDEX(基础资料!$G$2:$G$51,57-50)&""),"") | V64: =IF($U64="",0,IF(AND(57>50,COUNTIF(基础资料!$E$2:$E$51,$U64)>0),0,1)) | W64: =IF($V64=1,N(W63)+1,N(W63))
A65: =IF($S65="","",INDEX(数据录入!$B$5:$B$4999,$S65)) | B65: =IF($S65="","",INDEX(数据录入!$C$5:$C$4999,$S65)&"") | C65: =IF($S65="","",IF(N($F65)>0,"收款",IF(N($G65)>0,"付款",""))) | D65: =IF($S65="","",IF((INDEX(数据录入!$I$5:$I$4999,$S65)&"")<>"",INDEX(数据录入!$I$5:$I$4999,$S65)&"",INDEX(数据录入!$J$5:$J$4999,$S65)&"")) | E65: =IF($S65="","",INDEX(数据录入!$E$5:$E$4999,$S65)&"") | F65: =IF($S65="","",N(INDEX(数据录入!$F$5:$F$4999,$S65))) | G65: =IF($S65="","",N(INDEX(数据录入!$G$5:$G$4999,$S65))) | H65: =IF($S65="","",$G$2+SUM($F$8:$F65)-SUM($G$8:$G65)) | J65: =IF($K65="","",58) | K65: =IFERROR(INDEX($U$8:$U$107,MATCH(58,$W$8:$W$107,0)),"") | L65: =IF($K65="","",(SUMIFS(数据录入!$F$5:$F$4999,$Q$5:$Q$4999,1,数据录入!$B$5:$B$4999,"<"&$B$2,数据录入!$I$5:$I$4999,$K65)+SUMIFS(数据录入!$F$5:$F$4999,$Q$5:$Q$4999,1,数据录入!$B$5:$B$4999,"<"&$B$2,数据录入!$J$5:$J$4999,$K65))-(SUMIFS(数据录入!$G$5:$G$4999,$Q$5:$Q$4999,1,数据录入!$B$5:$B$4999,"<"&$B$2,数据录入!$I$5:$I$4999,$K65)+SUMIFS(数据录入!$G$5:$G$4999,$Q$5:$Q$4999,1,数据录入!$B$5:$B$4999,"<"&$B$2,数据录入!$J$5:$J$4999,$K65))) | M65: =IF($K65="","",SUMIFS(数据录入!$F$5:$F$4999,$Q$5:$Q$4999,1,数据录入!$B$5:$B$4999,">="&$B$2,数据录入!$B$5:$B$4999,"<="&$D$2,数据录入!$I$5:$I$4999,$K65)+SUMIFS(数据录入!$F$5:$F$4999,$Q$5:$Q$4999,1,数据录入!$B$5:$B$4999,">="&$B$2,数据录入!$B$5:$B$4999,"<="&$D$2,数据录入!$J$5:$J$4999,$K65)) | N65: =IF($K65="","",SUMIFS(数据录入!$G$5:$G$4999,$Q$5:$Q$4999,1,数据录入!$B$5:$B$4999,">="&$B$2,数据录入!$B$5:$B$4999,"<="&$D$2,数据录入!$I$5:$I$4999,$K65)+SUMIFS(数据录入!$G$5:$G$4999,$Q$5:$Q$4999,1,数据录入!$B$5:$B$4999,">="&$B$2,数据录入!$B$5:$B$4999,"<="&$D$2,数据录入!$J$5:$J$4999,$K65)) | O65: =IF($K65="","",L65+M65-N65) | Q65: =IF(数据录入!$B65="",0,IF(OR(数据录入!$D65="投标保证金",数据录入!$D65="合同履约保证金",ISNUMBER(FIND("保证金",数据录入!$E65))),1,0)) | R65: =IF(AND($Q65=1,数据录入!$B65>=$B$2,数据录入!$B65<=$D$2),N(R64)+1,N(R64)) | S65: =IFERROR(MATCH(58,$R$5:$R$4999,0),"") | U65: =IFERROR(IF(58<=50,INDEX(基础资料!$E$2:$E$51,58)&"",INDEX(基础资料!$G$2:$G$51,58-50)&""),"") | V65: =IF($U65="",0,IF(AND(58>50,COUNTIF(基础资料!$E$2:$E$51,$U65)>0),0,1)) | W65: =IF($V65=1,N(W64)+1,N(W64))
A66: =IF($S66="","",INDEX(数据录入!$B$5:$B$4999,$S66)) | B66: =IF($S66="","",INDEX(数据录入!$C$5:$C$4999,$S66)&"") | C66: =IF($S66="","",IF(N($F66)>0,"收款",IF(N($G66)>0,"付款",""))) | D66: =IF($S66="","",IF((INDEX(数据录入!$I$5:$I$4999,$S66)&"")<>"",INDEX(数据录入!$I$5:$I$4999,$S66)&"",INDEX(数据录入!$J$5:$J$4999,$S66)&"")) | E66: =IF($S66="","",INDEX(数据录入!$E$5:$E$4999,$S66)&"") | F66: =IF($S66="","",N(INDEX(数据录入!$F$5:$F$4999,$S66))) | G66: =IF($S66="","",N(INDEX(数据录入!$G$5:$G$4999,$S66))) | H66: =IF($S66="","",$G$2+SUM($F$8:$F66)-SUM($G$8:$G66)) | J66: =IF($K66="","",59) | K66: =IFERROR(INDEX($U$8:$U$107,MATCH(59,$W$8:$W$107,0)),"") | L66: =IF($K66="","",(SUMIFS(数据录入!$F$5:$F$4999,$Q$5:$Q$4999,1,数据录入!$B$5:$B$4999,"<"&$B$2,数据录入!$I$5:$I$4999,$K66)+SUMIFS(数据录入!$F$5:$F$4999,$Q$5:$Q$4999,1,数据录入!$B$5:$B$4999,"<"&$B$2,数据录入!$J$5:$J$4999,$K66))-(SUMIFS(数据录入!$G$5:$G$4999,$Q$5:$Q$4999,1,数据录入!$B$5:$B$4999,"<"&$B$2,数据录入!$I$5:$I$4999,$K66)+SUMIFS(数据录入!$G$5:$G$4999,$Q$5:$Q$4999,1,数据录入!$B$5:$B$4999,"<"&$B$2,数据录入!$J$5:$J$4999,$K66))) | M66: =IF($K66="","",SUMIFS(数据录入!$F$5:$F$4999,$Q$5:$Q$4999,1,数据录入!$B$5:$B$4999,">="&$B$2,数据录入!$B$5:$B$4999,"<="&$D$2,数据录入!$I$5:$I$4999,$K66)+SUMIFS(数据录入!$F$5:$F$4999,$Q$5:$Q$4999,1,数据录入!$B$5:$B$4999,">="&$B$2,数据录入!$B$5:$B$4999,"<="&$D$2,数据录入!$J$5:$J$4999,$K66)) | N66: =IF($K66="","",SUMIFS(数据录入!$G$5:$G$4999,$Q$5:$Q$4999,1,数据录入!$B$5:$B$4999,">="&$B$2,数据录入!$B$5:$B$4999,"<="&$D$2,数据录入!$I$5:$I$4999,$K66)+SUMIFS(数据录入!$G$5:$G$4999,$Q$5:$Q$4999,1,数据录入!$B$5:$B$4999,">="&$B$2,数据录入!$B$5:$B$4999,"<="&$D$2,数据录入!$J$5:$J$4999,$K66)) | O66: =IF($K66="","",L66+M66-N66) | Q66: =IF(数据录入!$B66="",0,IF(OR(数据录入!$D66="投标保证金",数据录入!$D66="合同履约保证金",ISNUMBER(FIND("保证金",数据录入!$E66))),1,0)) | R66: =IF(AND($Q66=1,数据录入!$B66>=$B$2,数据录入!$B66<=$D$2),N(R65)+1,N(R65)) | S66: =IFERROR(MATCH(59,$R$5:$R$4999,0),"") | U66: =IFERROR(IF(59<=50,INDEX(基础资料!$E$2:$E$51,59)&"",INDEX(基础资料!$G$2:$G$51,59-50)&""),"") | V66: =IF($U66="",0,IF(AND(59>50,COUNTIF(基础资料!$E$2:$E$51,$U66)>0),0,1)) | W66: =IF($V66=1,N(W65)+1,N(W65))
A67: =IF($S67="","",INDEX(数据录入!$B$5:$B$4999,$S67)) | B67: =IF($S67="","",INDEX(数据录入!$C$5:$C$4999,$S67)&"") | C67: =IF($S67="","",IF(N($F67)>0,"收款",IF(N($G67)>0,"付款",""))) | D67: =IF($S67="","",IF((INDEX(数据录入!$I$5:$I$4999,$S67)&"")<>"",INDEX(数据录入!$I$5:$I$4999,$S67)&"",INDEX(数据录入!$J$5:$J$4999,$S67)&"")) | E67: =IF($S67="","",INDEX(数据录入!$E$5:$E$4999,$S67)&"") | F67: =IF($S67="","",N(INDEX(数据录入!$F$5:$F$4999,$S67))) | G67: =IF($S67="","",N(INDEX(数据录入!$G$5:$G$4999,$S67))) | H67: =IF($S67="","",$G$2+SUM($F$8:$F67)-SUM($G$8:$G67)) | J67: =IF($K67="","",60) | K67: =IFERROR(INDEX($U$8:$U$107,MATCH(60,$W$8:$W$107,0)),"") | L67: =IF($K67="","",(SUMIFS(数据录入!$F$5:$F$4999,$Q$5:$Q$4999,1,数据录入!$B$5:$B$4999,"<"&$B$2,数据录入!$I$5:$I$4999,$K67)+SUMIFS(数据录入!$F$5:$F$4999,$Q$5:$Q$4999,1,数据录入!$B$5:$B$4999,"<"&$B$2,数据录入!$J$5:$J$4999,$K67))-(SUMIFS(数据录入!$G$5:$G$4999,$Q$5:$Q$4999,1,数据录入!$B$5:$B$4999,"<"&$B$2,数据录入!$I$5:$I$4999,$K67)+SUMIFS(数据录入!$G$5:$G$4999,$Q$5:$Q$4999,1,数据录入!$B$5:$B$4999,"<"&$B$2,数据录入!$J$5:$J$4999,$K67))) | M67: =IF($K67="","",SUMIFS(数据录入!$F$5:$F$4999,$Q$5:$Q$4999,1,数据录入!$B$5:$B$4999,">="&$B$2,数据录入!$B$5:$B$4999,"<="&$D$2,数据录入!$I$5:$I$4999,$K67)+SUMIFS(数据录入!$F$5:$F$4999,$Q$5:$Q$4999,1,数据录入!$B$5:$B$4999,">="&$B$2,数据录入!$B$5:$B$4999,"<="&$D$2,数据录入!$J$5:$J$4999,$K67)) | N67: =IF($K67="","",SUMIFS(数据录入!$G$5:$G$4999,$Q$5:$Q$4999,1,数据录入!$B$5:$B$4999,">="&$B$2,数据录入!$B$5:$B$4999,"<="&$D$2,数据录入!$I$5:$I$4999,$K67)+SUMIFS(数据录入!$G$5:$G$4999,$Q$5:$Q$4999,1,数据录入!$B$5:$B$4999,">="&$B$2,数据录入!$B$5:$B$4999,"<="&$D$2,数据录入!$J$5:$J$4999,$K67)) | O67: =IF($K67="","",L67+M67-N67) | Q67: =IF(数据录入!$B67="",0,IF(OR(数据录入!$D67="投标保证金",数据录入!$D67="合同履约保证金",ISNUMBER(FIND("保证金",数据录入!$E67))),1,0)) | R67: =IF(AND($Q67=1,数据录入!$B67>=$B$2,数据录入!$B67<=$D$2),N(R66)+1,N(R66)) | S67: =IFERROR(MATCH(60,$R$5:$R$4999,0),"") | U67: =IFERROR(IF(60<=50,INDEX(基础资料!$E$2:$E$51,60)&"",INDEX(基础资料!$G$2:$G$51,60-50)&""),"") | V67: =IF($U67="",0,IF(AND(60>50,COUNTIF(基础资料!$E$2:$E$51,$U67)>0),0,1)) | W67: =IF($V67=1,N(W66)+1,N(W66))
A68: =IF($S68="","",INDEX(数据录入!$B$5:$B$4999,$S68)) | B68: =IF($S68="","",INDEX(数据录入!$C$5:$C$4999,$S68)&"") | C68: =IF($S68="","",IF(N($F68)>0,"收款",IF(N($G68)>0,"付款",""))) | D68: =IF($S68="","",IF((INDEX(数据录入!$I$5:$I$4999,$S68)&"")<>"",INDEX(数据录入!$I$5:$I$4999,$S68)&"",INDEX(数据录入!$J$5:$J$4999,$S68)&"")) | E68: =IF($S68="","",INDEX(数据录入!$E$5:$E$4999,$S68)&"") | F68: =IF($S68="","",N(INDEX(数据录入!$F$5:$F$4999,$S68))) | G68: =IF($S68="","",N(INDEX(数据录入!$G$5:$G$4999,$S68))) | H68: =IF($S68="","",$G$2+SUM($F$8:$F68)-SUM($G$8:$G68)) | J68: =IF($K68="","",61) | K68: =IFERROR(INDEX($U$8:$U$107,MATCH(61,$W$8:$W$107,0)),"") | L68: =IF($K68="","",(SUMIFS(数据录入!$F$5:$F$4999,$Q$5:$Q$4999,1,数据录入!$B$5:$B$4999,"<"&$B$2,数据录入!$I$5:$I$4999,$K68)+SUMIFS(数据录入!$F$5:$F$4999,$Q$5:$Q$4999,1,数据录入!$B$5:$B$4999,"<"&$B$2,数据录入!$J$5:$J$4999,$K68))-(SUMIFS(数据录入!$G$5:$G$4999,$Q$5:$Q$4999,1,数据录入!$B$5:$B$4999,"<"&$B$2,数据录入!$I$5:$I$4999,$K68)+SUMIFS(数据录入!$G$5:$G$4999,$Q$5:$Q$4999,1,数据录入!$B$5:$B$4999,"<"&$B$2,数据录入!$J$5:$J$4999,$K68))) | M68: =IF($K68="","",SUMIFS(数据录入!$F$5:$F$4999,$Q$5:$Q$4999,1,数据录入!$B$5:$B$4999,">="&$B$2,数据录入!$B$5:$B$4999,"<="&$D$2,数据录入!$I$5:$I$4999,$K68)+SUMIFS(数据录入!$F$5:$F$4999,$Q$5:$Q$4999,1,数据录入!$B$5:$B$4999,">="&$B$2,数据录入!$B$5:$B$4999,"<="&$D$2,数据录入!$J$5:$J$4999,$K68)) | N68: =IF($K68="","",SUMIFS(数据录入!$G$5:$G$4999,$Q$5:$Q$4999,1,数据录入!$B$5:$B$4999,">="&$B$2,数据录入!$B$5:$B$4999,"<="&$D$2,数据录入!$I$5:$I$4999,$K68)+SUMIFS(数据录入!$G$5:$G$4999,$Q$5:$Q$4999,1,数据录入!$B$5:$B$4999,">="&$B$2,数据录入!$B$5:$B$4999,"<="&$D$2,数据录入!$J$5:$J$4999,$K68)) | O68: =IF($K68="","",L68+M68-N68) | Q68: =IF(数据录入!$B68="",0,IF(OR(数据录入!$D68="投标保证金",数据录入!$D68="合同履约保证金",ISNUMBER(FIND("保证金",数据录入!$E68))),1,0)) | R68: =IF(AND($Q68=1,数据录入!$B68>=$B$2,数据录入!$B68<=$D$2),N(R67)+1,N(R67)) | S68: =IFERROR(MATCH(61,$R$5:$R$4999,0),"") | U68: =IFERROR(IF(61<=50,INDEX(基础资料!$E$2:$E$51,61)&"",INDEX(基础资料!$G$2:$G$51,61-50)&""),"") | V68: =IF($U68="",0,IF(AND(61>50,COUNTIF(基础资料!$E$2:$E$51,$U68)>0),0,1)) | W68: =IF($V68=1,N(W67)+1,N(W67))
A69: =IF($S69="","",INDEX(数据录入!$B$5:$B$4999,$S69)) | B69: =IF($S69="","",INDEX(数据录入!$C$5:$C$4999,$S69)&"") | C69: =IF($S69="","",IF(N($F69)>0,"收款",IF(N($G69)>0,"付款",""))) | D69: =IF($S69="","",IF((INDEX(数据录入!$I$5:$I$4999,$S69)&"")<>"",INDEX(数据录入!$I$5:$I$4999,$S69)&"",INDEX(数据录入!$J$5:$J$4999,$S69)&"")) | E69: =IF($S69="","",INDEX(数据录入!$E$5:$E$4999,$S69)&"") | F69: =IF($S69="","",N(INDEX(数据录入!$F$5:$F$4999,$S69))) | G69: =IF($S69="","",N(INDEX(数据录入!$G$5:$G$4999,$S69))) | H69: =IF($S69="","",$G$2+SUM($F$8:$F69)-SUM($G$8:$G69)) | J69: =IF($K69="","",62) | K69: =IFERROR(INDEX($U$8:$U$107,MATCH(62,$W$8:$W$107,0)),"") | L69: =IF($K69="","",(SUMIFS(数据录入!$F$5:$F$4999,$Q$5:$Q$4999,1,数据录入!$B$5:$B$4999,"<"&$B$2,数据录入!$I$5:$I$4999,$K69)+SUMIFS(数据录入!$F$5:$F$4999,$Q$5:$Q$4999,1,数据录入!$B$5:$B$4999,"<"&$B$2,数据录入!$J$5:$J$4999,$K69))-(SUMIFS(数据录入!$G$5:$G$4999,$Q$5:$Q$4999,1,数据录入!$B$5:$B$4999,"<"&$B$2,数据录入!$I$5:$I$4999,$K69)+SUMIFS(数据录入!$G$5:$G$4999,$Q$5:$Q$4999,1,数据录入!$B$5:$B$4999,"<"&$B$2,数据录入!$J$5:$J$4999,$K69))) | M69: =IF($K69="","",SUMIFS(数据录入!$F$5:$F$4999,$Q$5:$Q$4999,1,数据录入!$B$5:$B$4999,">="&$B$2,数据录入!$B$5:$B$4999,"<="&$D$2,数据录入!$I$5:$I$4999,$K69)+SUMIFS(数据录入!$F$5:$F$4999,$Q$5:$Q$4999,1,数据录入!$B$5:$B$4999,">="&$B$2,数据录入!$B$5:$B$4999,"<="&$D$2,数据录入!$J$5:$J$4999,$K69)) | N69: =IF($K69="","",SUMIFS(数据录入!$G$5:$G$4999,$Q$5:$Q$4999,1,数据录入!$B$5:$B$4999,">="&$B$2,数据录入!$B$5:$B$4999,"<="&$D$2,数据录入!$I$5:$I$4999,$K69)+SUMIFS(数据录入!$G$5:$G$4999,$Q$5:$Q$4999,1,数据录入!$B$5:$B$4999,">="&$B$2,数据录入!$B$5:$B$4999,"<="&$D$2,数据录入!$J$5:$J$4999,$K69)) | O69: =IF($K69="","",L69+M69-N69) | Q69: =IF(数据录入!$B69="",0,IF(OR(数据录入!$D69="投标保证金",数据录入!$D69="合同履约保证金",ISNUMBER(FIND("保证金",数据录入!$E69))),1,0)) | R69: =IF(AND($Q69=1,数据录入!$B69>=$B$2,数据录入!$B69<=$D$2),N(R68)+1,N(R68)) | S69: =IFERROR(MATCH(62,$R$5:$R$4999,0),"") | U69: =IFERROR(IF(62<=50,INDEX(基础资料!$E$2:$E$51,62)&"",INDEX(基础资料!$G$2:$G$51,62-50)&""),"") | V69: =IF($U69="",0,IF(AND(62>50,COUNTIF(基础资料!$E$2:$E$51,$U69)>0),0,1)) | W69: =IF($V69=1,N(W68)+1,N(W68))
A70: =IF($S70="","",INDEX(数据录入!$B$5:$B$4999,$S70)) | B70: =IF($S70="","",INDEX(数据录入!$C$5:$C$4999,$S70)&"") | C70: =IF($S70="","",IF(N($F70)>0,"收款",IF(N($G70)>0,"付款",""))) | D70: =IF($S70="","",IF((INDEX(数据录入!$I$5:$I$4999,$S70)&"")<>"",INDEX(数据录入!$I$5:$I$4999,$S70)&"",INDEX(数据录入!$J$5:$J$4999,$S70)&"")) | E70: =IF($S70="","",INDEX(数据录入!$E$5:$E$4999,$S70)&"") | F70: =IF($S70="","",N(INDEX(数据录入!$F$5:$F$4999,$S70))) | G70: =IF($S70="","",N(INDEX(数据录入!$G$5:$G$4999,$S70))) | H70: =IF($S70="","",$G$2+SUM($F$8:$F70)-SUM($G$8:$G70)) | J70: =IF($K70="","",63) | K70: =IFERROR(INDEX($U$8:$U$107,MATCH(63,$W$8:$W$107,0)),"") | L70: =IF($K70="","",(SUMIFS(数据录入!$F$5:$F$4999,$Q$5:$Q$4999,1,数据录入!$B$5:$B$4999,"<"&$B$2,数据录入!$I$5:$I$4999,$K70)+SUMIFS(数据录入!$F$5:$F$4999,$Q$5:$Q$4999,1,数据录入!$B$5:$B$4999,"<"&$B$2,数据录入!$J$5:$J$4999,$K70))-(SUMIFS(数据录入!$G$5:$G$4999,$Q$5:$Q$4999,1,数据录入!$B$5:$B$4999,"<"&$B$2,数据录入!$I$5:$I$4999,$K70)+SUMIFS(数据录入!$G$5:$G$4999,$Q$5:$Q$4999,1,数据录入!$B$5:$B$4999,"<"&$B$2,数据录入!$J$5:$J$4999,$K70))) | M70: =IF($K70="","",SUMIFS(数据录入!$F$5:$F$4999,$Q$5:$Q$4999,1,数据录入!$B$5:$B$4999,">="&$B$2,数据录入!$B$5:$B$4999,"<="&$D$2,数据录入!$I$5:$I$4999,$K70)+SUMIFS(数据录入!$F$5:$F$4999,$Q$5:$Q$4999,1,数据录入!$B$5:$B$4999,">="&$B$2,数据录入!$B$5:$B$4999,"<="&$D$2,数据录入!$J$5:$J$4999,$K70)) | N70: =IF($K70="","",SUMIFS(数据录入!$G$5:$G$4999,$Q$5:$Q$4999,1,数据录入!$B$5:$B$4999,">="&$B$2,数据录入!$B$5:$B$4999,"<="&$D$2,数据录入!$I$5:$I$4999,$K70)+SUMIFS(数据录入!$G$5:$G$4999,$Q$5:$Q$4999,1,数据录入!$B$5:$B$4999,">="&$B$2,数据录入!$B$5:$B$4999,"<="&$D$2,数据录入!$J$5:$J$4999,$K70)) | O70: =IF($K70="","",L70+M70-N70) | Q70: =IF(数据录入!$B70="",0,IF(OR(数据录入!$D70="投标保证金",数据录入!$D70="合同履约保证金",ISNUMBER(FIND("保证金",数据录入!$E70))),1,0)) | R70: =IF(AND($Q70=1,数据录入!$B70>=$B$2,数据录入!$B70<=$D$2),N(R69)+1,N(R69)) | S70: =IFERROR(MATCH(63,$R$5:$R$4999,0),"") | U70: =IFERROR(IF(63<=50,INDEX(基础资料!$E$2:$E$51,63)&"",INDEX(基础资料!$G$2:$G$51,63-50)&""),"") | V70: =IF($U70="",0,IF(AND(63>50,COUNTIF(基础资料!$E$2:$E$51,$U70)>0),0,1)) | W70: =IF($V70=1,N(W69)+1,N(W69))
A71: =IF($S71="","",INDEX(数据录入!$B$5:$B$4999,$S71)) | B71: =IF($S71="","",INDEX(数据录入!$C$5:$C$4999,$S71)&"") | C71: =IF($S71="","",IF(N($F71)>0,"收款",IF(N($G71)>0,"付款",""))) | D71: =IF($S71="","",IF((INDEX(数据录入!$I$5:$I$4999,$S71)&"")<>"",INDEX(数据录入!$I$5:$I$4999,$S71)&"",INDEX(数据录入!$J$5:$J$4999,$S71)&"")) | E71: =IF($S71="","",INDEX(数据录入!$E$5:$E$4999,$S71)&"") | F71: =IF($S71="","",N(INDEX(数据录入!$F$5:$F$4999,$S71))) | G71: =IF($S71="","",N(INDEX(数据录入!$G$5:$G$4999,$S71))) | H71: =IF($S71="","",$G$2+SUM($F$8:$F71)-SUM($G$8:$G71)) | J71: =IF($K71="","",64) | K71: =IFERROR(INDEX($U$8:$U$107,MATCH(64,$W$8:$W$107,0)),"") | L71: =IF($K71="","",(SUMIFS(数据录入!$F$5:$F$4999,$Q$5:$Q$4999,1,数据录入!$B$5:$B$4999,"<"&$B$2,数据录入!$I$5:$I$4999,$K71)+SUMIFS(数据录入!$F$5:$F$4999,$Q$5:$Q$4999,1,数据录入!$B$5:$B$4999,"<"&$B$2,数据录入!$J$5:$J$4999,$K71))-(SUMIFS(数据录入!$G$5:$G$4999,$Q$5:$Q$4999,1,数据录入!$B$5:$B$4999,"<"&$B$2,数据录入!$I$5:$I$4999,$K71)+SUMIFS(数据录入!$G$5:$G$4999,$Q$5:$Q$4999,1,数据录入!$B$5:$B$4999,"<"&$B$2,数据录入!$J$5:$J$4999,$K71))) | M71: =IF($K71="","",SUMIFS(数据录入!$F$5:$F$4999,$Q$5:$Q$4999,1,数据录入!$B$5:$B$4999,">="&$B$2,数据录入!$B$5:$B$4999,"<="&$D$2,数据录入!$I$5:$I$4999,$K71)+SUMIFS(数据录入!$F$5:$F$4999,$Q$5:$Q$4999,1,数据录入!$B$5:$B$4999,">="&$B$2,数据录入!$B$5:$B$4999,"<="&$D$2,数据录入!$J$5:$J$4999,$K71)) | N71: =IF($K71="","",SUMIFS(数据录入!$G$5:$G$4999,$Q$5:$Q$4999,1,数据录入!$B$5:$B$4999,">="&$B$2,数据录入!$B$5:$B$4999,"<="&$D$2,数据录入!$I$5:$I$4999,$K71)+SUMIFS(数据录入!$G$5:$G$4999,$Q$5:$Q$4999,1,数据录入!$B$5:$B$4999,">="&$B$2,数据录入!$B$5:$B$4999,"<="&$D$2,数据录入!$J$5:$J$4999,$K71)) | O71: =IF($K71="","",L71+M71-N71) | Q71: =IF(数据录入!$B71="",0,IF(OR(数据录入!$D71="投标保证金",数据录入!$D71="合同履约保证金",ISNUMBER(FIND("保证金",数据录入!$E71))),1,0)) | R71: =IF(AND($Q71=1,数据录入!$B71>=$B$2,数据录入!$B71<=$D$2),N(R70)+1,N(R70)) | S71: =IFERROR(MATCH(64,$R$5:$R$4999,0),"") | U71: =IFERROR(IF(64<=50,INDEX(基础资料!$E$2:$E$51,64)&"",INDEX(基础资料!$G$2:$G$51,64-50)&""),"") | V71: =IF($U71="",0,IF(AND(64>50,COUNTIF(基础资料!$E$2:$E$51,$U71)>0),0,1)) | W71: =IF($V71=1,N(W70)+1,N(W70))
A72: =IF($S72="","",INDEX(数据录入!$B$5:$B$4999,$S72)) | B72: =IF($S72="","",INDEX(数据录入!$C$5:$C$4999,$S72)&"") | C72: =IF($S72="","",IF(N($F72)>0,"收款",IF(N($G72)>0,"付款",""))) | D72: =IF($S72="","",IF((INDEX(数据录入!$I$5:$I$4999,$S72)&"")<>"",INDEX(数据录入!$I$5:$I$4999,$S72)&"",INDEX(数据录入!$J$5:$J$4999,$S72)&"")) | E72: =IF($S72="","",INDEX(数据录入!$E$5:$E$4999,$S72)&"") | F72: =IF($S72="","",N(INDEX(数据录入!$F$5:$F$4999,$S72))) | G72: =IF($S72="","",N(INDEX(数据录入!$G$5:$G$4999,$S72))) | H72: =IF($S72="","",$G$2+SUM($F$8:$F72)-SUM($G$8:$G72)) | J72: =IF($K72="","",65) | K72: =IFERROR(INDEX($U$8:$U$107,MATCH(65,$W$8:$W$107,0)),"") | L72: =IF($K72="","",(SUMIFS(数据录入!$F$5:$F$4999,$Q$5:$Q$4999,1,数据录入!$B$5:$B$4999,"<"&$B$2,数据录入!$I$5:$I$4999,$K72)+SUMIFS(数据录入!$F$5:$F$4999,$Q$5:$Q$4999,1,数据录入!$B$5:$B$4999,"<"&$B$2,数据录入!$J$5:$J$4999,$K72))-(SUMIFS(数据录入!$G$5:$G$4999,$Q$5:$Q$4999,1,数据录入!$B$5:$B$4999,"<"&$B$2,数据录入!$I$5:$I$4999,$K72)+SUMIFS(数据录入!$G$5:$G$4999,$Q$5:$Q$4999,1,数据录入!$B$5:$B$4999,"<"&$B$2,数据录入!$J$5:$J$4999,$K72))) | M72: =IF($K72="","",SUMIFS(数据录入!$F$5:$F$4999,$Q$5:$Q$4999,1,数据录入!$B$5:$B$4999,">="&$B$2,数据录入!$B$5:$B$4999,"<="&$D$2,数据录入!$I$5:$I$4999,$K72)+SUMIFS(数据录入!$F$5:$F$4999,$Q$5:$Q$4999,1,数据录入!$B$5:$B$4999,">="&$B$2,数据录入!$B$5:$B$4999,"<="&$D$2,数据录入!$J$5:$J$4999,$K72)) | N72: =IF($K72="","",SUMIFS(数据录入!$G$5:$G$4999,$Q$5:$Q$4999,1,数据录入!$B$5:$B$4999,">="&$B$2,数据录入!$B$5:$B$4999,"<="&$D$2,数据录入!$I$5:$I$4999,$K72)+SUMIFS(数据录入!$G$5:$G$4999,$Q$5:$Q$4999,1,数据录入!$B$5:$B$4999,">="&$B$2,数据录入!$B$5:$B$4999,"<="&$D$2,数据录入!$J$5:$J$4999,$K72)) | O72: =IF($K72="","",L72+M72-N72) | Q72: =IF(数据录入!$B72="",0,IF(OR(数据录入!$D72="投标保证金",数据录入!$D72="合同履约保证金",ISNUMBER(FIND("保证金",数据录入!$E72))),1,0)) | R72: =IF(AND($Q72=1,数据录入!$B72>=$B$2,数据录入!$B72<=$D$2),N(R71)+1,N(R71)) | S72: =IFERROR(MATCH(65,$R$5:$R$4999,0),"") | U72: =IFERROR(IF(65<=50,INDEX(基础资料!$E$2:$E$51,65)&"",INDEX(基础资料!$G$2:$G$51,65-50)&""),"") | V72: =IF($U72="",0,IF(AND(65>50,COUNTIF(基础资料!$E$2:$E$51,$U72)>0),0,1)) | W72: =IF($V72=1,N(W71)+1,N(W71))
A73: =IF($S73="","",INDEX(数据录入!$B$5:$B$4999,$S73)) | B73: =IF($S73="","",INDEX(数据录入!$C$5:$C$4999,$S73)&"") | C73: =IF($S73="","",IF(N($F73)>0,"收款",IF(N($G73)>0,"付款",""))) | D73: =IF($S73="","",IF((INDEX(数据录入!$I$5:$I$4999,$S73)&"")<>"",INDEX(数据录入!$I$5:$I$4999,$S73)&"",INDEX(数据录入!$J$5:$J$4999,$S73)&"")) | E73: =IF($S73="","",INDEX(数据录入!$E$5:$E$4999,$S73)&"") | F73: =IF($S73="","",N(INDEX(数据录入!$F$5:$F$4999,$S73))) | G73: =IF($S73="","",N(INDEX(数据录入!$G$5:$G$4999,$S73))) | H73: =IF($S73="","",$G$2+SUM($F$8:$F73)-SUM($G$8:$G73)) | J73: =IF($K73="","",66) | K73: =IFERROR(INDEX($U$8:$U$107,MATCH(66,$W$8:$W$107,0)),"") | L73: =IF($K73="","",(SUMIFS(数据录入!$F$5:$F$4999,$Q$5:$Q$4999,1,数据录入!$B$5:$B$4999,"<"&$B$2,数据录入!$I$5:$I$4999,$K73)+SUMIFS(数据录入!$F$5:$F$4999,$Q$5:$Q$4999,1,数据录入!$B$5:$B$4999,"<"&$B$2,数据录入!$J$5:$J$4999,$K73))-(SUMIFS(数据录入!$G$5:$G$4999,$Q$5:$Q$4999,1,数据录入!$B$5:$B$4999,"<"&$B$2,数据录入!$I$5:$I$4999,$K73)+SUMIFS(数据录入!$G$5:$G$4999,$Q$5:$Q$4999,1,数据录入!$B$5:$B$4999,"<"&$B$2,数据录入!$J$5:$J$4999,$K73))) | M73: =IF($K73="","",SUMIFS(数据录入!$F$5:$F$4999,$Q$5:$Q$4999,1,数据录入!$B$5:$B$4999,">="&$B$2,数据录入!$B$5:$B$4999,"<="&$D$2,数据录入!$I$5:$I$4999,$K73)+SUMIFS(数据录入!$F$5:$F$4999,$Q$5:$Q$4999,1,数据录入!$B$5:$B$4999,">="&$B$2,数据录入!$B$5:$B$4999,"<="&$D$2,数据录入!$J$5:$J$4999,$K73)) | N73: =IF($K73="","",SUMIFS(数据录入!$G$5:$G$4999,$Q$5:$Q$4999,1,数据录入!$B$5:$B$4999,">="&$B$2,数据录入!$B$5:$B$4999,"<="&$D$2,数据录入!$I$5:$I$4999,$K73)+SUMIFS(数据录入!$G$5:$G$4999,$Q$5:$Q$4999,1,数据录入!$B$5:$B$4999,">="&$B$2,数据录入!$B$5:$B$4999,"<="&$D$2,数据录入!$J$5:$J$4999,$K73)) | O73: =IF($K73="","",L73+M73-N73) | Q73: =IF(数据录入!$B73="",0,IF(OR(数据录入!$D73="投标保证金",数据录入!$D73="合同履约保证金",ISNUMBER(FIND("保证金",数据录入!$E73))),1,0)) | R73: =IF(AND($Q73=1,数据录入!$B73>=$B$2,数据录入!$B73<=$D$2),N(R72)+1,N(R72)) | S73: =IFERROR(MATCH(66,$R$5:$R$4999,0),"") | U73: =IFERROR(IF(66<=50,INDEX(基础资料!$E$2:$E$51,66)&"",INDEX(基础资料!$G$2:$G$51,66-50)&""),"") | V73: =IF($U73="",0,IF(AND(66>50,COUNTIF(基础资料!$E$2:$E$51,$U73)>0),0,1)) | W73: =IF($V73=1,N(W72)+1,N(W72))
A74: =IF($S74="","",INDEX(数据录入!$B$5:$B$4999,$S74)) | B74: =IF($S74="","",INDEX(数据录入!$C$5:$C$4999,$S74)&"") | C74: =IF($S74="","",IF(N($F74)>0,"收款",IF(N($G74)>0,"付款",""))) | D74: =IF($S74="","",IF((INDEX(数据录入!$I$5:$I$4999,$S74)&"")<>"",INDEX(数据录入!$I$5:$I$4999,$S74)&"",INDEX(数据录入!$J$5:$J$4999,$S74)&"")) | E74: =IF($S74="","",INDEX(数据录入!$E$5:$E$4999,$S74)&"") | F74: =IF($S74="","",N(INDEX(数据录入!$F$5:$F$4999,$S74))) | G74: =IF($S74="","",N(INDEX(数据录入!$G$5:$G$4999,$S74))) | H74: =IF($S74="","",$G$2+SUM($F$8:$F74)-SUM($G$8:$G74)) | J74: =IF($K74="","",67) | K74: =IFERROR(INDEX($U$8:$U$107,MATCH(67,$W$8:$W$107,0)),"") | L74: =IF($K74="","",(SUMIFS(数据录入!$F$5:$F$4999,$Q$5:$Q$4999,1,数据录入!$B$5:$B$4999,"<"&$B$2,数据录入!$I$5:$I$4999,$K74)+SUMIFS(数据录入!$F$5:$F$4999,$Q$5:$Q$4999,1,数据录入!$B$5:$B$4999,"<"&$B$2,数据录入!$J$5:$J$4999,$K74))-(SUMIFS(数据录入!$G$5:$G$4999,$Q$5:$Q$4999,1,数据录入!$B$5:$B$4999,"<"&$B$2,数据录入!$I$5:$I$4999,$K74)+SUMIFS(数据录入!$G$5:$G$4999,$Q$5:$Q$4999,1,数据录入!$B$5:$B$4999,"<"&$B$2,数据录入!$J$5:$J$4999,$K74))) | M74: =IF($K74="","",SUMIFS(数据录入!$F$5:$F$4999,$Q$5:$Q$4999,1,数据录入!$B$5:$B$4999,">="&$B$2,数据录入!$B$5:$B$4999,"<="&$D$2,数据录入!$I$5:$I$4999,$K74)+SUMIFS(数据录入!$F$5:$F$4999,$Q$5:$Q$4999,1,数据录入!$B$5:$B$4999,">="&$B$2,数据录入!$B$5:$B$4999,"<="&$D$2,数据录入!$J$5:$J$4999,$K74)) | N74: =IF($K74="","",SUMIFS(数据录入!$G$5:$G$4999,$Q$5:$Q$4999,1,数据录入!$B$5:$B$4999,">="&$B$2,数据录入!$B$5:$B$4999,"<="&$D$2,数据录入!$I$5:$I$4999,$K74)+SUMIFS(数据录入!$G$5:$G$4999,$Q$5:$Q$4999,1,数据录入!$B$5:$B$4999,">="&$B$2,数据录入!$B$5:$B$4999,"<="&$D$2,数据录入!$J$5:$J$4999,$K74)) | O74: =IF($K74="","",L74+M74-N74) | Q74: =IF(数据录入!$B74="",0,IF(OR(数据录入!$D74="投标保证金",数据录入!$D74="合同履约保证金",ISNUMBER(FIND("保证金",数据录入!$E74))),1,0)) | R74: =IF(AND($Q74=1,数据录入!$B74>=$B$2,数据录入!$B74<=$D$2),N(R73)+1,N(R73)) | S74: =IFERROR(MATCH(67,$R$5:$R$4999,0),"") | U74: =IFERROR(IF(67<=50,INDEX(基础资料!$E$2:$E$51,67)&"",INDEX(基础资料!$G$2:$G$51,67-50)&""),"") | V74: =IF($U74="",0,IF(AND(67>50,COUNTIF(基础资料!$E$2:$E$51,$U74)>0),0,1)) | W74: =IF($V74=1,N(W73)+1,N(W73))
A75: =IF($S75="","",INDEX(数据录入!$B$5:$B$4999,$S75)) | B75: =IF($S75="","",INDEX(数据录入!$C$5:$C$4999,$S75)&"") | C75: =IF($S75="","",IF(N($F75)>0,"收款",IF(N($G75)>0,"付款",""))) | D75: =IF($S75="","",IF((INDEX(数据录入!$I$5:$I$4999,$S75)&"")<>"",INDEX(数据录入!$I$5:$I$4999,$S75)&"",INDEX(数据录入!$J$5:$J$4999,$S75)&"")) | E75: =IF($S75="","",INDEX(数据录入!$E$5:$E$4999,$S75)&"") | F75: =IF($S75="","",N(INDEX(数据录入!$F$5:$F$4999,$S75))) | G75: =IF($S75="","",N(INDEX(数据录入!$G$5:$G$4999,$S75))) | H75: =IF($S75="","",$G$2+SUM($F$8:$F75)-SUM($G$8:$G75)) | J75: =IF($K75="","",68) | K75: =IFERROR(INDEX($U$8:$U$107,MATCH(68,$W$8:$W$107,0)),"") | L75: =IF($K75="","",(SUMIFS(数据录入!$F$5:$F$4999,$Q$5:$Q$4999,1,数据录入!$B$5:$B$4999,"<"&$B$2,数据录入!$I$5:$I$4999,$K75)+SUMIFS(数据录入!$F$5:$F$4999,$Q$5:$Q$4999,1,数据录入!$B$5:$B$4999,"<"&$B$2,数据录入!$J$5:$J$4999,$K75))-(SUMIFS(数据录入!$G$5:$G$4999,$Q$5:$Q$4999,1,数据录入!$B$5:$B$4999,"<"&$B$2,数据录入!$I$5:$I$4999,$K75)+SUMIFS(数据录入!$G$5:$G$4999,$Q$5:$Q$4999,1,数据录入!$B$5:$B$4999,"<"&$B$2,数据录入!$J$5:$J$4999,$K75))) | M75: =IF($K75="","",SUMIFS(数据录入!$F$5:$F$4999,$Q$5:$Q$4999,1,数据录入!$B$5:$B$4999,">="&$B$2,数据录入!$B$5:$B$4999,"<="&$D$2,数据录入!$I$5:$I$4999,$K75)+SUMIFS(数据录入!$F$5:$F$4999,$Q$5:$Q$4999,1,数据录入!$B$5:$B$4999,">="&$B$2,数据录入!$B$5:$B$4999,"<="&$D$2,数据录入!$J$5:$J$4999,$K75)) | N75: =IF($K75="","",SUMIFS(数据录入!$G$5:$G$4999,$Q$5:$Q$4999,1,数据录入!$B$5:$B$4999,">="&$B$2,数据录入!$B$5:$B$4999,"<="&$D$2,数据录入!$I$5:$I$4999,$K75)+SUMIFS(数据录入!$G$5:$G$4999,$Q$5:$Q$4999,1,数据录入!$B$5:$B$4999,">="&$B$2,数据录入!$B$5:$B$4999,"<="&$D$2,数据录入!$J$5:$J$4999,$K75)) | O75: =IF($K75="","",L75+M75-N75) | Q75: =IF(数据录入!$B75="",0,IF(OR(数据录入!$D75="投标保证金",数据录入!$D75="合同履约保证金",ISNUMBER(FIND("保证金",数据录入!$E75))),1,0)) | R75: =IF(AND($Q75=1,数据录入!$B75>=$B$2,数据录入!$B75<=$D$2),N(R74)+1,N(R74)) | S75: =IFERROR(MATCH(68,$R$5:$R$4999,0),"") | U75: =IFERROR(IF(68<=50,INDEX(基础资料!$E$2:$E$51,68)&"",INDEX(基础资料!$G$2:$G$51,68-50)&""),"") | V75: =IF($U75="",0,IF(AND(68>50,COUNTIF(基础资料!$E$2:$E$51,$U75)>0),0,1)) | W75: =IF($V75=1,N(W74)+1,N(W74))
A76: =IF($S76="","",INDEX(数据录入!$B$5:$B$4999,$S76)) | B76: =IF($S76="","",INDEX(数据录入!$C$5:$C$4999,$S76)&"") | C76: =IF($S76="","",IF(N($F76)>0,"收款",IF(N($G76)>0,"付款",""))) | D76: =IF($S76="","",IF((INDEX(数据录入!$I$5:$I$4999,$S76)&"")<>"",INDEX(数据录入!$I$5:$I$4999,$S76)&"",INDEX(数据录入!$J$5:$J$4999,$S76)&"")) | E76: =IF($S76="","",INDEX(数据录入!$E$5:$E$4999,$S76)&"") | F76: =IF($S76="","",N(INDEX(数据录入!$F$5:$F$4999,$S76))) | G76: =IF($S76="","",N(INDEX(数据录入!$G$5:$G$4999,$S76))) | H76: =IF($S76="","",$G$2+SUM($F$8:$F76)-SUM($G$8:$G76)) | J76: =IF($K76="","",69) | K76: =IFERROR(INDEX($U$8:$U$107,MATCH(69,$W$8:$W$107,0)),"") | L76: =IF($K76="","",(SUMIFS(数据录入!$F$5:$F$4999,$Q$5:$Q$4999,1,数据录入!$B$5:$B$4999,"<"&$B$2,数据录入!$I$5:$I$4999,$K76)+SUMIFS(数据录入!$F$5:$F$4999,$Q$5:$Q$4999,1,数据录入!$B$5:$B$4999,"<"&$B$2,数据录入!$J$5:$J$4999,$K76))-(SUMIFS(数据录入!$G$5:$G$4999,$Q$5:$Q$4999,1,数据录入!$B$5:$B$4999,"<"&$B$2,数据录入!$I$5:$I$4999,$K76)+SUMIFS(数据录入!$G$5:$G$4999,$Q$5:$Q$4999,1,数据录入!$B$5:$B$4999,"<"&$B$2,数据录入!$J$5:$J$4999,$K76))) | M76: =IF($K76="","",SUMIFS(数据录入!$F$5:$F$4999,$Q$5:$Q$4999,1,数据录入!$B$5:$B$4999,">="&$B$2,数据录入!$B$5:$B$4999,"<="&$D$2,数据录入!$I$5:$I$4999,$K76)+SUMIFS(数据录入!$F$5:$F$4999,$Q$5:$Q$4999,1,数据录入!$B$5:$B$4999,">="&$B$2,数据录入!$B$5:$B$4999,"<="&$D$2,数据录入!$J$5:$J$4999,$K76)) | N76: =IF($K76="","",SUMIFS(数据录入!$G$5:$G$4999,$Q$5:$Q$4999,1,数据录入!$B$5:$B$4999,">="&$B$2,数据录入!$B$5:$B$4999,"<="&$D$2,数据录入!$I$5:$I$4999,$K76)+SUMIFS(数据录入!$G$5:$G$4999,$Q$5:$Q$4999,1,数据录入!$B$5:$B$4999,">="&$B$2,数据录入!$B$5:$B$4999,"<="&$D$2,数据录入!$J$5:$J$4999,$K76)) | O76: =IF($K76="","",L76+M76-N76) | Q76: =IF(数据录入!$B76="",0,IF(OR(数据录入!$D76="投标保证金",数据录入!$D76="合同履约保证金",ISNUMBER(FIND("保证金",数据录入!$E76))),1,0)) | R76: =IF(AND($Q76=1,数据录入!$B76>=$B$2,数据录入!$B76<=$D$2),N(R75)+1,N(R75)) | S76: =IFERROR(MATCH(69,$R$5:$R$4999,0),"") | U76: =IFERROR(IF(69<=50,INDEX(基础资料!$E$2:$E$51,69)&"",INDEX(基础资料!$G$2:$G$51,69-50)&""),"") | V76: =IF($U76="",0,IF(AND(69>50,COUNTIF(基础资料!$E$2:$E$51,$U76)>0),0,1)) | W76: =IF($V76=1,N(W75)+1,N(W75))
A77: =IF($S77="","",INDEX(数据录入!$B$5:$B$4999,$S77)) | B77: =IF($S77="","",INDEX(数据录入!$C$5:$C$4999,$S77)&"") | C77: =IF($S77="","",IF(N($F77)>0,"收款",IF(N($G77)>0,"付款",""))) | D77: =IF($S77="","",IF((INDEX(数据录入!$I$5:$I$4999,$S77)&"")<>"",INDEX(数据录入!$I$5:$I$4999,$S77)&"",INDEX(数据录入!$J$5:$J$4999,$S77)&"")) | E77: =IF($S77="","",INDEX(数据录入!$E$5:$E$4999,$S77)&"") | F77: =IF($S77="","",N(INDEX(数据录入!$F$5:$F$4999,$S77))) | G77: =IF($S77="","",N(INDEX(数据录入!$G$5:$G$4999,$S77))) | H77: =IF($S77="","",$G$2+SUM($F$8:$F77)-SUM($G$8:$G77)) | J77: =IF($K77="","",70) | K77: =IFERROR(INDEX($U$8:$U$107,MATCH(70,$W$8:$W$107,0)),"") | L77: =IF($K77="","",(SUMIFS(数据录入!$F$5:$F$4999,$Q$5:$Q$4999,1,数据录入!$B$5:$B$4999,"<"&$B$2,数据录入!$I$5:$I$4999,$K77)+SUMIFS(数据录入!$F$5:$F$4999,$Q$5:$Q$4999,1,数据录入!$B$5:$B$4999,"<"&$B$2,数据录入!$J$5:$J$4999,$K77))-(SUMIFS(数据录入!$G$5:$G$4999,$Q$5:$Q$4999,1,数据录入!$B$5:$B$4999,"<"&$B$2,数据录入!$I$5:$I$4999,$K77)+SUMIFS(数据录入!$G$5:$G$4999,$Q$5:$Q$4999,1,数据录入!$B$5:$B$4999,"<"&$B$2,数据录入!$J$5:$J$4999,$K77))) | M77: =IF($K77="","",SUMIFS(数据录入!$F$5:$F$4999,$Q$5:$Q$4999,1,数据录入!$B$5:$B$4999,">="&$B$2,数据录入!$B$5:$B$4999,"<="&$D$2,数据录入!$I$5:$I$4999,$K77)+SUMIFS(数据录入!$F$5:$F$4999,$Q$5:$Q$4999,1,数据录入!$B$5:$B$4999,">="&$B$2,数据录入!$B$5:$B$4999,"<="&$D$2,数据录入!$J$5:$J$4999,$K77)) | N77: =IF($K77="","",SUMIFS(数据录入!$G$5:$G$4999,$Q$5:$Q$4999,1,数据录入!$B$5:$B$4999,">="&$B$2,数据录入!$B$5:$B$4999,"<="&$D$2,数据录入!$I$5:$I$4999,$K77)+SUMIFS(数据录入!$G$5:$G$4999,$Q$5:$Q$4999,1,数据录入!$B$5:$B$4999,">="&$B$2,数据录入!$B$5:$B$4999,"<="&$D$2,数据录入!$J$5:$J$4999,$K77)) | O77: =IF($K77="","",L77+M77-N77) | Q77: =IF(数据录入!$B77="",0,IF(OR(数据录入!$D77="投标保证金",数据录入!$D77="合同履约保证金",ISNUMBER(FIND("保证金",数据录入!$E77))),1,0)) | R77: =IF(AND($Q77=1,数据录入!$B77>=$B$2,数据录入!$B77<=$D$2),N(R76)+1,N(R76)) | S77: =IFERROR(MATCH(70,$R$5:$R$4999,0),"") | U77: =IFERROR(IF(70<=50,INDEX(基础资料!$E$2:$E$51,70)&"",INDEX(基础资料!$G$2:$G$51,70-50)&""),"") | V77: =IF($U77="",0,IF(AND(70>50,COUNTIF(基础资料!$E$2:$E$51,$U77)>0),0,1)) | W77: =IF($V77=1,N(W76)+1,N(W76))
A78: =IF($S78="","",INDEX(数据录入!$B$5:$B$4999,$S78)) | B78: =IF($S78="","",INDEX(数据录入!$C$5:$C$4999,$S78)&"") | C78: =IF($S78="","",IF(N($F78)>0,"收款",IF(N($G78)>0,"付款",""))) | D78: =IF($S78="","",IF((INDEX(数据录入!$I$5:$I$4999,$S78)&"")<>"",INDEX(数据录入!$I$5:$I$4999,$S78)&"",INDEX(数据录入!$J$5:$J$4999,$S78)&"")) | E78: =IF($S78="","",INDEX(数据录入!$E$5:$E$4999,$S78)&"") | F78: =IF($S78="","",N(INDEX(数据录入!$F$5:$F$4999,$S78))) | G78: =IF($S78="","",N(INDEX(数据录入!$G$5:$G$4999,$S78))) | H78: =IF($S78="","",$G$2+SUM($F$8:$F78)-SUM($G$8:$G78)) | J78: =IF($K78="","",71) | K78: =IFERROR(INDEX($U$8:$U$107,MATCH(71,$W$8:$W$107,0)),"") | L78: =IF($K78="","",(SUMIFS(数据录入!$F$5:$F$4999,$Q$5:$Q$4999,1,数据录入!$B$5:$B$4999,"<"&$B$2,数据录入!$I$5:$I$4999,$K78)+SUMIFS(数据录入!$F$5:$F$4999,$Q$5:$Q$4999,1,数据录入!$B$5:$B$4999,"<"&$B$2,数据录入!$J$5:$J$4999,$K78))-(SUMIFS(数据录入!$G$5:$G$4999,$Q$5:$Q$4999,1,数据录入!$B$5:$B$4999,"<"&$B$2,数据录入!$I$5:$I$4999,$K78)+SUMIFS(数据录入!$G$5:$G$4999,$Q$5:$Q$4999,1,数据录入!$B$5:$B$4999,"<"&$B$2,数据录入!$J$5:$J$4999,$K78))) | M78: =IF($K78="","",SUMIFS(数据录入!$F$5:$F$4999,$Q$5:$Q$4999,1,数据录入!$B$5:$B$4999,">="&$B$2,数据录入!$B$5:$B$4999,"<="&$D$2,数据录入!$I$5:$I$4999,$K78)+SUMIFS(数据录入!$F$5:$F$4999,$Q$5:$Q$4999,1,数据录入!$B$5:$B$4999,">="&$B$2,数据录入!$B$5:$B$4999,"<="&$D$2,数据录入!$J$5:$J$4999,$K78)) | N78: =IF($K78="","",SUMIFS(数据录入!$G$5:$G$4999,$Q$5:$Q$4999,1,数据录入!$B$5:$B$4999,">="&$B$2,数据录入!$B$5:$B$4999,"<="&$D$2,数据录入!$I$5:$I$4999,$K78)+SUMIFS(数据录入!$G$5:$G$4999,$Q$5:$Q$4999,1,数据录入!$B$5:$B$4999,">="&$B$2,数据录入!$B$5:$B$4999,"<="&$D$2,数据录入!$J$5:$J$4999,$K78)) | O78: =IF($K78="","",L78+M78-N78) | Q78: =IF(数据录入!$B78="",0,IF(OR(数据录入!$D78="投标保证金",数据录入!$D78="合同履约保证金",ISNUMBER(FIND("保证金",数据录入!$E78))),1,0)) | R78: =IF(AND($Q78=1,数据录入!$B78>=$B$2,数据录入!$B78<=$D$2),N(R77)+1,N(R77)) | S78: =IFERROR(MATCH(71,$R$5:$R$4999,0),"") | U78: =IFERROR(IF(71<=50,INDEX(基础资料!$E$2:$E$51,71)&"",INDEX(基础资料!$G$2:$G$51,71-50)&""),"") | V78: =IF($U78="",0,IF(AND(71>50,COUNTIF(基础资料!$E$2:$E$51,$U78)>0),0,1)) | W78: =IF($V78=1,N(W77)+1,N(W77))
A79: =IF($S79="","",INDEX(数据录入!$B$5:$B$4999,$S79)) | B79: =IF($S79="","",INDEX(数据录入!$C$5:$C$4999,$S79)&"") | C79: =IF($S79="","",IF(N($F79)>0,"收款",IF(N($G79)>0,"付款",""))) | D79: =IF($S79="","",IF((INDEX(数据录入!$I$5:$I$4999,$S79)&"")<>"",INDEX(数据录入!$I$5:$I$4999,$S79)&"",INDEX(数据录入!$J$5:$J$4999,$S79)&"")) | E79: =IF($S79="","",INDEX(数据录入!$E$5:$E$4999,$S79)&"") | F79: =IF($S79="","",N(INDEX(数据录入!$F$5:$F$4999,$S79))) | G79: =IF($S79="","",N(INDEX(数据录入!$G$5:$G$4999,$S79))) | H79: =IF($S79="","",$G$2+SUM($F$8:$F79)-SUM($G$8:$G79)) | J79: =IF($K79="","",72) | K79: =IFERROR(INDEX($U$8:$U$107,MATCH(72,$W$8:$W$107,0)),"") | L79: =IF($K79="","",(SUMIFS(数据录入!$F$5:$F$4999,$Q$5:$Q$4999,1,数据录入!$B$5:$B$4999,"<"&$B$2,数据录入!$I$5:$I$4999,$K79)+SUMIFS(数据录入!$F$5:$F$4999,$Q$5:$Q$4999,1,数据录入!$B$5:$B$4999,"<"&$B$2,数据录入!$J$5:$J$4999,$K79))-(SUMIFS(数据录入!$G$5:$G$4999,$Q$5:$Q$4999,1,数据录入!$B$5:$B$4999,"<"&$B$2,数据录入!$I$5:$I$4999,$K79)+SUMIFS(数据录入!$G$5:$G$4999,$Q$5:$Q$4999,1,数据录入!$B$5:$B$4999,"<"&$B$2,数据录入!$J$5:$J$4999,$K79))) | M79: =IF($K79="","",SUMIFS(数据录入!$F$5:$F$4999,$Q$5:$Q$4999,1,数据录入!$B$5:$B$4999,">="&$B$2,数据录入!$B$5:$B$4999,"<="&$D$2,数据录入!$I$5:$I$4999,$K79)+SUMIFS(数据录入!$F$5:$F$4999,$Q$5:$Q$4999,1,数据录入!$B$5:$B$4999,">="&$B$2,数据录入!$B$5:$B$4999,"<="&$D$2,数据录入!$J$5:$J$4999,$K79)) | N79: =IF($K79="","",SUMIFS(数据录入!$G$5:$G$4999,$Q$5:$Q$4999,1,数据录入!$B$5:$B$4999,">="&$B$2,数据录入!$B$5:$B$4999,"<="&$D$2,数据录入!$I$5:$I$4999,$K79)+SUMIFS(数据录入!$G$5:$G$4999,$Q$5:$Q$4999,1,数据录入!$B$5:$B$4999,">="&$B$2,数据录入!$B$5:$B$4999,"<="&$D$2,数据录入!$J$5:$J$4999,$K79)) | O79: =IF($K79="","",L79+M79-N79) | Q79: =IF(数据录入!$B79="",0,IF(OR(数据录入!$D79="投标保证金",数据录入!$D79="合同履约保证金",ISNUMBER(FIND("保证金",数据录入!$E79))),1,0)) | R79: =IF(AND($Q79=1,数据录入!$B79>=$B$2,数据录入!$B79<=$D$2),N(R78)+1,N(R78)) | S79: =IFERROR(MATCH(72,$R$5:$R$4999,0),"") | U79: =IFERROR(IF(72<=50,INDEX(基础资料!$E$2:$E$51,72)&"",INDEX(基础资料!$G$2:$G$51,72-50)&""),"") | V79: =IF($U79="",0,IF(AND(72>50,COUNTIF(基础资料!$E$2:$E$51,$U79)>0),0,1)) | W79: =IF($V79=1,N(W78)+1,N(W78))
A80: =IF($S80="","",INDEX(数据录入!$B$5:$B$4999,$S80)) | B80: =IF($S80="","",INDEX(数据录入!$C$5:$C$4999,$S80)&"") | C80: =IF($S80="","",IF(N($F80)>0,"收款",IF(N($G80)>0,"付款",""))) | D80: =IF($S80="","",IF((INDEX(数据录入!$I$5:$I$4999,$S80)&"")<>"",INDEX(数据录入!$I$5:$I$4999,$S80)&"",INDEX(数据录入!$J$5:$J$4999,$S80)&"")) | E80: =IF($S80="","",INDEX(数据录入!$E$5:$E$4999,$S80)&"") | F80: =IF($S80="","",N(INDEX(数据录入!$F$5:$F$4999,$S80))) | G80: =IF($S80="","",N(INDEX(数据录入!$G$5:$G$4999,$S80))) | H80: =IF($S80="","",$G$2+SUM($F$8:$F80)-SUM($G$8:$G80)) | J80: =IF($K80="","",73) | K80: =IFERROR(INDEX($U$8:$U$107,MATCH(73,$W$8:$W$107,0)),"") | L80: =IF($K80="","",(SUMIFS(数据录入!$F$5:$F$4999,$Q$5:$Q$4999,1,数据录入!$B$5:$B$4999,"<"&$B$2,数据录入!$I$5:$I$4999,$K80)+SUMIFS(数据录入!$F$5:$F$4999,$Q$5:$Q$4999,1,数据录入!$B$5:$B$4999,"<"&$B$2,数据录入!$J$5:$J$4999,$K80))-(SUMIFS(数据录入!$G$5:$G$4999,$Q$5:$Q$4999,1,数据录入!$B$5:$B$4999,"<"&$B$2,数据录入!$I$5:$I$4999,$K80)+SUMIFS(数据录入!$G$5:$G$4999,$Q$5:$Q$4999,1,数据录入!$B$5:$B$4999,"<"&$B$2,数据录入!$J$5:$J$4999,$K80))) | M80: =IF($K80="","",SUMIFS(数据录入!$F$5:$F$4999,$Q$5:$Q$4999,1,数据录入!$B$5:$B$4999,">="&$B$2,数据录入!$B$5:$B$4999,"<="&$D$2,数据录入!$I$5:$I$4999,$K80)+SUMIFS(数据录入!$F$5:$F$4999,$Q$5:$Q$4999,1,数据录入!$B$5:$B$4999,">="&$B$2,数据录入!$B$5:$B$4999,"<="&$D$2,数据录入!$J$5:$J$4999,$K80)) | N80: =IF($K80="","",SUMIFS(数据录入!$G$5:$G$4999,$Q$5:$Q$4999,1,数据录入!$B$5:$B$4999,">="&$B$2,数据录入!$B$5:$B$4999,"<="&$D$2,数据录入!$I$5:$I$4999,$K80)+SUMIFS(数据录入!$G$5:$G$4999,$Q$5:$Q$4999,1,数据录入!$B$5:$B$4999,">="&$B$2,数据录入!$B$5:$B$4999,"<="&$D$2,数据录入!$J$5:$J$4999,$K80)) | O80: =IF($K80="","",L80+M80-N80) | Q80: =IF(数据录入!$B80="",0,IF(OR(数据录入!$D80="投标保证金",数据录入!$D80="合同履约保证金",ISNUMBER(FIND("保证金",数据录入!$E80))),1,0)) | R80: =IF(AND($Q80=1,数据录入!$B80>=$B$2,数据录入!$B80<=$D$2),N(R79)+1,N(R79)) | S80: =IFERROR(MATCH(73,$R$5:$R$4999,0),"") | U80: =IFERROR(IF(73<=50,INDEX(基础资料!$E$2:$E$51,73)&"",INDEX(基础资料!$G$2:$G$51,73-50)&""),"") | V80: =IF($U80="",0,IF(AND(73>50,COUNTIF(基础资料!$E$2:$E$51,$U80)>0),0,1)) | W80: =IF($V80=1,N(W79)+1,N(W79))
A81: =IF($S81="","",INDEX(数据录入!$B$5:$B$4999,$S81)) | B81: =IF($S81="","",INDEX(数据录入!$C$5:$C$4999,$S81)&"") | C81: =IF($S81="","",IF(N($F81)>0,"收款",IF(N($G81)>0,"付款",""))) | D81: =IF($S81="","",IF((INDEX(数据录入!$I$5:$I$4999,$S81)&"")<>"",INDEX(数据录入!$I$5:$I$4999,$S81)&"",INDEX(数据录入!$J$5:$J$4999,$S81)&"")) | E81: =IF($S81="","",INDEX(数据录入!$E$5:$E$4999,$S81)&"") | F81: =IF($S81="","",N(INDEX(数据录入!$F$5:$F$4999,$S81))) | G81: =IF($S81="","",N(INDEX(数据录入!$G$5:$G$4999,$S81))) | H81: =IF($S81="","",$G$2+SUM($F$8:$F81)-SUM($G$8:$G81)) | J81: =IF($K81="","",74) | K81: =IFERROR(INDEX($U$8:$U$107,MATCH(74,$W$8:$W$107,0)),"") | L81: =IF($K81="","",(SUMIFS(数据录入!$F$5:$F$4999,$Q$5:$Q$4999,1,数据录入!$B$5:$B$4999,"<"&$B$2,数据录入!$I$5:$I$4999,$K81)+SUMIFS(数据录入!$F$5:$F$4999,$Q$5:$Q$4999,1,数据录入!$B$5:$B$4999,"<"&$B$2,数据录入!$J$5:$J$4999,$K81))-(SUMIFS(数据录入!$G$5:$G$4999,$Q$5:$Q$4999,1,数据录入!$B$5:$B$4999,"<"&$B$2,数据录入!$I$5:$I$4999,$K81)+SUMIFS(数据录入!$G$5:$G$4999,$Q$5:$Q$4999,1,数据录入!$B$5:$B$4999,"<"&$B$2,数据录入!$J$5:$J$4999,$K81))) | M81: =IF($K81="","",SUMIFS(数据录入!$F$5:$F$4999,$Q$5:$Q$4999,1,数据录入!$B$5:$B$4999,">="&$B$2,数据录入!$B$5:$B$4999,"<="&$D$2,数据录入!$I$5:$I$4999,$K81)+SUMIFS(数据录入!$F$5:$F$4999,$Q$5:$Q$4999,1,数据录入!$B$5:$B$4999,">="&$B$2,数据录入!$B$5:$B$4999,"<="&$D$2,数据录入!$J$5:$J$4999,$K81)) | N81: =IF($K81="","",SUMIFS(数据录入!$G$5:$G$4999,$Q$5:$Q$4999,1,数据录入!$B$5:$B$4999,">="&$B$2,数据录入!$B$5:$B$4999,"<="&$D$2,数据录入!$I$5:$I$4999,$K81)+SUMIFS(数据录入!$G$5:$G$4999,$Q$5:$Q$4999,1,数据录入!$B$5:$B$4999,">="&$B$2,数据录入!$B$5:$B$4999,"<="&$D$2,数据录入!$J$5:$J$4999,$K81)) | O81: =IF($K81="","",L81+M81-N81) | Q81: =IF(数据录入!$B81="",0,IF(OR(数据录入!$D81="投标保证金",数据录入!$D81="合同履约保证金",ISNUMBER(FIND("保证金",数据录入!$E81))),1,0)) | R81: =IF(AND($Q81=1,数据录入!$B81>=$B$2,数据录入!$B81<=$D$2),N(R80)+1,N(R80)) | S81: =IFERROR(MATCH(74,$R$5:$R$4999,0),"") | U81: =IFERROR(IF(74<=50,INDEX(基础资料!$E$2:$E$51,74)&"",INDEX(基础资料!$G$2:$G$51,74-50)&""),"") | V81: =IF($U81="",0,IF(AND(74>50,COUNTIF(基础资料!$E$2:$E$51,$U81)>0),0,1)) | W81: =IF($V81=1,N(W80)+1,N(W80))
A82: =IF($S82="","",INDEX(数据录入!$B$5:$B$4999,$S82)) | B82: =IF($S82="","",INDEX(数据录入!$C$5:$C$4999,$S82)&"") | C82: =IF($S82="","",IF(N($F82)>0,"收款",IF(N($G82)>0,"付款",""))) | D82: =IF($S82="","",IF((INDEX(数据录入!$I$5:$I$4999,$S82)&"")<>"",INDEX(数据录入!$I$5:$I$4999,$S82)&"",INDEX(数据录入!$J$5:$J$4999,$S82)&"")) | E82: =IF($S82="","",INDEX(数据录入!$E$5:$E$4999,$S82)&"") | F82: =IF($S82="","",N(INDEX(数据录入!$F$5:$F$4999,$S82))) | G82: =IF($S82="","",N(INDEX(数据录入!$G$5:$G$4999,$S82))) | H82: =IF($S82="","",$G$2+SUM($F$8:$F82)-SUM($G$8:$G82)) | J82: =IF($K82="","",75) | K82: =IFERROR(INDEX($U$8:$U$107,MATCH(75,$W$8:$W$107,0)),"") | L82: =IF($K82="","",(SUMIFS(数据录入!$F$5:$F$4999,$Q$5:$Q$4999,1,数据录入!$B$5:$B$4999,"<"&$B$2,数据录入!$I$5:$I$4999,$K82)+SUMIFS(数据录入!$F$5:$F$4999,$Q$5:$Q$4999,1,数据录入!$B$5:$B$4999,"<"&$B$2,数据录入!$J$5:$J$4999,$K82))-(SUMIFS(数据录入!$G$5:$G$4999,$Q$5:$Q$4999,1,数据录入!$B$5:$B$4999,"<"&$B$2,数据录入!$I$5:$I$4999,$K82)+SUMIFS(数据录入!$G$5:$G$4999,$Q$5:$Q$4999,1,数据录入!$B$5:$B$4999,"<"&$B$2,数据录入!$J$5:$J$4999,$K82))) | M82: =IF($K82="","",SUMIFS(数据录入!$F$5:$F$4999,$Q$5:$Q$4999,1,数据录入!$B$5:$B$4999,">="&$B$2,数据录入!$B$5:$B$4999,"<="&$D$2,数据录入!$I$5:$I$4999,$K82)+SUMIFS(数据录入!$F$5:$F$4999,$Q$5:$Q$4999,1,数据录入!$B$5:$B$4999,">="&$B$2,数据录入!$B$5:$B$4999,"<="&$D$2,数据录入!$J$5:$J$4999,$K82)) | N82: =IF($K82="","",SUMIFS(数据录入!$G$5:$G$4999,$Q$5:$Q$4999,1,数据录入!$B$5:$B$4999,">="&$B$2,数据录入!$B$5:$B$4999,"<="&$D$2,数据录入!$I$5:$I$4999,$K82)+SUMIFS(数据录入!$G$5:$G$4999,$Q$5:$Q$4999,1,数据录入!$B$5:$B$4999,">="&$B$2,数据录入!$B$5:$B$4999,"<="&$D$2,数据录入!$J$5:$J$4999,$K82)) | O82: =IF($K82="","",L82+M82-N82) | Q82: =IF(数据录入!$B82="",0,IF(OR(数据录入!$D82="投标保证金",数据录入!$D82="合同履约保证金",ISNUMBER(FIND("保证金",数据录入!$E82))),1,0)) | R82: =IF(AND($Q82=1,数据录入!$B82>=$B$2,数据录入!$B82<=$D$2),N(R81)+1,N(R81)) | S82: =IFERROR(MATCH(75,$R$5:$R$4999,0),"") | U82: =IFERROR(IF(75<=50,INDEX(基础资料!$E$2:$E$51,75)&"",INDEX(基础资料!$G$2:$G$51,75-50)&""),"") | V82: =IF($U82="",0,IF(AND(75>50,COUNTIF(基础资料!$E$2:$E$51,$U82)>0),0,1)) | W82: =IF($V82=1,N(W81)+1,N(W81))
A83: =IF($S83="","",INDEX(数据录入!$B$5:$B$4999,$S83)) | B83: =IF($S83="","",INDEX(数据录入!$C$5:$C$4999,$S83)&"") | C83: =IF($S83="","",IF(N($F83)>0,"收款",IF(N($G83)>0,"付款",""))) | D83: =IF($S83="","",IF((INDEX(数据录入!$I$5:$I$4999,$S83)&"")<>"",INDEX(数据录入!$I$5:$I$4999,$S83)&"",INDEX(数据录入!$J$5:$J$4999,$S83)&"")) | E83: =IF($S83="","",INDEX(数据录入!$E$5:$E$4999,$S83)&"") | F83: =IF($S83="","",N(INDEX(数据录入!$F$5:$F$4999,$S83))) | G83: =IF($S83="","",N(INDEX(数据录入!$G$5:$G$4999,$S83))) | H83: =IF($S83="","",$G$2+SUM($F$8:$F83)-SUM($G$8:$G83)) | J83: =IF($K83="","",76) | K83: =IFERROR(INDEX($U$8:$U$107,MATCH(76,$W$8:$W$107,0)),"") | L83: =IF($K83="","",(SUMIFS(数据录入!$F$5:$F$4999,$Q$5:$Q$4999,1,数据录入!$B$5:$B$4999,"<"&$B$2,数据录入!$I$5:$I$4999,$K83)+SUMIFS(数据录入!$F$5:$F$4999,$Q$5:$Q$4999,1,数据录入!$B$5:$B$4999,"<"&$B$2,数据录入!$J$5:$J$4999,$K83))-(SUMIFS(数据录入!$G$5:$G$4999,$Q$5:$Q$4999,1,数据录入!$B$5:$B$4999,"<"&$B$2,数据录入!$I$5:$I$4999,$K83)+SUMIFS(数据录入!$G$5:$G$4999,$Q$5:$Q$4999,1,数据录入!$B$5:$B$4999,"<"&$B$2,数据录入!$J$5:$J$4999,$K83))) | M83: =IF($K83="","",SUMIFS(数据录入!$F$5:$F$4999,$Q$5:$Q$4999,1,数据录入!$B$5:$B$4999,">="&$B$2,数据录入!$B$5:$B$4999,"<="&$D$2,数据录入!$I$5:$I$4999,$K83)+SUMIFS(数据录入!$F$5:$F$4999,$Q$5:$Q$4999,1,数据录入!$B$5:$B$4999,">="&$B$2,数据录入!$B$5:$B$4999,"<="&$D$2,数据录入!$J$5:$J$4999,$K83)) | N83: =IF($K83="","",SUMIFS(数据录入!$G$5:$G$4999,$Q$5:$Q$4999,1,数据录入!$B$5:$B$4999,">="&$B$2,数据录入!$B$5:$B$4999,"<="&$D$2,数据录入!$I$5:$I$4999,$K83)+SUMIFS(数据录入!$G$5:$G$4999,$Q$5:$Q$4999,1,数据录入!$B$5:$B$4999,">="&$B$2,数据录入!$B$5:$B$4999,"<="&$D$2,数据录入!$J$5:$J$4999,$K83)) | O83: =IF($K83="","",L83+M83-N83) | Q83: =IF(数据录入!$B83="",0,IF(OR(数据录入!$D83="投标保证金",数据录入!$D83="合同履约保证金",ISNUMBER(FIND("保证金",数据录入!$E83))),1,0)) | R83: =IF(AND($Q83=1,数据录入!$B83>=$B$2,数据录入!$B83<=$D$2),N(R82)+1,N(R82)) | S83: =IFERROR(MATCH(76,$R$5:$R$4999,0),"") | U83: =IFERROR(IF(76<=50,INDEX(基础资料!$E$2:$E$51,76)&"",INDEX(基础资料!$G$2:$G$51,76-50)&""),"") | V83: =IF($U83="",0,IF(AND(76>50,COUNTIF(基础资料!$E$2:$E$51,$U83)>0),0,1)) | W83: =IF($V83=1,N(W82)+1,N(W82))
A84: =IF($S84="","",INDEX(数据录入!$B$5:$B$4999,$S84)) | B84: =IF($S84="","",INDEX(数据录入!$C$5:$C$4999,$S84)&"") | C84: =IF($S84="","",IF(N($F84)>0,"收款",IF(N($G84)>0,"付款",""))) | D84: =IF($S84="","",IF((INDEX(数据录入!$I$5:$I$4999,$S84)&"")<>"",INDEX(数据录入!$I$5:$I$4999,$S84)&"",INDEX(数据录入!$J$5:$J$4999,$S84)&"")) | E84: =IF($S84="","",INDEX(数据录入!$E$5:$E$4999,$S84)&"") | F84: =IF($S84="","",N(INDEX(数据录入!$F$5:$F$4999,$S84))) | G84: =IF($S84="","",N(INDEX(数据录入!$G$5:$G$4999,$S84))) | H84: =IF($S84="","",$G$2+SUM($F$8:$F84)-SUM($G$8:$G84)) | J84: =IF($K84="","",77) | K84: =IFERROR(INDEX($U$8:$U$107,MATCH(77,$W$8:$W$107,0)),"") | L84: =IF($K84="","",(SUMIFS(数据录入!$F$5:$F$4999,$Q$5:$Q$4999,1,数据录入!$B$5:$B$4999,"<"&$B$2,数据录入!$I$5:$I$4999,$K84)+SUMIFS(数据录入!$F$5:$F$4999,$Q$5:$Q$4999,1,数据录入!$B$5:$B$4999,"<"&$B$2,数据录入!$J$5:$J$4999,$K84))-(SUMIFS(数据录入!$G$5:$G$4999,$Q$5:$Q$4999,1,数据录入!$B$5:$B$4999,"<"&$B$2,数据录入!$I$5:$I$4999,$K84)+SUMIFS(数据录入!$G$5:$G$4999,$Q$5:$Q$4999,1,数据录入!$B$5:$B$4999,"<"&$B$2,数据录入!$J$5:$J$4999,$K84))) | M84: =IF($K84="","",SUMIFS(数据录入!$F$5:$F$4999,$Q$5:$Q$4999,1,数据录入!$B$5:$B$4999,">="&$B$2,数据录入!$B$5:$B$4999,"<="&$D$2,数据录入!$I$5:$I$4999,$K84)+SUMIFS(数据录入!$F$5:$F$4999,$Q$5:$Q$4999,1,数据录入!$B$5:$B$4999,">="&$B$2,数据录入!$B$5:$B$4999,"<="&$D$2,数据录入!$J$5:$J$4999,$K84)) | N84: =IF($K84="","",SUMIFS(数据录入!$G$5:$G$4999,$Q$5:$Q$4999,1,数据录入!$B$5:$B$4999,">="&$B$2,数据录入!$B$5:$B$4999,"<="&$D$2,数据录入!$I$5:$I$4999,$K84)+SUMIFS(数据录入!$G$5:$G$4999,$Q$5:$Q$4999,1,数据录入!$B$5:$B$4999,">="&$B$2,数据录入!$B$5:$B$4999,"<="&$D$2,数据录入!$J$5:$J$4999,$K84)) | O84: =IF($K84="","",L84+M84-N84) | Q84: =IF(数据录入!$B84="",0,IF(OR(数据录入!$D84="投标保证金",数据录入!$D84="合同履约保证金",ISNUMBER(FIND("保证金",数据录入!$E84))),1,0)) | R84: =IF(AND($Q84=1,数据录入!$B84>=$B$2,数据录入!$B84<=$D$2),N(R83)+1,N(R83)) | S84: =IFERROR(MATCH(77,$R$5:$R$4999,0),"") | U84: =IFERROR(IF(77<=50,INDEX(基础资料!$E$2:$E$51,77)&"",INDEX(基础资料!$G$2:$G$51,77-50)&""),"") | V84: =IF($U84="",0,IF(AND(77>50,COUNTIF(基础资料!$E$2:$E$51,$U84)>0),0,1)) | W84: =IF($V84=1,N(W83)+1,N(W83))
A85: =IF($S85="","",INDEX(数据录入!$B$5:$B$4999,$S85)) | B85: =IF($S85="","",INDEX(数据录入!$C$5:$C$4999,$S85)&"") | C85: =IF($S85="","",IF(N($F85)>0,"收款",IF(N($G85)>0,"付款",""))) | D85: =IF($S85="","",IF((INDEX(数据录入!$I$5:$I$4999,$S85)&"")<>"",INDEX(数据录入!$I$5:$I$4999,$S85)&"",INDEX(数据录入!$J$5:$J$4999,$S85)&"")) | E85: =IF($S85="","",INDEX(数据录入!$E$5:$E$4999,$S85)&"") | F85: =IF($S85="","",N(INDEX(数据录入!$F$5:$F$4999,$S85))) | G85: =IF($S85="","",N(INDEX(数据录入!$G$5:$G$4999,$S85))) | H85: =IF($S85="","",$G$2+SUM($F$8:$F85)-SUM($G$8:$G85)) | J85: =IF($K85="","",78) | K85: =IFERROR(INDEX($U$8:$U$107,MATCH(78,$W$8:$W$107,0)),"") | L85: =IF($K85="","",(SUMIFS(数据录入!$F$5:$F$4999,$Q$5:$Q$4999,1,数据录入!$B$5:$B$4999,"<"&$B$2,数据录入!$I$5:$I$4999,$K85)+SUMIFS(数据录入!$F$5:$F$4999,$Q$5:$Q$4999,1,数据录入!$B$5:$B$4999,"<"&$B$2,数据录入!$J$5:$J$4999,$K85))-(SUMIFS(数据录入!$G$5:$G$4999,$Q$5:$Q$4999,1,数据录入!$B$5:$B$4999,"<"&$B$2,数据录入!$I$5:$I$4999,$K85)+SUMIFS(数据录入!$G$5:$G$4999,$Q$5:$Q$4999,1,数据录入!$B$5:$B$4999,"<"&$B$2,数据录入!$J$5:$J$4999,$K85))) | M85: =IF($K85="","",SUMIFS(数据录入!$F$5:$F$4999,$Q$5:$Q$4999,1,数据录入!$B$5:$B$4999,">="&$B$2,数据录入!$B$5:$B$4999,"<="&$D$2,数据录入!$I$5:$I$4999,$K85)+SUMIFS(数据录入!$F$5:$F$4999,$Q$5:$Q$4999,1,数据录入!$B$5:$B$4999,">="&$B$2,数据录入!$B$5:$B$4999,"<="&$D$2,数据录入!$J$5:$J$4999,$K85)) | N85: =IF($K85="","",SUMIFS(数据录入!$G$5:$G$4999,$Q$5:$Q$4999,1,数据录入!$B$5:$B$4999,">="&$B$2,数据录入!$B$5:$B$4999,"<="&$D$2,数据录入!$I$5:$I$4999,$K85)+SUMIFS(数据录入!$G$5:$G$4999,$Q$5:$Q$4999,1,数据录入!$B$5:$B$4999,">="&$B$2,数据录入!$B$5:$B$4999,"<="&$D$2,数据录入!$J$5:$J$4999,$K85)) | O85: =IF($K85="","",L85+M85-N85) | Q85: =IF(数据录入!$B85="",0,IF(OR(数据录入!$D85="投标保证金",数据录入!$D85="合同履约保证金",ISNUMBER(FIND("保证金",数据录入!$E85))),1,0)) | R85: =IF(AND($Q85=1,数据录入!$B85>=$B$2,数据录入!$B85<=$D$2),N(R84)+1,N(R84)) | S85: =IFERROR(MATCH(78,$R$5:$R$4999,0),"") | U85: =IFERROR(IF(78<=50,INDEX(基础资料!$E$2:$E$51,78)&"",INDEX(基础资料!$G$2:$G$51,78-50)&""),"") | V85: =IF($U85="",0,IF(AND(78>50,COUNTIF(基础资料!$E$2:$E$51,$U85)>0),0,1)) | W85: =IF($V85=1,N(W84)+1,N(W84))
A86: =IF($S86="","",INDEX(数据录入!$B$5:$B$4999,$S86)) | B86: =IF($S86="","",INDEX(数据录入!$C$5:$C$4999,$S86)&"") | C86: =IF($S86="","",IF(N($F86)>0,"收款",IF(N($G86)>0,"付款",""))) | D86: =IF($S86="","",IF((INDEX(数据录入!$I$5:$I$4999,$S86)&"")<>"",INDEX(数据录入!$I$5:$I$4999,$S86)&"",INDEX(数据录入!$J$5:$J$4999,$S86)&"")) | E86: =IF($S86="","",INDEX(数据录入!$E$5:$E$4999,$S86)&"") | F86: =IF($S86="","",N(INDEX(数据录入!$F$5:$F$4999,$S86))) | G86: =IF($S86="","",N(INDEX(数据录入!$G$5:$G$4999,$S86))) | H86: =IF($S86="","",$G$2+SUM($F$8:$F86)-SUM($G$8:$G86)) | J86: =IF($K86="","",79) | K86: =IFERROR(INDEX($U$8:$U$107,MATCH(79,$W$8:$W$107,0)),"") | L86: =IF($K86="","",(SUMIFS(数据录入!$F$5:$F$4999,$Q$5:$Q$4999,1,数据录入!$B$5:$B$4999,"<"&$B$2,数据录入!$I$5:$I$4999,$K86)+SUMIFS(数据录入!$F$5:$F$4999,$Q$5:$Q$4999,1,数据录入!$B$5:$B$4999,"<"&$B$2,数据录入!$J$5:$J$4999,$K86))-(SUMIFS(数据录入!$G$5:$G$4999,$Q$5:$Q$4999,1,数据录入!$B$5:$B$4999,"<"&$B$2,数据录入!$I$5:$I$4999,$K86)+SUMIFS(数据录入!$G$5:$G$4999,$Q$5:$Q$4999,1,数据录入!$B$5:$B$4999,"<"&$B$2,数据录入!$J$5:$J$4999,$K86))) | M86: =IF($K86="","",SUMIFS(数据录入!$F$5:$F$4999,$Q$5:$Q$4999,1,数据录入!$B$5:$B$4999,">="&$B$2,数据录入!$B$5:$B$4999,"<="&$D$2,数据录入!$I$5:$I$4999,$K86)+SUMIFS(数据录入!$F$5:$F$4999,$Q$5:$Q$4999,1,数据录入!$B$5:$B$4999,">="&$B$2,数据录入!$B$5:$B$4999,"<="&$D$2,数据录入!$J$5:$J$4999,$K86)) | N86: =IF($K86="","",SUMIFS(数据录入!$G$5:$G$4999,$Q$5:$Q$4999,1,数据录入!$B$5:$B$4999,">="&$B$2,数据录入!$B$5:$B$4999,"<="&$D$2,数据录入!$I$5:$I$4999,$K86)+SUMIFS(数据录入!$G$5:$G$4999,$Q$5:$Q$4999,1,数据录入!$B$5:$B$4999,">="&$B$2,数据录入!$B$5:$B$4999,"<="&$D$2,数据录入!$J$5:$J$4999,$K86)) | O86: =IF($K86="","",L86+M86-N86) | Q86: =IF(数据录入!$B86="",0,IF(OR(数据录入!$D86="投标保证金",数据录入!$D86="合同履约保证金",ISNUMBER(FIND("保证金",数据录入!$E86))),1,0)) | R86: =IF(AND($Q86=1,数据录入!$B86>=$B$2,数据录入!$B86<=$D$2),N(R85)+1,N(R85)) | S86: =IFERROR(MATCH(79,$R$5:$R$4999,0),"") | U86: =IFERROR(IF(79<=50,INDEX(基础资料!$E$2:$E$51,79)&"",INDEX(基础资料!$G$2:$G$51,79-50)&""),"") | V86: =IF($U86="",0,IF(AND(79>50,COUNTIF(基础资料!$E$2:$E$51,$U86)>0),0,1)) | W86: =IF($V86=1,N(W85)+1,N(W85))
A87: =IF($S87="","",INDEX(数据录入!$B$5:$B$4999,$S87)) | B87: =IF($S87="","",INDEX(数据录入!$C$5:$C$4999,$S87)&"") | C87: =IF($S87="","",IF(N($F87)>0,"收款",IF(N($G87)>0,"付款",""))) | D87: =IF($S87="","",IF((INDEX(数据录入!$I$5:$I$4999,$S87)&"")<>"",INDEX(数据录入!$I$5:$I$4999,$S87)&"",INDEX(数据录入!$J$5:$J$4999,$S87)&"")) | E87: =IF($S87="","",INDEX(数据录入!$E$5:$E$4999,$S87)&"") | F87: =IF($S87="","",N(INDEX(数据录入!$F$5:$F$4999,$S87))) | G87: =IF($S87="","",N(INDEX(数据录入!$G$5:$G$4999,$S87))) | H87: =IF($S87="","",$G$2+SUM($F$8:$F87)-SUM($G$8:$G87)) | J87: =IF($K87="","",80) | K87: =IFERROR(INDEX($U$8:$U$107,MATCH(80,$W$8:$W$107,0)),"") | L87: =IF($K87="","",(SUMIFS(数据录入!$F$5:$F$4999,$Q$5:$Q$4999,1,数据录入!$B$5:$B$4999,"<"&$B$2,数据录入!$I$5:$I$4999,$K87)+SUMIFS(数据录入!$F$5:$F$4999,$Q$5:$Q$4999,1,数据录入!$B$5:$B$4999,"<"&$B$2,数据录入!$J$5:$J$4999,$K87))-(SUMIFS(数据录入!$G$5:$G$4999,$Q$5:$Q$4999,1,数据录入!$B$5:$B$4999,"<"&$B$2,数据录入!$I$5:$I$4999,$K87)+SUMIFS(数据录入!$G$5:$G$4999,$Q$5:$Q$4999,1,数据录入!$B$5:$B$4999,"<"&$B$2,数据录入!$J$5:$J$4999,$K87))) | M87: =IF($K87="","",SUMIFS(数据录入!$F$5:$F$4999,$Q$5:$Q$4999,1,数据录入!$B$5:$B$4999,">="&$B$2,数据录入!$B$5:$B$4999,"<="&$D$2,数据录入!$I$5:$I$4999,$K87)+SUMIFS(数据录入!$F$5:$F$4999,$Q$5:$Q$4999,1,数据录入!$B$5:$B$4999,">="&$B$2,数据录入!$B$5:$B$4999,"<="&$D$2,数据录入!$J$5:$J$4999,$K87)) | N87: =IF($K87="","",SUMIFS(数据录入!$G$5:$G$4999,$Q$5:$Q$4999,1,数据录入!$B$5:$B$4999,">="&$B$2,数据录入!$B$5:$B$4999,"<="&$D$2,数据录入!$I$5:$I$4999,$K87)+SUMIFS(数据录入!$G$5:$G$4999,$Q$5:$Q$4999,1,数据录入!$B$5:$B$4999,">="&$B$2,数据录入!$B$5:$B$4999,"<="&$D$2,数据录入!$J$5:$J$4999,$K87)) | O87: =IF($K87="","",L87+M87-N87) | Q87: =IF(数据录入!$B87="",0,IF(OR(数据录入!$D87="投标保证金",数据录入!$D87="合同履约保证金",ISNUMBER(FIND("保证金",数据录入!$E87))),1,0)) | R87: =IF(AND($Q87=1,数据录入!$B87>=$B$2,数据录入!$B87<=$D$2),N(R86)+1,N(R86)) | S87: =IFERROR(MATCH(80,$R$5:$R$4999,0),"") | U87: =IFERROR(IF(80<=50,INDEX(基础资料!$E$2:$E$51,80)&"",INDEX(基础资料!$G$2:$G$51,80-50)&""),"") | V87: =IF($U87="",0,IF(AND(80>50,COUNTIF(基础资料!$E$2:$E$51,$U87)>0),0,1)) | W87: =IF($V87=1,N(W86)+1,N(W86))
A88: =IF($S88="","",INDEX(数据录入!$B$5:$B$4999,$S88)) | B88: =IF($S88="","",INDEX(数据录入!$C$5:$C$4999,$S88)&"") | C88: =IF($S88="","",IF(N($F88)>0,"收款",IF(N($G88)>0,"付款",""))) | D88: =IF($S88="","",IF((INDEX(数据录入!$I$5:$I$4999,$S88)&"")<>"",INDEX(数据录入!$I$5:$I$4999,$S88)&"",INDEX(数据录入!$J$5:$J$4999,$S88)&"")) | E88: =IF($S88="","",INDEX(数据录入!$E$5:$E$4999,$S88)&"") | F88: =IF($S88="","",N(INDEX(数据录入!$F$5:$F$4999,$S88))) | G88: =IF($S88="","",N(INDEX(数据录入!$G$5:$G$4999,$S88))) | H88: =IF($S88="","",$G$2+SUM($F$8:$F88)-SUM($G$8:$G88)) | J88: =IF($K88="","",81) | K88: =IFERROR(INDEX($U$8:$U$107,MATCH(81,$W$8:$W$107,0)),"") | L88: =IF($K88="","",(SUMIFS(数据录入!$F$5:$F$4999,$Q$5:$Q$4999,1,数据录入!$B$5:$B$4999,"<"&$B$2,数据录入!$I$5:$I$4999,$K88)+SUMIFS(数据录入!$F$5:$F$4999,$Q$5:$Q$4999,1,数据录入!$B$5:$B$4999,"<"&$B$2,数据录入!$J$5:$J$4999,$K88))-(SUMIFS(数据录入!$G$5:$G$4999,$Q$5:$Q$4999,1,数据录入!$B$5:$B$4999,"<"&$B$2,数据录入!$I$5:$I$4999,$K88)+SUMIFS(数据录入!$G$5:$G$4999,$Q$5:$Q$4999,1,数据录入!$B$5:$B$4999,"<"&$B$2,数据录入!$J$5:$J$4999,$K88))) | M88: =IF($K88="","",SUMIFS(数据录入!$F$5:$F$4999,$Q$5:$Q$4999,1,数据录入!$B$5:$B$4999,">="&$B$2,数据录入!$B$5:$B$4999,"<="&$D$2,数据录入!$I$5:$I$4999,$K88)+SUMIFS(数据录入!$F$5:$F$4999,$Q$5:$Q$4999,1,数据录入!$B$5:$B$4999,">="&$B$2,数据录入!$B$5:$B$4999,"<="&$D$2,数据录入!$J$5:$J$4999,$K88)) | N88: =IF($K88="","",SUMIFS(数据录入!$G$5:$G$4999,$Q$5:$Q$4999,1,数据录入!$B$5:$B$4999,">="&$B$2,数据录入!$B$5:$B$4999,"<="&$D$2,数据录入!$I$5:$I$4999,$K88)+SUMIFS(数据录入!$G$5:$G$4999,$Q$5:$Q$4999,1,数据录入!$B$5:$B$4999,">="&$B$2,数据录入!$B$5:$B$4999,"<="&$D$2,数据录入!$J$5:$J$4999,$K88)) | O88: =IF($K88="","",L88+M88-N88) | Q88: =IF(数据录入!$B88="",0,IF(OR(数据录入!$D88="投标保证金",数据录入!$D88="合同履约保证金",ISNUMBER(FIND("保证金",数据录入!$E88))),1,0)) | R88: =IF(AND($Q88=1,数据录入!$B88>=$B$2,数据录入!$B88<=$D$2),N(R87)+1,N(R87)) | S88: =IFERROR(MATCH(81,$R$5:$R$4999,0),"") | U88: =IFERROR(IF(81<=50,INDEX(基础资料!$E$2:$E$51,81)&"",INDEX(基础资料!$G$2:$G$51,81-50)&""),"") | V88: =IF($U88="",0,IF(AND(81>50,COUNTIF(基础资料!$E$2:$E$51,$U88)>0),0,1)) | W88: =IF($V88=1,N(W87)+1,N(W87))
A89: =IF($S89="","",INDEX(数据录入!$B$5:$B$4999,$S89)) | B89: =IF($S89="","",INDEX(数据录入!$C$5:$C$4999,$S89)&"") | C89: =IF($S89="","",IF(N($F89)>0,"收款",IF(N($G89)>0,"付款",""))) | D89: =IF($S89="","",IF((INDEX(数据录入!$I$5:$I$4999,$S89)&"")<>"",INDEX(数据录入!$I$5:$I$4999,$S89)&"",INDEX(数据录入!$J$5:$J$4999,$S89)&"")) | E89: =IF($S89="","",INDEX(数据录入!$E$5:$E$4999,$S89)&"") | F89: =IF($S89="","",N(INDEX(数据录入!$F$5:$F$4999,$S89))) | G89: =IF($S89="","",N(INDEX(数据录入!$G$5:$G$4999,$S89))) | H89: =IF($S89="","",$G$2+SUM($F$8:$F89)-SUM($G$8:$G89)) | J89: =IF($K89="","",82) | K89: =IFERROR(INDEX($U$8:$U$107,MATCH(82,$W$8:$W$107,0)),"") | L89: =IF($K89="","",(SUMIFS(数据录入!$F$5:$F$4999,$Q$5:$Q$4999,1,数据录入!$B$5:$B$4999,"<"&$B$2,数据录入!$I$5:$I$4999,$K89)+SUMIFS(数据录入!$F$5:$F$4999,$Q$5:$Q$4999,1,数据录入!$B$5:$B$4999,"<"&$B$2,数据录入!$J$5:$J$4999,$K89))-(SUMIFS(数据录入!$G$5:$G$4999,$Q$5:$Q$4999,1,数据录入!$B$5:$B$4999,"<"&$B$2,数据录入!$I$5:$I$4999,$K89)+SUMIFS(数据录入!$G$5:$G$4999,$Q$5:$Q$4999,1,数据录入!$B$5:$B$4999,"<"&$B$2,数据录入!$J$5:$J$4999,$K89))) | M89: =IF($K89="","",SUMIFS(数据录入!$F$5:$F$4999,$Q$5:$Q$4999,1,数据录入!$B$5:$B$4999,">="&$B$2,数据录入!$B$5:$B$4999,"<="&$D$2,数据录入!$I$5:$I$4999,$K89)+SUMIFS(数据录入!$F$5:$F$4999,$Q$5:$Q$4999,1,数据录入!$B$5:$B$4999,">="&$B$2,数据录入!$B$5:$B$4999,"<="&$D$2,数据录入!$J$5:$J$4999,$K89)) | N89: =IF($K89="","",SUMIFS(数据录入!$G$5:$G$4999,$Q$5:$Q$4999,1,数据录入!$B$5:$B$4999,">="&$B$2,数据录入!$B$5:$B$4999,"<="&$D$2,数据录入!$I$5:$I$4999,$K89)+SUMIFS(数据录入!$G$5:$G$4999,$Q$5:$Q$4999,1,数据录入!$B$5:$B$4999,">="&$B$2,数据录入!$B$5:$B$4999,"<="&$D$2,数据录入!$J$5:$J$4999,$K89)) | O89: =IF($K89="","",L89+M89-N89) | Q89: =IF(数据录入!$B89="",0,IF(OR(数据录入!$D89="投标保证金",数据录入!$D89="合同履约保证金",ISNUMBER(FIND("保证金",数据录入!$E89))),1,0)) | R89: =IF(AND($Q89=1,数据录入!$B89>=$B$2,数据录入!$B89<=$D$2),N(R88)+1,N(R88)) | S89: =IFERROR(MATCH(82,$R$5:$R$4999,0),"") | U89: =IFERROR(IF(82<=50,INDEX(基础资料!$E$2:$E$51,82)&"",INDEX(基础资料!$G$2:$G$51,82-50)&""),"") | V89: =IF($U89="",0,IF(AND(82>50,COUNTIF(基础资料!$E$2:$E$51,$U89)>0),0,1)) | W89: =IF($V89=1,N(W88)+1,N(W88))
A90: =IF($S90="","",INDEX(数据录入!$B$5:$B$4999,$S90)) | B90: =IF($S90="","",INDEX(数据录入!$C$5:$C$4999,$S90)&"") | C90: =IF($S90="","",IF(N($F90)>0,"收款",IF(N($G90)>0,"付款",""))) | D90: =IF($S90="","",IF((INDEX(数据录入!$I$5:$I$4999,$S90)&"")<>"",INDEX(数据录入!$I$5:$I$4999,$S90)&"",INDEX(数据录入!$J$5:$J$4999,$S90)&"")) | E90: =IF($S90="","",INDEX(数据录入!$E$5:$E$4999,$S90)&"") | F90: =IF($S90="","",N(INDEX(数据录入!$F$5:$F$4999,$S90))) | G90: =IF($S90="","",N(INDEX(数据录入!$G$5:$G$4999,$S90))) | H90: =IF($S90="","",$G$2+SUM($F$8:$F90)-SUM($G$8:$G90)) | J90: =IF($K90="","",83) | K90: =IFERROR(INDEX($U$8:$U$107,MATCH(83,$W$8:$W$107,0)),"") | L90: =IF($K90="","",(SUMIFS(数据录入!$F$5:$F$4999,$Q$5:$Q$4999,1,数据录入!$B$5:$B$4999,"<"&$B$2,数据录入!$I$5:$I$4999,$K90)+SUMIFS(数据录入!$F$5:$F$4999,$Q$5:$Q$4999,1,数据录入!$B$5:$B$4999,"<"&$B$2,数据录入!$J$5:$J$4999,$K90))-(SUMIFS(数据录入!$G$5:$G$4999,$Q$5:$Q$4999,1,数据录入!$B$5:$B$4999,"<"&$B$2,数据录入!$I$5:$I$4999,$K90)+SUMIFS(数据录入!$G$5:$G$4999,$Q$5:$Q$4999,1,数据录入!$B$5:$B$4999,"<"&$B$2,数据录入!$J$5:$J$4999,$K90))) | M90: =IF($K90="","",SUMIFS(数据录入!$F$5:$F$4999,$Q$5:$Q$4999,1,数据录入!$B$5:$B$4999,">="&$B$2,数据录入!$B$5:$B$4999,"<="&$D$2,数据录入!$I$5:$I$4999,$K90)+SUMIFS(数据录入!$F$5:$F$4999,$Q$5:$Q$4999,1,数据录入!$B$5:$B$4999,">="&$B$2,数据录入!$B$5:$B$4999,"<="&$D$2,数据录入!$J$5:$J$4999,$K90)) | N90: =IF($K90="","",SUMIFS(数据录入!$G$5:$G$4999,$Q$5:$Q$4999,1,数据录入!$B$5:$B$4999,">="&$B$2,数据录入!$B$5:$B$4999,"<="&$D$2,数据录入!$I$5:$I$4999,$K90)+SUMIFS(数据录入!$G$5:$G$4999,$Q$5:$Q$4999,1,数据录入!$B$5:$B$4999,">="&$B$2,数据录入!$B$5:$B$4999,"<="&$D$2,数据录入!$J$5:$J$4999,$K90)) | O90: =IF($K90="","",L90+M90-N90) | Q90: =IF(数据录入!$B90="",0,IF(OR(数据录入!$D90="投标保证金",数据录入!$D90="合同履约保证金",ISNUMBER(FIND("保证金",数据录入!$E90))),1,0)) | R90: =IF(AND($Q90=1,数据录入!$B90>=$B$2,数据录入!$B90<=$D$2),N(R89)+1,N(R89)) | S90: =IFERROR(MATCH(83,$R$5:$R$4999,0),"") | U90: =IFERROR(IF(83<=50,INDEX(基础资料!$E$2:$E$51,83)&"",INDEX(基础资料!$G$2:$G$51,83-50)&""),"") | V90: =IF($U90="",0,IF(AND(83>50,COUNTIF(基础资料!$E$2:$E$51,$U90)>0),0,1)) | W90: =IF($V90=1,N(W89)+1,N(W89))
A91: =IF($S91="","",INDEX(数据录入!$B$5:$B$4999,$S91)) | B91: =IF($S91="","",INDEX(数据录入!$C$5:$C$4999,$S91)&"") | C91: =IF($S91="","",IF(N($F91)>0,"收款",IF(N($G91)>0,"付款",""))) | D91: =IF($S91="","",IF((INDEX(数据录入!$I$5:$I$4999,$S91)&"")<>"",INDEX(数据录入!$I$5:$I$4999,$S91)&"",INDEX(数据录入!$J$5:$J$4999,$S91)&"")) | E91: =IF($S91="","",INDEX(数据录入!$E$5:$E$4999,$S91)&"") | F91: =IF($S91="","",N(INDEX(数据录入!$F$5:$F$4999,$S91))) | G91: =IF($S91="","",N(INDEX(数据录入!$G$5:$G$4999,$S91))) | H91: =IF($S91="","",$G$2+SUM($F$8:$F91)-SUM($G$8:$G91)) | J91: =IF($K91="","",84) | K91: =IFERROR(INDEX($U$8:$U$107,MATCH(84,$W$8:$W$107,0)),"") | L91: =IF($K91="","",(SUMIFS(数据录入!$F$5:$F$4999,$Q$5:$Q$4999,1,数据录入!$B$5:$B$4999,"<"&$B$2,数据录入!$I$5:$I$4999,$K91)+SUMIFS(数据录入!$F$5:$F$4999,$Q$5:$Q$4999,1,数据录入!$B$5:$B$4999,"<"&$B$2,数据录入!$J$5:$J$4999,$K91))-(SUMIFS(数据录入!$G$5:$G$4999,$Q$5:$Q$4999,1,数据录入!$B$5:$B$4999,"<"&$B$2,数据录入!$I$5:$I$4999,$K91)+SUMIFS(数据录入!$G$5:$G$4999,$Q$5:$Q$4999,1,数据录入!$B$5:$B$4999,"<"&$B$2,数据录入!$J$5:$J$4999,$K91))) | M91: =IF($K91="","",SUMIFS(数据录入!$F$5:$F$4999,$Q$5:$Q$4999,1,数据录入!$B$5:$B$4999,">="&$B$2,数据录入!$B$5:$B$4999,"<="&$D$2,数据录入!$I$5:$I$4999,$K91)+SUMIFS(数据录入!$F$5:$F$4999,$Q$5:$Q$4999,1,数据录入!$B$5:$B$4999,">="&$B$2,数据录入!$B$5:$B$4999,"<="&$D$2,数据录入!$J$5:$J$4999,$K91)) | N91: =IF($K91="","",SUMIFS(数据录入!$G$5:$G$4999,$Q$5:$Q$4999,1,数据录入!$B$5:$B$4999,">="&$B$2,数据录入!$B$5:$B$4999,"<="&$D$2,数据录入!$I$5:$I$4999,$K91)+SUMIFS(数据录入!$G$5:$G$4999,$Q$5:$Q$4999,1,数据录入!$B$5:$B$4999,">="&$B$2,数据录入!$B$5:$B$4999,"<="&$D$2,数据录入!$J$5:$J$4999,$K91)) | O91: =IF($K91="","",L91+M91-N91) | Q91: =IF(数据录入!$B91="",0,IF(OR(数据录入!$D91="投标保证金",数据录入!$D91="合同履约保证金",ISNUMBER(FIND("保证金",数据录入!$E91))),1,0)) | R91: =IF(AND($Q91=1,数据录入!$B91>=$B$2,数据录入!$B91<=$D$2),N(R90)+1,N(R90)) | S91: =IFERROR(MATCH(84,$R$5:$R$4999,0),"") | U91: =IFERROR(IF(84<=50,INDEX(基础资料!$E$2:$E$51,84)&"",INDEX(基础资料!$G$2:$G$51,84-50)&""),"") | V91: =IF($U91="",0,IF(AND(84>50,COUNTIF(基础资料!$E$2:$E$51,$U91)>0),0,1)) | W91: =IF($V91=1,N(W90)+1,N(W90))
A92: =IF($S92="","",INDEX(数据录入!$B$5:$B$4999,$S92)) | B92: =IF($S92="","",INDEX(数据录入!$C$5:$C$4999,$S92)&"") | C92: =IF($S92="","",IF(N($F92)>0,"收款",IF(N($G92)>0,"付款",""))) | D92: =IF($S92="","",IF((INDEX(数据录入!$I$5:$I$4999,$S92)&"")<>"",INDEX(数据录入!$I$5:$I$4999,$S92)&"",INDEX(数据录入!$J$5:$J$4999,$S92)&"")) | E92: =IF($S92="","",INDEX(数据录入!$E$5:$E$4999,$S92)&"") | F92: =IF($S92="","",N(INDEX(数据录入!$F$5:$F$4999,$S92))) | G92: =IF($S92="","",N(INDEX(数据录入!$G$5:$G$4999,$S92))) | H92: =IF($S92="","",$G$2+SUM($F$8:$F92)-SUM($G$8:$G92)) | J92: =IF($K92="","",85) | K92: =IFERROR(INDEX($U$8:$U$107,MATCH(85,$W$8:$W$107,0)),"") | L92: =IF($K92="","",(SUMIFS(数据录入!$F$5:$F$4999,$Q$5:$Q$4999,1,数据录入!$B$5:$B$4999,"<"&$B$2,数据录入!$I$5:$I$4999,$K92)+SUMIFS(数据录入!$F$5:$F$4999,$Q$5:$Q$4999,1,数据录入!$B$5:$B$4999,"<"&$B$2,数据录入!$J$5:$J$4999,$K92))-(SUMIFS(数据录入!$G$5:$G$4999,$Q$5:$Q$4999,1,数据录入!$B$5:$B$4999,"<"&$B$2,数据录入!$I$5:$I$4999,$K92)+SUMIFS(数据录入!$G$5:$G$4999,$Q$5:$Q$4999,1,数据录入!$B$5:$B$4999,"<"&$B$2,数据录入!$J$5:$J$4999,$K92))) | M92: =IF($K92="","",SUMIFS(数据录入!$F$5:$F$4999,$Q$5:$Q$4999,1,数据录入!$B$5:$B$4999,">="&$B$2,数据录入!$B$5:$B$4999,"<="&$D$2,数据录入!$I$5:$I$4999,$K92)+SUMIFS(数据录入!$F$5:$F$4999,$Q$5:$Q$4999,1,数据录入!$B$5:$B$4999,">="&$B$2,数据录入!$B$5:$B$4999,"<="&$D$2,数据录入!$J$5:$J$4999,$K92)) | N92: =IF($K92="","",SUMIFS(数据录入!$G$5:$G$4999,$Q$5:$Q$4999,1,数据录入!$B$5:$B$4999,">="&$B$2,数据录入!$B$5:$B$4999,"<="&$D$2,数据录入!$I$5:$I$4999,$K92)+SUMIFS(数据录入!$G$5:$G$4999,$Q$5:$Q$4999,1,数据录入!$B$5:$B$4999,">="&$B$2,数据录入!$B$5:$B$4999,"<="&$D$2,数据录入!$J$5:$J$4999,$K92)) | O92: =IF($K92="","",L92+M92-N92) | Q92: =IF(数据录入!$B92="",0,IF(OR(数据录入!$D92="投标保证金",数据录入!$D92="合同履约保证金",ISNUMBER(FIND("保证金",数据录入!$E92))),1,0)) | R92: =IF(AND($Q92=1,数据录入!$B92>=$B$2,数据录入!$B92<=$D$2),N(R91)+1,N(R91)) | S92: =IFERROR(MATCH(85,$R$5:$R$4999,0),"") | U92: =IFERROR(IF(85<=50,INDEX(基础资料!$E$2:$E$51,85)&"",INDEX(基础资料!$G$2:$G$51,85-50)&""),"") | V92: =IF($U92="",0,IF(AND(85>50,COUNTIF(基础资料!$E$2:$E$51,$U92)>0),0,1)) | W92: =IF($V92=1,N(W91)+1,N(W91))
