Workbook

Sheet 使用说明
A1: 资金流水 + 成本核算 + 发票登记 一体化台账
A2: 适用：5~6家公司、16个银行账户、项目制经营；小规模与一般纳税人并存 ｜ 收入以开票金额为准
A4: 一、这套表解决什么问题
A5: 原来的做法是：每个账户一张表 → 再手工抄一遍收入明细 → 再手工抄一遍支出明细 → 再汇总。一笔流水要抄三遍，月底还要对不平。
A6: 现在的做法是：所有公司、所有账户的流水，只在「资金流水」一张表里录一遍；收入另外在「开票登记」一张表里录一遍。其余全部报表自动生成。
A7: 新增的三块联动：① 开票登记（既是收入来源，也按发票号自动核销收款）；② 项目核算（按项目自动归集收入与成本）；③ 应收应付台账（处理月末跨期）。
A9: 二、收入口径：以开票为准（重点）
A10: 公司确认的收入 = 「开票登记」里当月开出的发票金额，不是银行到账金额。开了票就算收入，钱什么时候到是回款问题。
A11: 含税还是不含税：由「基础资料」AH4 那一格开关控制，默认「价税合计(含税)」。改这一格，月度汇报表、项目核算表、趋势表、图表全部跟着变。
A12: 为什么默认含税：贵司的成本和费用都是按含税实付金额记的，缴的增值税又已经单列在支出的「税费」里。收入也用含税口径，三者才闭合。
A13: 如果要切到不含税，记得同时把支出端也换成不含税（剥离进项税），否则一般纳税人的毛利会被低估约一个税点。
A14: 没有发票的收入怎么办：利息、理财收益、政府补助这类永远开不出票，不登「开票登记」，在「资金流水」按实收登记，收入类别选「利息收入/理财收入/政府补助」即可 —— 报表会自动把它们并进「损益口径收入」，并在明细里标出取数来源。
... A61: 不够用时，选中最后一行整行下拉复制即可延伸公式；报表里的引用范围如需扩大，用「查找替换」把 3004 改成新的行号。

Sheet 基础资料
A1: 基础资料 — 所有下拉选项的数据源（改这里，全表下拉自动跟着变）
A2: ⚠ 黄色底=必须按贵司实际情况核对/填写。新增公司、账户、项目、类别，直接往下面空行里加即可，报表会自动识别。
A3: 公司简称 | B3: 公司全称 | C3: 纳税人类型 | E3: 账户名称 | F3: 所属公司 | G3: 账户类型 | I3: 项目编号 | J3: 项目名称 | K3: 所属公司 | L3: 客户 | M3: 合同金额 | N3: 签约日期 | O3: 项目状态 | Q3: 收入类别 | R3: 收入大类 | T3: 成本类别 | V3: 费用类别 | W3: 费用大类 | Y3: 客户 | AA3: 供应商 | AC3: 发票类型 | AE3: 税率 | AG3: 全局参数 | AH3: 取值
A4: 双思威 | B4: 双思威（请补全称） | C4: 一般纳税人 | E4: 双思威基本户 | F4: 双思威 | G4: 基本户 | I4: P001 | J4: 昌吉市中小学数字化校园建设工程（昌吉市第十五小学教学仪器设备采购项目） | K4: 双思威 | L4: 中移系统集成有限公司 | M4: 7443095.2 | N4: 2021年9月30 | O4: 在建 | Q4: 项目收入 | R4: 经营收入 | T4: 项目-材料 | V4: 办公费 | W4: 管理费用 | Y4: 客户1 | AA4: 供应商1 | AC4: 增值税专用发票 | AE4: 0.13 | AG4: 收入口径 | AH4: 价税合计(含税)
A5: 晨拓 | B5: 晨拓（请补全称） | C5: 一般纳税人 | E5: 双思威农商行一般户 | F5: 双思威 | G5: 一般户 | I5: P002 | J5: 昌吉市中小学数字化校园建设工程（昌吉市第十八小学教学仪器设备采购项目） | K5: 双思威 | L5: 昌吉代建局 | M5: 7790000 | N5: 2021年9月30 | O5: 在建 | Q5: 劳务/服务收入 | R5: 经营收入 | T5: 项目-人工 | V5: 水费 | W5: 管理费用 | Y5: 客户2 | AA5: 供应商2 | AC5: 增值税普通发票 | AE5: 0.09 | AG5: 说明 | AH5: 收入按开票金额确认。这个开关决定全表“开票收入”取价税合计还是不含税金额——改这一格，月度汇报表、项目核算表、趋势表、图表全部跟着变。因为成本费用都是含税实付、且增值税已单列在支出里，默认用价税合计才闭合。
A6: 瑞盛天 | B6: 瑞盛天（请补全称） | C6: 一般纳税人 | E6: 晨拓农商行基本户 | F6: 晨拓 | G6: 基本户 | I6: P003 | K6: 双思威 | N6: 44995 | O6: 已完工待收款 | Q6: 理财收入 | R6: 非经营收入 | T6: 项目-机械设备 | V6: 电费 | W6: 管理费用 | Y6: 客户3 | AA6: 供应商3 | AC6: 电子发票(普通票) | AE6: 0.06
A7: 鑫海特 | B7: 鑫海特（请补全称） | C7: 一般纳税人 | E7: 元界极光中行基本户 | F7: 元界极光 | G7: 基本户 | J7: 李广新昌吉市第十六小学教学仪器设备采购 | K7: 双思威 | L7: 新疆新广立科技有限公司 | M7: 6210476.1 | N7: 2022年3月20 | O7: 已完工待收款 | Q7: 利息收入 | R7: 非经营收入 | T7: 项目-零星开支 | V7: 伙食费 | W7: 管理费用 | Y7: 客户4 | AA7: 供应商4 | AC7: 电子发票(专用票) | AE7: 0.05
A8: 中展 | B8: 中展（请补全称） | C8: 小规模纳税人 | E8: 元界极光农商行一般户 | F8: 元界极光 | G8: 一般户 | J8: 昌吉市第十八小学教学设备采购及安装设备购置项目（二次） | K8: 双思威 | L8: 昌吉市教育局 | M8: 3733820 | N8: 2022年10月20 | O8: 已完工待收款 | Q8: 政府补助 | R8: 非经营收入 | T8: 项目-运费 | V8: 租赁费 | W8: 管理费用 | Y8: 客户5 | AA8: 供应商5 | AC8: 收据/未开票 | AE8: 0.03
A9: 元界极光 | B9: 元界极光 | C9: 小规模纳税人 | E9: 瑞盛天中行基本户 | F9: 瑞盛天 | G9: 基本户 | J9: 新疆某单位教育教学设备（二标段）六中项目 | K9: 双思威 | L9: 中移系统集成有限公司 | M9: 6515900.9 | N9: 44995 | O9: 已完工待收款 | Q9: 其他收入 | R9: 非经营收入 | T9: 项目-分包/劳务 | V9: 差旅费 | W9: 管理费用 | Y9: 客户6 | AA9: 供应商6 | AE9: 0.01
A10: 元界启辰 | B10: 元界启辰 | C10: 小规模纳税人 | E10: 瑞盛天农商行一般户 | F10: 瑞盛天 | G10: 一般户 | J10: 第二师铁门关市武安街消防站改造项目 | K10: 双思威 | L10: 中国电信股份有限公司巴音郭楞蒙古自治州分公司 | M10: 737890 | N10: 2025.11.24 | O10: 已完工待收款 | Q10: 保证金退回 | R10: 往来及保证金 | T10: 项目-税款 | V10: 业务招待费 | W10: 管理费用 | Y10: 客户7 | AA10: 供应商7 | AE10: 0
A11: 锐思维度 | B11: 锐思维度 | C11: 小规模纳税人 | E11: 中展中行基本户 | F11: 中展 | G11: 基本户 | J11: 昌吉市中等职业学校教学设备采购项目(二标段) | K11: 双思威 | L11: 中移建设有限公司新疆分公司 | M11: 2913561.4 | N11: 2025.8.26 | Q11: 借款收回 | R11: 往来及保证金 | T11: 项目-其他直接成本 | V11: 车辆费用 | W11: 管理费用 | Y11: 客户8 | AA11: 供应商8
A12: 鸿禧 | B12: 鸿禧 | C12: 小规模纳税人 | E12: 中展农商行一般户 | F12: 中展 | G12: 一般户 | J12: 中电信数智科技有限公司昌吉分公司2025年某学校智慧教室建设项目 | K12: 双思威 | L12: 中电信数智科技有限公司昌吉分公司 | M12: 295570 | N12: 2025.12.25 | Q12: 股东投入 | R12: 往来及保证金 | T12: 费用摊销 | V12: 通讯费 | W12: 管理费用 | Y12: 客户9 | AA12: 供应商9
A13: 卓卓通 | B13: 卓卓通 | C13: 小规模纳税人 | E13: 中展准东项目 | F13: 中展 | G13: 一般户 | J13: 中国电信巴州分公司2025年某部幼儿园视频监控系统服务采购 | K13: 双思威 | L13: 中国电信股份有限公司巴音郭楞蒙古自治州分公司 | M13: 126140 | N13: 2025.4.21 | Q13: 内部调拨转入 | R13: 往来及保证金 | V13: 快递费 | W13: 管理费用 | Y13: 客户10 | AA13: 供应商10
A14: 财兴通 | B14: 财兴通 | C14: 小规模纳税人 | E14: 卓卓通农商行基本户 | F14: 卓卓通 | G14: 基本户 | J14: 昌吉市中等职业学校教学设备采购项目（一标段） | K14: 双思威 | L14: 北京竞业达数码科技股份有限公司 | M14: 3903000 | N14: 2025.8.15 | V14: 公证费 | W14: 管理费用 | Y14: 客户11 | AA14: 供应商11
E15: 财兴通农商行基本户 | F15: 财兴通 | G15: 基本户 | J15: 草湖标识标牌项目 | K15: 双思威 | L15: 收新疆博创未来信息工程技术有限公司货款 | M15: 1240000 | N15: 2025.12.20 | V15: 咨询审计费 | W15: 管理费用 | Y15: 客户12 | AA15: 供应商12
E16: 鑫海特工行基本户 | F16: 鑫海特 | G16: 基本户 | J16: 昌吉市第二十一小学教育教学设备采购项目（三标段） | K16: 双思威 | L16: 昌吉市教育局 | M16: 1302839.1 | N16: 2025.8.8 | V16: 软件服务费 | W16: 管理费用 | Y16: 客户13 | AA16: 供应商13
E17: 鸿禧农行基本户 | F17: 鸿禧 | G17: 基本户 | J17: 昌吉市第七小学润苗楼教室文化墙、图书角及会议室项目 | K17: 元界极光 | L17: 昌吉市第七小学 | M17: 162144.8 | N17: 46051 | O17: 已完工已收款 | V17: 保险费 | W17: 管理费用
E18: 元界启辰中行基本户 | F18: 元界启辰 | G18: 基本户 | J18: 昌吉市第十小学售后 | K18: 中展 | L18: 昌吉市第十小学 | M18: 2760 | N18: 2026年3月17 | O18: 已完工已收款 | V18: 物业费 | W18: 管理费用
E19: 锐思维度中行基本户 | F19: 锐思维度 | G19: 基本户 | J19: 昌吉市第三幼儿园（二十幼）厨房设备采购项目 | K19: 中展 | L19: 昌吉市第三幼儿园 | M19: 25000 | N19: 46135 | O19: 已完工已收款 | V19: 职工福利费 | W19: 管理费用
E20: 备用7 | J20: 昌吉市南安幼儿园设备采购项目 | K20: 中展 | L20: 昌吉市第五幼儿园 | M20: 100000 | N20: 46141 | O20: 已完工已收款 | V20: 其他管理费用 | W20: 管理费用
E21: 备用8 | J21: 昌吉市第十小学（昌吉市第十九小学创客项目） | K21: 锐思维度 | L21: 昌吉市第十小学 | M21: 201460 | N21: 46157 | O21: 已完工已收款 | V21: 工资 | W21: 人工社保
E22: 备用9 | J22: 昌吉市第二小学智慧安防系统改造 | K22: 锐思维度 | L22: 昌吉市第二小学 | M22: 233000 | N22: 46164 | O22: 已完工待收款 | V22: 奖金/提成 | W22: 人工社保
E23: 备用10 | J23: 昌吉市第十六小学校园监控设备采购项目 | K23: 锐思维度 | L23: 昌吉市十四小学 | M23: 115130 | N23: 46164 | O23: 已完工待收款 | V23: 养老保险 | W23: 人工社保
J24: 昌吉市第十六小学校园广播设备采购项目 | K24: 中展 | L24: 昌吉市十四小学 | M24: 108510 | N24: 46164 | O24: 已完工待收款 | V24: 医疗保险 | W24: 人工社保
J25: 昌吉市第一小学学生机房项目 | K25: 元界启辰 | L25: 昌吉市第一小学 | M25: 332654 | N25: 46164 | O25: 已完工待收款 | V25: 失业/工伤保险 | W25: 人工社保
J26: 昌吉市第十小学智慧教室项目 | K26: 元界启辰 | L26: 昌吉市第十小学 | M26: 301080 | N26: 2026年6月30 | O26: 已完工已收款 | V26: 住房公积金 | W26: 人工社保
J27: 昌吉市第三中学安检门 | K27: 中展 | L27: 昌吉市第三中学 | M27: 72000 | N27: 2026年6月15 | O27: 已完工已收款 | V27: 劳务费 | W27: 人工社保
J28: 昌吉市第七小学阶梯教室设备采购项目 | K28: 瑞盛天 | L28: 昌吉市教育局 | M28: 1159595 | N28: 2026年7月23 | O28: 未完工未收款 | V28: 增值税 | W28: 税费
J29: 昌吉市第八小学5G+课堂建设采购项目 | K29: 中展 | L29: 昌吉市第八小学 | M29: 508600 | N29: 2026年7月17 | O29: 未完工未收款 | V29: 附加税 | W29: 税费
J30: 2026年新疆信友能源投资有限公司网格优化服务项目 | K30: 双思威 | L30: 新疆信友能源投资有限公司 | M30: 332000 | N30: 46223 | V30: 印花税 | W30: 税费
J31: 昌吉市第十七小学配套附属设施采购项目（教育教学设备 | K31: 元界启辰 | L31: 昌吉市教育局 | M31: 2937098 | N31: 2026年8月5 | O31: 未完工未收款 | V31: 企业所得税 | W31: 税费
J32: 昌吉市第十二小学阶梯教室设备采购项目 | K32: 双思威 | L32: 昌吉市第十二小学 | M32: 953360 | N32: 2026年6月16 | O32: 未完工未收款 | V32: 个人所得税 | W32: 税费
J33: 十八小的厨房监控 | K33: 中展 | L33: 昌吉市第十四小学 | M33: 45000 | N33: 2026年4月28 | O33: 已完工已收款 | V33: 其他税费 | W33: 税费
J34: 昌吉市南安幼儿园设备采购项目 | K34: 中展 | L34: 昌吉市第五幼儿园 | M34: 27155 | N34: 46163 | O34: 已完工已收款 | V34: 银行手续费 | W34: 财务费用
J35: 关于麦盖提县教育局“阳光食堂”硬件采购项目 | K35: 元界启辰 | L35: 新疆嘉盛鸿泰商贸有限公司 | M35: 202000 | V35: 利息支出 | W35: 财务费用
J36: 新疆某单位教育教学设备（二标段）甄选项目-六中 | K36: 双思威 | L36: 中移系统集成有限公司履约保证金 | M36: 6515900.9 | N36: 2023.3.2 | V36: 汇兑损益 | W36: 财务费用
J37: 代建局昌吉市第十八小学教学仪器设备采购项目 | K37: 双思威 | L37: 昌吉市政府投资建设项目代建管理中心 | M37: 7790000 | N37: 2021.9.30 | V37: 投标保证金 | W37: 往来及保证金
J38: 昌吉市四所幼儿园设备采购项目（三标段） | K38: 双思威 | L38: 昌吉市教育局 | M38: 2343634 | N38: 2024.7.2 | V38: 履约保证金 | W38: 往来及保证金
J39: 昌吉市中小学数字化校园建设工程（昌吉市第十五小学教学仪器设备采购项目） | K39: 双思威 | L39: 中移系统集成有限公司 | M39: 7443095.2 | N39: 2021.9.30 | V39: 备用金借出 | W39: 往来及保证金
J40: 铁门关经济技术开发区化工园区周界防护项目 | K40: 双思威 | L40: 中电信数智科技有限公司巴音郭楞蒙古自治州分公司 | M40: 3230000 | N40: 2025.7.20 | V40: 股东分红/抽资 | W40: 往来及保证金
J41: 第四师第一中学高中地理实验室设施设备采购项目 | K41: 元界极光 | L41: 新疆生产建设兵团第四师第一中学 | M41: 396980 | N41: 2025.12.17 | V41: 内部调拨转出 | W41: 往来及保证金
J42: 二师公安库铁大道监控引电（中国电信巴州分公司2025年第二师GAJ视频监控平台、云集成服务项目） | K42: 双思威 | L42: 中国电信股份有限公司巴音郭楞蒙古自治州分公司 | M42: 70000 | N42: 2025.5.10
J43: 第二师铁门关市师政数据防火墙维保服务采购项目 | K43: 双思威
J44: 铁门关市民中心视频汇聚项目 | K44: 双思威
J45: 昌吉市四所幼儿园设备采购项目（三标段） | K45: 双思威 | L45: 昌吉市教育局 | M45: 2343634
J46: 乌鲁木齐市第115中学食堂自营场地改造项目 | K46: 双思威 | M46: 596172.56
J47: 217线阿勒泰至布尔津公路建设项目 | K47: 双思威 | L47: 新疆明鸿通信技术有限公司 | M47: 3361997.4
J48: 昌吉市第十九小学教学仪器设备采购项目 | K48: 双思威 | L48: 昌吉市教育局 | M48: 12700000
J49: 库尔勒经济技术开发区第三幼儿园办公家具采购项目 | K49: 双思威 | L49: 新疆新广立科技有限公司 | M49: 179350
J50: 玛纳斯县总医院人民医院院区监控设备整合项目（二次） | K50: 中展 | L50: 玛纳斯县人民医院 | M50: 66800 | N50: 2025.11.11
J51: 昌吉市第二十一小教育教学设备采购项目（一标段） | K51: 双思威 | L51: 中移建设有限公司新疆分公司 | M51: 1302839.1 | N51: 2025.8.8
J52: 库尔勒市第九中学学生计算机采购项目 | K52: 双思威 | L52: 库尔勒市第九中学 | M52: 560000 | N52: 2025.6.10
J53: 第二师民兵训练基地综合指挥系统平台云集成服务项目（陪标中标 | K53: 双思威 | L53: 中国电信股份有限公司巴音郭楞蒙古自治州分公司 | M53: 240000 | N53: 2026.2.2
J54: 铁门关职业技术学院监控维修 | K54: 双思威 | L54: 中国电信股份有限公司和静分公司 | M54: 32900 | N54: 2025.12.3
J55: 御丰纺织厂无线覆盖项目 | K55: 双思威 | L55: 中国电信股份有限公司和静分公司 | M55: 16000 | N55: 2025.12.3
J56: 铁门关市乐美酒店监控项目 | K56: 双思威 | L56: 中国电信股份有限公司和静分公司 | M56: 18800 | N56: 2025.12.3
J57: 昌吉健康云120调度指挥中心项目 | K57: 双思威 | L57: 中国移动通信集团新疆有限公司昌吉州分公司 | M57: 1616642 | N57: 2022.3.14
J58: 库尔勒九中无线网络覆盖项目 | K58: 双思威 | L58: 中国电信股份有限公司和静分公司 | M58: 18000 | N58: 2025.8.10
J59: 第二师铁门关市信息技术服务中心机房设备搬迁服务项目 | K59: 双思威 | L59: 新疆生产建设兵团第二师铁门关市信息技术服务中心 | M59: 98000 | N59: 2025.12.10
J60: 社管局准东学校学术报告厅、会议室音频系统建设项目设备采购项目 | K60: 瑞盛天 | L60: 新疆八达科技发展有限公司 | M60: 345396 | N60: 2025.11.20
J61: 昌吉市第二十一小学建设项目-教育教学设备采购项目 | K61: 瑞盛天 | L61: 昌吉市教育局 | M61: 1185150 | N61: 2025.10.11
J62: 昌吉市第八小学黑板维护项目
J63: 乌鲁木齐市第122小学2025年采购高清扫描仪及软件 | K63: 中展 | L63: 乌鲁木齐市第122小学 | M63: 67800 | N63: 2025.4.25
J64: 乌鲁木齐第八十五小学教研平台采购项目 | K64: 中展 | L64: 乌鲁木齐市第八十五小学 | M64: 30000 | N64: 2025.9.3
J65: 昌吉市第十小学计算机教室设备采购项目 | K65: 鸿禧 | L65: 昌吉市第十小学 | M65: 79545 | N65: 2025.6.30
J66: 昌吉市第十小学计算机教室装修项目 | K66: 鸿禧 | L66: 昌吉市第十小学 | M66: 61675 | N66: 2025.6.30
J67: 中电信数智科技有限公司昌吉分公司2025年某学校智慧教室建设项目 | K67: 双思威 | L67: 中电信数智科技有限公司昌吉分公司 | M67: 1245580 | N67: 2025.8.10
J68: 中国电信巴州分公司2024年第二师铁门关市29团养殖基地监控部署及视频云存储项目 ]设备及相关服务采购合 | K68: 双思威 | L68: 中国电信股份有限公司巴音郭楞蒙古自治州分公司 | M68: 940710 | N68: 2025.1.21
J69: 二师市民中心迎宾机器人（中国电信巴州分公司2025年第二师铁门关市公安局视频监控链路的设备采购项目） | K69: 双思威 | L69: 中国电信股份有限公司巴音郭楞蒙古自治州分公司 | M69: 273460 | N69: 2025.6.10
J70: 关于社管局准东学校图书馆建设项） | K70: 双思威 | L70: 新疆准东经济技术开发区管理委员会 | M70: 5139158 | N70: 2025.12.12
J71: 克孜勒苏柯尔克孜自治州教育局项目 | K71: 中展 | L71: 克孜勒苏柯尔克孜自治州教育局 | M71: 1225 | N71: 2026.1.3
J72: 昌吉市第十五小学办公信息化设备项目 | K72: 双思威 | L72: 昌吉市教育局 | M72: 1865627 | N72: 2021.11.3
J73: 昌吉市第十小学台式电脑采购项目
J74: 昌吉市第二小学教学设备采购项目
J75: 昌吉市五中智慧黑板项目
J76: 社管局准东学校三期实验楼设施设备配置项目（二次） | K76: 双思威 | M76: 5139158 | N76: 2025.11.12
J77: 库尔楚园艺场中学机房采购 | K77: 中展 | L77: 库尔勒市库尔楚园艺场中学 | M77: 272044.02 | N77: 2025.4.12
J78: 昌吉市第十四小学项目新项目没有项目名称
J79: 第二师医疗保障事业管理中心视频联网及会议终端采购项目
J80: 草湖镇海康产品项目
J81: 第二师医疗保障事业管理中心视频联网及会议终端采购项目
J82: 吉木萨尔县第七幼儿园网上超市项目
J83: 库尔楚计算机设备
J84: 昌吉市第十小学智慧黑板采购项目
J85: 昌吉第八小学展台电池采购
J86: 中国人民解放军陆军第九四七医院智慧门诊合作项目 | K86: 双思威 | L86: 中电信数智科技有限公司喀什分公司 | M86: 313020 | N86: 2024.11.12
J87: 第二师铁门关信息技术服务中心租赁云服务资源采购项目技术服务 | K87: 双思威 | L87: 中国电信股份有限公司巴音郭楞蒙古自治州分公司 | M87: 349800 | N87: 2025.8.12
J88: 巴州农二师29团综治中心监控项目采购
J89: 要退回叶总申请
J90: 昌吉市第一中学学校校园无线网络改造项目 | M90: 833000 | N90: 2025.12.10
J91: 2026年现代职业教育质量提升项目
J92: 兵团十一师第一中学危化品实验室装备项目
J93: 昌吉市第十九小学教学仪器设备采购项目 | K93: 双思威 | L93: 昌吉市教育局 | M93: 12706500 | N93: 2021.8.10

Sheet 开票登记
A1: 开票登记表 — 收入以开票为准；逐张登记 + 收款自动核销（小规模 / 一般纳税人分开统计）
A2: 合计→ | C2: =IF(基础资料!$AH$4="不含税金额","本表口径收入(不含税)","本表口径收入(含税)") -> 本表口径收入(含税) | F2: =IF(基础资料!$AH$4="不含税金额",$J$2,$M$2) -> 24007854 | J2: =SUBTOTAL(109,$J$5:$J$504) -> 21870817 | L2: =SUBTOTAL(109,$L$5:$L$504) -> 2137037.7 | M2: =SUBTOTAL(109,$M$5:$M$504) -> 24007854 | N2: =SUBTOTAL(109,$N$5:$N$504) -> #VALUE! | O2: =SUBTOTAL(109,$O$5:$O$504) -> 19010886 | P2: =SUBTOTAL(109,$P$5:$P$504) -> #VALUE!
A3: 登记规则：①每张发票一行——公司确认的“收入”就是这张表，不是银行到账。②I列“发票号码”是核销的钥匙：收到这张票的钱时，在「资金流水」Q列填同一个发票号码，N列自动算出已收款、P列自动算未收款、S列自动算账龄（超90天标红）。③多票合并收款、对不上票号的，直接在O列手工登记已收金额。④H列“收入类别”决定这笔收入进汇报表哪一行，一般选“项目收入”。⑤L列税额=不含税×税率自动算，与发票实际税额有出入可直接覆盖。⑥利息、理财、补助这类永远没有发票的收入，不登这张表，在「资金流水」按实收登记即可，报表会自动并进来。
A4: 序号 | B4: 开票日期 | C4: 开票公司 | D4: 纳税人类型 (自动) | E4: 发票类型 | F4: 购方名称 | G4: 项目名称 | H4: 收入类别 | I4: 发票号码 | J4: 不含税金额 | K4: 税率 | L4: 税额 | M4: 价税合计 | N4: 已收款 (按票号自动) | O4: 已收款 (手工登记) | P4: 未收款 | Q4: 收款状态 | R4: 开票归属月 | S4: 账龄(天) | T4: 备注
A5: =IF($B5="","",COUNTA($B$5:$B5)) -> 1 | B5: 45981 | C5: 双思威 | D5: =IFERROR(INDEX(基础资料!$C$4:$C$11,MATCH($C5,基础资料!$A$4:$A$11,0)),"") -> 一般纳税人 | E5: 增值税专用发票 | F5: 客户3 | G5: 2025年结转项目 | H5: 项目收入 | I5: FP2025110001 | J5: 265486.73 | K5: 0.13 | L5: =IF($J5="","",ROUND($J5*$K5,2)) -> 34513.27 | M5: =IF($J5="","",ROUND($J5+$L5,2)) -> 300000 | N5: =IF($I5="","",SUMIFS(资金流水!$K$5:$K$3032,资金流水!$Q$5:$Q$3015,$I5)) -> #VALUE! | P5: =IF($J5="","",ROUND($M5-IF($N5="",0,$N5)-IF($O5="",0,$O5),2)) -> #VALUE! | Q5: =IF($J5="","",IF($P5<=0.005,"已收齐",IF(IF($N5="",0,$N5)+IF($O5="",0,$O5)<=0,"未收款","部分收款"))) -> #VALUE! | R5: =IF($B5="","",--TEXT($B5,"yyyymm")) -> 202511 | S5: =IF(OR($B5="",$P5="",$P5<=0.005),"",TODAY()-$B5) -> #VALUE! | T5: ★示例发票，可整行删除
A6: =IF($B6="","",COUNTA($B$5:$B6)) -> 2 | B6: 46026 | C6: 双思威 | D6: =IFERROR(INDEX(基础资料!$C$4:$C$11,MATCH($C6,基础资料!$A$4:$A$11,0)),"") -> 一般纳税人 | E6: 增值税专用发票 | F6: 北京竞业达数码科技股份有限公司 | G6: 昌吉市中等职业学校教学设备采购项目（一标段） | H6: 项目收入 | I6: FP20260601 | J6: 2409203.5 | K6: 0.13 | L6: =IF($J6="","",ROUND($J6*$K6,2)) -> 313196.46 | M6: =IF($J6="","",ROUND($J6+$L6,2)) -> 2722400 | O6: 2722400 | P6: =IF($J6="","",ROUND($M6-IF($N6="",0,$N6)-IF($O6="",0,$O6),2)) -> 0 | Q6: =IF($J6="","",IF($P6<=0.005,"已收齐",IF(IF($N6="",0,$N6)+IF($O6="",0,$O6)<=0,"未收款","部分收款"))) -> 已收齐 | R6: =IF($B6="","",--TEXT($B6,"yyyymm")) -> 202601 | S6: =IF(OR($B6="",$P6="",$P6<=0.005),"",TODAY()-$B6) | T6: ★示例发票，可整行删除
A7: =IF($B7="","",COUNTA($B$5:$B7)) -> 3 | B7: 46026 | C7: 双思威 | D7: =IFERROR(INDEX(基础资料!$C$4:$C$11,MATCH($C7,基础资料!$A$4:$A$11,0)),"") -> 一般纳税人 | E7: 增值税专用发票 | F7: 北京竞业达数码科技股份有限公司 | G7: 昌吉市中等职业学校教学设备采购项目（一标段） | H7: 项目收入 | I7: FP20260602 | J7: 377358.49 | K7: 0.06 | L7: =IF($J7="","",ROUND($J7*$K7,2)) -> 22641.51 | M7: =IF($J7="","",ROUND($J7+$L7,2)) -> 400000 | N7: =IF($I7="","",SUMIFS(资金流水!$K$5:$K$3032,资金流水!$Q$5:$Q$3015,$I7)) -> #VALUE! | O7: 400000 | P7: =IF($J7="","",ROUND($M7-IF($N7="",0,$N7)-IF($O7="",0,$O7),2)) -> #VALUE! | Q7: =IF($J7="","",IF($P7<=0.005,"已收齐",IF(IF($N7="",0,$N7)+IF($O7="",0,$O7)<=0,"未收款","部分收款"))) -> #VALUE! | R7: =IF($B7="","",--TEXT($B7,"yyyymm")) -> 202601 | S7: =IF(OR($B7="",$P7="",$P7<=0.005),"",TODAY()-$B7) -> #VALUE! | T7: ★示例发票，可整行删除
A8: =IF($B8="","",COUNTA($B$5:$B8)) -> 4 | B8: 46031 | C8: 双思威 | D8: =IFERROR(INDEX(基础资料!$C$4:$C$11,MATCH($C8,基础资料!$A$4:$A$11,0)),"") -> 一般纳税人 | E8: 增值税专用发票 | F8: 中电信数智科技有限公司昌吉分公司 | G8: 第二师铁门关市武安街消防站改造项目 | H8: 项目收入 | I8: FP20260602 | J8: 253743.29 | K8: 0.13 | L8: =IF($J8="","",ROUND($J8*$K8,2)) -> 32986.63 | M8: =IF($J8="","",ROUND($J8+$L8,2)) -> 286729.92 | N8: =IF($I8="","",SUMIFS(资金流水!$K$5:$K$3032,资金流水!$Q$5:$Q$3015,$I8)) -> #VALUE! | O8: 286729.92 | P8: =IF($J8="","",ROUND($M8-IF($N8="",0,$N8)-IF($O8="",0,$O8),2)) -> #VALUE! | Q8: =IF($J8="","",IF($P8<=0.005,"已收齐",IF(IF($N8="",0,$N8)+IF($O8="",0,$O8)<=0,"未收款","部分收款"))) -> #VALUE! | R8: =IF($B8="","",--TEXT($B8,"yyyymm")) -> 202601 | S8: =IF(OR($B8="",$P8="",$P8<=0.005),"",TODAY()-$B8) -> #VALUE!
A9: =IF($B9="","",COUNTA($B$5:$B9)) -> 5 | B9: 46036 | C9: 双思威 | D9: =IFERROR(INDEX(基础资料!$C$4:$C$11,MATCH($C9,基础资料!$A$4:$A$11,0)),"") -> 一般纳税人 | E9: 增值税专用发票 | F9: 中国电信股份有限公司和硕分公司 | G9: 中电信数智科技有限公司昌吉分公司2025年某学校智慧教室建设项目 | J9: 223071.7 | K9: 0.06 | L9: =IF($J9="","",ROUND($J9*$K9,2)) -> 13384.3 | M9: =IF($J9="","",ROUND($J9+$L9,2)) -> 236456 | N9: =IF($I9="","",SUMIFS(资金流水!$K$5:$K$3032,资金流水!$Q$5:$Q$3015,$I9)) | O9: 236456 | P9: =IF($J9="","",ROUND($M9-IF($N9="",0,$N9)-IF($O9="",0,$O9),2)) -> 0 | Q9: =IF($J9="","",IF($P9<=0.005,"已收齐",IF(IF($N9="",0,$N9)+IF($O9="",0,$O9)<=0,"未收款","部分收款"))) -> 已收齐 | R9: =IF($B9="","",--TEXT($B9,"yyyymm")) -> 202601 | S9: =IF(OR($B9="",$P9="",$P9<=0.005),"",TODAY()-$B9)
A10: =IF($B10="","",COUNTA($B$5:$B10)) -> 6 | B10: 46036 | C10: 双思威 | D10: =IFERROR(INDEX(基础资料!$C$4:$C$11,MATCH($C10,基础资料!$A$4:$A$11,0)),"") -> 一般纳税人 | E10: 增值税专用发票 | F10: 中国电信股份有限公司和硕分公司 | G10: 铁门关市乐美酒店监控项目 | J10: 17735.85 | K10: 0.06 | L10: =IF($J10="","",ROUND($J10*$K10,2)) -> 1064.15 | M10: =IF($J10="","",ROUND($J10+$L10,2)) -> 18800 | N10: =IF($I10="","",SUMIFS(资金流水!$K$5:$K$3032,资金流水!$Q$5:$Q$3015,$I10)) | O10: 18800 | P10: =IF($J10="","",ROUND($M10-IF($N10="",0,$N10)-IF($O10="",0,$O10),2)) -> 0 | Q10: =IF($J10="","",IF($P10<=0.005,"已收齐",IF(IF($N10="",0,$N10)+IF($O10="",0,$O10)<=0,"未收款","部分收款"))) -> 已收齐 | R10: =IF($B10="","",--TEXT($B10,"yyyymm")) -> 202601 | S10: =IF(OR($B10="",$P10="",$P10<=0.005),"",TODAY()-$B10)
A11: =IF($B11="","",COUNTA($B$5:$B11)) -> 7 | B11: 46036 | C11: 双思威 | D11: =IFERROR(INDEX(基础资料!$C$4:$C$11,MATCH($C11,基础资料!$A$4:$A$11,0)),"") -> 一般纳税人 | E11: 增值税专用发票 | F11: 中国电信股份有限公司和硕分公司 | J11: 15094.34 | K11: 0.06 | L11: =IF($J11="","",ROUND($J11*$K11,2)) -> 905.66 | M11: =IF($J11="","",ROUND($J11+$L11,2)) -> 16000 | N11: =IF($I11="","",SUMIFS(资金流水!$K$5:$K$3032,资金流水!$Q$5:$Q$3015,$I11)) | O11: 16000 | P11: =IF($J11="","",ROUND($M11-IF($N11="",0,$N11)-IF($O11="",0,$O11),2)) -> 0 | Q11: =IF($J11="","",IF($P11<=0.005,"已收齐",IF(IF($N11="",0,$N11)+IF($O11="",0,$O11)<=0,"未收款","部分收款"))) -> 已收齐 | R11: =IF($B11="","",--TEXT($B11,"yyyymm")) -> 202601 | S11: =IF(OR($B11="",$P11="",$P11<=0.005),"",TODAY()-$B11)
A12: =IF($B12="","",COUNTA($B$5:$B12)) -> 8 | B12: 46036 | C12: 双思威 | D12: =IFERROR(INDEX(基础资料!$C$4:$C$11,MATCH($C12,基础资料!$A$4:$A$11,0)),"") -> 一般纳税人 | E12: 增值税专用发票 | F12: 中电信数智科技有限公司昌吉分公司 | G12: 铁门关职业技术学院监控维修 | J12: 31037.74 | K12: 0.06 | L12: =IF($J12="","",ROUND($J12*$K12,2)) -> 1862.26 | M12: =IF($J12="","",ROUND($J12+$L12,2)) -> 32900 | N12: =IF($I12="","",SUMIFS(资金流水!$K$5:$K$3032,资金流水!$Q$5:$Q$3015,$I12)) | O12: 32900 | P12: =IF($J12="","",ROUND($M12-IF($N12="",0,$N12)-IF($O12="",0,$O12),2)) -> 0 | Q12: =IF($J12="","",IF($P12<=0.005,"已收齐",IF(IF($N12="",0,$N12)+IF($O12="",0,$O12)<=0,"未收款","部分收款"))) -> 已收齐 | R12: =IF($B12="","",--TEXT($B12,"yyyymm")) -> 202601 | S12: =IF(OR($B12="",$P12="",$P12<=0.005),"",TODAY()-$B12)
A13: =IF($B13="","",COUNTA($B$5:$B13)) -> 9 | B13: 46037 | C13: 双思威 | D13: =IFERROR(INDEX(基础资料!$C$4:$C$11,MATCH($C13,基础资料!$A$4:$A$11,0)),"") -> 一般纳税人 | E13: 增值税专用发票 | F13: 中国电信股份有限公司巴音郭楞蒙古自治州分公司 | G13: 中电信数智科技有限公司昌吉分公司2025年某学校智慧教室建设项目 | J13: 55767.92 | K13: 0.06 | L13: =IF($J13="","",ROUND($J13*$K13,2)) -> 3346.08 | M13: =IF($J13="","",ROUND($J13+$L13,2)) -> 59114 | N13: =IF($I13="","",SUMIFS(资金流水!$K$5:$K$3032,资金流水!$Q$5:$Q$3015,$I13)) | O13: 59114 | P13: =IF($J13="","",ROUND($M13-IF($N13="",0,$N13)-IF($O13="",0,$O13),2)) -> 0 | Q13: =IF($J13="","",IF($P13<=0.005,"已收齐",IF(IF($N13="",0,$N13)+IF($O13="",0,$O13)<=0,"未收款","部分收款"))) -> 已收齐 | R13: =IF($B13="","",--TEXT($B13,"yyyymm")) -> 202601 | S13: =IF(OR($B13="",$P13="",$P13<=0.005),"",TODAY()-$B13)
A14: =IF($B14="","",COUNTA($B$5:$B14)) -> 10 | B14: 46038 | C14: 双思威 | D14: =IFERROR(INDEX(基础资料!$C$4:$C$11,MATCH($C14,基础资料!$A$4:$A$11,0)),"") -> 一般纳税人 | E14: 增值税专用发票 | F14: 中国电信股份有限公司巴音郭楞蒙古自治州分公司 | G14: 中国电信巴州分公司2025年某部幼儿园视频监控系统服务采购 | J14: 72566.37 | K14: 0.13 | L14: =IF($J14="","",ROUND($J14*$K14,2)) -> 9433.63 | M14: =IF($J14="","",ROUND($J14+$L14,2)) -> 82000 | N14: =IF($I14="","",SUMIFS(资金流水!$K$5:$K$3032,资金流水!$Q$5:$Q$3015,$I14)) | O14: 82000 | P14: =IF($J14="","",ROUND($M14-IF($N14="",0,$N14)-IF($O14="",0,$O14),2)) -> 0 | Q14: =IF($J14="","",IF($P14<=0.005,"已收齐",IF(IF($N14="",0,$N14)+IF($O14="",0,$O14)<=0,"未收款","部分收款"))) -> 已收齐 | R14: =IF($B14="","",--TEXT($B14,"yyyymm")) -> 202601 | S14: =IF(OR($B14="",$P14="",$P14<=0.005),"",TODAY()-$B14)
A15: =IF($B15="","",COUNTA($B$5:$B15)) -> 11 | B15: 2026-2-2- | C15: 双思威 | D15: =IFERROR(INDEX(基础资料!$C$4:$C$11,MATCH($C15,基础资料!$A$4:$A$11,0)),"") -> 一般纳税人 | E15: 增值税专用发票 | F15: 中国电信股份有限公司巴音郭楞蒙古自治州分公司 | G15: 第二师民兵训练基地综合指挥系统平台云集成服务项目（陪标中标） | J15: 226415.09 | K15: 0.06 | L15: =IF($J15="","",ROUND($J15*$K15,2)) -> 13584.91 | M15: =IF($J15="","",ROUND($J15+$L15,2)) -> 240000 | N15: =IF($I15="","",SUMIFS(资金流水!$K$5:$K$3032,资金流水!$Q$5:$Q$3015,$I15)) | O15: 240000 | P15: =IF($J15="","",ROUND($M15-IF($N15="",0,$N15)-IF($O15="",0,$O15),2)) -> 0 | Q15: =IF($J15="","",IF($P15<=0.005,"已收齐",IF(IF($N15="",0,$N15)+IF($O15="",0,$O15)<=0,"未收款","部分收款"))) -> 已收齐 | R15: =IF($B15="","",--TEXT($B15,"yyyymm")) -> #VALUE! | S15: =IF(OR($B15="",$P15="",$P15<=0.005),"",TODAY()-$B15)
A16: =IF($B16="","",COUNTA($B$5:$B16)) -> 12 | B16: 46062 | C16: 双思威 | D16: =IFERROR(INDEX(基础资料!$C$4:$C$11,MATCH($C16,基础资料!$A$4:$A$11,0)),"") -> 一般纳税人 | E16: 增值税专用发票 | F16: 中国移动通信集团新疆有限公司昌吉州分公司 | G16: 昌吉健康云120调度指挥中心项目 | J16: 96117.43 | K16: 0.09 | L16: =IF($J16="","",ROUND($J16*$K16,2)) -> 8650.57 | M16: =IF($J16="","",ROUND($J16+$L16,2)) -> 104768 | N16: =IF($I16="","",SUMIFS(资金流水!$K$5:$K$3032,资金流水!$Q$5:$Q$3015,$I16)) | O16: 104768 | P16: =IF($J16="","",ROUND($M16-IF($N16="",0,$N16)-IF($O16="",0,$O16),2)) -> 0 | Q16: =IF($J16="","",IF($P16<=0.005,"已收齐",IF(IF($N16="",0,$N16)+IF($O16="",0,$O16)<=0,"未收款","部分收款"))) -> 已收齐 | R16: =IF($B16="","",--TEXT($B16,"yyyymm")) -> 202602 | S16: =IF(OR($B16="",$P16="",$P16<=0.005),"",TODAY()-$B16)
A17: =IF($B17="","",COUNTA($B$5:$B17)) -> 13 | B17: 46060 | C17: 双思威 | D17: =IFERROR(INDEX(基础资料!$C$4:$C$11,MATCH($C17,基础资料!$A$4:$A$11,0)),"") -> 一般纳税人 | E17: 增值税专用发票 | F17: 中国电信股份有限公司巴音郭楞蒙古自治州分公司 | G17: 中国电信巴州分公司2025年第二师GAJ视频监控平台、云集成服务项目设备及相关服务 | J17: 160000.09 | K17: 0.13 | L17: =IF($J17="","",ROUND($J17*$K17,2)) -> 20800.01 | M17: =IF($J17="","",ROUND($J17+$L17,2)) -> 180800.1 | N17: =IF($I17="","",SUMIFS(资金流水!$K$5:$K$3032,资金流水!$Q$5:$Q$3015,$I17)) | O17: 180800 | P17: =IF($J17="","",ROUND($M17-IF($N17="",0,$N17)-IF($O17="",0,$O17),2)) -> 0.1 | Q17: =IF($J17="","",IF($P17<=0.005,"已收齐",IF(IF($N17="",0,$N17)+IF($O17="",0,$O17)<=0,"未收款","部分收款"))) -> 部分收款 | R17: =IF($B17="","",--TEXT($B17,"yyyymm")) -> 202602 | S17: =IF(OR($B17="",$P17="",$P17<=0.005),"",TODAY()-$B17) -> 217
A18: =IF($B18="","",COUNTA($B$5:$B18)) -> 14 | B18: 46093 | C18: 双思威 | D18: =IFERROR(INDEX(基础资料!$C$4:$C$11,MATCH($C18,基础资料!$A$4:$A$11,0)),"") -> 一般纳税人 | E18: 增值税专用发票 | F18: 中国电信股份有限公司巴音郭楞蒙古自治州分公司 | G18: 中国电信巴州分公司2024年第二师铁门关市29团养殖基地监控部署及视频云存储项目 ]设备及相关服务采购合 | J18: 257180 | K18: 0.06 | L18: =IF($J18="","",ROUND($J18*$K18,2)) -> 15430.8 | M18: =IF($J18="","",ROUND($J18+$L18,2)) -> 272610.8 | N18: =IF($I18="","",SUMIFS(资金流水!$K$5:$K$3032,资金流水!$Q$5:$Q$3015,$I18)) | O18: 272610 | P18: =IF($J18="","",ROUND($M18-IF($N18="",0,$N18)-IF($O18="",0,$O18),2)) -> 0.8 | Q18: =IF($J18="","",IF($P18<=0.005,"已收齐",IF(IF($N18="",0,$N18)+IF($O18="",0,$O18)<=0,"未收款","部分收款"))) -> 部分收款 | R18: =IF($B18="","",--TEXT($B18,"yyyymm")) -> 202603 | S18: =IF(OR($B18="",$P18="",$P18<=0.005),"",TODAY()-$B18) -> 184
A19: =IF($B19="","",COUNTA($B$5:$B19)) -> 15 | B19: 46094 | C19: 双思威 | D19: =IFERROR(INDEX(基础资料!$C$4:$C$11,MATCH($C19,基础资料!$A$4:$A$11,0)),"") -> 一般纳税人 | E19: 增值税专用发票 | F19: 中国电信股份有限公司巴音郭楞蒙古自治州分公司 | G19: 中国电信巴州分公司2025年第二师GAJ视频监控平台、云集成服务项目设备及相关服务 | J19: 376000 | K19: 0.06 | L19: =IF($J19="","",ROUND($J19*$K19,2)) -> 22560 | M19: =IF($J19="","",ROUND($J19+$L19,2)) -> 398560 | N19: =IF($I19="","",SUMIFS(资金流水!$K$5:$K$3032,资金流水!$Q$5:$Q$3015,$I19)) | O19: 398560 | P19: =IF($J19="","",ROUND($M19-IF($N19="",0,$N19)-IF($O19="",0,$O19),2)) -> 0 | Q19: =IF($J19="","",IF($P19<=0.005,"已收齐",IF(IF($N19="",0,$N19)+IF($O19="",0,$O19)<=0,"未收款","部分收款"))) -> 已收齐 | R19: =IF($B19="","",--TEXT($B19,"yyyymm")) -> 202603 | S19: =IF(OR($B19="",$P19="",$P19<=0.005),"",TODAY()-$B19)
A20: =IF($B20="","",COUNTA($B$5:$B20)) -> 16 | B20: 46095 | C20: 双思威 | D20: =IFERROR(INDEX(基础资料!$C$4:$C$11,MATCH($C20,基础资料!$A$4:$A$11,0)),"") -> 一般纳税人 | E20: 增值税专用发票 | F20: 中电信数智科技有限公司昌吉分公司 | G20: 中电信数智科技有限公司昌吉分公司2025年某学校智慧教室建设项目 | J20: 168143.36 | K20: 0.13 | L20: =IF($J20="","",ROUND($J20*$K20,2)) -> 21858.64 | M20: =IF($J20="","",ROUND($J20+$L20,2)) -> 190002 | N20: =IF($I20="","",SUMIFS(资金流水!$K$5:$K$3032,资金流水!$Q$5:$Q$3015,$I20)) | O20: 190002 | P20: =IF($J20="","",ROUND($M20-IF($N20="",0,$N20)-IF($O20="",0,$O20),2)) -> 0 | Q20: =IF($J20="","",IF($P20<=0.005,"已收齐",IF(IF($N20="",0,$N20)+IF($O20="",0,$O20)<=0,"未收款","部分收款"))) -> 已收齐 | R20: =IF($B20="","",--TEXT($B20,"yyyymm")) -> 202603 | S20: =IF(OR($B20="",$P20="",$P20<=0.005),"",TODAY()-$B20)
A21: =IF($B21="","",COUNTA($B$5:$B21)) -> 17 | B21: 46098 | C21: 双思威 | D21: =IFERROR(INDEX(基础资料!$C$4:$C$11,MATCH($C21,基础资料!$A$4:$A$11,0)),"") -> 一般纳税人 | E21: 增值税专用发票 | F21: 中国电信股份有限公司巴音郭楞蒙古自治州分公司 | G21: 二师市民中心迎宾机器人（中国电信巴州分公司2025年第二师铁门关市公安局视频监控链路的设备采购项目） | J21: 242000 | K21: 0.13 | L21: =IF($J21="","",ROUND($J21*$K21,2)) -> 31460 | M21: =IF($J21="","",ROUND($J21+$L21,2)) -> 273460 | N21: =IF($I21="","",SUMIFS(资金流水!$K$5:$K$3032,资金流水!$Q$5:$Q$3015,$I21)) | O21: 273460 | P21: =IF($J21="","",ROUND($M21-IF($N21="",0,$N21)-IF($O21="",0,$O21),2)) -> 0 | Q21: =IF($J21="","",IF($P21<=0.005,"已收齐",IF(IF($N21="",0,$N21)+IF($O21="",0,$O21)<=0,"未收款","部分收款"))) -> 已收齐 | R21: =IF($B21="","",--TEXT($B21,"yyyymm")) -> 202603 | S21: =IF(OR($B21="",$P21="",$P21<=0.005),"",TODAY()-$B21)
A22: =IF($B22="","",COUNTA($B$5:$B22)) -> 18 | B22: 46092 | C22: 中展 | D22: =IFERROR(INDEX(基础资料!$C$4:$C$11,MATCH($C22,基础资料!$A$4:$A$11,0)),"") -> 小规模纳税人 | E22: 增值税普通发票 | F22: 库尔勒市库尔楚园艺场中学 | G22: 库尔楚计算机设备采购 | J22: 2913.84 | K22: 0.01 | L22: =IF($J22="","",ROUND($J22*$K22,2)) -> 29.14 | M22: =IF($J22="","",ROUND($J22+$L22,2)) -> 2942.98 | N22: =IF($I22="","",SUMIFS(资金流水!$K$5:$K$3032,资金流水!$Q$5:$Q$3015,$I22)) | O22: 2942.98 | P22: =IF($J22="","",ROUND($M22-IF($N22="",0,$N22)-IF($O22="",0,$O22),2)) -> 0 | Q22: =IF($J22="","",IF($P22<=0.005,"已收齐",IF(IF($N22="",0,$N22)+IF($O22="",0,$O22)<=0,"未收款","部分收款"))) -> 已收齐 | R22: =IF($B22="","",--TEXT($B22,"yyyymm")) -> 202603 | S22: =IF(OR($B22="",$P22="",$P22<=0.005),"",TODAY()-$B22)
A23: =IF($B23="","",COUNTA($B$5:$B23)) -> 19 | B23: 46092 | C23: 中展 | D23: =IFERROR(INDEX(基础资料!$C$4:$C$11,MATCH($C23,基础资料!$A$4:$A$11,0)),"") -> 小规模纳税人 | E23: 增值税普通发票 | F23: 库尔勒市库尔楚园艺场中学 | G23: 库尔楚计算机设备采购 | J23: 4963.37 | K23: 0.01 | L23: =IF($J23="","",ROUND($J23*$K23,2)) -> 49.63 | M23: =IF($J23="","",ROUND($J23+$L23,2)) -> 5013 | N23: =IF($I23="","",SUMIFS(资金流水!$K$5:$K$3032,资金流水!$Q$5:$Q$3015,$I23)) | O23: 5013 | P23: =IF($J23="","",ROUND($M23-IF($N23="",0,$N23)-IF($O23="",0,$O23),2)) -> 0 | Q23: =IF($J23="","",IF($P23<=0.005,"已收齐",IF(IF($N23="",0,$N23)+IF($O23="",0,$O23)<=0,"未收款","部分收款"))) -> 已收齐 | R23: =IF($B23="","",--TEXT($B23,"yyyymm")) -> 202603 | S23: =IF(OR($B23="",$P23="",$P23<=0.005),"",TODAY()-$B23)
A24: =IF($B24="","",COUNTA($B$5:$B24)) -> 20 | B24: 46098 | C24: 中展 | D24: =IFERROR(INDEX(基础资料!$C$4:$C$11,MATCH($C24,基础资料!$A$4:$A$11,0)),"") -> 小规模纳税人 | E24: 增值税普通发票 | F24: 昌吉市第十小学 | G24: 昌吉市第十小学智慧黑板 | J24: 42574.26 | K24: 0.01 | L24: =IF($J24="","",ROUND($J24*$K24,2)) -> 425.74 | M24: =IF($J24="","",ROUND($J24+$L24,2)) -> 43000 | N24: =IF($I24="","",SUMIFS(资金流水!$K$5:$K$3032,资金流水!$Q$5:$Q$3015,$I24)) | O24: 43000 | P24: =IF($J24="","",ROUND($M24-IF($N24="",0,$N24)-IF($O24="",0,$O24),2)) -> 0 | Q24: =IF($J24="","",IF($P24<=0.005,"已收齐",IF(IF($N24="",0,$N24)+IF($O24="",0,$O24)<=0,"未收款","部分收款"))) -> 已收齐 | R24: =IF($B24="","",--TEXT($B24,"yyyymm")) -> 202603 | S24: =IF(OR($B24="",$P24="",$P24<=0.005),"",TODAY()-$B24)
A25: =IF($B25="","",COUNTA($B$5:$B25)) -> 21 | B25: 46104 | C25: 中展 | D25: =IFERROR(INDEX(基础资料!$C$4:$C$11,MATCH($C25,基础资料!$A$4:$A$11,0)),"") -> 小规模纳税人 | E25: 增值税普通发票 | F25: 昌吉市第五中学 | G25: 昌吉市第五中学采购6台黑板 | J25: 127722.77 | K25: 0.01 | L25: =IF($J25="","",ROUND($J25*$K25,2)) -> 1277.23 | M25: =IF($J25="","",ROUND($J25+$L25,2)) -> 129000 | N25: =IF($I25="","",SUMIFS(资金流水!$K$5:$K$3032,资金流水!$Q$5:$Q$3015,$I25)) | O25: 129000 | P25: =IF($J25="","",ROUND($M25-IF($N25="",0,$N25)-IF($O25="",0,$O25),2)) -> 0 | Q25: =IF($J25="","",IF($P25<=0.005,"已收齐",IF(IF($N25="",0,$N25)+IF($O25="",0,$O25)<=0,"未收款","部分收款"))) -> 已收齐 | R25: =IF($B25="","",--TEXT($B25,"yyyymm")) -> 202603 | S25: =IF(OR($B25="",$P25="",$P25<=0.005),"",TODAY()-$B25)
A26: =IF($B26="","",COUNTA($B$5:$B26)) -> 22 | B26: 46108 | C26: 中展 | D26: =IFERROR(INDEX(基础资料!$C$4:$C$11,MATCH($C26,基础资料!$A$4:$A$11,0)),"") -> 小规模纳税人 | E26: 增值税普通发票 | F26: 昌吉市第十小学 | G26: 26年售后 | J26: 2732.67 | K26: 0.01 | L26: =IF($J26="","",ROUND($J26*$K26,2)) -> 27.33 | M26: =IF($J26="","",ROUND($J26+$L26,2)) -> 2760 | N26: =IF($I26="","",SUMIFS(资金流水!$K$5:$K$3032,资金流水!$Q$5:$Q$3015,$I26)) | O26: 2760 | P26: =IF($J26="","",ROUND($M26-IF($N26="",0,$N26)-IF($O26="",0,$O26),2)) -> 0 | Q26: =IF($J26="","",IF($P26<=0.005,"已收齐",IF(IF($N26="",0,$N26)+IF($O26="",0,$O26)<=0,"未收款","部分收款"))) -> 已收齐 | R26: =IF($B26="","",--TEXT($B26,"yyyymm")) -> 202603 | S26: =IF(OR($B26="",$P26="",$P26<=0.005),"",TODAY()-$B26)
A27: =IF($B27="","",COUNTA($B$5:$B27)) -> 23 | B27: 46121 | C27: 双思威 | D27: =IFERROR(INDEX(基础资料!$C$4:$C$11,MATCH($C27,基础资料!$A$4:$A$11,0)),"") -> 一般纳税人 | E27: 增值税专用发票 | F27: 新疆准东经济技术开发区管理委员会 | G27: 社管局准东学校三期实验楼设施设备配置项目（二次）追加 | J27: 406097.34 | K27: 0.13 | L27: =IF($J27="","",ROUND($J27*$K27,2)) -> 52792.65 | M27: =IF($J27="","",ROUND($J27+$L27,2)) -> 458889.99 | N27: =IF($I27="","",SUMIFS(资金流水!$K$5:$K$3032,资金流水!$Q$5:$Q$3015,$I27)) | O27: 458889.99 | P27: =IF($J27="","",ROUND($M27-IF($N27="",0,$N27)-IF($O27="",0,$O27),2)) -> 0 | Q27: =IF($J27="","",IF($P27<=0.005,"已收齐",IF(IF($N27="",0,$N27)+IF($O27="",0,$O27)<=0,"未收款","部分收款"))) -> 已收齐 | R27: =IF($B27="","",--TEXT($B27,"yyyymm")) -> 202604 | S27: =IF(OR($B27="",$P27="",$P27<=0.005),"",TODAY()-$B27)
... A29: =IF($B29="","",COUNTA($B$5:$B29)) -> 25 | B29: 46126 | C29: 双思威 | D29: =IFERROR(INDEX(基础资料!$C$4:$C$11,MATCH($C29,基础资料!$A$4:$A$11,0)),"") -> 一般纳税人 | E29: 增值税专用发票 | F29: 中国电信股份有限公司巴音郭楞蒙古自治州分公司 | G29: 第二师铁门关信息技术服务中心租赁云服务资源采购项目技术服务合同 | J29: 330000 | K29: 0.06 | L29: =IF($J29="","",ROUND($J29*$K29,2)) -> 19800 | M29: =IF($J29="","",ROUND($J29+$L29,2)) -> 349800 | N29: =IF($I29="","",SUMIFS(资金流水!$K$5:$K$3032,资金流水!$Q$5:$Q$3015,$I29)) | O29: 349800 | P29: =IF($J29="","",ROUND($M29-IF($N29="",0,$N29)-IF($O29="",0,$O29),2)) -> 0 | Q29: =IF($J29="","",IF($P29<=0.005,"已收齐",IF(IF($N29="",0,$N29)+IF($O29="",0,$O29)<=0,"未收款","部分收款"))) -> 已收齐 | R29: =IF($B29="","",--TEXT($B29,"yyyymm")) -> 202604 | S29: =IF(OR($B29="",$P29="",$P29<=0.005),"",TODAY()-$B29)
A30: =IF($B30="","",COUNTA($B$5:$B30)) -> 26 | B30: 46126 | C30: 双思威 | D30: =IFERROR(INDEX(基础资料!$C$4:$C$11,MATCH($C30,基础资料!$A$4:$A$11,0)),"") -> 一般纳税人 | E30: 增值税专用发票 | F30: 中国电信股份有限公司巴音郭楞蒙古自治州分公司 | G30: 中国电信股份有限公司巴州分公司2026年铁门关市民中心视频汇聚改造提升项目 | J30: 142000 | K30: 0.13 | L30: =IF($J30="","",ROUND($J30*$K30,2)) -> 18460 | M30: =IF($J30="","",ROUND($J30+$L30,2)) -> 160460 | N30: =IF($I30="","",SUMIFS(资金流水!$K$5:$K$3032,资金流水!$Q$5:$Q$3015,$I30)) | P30: =IF($J30="","",ROUND($M30-IF($N30="",0,$N30)-IF($O30="",0,$O30),2)) -> 160460 | Q30: =IF($J30="","",IF($P30<=0.005,"已收齐",IF(IF($N30="",0,$N30)+IF($O30="",0,$O30)<=0,"未收款","部分收款"))) -> 未收款 | R30: =IF($B30="","",--TEXT($B30,"yyyymm")) -> 202604 | S30: =IF(OR($B30="",$P30="",$P30<=0.005),"",TODAY()-$B30) -> 151
A31: =IF($B31="","",COUNTA($B$5:$B31)) -> 27 | B31: 46126 | C31: 双思威 | D31: =IFERROR(INDEX(基础资料!$C$4:$C$11,MATCH($C31,基础资料!$A$4:$A$11,0)),"") -> 一般纳税人 | E31: 增值税专用发票 | F31: 中国电信股份有限公司巴音郭楞蒙古自治州分公司 | G31: 中国电信股份有限公司巴州分公司2026年铁门关市民中心视频汇聚改造提升项目 | J31: 117831.13 | K31: 0.06 | L31: =IF($J31="","",ROUND($J31*$K31,2)) -> 7069.87 | M31: =IF($J31="","",ROUND($J31+$L31,2)) -> 124901 | N31: =IF($I31="","",SUMIFS(资金流水!$K$5:$K$3032,资金流水!$Q$5:$Q$3015,$I31)) | O31: 124901 | P31: =IF($J31="","",ROUND($M31-IF($N31="",0,$N31)-IF($O31="",0,$O31),2)) -> 0 | Q31: =IF($J31="","",IF($P31<=0.005,"已收齐",IF(IF($N31="",0,$N31)+IF($O31="",0,$O31)<=0,"未收款","部分收款"))) -> 已收齐 | R31: =IF($B31="","",--TEXT($B31,"yyyymm")) -> 202604 | S31: =IF(OR($B31="",$P31="",$P31<=0.005),"",TODAY()-$B31)
A32: =IF($B32="","",COUNTA($B$5:$B32)) -> 28 | B32: 46132 | C32: 双思威 | D32: =IFERROR(INDEX(基础资料!$C$4:$C$11,MATCH($C32,基础资料!$A$4:$A$11,0)),"") -> 一般纳税人 | E32: 增值税专用发票 | F32: 中电信数智科技有限公司巴音郭楞蒙 古自治州分公司 | G32: 中电信数智巴州分公司 2026 年铁门关经济技术开发区化工园区周界防护 | J32: 621592.92 | K32: 0.13 | L32: =IF($J32="","",ROUND($J32*$K32,2)) -> 80807.08 | M32: =IF($J32="","",ROUND($J32+$L32,2)) -> 702400 | N32: =IF($I32="","",SUMIFS(资金流水!$K$5:$K$3032,资金流水!$Q$5:$Q$3015,$I32)) | O32: 702400 | P32: =IF($J32="","",ROUND($M32-IF($N32="",0,$N32)-IF($O32="",0,$O32),2)) -> 0 | Q32: =IF($J32="","",IF($P32<=0.005,"已收齐",IF(IF($N32="",0,$N32)+IF($O32="",0,$O32)<=0,"未收款","部分收款"))) -> 已收齐 | R32: =IF($B32="","",--TEXT($B32,"yyyymm")) -> 202604 | S32: =IF(OR($B32="",$P32="",$P32<=0.005),"",TODAY()-$B32)
A33: =IF($B33="","",COUNTA($B$5:$B33)) -> 29 | B33: 46132 | C33: 双思威 | D33: =IFERROR(INDEX(基础资料!$C$4:$C$11,MATCH($C33,基础资料!$A$4:$A$11,0)),"") -> 一般纳税人 | E33: 增值税专用发票 | F33: 中电信数智科技有限公司巴音郭楞蒙 古自治州分公司 | G33: 项目采购项目]设备及相关服务采购合同 | J33: 245283.02 | K33: 0.06 | L33: =IF($J33="","",ROUND($J33*$K33,2)) -> 14716.98 | M33: =IF($J33="","",ROUND($J33+$L33,2)) -> 260000 | N33: =IF($I33="","",SUMIFS(资金流水!$K$5:$K$3032,资金流水!$Q$5:$Q$3015,$I33)) | O33: 260000 | P33: =IF($J33="","",ROUND($M33-IF($N33="",0,$N33)-IF($O33="",0,$O33),2)) -> 0 | Q33: =IF($J33="","",IF($P33<=0.005,"已收齐",IF(IF($N33="",0,$N33)+IF($O33="",0,$O33)<=0,"未收款","部分收款"))) -> 已收齐 | R33: =IF($B33="","",--TEXT($B33,"yyyymm")) -> 202604 | S33: =IF(OR($B33="",$P33="",$P33<=0.005),"",TODAY()-$B33)
A34: =IF($B34="","",COUNTA($B$5:$B34)) -> 30 | B34: 46134 | C34: 中展 | D34: =IFERROR(INDEX(基础资料!$C$4:$C$11,MATCH($C34,基础资料!$A$4:$A$11,0)),"") -> 小规模纳税人 | E34: 增值税普通发票 | F34: 玛纳斯县第一中学 | J34: 5445.54 | K34: 0.01 | L34: =IF($J34="","",ROUND($J34*$K34,2)) -> 54.46 | M34: =IF($J34="","",ROUND($J34+$L34,2)) -> 5500 | N34: =IF($I34="","",SUMIFS(资金流水!$K$5:$K$3032,资金流水!$Q$5:$Q$3015,$I34)) | O34: 5500 | P34: =IF($J34="","",ROUND($M34-IF($N34="",0,$N34)-IF($O34="",0,$O34),2)) -> 0 | Q34: =IF($J34="","",IF($P34<=0.005,"已收齐",IF(IF($N34="",0,$N34)+IF($O34="",0,$O34)<=0,"未收款","部分收款"))) -> 已收齐 | R34: =IF($B34="","",--TEXT($B34,"yyyymm")) -> 202604 | S34: =IF(OR($B34="",$P34="",$P34<=0.005),"",TODAY()-$B34)
A35: =IF($B35="","",COUNTA($B$5:$B35)) -> 31 | B35: 46134 | C35: 中展 | D35: =IFERROR(INDEX(基础资料!$C$4:$C$11,MATCH($C35,基础资料!$A$4:$A$11,0)),"") -> 小规模纳税人 | E35: 增值税普通发票 | F35: 玛纳斯县第一中学 | J35: 2277.23 | K35: 0.01 | L35: =IF($J35="","",ROUND($J35*$K35,2)) -> 22.77 | M35: =IF($J35="","",ROUND($J35+$L35,2)) -> 2300 | N35: =IF($I35="","",SUMIFS(资金流水!$K$5:$K$3032,资金流水!$Q$5:$Q$3015,$I35)) | O35: 2300 | P35: =IF($J35="","",ROUND($M35-IF($N35="",0,$N35)-IF($O35="",0,$O35),2)) -> 0 | Q35: =IF($J35="","",IF($P35<=0.005,"已收齐",IF(IF($N35="",0,$N35)+IF($O35="",0,$O35)<=0,"未收款","部分收款"))) -> 已收齐 | R35: =IF($B35="","",--TEXT($B35,"yyyymm")) -> 202604 | S35: =IF(OR($B35="",$P35="",$P35<=0.005),"",TODAY()-$B35)
A36: =IF($B36="","",COUNTA($B$5:$B36)) -> 32 | B36: 46134 | C36: 中展 | D36: =IFERROR(INDEX(基础资料!$C$4:$C$11,MATCH($C36,基础资料!$A$4:$A$11,0)),"") -> 小规模纳税人 | E36: 增值税普通发票 | F36: 昌吉市第十四小学 | G36: 昌吉市第十四小学项目新项目没有项目名称 | J36: 25346.53 | K36: 0.01 | L36: =IF($J36="","",ROUND($J36*$K36,2)) -> 253.47 | M36: =IF($J36="","",ROUND($J36+$L36,2)) -> 25600 | N36: =IF($I36="","",SUMIFS(资金流水!$K$5:$K$3032,资金流水!$Q$5:$Q$3015,$I36)) | O36: 25600 | P36: =IF($J36="","",ROUND($M36-IF($N36="",0,$N36)-IF($O36="",0,$O36),2)) -> 0 | Q36: =IF($J36="","",IF($P36<=0.005,"已收齐",IF(IF($N36="",0,$N36)+IF($O36="",0,$O36)<=0,"未收款","部分收款"))) -> 已收齐 | R36: =IF($B36="","",--TEXT($B36,"yyyymm")) -> 202604 | S36: =IF(OR($B36="",$P36="",$P36<=0.005),"",TODAY()-$B36)
A37: =IF($B37="","",COUNTA($B$5:$B37)) -> 33 | B37: 46140 | C37: 中展 | D37: =IFERROR(INDEX(基础资料!$C$4:$C$11,MATCH($C37,基础资料!$A$4:$A$11,0)),"") -> 小规模纳税人 | E37: 增值税普通发票 | F37: 昌吉市第三幼儿园（陈垒） | G37: 昌吉市第三幼儿园（二十幼）厨房设备采购项目 | J37: 24752.48 | K37: 0.01 | L37: =IF($J37="","",ROUND($J37*$K37,2)) -> 247.52 | M37: =IF($J37="","",ROUND($J37+$L37,2)) -> 25000 | N37: =IF($I37="","",SUMIFS(资金流水!$K$5:$K$3032,资金流水!$Q$5:$Q$3015,$I37)) | O37: 25000 | P37: =IF($J37="","",ROUND($M37-IF($N37="",0,$N37)-IF($O37="",0,$O37),2)) -> 0 | Q37: =IF($J37="","",IF($P37<=0.005,"已收齐",IF(IF($N37="",0,$N37)+IF($O37="",0,$O37)<=0,"未收款","部分收款"))) -> 已收齐 | R37: =IF($B37="","",--TEXT($B37,"yyyymm")) -> 202604 | S37: =IF(OR($B37="",$P37="",$P37<=0.005),"",TODAY()-$B37)
A38: =IF($B38="","",COUNTA($B$5:$B38)) -> 34 | B38: 46141 | C38: 中展 | D38: =IFERROR(INDEX(基础资料!$C$4:$C$11,MATCH($C38,基础资料!$A$4:$A$11,0)),"") -> 小规模纳税人 | E38: 增值税普通发票 | F38: 昌吉市第五幼儿园 | G38: 昌吉市南安幼儿园设备采购项目 | J38: 19801.98 | K38: 0.01 | L38: =IF($J38="","",ROUND($J38*$K38,2)) -> 198.02 | M38: =IF($J38="","",ROUND($J38+$L38,2)) -> 20000 | N38: =IF($I38="","",SUMIFS(资金流水!$K$5:$K$3032,资金流水!$Q$5:$Q$3015,$I38)) | O38: 20000 | P38: =IF($J38="","",ROUND($M38-IF($N38="",0,$N38)-IF($O38="",0,$O38),2)) -> 0 | Q38: =IF($J38="","",IF($P38<=0.005,"已收齐",IF(IF($N38="",0,$N38)+IF($O38="",0,$O38)<=0,"未收款","部分收款"))) -> 已收齐 | R38: =IF($B38="","",--TEXT($B38,"yyyymm")) -> 202604 | S38: =IF(OR($B38="",$P38="",$P38<=0.005),"",TODAY()-$B38)
A39: =IF($B39="","",COUNTA($B$5:$B39)) -> 35 | B39: 46150 | C39: 双思威 | D39: =IFERROR(INDEX(基础资料!$C$4:$C$11,MATCH($C39,基础资料!$A$4:$A$11,0)),"") -> 一般纳税人 | E39: 增值税专用发票 | F39: 昌吉市教育局 | G39: 昌吉市十七小学教学设备采购项目 | J39: 1135398.2 | K39: 0.13 | L39: =IF($J39="","",ROUND($J39*$K39,2)) -> 147601.77 | M39: =IF($J39="","",ROUND($J39+$L39,2)) -> 1283000 | N39: =IF($I39="","",SUMIFS(资金流水!$K$5:$K$3032,资金流水!$Q$5:$Q$3015,$I39)) | O39: 1283000 | P39: =IF($J39="","",ROUND($M39-IF($N39="",0,$N39)-IF($O39="",0,$O39),2)) -> 0 | Q39: =IF($J39="","",IF($P39<=0.005,"已收齐",IF(IF($N39="",0,$N39)+IF($O39="",0,$O39)<=0,"未收款","部分收款"))) -> 已收齐 | R39: =IF($B39="","",--TEXT($B39,"yyyymm")) -> 202605 | S39: =IF(OR($B39="",$P39="",$P39<=0.005),"",TODAY()-$B39)
A40: =IF($B40="","",COUNTA($B$5:$B40)) -> 36 | B40: 46162 | C40: 双思威 | D40: =IFERROR(INDEX(基础资料!$C$4:$C$11,MATCH($C40,基础资料!$A$4:$A$11,0)),"") -> 一般纳税人 | E40: 增值税专用发票 | F40: 新疆准东经济技术开发区管理委员会 | G40: :社管局准东学校三期实验楼设施设备配置项目(二次) | J40: 4141829.9 | K40: 0.13 | L40: =IF($J40="","",ROUND($J40*$K40,2)) -> 538437.89 | M40: =IF($J40="","",ROUND($J40+$L40,2)) -> 4680267.8 | N40: =IF($I40="","",SUMIFS(资金流水!$K$5:$K$3032,资金流水!$Q$5:$Q$3015,$I40)) | O40: 4680267.8 | P40: =IF($J40="","",ROUND($M40-IF($N40="",0,$N40)-IF($O40="",0,$O40),2)) -> 0 | Q40: =IF($J40="","",IF($P40<=0.005,"已收齐",IF(IF($N40="",0,$N40)+IF($O40="",0,$O40)<=0,"未收款","部分收款"))) -> 已收齐 | R40: =IF($B40="","",--TEXT($B40,"yyyymm")) -> 202605 | S40: =IF(OR($B40="",$P40="",$P40<=0.005),"",TODAY()-$B40)
A41: =IF($B41="","",COUNTA($B$5:$B41)) -> 37 | B41: 46148 | C41: 元界极光 | D41: =IFERROR(INDEX(基础资料!$C$4:$C$11,MATCH($C41,基础资料!$A$4:$A$11,0)),"") -> 小规模纳税人 | E41: 增值税普通发票 | F41: 昌吉市第七小学 | G41: 昌吉市第七小学润苗楼教室文化墙、图书角及会议室项目 | J41: 160539.42 | K41: 0.01 | L41: =IF($J41="","",ROUND($J41*$K41,2)) -> 1605.39 | M41: =IF($J41="","",ROUND($J41+$L41,2)) -> 162144.81 | N41: =IF($I41="","",SUMIFS(资金流水!$K$5:$K$3032,资金流水!$Q$5:$Q$3015,$I41)) | O41: 162144.81 | P41: =IF($J41="","",ROUND($M41-IF($N41="",0,$N41)-IF($O41="",0,$O41),2)) -> 0 | Q41: =IF($J41="","",IF($P41<=0.005,"已收齐",IF(IF($N41="",0,$N41)+IF($O41="",0,$O41)<=0,"未收款","部分收款"))) -> 已收齐 | R41: =IF($B41="","",--TEXT($B41,"yyyymm")) -> 202605 | S41: =IF(OR($B41="",$P41="",$P41<=0.005),"",TODAY()-$B41)
A42: =IF($B42="","",COUNTA($B$5:$B42)) -> 38 | B42: 46148 | C42: 中展 | D42: =IFERROR(INDEX(基础资料!$C$4:$C$11,MATCH($C42,基础资料!$A$4:$A$11,0)),"") -> 小规模纳税人 | E42: 增值税普通发票 | F42: 昌吉市第十四小学 | G42: 十八小的厨房监控 | J42: 44554.47 | K42: 0.01 | L42: =IF($J42="","",ROUND($J42*$K42,2)) -> 445.54 | M42: =IF($J42="","",ROUND($J42+$L42,2)) -> 45000.01 | N42: =IF($I42="","",SUMIFS(资金流水!$K$5:$K$3032,资金流水!$Q$5:$Q$3015,$I42)) | O42: 162144.81 | P42: =IF($J42="","",ROUND($M42-IF($N42="",0,$N42)-IF($O42="",0,$O42),2)) -> -117144.8 | Q42: =IF($J42="","",IF($P42<=0.005,"已收齐",IF(IF($N42="",0,$N42)+IF($O42="",0,$O42)<=0,"未收款","部分收款"))) -> 已收齐 | R42: =IF($B42="","",--TEXT($B42,"yyyymm")) -> 202605 | S42: =IF(OR($B42="",$P42="",$P42<=0.005),"",TODAY()-$B42)
A43: =IF($B43="","",COUNTA($B$5:$B43)) -> 39 | B43: 46148 | C43: 中展 | D43: =IFERROR(INDEX(基础资料!$C$4:$C$11,MATCH($C43,基础资料!$A$4:$A$11,0)),"") -> 小规模纳税人 | E43: 增值税普通发票 | F43: 昌吉市第十四小学 | G43: 以前公司的项目季总知道详细情况安排欢婷要的钱 | J43: 9702.97 | K43: 0.01 | L43: =IF($J43="","",ROUND($J43*$K43,2)) -> 97.03 | M43: =IF($J43="","",ROUND($J43+$L43,2)) -> 9800 | N43: =IF($I43="","",SUMIFS(资金流水!$K$5:$K$3032,资金流水!$Q$5:$Q$3015,$I43)) | O43: 9800 | P43: =IF($J43="","",ROUND($M43-IF($N43="",0,$N43)-IF($O43="",0,$O43),2)) -> 0 | Q43: =IF($J43="","",IF($P43<=0.005,"已收齐",IF(IF($N43="",0,$N43)+IF($O43="",0,$O43)<=0,"未收款","部分收款"))) -> 已收齐 | R43: =IF($B43="","",--TEXT($B43,"yyyymm")) -> 202605 | S43: =IF(OR($B43="",$P43="",$P43<=0.005),"",TODAY()-$B43)
A44: =IF($B44="","",COUNTA($B$5:$B44)) -> 40 | B44: 46150 | C44: 中展 | D44: =IFERROR(INDEX(基础资料!$C$4:$C$11,MATCH($C44,基础资料!$A$4:$A$11,0)),"") -> 小规模纳税人 | E44: 增值税普通发票 | F44: 昌吉市第二小学 | G44: 昌吉市第二小学学术报告厅灯光及扩声设备采购项目 | J44: 86571.95 | K44: 0.01 | L44: =IF($J44="","",ROUND($J44*$K44,2)) -> 865.72 | M44: =IF($J44="","",ROUND($J44+$L44,2)) -> 87437.67 | N44: =IF($I44="","",SUMIFS(资金流水!$K$5:$K$3032,资金流水!$Q$5:$Q$3015,$I44)) | O44: 87437.67 | P44: =IF($J44="","",ROUND($M44-IF($N44="",0,$N44)-IF($O44="",0,$O44),2)) -> 0 | Q44: =IF($J44="","",IF($P44<=0.005,"已收齐",IF(IF($N44="",0,$N44)+IF($O44="",0,$O44)<=0,"未收款","部分收款"))) -> 已收齐 | R44: =IF($B44="","",--TEXT($B44,"yyyymm")) -> 202605 | S44: =IF(OR($B44="",$P44="",$P44<=0.005),"",TODAY()-$B44)
A45: =IF($B45="","",COUNTA($B$5:$B45)) -> 41 | B45: 46153 | C45: 中展 | D45: =IFERROR(INDEX(基础资料!$C$4:$C$11,MATCH($C45,基础资料!$A$4:$A$11,0)),"") -> 小规模纳税人 | E45: 增值税普通发票 | F45: 昌吉市第五幼儿园 | G45: 昌吉市南安幼儿园设备采购项目 | J45: 79207.91 | K45: 0.01 | L45: =IF($J45="","",ROUND($J45*$K45,2)) -> 792.08 | M45: =IF($J45="","",ROUND($J45+$L45,2)) -> 79999.99 | N45: =IF($I45="","",SUMIFS(资金流水!$K$5:$K$3032,资金流水!$Q$5:$Q$3015,$I45)) | O45: 79999.99 | P45: =IF($J45="","",ROUND($M45-IF($N45="",0,$N45)-IF($O45="",0,$O45),2)) -> 0 | Q45: =IF($J45="","",IF($P45<=0.005,"已收齐",IF(IF($N45="",0,$N45)+IF($O45="",0,$O45)<=0,"未收款","部分收款"))) -> 已收齐 | R45: =IF($B45="","",--TEXT($B45,"yyyymm")) -> 202605 | S45: =IF(OR($B45="",$P45="",$P45<=0.005),"",TODAY()-$B45)
A46: =IF($B46="","",COUNTA($B$5:$B46)) -> 42 | B46: 46164 | C46: 中展 | D46: =IFERROR(INDEX(基础资料!$C$4:$C$11,MATCH($C46,基础资料!$A$4:$A$11,0)),"") -> 小规模纳税人 | E46: 增值税普通发票 | F46: 昌吉市第五幼儿园 | G46: 昌吉市南安幼儿园设备采购项目 | J46: 26886.15 | K46: 0.01 | L46: =IF($J46="","",ROUND($J46*$K46,2)) -> 268.86 | M46: =IF($J46="","",ROUND($J46+$L46,2)) -> 27155.01 | N46: =IF($I46="","",SUMIFS(资金流水!$K$5:$K$3032,资金流水!$Q$5:$Q$3015,$I46)) | O46: 27155.01 | P46: =IF($J46="","",ROUND($M46-IF($N46="",0,$N46)-IF($O46="",0,$O46),2)) -> 0 | Q46: =IF($J46="","",IF($P46<=0.005,"已收齐",IF(IF($N46="",0,$N46)+IF($O46="",0,$O46)<=0,"未收款","部分收款"))) -> 已收齐 | R46: =IF($B46="","",--TEXT($B46,"yyyymm")) -> 202605 | S46: =IF(OR($B46="",$P46="",$P46<=0.005),"",TODAY()-$B46)
A47: =IF($B47="","",COUNTA($B$5:$B47)) -> 43 | B47: 46164 | C47: 中展 | D47: =IFERROR(INDEX(基础资料!$C$4:$C$11,MATCH($C47,基础资料!$A$4:$A$11,0)),"") -> 小规模纳税人 | E47: 增值税普通发票 | F47: 昌吉市第四中学 | G47: 2套黑板 | J47: 41188.12 | K47: 0.01 | L47: =IF($J47="","",ROUND($J47*$K47,2)) -> 411.88 | M47: =IF($J47="","",ROUND($J47+$L47,2)) -> 41600 | N47: =IF($I47="","",SUMIFS(资金流水!$K$5:$K$3032,资金流水!$Q$5:$Q$3015,$I47)) | O47: 41300 | P47: =IF($J47="","",ROUND($M47-IF($N47="",0,$N47)-IF($O47="",0,$O47),2)) -> 300 | Q47: =IF($J47="","",IF($P47<=0.005,"已收齐",IF(IF($N47="",0,$N47)+IF($O47="",0,$O47)<=0,"未收款","部分收款"))) -> 部分收款 | R47: =IF($B47="","",--TEXT($B47,"yyyymm")) -> 202605 | S47: =IF(OR($B47="",$P47="",$P47<=0.005),"",TODAY()-$B47) -> 113
... A50: =IF($B50="","",COUNTA($B$5:$B50)) -> 46 | B50: 46167 | C50: 元界启辰 | D50: =IFERROR(INDEX(基础资料!$C$4:$C$11,MATCH($C50,基础资料!$A$4:$A$11,0)),"") -> 小规模纳税人 | E50: 增值税普通发票 | F50: 昌吉市第一小学 | G50: 昌吉市第一小学机房项目 | J50: 100277.22 | K50: 0.01 | L50: =IF($J50="","",ROUND($J50*$K50,2)) -> 1002.77 | M50: =IF($J50="","",ROUND($J50+$L50,2)) -> 101279.99 | N50: =IF($I50="","",SUMIFS(资金流水!$K$5:$K$3032,资金流水!$Q$5:$Q$3015,$I50)) | O50: 101279.99 | P50: =IF($J50="","",ROUND($M50-IF($N50="",0,$N50)-IF($O50="",0,$O50),2)) -> 0 | Q50: =IF($J50="","",IF($P50<=0.005,"已收齐",IF(IF($N50="",0,$N50)+IF($O50="",0,$O50)<=0,"未收款","部分收款"))) -> 已收齐 | R50: =IF($B50="","",--TEXT($B50,"yyyymm")) -> 202605 | S50: =IF(OR($B50="",$P50="",$P50<=0.005),"",TODAY()-$B50)
A51: =IF($B51="","",COUNTA($B$5:$B51)) -> 47 | B51: 46157 | C51: 锐思维度 | D51: =IFERROR(INDEX(基础资料!$C$4:$C$11,MATCH($C51,基础资料!$A$4:$A$11,0)),"") -> 小规模纳税人 | E51: 增值税普通发票 | F51: 天康生物股份有限公司 | J51: 5445.55 | K51: 0.01 | L51: 54.45 | M51: =IF($J51="","",ROUND($J51+$L51,2)) -> 5500 | N51: =IF($I51="","",SUMIFS(资金流水!$K$5:$K$3032,资金流水!$Q$5:$Q$3015,$I51)) | O51: 5500 | P51: =IF($J51="","",ROUND($M51-IF($N51="",0,$N51)-IF($O51="",0,$O51),2)) -> 0 | Q51: =IF($J51="","",IF($P51<=0.005,"已收齐",IF(IF($N51="",0,$N51)+IF($O51="",0,$O51)<=0,"未收款","部分收款"))) -> 已收齐 | R51: =IF($B51="","",--TEXT($B51,"yyyymm")) -> 202605 | S51: =IF(OR($B51="",$P51="",$P51<=0.005),"",TODAY()-$B51)
A52: =IF($B52="","",COUNTA($B$5:$B52)) -> 48 | B52: 46161 | C52: 锐思维度 | D52: =IFERROR(INDEX(基础资料!$C$4:$C$11,MATCH($C52,基础资料!$A$4:$A$11,0)),"") -> 小规模纳税人 | E52: 增值税普通发票 | F52: 昌吉市第十小学 | G52: 小学创客教室方案（昌吉市第十九小学） | J52: 129123.76 | K52: 0.01 | L52: =IF($J52="","",ROUND($J52*$K52,2)) -> 1291.24 | M52: =IF($J52="","",ROUND($J52+$L52,2)) -> 130415 | N52: =IF($I52="","",SUMIFS(资金流水!$K$5:$K$3032,资金流水!$Q$5:$Q$3015,$I52)) | O52: 130415 | P52: =IF($J52="","",ROUND($M52-IF($N52="",0,$N52)-IF($O52="",0,$O52),2)) -> 0 | Q52: =IF($J52="","",IF($P52<=0.005,"已收齐",IF(IF($N52="",0,$N52)+IF($O52="",0,$O52)<=0,"未收款","部分收款"))) -> 已收齐 | R52: =IF($B52="","",--TEXT($B52,"yyyymm")) -> 202605 | S52: =IF(OR($B52="",$P52="",$P52<=0.005),"",TODAY()-$B52)
A53: =IF($B53="","",COUNTA($B$5:$B53)) -> 49 | B53: 46168 | C53: 锐思维度 | D53: =IFERROR(INDEX(基础资料!$C$4:$C$11,MATCH($C53,基础资料!$A$4:$A$11,0)),"") -> 小规模纳税人 | E53: 增值税普通发票 | F53: 昌吉市第二小学 | G53: 昌吉市第二小学智慧安防系统改造项目 | J53: 69222.79 | K53: 0.01 | L53: 692.21 | M53: =IF($J53="","",ROUND($J53+$L53,2)) -> 69915 | N53: =IF($I53="","",SUMIFS(资金流水!$K$5:$K$3032,资金流水!$Q$5:$Q$3015,$I53)) | O53: 69915 | P53: =IF($J53="","",ROUND($M53-IF($N53="",0,$N53)-IF($O53="",0,$O53),2)) -> 0 | Q53: =IF($J53="","",IF($P53<=0.005,"已收齐",IF(IF($N53="",0,$N53)+IF($O53="",0,$O53)<=0,"未收款","部分收款"))) -> 已收齐 | R53: =IF($B53="","",--TEXT($B53,"yyyymm")) -> 202605 | S53: =IF(OR($B53="",$P53="",$P53<=0.005),"",TODAY()-$B53)
A54: =IF($B54="","",COUNTA($B$5:$B54)) -> 50 | B54: 46181 | C54: 双思威 | D54: =IFERROR(INDEX(基础资料!$C$4:$C$11,MATCH($C54,基础资料!$A$4:$A$11,0)),"") -> 一般纳税人 | E54: 增值税专用发票 | F54: 中电信数智科技有限公司巴音郭楞蒙古自治州分公司 | G54: 中电信数智巴州分公司 2026 年铁门关经济技术开发区化工园区周界防护 | J54: 1654867.3 | K54: 0.13 | L54: =IF($J54="","",ROUND($J54*$K54,2)) -> 215132.74 | M54: =IF($J54="","",ROUND($J54+$L54,2)) -> 1870000 | N54: =IF($I54="","",SUMIFS(资金流水!$K$5:$K$3032,资金流水!$Q$5:$Q$3015,$I54)) | P54: =IF($J54="","",ROUND($M54-IF($N54="",0,$N54)-IF($O54="",0,$O54),2)) -> 1870000 | Q54: =IF($J54="","",IF($P54<=0.005,"已收齐",IF(IF($N54="",0,$N54)+IF($O54="",0,$O54)<=0,"未收款","部分收款"))) -> 未收款 | R54: =IF($B54="","",--TEXT($B54,"yyyymm")) -> 202606 | S54: =IF(OR($B54="",$P54="",$P54<=0.005),"",TODAY()-$B54) -> 96
A55: =IF($B55="","",COUNTA($B$5:$B55)) -> 51 | B55: 46181 | C55: 双思威 | D55: =IFERROR(INDEX(基础资料!$C$4:$C$11,MATCH($C55,基础资料!$A$4:$A$11,0)),"") -> 一般纳税人 | E55: 增值税专用发票 | F55: 新疆永旺信息技术有限公司 | G55: 张立猛30706合同，总合同是52908元 | J55: 27173.45 | K55: 0.13 | L55: =IF($J55="","",ROUND($J55*$K55,2)) -> 3532.55 | M55: =IF($J55="","",ROUND($J55+$L55,2)) -> 30706 | N55: =IF($I55="","",SUMIFS(资金流水!$K$5:$K$3032,资金流水!$Q$5:$Q$3015,$I55)) | O55: 30706 | P55: =IF($J55="","",ROUND($M55-IF($N55="",0,$N55)-IF($O55="",0,$O55),2)) -> 0 | Q55: =IF($J55="","",IF($P55<=0.005,"已收齐",IF(IF($N55="",0,$N55)+IF($O55="",0,$O55)<=0,"未收款","部分收款"))) -> 已收齐 | R55: =IF($B55="","",--TEXT($B55,"yyyymm")) -> 202606 | S55: =IF(OR($B55="",$P55="",$P55<=0.005),"",TODAY()-$B55)
A56: =IF($B56="","",COUNTA($B$5:$B56)) -> 52 | B56: 46190 | C56: 双思威 | D56: =IFERROR(INDEX(基础资料!$C$4:$C$11,MATCH($C56,基础资料!$A$4:$A$11,0)),"") -> 一般纳税人 | E56: 增值税专用发票 | F56: 新疆博创未来信息工程技术有限公司 | G56: 草湖标识标牌项目 | J56: 442584.07 | K56: 0.13 | L56: =IF($J56="","",ROUND($J56*$K56,2)) -> 57535.93 | M56: =IF($J56="","",ROUND($J56+$L56,2)) -> 500120 | N56: =IF($I56="","",SUMIFS(资金流水!$K$5:$K$3032,资金流水!$Q$5:$Q$3015,$I56)) | O56: 500120 | P56: =IF($J56="","",ROUND($M56-IF($N56="",0,$N56)-IF($O56="",0,$O56),2)) -> 0 | Q56: =IF($J56="","",IF($P56<=0.005,"已收齐",IF(IF($N56="",0,$N56)+IF($O56="",0,$O56)<=0,"未收款","部分收款"))) -> 已收齐 | R56: =IF($B56="","",--TEXT($B56,"yyyymm")) -> 202606 | S56: =IF(OR($B56="",$P56="",$P56<=0.005),"",TODAY()-$B56)
A57: =IF($B57="","",COUNTA($B$5:$B57)) -> 53 | B57: 46190 | C57: 双思威 | D57: =IFERROR(INDEX(基础资料!$C$4:$C$11,MATCH($C57,基础资料!$A$4:$A$11,0)),"") -> 一般纳税人 | E57: 增值税专用发票 | F57: 昌吉市第十二小学 | G57: 昌吉市第十二小学综合楼阶梯教室采购项目 | J57: 253104.4 | K57: 0.13 | L57: 32903.6 | M57: =IF($J57="","",ROUND($J57+$L57,2)) -> 286008 | N57: =IF($I57="","",SUMIFS(资金流水!$K$5:$K$3032,资金流水!$Q$5:$Q$3015,$I57)) | O57: 286008 | P57: =IF($J57="","",ROUND($M57-IF($N57="",0,$N57)-IF($O57="",0,$O57),2)) -> 0 | Q57: =IF($J57="","",IF($P57<=0.005,"已收齐",IF(IF($N57="",0,$N57)+IF($O57="",0,$O57)<=0,"未收款","部分收款"))) -> 已收齐 | R57: =IF($B57="","",--TEXT($B57,"yyyymm")) -> 202606 | S57: =IF(OR($B57="",$P57="",$P57<=0.005),"",TODAY()-$B57)
A58: =IF($B58="","",COUNTA($B$5:$B58)) -> 54 | B58: 46191 | C58: 元界极光 | D58: 小规模纳税人 | E58: 增值税普通发票 | F58: 昌吉市第十二小学 | G58: 昌吉市第十二小学设计方案 | J58: 990.1 | K58: 0.01 | L58: =IF($J58="","",ROUND($J58*$K58,2)) -> 9.9 | M58: =IF($J58="","",ROUND($J58+$L58,2)) -> 1000 | N58: =IF($I58="","",SUMIFS(资金流水!$K$5:$K$3032,资金流水!$Q$5:$Q$3015,$I58)) | O58: 1000 | P58: =IF($J58="","",ROUND($M58-IF($N58="",0,$N58)-IF($O58="",0,$O58),2)) -> 0 | Q58: =IF($J58="","",IF($P58<=0.005,"已收齐",IF(IF($N58="",0,$N58)+IF($O58="",0,$O58)<=0,"未收款","部分收款"))) -> 已收齐 | R58: =IF($B58="","",--TEXT($B58,"yyyymm")) -> 202606 | S58: =IF(OR($B58="",$P58="",$P58<=0.005),"",TODAY()-$B58)
A59: =IF($B59="","",COUNTA($B$5:$B59)) -> 55 | B59: 46197 | C59: 中展 | D59: =IFERROR(INDEX(基础资料!$C$4:$C$11,MATCH($C59,基础资料!$A$4:$A$11,0)),"") -> 小规模纳税人 | E59: 增值税普通发票 | F59: 昌吉市第三中学 | G59: 昌吉市第三中学安检门 | J59: 71287.13 | K59: 0.01 | L59: =IF($J59="","",ROUND($J59*$K59,2)) -> 712.87 | M59: =IF($J59="","",ROUND($J59+$L59,2)) -> 72000 | N59: =IF($I59="","",SUMIFS(资金流水!$K$5:$K$3032,资金流水!$Q$5:$Q$3015,$I59)) | O59: 72000 | P59: =IF($J59="","",ROUND($M59-IF($N59="",0,$N59)-IF($O59="",0,$O59),2)) -> 0 | Q59: =IF($J59="","",IF($P59<=0.005,"已收齐",IF(IF($N59="",0,$N59)+IF($O59="",0,$O59)<=0,"未收款","部分收款"))) -> 已收齐 | R59: =IF($B59="","",--TEXT($B59,"yyyymm")) -> 202606 | S59: =IF(OR($B59="",$P59="",$P59<=0.005),"",TODAY()-$B59)
A60: =IF($B60="","",COUNTA($B$5:$B60)) -> 56 | B60: 46181 | C60: 元界启辰 | D60: =IFERROR(INDEX(基础资料!$C$4:$C$11,MATCH($C60,基础资料!$A$4:$A$11,0)),"") -> 小规模纳税人 | E60: 增值税普通发票 | F60: 昌吉市第一小学 | G60: 昌吉市第一小学机房项目 | J60: 165326.73 | K60: 0.01 | L60: =IF($J60="","",ROUND($J60*$K60,2)) -> 1653.27 | M60: =IF($J60="","",ROUND($J60+$L60,2)) -> 166980 | N60: =IF($I60="","",SUMIFS(资金流水!$K$5:$K$3032,资金流水!$Q$5:$Q$3015,$I60)) | O60: 166980 | P60: =IF($J60="","",ROUND($M60-IF($N60="",0,$N60)-IF($O60="",0,$O60),2)) -> 0 | Q60: =IF($J60="","",IF($P60<=0.005,"已收齐",IF(IF($N60="",0,$N60)+IF($O60="",0,$O60)<=0,"未收款","部分收款"))) -> 已收齐 | R60: =IF($B60="","",--TEXT($B60,"yyyymm")) -> 202606 | S60: =IF(OR($B60="",$P60="",$P60<=0.005),"",TODAY()-$B60)
A61: =IF($B61="","",COUNTA($B$5:$B61)) -> 57 | B61: 46195 | C61: 元界启辰 | D61: =IFERROR(INDEX(基础资料!$C$4:$C$11,MATCH($C61,基础资料!$A$4:$A$11,0)),"") -> 小规模纳税人 | E61: 增值税普通发票 | F61: 新疆生产建设兵团第二师交通运输局 | G61: 维护费 | J61: 1980.2 | K61: 0.01 | L61: =IF($J61="","",ROUND($J61*$K61,2)) -> 19.8 | M61: =IF($J61="","",ROUND($J61+$L61,2)) -> 2000 | N61: =IF($I61="","",SUMIFS(资金流水!$K$5:$K$3032,资金流水!$Q$5:$Q$3015,$I61)) | O61: 2000 | P61: =IF($J61="","",ROUND($M61-IF($N61="",0,$N61)-IF($O61="",0,$O61),2)) -> 0 | Q61: =IF($J61="","",IF($P61<=0.005,"已收齐",IF(IF($N61="",0,$N61)+IF($O61="",0,$O61)<=0,"未收款","部分收款"))) -> 已收齐 | R61: =IF($B61="","",--TEXT($B61,"yyyymm")) -> 202606 | S61: =IF(OR($B61="",$P61="",$P61<=0.005),"",TODAY()-$B61)
A62: =IF($B62="","",COUNTA($B$5:$B62)) -> 58 | B62: 46209 | C62: 双思威 | D62: =IFERROR(INDEX(基础资料!$C$4:$C$11,MATCH($C62,基础资料!$A$4:$A$11,0)),"") -> 一般纳税人 | E62: 增值税专用发票 | F62: 昌吉市第十二小学 | G62: 昌吉市第十二小学综合楼阶梯教室采购项目 | J62: 407858.41 | K62: 0.13 | L62: =IF($J62="","",ROUND($J62*$K62,2)) -> 53021.59 | M62: =IF($J62="","",ROUND($J62+$L62,2)) -> 460880 | N62: =IF($I62="","",SUMIFS(资金流水!$K$5:$K$3032,资金流水!$Q$5:$Q$3015,$I62)) | O62: 460880 | P62: =IF($J62="","",ROUND($M62-IF($N62="",0,$N62)-IF($O62="",0,$O62),2)) -> 0 | Q62: =IF($J62="","",IF($P62<=0.005,"已收齐",IF(IF($N62="",0,$N62)+IF($O62="",0,$O62)<=0,"未收款","部分收款"))) -> 已收齐 | R62: =IF($B62="","",--TEXT($B62,"yyyymm")) -> 202607 | S62: =IF(OR($B62="",$P62="",$P62<=0.005),"",TODAY()-$B62)
A63: =IF($B63="","",COUNTA($B$5:$B63)) -> 59 | B63: 46209 | C63: 双思威 | D63: =IFERROR(INDEX(基础资料!$C$4:$C$11,MATCH($C63,基础资料!$A$4:$A$11,0)),"") -> 一般纳税人 | E63: 增值税专用发票 | F63: 昌吉市第十二小学 | G63: 昌吉市第十二小学综合楼阶梯教室采购项目 | J63: 14905.66 | K63: 0.06 | L63: =IF($J63="","",ROUND($J63*$K63,2)) -> 894.34 | M63: =IF($J63="","",ROUND($J63+$L63,2)) -> 15800 | N63: =IF($I63="","",SUMIFS(资金流水!$K$5:$K$3032,资金流水!$Q$5:$Q$3015,$I63)) | O63: 15800 | P63: =IF($J63="","",ROUND($M63-IF($N63="",0,$N63)-IF($O63="",0,$O63),2)) -> 0 | Q63: =IF($J63="","",IF($P63<=0.005,"已收齐",IF(IF($N63="",0,$N63)+IF($O63="",0,$O63)<=0,"未收款","部分收款"))) -> 已收齐 | R63: =IF($B63="","",--TEXT($B63,"yyyymm")) -> 202607 | S63: =IF(OR($B63="",$P63="",$P63<=0.005),"",TODAY()-$B63)
A64: =IF($B64="","",COUNTA($B$5:$B64)) -> 60 | B64: 46211 | C64: 双思威 | D64: =IFERROR(INDEX(基础资料!$C$4:$C$11,MATCH($C64,基础资料!$A$4:$A$11,0)),"") -> 一般纳税人 | E64: 增值税专用发票 | F64: 昌吉市锐步电子科技有限公司 | G64: 昌吉州第三中学标准化考场建设采购项目 | J64: 761543.35 | K64: 0.13 | L64: 99000.65 | M64: =IF($J64="","",ROUND($J64+$L64,2)) -> 860544 | N64: =IF($I64="","",SUMIFS(资金流水!$K$5:$K$3032,资金流水!$Q$5:$Q$3015,$I64)) | O64: 836750 | P64: =IF($J64="","",ROUND($M64-IF($N64="",0,$N64)-IF($O64="",0,$O64),2)) -> 23794 | Q64: =IF($J64="","",IF($P64<=0.005,"已收齐",IF(IF($N64="",0,$N64)+IF($O64="",0,$O64)<=0,"未收款","部分收款"))) -> 部分收款 | R64: =IF($B64="","",--TEXT($B64,"yyyymm")) -> 202607 | S64: =IF(OR($B64="",$P64="",$P64<=0.005),"",TODAY()-$B64) -> 66
A65: =IF($B65="","",COUNTA($B$5:$B65)) -> 61 | B65: 46219 | C65: 双思威 | D65: =IFERROR(INDEX(基础资料!$C$4:$C$11,MATCH($C65,基础资料!$A$4:$A$11,0)),"") -> 一般纳税人 | E65: 增值税专用发票 | F65: 中国电信股份有限公司巴音郭楞蒙古自治州分公司 | G65: 张宝安项目设备维修费 | J65: 781.42 | K65: 0.13 | L65: =IF($J65="","",ROUND($J65*$K65,2)) -> 101.58 | M65: =IF($J65="","",ROUND($J65+$L65,2)) -> 883 | N65: =IF($I65="","",SUMIFS(资金流水!$K$5:$K$3032,资金流水!$Q$5:$Q$3015,$I65)) | O65: 883 | P65: =IF($J65="","",ROUND($M65-IF($N65="",0,$N65)-IF($O65="",0,$O65),2)) -> 0 | Q65: =IF($J65="","",IF($P65<=0.005,"已收齐",IF(IF($N65="",0,$N65)+IF($O65="",0,$O65)<=0,"未收款","部分收款"))) -> 已收齐 | R65: =IF($B65="","",--TEXT($B65,"yyyymm")) -> 202607 | S65: =IF(OR($B65="",$P65="",$P65<=0.005),"",TODAY()-$B65)
A66: =IF($B66="","",COUNTA($B$5:$B66)) -> 62 | B66: 46233 | C66: 瑞盛天 | D66: =IFERROR(INDEX(基础资料!$C$4:$C$11,MATCH($C66,基础资料!$A$4:$A$11,0)),"") -> 一般纳税人 | E66: 增值税普通发票 | F66: 昌吉市第七小学 | G66: 昌吉市第七小学阶梯教室设备采购项目 | J66: 307797.34 | K66: 0.13 | L66: 40013.66 | M66: =IF($J66="","",ROUND($J66+$L66,2)) -> 347811 | N66: =IF($I66="","",SUMIFS(资金流水!$K$5:$K$3032,资金流水!$Q$5:$Q$3015,$I66)) | O66: 347811 | P66: =IF($J66="","",ROUND($M66-IF($N66="",0,$N66)-IF($O66="",0,$O66),2)) -> 0 | Q66: =IF($J66="","",IF($P66<=0.005,"已收齐",IF(IF($N66="",0,$N66)+IF($O66="",0,$O66)<=0,"未收款","部分收款"))) -> 已收齐 | R66: =IF($B66="","",--TEXT($B66,"yyyymm")) -> 202607 | S66: =IF(OR($B66="",$P66="",$P66<=0.005),"",TODAY()-$B66)
A67: =IF($B67="","",COUNTA($B$5:$B67)) -> 63 | B67: 46217 | C67: 元界启辰 | D67: =IFERROR(INDEX(基础资料!$C$4:$C$11,MATCH($C67,基础资料!$A$4:$A$11,0)),"") -> 小规模纳税人 | E67: 增值税普通发票 | F67: 昌吉市第十小学 | G67: 昌吉市第十小学智慧教室项目 | J67: 148178.23 | K67: 0.01 | L67: 1481.77 | M67: =IF($J67="","",ROUND($J67+$L67,2)) -> 149660 | N67: =IF($I67="","",SUMIFS(资金流水!$K$5:$K$3032,资金流水!$Q$5:$Q$3015,$I67)) | O67: 149660 | P67: =IF($J67="","",ROUND($M67-IF($N67="",0,$N67)-IF($O67="",0,$O67),2)) -> 0 | Q67: =IF($J67="","",IF($P67<=0.005,"已收齐",IF(IF($N67="",0,$N67)+IF($O67="",0,$O67)<=0,"未收款","部分收款"))) -> 已收齐 | R67: =IF($B67="","",--TEXT($B67,"yyyymm")) -> 202607 | S67: =IF(OR($B67="",$P67="",$P67<=0.005),"",TODAY()-$B67)
A68: =IF($B68="","",COUNTA($B$5:$B68)) -> 64 | B68: 46217 | C68: 锐思维度 | D68: =IFERROR(INDEX(基础资料!$C$4:$C$11,MATCH($C68,基础资料!$A$4:$A$11,0)),"") -> 小规模纳税人 | E68: 增值税普通发票 | F68: 昌吉市第二小学 | G68: 昌吉市第二小学智慧安防系统改造 | J68: 115099.01 | K68: 0.01 | L68: =IF($J68="","",ROUND($J68*$K68,2)) -> 1150.99 | M68: =IF($J68="","",ROUND($J68+$L68,2)) -> 116250 | N68: =IF($I68="","",SUMIFS(资金流水!$K$5:$K$3032,资金流水!$Q$5:$Q$3015,$I68)) | O68: 116250 | P68: =IF($J68="","",ROUND($M68-IF($N68="",0,$N68)-IF($O68="",0,$O68),2)) -> 0 | Q68: =IF($J68="","",IF($P68<=0.005,"已收齐",IF(IF($N68="",0,$N68)+IF($O68="",0,$O68)<=0,"未收款","部分收款"))) -> 已收齐 | R68: =IF($B68="","",--TEXT($B68,"yyyymm")) -> 202607 | S68: =IF(OR($B68="",$P68="",$P68<=0.005),"",TODAY()-$B68)
A69: =IF($B69="","",COUNTA($B$5:$B69)) -> 65 | B69: 46217 | C69: 锐思维度 | D69: =IFERROR(INDEX(基础资料!$C$4:$C$11,MATCH($C69,基础资料!$A$4:$A$11,0)),"") -> 小规模纳税人 | E69: 增值税普通发票 | F69: 昌吉市第十小学 | G69: 昌吉市第十小学（昌吉市第十九小学创客项目） | J69: 70341.57 | K69: 0.01 | L69: 703.43 | M69: =IF($J69="","",ROUND($J69+$L69,2)) -> 71045 | N69: =IF($I69="","",SUMIFS(资金流水!$K$5:$K$3032,资金流水!$Q$5:$Q$3015,$I69)) | O69: 71045 | P69: =IF($J69="","",ROUND($M69-IF($N69="",0,$N69)-IF($O69="",0,$O69),2)) -> 0 | Q69: =IF($J69="","",IF($P69<=0.005,"已收齐",IF(IF($N69="",0,$N69)+IF($O69="",0,$O69)<=0,"未收款","部分收款"))) -> 已收齐 | R69: =IF($B69="","",--TEXT($B69,"yyyymm")) -> 202607 | S69: =IF(OR($B69="",$P69="",$P69<=0.005),"",TODAY()-$B69)
A70: =IF($B70="","",COUNTA($B$5:$B70)) -> 66 | B70: 46244 | C70: 双思威 | D70: =IFERROR(INDEX(基础资料!$C$4:$C$11,MATCH($C70,基础资料!$A$4:$A$11,0)),"") -> 一般纳税人 | E70: 增值税专用发票 | F70: 新疆信友能源投资有限公司 | G70: 2026年新疆信友能源投资有限公司网格优化服务项目 | J70: 84905.66 | K70: 0.06 | L70: =IF($J70="","",ROUND($J70*$K70,2)) -> 5094.34 | M70: =IF($J70="","",ROUND($J70+$L70,2)) -> 90000 | N70: =IF($I70="","",SUMIFS(资金流水!$K$5:$K$3032,资金流水!$Q$5:$Q$3015,$I70)) | O70: 90000 | P70: =IF($J70="","",ROUND($M70-IF($N70="",0,$N70)-IF($O70="",0,$O70),2)) -> 0 | Q70: =IF($J70="","",IF($P70<=0.005,"已收齐",IF(IF($N70="",0,$N70)+IF($O70="",0,$O70)<=0,"未收款","部分收款"))) -> 已收齐 | R70: =IF($B70="","",--TEXT($B70,"yyyymm")) -> 202608 | S70: =IF(OR($B70="",$P70="",$P70<=0.005),"",TODAY()-$B70)
A71: =IF($B71="","",COUNTA($B$5:$B71)) -> 67 | B71: 46251 | C71: 双思威 | D71: =IFERROR(INDEX(基础资料!$C$4:$C$11,MATCH($C71,基础资料!$A$4:$A$11,0)),"") -> 一般纳税人 | E71: 增值税专用发票 | F71: 库尔勒天盛佳源安全技术防范工程有限公司 | G71: 宇视的摄像机2026年7月21日购买不合格卖出开发票 | J71: 69026.55 | K71: 0.13 | L71: =IF($J71="","",ROUND($J71*$K71,2)) -> 8973.45 | M71: =IF($J71="","",ROUND($J71+$L71,2)) -> 78000 | N71: =IF($I71="","",SUMIFS(资金流水!$K$5:$K$3032,资金流水!$Q$5:$Q$3015,$I71)) | O71: 78000 | P71: =IF($J71="","",ROUND($M71-IF($N71="",0,$N71)-IF($O71="",0,$O71),2)) -> 0 | Q71: =IF($J71="","",IF($P71<=0.005,"已收齐",IF(IF($N71="",0,$N71)+IF($O71="",0,$O71)<=0,"未收款","部分收款"))) -> 已收齐 | R71: =IF($B71="","",--TEXT($B71,"yyyymm")) -> 202608 | S71: =IF(OR($B71="",$P71="",$P71<=0.005),"",TODAY()-$B71)
A72: =IF($B72="","",COUNTA($B$5:$B72)) -> 68 | B72: 46260 | C72: 双思威 | D72: =IFERROR(INDEX(基础资料!$C$4:$C$11,MATCH($C72,基础资料!$A$4:$A$11,0)),"") -> 一般纳税人 | E72: 增值税专用发票 | F72: 新疆博创未来信息工程技术有限公司 | G72: 草湖标识标牌项目 | J72: 654761.02 | K72: 0.13 | L72: 85118.98 | M72: =IF($J72="","",ROUND($J72+$L72,2)) -> 739880 | N72: =IF($I72="","",SUMIFS(资金流水!$K$5:$K$3032,资金流水!$Q$5:$Q$3015,$I72)) | P72: =IF($J72="","",ROUND($M72-IF($N72="",0,$N72)-IF($O72="",0,$O72),2)) -> 739880 | Q72: =IF($J72="","",IF($P72<=0.005,"已收齐",IF(IF($N72="",0,$N72)+IF($O72="",0,$O72)<=0,"未收款","部分收款"))) -> 未收款 | R72: =IF($B72="","",--TEXT($B72,"yyyymm")) -> 202608 | S72: =IF(OR($B72="",$P72="",$P72<=0.005),"",TODAY()-$B72) -> 17
A73: =IF($B73="","",COUNTA($B$5:$B73)) -> 69 | B73: 46240 | C73: 瑞盛天 | D73: =IFERROR(INDEX(基础资料!$C$4:$C$11,MATCH($C73,基础资料!$A$4:$A$11,0)),"") -> 一般纳税人 | E73: 增值税普通发票 | F73: 昌吉市第七小学 | G73: 昌吉市第七小学阶梯教室设备采购项目 | J73: 577574.35 | K73: 0.13 | L73: 75084.65 | M73: =IF($J73="","",ROUND($J73+$L73,2)) -> 652659 | N73: =IF($I73="","",SUMIFS(资金流水!$K$5:$K$3032,资金流水!$Q$5:$Q$3015,$I73)) | O73: 652659 | P73: =IF($J73="","",ROUND($M73-IF($N73="",0,$N73)-IF($O73="",0,$O73),2)) -> 0 | Q73: =IF($J73="","",IF($P73<=0.005,"已收齐",IF(IF($N73="",0,$N73)+IF($O73="",0,$O73)<=0,"未收款","部分收款"))) -> 已收齐 | R73: =IF($B73="","",--TEXT($B73,"yyyymm")) -> 202608 | S73: =IF(OR($B73="",$P73="",$P73<=0.005),"",TODAY()-$B73)
A74: =IF($B74="","",COUNTA($B$5:$B74)) -> 70 | B74: 46237 | C74: 中展 | D74: =IFERROR(INDEX(基础资料!$C$4:$C$11,MATCH($C74,基础资料!$A$4:$A$11,0)),"") -> 小规模纳税人 | E74: 增值税普通发票 | F74: 昌吉市第八小学 | G74: 昌吉市第八小学5G+课堂建设采购项目 | J74: 154386.16 | K74: 0.01 | L74: 1543.84 | M74: =IF($J74="","",ROUND($J74+$L74,2)) -> 155930 | N74: =IF($I74="","",SUMIFS(资金流水!$K$5:$K$3032,资金流水!$Q$5:$Q$3015,$I74)) | O74: 155930 | P74: =IF($J74="","",ROUND($M74-IF($N74="",0,$N74)-IF($O74="",0,$O74),2)) -> 0 | Q74: =IF($J74="","",IF($P74<=0.005,"已收齐",IF(IF($N74="",0,$N74)+IF($O74="",0,$O74)<=0,"未收款","部分收款"))) -> 已收齐 | R74: =IF($B74="","",--TEXT($B74,"yyyymm")) -> 202608 | S74: =IF(OR($B74="",$P74="",$P74<=0.005),"",TODAY()-$B74)
A75: =IF($B75="","",COUNTA($B$5:$B75)) -> 71 | B75: 46247 | C75: 中展 | D75: =IFERROR(INDEX(基础资料!$C$4:$C$11,MATCH($C75,基础资料!$A$4:$A$11,0)),"") -> 小规模纳税人 | E75: 增值税普通发票 | F75: 昌吉市第八小学 | G75: 昌吉市第八小学5G+课堂建设采购项目 | J75: 251534.66 | K75: 0.01 | L75: 2515.34 | M75: =IF($J75="","",ROUND($J75+$L75,2)) -> 254050 | N75: =IF($I75="","",SUMIFS(资金流水!$K$5:$K$3032,资金流水!$Q$5:$Q$3015,$I75)) | O75: 254050 | P75: =IF($J75="","",ROUND($M75-IF($N75="",0,$N75)-IF($O75="",0,$O75),2)) -> 0 | Q75: =IF($J75="","",IF($P75<=0.005,"已收齐",IF(IF($N75="",0,$N75)+IF($O75="",0,$O75)<=0,"未收款","部分收款"))) -> 已收齐 | R75: =IF($B75="","",--TEXT($B75,"yyyymm")) -> 202608 | S75: =IF(OR($B75="",$P75="",$P75<=0.005),"",TODAY()-$B75)
A76: =IF($B76="","",COUNTA($B$5:$B76)) -> 72 | B76: 46254 | C76: 元界启辰 | D76: =IFERROR(INDEX(基础资料!$C$4:$C$11,MATCH($C76,基础资料!$A$4:$A$11,0)),"") -> 小规模纳税人 | E76: 增值税普通发票 | F76: 昌吉市教育局 | G76: 昌吉市第十七小学配套附属设施采购项目（教育教学设备 | J76: 872405.35 | K76: 0.01 | L76: =IF($J76="","",ROUND($J76*$K76,2)) -> 8724.05 | M76: =IF($J76="","",ROUND($J76+$L76,2)) -> 881129.4 | N76: =IF($I76="","",SUMIFS(资金流水!$K$5:$K$3032,资金流水!$Q$5:$Q$3015,$I76)) | P76: =IF($J76="","",ROUND($M76-IF($N76="",0,$N76)-IF($O76="",0,$O76),2)) -> 881129.4 | Q76: =IF($J76="","",IF($P76<=0.005,"已收齐",IF(IF($N76="",0,$N76)+IF($O76="",0,$O76)<=0,"未收款","部分收款"))) -> 未收款 | R76: =IF($B76="","",--TEXT($B76,"yyyymm")) -> 202608 | S76: =IF(OR($B76="",$P76="",$P76<=0.005),"",TODAY()-$B76) -> 23
A77: =IF($B77="","",COUNTA($B$5:$B77)) -> 73 | B77: 46260 | C77: 元界启辰 | D77: =IFERROR(INDEX(基础资料!$C$4:$C$11,MATCH($C77,基础资料!$A$4:$A$11,0)),"") -> 小规模纳税人 | E77: 增值税普通发票 | F77: 昌吉市教育局 | G77: 昌吉市第十七小学配套附属设施采购项目（教育教学设备 | J77: 1454008.9 | K77: 0.01 | L77: 14540.11 | M77: =IF($J77="","",ROUND($J77+$L77,2)) -> 1468549 | N77: =IF($I77="","",SUMIFS(资金流水!$K$5:$K$3032,资金流水!$Q$5:$Q$3015,$I77)) | P77: =IF($J77="","",ROUND($M77-IF($N77="",0,$N77)-IF($O77="",0,$O77),2)) -> 1468549 | Q77: =IF($J77="","",IF($P77<=0.005,"已收齐",IF(IF($N77="",0,$N77)+IF($O77="",0,$O77)<=0,"未收款","部分收款"))) -> 未收款 | R77: =IF($B77="","",--TEXT($B77,"yyyymm")) -> 202608 | S77: =IF(OR($B77="",$P77="",$P77<=0.005),"",TODAY()-$B77) -> 17
A78: =IF($B78="","",COUNTA($B$5:$B78)) | D78: =IFERROR(INDEX(基础资料!$C$4:$C$11,MATCH($C78,基础资料!$A$4:$A$11,0)),"") | L78: =IF($J78="","",ROUND($J78*$K78,2)) | M78: =IF($J78="","",ROUND($J78+$L78,2)) | N78: =IF($I78="","",SUMIFS(资金流水!$K$5:$K$3032,资金流水!$Q$5:$Q$3015,$I78)) | P78: =IF($J78="","",ROUND($M78-IF($N78="",0,$N78)-IF($O78="",0,$O78),2)) | Q78: =IF($J78="","",IF($P78<=0.005,"已收齐",IF(IF($N78="",0,$N78)+IF($O78="",0,$O78)<=0,"未收款","部分收款"))) | R78: =IF($B78="","",--TEXT($B78,"yyyymm")) | S78: =IF(OR($B78="",$P78="",$P78<=0.005),"",TODAY()-$B78)
A79: =IF($B79="","",COUNTA($B$5:$B79)) | D79: =IFERROR(INDEX(基础资料!$C$4:$C$11,MATCH($C79,基础资料!$A$4:$A$11,0)),"") | L79: =IF($J79="","",ROUND($J79*$K79,2)) | M79: =IF($J79="","",ROUND($J79+$L79,2)) | N79: =IF($I79="","",SUMIFS(资金流水!$K$5:$K$3032,资金流水!$Q$5:$Q$3015,$I79)) | P79: =IF($J79="","",ROUND($M79-IF($N79="",0,$N79)-IF($O79="",0,$O79),2)) | Q79: =IF($J79="","",IF($P79<=0.005,"已收齐",IF(IF($N79="",0,$N79)+IF($O79="",0,$O79)<=0,"未收款","部分收款"))) | R79: =IF($B79="","",--TEXT($B79,"yyyymm")) | S79: =IF(OR($B79="",$P79="",$P79<=0.005),"",TODAY()-$B79)
A80: =IF($B80="","",COUNTA($B$5:$B80)) | D80: =IFERROR(INDEX(基础资料!$C$4:$C$11,MATCH($C80,基础资料!$A$4:$A$11,0)),"") | L80: =IF($J80="","",ROUND($J80*$K80,2)) | M80: =IF($J80="","",ROUND($J80+$L80,2)) | N80: =IF($I80="","",SUMIFS(资金流水!$K$5:$K$3032,资金流水!$Q$5:$Q$3015,$I80)) | P80: =IF($J80="","",ROUND($M80-IF($N80="",0,$N80)-IF($O80="",0,$O80),2)) | Q80: =IF($J80="","",IF($P80<=0.005,"已收齐",IF(IF($N80="",0,$N80)+IF($O80="",0,$O80)<=0,"未收款","部分收款"))) | R80: =IF($B80="","",--TEXT($B80,"yyyymm")) | S80: =IF(OR($B80="",$P80="",$P80<=0.005),"",TODAY()-$B80)
A81: =IF($B81="","",COUNTA($B$5:$B81)) | D81: =IFERROR(INDEX(基础资料!$C$4:$C$11,MATCH($C81,基础资料!$A$4:$A$11,0)),"") | L81: =IF($J81="","",ROUND($J81*$K81,2)) | M81: =IF($J81="","",ROUND($J81+$L81,2)) | N81: =IF($I81="","",SUMIFS(资金流水!$K$5:$K$3032,资金流水!$Q$5:$Q$3015,$I81)) | P81: =IF($J81="","",ROUND($M81-IF($N81="",0,$N81)-IF($O81="",0,$O81),2)) | Q81: =IF($J81="","",IF($P81<=0.005,"已收齐",IF(IF($N81="",0,$N81)+IF($O81="",0,$O81)<=0,"未收款","部分收款"))) | R81: =IF($B81="","",--TEXT($B81,"yyyymm")) | S81: =IF(OR($B81="",$P81="",$P81<=0.005),"",TODAY()-$B81)
A82: =IF($B82="","",COUNTA($B$5:$B82)) | D82: =IFERROR(INDEX(基础资料!$C$4:$C$11,MATCH($C82,基础资料!$A$4:$A$11,0)),"") | L82: =IF($J82="","",ROUND($J82*$K82,2)) | M82: =IF($J82="","",ROUND($J82+$L82,2)) | N82: =IF($I82="","",SUMIFS(资金流水!$K$5:$K$3032,资金流水!$Q$5:$Q$3015,$I82)) | P82: =IF($J82="","",ROUND($M82-IF($N82="",0,$N82)-IF($O82="",0,$O82),2)) | Q82: =IF($J82="","",IF($P82<=0.005,"已收齐",IF(IF($N82="",0,$N82)+IF($O82="",0,$O82)<=0,"未收款","部分收款"))) | R82: =IF($B82="","",--TEXT($B82,"yyyymm")) | S82: =IF(OR($B82="",$P82="",$P82<=0.005),"",TODAY()-$B82)
A83: =IF($B83="","",COUNTA($B$5:$B83)) | D83: =IFERROR(INDEX(基础资料!$C$4:$C$11,MATCH($C83,基础资料!$A$4:$A$11,0)),"") | L83: =IF($J83="","",ROUND($J83*$K83,2)) | M83: =IF($J83="","",ROUND($J83+$L83,2)) | N83: =IF($I83="","",SUMIFS(资金流水!$K$5:$K$3032,资金流水!$Q$5:$Q$3015,$I83)) | P83: =IF($J83="","",ROUND($M83-IF($N83="",0,$N83)-IF($O83="",0,$O83),2)) | Q83: =IF($J83="","",IF($P83<=0.005,"已收齐",IF(IF($N83="",0,$N83)+IF($O83="",0,$O83)<=0,"未收款","部分收款"))) | R83: =IF($B83="","",--TEXT($B83,"yyyymm")) | S83: =IF(OR($B83="",$P83="",$P83<=0.005),"",TODAY()-$B83)
A84: =IF($B84="","",COUNTA($B$5:$B84)) | D84: =IFERROR(INDEX(基础资料!$C$4:$C$11,MATCH($C84,基础资料!$A$4:$A$11,0)),"") | L84: =IF($J84="","",ROUND($J84*$K84,2)) | M84: =IF($J84="","",ROUND($J84+$L84,2)) | N84: =IF($I84="","",SUMIFS(资金流水!$K$5:$K$3032,资金流水!$Q$5:$Q$3015,$I84)) | P84: =IF($J84="","",ROUND($M84-IF($N84="",0,$N84)-IF($O84="",0,$O84),2)) | Q84: =IF($J84="","",IF($P84<=0.005,"已收齐",IF(IF($N84="",0,$N84)+IF($O84="",0,$O84)<=0,"未收款","部分收款"))) | R84: =IF($B84="","",--TEXT($B84,"yyyymm")) | S84: =IF(OR($B84="",$P84="",$P84<=0.005),"",TODAY()-$B84)
A85: =IF($B85="","",COUNTA($B$5:$B85)) | D85: =IFERROR(INDEX(基础资料!$C$4:$C$11,MATCH($C85,基础资料!$A$4:$A$11,0)),"") | L85: =IF($J85="","",ROUND($J85*$K85,2)) | M85: =IF($J85="","",ROUND($J85+$L85,2)) | N85: =IF($I85="","",SUMIFS(资金流水!$K$5:$K$3032,资金流水!$Q$5:$Q$3015,$I85)) | P85: =IF($J85="","",ROUND($M85-IF($N85="",0,$N85)-IF($O85="",0,$O85),2)) | Q85: =IF($J85="","",IF($P85<=0.005,"已收齐",IF(IF($N85="",0,$N85)+IF($O85="",0,$O85)<=0,"未收款","部分收款"))) | R85: =IF($B85="","",--TEXT($B85,"yyyymm")) | S85: =IF(OR($B85="",$P85="",$P85<=0.005),"",TODAY()-$B85)
A86: =IF($B86="","",COUNTA($B$5:$B86)) | D86: =IFERROR(INDEX(基础资料!$C$4:$C$11,MATCH($C86,基础资料!$A$4:$A$11,0)),"") | L86: =IF($J86="","",ROUND($J86*$K86,2)) | M86: =IF($J86="","",ROUND($J86+$L86,2)) | N86: =IF($I86="","",SUMIFS(资金流水!$K$5:$K$3032,资金流水!$Q$5:$Q$3015,$I86)) | P86: =IF($J86="","",ROUND($M86-IF($N86="",0,$N86)-IF($O86="",0,$O86),2)) | Q86: =IF($J86="","",IF($P86<=0.005,"已收齐",IF(IF($N86="",0,$N86)+IF($O86="",0,$O86)<=0,"未收款","部分收款"))) | R86: =IF($B86="","",--TEXT($B86,"yyyymm")) | S86: =IF(OR($B86="",$P86="",$P86<=0.005),"",TODAY()-$B86)
A87: =IF($B87="","",COUNTA($B$5:$B87)) | D87: =IFERROR(INDEX(基础资料!$C$4:$C$11,MATCH($C87,基础资料!$A$4:$A$11,0)),"") | L87: =IF($J87="","",ROUND($J87*$K87,2)) | M87: =IF($J87="","",ROUND($J87+$L87,2)) | N87: =IF($I87="","",SUMIFS(资金流水!$K$5:$K$3032,资金流水!$Q$5:$Q$3015,$I87)) | P87: =IF($J87="","",ROUND($M87-IF($N87="",0,$N87)-IF($O87="",0,$O87),2)) | Q87: =IF($J87="","",IF($P87<=0.005,"已收齐",IF(IF($N87="",0,$N87)+IF($O87="",0,$O87)<=0,"未收款","部分收款"))) | R87: =IF($B87="","",--TEXT($B87,"yyyymm")) | S87: =IF(OR($B87="",$P87="",$P87<=0.005),"",TODAY()-$B87)
A88: =IF($B88="","",COUNTA($B$5:$B88)) | D88: =IFERROR(INDEX(基础资料!$C$4:$C$11,MATCH($C88,基础资料!$A$4:$A$11,0)),"") | L88: =IF($J88="","",ROUND($J88*$K88,2)) | M88: =IF($J88="","",ROUND($J88+$L88,2)) | N88: =IF($I88="","",SUMIFS(资金流水!$K$5:$K$3032,资金流水!$Q$5:$Q$3015,$I88)) | P88: =IF($J88="","",ROUND($M88-IF($N88="",0,$N88)-IF($O88="",0,$O88),2)) | Q88: =IF($J88="","",IF($P88<=0.005,"已收齐",IF(IF($N88="",0,$N88)+IF($O88="",0,$O88)<=0,"未收款","部分收款"))) | R88: =IF($B88="","",--TEXT($B88,"yyyymm")) | S88: =IF(OR($B88="",$P88="",$P88<=0.005),"",TODAY()-$B88)
A89: =IF($B89="","",COUNTA($B$5:$B89)) | D89: =IFERROR(INDEX(基础资料!$C$4:$C$11,MATCH($C89,基础资料!$A$4:$A$11,0)),"") | L89: =IF($J89="","",ROUND($J89*$K89,2)) | M89: =IF($J89="","",ROUND($J89+$L89,2)) | N89: =IF($I89="","",SUMIFS(资金流水!$K$5:$K$3032,资金流水!$Q$5:$Q$3015,$I89)) | P89: =IF($J89="","",ROUND($M89-IF($N89="",0,$N89)-IF($O89="",0,$O89),2)) | Q89: =IF($J89="","",IF($P89<=0.005,"已收齐",IF(IF($N89="",0,$N89)+IF($O89="",0,$O89)<=0,"未收款","部分收款"))) | R89: =IF($B89="","",--TEXT($B89,"yyyymm")) | S89: =IF(OR($B89="",$P89="",$P89<=0.005),"",TODAY()-$B89)
... A504: =IF($B504="","",COUNTA($B$5:$B504)) | D504: =IFERROR(INDEX(基础资料!$C$4:$C$11,MATCH($C504,基础资料!$A$4:$A$11,0)),"") | L504: =IF($J504="","",ROUND($J504*$K504,2)) | M504: =IF($J504="","",ROUND($J504+$L504,2)) | N504: =IF($I504="","",SUMIFS(资金流水!$K$5:$K$3032,资金流水!$Q$5:$Q$3015,$I504)) | P504: =IF($J504="","",ROUND($M504-IF($N504="",0,$N504)-IF($O504="",0,$O504),2)) | Q504: =IF($J504="","",IF($P504<=0.005,"已收齐",IF(IF($N504="",0,$N504)+IF($O504="",0,$O504)<=0,"未收款","部分收款"))) | R504: =IF($B504="","",--TEXT($B504,"yyyymm")) | S504: =IF(OR($B504="",$P504="",$P504<=0.005),"",TODAY()-$B504)

Sheet 资金流水
A1: 资金流水台账 — 全部公司 / 全部账户，只在这一张表录一遍
A2: 资金总余额(随筛选) | C2: =$M$2+$K$2-$L$2 -> 1.8048975e+09 | D2: 跨期笔数 | F2: =COUNTIF($U$5:$U$3015,"跨期") -> 2 | G2: 已录笔数 | I2: =COUNT($B$5:$B$3032) -> 673 | J2: 筛选后合计→ | K2: =SUBTOTAL(109,$K$5:$K$3032) -> 15241709 | L2: =SUBTOTAL(109,$L$5:$L$3032) -> 9937223.2 | M2: =SUBTOTAL(109,$M$5:$M$3015) -> 1.799593e+09
A3: 录入规则：①每笔银行流水一行，收入填K列、支出填L列（不要同时填）。②每个账户开账时录一行“期初余额”，收支类型选“期初余额”、金额填M列。③项目类收支必须选“项目名称”；支出属于项目成本的填H列成本类别，属于日常费用/税金的填I列费用类别。④跨期业务（如收到去年项目的尾款）在P列填业务归属月(如202512)，留空默认按发生月。⑤与发票或应收应付挂钩的，在Q列填同一个“关联单号”即可自动核销。灰色S~X列是自动计算，请勿手输。
A4: 序号 | B4: 日期 | C4: 账户 | D4: 公司(自动) | E4: 收支类型 | F4: 项目名称 | G4: 收入类别 | H4: 成本类别 | I4: 费用类别 | J4: 摘要内容 | K4: 收入金额 | L4: 支出金额 | M4: 余额 | N4: 客户 | O4: 供应商 | P4: 业务归属月 (跨期时填) | Q4: 关联单号 (发票号/往来号) | R4: 备注 | S4: 发生月 | T4: 归属月 | U4: 跨期 | V4: 项目行号 | W4: 支出大类 | X4: 收入大类
A5: =IF($B5="","",COUNTA($B$5:$B5)) -> 1 | B5: 46023 | C5: 双思威基本户 | D5: =IFERROR(INDEX(基础资料!$F$4:$F$23,MATCH($C5,基础资料!$E$4:$E$23,0)),IF($C5="","","未匹配账户")) -> 双思威 | E5: 期初余额 | J5: 期初余额 | M5: 857870.23 | R5: ★请填入该账户实际期初余额 | S5: =IF($B5="","",--TEXT($B5,"yyyymm")) -> 202601 | T5: =IF($B5="","",IF($P5="",$S5,IFERROR($P5*1,$P5))) -> 202601 | U5: =IF($B5="","",IF($T5=$S5,"","跨期")) | V5: =IF(AND($B5<>"",$F5<>"",$F5=项目明细账!$C$2),N(V4)+1,N(V4)) -> 0 | W5: =IF($H5<>"","项目成本",IFERROR(INDEX(基础资料!$W$4:$W$49,MATCH($I5,基础资料!$V$4:$V$49,0)),"")) | X5: =IFERROR(INDEX(基础资料!$R$4:$R$17,MATCH($G5,基础资料!$Q$4:$Q$17,0)),"")
A6: =IF($B6="","",COUNTA($B$5:$B6)) -> 2 | B6: 46023 | C6: 双思威农商行一般户 | D6: =IFERROR(INDEX(基础资料!$F$4:$F$23,MATCH($C6,基础资料!$E$4:$E$23,0)),IF($C6="","","未匹配账户")) -> 双思威 | E6: 期初余额 | J6: 期初余额 | M6: 996321.15 | R6: ★请填入该账户实际期初余额 | S6: =IF($B6="","",--TEXT($B6,"yyyymm")) -> 202601 | T6: =IF($B6="","",IF($P6="",$S6,IFERROR($P6*1,$P6))) -> 202601 | U6: =IF($B6="","",IF($T6=$S6,"","跨期")) | V6: =IF(AND($B6<>"",$F6<>"",$F6=项目明细账!$C$2),N(V5)+1,N(V5)) -> 0 | W6: =IF($H6<>"","项目成本",IFERROR(INDEX(基础资料!$W$4:$W$49,MATCH($I6,基础资料!$V$4:$V$49,0)),"")) | X6: =IFERROR(INDEX(基础资料!$R$4:$R$17,MATCH($G6,基础资料!$Q$4:$Q$17,0)),"")
A7: =IF($B7="","",COUNTA($B$5:$B7)) -> 3 | B7: 46023 | C7: 晨拓农商行基本户 | D7: =IFERROR(INDEX(基础资料!$F$4:$F$23,MATCH($C7,基础资料!$E$4:$E$23,0)),IF($C7="","","未匹配账户")) -> 晨拓 | E7: 期初余额 | J7: 期初余额 | M7: 1695593.5 | R7: ★请填入该账户实际期初余额 | S7: =IF($B7="","",--TEXT($B7,"yyyymm")) -> 202601 | T7: =IF($B7="","",IF($P7="",$S7,IFERROR($P7*1,$P7))) -> 202601 | U7: =IF($B7="","",IF($T7=$S7,"","跨期")) | V7: =IF(AND($B7<>"",$F7<>"",$F7=项目明细账!$C$2),N(V6)+1,N(V6)) -> 0 | W7: =IF($H7<>"","项目成本",IFERROR(INDEX(基础资料!$W$4:$W$49,MATCH($I7,基础资料!$V$4:$V$49,0)),"")) | X7: =IFERROR(INDEX(基础资料!$R$4:$R$17,MATCH($G7,基础资料!$Q$4:$Q$17,0)),"")
A8: =IF($B8="","",COUNTA($B$5:$B8)) -> 4 | B8: 46023 | C8: 元界极光中行基本户 | D8: =IFERROR(INDEX(基础资料!$F$4:$F$23,MATCH($C8,基础资料!$E$4:$E$23,0)),IF($C8="","","未匹配账户")) -> 元界极光 | E8: 期初余额 | J8: 期初余额 | M8: 450747.19 | R8: ★请填入该账户实际期初余额 | S8: =IF($B8="","",--TEXT($B8,"yyyymm")) -> 202601 | T8: =IF($B8="","",IF($P8="",$S8,IFERROR($P8*1,$P8))) -> 202601 | U8: =IF($B8="","",IF($T8=$S8,"","跨期")) | V8: =IF(AND($B8<>"",$F8<>"",$F8=项目明细账!$C$2),N(V7)+1,N(V7)) -> 0 | W8: =IF($H8<>"","项目成本",IFERROR(INDEX(基础资料!$W$4:$W$49,MATCH($I8,基础资料!$V$4:$V$49,0)),"")) | X8: =IFERROR(INDEX(基础资料!$R$4:$R$17,MATCH($G8,基础资料!$Q$4:$Q$17,0)),"")
A9: =IF($B9="","",COUNTA($B$5:$B9)) -> 5 | B9: 46023 | C9: 元界极光农商行一般户 | D9: =IFERROR(INDEX(基础资料!$F$4:$F$23,MATCH($C9,基础资料!$E$4:$E$23,0)),IF($C9="","","未匹配账户")) -> 元界极光 | E9: 期初余额 | J9: 期初余额 | M9: 200010.67 | R9: ★请填入该账户实际期初余额 | S9: =IF($B9="","",--TEXT($B9,"yyyymm")) -> 202601 | T9: =IF($B9="","",IF($P9="",$S9,IFERROR($P9*1,$P9))) -> 202601 | U9: =IF($B9="","",IF($T9=$S9,"","跨期")) | V9: =IF(AND($B9<>"",$F9<>"",$F9=项目明细账!$C$2),N(V8)+1,N(V8)) -> 0 | W9: =IF($H9<>"","项目成本",IFERROR(INDEX(基础资料!$W$4:$W$49,MATCH($I9,基础资料!$V$4:$V$49,0)),"")) | X9: =IFERROR(INDEX(基础资料!$R$4:$R$17,MATCH($G9,基础资料!$Q$4:$Q$17,0)),"")
A10: =IF($B10="","",COUNTA($B$5:$B10)) -> 6 | B10: 46023 | C10: 瑞盛天中行基本户 | D10: =IFERROR(INDEX(基础资料!$F$4:$F$23,MATCH($C10,基础资料!$E$4:$E$23,0)),IF($C10="","","未匹配账户")) -> 瑞盛天 | E10: 期初余额 | J10: 期初余额 | M10: 1332384.2 | R10: ★请填入该账户实际期初余额 | S10: =IF($B10="","",--TEXT($B10,"yyyymm")) -> 202601 | T10: =IF($B10="","",IF($P10="",$S10,IFERROR($P10*1,$P10))) -> 202601 | U10: =IF($B10="","",IF($T10=$S10,"","跨期")) | V10: =IF(AND($B10<>"",$F10<>"",$F10=项目明细账!$C$2),N(V9)+1,N(V9)) -> 0 | W10: =IF($H10<>"","项目成本",IFERROR(INDEX(基础资料!$W$4:$W$49,MATCH($I10,基础资料!$V$4:$V$49,0)),"")) | X10: =IFERROR(INDEX(基础资料!$R$4:$R$17,MATCH($G10,基础资料!$Q$4:$Q$17,0)),"")
A11: =IF($B11="","",COUNTA($B$5:$B11)) -> 7 | B11: 46023 | C11: 瑞盛天农商行一般户 | D11: =IFERROR(INDEX(基础资料!$F$4:$F$23,MATCH($C11,基础资料!$E$4:$E$23,0)),IF($C11="","","未匹配账户")) -> 瑞盛天 | E11: 期初余额 | J11: 期初余额 | M11: 201465.55 | R11: ★请填入该账户实际期初余额 | S11: =IF($B11="","",--TEXT($B11,"yyyymm")) -> 202601 | T11: =IF($B11="","",IF($P11="",$S11,IFERROR($P11*1,$P11))) -> 202601 | U11: =IF($B11="","",IF($T11=$S11,"","跨期")) | V11: =IF(AND($B11<>"",$F11<>"",$F11=项目明细账!$C$2),N(V10)+1,N(V10)) -> 0 | W11: =IF($H11<>"","项目成本",IFERROR(INDEX(基础资料!$W$4:$W$49,MATCH($I11,基础资料!$V$4:$V$49,0)),"")) | X11: =IFERROR(INDEX(基础资料!$R$4:$R$17,MATCH($G11,基础资料!$Q$4:$Q$17,0)),"")
A12: =IF($B12="","",COUNTA($B$5:$B12)) -> 8 | B12: 46023 | C12: 中展中行基本户 | D12: =IFERROR(INDEX(基础资料!$F$4:$F$23,MATCH($C12,基础资料!$E$4:$E$23,0)),IF($C12="","","未匹配账户")) -> 中展 | E12: 期初余额 | J12: 期初余额 | M12: 237547.75 | R12: ★请填入该账户实际期初余额 | S12: =IF($B12="","",--TEXT($B12,"yyyymm")) -> 202601 | T12: =IF($B12="","",IF($P12="",$S12,IFERROR($P12*1,$P12))) -> 202601 | U12: =IF($B12="","",IF($T12=$S12,"","跨期")) | V12: =IF(AND($B12<>"",$F12<>"",$F12=项目明细账!$C$2),N(V11)+1,N(V11)) -> 0 | W12: =IF($H12<>"","项目成本",IFERROR(INDEX(基础资料!$W$4:$W$49,MATCH($I12,基础资料!$V$4:$V$49,0)),"")) | X12: =IFERROR(INDEX(基础资料!$R$4:$R$17,MATCH($G12,基础资料!$Q$4:$Q$17,0)),"")
A13: =IF($B13="","",COUNTA($B$5:$B13)) -> 9 | B13: 46050 | C13: 中展农商行一般户 | D13: =IFERROR(INDEX(基础资料!$F$4:$F$23,MATCH($C13,基础资料!$E$4:$E$23,0)),IF($C13="","","未匹配账户")) -> 中展 | E13: 期初余额 | J13: 期初余额 | M13: 100000 | R13: ★请填入该账户实际期初余额 | S13: =IF($B13="","",--TEXT($B13,"yyyymm")) -> 202601 | T13: =IF($B13="","",IF($P13="",$S13,IFERROR($P13*1,$P13))) -> 202601 | U13: =IF($B13="","",IF($T13=$S13,"","跨期")) | V13: =IF(AND($B13<>"",$F13<>"",$F13=项目明细账!$C$2),N(V12)+1,N(V12)) -> 0 | W13: =IF($H13<>"","项目成本",IFERROR(INDEX(基础资料!$W$4:$W$49,MATCH($I13,基础资料!$V$4:$V$49,0)),"")) | X13: =IFERROR(INDEX(基础资料!$R$4:$R$17,MATCH($G13,基础资料!$Q$4:$Q$17,0)),"")
A14: =IF($B14="","",COUNTA($B$5:$B14)) -> 10 | B14: 46023 | C14: 卓卓通农商行基本户 | D14: =IFERROR(INDEX(基础资料!$F$4:$F$23,MATCH($C14,基础资料!$E$4:$E$23,0)),IF($C14="","","未匹配账户")) -> 卓卓通 | E14: 期初余额 | J14: 期初余额 | M14: 283669.65 | R14: ★请填入该账户实际期初余额 | S14: =IF($B14="","",--TEXT($B14,"yyyymm")) -> 202601 | T14: =IF($B14="","",IF($P14="",$S14,IFERROR($P14*1,$P14))) -> 202601 | U14: =IF($B14="","",IF($T14=$S14,"","跨期")) | V14: =IF(AND($B14<>"",$F14<>"",$F14=项目明细账!$C$2),N(V13)+1,N(V13)) -> 0 | W14: =IF($H14<>"","项目成本",IFERROR(INDEX(基础资料!$W$4:$W$49,MATCH($I14,基础资料!$V$4:$V$49,0)),"")) | X14: =IFERROR(INDEX(基础资料!$R$4:$R$17,MATCH($G14,基础资料!$Q$4:$Q$17,0)),"")
A15: =IF($B15="","",COUNTA($B$5:$B15)) -> 11 | B15: 46023 | C15: 财兴通农商行基本户 | D15: =IFERROR(INDEX(基础资料!$F$4:$F$23,MATCH($C15,基础资料!$E$4:$E$23,0)),IF($C15="","","未匹配账户")) -> 财兴通 | E15: 期初余额 | J15: 期初余额 | M15: 174172.53 | R15: ★请填入该账户实际期初余额 | S15: =IF($B15="","",--TEXT($B15,"yyyymm")) -> 202601 | T15: =IF($B15="","",IF($P15="",$S15,IFERROR($P15*1,$P15))) -> 202601 | U15: =IF($B15="","",IF($T15=$S15,"","跨期")) | V15: =IF(AND($B15<>"",$F15<>"",$F15=项目明细账!$C$2),N(V14)+1,N(V14)) -> 0 | W15: =IF($H15<>"","项目成本",IFERROR(INDEX(基础资料!$W$4:$W$49,MATCH($I15,基础资料!$V$4:$V$49,0)),"")) | X15: =IFERROR(INDEX(基础资料!$R$4:$R$17,MATCH($G15,基础资料!$Q$4:$Q$17,0)),"")
A16: =IF($B16="","",COUNTA($B$5:$B16)) -> 12 | B16: 46023 | C16: 鑫海特工行基本户 | D16: =IFERROR(INDEX(基础资料!$F$4:$F$23,MATCH($C16,基础资料!$E$4:$E$23,0)),IF($C16="","","未匹配账户")) -> 鑫海特 | E16: 期初余额 | J16: 期初余额 | M16: 3110.37 | R16: ★请填入该账户实际期初余额 | S16: =IF($B16="","",--TEXT($B16,"yyyymm")) -> 202601 | T16: =IF($B16="","",IF($P16="",$S16,IFERROR($P16*1,$P16))) -> 202601 | U16: =IF($B16="","",IF($T16=$S16,"","跨期")) | V16: =IF(AND($B16<>"",$F16<>"",$F16=项目明细账!$C$2),N(V15)+1,N(V15)) -> 0 | W16: =IF($H16<>"","项目成本",IFERROR(INDEX(基础资料!$W$4:$W$49,MATCH($I16,基础资料!$V$4:$V$49,0)),"")) | X16: =IFERROR(INDEX(基础资料!$R$4:$R$17,MATCH($G16,基础资料!$Q$4:$Q$17,0)),"")
... A24: =IF($B24="","",COUNTA($B$5:$B24)) -> 20 | B24: 46023 | C24: 备用10 | D24: =IFERROR(INDEX(基础资料!$F$4:$F$23,MATCH($C24,基础资料!$E$4:$E$23,0)),IF($C24="","","未匹配账户")) -> 0 | E24: 期初余额 | J24: 期初余额 | M24: 0 | R24: ★请填入该账户实际期初余额 | S24: =IF($B24="","",--TEXT($B24,"yyyymm")) -> 202601 | T24: =IF($B24="","",IF($P24="",$S24,IFERROR($P24*1,$P24))) -> 202601 | U24: =IF($B24="","",IF($T24=$S24,"","跨期")) | V24: =IF(AND($B24<>"",$F24<>"",$F24=项目明细账!$C$2),N(V23)+1,N(V23)) -> 0 | W24: =IF($H24<>"","项目成本",IFERROR(INDEX(基础资料!$W$4:$W$49,MATCH($I24,基础资料!$V$4:$V$49,0)),"")) | X24: =IFERROR(INDEX(基础资料!$R$4:$R$17,MATCH($G24,基础资料!$Q$4:$Q$17,0)),"")
A25: =IF($B25="","",COUNTA($B$5:$B25)) -> 21 | B25: 46023 | C25: 双思威基本户 | D25: =IFERROR(INDEX(基础资料!$F$4:$F$23,MATCH($C25,基础资料!$E$4:$E$23,0)),IF($C25="","","未匹配账户")) -> 双思威 | E25: 收入 | F25: 第二师铁门关市武安街消防站改造项目 | G25: 项目收入 | J25: 收中国电信股份有限公司新疆分公司货款 | K25: 286729.93 | M25: =IFERROR(VLOOKUP($C25,$C$5:$M$24,11,0)+SUMIF($C$25:$C25,$C25,$K$25:$K25)-SUMIF($C$25:$C25,$C25,$L$25:$L25),"") -> 1144600.2 | R25: 示例：由2026年6月原表导入 | S25: =IF($B25="","",--TEXT($B25,"yyyymm")) -> 202601 | T25: =IF($B25="","",IF($P25="",$S25,IFERROR($P25*1,$P25))) -> 202601 | U25: =IF($B25="","",IF($T25=$S25,"","跨期")) | V25: =IF(AND($B25<>"",$F25<>"",$F25=项目明细账!$C$2),N(V24)+1,N(V24)) -> 0 | W25: =IF($H25<>"","项目成本",IFERROR(INDEX(基础资料!$W$4:$W$49,MATCH($I25,基础资料!$V$4:$V$49,0)),"")) | X25: =IFERROR(INDEX(基础资料!$R$4:$R$17,MATCH($G25,基础资料!$Q$4:$Q$17,0)),"") -> 经营收入
A26: =IF($B26="","",COUNTA($B$5:$B26)) -> 22 | B26: 46048 | C26: 双思威基本户 | D26: =IFERROR(INDEX(基础资料!$F$4:$F$23,MATCH($C26,基础资料!$E$4:$E$23,0)),IF($C26="","","未匹配账户")) -> 双思威 | E26: 收入 | F26: 昌吉市中等职业学校教学设备采购项目(二标段) | G26: 项目收入 | J26: 收中移建设有限公司新疆分公司货款 | K26: 582712.28 | M26: =IFERROR(VLOOKUP($C26,$C$5:$M$24,11,0)+SUMIF($C$25:$C26,$C26,$K$25:$K26)-SUMIF($C$25:$C26,$C26,$L$25:$L26),"") -> 1727312.4 | R26: 示例：由2026年6月原表导入 | S26: =IF($B26="","",--TEXT($B26,"yyyymm")) -> 202601 | T26: =IF($B26="","",IF($P26="",$S26,IFERROR($P26*1,$P26))) -> 202601 | U26: =IF($B26="","",IF($T26=$S26,"","跨期")) | V26: =IF(AND($B26<>"",$F26<>"",$F26=项目明细账!$C$2),N(V25)+1,N(V25)) -> 0 | W26: =IF($H26<>"","项目成本",IFERROR(INDEX(基础资料!$W$4:$W$49,MATCH($I26,基础资料!$V$4:$V$49,0)),"")) | X26: =IFERROR(INDEX(基础资料!$R$4:$R$17,MATCH($G26,基础资料!$Q$4:$Q$17,0)),"") -> 经营收入
A27: =IF($B27="","",COUNTA($B$5:$B27)) -> 23 | B27: 46049 | C27: 双思威基本户 | D27: =IFERROR(INDEX(基础资料!$F$4:$F$23,MATCH($C27,基础资料!$E$4:$E$23,0)),IF($C27="","","未匹配账户")) -> 双思威 | E27: 收入 | F27: 中电信数智科技有限公司昌吉分公司2025年某学校智慧教室建设项目 | G27: 项目收入 | J27: 中电信数智科技有限公司昌吉分公司2025年某学校智慧教室建设项目 | K27: 236456 | M27: =IFERROR(VLOOKUP($C27,$C$5:$M$24,11,0)+SUMIF($C$25:$C27,$C27,$K$25:$K27)-SUMIF($C$25:$C27,$C27,$L$25:$L27),"") -> 1963768.4 | R27: 示例：由2026年6月原表导入 | S27: =IF($B27="","",--TEXT($B27,"yyyymm")) -> 202601 | T27: =IF($B27="","",IF($P27="",$S27,IFERROR($P27*1,$P27))) -> 202601 | U27: =IF($B27="","",IF($T27=$S27,"","跨期")) | V27: =IF(AND($B27<>"",$F27<>"",$F27=项目明细账!$C$2),N(V26)+1,N(V26)) -> 0 | W27: =IF($H27<>"","项目成本",IFERROR(INDEX(基础资料!$W$4:$W$49,MATCH($I27,基础资料!$V$4:$V$49,0)),"")) | X27: =IFERROR(INDEX(基础资料!$R$4:$R$17,MATCH($G27,基础资料!$Q$4:$Q$17,0)),"") -> 经营收入
A28: =IF($B28="","",COUNTA($B$5:$B28)) -> 24 | B28: 46049 | C28: 双思威基本户 | D28: =IFERROR(INDEX(基础资料!$F$4:$F$23,MATCH($C28,基础资料!$E$4:$E$23,0)),IF($C28="","","未匹配账户")) -> 双思威 | E28: 收入 | F28: 中国电信巴州分公司2025年某部幼儿园视频监控系统服务采购 | G28: 项目收入 | J28: 中国电信巴州分公司2025年某部幼儿园视频监控系统服务采购 | K28: 82000 | M28: =IFERROR(VLOOKUP($C28,$C$5:$M$24,11,0)+SUMIF($C$25:$C28,$C28,$K$25:$K28)-SUMIF($C$25:$C28,$C28,$L$25:$L28),"") -> 2045768.4 | R28: 示例：由2026年6月原表导入 | S28: =IF($B28="","",--TEXT($B28,"yyyymm")) -> 202601 | T28: =IF($B28="","",IF($P28="",$S28,IFERROR($P28*1,$P28))) -> 202601 | U28: =IF($B28="","",IF($T28=$S28,"","跨期")) | V28: =IF(AND($B28<>"",$F28<>"",$F28=项目明细账!$C$2),N(V27)+1,N(V27)) -> 0 | W28: =IF($H28<>"","项目成本",IFERROR(INDEX(基础资料!$W$4:$W$49,MATCH($I28,基础资料!$V$4:$V$49,0)),"")) | X28: =IFERROR(INDEX(基础资料!$R$4:$R$17,MATCH($G28,基础资料!$Q$4:$Q$17,0)),"") -> 经营收入
A29: =IF($B29="","",COUNTA($B$5:$B29)) -> 25 | B29: 46034 | C29: 双思威农商行一般户 | D29: =IFERROR(INDEX(基础资料!$F$4:$F$23,MATCH($C29,基础资料!$E$4:$E$23,0)),IF($C29="","","未匹配账户")) -> 双思威 | E29: 收入 | F29: 昌吉市中等职业学校教学设备采购项目（一标段） | G29: 项目收入 | J29: 收北京竞业达数码科技股份有限公司 | K29: 3122400 | M29: =IFERROR(VLOOKUP($C29,$C$5:$M$24,11,0)+SUMIF($C$25:$C29,$C29,$K$25:$K29)-SUMIF($C$25:$C29,$C29,$L$25:$L29),"") -> 4118721.1 | R29: 示例：由2026年6月原表导入 | S29: =IF($B29="","",--TEXT($B29,"yyyymm")) -> 202601 | T29: =IF($B29="","",IF($P29="",$S29,IFERROR($P29*1,$P29))) -> 202601 | U29: =IF($B29="","",IF($T29=$S29,"","跨期")) | V29: =IF(AND($B29<>"",$F29<>"",$F29=项目明细账!$C$2),N(V28)+1,N(V28)) -> 0 | W29: =IF($H29<>"","项目成本",IFERROR(INDEX(基础资料!$W$4:$W$49,MATCH($I29,基础资料!$V$4:$V$49,0)),"")) | X29: =IFERROR(INDEX(基础资料!$R$4:$R$17,MATCH($G29,基础资料!$Q$4:$Q$17,0)),"") -> 经营收入
A30: =IF($B30="","",COUNTA($B$5:$B30)) -> 26 | B30: 46051 | C30: 瑞盛天中行基本户 | D30: =IFERROR(INDEX(基础资料!$F$4:$F$23,MATCH($C30,基础资料!$E$4:$E$23,0)),IF($C30="","","未匹配账户")) -> 瑞盛天 | E30: 收入 | F30: 草湖标识标牌项目 | G30: 项目收入 | J30: 收新疆博创未来信息工程技术有限公司货款 | K30: 200000 | M30: =IFERROR(VLOOKUP($C30,$C$5:$M$24,11,0)+SUMIF($C$25:$C30,$C30,$K$25:$K30)-SUMIF($C$25:$C30,$C30,$L$25:$L30),"") -> 1532384.2 | R30: 示例：由2026年6月原表导入 | S30: =IF($B30="","",--TEXT($B30,"yyyymm")) -> 202601 | T30: =IF($B30="","",IF($P30="",$S30,IFERROR($P30*1,$P30))) -> 202601 | U30: =IF($B30="","",IF($T30=$S30,"","跨期")) | V30: =IF(AND($B30<>"",$F30<>"",$F30=项目明细账!$C$2),N(V29)+1,N(V29)) -> 0 | W30: =IF($H30<>"","项目成本",IFERROR(INDEX(基础资料!$W$4:$W$49,MATCH($I30,基础资料!$V$4:$V$49,0)),"")) | X30: =IFERROR(INDEX(基础资料!$R$4:$R$17,MATCH($G30,基础资料!$Q$4:$Q$17,0)),"") -> 经营收入
A31: =IF($B31="","",COUNTA($B$5:$B31)) -> 27 | B31: 46032 | C31: 双思威基本户 | D31: =IFERROR(INDEX(基础资料!$F$4:$F$23,MATCH($C31,基础资料!$E$4:$E$23,0)),IF($C31="","","未匹配账户")) -> 双思威 | E31: 支出 | I31: 银行手续费 | J31: 付款手续费 | L31: 4.05 | M31: =IFERROR(VLOOKUP($C31,$C$5:$M$24,11,0)+SUMIF($C$25:$C31,$C31,$K$25:$K31)-SUMIF($C$25:$C31,$C31,$L$25:$L31),"") -> 2045764.4 | R31: 示例：由2026年6月原表导入 | S31: =IF($B31="","",--TEXT($B31,"yyyymm")) -> 202601 | T31: =IF($B31="","",IF($P31="",$S31,IFERROR($P31*1,$P31))) -> 202601 | U31: =IF($B31="","",IF($T31=$S31,"","跨期")) | V31: =IF(AND($B31<>"",$F31<>"",$F31=项目明细账!$C$2),N(V30)+1,N(V30)) -> 0 | W31: =IF($H31<>"","项目成本",IFERROR(INDEX(基础资料!$W$4:$W$49,MATCH($I31,基础资料!$V$4:$V$49,0)),"")) -> 财务费用 | X31: =IFERROR(INDEX(基础资料!$R$4:$R$17,MATCH($G31,基础资料!$Q$4:$Q$17,0)),"")
A32: =IF($B32="","",COUNTA($B$5:$B32)) -> 28 | B32: 46035 | C32: 双思威基本户 | D32: =IFERROR(INDEX(基础资料!$F$4:$F$23,MATCH($C32,基础资料!$E$4:$E$23,0)),IF($C32="","","未匹配账户")) -> 双思威 | E32: 支出 | I32: 银行手续费 | J32: 付款手续费 | L32: 4.05 | M32: =IFERROR(VLOOKUP($C32,$C$5:$M$24,11,0)+SUMIF($C$25:$C32,$C32,$K$25:$K32)-SUMIF($C$25:$C32,$C32,$L$25:$L32),"") -> 2045760.3 | R32: 示例：由2026年6月原表导入 | S32: =IF($B32="","",--TEXT($B32,"yyyymm")) -> 202601 | T32: =IF($B32="","",IF($P32="",$S32,IFERROR($P32*1,$P32))) -> 202601 | U32: =IF($B32="","",IF($T32=$S32,"","跨期")) | V32: =IF(AND($B32<>"",$F32<>"",$F32=项目明细账!$C$2),N(V31)+1,N(V31)) -> 0 | W32: =IF($H32<>"","项目成本",IFERROR(INDEX(基础资料!$W$4:$W$49,MATCH($I32,基础资料!$V$4:$V$49,0)),"")) -> 财务费用 | X32: =IFERROR(INDEX(基础资料!$R$4:$R$17,MATCH($G32,基础资料!$Q$4:$Q$17,0)),"")
A33: =IF($B33="","",COUNTA($B$5:$B33)) -> 29 | B33: 46036 | C33: 双思威基本户 | D33: =IFERROR(INDEX(基础资料!$F$4:$F$23,MATCH($C33,基础资料!$E$4:$E$23,0)),IF($C33="","","未匹配账户")) -> 双思威 | E33: 支出 | I33: 工资 | J33: 年终奖 | L33: 250000 | M33: =IFERROR(VLOOKUP($C33,$C$5:$M$24,11,0)+SUMIF($C$25:$C33,$C33,$K$25:$K33)-SUMIF($C$25:$C33,$C33,$L$25:$L33),"") -> 1795760.3 | R33: 示例：由2026年6月原表导入 | S33: =IF($B33="","",--TEXT($B33,"yyyymm")) -> 202601 | T33: =IF($B33="","",IF($P33="",$S33,IFERROR($P33*1,$P33))) -> 202601 | U33: =IF($B33="","",IF($T33=$S33,"","跨期")) | V33: =IF(AND($B33<>"",$F33<>"",$F33=项目明细账!$C$2),N(V32)+1,N(V32)) -> 0 | W33: =IF($H33<>"","项目成本",IFERROR(INDEX(基础资料!$W$4:$W$49,MATCH($I33,基础资料!$V$4:$V$49,0)),"")) -> 人工社保 | X33: =IFERROR(INDEX(基础资料!$R$4:$R$17,MATCH($G33,基础资料!$Q$4:$Q$17,0)),"")
A34: =IF($B34="","",COUNTA($B$5:$B34)) -> 30 | B34: 46036 | C34: 双思威基本户 | D34: =IFERROR(INDEX(基础资料!$F$4:$F$23,MATCH($C34,基础资料!$E$4:$E$23,0)),IF($C34="","","未匹配账户")) -> 双思威 | E34: 支出 | I34: 银行手续费 | J34: 付款手续费 | L34: 200 | M34: =IFERROR(VLOOKUP($C34,$C$5:$M$24,11,0)+SUMIF($C$25:$C34,$C34,$K$25:$K34)-SUMIF($C$25:$C34,$C34,$L$25:$L34),"") -> 1795560.3 | R34: 示例：由2026年6月原表导入 | S34: =IF($B34="","",--TEXT($B34,"yyyymm")) -> 202601 | T34: =IF($B34="","",IF($P34="",$S34,IFERROR($P34*1,$P34))) -> 202601 | U34: =IF($B34="","",IF($T34=$S34,"","跨期")) | V34: =IF(AND($B34<>"",$F34<>"",$F34=项目明细账!$C$2),N(V33)+1,N(V33)) -> 0 | W34: =IF($H34<>"","项目成本",IFERROR(INDEX(基础资料!$W$4:$W$49,MATCH($I34,基础资料!$V$4:$V$49,0)),"")) -> 财务费用 | X34: =IFERROR(INDEX(基础资料!$R$4:$R$17,MATCH($G34,基础资料!$Q$4:$Q$17,0)),"")
A35: =IF($B35="","",COUNTA($B$5:$B35)) -> 31 | B35: 46036 | C35: 双思威基本户 | D35: =IFERROR(INDEX(基础资料!$F$4:$F$23,MATCH($C35,基础资料!$E$4:$E$23,0)),IF($C35="","","未匹配账户")) -> 双思威 | E35: 支出 | I35: 工资 | J35: 付季新军工资 | L35: 8582.47 | M35: =IFERROR(VLOOKUP($C35,$C$5:$M$24,11,0)+SUMIF($C$25:$C35,$C35,$K$25:$K35)-SUMIF($C$25:$C35,$C35,$L$25:$L35),"") -> 1786977.9 | R35: 示例：由2026年6月原表导入 | S35: =IF($B35="","",--TEXT($B35,"yyyymm")) -> 202601 | T35: =IF($B35="","",IF($P35="",$S35,IFERROR($P35*1,$P35))) -> 202601 | U35: =IF($B35="","",IF($T35=$S35,"","跨期")) | V35: =IF(AND($B35<>"",$F35<>"",$F35=项目明细账!$C$2),N(V34)+1,N(V34)) -> 0 | W35: =IF($H35<>"","项目成本",IFERROR(INDEX(基础资料!$W$4:$W$49,MATCH($I35,基础资料!$V$4:$V$49,0)),"")) -> 人工社保 | X35: =IFERROR(INDEX(基础资料!$R$4:$R$17,MATCH($G35,基础资料!$Q$4:$Q$17,0)),"")
A36: =IF($B36="","",COUNTA($B$5:$B36)) -> 32 | B36: 46036 | C36: 双思威基本户 | D36: =IFERROR(INDEX(基础资料!$F$4:$F$23,MATCH($C36,基础资料!$E$4:$E$23,0)),IF($C36="","","未匹配账户")) -> 双思威 | E36: 支出 | I36: 工资 | J36: 付席科工资 | L36: 3157.61 | M36: =IFERROR(VLOOKUP($C36,$C$5:$M$24,11,0)+SUMIF($C$25:$C36,$C36,$K$25:$K36)-SUMIF($C$25:$C36,$C36,$L$25:$L36),"") -> 1783820.3 | R36: 示例：由2026年6月原表导入 | S36: =IF($B36="","",--TEXT($B36,"yyyymm")) -> 202601 | T36: =IF($B36="","",IF($P36="",$S36,IFERROR($P36*1,$P36))) -> 202601 | U36: =IF($B36="","",IF($T36=$S36,"","跨期")) | V36: =IF(AND($B36<>"",$F36<>"",$F36=项目明细账!$C$2),N(V35)+1,N(V35)) -> 0 | W36: =IF($H36<>"","项目成本",IFERROR(INDEX(基础资料!$W$4:$W$49,MATCH($I36,基础资料!$V$4:$V$49,0)),"")) -> 人工社保 | X36: =IFERROR(INDEX(基础资料!$R$4:$R$17,MATCH($G36,基础资料!$Q$4:$Q$17,0)),"")
A37: =IF($B37="","",COUNTA($B$5:$B37)) -> 33 | B37: 46036 | C37: 双思威基本户 | D37: =IFERROR(INDEX(基础资料!$F$4:$F$23,MATCH($C37,基础资料!$E$4:$E$23,0)),IF($C37="","","未匹配账户")) -> 双思威 | E37: 支出 | I37: 工资 | J37: 付高愉工资 | L37: 3152.48 | M37: =IFERROR(VLOOKUP($C37,$C$5:$M$24,11,0)+SUMIF($C$25:$C37,$C37,$K$25:$K37)-SUMIF($C$25:$C37,$C37,$L$25:$L37),"") -> 1780667.8 | R37: 示例：由2026年6月原表导入 | S37: =IF($B37="","",--TEXT($B37,"yyyymm")) -> 202601 | T37: =IF($B37="","",IF($P37="",$S37,IFERROR($P37*1,$P37))) -> 202601 | U37: =IF($B37="","",IF($T37=$S37,"","跨期")) | V37: =IF(AND($B37<>"",$F37<>"",$F37=项目明细账!$C$2),N(V36)+1,N(V36)) -> 0 | W37: =IF($H37<>"","项目成本",IFERROR(INDEX(基础资料!$W$4:$W$49,MATCH($I37,基础资料!$V$4:$V$49,0)),"")) -> 人工社保 | X37: =IFERROR(INDEX(基础资料!$R$4:$R$17,MATCH($G37,基础资料!$Q$4:$Q$17,0)),"")
A38: =IF($B38="","",COUNTA($B$5:$B38)) -> 34 | B38: 46036 | C38: 双思威基本户 | D38: =IFERROR(INDEX(基础资料!$F$4:$F$23,MATCH($C38,基础资料!$E$4:$E$23,0)),IF($C38="","","未匹配账户")) -> 双思威 | E38: 支出 | I38: 工资 | J38: 付张宝婷工资 | L38: 6677.12 | M38: =IFERROR(VLOOKUP($C38,$C$5:$M$24,11,0)+SUMIF($C$25:$C38,$C38,$K$25:$K38)-SUMIF($C$25:$C38,$C38,$L$25:$L38),"") -> 1773990.7 | R38: 示例：由2026年6月原表导入 | S38: =IF($B38="","",--TEXT($B38,"yyyymm")) -> 202601 | T38: =IF($B38="","",IF($P38="",$S38,IFERROR($P38*1,$P38))) -> 202601 | U38: =IF($B38="","",IF($T38=$S38,"","跨期")) | V38: =IF(AND($B38<>"",$F38<>"",$F38=项目明细账!$C$2),N(V37)+1,N(V37)) -> 0 | W38: =IF($H38<>"","项目成本",IFERROR(INDEX(基础资料!$W$4:$W$49,MATCH($I38,基础资料!$V$4:$V$49,0)),"")) -> 人工社保 | X38: =IFERROR(INDEX(基础资料!$R$4:$R$17,MATCH($G38,基础资料!$Q$4:$Q$17,0)),"")
A39: =IF($B39="","",COUNTA($B$5:$B39)) -> 35 | B39: 46036 | C39: 双思威基本户 | D39: =IFERROR(INDEX(基础资料!$F$4:$F$23,MATCH($C39,基础资料!$E$4:$E$23,0)),IF($C39="","","未匹配账户")) -> 双思威 | E39: 支出 | I39: 工资 | J39: 付何春华工资 | L39: 2657.61 | M39: =IFERROR(VLOOKUP($C39,$C$5:$M$24,11,0)+SUMIF($C$25:$C39,$C39,$K$25:$K39)-SUMIF($C$25:$C39,$C39,$L$25:$L39),"") -> 1771333.1 | R39: 示例：由2026年6月原表导入 | S39: =IF($B39="","",--TEXT($B39,"yyyymm")) -> 202601 | T39: =IF($B39="","",IF($P39="",$S39,IFERROR($P39*1,$P39))) -> 202601 | U39: =IF($B39="","",IF($T39=$S39,"","跨期")) | V39: =IF(AND($B39<>"",$F39<>"",$F39=项目明细账!$C$2),N(V38)+1,N(V38)) -> 0 | W39: =IF($H39<>"","项目成本",IFERROR(INDEX(基础资料!$W$4:$W$49,MATCH($I39,基础资料!$V$4:$V$49,0)),"")) -> 人工社保 | X39: =IFERROR(INDEX(基础资料!$R$4:$R$17,MATCH($G39,基础资料!$Q$4:$Q$17,0)),"")
A40: =IF($B40="","",COUNTA($B$5:$B40)) -> 36 | B40: 46036 | C40: 双思威基本户 | D40: =IFERROR(INDEX(基础资料!$F$4:$F$23,MATCH($C40,基础资料!$E$4:$E$23,0)),IF($C40="","","未匹配账户")) -> 双思威 | E40: 支出 | I40: 工资 | J40: 付陈垒工资 | L40: 2657.61 | M40: =IFERROR(VLOOKUP($C40,$C$5:$M$24,11,0)+SUMIF($C$25:$C40,$C40,$K$25:$K40)-SUMIF($C$25:$C40,$C40,$L$25:$L40),"") -> 1768675.4 | R40: 示例：由2026年6月原表导入 | S40: =IF($B40="","",--TEXT($B40,"yyyymm")) -> 202601 | T40: =IF($B40="","",IF($P40="",$S40,IFERROR($P40*1,$P40))) -> 202601 | U40: =IF($B40="","",IF($T40=$S40,"","跨期")) | V40: =IF(AND($B40<>"",$F40<>"",$F40=项目明细账!$C$2),N(V39)+1,N(V39)) -> 0 | W40: =IF($H40<>"","项目成本",IFERROR(INDEX(基础资料!$W$4:$W$49,MATCH($I40,基础资料!$V$4:$V$49,0)),"")) -> 人工社保 | X40: =IFERROR(INDEX(基础资料!$R$4:$R$17,MATCH($G40,基础资料!$Q$4:$Q$17,0)),"")
A41: =IF($B41="","",COUNTA($B$5:$B41)) -> 37 | B41: 46036 | C41: 双思威基本户 | D41: =IFERROR(INDEX(基础资料!$F$4:$F$23,MATCH($C41,基础资料!$E$4:$E$23,0)),IF($C41="","","未匹配账户")) -> 双思威 | E41: 支出 | I41: 工资 | J41: 付叶创将工资 | L41: 2757.61 | M41: =IFERROR(VLOOKUP($C41,$C$5:$M$24,11,0)+SUMIF($C$25:$C41,$C41,$K$25:$K41)-SUMIF($C$25:$C41,$C41,$L$25:$L41),"") -> 1765917.8 | R41: 示例：由2026年6月原表导入 | S41: =IF($B41="","",--TEXT($B41,"yyyymm")) -> 202601 | T41: =IF($B41="","",IF($P41="",$S41,IFERROR($P41*1,$P41))) -> 202601 | U41: =IF($B41="","",IF($T41=$S41,"","跨期")) | V41: =IF(AND($B41<>"",$F41<>"",$F41=项目明细账!$C$2),N(V40)+1,N(V40)) -> 0 | W41: =IF($H41<>"","项目成本",IFERROR(INDEX(基础资料!$W$4:$W$49,MATCH($I41,基础资料!$V$4:$V$49,0)),"")) -> 人工社保 | X41: =IFERROR(INDEX(基础资料!$R$4:$R$17,MATCH($G41,基础资料!$Q$4:$Q$17,0)),"")
A42: =IF($B42="","",COUNTA($B$5:$B42)) -> 38 | B42: 46036 | C42: 双思威基本户 | D42: =IFERROR(INDEX(基础资料!$F$4:$F$23,MATCH($C42,基础资料!$E$4:$E$23,0)),IF($C42="","","未匹配账户")) -> 双思威 | E42: 支出 | I42: 工资 | J42: 付侯云霞工资 | L42: 1500 | M42: =IFERROR(VLOOKUP($C42,$C$5:$M$24,11,0)+SUMIF($C$25:$C42,$C42,$K$25:$K42)-SUMIF($C$25:$C42,$C42,$L$25:$L42),"") -> 1764417.8 | R42: 示例：由2026年6月原表导入 | S42: =IF($B42="","",--TEXT($B42,"yyyymm")) -> 202601 | T42: =IF($B42="","",IF($P42="",$S42,IFERROR($P42*1,$P42))) -> 202601 | U42: =IF($B42="","",IF($T42=$S42,"","跨期")) | V42: =IF(AND($B42<>"",$F42<>"",$F42=项目明细账!$C$2),N(V41)+1,N(V41)) -> 0 | W42: =IF($H42<>"","项目成本",IFERROR(INDEX(基础资料!$W$4:$W$49,MATCH($I42,基础资料!$V$4:$V$49,0)),"")) -> 人工社保 | X42: =IFERROR(INDEX(基础资料!$R$4:$R$17,MATCH($G42,基础资料!$Q$4:$Q$17,0)),"")
... A56: =IF($B56="","",COUNTA($B$5:$B56)) -> 52 | B56: 46036 | C56: 双思威基本户 | D56: =IFERROR(INDEX(基础资料!$F$4:$F$23,MATCH($C56,基础资料!$E$4:$E$23,0)),IF($C56="","","未匹配账户")) -> 双思威 | E56: 支出 | I56: 工资 | J56: 付叶创将业务执行费 | L56: 1700 | M56: =IFERROR(VLOOKUP($C56,$C$5:$M$24,11,0)+SUMIF($C$25:$C56,$C56,$K$25:$K56)-SUMIF($C$25:$C56,$C56,$L$25:$L56),"") -> 1740349.8 | R56: 示例：由2026年6月原表导入 | S56: =IF($B56="","",--TEXT($B56,"yyyymm")) -> 202601 | T56: =IF($B56="","",IF($P56="",$S56,IFERROR($P56*1,$P56))) -> 202601 | U56: =IF($B56="","",IF($T56=$S56,"","跨期")) | V56: =IF(AND($B56<>"",$F56<>"",$F56=项目明细账!$C$2),N(V55)+1,N(V55)) -> 0 | W56: =IF($H56<>"","项目成本",IFERROR(INDEX(基础资料!$W$4:$W$49,MATCH($I56,基础资料!$V$4:$V$49,0)),"")) -> 人工社保 | X56: =IFERROR(INDEX(基础资料!$R$4:$R$17,MATCH($G56,基础资料!$Q$4:$Q$17,0)),"")
A57: =IF($B57="","",COUNTA($B$5:$B57)) -> 53 | B57: 46036 | C57: 双思威基本户 | D57: =IFERROR(INDEX(基础资料!$F$4:$F$23,MATCH($C57,基础资料!$E$4:$E$23,0)),IF($C57="","","未匹配账户")) -> 双思威 | E57: 支出 | I57: 工资 | J57: 付邱雅静业务执行费 | L57: 1200 | M57: =IFERROR(VLOOKUP($C57,$C$5:$M$24,11,0)+SUMIF($C$25:$C57,$C57,$K$25:$K57)-SUMIF($C$25:$C57,$C57,$L$25:$L57),"") -> 1739149.8 | O57: 供应商1 | R57: 示例：由2026年6月原表导入 | S57: =IF($B57="","",--TEXT($B57,"yyyymm")) -> 202601 | T57: =IF($B57="","",IF($P57="",$S57,IFERROR($P57*1,$P57))) -> 202601 | U57: =IF($B57="","",IF($T57=$S57,"","跨期")) | V57: =IF(AND($B57<>"",$F57<>"",$F57=项目明细账!$C$2),N(V56)+1,N(V56)) -> 0 | W57: =IF($H57<>"","项目成本",IFERROR(INDEX(基础资料!$W$4:$W$49,MATCH($I57,基础资料!$V$4:$V$49,0)),"")) -> 人工社保 | X57: =IFERROR(INDEX(基础资料!$R$4:$R$17,MATCH($G57,基础资料!$Q$4:$Q$17,0)),"")
A58: =IF($B58="","",COUNTA($B$5:$B58)) -> 54 | B58: 46036 | C58: 双思威基本户 | D58: =IFERROR(INDEX(基础资料!$F$4:$F$23,MATCH($C58,基础资料!$E$4:$E$23,0)),IF($C58="","","未匹配账户")) -> 双思威 | E58: 支出 | I58: 工资 | J58: 付戚盈丽业务执行费 | L58: 600 | M58: =IFERROR(VLOOKUP($C58,$C$5:$M$24,11,0)+SUMIF($C$25:$C58,$C58,$K$25:$K58)-SUMIF($C$25:$C58,$C58,$L$25:$L58),"") -> 1738549.8 | O58: 供应商1 | R58: 示例：由2026年6月原表导入 | S58: =IF($B58="","",--TEXT($B58,"yyyymm")) -> 202601 | T58: =IF($B58="","",IF($P58="",$S58,IFERROR($P58*1,$P58))) -> 202601 | U58: =IF($B58="","",IF($T58=$S58,"","跨期")) | V58: =IF(AND($B58<>"",$F58<>"",$F58=项目明细账!$C$2),N(V57)+1,N(V57)) -> 0 | W58: =IF($H58<>"","项目成本",IFERROR(INDEX(基础资料!$W$4:$W$49,MATCH($I58,基础资料!$V$4:$V$49,0)),"")) -> 人工社保 | X58: =IFERROR(INDEX(基础资料!$R$4:$R$17,MATCH($G58,基础资料!$Q$4:$Q$17,0)),"")
A59: =IF($B59="","",COUNTA($B$5:$B59)) -> 55 | B59: 46036 | C59: 双思威基本户 | D59: =IFERROR(INDEX(基础资料!$F$4:$F$23,MATCH($C59,基础资料!$E$4:$E$23,0)),IF($C59="","","未匹配账户")) -> 双思威 | E59: 支出 | I59: 工资 | J59: 付陈冬梅业务执行费 | L59: 1168.59 | M59: =IFERROR(VLOOKUP($C59,$C$5:$M$24,11,0)+SUMIF($C$25:$C59,$C59,$K$25:$K59)-SUMIF($C$25:$C59,$C59,$L$25:$L59),"") -> 1737381.2 | O59: 供应商1 | R59: 示例：由2026年6月原表导入 | S59: =IF($B59="","",--TEXT($B59,"yyyymm")) -> 202601 | T59: =IF($B59="","",IF($P59="",$S59,IFERROR($P59*1,$P59))) -> 202601 | U59: =IF($B59="","",IF($T59=$S59,"","跨期")) | V59: =IF(AND($B59<>"",$F59<>"",$F59=项目明细账!$C$2),N(V58)+1,N(V58)) -> 0 | W59: =IF($H59<>"","项目成本",IFERROR(INDEX(基础资料!$W$4:$W$49,MATCH($I59,基础资料!$V$4:$V$49,0)),"")) -> 人工社保 | X59: =IFERROR(INDEX(基础资料!$R$4:$R$17,MATCH($G59,基础资料!$Q$4:$Q$17,0)),"")
A60: =IF($B60="","",COUNTA($B$5:$B60)) -> 56 | B60: 46036 | C60: 双思威基本户 | D60: =IFERROR(INDEX(基础资料!$F$4:$F$23,MATCH($C60,基础资料!$E$4:$E$23,0)),IF($C60="","","未匹配账户")) -> 双思威 | E60: 支出 | I60: 工资 | J60: 付钟苗业务执行费 | L60: 1000 | M60: =IFERROR(VLOOKUP($C60,$C$5:$M$24,11,0)+SUMIF($C$25:$C60,$C60,$K$25:$K60)-SUMIF($C$25:$C60,$C60,$L$25:$L60),"") -> 1736381.2 | O60: 供应商2 | R60: 示例：由2026年6月原表导入 | S60: =IF($B60="","",--TEXT($B60,"yyyymm")) -> 202601 | T60: =IF($B60="","",IF($P60="",$S60,IFERROR($P60*1,$P60))) -> 202601 | U60: =IF($B60="","",IF($T60=$S60,"","跨期")) | V60: =IF(AND($B60<>"",$F60<>"",$F60=项目明细账!$C$2),N(V59)+1,N(V59)) -> 0 | W60: =IF($H60<>"","项目成本",IFERROR(INDEX(基础资料!$W$4:$W$49,MATCH($I60,基础资料!$V$4:$V$49,0)),"")) -> 人工社保 | X60: =IFERROR(INDEX(基础资料!$R$4:$R$17,MATCH($G60,基础资料!$Q$4:$Q$17,0)),"")
A61: =IF($B61="","",COUNTA($B$5:$B61)) -> 57 | B61: 46036 | C61: 双思威基本户 | D61: =IFERROR(INDEX(基础资料!$F$4:$F$23,MATCH($C61,基础资料!$E$4:$E$23,0)),IF($C61="","","未匹配账户")) -> 双思威 | E61: 支出 | I61: 工资 | J61: 付吴佳慧业务执行费 | L61: 1500 | M61: =IFERROR(VLOOKUP($C61,$C$5:$M$24,11,0)+SUMIF($C$25:$C61,$C61,$K$25:$K61)-SUMIF($C$25:$C61,$C61,$L$25:$L61),"") -> 1734881.2 | O61: 供应商2 | R61: 示例：由2026年6月原表导入 | S61: =IF($B61="","",--TEXT($B61,"yyyymm")) -> 202601 | T61: =IF($B61="","",IF($P61="",$S61,IFERROR($P61*1,$P61))) -> 202601 | U61: =IF($B61="","",IF($T61=$S61,"","跨期")) | V61: =IF(AND($B61<>"",$F61<>"",$F61=项目明细账!$C$2),N(V60)+1,N(V60)) -> 0 | W61: =IF($H61<>"","项目成本",IFERROR(INDEX(基础资料!$W$4:$W$49,MATCH($I61,基础资料!$V$4:$V$49,0)),"")) -> 人工社保 | X61: =IFERROR(INDEX(基础资料!$R$4:$R$17,MATCH($G61,基础资料!$Q$4:$Q$17,0)),"")
A62: =IF($B62="","",COUNTA($B$5:$B62)) -> 58 | B62: 46042 | C62: 双思威基本户 | D62: =IFERROR(INDEX(基础资料!$F$4:$F$23,MATCH($C62,基础资料!$E$4:$E$23,0)),IF($C62="","","未匹配账户")) -> 双思威 | E62: 支出 | I62: 企业所得税 | J62: 缴纳所得税 | L62: 3653.4 | M62: =IFERROR(VLOOKUP($C62,$C$5:$M$24,11,0)+SUMIF($C$25:$C62,$C62,$K$25:$K62)-SUMIF($C$25:$C62,$C62,$L$25:$L62),"") -> 1731227.8 | O62: 供应商1 | R62: 示例：由2026年6月原表导入 | S62: =IF($B62="","",--TEXT($B62,"yyyymm")) -> 202601 | T62: =IF($B62="","",IF($P62="",$S62,IFERROR($P62*1,$P62))) -> 202601 | U62: =IF($B62="","",IF($T62=$S62,"","跨期")) | V62: =IF(AND($B62<>"",$F62<>"",$F62=项目明细账!$C$2),N(V61)+1,N(V61)) -> 0 | W62: =IF($H62<>"","项目成本",IFERROR(INDEX(基础资料!$W$4:$W$49,MATCH($I62,基础资料!$V$4:$V$49,0)),"")) -> 税费 | X62: =IFERROR(INDEX(基础资料!$R$4:$R$17,MATCH($G62,基础资料!$Q$4:$Q$17,0)),"")
A63: =IF($B63="","",COUNTA($B$5:$B63)) -> 59 | B63: 46042 | C63: 双思威基本户 | D63: =IFERROR(INDEX(基础资料!$F$4:$F$23,MATCH($C63,基础资料!$E$4:$E$23,0)),IF($C63="","","未匹配账户")) -> 双思威 | E63: 支出 | J63: 缴纳工会经费 | L63: 1654.37 | M63: =IFERROR(VLOOKUP($C63,$C$5:$M$24,11,0)+SUMIF($C$25:$C63,$C63,$K$25:$K63)-SUMIF($C$25:$C63,$C63,$L$25:$L63),"") -> 1729573.4 | O63: 供应商1 | R63: 示例：由2026年6月原表导入 | S63: =IF($B63="","",--TEXT($B63,"yyyymm")) -> 202601 | T63: =IF($B63="","",IF($P63="",$S63,IFERROR($P63*1,$P63))) -> 202601 | U63: =IF($B63="","",IF($T63=$S63,"","跨期")) | V63: =IF(AND($B63<>"",$F63<>"",$F63=项目明细账!$C$2),N(V62)+1,N(V62)) -> 0 | W63: =IF($H63<>"","项目成本",IFERROR(INDEX(基础资料!$W$4:$W$49,MATCH($I63,基础资料!$V$4:$V$49,0)),"")) | X63: =IFERROR(INDEX(基础资料!$R$4:$R$17,MATCH($G63,基础资料!$Q$4:$Q$17,0)),"")
A64: =IF($B64="","",COUNTA($B$5:$B64)) -> 60 | B64: 46042 | C64: 双思威基本户 | D64: =IFERROR(INDEX(基础资料!$F$4:$F$23,MATCH($C64,基础资料!$E$4:$E$23,0)),IF($C64="","","未匹配账户")) -> 双思威 | E64: 支出 | I64: 增值税 | J64: 缴纳增值税 | L64: 8022.84 | M64: =IFERROR(VLOOKUP($C64,$C$5:$M$24,11,0)+SUMIF($C$25:$C64,$C64,$K$25:$K64)-SUMIF($C$25:$C64,$C64,$L$25:$L64),"") -> 1721550.6 | R64: 示例：由2026年6月原表导入 | S64: =IF($B64="","",--TEXT($B64,"yyyymm")) -> 202601 | T64: =IF($B64="","",IF($P64="",$S64,IFERROR($P64*1,$P64))) -> 202601 | U64: =IF($B64="","",IF($T64=$S64,"","跨期")) | V64: =IF(AND($B64<>"",$F64<>"",$F64=项目明细账!$C$2),N(V63)+1,N(V63)) -> 0 | W64: =IF($H64<>"","项目成本",IFERROR(INDEX(基础资料!$W$4:$W$49,MATCH($I64,基础资料!$V$4:$V$49,0)),"")) -> 税费 | X64: =IFERROR(INDEX(基础资料!$R$4:$R$17,MATCH($G64,基础资料!$Q$4:$Q$17,0)),"")
A65: =IF($B65="","",COUNTA($B$5:$B65)) -> 61 | B65: 46042 | C65: 双思威基本户 | D65: =IFERROR(INDEX(基础资料!$F$4:$F$23,MATCH($C65,基础资料!$E$4:$E$23,0)),IF($C65="","","未匹配账户")) -> 双思威 | E65: 支出 | I65: 附加税 | J65: 缴纳附加税 | L65: 481.37 | M65: =IFERROR(VLOOKUP($C65,$C$5:$M$24,11,0)+SUMIF($C$25:$C65,$C65,$K$25:$K65)-SUMIF($C$25:$C65,$C65,$L$25:$L65),"") -> 1721069.2 | R65: 示例：由2026年6月原表导入 | S65: =IF($B65="","",--TEXT($B65,"yyyymm")) -> 202601 | T65: =IF($B65="","",IF($P65="",$S65,IFERROR($P65*1,$P65))) -> 202601 | U65: =IF($B65="","",IF($T65=$S65,"","跨期")) | V65: =IF(AND($B65<>"",$F65<>"",$F65=项目明细账!$C$2),N(V64)+1,N(V64)) -> 0 | W65: =IF($H65<>"","项目成本",IFERROR(INDEX(基础资料!$W$4:$W$49,MATCH($I65,基础资料!$V$4:$V$49,0)),"")) -> 税费 | X65: =IFERROR(INDEX(基础资料!$R$4:$R$17,MATCH($G65,基础资料!$Q$4:$Q$17,0)),"")
A66: =IF($B66="","",COUNTA($B$5:$B66)) -> 62 | B66: 46042 | C66: 双思威基本户 | D66: =IFERROR(INDEX(基础资料!$F$4:$F$23,MATCH($C66,基础资料!$E$4:$E$23,0)),IF($C66="","","未匹配账户")) -> 双思威 | E66: 支出 | I66: 印花税 | J66: 缴纳印花税 | L66: 2753.62 | M66: =IFERROR(VLOOKUP($C66,$C$5:$M$24,11,0)+SUMIF($C$25:$C66,$C66,$K$25:$K66)-SUMIF($C$25:$C66,$C66,$L$25:$L66),"") -> 1718315.6 | R66: 示例：由2026年6月原表导入 | S66: =IF($B66="","",--TEXT($B66,"yyyymm")) -> 202601 | T66: =IF($B66="","",IF($P66="",$S66,IFERROR($P66*1,$P66))) -> 202601 | U66: =IF($B66="","",IF($T66=$S66,"","跨期")) | V66: =IF(AND($B66<>"",$F66<>"",$F66=项目明细账!$C$2),N(V65)+1,N(V65)) -> 0 | W66: =IF($H66<>"","项目成本",IFERROR(INDEX(基础资料!$W$4:$W$49,MATCH($I66,基础资料!$V$4:$V$49,0)),"")) -> 税费 | X66: =IFERROR(INDEX(基础资料!$R$4:$R$17,MATCH($G66,基础资料!$Q$4:$Q$17,0)),"")
A67: =IF($B67="","",COUNTA($B$5:$B67)) -> 63 | B67: 46042 | C67: 双思威基本户 | D67: =IFERROR(INDEX(基础资料!$F$4:$F$23,MATCH($C67,基础资料!$E$4:$E$23,0)),IF($C67="","","未匹配账户")) -> 双思威 | E67: 支出 | I67: 印花税 | J67: 缴纳印花税 | L67: 34.21 | M67: =IFERROR(VLOOKUP($C67,$C$5:$M$24,11,0)+SUMIF($C$25:$C67,$C67,$K$25:$K67)-SUMIF($C$25:$C67,$C67,$L$25:$L67),"") -> 1718281.4 | O67: 供应商3 | R67: 示例：由2026年6月原表导入 | S67: =IF($B67="","",--TEXT($B67,"yyyymm")) -> 202601 | T67: =IF($B67="","",IF($P67="",$S67,IFERROR($P67*1,$P67))) -> 202601 | U67: =IF($B67="","",IF($T67=$S67,"","跨期")) | V67: =IF(AND($B67<>"",$F67<>"",$F67=项目明细账!$C$2),N(V66)+1,N(V66)) -> 0 | W67: =IF($H67<>"","项目成本",IFERROR(INDEX(基础资料!$W$4:$W$49,MATCH($I67,基础资料!$V$4:$V$49,0)),"")) -> 税费 | X67: =IFERROR(INDEX(基础资料!$R$4:$R$17,MATCH($G67,基础资料!$Q$4:$Q$17,0)),"")
A68: =IF($B68="","",COUNTA($B$5:$B68)) -> 64 | B68: 46044 | C68: 双思威基本户 | D68: =IFERROR(INDEX(基础资料!$F$4:$F$23,MATCH($C68,基础资料!$E$4:$E$23,0)),IF($C68="","","未匹配账户")) -> 双思威 | E68: 支出 | I68: 银行手续费 | J68: 付款手续费 | L68: 9 | M68: =IFERROR(VLOOKUP($C68,$C$5:$M$24,11,0)+SUMIF($C$25:$C68,$C68,$K$25:$K68)-SUMIF($C$25:$C68,$C68,$L$25:$L68),"") -> 1718272.4 | O68: 供应商1 | R68: 示例：由2026年6月原表导入 | S68: =IF($B68="","",--TEXT($B68,"yyyymm")) -> 202601 | T68: =IF($B68="","",IF($P68="",$S68,IFERROR($P68*1,$P68))) -> 202601 | U68: =IF($B68="","",IF($T68=$S68,"","跨期")) | V68: =IF(AND($B68<>"",$F68<>"",$F68=项目明细账!$C$2),N(V67)+1,N(V67)) -> 0 | W68: =IF($H68<>"","项目成本",IFERROR(INDEX(基础资料!$W$4:$W$49,MATCH($I68,基础资料!$V$4:$V$49,0)),"")) -> 财务费用 | X68: =IFERROR(INDEX(基础资料!$R$4:$R$17,MATCH($G68,基础资料!$Q$4:$Q$17,0)),"")
A69: =IF($B69="","",COUNTA($B$5:$B69)) -> 65 | B69: 46045 | C69: 双思威基本户 | D69: =IFERROR(INDEX(基础资料!$F$4:$F$23,MATCH($C69,基础资料!$E$4:$E$23,0)),IF($C69="","","未匹配账户")) -> 双思威 | E69: 支出 | I69: 养老保险 | J69: 缴纳养老保险 | L69: 20703.73 | M69: =IFERROR(VLOOKUP($C69,$C$5:$M$24,11,0)+SUMIF($C$25:$C69,$C69,$K$25:$K69)-SUMIF($C$25:$C69,$C69,$L$25:$L69),"") -> 1697568.6 | O69: 供应商1 | R69: 示例：由2026年6月原表导入 | S69: =IF($B69="","",--TEXT($B69,"yyyymm")) -> 202601 | T69: =IF($B69="","",IF($P69="",$S69,IFERROR($P69*1,$P69))) -> 202601 | U69: =IF($B69="","",IF($T69=$S69,"","跨期")) | V69: =IF(AND($B69<>"",$F69<>"",$F69=项目明细账!$C$2),N(V68)+1,N(V68)) -> 0 | W69: =IF($H69<>"","项目成本",IFERROR(INDEX(基础资料!$W$4:$W$49,MATCH($I69,基础资料!$V$4:$V$49,0)),"")) -> 人工社保 | X69: =IFERROR(INDEX(基础资料!$R$4:$R$17,MATCH($G69,基础资料!$Q$4:$Q$17,0)),"")
A70: =IF($B70="","",COUNTA($B$5:$B70)) -> 66 | B70: 46045 | C70: 双思威基本户 | D70: =IFERROR(INDEX(基础资料!$F$4:$F$23,MATCH($C70,基础资料!$E$4:$E$23,0)),IF($C70="","","未匹配账户")) -> 双思威 | E70: 支出 | I70: 医疗保险 | J70: 缴纳医疗保险 | L70: 9637.29 | M70: =IFERROR(VLOOKUP($C70,$C$5:$M$24,11,0)+SUMIF($C$25:$C70,$C70,$K$25:$K70)-SUMIF($C$25:$C70,$C70,$L$25:$L70),"") -> 1687931.4 | O70: 供应商4 | R70: 示例：由2026年6月原表导入 | S70: =IF($B70="","",--TEXT($B70,"yyyymm")) -> 202601 | T70: =IF($B70="","",IF($P70="",$S70,IFERROR($P70*1,$P70))) -> 202601 | U70: =IF($B70="","",IF($T70=$S70,"","跨期")) | V70: =IF(AND($B70<>"",$F70<>"",$F70=项目明细账!$C$2),N(V69)+1,N(V69)) -> 0 | W70: =IF($H70<>"","项目成本",IFERROR(INDEX(基础资料!$W$4:$W$49,MATCH($I70,基础资料!$V$4:$V$49,0)),"")) -> 人工社保 | X70: =IFERROR(INDEX(基础资料!$R$4:$R$17,MATCH($G70,基础资料!$Q$4:$Q$17,0)),"")
A71: =IF($B71="","",COUNTA($B$5:$B71)) -> 67 | B71: 46049 | C71: 双思威基本户 | D71: =IFERROR(INDEX(基础资料!$F$4:$F$23,MATCH($C71,基础资料!$E$4:$E$23,0)),IF($C71="","","未匹配账户")) -> 双思威 | E71: 支出 | I71: 银行手续费 | J71: 付款手续费 | L71: 4.5 | M71: =IFERROR(VLOOKUP($C71,$C$5:$M$24,11,0)+SUMIF($C$25:$C71,$C71,$K$25:$K71)-SUMIF($C$25:$C71,$C71,$L$25:$L71),"") -> 1687926.9 | R71: 示例：由2026年6月原表导入 | S71: =IF($B71="","",--TEXT($B71,"yyyymm")) -> 202601 | T71: =IF($B71="","",IF($P71="",$S71,IFERROR($P71*1,$P71))) -> 202601 | U71: =IF($B71="","",IF($T71=$S71,"","跨期")) | V71: =IF(AND($B71<>"",$F71<>"",$F71=项目明细账!$C$2),N(V70)+1,N(V70)) -> 0 | W71: =IF($H71<>"","项目成本",IFERROR(INDEX(基础资料!$W$4:$W$49,MATCH($I71,基础资料!$V$4:$V$49,0)),"")) -> 财务费用 | X71: =IFERROR(INDEX(基础资料!$R$4:$R$17,MATCH($G71,基础资料!$Q$4:$Q$17,0)),"")
A72: =IF($B72="","",COUNTA($B$5:$B72)) -> 68 | B72: 46049 | C72: 双思威基本户 | D72: =IFERROR(INDEX(基础资料!$F$4:$F$23,MATCH($C72,基础资料!$E$4:$E$23,0)),IF($C72="","","未匹配账户")) -> 双思威 | E72: 支出 | I72: 银行手续费 | J72: 付款手续费 | L72: 4.5 | M72: =IFERROR(VLOOKUP($C72,$C$5:$M$24,11,0)+SUMIF($C$25:$C72,$C72,$K$25:$K72)-SUMIF($C$25:$C72,$C72,$L$25:$L72),"") -> 1687922.4 | R72: 示例：由2026年6月原表导入 | S72: =IF($B72="","",--TEXT($B72,"yyyymm")) -> 202601 | T72: =IF($B72="","",IF($P72="",$S72,IFERROR($P72*1,$P72))) -> 202601 | U72: =IF($B72="","",IF($T72=$S72,"","跨期")) | V72: =IF(AND($B72<>"",$F72<>"",$F72=项目明细账!$C$2),N(V71)+1,N(V71)) -> 0 | W72: =IF($H72<>"","项目成本",IFERROR(INDEX(基础资料!$W$4:$W$49,MATCH($I72,基础资料!$V$4:$V$49,0)),"")) -> 财务费用 | X72: =IFERROR(INDEX(基础资料!$R$4:$R$17,MATCH($G72,基础资料!$Q$4:$Q$17,0)),"")
A73: =IF($B73="","",COUNTA($B$5:$B73)) -> 69 | B73: 46024 | C73: 双思威农商行一般户 | D73: =IFERROR(INDEX(基础资料!$F$4:$F$23,MATCH($C73,基础资料!$E$4:$E$23,0)),IF($C73="","","未匹配账户")) -> 双思威 | E73: 支出 | I73: 保险费 | J73: 付中国平安财产保险股份有限公司乌鲁木齐中心支公司车保险 | L73: 4715 | M73: =IFERROR(VLOOKUP($C73,$C$5:$M$24,11,0)+SUMIF($C$25:$C73,$C73,$K$25:$K73)-SUMIF($C$25:$C73,$C73,$L$25:$L73),"") -> 4114006.1 | R73: 示例：由2026年6月原表导入 | S73: =IF($B73="","",--TEXT($B73,"yyyymm")) -> 202601 | T73: =IF($B73="","",IF($P73="",$S73,IFERROR($P73*1,$P73))) -> 202601 | U73: =IF($B73="","",IF($T73=$S73,"","跨期")) | V73: =IF(AND($B73<>"",$F73<>"",$F73=项目明细账!$C$2),N(V72)+1,N(V72)) -> 0 | W73: =IF($H73<>"","项目成本",IFERROR(INDEX(基础资料!$W$4:$W$49,MATCH($I73,基础资料!$V$4:$V$49,0)),"")) -> 管理费用 | X73: =IFERROR(INDEX(基础资料!$R$4:$R$17,MATCH($G73,基础资料!$Q$4:$Q$17,0)),"")
A74: =IF($B74="","",COUNTA($B$5:$B74)) -> 70 | B74: 46025 | C74: 双思威农商行一般户 | D74: =IFERROR(INDEX(基础资料!$F$4:$F$23,MATCH($C74,基础资料!$E$4:$E$23,0)),IF($C74="","","未匹配账户")) -> 双思威 | E74: 支出 | F74: 昌吉市第二十一小学教育教学设备采购项目（三标段） | H74: 项目-材料 | J74: 付伊犁海智泓商贸有限公司空调 | L74: 5898 | M74: =IFERROR(VLOOKUP($C74,$C$5:$M$24,11,0)+SUMIF($C$25:$C74,$C74,$K$25:$K74)-SUMIF($C$25:$C74,$C74,$L$25:$L74),"") -> 4108108.1 | R74: 示例：由2026年6月原表导入 | S74: =IF($B74="","",--TEXT($B74,"yyyymm")) -> 202601 | T74: =IF($B74="","",IF($P74="",$S74,IFERROR($P74*1,$P74))) -> 202601 | U74: =IF($B74="","",IF($T74=$S74,"","跨期")) | V74: =IF(AND($B74<>"",$F74<>"",$F74=项目明细账!$C$2),N(V73)+1,N(V73)) -> 0 | W74: =IF($H74<>"","项目成本",IFERROR(INDEX(基础资料!$W$4:$W$49,MATCH($I74,基础资料!$V$4:$V$49,0)),"")) -> 项目成本 | X74: =IFERROR(INDEX(基础资料!$R$4:$R$17,MATCH($G74,基础资料!$Q$4:$Q$17,0)),"")
A75: =IF($B75="","",COUNTA($B$5:$B75)) -> 71 | B75: 46026 | C75: 双思威农商行一般户 | D75: =IFERROR(INDEX(基础资料!$F$4:$F$23,MATCH($C75,基础资料!$E$4:$E$23,0)),IF($C75="","","未匹配账户")) -> 双思威 | E75: 支出 | I75: 伙食费 | J75: 付邱雅静报销款 | L75: 1845.66 | M75: =IFERROR(VLOOKUP($C75,$C$5:$M$24,11,0)+SUMIF($C$25:$C75,$C75,$K$25:$K75)-SUMIF($C$25:$C75,$C75,$L$25:$L75),"") -> 4106262.5 | R75: 示例：由2026年6月原表导入 | S75: =IF($B75="","",--TEXT($B75,"yyyymm")) -> 202601 | T75: =IF($B75="","",IF($P75="",$S75,IFERROR($P75*1,$P75))) -> 202601 | U75: =IF($B75="","",IF($T75=$S75,"","跨期")) | V75: =IF(AND($B75<>"",$F75<>"",$F75=项目明细账!$C$2),N(V74)+1,N(V74)) -> 0 | W75: =IF($H75<>"","项目成本",IFERROR(INDEX(基础资料!$W$4:$W$49,MATCH($I75,基础资料!$V$4:$V$49,0)),"")) -> 管理费用 | X75: =IFERROR(INDEX(基础资料!$R$4:$R$17,MATCH($G75,基础资料!$Q$4:$Q$17,0)),"")
A76: =IF($B76="","",COUNTA($B$5:$B76)) -> 72 | B76: 46027 | C76: 双思威农商行一般户 | D76: =IFERROR(INDEX(基础资料!$F$4:$F$23,MATCH($C76,基础资料!$E$4:$E$23,0)),IF($C76="","","未匹配账户")) -> 双思威 | E76: 支出 | F76: 新疆某单位教育教学设备（二标段）甄选项目-六中 | H76: 项目-材料 | J76: 付乌鲁木齐市盛兴隆商贸有限公司话筒线等 | L76: 6930 | M76: =IFERROR(VLOOKUP($C76,$C$5:$M$24,11,0)+SUMIF($C$25:$C76,$C76,$K$25:$K76)-SUMIF($C$25:$C76,$C76,$L$25:$L76),"") -> 4099332.5 | R76: 示例：由2026年6月原表导入 | S76: =IF($B76="","",--TEXT($B76,"yyyymm")) -> 202601 | T76: =IF($B76="","",IF($P76="",$S76,IFERROR($P76*1,$P76))) -> 202601 | U76: =IF($B76="","",IF($T76=$S76,"","跨期")) | V76: =IF(AND($B76<>"",$F76<>"",$F76=项目明细账!$C$2),N(V75)+1,N(V75)) -> 0 | W76: =IF($H76<>"","项目成本",IFERROR(INDEX(基础资料!$W$4:$W$49,MATCH($I76,基础资料!$V$4:$V$49,0)),"")) -> 项目成本 | X76: =IFERROR(INDEX(基础资料!$R$4:$R$17,MATCH($G76,基础资料!$Q$4:$Q$17,0)),"")
A77: =IF($B77="","",COUNTA($B$5:$B77)) -> 73 | B77: 46027 | C77: 双思威农商行一般户 | D77: =IFERROR(INDEX(基础资料!$F$4:$F$23,MATCH($C77,基础资料!$E$4:$E$23,0)),IF($C77="","","未匹配账户")) -> 双思威 | E77: 支出 | F77: 代建局昌吉市第十八小学教学仪器设备采购项目 | H77: 项目-材料 | J77: 付乌鲁木齐市盛兴隆商贸有限公司话筒 | L77: 1800 | M77: =IFERROR(VLOOKUP($C77,$C$5:$M$24,11,0)+SUMIF($C$25:$C77,$C77,$K$25:$K77)-SUMIF($C$25:$C77,$C77,$L$25:$L77),"") -> 4097532.5 | R77: 示例：由2026年6月原表导入 | S77: =IF($B77="","",--TEXT($B77,"yyyymm")) -> 202601 | T77: =IF($B77="","",IF($P77="",$S77,IFERROR($P77*1,$P77))) -> 202601 | U77: =IF($B77="","",IF($T77=$S77,"","跨期")) | V77: =IF(AND($B77<>"",$F77<>"",$F77=项目明细账!$C$2),N(V76)+1,N(V76)) -> 0 | W77: =IF($H77<>"","项目成本",IFERROR(INDEX(基础资料!$W$4:$W$49,MATCH($I77,基础资料!$V$4:$V$49,0)),"")) -> 项目成本 | X77: =IFERROR(INDEX(基础资料!$R$4:$R$17,MATCH($G77,基础资料!$Q$4:$Q$17,0)),"")
A78: =IF($B78="","",COUNTA($B$5:$B78)) -> 74 | B78: 46027 | C78: 双思威农商行一般户 | D78: =IFERROR(INDEX(基础资料!$F$4:$F$23,MATCH($C78,基础资料!$E$4:$E$23,0)),IF($C78="","","未匹配账户")) -> 双思威 | E78: 支出 | F78: 昌吉市四所幼儿园设备采购项目（三标段） | H78: 项目-材料 | J78: 付新疆佳誉创新电子商务有限公司打印机 | L78: 11900 | M78: =IFERROR(VLOOKUP($C78,$C$5:$M$24,11,0)+SUMIF($C$25:$C78,$C78,$K$25:$K78)-SUMIF($C$25:$C78,$C78,$L$25:$L78),"") -> 4085632.5 | O78: 供应商4 | R78: 示例：由2026年6月原表导入 | S78: =IF($B78="","",--TEXT($B78,"yyyymm")) -> 202601 | T78: =IF($B78="","",IF($P78="",$S78,IFERROR($P78*1,$P78))) -> 202601 | U78: =IF($B78="","",IF($T78=$S78,"","跨期")) | V78: =IF(AND($B78<>"",$F78<>"",$F78=项目明细账!$C$2),N(V77)+1,N(V77)) -> 0 | W78: =IF($H78<>"","项目成本",IFERROR(INDEX(基础资料!$W$4:$W$49,MATCH($I78,基础资料!$V$4:$V$49,0)),"")) -> 项目成本 | X78: =IFERROR(INDEX(基础资料!$R$4:$R$17,MATCH($G78,基础资料!$Q$4:$Q$17,0)),"")
A79: =IF($B79="","",COUNTA($B$5:$B79)) -> 75 | B79: 46027 | C79: 双思威农商行一般户 | D79: =IFERROR(INDEX(基础资料!$F$4:$F$23,MATCH($C79,基础资料!$E$4:$E$23,0)),IF($C79="","","未匹配账户")) -> 双思威 | E79: 支出 | I79: 其他管理费用 | J79: 付季新军报销款 | L79: 1129.1 | M79: =IFERROR(VLOOKUP($C79,$C$5:$M$24,11,0)+SUMIF($C$25:$C79,$C79,$K$25:$K79)-SUMIF($C$25:$C79,$C79,$L$25:$L79),"") -> 4084503.4 | O79: 供应商4 | R79: 示例：由2026年6月原表导入 | S79: =IF($B79="","",--TEXT($B79,"yyyymm")) -> 202601 | T79: =IF($B79="","",IF($P79="",$S79,IFERROR($P79*1,$P79))) -> 202601 | U79: =IF($B79="","",IF($T79=$S79,"","跨期")) | V79: =IF(AND($B79<>"",$F79<>"",$F79=项目明细账!$C$2),N(V78)+1,N(V78)) -> 0 | W79: =IF($H79<>"","项目成本",IFERROR(INDEX(基础资料!$W$4:$W$49,MATCH($I79,基础资料!$V$4:$V$49,0)),"")) -> 管理费用 | X79: =IFERROR(INDEX(基础资料!$R$4:$R$17,MATCH($G79,基础资料!$Q$4:$Q$17,0)),"")
A80: =IF($B80="","",COUNTA($B$5:$B80)) -> 76 | B80: 46027 | C80: 双思威农商行一般户 | D80: =IFERROR(INDEX(基础资料!$F$4:$F$23,MATCH($C80,基础资料!$E$4:$E$23,0)),IF($C80="","","未匹配账户")) -> 双思威 | E80: 支出 | F80: 昌吉市中小学数字化校园建设工程（昌吉市第十五小学教学仪器设备采购项目） | H80: 项目-材料 | J80: 付昌吉市美雅装饰店辅材 | L80: 5300 | M80: =IFERROR(VLOOKUP($C80,$C$5:$M$24,11,0)+SUMIF($C$25:$C80,$C80,$K$25:$K80)-SUMIF($C$25:$C80,$C80,$L$25:$L80),"") -> 4079203.4 | O80: 供应商4 | R80: 示例：由2026年6月原表导入 | S80: =IF($B80="","",--TEXT($B80,"yyyymm")) -> 202601 | T80: =IF($B80="","",IF($P80="",$S80,IFERROR($P80*1,$P80))) -> 202601 | U80: =IF($B80="","",IF($T80=$S80,"","跨期")) | V80: =IF(AND($B80<>"",$F80<>"",$F80=项目明细账!$C$2),N(V79)+1,N(V79)) -> 0 | W80: =IF($H80<>"","项目成本",IFERROR(INDEX(基础资料!$W$4:$W$49,MATCH($I80,基础资料!$V$4:$V$49,0)),"")) -> 项目成本 | X80: =IFERROR(INDEX(基础资料!$R$4:$R$17,MATCH($G80,基础资料!$Q$4:$Q$17,0)),"")
A81: =IF($B81="","",COUNTA($B$5:$B81)) -> 77 | B81: 46027 | C81: 双思威农商行一般户 | D81: =IFERROR(INDEX(基础资料!$F$4:$F$23,MATCH($C81,基础资料!$E$4:$E$23,0)),IF($C81="","","未匹配账户")) -> 双思威 | E81: 支出 | F81: 代建局昌吉市第十八小学教学仪器设备采购项目 | H81: 项目-人工 | J81: 付昌吉市聚合铭创广告文化传播中心施工费 | L81: 980 | M81: =IFERROR(VLOOKUP($C81,$C$5:$M$24,11,0)+SUMIF($C$25:$C81,$C81,$K$25:$K81)-SUMIF($C$25:$C81,$C81,$L$25:$L81),"") -> 4078223.4 | O81: 供应商1 | R81: 示例：由2026年6月原表导入 | S81: =IF($B81="","",--TEXT($B81,"yyyymm")) -> 202601 | T81: =IF($B81="","",IF($P81="",$S81,IFERROR($P81*1,$P81))) -> 202601 | U81: =IF($B81="","",IF($T81=$S81,"","跨期")) | V81: =IF(AND($B81<>"",$F81<>"",$F81=项目明细账!$C$2),N(V80)+1,N(V80)) -> 0 | W81: =IF($H81<>"","项目成本",IFERROR(INDEX(基础资料!$W$4:$W$49,MATCH($I81,基础资料!$V$4:$V$49,0)),"")) -> 项目成本 | X81: =IFERROR(INDEX(基础资料!$R$4:$R$17,MATCH($G81,基础资料!$Q$4:$Q$17,0)),"")
A82: =IF($B82="","",COUNTA($B$5:$B82)) -> 78 | B82: 46027 | C82: 双思威农商行一般户 | D82: =IFERROR(INDEX(基础资料!$F$4:$F$23,MATCH($C82,基础资料!$E$4:$E$23,0)),IF($C82="","","未匹配账户")) -> 双思威 | E82: 支出 | F82: 新疆某单位教育教学设备（二标段）甄选项目-六中 | H82: 项目-人工 | J82: 付昌吉市李小强装饰材料经销部心理咨询室软包装修 | L82: 2500 | M82: =IFERROR(VLOOKUP($C82,$C$5:$M$24,11,0)+SUMIF($C$25:$C82,$C82,$K$25:$K82)-SUMIF($C$25:$C82,$C82,$L$25:$L82),"") -> 4075723.4 | O82: 供应商1 | R82: 示例：由2026年6月原表导入 | S82: =IF($B82="","",--TEXT($B82,"yyyymm")) -> 202601 | T82: =IF($B82="","",IF($P82="",$S82,IFERROR($P82*1,$P82))) -> 202601 | U82: =IF($B82="","",IF($T82=$S82,"","跨期")) | V82: =IF(AND($B82<>"",$F82<>"",$F82=项目明细账!$C$2),N(V81)+1,N(V81)) -> 0 | W82: =IF($H82<>"","项目成本",IFERROR(INDEX(基础资料!$W$4:$W$49,MATCH($I82,基础资料!$V$4:$V$49,0)),"")) -> 项目成本 | X82: =IFERROR(INDEX(基础资料!$R$4:$R$17,MATCH($G82,基础资料!$Q$4:$Q$17,0)),"")
A83: =IF($B83="","",COUNTA($B$5:$B83)) -> 79 | B83: 46027 | C83: 双思威农商行一般户 | D83: =IFERROR(INDEX(基础资料!$F$4:$F$23,MATCH($C83,基础资料!$E$4:$E$23,0)),IF($C83="","","未匹配账户")) -> 双思威 | E83: 支出 | I83: 其他管理费用 | J83: 付昌吉市鑫宏盛广告服务部商务费 | L83: 3030 | M83: =IFERROR(VLOOKUP($C83,$C$5:$M$24,11,0)+SUMIF($C$25:$C83,$C83,$K$25:$K83)-SUMIF($C$25:$C83,$C83,$L$25:$L83),"") -> 4072693.4 | R83: 示例：由2026年6月原表导入 | S83: =IF($B83="","",--TEXT($B83,"yyyymm")) -> 202601 | T83: =IF($B83="","",IF($P83="",$S83,IFERROR($P83*1,$P83))) -> 202601 | U83: =IF($B83="","",IF($T83=$S83,"","跨期")) | V83: =IF(AND($B83<>"",$F83<>"",$F83=项目明细账!$C$2),N(V82)+1,N(V82)) -> 0 | W83: =IF($H83<>"","项目成本",IFERROR(INDEX(基础资料!$W$4:$W$49,MATCH($I83,基础资料!$V$4:$V$49,0)),"")) -> 管理费用 | X83: =IFERROR(INDEX(基础资料!$R$4:$R$17,MATCH($G83,基础资料!$Q$4:$Q$17,0)),"")
A84: =IF($B84="","",COUNTA($B$5:$B84)) -> 80 | B84: 46027 | C84: 双思威农商行一般户 | D84: =IFERROR(INDEX(基础资料!$F$4:$F$23,MATCH($C84,基础资料!$E$4:$E$23,0)),IF($C84="","","未匹配账户")) -> 双思威 | E84: 支出 | F84: 新疆某单位教育教学设备（二标段）甄选项目-六中 | H84: 项目-人工 | J84: 付昌吉市成达护栏网片铁件销售部施工费 | L84: 7000 | M84: =IFERROR(VLOOKUP($C84,$C$5:$M$24,11,0)+SUMIF($C$25:$C84,$C84,$K$25:$K84)-SUMIF($C$25:$C84,$C84,$L$25:$L84),"") -> 4065693.4 | R84: 示例：由2026年6月原表导入 | S84: =IF($B84="","",--TEXT($B84,"yyyymm")) -> 202601 | T84: =IF($B84="","",IF($P84="",$S84,IFERROR($P84*1,$P84))) -> 202601 | U84: =IF($B84="","",IF($T84=$S84,"","跨期")) | V84: =IF(AND($B84<>"",$F84<>"",$F84=项目明细账!$C$2),N(V83)+1,N(V83)) -> 0 | W84: =IF($H84<>"","项目成本",IFERROR(INDEX(基础资料!$W$4:$W$49,MATCH($I84,基础资料!$V$4:$V$49,0)),"")) -> 项目成本 | X84: =IFERROR(INDEX(基础资料!$R$4:$R$17,MATCH($G84,基础资料!$Q$4:$Q$17,0)),"")
A85: =IF($B85="","",COUNTA($B$5:$B85)) -> 81 | B85: 46028 | C85: 双思威农商行一般户 | D85: =IFERROR(INDEX(基础资料!$F$4:$F$23,MATCH($C85,基础资料!$E$4:$E$23,0)),IF($C85="","","未匹配账户")) -> 双思威 | E85: 支出 | I85: 其他管理费用 | J85: 付高愉报销款 | L85: 2722.59 | M85: =IFERROR(VLOOKUP($C85,$C$5:$M$24,11,0)+SUMIF($C$25:$C85,$C85,$K$25:$K85)-SUMIF($C$25:$C85,$C85,$L$25:$L85),"") -> 4062970.8 | O85: 供应商1 | R85: 示例：由2026年6月原表导入 | S85: =IF($B85="","",--TEXT($B85,"yyyymm")) -> 202601 | T85: =IF($B85="","",IF($P85="",$S85,IFERROR($P85*1,$P85))) -> 202601 | U85: =IF($B85="","",IF($T85=$S85,"","跨期")) | V85: =IF(AND($B85<>"",$F85<>"",$F85=项目明细账!$C$2),N(V84)+1,N(V84)) -> 0 | W85: =IF($H85<>"","项目成本",IFERROR(INDEX(基础资料!$W$4:$W$49,MATCH($I85,基础资料!$V$4:$V$49,0)),"")) -> 管理费用 | X85: =IFERROR(INDEX(基础资料!$R$4:$R$17,MATCH($G85,基础资料!$Q$4:$Q$17,0)),"")
A86: =IF($B86="","",COUNTA($B$5:$B86)) -> 82 | B86: 46028 | C86: 双思威农商行一般户 | D86: =IFERROR(INDEX(基础资料!$F$4:$F$23,MATCH($C86,基础资料!$E$4:$E$23,0)),IF($C86="","","未匹配账户")) -> 双思威 | E86: 支出 | I86: 其他管理费用 | J86: 付陈垒报销款 | L86: 11344.5 | M86: =IFERROR(VLOOKUP($C86,$C$5:$M$24,11,0)+SUMIF($C$25:$C86,$C86,$K$25:$K86)-SUMIF($C$25:$C86,$C86,$L$25:$L86),"") -> 4051626.3 | O86: 供应商1 | R86: 示例：由2026年6月原表导入 | S86: =IF($B86="","",--TEXT($B86,"yyyymm")) -> 202601 | T86: =IF($B86="","",IF($P86="",$S86,IFERROR($P86*1,$P86))) -> 202601 | U86: =IF($B86="","",IF($T86=$S86,"","跨期")) | V86: =IF(AND($B86<>"",$F86<>"",$F86=项目明细账!$C$2),N(V85)+1,N(V85)) -> 0 | W86: =IF($H86<>"","项目成本",IFERROR(INDEX(基础资料!$W$4:$W$49,MATCH($I86,基础资料!$V$4:$V$49,0)),"")) -> 管理费用 | X86: =IFERROR(INDEX(基础资料!$R$4:$R$17,MATCH($G86,基础资料!$Q$4:$Q$17,0)),"")
A87: =IF($B87="","",COUNTA($B$5:$B87)) -> 83 | B87: 46028 | C87: 双思威农商行一般户 | D87: =IFERROR(INDEX(基础资料!$F$4:$F$23,MATCH($C87,基础资料!$E$4:$E$23,0)),IF($C87="","","未匹配账户")) -> 双思威 | E87: 收入 | F87: 铁门关经济技术开发区化工园区周界防护项目 | J87: 收巴州筑磊建材有限公司退回材料款 | K87: 1010 | M87: =IFERROR(VLOOKUP($C87,$C$5:$M$24,11,0)+SUMIF($C$25:$C87,$C87,$K$25:$K87)-SUMIF($C$25:$C87,$C87,$L$25:$L87),"") -> 4052636.3 | O87: 供应商2 | R87: 示例：由2026年6月原表导入 | S87: =IF($B87="","",--TEXT($B87,"yyyymm")) -> 202601 | T87: =IF($B87="","",IF($P87="",$S87,IFERROR($P87*1,$P87))) -> 202601 | U87: =IF($B87="","",IF($T87=$S87,"","跨期")) | V87: =IF(AND($B87<>"",$F87<>"",$F87=项目明细账!$C$2),N(V86)+1,N(V86)) -> 0 | W87: =IF($H87<>"","项目成本",IFERROR(INDEX(基础资料!$W$4:$W$49,MATCH($I87,基础资料!$V$4:$V$49,0)),"")) | X87: =IFERROR(INDEX(基础资料!$R$4:$R$17,MATCH($G87,基础资料!$Q$4:$Q$17,0)),"")
A88: =IF($B88="","",COUNTA($B$5:$B88)) -> 84 | B88: 46029 | C88: 双思威农商行一般户 | D88: =IFERROR(INDEX(基础资料!$F$4:$F$23,MATCH($C88,基础资料!$E$4:$E$23,0)),IF($C88="","","未匹配账户")) -> 双思威 | E88: 支出 | F88: 昌吉市中小学数字化校园建设工程（昌吉市第十五小学教学仪器设备采购项目） | H88: 项目-材料 | J88: 付乌鲁木齐头屯河区芯智联电子设备经销部补光灯 | L88: 2730 | M88: =IFERROR(VLOOKUP($C88,$C$5:$M$24,11,0)+SUMIF($C$25:$C88,$C88,$K$25:$K88)-SUMIF($C$25:$C88,$C88,$L$25:$L88),"") -> 4049906.3 | R88: 示例：由2026年6月原表导入 | S88: =IF($B88="","",--TEXT($B88,"yyyymm")) -> 202601 | T88: =IF($B88="","",IF($P88="",$S88,IFERROR($P88*1,$P88))) -> 202601 | U88: =IF($B88="","",IF($T88=$S88,"","跨期")) | V88: =IF(AND($B88<>"",$F88<>"",$F88=项目明细账!$C$2),N(V87)+1,N(V87)) -> 0 | W88: =IF($H88<>"","项目成本",IFERROR(INDEX(基础资料!$W$4:$W$49,MATCH($I88,基础资料!$V$4:$V$49,0)),"")) -> 项目成本 | X88: =IFERROR(INDEX(基础资料!$R$4:$R$17,MATCH($G88,基础资料!$Q$4:$Q$17,0)),"")
A89: =IF($B89="","",COUNTA($B$5:$B89)) -> 85 | B89: 46029 | C89: 双思威农商行一般户 | D89: =IFERROR(INDEX(基础资料!$F$4:$F$23,MATCH($C89,基础资料!$E$4:$E$23,0)),IF($C89="","","未匹配账户")) -> 双思威 | E89: 支出 | F89: 代建局昌吉市第十八小学教学仪器设备采购项目 | H89: 项目-人工 | J89: 付赵刚安装费 | L89: 3500 | M89: =IFERROR(VLOOKUP($C89,$C$5:$M$24,11,0)+SUMIF($C$25:$C89,$C89,$K$25:$K89)-SUMIF($C$25:$C89,$C89,$L$25:$L89),"") -> 4046406.3 | R89: 示例：由2026年6月原表导入 | S89: =IF($B89="","",--TEXT($B89,"yyyymm")) -> 202601 | T89: =IF($B89="","",IF($P89="",$S89,IFERROR($P89*1,$P89))) -> 202601 | U89: =IF($B89="","",IF($T89=$S89,"","跨期")) | V89: =IF(AND($B89<>"",$F89<>"",$F89=项目明细账!$C$2),N(V88)+1,N(V88)) -> 0 | W89: =IF($H89<>"","项目成本",IFERROR(INDEX(基础资料!$W$4:$W$49,MATCH($I89,基础资料!$V$4:$V$49,0)),"")) -> 项目成本 | X89: =IFERROR(INDEX(基础资料!$R$4:$R$17,MATCH($G89,基础资料!$Q$4:$Q$17,0)),"")
A90: =IF($B90="","",COUNTA($B$5:$B90)) -> 86 | B90: 46030 | C90: 双思威农商行一般户 | D90: =IFERROR(INDEX(基础资料!$F$4:$F$23,MATCH($C90,基础资料!$E$4:$E$23,0)),IF($C90="","","未匹配账户")) -> 双思威 | E90: 支出 | F90: 第四师第一中学高中地理实验室设施设备采购项目 | H90: 项目-材料 | J90: 付新疆华耀信达信息科技有限公司智慧黑板 | L90: 13000 | M90: =IFERROR(VLOOKUP($C90,$C$5:$M$24,11,0)+SUMIF($C$25:$C90,$C90,$K$25:$K90)-SUMIF($C$25:$C90,$C90,$L$25:$L90),"") -> 4033406.3 | O90: 供应商1 | R90: 示例：由2026年6月原表导入 | S90: =IF($B90="","",--TEXT($B90,"yyyymm")) -> 202601 | T90: =IF($B90="","",IF($P90="",$S90,IFERROR($P90*1,$P90))) -> 202601 | U90: =IF($B90="","",IF($T90=$S90,"","跨期")) | V90: =IF(AND($B90<>"",$F90<>"",$F90=项目明细账!$C$2),N(V89)+1,N(V89)) -> 0 | W90: =IF($H90<>"","项目成本",IFERROR(INDEX(基础资料!$W$4:$W$49,MATCH($I90,基础资料!$V$4:$V$49,0)),"")) -> 项目成本 | X90: =IFERROR(INDEX(基础资料!$R$4:$R$17,MATCH($G90,基础资料!$Q$4:$Q$17,0)),"")
A91: =IF($B91="","",COUNTA($B$5:$B91)) -> 87 | B91: 46030 | C91: 双思威农商行一般户 | D91: =IFERROR(INDEX(基础资料!$F$4:$F$23,MATCH($C91,基础资料!$E$4:$E$23,0)),IF($C91="","","未匹配账户")) -> 双思威 | E91: 支出 | F91: 第四师第一中学高中地理实验室设施设备采购项目 | H91: 项目-材料 | J91: 付上海丝路疆至造科技有限公司数据采集器 | L91: 1500 | M91: =IFERROR(VLOOKUP($C91,$C$5:$M$24,11,0)+SUMIF($C$25:$C91,$C91,$K$25:$K91)-SUMIF($C$25:$C91,$C91,$L$25:$L91),"") -> 4031906.3 | O91: 供应商1 | R91: 示例：由2026年6月原表导入 | S91: =IF($B91="","",--TEXT($B91,"yyyymm")) -> 202601 | T91: =IF($B91="","",IF($P91="",$S91,IFERROR($P91*1,$P91))) -> 202601 | U91: =IF($B91="","",IF($T91=$S91,"","跨期")) | V91: =IF(AND($B91<>"",$F91<>"",$F91=项目明细账!$C$2),N(V90)+1,N(V90)) -> 0 | W91: =IF($H91<>"","项目成本",IFERROR(INDEX(基础资料!$W$4:$W$49,MATCH($I91,基础资料!$V$4:$V$49,0)),"")) -> 项目成本 | X91: =IFERROR(INDEX(基础资料!$R$4:$R$17,MATCH($G91,基础资料!$Q$4:$Q$17,0)),"")
A92: =IF($B92="","",COUNTA($B$5:$B92)) -> 88 | B92: 46030 | C92: 双思威农商行一般户 | D92: =IFERROR(INDEX(基础资料!$F$4:$F$23,MATCH($C92,基础资料!$E$4:$E$23,0)),IF($C92="","","未匹配账户")) -> 双思威 | E92: 支出 | F92: 第四师第一中学高中地理实验室设施设备采购项目 | H92: 项目-材料 | J92: 付上海丝路疆至造科技有限公司数据采集器 | L92: 13500 | M92: =IFERROR(VLOOKUP($C92,$C$5:$M$24,11,0)+SUMIF($C$25:$C92,$C92,$K$25:$K92)-SUMIF($C$25:$C92,$C92,$L$25:$L92),"") -> 4018406.3 | O92: 供应商1 | R92: 示例：由2026年6月原表导入 | S92: =IF($B92="","",--TEXT($B92,"yyyymm")) -> 202601 | T92: =IF($B92="","",IF($P92="",$S92,IFERROR($P92*1,$P92))) -> 202601 | U92: =IF($B92="","",IF($T92=$S92,"","跨期")) | V92: =IF(AND($B92<>"",$F92<>"",$F92=项目明细账!$C$2),N(V91)+1,N(V91)) -> 0 | W92: =IF($H92<>"","项目成本",IFERROR(INDEX(基础资料!$W$4:$W$49,MATCH($I92,基础资料!$V$4:$V$49,0)),"")) -> 项目成本 | X92: =IFERROR(INDEX(基础资料!$R$4:$R$17,MATCH($G92,基础资料!$Q$4:$Q$17,0)),"")
A93: =IF($B93="","",COUNTA($B$5:$B93)) -> 89 | B93: 46032 | C93: 双思威农商行一般户 | D93: =IFERROR(INDEX(基础资料!$F$4:$F$23,MATCH($C93,基础资料!$E$4:$E$23,0)),IF($C93="","","未匹配账户")) -> 双思威 | E93: 支出 | F93: 新疆某单位教育教学设备（二标段）甄选项目-六中 | H93: 项目-材料 | J93: 付昌吉市艺欧窗帘经营中心窗帘 | L93: 42500 | M93: =IFERROR(VLOOKUP($C93,$C$5:$M$24,11,0)+SUMIF($C$25:$C93,$C93,$K$25:$K93)-SUMIF($C$25:$C93,$C93,$L$25:$L93),"") -> 3975906.3 | R93: 示例：由2026年6月原表导入 | S93: =IF($B93="","",--TEXT($B93,"yyyymm")) -> 202601 | T93: =IF($B93="","",IF($P93="",$S93,IFERROR($P93*1,$P93))) -> 202601 | U93: =IF($B93="","",IF($T93=$S93,"","跨期")) | V93: =IF(AND($B93<>"",$F93<>"",$F93=项目明细账!$C$2),N(V92)+1,N(V92)) -> 0 | W93: =IF($H93<>"","项目成本",IFERROR(INDEX(基础资料!$W$4:$W$49,MATCH($I93,基础资料!$V$4:$V$49,0)),"")) -> 项目成本 | X93: =IFERROR(INDEX(基础资料!$R$4:$R$17,MATCH($G93,基础资料!$Q$4:$Q$17,0)),"")
A94: =IF($B94="","",COUNTA($B$5:$B94)) -> 90 | B94: 46032 | C94: 双思威农商行一般户 | D94: =IFERROR(INDEX(基础资料!$F$4:$F$23,MATCH($C94,基础资料!$E$4:$E$23,0)),IF($C94="","","未匹配账户")) -> 双思威 | E94: 支出 | I94: 其他管理费用 | J94: 付乌鲁木齐图腾讯科电子科技有限公司机柜 | L94: 875 | M94: =IFERROR(VLOOKUP($C94,$C$5:$M$24,11,0)+SUMIF($C$25:$C94,$C94,$K$25:$K94)-SUMIF($C$25:$C94,$C94,$L$25:$L94),"") -> 3975031.3 | R94: 示例：由2026年6月原表导入 | S94: =IF($B94="","",--TEXT($B94,"yyyymm")) -> 202601 | T94: =IF($B94="","",IF($P94="",$S94,IFERROR($P94*1,$P94))) -> 202601 | U94: =IF($B94="","",IF($T94=$S94,"","跨期")) | V94: =IF(AND($B94<>"",$F94<>"",$F94=项目明细账!$C$2),N(V93)+1,N(V93)) -> 0 | W94: =IF($H94<>"","项目成本",IFERROR(INDEX(基础资料!$W$4:$W$49,MATCH($I94,基础资料!$V$4:$V$49,0)),"")) -> 管理费用 | X94: =IFERROR(INDEX(基础资料!$R$4:$R$17,MATCH($G94,基础资料!$Q$4:$Q$17,0)),"")
A95: =IF($B95="","",COUNTA($B$5:$B95)) -> 91 | B95: 46032 | C95: 双思威农商行一般户 | D95: =IFERROR(INDEX(基础资料!$F$4:$F$23,MATCH($C95,基础资料!$E$4:$E$23,0)),IF($C95="","","未匹配账户")) -> 双思威 | E95: 支出 | F95: 铁门关经济技术开发区化工园区周界防护项目 | H95: 项目-材料 | J95: 付库尔勒今日兴盛五金建材店（个体工商户五金 | L95: 6134.6 | M95: =IFERROR(VLOOKUP($C95,$C$5:$M$24,11,0)+SUMIF($C$25:$C95,$C95,$K$25:$K95)-SUMIF($C$25:$C95,$C95,$L$25:$L95),"") -> 3968896.7 | R95: 示例：由2026年6月原表导入 | S95: =IF($B95="","",--TEXT($B95,"yyyymm")) -> 202601 | T95: =IF($B95="","",IF($P95="",$S95,IFERROR($P95*1,$P95))) -> 202601 | U95: =IF($B95="","",IF($T95=$S95,"","跨期")) | V95: =IF(AND($B95<>"",$F95<>"",$F95=项目明细账!$C$2),N(V94)+1,N(V94)) -> 0 | W95: =IF($H95<>"","项目成本",IFERROR(INDEX(基础资料!$W$4:$W$49,MATCH($I95,基础资料!$V$4:$V$49,0)),"")) -> 项目成本 | X95: =IFERROR(INDEX(基础资料!$R$4:$R$17,MATCH($G95,基础资料!$Q$4:$Q$17,0)),"")
A96: =IF($B96="","",COUNTA($B$5:$B96)) -> 92 | B96: 46032 | C96: 双思威农商行一般户 | D96: =IFERROR(INDEX(基础资料!$F$4:$F$23,MATCH($C96,基础资料!$E$4:$E$23,0)),IF($C96="","","未匹配账户")) -> 双思威 | E96: 支出 | F96: 二师公安库铁大道监控引电（中国电信巴州分公司2025年第二师GAJ视频监控平台、云集成服务项目） | H96: 项目-材料 | J96: 付铁门关市昊翼商贸有限公司网线 | L96: 2408 | M96: =IFERROR(VLOOKUP($C96,$C$5:$M$24,11,0)+SUMIF($C$25:$C96,$C96,$K$25:$K96)-SUMIF($C$25:$C96,$C96,$L$25:$L96),"") -> 3966488.7 | R96: 示例：由2026年6月原表导入 | S96: =IF($B96="","",--TEXT($B96,"yyyymm")) -> 202601 | T96: =IF($B96="","",IF($P96="",$S96,IFERROR($P96*1,$P96))) -> 202601 | U96: =IF($B96="","",IF($T96=$S96,"","跨期")) | V96: =IF(AND($B96<>"",$F96<>"",$F96=项目明细账!$C$2),N(V95)+1,N(V95)) -> 0 | W96: =IF($H96<>"","项目成本",IFERROR(INDEX(基础资料!$W$4:$W$49,MATCH($I96,基础资料!$V$4:$V$49,0)),"")) -> 项目成本 | X96: =IFERROR(INDEX(基础资料!$R$4:$R$17,MATCH($G96,基础资料!$Q$4:$Q$17,0)),"")
A97: =IF($B97="","",COUNTA($B$5:$B97)) -> 93 | B97: 46032 | C97: 双思威农商行一般户 | D97: =IFERROR(INDEX(基础资料!$F$4:$F$23,MATCH($C97,基础资料!$E$4:$E$23,0)),IF($C97="","","未匹配账户")) -> 双思威 | E97: 支出 | F97: 铁门关经济技术开发区化工园区周界防护项目 | H97: 项目-材料 | J97: 付铁门关市昊翼商贸有限公司施工费 | L97: 7969 | M97: =IFERROR(VLOOKUP($C97,$C$5:$M$24,11,0)+SUMIF($C$25:$C97,$C97,$K$25:$K97)-SUMIF($C$25:$C97,$C97,$L$25:$L97),"") -> 3958519.7 | R97: 示例：由2026年6月原表导入 | S97: =IF($B97="","",--TEXT($B97,"yyyymm")) -> 202601 | T97: =IF($B97="","",IF($P97="",$S97,IFERROR($P97*1,$P97))) -> 202601 | U97: =IF($B97="","",IF($T97=$S97,"","跨期")) | V97: =IF(AND($B97<>"",$F97<>"",$F97=项目明细账!$C$2),N(V96)+1,N(V96)) -> 0 | W97: =IF($H97<>"","项目成本",IFERROR(INDEX(基础资料!$W$4:$W$49,MATCH($I97,基础资料!$V$4:$V$49,0)),"")) -> 项目成本 | X97: =IFERROR(INDEX(基础资料!$R$4:$R$17,MATCH($G97,基础资料!$Q$4:$Q$17,0)),"")
A98: =IF($B98="","",COUNTA($B$5:$B98)) -> 94 | B98: 46034 | C98: 双思威农商行一般户 | D98: =IFERROR(INDEX(基础资料!$F$4:$F$23,MATCH($C98,基础资料!$E$4:$E$23,0)),IF($C98="","","未匹配账户")) -> 双思威 | E98: 支出 | F98: 昌吉市中等职业学校教学设备采购项目（一标段） | G98: 项目收入 | J98: 收北京竞业达数码科技股份有限公司 | K98: 3122400 | M98: =IFERROR(VLOOKUP($C98,$C$5:$M$24,11,0)+SUMIF($C$25:$C98,$C98,$K$25:$K98)-SUMIF($C$25:$C98,$C98,$L$25:$L98),"") -> 7080919.7 | O98: 供应商1 | R98: 示例：由2026年6月原表导入 | S98: =IF($B98="","",--TEXT($B98,"yyyymm")) -> 202601 | T98: =IF($B98="","",IF($P98="",$S98,IFERROR($P98*1,$P98))) -> 202601 | U98: =IF($B98="","",IF($T98=$S98,"","跨期")) | V98: =IF(AND($B98<>"",$F98<>"",$F98=项目明细账!$C$2),N(V97)+1,N(V97)) -> 0 | W98: =IF($H98<>"","项目成本",IFERROR(INDEX(基础资料!$W$4:$W$49,MATCH($I98,基础资料!$V$4:$V$49,0)),"")) | X98: =IFERROR(INDEX(基础资料!$R$4:$R$17,MATCH($G98,基础资料!$Q$4:$Q$17,0)),"") -> 经营收入
A99: =IF($B99="","",COUNTA($B$5:$B99)) -> 95 | B99: 46034 | C99: 双思威农商行一般户 | D99: =IFERROR(INDEX(基础资料!$F$4:$F$23,MATCH($C99,基础资料!$E$4:$E$23,0)),IF($C99="","","未匹配账户")) -> 双思威 | E99: 支出 | F99: 李广新昌吉市第十六小学教学仪器设备采购 | H99: 项目-材料 | J99: 付新疆鲲鹏特变线缆有限公司紫外线消毒灯 | L99: 11000 | M99: =IFERROR(VLOOKUP($C99,$C$5:$M$24,11,0)+SUMIF($C$25:$C99,$C99,$K$25:$K99)-SUMIF($C$25:$C99,$C99,$L$25:$L99),"") -> 7069919.7 | R99: 示例：由2026年6月原表导入 | S99: =IF($B99="","",--TEXT($B99,"yyyymm")) -> 202601 | T99: =IF($B99="","",IF($P99="",$S99,IFERROR($P99*1,$P99))) -> 202601 | U99: =IF($B99="","",IF($T99=$S99,"","跨期")) | V99: =IF(AND($B99<>"",$F99<>"",$F99=项目明细账!$C$2),N(V98)+1,N(V98)) -> 0 | W99: =IF($H99<>"","项目成本",IFERROR(INDEX(基础资料!$W$4:$W$49,MATCH($I99,基础资料!$V$4:$V$49,0)),"")) -> 项目成本 | X99: =IFERROR(INDEX(基础资料!$R$4:$R$17,MATCH($G99,基础资料!$Q$4:$Q$17,0)),"")
A100: =IF($B100="","",COUNTA($B$5:$B100)) -> 96 | B100: 46035 | C100: 双思威农商行一般户 | D100: =IFERROR(INDEX(基础资料!$F$4:$F$23,MATCH($C100,基础资料!$E$4:$E$23,0)),IF($C100="","","未匹配账户")) -> 双思威 | E100: 支出 | F100: 新疆某单位教育教学设备（二标段）甄选项目-六中 | H100: 项目-材料 | J100: 付新疆众利创兴电子科技有限公司电视 | L100: 2300 | M100: =IFERROR(VLOOKUP($C100,$C$5:$M$24,11,0)+SUMIF($C$25:$C100,$C100,$K$25:$K100)-SUMIF($C$25:$C100,$C100,$L$25:$L100),"") -> 7067619.7 | R100: 示例：由2026年6月原表导入 | S100: =IF($B100="","",--TEXT($B100,"yyyymm")) -> 202601 | T100: =IF($B100="","",IF($P100="",$S100,IFERROR($P100*1,$P100))) -> 202601 | U100: =IF($B100="","",IF($T100=$S100,"","跨期")) | V100: =IF(AND($B100<>"",$F100<>"",$F100=项目明细账!$C$2),N(V99)+1,N(V99)) -> 0 | W100: =IF($H100<>"","项目成本",IFERROR(INDEX(基础资料!$W$4:$W$49,MATCH($I100,基础资料!$V$4:$V$49,0)),"")) -> 项目成本 | X100: =IFERROR(INDEX(基础资料!$R$4:$R$17,MATCH($G100,基础资料!$Q$4:$Q$17,0)),"")
A101: =IF($B101="","",COUNTA($B$5:$B101)) -> 97 | B101: 46036 | C101: 双思威农商行一般户 | D101: =IFERROR(INDEX(基础资料!$F$4:$F$23,MATCH($C101,基础资料!$E$4:$E$23,0)),IF($C101="","","未匹配账户")) -> 双思威 | E101: 支出 | F101: 昌吉市中等职业学校教学设备采购项目（一标段） | H101: 项目-零星开支 | J101: 付北京竞业达数码科技股份有限公司保函费 | L101: 300 | M101: =IFERROR(VLOOKUP($C101,$C$5:$M$24,11,0)+SUMIF($C$25:$C101,$C101,$K$25:$K101)-SUMIF($C$25:$C101,$C101,$L$25:$L101),"") -> 7067319.7 | R101: 示例：由2026年6月原表导入 | S101: =IF($B101="","",--TEXT($B101,"yyyymm")) -> 202601 | T101: =IF($B101="","",IF($P101="",$S101,IFERROR($P101*1,$P101))) -> 202601 | U101: =IF($B101="","",IF($T101=$S101,"","跨期")) | V101: =IF(AND($B101<>"",$F101<>"",$F101=项目明细账!$C$2),N(V100)+1,N(V100)) -> 0 | W101: =IF($H101<>"","项目成本",IFERROR(INDEX(基础资料!$W$4:$W$49,MATCH($I101,基础资料!$V$4:$V$49,0)),"")) -> 项目成本 | X101: =IFERROR(INDEX(基础资料!$R$4:$R$17,MATCH($G101,基础资料!$Q$4:$Q$17,0)),"")
A102: =IF($B102="","",COUNTA($B$5:$B102)) -> 98 | B102: 46036 | C102: 双思威农商行一般户 | D102: =IFERROR(INDEX(基础资料!$F$4:$F$23,MATCH($C102,基础资料!$E$4:$E$23,0)),IF($C102="","","未匹配账户")) -> 双思威 | E102: 支出 | F102: 代建局昌吉市第十八小学教学仪器设备采购项目 | H102: 项目-材料 | J102: 付新疆博远恒业电子科技有限公司LED | L102: 15400 | M102: =IFERROR(VLOOKUP($C102,$C$5:$M$24,11,0)+SUMIF($C$25:$C102,$C102,$K$25:$K102)-SUMIF($C$25:$C102,$C102,$L$25:$L102),"") -> 7051919.7 | R102: 示例：由2026年6月原表导入 | S102: =IF($B102="","",--TEXT($B102,"yyyymm")) -> 202601 | T102: =IF($B102="","",IF($P102="",$S102,IFERROR($P102*1,$P102))) -> 202601 | U102: =IF($B102="","",IF($T102=$S102,"","跨期")) | V102: =IF(AND($B102<>"",$F102<>"",$F102=项目明细账!$C$2),N(V101)+1,N(V101)) -> 0 | W102: =IF($H102<>"","项目成本",IFERROR(INDEX(基础资料!$W$4:$W$49,MATCH($I102,基础资料!$V$4:$V$49,0)),"")) -> 项目成本 | X102: =IFERROR(INDEX(基础资料!$R$4:$R$17,MATCH($G102,基础资料!$Q$4:$Q$17,0)),"")
A103: =IF($B103="","",COUNTA($B$5:$B103)) -> 99 | B103: 46036 | C103: 双思威农商行一般户 | D103: =IFERROR(INDEX(基础资料!$F$4:$F$23,MATCH($C103,基础资料!$E$4:$E$23,0)),IF($C103="","","未匹配账户")) -> 双思威 | E103: 支出 | F103: 代建局昌吉市第十八小学教学仪器设备采购项目 | H103: 项目-材料 | J103: 付新疆世纪昶泰家具有限公司主席台等 | L103: 4080 | M103: =IFERROR(VLOOKUP($C103,$C$5:$M$24,11,0)+SUMIF($C$25:$C103,$C103,$K$25:$K103)-SUMIF($C$25:$C103,$C103,$L$25:$L103),"") -> 7047839.7 | R103: 示例：由2026年6月原表导入 | S103: =IF($B103="","",--TEXT($B103,"yyyymm")) -> 202601 | T103: =IF($B103="","",IF($P103="",$S103,IFERROR($P103*1,$P103))) -> 202601 | U103: =IF($B103="","",IF($T103=$S103,"","跨期")) | V103: =IF(AND($B103<>"",$F103<>"",$F103=项目明细账!$C$2),N(V102)+1,N(V102)) -> 0 | W103: =IF($H103<>"","项目成本",IFERROR(INDEX(基础资料!$W$4:$W$49,MATCH($I103,基础资料!$V$4:$V$49,0)),"")) -> 项目成本 | X103: =IFERROR(INDEX(基础资料!$R$4:$R$17,MATCH($G103,基础资料!$Q$4:$Q$17,0)),"")
A104: =IF($B104="","",COUNTA($B$5:$B104)) -> 100 | B104: 46037 | C104: 双思威农商行一般户 | D104: =IFERROR(INDEX(基础资料!$F$4:$F$23,MATCH($C104,基础资料!$E$4:$E$23,0)),IF($C104="","","未匹配账户")) -> 双思威 | E104: 支出 | F104: 第二师铁门关市师政数据防火墙维保服务采购项目 | H104: 项目-材料 | J104: 付新疆亿安达科技发展有限公司防火墙技术服务费 | L104: 18000 | M104: =IFERROR(VLOOKUP($C104,$C$5:$M$24,11,0)+SUMIF($C$25:$C104,$C104,$K$25:$K104)-SUMIF($C$25:$C104,$C104,$L$25:$L104),"") -> 7029839.7 | R104: 示例：由2026年6月原表导入 | S104: =IF($B104="","",--TEXT($B104,"yyyymm")) -> 202601 | T104: =IF($B104="","",IF($P104="",$S104,IFERROR($P104*1,$P104))) -> 202601 | U104: =IF($B104="","",IF($T104=$S104,"","跨期")) | V104: =IF(AND($B104<>"",$F104<>"",$F104=项目明细账!$C$2),N(V103)+1,N(V103)) -> 0 | W104: =IF($H104<>"","项目成本",IFERROR(INDEX(基础资料!$W$4:$W$49,MATCH($I104,基础资料!$V$4:$V$49,0)),"")) -> 项目成本 | X104: =IFERROR(INDEX(基础资料!$R$4:$R$17,MATCH($G104,基础资料!$Q$4:$Q$17,0)),"")
A105: =IF($B105="","",COUNTA($B$5:$B105)) -> 101 | B105: 46037 | C105: 双思威农商行一般户 | D105: =IFERROR(INDEX(基础资料!$F$4:$F$23,MATCH($C105,基础资料!$E$4:$E$23,0)),IF($C105="","","未匹配账户")) -> 双思威 | E105: 支出 | F105: 铁门关经济技术开发区化工园区周界防护项目 | H105: 项目-材料 | J105: 付巴州恒业视讯网络科技有限公司熔纤费 | L105: 1500 | M105: =IFERROR(VLOOKUP($C105,$C$5:$M$24,11,0)+SUMIF($C$25:$C105,$C105,$K$25:$K105)-SUMIF($C$25:$C105,$C105,$L$25:$L105),"") -> 7028339.7 | R105: 示例：由2026年6月原表导入 | S105: =IF($B105="","",--TEXT($B105,"yyyymm")) -> 202601 | T105: =IF($B105="","",IF($P105="",$S105,IFERROR($P105*1,$P105))) -> 202601 | U105: =IF($B105="","",IF($T105=$S105,"","跨期")) | V105: =IF(AND($B105<>"",$F105<>"",$F105=项目明细账!$C$2),N(V104)+1,N(V104)) -> 0 | W105: =IF($H105<>"","项目成本",IFERROR(INDEX(基础资料!$W$4:$W$49,MATCH($I105,基础资料!$V$4:$V$49,0)),"")) -> 项目成本 | X105: =IFERROR(INDEX(基础资料!$R$4:$R$17,MATCH($G105,基础资料!$Q$4:$Q$17,0)),"")
A106: =IF($B106="","",COUNTA($B$5:$B106)) -> 102 | B106: 46039 | C106: 双思威农商行一般户 | D106: =IFERROR(INDEX(基础资料!$F$4:$F$23,MATCH($C106,基础资料!$E$4:$E$23,0)),IF($C106="","","未匹配账户")) -> 双思威 | E106: 支出 | F106: 代建局昌吉市第十八小学教学仪器设备采购项目 | H106: 项目-材料 | J106: 付新疆隆昌天弘金属制品制造有限公司操作台 | L106: 2800 | M106: =IFERROR(VLOOKUP($C106,$C$5:$M$24,11,0)+SUMIF($C$25:$C106,$C106,$K$25:$K106)-SUMIF($C$25:$C106,$C106,$L$25:$L106),"") -> 7025539.7 | R106: 示例：由2026年6月原表导入 | S106: =IF($B106="","",--TEXT($B106,"yyyymm")) -> 202601 | T106: =IF($B106="","",IF($P106="",$S106,IFERROR($P106*1,$P106))) -> 202601 | U106: =IF($B106="","",IF($T106=$S106,"","跨期")) | V106: =IF(AND($B106<>"",$F106<>"",$F106=项目明细账!$C$2),N(V105)+1,N(V105)) -> 0 | W106: =IF($H106<>"","项目成本",IFERROR(INDEX(基础资料!$W$4:$W$49,MATCH($I106,基础资料!$V$4:$V$49,0)),"")) -> 项目成本 | X106: =IFERROR(INDEX(基础资料!$R$4:$R$17,MATCH($G106,基础资料!$Q$4:$Q$17,0)),"")
A107: =IF($B107="","",COUNTA($B$5:$B107)) -> 103 | B107: 46041 | C107: 双思威农商行一般户 | D107: =IFERROR(INDEX(基础资料!$F$4:$F$23,MATCH($C107,基础资料!$E$4:$E$23,0)),IF($C107="","","未匹配账户")) -> 双思威 | E107: 支出 | F107: 代建局昌吉市第十八小学教学仪器设备采购项目 | H107: 项目-材料 | J107: 付新疆福睿鑫办公家具有限公司椅子等 | L107: 1930 | M107: =IFERROR(VLOOKUP($C107,$C$5:$M$24,11,0)+SUMIF($C$25:$C107,$C107,$K$25:$K107)-SUMIF($C$25:$C107,$C107,$L$25:$L107),"") -> 7023609.7 | R107: 示例：由2026年6月原表导入 | S107: =IF($B107="","",--TEXT($B107,"yyyymm")) -> 202601 | T107: =IF($B107="","",IF($P107="",$S107,IFERROR($P107*1,$P107))) -> 202601 | U107: =IF($B107="","",IF($T107=$S107,"","跨期")) | V107: =IF(AND($B107<>"",$F107<>"",$F107=项目明细账!$C$2),N(V106)+1,N(V106)) -> 0 | W107: =IF($H107<>"","项目成本",IFERROR(INDEX(基础资料!$W$4:$W$49,MATCH($I107,基础资料!$V$4:$V$49,0)),"")) -> 项目成本 | X107: =IFERROR(INDEX(基础资料!$R$4:$R$17,MATCH($G107,基础资料!$Q$4:$Q$17,0)),"")
A108: =IF($B108="","",COUNTA($B$5:$B108)) -> 104 | B108: 46041 | C108: 双思威农商行一般户 | D108: =IFERROR(INDEX(基础资料!$F$4:$F$23,MATCH($C108,基础资料!$E$4:$E$23,0)),IF($C108="","","未匹配账户")) -> 双思威 | E108: 支出 | F108: 昌吉市中小学数字化校园建设工程（昌吉市第十五小学教学仪器设备采购项目） | H108: 项目-人工 | J108: 付昌吉市振安电子经销部施工费 | L108: 9000 | M108: =IFERROR(VLOOKUP($C108,$C$5:$M$24,11,0)+SUMIF($C$25:$C108,$C108,$K$25:$K108)-SUMIF($C$25:$C108,$C108,$L$25:$L108),"") -> 7014609.7 | R108: 示例：由2026年6月原表导入 | S108: =IF($B108="","",--TEXT($B108,"yyyymm")) -> 202601 | T108: =IF($B108="","",IF($P108="",$S108,IFERROR($P108*1,$P108))) -> 202601 | U108: =IF($B108="","",IF($T108=$S108,"","跨期")) | V108: =IF(AND($B108<>"",$F108<>"",$F108=项目明细账!$C$2),N(V107)+1,N(V107)) -> 0 | W108: =IF($H108<>"","项目成本",IFERROR(INDEX(基础资料!$W$4:$W$49,MATCH($I108,基础资料!$V$4:$V$49,0)),"")) -> 项目成本 | X108: =IFERROR(INDEX(基础资料!$R$4:$R$17,MATCH($G108,基础资料!$Q$4:$Q$17,0)),"")
A109: =IF($B109="","",COUNTA($B$5:$B109)) -> 105 | B109: 46041 | C109: 双思威农商行一般户 | D109: =IFERROR(INDEX(基础资料!$F$4:$F$23,MATCH($C109,基础资料!$E$4:$E$23,0)),IF($C109="","","未匹配账户")) -> 双思威 | E109: 支出 | F109: 昌吉市中小学数字化校园建设工程（昌吉市第十五小学教学仪器设备采购项目） | H109: 项目-人工 | J109: 付乌鲁木齐头屯河区芯智联电子设备经销部施工费 | L109: 6400 | M109: =IFERROR(VLOOKUP($C109,$C$5:$M$24,11,0)+SUMIF($C$25:$C109,$C109,$K$25:$K109)-SUMIF($C$25:$C109,$C109,$L$25:$L109),"") -> 7008209.7 | R109: 示例：由2026年6月原表导入 | S109: =IF($B109="","",--TEXT($B109,"yyyymm")) -> 202601 | T109: =IF($B109="","",IF($P109="",$S109,IFERROR($P109*1,$P109))) -> 202601 | U109: =IF($B109="","",IF($T109=$S109,"","跨期")) | V109: =IF(AND($B109<>"",$F109<>"",$F109=项目明细账!$C$2),N(V108)+1,N(V108)) -> 0 | W109: =IF($H109<>"","项目成本",IFERROR(INDEX(基础资料!$W$4:$W$49,MATCH($I109,基础资料!$V$4:$V$49,0)),"")) -> 项目成本 | X109: =IFERROR(INDEX(基础资料!$R$4:$R$17,MATCH($G109,基础资料!$Q$4:$Q$17,0)),"")
A110: =IF($B110="","",COUNTA($B$5:$B110)) -> 106 | B110: 46042 | C110: 双思威农商行一般户 | D110: =IFERROR(INDEX(基础资料!$F$4:$F$23,MATCH($C110,基础资料!$E$4:$E$23,0)),IF($C110="","","未匹配账户")) -> 双思威 | E110: 支出 | F110: 昌吉市中小学数字化校园建设工程（昌吉市第十五小学教学仪器设备采购项目） | H110: 项目-材料 | J110: 付新华互联电子商务有限责任公司图书 | L110: 55592 | M110: =IFERROR(VLOOKUP($C110,$C$5:$M$24,11,0)+SUMIF($C$25:$C110,$C110,$K$25:$K110)-SUMIF($C$25:$C110,$C110,$L$25:$L110),"") -> 6952617.7 | R110: 示例：由2026年6月原表导入 | S110: =IF($B110="","",--TEXT($B110,"yyyymm")) -> 202601 | T110: =IF($B110="","",IF($P110="",$S110,IFERROR($P110*1,$P110))) -> 202601 | U110: =IF($B110="","",IF($T110=$S110,"","跨期")) | V110: =IF(AND($B110<>"",$F110<>"",$F110=项目明细账!$C$2),N(V109)+1,N(V109)) -> 0 | W110: =IF($H110<>"","项目成本",IFERROR(INDEX(基础资料!$W$4:$W$49,MATCH($I110,基础资料!$V$4:$V$49,0)),"")) -> 项目成本 | X110: =IFERROR(INDEX(基础资料!$R$4:$R$17,MATCH($G110,基础资料!$Q$4:$Q$17,0)),"")
... A113: =IF($B113="","",COUNTA($B$5:$B113)) -> 109 | B113: 46042 | C113: 双思威农商行一般户 | D113: =IFERROR(INDEX(基础资料!$F$4:$F$23,MATCH($C113,基础资料!$E$4:$E$23,0)),IF($C113="","","未匹配账户")) -> 双思威 | E113: 支出 | F113: 昌吉市第二十一小学教育教学设备采购项目（三标段） | H113: 项目-材料 | J113: 付乌鲁木齐市米东区锦恒冠皮革布艺经营部软包 | L113: 2250 | M113: =IFERROR(VLOOKUP($C113,$C$5:$M$24,11,0)+SUMIF($C$25:$C113,$C113,$K$25:$K113)-SUMIF($C$25:$C113,$C113,$L$25:$L113),"") -> 6839534.7 | R113: 示例：由2026年6月原表导入 | S113: =IF($B113="","",--TEXT($B113,"yyyymm")) -> 202601 | T113: =IF($B113="","",IF($P113="",$S113,IFERROR($P113*1,$P113))) -> 202601 | U113: =IF($B113="","",IF($T113=$S113,"","跨期")) | V113: =IF(AND($B113<>"",$F113<>"",$F113=项目明细账!$C$2),N(V112)+1,N(V112)) -> 0 | W113: =IF($H113<>"","项目成本",IFERROR(INDEX(基础资料!$W$4:$W$49,MATCH($I113,基础资料!$V$4:$V$49,0)),"")) -> 项目成本 | X113: =IFERROR(INDEX(基础资料!$R$4:$R$17,MATCH($G113,基础资料!$Q$4:$Q$17,0)),"")
A114: =IF($B114="","",COUNTA($B$5:$B114)) -> 110 | B114: 46043 | C114: 双思威农商行一般户 | D114: =IFERROR(INDEX(基础资料!$F$4:$F$23,MATCH($C114,基础资料!$E$4:$E$23,0)),IF($C114="","","未匹配账户")) -> 双思威 | E114: 支出 | I114: 其他管理费用 | J114: 中石油新疆销售有限公司昌吉分公司 | L114: 10000 | M114: =IFERROR(VLOOKUP($C114,$C$5:$M$24,11,0)+SUMIF($C$25:$C114,$C114,$K$25:$K114)-SUMIF($C$25:$C114,$C114,$L$25:$L114),"") -> 6829534.7 | R114: 示例：由2026年6月原表导入 | S114: =IF($B114="","",--TEXT($B114,"yyyymm")) -> 202601 | T114: =IF($B114="","",IF($P114="",$S114,IFERROR($P114*1,$P114))) -> 202601 | U114: =IF($B114="","",IF($T114=$S114,"","跨期")) | V114: =IF(AND($B114<>"",$F114<>"",$F114=项目明细账!$C$2),N(V113)+1,N(V113)) -> 0 | W114: =IF($H114<>"","项目成本",IFERROR(INDEX(基础资料!$W$4:$W$49,MATCH($I114,基础资料!$V$4:$V$49,0)),"")) -> 管理费用 | X114: =IFERROR(INDEX(基础资料!$R$4:$R$17,MATCH($G114,基础资料!$Q$4:$Q$17,0)),"")
A115: =IF($B115="","",COUNTA($B$5:$B115)) -> 111 | B115: 46044 | C115: 双思威农商行一般户 | D115: =IFERROR(INDEX(基础资料!$F$4:$F$23,MATCH($C115,基础资料!$E$4:$E$23,0)),IF($C115="","","未匹配账户")) -> 双思威 | E115: 支出 | F115: 昌吉市中小学数字化校园建设工程（昌吉市第十五小学教学仪器设备采购项目） | H115: 项目-运费 | J115: 付北京知鸟供应链管理有限公司图书运费 | L115: 8951 | M115: =IFERROR(VLOOKUP($C115,$C$5:$M$24,11,0)+SUMIF($C$25:$C115,$C115,$K$25:$K115)-SUMIF($C$25:$C115,$C115,$L$25:$L115),"") -> 6820583.7 | R115: 示例：由2026年6月原表导入 | S115: =IF($B115="","",--TEXT($B115,"yyyymm")) -> 202601 | T115: =IF($B115="","",IF($P115="",$S115,IFERROR($P115*1,$P115))) -> 202601 | U115: =IF($B115="","",IF($T115=$S115,"","跨期")) | V115: =IF(AND($B115<>"",$F115<>"",$F115=项目明细账!$C$2),N(V114)+1,N(V114)) -> 0 | W115: =IF($H115<>"","项目成本",IFERROR(INDEX(基础资料!$W$4:$W$49,MATCH($I115,基础资料!$V$4:$V$49,0)),"")) -> 项目成本 | X115: =IFERROR(INDEX(基础资料!$R$4:$R$17,MATCH($G115,基础资料!$Q$4:$Q$17,0)),"")
A116: =IF($B116="","",COUNTA($B$5:$B116)) -> 112 | B116: 46046 | C116: 双思威农商行一般户 | D116: =IFERROR(INDEX(基础资料!$F$4:$F$23,MATCH($C116,基础资料!$E$4:$E$23,0)),IF($C116="","","未匹配账户")) -> 双思威 | E116: 支出 | F116: 代建局昌吉市第十八小学教学仪器设备采购项目 | H116: 项目-材料 | J116: 付昌吉市艺雅装饰设计工作室(个体工商户)辅材 | L116: 14000 | M116: =IFERROR(VLOOKUP($C116,$C$5:$M$24,11,0)+SUMIF($C$25:$C116,$C116,$K$25:$K116)-SUMIF($C$25:$C116,$C116,$L$25:$L116),"") -> 6806583.7 | R116: 示例：由2026年6月原表导入 | S116: =IF($B116="","",--TEXT($B116,"yyyymm")) -> 202601 | T116: =IF($B116="","",IF($P116="",$S116,IFERROR($P116*1,$P116))) -> 202601 | U116: =IF($B116="","",IF($T116=$S116,"","跨期")) | V116: =IF(AND($B116<>"",$F116<>"",$F116=项目明细账!$C$2),N(V115)+1,N(V115)) -> 0 | W116: =IF($H116<>"","项目成本",IFERROR(INDEX(基础资料!$W$4:$W$49,MATCH($I116,基础资料!$V$4:$V$49,0)),"")) -> 项目成本 | X116: =IFERROR(INDEX(基础资料!$R$4:$R$17,MATCH($G116,基础资料!$Q$4:$Q$17,0)),"")
A117: =IF($B117="","",COUNTA($B$5:$B117)) -> 113 | B117: 46046 | C117: 双思威农商行一般户 | D117: =IFERROR(INDEX(基础资料!$F$4:$F$23,MATCH($C117,基础资料!$E$4:$E$23,0)),IF($C117="","","未匹配账户")) -> 双思威 | E117: 支出 | F117: 代建局昌吉市第十八小学教学仪器设备采购项目 | H117: 项目-材料 | J117: 付上海美冠办公家具有限公司演播台 | L117: 2550 | M117: =IFERROR(VLOOKUP($C117,$C$5:$M$24,11,0)+SUMIF($C$25:$C117,$C117,$K$25:$K117)-SUMIF($C$25:$C117,$C117,$L$25:$L117),"") -> 6804033.7 | R117: 示例：由2026年6月原表导入 | S117: =IF($B117="","",--TEXT($B117,"yyyymm")) -> 202601 | T117: =IF($B117="","",IF($P117="",$S117,IFERROR($P117*1,$P117))) -> 202601 | U117: =IF($B117="","",IF($T117=$S117,"","跨期")) | V117: =IF(AND($B117<>"",$F117<>"",$F117=项目明细账!$C$2),N(V116)+1,N(V116)) -> 0 | W117: =IF($H117<>"","项目成本",IFERROR(INDEX(基础资料!$W$4:$W$49,MATCH($I117,基础资料!$V$4:$V$49,0)),"")) -> 项目成本 | X117: =IFERROR(INDEX(基础资料!$R$4:$R$17,MATCH($G117,基础资料!$Q$4:$Q$17,0)),"")
A118: =IF($B118="","",COUNTA($B$5:$B118)) -> 114 | B118: 46046 | C118: 双思威农商行一般户 | D118: =IFERROR(INDEX(基础资料!$F$4:$F$23,MATCH($C118,基础资料!$E$4:$E$23,0)),IF($C118="","","未匹配账户")) -> 双思威 | E118: 支出 | F118: 第四师第一中学高中地理实验室设施设备采购项目 | H118: 项目-材料 | J118: 付新疆翼企飞航空科技有限公司大疆无人机，口袋摄像机 | L118: 17918 | M118: =IFERROR(VLOOKUP($C118,$C$5:$M$24,11,0)+SUMIF($C$25:$C118,$C118,$K$25:$K118)-SUMIF($C$25:$C118,$C118,$L$25:$L118),"") -> 6786115.7 | R118: 示例：由2026年6月原表导入 | S118: =IF($B118="","",--TEXT($B118,"yyyymm")) -> 202601 | T118: =IF($B118="","",IF($P118="",$S118,IFERROR($P118*1,$P118))) -> 202601 | U118: =IF($B118="","",IF($T118=$S118,"","跨期")) | V118: =IF(AND($B118<>"",$F118<>"",$F118=项目明细账!$C$2),N(V117)+1,N(V117)) -> 0 | W118: =IF($H118<>"","项目成本",IFERROR(INDEX(基础资料!$W$4:$W$49,MATCH($I118,基础资料!$V$4:$V$49,0)),"")) -> 项目成本 | X118: =IFERROR(INDEX(基础资料!$R$4:$R$17,MATCH($G118,基础资料!$Q$4:$Q$17,0)),"")
A119: =IF($B119="","",COUNTA($B$5:$B119)) -> 115 | B119: 46049 | C119: 双思威农商行一般户 | D119: =IFERROR(INDEX(基础资料!$F$4:$F$23,MATCH($C119,基础资料!$E$4:$E$23,0)),IF($C119="","","未匹配账户")) -> 双思威 | E119: 支出 | I119: 其他管理费用 | J119: 付铁门关市小耿汽车修理店维修费 | L119: 1645 | M119: =IFERROR(VLOOKUP($C119,$C$5:$M$24,11,0)+SUMIF($C$25:$C119,$C119,$K$25:$K119)-SUMIF($C$25:$C119,$C119,$L$25:$L119),"") -> 6784470.7 | R119: 示例：由2026年6月原表导入 | S119: =IF($B119="","",--TEXT($B119,"yyyymm")) -> 202601 | T119: =IF($B119="","",IF($P119="",$S119,IFERROR($P119*1,$P119))) -> 202601 | U119: =IF($B119="","",IF($T119=$S119,"","跨期")) | V119: =IF(AND($B119<>"",$F119<>"",$F119=项目明细账!$C$2),N(V118)+1,N(V118)) -> 0 | W119: =IF($H119<>"","项目成本",IFERROR(INDEX(基础资料!$W$4:$W$49,MATCH($I119,基础资料!$V$4:$V$49,0)),"")) -> 管理费用 | X119: =IFERROR(INDEX(基础资料!$R$4:$R$17,MATCH($G119,基础资料!$Q$4:$Q$17,0)),"")
A120: =IF($B120="","",COUNTA($B$5:$B120)) -> 116 | B120: 46049 | C120: 双思威农商行一般户 | D120: =IFERROR(INDEX(基础资料!$F$4:$F$23,MATCH($C120,基础资料!$E$4:$E$23,0)),IF($C120="","","未匹配账户")) -> 双思威 | E120: 支出 | I120: 其他管理费用 | J120: 付库尔勒经济技术开发区建宏汽车养护服务中心维修费 | L120: 3810 | M120: =IFERROR(VLOOKUP($C120,$C$5:$M$24,11,0)+SUMIF($C$25:$C120,$C120,$K$25:$K120)-SUMIF($C$25:$C120,$C120,$L$25:$L120),"") -> 6780660.7 | R120: 示例：由2026年6月原表导入 | S120: =IF($B120="","",--TEXT($B120,"yyyymm")) -> 202601 | T120: =IF($B120="","",IF($P120="",$S120,IFERROR($P120*1,$P120))) -> 202601 | U120: =IF($B120="","",IF($T120=$S120,"","跨期")) | V120: =IF(AND($B120<>"",$F120<>"",$F120=项目明细账!$C$2),N(V119)+1,N(V119)) -> 0 | W120: =IF($H120<>"","项目成本",IFERROR(INDEX(基础资料!$W$4:$W$49,MATCH($I120,基础资料!$V$4:$V$49,0)),"")) -> 管理费用 | X120: =IFERROR(INDEX(基础资料!$R$4:$R$17,MATCH($G120,基础资料!$Q$4:$Q$17,0)),"")
A121: =IF($B121="","",COUNTA($B$5:$B121)) -> 117 | B121: 46049 | C121: 双思威农商行一般户 | D121: =IFERROR(INDEX(基础资料!$F$4:$F$23,MATCH($C121,基础资料!$E$4:$E$23,0)),IF($C121="","","未匹配账户")) -> 双思威 | E121: 支出 | F121: 李广新昌吉市第十六小学教学仪器设备采购 | H121: 项目-材料 | J121: 付齐鲁宏博教育装备集团有限公司教学仪器设备 | L121: 1150 | M121: =IFERROR(VLOOKUP($C121,$C$5:$M$24,11,0)+SUMIF($C$25:$C121,$C121,$K$25:$K121)-SUMIF($C$25:$C121,$C121,$L$25:$L121),"") -> 6779510.7 | R121: 示例：由2026年6月原表导入 | S121: =IF($B121="","",--TEXT($B121,"yyyymm")) -> 202601 | T121: =IF($B121="","",IF($P121="",$S121,IFERROR($P121*1,$P121))) -> 202601 | U121: =IF($B121="","",IF($T121=$S121,"","跨期")) | V121: =IF(AND($B121<>"",$F121<>"",$F121=项目明细账!$C$2),N(V120)+1,N(V120)) -> 0 | W121: =IF($H121<>"","项目成本",IFERROR(INDEX(基础资料!$W$4:$W$49,MATCH($I121,基础资料!$V$4:$V$49,0)),"")) -> 项目成本 | X121: =IFERROR(INDEX(基础资料!$R$4:$R$17,MATCH($G121,基础资料!$Q$4:$Q$17,0)),"")
A122: =IF($B122="","",COUNTA($B$5:$B122)) -> 118 | B122: 46050 | C122: 双思威农商行一般户 | D122: =IFERROR(INDEX(基础资料!$F$4:$F$23,MATCH($C122,基础资料!$E$4:$E$23,0)),IF($C122="","","未匹配账户")) -> 双思威 | E122: 支出 | F122: 昌吉市第二十一小学教育教学设备采购项目（三标段） | H122: 项目-材料 | J122: 付乌鲁木齐市米东区锦恒冠皮革布艺经营部软包 | L122: 2250 | M122: =IFERROR(VLOOKUP($C122,$C$5:$M$24,11,0)+SUMIF($C$25:$C122,$C122,$K$25:$K122)-SUMIF($C$25:$C122,$C122,$L$25:$L122),"") -> 6777260.7 | R122: 示例：由2026年6月原表导入 | S122: =IF($B122="","",--TEXT($B122,"yyyymm")) -> 202601 | T122: =IF($B122="","",IF($P122="",$S122,IFERROR($P122*1,$P122))) -> 202601 | U122: =IF($B122="","",IF($T122=$S122,"","跨期")) | V122: =IF(AND($B122<>"",$F122<>"",$F122=项目明细账!$C$2),N(V121)+1,N(V121)) -> 0 | W122: =IF($H122<>"","项目成本",IFERROR(INDEX(基础资料!$W$4:$W$49,MATCH($I122,基础资料!$V$4:$V$49,0)),"")) -> 项目成本 | X122: =IFERROR(INDEX(基础资料!$R$4:$R$17,MATCH($G122,基础资料!$Q$4:$Q$17,0)),"")
...

Sheet 应收应付台账
A1: 应收 / 应付台账 — 只登记月末尚未结算的跨期款项
A2: 应收余额合计 | C2: =SUMIFS($L$5:$L$304,$B$5:$B$304,"应收") -> #VALUE! | D2: 应付余额合计 | F2: =SUMIFS($L$5:$L$304,$B$5:$B$304,"应付") -> #VALUE! | G2: 净往来（应收-应付） | I2: =$C$2-$F$2 -> #VALUE!
A3: 登记规则：①贵司应收应付很少、基本当月收付，所以这张表只登“月末没收/没付完”的那几笔。②I列“关联单号”是核销的钥匙：下月实际收付时，在“资金流水”Q列填同一个单号，J列自动冲减。③零星、没法用单号对上的，直接在K列手工冲销。④F列“业务归属月”决定这笔算哪个月的损益。
A4: 序号 | B4: 类型 | C4: 公司 | D4: 往来单位 | E4: 项目名称 | F4: 业务归属月 | G4: 确认日期 | H4: 金额 | I4: 关联单号 | J4: 已结算 (按单号自动) | K4: 手工冲销 | L4: 未结算余额 | M4: 状态 | N4: 账龄(天) | O4: 预计结算日 | P4: 备注
A5: =IF($D5="","",COUNTA($D$5:$D5)) -> 1 | B5: 应收 | C5: 双思威 | D5: 客户3 | E5: 2025年结转项目 | F5: 202512 | G5: 45981 | H5: 300000 | I5: FP2025110001 | J5: =IF($I5="","",IF($B5="应收",SUMIFS(资金流水!$K$5:$K$3032,资金流水!$Q$5:$Q$3015,$I5),SUMIFS(资金流水!$L$5:$L$3032,资金流水!$Q$5:$Q$3015,$I5))) -> #VALUE! | L5: =IF($H5="","",ROUND($H5-IF($J5="",0,$J5)-IF($K5="",0,$K5),2)) -> #VALUE! | M5: =IF($H5="","",IF($L5<=0.005,"已结清",IF($L5<$H5,"部分结算","未结算"))) -> #VALUE! | N5: =IF(OR($G5="",$L5="",$L5<=0.005),"",TODAY()-$G5) -> #VALUE! | O5: 46295 | P5: ★示例：去年开票、今年才收回的尾款
A6: =IF($D6="","",COUNTA($D$5:$D6)) -> 2 | B6: 应付 | C6: 中 | D6: 供应商1 | E6: 2025年结转项目 | F6: 202512 | G6: 46019 | H6: 50000 | I6: YF202512001 | J6: =IF($I6="","",IF($B6="应收",SUMIFS(资金流水!$K$5:$K$3032,资金流水!$Q$5:$Q$3015,$I6),SUMIFS(资金流水!$L$5:$L$3032,资金流水!$Q$5:$Q$3015,$I6))) -> #VALUE! | L6: =IF($H6="","",ROUND($H6-IF($J6="",0,$J6)-IF($K6="",0,$K6),2)) -> #VALUE! | M6: =IF($H6="","",IF($L6<=0.005,"已结清",IF($L6<$H6,"部分结算","未结算"))) -> #VALUE! | N6: =IF(OR($G6="",$L6="",$L6<=0.005),"",TODAY()-$G6) -> #VALUE! | O6: 46203 | P6: ★示例：去年发生、今年才付的材料款
A7: =IF($D7="","",COUNTA($D$5:$D7)) | J7: =IF($I7="","",IF($B7="应收",SUMIFS(资金流水!$K$5:$K$3032,资金流水!$Q$5:$Q$3015,$I7),SUMIFS(资金流水!$L$5:$L$3032,资金流水!$Q$5:$Q$3015,$I7))) | L7: =IF($H7="","",ROUND($H7-IF($J7="",0,$J7)-IF($K7="",0,$K7),2)) | M7: =IF($H7="","",IF($L7<=0.005,"已结清",IF($L7<$H7,"部分结算","未结算"))) | N7: =IF(OR($G7="",$L7="",$L7<=0.005),"",TODAY()-$G7)
A8: =IF($D8="","",COUNTA($D$5:$D8)) | J8: =IF($I8="","",IF($B8="应收",SUMIFS(资金流水!$K$5:$K$3032,资金流水!$Q$5:$Q$3015,$I8),SUMIFS(资金流水!$L$5:$L$3032,资金流水!$Q$5:$Q$3015,$I8))) | L8: =IF($H8="","",ROUND($H8-IF($J8="",0,$J8)-IF($K8="",0,$K8),2)) | M8: =IF($H8="","",IF($L8<=0.005,"已结清",IF($L8<$H8,"部分结算","未结算"))) | N8: =IF(OR($G8="",$L8="",$L8<=0.005),"",TODAY()-$G8)
A9: =IF($D9="","",COUNTA($D$5:$D9)) | J9: =IF($I9="","",IF($B9="应收",SUMIFS(资金流水!$K$5:$K$3032,资金流水!$Q$5:$Q$3015,$I9),SUMIFS(资金流水!$L$5:$L$3032,资金流水!$Q$5:$Q$3015,$I9))) | L9: =IF($H9="","",ROUND($H9-IF($J9="",0,$J9)-IF($K9="",0,$K9),2)) | M9: =IF($H9="","",IF($L9<=0.005,"已结清",IF($L9<$H9,"部分结算","未结算"))) | N9: =IF(OR($G9="",$L9="",$L9<=0.005),"",TODAY()-$G9)
A10: =IF($D10="","",COUNTA($D$5:$D10)) | J10: =IF($I10="","",IF($B10="应收",SUMIFS(资金流水!$K$5:$K$3032,资金流水!$Q$5:$Q$3015,$I10),SUMIFS(资金流水!$L$5:$L$3032,资金流水!$Q$5:$Q$3015,$I10))) | L10: =IF($H10="","",ROUND($H10-IF($J10="",0,$J10)-IF($K10="",0,$K10),2)) | M10: =IF($H10="","",IF($L10<=0.005,"已结清",IF($L10<$H10,"部分结算","未结算"))) | N10: =IF(OR($G10="",$L10="",$L10<=0.005),"",TODAY()-$G10)
A11: =IF($D11="","",COUNTA($D$5:$D11)) | J11: =IF($I11="","",IF($B11="应收",SUMIFS(资金流水!$K$5:$K$3032,资金流水!$Q$5:$Q$3015,$I11),SUMIFS(资金流水!$L$5:$L$3032,资金流水!$Q$5:$Q$3015,$I11))) | L11: =IF($H11="","",ROUND($H11-IF($J11="",0,$J11)-IF($K11="",0,$K11),2)) | M11: =IF($H11="","",IF($L11<=0.005,"已结清",IF($L11<$H11,"部分结算","未结算"))) | N11: =IF(OR($G11="",$L11="",$L11<=0.005),"",TODAY()-$G11)
A12: =IF($D12="","",COUNTA($D$5:$D12)) | J12: =IF($I12="","",IF($B12="应收",SUMIFS(资金流水!$K$5:$K$3032,资金流水!$Q$5:$Q$3015,$I12),SUMIFS(资金流水!$L$5:$L$3032,资金流水!$Q$5:$Q$3015,$I12))) | L12: =IF($H12="","",ROUND($H12-IF($J12="",0,$J12)-IF($K12="",0,$K12),2)) | M12: =IF($H12="","",IF($L12<=0.005,"已结清",IF($L12<$H12,"部分结算","未结算"))) | N12: =IF(OR($G12="",$L12="",$L12<=0.005),"",TODAY()-$G12)
A13: =IF($D13="","",COUNTA($D$5:$D13)) | J13: =IF($I13="","",IF($B13="应收",SUMIFS(资金流水!$K$5:$K$3032,资金流水!$Q$5:$Q$3015,$I13),SUMIFS(资金流水!$L$5:$L$3032,资金流水!$Q$5:$Q$3015,$I13))) | L13: =IF($H13="","",ROUND($H13-IF($J13="",0,$J13)-IF($K13="",0,$K13),2)) | M13: =IF($H13="","",IF($L13<=0.005,"已结清",IF($L13<$H13,"部分结算","未结算"))) | N13: =IF(OR($G13="",$L13="",$L13<=0.005),"",TODAY()-$G13)
A14: =IF($D14="","",COUNTA($D$5:$D14)) | J14: =IF($I14="","",IF($B14="应收",SUMIFS(资金流水!$K$5:$K$3032,资金流水!$Q$5:$Q$3015,$I14),SUMIFS(资金流水!$L$5:$L$3032,资金流水!$Q$5:$Q$3015,$I14))) | L14: =IF($H14="","",ROUND($H14-IF($J14="",0,$J14)-IF($K14="",0,$K14),2)) | M14: =IF($H14="","",IF($L14<=0.005,"已结清",IF($L14<$H14,"部分结算","未结算"))) | N14: =IF(OR($G14="",$L14="",$L14<=0.005),"",TODAY()-$G14)
A15: =IF($D15="","",COUNTA($D$5:$D15)) | J15: =IF($I15="","",IF($B15="应收",SUMIFS(资金流水!$K$5:$K$3032,资金流水!$Q$5:$Q$3015,$I15),SUMIFS(资金流水!$L$5:$L$3032,资金流水!$Q$5:$Q$3015,$I15))) | L15: =IF($H15="","",ROUND($H15-IF($J15="",0,$J15)-IF($K15="",0,$K15),2)) | M15: =IF($H15="","",IF($L15<=0.005,"已结清",IF($L15<$H15,"部分结算","未结算"))) | N15: =IF(OR($G15="",$L15="",$L15<=0.005),"",TODAY()-$G15)
A16: =IF($D16="","",COUNTA($D$5:$D16)) | J16: =IF($I16="","",IF($B16="应收",SUMIFS(资金流水!$K$5:$K$3032,资金流水!$Q$5:$Q$3015,$I16),SUMIFS(资金流水!$L$5:$L$3032,资金流水!$Q$5:$Q$3015,$I16))) | L16: =IF($H16="","",ROUND($H16-IF($J16="",0,$J16)-IF($K16="",0,$K16),2)) | M16: =IF($H16="","",IF($L16<=0.005,"已结清",IF($L16<$H16,"部分结算","未结算"))) | N16: =IF(OR($G16="",$L16="",$L16<=0.005),"",TODAY()-$G16)
A17: =IF($D17="","",COUNTA($D$5:$D17)) | J17: =IF($I17="","",IF($B17="应收",SUMIFS(资金流水!$K$5:$K$3032,资金流水!$Q$5:$Q$3015,$I17),SUMIFS(资金流水!$L$5:$L$3032,资金流水!$Q$5:$Q$3015,$I17))) | L17: =IF($H17="","",ROUND($H17-IF($J17="",0,$J17)-IF($K17="",0,$K17),2)) | M17: =IF($H17="","",IF($L17<=0.005,"已结清",IF($L17<$H17,"部分结算","未结算"))) | N17: =IF(OR($G17="",$L17="",$L17<=0.005),"",TODAY()-$G17)
A18: =IF($D18="","",COUNTA($D$5:$D18)) | J18: =IF($I18="","",IF($B18="应收",SUMIFS(资金流水!$K$5:$K$3032,资金流水!$Q$5:$Q$3015,$I18),SUMIFS(资金流水!$L$5:$L$3032,资金流水!$Q$5:$Q$3015,$I18))) | L18: =IF($H18="","",ROUND($H18-IF($J18="",0,$J18)-IF($K18="",0,$K18),2)) | M18: =IF($H18="","",IF($L18<=0.005,"已结清",IF($L18<$H18,"部分结算","未结算"))) | N18: =IF(OR($G18="",$L18="",$L18<=0.005),"",TODAY()-$G18)
... A304: =IF($D304="","",COUNTA($D$5:$D304)) | J304: =IF($I304="","",IF($B304="应收",SUMIFS(资金流水!$K$5:$K$3032,资金流水!$Q$5:$Q$3015,$I304),SUMIFS(资金流水!$L$5:$L$3032,资金流水!$Q$5:$Q$3015,$I304))) | L304: =IF($H304="","",ROUND($H304-IF($J304="",0,$J304)-IF($K304="",0,$K304),2)) | M304: =IF($H304="","",IF($L304<=0.005,"已结清",IF($L304<$H304,"部分结算","未结算"))) | N304: =IF(OR($G304="",$L304="",$L304<=0.005),"",TODAY()-$G304)

Sheet 项目核算表
A1: 项目核算表 — 每个项目的收入、成本、毛利、收款进度（全自动，无需录入）
A2: 本表全部自动生成：项目档案来自“基础资料”；收入取自「开票登记」（口径由 基础资料!AH4 控制），成本取自「资金流水」按项目名称汇总；成本列头随“基础资料→成本类别”自动变化。项目毛利 = 累计开票 − 成本合计（开票口径）；预计毛利 = 合同金额 − 已发生成本；“累计收款”只反映回款进度，不参与毛利。注意：只有填了“成本类别”的支出才计入项目成本；挂在项目名下但填“费用类别”的支出（如工资、招待费）不进成本，要看该项目的全部现金进出请到「项目明细账」看“项目净现金流”。
A4: 项目编号 | B4: 项目名称 | C4: 所属公司 | D4: 客户 | E4: 合同金额 | F4: 累计开票 (收入口径) | G4: 累计收款 | H4: 合同未收款 | I4: 已开票未收款 (含税) | J4: =IF(基础资料!$T$4="","",基础资料!$T$4) -> 项目-材料 | K4: =IF(基础资料!$T$5="","",基础资料!$T$5) -> 项目-人工 | L4: =IF(基础资料!$T$6="","",基础资料!$T$6) -> 项目-机械设备 | M4: =IF(基础资料!$T$7="","",基础资料!$T$7) -> 项目-零星开支 | N4: =IF(基础资料!$T$8="","",基础资料!$T$8) -> 项目-运费 | O4: =IF(基础资料!$T$9="","",基础资料!$T$9) -> 项目-分包/劳务 | P4: =IF(基础资料!$T$10="","",基础资料!$T$10) -> 项目-税款 | Q4: =IF(基础资料!$T$11="","",基础资料!$T$11) -> 项目-其他直接成本 | R4: =IF(基础资料!$T$12="","",基础资料!$T$12) -> 费用摊销 | S4: =IF(基础资料!$T$13="","",基础资料!$T$13) | T4: =IF(基础资料!$T$14="","",基础资料!$T$14) | U4: =IF(基础资料!$T$15="","",基础资料!$T$15) | V4: =IF(基础资料!$T$16="","",基础资料!$T$16) | W4: =IF(基础资料!$T$17="","",基础资料!$T$17) | X4: 成本合计 | Y4: 项目毛利 (开票-成本) | Z4: 毛利率 | AA4: 预计毛利 (合同-已发生成本) | AB4: 收款进度 | AC4: 项目状态
A5: =IF(基础资料!$I4="","",基础资料!$I4) -> P001 | B5: =IF(基础资料!$J4="","",基础资料!$J4) -> 昌吉市中小学数字化校园建设工程（昌吉市第十五小学教学仪器设备采购项目） | C5: =IF(基础资料!$K4="","",基础资料!$K4) -> 双思威 | D5: =IF(基础资料!$L4="","",基础资料!$L4) -> 中移系统集成有限公司 | E5: =IF(基础资料!$M4="","",基础资料!$M4) -> 7443095.2 | F5: =IF($B5="","",IF(基础资料!$AH$4="不含税金额",SUMIFS(开票登记!$J$5:$J$504,开票登记!$G$5:$G$504,$B5),SUMIFS(开票登记!$M$5:$M$504,开票登记!$G$5:$G$504,$B5))) -> 0 | G5: =IF($B5="","",SUMIFS(资金流水!$K$5:$K$3032,资金流水!$F$5:$F$3032,$B5)) -> 0 | H5: =IF(OR($B5="",$E5=""),"",$E5-$G5) -> 7443095.2 | I5: =IF($B5="","",SUMIFS(开票登记!$M$5:$M$504,开票登记!$G$5:$G$504,$B5)-$G5) -> 0 | J5: =IF(OR($B5="",J$4=""),"",SUMIFS(资金流水!$L$5:$L$3032,资金流水!$F$5:$F$3032,$B5,资金流水!$H$5:$H$3032,J$4)) -> 391660.71 | K5: =IF(OR($B5="",K$4=""),"",SUMIFS(资金流水!$L$5:$L$3032,资金流水!$F$5:$F$3032,$B5,资金流水!$H$5:$H$3032,K$4)) -> 39453 | L5: =IF(OR($B5="",L$4=""),"",SUMIFS(资金流水!$L$5:$L$3032,资金流水!$F$5:$F$3032,$B5,资金流水!$H$5:$H$3032,L$4)) -> 0 | M5: =IF(OR($B5="",M$4=""),"",SUMIFS(资金流水!$L$5:$L$3032,资金流水!$F$5:$F$3032,$B5,资金流水!$H$5:$H$3032,M$4)) -> 0 | N5: =IF(OR($B5="",N$4=""),"",SUMIFS(资金流水!$L$5:$L$3032,资金流水!$F$5:$F$3032,$B5,资金流水!$H$5:$H$3032,N$4)) -> 8951 | O5: =IF(OR($B5="",O$4=""),"",SUMIFS(资金流水!$L$5:$L$3032,资金流水!$F$5:$F$3032,$B5,资金流水!$H$5:$H$3032,O$4)) -> 0 | P5: =IF(OR($B5="",P$4=""),"",SUMIFS(资金流水!$L$5:$L$3032,资金流水!$F$5:$F$3032,$B5,资金流水!$H$5:$H$3032,P$4)) -> 0 | Q5: =IF(OR($B5="",Q$4=""),"",SUMIFS(资金流水!$L$5:$L$3032,资金流水!$F$5:$F$3032,$B5,资金流水!$H$5:$H$3032,Q$4)) -> 0 | ... W5: =IF(OR($B5="",W$4=""),"",SUMIFS(资金流水!$L$5:$L$3032,资金流水!$F$5:$F$3032,$B5,资金流水!$H$5:$H$3032,W$4)) | X5: =IF($B5="","",SUM($J5:$W5)) -> 440064.71 | Y5: =IF($B5="","",$F5-$X5) -> -440064.71 | Z5: =IFERROR($Y5/$F5,"") | AA5: =IF(OR($B5="",$E5=""),"",$E5-$X5) -> 7003030.5 | AB5: =IFERROR($G5/$E5,"") -> 0 | AC5: =IF(基础资料!$O4="","",基础资料!$O4) -> 在建
A6: =IF(基础资料!$I5="","",基础资料!$I5) -> P002 | B6: =IF(基础资料!$J5="","",基础资料!$J5) -> 昌吉市中小学数字化校园建设工程（昌吉市第十八小学教学仪器设备采购项目） | C6: =IF(基础资料!$K5="","",基础资料!$K5) -> 双思威 | D6: =IF(基础资料!$L5="","",基础资料!$L5) -> 昌吉代建局 | E6: =IF(基础资料!$M5="","",基础资料!$M5) -> 7790000 | F6: =IF($B6="","",IF(基础资料!$AH$4="不含税金额",SUMIFS(开票登记!$J$5:$J$504,开票登记!$G$5:$G$504,$B6),SUMIFS(开票登记!$M$5:$M$504,开票登记!$G$5:$G$504,$B6))) -> 0 | G6: =IF($B6="","",SUMIFS(资金流水!$K$5:$K$3032,资金流水!$F$5:$F$3032,$B6)) -> 0 | H6: =IF(OR($B6="",$E6=""),"",$E6-$G6) -> 7790000 | I6: =IF($B6="","",SUMIFS(开票登记!$M$5:$M$504,开票登记!$G$5:$G$504,$B6)-$G6) -> 0 | J6: =IF(OR($B6="",J$4=""),"",SUMIFS(资金流水!$L$5:$L$3032,资金流水!$F$5:$F$3032,$B6,资金流水!$H$5:$H$3032,J$4)) -> 0 | K6: =IF(OR($B6="",K$4=""),"",SUMIFS(资金流水!$L$5:$L$3032,资金流水!$F$5:$F$3032,$B6,资金流水!$H$5:$H$3032,K$4)) -> 0 | L6: =IF(OR($B6="",L$4=""),"",SUMIFS(资金流水!$L$5:$L$3032,资金流水!$F$5:$F$3032,$B6,资金流水!$H$5:$H$3032,L$4)) -> 0 | M6: =IF(OR($B6="",M$4=""),"",SUMIFS(资金流水!$L$5:$L$3032,资金流水!$F$5:$F$3032,$B6,资金流水!$H$5:$H$3032,M$4)) -> 0 | N6: =IF(OR($B6="",N$4=""),"",SUMIFS(资金流水!$L$5:$L$3032,资金流水!$F$5:$F$3032,$B6,资金流水!$H$5:$H$3032,N$4)) -> 0 | O6: =IF(OR($B6="",O$4=""),"",SUMIFS(资金流水!$L$5:$L$3032,资金流水!$F$5:$F$3032,$B6,资金流水!$H$5:$H$3032,O$4)) -> 0 | P6: =IF(OR($B6="",P$4=""),"",SUMIFS(资金流水!$L$5:$L$3032,资金流水!$F$5:$F$3032,$B6,资金流水!$H$5:$H$3032,P$4)) -> 0 | Q6: =IF(OR($B6="",Q$4=""),"",SUMIFS(资金流水!$L$5:$L$3032,资金流水!$F$5:$F$3032,$B6,资金流水!$H$5:$H$3032,Q$4)) -> 0 | ... W6: =IF(OR($B6="",W$4=""),"",SUMIFS(资金流水!$L$5:$L$3032,资金流水!$F$5:$F$3032,$B6,资金流水!$H$5:$H$3032,W$4)) | X6: =IF($B6="","",SUM($J6:$W6)) -> 0 | Y6: =IF($B6="","",$F6-$X6) -> 0 | Z6: =IFERROR($Y6/$F6,"") | AA6: =IF(OR($B6="",$E6=""),"",$E6-$X6) -> 7790000 | AB6: =IFERROR($G6/$E6,"") -> 0 | AC6: =IF(基础资料!$O5="","",基础资料!$O5) -> 在建
A7: =IF(基础资料!$I6="","",基础资料!$I6) -> P003 | B7: =IF(基础资料!$J6="","",基础资料!$J6) | C7: =IF(基础资料!$K6="","",基础资料!$K6) -> 双思威 | D7: =IF(基础资料!$L6="","",基础资料!$L6) | E7: =IF(基础资料!$M6="","",基础资料!$M6) | F7: =IF($B7="","",IF(基础资料!$AH$4="不含税金额",SUMIFS(开票登记!$J$5:$J$504,开票登记!$G$5:$G$504,$B7),SUMIFS(开票登记!$M$5:$M$504,开票登记!$G$5:$G$504,$B7))) | G7: =IF($B7="","",SUMIFS(资金流水!$K$5:$K$3032,资金流水!$F$5:$F$3032,$B7)) | H7: =IF(OR($B7="",$E7=""),"",$E7-$G7) | I7: =IF($B7="","",SUMIFS(开票登记!$M$5:$M$504,开票登记!$G$5:$G$504,$B7)-$G7) | J7: =IF(OR($B7="",J$4=""),"",SUMIFS(资金流水!$L$5:$L$3032,资金流水!$F$5:$F$3032,$B7,资金流水!$H$5:$H$3032,J$4)) | K7: =IF(OR($B7="",K$4=""),"",SUMIFS(资金流水!$L$5:$L$3032,资金流水!$F$5:$F$3032,$B7,资金流水!$H$5:$H$3032,K$4)) | L7: =IF(OR($B7="",L$4=""),"",SUMIFS(资金流水!$L$5:$L$3032,资金流水!$F$5:$F$3032,$B7,资金流水!$H$5:$H$3032,L$4)) | M7: =IF(OR($B7="",M$4=""),"",SUMIFS(资金流水!$L$5:$L$3032,资金流水!$F$5:$F$3032,$B7,资金流水!$H$5:$H$3032,M$4)) | N7: =IF(OR($B7="",N$4=""),"",SUMIFS(资金流水!$L$5:$L$3032,资金流水!$F$5:$F$3032,$B7,资金流水!$H$5:$H$3032,N$4)) | O7: =IF(OR($B7="",O$4=""),"",SUMIFS(资金流水!$L$5:$L$3032,资金流水!$F$5:$F$3032,$B7,资金流水!$H$5:$H$3032,O$4)) | P7: =IF(OR($B7="",P$4=""),"",SUMIFS(资金流水!$L$5:$L$3032,资金流水!$F$5:$F$3032,$B7,资金流水!$H$5:$H$3032,P$4)) | Q7: =IF(OR($B7="",Q$4=""),"",SUMIFS(资金流水!$L$5:$L$3032,资金流水!$F$5:$F$3032,$B7,资金流水!$H$5:$H$3032,Q$4)) | ... W7: =IF(OR($B7="",W$4=""),"",SUMIFS(资金流水!$L$5:$L$3032,资金流水!$F$5:$F$3032,$B7,资金流水!$H$5:$H$3032,W$4)) | X7: =IF($B7="","",SUM($J7:$W7)) | Y7: =IF($B7="","",$F7-$X7) | Z7: =IFERROR($Y7/$F7,"") | AA7: =IF(OR($B7="",$E7=""),"",$E7-$X7) | AB7: =IFERROR($G7/$E7,"") | AC7: =IF(基础资料!$O6="","",基础资料!$O6) -> 已完工待收款
A8: =IF(基础资料!$I7="","",基础资料!$I7) | B8: =IF(基础资料!$J7="","",基础资料!$J7) -> 李广新昌吉市第十六小学教学仪器设备采购 | C8: =IF(基础资料!$K7="","",基础资料!$K7) -> 双思威 | D8: =IF(基础资料!$L7="","",基础资料!$L7) -> 新疆新广立科技有限公司 | E8: =IF(基础资料!$M7="","",基础资料!$M7) -> 6210476.1 | F8: =IF($B8="","",IF(基础资料!$AH$4="不含税金额",SUMIFS(开票登记!$J$5:$J$504,开票登记!$G$5:$G$504,$B8),SUMIFS(开票登记!$M$5:$M$504,开票登记!$G$5:$G$504,$B8))) -> 0 | G8: =IF($B8="","",SUMIFS(资金流水!$K$5:$K$3032,资金流水!$F$5:$F$3032,$B8)) -> 0 | H8: =IF(OR($B8="",$E8=""),"",$E8-$G8) -> 6210476.1 | I8: =IF($B8="","",SUMIFS(开票登记!$M$5:$M$504,开票登记!$G$5:$G$504,$B8)-$G8) -> 0 | J8: =IF(OR($B8="",J$4=""),"",SUMIFS(资金流水!$L$5:$L$3032,资金流水!$F$5:$F$3032,$B8,资金流水!$H$5:$H$3032,J$4)) -> 147063.5 | K8: =IF(OR($B8="",K$4=""),"",SUMIFS(资金流水!$L$5:$L$3032,资金流水!$F$5:$F$3032,$B8,资金流水!$H$5:$H$3032,K$4)) -> 73839 | L8: =IF(OR($B8="",L$4=""),"",SUMIFS(资金流水!$L$5:$L$3032,资金流水!$F$5:$F$3032,$B8,资金流水!$H$5:$H$3032,L$4)) -> 0 | M8: =IF(OR($B8="",M$4=""),"",SUMIFS(资金流水!$L$5:$L$3032,资金流水!$F$5:$F$3032,$B8,资金流水!$H$5:$H$3032,M$4)) -> 0 | N8: =IF(OR($B8="",N$4=""),"",SUMIFS(资金流水!$L$5:$L$3032,资金流水!$F$5:$F$3032,$B8,资金流水!$H$5:$H$3032,N$4)) -> 0 | O8: =IF(OR($B8="",O$4=""),"",SUMIFS(资金流水!$L$5:$L$3032,资金流水!$F$5:$F$3032,$B8,资金流水!$H$5:$H$3032,O$4)) -> 0 | P8: =IF(OR($B8="",P$4=""),"",SUMIFS(资金流水!$L$5:$L$3032,资金流水!$F$5:$F$3032,$B8,资金流水!$H$5:$H$3032,P$4)) -> 0 | Q8: =IF(OR($B8="",Q$4=""),"",SUMIFS(资金流水!$L$5:$L$3032,资金流水!$F$5:$F$3032,$B8,资金流水!$H$5:$H$3032,Q$4)) -> 0 | ... W8: =IF(OR($B8="",W$4=""),"",SUMIFS(资金流水!$L$5:$L$3032,资金流水!$F$5:$F$3032,$B8,资金流水!$H$5:$H$3032,W$4)) | X8: =IF($B8="","",SUM($J8:$W8)) -> 220902.5 | Y8: =IF($B8="","",$F8-$X8) -> -220902.5 | Z8: =IFERROR($Y8/$F8,"") | AA8: =IF(OR($B8="",$E8=""),"",$E8-$X8) -> 5989573.6 | AB8: =IFERROR($G8/$E8,"") -> 0 | AC8: =IF(基础资料!$O7="","",基础资料!$O7) -> 已完工待收款
A9: =IF(基础资料!$I8="","",基础资料!$I8) | B9: =IF(基础资料!$J8="","",基础资料!$J8) -> 昌吉市第十八小学教学设备采购及安装设备购置项目（二次） | C9: =IF(基础资料!$K8="","",基础资料!$K8) -> 双思威 | D9: =IF(基础资料!$L8="","",基础资料!$L8) -> 昌吉市教育局 | E9: =IF(基础资料!$M8="","",基础资料!$M8) -> 3733820 | F9: =IF($B9="","",IF(基础资料!$AH$4="不含税金额",SUMIFS(开票登记!$J$5:$J$504,开票登记!$G$5:$G$504,$B9),SUMIFS(开票登记!$M$5:$M$504,开票登记!$G$5:$G$504,$B9))) -> 0 | G9: =IF($B9="","",SUMIFS(资金流水!$K$5:$K$3032,资金流水!$F$5:$F$3032,$B9)) -> 0 | H9: =IF(OR($B9="",$E9=""),"",$E9-$G9) -> 3733820 | I9: =IF($B9="","",SUMIFS(开票登记!$M$5:$M$504,开票登记!$G$5:$G$504,$B9)-$G9) -> 0 | J9: =IF(OR($B9="",J$4=""),"",SUMIFS(资金流水!$L$5:$L$3032,资金流水!$F$5:$F$3032,$B9,资金流水!$H$5:$H$3032,J$4)) -> 0 | K9: =IF(OR($B9="",K$4=""),"",SUMIFS(资金流水!$L$5:$L$3032,资金流水!$F$5:$F$3032,$B9,资金流水!$H$5:$H$3032,K$4)) -> 0 | L9: =IF(OR($B9="",L$4=""),"",SUMIFS(资金流水!$L$5:$L$3032,资金流水!$F$5:$F$3032,$B9,资金流水!$H$5:$H$3032,L$4)) -> 0 | M9: =IF(OR($B9="",M$4=""),"",SUMIFS(资金流水!$L$5:$L$3032,资金流水!$F$5:$F$3032,$B9,资金流水!$H$5:$H$3032,M$4)) -> 0 | N9: =IF(OR($B9="",N$4=""),"",SUMIFS(资金流水!$L$5:$L$3032,资金流水!$F$5:$F$3032,$B9,资金流水!$H$5:$H$3032,N$4)) -> 0 | O9: =IF(OR($B9="",O$4=""),"",SUMIFS(资金流水!$L$5:$L$3032,资金流水!$F$5:$F$3032,$B9,资金流水!$H$5:$H$3032,O$4)) -> 0 | P9: =IF(OR($B9="",P$4=""),"",SUMIFS(资金流水!$L$5:$L$3032,资金流水!$F$5:$F$3032,$B9,资金流水!$H$5:$H$3032,P$4)) -> 0 | Q9: =IF(OR($B9="",Q$4=""),"",SUMIFS(资金流水!$L$5:$L$3032,资金流水!$F$5:$F$3032,$B9,资金流水!$H$5:$H$3032,Q$4)) -> 0 | ... W9: =IF(OR($B9="",W$4=""),"",SUMIFS(资金流水!$L$5:$L$3032,资金流水!$F$5:$F$3032,$B9,资金流水!$H$5:$H$3032,W$4)) | X9: =IF($B9="","",SUM($J9:$W9)) -> 0 | Y9: =IF($B9="","",$F9-$X9) -> 0 | Z9: =IFERROR($Y9/$F9,"") | AA9: =IF(OR($B9="",$E9=""),"",$E9-$X9) -> 3733820 | AB9: =IFERROR($G9/$E9,"") -> 0 | AC9: =IF(基础资料!$O8="","",基础资料!$O8) -> 已完工待收款
A10: =IF(基础资料!$I9="","",基础资料!$I9) | B10: =IF(基础资料!$J9="","",基础资料!$J9) -> 新疆某单位教育教学设备（二标段）六中项目 | C10: =IF(基础资料!$K9="","",基础资料!$K9) -> 双思威 | D10: =IF(基础资料!$L9="","",基础资料!$L9) -> 中移系统集成有限公司 | E10: =IF(基础资料!$M9="","",基础资料!$M9) -> 6515900.9 | F10: =IF($B10="","",IF(基础资料!$AH$4="不含税金额",SUMIFS(开票登记!$J$5:$J$504,开票登记!$G$5:$G$504,$B10),SUMIFS(开票登记!$M$5:$M$504,开票登记!$G$5:$G$504,$B10))) -> 0 | G10: =IF($B10="","",SUMIFS(资金流水!$K$5:$K$3032,资金流水!$F$5:$F$3032,$B10)) -> 0 | H10: =IF(OR($B10="",$E10=""),"",$E10-$G10) -> 6515900.9 | I10: =IF($B10="","",SUMIFS(开票登记!$M$5:$M$504,开票登记!$G$5:$G$504,$B10)-$G10) -> 0 | J10: =IF(OR($B10="",J$4=""),"",SUMIFS(资金流水!$L$5:$L$3032,资金流水!$F$5:$F$3032,$B10,资金流水!$H$5:$H$3032,J$4)) -> 0 | K10: =IF(OR($B10="",K$4=""),"",SUMIFS(资金流水!$L$5:$L$3032,资金流水!$F$5:$F$3032,$B10,资金流水!$H$5:$H$3032,K$4)) -> 7000 | L10: =IF(OR($B10="",L$4=""),"",SUMIFS(资金流水!$L$5:$L$3032,资金流水!$F$5:$F$3032,$B10,资金流水!$H$5:$H$3032,L$4)) -> 0 | M10: =IF(OR($B10="",M$4=""),"",SUMIFS(资金流水!$L$5:$L$3032,资金流水!$F$5:$F$3032,$B10,资金流水!$H$5:$H$3032,M$4)) -> 0 | N10: =IF(OR($B10="",N$4=""),"",SUMIFS(资金流水!$L$5:$L$3032,资金流水!$F$5:$F$3032,$B10,资金流水!$H$5:$H$3032,N$4)) -> 0 | O10: =IF(OR($B10="",O$4=""),"",SUMIFS(资金流水!$L$5:$L$3032,资金流水!$F$5:$F$3032,$B10,资金流水!$H$5:$H$3032,O$4)) -> 0 | P10: =IF(OR($B10="",P$4=""),"",SUMIFS(资金流水!$L$5:$L$3032,资金流水!$F$5:$F$3032,$B10,资金流水!$H$5:$H$3032,P$4)) -> 0 | Q10: =IF(OR($B10="",Q$4=""),"",SUMIFS(资金流水!$L$5:$L$3032,资金流水!$F$5:$F$3032,$B10,资金流水!$H$5:$H$3032,Q$4)) -> 0 | ... W10: =IF(OR($B10="",W$4=""),"",SUMIFS(资金流水!$L$5:$L$3032,资金流水!$F$5:$F$3032,$B10,资金流水!$H$5:$H$3032,W$4)) | X10: =IF($B10="","",SUM($J10:$W10)) -> 7000 | Y10: =IF($B10="","",$F10-$X10) -> -7000 | Z10: =IFERROR($Y10/$F10,"") | AA10: =IF(OR($B10="",$E10=""),"",$E10-$X10) -> 6508900.9 | AB10: =IFERROR($G10/$E10,"") -> 0 | AC10: =IF(基础资料!$O9="","",基础资料!$O9) -> 已完工待收款
A11: =IF(基础资料!$I10="","",基础资料!$I10) | B11: =IF(基础资料!$J10="","",基础资料!$J10) -> 第二师铁门关市武安街消防站改造项目 | C11: =IF(基础资料!$K10="","",基础资料!$K10) -> 双思威 | D11: =IF(基础资料!$L10="","",基础资料!$L10) -> 中国电信股份有限公司巴音郭楞蒙古自治州分公司 | E11: =IF(基础资料!$M10="","",基础资料!$M10) -> 737890 | F11: =IF($B11="","",IF(基础资料!$AH$4="不含税金额",SUMIFS(开票登记!$J$5:$J$504,开票登记!$G$5:$G$504,$B11),SUMIFS(开票登记!$M$5:$M$504,开票登记!$G$5:$G$504,$B11))) -> 286729.92 | G11: =IF($B11="","",SUMIFS(资金流水!$K$5:$K$3032,资金流水!$F$5:$F$3032,$B11)) -> 286729.93 | H11: =IF(OR($B11="",$E11=""),"",$E11-$G11) -> 451160.07 | I11: =IF($B11="","",SUMIFS(开票登记!$M$5:$M$504,开票登记!$G$5:$G$504,$B11)-$G11) -> -0.01 | J11: =IF(OR($B11="",J$4=""),"",SUMIFS(资金流水!$L$5:$L$3032,资金流水!$F$5:$F$3032,$B11,资金流水!$H$5:$H$3032,J$4)) -> 0 | K11: =IF(OR($B11="",K$4=""),"",SUMIFS(资金流水!$L$5:$L$3032,资金流水!$F$5:$F$3032,$B11,资金流水!$H$5:$H$3032,K$4)) -> 0 | L11: =IF(OR($B11="",L$4=""),"",SUMIFS(资金流水!$L$5:$L$3032,资金流水!$F$5:$F$3032,$B11,资金流水!$H$5:$H$3032,L$4)) -> 0 | M11: =IF(OR($B11="",M$4=""),"",SUMIFS(资金流水!$L$5:$L$3032,资金流水!$F$5:$F$3032,$B11,资金流水!$H$5:$H$3032,M$4)) -> 0 | N11: =IF(OR($B11="",N$4=""),"",SUMIFS(资金流水!$L$5:$L$3032,资金流水!$F$5:$F$3032,$B11,资金流水!$H$5:$H$3032,N$4)) -> 0 | O11: =IF(OR($B11="",O$4=""),"",SUMIFS(资金流水!$L$5:$L$3032,资金流水!$F$5:$F$3032,$B11,资金流水!$H$5:$H$3032,O$4)) -> 0 | P11: =IF(OR($B11="",P$4=""),"",SUMIFS(资金流水!$L$5:$L$3032,资金流水!$F$5:$F$3032,$B11,资金流水!$H$5:$H$3032,P$4)) -> 0 | Q11: =IF(OR($B11="",Q$4=""),"",SUMIFS(资金流水!$L$5:$L$3032,资金流水!$F$5:$F$3032,$B11,资金流水!$H$5:$H$3032,Q$4)) -> 0 | ... W11: =IF(OR($B11="",W$4=""),"",SUMIFS(资金流水!$L$5:$L$3032,资金流水!$F$5:$F$3032,$B11,资金流水!$H$5:$H$3032,W$4)) | X11: =IF($B11="","",SUM($J11:$W11)) -> 0 | Y11: =IF($B11="","",$F11-$X11) -> 286729.92 | Z11: =IFERROR($Y11/$F11,"") -> 1 | AA11: =IF(OR($B11="",$E11=""),"",$E11-$X11) -> 737890 | AB11: =IFERROR($G11/$E11,"") -> 0.38858086 | AC11: =IF(基础资料!$O10="","",基础资料!$O10) -> 已完工待收款
A12: =IF(基础资料!$I11="","",基础资料!$I11) | B12: =IF(基础资料!$J11="","",基础资料!$J11) -> 昌吉市中等职业学校教学设备采购项目(二标段) | C12: =IF(基础资料!$K11="","",基础资料!$K11) -> 双思威 | D12: =IF(基础资料!$L11="","",基础资料!$L11) -> 中移建设有限公司新疆分公司 | E12: =IF(基础资料!$M11="","",基础资料!$M11) -> 2913561.4 | F12: =IF($B12="","",IF(基础资料!$AH$4="不含税金额",SUMIFS(开票登记!$J$5:$J$504,开票登记!$G$5:$G$504,$B12),SUMIFS(开票登记!$M$5:$M$504,开票登记!$G$5:$G$504,$B12))) -> 0 | G12: =IF($B12="","",SUMIFS(资金流水!$K$5:$K$3032,资金流水!$F$5:$F$3032,$B12)) -> 582712.28 | H12: =IF(OR($B12="",$E12=""),"",$E12-$G12) -> 2330849.1 | I12: =IF($B12="","",SUMIFS(开票登记!$M$5:$M$504,开票登记!$G$5:$G$504,$B12)-$G12) -> -582712.28 | J12: =IF(OR($B12="",J$4=""),"",SUMIFS(资金流水!$L$5:$L$3032,资金流水!$F$5:$F$3032,$B12,资金流水!$H$5:$H$3032,J$4)) -> 0 | K12: =IF(OR($B12="",K$4=""),"",SUMIFS(资金流水!$L$5:$L$3032,资金流水!$F$5:$F$3032,$B12,资金流水!$H$5:$H$3032,K$4)) -> 0 | L12: =IF(OR($B12="",L$4=""),"",SUMIFS(资金流水!$L$5:$L$3032,资金流水!$F$5:$F$3032,$B12,资金流水!$H$5:$H$3032,L$4)) -> 0 | M12: =IF(OR($B12="",M$4=""),"",SUMIFS(资金流水!$L$5:$L$3032,资金流水!$F$5:$F$3032,$B12,资金流水!$H$5:$H$3032,M$4)) -> 0 | N12: =IF(OR($B12="",N$4=""),"",SUMIFS(资金流水!$L$5:$L$3032,资金流水!$F$5:$F$3032,$B12,资金流水!$H$5:$H$3032,N$4)) -> 0 | O12: =IF(OR($B12="",O$4=""),"",SUMIFS(资金流水!$L$5:$L$3032,资金流水!$F$5:$F$3032,$B12,资金流水!$H$5:$H$3032,O$4)) -> 0 | P12: =IF(OR($B12="",P$4=""),"",SUMIFS(资金流水!$L$5:$L$3032,资金流水!$F$5:$F$3032,$B12,资金流水!$H$5:$H$3032,P$4)) -> 0 | Q12: =IF(OR($B12="",Q$4=""),"",SUMIFS(资金流水!$L$5:$L$3032,资金流水!$F$5:$F$3032,$B12,资金流水!$H$5:$H$3032,Q$4)) -> 0 | ... W12: =IF(OR($B12="",W$4=""),"",SUMIFS(资金流水!$L$5:$L$3032,资金流水!$F$5:$F$3032,$B12,资金流水!$H$5:$H$3032,W$4)) | X12: =IF($B12="","",SUM($J12:$W12)) -> 0 | Y12: =IF($B12="","",$F12-$X12) -> 0 | Z12: =IFERROR($Y12/$F12,"") | AA12: =IF(OR($B12="",$E12=""),"",$E12-$X12) -> 2913561.4 | AB12: =IFERROR($G12/$E12,"") -> 0.2 | AC12: =IF(基础资料!$O11="","",基础资料!$O11)
A13: =IF(基础资料!$I12="","",基础资料!$I12) | B13: =IF(基础资料!$J12="","",基础资料!$J12) -> 中电信数智科技有限公司昌吉分公司2025年某学校智慧教室建设项目 | C13: =IF(基础资料!$K12="","",基础资料!$K12) -> 双思威 | D13: =IF(基础资料!$L12="","",基础资料!$L12) -> 中电信数智科技有限公司昌吉分公司 | E13: =IF(基础资料!$M12="","",基础资料!$M12) -> 295570 | F13: =IF($B13="","",IF(基础资料!$AH$4="不含税金额",SUMIFS(开票登记!$J$5:$J$504,开票登记!$G$5:$G$504,$B13),SUMIFS(开票登记!$M$5:$M$504,开票登记!$G$5:$G$504,$B13))) -> 485572 | G13: =IF($B13="","",SUMIFS(资金流水!$K$5:$K$3032,资金流水!$F$5:$F$3032,$B13)) -> 485572 | H13: =IF(OR($B13="",$E13=""),"",$E13-$G13) -> -190002 | I13: =IF($B13="","",SUMIFS(开票登记!$M$5:$M$504,开票登记!$G$5:$G$504,$B13)-$G13) -> 0 | J13: =IF(OR($B13="",J$4=""),"",SUMIFS(资金流水!$L$5:$L$3032,资金流水!$F$5:$F$3032,$B13,资金流水!$H$5:$H$3032,J$4)) -> 0 | K13: =IF(OR($B13="",K$4=""),"",SUMIFS(资金流水!$L$5:$L$3032,资金流水!$F$5:$F$3032,$B13,资金流水!$H$5:$H$3032,K$4)) -> 0 | L13: =IF(OR($B13="",L$4=""),"",SUMIFS(资金流水!$L$5:$L$3032,资金流水!$F$5:$F$3032,$B13,资金流水!$H$5:$H$3032,L$4)) -> 0 | M13: =IF(OR($B13="",M$4=""),"",SUMIFS(资金流水!$L$5:$L$3032,资金流水!$F$5:$F$3032,$B13,资金流水!$H$5:$H$3032,M$4)) -> 0 | N13: =IF(OR($B13="",N$4=""),"",SUMIFS(资金流水!$L$5:$L$3032,资金流水!$F$5:$F$3032,$B13,资金流水!$H$5:$H$3032,N$4)) -> 0 | O13: =IF(OR($B13="",O$4=""),"",SUMIFS(资金流水!$L$5:$L$3032,资金流水!$F$5:$F$3032,$B13,资金流水!$H$5:$H$3032,O$4)) -> 0 | P13: =IF(OR($B13="",P$4=""),"",SUMIFS(资金流水!$L$5:$L$3032,资金流水!$F$5:$F$3032,$B13,资金流水!$H$5:$H$3032,P$4)) -> 0 | Q13: =IF(OR($B13="",Q$4=""),"",SUMIFS(资金流水!$L$5:$L$3032,资金流水!$F$5:$F$3032,$B13,资金流水!$H$5:$H$3032,Q$4)) -> 0 | ... W13: =IF(OR($B13="",W$4=""),"",SUMIFS(资金流水!$L$5:$L$3032,资金流水!$F$5:$F$3032,$B13,资金流水!$H$5:$H$3032,W$4)) | X13: =IF($B13="","",SUM($J13:$W13)) -> 0 | Y13: =IF($B13="","",$F13-$X13) -> 485572 | Z13: =IFERROR($Y13/$F13,"") -> 1 | AA13: =IF(OR($B13="",$E13=""),"",$E13-$X13) -> 295570 | AB13: =IFERROR($G13/$E13,"") -> 1.6428325 | AC13: =IF(基础资料!$O12="","",基础资料!$O12)
A14: =IF(基础资料!$I13="","",基础资料!$I13) | B14: =IF(基础资料!$J13="","",基础资料!$J13) -> 中国电信巴州分公司2025年某部幼儿园视频监控系统服务采购 | C14: =IF(基础资料!$K13="","",基础资料!$K13) -> 双思威 | D14: =IF(基础资料!$L13="","",基础资料!$L13) -> 中国电信股份有限公司巴音郭楞蒙古自治州分公司 | E14: =IF(基础资料!$M13="","",基础资料!$M13) -> 126140 | F14: =IF($B14="","",IF(基础资料!$AH$4="不含税金额",SUMIFS(开票登记!$J$5:$J$504,开票登记!$G$5:$G$504,$B14),SUMIFS(开票登记!$M$5:$M$504,开票登记!$G$5:$G$504,$B14))) -> 108867 | G14: =IF($B14="","",SUMIFS(资金流水!$K$5:$K$3032,资金流水!$F$5:$F$3032,$B14)) -> 82000 | H14: =IF(OR($B14="",$E14=""),"",$E14-$G14) -> 44140 | I14: =IF($B14="","",SUMIFS(开票登记!$M$5:$M$504,开票登记!$G$5:$G$504,$B14)-$G14) -> 26867 | J14: =IF(OR($B14="",J$4=""),"",SUMIFS(资金流水!$L$5:$L$3032,资金流水!$F$5:$F$3032,$B14,资金流水!$H$5:$H$3032,J$4)) -> 0 | K14: =IF(OR($B14="",K$4=""),"",SUMIFS(资金流水!$L$5:$L$3032,资金流水!$F$5:$F$3032,$B14,资金流水!$H$5:$H$3032,K$4)) -> 0 | L14: =IF(OR($B14="",L$4=""),"",SUMIFS(资金流水!$L$5:$L$3032,资金流水!$F$5:$F$3032,$B14,资金流水!$H$5:$H$3032,L$4)) -> 0 | M14: =IF(OR($B14="",M$4=""),"",SUMIFS(资金流水!$L$5:$L$3032,资金流水!$F$5:$F$3032,$B14,资金流水!$H$5:$H$3032,M$4)) -> 0 | N14: =IF(OR($B14="",N$4=""),"",SUMIFS(资金流水!$L$5:$L$3032,资金流水!$F$5:$F$3032,$B14,资金流水!$H$5:$H$3032,N$4)) -> 0 | O14: =IF(OR($B14="",O$4=""),"",SUMIFS(资金流水!$L$5:$L$3032,资金流水!$F$5:$F$3032,$B14,资金流水!$H$5:$H$3032,O$4)) -> 0 | P14: =IF(OR($B14="",P$4=""),"",SUMIFS(资金流水!$L$5:$L$3032,资金流水!$F$5:$F$3032,$B14,资金流水!$H$5:$H$3032,P$4)) -> 0 | Q14: =IF(OR($B14="",Q$4=""),"",SUMIFS(资金流水!$L$5:$L$3032,资金流水!$F$5:$F$3032,$B14,资金流水!$H$5:$H$3032,Q$4)) -> 0 | ... W14: =IF(OR($B14="",W$4=""),"",SUMIFS(资金流水!$L$5:$L$3032,资金流水!$F$5:$F$3032,$B14,资金流水!$H$5:$H$3032,W$4)) | X14: =IF($B14="","",SUM($J14:$W14)) -> 0 | Y14: =IF($B14="","",$F14-$X14) -> 108867 | Z14: =IFERROR($Y14/$F14,"") -> 1 | AA14: =IF(OR($B14="",$E14=""),"",$E14-$X14) -> 126140 | AB14: =IFERROR($G14/$E14,"") -> 0.65007135 | AC14: =IF(基础资料!$O13="","",基础资料!$O13)
A15: =IF(基础资料!$I14="","",基础资料!$I14) | B15: =IF(基础资料!$J14="","",基础资料!$J14) -> 昌吉市中等职业学校教学设备采购项目（一标段） | C15: =IF(基础资料!$K14="","",基础资料!$K14) -> 双思威 | D15: =IF(基础资料!$L14="","",基础资料!$L14) -> 北京竞业达数码科技股份有限公司 | E15: =IF(基础资料!$M14="","",基础资料!$M14) -> 3903000 | F15: =IF($B15="","",IF(基础资料!$AH$4="不含税金额",SUMIFS(开票登记!$J$5:$J$504,开票登记!$G$5:$G$504,$B15),SUMIFS(开票登记!$M$5:$M$504,开票登记!$G$5:$G$504,$B15))) -> 3122400 | G15: =IF($B15="","",SUMIFS(资金流水!$K$5:$K$3032,资金流水!$F$5:$F$3032,$B15)) -> 6244800 | H15: =IF(OR($B15="",$E15=""),"",$E15-$G15) -> -2341800 | I15: =IF($B15="","",SUMIFS(开票登记!$M$5:$M$504,开票登记!$G$5:$G$504,$B15)-$G15) -> -3122400 | J15: =IF(OR($B15="",J$4=""),"",SUMIFS(资金流水!$L$5:$L$3032,资金流水!$F$5:$F$3032,$B15,资金流水!$H$5:$H$3032,J$4)) -> 0 | K15: =IF(OR($B15="",K$4=""),"",SUMIFS(资金流水!$L$5:$L$3032,资金流水!$F$5:$F$3032,$B15,资金流水!$H$5:$H$3032,K$4)) -> 0 | L15: =IF(OR($B15="",L$4=""),"",SUMIFS(资金流水!$L$5:$L$3032,资金流水!$F$5:$F$3032,$B15,资金流水!$H$5:$H$3032,L$4)) -> 0 | M15: =IF(OR($B15="",M$4=""),"",SUMIFS(资金流水!$L$5:$L$3032,资金流水!$F$5:$F$3032,$B15,资金流水!$H$5:$H$3032,M$4)) -> 300 | N15: =IF(OR($B15="",N$4=""),"",SUMIFS(资金流水!$L$5:$L$3032,资金流水!$F$5:$F$3032,$B15,资金流水!$H$5:$H$3032,N$4)) -> 0 | O15: =IF(OR($B15="",O$4=""),"",SUMIFS(资金流水!$L$5:$L$3032,资金流水!$F$5:$F$3032,$B15,资金流水!$H$5:$H$3032,O$4)) -> 0 | P15: =IF(OR($B15="",P$4=""),"",SUMIFS(资金流水!$L$5:$L$3032,资金流水!$F$5:$F$3032,$B15,资金流水!$H$5:$H$3032,P$4)) -> 0 | Q15: =IF(OR($B15="",Q$4=""),"",SUMIFS(资金流水!$L$5:$L$3032,资金流水!$F$5:$F$3032,$B15,资金流水!$H$5:$H$3032,Q$4)) -> 0 | ... W15: =IF(OR($B15="",W$4=""),"",SUMIFS(资金流水!$L$5:$L$3032,资金流水!$F$5:$F$3032,$B15,资金流水!$H$5:$H$3032,W$4)) | X15: =IF($B15="","",SUM($J15:$W15)) -> 300 | Y15: =IF($B15="","",$F15-$X15) -> 3122100 | Z15: =IFERROR($Y15/$F15,"") -> 0.99990392 | AA15: =IF(OR($B15="",$E15=""),"",$E15-$X15) -> 3902700 | AB15: =IFERROR($G15/$E15,"") -> 1.6 | AC15: =IF(基础资料!$O14="","",基础资料!$O14)
A16: =IF(基础资料!$I15="","",基础资料!$I15) | B16: =IF(基础资料!$J15="","",基础资料!$J15) -> 草湖标识标牌项目 | C16: =IF(基础资料!$K15="","",基础资料!$K15) -> 双思威 | D16: =IF(基础资料!$L15="","",基础资料!$L15) -> 收新疆博创未来信息工程技术有限公司货款 | E16: =IF(基础资料!$M15="","",基础资料!$M15) -> 1240000 | F16: =IF($B16="","",IF(基础资料!$AH$4="不含税金额",SUMIFS(开票登记!$J$5:$J$504,开票登记!$G$5:$G$504,$B16),SUMIFS(开票登记!$M$5:$M$504,开票登记!$G$5:$G$504,$B16))) -> 1240000 | G16: =IF($B16="","",SUMIFS(资金流水!$K$5:$K$3032,资金流水!$F$5:$F$3032,$B16)) -> 400000 | H16: =IF(OR($B16="",$E16=""),"",$E16-$G16) -> 840000 | I16: =IF($B16="","",SUMIFS(开票登记!$M$5:$M$504,开票登记!$G$5:$G$504,$B16)-$G16) -> 840000 | J16: =IF(OR($B16="",J$4=""),"",SUMIFS(资金流水!$L$5:$L$3032,资金流水!$F$5:$F$3032,$B16,资金流水!$H$5:$H$3032,J$4)) -> 175 | K16: =IF(OR($B16="",K$4=""),"",SUMIFS(资金流水!$L$5:$L$3032,资金流水!$F$5:$F$3032,$B16,资金流水!$H$5:$H$3032,K$4)) -> 0 | L16: =IF(OR($B16="",L$4=""),"",SUMIFS(资金流水!$L$5:$L$3032,资金流水!$F$5:$F$3032,$B16,资金流水!$H$5:$H$3032,L$4)) -> 0 | M16: =IF(OR($B16="",M$4=""),"",SUMIFS(资金流水!$L$5:$L$3032,资金流水!$F$5:$F$3032,$B16,资金流水!$H$5:$H$3032,M$4)) -> 0 | N16: =IF(OR($B16="",N$4=""),"",SUMIFS(资金流水!$L$5:$L$3032,资金流水!$F$5:$F$3032,$B16,资金流水!$H$5:$H$3032,N$4)) -> 0 | O16: =IF(OR($B16="",O$4=""),"",SUMIFS(资金流水!$L$5:$L$3032,资金流水!$F$5:$F$3032,$B16,资金流水!$H$5:$H$3032,O$4)) -> 0 | P16: =IF(OR($B16="",P$4=""),"",SUMIFS(资金流水!$L$5:$L$3032,资金流水!$F$5:$F$3032,$B16,资金流水!$H$5:$H$3032,P$4)) -> 0 | Q16: =IF(OR($B16="",Q$4=""),"",SUMIFS(资金流水!$L$5:$L$3032,资金流水!$F$5:$F$3032,$B16,资金流水!$H$5:$H$3032,Q$4)) -> 0 | ... W16: =IF(OR($B16="",W$4=""),"",SUMIFS(资金流水!$L$5:$L$3032,资金流水!$F$5:$F$3032,$B16,资金流水!$H$5:$H$3032,W$4)) | X16: =IF($B16="","",SUM($J16:$W16)) -> 175 | Y16: =IF($B16="","",$F16-$X16) -> 1239825 | Z16: =IFERROR($Y16/$F16,"") -> 0.99985887 | AA16: =IF(OR($B16="",$E16=""),"",$E16-$X16) -> 1239825 | AB16: =IFERROR($G16/$E16,"") -> 0.32258065 | AC16: =IF(基础资料!$O15="","",基础资料!$O15)
... A64: =IF(基础资料!$I63="","",基础资料!$I63) | B64: =IF(基础资料!$J63="","",基础资料!$J63) -> 乌鲁木齐市第122小学2025年采购高清扫描仪及软件 | C64: =IF(基础资料!$K63="","",基础资料!$K63) -> 中展 | D64: =IF(基础资料!$L63="","",基础资料!$L63) -> 乌鲁木齐市第122小学 | E64: =IF(基础资料!$M63="","",基础资料!$M63) -> 67800 | F64: =IF($B64="","",IF(基础资料!$AH$4="不含税金额",SUMIFS(开票登记!$J$5:$J$504,开票登记!$G$5:$G$504,$B64),SUMIFS(开票登记!$M$5:$M$504,开票登记!$G$5:$G$504,$B64))) -> 0 | G64: =IF($B64="","",SUMIFS(资金流水!$K$5:$K$3032,资金流水!$F$5:$F$3032,$B64)) -> 0 | H64: =IF(OR($B64="",$E64=""),"",$E64-$G64) -> 67800 | I64: =IF($B64="","",SUMIFS(开票登记!$M$5:$M$504,开票登记!$G$5:$G$504,$B64)-$G64) -> 0 | J64: =IF(OR($B64="",J$4=""),"",SUMIFS(资金流水!$L$5:$L$3032,资金流水!$F$5:$F$3032,$B64,资金流水!$H$5:$H$3032,J$4)) -> 0 | K64: =IF(OR($B64="",K$4=""),"",SUMIFS(资金流水!$L$5:$L$3032,资金流水!$F$5:$F$3032,$B64,资金流水!$H$5:$H$3032,K$4)) -> 0 | L64: =IF(OR($B64="",L$4=""),"",SUMIFS(资金流水!$L$5:$L$3032,资金流水!$F$5:$F$3032,$B64,资金流水!$H$5:$H$3032,L$4)) -> 0 | M64: =IF(OR($B64="",M$4=""),"",SUMIFS(资金流水!$L$5:$L$3032,资金流水!$F$5:$F$3032,$B64,资金流水!$H$5:$H$3032,M$4)) -> 0 | N64: =IF(OR($B64="",N$4=""),"",SUMIFS(资金流水!$L$5:$L$3032,资金流水!$F$5:$F$3032,$B64,资金流水!$H$5:$H$3032,N$4)) -> 0 | O64: =IF(OR($B64="",O$4=""),"",SUMIFS(资金流水!$L$5:$L$3032,资金流水!$F$5:$F$3032,$B64,资金流水!$H$5:$H$3032,O$4)) -> 0 | P64: =IF(OR($B64="",P$4=""),"",SUMIFS(资金流水!$L$5:$L$3032,资金流水!$F$5:$F$3032,$B64,资金流水!$H$5:$H$3032,P$4)) -> 0 | Q64: =IF(OR($B64="",Q$4=""),"",SUMIFS(资金流水!$L$5:$L$3032,资金流水!$F$5:$F$3032,$B64,资金流水!$H$5:$H$3032,Q$4)) -> 0 | ... W64: =IF(OR($B64="",W$4=""),"",SUMIFS(资金流水!$L$5:$L$3032,资金流水!$F$5:$F$3032,$B64,资金流水!$H$5:$H$3032,W$4)) | X64: =IF($B64="","",SUM($J64:$W64)) -> 0 | Y64: =IF($B64="","",$F64-$X64) -> 0 | Z64: =IFERROR($Y64/$F64,"") | AA64: =IF(OR($B64="",$E64=""),"",$E64-$X64) -> 67800 | AB64: =IFERROR($G64/$E64,"") -> 0 | AC64: =IF(基础资料!$O63="","",基础资料!$O63)
B65: 合计 | E65: =SUM(E5:E64) -> 1.0256993e+08 | F65: =SUM(F5:F64) -> 10145575 | G65: =SUM(G5:G64) -> 12734483 | H65: =SUM(H5:H64) -> 89835447 | I65: =SUM(I5:I64) -> -2588908.2 | J65: =SUM(J5:J64) -> 4047702.7 | K65: =SUM(K5:K64) -> 579217 | L65: =SUM(L5:L64) -> 0 | ... Y65: =SUM(Y5:Y64) -> 5494053.4 | Z65: =IFERROR($Y65/$F65,"") -> 0.54152213 | AA65: =SUM(AA5:AA64) -> 97996663 | AB65: =IFERROR($G65/$E65,"") -> 0.12415416

Sheet 项目明细账
A1: 项目明细账 — 选一个项目，看它全部的收支流水
A2: 选择项目 → | C2: xxx采购项目A | E2: （黄色格是下拉框，换项目后下面全部自动刷新）
A3: 合同金额 | C3: =IFERROR(INDEX(基础资料!$M$4:$M$63,MATCH($C$2,基础资料!$J$4:$J$63,0)),"") | D3: 累计收款 | F3: =SUMIFS(资金流水!$K$5:$K$3032,资金流水!$F$5:$F$3032,$C$2) -> 0 | G3: 累计项目成本 | I3: =SUMIFS(资金流水!$L$5:$L$3032,资金流水!$F$5:$F$3032,$C$2,资金流水!$W$5:$W$3015,"项目成本") -> #VALUE! | J3: 项目毛利 | L3: =$F$4-$I$3 -> #VALUE!
A4: 毛利率 | C4: =IFERROR($L$3/$F$4,"") | D4: 累计开票(收入口径) | F4: =IF(基础资料!$AH$4="不含税金额",SUMIFS(开票登记!$J$5:$J$504,开票登记!$G$5:$G$504,$C$2),SUMIFS(开票登记!$M$5:$M$504,开票登记!$G$5:$G$504,$C$2)) -> 0 | G4: 已开票未收款 | I4: =SUMIFS(开票登记!$M$5:$M$504,开票登记!$G$5:$G$504,$C$2)-$F$3 -> 0 | J4: 收款进度 | L4: =IFERROR($F$3/$C$3,"")
A5: 项目其他费用 | C5: =SUMIFS(资金流水!$L$5:$L$3032,资金流水!$F$5:$F$3032,$C$2)-$I$3 -> #VALUE! | D5: 项目净现金流 | F5: =$F$3-SUMIFS(资金流水!$L$5:$L$3032,资金流水!$F$5:$F$3032,$C$2) -> 0 | G5: 本项目笔数 | I5: =COUNTIFS(资金流水!$F$5:$F$3032,$C$2) -> 0 | J5: 项目状态 | L5: =IFERROR(INDEX(基础资料!$O$4:$O$63,MATCH($C$2,基础资料!$J$4:$J$63,0)),"")
A6: 口径提醒：收入以开票为准 ——「项目毛利」= 累计开票 − 累计项目成本（与项目核算表一致）；「累计收款」只看回款进度，不参与毛利；「项目净现金流」= 累计收款 − 该项目全部支出，是纯现金视角。「累计项目成本」只统计填了成本类别的支出，「项目其他费用」是挂在本项目名下但归到日常费用/工资/税金的支出。三个数不同不是错。
A7: 序号 | B7: 日期 | C7: 账户 | D7: 公司 | E7: 收支类型 | F7: 摘要内容 | G7: 收入 | H7: 成本类别 | I7: 支出 | J7: 费用类别 | K7: 归属月 | L7: 跨期 | M7: 关联单号 | O7: 行定位
A8: 1 | B8: =IF($O8="","",IF(INDEX(资金流水!B$5:B$3032,$O8)="","",INDEX(资金流水!B$5:B$3032,$O8))) | C8: =IF($O8="","",IF(INDEX(资金流水!C$5:C$3032,$O8)="","",INDEX(资金流水!C$5:C$3032,$O8))) | D8: =IF($O8="","",IF(INDEX(资金流水!D$5:D$3032,$O8)="","",INDEX(资金流水!D$5:D$3032,$O8))) | E8: =IF($O8="","",IF(INDEX(资金流水!E$5:E$3032,$O8)="","",INDEX(资金流水!E$5:E$3032,$O8))) | F8: =IF($O8="","",IF(INDEX(资金流水!J$5:J$3032,$O8)="","",INDEX(资金流水!J$5:J$3032,$O8))) | G8: =IF($O8="","",IF(INDEX(资金流水!K$5:K$3032,$O8)="","",INDEX(资金流水!K$5:K$3032,$O8))) | H8: =IF($O8="","",IF(INDEX(资金流水!H$5:H$3032,$O8)="","",INDEX(资金流水!H$5:H$3032,$O8))) | I8: =IF($O8="","",IF(INDEX(资金流水!L$5:L$3032,$O8)="","",INDEX(资金流水!L$5:L$3032,$O8))) | J8: =IF($O8="","",IF(INDEX(资金流水!I$5:I$3032,$O8)="","",INDEX(资金流水!I$5:I$3032,$O8))) | K8: =IF($O8="","",IF(INDEX(资金流水!T$5:T$3015,$O8)="","",INDEX(资金流水!T$5:T$3015,$O8))) | L8: =IF($O8="","",IF(INDEX(资金流水!U$5:U$3015,$O8)="","",INDEX(资金流水!U$5:U$3015,$O8))) | M8: =IF($O8="","",IF(INDEX(资金流水!Q$5:Q$3015,$O8)="","",INDEX(资金流水!Q$5:Q$3015,$O8))) | O8: =IFERROR(MATCH($A8,资金流水!$V$5:$V$3015,0),"")
A9: 2 | B9: =IF($O9="","",IF(INDEX(资金流水!B$5:B$3032,$O9)="","",INDEX(资金流水!B$5:B$3032,$O9))) | C9: =IF($O9="","",IF(INDEX(资金流水!C$5:C$3032,$O9)="","",INDEX(资金流水!C$5:C$3032,$O9))) | D9: =IF($O9="","",IF(INDEX(资金流水!D$5:D$3032,$O9)="","",INDEX(资金流水!D$5:D$3032,$O9))) | E9: =IF($O9="","",IF(INDEX(资金流水!E$5:E$3032,$O9)="","",INDEX(资金流水!E$5:E$3032,$O9))) | F9: =IF($O9="","",IF(INDEX(资金流水!J$5:J$3032,$O9)="","",INDEX(资金流水!J$5:J$3032,$O9))) | G9: =IF($O9="","",IF(INDEX(资金流水!K$5:K$3032,$O9)="","",INDEX(资金流水!K$5:K$3032,$O9))) | H9: =IF($O9="","",IF(INDEX(资金流水!H$5:H$3032,$O9)="","",INDEX(资金流水!H$5:H$3032,$O9))) | I9: =IF($O9="","",IF(INDEX(资金流水!L$5:L$3032,$O9)="","",INDEX(资金流水!L$5:L$3032,$O9))) | J9: =IF($O9="","",IF(INDEX(资金流水!I$5:I$3032,$O9)="","",INDEX(资金流水!I$5:I$3032,$O9))) | K9: =IF($O9="","",IF(INDEX(资金流水!T$5:T$3015,$O9)="","",INDEX(资金流水!T$5:T$3015,$O9))) | L9: =IF($O9="","",IF(INDEX(资金流水!U$5:U$3015,$O9)="","",INDEX(资金流水!U$5:U$3015,$O9))) | M9: =IF($O9="","",IF(INDEX(资金流水!Q$5:Q$3015,$O9)="","",INDEX(资金流水!Q$5:Q$3015,$O9))) | O9: =IFERROR(MATCH($A9,资金流水!$V$5:$V$3015,0),"")
A10: 3 | B10: =IF($O10="","",IF(INDEX(资金流水!B$5:B$3032,$O10)="","",INDEX(资金流水!B$5:B$3032,$O10))) | C10: =IF($O10="","",IF(INDEX(资金流水!C$5:C$3032,$O10)="","",INDEX(资金流水!C$5:C$3032,$O10))) | D10: =IF($O10="","",IF(INDEX(资金流水!D$5:D$3032,$O10)="","",INDEX(资金流水!D$5:D$3032,$O10))) | E10: =IF($O10="","",IF(INDEX(资金流水!E$5:E$3032,$O10)="","",INDEX(资金流水!E$5:E$3032,$O10))) | F10: =IF($O10="","",IF(INDEX(资金流水!J$5:J$3032,$O10)="","",INDEX(资金流水!J$5:J$3032,$O10))) | G10: =IF($O10="","",IF(INDEX(资金流水!K$5:K$3032,$O10)="","",INDEX(资金流水!K$5:K$3032,$O10))) | H10: =IF($O10="","",IF(INDEX(资金流水!H$5:H$3032,$O10)="","",INDEX(资金流水!H$5:H$3032,$O10))) | I10: =IF($O10="","",IF(INDEX(资金流水!L$5:L$3032,$O10)="","",INDEX(资金流水!L$5:L$3032,$O10))) | J10: =IF($O10="","",IF(INDEX(资金流水!I$5:I$3032,$O10)="","",INDEX(资金流水!I$5:I$3032,$O10))) | K10: =IF($O10="","",IF(INDEX(资金流水!T$5:T$3015,$O10)="","",INDEX(资金流水!T$5:T$3015,$O10))) | L10: =IF($O10="","",IF(INDEX(资金流水!U$5:U$3015,$O10)="","",INDEX(资金流水!U$5:U$3015,$O10))) | M10: =IF($O10="","",IF(INDEX(资金流水!Q$5:Q$3015,$O10)="","",INDEX(资金流水!Q$5:Q$3015,$O10))) | O10: =IFERROR(MATCH($A10,资金流水!$V$5:$V$3015,0),"")
A11: 4 | B11: =IF($O11="","",IF(INDEX(资金流水!B$5:B$3032,$O11)="","",INDEX(资金流水!B$5:B$3032,$O11))) | C11: =IF($O11="","",IF(INDEX(资金流水!C$5:C$3032,$O11)="","",INDEX(资金流水!C$5:C$3032,$O11))) | D11: =IF($O11="","",IF(INDEX(资金流水!D$5:D$3032,$O11)="","",INDEX(资金流水!D$5:D$3032,$O11))) | E11: =IF($O11="","",IF(INDEX(资金流水!E$5:E$3032,$O11)="","",INDEX(资金流水!E$5:E$3032,$O11))) | F11: =IF($O11="","",IF(INDEX(资金流水!J$5:J$3032,$O11)="","",INDEX(资金流水!J$5:J$3032,$O11))) | G11: =IF($O11="","",IF(INDEX(资金流水!K$5:K$3032,$O11)="","",INDEX(资金流水!K$5:K$3032,$O11))) | H11: =IF($O11="","",IF(INDEX(资金流水!H$5:H$3032,$O11)="","",INDEX(资金流水!H$5:H$3032,$O11))) | I11: =IF($O11="","",IF(INDEX(资金流水!L$5:L$3032,$O11)="","",INDEX(资金流水!L$5:L$3032,$O11))) | J11: =IF($O11="","",IF(INDEX(资金流水!I$5:I$3032,$O11)="","",INDEX(资金流水!I$5:I$3032,$O11))) | K11: =IF($O11="","",IF(INDEX(资金流水!T$5:T$3015,$O11)="","",INDEX(资金流水!T$5:T$3015,$O11))) | L11: =IF($O11="","",IF(INDEX(资金流水!U$5:U$3015,$O11)="","",INDEX(资金流水!U$5:U$3015,$O11))) | M11: =IF($O11="","",IF(INDEX(资金流水!Q$5:Q$3015,$O11)="","",INDEX(资金流水!Q$5:Q$3015,$O11))) | O11: =IFERROR(MATCH($A11,资金流水!$V$5:$V$3015,0),"")
A12: 5 | B12: =IF($O12="","",IF(INDEX(资金流水!B$5:B$3032,$O12)="","",INDEX(资金流水!B$5:B$3032,$O12))) | C12: =IF($O12="","",IF(INDEX(资金流水!C$5:C$3032,$O12)="","",INDEX(资金流水!C$5:C$3032,$O12))) | D12: =IF($O12="","",IF(INDEX(资金流水!D$5:D$3032,$O12)="","",INDEX(资金流水!D$5:D$3032,$O12))) | E12: =IF($O12="","",IF(INDEX(资金流水!E$5:E$3032,$O12)="","",INDEX(资金流水!E$5:E$3032,$O12))) | F12: =IF($O12="","",IF(INDEX(资金流水!J$5:J$3032,$O12)="","",INDEX(资金流水!J$5:J$3032,$O12))) | G12: =IF($O12="","",IF(INDEX(资金流水!K$5:K$3032,$O12)="","",INDEX(资金流水!K$5:K$3032,$O12))) | H12: =IF($O12="","",IF(INDEX(资金流水!H$5:H$3032,$O12)="","",INDEX(资金流水!H$5:H$3032,$O12))) | I12: =IF($O12="","",IF(INDEX(资金流水!L$5:L$3032,$O12)="","",INDEX(资金流水!L$5:L$3032,$O12))) | J12: =IF($O12="","",IF(INDEX(资金流水!I$5:I$3032,$O12)="","",INDEX(资金流水!I$5:I$3032,$O12))) | K12: =IF($O12="","",IF(INDEX(资金流水!T$5:T$3015,$O12)="","",INDEX(资金流水!T$5:T$3015,$O12))) | L12: =IF($O12="","",IF(INDEX(资金流水!U$5:U$3015,$O12)="","",INDEX(资金流水!U$5:U$3015,$O12))) | M12: =IF($O12="","",IF(INDEX(资金流水!Q$5:Q$3015,$O12)="","",INDEX(资金流水!Q$5:Q$3015,$O12))) | O12: =IFERROR(MATCH($A12,资金流水!$V$5:$V$3015,0),"")
A13: 6 | B13: =IF($O13="","",IF(INDEX(资金流水!B$5:B$3032,$O13)="","",INDEX(资金流水!B$5:B$3032,$O13))) | C13: =IF($O13="","",IF(INDEX(资金流水!C$5:C$3032,$O13)="","",INDEX(资金流水!C$5:C$3032,$O13))) | D13: =IF($O13="","",IF(INDEX(资金流水!D$5:D$3032,$O13)="","",INDEX(资金流水!D$5:D$3032,$O13))) | E13: =IF($O13="","",IF(INDEX(资金流水!E$5:E$3032,$O13)="","",INDEX(资金流水!E$5:E$3032,$O13))) | F13: =IF($O13="","",IF(INDEX(资金流水!J$5:J$3032,$O13)="","",INDEX(资金流水!J$5:J$3032,$O13))) | G13: =IF($O13="","",IF(INDEX(资金流水!K$5:K$3032,$O13)="","",INDEX(资金流水!K$5:K$3032,$O13))) | H13: =IF($O13="","",IF(INDEX(资金流水!H$5:H$3032,$O13)="","",INDEX(资金流水!H$5:H$3032,$O13))) | I13: =IF($O13="","",IF(INDEX(资金流水!L$5:L$3032,$O13)="","",INDEX(资金流水!L$5:L$3032,$O13))) | J13: =IF($O13="","",IF(INDEX(资金流水!I$5:I$3032,$O13)="","",INDEX(资金流水!I$5:I$3032,$O13))) | K13: =IF($O13="","",IF(INDEX(资金流水!T$5:T$3015,$O13)="","",INDEX(资金流水!T$5:T$3015,$O13))) | L13: =IF($O13="","",IF(INDEX(资金流水!U$5:U$3015,$O13)="","",INDEX(资金流水!U$5:U$3015,$O13))) | M13: =IF($O13="","",IF(INDEX(资金流水!Q$5:Q$3015,$O13)="","",INDEX(资金流水!Q$5:Q$3015,$O13))) | O13: =IFERROR(MATCH($A13,资金流水!$V$5:$V$3015,0),"")
A14: 7 | B14: =IF($O14="","",IF(INDEX(资金流水!B$5:B$3032,$O14)="","",INDEX(资金流水!B$5:B$3032,$O14))) | C14: =IF($O14="","",IF(INDEX(资金流水!C$5:C$3032,$O14)="","",INDEX(资金流水!C$5:C$3032,$O14))) | D14: =IF($O14="","",IF(INDEX(资金流水!D$5:D$3032,$O14)="","",INDEX(资金流水!D$5:D$3032,$O14))) | E14: =IF($O14="","",IF(INDEX(资金流水!E$5:E$3032,$O14)="","",INDEX(资金流水!E$5:E$3032,$O14))) | F14: =IF($O14="","",IF(INDEX(资金流水!J$5:J$3032,$O14)="","",INDEX(资金流水!J$5:J$3032,$O14))) | G14: =IF($O14="","",IF(INDEX(资金流水!K$5:K$3032,$O14)="","",INDEX(资金流水!K$5:K$3032,$O14))) | H14: =IF($O14="","",IF(INDEX(资金流水!H$5:H$3032,$O14)="","",INDEX(资金流水!H$5:H$3032,$O14))) | I14: =IF($O14="","",IF(INDEX(资金流水!L$5:L$3032,$O14)="","",INDEX(资金流水!L$5:L$3032,$O14))) | J14: =IF($O14="","",IF(INDEX(资金流水!I$5:I$3032,$O14)="","",INDEX(资金流水!I$5:I$3032,$O14))) | K14: =IF($O14="","",IF(INDEX(资金流水!T$5:T$3015,$O14)="","",INDEX(资金流水!T$5:T$3015,$O14))) | L14: =IF($O14="","",IF(INDEX(资金流水!U$5:U$3015,$O14)="","",INDEX(资金流水!U$5:U$3015,$O14))) | M14: =IF($O14="","",IF(INDEX(资金流水!Q$5:Q$3015,$O14)="","",INDEX(资金流水!Q$5:Q$3015,$O14))) | O14: =IFERROR(MATCH($A14,资金流水!$V$5:$V$3015,0),"")
A15: 8 | B15: =IF($O15="","",IF(INDEX(资金流水!B$5:B$3032,$O15)="","",INDEX(资金流水!B$5:B$3032,$O15))) | C15: =IF($O15="","",IF(INDEX(资金流水!C$5:C$3032,$O15)="","",INDEX(资金流水!C$5:C$3032,$O15))) | D15: =IF($O15="","",IF(INDEX(资金流水!D$5:D$3032,$O15)="","",INDEX(资金流水!D$5:D$3032,$O15))) | E15: =IF($O15="","",IF(INDEX(资金流水!E$5:E$3032,$O15)="","",INDEX(资金流水!E$5:E$3032,$O15))) | F15: =IF($O15="","",IF(INDEX(资金流水!J$5:J$3032,$O15)="","",INDEX(资金流水!J$5:J$3032,$O15))) | G15: =IF($O15="","",IF(INDEX(资金流水!K$5:K$3032,$O15)="","",INDEX(资金流水!K$5:K$3032,$O15))) | H15: =IF($O15="","",IF(INDEX(资金流水!H$5:H$3032,$O15)="","",INDEX(资金流水!H$5:H$3032,$O15))) | I15: =IF($O15="","",IF(INDEX(资金流水!L$5:L$3032,$O15)="","",INDEX(资金流水!L$5:L$3032,$O15))) | J15: =IF($O15="","",IF(INDEX(资金流水!I$5:I$3032,$O15)="","",INDEX(资金流水!I$5:I$3032,$O15))) | K15: =IF($O15="","",IF(INDEX(资金流水!T$5:T$3015,$O15)="","",INDEX(资金流水!T$5:T$3015,$O15))) | L15: =IF($O15="","",IF(INDEX(资金流水!U$5:U$3015,$O15)="","",INDEX(资金流水!U$5:U$3015,$O15))) | M15: =IF($O15="","",IF(INDEX(资金流水!Q$5:Q$3015,$O15)="","",INDEX(资金流水!Q$5:Q$3015,$O15))) | O15: =IFERROR(MATCH($A15,资金流水!$V$5:$V$3015,0),"")
A16: 9 | B16: =IF($O16="","",IF(INDEX(资金流水!B$5:B$3032,$O16)="","",INDEX(资金流水!B$5:B$3032,$O16))) | C16: =IF($O16="","",IF(INDEX(资金流水!C$5:C$3032,$O16)="","",INDEX(资金流水!C$5:C$3032,$O16))) | D16: =IF($O16="","",IF(INDEX(资金流水!D$5:D$3032,$O16)="","",INDEX(资金流水!D$5:D$3032,$O16))) | E16: =IF($O16="","",IF(INDEX(资金流水!E$5:E$3032,$O16)="","",INDEX(资金流水!E$5:E$3032,$O16))) | F16: =IF($O16="","",IF(INDEX(资金流水!J$5:J$3032,$O16)="","",INDEX(资金流水!J$5:J$3032,$O16))) | G16: =IF($O16="","",IF(INDEX(资金流水!K$5:K$3032,$O16)="","",INDEX(资金流水!K$5:K$3032,$O16))) | H16: =IF($O16="","",IF(INDEX(资金流水!H$5:H$3032,$O16)="","",INDEX(资金流水!H$5:H$3032,$O16))) | I16: =IF($O16="","",IF(INDEX(资金流水!L$5:L$3032,$O16)="","",INDEX(资金流水!L$5:L$3032,$O16))) | J16: =IF($O16="","",IF(INDEX(资金流水!I$5:I$3032,$O16)="","",INDEX(资金流水!I$5:I$3032,$O16))) | K16: =IF($O16="","",IF(INDEX(资金流水!T$5:T$3015,$O16)="","",INDEX(资金流水!T$5:T$3015,$O16))) | L16: =IF($O16="","",IF(INDEX(资金流水!U$5:U$3015,$O16)="","",INDEX(资金流水!U$5:U$3015,$O16))) | M16: =IF($O16="","",IF(INDEX(资金流水!Q$5:Q$3015,$O16)="","",INDEX(资金流水!Q$5:Q$3015,$O16))) | O16: =IFERROR(MATCH($A16,资金流水!$V$5:$V$3015,0),"")
A17: 10 | B17: =IF($O17="","",IF(INDEX(资金流水!B$5:B$3032,$O17)="","",INDEX(资金流水!B$5:B$3032,$O17))) | C17: =IF($O17="","",IF(INDEX(资金流水!C$5:C$3032,$O17)="","",INDEX(资金流水!C$5:C$3032,$O17))) | D17: =IF($O17="","",IF(INDEX(资金流水!D$5:D$3032,$O17)="","",INDEX(资金流水!D$5:D$3032,$O17))) | E17: =IF($O17="","",IF(INDEX(资金流水!E$5:E$3032,$O17)="","",INDEX(资金流水!E$5:E$3032,$O17))) | F17: =IF($O17="","",IF(INDEX(资金流水!J$5:J$3032,$O17)="","",INDEX(资金流水!J$5:J$3032,$O17))) | G17: =IF($O17="","",IF(INDEX(资金流水!K$5:K$3032,$O17)="","",INDEX(资金流水!K$5:K$3032,$O17))) | H17: =IF($O17="","",IF(INDEX(资金流水!H$5:H$3032,$O17)="","",INDEX(资金流水!H$5:H$3032,$O17))) | I17: =IF($O17="","",IF(INDEX(资金流水!L$5:L$3032,$O17)="","",INDEX(资金流水!L$5:L$3032,$O17))) | J17: =IF($O17="","",IF(INDEX(资金流水!I$5:I$3032,$O17)="","",INDEX(资金流水!I$5:I$3032,$O17))) | K17: =IF($O17="","",IF(INDEX(资金流水!T$5:T$3015,$O17)="","",INDEX(资金流水!T$5:T$3015,$O17))) | L17: =IF($O17="","",IF(INDEX(资金流水!U$5:U$3015,$O17)="","",INDEX(资金流水!U$5:U$3015,$O17))) | M17: =IF($O17="","",IF(INDEX(资金流水!Q$5:Q$3015,$O17)="","",INDEX(资金流水!Q$5:Q$3015,$O17))) | O17: =IFERROR(MATCH($A17,资金流水!$V$5:$V$3015,0),"")
A18: 11 | B18: =IF($O18="","",IF(INDEX(资金流水!B$5:B$3032,$O18)="","",INDEX(资金流水!B$5:B$3032,$O18))) | C18: =IF($O18="","",IF(INDEX(资金流水!C$5:C$3032,$O18)="","",INDEX(资金流水!C$5:C$3032,$O18))) | D18: =IF($O18="","",IF(INDEX(资金流水!D$5:D$3032,$O18)="","",INDEX(资金流水!D$5:D$3032,$O18))) | E18: =IF($O18="","",IF(INDEX(资金流水!E$5:E$3032,$O18)="","",INDEX(资金流水!E$5:E$3032,$O18))) | F18: =IF($O18="","",IF(INDEX(资金流水!J$5:J$3032,$O18)="","",INDEX(资金流水!J$5:J$3032,$O18))) | G18: =IF($O18="","",IF(INDEX(资金流水!K$5:K$3032,$O18)="","",INDEX(资金流水!K$5:K$3032,$O18))) | H18: =IF($O18="","",IF(INDEX(资金流水!H$5:H$3032,$O18)="","",INDEX(资金流水!H$5:H$3032,$O18))) | I18: =IF($O18="","",IF(INDEX(资金流水!L$5:L$3032,$O18)="","",INDEX(资金流水!L$5:L$3032,$O18))) | J18: =IF($O18="","",IF(INDEX(资金流水!I$5:I$3032,$O18)="","",INDEX(资金流水!I$5:I$3032,$O18))) | K18: =IF($O18="","",IF(INDEX(资金流水!T$5:T$3015,$O18)="","",INDEX(资金流水!T$5:T$3015,$O18))) | L18: =IF($O18="","",IF(INDEX(资金流水!U$5:U$3015,$O18)="","",INDEX(资金流水!U$5:U$3015,$O18))) | M18: =IF($O18="","",IF(INDEX(资金流水!Q$5:Q$3015,$O18)="","",INDEX(资金流水!Q$5:Q$3015,$O18))) | O18: =IFERROR(MATCH($A18,资金流水!$V$5:$V$3015,0),"")
A19: 12 | B19: =IF($O19="","",IF(INDEX(资金流水!B$5:B$3032,$O19)="","",INDEX(资金流水!B$5:B$3032,$O19))) | C19: =IF($O19="","",IF(INDEX(资金流水!C$5:C$3032,$O19)="","",INDEX(资金流水!C$5:C$3032,$O19))) | D19: =IF($O19="","",IF(INDEX(资金流水!D$5:D$3032,$O19)="","",INDEX(资金流水!D$5:D$3032,$O19))) | E19: =IF($O19="","",IF(INDEX(资金流水!E$5:E$3032,$O19)="","",INDEX(资金流水!E$5:E$3032,$O19))) | F19: =IF($O19="","",IF(INDEX(资金流水!J$5:J$3032,$O19)="","",INDEX(资金流水!J$5:J$3032,$O19))) | G19: =IF($O19="","",IF(INDEX(资金流水!K$5:K$3032,$O19)="","",INDEX(资金流水!K$5:K$3032,$O19))) | H19: =IF($O19="","",IF(INDEX(资金流水!H$5:H$3032,$O19)="","",INDEX(资金流水!H$5:H$3032,$O19))) | I19: =IF($O19="","",IF(INDEX(资金流水!L$5:L$3032,$O19)="","",INDEX(资金流水!L$5:L$3032,$O19))) | J19: =IF($O19="","",IF(INDEX(资金流水!I$5:I$3032,$O19)="","",INDEX(资金流水!I$5:I$3032,$O19))) | K19: =IF($O19="","",IF(INDEX(资金流水!T$5:T$3015,$O19)="","",INDEX(资金流水!T$5:T$3015,$O19))) | L19: =IF($O19="","",IF(INDEX(资金流水!U$5:U$3015,$O19)="","",INDEX(资金流水!U$5:U$3015,$O19))) | M19: =IF($O19="","",IF(INDEX(资金流水!Q$5:Q$3015,$O19)="","",INDEX(资金流水!Q$5:Q$3015,$O19))) | O19: =IFERROR(MATCH($A19,资金流水!$V$5:$V$3015,0),"")
... A207: 200 | B207: =IF($O207="","",IF(INDEX(资金流水!B$5:B$3032,$O207)="","",INDEX(资金流水!B$5:B$3032,$O207))) | C207: =IF($O207="","",IF(INDEX(资金流水!C$5:C$3032,$O207)="","",INDEX(资金流水!C$5:C$3032,$O207))) | D207: =IF($O207="","",IF(INDEX(资金流水!D$5:D$3032,$O207)="","",INDEX(资金流水!D$5:D$3032,$O207))) | E207: =IF($O207="","",IF(INDEX(资金流水!E$5:E$3032,$O207)="","",INDEX(资金流水!E$5:E$3032,$O207))) | F207: =IF($O207="","",IF(INDEX(资金流水!J$5:J$3032,$O207)="","",INDEX(资金流水!J$5:J$3032,$O207))) | G207: =IF($O207="","",IF(INDEX(资金流水!K$5:K$3032,$O207)="","",INDEX(资金流水!K$5:K$3032,$O207))) | H207: =IF($O207="","",IF(INDEX(资金流水!H$5:H$3032,$O207)="","",INDEX(资金流水!H$5:H$3032,$O207))) | I207: =IF($O207="","",IF(INDEX(资金流水!L$5:L$3032,$O207)="","",INDEX(资金流水!L$5:L$3032,$O207))) | J207: =IF($O207="","",IF(INDEX(资金流水!I$5:I$3032,$O207)="","",INDEX(资金流水!I$5:I$3032,$O207))) | K207: =IF($O207="","",IF(INDEX(资金流水!T$5:T$3015,$O207)="","",INDEX(资金流水!T$5:T$3015,$O207))) | L207: =IF($O207="","",IF(INDEX(资金流水!U$5:U$3015,$O207)="","",INDEX(资金流水!U$5:U$3015,$O207))) | M207: =IF($O207="","",IF(INDEX(资金流水!Q$5:Q$3015,$O207)="","",INDEX(资金流水!Q$5:Q$3015,$O207))) | O207: =IFERROR(MATCH($A207,资金流水!$V$5:$V$3015,0),"")
F208: 本项目合计 | G208: =SUM(G8:G207) -> 0 | I208: =SUM(I8:I207) -> 0

Sheet 月度汇报表
A1: 月度经营汇报表 — 给老板看的一页纸
A2: 汇报年月 | B2: 202602 | C2: 格式如 202606 | D2: 公司范围 | E2: 全部 | F2: 下拉可选某家公司；要看全集团请手打“全部”两字。本页所有栏目都跟着它走。
A3: 口径说明：【收入以开票为准】经营收入取自「开票登记」（含税或不含税由 基础资料!AH4 开关控制），利息/理财/补助这类永远没有发票的收入仍按「资金流水」实收计入。【现金口径】= 当月银行实际进出，回答“钱是多是少”；【损益口径】= 开票收入 + 非开票收入 − 按业务归属月匹配的成本费用，并剔除保证金、股东往来等非损益项，回答“这个月真赚了多少”。开票了没收到钱、或收到去年项目的尾款，都不会让本月内帐盈亏失真。
A5: 一、本月核心指标
A6: 本月开票收入 | B6: =IF(基础资料!$AH$4="不含税金额",SUMIFS(开票登记!$J$5:$J$504,开票登记!$R$5:$R$504,$B$2,开票登记!$C$5:$C$504,IF($E$2="全部","*",$E$2)),SUMIFS(开票登记!$M$5:$M$504,开票登记!$R$5:$R$504,$B$2,开票登记!$C$5:$C$504,IF($E$2="全部","*",$E$2))) -> 285568.1 | C6: 现金流入(实收) | D6: =SUMIFS(资金流水!$K$5:$K$3032,资金流水!$S$5:$S$3015,$B$2,资金流水!$D$5:$D$3032,IF($E$2="全部","*",$E$2)) -> #VALUE! | E6: 现金流出 | F6: =SUMIFS(资金流水!$L$5:$L$3032,资金流水!$S$5:$S$3015,$B$2,资金流水!$D$5:$D$3032,IF($E$2="全部","*",$E$2)) -> #VALUE! | G6: 现金净流量 | H6: =$D$6-$F$6 -> #VALUE!
A7: 损益口径收入 | B7: =$B$6+SUMIFS(资金流水!$K$5:$K$3032,资金流水!$T$5:$T$3015,$B$2,资金流水!$D$5:$D$3032,IF($E$2="全部","*",$E$2),资金流水!$X$5:$X$3015,"非经营收入") -> #VALUE! | C7: 损益口径成本费用 | D7: =SUMIFS(资金流水!$L$5:$L$3032,资金流水!$T$5:$T$3015,$B$2,资金流水!$D$5:$D$3032,IF($E$2="全部","*",$E$2),资金流水!$W$5:$W$3015,"项目成本")+SUMIFS(资金流水!$L$5:$L$3032,资金流水!$T$5:$T$3015,$B$2,资金流水!$D$5:$D$3032,IF($E$2="全部","*",$E$2),资金流水!$W$5:$W$3015,"管理费用")+SUMIFS(资金流水!$L$5:$L$3032,资金流水!$T$5:$T$3015,$B$2,资金流水!$D$5:$D$3032,IF($E$2="全部","*",$E$2),资金流水!$W$5:$W$3015,"人工社保")+SUMIFS(资金流水!$L$5:$L$3032,资金流水!$T$5:$T$3015,$B$2,资金流水!$D$5:$D$3032,IF($E$2="全部","*",$E$2),资金流水!$W$5:$W$3015,"税费")+SUMIFS(资金流水!$L$5:$L$3032,资金流水!$T$5:$T$3015,$B$2,资金流水!$D$5:$D$3032,IF($E$2="全部","*",$E$2),资金流水!$W$5:$W$3015,"财务费用") -> #VALUE! | E7: 内帐盈亏 | F7: =$B$7-$D$7 -> #VALUE! | G7: 内帐利润率 | H7: =IFERROR($F$7/$B$7,"")
A8: 本月开票税额 | B8: =SUMIFS(开票登记!$L$5:$L$504,开票登记!$R$5:$R$504,$B$2,开票登记!$C$5:$C$504,IF($E$2="全部","*",$E$2)) -> 29450.58 | C8: 已开票未收款(累计) | D8: =SUMIFS(开票登记!$P$5:$P$504,开票登记!$C$5:$C$504,IF($E$2="全部","*",$E$2)) -> #VALUE! | E8: 台账应收余额 | F8: =SUMIFS(应收应付台账!$L$5:$L$304,应收应付台账!$B$5:$B$304,"应收",应收应付台账!$C$5:$C$304,IF($E$2="全部","*",$E$2)) -> #VALUE! | G8: 期末资金总额 | H8: =SUMIFS(资金流水!$M$5:$M$3015,资金流水!$D$5:$D$3032,IF($E$2="全部","*",$E$2),资金流水!$S$5:$S$3015,"<="&$B$2)+SUMIFS(资金流水!$K$5:$K$3032,资金流水!$D$5:$D$3032,IF($E$2="全部","*",$E$2),资金流水!$S$5:$S$3015,"<="&$B$2)-SUMIFS(资金流水!$L$5:$L$3032,资金流水!$D$5:$D$3032,IF($E$2="全部","*",$E$2),资金流水!$S$5:$S$3015,"<="&$B$2) -> #VALUE!
A9: 台账应付余额 | B9: =SUMIFS(应收应付台账!$L$5:$L$304,应收应付台账!$B$5:$B$304,"应付",应收应付台账!$C$5:$C$304,IF($E$2="全部","*",$E$2)) -> #VALUE! | C9: 本月收到往期款 | D9: =SUMIFS(资金流水!$K$5:$K$3032,资金流水!$S$5:$S$3015,$B$2,资金流水!$D$5:$D$3032,IF($E$2="全部","*",$E$2),资金流水!$T$5:$T$3015,"<"&$B$2) -> #VALUE! | E9: 本月支付往期成本 | F9: =SUMIFS(资金流水!$L$5:$L$3032,资金流水!$S$5:$S$3015,$B$2,资金流水!$D$5:$D$3032,IF($E$2="全部","*",$E$2),资金流水!$T$5:$T$3015,"<"&$B$2) -> #VALUE! | G9: 本月跨期笔数 | H9: =COUNTIFS(资金流水!$S$5:$S$3015,$B$2,资金流水!$D$5:$D$3032,IF($E$2="全部","*",$E$2),资金流水!$U$5:$U$3015,"跨期") -> #VALUE!
A11: 二、收入明细（按收入类别）
A12: 收入类别 | B12: 收入大类 | C12: 本月收入 (损益口径) | D12: 占比 | E12: 本月实收现金 (按发生月) | F12: 取数来源
