Workbook

Sheet 使用说明
A1: 更多财务实操模板，可自行搜索抖音/视频号：老财务的实操笔记
A3: 【老财务实操自用｜初级版财务台账模板】
A4: 作者：老财务的实操笔记
A5: ——————————————————————————
A6: 适用对象：小微企业、个体工商户、小规模纳税人、商贸服务类等
A7: 版本说明
A8: 本套为**通用基础初级版**，满足税务管理、费用报销、收支登记、票据管理等
A9: 可根据行业属性、业务规模、升级定制版。
A11: 模板清单，持续更新
A12: 1、应收账款风险预警表
A13: 2、日常经营情况汇总表
A14: 3、进项台帐自动查重表
... A47: 老财务自用模板｜禁止外传、倒卖、商用

Sheet 基础资料
A1: 账户 | B1: 收支类别 （无筛选） | C1: 收/支项目类别 | E1: 客户 | F1: 客户期初余额 | H1: 供应商 | I1: 供应商期初余额
A2: 金辉稠州 | C2: 借款本金 | E2: 曹泰宁 | H2: 供应商1
A3: 典当微信 | B3: 收入类 | C3: 借款利息 | E3: 曹玉洁 | H3: 供应商2
A4: 林总浦发 | B4: 收入类 | C4: 借款滞纳金 | E4: 曾光雄 | H4: 供应商3
A5: 吴姐建行 | B5: 收入类 | C5: 银行结息 | E5: 曾云 | H5: 供应商4
A6: 吴姐民生 | B6: 费用支出类 | C6: 员工工资 | E6: 常虹 | H6: 供应商5
A7: 吴建忠浦发 | B7: 费用支出类 | C7: 水电费 | E7: 陈滨 | H7: 供应商6
A8: 吴姐兴业 | B8: 费用支出类 | C8: 房租 | E8: 陈承辉 | H8: 供应商7
A9: 明道对公 | B9: 费用支出类 | C9: 办公费用 | E9: 陈大鑫 | H9: 供应商8
A10: 金辉对公 | B10: 费用支出类 | C10: 招待费 | E10: 陈东 | H10: 供应商9
A11: 吴姐微信 | B11: 费用支出类 | C11: 渠道费用 | E11: 陈福荣 | H11: 供应商10
A12: 备用1 | B12: 收入类 | C12: 手续费-收 | E12: 陈国宝 | H12: 供应商11
A13: 备用2 | C13: 过桥/解押本金 | E13: 陈建华 | H13: 供应商12
A14: 备用3 | B14: 往来款 | C14: 客户款项 | E14: 陈乐贵 | H14: 供应商13
A15: 备用4 | B15: 往来款 | C15: 调拔款 | E15: 陈立
B16: 费用支出类 | C16: 明道利息 | E16: 陈隆鑫
C17: 抵押物回收款 | E17: 陈敏峰
B18: 费用支出类 | C18: 律师诉讼费 | E18: 陈琴
B19: 费用支出类 | C19: 金辉利息 | E19: 陈庆生
B20: 费用支出类 | C20: 社医保 | E20: 陈守琴
B21: 往来款 | C21: 收入其他 | E21: 陈天敏
B22: 费用支出类 | C22: 个税 | E22: 陈跃飞
C23: 公积金 | E23: 陈征
C24: 金辉本金 | E24: 陈忠军
C25: 明道本金 | E25: 池鸿
E26: 典当微信
E27: 董智宇
E28: 杜若
E29: 段乐
E30: 方楚钰
E31: 方士雯
E32: 方秀全
E33: 高文玉
E34: 郭宝龙
E35: 郭联兵
E36: 何博文
E37: 胡建通
... E172: 朱俊良

Sheet 数据录入
A1: 多帐户收支登记表
F2: 收入总额 | G2: 支出总额 | H2: 账户余额
F3: =SUBTOTAL(109,$F$4:$F$5077) -> 38290244 | G3: =SUBTOTAL(109,$G$4:$G$5077) -> 36629662 | H3: =SUBTOTAL(109,$H$5:$H$18)+F3-G3 -> 2380462.6
A4: 序号 | B4: 日期 | C4: 公司账户 | D4: 收/支项目类别 | E4: 摘要内容 | F4: 收入 | G4: 支出 | H4: 账户余额 | I4: 客户 | J4: 供应商 | K4: 月份
A5: =IF(B5="","",COUNTA($B$5:B5)) -> 1 | B5: 46174 | C5: 金辉稠州 | E5: 期初余额 | H5: 219263.12 | K5: =IF($B5="","",--TEXT($B5,"yyyymm")) -> 202606
A6: =IF(B6="","",COUNTA($B$5:B6)) -> 2 | B6: 46174 | C6: 典当微信 | E6: 期初余额 | H6: 112326.39 | K6: =IF($B6="","",--TEXT($B6,"yyyymm")) -> 202606
A7: =IF(B7="","",COUNTA($B$5:B7)) -> 3 | B7: 46174 | C7: 林总浦发 | E7: 期初余额 | H7: 73513.15 | K7: =IF($B7="","",--TEXT($B7,"yyyymm")) -> 202606
A8: =IF(B8="","",COUNTA($B$5:B8)) -> 4 | B8: 46174 | C8: 吴姐建行 | E8: 期初余额 | H8: 90026.28 | K8: =IF($B8="","",--TEXT($B8,"yyyymm")) -> 202606
A9: =IF(B9="","",COUNTA($B$5:B9)) -> 5 | B9: 46174 | C9: 吴姐民生 | E9: 期初余额 | H9: 15829.44 | K9: =IF($B9="","",--TEXT($B9,"yyyymm")) -> 202606
A10: =IF(B10="","",COUNTA($B$5:B10)) -> 6 | B10: 46174 | C10: 吴建忠浦发 | E10: 期初余额 | H10: 208922.52 | K10: =IF($B10="","",--TEXT($B10,"yyyymm")) -> 202606
A11: =IF(B11="","",COUNTA($B$5:B11)) -> 7 | B11: 46174 | C11: 吴姐兴业 | E11: 期初余额 | H11: 0 | K11: =IF($B11="","",--TEXT($B11,"yyyymm")) -> 202606
A12: =IF(B12="","",COUNTA($B$5:B12)) -> 8 | B12: 46174 | C12: 明道对公 | E12: 期初余额 | H12: 0 | K12: =IF($B12="","",--TEXT($B12,"yyyymm")) -> 202606
A13: =IF(B13="","",COUNTA($B$5:B13)) -> 9 | B13: 46174 | C13: 金辉对公 | E13: 期初余额 | H13: 0 | K13: =IF($B13="","",--TEXT($B13,"yyyymm")) -> 202606
A14: =IF(B14="","",COUNTA($B$5:B14)) -> 10 | B14: 46174 | C14: 吴姐微信 | E14: 期初余额 | H14: 0 | K14: =IF($B14="","",--TEXT($B14,"yyyymm")) -> 202606
A15: =IF(B15="","",COUNTA($B$5:B15)) -> 11 | B15: 46174 | C15: 备用1 | E15: 期初余额 | H15: 0 | K15: =IF($B15="","",--TEXT($B15,"yyyymm")) -> 202606
A16: =IF(B16="","",COUNTA($B$5:B16)) -> 12 | B16: 46174 | C16: 备用2 | E16: 期初余额 | H16: 0 | K16: =IF($B16="","",--TEXT($B16,"yyyymm")) -> 202606
... A18: =IF(B18="","",COUNTA($B$5:B18)) -> 14 | B18: 46174 | C18: 备用4 | E18: 期初余额 | H18: 0 | K18: =IF($B18="","",--TEXT($B18,"yyyymm")) -> 202606
A19: =IF(B19="","",COUNTA($B$5:B19)) -> 15 | B19: 46204 | C19: 吴建忠浦发 | D19: 借款本金 | E19: 杨文昕转回款 | F19: 500000 | H19: =IFERROR(VLOOKUP($C19,$C$5:$H$18,6,0)+SUMIF($C$19:$C19,$C19,$F$19:$F19)-SUMIF($C$19:$C19,$C19,$G$19:$G19),"") -> 708922.52 | I19: 杨文昕 | K19: =IF($B19="","",--TEXT($B19,"yyyymm")) -> 202607
A20: =IF(B20="","",COUNTA($B$5:B20)) -> 16 | B20: 46204 | C20: 吴建忠浦发 | D20: 借款本金 | E20: 陈庆生回款 | F20: 500000 | H20: =IFERROR(VLOOKUP($C20,$C$5:$H$18,6,0)+SUMIF($C$19:$C20,$C20,$F$19:$F20)-SUMIF($C$19:$C20,$C20,$G$19:$G20),"") -> 1208922.5 | I20: 陈庆生 | K20: =IF($B20="","",--TEXT($B20,"yyyymm")) -> 202607
A21: =IF(B21="","",COUNTA($B$5:B21)) -> 17 | B21: 46204 | C21: 吴建忠浦发 | D21: 调拔款 | E21: 吴建忠浦发转林总浦发 | G21: 700000 | H21: =IFERROR(VLOOKUP($C21,$C$5:$H$18,6,0)+SUMIF($C$19:$C21,$C21,$F$19:$F21)-SUMIF($C$19:$C21,$C21,$G$19:$G21),"") -> 508922.52 | I21: 林总浦发 | K21: =IF($B21="","",--TEXT($B21,"yyyymm")) -> 202607
A22: =IF(B22="","",COUNTA($B$5:B22)) -> 18 | B22: 46204 | C22: 吴建忠浦发 | D22: 调拔款 | E22: 吴建忠浦发转林总浦发 | G22: 500000 | H22: =IFERROR(VLOOKUP($C22,$C$5:$H$18,6,0)+SUMIF($C$19:$C22,$C22,$F$19:$F22)-SUMIF($C$19:$C22,$C22,$G$19:$G22),"") -> 8922.52 | I22: 林总浦发 | K22: =IF($B22="","",--TEXT($B22,"yyyymm")) -> 202607
A23: =IF(B23="","",COUNTA($B$5:B23)) -> 19 | B23: 46205 | C23: 吴建忠浦发 | D23: 借款本金 | E23: 杨文昕回款 | F23: 500000 | H23: =IFERROR(VLOOKUP($C23,$C$5:$H$18,6,0)+SUMIF($C$19:$C23,$C23,$F$19:$F23)-SUMIF($C$19:$C23,$C23,$G$19:$G23),"") -> 508922.52 | I23: 杨文昕 | K23: =IF($B23="","",--TEXT($B23,"yyyymm")) -> 202607
A24: =IF(B24="","",COUNTA($B$5:B24)) -> 20 | B24: 46205 | C24: 吴建忠浦发 | D24: 调拔款 | E24: 吴建忠浦发转林总浦发 | G24: 500000 | H24: =IFERROR(VLOOKUP($C24,$C$5:$H$18,6,0)+SUMIF($C$19:$C24,$C24,$F$19:$F24)-SUMIF($C$19:$C24,$C24,$G$19:$G24),"") -> 8922.52 | I24: 林总浦发 | K24: =IF($B24="","",--TEXT($B24,"yyyymm")) -> 202607
A25: =IF(B25="","",COUNTA($B$5:B25)) -> 21 | B25: 46206 | C25: 吴建忠浦发 | D25: 借款本金 | E25: 收到杨文昕回款 | F25: 300000 | H25: =IFERROR(VLOOKUP($C25,$C$5:$H$18,6,0)+SUMIF($C$19:$C25,$C25,$F$19:$F25)-SUMIF($C$19:$C25,$C25,$G$19:$G25),"") -> 308922.52 | I25: 杨文昕 | K25: =IF($B25="","",--TEXT($B25,"yyyymm")) -> 202607
A26: =IF(B26="","",COUNTA($B$5:B26)) -> 22 | B26: 46207 | C26: 吴建忠浦发 | D26: 借款本金 | E26: 收到杨文昕回款 | F26: 100000 | H26: =IFERROR(VLOOKUP($C26,$C$5:$H$18,6,0)+SUMIF($C$19:$C26,$C26,$F$19:$F26)-SUMIF($C$19:$C26,$C26,$G$19:$G26),"") -> 408922.52 | I26: 杨文昕 | K26: =IF($B26="","",--TEXT($B26,"yyyymm")) -> 202607
A27: =IF(B27="","",COUNTA($B$5:B27)) -> 23 | B27: 46209 | C27: 吴建忠浦发 | D27: 借款本金 | E27: 收到杨文昕回款 | F27: 120000 | H27: =IFERROR(VLOOKUP($C27,$C$5:$H$18,6,0)+SUMIF($C$19:$C27,$C27,$F$19:$F27)-SUMIF($C$19:$C27,$C27,$G$19:$G27),"") -> 528922.52 | I27: 杨文昕 | K27: =IF($B27="","",--TEXT($B27,"yyyymm")) -> 202607
A28: =IF(B28="","",COUNTA($B$5:B28)) -> 24 | B28: 46209 | C28: 吴建忠浦发 | D28: 调拔款 | E28: 吴建忠浦发转林总浦发 | G28: 20000 | H28: =IFERROR(VLOOKUP($C28,$C$5:$H$18,6,0)+SUMIF($C$19:$C28,$C28,$F$19:$F28)-SUMIF($C$19:$C28,$C28,$G$19:$G28),"") -> 508922.52 | I28: 林总浦发 | K28: =IF($B28="","",--TEXT($B28,"yyyymm")) -> 202607
A29: =IF(B29="","",COUNTA($B$5:B29)) -> 25 | B29: 46209 | C29: 吴建忠浦发 | D29: 调拔款 | E29: 吴建忠浦发转吴姐建行 | G29: 300000 | H29: =IFERROR(VLOOKUP($C29,$C$5:$H$18,6,0)+SUMIF($C$19:$C29,$C29,$F$19:$F29)-SUMIF($C$19:$C29,$C29,$G$19:$G29),"") -> 208922.52 | I29: 吴姐建行 | K29: =IF($B29="","",--TEXT($B29,"yyyymm")) -> 202607
A30: =IF(B30="","",COUNTA($B$5:B30)) -> 26 | B30: 46209 | C30: 吴建忠浦发 | D30: 借款利息 | E30: 杜若利息 | F30: 72800 | H30: =IFERROR(VLOOKUP($C30,$C$5:$H$18,6,0)+SUMIF($C$19:$C30,$C30,$F$19:$F30)-SUMIF($C$19:$C30,$C30,$G$19:$G30),"") -> 281722.52 | I30: 杜若 | K30: =IF($B30="","",--TEXT($B30,"yyyymm")) -> 202607
A31: =IF(B31="","",COUNTA($B$5:B31)) -> 27 | B31: 46209 | C31: 吴建忠浦发 | D31: 借款本金 | E31: 林熙铭本金 | F31: 8333.33 | H31: =IFERROR(VLOOKUP($C31,$C$5:$H$18,6,0)+SUMIF($C$19:$C31,$C31,$F$19:$F31)-SUMIF($C$19:$C31,$C31,$G$19:$G31),"") -> 290055.85 | I31: 林熙铭 | K31: =IF($B31="","",--TEXT($B31,"yyyymm")) -> 202607
A32: =IF(B32="","",COUNTA($B$5:B32)) -> 28 | B32: 46209 | C32: 吴建忠浦发 | D32: 借款利息 | E32: 林熙铭利息 | F32: 6000 | H32: =IFERROR(VLOOKUP($C32,$C$5:$H$18,6,0)+SUMIF($C$19:$C32,$C32,$F$19:$F32)-SUMIF($C$19:$C32,$C32,$G$19:$G32),"") -> 296055.85 | I32: 林熙铭 | K32: =IF($B32="","",--TEXT($B32,"yyyymm")) -> 202607
A33: =IF(B33="","",COUNTA($B$5:B33)) -> 29 | B33: 46209 | C33: 吴建忠浦发 | D33: 明道利息 | E33: 代林熙铭还利息到明道对公 | G33: 4500 | H33: =IFERROR(VLOOKUP($C33,$C$5:$H$18,6,0)+SUMIF($C$19:$C33,$C33,$F$19:$F33)-SUMIF($C$19:$C33,$C33,$G$19:$G33),"") -> 291555.85 | I33: 林熙铭 | K33: =IF($B33="","",--TEXT($B33,"yyyymm")) -> 202607
A34: =IF(B34="","",COUNTA($B$5:B34)) -> 30 | B34: 46210 | C34: 吴建忠浦发 | D34: 调拔款 | E34: 吴建忠浦发转吴姐建行 | G34: 72800 | H34: =IFERROR(VLOOKUP($C34,$C$5:$H$18,6,0)+SUMIF($C$19:$C34,$C34,$F$19:$F34)-SUMIF($C$19:$C34,$C34,$G$19:$G34),"") -> 218755.85 | I34: 吴姐建行 | K34: =IF($B34="","",--TEXT($B34,"yyyymm")) -> 202607
A35: =IF(B35="","",COUNTA($B$5:B35)) -> 31 | B35: 46211 | C35: 吴建忠浦发 | D35: 借款本金 | E35: 潘敏回款 | F35: 900000 | H35: =IFERROR(VLOOKUP($C35,$C$5:$H$18,6,0)+SUMIF($C$19:$C35,$C35,$F$19:$F35)-SUMIF($C$19:$C35,$C35,$G$19:$G35),"") -> 1118755.9 | I35: 潘敏 | K35: =IF($B35="","",--TEXT($B35,"yyyymm")) -> 202607
A36: =IF(B36="","",COUNTA($B$5:B36)) -> 32 | B36: 46211 | C36: 吴建忠浦发 | D36: 手续费-收 | E36: 潘敏回款手续费 | F36: 4540 | H36: =IFERROR(VLOOKUP($C36,$C$5:$H$18,6,0)+SUMIF($C$19:$C36,$C36,$F$19:$F36)-SUMIF($C$19:$C36,$C36,$G$19:$G36),"") -> 1123295.9 | I36: 潘敏 | K36: =IF($B36="","",--TEXT($B36,"yyyymm")) -> 202607
A37: =IF(B37="","",COUNTA($B$5:B37)) -> 33 | B37: 46211 | C37: 吴建忠浦发 | D37: 渠道费用 | E37: 潘敏回款渠道费用 | F37: 5540 | H37: =IFERROR(VLOOKUP($C37,$C$5:$H$18,6,0)+SUMIF($C$19:$C37,$C37,$F$19:$F37)-SUMIF($C$19:$C37,$C37,$G$19:$G37),"") -> 1128835.9 | I37: 潘敏 | K37: =IF($B37="","",--TEXT($B37,"yyyymm")) -> 202607
A38: =IF(B38="","",COUNTA($B$5:B38)) -> 34 | B38: 46211 | C38: 吴建忠浦发 | D38: 客户款项 | E38: 潘敏余款 | F38: 89870 | H38: =IFERROR(VLOOKUP($C38,$C$5:$H$18,6,0)+SUMIF($C$19:$C38,$C38,$F$19:$F38)-SUMIF($C$19:$C38,$C38,$G$19:$G38),"") -> 1218705.9 | I38: 潘敏 | K38: =IF($B38="","",--TEXT($B38,"yyyymm")) -> 202607
A39: =IF(B39="","",COUNTA($B$5:B39)) -> 35 | B39: 46211 | C39: 吴建忠浦发 | D39: 调拔款 | E39: 吴建忠浦发转吴姐建行-潘敏回款 | G39: 900000 | H39: =IFERROR(VLOOKUP($C39,$C$5:$H$18,6,0)+SUMIF($C$19:$C39,$C39,$F$19:$F39)-SUMIF($C$19:$C39,$C39,$G$19:$G39),"") -> 318705.85 | I39: 吴姐建行 | K39: =IF($B39="","",--TEXT($B39,"yyyymm")) -> 202607
A40: =IF(B40="","",COUNTA($B$5:B40)) -> 36 | B40: 46211 | C40: 吴建忠浦发 | D40: 客户款项 | E40: 退潘敏余款 | G40: 89870 | H40: =IFERROR(VLOOKUP($C40,$C$5:$H$18,6,0)+SUMIF($C$19:$C40,$C40,$F$19:$F40)-SUMIF($C$19:$C40,$C40,$G$19:$G40),"") -> 228835.85 | I40: 潘敏 | K40: =IF($B40="","",--TEXT($B40,"yyyymm")) -> 202607
A41: =IF(B41="","",COUNTA($B$5:B41)) -> 37 | B41: 46211 | C41: 吴建忠浦发 | D41: 渠道费用 | E41: 转吴志鑫费用-潘敏回款 | G41: 5540 | H41: =IFERROR(VLOOKUP($C41,$C$5:$H$18,6,0)+SUMIF($C$19:$C41,$C41,$F$19:$F41)-SUMIF($C$19:$C41,$C41,$G$19:$G41),"") -> 223295.85 | I41: 潘敏 | K41: =IF($B41="","",--TEXT($B41,"yyyymm")) -> 202607
A42: =IF(B42="","",COUNTA($B$5:B42)) -> 38 | B42: 46212 | C42: 吴建忠浦发 | D42: 借款本金 | E42: 徐文贵过账的款转回 | F42: 30000 | H42: =IFERROR(VLOOKUP($C42,$C$5:$H$18,6,0)+SUMIF($C$19:$C42,$C42,$F$19:$F42)-SUMIF($C$19:$C42,$C42,$G$19:$G42),"") -> 253295.85 | I42: 徐文贵 | K42: =IF($B42="","",--TEXT($B42,"yyyymm")) -> 202607
A43: =IF(B43="","",COUNTA($B$5:B43)) -> 39 | B43: 46213 | C43: 吴建忠浦发 | D43: 调拔款 | E43: 吴建忠浦发转吴姐建行 | G43: 30000 | H43: =IFERROR(VLOOKUP($C43,$C$5:$H$18,6,0)+SUMIF($C$19:$C43,$C43,$F$19:$F43)-SUMIF($C$19:$C43,$C43,$G$19:$G43),"") -> 223295.85 | I43: 吴姐建行 | K43: =IF($B43="","",--TEXT($B43,"yyyymm")) -> 202607
A44: =IF(B44="","",COUNTA($B$5:B44)) -> 40 | B44: 46218 | C44: 吴建忠浦发 | D44: 借款本金 | E44: 王昌善本金3750 | F44: 3750 | H44: =IFERROR(VLOOKUP($C44,$C$5:$H$18,6,0)+SUMIF($C$19:$C44,$C44,$F$19:$F44)-SUMIF($C$19:$C44,$C44,$G$19:$G44),"") -> 227045.85 | I44: 王昌善 | K44: =IF($B44="","",--TEXT($B44,"yyyymm")) -> 202607
A45: =IF(B45="","",COUNTA($B$5:B45)) -> 41 | B45: 46218 | C45: 吴建忠浦发 | D45: 借款利息 | E45: 王昌善利息1125 | F45: 1125 | H45: =IFERROR(VLOOKUP($C45,$C$5:$H$18,6,0)+SUMIF($C$19:$C45,$C45,$F$19:$F45)-SUMIF($C$19:$C45,$C45,$G$19:$G45),"") -> 228170.85 | I45: 王昌善 | K45: =IF($B45="","",--TEXT($B45,"yyyymm")) -> 202607
A46: =IF(B46="","",COUNTA($B$5:B46)) -> 42 | B46: 46218 | C46: 吴建忠浦发 | D46: 明道利息 | E46: 代王昌善还明道对公1.5分利息750元 | G46: 750 | H46: =IFERROR(VLOOKUP($C46,$C$5:$H$18,6,0)+SUMIF($C$19:$C46,$C46,$F$19:$F46)-SUMIF($C$19:$C46,$C46,$G$19:$G46),"") -> 227420.85 | I46: 王昌善 | K46: =IF($B46="","",--TEXT($B46,"yyyymm")) -> 202607
A47: =IF(B47="","",COUNTA($B$5:B47)) -> 43 | B47: 46218 | C47: 吴建忠浦发 | D47: 借款利息 | E47: 陈天敏7月利息 | F47: 4000 | H47: =IFERROR(VLOOKUP($C47,$C$5:$H$18,6,0)+SUMIF($C$19:$C47,$C47,$F$19:$F47)-SUMIF($C$19:$C47,$C47,$G$19:$G47),"") -> 231420.85 | I47: 陈天敏 | K47: =IF($B47="","",--TEXT($B47,"yyyymm")) -> 202607
A48: =IF(B48="","",COUNTA($B$5:B48)) -> 44 | B48: 46218 | C48: 吴建忠浦发 | D48: 明道利息 | E48: 代陈天敏还明道对公1.5分利息3000元 | G48: 3000 | H48: =IFERROR(VLOOKUP($C48,$C$5:$H$18,6,0)+SUMIF($C$19:$C48,$C48,$F$19:$F48)-SUMIF($C$19:$C48,$C48,$G$19:$G48),"") -> 228420.85 | I48: 明道对公 | K48: =IF($B48="","",--TEXT($B48,"yyyymm")) -> 202607
A49: =IF(B49="","",COUNTA($B$5:B49)) -> 45 | B49: 46218 | C49: 吴建忠浦发 | D49: 借款本金 | E49: 转郑晓龙-置换 | G49: 50000 | H49: =IFERROR(VLOOKUP($C49,$C$5:$H$18,6,0)+SUMIF($C$19:$C49,$C49,$F$19:$F49)-SUMIF($C$19:$C49,$C49,$G$19:$G49),"") -> 178420.85 | I49: 郑晓龙 | K49: =IF($B49="","",--TEXT($B49,"yyyymm")) -> 202607
A50: =IF(B50="","",COUNTA($B$5:B50)) -> 46 | B50: 46219 | C50: 吴建忠浦发 | D50: 调拔款 | E50: 林总建行转吴建忠浦发-置换款转回15万 | F50: 150000 | H50: =IFERROR(VLOOKUP($C50,$C$5:$H$18,6,0)+SUMIF($C$19:$C50,$C50,$F$19:$F50)-SUMIF($C$19:$C50,$C50,$G$19:$G50),"") -> 328420.85 | I50: 林总建行 | K50: =IF($B50="","",--TEXT($B50,"yyyymm")) -> 202607
A51: =IF(B51="","",COUNTA($B$5:B51)) -> 47 | B51: 46219 | C51: 吴建忠浦发 | D51: 调拔款 | E51: 吴姐建行转吴建忠浦发 | F51: 180000 | H51: =IFERROR(VLOOKUP($C51,$C$5:$H$18,6,0)+SUMIF($C$19:$C51,$C51,$F$19:$F51)-SUMIF($C$19:$C51,$C51,$G$19:$G51),"") -> 508420.85 | I51: 吴姐建行 | K51: =IF($B51="","",--TEXT($B51,"yyyymm")) -> 202607
A52: =IF(B52="","",COUNTA($B$5:B52)) -> 48 | B52: 46219 | C52: 吴建忠浦发 | D52: 借款本金 | E52: 转郑晓龙-置换 | G52: 249950 | H52: =IFERROR(VLOOKUP($C52,$C$5:$H$18,6,0)+SUMIF($C$19:$C52,$C52,$F$19:$F52)-SUMIF($C$19:$C52,$C52,$G$19:$G52),"") -> 258470.85 | I52: 郑晓龙 | K52: =IF($B52="","",--TEXT($B52,"yyyymm")) -> 202607
A53: =IF(B53="","",COUNTA($B$5:B53)) -> 49 | B53: 46219 | C53: 吴建忠浦发 | D53: 调拔款 | E53: 吴建忠浦发转林总浦发 | G53: 30000 | H53: =IFERROR(VLOOKUP($C53,$C$5:$H$18,6,0)+SUMIF($C$19:$C53,$C53,$F$19:$F53)-SUMIF($C$19:$C53,$C53,$G$19:$G53),"") -> 228470.85 | I53: 林总浦发 | K53: =IF($B53="","",--TEXT($B53,"yyyymm")) -> 202607
A54: =IF(B54="","",COUNTA($B$5:B54)) -> 50 | B54: 46219 | C54: 吴建忠浦发 | D54: 借款利息 | E54: 汪琼宇（李伟）40万对公利息款-金辉 | F54: 7200 | H54: =IFERROR(VLOOKUP($C54,$C$5:$H$18,6,0)+SUMIF($C$19:$C54,$C54,$F$19:$F54)-SUMIF($C$19:$C54,$C54,$G$19:$G54),"") -> 235670.85 | I54: 汪琼宇 | K54: =IF($B54="","",--TEXT($B54,"yyyymm")) -> 202607
A55: =IF(B55="","",COUNTA($B$5:B55)) -> 51 | B55: 46220 | C55: 吴建忠浦发 | D55: 调拔款 | E55: 吴建忠浦发转林总浦发 | G55: 7200 | H55: =IFERROR(VLOOKUP($C55,$C$5:$H$18,6,0)+SUMIF($C$19:$C55,$C55,$F$19:$F55)-SUMIF($C$19:$C55,$C55,$G$19:$G55),"") -> 228470.85 | I55: 林总浦发 | K55: =IF($B55="","",--TEXT($B55,"yyyymm")) -> 202607
A56: =IF(B56="","",COUNTA($B$5:B56)) -> 52 | B56: 46223 | C56: 吴建忠浦发 | D56: 金辉本金 | E56: 代林昌耿还本金-金辉对公 | G56: 200000 | H56: =IFERROR(VLOOKUP($C56,$C$5:$H$18,6,0)+SUMIF($C$19:$C56,$C56,$F$19:$F56)-SUMIF($C$19:$C56,$C56,$G$19:$G56),"") -> 28470.85 | I56: 金辉稠州 | K56: =IF($B56="","",--TEXT($B56,"yyyymm")) -> 202607
A57: =IF(B57="","",COUNTA($B$5:B57)) -> 53 | B57: 46223 | C57: 吴建忠浦发 | D57: 借款利息 | E57: 汪琼宇（李伟）80万对公利息款-明道 | F57: 14400 | H57: =IFERROR(VLOOKUP($C57,$C$5:$H$18,6,0)+SUMIF($C$19:$C57,$C57,$F$19:$F57)-SUMIF($C$19:$C57,$C57,$G$19:$G57),"") -> 42870.85 | I57: 汪琼宇 | K57: =IF($B57="","",--TEXT($B57,"yyyymm")) -> 202607
A58: =IF(B58="","",COUNTA($B$5:B58)) -> 54 | B58: 46225 | C58: 吴建忠浦发 | D58: 调拔款 | E58: 林总浦发转吴建忠浦发 | F58: 200000 | H58: =IFERROR(VLOOKUP($C58,$C$5:$H$18,6,0)+SUMIF($C$19:$C58,$C58,$F$19:$F58)-SUMIF($C$19:$C58,$C58,$G$19:$G58),"") -> 242870.85 | I58: 林总浦发 | K58: =IF($B58="","",--TEXT($B58,"yyyymm")) -> 202607
A59: =IF(B59="","",COUNTA($B$5:B59)) -> 55 | B59: 46225 | C59: 吴建忠浦发 | D59: 明道利息 | E59: 代汪琼宇还利息款-明道 | G59: 12000 | H59: =IFERROR(VLOOKUP($C59,$C$5:$H$18,6,0)+SUMIF($C$19:$C59,$C59,$F$19:$F59)-SUMIF($C$19:$C59,$C59,$G$19:$G59),"") -> 230870.85 | I59: 汪琼宇 | K59: =IF($B59="","",--TEXT($B59,"yyyymm")) -> 202607
A60: =IF(B60="","",COUNTA($B$5:B60)) -> 56 | B60: 46225 | C60: 吴建忠浦发 | D60: 借款利息 | E60: 林志15万利息1.4分2100 | F60: 2100 | H60: =IFERROR(VLOOKUP($C60,$C$5:$H$18,6,0)+SUMIF($C$19:$C60,$C60,$F$19:$F60)-SUMIF($C$19:$C60,$C60,$G$19:$G60),"") -> 232970.85 | I60: 林志 | K60: =IF($B60="","",--TEXT($B60,"yyyymm")) -> 202607
A61: =IF(B61="","",COUNTA($B$5:B61)) -> 57 | B61: 46225 | C61: 吴建忠浦发 | D61: 手续费-收 | E61: 林志15万手续费 | F61: 800 | H61: =IFERROR(VLOOKUP($C61,$C$5:$H$18,6,0)+SUMIF($C$19:$C61,$C61,$F$19:$F61)-SUMIF($C$19:$C61,$C61,$G$19:$G61),"") -> 233770.85 | I61: 林志 | K61: =IF($B61="","",--TEXT($B61,"yyyymm")) -> 202607
A62: =IF(B62="","",COUNTA($B$5:B62)) -> 58 | B62: 46225 | C62: 吴建忠浦发 | D62: 借款本金 | E62: 胡小丽本金15万 | F62: 150000 | H62: =IFERROR(VLOOKUP($C62,$C$5:$H$18,6,0)+SUMIF($C$19:$C62,$C62,$F$19:$F62)-SUMIF($C$19:$C62,$C62,$G$19:$G62),"") -> 383770.85 | I62: 胡小丽 | K62: =IF($B62="","",--TEXT($B62,"yyyymm")) -> 202607
A63: =IF(B63="","",COUNTA($B$5:B63)) -> 59 | B63: 46225 | C63: 吴建忠浦发 | D63: 手续费-收 | E63: 胡小丽费用12750 | F63: 12750 | H63: =IFERROR(VLOOKUP($C63,$C$5:$H$18,6,0)+SUMIF($C$19:$C63,$C63,$F$19:$F63)-SUMIF($C$19:$C63,$C63,$G$19:$G63),"") -> 396520.85 | I63: 胡小丽 | K63: =IF($B63="","",--TEXT($B63,"yyyymm")) -> 202607
A64: =IF(B64="","",COUNTA($B$5:B64)) -> 60 | B64: 46226 | C64: 吴建忠浦发 | D64: 金辉本金 | E64: 代胡小丽还本金15万+利息3125到金辉对公 | G64: 150000 | H64: =IFERROR(VLOOKUP($C64,$C$5:$H$18,6,0)+SUMIF($C$19:$C64,$C64,$F$19:$F64)-SUMIF($C$19:$C64,$C64,$G$19:$G64),"") -> 246520.85 | I64: 金辉稠州 | K64: =IF($B64="","",--TEXT($B64,"yyyymm")) -> 202607
A65: =IF(B65="","",COUNTA($B$5:B65)) -> 61 | B65: 46226 | C65: 吴建忠浦发 | D65: 金辉利息 | E65: 代胡小丽还利息3125到金辉对公 | G65: 3125 | H65: =IFERROR(VLOOKUP($C65,$C$5:$H$18,6,0)+SUMIF($C$19:$C65,$C65,$F$19:$F65)-SUMIF($C$19:$C65,$C65,$G$19:$G65),"") -> 243395.85 | I65: 金辉稠州 | K65: =IF($B65="","",--TEXT($B65,"yyyymm")) -> 202607
A66: =IF(B66="","",COUNTA($B$5:B66)) -> 62 | B66: 46226 | C66: 吴建忠浦发 | D66: 调拔款 | E66: 吴建忠浦发转林总浦发 | G66: 10000 | H66: =IFERROR(VLOOKUP($C66,$C$5:$H$18,6,0)+SUMIF($C$19:$C66,$C66,$F$19:$F66)-SUMIF($C$19:$C66,$C66,$G$19:$G66),"") -> 233395.85 | I66: 林总浦发 | K66: =IF($B66="","",--TEXT($B66,"yyyymm")) -> 202607
A67: =IF(B67="","",COUNTA($B$5:B67)) -> 63 | B67: 46226 | C67: 吴建忠浦发 | D67: 抵押物回收款 | E67: 杨观宝黄金回收补差价 | G67: 1829 | H67: =IFERROR(VLOOKUP($C67,$C$5:$H$18,6,0)+SUMIF($C$19:$C67,$C67,$F$19:$F67)-SUMIF($C$19:$C67,$C67,$G$19:$G67),"") -> 231566.85 | I67: 杨观宝 | K67: =IF($B67="","",--TEXT($B67,"yyyymm")) -> 202607
A68: =IF(B68="","",COUNTA($B$5:B68)) -> 64 | B68: 46230 | C68: 吴建忠浦发 | D68: 手续费-收 | E68: 吴丹辉杂费-陈乐贵转入 | F68: 1000 | H68: =IFERROR(VLOOKUP($C68,$C$5:$H$18,6,0)+SUMIF($C$19:$C68,$C68,$F$19:$F68)-SUMIF($C$19:$C68,$C68,$G$19:$G68),"") -> 232566.85 | I68: 吴丹辉 | K68: =IF($B68="","",--TEXT($B68,"yyyymm")) -> 202607
A69: =IF(B69="","",COUNTA($B$5:B69)) -> 65 | B69: 46230 | C69: 吴建忠浦发 | D69: 手续费-收 | E69: 曹泰宁费用 | F69: 3500 | H69: =IFERROR(VLOOKUP($C69,$C$5:$H$18,6,0)+SUMIF($C$19:$C69,$C69,$F$19:$F69)-SUMIF($C$19:$C69,$C69,$G$19:$G69),"") -> 236066.85 | I69: 曹泰宁 | K69: =IF($B69="","",--TEXT($B69,"yyyymm")) -> 202607
A70: =IF(B70="","",COUNTA($B$5:B70)) -> 66 | B70: 46231 | C70: 吴建忠浦发 | D70: 借款利息 | E70: 徐远转入明道利息款（后息） | F70: 10000 | H70: =IFERROR(VLOOKUP($C70,$C$5:$H$18,6,0)+SUMIF($C$19:$C70,$C70,$F$19:$F70)-SUMIF($C$19:$C70,$C70,$G$19:$G70),"") -> 246066.85 | I70: 徐远 | K70: =IF($B70="","",--TEXT($B70,"yyyymm")) -> 202607
A71: =IF(B71="","",COUNTA($B$5:B71)) -> 67 | B71: 46231 | C71: 吴建忠浦发 | D71: 调拔款 | E71: 陈乐贵转入拼单款-吴丹辉 | F71: 150000 | H71: =IFERROR(VLOOKUP($C71,$C$5:$H$18,6,0)+SUMIF($C$19:$C71,$C71,$F$19:$F71)-SUMIF($C$19:$C71,$C71,$G$19:$G71),"") -> 396066.85 | I71: 陈乐贵 | K71: =IF($B71="","",--TEXT($B71,"yyyymm")) -> 202607
A72: =IF(B72="","",COUNTA($B$5:B72)) -> 68 | B72: 46231 | C72: 吴建忠浦发 | D72: 明道利息 | E72: 徐远转入明道利息款（后息） | G72: 10000 | H72: =IFERROR(VLOOKUP($C72,$C$5:$H$18,6,0)+SUMIF($C$19:$C72,$C72,$F$19:$F72)-SUMIF($C$19:$C72,$C72,$G$19:$G72),"") -> 386066.85 | I72: 明道对公 | K72: =IF($B72="","",--TEXT($B72,"yyyymm")) -> 202607
A73: =IF(B73="","",COUNTA($B$5:B73)) -> 69 | B73: 46231 | C73: 吴建忠浦发 | D73: 手续费-收 | E73: 吴丹辉提放费1750元 | F73: 1750 | H73: =IFERROR(VLOOKUP($C73,$C$5:$H$18,6,0)+SUMIF($C$19:$C73,$C73,$F$19:$F73)-SUMIF($C$19:$C73,$C73,$G$19:$G73),"") -> 387816.85 | I73: 吴丹辉 | K73: =IF($B73="","",--TEXT($B73,"yyyymm")) -> 202607
A74: =IF(B74="","",COUNTA($B$5:B74)) -> 70 | B74: 46231 | C74: 吴建忠浦发 | D74: 借款利息 | E74: 吴丹辉30万利息费用4500 | F74: 4500 | H74: =IFERROR(VLOOKUP($C74,$C$5:$H$18,6,0)+SUMIF($C$19:$C74,$C74,$F$19:$F74)-SUMIF($C$19:$C74,$C74,$G$19:$G74),"") -> 392316.85 | I74: 吴丹辉 | K74: =IF($B74="","",--TEXT($B74,"yyyymm")) -> 202607
A75: =IF(B75="","",COUNTA($B$5:B75)) -> 71 | B75: 46231 | C75: 吴建忠浦发 | D75: 借款利息 | E75: 唐嘉转入-徐远1分利润转回 | F75: 4000 | H75: =IFERROR(VLOOKUP($C75,$C$5:$H$18,6,0)+SUMIF($C$19:$C75,$C75,$F$19:$F75)-SUMIF($C$19:$C75,$C75,$G$19:$G75),"") -> 396316.85 | I75: 徐远 | K75: =IF($B75="","",--TEXT($B75,"yyyymm")) -> 202607
A76: =IF(B76="","",COUNTA($B$5:B76)) -> 72 | B76: 46234 | C76: 吴建忠浦发 | D76: 调拔款 | E76: 吴建忠浦发转林总浦发 | G76: 16000 | H76: =IFERROR(VLOOKUP($C76,$C$5:$H$18,6,0)+SUMIF($C$19:$C76,$C76,$F$19:$F76)-SUMIF($C$19:$C76,$C76,$G$19:$G76),"") -> 380316.85 | I76: 林总浦发 | K76: =IF($B76="","",--TEXT($B76,"yyyymm")) -> 202607
A77: =IF(B77="","",COUNTA($B$5:B77)) -> 73 | B77: 46234 | C77: 吴建忠浦发 | D77: 调拔款 | E77: 吴建忠浦发转林总浦发 | G77: 50000 | H77: =IFERROR(VLOOKUP($C77,$C$5:$H$18,6,0)+SUMIF($C$19:$C77,$C77,$F$19:$F77)-SUMIF($C$19:$C77,$C77,$G$19:$G77),"") -> 330316.85 | I77: 林总浦发 | K77: =IF($B77="","",--TEXT($B77,"yyyymm")) -> 202607
A78: =IF(B78="","",COUNTA($B$5:B78)) -> 74 | B78: 46204 | C78: 典当微信 | D78: 借款利息 | E78: 姜玉枝利息 | F78: 2250 | H78: =IFERROR(VLOOKUP($C78,$C$5:$H$18,6,0)+SUMIF($C$19:$C78,$C78,$F$19:$F78)-SUMIF($C$19:$C78,$C78,$G$19:$G78),"") -> 114576.39 | I78: 姜玉枝 | K78: =IF($B78="","",--TEXT($B78,"yyyymm")) -> 202607
A79: =IF(B79="","",COUNTA($B$5:B79)) -> 75 | B79: 46204 | C79: 典当微信 | D79: 渠道费用 | E79: 转唐嘉抽成款-叶敏 | G79: 2080 | H79: =IFERROR(VLOOKUP($C79,$C$5:$H$18,6,0)+SUMIF($C$19:$C79,$C79,$F$19:$F79)-SUMIF($C$19:$C79,$C79,$G$19:$G79),"") -> 112496.39 | K79: =IF($B79="","",--TEXT($B79,"yyyymm")) -> 202607
A80: =IF(B80="","",COUNTA($B$5:B80)) -> 76 | B80: 46204 | C80: 典当微信 | D80: 办公费用 | E80: 转梦麟报销款 | G80: 136 | H80: =IFERROR(VLOOKUP($C80,$C$5:$H$18,6,0)+SUMIF($C$19:$C80,$C80,$F$19:$F80)-SUMIF($C$19:$C80,$C80,$G$19:$G80),"") -> 112360.39 | K80: =IF($B80="","",--TEXT($B80,"yyyymm")) -> 202607
A81: =IF(B81="","",COUNTA($B$5:B81)) -> 77 | B81: 46204 | C81: 典当微信 | D81: 办公费用 | E81: 转陈琴报销款-日用品 | G81: 264 | H81: =IFERROR(VLOOKUP($C81,$C$5:$H$18,6,0)+SUMIF($C$19:$C81,$C81,$F$19:$F81)-SUMIF($C$19:$C81,$C81,$G$19:$G81),"") -> 112096.39 | K81: =IF($B81="","",--TEXT($B81,"yyyymm")) -> 202607
A82: =IF(B82="","",COUNTA($B$5:B82)) -> 78 | B82: 46204 | C82: 典当微信 | D82: 调拔款 | E82: 转吴姐提现到建行 | G82: 50000 | H82: =IFERROR(VLOOKUP($C82,$C$5:$H$18,6,0)+SUMIF($C$19:$C82,$C82,$F$19:$F82)-SUMIF($C$19:$C82,$C82,$G$19:$G82),"") -> 62096.39 | I82: 吴姐建行 | K82: =IF($B82="","",--TEXT($B82,"yyyymm")) -> 202607
A83: =IF(B83="","",COUNTA($B$5:B83)) -> 79 | B83: 46204 | C83: 典当微信 | D83: 借款利息 | E83: 林芬利息 | F83: 230 | H83: =IFERROR(VLOOKUP($C83,$C$5:$H$18,6,0)+SUMIF($C$19:$C83,$C83,$F$19:$F83)-SUMIF($C$19:$C83,$C83,$G$19:$G83),"") -> 62326.39 | I83: 林芬 | K83: =IF($B83="","",--TEXT($B83,"yyyymm")) -> 202607
A84: =IF(B84="","",COUNTA($B$5:B84)) -> 80 | B84: 46206 | C84: 典当微信 | D84: 借款本金 | E84: 叶金出款 | G84: 5000 | H84: =IFERROR(VLOOKUP($C84,$C$5:$H$18,6,0)+SUMIF($C$19:$C84,$C84,$F$19:$F84)-SUMIF($C$19:$C84,$C84,$G$19:$G84),"") -> 57326.39 | I84: 叶金 | K84: =IF($B84="","",--TEXT($B84,"yyyymm")) -> 202607
A85: =IF(B85="","",COUNTA($B$5:B85)) -> 81 | B85: 46206 | C85: 典当微信 | D85: 借款利息 | E85: 叶金5000利息 | F85: 200 | H85: =IFERROR(VLOOKUP($C85,$C$5:$H$18,6,0)+SUMIF($C$19:$C85,$C85,$F$19:$F85)-SUMIF($C$19:$C85,$C85,$G$19:$G85),"") -> 57526.39 | I85: 叶金 | K85: =IF($B85="","",--TEXT($B85,"yyyymm")) -> 202607
A86: =IF(B86="","",COUNTA($B$5:B86)) -> 82 | B86: 46206 | C86: 典当微信 | D86: 借款本金 | E86: 张文海出款 | G86: 8000 | H86: =IFERROR(VLOOKUP($C86,$C$5:$H$18,6,0)+SUMIF($C$19:$C86,$C86,$F$19:$F86)-SUMIF($C$19:$C86,$C86,$G$19:$G86),"") -> 49526.39 | I86: 张文海 | K86: =IF($B86="","",--TEXT($B86,"yyyymm")) -> 202607
A87: =IF(B87="","",COUNTA($B$5:B87)) -> 83 | B87: 46206 | C87: 典当微信 | D87: 借款利息 | E87: 张文海8000利息 | F87: 200 | H87: =IFERROR(VLOOKUP($C87,$C$5:$H$18,6,0)+SUMIF($C$19:$C87,$C87,$F$19:$F87)-SUMIF($C$19:$C87,$C87,$G$19:$G87),"") -> 49726.39 | I87: 张文海 | K87: =IF($B87="","",--TEXT($B87,"yyyymm")) -> 202607
A88: =IF(B88="","",COUNTA($B$5:B88)) -> 84 | B88: 46207 | C88: 典当微信 | D88: 借款利息 | E88: 陆林广利息 | F88: 2250 | H88: =IFERROR(VLOOKUP($C88,$C$5:$H$18,6,0)+SUMIF($C$19:$C88,$C88,$F$19:$F88)-SUMIF($C$19:$C88,$C88,$G$19:$G88),"") -> 51976.39 | I88: 陆林广 | K88: =IF($B88="","",--TEXT($B88,"yyyymm")) -> 202607
A89: =IF(B89="","",COUNTA($B$5:B89)) -> 85 | B89: 46208 | C89: 典当微信 | D89: 借款利息 | E89: 陈东4万利息 | F89: 1000 | H89: =IFERROR(VLOOKUP($C89,$C$5:$H$18,6,0)+SUMIF($C$19:$C89,$C89,$F$19:$F89)-SUMIF($C$19:$C89,$C89,$G$19:$G89),"") -> 52976.39 | I89: 陈东 | K89: =IF($B89="","",--TEXT($B89,"yyyymm")) -> 202607
A90: =IF(B90="","",COUNTA($B$5:B90)) -> 86 | B90: 46208 | C90: 典当微信 | D90: 借款利息 | E90: 郑庆民1000利息（7月） | F90: 50 | H90: =IFERROR(VLOOKUP($C90,$C$5:$H$18,6,0)+SUMIF($C$19:$C90,$C90,$F$19:$F90)-SUMIF($C$19:$C90,$C90,$G$19:$G90),"") -> 53026.39 | I90: 郑庆民 | K90: =IF($B90="","",--TEXT($B90,"yyyymm")) -> 202607
A91: =IF(B91="","",COUNTA($B$5:B91)) -> 87 | B91: 46208 | C91: 典当微信 | D91: 借款利息 | E91: 郑庆民8000利息（7月） | F91: 240 | H91: =IFERROR(VLOOKUP($C91,$C$5:$H$18,6,0)+SUMIF($C$19:$C91,$C91,$F$19:$F91)-SUMIF($C$19:$C91,$C91,$G$19:$G91),"") -> 53266.39 | I91: 郑庆民 | K91: =IF($B91="","",--TEXT($B91,"yyyymm")) -> 202607
A92: =IF(B92="","",COUNTA($B$5:B92)) -> 88 | B92: 46209 | C92: 典当微信 | D92: 借款本金 | E92: 陈东出款 | G92: 3600 | H92: =IFERROR(VLOOKUP($C92,$C$5:$H$18,6,0)+SUMIF($C$19:$C92,$C92,$F$19:$F92)-SUMIF($C$19:$C92,$C92,$G$19:$G92),"") -> 49666.39 | I92: 陈东 | K92: =IF($B92="","",--TEXT($B92,"yyyymm")) -> 202607
A93: =IF(B93="","",COUNTA($B$5:B93)) -> 89 | B93: 46209 | C93: 典当微信 | D93: 借款利息 | E93: 陈东3600利息 | F93: 200 | H93: =IFERROR(VLOOKUP($C93,$C$5:$H$18,6,0)+SUMIF($C$19:$C93,$C93,$F$19:$F93)-SUMIF($C$19:$C93,$C93,$G$19:$G93),"") -> 49866.39 | I93: 陈东 | K93: =IF($B93="","",--TEXT($B93,"yyyymm")) -> 202607
A94: =IF(B94="","",COUNTA($B$5:B94)) -> 90 | B94: 46209 | C94: 典当微信 | D94: 借款利息 | E94: 曾光雄3000利息 | F94: 100 | H94: =IFERROR(VLOOKUP($C94,$C$5:$H$18,6,0)+SUMIF($C$19:$C94,$C94,$F$19:$F94)-SUMIF($C$19:$C94,$C94,$G$19:$G94),"") -> 49966.39 | I94: 曾光雄 | K94: =IF($B94="","",--TEXT($B94,"yyyymm")) -> 202607
A95: =IF(B95="","",COUNTA($B$5:B95)) -> 91 | B95: 46210 | C95: 典当微信 | D95: 借款利息 | E95: 常虹利息 | F95: 100 | H95: =IFERROR(VLOOKUP($C95,$C$5:$H$18,6,0)+SUMIF($C$19:$C95,$C95,$F$19:$F95)-SUMIF($C$19:$C95,$C95,$G$19:$G95),"") -> 50066.39 | I95: 常虹 | K95: =IF($B95="","",--TEXT($B95,"yyyymm")) -> 202607
A96: =IF(B96="","",COUNTA($B$5:B96)) -> 92 | B96: 46210 | C96: 典当微信 | D96: 抵押物回收款 | E96: 转张贺勤-黄金回收 | G96: 593 | H96: =IFERROR(VLOOKUP($C96,$C$5:$H$18,6,0)+SUMIF($C$19:$C96,$C96,$F$19:$F96)-SUMIF($C$19:$C96,$C96,$G$19:$G96),"") -> 49473.39 | I96: 张贺勤 | K96: =IF($B96="","",--TEXT($B96,"yyyymm")) -> 202607
A97: =IF(B97="","",COUNTA($B$5:B97)) -> 93 | B97: 46210 | C97: 典当微信 | D97: 水电费 | E97: 门店电费 | G97: 1500 | H97: =IFERROR(VLOOKUP($C97,$C$5:$H$18,6,0)+SUMIF($C$19:$C97,$C97,$F$19:$F97)-SUMIF($C$19:$C97,$C97,$G$19:$G97),"") -> 47973.39 | K97: =IF($B97="","",--TEXT($B97,"yyyymm")) -> 202607
A98: =IF(B98="","",COUNTA($B$5:B98)) -> 94 | B98: 46210 | C98: 典当微信 | D98: 水电费 | E98: 门店水费 | G98: 50 | H98: =IFERROR(VLOOKUP($C98,$C$5:$H$18,6,0)+SUMIF($C$19:$C98,$C98,$F$19:$F98)-SUMIF($C$19:$C98,$C98,$G$19:$G98),"") -> 47923.39 | K98: =IF($B98="","",--TEXT($B98,"yyyymm")) -> 202607
A99: =IF(B99="","",COUNTA($B$5:B99)) -> 95 | B99: 46210 | C99: 典当微信 | D99: 手续费-收 | E99: 蒙媛媛押车杂费 | F99: 500 | H99: =IFERROR(VLOOKUP($C99,$C$5:$H$18,6,0)+SUMIF($C$19:$C99,$C99,$F$19:$F99)-SUMIF($C$19:$C99,$C99,$G$19:$G99),"") -> 48423.39 | K99: =IF($B99="","",--TEXT($B99,"yyyymm")) -> 202607
A100: =IF(B100="","",COUNTA($B$5:B100)) -> 96 | B100: 46210 | C100: 典当微信 | D100: 借款利息 | E100: 张建云利息 | F100: 250 | H100: =IFERROR(VLOOKUP($C100,$C$5:$H$18,6,0)+SUMIF($C$19:$C100,$C100,$F$19:$F100)-SUMIF($C$19:$C100,$C100,$G$19:$G100),"") -> 48673.39 | I100: 张建云 | K100: =IF($B100="","",--TEXT($B100,"yyyymm")) -> 202607
A101: =IF(B101="","",COUNTA($B$5:B101)) -> 97 | B101: 46211 | C101: 典当微信 | D101: 借款利息 | E101: 柯重文利息 | F101: 200 | H101: =IFERROR(VLOOKUP($C101,$C$5:$H$18,6,0)+SUMIF($C$19:$C101,$C101,$F$19:$F101)-SUMIF($C$19:$C101,$C101,$G$19:$G101),"") -> 48873.39 | I101: 柯重文 | K101: =IF($B101="","",--TEXT($B101,"yyyymm")) -> 202607
...

Sheet 汇报表
A1: 资金日报统计表（任意连续日期 / 单独一天查询）
A2: 起始日期 | B2: 46204 | D2: 截止日期 | E2: 46233 | G2: 查询天数 | H2: =IF(OR($B$2="",$E$2=""),"",IF($E$2<$B$2,"日期错误",IF($E$2-$B$2+1>31,"超过31天",$E$2-$B$2+1))) -> 30
A3: 提示：修改黄色日期即可查询；单独一天时起始日期=截止日期；默认展开31天，超过31天建议按月分段查询。
A4: 公司期初余额 | C4: 期间收款合计 | E4: 期间付款合计 | G4: 期末结余金额
B5: =SUM(B8:B21) -> 719880.9 | D5: =SUM(BM8:BM21) -> 13739232 | F5: =SUM(BN8:BN21) -> 13815171 | H5: =SUM(BO8:BO21) -> 643942.29
C6: =IF(1<=MIN($H$2,31),$B$2+0,"") -> 46204 | D6: =IF(1<=MIN($H$2,31),$B$2+0,"") -> 46204 | E6: =IF(2<=MIN($H$2,31),$B$2+1,"") -> 46205 | F6: =IF(2<=MIN($H$2,31),$B$2+1,"") -> 46205 | G6: =IF(3<=MIN($H$2,31),$B$2+2,"") -> 46206 | H6: =IF(3<=MIN($H$2,31),$B$2+2,"") -> 46206 | I6: =IF(4<=MIN($H$2,31),$B$2+3,"") -> 46207 | J6: =IF(4<=MIN($H$2,31),$B$2+3,"") -> 46207 | K6: =IF(5<=MIN($H$2,31),$B$2+4,"") -> 46208 | L6: =IF(5<=MIN($H$2,31),$B$2+4,"") -> 46208 | M6: =IF(6<=MIN($H$2,31),$B$2+5,"") -> 46209 | N6: =IF(6<=MIN($H$2,31),$B$2+5,"") -> 46209 | O6: =IF(7<=MIN($H$2,31),$B$2+6,"") -> 46210 | P6: =IF(7<=MIN($H$2,31),$B$2+6,"") -> 46210 | Q6: =IF(8<=MIN($H$2,31),$B$2+7,"") -> 46211 | R6: =IF(8<=MIN($H$2,31),$B$2+7,"") -> 46211 | S6: =IF(9<=MIN($H$2,31),$B$2+8,"") -> 46212 | T6: =IF(9<=MIN($H$2,31),$B$2+8,"") -> 46212 | U6: =IF(10<=MIN($H$2,31),$B$2+9,"") -> 46213 | V6: =IF(10<=MIN($H$2,31),$B$2+9,"") -> 46213 | W6: =IF(11<=MIN($H$2,31),$B$2+10,"") -> 46214 | X6: =IF(11<=MIN($H$2,31),$B$2+10,"") -> 46214 | Y6: =IF(12<=MIN($H$2,31),$B$2+11,"") -> 46215 | Z6: =IF(12<=MIN($H$2,31),$B$2+11,"") -> 46215 | AA6: =IF(13<=MIN($H$2,31),$B$2+12,"") -> 46216 | AB6: =IF(13<=MIN($H$2,31),$B$2+12,"") -> 46216 | AC6: =IF(14<=MIN($H$2,31),$B$2+13,"") -> 46217 | AD6: =IF(14<=MIN($H$2,31),$B$2+13,"") -> 46217 | AE6: =IF(15<=MIN($H$2,31),$B$2+14,"") -> 46218 | AF6: =IF(15<=MIN($H$2,31),$B$2+14,"") -> 46218 | AG6: =IF(16<=MIN($H$2,31),$B$2+15,"") -> 46219 | AH6: =IF(16<=MIN($H$2,31),$B$2+15,"") -> 46219 | AI6: =IF(17<=MIN($H$2,31),$B$2+16,"") -> 46220 | AJ6: =IF(17<=MIN($H$2,31),$B$2+16,"") -> 46220 | AK6: =IF(18<=MIN($H$2,31),$B$2+17,"") -> 46221 | AL6: =IF(18<=MIN($H$2,31),$B$2+17,"") -> 46221 | AM6: =IF(19<=MIN($H$2,31),$B$2+18,"") -> 46222 | AN6: =IF(19<=MIN($H$2,31),$B$2+18,"") -> 46222 | AO6: =IF(20<=MIN($H$2,31),$B$2+19,"") -> 46223 | AP6: =IF(20<=MIN($H$2,31),$B$2+19,"") -> 46223 | AQ6: =IF(21<=MIN($H$2,31),$B$2+20,"") -> 46224 | AR6: =IF(21<=MIN($H$2,31),$B$2+20,"") -> 46224 | AS6: =IF(22<=MIN($H$2,31),$B$2+21,"") -> 46225 | AT6: =IF(22<=MIN($H$2,31),$B$2+21,"") -> 46225 | AU6: =IF(23<=MIN($H$2,31),$B$2+22,"") -> 46226 | AV6: =IF(23<=MIN($H$2,31),$B$2+22,"") -> 46226 | AW6: =IF(24<=MIN($H$2,31),$B$2+23,"") -> 46227 | AX6: =IF(24<=MIN($H$2,31),$B$2+23,"") -> 46227 | AY6: =IF(25<=MIN($H$2,31),$B$2+24,"") -> 46228 | AZ6: =IF(25<=MIN($H$2,31),$B$2+24,"") -> 46228 | BA6: =IF(26<=MIN($H$2,31),$B$2+25,"") -> 46229 | BB6: =IF(26<=MIN($H$2,31),$B$2+25,"") -> 46229 | BC6: =IF(27<=MIN($H$2,31),$B$2+26,"") -> 46230 | BD6: =IF(27<=MIN($H$2,31),$B$2+26,"") -> 46230 | BE6: =IF(28<=MIN($H$2,31),$B$2+27,"") -> 46231 | BF6: =IF(28<=MIN($H$2,31),$B$2+27,"") -> 46231 | BG6: =IF(29<=MIN($H$2,31),$B$2+28,"") -> 46232 | BH6: =IF(29<=MIN($H$2,31),$B$2+28,"") -> 46232 | BI6: =IF(30<=MIN($H$2,31),$B$2+29,"") -> 46233 | BJ6: =IF(30<=MIN($H$2,31),$B$2+29,"") -> 46233 | BK6: =IF(31<=MIN($H$2,31),$B$2+30,"") | BL6: =IF(31<=MIN($H$2,31),$B$2+30,"")
A7: 账户 | B7: 期初余额 | C7: =IF(C$6="","","收款") -> 收款 | D7: =IF(D$6="","","付款") -> 付款 | E7: =IF(E$6="","","收款") -> 收款 | F7: =IF(F$6="","","付款") -> 付款 | G7: =IF(G$6="","","收款") -> 收款 | H7: =IF(H$6="","","付款") -> 付款 | I7: =IF(I$6="","","收款") -> 收款 | J7: =IF(J$6="","","付款") -> 付款 | K7: =IF(K$6="","","收款") -> 收款 | L7: =IF(L$6="","","付款") -> 付款 | M7: =IF(M$6="","","收款") -> 收款 | N7: =IF(N$6="","","付款") -> 付款 | O7: =IF(O$6="","","收款") -> 收款 | P7: =IF(P$6="","","付款") -> 付款 | Q7: =IF(Q$6="","","收款") -> 收款 | R7: =IF(R$6="","","付款") -> 付款 | S7: =IF(S$6="","","收款") -> 收款 | T7: =IF(T$6="","","付款") -> 付款 | U7: =IF(U$6="","","收款") -> 收款 | V7: =IF(V$6="","","付款") -> 付款 | W7: =IF(W$6="","","收款") -> 收款 | X7: =IF(X$6="","","付款") -> 付款 | Y7: =IF(Y$6="","","收款") -> 收款 | Z7: =IF(Z$6="","","付款") -> 付款 | AA7: =IF(AA$6="","","收款") -> 收款 | AB7: =IF(AB$6="","","付款") -> 付款 | AC7: =IF(AC$6="","","收款") -> 收款 | AD7: =IF(AD$6="","","付款") -> 付款 | AE7: =IF(AE$6="","","收款") -> 收款 | AF7: =IF(AF$6="","","付款") -> 付款 | AG7: =IF(AG$6="","","收款") -> 收款 | AH7: =IF(AH$6="","","付款") -> 付款 | AI7: =IF(AI$6="","","收款") -> 收款 | AJ7: =IF(AJ$6="","","付款") -> 付款 | AK7: =IF(AK$6="","","收款") -> 收款 | AL7: =IF(AL$6="","","付款") -> 付款 | AM7: =IF(AM$6="","","收款") -> 收款 | AN7: =IF(AN$6="","","付款") -> 付款 | AO7: =IF(AO$6="","","收款") -> 收款 | AP7: =IF(AP$6="","","付款") -> 付款 | AQ7: =IF(AQ$6="","","收款") -> 收款 | AR7: =IF(AR$6="","","付款") -> 付款 | AS7: =IF(AS$6="","","收款") -> 收款 | AT7: =IF(AT$6="","","付款") -> 付款 | AU7: =IF(AU$6="","","收款") -> 收款 | AV7: =IF(AV$6="","","付款") -> 付款 | AW7: =IF(AW$6="","","收款") -> 收款 | AX7: =IF(AX$6="","","付款") -> 付款 | AY7: =IF(AY$6="","","收款") -> 收款 | AZ7: =IF(AZ$6="","","付款") -> 付款 | BA7: =IF(BA$6="","","收款") -> 收款 | BB7: =IF(BB$6="","","付款") -> 付款 | BC7: =IF(BC$6="","","收款") -> 收款 | BD7: =IF(BD$6="","","付款") -> 付款 | BE7: =IF(BE$6="","","收款") -> 收款 | BF7: =IF(BF$6="","","付款") -> 付款 | BG7: =IF(BG$6="","","收款") -> 收款 | BH7: =IF(BH$6="","","付款") -> 付款 | BI7: =IF(BI$6="","","收款") -> 收款 | BJ7: =IF(BJ$6="","","付款") -> 付款 | BK7: =IF(BK$6="","","收款") | BL7: =IF(BL$6="","","付款") | BM7: 收款合计 | BN7: 付款合计 | BO7: 期末余额
A8: 金辉稠州 | B8: =IF(OR($A8="",NOT(ISNUMBER($H$2))),"",SUMIFS(数据录入!$H$5:$H$785,数据录入!$C$5:$C$785,$A8,数据录入!$E$5:$E$785,"期初余额",数据录入!$B$5:$B$785,"<="&$B$2)+SUMIFS(数据录入!$F$5:$F$785,数据录入!$C$5:$C$785,$A8,数据录入!$B$5:$B$785,"<"&$B$2)-SUMIFS(数据录入!$G$5:$G$785,数据录入!$C$5:$C$785,$A8,数据录入!$B$5:$B$785,"<"&$B$2)) -> 219263.12 | C8: =IF(OR($A8="",C$6="",NOT(ISNUMBER($H$2))),"",SUMIFS(数据录入!$F$5:$F$785,数据录入!$C$5:$C$785,$A8,数据录入!$B$5:$B$785,C$6)) -> 0 | D8: =IF(OR($A8="",D$6="",NOT(ISNUMBER($H$2))),"",SUMIFS(数据录入!$G$5:$G$785,数据录入!$C$5:$C$785,$A8,数据录入!$B$5:$B$785,D$6)) -> 596 | E8: =IF(OR($A8="",E$6="",NOT(ISNUMBER($H$2))),"",SUMIFS(数据录入!$F$5:$F$785,数据录入!$C$5:$C$785,$A8,数据录入!$B$5:$B$785,E$6)) -> 0 | F8: =IF(OR($A8="",F$6="",NOT(ISNUMBER($H$2))),"",SUMIFS(数据录入!$G$5:$G$785,数据录入!$C$5:$C$785,$A8,数据录入!$B$5:$B$785,F$6)) -> 0 | G8: =IF(OR($A8="",G$6="",NOT(ISNUMBER($H$2))),"",SUMIFS(数据录入!$F$5:$F$785,数据录入!$C$5:$C$785,$A8,数据录入!$B$5:$B$785,G$6)) -> 0 | H8: =IF(OR($A8="",H$6="",NOT(ISNUMBER($H$2))),"",SUMIFS(数据录入!$G$5:$G$785,数据录入!$C$5:$C$785,$A8,数据录入!$B$5:$B$785,H$6)) -> 5500 | I8: =IF(OR($A8="",I$6="",NOT(ISNUMBER($H$2))),"",SUMIFS(数据录入!$F$5:$F$785,数据录入!$C$5:$C$785,$A8,数据录入!$B$5:$B$785,I$6)) -> 0 | J8: =IF(OR($A8="",J$6="",NOT(ISNUMBER($H$2))),"",SUMIFS(数据录入!$G$5:$G$785,数据录入!$C$5:$C$785,$A8,数据录入!$B$5:$B$785,J$6)) -> 0 | K8: =IF(OR($A8="",K$6="",NOT(ISNUMBER($H$2))),"",SUMIFS(数据录入!$F$5:$F$785,数据录入!$C$5:$C$785,$A8,数据录入!$B$5:$B$785,K$6)) -> 0 | L8: =IF(OR($A8="",L$6="",NOT(ISNUMBER($H$2))),"",SUMIFS(数据录入!$G$5:$G$785,数据录入!$C$5:$C$785,$A8,数据录入!$B$5:$B$785,L$6)) -> 0 | M8: =IF(OR($A8="",M$6="",NOT(ISNUMBER($H$2))),"",SUMIFS(数据录入!$F$5:$F$785,数据录入!$C$5:$C$785,$A8,数据录入!$B$5:$B$785,M$6)) -> 2000 | N8: =IF(OR($A8="",N$6="",NOT(ISNUMBER($H$2))),"",SUMIFS(数据录入!$G$5:$G$785,数据录入!$C$5:$C$785,$A8,数据录入!$B$5:$B$785,N$6)) -> 0 | O8: =IF(OR($A8="",O$6="",NOT(ISNUMBER($H$2))),"",SUMIFS(数据录入!$F$5:$F$785,数据录入!$C$5:$C$785,$A8,数据录入!$B$5:$B$785,O$6)) -> 1000 | P8: =IF(OR($A8="",P$6="",NOT(ISNUMBER($H$2))),"",SUMIFS(数据录入!$G$5:$G$785,数据录入!$C$5:$C$785,$A8,数据录入!$B$5:$B$785,P$6)) -> 50000 | Q8: =IF(OR($A8="",Q$6="",NOT(ISNUMBER($H$2))),"",SUMIFS(数据录入!$F$5:$F$785,数据录入!$C$5:$C$785,$A8,数据录入!$B$5:$B$785,Q$6)) -> 9000 | R8: =IF(OR($A8="",R$6="",NOT(ISNUMBER($H$2))),"",SUMIFS(数据录入!$G$5:$G$785,数据录入!$C$5:$C$785,$A8,数据录入!$B$5:$B$785,R$6)) -> 0 | S8: =IF(OR($A8="",S$6="",NOT(ISNUMBER($H$2))),"",SUMIFS(数据录入!$F$5:$F$785,数据录入!$C$5:$C$785,$A8,数据录入!$B$5:$B$785,S$6)) -> 0 | T8: =IF(OR($A8="",T$6="",NOT(ISNUMBER($H$2))),"",SUMIFS(数据录入!$G$5:$G$785,数据录入!$C$5:$C$785,$A8,数据录入!$B$5:$B$785,T$6)) -> 150000 | U8: =IF(OR($A8="",U$6="",NOT(ISNUMBER($H$2))),"",SUMIFS(数据录入!$F$5:$F$785,数据录入!$C$5:$C$785,$A8,数据录入!$B$5:$B$785,U$6)) -> 90 | V8: =IF(OR($A8="",V$6="",NOT(ISNUMBER($H$2))),"",SUMIFS(数据录入!$G$5:$G$785,数据录入!$C$5:$C$785,$A8,数据录入!$B$5:$B$785,V$6)) -> 17.5 | W8: =IF(OR($A8="",W$6="",NOT(ISNUMBER($H$2))),"",SUMIFS(数据录入!$F$5:$F$785,数据录入!$C$5:$C$785,$A8,数据录入!$B$5:$B$785,W$6)) -> 0 | X8: =IF(OR($A8="",X$6="",NOT(ISNUMBER($H$2))),"",SUMIFS(数据录入!$G$5:$G$785,数据录入!$C$5:$C$785,$A8,数据录入!$B$5:$B$785,X$6)) -> 0 | Y8: =IF(OR($A8="",Y$6="",NOT(ISNUMBER($H$2))),"",SUMIFS(数据录入!$F$5:$F$785,数据录入!$C$5:$C$785,$A8,数据录入!$B$5:$B$785,Y$6)) -> 0 | Z8: =IF(OR($A8="",Z$6="",NOT(ISNUMBER($H$2))),"",SUMIFS(数据录入!$G$5:$G$785,数据录入!$C$5:$C$785,$A8,数据录入!$B$5:$B$785,Z$6)) -> 0 | AA8: =IF(OR($A8="",AA$6="",NOT(ISNUMBER($H$2))),"",SUMIFS(数据录入!$F$5:$F$785,数据录入!$C$5:$C$785,$A8,数据录入!$B$5:$B$785,AA$6)) -> 12500 | AB8: =IF(OR($A8="",AB$6="",NOT(ISNUMBER($H$2))),"",SUMIFS(数据录入!$G$5:$G$785,数据录入!$C$5:$C$785,$A8,数据录入!$B$5:$B$785,AB$6)) -> 0 | AC8: =IF(OR($A8="",AC$6="",NOT(ISNUMBER($H$2))),"",SUMIFS(数据录入!$F$5:$F$785,数据录入!$C$5:$C$785,$A8,数据录入!$B$5:$B$785,AC$6)) -> 5200 | AD8: =IF(OR($A8="",AD$6="",NOT(ISNUMBER($H$2))),"",SUMIFS(数据录入!$G$5:$G$785,数据录入!$C$5:$C$785,$A8,数据录入!$B$5:$B$785,AD$6)) -> 0 | AE8: =IF(OR($A8="",AE$6="",NOT(ISNUMBER($H$2))),"",SUMIFS(数据录入!$F$5:$F$785,数据录入!$C$5:$C$785,$A8,数据录入!$B$5:$B$785,AE$6)) -> 9380 | AF8: =IF(OR($A8="",AF$6="",NOT(ISNUMBER($H$2))),"",SUMIFS(数据录入!$G$5:$G$785,数据录入!$C$5:$C$785,$A8,数据录入!$B$5:$B$785,AF$6)) -> 29687.36 | AG8: =IF(OR($A8="",AG$6="",NOT(ISNUMBER($H$2))),"",SUMIFS(数据录入!$F$5:$F$785,数据录入!$C$5:$C$785,$A8,数据录入!$B$5:$B$785,AG$6)) -> 380000 | AH8: =IF(OR($A8="",AH$6="",NOT(ISNUMBER($H$2))),"",SUMIFS(数据录入!$G$5:$G$785,数据录入!$C$5:$C$785,$A8,数据录入!$B$5:$B$785,AH$6)) -> 400000 | AI8: =IF(OR($A8="",AI$6="",NOT(ISNUMBER($H$2))),"",SUMIFS(数据录入!$F$5:$F$785,数据录入!$C$5:$C$785,$A8,数据录入!$B$5:$B$785,AI$6)) -> 0 | AJ8: =IF(OR($A8="",AJ$6="",NOT(ISNUMBER($H$2))),"",SUMIFS(数据录入!$G$5:$G$785,数据录入!$C$5:$C$785,$A8,数据录入!$B$5:$B$785,AJ$6)) -> 0 | AK8: =IF(OR($A8="",AK$6="",NOT(ISNUMBER($H$2))),"",SUMIFS(数据录入!$F$5:$F$785,数据录入!$C$5:$C$785,$A8,数据录入!$B$5:$B$785,AK$6)) -> 0 | AL8: =IF(OR($A8="",AL$6="",NOT(ISNUMBER($H$2))),"",SUMIFS(数据录入!$G$5:$G$785,数据录入!$C$5:$C$785,$A8,数据录入!$B$5:$B$785,AL$6)) -> 0 | AM8: =IF(OR($A8="",AM$6="",NOT(ISNUMBER($H$2))),"",SUMIFS(数据录入!$F$5:$F$785,数据录入!$C$5:$C$785,$A8,数据录入!$B$5:$B$785,AM$6)) -> 0 | AN8: =IF(OR($A8="",AN$6="",NOT(ISNUMBER($H$2))),"",SUMIFS(数据录入!$G$5:$G$785,数据录入!$C$5:$C$785,$A8,数据录入!$B$5:$B$785,AN$6)) -> 0 | AO8: =IF(OR($A8="",AO$6="",NOT(ISNUMBER($H$2))),"",SUMIFS(数据录入!$F$5:$F$785,数据录入!$C$5:$C$785,$A8,数据录入!$B$5:$B$785,AO$6)) -> 230000 | AP8: =IF(OR($A8="",AP$6="",NOT(ISNUMBER($H$2))),"",SUMIFS(数据录入!$G$5:$G$785,数据录入!$C$5:$C$785,$A8,数据录入!$B$5:$B$785,AP$6)) -> 225000 | AQ8: =IF(OR($A8="",AQ$6="",NOT(ISNUMBER($H$2))),"",SUMIFS(数据录入!$F$5:$F$785,数据录入!$C$5:$C$785,$A8,数据录入!$B$5:$B$785,AQ$6)) -> 1000 | AR8: =IF(OR($A8="",AR$6="",NOT(ISNUMBER($H$2))),"",SUMIFS(数据录入!$G$5:$G$785,数据录入!$C$5:$C$785,$A8,数据录入!$B$5:$B$785,AR$6)) -> 6038.16 | AS8: =IF(OR($A8="",AS$6="",NOT(ISNUMBER($H$2))),"",SUMIFS(数据录入!$F$5:$F$785,数据录入!$C$5:$C$785,$A8,数据录入!$B$5:$B$785,AS$6)) -> 0 | AT8: =IF(OR($A8="",AT$6="",NOT(ISNUMBER($H$2))),"",SUMIFS(数据录入!$G$5:$G$785,数据录入!$C$5:$C$785,$A8,数据录入!$B$5:$B$785,AT$6)) -> 0 | AU8: =IF(OR($A8="",AU$6="",NOT(ISNUMBER($H$2))),"",SUMIFS(数据录入!$F$5:$F$785,数据录入!$C$5:$C$785,$A8,数据录入!$B$5:$B$785,AU$6)) -> 153125 | AV8: =IF(OR($A8="",AV$6="",NOT(ISNUMBER($H$2))),"",SUMIFS(数据录入!$G$5:$G$785,数据录入!$C$5:$C$785,$A8,数据录入!$B$5:$B$785,AV$6)) -> 17000 | AW8: =IF(OR($A8="",AW$6="",NOT(ISNUMBER($H$2))),"",SUMIFS(数据录入!$F$5:$F$785,数据录入!$C$5:$C$785,$A8,数据录入!$B$5:$B$785,AW$6)) -> 2500 | AX8: =IF(OR($A8="",AX$6="",NOT(ISNUMBER($H$2))),"",SUMIFS(数据录入!$G$5:$G$785,数据录入!$C$5:$C$785,$A8,数据录入!$B$5:$B$785,AX$6)) -> 0 | AY8: =IF(OR($A8="",AY$6="",NOT(ISNUMBER($H$2))),"",SUMIFS(数据录入!$F$5:$F$785,数据录入!$C$5:$C$785,$A8,数据录入!$B$5:$B$785,AY$6)) -> 0 | AZ8: =IF(OR($A8="",AZ$6="",NOT(ISNUMBER($H$2))),"",SUMIFS(数据录入!$G$5:$G$785,数据录入!$C$5:$C$785,$A8,数据录入!$B$5:$B$785,AZ$6)) -> 0 | BA8: =IF(OR($A8="",BA$6="",NOT(ISNUMBER($H$2))),"",SUMIFS(数据录入!$F$5:$F$785,数据录入!$C$5:$C$785,$A8,数据录入!$B$5:$B$785,BA$6)) -> 0 | BB8: =IF(OR($A8="",BB$6="",NOT(ISNUMBER($H$2))),"",SUMIFS(数据录入!$G$5:$G$785,数据录入!$C$5:$C$785,$A8,数据录入!$B$5:$B$785,BB$6)) -> 0 | BC8: =IF(OR($A8="",BC$6="",NOT(ISNUMBER($H$2))),"",SUMIFS(数据录入!$F$5:$F$785,数据录入!$C$5:$C$785,$A8,数据录入!$B$5:$B$785,BC$6)) -> 75033.34 | BD8: =IF(OR($A8="",BD$6="",NOT(ISNUMBER($H$2))),"",SUMIFS(数据录入!$G$5:$G$785,数据录入!$C$5:$C$785,$A8,数据录入!$B$5:$B$785,BD$6)) -> 200000 | BE8: =IF(OR($A8="",BE$6="",NOT(ISNUMBER($H$2))),"",SUMIFS(数据录入!$F$5:$F$785,数据录入!$C$5:$C$785,$A8,数据录入!$B$5:$B$785,BE$6)) -> 0 | BF8: =IF(OR($A8="",BF$6="",NOT(ISNUMBER($H$2))),"",SUMIFS(数据录入!$G$5:$G$785,数据录入!$C$5:$C$785,$A8,数据录入!$B$5:$B$785,BF$6)) -> 0 | BG8: =IF(OR($A8="",BG$6="",NOT(ISNUMBER($H$2))),"",SUMIFS(数据录入!$F$5:$F$785,数据录入!$C$5:$C$785,$A8,数据录入!$B$5:$B$785,BG$6)) -> 0 | BH8: =IF(OR($A8="",BH$6="",NOT(ISNUMBER($H$2))),"",SUMIFS(数据录入!$G$5:$G$785,数据录入!$C$5:$C$785,$A8,数据录入!$B$5:$B$785,BH$6)) -> 0 | BI8: =IF(OR($A8="",BI$6="",NOT(ISNUMBER($H$2))),"",SUMIFS(数据录入!$F$5:$F$785,数据录入!$C$5:$C$785,$A8,数据录入!$B$5:$B$785,BI$6)) -> 2000 | BJ8: =IF(OR($A8="",BJ$6="",NOT(ISNUMBER($H$2))),"",SUMIFS(数据录入!$G$5:$G$785,数据录入!$C$5:$C$785,$A8,数据录入!$B$5:$B$785,BJ$6)) -> 490.3 | BK8: =IF(OR($A8="",BK$6="",NOT(ISNUMBER($H$2))),"",SUMIFS(数据录入!$F$5:$F$785,数据录入!$C$5:$C$785,$A8,数据录入!$B$5:$B$785,BK$6)) | BL8: =IF(OR($A8="",BL$6="",NOT(ISNUMBER($H$2))),"",SUMIFS(数据录入!$G$5:$G$785,数据录入!$C$5:$C$785,$A8,数据录入!$B$5:$B$785,BL$6)) | BM8: =IF($A8="","",SUMIF($C$7:$BL$7,"收款",C8:BL8)) -> 882828.34 | BN8: =IF($A8="","",SUMIF($C$7:$BL$7,"付款",C8:BL8)) -> 1084329.3 | BO8: =IF($A8="","",B8+BM8-BN8) -> 17762.14
A9: 典当微信 | B9: =IF(OR($A9="",NOT(ISNUMBER($H$2))),"",SUMIFS(数据录入!$H$5:$H$785,数据录入!$C$5:$C$785,$A9,数据录入!$E$5:$E$785,"期初余额",数据录入!$B$5:$B$785,"<="&$B$2)+SUMIFS(数据录入!$F$5:$F$785,数据录入!$C$5:$C$785,$A9,数据录入!$B$5:$B$785,"<"&$B$2)-SUMIFS(数据录入!$G$5:$G$785,数据录入!$C$5:$C$785,$A9,数据录入!$B$5:$B$785,"<"&$B$2)) -> 112326.39 | C9: =IF(OR($A9="",C$6="",NOT(ISNUMBER($H$2))),"",SUMIFS(数据录入!$F$5:$F$785,数据录入!$C$5:$C$785,$A9,数据录入!$B$5:$B$785,C$6)) -> 2480 | D9: =IF(OR($A9="",D$6="",NOT(ISNUMBER($H$2))),"",SUMIFS(数据录入!$G$5:$G$785,数据录入!$C$5:$C$785,$A9,数据录入!$B$5:$B$785,D$6)) -> 52480 | E9: =IF(OR($A9="",E$6="",NOT(ISNUMBER($H$2))),"",SUMIFS(数据录入!$F$5:$F$785,数据录入!$C$5:$C$785,$A9,数据录入!$B$5:$B$785,E$6)) -> 0 | F9: =IF(OR($A9="",F$6="",NOT(ISNUMBER($H$2))),"",SUMIFS(数据录入!$G$5:$G$785,数据录入!$C$5:$C$785,$A9,数据录入!$B$5:$B$785,F$6)) -> 0 | G9: =IF(OR($A9="",G$6="",NOT(ISNUMBER($H$2))),"",SUMIFS(数据录入!$F$5:$F$785,数据录入!$C$5:$C$785,$A9,数据录入!$B$5:$B$785,G$6)) -> 400 | H9: =IF(OR($A9="",H$6="",NOT(ISNUMBER($H$2))),"",SUMIFS(数据录入!$G$5:$G$785,数据录入!$C$5:$C$785,$A9,数据录入!$B$5:$B$785,H$6)) -> 13000 | I9: =IF(OR($A9="",I$6="",NOT(ISNUMBER($H$2))),"",SUMIFS(数据录入!$F$5:$F$785,数据录入!$C$5:$C$785,$A9,数据录入!$B$5:$B$785,I$6)) -> 2250 | J9: =IF(OR($A9="",J$6="",NOT(ISNUMBER($H$2))),"",SUMIFS(数据录入!$G$5:$G$785,数据录入!$C$5:$C$785,$A9,数据录入!$B$5:$B$785,J$6)) -> 0 | K9: =IF(OR($A9="",K$6="",NOT(ISNUMBER($H$2))),"",SUMIFS(数据录入!$F$5:$F$785,数据录入!$C$5:$C$785,$A9,数据录入!$B$5:$B$785,K$6)) -> 1290 | L9: =IF(OR($A9="",L$6="",NOT(ISNUMBER($H$2))),"",SUMIFS(数据录入!$G$5:$G$785,数据录入!$C$5:$C$785,$A9,数据录入!$B$5:$B$785,L$6)) -> 0 | M9: =IF(OR($A9="",M$6="",NOT(ISNUMBER($H$2))),"",SUMIFS(数据录入!$F$5:$F$785,数据录入!$C$5:$C$785,$A9,数据录入!$B$5:$B$785,M$6)) -> 300 | N9: =IF(OR($A9="",N$6="",NOT(ISNUMBER($H$2))),"",SUMIFS(数据录入!$G$5:$G$785,数据录入!$C$5:$C$785,$A9,数据录入!$B$5:$B$785,N$6)) -> 3600 | O9: =IF(OR($A9="",O$6="",NOT(ISNUMBER($H$2))),"",SUMIFS(数据录入!$F$5:$F$785,数据录入!$C$5:$C$785,$A9,数据录入!$B$5:$B$785,O$6)) -> 850 | P9: =IF(OR($A9="",P$6="",NOT(ISNUMBER($H$2))),"",SUMIFS(数据录入!$G$5:$G$785,数据录入!$C$5:$C$785,$A9,数据录入!$B$5:$B$785,P$6)) -> 2143 | Q9: =IF(OR($A9="",Q$6="",NOT(ISNUMBER($H$2))),"",SUMIFS(数据录入!$F$5:$F$785,数据录入!$C$5:$C$785,$A9,数据录入!$B$5:$B$785,Q$6)) -> 8700 | R9: =IF(OR($A9="",R$6="",NOT(ISNUMBER($H$2))),"",SUMIFS(数据录入!$G$5:$G$785,数据录入!$C$5:$C$785,$A9,数据录入!$B$5:$B$785,R$6)) -> 0 | S9: =IF(OR($A9="",S$6="",NOT(ISNUMBER($H$2))),"",SUMIFS(数据录入!$F$5:$F$785,数据录入!$C$5:$C$785,$A9,数据录入!$B$5:$B$785,S$6)) -> 4200 | T9: =IF(OR($A9="",T$6="",NOT(ISNUMBER($H$2))),"",SUMIFS(数据录入!$G$5:$G$785,数据录入!$C$5:$C$785,$A9,数据录入!$B$5:$B$785,T$6)) -> 0 | U9: =IF(OR($A9="",U$6="",NOT(ISNUMBER($H$2))),"",SUMIFS(数据录入!$F$5:$F$785,数据录入!$C$5:$C$785,$A9,数据录入!$B$5:$B$785,U$6)) -> 12540 | V9: =IF(OR($A9="",V$6="",NOT(ISNUMBER($H$2))),"",SUMIFS(数据录入!$G$5:$G$785,数据录入!$C$5:$C$785,$A9,数据录入!$B$5:$B$785,V$6)) -> 0 | W9: =IF(OR($A9="",W$6="",NOT(ISNUMBER($H$2))),"",SUMIFS(数据录入!$F$5:$F$785,数据录入!$C$5:$C$785,$A9,数据录入!$B$5:$B$785,W$6)) -> 1650 | X9: =IF(OR($A9="",X$6="",NOT(ISNUMBER($H$2))),"",SUMIFS(数据录入!$G$5:$G$785,数据录入!$C$5:$C$785,$A9,数据录入!$B$5:$B$785,X$6)) -> 0 | Y9: =IF(OR($A9="",Y$6="",NOT(ISNUMBER($H$2))),"",SUMIFS(数据录入!$F$5:$F$785,数据录入!$C$5:$C$785,$A9,数据录入!$B$5:$B$785,Y$6)) -> 3000 | Z9: =IF(OR($A9="",Z$6="",NOT(ISNUMBER($H$2))),"",SUMIFS(数据录入!$G$5:$G$785,数据录入!$C$5:$C$785,$A9,数据录入!$B$5:$B$785,Z$6)) -> 0 | AA9: =IF(OR($A9="",AA$6="",NOT(ISNUMBER($H$2))),"",SUMIFS(数据录入!$F$5:$F$785,数据录入!$C$5:$C$785,$A9,数据录入!$B$5:$B$785,AA$6)) -> 19465 | AB9: =IF(OR($A9="",AB$6="",NOT(ISNUMBER($H$2))),"",SUMIFS(数据录入!$G$5:$G$785,数据录入!$C$5:$C$785,$A9,数据录入!$B$5:$B$785,AB$6)) -> 0 | AC9: =IF(OR($A9="",AC$6="",NOT(ISNUMBER($H$2))),"",SUMIFS(数据录入!$F$5:$F$785,数据录入!$C$5:$C$785,$A9,数据录入!$B$5:$B$785,AC$6)) -> 5015 | AD9: =IF(OR($A9="",AD$6="",NOT(ISNUMBER($H$2))),"",SUMIFS(数据录入!$G$5:$G$785,数据录入!$C$5:$C$785,$A9,数据录入!$B$5:$B$785,AD$6)) -> 1566 | AE9: =IF(OR($A9="",AE$6="",NOT(ISNUMBER($H$2))),"",SUMIFS(数据录入!$F$5:$F$785,数据录入!$C$5:$C$785,$A9,数据录入!$B$5:$B$785,AE$6)) -> 5500 | AF9: =IF(OR($A9="",AF$6="",NOT(ISNUMBER($H$2))),"",SUMIFS(数据录入!$G$5:$G$785,数据录入!$C$5:$C$785,$A9,数据录入!$B$5:$B$785,AF$6)) -> 0 | AG9: =IF(OR($A9="",AG$6="",NOT(ISNUMBER($H$2))),"",SUMIFS(数据录入!$F$5:$F$785,数据录入!$C$5:$C$785,$A9,数据录入!$B$5:$B$785,AG$6)) -> 150 | AH9: =IF(OR($A9="",AH$6="",NOT(ISNUMBER($H$2))),"",SUMIFS(数据录入!$G$5:$G$785,数据录入!$C$5:$C$785,$A9,数据录入!$B$5:$B$785,AH$6)) -> 0 | AI9: =IF(OR($A9="",AI$6="",NOT(ISNUMBER($H$2))),"",SUMIFS(数据录入!$F$5:$F$785,数据录入!$C$5:$C$785,$A9,数据录入!$B$5:$B$785,AI$6)) -> 2900 | AJ9: =IF(OR($A9="",AJ$6="",NOT(ISNUMBER($H$2))),"",SUMIFS(数据录入!$G$5:$G$785,数据录入!$C$5:$C$785,$A9,数据录入!$B$5:$B$785,AJ$6)) -> 0 | AK9: =IF(OR($A9="",AK$6="",NOT(ISNUMBER($H$2))),"",SUMIFS(数据录入!$F$5:$F$785,数据录入!$C$5:$C$785,$A9,数据录入!$B$5:$B$785,AK$6)) -> 4000 | AL9: =IF(OR($A9="",AL$6="",NOT(ISNUMBER($H$2))),"",SUMIFS(数据录入!$G$5:$G$785,数据录入!$C$5:$C$785,$A9,数据录入!$B$5:$B$785,AL$6)) -> 0 | AM9: =IF(OR($A9="",AM$6="",NOT(ISNUMBER($H$2))),"",SUMIFS(数据录入!$F$5:$F$785,数据录入!$C$5:$C$785,$A9,数据录入!$B$5:$B$785,AM$6)) -> 1125 | AN9: =IF(OR($A9="",AN$6="",NOT(ISNUMBER($H$2))),"",SUMIFS(数据录入!$G$5:$G$785,数据录入!$C$5:$C$785,$A9,数据录入!$B$5:$B$785,AN$6)) -> 0 | AO9: =IF(OR($A9="",AO$6="",NOT(ISNUMBER($H$2))),"",SUMIFS(数据录入!$F$5:$F$785,数据录入!$C$5:$C$785,$A9,数据录入!$B$5:$B$785,AO$6)) -> 7650 | AP9: =IF(OR($A9="",AP$6="",NOT(ISNUMBER($H$2))),"",SUMIFS(数据录入!$G$5:$G$785,数据录入!$C$5:$C$785,$A9,数据录入!$B$5:$B$785,AP$6)) -> 8880 | AQ9: =IF(OR($A9="",AQ$6="",NOT(ISNUMBER($H$2))),"",SUMIFS(数据录入!$F$5:$F$785,数据录入!$C$5:$C$785,$A9,数据录入!$B$5:$B$785,AQ$6)) -> 7500 | AR9: =IF(OR($A9="",AR$6="",NOT(ISNUMBER($H$2))),"",SUMIFS(数据录入!$G$5:$G$785,数据录入!$C$5:$C$785,$A9,数据录入!$B$5:$B$785,AR$6)) -> 0 | AS9: =IF(OR($A9="",AS$6="",NOT(ISNUMBER($H$2))),"",SUMIFS(数据录入!$F$5:$F$785,数据录入!$C$5:$C$785,$A9,数据录入!$B$5:$B$785,AS$6)) -> 970 | AT9: =IF(OR($A9="",AT$6="",NOT(ISNUMBER($H$2))),"",SUMIFS(数据录入!$G$5:$G$785,数据录入!$C$5:$C$785,$A9,数据录入!$B$5:$B$785,AT$6)) -> 0 | AU9: =IF(OR($A9="",AU$6="",NOT(ISNUMBER($H$2))),"",SUMIFS(数据录入!$F$5:$F$785,数据录入!$C$5:$C$785,$A9,数据录入!$B$5:$B$785,AU$6)) -> 2325 | AV9: =IF(OR($A9="",AV$6="",NOT(ISNUMBER($H$2))),"",SUMIFS(数据录入!$G$5:$G$785,数据录入!$C$5:$C$785,$A9,数据录入!$B$5:$B$785,AV$6)) -> 0 | AW9: =IF(OR($A9="",AW$6="",NOT(ISNUMBER($H$2))),"",SUMIFS(数据录入!$F$5:$F$785,数据录入!$C$5:$C$785,$A9,数据录入!$B$5:$B$785,AW$6)) -> 6630 | AX9: =IF(OR($A9="",AX$6="",NOT(ISNUMBER($H$2))),"",SUMIFS(数据录入!$G$5:$G$785,数据录入!$C$5:$C$785,$A9,数据录入!$B$5:$B$785,AX$6)) -> 0 | AY9: =IF(OR($A9="",AY$6="",NOT(ISNUMBER($H$2))),"",SUMIFS(数据录入!$F$5:$F$785,数据录入!$C$5:$C$785,$A9,数据录入!$B$5:$B$785,AY$6)) -> 0 | AZ9: =IF(OR($A9="",AZ$6="",NOT(ISNUMBER($H$2))),"",SUMIFS(数据录入!$G$5:$G$785,数据录入!$C$5:$C$785,$A9,数据录入!$B$5:$B$785,AZ$6)) -> 0 | BA9: =IF(OR($A9="",BA$6="",NOT(ISNUMBER($H$2))),"",SUMIFS(数据录入!$F$5:$F$785,数据录入!$C$5:$C$785,$A9,数据录入!$B$5:$B$785,BA$6)) -> 0 | BB9: =IF(OR($A9="",BB$6="",NOT(ISNUMBER($H$2))),"",SUMIFS(数据录入!$G$5:$G$785,数据录入!$C$5:$C$785,$A9,数据录入!$B$5:$B$785,BB$6)) -> 0 | BC9: =IF(OR($A9="",BC$6="",NOT(ISNUMBER($H$2))),"",SUMIFS(数据录入!$F$5:$F$785,数据录入!$C$5:$C$785,$A9,数据录入!$B$5:$B$785,BC$6)) -> 5275 | BD9: =IF(OR($A9="",BD$6="",NOT(ISNUMBER($H$2))),"",SUMIFS(数据录入!$G$5:$G$785,数据录入!$C$5:$C$785,$A9,数据录入!$B$5:$B$785,BD$6)) -> 16000 | BE9: =IF(OR($A9="",BE$6="",NOT(ISNUMBER($H$2))),"",SUMIFS(数据录入!$F$5:$F$785,数据录入!$C$5:$C$785,$A9,数据录入!$B$5:$B$785,BE$6)) -> 2575 | BF9: =IF(OR($A9="",BF$6="",NOT(ISNUMBER($H$2))),"",SUMIFS(数据录入!$G$5:$G$785,数据录入!$C$5:$C$785,$A9,数据录入!$B$5:$B$785,BF$6)) -> 0 | BG9: =IF(OR($A9="",BG$6="",NOT(ISNUMBER($H$2))),"",SUMIFS(数据录入!$F$5:$F$785,数据录入!$C$5:$C$785,$A9,数据录入!$B$5:$B$785,BG$6)) -> 0 | BH9: =IF(OR($A9="",BH$6="",NOT(ISNUMBER($H$2))),"",SUMIFS(数据录入!$G$5:$G$785,数据录入!$C$5:$C$785,$A9,数据录入!$B$5:$B$785,BH$6)) -> 0 | BI9: =IF(OR($A9="",BI$6="",NOT(ISNUMBER($H$2))),"",SUMIFS(数据录入!$F$5:$F$785,数据录入!$C$5:$C$785,$A9,数据录入!$B$5:$B$785,BI$6)) -> 6100 | BJ9: =IF(OR($A9="",BJ$6="",NOT(ISNUMBER($H$2))),"",SUMIFS(数据录入!$G$5:$G$785,数据录入!$C$5:$C$785,$A9,数据录入!$B$5:$B$785,BJ$6)) -> 30000 | BK9: =IF(OR($A9="",BK$6="",NOT(ISNUMBER($H$2))),"",SUMIFS(数据录入!$F$5:$F$785,数据录入!$C$5:$C$785,$A9,数据录入!$B$5:$B$785,BK$6)) | BL9: =IF(OR($A9="",BL$6="",NOT(ISNUMBER($H$2))),"",SUMIFS(数据录入!$G$5:$G$785,数据录入!$C$5:$C$785,$A9,数据录入!$B$5:$B$785,BL$6)) | BM9: =IF($A9="","",SUMIF($C$7:$BL$7,"收款",C9:BL9)) -> 114840 | BN9: =IF($A9="","",SUMIF($C$7:$BL$7,"付款",C9:BL9)) -> 127669 | BO9: =IF($A9="","",B9+BM9-BN9) -> 99497.39
A10: 林总浦发 | B10: =IF(OR($A10="",NOT(ISNUMBER($H$2))),"",SUMIFS(数据录入!$H$5:$H$785,数据录入!$C$5:$C$785,$A10,数据录入!$E$5:$E$785,"期初余额",数据录入!$B$5:$B$785,"<="&$B$2)+SUMIFS(数据录入!$F$5:$F$785,数据录入!$C$5:$C$785,$A10,数据录入!$B$5:$B$785,"<"&$B$2)-SUMIFS(数据录入!$G$5:$G$785,数据录入!$C$5:$C$785,$A10,数据录入!$B$5:$B$785,"<"&$B$2)) -> 73513.15 | C10: =IF(OR($A10="",C$6="",NOT(ISNUMBER($H$2))),"",SUMIFS(数据录入!$F$5:$F$785,数据录入!$C$5:$C$785,$A10,数据录入!$B$5:$B$785,C$6)) -> 2240000 | D10: =IF(OR($A10="",D$6="",NOT(ISNUMBER($H$2))),"",SUMIFS(数据录入!$G$5:$G$785,数据录入!$C$5:$C$785,$A10,数据录入!$B$5:$B$785,D$6)) -> 2300000 | E10: =IF(OR($A10="",E$6="",NOT(ISNUMBER($H$2))),"",SUMIFS(数据录入!$F$5:$F$785,数据录入!$C$5:$C$785,$A10,数据录入!$B$5:$B$785,E$6)) -> 515500 | F10: =IF(OR($A10="",F$6="",NOT(ISNUMBER($H$2))),"",SUMIFS(数据录入!$G$5:$G$785,数据录入!$C$5:$C$785,$A10,数据录入!$B$5:$B$785,F$6)) -> 520000 | G10: =IF(OR($A10="",G$6="",NOT(ISNUMBER($H$2))),"",SUMIFS(数据录入!$F$5:$F$785,数据录入!$C$5:$C$785,$A10,数据录入!$B$5:$B$785,G$6)) -> 0 | H10: =IF(OR($A10="",H$6="",NOT(ISNUMBER($H$2))),"",SUMIFS(数据录入!$G$5:$G$785,数据录入!$C$5:$C$785,$A10,数据录入!$B$5:$B$785,H$6)) -> 2400 | I10: =IF(OR($A10="",I$6="",NOT(ISNUMBER($H$2))),"",SUMIFS(数据录入!$F$5:$F$785,数据录入!$C$5:$C$785,$A10,数据录入!$B$5:$B$785,I$6)) -> 0 | J10: =IF(OR($A10="",J$6="",NOT(ISNUMBER($H$2))),"",SUMIFS(数据录入!$G$5:$G$785,数据录入!$C$5:$C$785,$A10,数据录入!$B$5:$B$785,J$6)) -> 0 | K10: =IF(OR($A10="",K$6="",NOT(ISNUMBER($H$2))),"",SUMIFS(数据录入!$F$5:$F$785,数据录入!$C$5:$C$785,$A10,数据录入!$B$5:$B$785,K$6)) -> 0 | L10: =IF(OR($A10="",L$6="",NOT(ISNUMBER($H$2))),"",SUMIFS(数据录入!$G$5:$G$785,数据录入!$C$5:$C$785,$A10,数据录入!$B$5:$B$785,L$6)) -> 0 | M10: =IF(OR($A10="",M$6="",NOT(ISNUMBER($H$2))),"",SUMIFS(数据录入!$F$5:$F$785,数据录入!$C$5:$C$785,$A10,数据录入!$B$5:$B$785,M$6)) -> 20000 | N10: =IF(OR($A10="",N$6="",NOT(ISNUMBER($H$2))),"",SUMIFS(数据录入!$G$5:$G$785,数据录入!$C$5:$C$785,$A10,数据录入!$B$5:$B$785,N$6)) -> 19100 | O10: =IF(OR($A10="",O$6="",NOT(ISNUMBER($H$2))),"",SUMIFS(数据录入!$F$5:$F$785,数据录入!$C$5:$C$785,$A10,数据录入!$B$5:$B$785,O$6)) -> 106333.33 | P10: =IF(OR($A10="",P$6="",NOT(ISNUMBER($H$2))),"",SUMIFS(数据录入!$G$5:$G$785,数据录入!$C$5:$C$785,$A10,数据录入!$B$5:$B$785,P$6)) -> 200000 | Q10: =IF(OR($A10="",Q$6="",NOT(ISNUMBER($H$2))),"",SUMIFS(数据录入!$F$5:$F$785,数据录入!$C$5:$C$785,$A10,数据录入!$B$5:$B$785,Q$6)) -> 200000 | R10: =IF(OR($A10="",R$6="",NOT(ISNUMBER($H$2))),"",SUMIFS(数据录入!$G$5:$G$785,数据录入!$C$5:$C$785,$A10,数据录入!$B$5:$B$785,R$6)) -> 0 | S10: =IF(OR($A10="",S$6="",NOT(ISNUMBER($H$2))),"",SUMIFS(数据录入!$F$5:$F$785,数据录入!$C$5:$C$785,$A10,数据录入!$B$5:$B$785,S$6)) -> 0 | T10: =IF(OR($A10="",T$6="",NOT(ISNUMBER($H$2))),"",SUMIFS(数据录入!$G$5:$G$785,数据录入!$C$5:$C$785,$A10,数据录入!$B$5:$B$785,T$6)) -> 30000 | U10: =IF(OR($A10="",U$6="",NOT(ISNUMBER($H$2))),"",SUMIFS(数据录入!$F$5:$F$785,数据录入!$C$5:$C$785,$A10,数据录入!$B$5:$B$785,U$6)) -> 90000 | V10: =IF(OR($A10="",V$6="",NOT(ISNUMBER($H$2))),"",SUMIFS(数据录入!$G$5:$G$785,数据录入!$C$5:$C$785,$A10,数据录入!$B$5:$B$785,V$6)) -> 154447 | W10: =IF(OR($A10="",W$6="",NOT(ISNUMBER($H$2))),"",SUMIFS(数据录入!$F$5:$F$785,数据录入!$C$5:$C$785,$A10,数据录入!$B$5:$B$785,W$6)) -> 0 | X10: =IF(OR($A10="",X$6="",NOT(ISNUMBER($H$2))),"",SUMIFS(数据录入!$G$5:$G$785,数据录入!$C$5:$C$785,$A10,数据录入!$B$5:$B$785,X$6)) -> 0 | Y10: =IF(OR($A10="",Y$6="",NOT(ISNUMBER($H$2))),"",SUMIFS(数据录入!$F$5:$F$785,数据录入!$C$5:$C$785,$A10,数据录入!$B$5:$B$785,Y$6)) -> 0 | Z10: =IF(OR($A10="",Z$6="",NOT(ISNUMBER($H$2))),"",SUMIFS(数据录入!$G$5:$G$785,数据录入!$C$5:$C$785,$A10,数据录入!$B$5:$B$785,Z$6)) -> 0 | AA10: =IF(OR($A10="",AA$6="",NOT(ISNUMBER($H$2))),"",SUMIFS(数据录入!$F$5:$F$785,数据录入!$C$5:$C$785,$A10,数据录入!$B$5:$B$785,AA$6)) -> 60000 | AB10: =IF(OR($A10="",AB$6="",NOT(ISNUMBER($H$2))),"",SUMIFS(数据录入!$G$5:$G$785,数据录入!$C$5:$C$785,$A10,数据录入!$B$5:$B$785,AB$6)) -> 55000 | AC10: =IF(OR($A10="",AC$6="",NOT(ISNUMBER($H$2))),"",SUMIFS(数据录入!$F$5:$F$785,数据录入!$C$5:$C$785,$A10,数据录入!$B$5:$B$785,AC$6)) -> 32735.47 | AD10: =IF(OR($A10="",AD$6="",NOT(ISNUMBER($H$2))),"",SUMIFS(数据录入!$G$5:$G$785,数据录入!$C$5:$C$785,$A10,数据录入!$B$5:$B$785,AD$6)) -> 0 | AE10: =IF(OR($A10="",AE$6="",NOT(ISNUMBER($H$2))),"",SUMIFS(数据录入!$F$5:$F$785,数据录入!$C$5:$C$785,$A10,数据录入!$B$5:$B$785,AE$6)) -> 0 | AF10: =IF(OR($A10="",AF$6="",NOT(ISNUMBER($H$2))),"",SUMIFS(数据录入!$G$5:$G$785,数据录入!$C$5:$C$785,$A10,数据录入!$B$5:$B$785,AF$6)) -> 500 | AG10: =IF(OR($A10="",AG$6="",NOT(ISNUMBER($H$2))),"",SUMIFS(数据录入!$F$5:$F$785,数据录入!$C$5:$C$785,$A10,数据录入!$B$5:$B$785,AG$6)) -> 330000 | AH10: =IF(OR($A10="",AH$6="",NOT(ISNUMBER($H$2))),"",SUMIFS(数据录入!$G$5:$G$785,数据录入!$C$5:$C$785,$A10,数据录入!$B$5:$B$785,AH$6)) -> 380000 | AI10: =IF(OR($A10="",AI$6="",NOT(ISNUMBER($H$2))),"",SUMIFS(数据录入!$F$5:$F$785,数据录入!$C$5:$C$785,$A10,数据录入!$B$5:$B$785,AI$6)) -> 7200 | AJ10: =IF(OR($A10="",AJ$6="",NOT(ISNUMBER($H$2))),"",SUMIFS(数据录入!$G$5:$G$785,数据录入!$C$5:$C$785,$A10,数据录入!$B$5:$B$785,AJ$6)) -> 0 | AK10: =IF(OR($A10="",AK$6="",NOT(ISNUMBER($H$2))),"",SUMIFS(数据录入!$F$5:$F$785,数据录入!$C$5:$C$785,$A10,数据录入!$B$5:$B$785,AK$6)) -> 0 | AL10: =IF(OR($A10="",AL$6="",NOT(ISNUMBER($H$2))),"",SUMIFS(数据录入!$G$5:$G$785,数据录入!$C$5:$C$785,$A10,数据录入!$B$5:$B$785,AL$6)) -> 10400 | AM10: =IF(OR($A10="",AM$6="",NOT(ISNUMBER($H$2))),"",SUMIFS(数据录入!$F$5:$F$785,数据录入!$C$5:$C$785,$A10,数据录入!$B$5:$B$785,AM$6)) -> 0 | AN10: =IF(OR($A10="",AN$6="",NOT(ISNUMBER($H$2))),"",SUMIFS(数据录入!$G$5:$G$785,数据录入!$C$5:$C$785,$A10,数据录入!$B$5:$B$785,AN$6)) -> 0 | AO10: =IF(OR($A10="",AO$6="",NOT(ISNUMBER($H$2))),"",SUMIFS(数据录入!$F$5:$F$785,数据录入!$C$5:$C$785,$A10,数据录入!$B$5:$B$785,AO$6)) -> 250000 | AP10: =IF(OR($A10="",AP$6="",NOT(ISNUMBER($H$2))),"",SUMIFS(数据录入!$G$5:$G$785,数据录入!$C$5:$C$785,$A10,数据录入!$B$5:$B$785,AP$6)) -> 103090 | AQ10: =IF(OR($A10="",AQ$6="",NOT(ISNUMBER($H$2))),"",SUMIFS(数据录入!$F$5:$F$785,数据录入!$C$5:$C$785,$A10,数据录入!$B$5:$B$785,AQ$6)) -> 1250 | AR10: =IF(OR($A10="",AR$6="",NOT(ISNUMBER($H$2))),"",SUMIFS(数据录入!$G$5:$G$785,数据录入!$C$5:$C$785,$A10,数据录入!$B$5:$B$785,AR$6)) -> 0 | AS10: =IF(OR($A10="",AS$6="",NOT(ISNUMBER($H$2))),"",SUMIFS(数据录入!$F$5:$F$785,数据录入!$C$5:$C$785,$A10,数据录入!$B$5:$B$785,AS$6)) -> 110000 | AT10: =IF(OR($A10="",AT$6="",NOT(ISNUMBER($H$2))),"",SUMIFS(数据录入!$G$5:$G$785,数据录入!$C$5:$C$785,$A10,数据录入!$B$5:$B$785,AT$6)) -> 220500 | AU10: =IF(OR($A10="",AU$6="",NOT(ISNUMBER($H$2))),"",SUMIFS(数据录入!$F$5:$F$785,数据录入!$C$5:$C$785,$A10,数据录入!$B$5:$B$785,AU$6)) -> 82700 | AV10: =IF(OR($A10="",AV$6="",NOT(ISNUMBER($H$2))),"",SUMIFS(数据录入!$G$5:$G$785,数据录入!$C$5:$C$785,$A10,数据录入!$B$5:$B$785,AV$6)) -> 99500 | AW10: =IF(OR($A10="",AW$6="",NOT(ISNUMBER($H$2))),"",SUMIFS(数据录入!$F$5:$F$785,数据录入!$C$5:$C$785,$A10,数据录入!$B$5:$B$785,AW$6)) -> 212000 | AX10: =IF(OR($A10="",AX$6="",NOT(ISNUMBER($H$2))),"",SUMIFS(数据录入!$G$5:$G$785,数据录入!$C$5:$C$785,$A10,数据录入!$B$5:$B$785,AX$6)) -> 120093.76 | AY10: =IF(OR($A10="",AY$6="",NOT(ISNUMBER($H$2))),"",SUMIFS(数据录入!$F$5:$F$785,数据录入!$C$5:$C$785,$A10,数据录入!$B$5:$B$785,AY$6)) -> 0 | AZ10: =IF(OR($A10="",AZ$6="",NOT(ISNUMBER($H$2))),"",SUMIFS(数据录入!$G$5:$G$785,数据录入!$C$5:$C$785,$A10,数据录入!$B$5:$B$785,AZ$6)) -> 0 | BA10: =IF(OR($A10="",BA$6="",NOT(ISNUMBER($H$2))),"",SUMIFS(数据录入!$F$5:$F$785,数据录入!$C$5:$C$785,$A10,数据录入!$B$5:$B$785,BA$6)) -> 0 | BB10: =IF(OR($A10="",BB$6="",NOT(ISNUMBER($H$2))),"",SUMIFS(数据录入!$G$5:$G$785,数据录入!$C$5:$C$785,$A10,数据录入!$B$5:$B$785,BB$6)) -> 0 | BC10: =IF(OR($A10="",BC$6="",NOT(ISNUMBER($H$2))),"",SUMIFS(数据录入!$F$5:$F$785,数据录入!$C$5:$C$785,$A10,数据录入!$B$5:$B$785,BC$6)) -> 1103600 | BD10: =IF(OR($A10="",BD$6="",NOT(ISNUMBER($H$2))),"",SUMIFS(数据录入!$G$5:$G$785,数据录入!$C$5:$C$785,$A10,数据录入!$B$5:$B$785,BD$6)) -> 1150033.3 | BE10: =IF(OR($A10="",BE$6="",NOT(ISNUMBER($H$2))),"",SUMIFS(数据录入!$F$5:$F$785,数据录入!$C$5:$C$785,$A10,数据录入!$B$5:$B$785,BE$6)) -> 340500 | BF10: =IF(OR($A10="",BF$6="",NOT(ISNUMBER($H$2))),"",SUMIFS(数据录入!$G$5:$G$785,数据录入!$C$5:$C$785,$A10,数据录入!$B$5:$B$785,BF$6)) -> 400000 | BG10: =IF(OR($A10="",BG$6="",NOT(ISNUMBER($H$2))),"",SUMIFS(数据录入!$F$5:$F$785,数据录入!$C$5:$C$785,$A10,数据录入!$B$5:$B$785,BG$6)) -> 24000 | BH10: =IF(OR($A10="",BH$6="",NOT(ISNUMBER($H$2))),"",SUMIFS(数据录入!$G$5:$G$785,数据录入!$C$5:$C$785,$A10,数据录入!$B$5:$B$785,BH$6)) -> 0 | BI10: =IF(OR($A10="",BI$6="",NOT(ISNUMBER($H$2))),"",SUMIFS(数据录入!$F$5:$F$785,数据录入!$C$5:$C$785,$A10,数据录入!$B$5:$B$785,BI$6)) -> 400000 | BJ10: =IF(OR($A10="",BJ$6="",NOT(ISNUMBER($H$2))),"",SUMIFS(数据录入!$G$5:$G$785,数据录入!$C$5:$C$785,$A10,数据录入!$B$5:$B$785,BJ$6)) -> 400000 | BK10: =IF(OR($A10="",BK$6="",NOT(ISNUMBER($H$2))),"",SUMIFS(数据录入!$F$5:$F$785,数据录入!$C$5:$C$785,$A10,数据录入!$B$5:$B$785,BK$6)) | BL10: =IF(OR($A10="",BL$6="",NOT(ISNUMBER($H$2))),"",SUMIFS(数据录入!$G$5:$G$785,数据录入!$C$5:$C$785,$A10,数据录入!$B$5:$B$785,BL$6)) | BM10: =IF($A10="","",SUMIF($C$7:$BL$7,"收款",C10:BL10)) -> 6125818.8 | BN10: =IF($A10="","",SUMIF($C$7:$BL$7,"付款",C10:BL10)) -> 6165064.1 | BO10: =IF($A10="","",B10+BM10-BN10) -> 34267.85
A11: 吴姐建行 | B11: =IF(OR($A11="",NOT(ISNUMBER($H$2))),"",SUMIFS(数据录入!$H$5:$H$785,数据录入!$C$5:$C$785,$A11,数据录入!$E$5:$E$785,"期初余额",数据录入!$B$5:$B$785,"<="&$B$2)+SUMIFS(数据录入!$F$5:$F$785,数据录入!$C$5:$C$785,$A11,数据录入!$B$5:$B$785,"<"&$B$2)-SUMIFS(数据录入!$G$5:$G$785,数据录入!$C$5:$C$785,$A11,数据录入!$B$5:$B$785,"<"&$B$2)) -> 90026.28 | C11: =IF(OR($A11="",C$6="",NOT(ISNUMBER($H$2))),"",SUMIFS(数据录入!$F$5:$F$785,数据录入!$C$5:$C$785,$A11,数据录入!$B$5:$B$785,C$6)) -> 56162.04 | D11: =IF(OR($A11="",D$6="",NOT(ISNUMBER($H$2))),"",SUMIFS(数据录入!$G$5:$G$785,数据录入!$C$5:$C$785,$A11,数据录入!$B$5:$B$785,D$6)) -> 130000 | E11: =IF(OR($A11="",E$6="",NOT(ISNUMBER($H$2))),"",SUMIFS(数据录入!$F$5:$F$785,数据录入!$C$5:$C$785,$A11,数据录入!$B$5:$B$785,E$6)) -> 0 | F11: =IF(OR($A11="",F$6="",NOT(ISNUMBER($H$2))),"",SUMIFS(数据录入!$G$5:$G$785,数据录入!$C$5:$C$785,$A11,数据录入!$B$5:$B$785,F$6)) -> 0 | G11: =IF(OR($A11="",G$6="",NOT(ISNUMBER($H$2))),"",SUMIFS(数据录入!$F$5:$F$785,数据录入!$C$5:$C$785,$A11,数据录入!$B$5:$B$785,G$6)) -> 100 | H11: =IF(OR($A11="",H$6="",NOT(ISNUMBER($H$2))),"",SUMIFS(数据录入!$G$5:$G$785,数据录入!$C$5:$C$785,$A11,数据录入!$B$5:$B$785,H$6)) -> 0 | I11: =IF(OR($A11="",I$6="",NOT(ISNUMBER($H$2))),"",SUMIFS(数据录入!$F$5:$F$785,数据录入!$C$5:$C$785,$A11,数据录入!$B$5:$B$785,I$6)) -> 800 | J11: =IF(OR($A11="",J$6="",NOT(ISNUMBER($H$2))),"",SUMIFS(数据录入!$G$5:$G$785,数据录入!$C$5:$C$785,$A11,数据录入!$B$5:$B$785,J$6)) -> 0 | K11: =IF(OR($A11="",K$6="",NOT(ISNUMBER($H$2))),"",SUMIFS(数据录入!$F$5:$F$785,数据录入!$C$5:$C$785,$A11,数据录入!$B$5:$B$785,K$6)) -> 0 | L11: =IF(OR($A11="",L$6="",NOT(ISNUMBER($H$2))),"",SUMIFS(数据录入!$G$5:$G$785,数据录入!$C$5:$C$785,$A11,数据录入!$B$5:$B$785,L$6)) -> 0 | M11: =IF(OR($A11="",M$6="",NOT(ISNUMBER($H$2))),"",SUMIFS(数据录入!$F$5:$F$785,数据录入!$C$5:$C$785,$A11,数据录入!$B$5:$B$785,M$6)) -> 300000 | N11: =IF(OR($A11="",N$6="",NOT(ISNUMBER($H$2))),"",SUMIFS(数据录入!$G$5:$G$785,数据录入!$C$5:$C$785,$A11,数据录入!$B$5:$B$785,N$6)) -> 0 | O11: =IF(OR($A11="",O$6="",NOT(ISNUMBER($H$2))),"",SUMIFS(数据录入!$F$5:$F$785,数据录入!$C$5:$C$785,$A11,数据录入!$B$5:$B$785,O$6)) -> 72800 | P11: =IF(OR($A11="",P$6="",NOT(ISNUMBER($H$2))),"",SUMIFS(数据录入!$G$5:$G$785,数据录入!$C$5:$C$785,$A11,数据录入!$B$5:$B$785,P$6)) -> 500 | Q11: =IF(OR($A11="",Q$6="",NOT(ISNUMBER($H$2))),"",SUMIFS(数据录入!$F$5:$F$785,数据录入!$C$5:$C$785,$A11,数据录入!$B$5:$B$785,Q$6)) -> 1100000 | R11: =IF(OR($A11="",R$6="",NOT(ISNUMBER($H$2))),"",SUMIFS(数据录入!$G$5:$G$785,数据录入!$C$5:$C$785,$A11,数据录入!$B$5:$B$785,R$6)) -> 0 | S11: =IF(OR($A11="",S$6="",NOT(ISNUMBER($H$2))),"",SUMIFS(数据录入!$F$5:$F$785,数据录入!$C$5:$C$785,$A11,数据录入!$B$5:$B$785,S$6)) -> 4533 | T11: =IF(OR($A11="",T$6="",NOT(ISNUMBER($H$2))),"",SUMIFS(数据录入!$G$5:$G$785,数据录入!$C$5:$C$785,$A11,数据录入!$B$5:$B$785,T$6)) -> 0 | U11: =IF(OR($A11="",U$6="",NOT(ISNUMBER($H$2))),"",SUMIFS(数据录入!$F$5:$F$785,数据录入!$C$5:$C$785,$A11,数据录入!$B$5:$B$785,U$6)) -> 184200 | V11: =IF(OR($A11="",V$6="",NOT(ISNUMBER($H$2))),"",SUMIFS(数据录入!$G$5:$G$785,数据录入!$C$5:$C$785,$A11,数据录入!$B$5:$B$785,V$6)) -> 200000 | W11: =IF(OR($A11="",W$6="",NOT(ISNUMBER($H$2))),"",SUMIFS(数据录入!$F$5:$F$785,数据录入!$C$5:$C$785,$A11,数据录入!$B$5:$B$785,W$6)) -> 0 | X11: =IF(OR($A11="",X$6="",NOT(ISNUMBER($H$2))),"",SUMIFS(数据录入!$G$5:$G$785,数据录入!$C$5:$C$785,$A11,数据录入!$B$5:$B$785,X$6)) -> 0 | Y11: =IF(OR($A11="",Y$6="",NOT(ISNUMBER($H$2))),"",SUMIFS(数据录入!$F$5:$F$785,数据录入!$C$5:$C$785,$A11,数据录入!$B$5:$B$785,Y$6)) -> 0 | Z11: =IF(OR($A11="",Z$6="",NOT(ISNUMBER($H$2))),"",SUMIFS(数据录入!$G$5:$G$785,数据录入!$C$5:$C$785,$A11,数据录入!$B$5:$B$785,Z$6)) -> 0 | AA11: =IF(OR($A11="",AA$6="",NOT(ISNUMBER($H$2))),"",SUMIFS(数据录入!$F$5:$F$785,数据录入!$C$5:$C$785,$A11,数据录入!$B$5:$B$785,AA$6)) -> 5500 | AB11: =IF(OR($A11="",AB$6="",NOT(ISNUMBER($H$2))),"",SUMIFS(数据录入!$G$5:$G$785,数据录入!$C$5:$C$785,$A11,数据录入!$B$5:$B$785,AB$6)) -> 60027.4 | AC11: =IF(OR($A11="",AC$6="",NOT(ISNUMBER($H$2))),"",SUMIFS(数据录入!$F$5:$F$785,数据录入!$C$5:$C$785,$A11,数据录入!$B$5:$B$785,AC$6)) -> 0 | AD11: =IF(OR($A11="",AD$6="",NOT(ISNUMBER($H$2))),"",SUMIFS(数据录入!$G$5:$G$785,数据录入!$C$5:$C$785,$A11,数据录入!$B$5:$B$785,AD$6)) -> 0 | AE11: =IF(OR($A11="",AE$6="",NOT(ISNUMBER($H$2))),"",SUMIFS(数据录入!$F$5:$F$785,数据录入!$C$5:$C$785,$A11,数据录入!$B$5:$B$785,AE$6)) -> 0 | AF11: =IF(OR($A11="",AF$6="",NOT(ISNUMBER($H$2))),"",SUMIFS(数据录入!$G$5:$G$785,数据录入!$C$5:$C$785,$A11,数据录入!$B$5:$B$785,AF$6)) -> 0 | AG11: =IF(OR($A11="",AG$6="",NOT(ISNUMBER($H$2))),"",SUMIFS(数据录入!$F$5:$F$785,数据录入!$C$5:$C$785,$A11,数据录入!$B$5:$B$785,AG$6)) -> 210 | AH11: =IF(OR($A11="",AH$6="",NOT(ISNUMBER($H$2))),"",SUMIFS(数据录入!$G$5:$G$785,数据录入!$C$5:$C$785,$A11,数据录入!$B$5:$B$785,AH$6)) -> 331000 | AI11: =IF(OR($A11="",AI$6="",NOT(ISNUMBER($H$2))),"",SUMIFS(数据录入!$F$5:$F$785,数据录入!$C$5:$C$785,$A11,数据录入!$B$5:$B$785,AI$6)) -> 200 | AJ11: =IF(OR($A11="",AJ$6="",NOT(ISNUMBER($H$2))),"",SUMIFS(数据录入!$G$5:$G$785,数据录入!$C$5:$C$785,$A11,数据录入!$B$5:$B$785,AJ$6)) -> 0 | AK11: =IF(OR($A11="",AK$6="",NOT(ISNUMBER($H$2))),"",SUMIFS(数据录入!$F$5:$F$785,数据录入!$C$5:$C$785,$A11,数据录入!$B$5:$B$785,AK$6)) -> 7171.67 | AL11: =IF(OR($A11="",AL$6="",NOT(ISNUMBER($H$2))),"",SUMIFS(数据录入!$G$5:$G$785,数据录入!$C$5:$C$785,$A11,数据录入!$B$5:$B$785,AL$6)) -> 158.97 | AM11: =IF(OR($A11="",AM$6="",NOT(ISNUMBER($H$2))),"",SUMIFS(数据录入!$F$5:$F$785,数据录入!$C$5:$C$785,$A11,数据录入!$B$5:$B$785,AM$6)) -> 0 | AN11: =IF(OR($A11="",AN$6="",NOT(ISNUMBER($H$2))),"",SUMIFS(数据录入!$G$5:$G$785,数据录入!$C$5:$C$785,$A11,数据录入!$B$5:$B$785,AN$6)) -> 0 | AO11: =IF(OR($A11="",AO$6="",NOT(ISNUMBER($H$2))),"",SUMIFS(数据录入!$F$5:$F$785,数据录入!$C$5:$C$785,$A11,数据录入!$B$5:$B$785,AO$6)) -> 4875 | AP11: =IF(OR($A11="",AP$6="",NOT(ISNUMBER($H$2))),"",SUMIFS(数据录入!$G$5:$G$785,数据录入!$C$5:$C$785,$A11,数据录入!$B$5:$B$785,AP$6)) -> 50000 | AQ11: =IF(OR($A11="",AQ$6="",NOT(ISNUMBER($H$2))),"",SUMIFS(数据录入!$F$5:$F$785,数据录入!$C$5:$C$785,$A11,数据录入!$B$5:$B$785,AQ$6)) -> 0 | AR11: =IF(OR($A11="",AR$6="",NOT(ISNUMBER($H$2))),"",SUMIFS(数据录入!$G$5:$G$785,数据录入!$C$5:$C$785,$A11,数据录入!$B$5:$B$785,AR$6)) -> 0 | AS11: =IF(OR($A11="",AS$6="",NOT(ISNUMBER($H$2))),"",SUMIFS(数据录入!$F$5:$F$785,数据录入!$C$5:$C$785,$A11,数据录入!$B$5:$B$785,AS$6)) -> 1500 | AT11: =IF(OR($A11="",AT$6="",NOT(ISNUMBER($H$2))),"",SUMIFS(数据录入!$G$5:$G$785,数据录入!$C$5:$C$785,$A11,数据录入!$B$5:$B$785,AT$6)) -> 0 | AU11: =IF(OR($A11="",AU$6="",NOT(ISNUMBER($H$2))),"",SUMIFS(数据录入!$F$5:$F$785,数据录入!$C$5:$C$785,$A11,数据录入!$B$5:$B$785,AU$6)) -> 0 | AV11: =IF(OR($A11="",AV$6="",NOT(ISNUMBER($H$2))),"",SUMIFS(数据录入!$G$5:$G$785,数据录入!$C$5:$C$785,$A11,数据录入!$B$5:$B$785,AV$6)) -> 0 | AW11: =IF(OR($A11="",AW$6="",NOT(ISNUMBER($H$2))),"",SUMIFS(数据录入!$F$5:$F$785,数据录入!$C$5:$C$785,$A11,数据录入!$B$5:$B$785,AW$6)) -> 250100 | AX11: =IF(OR($A11="",AX$6="",NOT(ISNUMBER($H$2))),"",SUMIFS(数据录入!$G$5:$G$785,数据录入!$C$5:$C$785,$A11,数据录入!$B$5:$B$785,AX$6)) -> 150000 | AY11: =IF(OR($A11="",AY$6="",NOT(ISNUMBER($H$2))),"",SUMIFS(数据录入!$F$5:$F$785,数据录入!$C$5:$C$785,$A11,数据录入!$B$5:$B$785,AY$6)) -> 0 | AZ11: =IF(OR($A11="",AZ$6="",NOT(ISNUMBER($H$2))),"",SUMIFS(数据录入!$G$5:$G$785,数据录入!$C$5:$C$785,$A11,数据录入!$B$5:$B$785,AZ$6)) -> 0 | BA11: =IF(OR($A11="",BA$6="",NOT(ISNUMBER($H$2))),"",SUMIFS(数据录入!$F$5:$F$785,数据录入!$C$5:$C$785,$A11,数据录入!$B$5:$B$785,BA$6)) -> 0 | BB11: =IF(OR($A11="",BB$6="",NOT(ISNUMBER($H$2))),"",SUMIFS(数据录入!$G$5:$G$785,数据录入!$C$5:$C$785,$A11,数据录入!$B$5:$B$785,BB$6)) -> 0 | BC11: =IF(OR($A11="",BC$6="",NOT(ISNUMBER($H$2))),"",SUMIFS(数据录入!$F$5:$F$785,数据录入!$C$5:$C$785,$A11,数据录入!$B$5:$B$785,BC$6)) -> 450 | BD11: =IF(OR($A11="",BD$6="",NOT(ISNUMBER($H$2))),"",SUMIFS(数据录入!$G$5:$G$785,数据录入!$C$5:$C$785,$A11,数据录入!$B$5:$B$785,BD$6)) -> 550000 | BE11: =IF(OR($A11="",BE$6="",NOT(ISNUMBER($H$2))),"",SUMIFS(数据录入!$F$5:$F$785,数据录入!$C$5:$C$785,$A11,数据录入!$B$5:$B$785,BE$6)) -> 552100 | BF11: =IF(OR($A11="",BF$6="",NOT(ISNUMBER($H$2))),"",SUMIFS(数据录入!$G$5:$G$785,数据录入!$C$5:$C$785,$A11,数据录入!$B$5:$B$785,BF$6)) -> 160000 | BG11: =IF(OR($A11="",BG$6="",NOT(ISNUMBER($H$2))),"",SUMIFS(数据录入!$F$5:$F$785,数据录入!$C$5:$C$785,$A11,数据录入!$B$5:$B$785,BG$6)) -> 18000 | BH11: =IF(OR($A11="",BH$6="",NOT(ISNUMBER($H$2))),"",SUMIFS(数据录入!$G$5:$G$785,数据录入!$C$5:$C$785,$A11,数据录入!$B$5:$B$785,BH$6)) -> 755858 | BI11: =IF(OR($A11="",BI$6="",NOT(ISNUMBER($H$2))),"",SUMIFS(数据录入!$F$5:$F$785,数据录入!$C$5:$C$785,$A11,数据录入!$B$5:$B$785,BI$6)) -> 0 | BJ11: =IF(OR($A11="",BJ$6="",NOT(ISNUMBER($H$2))),"",SUMIFS(数据录入!$G$5:$G$785,数据录入!$C$5:$C$785,$A11,数据录入!$B$5:$B$785,BJ$6)) -> 200000 | BK11: =IF(OR($A11="",BK$6="",NOT(ISNUMBER($H$2))),"",SUMIFS(数据录入!$F$5:$F$785,数据录入!$C$5:$C$785,$A11,数据录入!$B$5:$B$785,BK$6)) | BL11: =IF(OR($A11="",BL$6="",NOT(ISNUMBER($H$2))),"",SUMIFS(数据录入!$G$5:$G$785,数据录入!$C$5:$C$785,$A11,数据录入!$B$5:$B$785,BL$6)) | BM11: =IF($A11="","",SUMIF($C$7:$BL$7,"收款",C11:BL11)) -> 2558701.7 | BN11: =IF($A11="","",SUMIF($C$7:$BL$7,"付款",C11:BL11)) -> 2587544.4 | BO11: =IF($A11="","",B11+BM11-BN11) -> 61183.62
A12: 吴姐民生 | B12: =IF(OR($A12="",NOT(ISNUMBER($H$2))),"",SUMIFS(数据录入!$H$5:$H$785,数据录入!$C$5:$C$785,$A12,数据录入!$E$5:$E$785,"期初余额",数据录入!$B$5:$B$785,"<="&$B$2)+SUMIFS(数据录入!$F$5:$F$785,数据录入!$C$5:$C$785,$A12,数据录入!$B$5:$B$785,"<"&$B$2)-SUMIFS(数据录入!$G$5:$G$785,数据录入!$C$5:$C$785,$A12,数据录入!$B$5:$B$785,"<"&$B$2)) -> 15829.44 | C12: =IF(OR($A12="",C$6="",NOT(ISNUMBER($H$2))),"",SUMIFS(数据录入!$F$5:$F$785,数据录入!$C$5:$C$785,$A12,数据录入!$B$5:$B$785,C$6)) -> 0 | D12: =IF(OR($A12="",D$6="",NOT(ISNUMBER($H$2))),"",SUMIFS(数据录入!$G$5:$G$785,数据录入!$C$5:$C$785,$A12,数据录入!$B$5:$B$785,D$6)) -> 0 | E12: =IF(OR($A12="",E$6="",NOT(ISNUMBER($H$2))),"",SUMIFS(数据录入!$F$5:$F$785,数据录入!$C$5:$C$785,$A12,数据录入!$B$5:$B$785,E$6)) -> 5400 | F12: =IF(OR($A12="",F$6="",NOT(ISNUMBER($H$2))),"",SUMIFS(数据录入!$G$5:$G$785,数据录入!$C$5:$C$785,$A12,数据录入!$B$5:$B$785,F$6)) -> 0 | G12: =IF(OR($A12="",G$6="",NOT(ISNUMBER($H$2))),"",SUMIFS(数据录入!$F$5:$F$785,数据录入!$C$5:$C$785,$A12,数据录入!$B$5:$B$785,G$6)) -> 0 | H12: =IF(OR($A12="",H$6="",NOT(ISNUMBER($H$2))),"",SUMIFS(数据录入!$G$5:$G$785,数据录入!$C$5:$C$785,$A12,数据录入!$B$5:$B$785,H$6)) -> 0 | I12: =IF(OR($A12="",I$6="",NOT(ISNUMBER($H$2))),"",SUMIFS(数据录入!$F$5:$F$785,数据录入!$C$5:$C$785,$A12,数据录入!$B$5:$B$785,I$6)) -> 0 | J12: =IF(OR($A12="",J$6="",NOT(ISNUMBER($H$2))),"",SUMIFS(数据录入!$G$5:$G$785,数据录入!$C$5:$C$785,$A12,数据录入!$B$5:$B$785,J$6)) -> 0 | K12: =IF(OR($A12="",K$6="",NOT(ISNUMBER($H$2))),"",SUMIFS(数据录入!$F$5:$F$785,数据录入!$C$5:$C$785,$A12,数据录入!$B$5:$B$785,K$6)) -> 0 | L12: =IF(OR($A12="",L$6="",NOT(ISNUMBER($H$2))),"",SUMIFS(数据录入!$G$5:$G$785,数据录入!$C$5:$C$785,$A12,数据录入!$B$5:$B$785,L$6)) -> 0 | M12: =IF(OR($A12="",M$6="",NOT(ISNUMBER($H$2))),"",SUMIFS(数据录入!$F$5:$F$785,数据录入!$C$5:$C$785,$A12,数据录入!$B$5:$B$785,M$6)) -> 875 | N12: =IF(OR($A12="",N$6="",NOT(ISNUMBER($H$2))),"",SUMIFS(数据录入!$G$5:$G$785,数据录入!$C$5:$C$785,$A12,数据录入!$B$5:$B$785,N$6)) -> 0 | O12: =IF(OR($A12="",O$6="",NOT(ISNUMBER($H$2))),"",SUMIFS(数据录入!$F$5:$F$785,数据录入!$C$5:$C$785,$A12,数据录入!$B$5:$B$785,O$6)) -> 0 | P12: =IF(OR($A12="",P$6="",NOT(ISNUMBER($H$2))),"",SUMIFS(数据录入!$G$5:$G$785,数据录入!$C$5:$C$785,$A12,数据录入!$B$5:$B$785,P$6)) -> 0 | Q12: =IF(OR($A12="",Q$6="",NOT(ISNUMBER($H$2))),"",SUMIFS(数据录入!$F$5:$F$785,数据录入!$C$5:$C$785,$A12,数据录入!$B$5:$B$785,Q$6)) -> 0 | R12: =IF(OR($A12="",R$6="",NOT(ISNUMBER($H$2))),"",SUMIFS(数据录入!$G$5:$G$785,数据录入!$C$5:$C$785,$A12,数据录入!$B$5:$B$785,R$6)) -> 0 | S12: =IF(OR($A12="",S$6="",NOT(ISNUMBER($H$2))),"",SUMIFS(数据录入!$F$5:$F$785,数据录入!$C$5:$C$785,$A12,数据录入!$B$5:$B$785,S$6)) -> 0 | T12: =IF(OR($A12="",T$6="",NOT(ISNUMBER($H$2))),"",SUMIFS(数据录入!$G$5:$G$785,数据录入!$C$5:$C$785,$A12,数据录入!$B$5:$B$785,T$6)) -> 0 | U12: =IF(OR($A12="",U$6="",NOT(ISNUMBER($H$2))),"",SUMIFS(数据录入!$F$5:$F$785,数据录入!$C$5:$C$785,$A12,数据录入!$B$5:$B$785,U$6)) -> 0 | V12: =IF(OR($A12="",V$6="",NOT(ISNUMBER($H$2))),"",SUMIFS(数据录入!$G$5:$G$785,数据录入!$C$5:$C$785,$A12,数据录入!$B$5:$B$785,V$6)) -> 0 | W12: =IF(OR($A12="",W$6="",NOT(ISNUMBER($H$2))),"",SUMIFS(数据录入!$F$5:$F$785,数据录入!$C$5:$C$785,$A12,数据录入!$B$5:$B$785,W$6)) -> 0 | X12: =IF(OR($A12="",X$6="",NOT(ISNUMBER($H$2))),"",SUMIFS(数据录入!$G$5:$G$785,数据录入!$C$5:$C$785,$A12,数据录入!$B$5:$B$785,X$6)) -> 0 | Y12: =IF(OR($A12="",Y$6="",NOT(ISNUMBER($H$2))),"",SUMIFS(数据录入!$F$5:$F$785,数据录入!$C$5:$C$785,$A12,数据录入!$B$5:$B$785,Y$6)) -> 0 | Z12: =IF(OR($A12="",Z$6="",NOT(ISNUMBER($H$2))),"",SUMIFS(数据录入!$G$5:$G$785,数据录入!$C$5:$C$785,$A12,数据录入!$B$5:$B$785,Z$6)) -> 0 | AA12: =IF(OR($A12="",AA$6="",NOT(ISNUMBER($H$2))),"",SUMIFS(数据录入!$F$5:$F$785,数据录入!$C$5:$C$785,$A12,数据录入!$B$5:$B$785,AA$6)) -> 0 | AB12: =IF(OR($A12="",AB$6="",NOT(ISNUMBER($H$2))),"",SUMIFS(数据录入!$G$5:$G$785,数据录入!$C$5:$C$785,$A12,数据录入!$B$5:$B$785,AB$6)) -> 0 | AC12: =IF(OR($A12="",AC$6="",NOT(ISNUMBER($H$2))),"",SUMIFS(数据录入!$F$5:$F$785,数据录入!$C$5:$C$785,$A12,数据录入!$B$5:$B$785,AC$6)) -> 0 | AD12: =IF(OR($A12="",AD$6="",NOT(ISNUMBER($H$2))),"",SUMIFS(数据录入!$G$5:$G$785,数据录入!$C$5:$C$785,$A12,数据录入!$B$5:$B$785,AD$6)) -> 0 | AE12: =IF(OR($A12="",AE$6="",NOT(ISNUMBER($H$2))),"",SUMIFS(数据录入!$F$5:$F$785,数据录入!$C$5:$C$785,$A12,数据录入!$B$5:$B$785,AE$6)) -> 2500 | AF12: =IF(OR($A12="",AF$6="",NOT(ISNUMBER($H$2))),"",SUMIFS(数据录入!$G$5:$G$785,数据录入!$C$5:$C$785,$A12,数据录入!$B$5:$B$785,AF$6)) -> 0 | AG12: =IF(OR($A12="",AG$6="",NOT(ISNUMBER($H$2))),"",SUMIFS(数据录入!$F$5:$F$785,数据录入!$C$5:$C$785,$A12,数据录入!$B$5:$B$785,AG$6)) -> 0 | AH12: =IF(OR($A12="",AH$6="",NOT(ISNUMBER($H$2))),"",SUMIFS(数据录入!$G$5:$G$785,数据录入!$C$5:$C$785,$A12,数据录入!$B$5:$B$785,AH$6)) -> 0 | AI12: =IF(OR($A12="",AI$6="",NOT(ISNUMBER($H$2))),"",SUMIFS(数据录入!$F$5:$F$785,数据录入!$C$5:$C$785,$A12,数据录入!$B$5:$B$785,AI$6)) -> 800 | AJ12: =IF(OR($A12="",AJ$6="",NOT(ISNUMBER($H$2))),"",SUMIFS(数据录入!$G$5:$G$785,数据录入!$C$5:$C$785,$A12,数据录入!$B$5:$B$785,AJ$6)) -> 0 | AK12: =IF(OR($A12="",AK$6="",NOT(ISNUMBER($H$2))),"",SUMIFS(数据录入!$F$5:$F$785,数据录入!$C$5:$C$785,$A12,数据录入!$B$5:$B$785,AK$6)) -> 0 | AL12: =IF(OR($A12="",AL$6="",NOT(ISNUMBER($H$2))),"",SUMIFS(数据录入!$G$5:$G$785,数据录入!$C$5:$C$785,$A12,数据录入!$B$5:$B$785,AL$6)) -> 0 | AM12: =IF(OR($A12="",AM$6="",NOT(ISNUMBER($H$2))),"",SUMIFS(数据录入!$F$5:$F$785,数据录入!$C$5:$C$785,$A12,数据录入!$B$5:$B$785,AM$6)) -> 0 | AN12: =IF(OR($A12="",AN$6="",NOT(ISNUMBER($H$2))),"",SUMIFS(数据录入!$G$5:$G$785,数据录入!$C$5:$C$785,$A12,数据录入!$B$5:$B$785,AN$6)) -> 0 | AO12: =IF(OR($A12="",AO$6="",NOT(ISNUMBER($H$2))),"",SUMIFS(数据录入!$F$5:$F$785,数据录入!$C$5:$C$785,$A12,数据录入!$B$5:$B$785,AO$6)) -> 1010 | AP12: =IF(OR($A12="",AP$6="",NOT(ISNUMBER($H$2))),"",SUMIFS(数据录入!$G$5:$G$785,数据录入!$C$5:$C$785,$A12,数据录入!$B$5:$B$785,AP$6)) -> 0 | AQ12: =IF(OR($A12="",AQ$6="",NOT(ISNUMBER($H$2))),"",SUMIFS(数据录入!$F$5:$F$785,数据录入!$C$5:$C$785,$A12,数据录入!$B$5:$B$785,AQ$6)) -> 8500 | AR12: =IF(OR($A12="",AR$6="",NOT(ISNUMBER($H$2))),"",SUMIFS(数据录入!$G$5:$G$785,数据录入!$C$5:$C$785,$A12,数据录入!$B$5:$B$785,AR$6)) -> 0 | AS12: =IF(OR($A12="",AS$6="",NOT(ISNUMBER($H$2))),"",SUMIFS(数据录入!$F$5:$F$785,数据录入!$C$5:$C$785,$A12,数据录入!$B$5:$B$785,AS$6)) -> 0 | AT12: =IF(OR($A12="",AT$6="",NOT(ISNUMBER($H$2))),"",SUMIFS(数据录入!$G$5:$G$785,数据录入!$C$5:$C$785,$A12,数据录入!$B$5:$B$785,AT$6)) -> 0 | AU12: =IF(OR($A12="",AU$6="",NOT(ISNUMBER($H$2))),"",SUMIFS(数据录入!$F$5:$F$785,数据录入!$C$5:$C$785,$A12,数据录入!$B$5:$B$785,AU$6)) -> 0 | AV12: =IF(OR($A12="",AV$6="",NOT(ISNUMBER($H$2))),"",SUMIFS(数据录入!$G$5:$G$785,数据录入!$C$5:$C$785,$A12,数据录入!$B$5:$B$785,AV$6)) -> 0 | AW12: =IF(OR($A12="",AW$6="",NOT(ISNUMBER($H$2))),"",SUMIFS(数据录入!$F$5:$F$785,数据录入!$C$5:$C$785,$A12,数据录入!$B$5:$B$785,AW$6)) -> 0 | AX12: =IF(OR($A12="",AX$6="",NOT(ISNUMBER($H$2))),"",SUMIFS(数据录入!$G$5:$G$785,数据录入!$C$5:$C$785,$A12,数据录入!$B$5:$B$785,AX$6)) -> 0 | AY12: =IF(OR($A12="",AY$6="",NOT(ISNUMBER($H$2))),"",SUMIFS(数据录入!$F$5:$F$785,数据录入!$C$5:$C$785,$A12,数据录入!$B$5:$B$785,AY$6)) -> 0 | AZ12: =IF(OR($A12="",AZ$6="",NOT(ISNUMBER($H$2))),"",SUMIFS(数据录入!$G$5:$G$785,数据录入!$C$5:$C$785,$A12,数据录入!$B$5:$B$785,AZ$6)) -> 0 | BA12: =IF(OR($A12="",BA$6="",NOT(ISNUMBER($H$2))),"",SUMIFS(数据录入!$F$5:$F$785,数据录入!$C$5:$C$785,$A12,数据录入!$B$5:$B$785,BA$6)) -> 0 | BB12: =IF(OR($A12="",BB$6="",NOT(ISNUMBER($H$2))),"",SUMIFS(数据录入!$G$5:$G$785,数据录入!$C$5:$C$785,$A12,数据录入!$B$5:$B$785,BB$6)) -> 0 | BC12: =IF(OR($A12="",BC$6="",NOT(ISNUMBER($H$2))),"",SUMIFS(数据录入!$F$5:$F$785,数据录入!$C$5:$C$785,$A12,数据录入!$B$5:$B$785,BC$6)) -> 0 | BD12: =IF(OR($A12="",BD$6="",NOT(ISNUMBER($H$2))),"",SUMIFS(数据录入!$G$5:$G$785,数据录入!$C$5:$C$785,$A12,数据录入!$B$5:$B$785,BD$6)) -> 0 | BE12: =IF(OR($A12="",BE$6="",NOT(ISNUMBER($H$2))),"",SUMIFS(数据录入!$F$5:$F$785,数据录入!$C$5:$C$785,$A12,数据录入!$B$5:$B$785,BE$6)) -> 0 | BF12: =IF(OR($A12="",BF$6="",NOT(ISNUMBER($H$2))),"",SUMIFS(数据录入!$G$5:$G$785,数据录入!$C$5:$C$785,$A12,数据录入!$B$5:$B$785,BF$6)) -> 0 | BG12: =IF(OR($A12="",BG$6="",NOT(ISNUMBER($H$2))),"",SUMIFS(数据录入!$F$5:$F$785,数据录入!$C$5:$C$785,$A12,数据录入!$B$5:$B$785,BG$6)) -> 0 | BH12: =IF(OR($A12="",BH$6="",NOT(ISNUMBER($H$2))),"",SUMIFS(数据录入!$G$5:$G$785,数据录入!$C$5:$C$785,$A12,数据录入!$B$5:$B$785,BH$6)) -> 0 | BI12: =IF(OR($A12="",BI$6="",NOT(ISNUMBER($H$2))),"",SUMIFS(数据录入!$F$5:$F$785,数据录入!$C$5:$C$785,$A12,数据录入!$B$5:$B$785,BI$6)) -> 0 | BJ12: =IF(OR($A12="",BJ$6="",NOT(ISNUMBER($H$2))),"",SUMIFS(数据录入!$G$5:$G$785,数据录入!$C$5:$C$785,$A12,数据录入!$B$5:$B$785,BJ$6)) -> 0 | BK12: =IF(OR($A12="",BK$6="",NOT(ISNUMBER($H$2))),"",SUMIFS(数据录入!$F$5:$F$785,数据录入!$C$5:$C$785,$A12,数据录入!$B$5:$B$785,BK$6)) | BL12: =IF(OR($A12="",BL$6="",NOT(ISNUMBER($H$2))),"",SUMIFS(数据录入!$G$5:$G$785,数据录入!$C$5:$C$785,$A12,数据录入!$B$5:$B$785,BL$6)) | BM12: =IF($A12="","",SUMIF($C$7:$BL$7,"收款",C12:BL12)) -> 19085 | BN12: =IF($A12="","",SUMIF($C$7:$BL$7,"付款",C12:BL12)) -> 0 | BO12: =IF($A12="","",B12+BM12-BN12) -> 34914.44
A13: 吴建忠浦发 | B13: =IF(OR($A13="",NOT(ISNUMBER($H$2))),"",SUMIFS(数据录入!$H$5:$H$785,数据录入!$C$5:$C$785,$A13,数据录入!$E$5:$E$785,"期初余额",数据录入!$B$5:$B$785,"<="&$B$2)+SUMIFS(数据录入!$F$5:$F$785,数据录入!$C$5:$C$785,$A13,数据录入!$B$5:$B$785,"<"&$B$2)-SUMIFS(数据录入!$G$5:$G$785,数据录入!$C$5:$C$785,$A13,数据录入!$B$5:$B$785,"<"&$B$2)) -> 208922.52 | C13: =IF(OR($A13="",C$6="",NOT(ISNUMBER($H$2))),"",SUMIFS(数据录入!$F$5:$F$785,数据录入!$C$5:$C$785,$A13,数据录入!$B$5:$B$785,C$6)) -> 1000000 | D13: =IF(OR($A13="",D$6="",NOT(ISNUMBER($H$2))),"",SUMIFS(数据录入!$G$5:$G$785,数据录入!$C$5:$C$785,$A13,数据录入!$B$5:$B$785,D$6)) -> 1200000 | E13: =IF(OR($A13="",E$6="",NOT(ISNUMBER($H$2))),"",SUMIFS(数据录入!$F$5:$F$785,数据录入!$C$5:$C$785,$A13,数据录入!$B$5:$B$785,E$6)) -> 500000 | F13: =IF(OR($A13="",F$6="",NOT(ISNUMBER($H$2))),"",SUMIFS(数据录入!$G$5:$G$785,数据录入!$C$5:$C$785,$A13,数据录入!$B$5:$B$785,F$6)) -> 500000 | G13: =IF(OR($A13="",G$6="",NOT(ISNUMBER($H$2))),"",SUMIFS(数据录入!$F$5:$F$785,数据录入!$C$5:$C$785,$A13,数据录入!$B$5:$B$785,G$6)) -> 300000 | H13: =IF(OR($A13="",H$6="",NOT(ISNUMBER($H$2))),"",SUMIFS(数据录入!$G$5:$G$785,数据录入!$C$5:$C$785,$A13,数据录入!$B$5:$B$785,H$6)) -> 0 | I13: =IF(OR($A13="",I$6="",NOT(ISNUMBER($H$2))),"",SUMIFS(数据录入!$F$5:$F$785,数据录入!$C$5:$C$785,$A13,数据录入!$B$5:$B$785,I$6)) -> 100000 | J13: =IF(OR($A13="",J$6="",NOT(ISNUMBER($H$2))),"",SUMIFS(数据录入!$G$5:$G$785,数据录入!$C$5:$C$785,$A13,数据录入!$B$5:$B$785,J$6)) -> 0 | K13: =IF(OR($A13="",K$6="",NOT(ISNUMBER($H$2))),"",SUMIFS(数据录入!$F$5:$F$785,数据录入!$C$5:$C$785,$A13,数据录入!$B$5:$B$785,K$6)) -> 0 | L13: =IF(OR($A13="",L$6="",NOT(ISNUMBER($H$2))),"",SUMIFS(数据录入!$G$5:$G$785,数据录入!$C$5:$C$785,$A13,数据录入!$B$5:$B$785,L$6)) -> 0 | M13: =IF(OR($A13="",M$6="",NOT(ISNUMBER($H$2))),"",SUMIFS(数据录入!$F$5:$F$785,数据录入!$C$5:$C$785,$A13,数据录入!$B$5:$B$785,M$6)) -> 207133.33 | N13: =IF(OR($A13="",N$6="",NOT(ISNUMBER($H$2))),"",SUMIFS(数据录入!$G$5:$G$785,数据录入!$C$5:$C$785,$A13,数据录入!$B$5:$B$785,N$6)) -> 324500 | O13: =IF(OR($A13="",O$6="",NOT(ISNUMBER($H$2))),"",SUMIFS(数据录入!$F$5:$F$785,数据录入!$C$5:$C$785,$A13,数据录入!$B$5:$B$785,O$6)) -> 0 | P13: =IF(OR($A13="",P$6="",NOT(ISNUMBER($H$2))),"",SUMIFS(数据录入!$G$5:$G$785,数据录入!$C$5:$C$785,$A13,数据录入!$B$5:$B$785,P$6)) -> 72800 | Q13: =IF(OR($A13="",Q$6="",NOT(ISNUMBER($H$2))),"",SUMIFS(数据录入!$F$5:$F$785,数据录入!$C$5:$C$785,$A13,数据录入!$B$5:$B$785,Q$6)) -> 999950 | R13: =IF(OR($A13="",R$6="",NOT(ISNUMBER($H$2))),"",SUMIFS(数据录入!$G$5:$G$785,数据录入!$C$5:$C$785,$A13,数据录入!$B$5:$B$785,R$6)) -> 995410 | S13: =IF(OR($A13="",S$6="",NOT(ISNUMBER($H$2))),"",SUMIFS(数据录入!$F$5:$F$785,数据录入!$C$5:$C$785,$A13,数据录入!$B$5:$B$785,S$6)) -> 30000 | T13: =IF(OR($A13="",T$6="",NOT(ISNUMBER($H$2))),"",SUMIFS(数据录入!$G$5:$G$785,数据录入!$C$5:$C$785,$A13,数据录入!$B$5:$B$785,T$6)) -> 0 | U13: =IF(OR($A13="",U$6="",NOT(ISNUMBER($H$2))),"",SUMIFS(数据录入!$F$5:$F$785,数据录入!$C$5:$C$785,$A13,数据录入!$B$5:$B$785,U$6)) -> 0 | V13: =IF(OR($A13="",V$6="",NOT(ISNUMBER($H$2))),"",SUMIFS(数据录入!$G$5:$G$785,数据录入!$C$5:$C$785,$A13,数据录入!$B$5:$B$785,V$6)) -> 30000 | W13: =IF(OR($A13="",W$6="",NOT(ISNUMBER($H$2))),"",SUMIFS(数据录入!$F$5:$F$785,数据录入!$C$5:$C$785,$A13,数据录入!$B$5:$B$785,W$6)) -> 0 | X13: =IF(OR($A13="",X$6="",NOT(ISNUMBER($H$2))),"",SUMIFS(数据录入!$G$5:$G$785,数据录入!$C$5:$C$785,$A13,数据录入!$B$5:$B$785,X$6)) -> 0 | Y13: =IF(OR($A13="",Y$6="",NOT(ISNUMBER($H$2))),"",SUMIFS(数据录入!$F$5:$F$785,数据录入!$C$5:$C$785,$A13,数据录入!$B$5:$B$785,Y$6)) -> 0 | Z13: =IF(OR($A13="",Z$6="",NOT(ISNUMBER($H$2))),"",SUMIFS(数据录入!$G$5:$G$785,数据录入!$C$5:$C$785,$A13,数据录入!$B$5:$B$785,Z$6)) -> 0 | AA13: =IF(OR($A13="",AA$6="",NOT(ISNUMBER($H$2))),"",SUMIFS(数据录入!$F$5:$F$785,数据录入!$C$5:$C$785,$A13,数据录入!$B$5:$B$785,AA$6)) -> 0 | AB13: =IF(OR($A13="",AB$6="",NOT(ISNUMBER($H$2))),"",SUMIFS(数据录入!$G$5:$G$785,数据录入!$C$5:$C$785,$A13,数据录入!$B$5:$B$785,AB$6)) -> 0 | AC13: =IF(OR($A13="",AC$6="",NOT(ISNUMBER($H$2))),"",SUMIFS(数据录入!$F$5:$F$785,数据录入!$C$5:$C$785,$A13,数据录入!$B$5:$B$785,AC$6)) -> 0 | AD13: =IF(OR($A13="",AD$6="",NOT(ISNUMBER($H$2))),"",SUMIFS(数据录入!$G$5:$G$785,数据录入!$C$5:$C$785,$A13,数据录入!$B$5:$B$785,AD$6)) -> 0 | AE13: =IF(OR($A13="",AE$6="",NOT(ISNUMBER($H$2))),"",SUMIFS(数据录入!$F$5:$F$785,数据录入!$C$5:$C$785,$A13,数据录入!$B$5:$B$785,AE$6)) -> 8875 | AF13: =IF(OR($A13="",AF$6="",NOT(ISNUMBER($H$2))),"",SUMIFS(数据录入!$G$5:$G$785,数据录入!$C$5:$C$785,$A13,数据录入!$B$5:$B$785,AF$6)) -> 53750 | AG13: =IF(OR($A13="",AG$6="",NOT(ISNUMBER($H$2))),"",SUMIFS(数据录入!$F$5:$F$785,数据录入!$C$5:$C$785,$A13,数据录入!$B$5:$B$785,AG$6)) -> 337200 | AH13: =IF(OR($A13="",AH$6="",NOT(ISNUMBER($H$2))),"",SUMIFS(数据录入!$G$5:$G$785,数据录入!$C$5:$C$785,$A13,数据录入!$B$5:$B$785,AH$6)) -> 279950 | AI13: =IF(OR($A13="",AI$6="",NOT(ISNUMBER($H$2))),"",SUMIFS(数据录入!$F$5:$F$785,数据录入!$C$5:$C$785,$A13,数据录入!$B$5:$B$785,AI$6)) -> 0 | AJ13: =IF(OR($A13="",AJ$6="",NOT(ISNUMBER($H$2))),"",SUMIFS(数据录入!$G$5:$G$785,数据录入!$C$5:$C$785,$A13,数据录入!$B$5:$B$785,AJ$6)) -> 7200 | AK13: =IF(OR($A13="",AK$6="",NOT(ISNUMBER($H$2))),"",SUMIFS(数据录入!$F$5:$F$785,数据录入!$C$5:$C$785,$A13,数据录入!$B$5:$B$785,AK$6)) -> 0 | AL13: =IF(OR($A13="",AL$6="",NOT(ISNUMBER($H$2))),"",SUMIFS(数据录入!$G$5:$G$785,数据录入!$C$5:$C$785,$A13,数据录入!$B$5:$B$785,AL$6)) -> 0 | AM13: =IF(OR($A13="",AM$6="",NOT(ISNUMBER($H$2))),"",SUMIFS(数据录入!$F$5:$F$785,数据录入!$C$5:$C$785,$A13,数据录入!$B$5:$B$785,AM$6)) -> 0 | AN13: =IF(OR($A13="",AN$6="",NOT(ISNUMBER($H$2))),"",SUMIFS(数据录入!$G$5:$G$785,数据录入!$C$5:$C$785,$A13,数据录入!$B$5:$B$785,AN$6)) -> 0 | AO13: =IF(OR($A13="",AO$6="",NOT(ISNUMBER($H$2))),"",SUMIFS(数据录入!$F$5:$F$785,数据录入!$C$5:$C$785,$A13,数据录入!$B$5:$B$785,AO$6)) -> 14400 | AP13: =IF(OR($A13="",AP$6="",NOT(ISNUMBER($H$2))),"",SUMIFS(数据录入!$G$5:$G$785,数据录入!$C$5:$C$785,$A13,数据录入!$B$5:$B$785,AP$6)) -> 200000 | AQ13: =IF(OR($A13="",AQ$6="",NOT(ISNUMBER($H$2))),"",SUMIFS(数据录入!$F$5:$F$785,数据录入!$C$5:$C$785,$A13,数据录入!$B$5:$B$785,AQ$6)) -> 0 | AR13: =IF(OR($A13="",AR$6="",NOT(ISNUMBER($H$2))),"",SUMIFS(数据录入!$G$5:$G$785,数据录入!$C$5:$C$785,$A13,数据录入!$B$5:$B$785,AR$6)) -> 0 | AS13: =IF(OR($A13="",AS$6="",NOT(ISNUMBER($H$2))),"",SUMIFS(数据录入!$F$5:$F$785,数据录入!$C$5:$C$785,$A13,数据录入!$B$5:$B$785,AS$6)) -> 365650 | AT13: =IF(OR($A13="",AT$6="",NOT(ISNUMBER($H$2))),"",SUMIFS(数据录入!$G$5:$G$785,数据录入!$C$5:$C$785,$A13,数据录入!$B$5:$B$785,AT$6)) -> 12000 | AU13: =IF(OR($A13="",AU$6="",NOT(ISNUMBER($H$2))),"",SUMIFS(数据录入!$F$5:$F$785,数据录入!$C$5:$C$785,$A13,数据录入!$B$5:$B$785,AU$6)) -> 0 | AV13: =IF(OR($A13="",AV$6="",NOT(ISNUMBER($H$2))),"",SUMIFS(数据录入!$G$5:$G$785,数据录入!$C$5:$C$785,$A13,数据录入!$B$5:$B$785,AV$6)) -> 164954 | AW13: =IF(OR($A13="",AW$6="",NOT(ISNUMBER($H$2))),"",SUMIFS(数据录入!$F$5:$F$785,数据录入!$C$5:$C$785,$A13,数据录入!$B$5:$B$785,AW$6)) -> 0 | AX13: =IF(OR($A13="",AX$6="",NOT(ISNUMBER($H$2))),"",SUMIFS(数据录入!$G$5:$G$785,数据录入!$C$5:$C$785,$A13,数据录入!$B$5:$B$785,AX$6)) -> 0 | AY13: =IF(OR($A13="",AY$6="",NOT(ISNUMBER($H$2))),"",SUMIFS(数据录入!$F$5:$F$785,数据录入!$C$5:$C$785,$A13,数据录入!$B$5:$B$785,AY$6)) -> 0 | AZ13: =IF(OR($A13="",AZ$6="",NOT(ISNUMBER($H$2))),"",SUMIFS(数据录入!$G$5:$G$785,数据录入!$C$5:$C$785,$A13,数据录入!$B$5:$B$785,AZ$6)) -> 0 | BA13: =IF(OR($A13="",BA$6="",NOT(ISNUMBER($H$2))),"",SUMIFS(数据录入!$F$5:$F$785,数据录入!$C$5:$C$785,$A13,数据录入!$B$5:$B$785,BA$6)) -> 0 | BB13: =IF(OR($A13="",BB$6="",NOT(ISNUMBER($H$2))),"",SUMIFS(数据录入!$G$5:$G$785,数据录入!$C$5:$C$785,$A13,数据录入!$B$5:$B$785,BB$6)) -> 0 | BC13: =IF(OR($A13="",BC$6="",NOT(ISNUMBER($H$2))),"",SUMIFS(数据录入!$F$5:$F$785,数据录入!$C$5:$C$785,$A13,数据录入!$B$5:$B$785,BC$6)) -> 4500 | BD13: =IF(OR($A13="",BD$6="",NOT(ISNUMBER($H$2))),"",SUMIFS(数据录入!$G$5:$G$785,数据录入!$C$5:$C$785,$A13,数据录入!$B$5:$B$785,BD$6)) -> 0 | BE13: =IF(OR($A13="",BE$6="",NOT(ISNUMBER($H$2))),"",SUMIFS(数据录入!$F$5:$F$785,数据录入!$C$5:$C$785,$A13,数据录入!$B$5:$B$785,BE$6)) -> 170250 | BF13: =IF(OR($A13="",BF$6="",NOT(ISNUMBER($H$2))),"",SUMIFS(数据录入!$G$5:$G$785,数据录入!$C$5:$C$785,$A13,数据录入!$B$5:$B$785,BF$6)) -> 10000 | BG13: =IF(OR($A13="",BG$6="",NOT(ISNUMBER($H$2))),"",SUMIFS(数据录入!$F$5:$F$785,数据录入!$C$5:$C$785,$A13,数据录入!$B$5:$B$785,BG$6)) -> 0 | BH13: =IF(OR($A13="",BH$6="",NOT(ISNUMBER($H$2))),"",SUMIFS(数据录入!$G$5:$G$785,数据录入!$C$5:$C$785,$A13,数据录入!$B$5:$B$785,BH$6)) -> 0 | BI13: =IF(OR($A13="",BI$6="",NOT(ISNUMBER($H$2))),"",SUMIFS(数据录入!$F$5:$F$785,数据录入!$C$5:$C$785,$A13,数据录入!$B$5:$B$785,BI$6)) -> 0 | BJ13: =IF(OR($A13="",BJ$6="",NOT(ISNUMBER($H$2))),"",SUMIFS(数据录入!$G$5:$G$785,数据录入!$C$5:$C$785,$A13,数据录入!$B$5:$B$785,BJ$6)) -> 0 | BK13: =IF(OR($A13="",BK$6="",NOT(ISNUMBER($H$2))),"",SUMIFS(数据录入!$F$5:$F$785,数据录入!$C$5:$C$785,$A13,数据录入!$B$5:$B$785,BK$6)) | BL13: =IF(OR($A13="",BL$6="",NOT(ISNUMBER($H$2))),"",SUMIFS(数据录入!$G$5:$G$785,数据录入!$C$5:$C$785,$A13,数据录入!$B$5:$B$785,BL$6)) | BM13: =IF($A13="","",SUMIF($C$7:$BL$7,"收款",C13:BL13)) -> 4037958.3 | BN13: =IF($A13="","",SUMIF($C$7:$BL$7,"付款",C13:BL13)) -> 3850564 | BO13: =IF($A13="","",B13+BM13-BN13) -> 396316.85
A14: 吴姐兴业 | B14: =IF(OR($A14="",NOT(ISNUMBER($H$2))),"",SUMIFS(数据录入!$H$5:$H$785,数据录入!$C$5:$C$785,$A14,数据录入!$E$5:$E$785,"期初余额",数据录入!$B$5:$B$785,"<="&$B$2)+SUMIFS(数据录入!$F$5:$F$785,数据录入!$C$5:$C$785,$A14,数据录入!$B$5:$B$785,"<"&$B$2)-SUMIFS(数据录入!$G$5:$G$785,数据录入!$C$5:$C$785,$A14,数据录入!$B$5:$B$785,"<"&$B$2)) -> 0 | C14: =IF(OR($A14="",C$6="",NOT(ISNUMBER($H$2))),"",SUMIFS(数据录入!$F$5:$F$785,数据录入!$C$5:$C$785,$A14,数据录入!$B$5:$B$785,C$6)) -> 0 | D14: =IF(OR($A14="",D$6="",NOT(ISNUMBER($H$2))),"",SUMIFS(数据录入!$G$5:$G$785,数据录入!$C$5:$C$785,$A14,数据录入!$B$5:$B$785,D$6)) -> 0 | E14: =IF(OR($A14="",E$6="",NOT(ISNUMBER($H$2))),"",SUMIFS(数据录入!$F$5:$F$785,数据录入!$C$5:$C$785,$A14,数据录入!$B$5:$B$785,E$6)) -> 0 | F14: =IF(OR($A14="",F$6="",NOT(ISNUMBER($H$2))),"",SUMIFS(数据录入!$G$5:$G$785,数据录入!$C$5:$C$785,$A14,数据录入!$B$5:$B$785,F$6)) -> 0 | G14: =IF(OR($A14="",G$6="",NOT(ISNUMBER($H$2))),"",SUMIFS(数据录入!$F$5:$F$785,数据录入!$C$5:$C$785,$A14,数据录入!$B$5:$B$785,G$6)) -> 0 | H14: =IF(OR($A14="",H$6="",NOT(ISNUMBER($H$2))),"",SUMIFS(数据录入!$G$5:$G$785,数据录入!$C$5:$C$785,$A14,数据录入!$B$5:$B$785,H$6)) -> 0 | I14: =IF(OR($A14="",I$6="",NOT(ISNUMBER($H$2))),"",SUMIFS(数据录入!$F$5:$F$785,数据录入!$C$5:$C$785,$A14,数据录入!$B$5:$B$785,I$6)) -> 0 | J14: =IF(OR($A14="",J$6="",NOT(ISNUMBER($H$2))),"",SUMIFS(数据录入!$G$5:$G$785,数据录入!$C$5:$C$785,$A14,数据录入!$B$5:$B$785,J$6)) -> 0 | K14: =IF(OR($A14="",K$6="",NOT(ISNUMBER($H$2))),"",SUMIFS(数据录入!$F$5:$F$785,数据录入!$C$5:$C$785,$A14,数据录入!$B$5:$B$785,K$6)) -> 0 | L14: =IF(OR($A14="",L$6="",NOT(ISNUMBER($H$2))),"",SUMIFS(数据录入!$G$5:$G$785,数据录入!$C$5:$C$785,$A14,数据录入!$B$5:$B$785,L$6)) -> 0 | M14: =IF(OR($A14="",M$6="",NOT(ISNUMBER($H$2))),"",SUMIFS(数据录入!$F$5:$F$785,数据录入!$C$5:$C$785,$A14,数据录入!$B$5:$B$785,M$6)) -> 0 | N14: =IF(OR($A14="",N$6="",NOT(ISNUMBER($H$2))),"",SUMIFS(数据录入!$G$5:$G$785,数据录入!$C$5:$C$785,$A14,数据录入!$B$5:$B$785,N$6)) -> 0 | O14: =IF(OR($A14="",O$6="",NOT(ISNUMBER($H$2))),"",SUMIFS(数据录入!$F$5:$F$785,数据录入!$C$5:$C$785,$A14,数据录入!$B$5:$B$785,O$6)) -> 0 | P14: =IF(OR($A14="",P$6="",NOT(ISNUMBER($H$2))),"",SUMIFS(数据录入!$G$5:$G$785,数据录入!$C$5:$C$785,$A14,数据录入!$B$5:$B$785,P$6)) -> 0 | Q14: =IF(OR($A14="",Q$6="",NOT(ISNUMBER($H$2))),"",SUMIFS(数据录入!$F$5:$F$785,数据录入!$C$5:$C$785,$A14,数据录入!$B$5:$B$785,Q$6)) -> 0 | R14: =IF(OR($A14="",R$6="",NOT(ISNUMBER($H$2))),"",SUMIFS(数据录入!$G$5:$G$785,数据录入!$C$5:$C$785,$A14,数据录入!$B$5:$B$785,R$6)) -> 0 | S14: =IF(OR($A14="",S$6="",NOT(ISNUMBER($H$2))),"",SUMIFS(数据录入!$F$5:$F$785,数据录入!$C$5:$C$785,$A14,数据录入!$B$5:$B$785,S$6)) -> 0 | T14: =IF(OR($A14="",T$6="",NOT(ISNUMBER($H$2))),"",SUMIFS(数据录入!$G$5:$G$785,数据录入!$C$5:$C$785,$A14,数据录入!$B$5:$B$785,T$6)) -> 0 | U14: =IF(OR($A14="",U$6="",NOT(ISNUMBER($H$2))),"",SUMIFS(数据录入!$F$5:$F$785,数据录入!$C$5:$C$785,$A14,数据录入!$B$5:$B$785,U$6)) -> 0 | V14: =IF(OR($A14="",V$6="",NOT(ISNUMBER($H$2))),"",SUMIFS(数据录入!$G$5:$G$785,数据录入!$C$5:$C$785,$A14,数据录入!$B$5:$B$785,V$6)) -> 0 | W14: =IF(OR($A14="",W$6="",NOT(ISNUMBER($H$2))),"",SUMIFS(数据录入!$F$5:$F$785,数据录入!$C$5:$C$785,$A14,数据录入!$B$5:$B$785,W$6)) -> 0 | X14: =IF(OR($A14="",X$6="",NOT(ISNUMBER($H$2))),"",SUMIFS(数据录入!$G$5:$G$785,数据录入!$C$5:$C$785,$A14,数据录入!$B$5:$B$785,X$6)) -> 0 | Y14: =IF(OR($A14="",Y$6="",NOT(ISNUMBER($H$2))),"",SUMIFS(数据录入!$F$5:$F$785,数据录入!$C$5:$C$785,$A14,数据录入!$B$5:$B$785,Y$6)) -> 0 | Z14: =IF(OR($A14="",Z$6="",NOT(ISNUMBER($H$2))),"",SUMIFS(数据录入!$G$5:$G$785,数据录入!$C$5:$C$785,$A14,数据录入!$B$5:$B$785,Z$6)) -> 0 | AA14: =IF(OR($A14="",AA$6="",NOT(ISNUMBER($H$2))),"",SUMIFS(数据录入!$F$5:$F$785,数据录入!$C$5:$C$785,$A14,数据录入!$B$5:$B$785,AA$6)) -> 0 | AB14: =IF(OR($A14="",AB$6="",NOT(ISNUMBER($H$2))),"",SUMIFS(数据录入!$G$5:$G$785,数据录入!$C$5:$C$785,$A14,数据录入!$B$5:$B$785,AB$6)) -> 0 | AC14: =IF(OR($A14="",AC$6="",NOT(ISNUMBER($H$2))),"",SUMIFS(数据录入!$F$5:$F$785,数据录入!$C$5:$C$785,$A14,数据录入!$B$5:$B$785,AC$6)) -> 0 | AD14: =IF(OR($A14="",AD$6="",NOT(ISNUMBER($H$2))),"",SUMIFS(数据录入!$G$5:$G$785,数据录入!$C$5:$C$785,$A14,数据录入!$B$5:$B$785,AD$6)) -> 0 | AE14: =IF(OR($A14="",AE$6="",NOT(ISNUMBER($H$2))),"",SUMIFS(数据录入!$F$5:$F$785,数据录入!$C$5:$C$785,$A14,数据录入!$B$5:$B$785,AE$6)) -> 0 | AF14: =IF(OR($A14="",AF$6="",NOT(ISNUMBER($H$2))),"",SUMIFS(数据录入!$G$5:$G$785,数据录入!$C$5:$C$785,$A14,数据录入!$B$5:$B$785,AF$6)) -> 0 | AG14: =IF(OR($A14="",AG$6="",NOT(ISNUMBER($H$2))),"",SUMIFS(数据录入!$F$5:$F$785,数据录入!$C$5:$C$785,$A14,数据录入!$B$5:$B$785,AG$6)) -> 0 | AH14: =IF(OR($A14="",AH$6="",NOT(ISNUMBER($H$2))),"",SUMIFS(数据录入!$G$5:$G$785,数据录入!$C$5:$C$785,$A14,数据录入!$B$5:$B$785,AH$6)) -> 0 | AI14: =IF(OR($A14="",AI$6="",NOT(ISNUMBER($H$2))),"",SUMIFS(数据录入!$F$5:$F$785,数据录入!$C$5:$C$785,$A14,数据录入!$B$5:$B$785,AI$6)) -> 0 | AJ14: =IF(OR($A14="",AJ$6="",NOT(ISNUMBER($H$2))),"",SUMIFS(数据录入!$G$5:$G$785,数据录入!$C$5:$C$785,$A14,数据录入!$B$5:$B$785,AJ$6)) -> 0 | AK14: =IF(OR($A14="",AK$6="",NOT(ISNUMBER($H$2))),"",SUMIFS(数据录入!$F$5:$F$785,数据录入!$C$5:$C$785,$A14,数据录入!$B$5:$B$785,AK$6)) -> 0 | AL14: =IF(OR($A14="",AL$6="",NOT(ISNUMBER($H$2))),"",SUMIFS(数据录入!$G$5:$G$785,数据录入!$C$5:$C$785,$A14,数据录入!$B$5:$B$785,AL$6)) -> 0 | AM14: =IF(OR($A14="",AM$6="",NOT(ISNUMBER($H$2))),"",SUMIFS(数据录入!$F$5:$F$785,数据录入!$C$5:$C$785,$A14,数据录入!$B$5:$B$785,AM$6)) -> 0 | AN14: =IF(OR($A14="",AN$6="",NOT(ISNUMBER($H$2))),"",SUMIFS(数据录入!$G$5:$G$785,数据录入!$C$5:$C$785,$A14,数据录入!$B$5:$B$785,AN$6)) -> 0 | AO14: =IF(OR($A14="",AO$6="",NOT(ISNUMBER($H$2))),"",SUMIFS(数据录入!$F$5:$F$785,数据录入!$C$5:$C$785,$A14,数据录入!$B$5:$B$785,AO$6)) -> 0 | AP14: =IF(OR($A14="",AP$6="",NOT(ISNUMBER($H$2))),"",SUMIFS(数据录入!$G$5:$G$785,数据录入!$C$5:$C$785,$A14,数据录入!$B$5:$B$785,AP$6)) -> 0 | AQ14: =IF(OR($A14="",AQ$6="",NOT(ISNUMBER($H$2))),"",SUMIFS(数据录入!$F$5:$F$785,数据录入!$C$5:$C$785,$A14,数据录入!$B$5:$B$785,AQ$6)) -> 0 | AR14: =IF(OR($A14="",AR$6="",NOT(ISNUMBER($H$2))),"",SUMIFS(数据录入!$G$5:$G$785,数据录入!$C$5:$C$785,$A14,数据录入!$B$5:$B$785,AR$6)) -> 0 | AS14: =IF(OR($A14="",AS$6="",NOT(ISNUMBER($H$2))),"",SUMIFS(数据录入!$F$5:$F$785,数据录入!$C$5:$C$785,$A14,数据录入!$B$5:$B$785,AS$6)) -> 0 | AT14: =IF(OR($A14="",AT$6="",NOT(ISNUMBER($H$2))),"",SUMIFS(数据录入!$G$5:$G$785,数据录入!$C$5:$C$785,$A14,数据录入!$B$5:$B$785,AT$6)) -> 0 | AU14: =IF(OR($A14="",AU$6="",NOT(ISNUMBER($H$2))),"",SUMIFS(数据录入!$F$5:$F$785,数据录入!$C$5:$C$785,$A14,数据录入!$B$5:$B$785,AU$6)) -> 0 | AV14: =IF(OR($A14="",AV$6="",NOT(ISNUMBER($H$2))),"",SUMIFS(数据录入!$G$5:$G$785,数据录入!$C$5:$C$785,$A14,数据录入!$B$5:$B$785,AV$6)) -> 0 | AW14: =IF(OR($A14="",AW$6="",NOT(ISNUMBER($H$2))),"",SUMIFS(数据录入!$F$5:$F$785,数据录入!$C$5:$C$785,$A14,数据录入!$B$5:$B$785,AW$6)) -> 0 | AX14: =IF(OR($A14="",AX$6="",NOT(ISNUMBER($H$2))),"",SUMIFS(数据录入!$G$5:$G$785,数据录入!$C$5:$C$785,$A14,数据录入!$B$5:$B$785,AX$6)) -> 0 | AY14: =IF(OR($A14="",AY$6="",NOT(ISNUMBER($H$2))),"",SUMIFS(数据录入!$F$5:$F$785,数据录入!$C$5:$C$785,$A14,数据录入!$B$5:$B$785,AY$6)) -> 0 | AZ14: =IF(OR($A14="",AZ$6="",NOT(ISNUMBER($H$2))),"",SUMIFS(数据录入!$G$5:$G$785,数据录入!$C$5:$C$785,$A14,数据录入!$B$5:$B$785,AZ$6)) -> 0 | BA14: =IF(OR($A14="",BA$6="",NOT(ISNUMBER($H$2))),"",SUMIFS(数据录入!$F$5:$F$785,数据录入!$C$5:$C$785,$A14,数据录入!$B$5:$B$785,BA$6)) -> 0 | BB14: =IF(OR($A14="",BB$6="",NOT(ISNUMBER($H$2))),"",SUMIFS(数据录入!$G$5:$G$785,数据录入!$C$5:$C$785,$A14,数据录入!$B$5:$B$785,BB$6)) -> 0 | BC14: =IF(OR($A14="",BC$6="",NOT(ISNUMBER($H$2))),"",SUMIFS(数据录入!$F$5:$F$785,数据录入!$C$5:$C$785,$A14,数据录入!$B$5:$B$785,BC$6)) -> 0 | BD14: =IF(OR($A14="",BD$6="",NOT(ISNUMBER($H$2))),"",SUMIFS(数据录入!$G$5:$G$785,数据录入!$C$5:$C$785,$A14,数据录入!$B$5:$B$785,BD$6)) -> 0 | BE14: =IF(OR($A14="",BE$6="",NOT(ISNUMBER($H$2))),"",SUMIFS(数据录入!$F$5:$F$785,数据录入!$C$5:$C$785,$A14,数据录入!$B$5:$B$785,BE$6)) -> 0 | BF14: =IF(OR($A14="",BF$6="",NOT(ISNUMBER($H$2))),"",SUMIFS(数据录入!$G$5:$G$785,数据录入!$C$5:$C$785,$A14,数据录入!$B$5:$B$785,BF$6)) -> 0 | BG14: =IF(OR($A14="",BG$6="",NOT(ISNUMBER($H$2))),"",SUMIFS(数据录入!$F$5:$F$785,数据录入!$C$5:$C$785,$A14,数据录入!$B$5:$B$785,BG$6)) -> 0 | BH14: =IF(OR($A14="",BH$6="",NOT(ISNUMBER($H$2))),"",SUMIFS(数据录入!$G$5:$G$785,数据录入!$C$5:$C$785,$A14,数据录入!$B$5:$B$785,BH$6)) -> 0 | BI14: =IF(OR($A14="",BI$6="",NOT(ISNUMBER($H$2))),"",SUMIFS(数据录入!$F$5:$F$785,数据录入!$C$5:$C$785,$A14,数据录入!$B$5:$B$785,BI$6)) -> 0 | BJ14: =IF(OR($A14="",BJ$6="",NOT(ISNUMBER($H$2))),"",SUMIFS(数据录入!$G$5:$G$785,数据录入!$C$5:$C$785,$A14,数据录入!$B$5:$B$785,BJ$6)) -> 0 | BK14: =IF(OR($A14="",BK$6="",NOT(ISNUMBER($H$2))),"",SUMIFS(数据录入!$F$5:$F$785,数据录入!$C$5:$C$785,$A14,数据录入!$B$5:$B$785,BK$6)) | BL14: =IF(OR($A14="",BL$6="",NOT(ISNUMBER($H$2))),"",SUMIFS(数据录入!$G$5:$G$785,数据录入!$C$5:$C$785,$A14,数据录入!$B$5:$B$785,BL$6)) | BM14: =IF($A14="","",SUMIF($C$7:$BL$7,"收款",C14:BL14)) -> 0 | BN14: =IF($A14="","",SUMIF($C$7:$BL$7,"付款",C14:BL14)) -> 0 | BO14: =IF($A14="","",B14+BM14-BN14) -> 0
A15: 明道对公 | B15: =IF(OR($A15="",NOT(ISNUMBER($H$2))),"",SUMIFS(数据录入!$H$5:$H$785,数据录入!$C$5:$C$785,$A15,数据录入!$E$5:$E$785,"期初余额",数据录入!$B$5:$B$785,"<="&$B$2)+SUMIFS(数据录入!$F$5:$F$785,数据录入!$C$5:$C$785,$A15,数据录入!$B$5:$B$785,"<"&$B$2)-SUMIFS(数据录入!$G$5:$G$785,数据录入!$C$5:$C$785,$A15,数据录入!$B$5:$B$785,"<"&$B$2)) -> 0 | C15: =IF(OR($A15="",C$6="",NOT(ISNUMBER($H$2))),"",SUMIFS(数据录入!$F$5:$F$785,数据录入!$C$5:$C$785,$A15,数据录入!$B$5:$B$785,C$6)) -> 0 | D15: =IF(OR($A15="",D$6="",NOT(ISNUMBER($H$2))),"",SUMIFS(数据录入!$G$5:$G$785,数据录入!$C$5:$C$785,$A15,数据录入!$B$5:$B$785,D$6)) -> 0 | E15: =IF(OR($A15="",E$6="",NOT(ISNUMBER($H$2))),"",SUMIFS(数据录入!$F$5:$F$785,数据录入!$C$5:$C$785,$A15,数据录入!$B$5:$B$785,E$6)) -> 0 | F15: =IF(OR($A15="",F$6="",NOT(ISNUMBER($H$2))),"",SUMIFS(数据录入!$G$5:$G$785,数据录入!$C$5:$C$785,$A15,数据录入!$B$5:$B$785,F$6)) -> 0 | G15: =IF(OR($A15="",G$6="",NOT(ISNUMBER($H$2))),"",SUMIFS(数据录入!$F$5:$F$785,数据录入!$C$5:$C$785,$A15,数据录入!$B$5:$B$785,G$6)) -> 0 | H15: =IF(OR($A15="",H$6="",NOT(ISNUMBER($H$2))),"",SUMIFS(数据录入!$G$5:$G$785,数据录入!$C$5:$C$785,$A15,数据录入!$B$5:$B$785,H$6)) -> 0 | I15: =IF(OR($A15="",I$6="",NOT(ISNUMBER($H$2))),"",SUMIFS(数据录入!$F$5:$F$785,数据录入!$C$5:$C$785,$A15,数据录入!$B$5:$B$785,I$6)) -> 0 | J15: =IF(OR($A15="",J$6="",NOT(ISNUMBER($H$2))),"",SUMIFS(数据录入!$G$5:$G$785,数据录入!$C$5:$C$785,$A15,数据录入!$B$5:$B$785,J$6)) -> 0 | K15: =IF(OR($A15="",K$6="",NOT(ISNUMBER($H$2))),"",SUMIFS(数据录入!$F$5:$F$785,数据录入!$C$5:$C$785,$A15,数据录入!$B$5:$B$785,K$6)) -> 0 | L15: =IF(OR($A15="",L$6="",NOT(ISNUMBER($H$2))),"",SUMIFS(数据录入!$G$5:$G$785,数据录入!$C$5:$C$785,$A15,数据录入!$B$5:$B$785,L$6)) -> 0 | M15: =IF(OR($A15="",M$6="",NOT(ISNUMBER($H$2))),"",SUMIFS(数据录入!$F$5:$F$785,数据录入!$C$5:$C$785,$A15,数据录入!$B$5:$B$785,M$6)) -> 0 | N15: =IF(OR($A15="",N$6="",NOT(ISNUMBER($H$2))),"",SUMIFS(数据录入!$G$5:$G$785,数据录入!$C$5:$C$785,$A15,数据录入!$B$5:$B$785,N$6)) -> 0 | O15: =IF(OR($A15="",O$6="",NOT(ISNUMBER($H$2))),"",SUMIFS(数据录入!$F$5:$F$785,数据录入!$C$5:$C$785,$A15,数据录入!$B$5:$B$785,O$6)) -> 0 | P15: =IF(OR($A15="",P$6="",NOT(ISNUMBER($H$2))),"",SUMIFS(数据录入!$G$5:$G$785,数据录入!$C$5:$C$785,$A15,数据录入!$B$5:$B$785,P$6)) -> 0 | Q15: =IF(OR($A15="",Q$6="",NOT(ISNUMBER($H$2))),"",SUMIFS(数据录入!$F$5:$F$785,数据录入!$C$5:$C$785,$A15,数据录入!$B$5:$B$785,Q$6)) -> 0 | R15: =IF(OR($A15="",R$6="",NOT(ISNUMBER($H$2))),"",SUMIFS(数据录入!$G$5:$G$785,数据录入!$C$5:$C$785,$A15,数据录入!$B$5:$B$785,R$6)) -> 0 | S15: =IF(OR($A15="",S$6="",NOT(ISNUMBER($H$2))),"",SUMIFS(数据录入!$F$5:$F$785,数据录入!$C$5:$C$785,$A15,数据录入!$B$5:$B$785,S$6)) -> 0 | T15: =IF(OR($A15="",T$6="",NOT(ISNUMBER($H$2))),"",SUMIFS(数据录入!$G$5:$G$785,数据录入!$C$5:$C$785,$A15,数据录入!$B$5:$B$785,T$6)) -> 0 | U15: =IF(OR($A15="",U$6="",NOT(ISNUMBER($H$2))),"",SUMIFS(数据录入!$F$5:$F$785,数据录入!$C$5:$C$785,$A15,数据录入!$B$5:$B$785,U$6)) -> 0 | V15: =IF(OR($A15="",V$6="",NOT(ISNUMBER($H$2))),"",SUMIFS(数据录入!$G$5:$G$785,数据录入!$C$5:$C$785,$A15,数据录入!$B$5:$B$785,V$6)) -> 0 | W15: =IF(OR($A15="",W$6="",NOT(ISNUMBER($H$2))),"",SUMIFS(数据录入!$F$5:$F$785,数据录入!$C$5:$C$785,$A15,数据录入!$B$5:$B$785,W$6)) -> 0 | X15: =IF(OR($A15="",X$6="",NOT(ISNUMBER($H$2))),"",SUMIFS(数据录入!$G$5:$G$785,数据录入!$C$5:$C$785,$A15,数据录入!$B$5:$B$785,X$6)) -> 0 | Y15: =IF(OR($A15="",Y$6="",NOT(ISNUMBER($H$2))),"",SUMIFS(数据录入!$F$5:$F$785,数据录入!$C$5:$C$785,$A15,数据录入!$B$5:$B$785,Y$6)) -> 0 | Z15: =IF(OR($A15="",Z$6="",NOT(ISNUMBER($H$2))),"",SUMIFS(数据录入!$G$5:$G$785,数据录入!$C$5:$C$785,$A15,数据录入!$B$5:$B$785,Z$6)) -> 0 | AA15: =IF(OR($A15="",AA$6="",NOT(ISNUMBER($H$2))),"",SUMIFS(数据录入!$F$5:$F$785,数据录入!$C$5:$C$785,$A15,数据录入!$B$5:$B$785,AA$6)) -> 0 | AB15: =IF(OR($A15="",AB$6="",NOT(ISNUMBER($H$2))),"",SUMIFS(数据录入!$G$5:$G$785,数据录入!$C$5:$C$785,$A15,数据录入!$B$5:$B$785,AB$6)) -> 0 | AC15: =IF(OR($A15="",AC$6="",NOT(ISNUMBER($H$2))),"",SUMIFS(数据录入!$F$5:$F$785,数据录入!$C$5:$C$785,$A15,数据录入!$B$5:$B$785,AC$6)) -> 0 | AD15: =IF(OR($A15="",AD$6="",NOT(ISNUMBER($H$2))),"",SUMIFS(数据录入!$G$5:$G$785,数据录入!$C$5:$C$785,$A15,数据录入!$B$5:$B$785,AD$6)) -> 0 | AE15: =IF(OR($A15="",AE$6="",NOT(ISNUMBER($H$2))),"",SUMIFS(数据录入!$F$5:$F$785,数据录入!$C$5:$C$785,$A15,数据录入!$B$5:$B$785,AE$6)) -> 0 | AF15: =IF(OR($A15="",AF$6="",NOT(ISNUMBER($H$2))),"",SUMIFS(数据录入!$G$5:$G$785,数据录入!$C$5:$C$785,$A15,数据录入!$B$5:$B$785,AF$6)) -> 0 | AG15: =IF(OR($A15="",AG$6="",NOT(ISNUMBER($H$2))),"",SUMIFS(数据录入!$F$5:$F$785,数据录入!$C$5:$C$785,$A15,数据录入!$B$5:$B$785,AG$6)) -> 0 | AH15: =IF(OR($A15="",AH$6="",NOT(ISNUMBER($H$2))),"",SUMIFS(数据录入!$G$5:$G$785,数据录入!$C$5:$C$785,$A15,数据录入!$B$5:$B$785,AH$6)) -> 0 | AI15: =IF(OR($A15="",AI$6="",NOT(ISNUMBER($H$2))),"",SUMIFS(数据录入!$F$5:$F$785,数据录入!$C$5:$C$785,$A15,数据录入!$B$5:$B$785,AI$6)) -> 0 | AJ15: =IF(OR($A15="",AJ$6="",NOT(ISNUMBER($H$2))),"",SUMIFS(数据录入!$G$5:$G$785,数据录入!$C$5:$C$785,$A15,数据录入!$B$5:$B$785,AJ$6)) -> 0 | AK15: =IF(OR($A15="",AK$6="",NOT(ISNUMBER($H$2))),"",SUMIFS(数据录入!$F$5:$F$785,数据录入!$C$5:$C$785,$A15,数据录入!$B$5:$B$785,AK$6)) -> 0 | AL15: =IF(OR($A15="",AL$6="",NOT(ISNUMBER($H$2))),"",SUMIFS(数据录入!$G$5:$G$785,数据录入!$C$5:$C$785,$A15,数据录入!$B$5:$B$785,AL$6)) -> 0 | AM15: =IF(OR($A15="",AM$6="",NOT(ISNUMBER($H$2))),"",SUMIFS(数据录入!$F$5:$F$785,数据录入!$C$5:$C$785,$A15,数据录入!$B$5:$B$785,AM$6)) -> 0 | AN15: =IF(OR($A15="",AN$6="",NOT(ISNUMBER($H$2))),"",SUMIFS(数据录入!$G$5:$G$785,数据录入!$C$5:$C$785,$A15,数据录入!$B$5:$B$785,AN$6)) -> 0 | AO15: =IF(OR($A15="",AO$6="",NOT(ISNUMBER($H$2))),"",SUMIFS(数据录入!$F$5:$F$785,数据录入!$C$5:$C$785,$A15,数据录入!$B$5:$B$785,AO$6)) -> 0 | AP15: =IF(OR($A15="",AP$6="",NOT(ISNUMBER($H$2))),"",SUMIFS(数据录入!$G$5:$G$785,数据录入!$C$5:$C$785,$A15,数据录入!$B$5:$B$785,AP$6)) -> 0 | AQ15: =IF(OR($A15="",AQ$6="",NOT(ISNUMBER($H$2))),"",SUMIFS(数据录入!$F$5:$F$785,数据录入!$C$5:$C$785,$A15,数据录入!$B$5:$B$785,AQ$6)) -> 0 | AR15: =IF(OR($A15="",AR$6="",NOT(ISNUMBER($H$2))),"",SUMIFS(数据录入!$G$5:$G$785,数据录入!$C$5:$C$785,$A15,数据录入!$B$5:$B$785,AR$6)) -> 0 | AS15: =IF(OR($A15="",AS$6="",NOT(ISNUMBER($H$2))),"",SUMIFS(数据录入!$F$5:$F$785,数据录入!$C$5:$C$785,$A15,数据录入!$B$5:$B$785,AS$6)) -> 0 | AT15: =IF(OR($A15="",AT$6="",NOT(ISNUMBER($H$2))),"",SUMIFS(数据录入!$G$5:$G$785,数据录入!$C$5:$C$785,$A15,数据录入!$B$5:$B$785,AT$6)) -> 0 | AU15: =IF(OR($A15="",AU$6="",NOT(ISNUMBER($H$2))),"",SUMIFS(数据录入!$F$5:$F$785,数据录入!$C$5:$C$785,$A15,数据录入!$B$5:$B$785,AU$6)) -> 0 | AV15: =IF(OR($A15="",AV$6="",NOT(ISNUMBER($H$2))),"",SUMIFS(数据录入!$G$5:$G$785,数据录入!$C$5:$C$785,$A15,数据录入!$B$5:$B$785,AV$6)) -> 0 | AW15: =IF(OR($A15="",AW$6="",NOT(ISNUMBER($H$2))),"",SUMIFS(数据录入!$F$5:$F$785,数据录入!$C$5:$C$785,$A15,数据录入!$B$5:$B$785,AW$6)) -> 0 | AX15: =IF(OR($A15="",AX$6="",NOT(ISNUMBER($H$2))),"",SUMIFS(数据录入!$G$5:$G$785,数据录入!$C$5:$C$785,$A15,数据录入!$B$5:$B$785,AX$6)) -> 0 | AY15: =IF(OR($A15="",AY$6="",NOT(ISNUMBER($H$2))),"",SUMIFS(数据录入!$F$5:$F$785,数据录入!$C$5:$C$785,$A15,数据录入!$B$5:$B$785,AY$6)) -> 0 | AZ15: =IF(OR($A15="",AZ$6="",NOT(ISNUMBER($H$2))),"",SUMIFS(数据录入!$G$5:$G$785,数据录入!$C$5:$C$785,$A15,数据录入!$B$5:$B$785,AZ$6)) -> 0 | BA15: =IF(OR($A15="",BA$6="",NOT(ISNUMBER($H$2))),"",SUMIFS(数据录入!$F$5:$F$785,数据录入!$C$5:$C$785,$A15,数据录入!$B$5:$B$785,BA$6)) -> 0 | BB15: =IF(OR($A15="",BB$6="",NOT(ISNUMBER($H$2))),"",SUMIFS(数据录入!$G$5:$G$785,数据录入!$C$5:$C$785,$A15,数据录入!$B$5:$B$785,BB$6)) -> 0 | BC15: =IF(OR($A15="",BC$6="",NOT(ISNUMBER($H$2))),"",SUMIFS(数据录入!$F$5:$F$785,数据录入!$C$5:$C$785,$A15,数据录入!$B$5:$B$785,BC$6)) -> 0 | BD15: =IF(OR($A15="",BD$6="",NOT(ISNUMBER($H$2))),"",SUMIFS(数据录入!$G$5:$G$785,数据录入!$C$5:$C$785,$A15,数据录入!$B$5:$B$785,BD$6)) -> 0 | BE15: =IF(OR($A15="",BE$6="",NOT(ISNUMBER($H$2))),"",SUMIFS(数据录入!$F$5:$F$785,数据录入!$C$5:$C$785,$A15,数据录入!$B$5:$B$785,BE$6)) -> 0 | BF15: =IF(OR($A15="",BF$6="",NOT(ISNUMBER($H$2))),"",SUMIFS(数据录入!$G$5:$G$785,数据录入!$C$5:$C$785,$A15,数据录入!$B$5:$B$785,BF$6)) -> 0 | BG15: =IF(OR($A15="",BG$6="",NOT(ISNUMBER($H$2))),"",SUMIFS(数据录入!$F$5:$F$785,数据录入!$C$5:$C$785,$A15,数据录入!$B$5:$B$785,BG$6)) -> 0 | BH15: =IF(OR($A15="",BH$6="",NOT(ISNUMBER($H$2))),"",SUMIFS(数据录入!$G$5:$G$785,数据录入!$C$5:$C$785,$A15,数据录入!$B$5:$B$785,BH$6)) -> 0 | BI15: =IF(OR($A15="",BI$6="",NOT(ISNUMBER($H$2))),"",SUMIFS(数据录入!$F$5:$F$785,数据录入!$C$5:$C$785,$A15,数据录入!$B$5:$B$785,BI$6)) -> 0 | BJ15: =IF(OR($A15="",BJ$6="",NOT(ISNUMBER($H$2))),"",SUMIFS(数据录入!$G$5:$G$785,数据录入!$C$5:$C$785,$A15,数据录入!$B$5:$B$785,BJ$6)) -> 0 | BK15: =IF(OR($A15="",BK$6="",NOT(ISNUMBER($H$2))),"",SUMIFS(数据录入!$F$5:$F$785,数据录入!$C$5:$C$785,$A15,数据录入!$B$5:$B$785,BK$6)) | BL15: =IF(OR($A15="",BL$6="",NOT(ISNUMBER($H$2))),"",SUMIFS(数据录入!$G$5:$G$785,数据录入!$C$5:$C$785,$A15,数据录入!$B$5:$B$785,BL$6)) | BM15: =IF($A15="","",SUMIF($C$7:$BL$7,"收款",C15:BL15)) -> 0 | BN15: =IF($A15="","",SUMIF($C$7:$BL$7,"付款",C15:BL15)) -> 0 | BO15: =IF($A15="","",B15+BM15-BN15) -> 0
A16: 金辉对公 | B16: =IF(OR($A16="",NOT(ISNUMBER($H$2))),"",SUMIFS(数据录入!$H$5:$H$785,数据录入!$C$5:$C$785,$A16,数据录入!$E$5:$E$785,"期初余额",数据录入!$B$5:$B$785,"<="&$B$2)+SUMIFS(数据录入!$F$5:$F$785,数据录入!$C$5:$C$785,$A16,数据录入!$B$5:$B$785,"<"&$B$2)-SUMIFS(数据录入!$G$5:$G$785,数据录入!$C$5:$C$785,$A16,数据录入!$B$5:$B$785,"<"&$B$2)) -> 0 | C16: =IF(OR($A16="",C$6="",NOT(ISNUMBER($H$2))),"",SUMIFS(数据录入!$F$5:$F$785,数据录入!$C$5:$C$785,$A16,数据录入!$B$5:$B$785,C$6)) -> 0 | D16: =IF(OR($A16="",D$6="",NOT(ISNUMBER($H$2))),"",SUMIFS(数据录入!$G$5:$G$785,数据录入!$C$5:$C$785,$A16,数据录入!$B$5:$B$785,D$6)) -> 0 | E16: =IF(OR($A16="",E$6="",NOT(ISNUMBER($H$2))),"",SUMIFS(数据录入!$F$5:$F$785,数据录入!$C$5:$C$785,$A16,数据录入!$B$5:$B$785,E$6)) -> 0 | F16: =IF(OR($A16="",F$6="",NOT(ISNUMBER($H$2))),"",SUMIFS(数据录入!$G$5:$G$785,数据录入!$C$5:$C$785,$A16,数据录入!$B$5:$B$785,F$6)) -> 0 | G16: =IF(OR($A16="",G$6="",NOT(ISNUMBER($H$2))),"",SUMIFS(数据录入!$F$5:$F$785,数据录入!$C$5:$C$785,$A16,数据录入!$B$5:$B$785,G$6)) -> 0 | H16: =IF(OR($A16="",H$6="",NOT(ISNUMBER($H$2))),"",SUMIFS(数据录入!$G$5:$G$785,数据录入!$C$5:$C$785,$A16,数据录入!$B$5:$B$785,H$6)) -> 0 | I16: =IF(OR($A16="",I$6="",NOT(ISNUMBER($H$2))),"",SUMIFS(数据录入!$F$5:$F$785,数据录入!$C$5:$C$785,$A16,数据录入!$B$5:$B$785,I$6)) -> 0 | J16: =IF(OR($A16="",J$6="",NOT(ISNUMBER($H$2))),"",SUMIFS(数据录入!$G$5:$G$785,数据录入!$C$5:$C$785,$A16,数据录入!$B$5:$B$785,J$6)) -> 0 | K16: =IF(OR($A16="",K$6="",NOT(ISNUMBER($H$2))),"",SUMIFS(数据录入!$F$5:$F$785,数据录入!$C$5:$C$785,$A16,数据录入!$B$5:$B$785,K$6)) -> 0 | L16: =IF(OR($A16="",L$6="",NOT(ISNUMBER($H$2))),"",SUMIFS(数据录入!$G$5:$G$785,数据录入!$C$5:$C$785,$A16,数据录入!$B$5:$B$785,L$6)) -> 0 | M16: =IF(OR($A16="",M$6="",NOT(ISNUMBER($H$2))),"",SUMIFS(数据录入!$F$5:$F$785,数据录入!$C$5:$C$785,$A16,数据录入!$B$5:$B$785,M$6)) -> 0 | N16: =IF(OR($A16="",N$6="",NOT(ISNUMBER($H$2))),"",SUMIFS(数据录入!$G$5:$G$785,数据录入!$C$5:$C$785,$A16,数据录入!$B$5:$B$785,N$6)) -> 0 | O16: =IF(OR($A16="",O$6="",NOT(ISNUMBER($H$2))),"",SUMIFS(数据录入!$F$5:$F$785,数据录入!$C$5:$C$785,$A16,数据录入!$B$5:$B$785,O$6)) -> 0 | P16: =IF(OR($A16="",P$6="",NOT(ISNUMBER($H$2))),"",SUMIFS(数据录入!$G$5:$G$785,数据录入!$C$5:$C$785,$A16,数据录入!$B$5:$B$785,P$6)) -> 0 | Q16: =IF(OR($A16="",Q$6="",NOT(ISNUMBER($H$2))),"",SUMIFS(数据录入!$F$5:$F$785,数据录入!$C$5:$C$785,$A16,数据录入!$B$5:$B$785,Q$6)) -> 0 | R16: =IF(OR($A16="",R$6="",NOT(ISNUMBER($H$2))),"",SUMIFS(数据录入!$G$5:$G$785,数据录入!$C$5:$C$785,$A16,数据录入!$B$5:$B$785,R$6)) -> 0 | S16: =IF(OR($A16="",S$6="",NOT(ISNUMBER($H$2))),"",SUMIFS(数据录入!$F$5:$F$785,数据录入!$C$5:$C$785,$A16,数据录入!$B$5:$B$785,S$6)) -> 0 | T16: =IF(OR($A16="",T$6="",NOT(ISNUMBER($H$2))),"",SUMIFS(数据录入!$G$5:$G$785,数据录入!$C$5:$C$785,$A16,数据录入!$B$5:$B$785,T$6)) -> 0 | U16: =IF(OR($A16="",U$6="",NOT(ISNUMBER($H$2))),"",SUMIFS(数据录入!$F$5:$F$785,数据录入!$C$5:$C$785,$A16,数据录入!$B$5:$B$785,U$6)) -> 0 | V16: =IF(OR($A16="",V$6="",NOT(ISNUMBER($H$2))),"",SUMIFS(数据录入!$G$5:$G$785,数据录入!$C$5:$C$785,$A16,数据录入!$B$5:$B$785,V$6)) -> 0 | W16: =IF(OR($A16="",W$6="",NOT(ISNUMBER($H$2))),"",SUMIFS(数据录入!$F$5:$F$785,数据录入!$C$5:$C$785,$A16,数据录入!$B$5:$B$785,W$6)) -> 0 | X16: =IF(OR($A16="",X$6="",NOT(ISNUMBER($H$2))),"",SUMIFS(数据录入!$G$5:$G$785,数据录入!$C$5:$C$785,$A16,数据录入!$B$5:$B$785,X$6)) -> 0 | Y16: =IF(OR($A16="",Y$6="",NOT(ISNUMBER($H$2))),"",SUMIFS(数据录入!$F$5:$F$785,数据录入!$C$5:$C$785,$A16,数据录入!$B$5:$B$785,Y$6)) -> 0 | Z16: =IF(OR($A16="",Z$6="",NOT(ISNUMBER($H$2))),"",SUMIFS(数据录入!$G$5:$G$785,数据录入!$C$5:$C$785,$A16,数据录入!$B$5:$B$785,Z$6)) -> 0 | AA16: =IF(OR($A16="",AA$6="",NOT(ISNUMBER($H$2))),"",SUMIFS(数据录入!$F$5:$F$785,数据录入!$C$5:$C$785,$A16,数据录入!$B$5:$B$785,AA$6)) -> 0 | AB16: =IF(OR($A16="",AB$6="",NOT(ISNUMBER($H$2))),"",SUMIFS(数据录入!$G$5:$G$785,数据录入!$C$5:$C$785,$A16,数据录入!$B$5:$B$785,AB$6)) -> 0 | AC16: =IF(OR($A16="",AC$6="",NOT(ISNUMBER($H$2))),"",SUMIFS(数据录入!$F$5:$F$785,数据录入!$C$5:$C$785,$A16,数据录入!$B$5:$B$785,AC$6)) -> 0 | AD16: =IF(OR($A16="",AD$6="",NOT(ISNUMBER($H$2))),"",SUMIFS(数据录入!$G$5:$G$785,数据录入!$C$5:$C$785,$A16,数据录入!$B$5:$B$785,AD$6)) -> 0 | AE16: =IF(OR($A16="",AE$6="",NOT(ISNUMBER($H$2))),"",SUMIFS(数据录入!$F$5:$F$785,数据录入!$C$5:$C$785,$A16,数据录入!$B$5:$B$785,AE$6)) -> 0 | AF16: =IF(OR($A16="",AF$6="",NOT(ISNUMBER($H$2))),"",SUMIFS(数据录入!$G$5:$G$785,数据录入!$C$5:$C$785,$A16,数据录入!$B$5:$B$785,AF$6)) -> 0 | AG16: =IF(OR($A16="",AG$6="",NOT(ISNUMBER($H$2))),"",SUMIFS(数据录入!$F$5:$F$785,数据录入!$C$5:$C$785,$A16,数据录入!$B$5:$B$785,AG$6)) -> 0 | AH16: =IF(OR($A16="",AH$6="",NOT(ISNUMBER($H$2))),"",SUMIFS(数据录入!$G$5:$G$785,数据录入!$C$5:$C$785,$A16,数据录入!$B$5:$B$785,AH$6)) -> 0 | AI16: =IF(OR($A16="",AI$6="",NOT(ISNUMBER($H$2))),"",SUMIFS(数据录入!$F$5:$F$785,数据录入!$C$5:$C$785,$A16,数据录入!$B$5:$B$785,AI$6)) -> 0 | AJ16: =IF(OR($A16="",AJ$6="",NOT(ISNUMBER($H$2))),"",SUMIFS(数据录入!$G$5:$G$785,数据录入!$C$5:$C$785,$A16,数据录入!$B$5:$B$785,AJ$6)) -> 0 | AK16: =IF(OR($A16="",AK$6="",NOT(ISNUMBER($H$2))),"",SUMIFS(数据录入!$F$5:$F$785,数据录入!$C$5:$C$785,$A16,数据录入!$B$5:$B$785,AK$6)) -> 0 | AL16: =IF(OR($A16="",AL$6="",NOT(ISNUMBER($H$2))),"",SUMIFS(数据录入!$G$5:$G$785,数据录入!$C$5:$C$785,$A16,数据录入!$B$5:$B$785,AL$6)) -> 0 | AM16: =IF(OR($A16="",AM$6="",NOT(ISNUMBER($H$2))),"",SUMIFS(数据录入!$F$5:$F$785,数据录入!$C$5:$C$785,$A16,数据录入!$B$5:$B$785,AM$6)) -> 0 | AN16: =IF(OR($A16="",AN$6="",NOT(ISNUMBER($H$2))),"",SUMIFS(数据录入!$G$5:$G$785,数据录入!$C$5:$C$785,$A16,数据录入!$B$5:$B$785,AN$6)) -> 0 | AO16: =IF(OR($A16="",AO$6="",NOT(ISNUMBER($H$2))),"",SUMIFS(数据录入!$F$5:$F$785,数据录入!$C$5:$C$785,$A16,数据录入!$B$5:$B$785,AO$6)) -> 0 | AP16: =IF(OR($A16="",AP$6="",NOT(ISNUMBER($H$2))),"",SUMIFS(数据录入!$G$5:$G$785,数据录入!$C$5:$C$785,$A16,数据录入!$B$5:$B$785,AP$6)) -> 0 | AQ16: =IF(OR($A16="",AQ$6="",NOT(ISNUMBER($H$2))),"",SUMIFS(数据录入!$F$5:$F$785,数据录入!$C$5:$C$785,$A16,数据录入!$B$5:$B$785,AQ$6)) -> 0 | AR16: =IF(OR($A16="",AR$6="",NOT(ISNUMBER($H$2))),"",SUMIFS(数据录入!$G$5:$G$785,数据录入!$C$5:$C$785,$A16,数据录入!$B$5:$B$785,AR$6)) -> 0 | AS16: =IF(OR($A16="",AS$6="",NOT(ISNUMBER($H$2))),"",SUMIFS(数据录入!$F$5:$F$785,数据录入!$C$5:$C$785,$A16,数据录入!$B$5:$B$785,AS$6)) -> 0 | AT16: =IF(OR($A16="",AT$6="",NOT(ISNUMBER($H$2))),"",SUMIFS(数据录入!$G$5:$G$785,数据录入!$C$5:$C$785,$A16,数据录入!$B$5:$B$785,AT$6)) -> 0 | AU16: =IF(OR($A16="",AU$6="",NOT(ISNUMBER($H$2))),"",SUMIFS(数据录入!$F$5:$F$785,数据录入!$C$5:$C$785,$A16,数据录入!$B$5:$B$785,AU$6)) -> 0 | AV16: =IF(OR($A16="",AV$6="",NOT(ISNUMBER($H$2))),"",SUMIFS(数据录入!$G$5:$G$785,数据录入!$C$5:$C$785,$A16,数据录入!$B$5:$B$785,AV$6)) -> 0 | AW16: =IF(OR($A16="",AW$6="",NOT(ISNUMBER($H$2))),"",SUMIFS(数据录入!$F$5:$F$785,数据录入!$C$5:$C$785,$A16,数据录入!$B$5:$B$785,AW$6)) -> 0 | AX16: =IF(OR($A16="",AX$6="",NOT(ISNUMBER($H$2))),"",SUMIFS(数据录入!$G$5:$G$785,数据录入!$C$5:$C$785,$A16,数据录入!$B$5:$B$785,AX$6)) -> 0 | AY16: =IF(OR($A16="",AY$6="",NOT(ISNUMBER($H$2))),"",SUMIFS(数据录入!$F$5:$F$785,数据录入!$C$5:$C$785,$A16,数据录入!$B$5:$B$785,AY$6)) -> 0 | AZ16: =IF(OR($A16="",AZ$6="",NOT(ISNUMBER($H$2))),"",SUMIFS(数据录入!$G$5:$G$785,数据录入!$C$5:$C$785,$A16,数据录入!$B$5:$B$785,AZ$6)) -> 0 | BA16: =IF(OR($A16="",BA$6="",NOT(ISNUMBER($H$2))),"",SUMIFS(数据录入!$F$5:$F$785,数据录入!$C$5:$C$785,$A16,数据录入!$B$5:$B$785,BA$6)) -> 0 | BB16: =IF(OR($A16="",BB$6="",NOT(ISNUMBER($H$2))),"",SUMIFS(数据录入!$G$5:$G$785,数据录入!$C$5:$C$785,$A16,数据录入!$B$5:$B$785,BB$6)) -> 0 | BC16: =IF(OR($A16="",BC$6="",NOT(ISNUMBER($H$2))),"",SUMIFS(数据录入!$F$5:$F$785,数据录入!$C$5:$C$785,$A16,数据录入!$B$5:$B$785,BC$6)) -> 0 | BD16: =IF(OR($A16="",BD$6="",NOT(ISNUMBER($H$2))),"",SUMIFS(数据录入!$G$5:$G$785,数据录入!$C$5:$C$785,$A16,数据录入!$B$5:$B$785,BD$6)) -> 0 | BE16: =IF(OR($A16="",BE$6="",NOT(ISNUMBER($H$2))),"",SUMIFS(数据录入!$F$5:$F$785,数据录入!$C$5:$C$785,$A16,数据录入!$B$5:$B$785,BE$6)) -> 0 | BF16: =IF(OR($A16="",BF$6="",NOT(ISNUMBER($H$2))),"",SUMIFS(数据录入!$G$5:$G$785,数据录入!$C$5:$C$785,$A16,数据录入!$B$5:$B$785,BF$6)) -> 0 | BG16: =IF(OR($A16="",BG$6="",NOT(ISNUMBER($H$2))),"",SUMIFS(数据录入!$F$5:$F$785,数据录入!$C$5:$C$785,$A16,数据录入!$B$5:$B$785,BG$6)) -> 0 | BH16: =IF(OR($A16="",BH$6="",NOT(ISNUMBER($H$2))),"",SUMIFS(数据录入!$G$5:$G$785,数据录入!$C$5:$C$785,$A16,数据录入!$B$5:$B$785,BH$6)) -> 0 | BI16: =IF(OR($A16="",BI$6="",NOT(ISNUMBER($H$2))),"",SUMIFS(数据录入!$F$5:$F$785,数据录入!$C$5:$C$785,$A16,数据录入!$B$5:$B$785,BI$6)) -> 0 | BJ16: =IF(OR($A16="",BJ$6="",NOT(ISNUMBER($H$2))),"",SUMIFS(数据录入!$G$5:$G$785,数据录入!$C$5:$C$785,$A16,数据录入!$B$5:$B$785,BJ$6)) -> 0 | BK16: =IF(OR($A16="",BK$6="",NOT(ISNUMBER($H$2))),"",SUMIFS(数据录入!$F$5:$F$785,数据录入!$C$5:$C$785,$A16,数据录入!$B$5:$B$785,BK$6)) | BL16: =IF(OR($A16="",BL$6="",NOT(ISNUMBER($H$2))),"",SUMIFS(数据录入!$G$5:$G$785,数据录入!$C$5:$C$785,$A16,数据录入!$B$5:$B$785,BL$6)) | BM16: =IF($A16="","",SUMIF($C$7:$BL$7,"收款",C16:BL16)) -> 0 | BN16: =IF($A16="","",SUMIF($C$7:$BL$7,"付款",C16:BL16)) -> 0 | BO16: =IF($A16="","",B16+BM16-BN16) -> 0
A17: 吴姐微信 | B17: =IF(OR($A17="",NOT(ISNUMBER($H$2))),"",SUMIFS(数据录入!$H$5:$H$785,数据录入!$C$5:$C$785,$A17,数据录入!$E$5:$E$785,"期初余额",数据录入!$B$5:$B$785,"<="&$B$2)+SUMIFS(数据录入!$F$5:$F$785,数据录入!$C$5:$C$785,$A17,数据录入!$B$5:$B$785,"<"&$B$2)-SUMIFS(数据录入!$G$5:$G$785,数据录入!$C$5:$C$785,$A17,数据录入!$B$5:$B$785,"<"&$B$2)) -> 0 | C17: =IF(OR($A17="",C$6="",NOT(ISNUMBER($H$2))),"",SUMIFS(数据录入!$F$5:$F$785,数据录入!$C$5:$C$785,$A17,数据录入!$B$5:$B$785,C$6)) -> 0 | D17: =IF(OR($A17="",D$6="",NOT(ISNUMBER($H$2))),"",SUMIFS(数据录入!$G$5:$G$785,数据录入!$C$5:$C$785,$A17,数据录入!$B$5:$B$785,D$6)) -> 0 | E17: =IF(OR($A17="",E$6="",NOT(ISNUMBER($H$2))),"",SUMIFS(数据录入!$F$5:$F$785,数据录入!$C$5:$C$785,$A17,数据录入!$B$5:$B$785,E$6)) -> 0 | F17: =IF(OR($A17="",F$6="",NOT(ISNUMBER($H$2))),"",SUMIFS(数据录入!$G$5:$G$785,数据录入!$C$5:$C$785,$A17,数据录入!$B$5:$B$785,F$6)) -> 0 | G17: =IF(OR($A17="",G$6="",NOT(ISNUMBER($H$2))),"",SUMIFS(数据录入!$F$5:$F$785,数据录入!$C$5:$C$785,$A17,数据录入!$B$5:$B$785,G$6)) -> 0 | H17: =IF(OR($A17="",H$6="",NOT(ISNUMBER($H$2))),"",SUMIFS(数据录入!$G$5:$G$785,数据录入!$C$5:$C$785,$A17,数据录入!$B$5:$B$785,H$6)) -> 0 | I17: =IF(OR($A17="",I$6="",NOT(ISNUMBER($H$2))),"",SUMIFS(数据录入!$F$5:$F$785,数据录入!$C$5:$C$785,$A17,数据录入!$B$5:$B$785,I$6)) -> 0 | J17: =IF(OR($A17="",J$6="",NOT(ISNUMBER($H$2))),"",SUMIFS(数据录入!$G$5:$G$785,数据录入!$C$5:$C$785,$A17,数据录入!$B$5:$B$785,J$6)) -> 0 | K17: =IF(OR($A17="",K$6="",NOT(ISNUMBER($H$2))),"",SUMIFS(数据录入!$F$5:$F$785,数据录入!$C$5:$C$785,$A17,数据录入!$B$5:$B$785,K$6)) -> 0 | L17: =IF(OR($A17="",L$6="",NOT(ISNUMBER($H$2))),"",SUMIFS(数据录入!$G$5:$G$785,数据录入!$C$5:$C$785,$A17,数据录入!$B$5:$B$785,L$6)) -> 0 | M17: =IF(OR($A17="",M$6="",NOT(ISNUMBER($H$2))),"",SUMIFS(数据录入!$F$5:$F$785,数据录入!$C$5:$C$785,$A17,数据录入!$B$5:$B$785,M$6)) -> 0 | N17: =IF(OR($A17="",N$6="",NOT(ISNUMBER($H$2))),"",SUMIFS(数据录入!$G$5:$G$785,数据录入!$C$5:$C$785,$A17,数据录入!$B$5:$B$785,N$6)) -> 0 | O17: =IF(OR($A17="",O$6="",NOT(ISNUMBER($H$2))),"",SUMIFS(数据录入!$F$5:$F$785,数据录入!$C$5:$C$785,$A17,数据录入!$B$5:$B$785,O$6)) -> 0 | P17: =IF(OR($A17="",P$6="",NOT(ISNUMBER($H$2))),"",SUMIFS(数据录入!$G$5:$G$785,数据录入!$C$5:$C$785,$A17,数据录入!$B$5:$B$785,P$6)) -> 0 | Q17: =IF(OR($A17="",Q$6="",NOT(ISNUMBER($H$2))),"",SUMIFS(数据录入!$F$5:$F$785,数据录入!$C$5:$C$785,$A17,数据录入!$B$5:$B$785,Q$6)) -> 0 | R17: =IF(OR($A17="",R$6="",NOT(ISNUMBER($H$2))),"",SUMIFS(数据录入!$G$5:$G$785,数据录入!$C$5:$C$785,$A17,数据录入!$B$5:$B$785,R$6)) -> 0 | S17: =IF(OR($A17="",S$6="",NOT(ISNUMBER($H$2))),"",SUMIFS(数据录入!$F$5:$F$785,数据录入!$C$5:$C$785,$A17,数据录入!$B$5:$B$785,S$6)) -> 0 | T17: =IF(OR($A17="",T$6="",NOT(ISNUMBER($H$2))),"",SUMIFS(数据录入!$G$5:$G$785,数据录入!$C$5:$C$785,$A17,数据录入!$B$5:$B$785,T$6)) -> 0 | U17: =IF(OR($A17="",U$6="",NOT(ISNUMBER($H$2))),"",SUMIFS(数据录入!$F$5:$F$785,数据录入!$C$5:$C$785,$A17,数据录入!$B$5:$B$785,U$6)) -> 0 | V17: =IF(OR($A17="",V$6="",NOT(ISNUMBER($H$2))),"",SUMIFS(数据录入!$G$5:$G$785,数据录入!$C$5:$C$785,$A17,数据录入!$B$5:$B$785,V$6)) -> 0 | W17: =IF(OR($A17="",W$6="",NOT(ISNUMBER($H$2))),"",SUMIFS(数据录入!$F$5:$F$785,数据录入!$C$5:$C$785,$A17,数据录入!$B$5:$B$785,W$6)) -> 0 | X17: =IF(OR($A17="",X$6="",NOT(ISNUMBER($H$2))),"",SUMIFS(数据录入!$G$5:$G$785,数据录入!$C$5:$C$785,$A17,数据录入!$B$5:$B$785,X$6)) -> 0 | Y17: =IF(OR($A17="",Y$6="",NOT(ISNUMBER($H$2))),"",SUMIFS(数据录入!$F$5:$F$785,数据录入!$C$5:$C$785,$A17,数据录入!$B$5:$B$785,Y$6)) -> 0 | Z17: =IF(OR($A17="",Z$6="",NOT(ISNUMBER($H$2))),"",SUMIFS(数据录入!$G$5:$G$785,数据录入!$C$5:$C$785,$A17,数据录入!$B$5:$B$785,Z$6)) -> 0 | AA17: =IF(OR($A17="",AA$6="",NOT(ISNUMBER($H$2))),"",SUMIFS(数据录入!$F$5:$F$785,数据录入!$C$5:$C$785,$A17,数据录入!$B$5:$B$785,AA$6)) -> 0 | AB17: =IF(OR($A17="",AB$6="",NOT(ISNUMBER($H$2))),"",SUMIFS(数据录入!$G$5:$G$785,数据录入!$C$5:$C$785,$A17,数据录入!$B$5:$B$785,AB$6)) -> 0 | AC17: =IF(OR($A17="",AC$6="",NOT(ISNUMBER($H$2))),"",SUMIFS(数据录入!$F$5:$F$785,数据录入!$C$5:$C$785,$A17,数据录入!$B$5:$B$785,AC$6)) -> 0 | AD17: =IF(OR($A17="",AD$6="",NOT(ISNUMBER($H$2))),"",SUMIFS(数据录入!$G$5:$G$785,数据录入!$C$5:$C$785,$A17,数据录入!$B$5:$B$785,AD$6)) -> 0 | AE17: =IF(OR($A17="",AE$6="",NOT(ISNUMBER($H$2))),"",SUMIFS(数据录入!$F$5:$F$785,数据录入!$C$5:$C$785,$A17,数据录入!$B$5:$B$785,AE$6)) -> 0 | AF17: =IF(OR($A17="",AF$6="",NOT(ISNUMBER($H$2))),"",SUMIFS(数据录入!$G$5:$G$785,数据录入!$C$5:$C$785,$A17,数据录入!$B$5:$B$785,AF$6)) -> 0 | AG17: =IF(OR($A17="",AG$6="",NOT(ISNUMBER($H$2))),"",SUMIFS(数据录入!$F$5:$F$785,数据录入!$C$5:$C$785,$A17,数据录入!$B$5:$B$785,AG$6)) -> 0 | AH17: =IF(OR($A17="",AH$6="",NOT(ISNUMBER($H$2))),"",SUMIFS(数据录入!$G$5:$G$785,数据录入!$C$5:$C$785,$A17,数据录入!$B$5:$B$785,AH$6)) -> 0 | AI17: =IF(OR($A17="",AI$6="",NOT(ISNUMBER($H$2))),"",SUMIFS(数据录入!$F$5:$F$785,数据录入!$C$5:$C$785,$A17,数据录入!$B$5:$B$785,AI$6)) -> 0 | AJ17: =IF(OR($A17="",AJ$6="",NOT(ISNUMBER($H$2))),"",SUMIFS(数据录入!$G$5:$G$785,数据录入!$C$5:$C$785,$A17,数据录入!$B$5:$B$785,AJ$6)) -> 0 | AK17: =IF(OR($A17="",AK$6="",NOT(ISNUMBER($H$2))),"",SUMIFS(数据录入!$F$5:$F$785,数据录入!$C$5:$C$785,$A17,数据录入!$B$5:$B$785,AK$6)) -> 0 | AL17: =IF(OR($A17="",AL$6="",NOT(ISNUMBER($H$2))),"",SUMIFS(数据录入!$G$5:$G$785,数据录入!$C$5:$C$785,$A17,数据录入!$B$5:$B$785,AL$6)) -> 0 | AM17: =IF(OR($A17="",AM$6="",NOT(ISNUMBER($H$2))),"",SUMIFS(数据录入!$F$5:$F$785,数据录入!$C$5:$C$785,$A17,数据录入!$B$5:$B$785,AM$6)) -> 0 | AN17: =IF(OR($A17="",AN$6="",NOT(ISNUMBER($H$2))),"",SUMIFS(数据录入!$G$5:$G$785,数据录入!$C$5:$C$785,$A17,数据录入!$B$5:$B$785,AN$6)) -> 0 | AO17: =IF(OR($A17="",AO$6="",NOT(ISNUMBER($H$2))),"",SUMIFS(数据录入!$F$5:$F$785,数据录入!$C$5:$C$785,$A17,数据录入!$B$5:$B$785,AO$6)) -> 0 | AP17: =IF(OR($A17="",AP$6="",NOT(ISNUMBER($H$2))),"",SUMIFS(数据录入!$G$5:$G$785,数据录入!$C$5:$C$785,$A17,数据录入!$B$5:$B$785,AP$6)) -> 0 | AQ17: =IF(OR($A17="",AQ$6="",NOT(ISNUMBER($H$2))),"",SUMIFS(数据录入!$F$5:$F$785,数据录入!$C$5:$C$785,$A17,数据录入!$B$5:$B$785,AQ$6)) -> 0 | AR17: =IF(OR($A17="",AR$6="",NOT(ISNUMBER($H$2))),"",SUMIFS(数据录入!$G$5:$G$785,数据录入!$C$5:$C$785,$A17,数据录入!$B$5:$B$785,AR$6)) -> 0 | AS17: =IF(OR($A17="",AS$6="",NOT(ISNUMBER($H$2))),"",SUMIFS(数据录入!$F$5:$F$785,数据录入!$C$5:$C$785,$A17,数据录入!$B$5:$B$785,AS$6)) -> 0 | AT17: =IF(OR($A17="",AT$6="",NOT(ISNUMBER($H$2))),"",SUMIFS(数据录入!$G$5:$G$785,数据录入!$C$5:$C$785,$A17,数据录入!$B$5:$B$785,AT$6)) -> 0 | AU17: =IF(OR($A17="",AU$6="",NOT(ISNUMBER($H$2))),"",SUMIFS(数据录入!$F$5:$F$785,数据录入!$C$5:$C$785,$A17,数据录入!$B$5:$B$785,AU$6)) -> 0 | AV17: =IF(OR($A17="",AV$6="",NOT(ISNUMBER($H$2))),"",SUMIFS(数据录入!$G$5:$G$785,数据录入!$C$5:$C$785,$A17,数据录入!$B$5:$B$785,AV$6)) -> 0 | AW17: =IF(OR($A17="",AW$6="",NOT(ISNUMBER($H$2))),"",SUMIFS(数据录入!$F$5:$F$785,数据录入!$C$5:$C$785,$A17,数据录入!$B$5:$B$785,AW$6)) -> 0 | AX17: =IF(OR($A17="",AX$6="",NOT(ISNUMBER($H$2))),"",SUMIFS(数据录入!$G$5:$G$785,数据录入!$C$5:$C$785,$A17,数据录入!$B$5:$B$785,AX$6)) -> 0 | AY17: =IF(OR($A17="",AY$6="",NOT(ISNUMBER($H$2))),"",SUMIFS(数据录入!$F$5:$F$785,数据录入!$C$5:$C$785,$A17,数据录入!$B$5:$B$785,AY$6)) -> 0 | AZ17: =IF(OR($A17="",AZ$6="",NOT(ISNUMBER($H$2))),"",SUMIFS(数据录入!$G$5:$G$785,数据录入!$C$5:$C$785,$A17,数据录入!$B$5:$B$785,AZ$6)) -> 0 | BA17: =IF(OR($A17="",BA$6="",NOT(ISNUMBER($H$2))),"",SUMIFS(数据录入!$F$5:$F$785,数据录入!$C$5:$C$785,$A17,数据录入!$B$5:$B$785,BA$6)) -> 0 | BB17: =IF(OR($A17="",BB$6="",NOT(ISNUMBER($H$2))),"",SUMIFS(数据录入!$G$5:$G$785,数据录入!$C$5:$C$785,$A17,数据录入!$B$5:$B$785,BB$6)) -> 0 | BC17: =IF(OR($A17="",BC$6="",NOT(ISNUMBER($H$2))),"",SUMIFS(数据录入!$F$5:$F$785,数据录入!$C$5:$C$785,$A17,数据录入!$B$5:$B$785,BC$6)) -> 0 | BD17: =IF(OR($A17="",BD$6="",NOT(ISNUMBER($H$2))),"",SUMIFS(数据录入!$G$5:$G$785,数据录入!$C$5:$C$785,$A17,数据录入!$B$5:$B$785,BD$6)) -> 0 | BE17: =IF(OR($A17="",BE$6="",NOT(ISNUMBER($H$2))),"",SUMIFS(数据录入!$F$5:$F$785,数据录入!$C$5:$C$785,$A17,数据录入!$B$5:$B$785,BE$6)) -> 0 | BF17: =IF(OR($A17="",BF$6="",NOT(ISNUMBER($H$2))),"",SUMIFS(数据录入!$G$5:$G$785,数据录入!$C$5:$C$785,$A17,数据录入!$B$5:$B$785,BF$6)) -> 0 | BG17: =IF(OR($A17="",BG$6="",NOT(ISNUMBER($H$2))),"",SUMIFS(数据录入!$F$5:$F$785,数据录入!$C$5:$C$785,$A17,数据录入!$B$5:$B$785,BG$6)) -> 0 | BH17: =IF(OR($A17="",BH$6="",NOT(ISNUMBER($H$2))),"",SUMIFS(数据录入!$G$5:$G$785,数据录入!$C$5:$C$785,$A17,数据录入!$B$5:$B$785,BH$6)) -> 0 | BI17: =IF(OR($A17="",BI$6="",NOT(ISNUMBER($H$2))),"",SUMIFS(数据录入!$F$5:$F$785,数据录入!$C$5:$C$785,$A17,数据录入!$B$5:$B$785,BI$6)) -> 0 | BJ17: =IF(OR($A17="",BJ$6="",NOT(ISNUMBER($H$2))),"",SUMIFS(数据录入!$G$5:$G$785,数据录入!$C$5:$C$785,$A17,数据录入!$B$5:$B$785,BJ$6)) -> 0 | BK17: =IF(OR($A17="",BK$6="",NOT(ISNUMBER($H$2))),"",SUMIFS(数据录入!$F$5:$F$785,数据录入!$C$5:$C$785,$A17,数据录入!$B$5:$B$785,BK$6)) | BL17: =IF(OR($A17="",BL$6="",NOT(ISNUMBER($H$2))),"",SUMIFS(数据录入!$G$5:$G$785,数据录入!$C$5:$C$785,$A17,数据录入!$B$5:$B$785,BL$6)) | BM17: =IF($A17="","",SUMIF($C$7:$BL$7,"收款",C17:BL17)) -> 0 | BN17: =IF($A17="","",SUMIF($C$7:$BL$7,"付款",C17:BL17)) -> 0 | BO17: =IF($A17="","",B17+BM17-BN17) -> 0
A18: 备用1 | B18: =IF(OR($A18="",NOT(ISNUMBER($H$2))),"",SUMIFS(数据录入!$H$5:$H$785,数据录入!$C$5:$C$785,$A18,数据录入!$E$5:$E$785,"期初余额",数据录入!$B$5:$B$785,"<="&$B$2)+SUMIFS(数据录入!$F$5:$F$785,数据录入!$C$5:$C$785,$A18,数据录入!$B$5:$B$785,"<"&$B$2)-SUMIFS(数据录入!$G$5:$G$785,数据录入!$C$5:$C$785,$A18,数据录入!$B$5:$B$785,"<"&$B$2)) -> 0 | C18: =IF(OR($A18="",C$6="",NOT(ISNUMBER($H$2))),"",SUMIFS(数据录入!$F$5:$F$785,数据录入!$C$5:$C$785,$A18,数据录入!$B$5:$B$785,C$6)) -> 0 | D18: =IF(OR($A18="",D$6="",NOT(ISNUMBER($H$2))),"",SUMIFS(数据录入!$G$5:$G$785,数据录入!$C$5:$C$785,$A18,数据录入!$B$5:$B$785,D$6)) -> 0 | E18: =IF(OR($A18="",E$6="",NOT(ISNUMBER($H$2))),"",SUMIFS(数据录入!$F$5:$F$785,数据录入!$C$5:$C$785,$A18,数据录入!$B$5:$B$785,E$6)) -> 0 | F18: =IF(OR($A18="",F$6="",NOT(ISNUMBER($H$2))),"",SUMIFS(数据录入!$G$5:$G$785,数据录入!$C$5:$C$785,$A18,数据录入!$B$5:$B$785,F$6)) -> 0 | G18: =IF(OR($A18="",G$6="",NOT(ISNUMBER($H$2))),"",SUMIFS(数据录入!$F$5:$F$785,数据录入!$C$5:$C$785,$A18,数据录入!$B$5:$B$785,G$6)) -> 0 | H18: =IF(OR($A18="",H$6="",NOT(ISNUMBER($H$2))),"",SUMIFS(数据录入!$G$5:$G$785,数据录入!$C$5:$C$785,$A18,数据录入!$B$5:$B$785,H$6)) -> 0 | I18: =IF(OR($A18="",I$6="",NOT(ISNUMBER($H$2))),"",SUMIFS(数据录入!$F$5:$F$785,数据录入!$C$5:$C$785,$A18,数据录入!$B$5:$B$785,I$6)) -> 0 | J18: =IF(OR($A18="",J$6="",NOT(ISNUMBER($H$2))),"",SUMIFS(数据录入!$G$5:$G$785,数据录入!$C$5:$C$785,$A18,数据录入!$B$5:$B$785,J$6)) -> 0 | K18: =IF(OR($A18="",K$6="",NOT(ISNUMBER($H$2))),"",SUMIFS(数据录入!$F$5:$F$785,数据录入!$C$5:$C$785,$A18,数据录入!$B$5:$B$785,K$6)) -> 0 | L18: =IF(OR($A18="",L$6="",NOT(ISNUMBER($H$2))),"",SUMIFS(数据录入!$G$5:$G$785,数据录入!$C$5:$C$785,$A18,数据录入!$B$5:$B$785,L$6)) -> 0 | M18: =IF(OR($A18="",M$6="",NOT(ISNUMBER($H$2))),"",SUMIFS(数据录入!$F$5:$F$785,数据录入!$C$5:$C$785,$A18,数据录入!$B$5:$B$785,M$6)) -> 0 | N18: =IF(OR($A18="",N$6="",NOT(ISNUMBER($H$2))),"",SUMIFS(数据录入!$G$5:$G$785,数据录入!$C$5:$C$785,$A18,数据录入!$B$5:$B$785,N$6)) -> 0 | O18: =IF(OR($A18="",O$6="",NOT(ISNUMBER($H$2))),"",SUMIFS(数据录入!$F$5:$F$785,数据录入!$C$5:$C$785,$A18,数据录入!$B$5:$B$785,O$6)) -> 0 | P18: =IF(OR($A18="",P$6="",NOT(ISNUMBER($H$2))),"",SUMIFS(数据录入!$G$5:$G$785,数据录入!$C$5:$C$785,$A18,数据录入!$B$5:$B$785,P$6)) -> 0 | Q18: =IF(OR($A18="",Q$6="",NOT(ISNUMBER($H$2))),"",SUMIFS(数据录入!$F$5:$F$785,数据录入!$C$5:$C$785,$A18,数据录入!$B$5:$B$785,Q$6)) -> 0 | R18: =IF(OR($A18="",R$6="",NOT(ISNUMBER($H$2))),"",SUMIFS(数据录入!$G$5:$G$785,数据录入!$C$5:$C$785,$A18,数据录入!$B$5:$B$785,R$6)) -> 0 | S18: =IF(OR($A18="",S$6="",NOT(ISNUMBER($H$2))),"",SUMIFS(数据录入!$F$5:$F$785,数据录入!$C$5:$C$785,$A18,数据录入!$B$5:$B$785,S$6)) -> 0 | T18: =IF(OR($A18="",T$6="",NOT(ISNUMBER($H$2))),"",SUMIFS(数据录入!$G$5:$G$785,数据录入!$C$5:$C$785,$A18,数据录入!$B$5:$B$785,T$6)) -> 0 | U18: =IF(OR($A18="",U$6="",NOT(ISNUMBER($H$2))),"",SUMIFS(数据录入!$F$5:$F$785,数据录入!$C$5:$C$785,$A18,数据录入!$B$5:$B$785,U$6)) -> 0 | V18: =IF(OR($A18="",V$6="",NOT(ISNUMBER($H$2))),"",SUMIFS(数据录入!$G$5:$G$785,数据录入!$C$5:$C$785,$A18,数据录入!$B$5:$B$785,V$6)) -> 0 | W18: =IF(OR($A18="",W$6="",NOT(ISNUMBER($H$2))),"",SUMIFS(数据录入!$F$5:$F$785,数据录入!$C$5:$C$785,$A18,数据录入!$B$5:$B$785,W$6)) -> 0 | X18: =IF(OR($A18="",X$6="",NOT(ISNUMBER($H$2))),"",SUMIFS(数据录入!$G$5:$G$785,数据录入!$C$5:$C$785,$A18,数据录入!$B$5:$B$785,X$6)) -> 0 | Y18: =IF(OR($A18="",Y$6="",NOT(ISNUMBER($H$2))),"",SUMIFS(数据录入!$F$5:$F$785,数据录入!$C$5:$C$785,$A18,数据录入!$B$5:$B$785,Y$6)) -> 0 | Z18: =IF(OR($A18="",Z$6="",NOT(ISNUMBER($H$2))),"",SUMIFS(数据录入!$G$5:$G$785,数据录入!$C$5:$C$785,$A18,数据录入!$B$5:$B$785,Z$6)) -> 0 | AA18: =IF(OR($A18="",AA$6="",NOT(ISNUMBER($H$2))),"",SUMIFS(数据录入!$F$5:$F$785,数据录入!$C$5:$C$785,$A18,数据录入!$B$5:$B$785,AA$6)) -> 0 | AB18: =IF(OR($A18="",AB$6="",NOT(ISNUMBER($H$2))),"",SUMIFS(数据录入!$G$5:$G$785,数据录入!$C$5:$C$785,$A18,数据录入!$B$5:$B$785,AB$6)) -> 0 | AC18: =IF(OR($A18="",AC$6="",NOT(ISNUMBER($H$2))),"",SUMIFS(数据录入!$F$5:$F$785,数据录入!$C$5:$C$785,$A18,数据录入!$B$5:$B$785,AC$6)) -> 0 | AD18: =IF(OR($A18="",AD$6="",NOT(ISNUMBER($H$2))),"",SUMIFS(数据录入!$G$5:$G$785,数据录入!$C$5:$C$785,$A18,数据录入!$B$5:$B$785,AD$6)) -> 0 | AE18: =IF(OR($A18="",AE$6="",NOT(ISNUMBER($H$2))),"",SUMIFS(数据录入!$F$5:$F$785,数据录入!$C$5:$C$785,$A18,数据录入!$B$5:$B$785,AE$6)) -> 0 | AF18: =IF(OR($A18="",AF$6="",NOT(ISNUMBER($H$2))),"",SUMIFS(数据录入!$G$5:$G$785,数据录入!$C$5:$C$785,$A18,数据录入!$B$5:$B$785,AF$6)) -> 0 | AG18: =IF(OR($A18="",AG$6="",NOT(ISNUMBER($H$2))),"",SUMIFS(数据录入!$F$5:$F$785,数据录入!$C$5:$C$785,$A18,数据录入!$B$5:$B$785,AG$6)) -> 0 | AH18: =IF(OR($A18="",AH$6="",NOT(ISNUMBER($H$2))),"",SUMIFS(数据录入!$G$5:$G$785,数据录入!$C$5:$C$785,$A18,数据录入!$B$5:$B$785,AH$6)) -> 0 | AI18: =IF(OR($A18="",AI$6="",NOT(ISNUMBER($H$2))),"",SUMIFS(数据录入!$F$5:$F$785,数据录入!$C$5:$C$785,$A18,数据录入!$B$5:$B$785,AI$6)) -> 0 | AJ18: =IF(OR($A18="",AJ$6="",NOT(ISNUMBER($H$2))),"",SUMIFS(数据录入!$G$5:$G$785,数据录入!$C$5:$C$785,$A18,数据录入!$B$5:$B$785,AJ$6)) -> 0 | AK18: =IF(OR($A18="",AK$6="",NOT(ISNUMBER($H$2))),"",SUMIFS(数据录入!$F$5:$F$785,数据录入!$C$5:$C$785,$A18,数据录入!$B$5:$B$785,AK$6)) -> 0 | AL18: =IF(OR($A18="",AL$6="",NOT(ISNUMBER($H$2))),"",SUMIFS(数据录入!$G$5:$G$785,数据录入!$C$5:$C$785,$A18,数据录入!$B$5:$B$785,AL$6)) -> 0 | AM18: =IF(OR($A18="",AM$6="",NOT(ISNUMBER($H$2))),"",SUMIFS(数据录入!$F$5:$F$785,数据录入!$C$5:$C$785,$A18,数据录入!$B$5:$B$785,AM$6)) -> 0 | AN18: =IF(OR($A18="",AN$6="",NOT(ISNUMBER($H$2))),"",SUMIFS(数据录入!$G$5:$G$785,数据录入!$C$5:$C$785,$A18,数据录入!$B$5:$B$785,AN$6)) -> 0 | AO18: =IF(OR($A18="",AO$6="",NOT(ISNUMBER($H$2))),"",SUMIFS(数据录入!$F$5:$F$785,数据录入!$C$5:$C$785,$A18,数据录入!$B$5:$B$785,AO$6)) -> 0 | AP18: =IF(OR($A18="",AP$6="",NOT(ISNUMBER($H$2))),"",SUMIFS(数据录入!$G$5:$G$785,数据录入!$C$5:$C$785,$A18,数据录入!$B$5:$B$785,AP$6)) -> 0 | AQ18: =IF(OR($A18="",AQ$6="",NOT(ISNUMBER($H$2))),"",SUMIFS(数据录入!$F$5:$F$785,数据录入!$C$5:$C$785,$A18,数据录入!$B$5:$B$785,AQ$6)) -> 0 | AR18: =IF(OR($A18="",AR$6="",NOT(ISNUMBER($H$2))),"",SUMIFS(数据录入!$G$5:$G$785,数据录入!$C$5:$C$785,$A18,数据录入!$B$5:$B$785,AR$6)) -> 0 | AS18: =IF(OR($A18="",AS$6="",NOT(ISNUMBER($H$2))),"",SUMIFS(数据录入!$F$5:$F$785,数据录入!$C$5:$C$785,$A18,数据录入!$B$5:$B$785,AS$6)) -> 0 | AT18: =IF(OR($A18="",AT$6="",NOT(ISNUMBER($H$2))),"",SUMIFS(数据录入!$G$5:$G$785,数据录入!$C$5:$C$785,$A18,数据录入!$B$5:$B$785,AT$6)) -> 0 | AU18: =IF(OR($A18="",AU$6="",NOT(ISNUMBER($H$2))),"",SUMIFS(数据录入!$F$5:$F$785,数据录入!$C$5:$C$785,$A18,数据录入!$B$5:$B$785,AU$6)) -> 0 | AV18: =IF(OR($A18="",AV$6="",NOT(ISNUMBER($H$2))),"",SUMIFS(数据录入!$G$5:$G$785,数据录入!$C$5:$C$785,$A18,数据录入!$B$5:$B$785,AV$6)) -> 0 | AW18: =IF(OR($A18="",AW$6="",NOT(ISNUMBER($H$2))),"",SUMIFS(数据录入!$F$5:$F$785,数据录入!$C$5:$C$785,$A18,数据录入!$B$5:$B$785,AW$6)) -> 0 | AX18: =IF(OR($A18="",AX$6="",NOT(ISNUMBER($H$2))),"",SUMIFS(数据录入!$G$5:$G$785,数据录入!$C$5:$C$785,$A18,数据录入!$B$5:$B$785,AX$6)) -> 0 | AY18: =IF(OR($A18="",AY$6="",NOT(ISNUMBER($H$2))),"",SUMIFS(数据录入!$F$5:$F$785,数据录入!$C$5:$C$785,$A18,数据录入!$B$5:$B$785,AY$6)) -> 0 | AZ18: =IF(OR($A18="",AZ$6="",NOT(ISNUMBER($H$2))),"",SUMIFS(数据录入!$G$5:$G$785,数据录入!$C$5:$C$785,$A18,数据录入!$B$5:$B$785,AZ$6)) -> 0 | BA18: =IF(OR($A18="",BA$6="",NOT(ISNUMBER($H$2))),"",SUMIFS(数据录入!$F$5:$F$785,数据录入!$C$5:$C$785,$A18,数据录入!$B$5:$B$785,BA$6)) -> 0 | BB18: =IF(OR($A18="",BB$6="",NOT(ISNUMBER($H$2))),"",SUMIFS(数据录入!$G$5:$G$785,数据录入!$C$5:$C$785,$A18,数据录入!$B$5:$B$785,BB$6)) -> 0 | BC18: =IF(OR($A18="",BC$6="",NOT(ISNUMBER($H$2))),"",SUMIFS(数据录入!$F$5:$F$785,数据录入!$C$5:$C$785,$A18,数据录入!$B$5:$B$785,BC$6)) -> 0 | BD18: =IF(OR($A18="",BD$6="",NOT(ISNUMBER($H$2))),"",SUMIFS(数据录入!$G$5:$G$785,数据录入!$C$5:$C$785,$A18,数据录入!$B$5:$B$785,BD$6)) -> 0 | BE18: =IF(OR($A18="",BE$6="",NOT(ISNUMBER($H$2))),"",SUMIFS(数据录入!$F$5:$F$785,数据录入!$C$5:$C$785,$A18,数据录入!$B$5:$B$785,BE$6)) -> 0 | BF18: =IF(OR($A18="",BF$6="",NOT(ISNUMBER($H$2))),"",SUMIFS(数据录入!$G$5:$G$785,数据录入!$C$5:$C$785,$A18,数据录入!$B$5:$B$785,BF$6)) -> 0 | BG18: =IF(OR($A18="",BG$6="",NOT(ISNUMBER($H$2))),"",SUMIFS(数据录入!$F$5:$F$785,数据录入!$C$5:$C$785,$A18,数据录入!$B$5:$B$785,BG$6)) -> 0 | BH18: =IF(OR($A18="",BH$6="",NOT(ISNUMBER($H$2))),"",SUMIFS(数据录入!$G$5:$G$785,数据录入!$C$5:$C$785,$A18,数据录入!$B$5:$B$785,BH$6)) -> 0 | BI18: =IF(OR($A18="",BI$6="",NOT(ISNUMBER($H$2))),"",SUMIFS(数据录入!$F$5:$F$785,数据录入!$C$5:$C$785,$A18,数据录入!$B$5:$B$785,BI$6)) -> 0 | BJ18: =IF(OR($A18="",BJ$6="",NOT(ISNUMBER($H$2))),"",SUMIFS(数据录入!$G$5:$G$785,数据录入!$C$5:$C$785,$A18,数据录入!$B$5:$B$785,BJ$6)) -> 0 | BK18: =IF(OR($A18="",BK$6="",NOT(ISNUMBER($H$2))),"",SUMIFS(数据录入!$F$5:$F$785,数据录入!$C$5:$C$785,$A18,数据录入!$B$5:$B$785,BK$6)) | BL18: =IF(OR($A18="",BL$6="",NOT(ISNUMBER($H$2))),"",SUMIFS(数据录入!$G$5:$G$785,数据录入!$C$5:$C$785,$A18,数据录入!$B$5:$B$785,BL$6)) | BM18: =IF($A18="","",SUMIF($C$7:$BL$7,"收款",C18:BL18)) -> 0 | BN18: =IF($A18="","",SUMIF($C$7:$BL$7,"付款",C18:BL18)) -> 0 | BO18: =IF($A18="","",B18+BM18-BN18) -> 0
A19: 备用2 | B19: =IF(OR($A19="",NOT(ISNUMBER($H$2))),"",SUMIFS(数据录入!$H$5:$H$785,数据录入!$C$5:$C$785,$A19,数据录入!$E$5:$E$785,"期初余额",数据录入!$B$5:$B$785,"<="&$B$2)+SUMIFS(数据录入!$F$5:$F$785,数据录入!$C$5:$C$785,$A19,数据录入!$B$5:$B$785,"<"&$B$2)-SUMIFS(数据录入!$G$5:$G$785,数据录入!$C$5:$C$785,$A19,数据录入!$B$5:$B$785,"<"&$B$2)) -> 0 | C19: =IF(OR($A19="",C$6="",NOT(ISNUMBER($H$2))),"",SUMIFS(数据录入!$F$5:$F$785,数据录入!$C$5:$C$785,$A19,数据录入!$B$5:$B$785,C$6)) -> 0 | D19: =IF(OR($A19="",D$6="",NOT(ISNUMBER($H$2))),"",SUMIFS(数据录入!$G$5:$G$785,数据录入!$C$5:$C$785,$A19,数据录入!$B$5:$B$785,D$6)) -> 0 | E19: =IF(OR($A19="",E$6="",NOT(ISNUMBER($H$2))),"",SUMIFS(数据录入!$F$5:$F$785,数据录入!$C$5:$C$785,$A19,数据录入!$B$5:$B$785,E$6)) -> 0 | F19: =IF(OR($A19="",F$6="",NOT(ISNUMBER($H$2))),"",SUMIFS(数据录入!$G$5:$G$785,数据录入!$C$5:$C$785,$A19,数据录入!$B$5:$B$785,F$6)) -> 0 | G19: =IF(OR($A19="",G$6="",NOT(ISNUMBER($H$2))),"",SUMIFS(数据录入!$F$5:$F$785,数据录入!$C$5:$C$785,$A19,数据录入!$B$5:$B$785,G$6)) -> 0 | H19: =IF(OR($A19="",H$6="",NOT(ISNUMBER($H$2))),"",SUMIFS(数据录入!$G$5:$G$785,数据录入!$C$5:$C$785,$A19,数据录入!$B$5:$B$785,H$6)) -> 0 | I19: =IF(OR($A19="",I$6="",NOT(ISNUMBER($H$2))),"",SUMIFS(数据录入!$F$5:$F$785,数据录入!$C$5:$C$785,$A19,数据录入!$B$5:$B$785,I$6)) -> 0 | J19: =IF(OR($A19="",J$6="",NOT(ISNUMBER($H$2))),"",SUMIFS(数据录入!$G$5:$G$785,数据录入!$C$5:$C$785,$A19,数据录入!$B$5:$B$785,J$6)) -> 0 | K19: =IF(OR($A19="",K$6="",NOT(ISNUMBER($H$2))),"",SUMIFS(数据录入!$F$5:$F$785,数据录入!$C$5:$C$785,$A19,数据录入!$B$5:$B$785,K$6)) -> 0 | L19: =IF(OR($A19="",L$6="",NOT(ISNUMBER($H$2))),"",SUMIFS(数据录入!$G$5:$G$785,数据录入!$C$5:$C$785,$A19,数据录入!$B$5:$B$785,L$6)) -> 0 | M19: =IF(OR($A19="",M$6="",NOT(ISNUMBER($H$2))),"",SUMIFS(数据录入!$F$5:$F$785,数据录入!$C$5:$C$785,$A19,数据录入!$B$5:$B$785,M$6)) -> 0 | N19: =IF(OR($A19="",N$6="",NOT(ISNUMBER($H$2))),"",SUMIFS(数据录入!$G$5:$G$785,数据录入!$C$5:$C$785,$A19,数据录入!$B$5:$B$785,N$6)) -> 0 | O19: =IF(OR($A19="",O$6="",NOT(ISNUMBER($H$2))),"",SUMIFS(数据录入!$F$5:$F$785,数据录入!$C$5:$C$785,$A19,数据录入!$B$5:$B$785,O$6)) -> 0 | P19: =IF(OR($A19="",P$6="",NOT(ISNUMBER($H$2))),"",SUMIFS(数据录入!$G$5:$G$785,数据录入!$C$5:$C$785,$A19,数据录入!$B$5:$B$785,P$6)) -> 0 | Q19: =IF(OR($A19="",Q$6="",NOT(ISNUMBER($H$2))),"",SUMIFS(数据录入!$F$5:$F$785,数据录入!$C$5:$C$785,$A19,数据录入!$B$5:$B$785,Q$6)) -> 0 | R19: =IF(OR($A19="",R$6="",NOT(ISNUMBER($H$2))),"",SUMIFS(数据录入!$G$5:$G$785,数据录入!$C$5:$C$785,$A19,数据录入!$B$5:$B$785,R$6)) -> 0 | S19: =IF(OR($A19="",S$6="",NOT(ISNUMBER($H$2))),"",SUMIFS(数据录入!$F$5:$F$785,数据录入!$C$5:$C$785,$A19,数据录入!$B$5:$B$785,S$6)) -> 0 | T19: =IF(OR($A19="",T$6="",NOT(ISNUMBER($H$2))),"",SUMIFS(数据录入!$G$5:$G$785,数据录入!$C$5:$C$785,$A19,数据录入!$B$5:$B$785,T$6)) -> 0 | U19: =IF(OR($A19="",U$6="",NOT(ISNUMBER($H$2))),"",SUMIFS(数据录入!$F$5:$F$785,数据录入!$C$5:$C$785,$A19,数据录入!$B$5:$B$785,U$6)) -> 0 | V19: =IF(OR($A19="",V$6="",NOT(ISNUMBER($H$2))),"",SUMIFS(数据录入!$G$5:$G$785,数据录入!$C$5:$C$785,$A19,数据录入!$B$5:$B$785,V$6)) -> 0 | W19: =IF(OR($A19="",W$6="",NOT(ISNUMBER($H$2))),"",SUMIFS(数据录入!$F$5:$F$785,数据录入!$C$5:$C$785,$A19,数据录入!$B$5:$B$785,W$6)) -> 0 | X19: =IF(OR($A19="",X$6="",NOT(ISNUMBER($H$2))),"",SUMIFS(数据录入!$G$5:$G$785,数据录入!$C$5:$C$785,$A19,数据录入!$B$5:$B$785,X$6)) -> 0 | Y19: =IF(OR($A19="",Y$6="",NOT(ISNUMBER($H$2))),"",SUMIFS(数据录入!$F$5:$F$785,数据录入!$C$5:$C$785,$A19,数据录入!$B$5:$B$785,Y$6)) -> 0 | Z19: =IF(OR($A19="",Z$6="",NOT(ISNUMBER($H$2))),"",SUMIFS(数据录入!$G$5:$G$785,数据录入!$C$5:$C$785,$A19,数据录入!$B$5:$B$785,Z$6)) -> 0 | AA19: =IF(OR($A19="",AA$6="",NOT(ISNUMBER($H$2))),"",SUMIFS(数据录入!$F$5:$F$785,数据录入!$C$5:$C$785,$A19,数据录入!$B$5:$B$785,AA$6)) -> 0 | AB19: =IF(OR($A19="",AB$6="",NOT(ISNUMBER($H$2))),"",SUMIFS(数据录入!$G$5:$G$785,数据录入!$C$5:$C$785,$A19,数据录入!$B$5:$B$785,AB$6)) -> 0 | AC19: =IF(OR($A19="",AC$6="",NOT(ISNUMBER($H$2))),"",SUMIFS(数据录入!$F$5:$F$785,数据录入!$C$5:$C$785,$A19,数据录入!$B$5:$B$785,AC$6)) -> 0 | AD19: =IF(OR($A19="",AD$6="",NOT(ISNUMBER($H$2))),"",SUMIFS(数据录入!$G$5:$G$785,数据录入!$C$5:$C$785,$A19,数据录入!$B$5:$B$785,AD$6)) -> 0 | AE19: =IF(OR($A19="",AE$6="",NOT(ISNUMBER($H$2))),"",SUMIFS(数据录入!$F$5:$F$785,数据录入!$C$5:$C$785,$A19,数据录入!$B$5:$B$785,AE$6)) -> 0 | AF19: =IF(OR($A19="",AF$6="",NOT(ISNUMBER($H$2))),"",SUMIFS(数据录入!$G$5:$G$785,数据录入!$C$5:$C$785,$A19,数据录入!$B$5:$B$785,AF$6)) -> 0 | AG19: =IF(OR($A19="",AG$6="",NOT(ISNUMBER($H$2))),"",SUMIFS(数据录入!$F$5:$F$785,数据录入!$C$5:$C$785,$A19,数据录入!$B$5:$B$785,AG$6)) -> 0 | AH19: =IF(OR($A19="",AH$6="",NOT(ISNUMBER($H$2))),"",SUMIFS(数据录入!$G$5:$G$785,数据录入!$C$5:$C$785,$A19,数据录入!$B$5:$B$785,AH$6)) -> 0 | AI19: =IF(OR($A19="",AI$6="",NOT(ISNUMBER($H$2))),"",SUMIFS(数据录入!$F$5:$F$785,数据录入!$C$5:$C$785,$A19,数据录入!$B$5:$B$785,AI$6)) -> 0 | AJ19: =IF(OR($A19="",AJ$6="",NOT(ISNUMBER($H$2))),"",SUMIFS(数据录入!$G$5:$G$785,数据录入!$C$5:$C$785,$A19,数据录入!$B$5:$B$785,AJ$6)) -> 0 | AK19: =IF(OR($A19="",AK$6="",NOT(ISNUMBER($H$2))),"",SUMIFS(数据录入!$F$5:$F$785,数据录入!$C$5:$C$785,$A19,数据录入!$B$5:$B$785,AK$6)) -> 0 | AL19: =IF(OR($A19="",AL$6="",NOT(ISNUMBER($H$2))),"",SUMIFS(数据录入!$G$5:$G$785,数据录入!$C$5:$C$785,$A19,数据录入!$B$5:$B$785,AL$6)) -> 0 | AM19: =IF(OR($A19="",AM$6="",NOT(ISNUMBER($H$2))),"",SUMIFS(数据录入!$F$5:$F$785,数据录入!$C$5:$C$785,$A19,数据录入!$B$5:$B$785,AM$6)) -> 0 | AN19: =IF(OR($A19="",AN$6="",NOT(ISNUMBER($H$2))),"",SUMIFS(数据录入!$G$5:$G$785,数据录入!$C$5:$C$785,$A19,数据录入!$B$5:$B$785,AN$6)) -> 0 | AO19: =IF(OR($A19="",AO$6="",NOT(ISNUMBER($H$2))),"",SUMIFS(数据录入!$F$5:$F$785,数据录入!$C$5:$C$785,$A19,数据录入!$B$5:$B$785,AO$6)) -> 0 | AP19: =IF(OR($A19="",AP$6="",NOT(ISNUMBER($H$2))),"",SUMIFS(数据录入!$G$5:$G$785,数据录入!$C$5:$C$785,$A19,数据录入!$B$5:$B$785,AP$6)) -> 0 | AQ19: =IF(OR($A19="",AQ$6="",NOT(ISNUMBER($H$2))),"",SUMIFS(数据录入!$F$5:$F$785,数据录入!$C$5:$C$785,$A19,数据录入!$B$5:$B$785,AQ$6)) -> 0 | AR19: =IF(OR($A19="",AR$6="",NOT(ISNUMBER($H$2))),"",SUMIFS(数据录入!$G$5:$G$785,数据录入!$C$5:$C$785,$A19,数据录入!$B$5:$B$785,AR$6)) -> 0 | AS19: =IF(OR($A19="",AS$6="",NOT(ISNUMBER($H$2))),"",SUMIFS(数据录入!$F$5:$F$785,数据录入!$C$5:$C$785,$A19,数据录入!$B$5:$B$785,AS$6)) -> 0 | AT19: =IF(OR($A19="",AT$6="",NOT(ISNUMBER($H$2))),"",SUMIFS(数据录入!$G$5:$G$785,数据录入!$C$5:$C$785,$A19,数据录入!$B$5:$B$785,AT$6)) -> 0 | AU19: =IF(OR($A19="",AU$6="",NOT(ISNUMBER($H$2))),"",SUMIFS(数据录入!$F$5:$F$785,数据录入!$C$5:$C$785,$A19,数据录入!$B$5:$B$785,AU$6)) -> 0 | AV19: =IF(OR($A19="",AV$6="",NOT(ISNUMBER($H$2))),"",SUMIFS(数据录入!$G$5:$G$785,数据录入!$C$5:$C$785,$A19,数据录入!$B$5:$B$785,AV$6)) -> 0 | AW19: =IF(OR($A19="",AW$6="",NOT(ISNUMBER($H$2))),"",SUMIFS(数据录入!$F$5:$F$785,数据录入!$C$5:$C$785,$A19,数据录入!$B$5:$B$785,AW$6)) -> 0 | AX19: =IF(OR($A19="",AX$6="",NOT(ISNUMBER($H$2))),"",SUMIFS(数据录入!$G$5:$G$785,数据录入!$C$5:$C$785,$A19,数据录入!$B$5:$B$785,AX$6)) -> 0 | AY19: =IF(OR($A19="",AY$6="",NOT(ISNUMBER($H$2))),"",SUMIFS(数据录入!$F$5:$F$785,数据录入!$C$5:$C$785,$A19,数据录入!$B$5:$B$785,AY$6)) -> 0 | AZ19: =IF(OR($A19="",AZ$6="",NOT(ISNUMBER($H$2))),"",SUMIFS(数据录入!$G$5:$G$785,数据录入!$C$5:$C$785,$A19,数据录入!$B$5:$B$785,AZ$6)) -> 0 | BA19: =IF(OR($A19="",BA$6="",NOT(ISNUMBER($H$2))),"",SUMIFS(数据录入!$F$5:$F$785,数据录入!$C$5:$C$785,$A19,数据录入!$B$5:$B$785,BA$6)) -> 0 | BB19: =IF(OR($A19="",BB$6="",NOT(ISNUMBER($H$2))),"",SUMIFS(数据录入!$G$5:$G$785,数据录入!$C$5:$C$785,$A19,数据录入!$B$5:$B$785,BB$6)) -> 0 | BC19: =IF(OR($A19="",BC$6="",NOT(ISNUMBER($H$2))),"",SUMIFS(数据录入!$F$5:$F$785,数据录入!$C$5:$C$785,$A19,数据录入!$B$5:$B$785,BC$6)) -> 0 | BD19: =IF(OR($A19="",BD$6="",NOT(ISNUMBER($H$2))),"",SUMIFS(数据录入!$G$5:$G$785,数据录入!$C$5:$C$785,$A19,数据录入!$B$5:$B$785,BD$6)) -> 0 | BE19: =IF(OR($A19="",BE$6="",NOT(ISNUMBER($H$2))),"",SUMIFS(数据录入!$F$5:$F$785,数据录入!$C$5:$C$785,$A19,数据录入!$B$5:$B$785,BE$6)) -> 0 | BF19: =IF(OR($A19="",BF$6="",NOT(ISNUMBER($H$2))),"",SUMIFS(数据录入!$G$5:$G$785,数据录入!$C$5:$C$785,$A19,数据录入!$B$5:$B$785,BF$6)) -> 0 | BG19: =IF(OR($A19="",BG$6="",NOT(ISNUMBER($H$2))),"",SUMIFS(数据录入!$F$5:$F$785,数据录入!$C$5:$C$785,$A19,数据录入!$B$5:$B$785,BG$6)) -> 0 | BH19: =IF(OR($A19="",BH$6="",NOT(ISNUMBER($H$2))),"",SUMIFS(数据录入!$G$5:$G$785,数据录入!$C$5:$C$785,$A19,数据录入!$B$5:$B$785,BH$6)) -> 0 | BI19: =IF(OR($A19="",BI$6="",NOT(ISNUMBER($H$2))),"",SUMIFS(数据录入!$F$5:$F$785,数据录入!$C$5:$C$785,$A19,数据录入!$B$5:$B$785,BI$6)) -> 0 | BJ19: =IF(OR($A19="",BJ$6="",NOT(ISNUMBER($H$2))),"",SUMIFS(数据录入!$G$5:$G$785,数据录入!$C$5:$C$785,$A19,数据录入!$B$5:$B$785,BJ$6)) -> 0 | BK19: =IF(OR($A19="",BK$6="",NOT(ISNUMBER($H$2))),"",SUMIFS(数据录入!$F$5:$F$785,数据录入!$C$5:$C$785,$A19,数据录入!$B$5:$B$785,BK$6)) | BL19: =IF(OR($A19="",BL$6="",NOT(ISNUMBER($H$2))),"",SUMIFS(数据录入!$G$5:$G$785,数据录入!$C$5:$C$785,$A19,数据录入!$B$5:$B$785,BL$6)) | BM19: =IF($A19="","",SUMIF($C$7:$BL$7,"收款",C19:BL19)) -> 0 | BN19: =IF($A19="","",SUMIF($C$7:$BL$7,"付款",C19:BL19)) -> 0 | BO19: =IF($A19="","",B19+BM19-BN19) -> 0
... A21: 备用4 | B21: =IF(OR($A21="",NOT(ISNUMBER($H$2))),"",SUMIFS(数据录入!$H$5:$H$785,数据录入!$C$5:$C$785,$A21,数据录入!$E$5:$E$785,"期初余额",数据录入!$B$5:$B$785,"<="&$B$2)+SUMIFS(数据录入!$F$5:$F$785,数据录入!$C$5:$C$785,$A21,数据录入!$B$5:$B$785,"<"&$B$2)-SUMIFS(数据录入!$G$5:$G$785,数据录入!$C$5:$C$785,$A21,数据录入!$B$5:$B$785,"<"&$B$2)) -> 0 | C21: =IF(OR($A21="",C$6="",NOT(ISNUMBER($H$2))),"",SUMIFS(数据录入!$F$5:$F$785,数据录入!$C$5:$C$785,$A21,数据录入!$B$5:$B$785,C$6)) -> 0 | D21: =IF(OR($A21="",D$6="",NOT(ISNUMBER($H$2))),"",SUMIFS(数据录入!$G$5:$G$785,数据录入!$C$5:$C$785,$A21,数据录入!$B$5:$B$785,D$6)) -> 0 | E21: =IF(OR($A21="",E$6="",NOT(ISNUMBER($H$2))),"",SUMIFS(数据录入!$F$5:$F$785,数据录入!$C$5:$C$785,$A21,数据录入!$B$5:$B$785,E$6)) -> 0 | F21: =IF(OR($A21="",F$6="",NOT(ISNUMBER($H$2))),"",SUMIFS(数据录入!$G$5:$G$785,数据录入!$C$5:$C$785,$A21,数据录入!$B$5:$B$785,F$6)) -> 0 | G21: =IF(OR($A21="",G$6="",NOT(ISNUMBER($H$2))),"",SUMIFS(数据录入!$F$5:$F$785,数据录入!$C$5:$C$785,$A21,数据录入!$B$5:$B$785,G$6)) -> 0 | H21: =IF(OR($A21="",H$6="",NOT(ISNUMBER($H$2))),"",SUMIFS(数据录入!$G$5:$G$785,数据录入!$C$5:$C$785,$A21,数据录入!$B$5:$B$785,H$6)) -> 0 | I21: =IF(OR($A21="",I$6="",NOT(ISNUMBER($H$2))),"",SUMIFS(数据录入!$F$5:$F$785,数据录入!$C$5:$C$785,$A21,数据录入!$B$5:$B$785,I$6)) -> 0 | J21: =IF(OR($A21="",J$6="",NOT(ISNUMBER($H$2))),"",SUMIFS(数据录入!$G$5:$G$785,数据录入!$C$5:$C$785,$A21,数据录入!$B$5:$B$785,J$6)) -> 0 | K21: =IF(OR($A21="",K$6="",NOT(ISNUMBER($H$2))),"",SUMIFS(数据录入!$F$5:$F$785,数据录入!$C$5:$C$785,$A21,数据录入!$B$5:$B$785,K$6)) -> 0 | L21: =IF(OR($A21="",L$6="",NOT(ISNUMBER($H$2))),"",SUMIFS(数据录入!$G$5:$G$785,数据录入!$C$5:$C$785,$A21,数据录入!$B$5:$B$785,L$6)) -> 0 | M21: =IF(OR($A21="",M$6="",NOT(ISNUMBER($H$2))),"",SUMIFS(数据录入!$F$5:$F$785,数据录入!$C$5:$C$785,$A21,数据录入!$B$5:$B$785,M$6)) -> 0 | N21: =IF(OR($A21="",N$6="",NOT(ISNUMBER($H$2))),"",SUMIFS(数据录入!$G$5:$G$785,数据录入!$C$5:$C$785,$A21,数据录入!$B$5:$B$785,N$6)) -> 0 | O21: =IF(OR($A21="",O$6="",NOT(ISNUMBER($H$2))),"",SUMIFS(数据录入!$F$5:$F$785,数据录入!$C$5:$C$785,$A21,数据录入!$B$5:$B$785,O$6)) -> 0 | P21: =IF(OR($A21="",P$6="",NOT(ISNUMBER($H$2))),"",SUMIFS(数据录入!$G$5:$G$785,数据录入!$C$5:$C$785,$A21,数据录入!$B$5:$B$785,P$6)) -> 0 | Q21: =IF(OR($A21="",Q$6="",NOT(ISNUMBER($H$2))),"",SUMIFS(数据录入!$F$5:$F$785,数据录入!$C$5:$C$785,$A21,数据录入!$B$5:$B$785,Q$6)) -> 0 | R21: =IF(OR($A21="",R$6="",NOT(ISNUMBER($H$2))),"",SUMIFS(数据录入!$G$5:$G$785,数据录入!$C$5:$C$785,$A21,数据录入!$B$5:$B$785,R$6)) -> 0 | S21: =IF(OR($A21="",S$6="",NOT(ISNUMBER($H$2))),"",SUMIFS(数据录入!$F$5:$F$785,数据录入!$C$5:$C$785,$A21,数据录入!$B$5:$B$785,S$6)) -> 0 | T21: =IF(OR($A21="",T$6="",NOT(ISNUMBER($H$2))),"",SUMIFS(数据录入!$G$5:$G$785,数据录入!$C$5:$C$785,$A21,数据录入!$B$5:$B$785,T$6)) -> 0 | U21: =IF(OR($A21="",U$6="",NOT(ISNUMBER($H$2))),"",SUMIFS(数据录入!$F$5:$F$785,数据录入!$C$5:$C$785,$A21,数据录入!$B$5:$B$785,U$6)) -> 0 | V21: =IF(OR($A21="",V$6="",NOT(ISNUMBER($H$2))),"",SUMIFS(数据录入!$G$5:$G$785,数据录入!$C$5:$C$785,$A21,数据录入!$B$5:$B$785,V$6)) -> 0 | W21: =IF(OR($A21="",W$6="",NOT(ISNUMBER($H$2))),"",SUMIFS(数据录入!$F$5:$F$785,数据录入!$C$5:$C$785,$A21,数据录入!$B$5:$B$785,W$6)) -> 0 | X21: =IF(OR($A21="",X$6="",NOT(ISNUMBER($H$2))),"",SUMIFS(数据录入!$G$5:$G$785,数据录入!$C$5:$C$785,$A21,数据录入!$B$5:$B$785,X$6)) -> 0 | Y21: =IF(OR($A21="",Y$6="",NOT(ISNUMBER($H$2))),"",SUMIFS(数据录入!$F$5:$F$785,数据录入!$C$5:$C$785,$A21,数据录入!$B$5:$B$785,Y$6)) -> 0 | Z21: =IF(OR($A21="",Z$6="",NOT(ISNUMBER($H$2))),"",SUMIFS(数据录入!$G$5:$G$785,数据录入!$C$5:$C$785,$A21,数据录入!$B$5:$B$785,Z$6)) -> 0 | AA21: =IF(OR($A21="",AA$6="",NOT(ISNUMBER($H$2))),"",SUMIFS(数据录入!$F$5:$F$785,数据录入!$C$5:$C$785,$A21,数据录入!$B$5:$B$785,AA$6)) -> 0 | AB21: =IF(OR($A21="",AB$6="",NOT(ISNUMBER($H$2))),"",SUMIFS(数据录入!$G$5:$G$785,数据录入!$C$5:$C$785,$A21,数据录入!$B$5:$B$785,AB$6)) -> 0 | AC21: =IF(OR($A21="",AC$6="",NOT(ISNUMBER($H$2))),"",SUMIFS(数据录入!$F$5:$F$785,数据录入!$C$5:$C$785,$A21,数据录入!$B$5:$B$785,AC$6)) -> 0 | AD21: =IF(OR($A21="",AD$6="",NOT(ISNUMBER($H$2))),"",SUMIFS(数据录入!$G$5:$G$785,数据录入!$C$5:$C$785,$A21,数据录入!$B$5:$B$785,AD$6)) -> 0 | AE21: =IF(OR($A21="",AE$6="",NOT(ISNUMBER($H$2))),"",SUMIFS(数据录入!$F$5:$F$785,数据录入!$C$5:$C$785,$A21,数据录入!$B$5:$B$785,AE$6)) -> 0 | AF21: =IF(OR($A21="",AF$6="",NOT(ISNUMBER($H$2))),"",SUMIFS(数据录入!$G$5:$G$785,数据录入!$C$5:$C$785,$A21,数据录入!$B$5:$B$785,AF$6)) -> 0 | AG21: =IF(OR($A21="",AG$6="",NOT(ISNUMBER($H$2))),"",SUMIFS(数据录入!$F$5:$F$785,数据录入!$C$5:$C$785,$A21,数据录入!$B$5:$B$785,AG$6)) -> 0 | AH21: =IF(OR($A21="",AH$6="",NOT(ISNUMBER($H$2))),"",SUMIFS(数据录入!$G$5:$G$785,数据录入!$C$5:$C$785,$A21,数据录入!$B$5:$B$785,AH$6)) -> 0 | AI21: =IF(OR($A21="",AI$6="",NOT(ISNUMBER($H$2))),"",SUMIFS(数据录入!$F$5:$F$785,数据录入!$C$5:$C$785,$A21,数据录入!$B$5:$B$785,AI$6)) -> 0 | AJ21: =IF(OR($A21="",AJ$6="",NOT(ISNUMBER($H$2))),"",SUMIFS(数据录入!$G$5:$G$785,数据录入!$C$5:$C$785,$A21,数据录入!$B$5:$B$785,AJ$6)) -> 0 | AK21: =IF(OR($A21="",AK$6="",NOT(ISNUMBER($H$2))),"",SUMIFS(数据录入!$F$5:$F$785,数据录入!$C$5:$C$785,$A21,数据录入!$B$5:$B$785,AK$6)) -> 0 | AL21: =IF(OR($A21="",AL$6="",NOT(ISNUMBER($H$2))),"",SUMIFS(数据录入!$G$5:$G$785,数据录入!$C$5:$C$785,$A21,数据录入!$B$5:$B$785,AL$6)) -> 0 | AM21: =IF(OR($A21="",AM$6="",NOT(ISNUMBER($H$2))),"",SUMIFS(数据录入!$F$5:$F$785,数据录入!$C$5:$C$785,$A21,数据录入!$B$5:$B$785,AM$6)) -> 0 | AN21: =IF(OR($A21="",AN$6="",NOT(ISNUMBER($H$2))),"",SUMIFS(数据录入!$G$5:$G$785,数据录入!$C$5:$C$785,$A21,数据录入!$B$5:$B$785,AN$6)) -> 0 | AO21: =IF(OR($A21="",AO$6="",NOT(ISNUMBER($H$2))),"",SUMIFS(数据录入!$F$5:$F$785,数据录入!$C$5:$C$785,$A21,数据录入!$B$5:$B$785,AO$6)) -> 0 | AP21: =IF(OR($A21="",AP$6="",NOT(ISNUMBER($H$2))),"",SUMIFS(数据录入!$G$5:$G$785,数据录入!$C$5:$C$785,$A21,数据录入!$B$5:$B$785,AP$6)) -> 0 | AQ21: =IF(OR($A21="",AQ$6="",NOT(ISNUMBER($H$2))),"",SUMIFS(数据录入!$F$5:$F$785,数据录入!$C$5:$C$785,$A21,数据录入!$B$5:$B$785,AQ$6)) -> 0 | AR21: =IF(OR($A21="",AR$6="",NOT(ISNUMBER($H$2))),"",SUMIFS(数据录入!$G$5:$G$785,数据录入!$C$5:$C$785,$A21,数据录入!$B$5:$B$785,AR$6)) -> 0 | AS21: =IF(OR($A21="",AS$6="",NOT(ISNUMBER($H$2))),"",SUMIFS(数据录入!$F$5:$F$785,数据录入!$C$5:$C$785,$A21,数据录入!$B$5:$B$785,AS$6)) -> 0 | AT21: =IF(OR($A21="",AT$6="",NOT(ISNUMBER($H$2))),"",SUMIFS(数据录入!$G$5:$G$785,数据录入!$C$5:$C$785,$A21,数据录入!$B$5:$B$785,AT$6)) -> 0 | AU21: =IF(OR($A21="",AU$6="",NOT(ISNUMBER($H$2))),"",SUMIFS(数据录入!$F$5:$F$785,数据录入!$C$5:$C$785,$A21,数据录入!$B$5:$B$785,AU$6)) -> 0 | AV21: =IF(OR($A21="",AV$6="",NOT(ISNUMBER($H$2))),"",SUMIFS(数据录入!$G$5:$G$785,数据录入!$C$5:$C$785,$A21,数据录入!$B$5:$B$785,AV$6)) -> 0 | AW21: =IF(OR($A21="",AW$6="",NOT(ISNUMBER($H$2))),"",SUMIFS(数据录入!$F$5:$F$785,数据录入!$C$5:$C$785,$A21,数据录入!$B$5:$B$785,AW$6)) -> 0 | AX21: =IF(OR($A21="",AX$6="",NOT(ISNUMBER($H$2))),"",SUMIFS(数据录入!$G$5:$G$785,数据录入!$C$5:$C$785,$A21,数据录入!$B$5:$B$785,AX$6)) -> 0 | AY21: =IF(OR($A21="",AY$6="",NOT(ISNUMBER($H$2))),"",SUMIFS(数据录入!$F$5:$F$785,数据录入!$C$5:$C$785,$A21,数据录入!$B$5:$B$785,AY$6)) -> 0 | AZ21: =IF(OR($A21="",AZ$6="",NOT(ISNUMBER($H$2))),"",SUMIFS(数据录入!$G$5:$G$785,数据录入!$C$5:$C$785,$A21,数据录入!$B$5:$B$785,AZ$6)) -> 0 | BA21: =IF(OR($A21="",BA$6="",NOT(ISNUMBER($H$2))),"",SUMIFS(数据录入!$F$5:$F$785,数据录入!$C$5:$C$785,$A21,数据录入!$B$5:$B$785,BA$6)) -> 0 | BB21: =IF(OR($A21="",BB$6="",NOT(ISNUMBER($H$2))),"",SUMIFS(数据录入!$G$5:$G$785,数据录入!$C$5:$C$785,$A21,数据录入!$B$5:$B$785,BB$6)) -> 0 | BC21: =IF(OR($A21="",BC$6="",NOT(ISNUMBER($H$2))),"",SUMIFS(数据录入!$F$5:$F$785,数据录入!$C$5:$C$785,$A21,数据录入!$B$5:$B$785,BC$6)) -> 0 | BD21: =IF(OR($A21="",BD$6="",NOT(ISNUMBER($H$2))),"",SUMIFS(数据录入!$G$5:$G$785,数据录入!$C$5:$C$785,$A21,数据录入!$B$5:$B$785,BD$6)) -> 0 | BE21: =IF(OR($A21="",BE$6="",NOT(ISNUMBER($H$2))),"",SUMIFS(数据录入!$F$5:$F$785,数据录入!$C$5:$C$785,$A21,数据录入!$B$5:$B$785,BE$6)) -> 0 | BF21: =IF(OR($A21="",BF$6="",NOT(ISNUMBER($H$2))),"",SUMIFS(数据录入!$G$5:$G$785,数据录入!$C$5:$C$785,$A21,数据录入!$B$5:$B$785,BF$6)) -> 0 | BG21: =IF(OR($A21="",BG$6="",NOT(ISNUMBER($H$2))),"",SUMIFS(数据录入!$F$5:$F$785,数据录入!$C$5:$C$785,$A21,数据录入!$B$5:$B$785,BG$6)) -> 0 | BH21: =IF(OR($A21="",BH$6="",NOT(ISNUMBER($H$2))),"",SUMIFS(数据录入!$G$5:$G$785,数据录入!$C$5:$C$785,$A21,数据录入!$B$5:$B$785,BH$6)) -> 0 | BI21: =IF(OR($A21="",BI$6="",NOT(ISNUMBER($H$2))),"",SUMIFS(数据录入!$F$5:$F$785,数据录入!$C$5:$C$785,$A21,数据录入!$B$5:$B$785,BI$6)) -> 0 | BJ21: =IF(OR($A21="",BJ$6="",NOT(ISNUMBER($H$2))),"",SUMIFS(数据录入!$G$5:$G$785,数据录入!$C$5:$C$785,$A21,数据录入!$B$5:$B$785,BJ$6)) -> 0 | BK21: =IF(OR($A21="",BK$6="",NOT(ISNUMBER($H$2))),"",SUMIFS(数据录入!$F$5:$F$785,数据录入!$C$5:$C$785,$A21,数据录入!$B$5:$B$785,BK$6)) | BL21: =IF(OR($A21="",BL$6="",NOT(ISNUMBER($H$2))),"",SUMIFS(数据录入!$G$5:$G$785,数据录入!$C$5:$C$785,$A21,数据录入!$B$5:$B$785,BL$6)) | BM21: =IF($A21="","",SUMIF($C$7:$BL$7,"收款",C21:BL21)) -> 0 | BN21: =IF($A21="","",SUMIF($C$7:$BL$7,"付款",C21:BL21)) -> 0 | BO21: =IF($A21="","",B21+BM21-BN21) -> 0
A22: 合计 | B22: =SUM(B8:B21) -> 719880.9 | C22: =SUM(C8:C21) -> 3298642 | D22: =SUM(D8:D21) -> 3683076 | E22: =SUM(E8:E21) -> 1020900 | F22: =SUM(F8:F21) -> 1020000 | G22: =SUM(G8:G21) -> 300500 | H22: =SUM(H8:H21) -> 20900 | I22: =SUM(I8:I21) -> 103050 | ... BO22: =SUM(BO8:BO21) -> 643942.29
A24: 多账户资金日报表 | H24: 多帐户资金汇总表（月度汇总）
B25: 日期： | C25: 46280 | F25: 单位：元 | I25: 月份： | K25: 46266
A26: 序号 | B26: 账户 | C26: 昨日余额 | D26: 本日收入 | E26: 本日支出 | F26: 本日余额 | H26: 序号 | I26: 账号名称 | J26: 期初余额 | K26: 本月收入 | L26: 本月支出 | M26: 结余 | P26: 本列不要删除
A27: 1 | B27: 金辉稠州 | C27: =IF($B27="","",SUMIFS(数据录入!$H$5:$H$20000,数据录入!$C$5:$C$20000,$B27,数据录入!$E$5:$E$20000,"期初余额",数据录入!$B$5:$B$20000,"<="&$C$25)+SUMIFS(数据录入!$F$5:$F$20000,数据录入!$C$5:$C$20000,$B27,数据录入!$B$5:$B$20000,"<"&$C$25)-SUMIFS(数据录入!$G$5:$G$20000,数据录入!$C$5:$C$20000,$B27,数据录入!$B$5:$B$20000,"<"&$C$25)) -> 82980.2 | D27: =IF($B27="","",SUMIFS(数据录入!$F$5:$F$199999,数据录入!$C$5:$C$199999,$B27,数据录入!$B$5:$B$199999,$C$25)) -> 3920 | E27: =IF($B27="","",SUMIFS(数据录入!$G$5:$G$199999,数据录入!$C$5:$C$199999,$B27,数据录入!$B$5:$B$199999,$C$25)) -> 26236.61 | F27: =IF($B27="","",C27+D27-E27) -> 60663.59 | H27: 1 | I27: 金辉稠州 | J27: =IF($I27="","",SUMIFS(数据录入!$H$5:$H$20000,数据录入!$C$5:$C$20000,$I27,数据录入!$E$5:$E$20000,"期初余额",数据录入!$B$5:$B$20000,"<="&DATE(YEAR($K$25),MONTH($K$25),1))+SUMIFS(数据录入!$F$5:$F$20000,数据录入!$C$5:$C$20000,$I27,数据录入!$B$5:$B$20000,"<"&DATE(YEAR($K$25),MONTH($K$25),1))-SUMIFS(数据录入!$G$5:$G$20000,数据录入!$C$5:$C$20000,$I27,数据录入!$B$5:$B$20000,"<"&DATE(YEAR($K$25),MONTH($K$25),1))) -> 552046.24 | K27: =IF($I27="","",SUMIFS(数据录入!$F$5:$F$20000,数据录入!$C$5:$C$20000,$I27,数据录入!$B$5:$B$20000,">="&DATE(YEAR($K$25),MONTH($K$25),1),数据录入!$B$5:$B$20000,"<="&DATE(YEAR($K$25),MONTH($K$25)+1,0))) -> 728060 | L27: =IF($I27="","",SUMIFS(数据录入!$G$5:$G$20000,数据录入!$C$5:$C$20000,$I27,数据录入!$B$5:$B$20000,">="&DATE(YEAR($K$25),MONTH($K$25),1),数据录入!$B$5:$B$20000,"<="&DATE(YEAR($K$25),MONTH($K$25)+1,0))) -> 1219442.6 | M27: =IF($I27="","",J27+K27-L27) -> 60663.59 | P27: 月份筛选列
A28: 2 | B28: 典当微信 | C28: =IF($B28="","",SUMIFS(数据录入!$H$5:$H$20000,数据录入!$C$5:$C$20000,$B28,数据录入!$E$5:$E$20000,"期初余额",数据录入!$B$5:$B$20000,"<="&$C$25)+SUMIFS(数据录入!$F$5:$F$20000,数据录入!$C$5:$C$20000,$B28,数据录入!$B$5:$B$20000,"<"&$C$25)-SUMIFS(数据录入!$G$5:$G$20000,数据录入!$C$5:$C$20000,$B28,数据录入!$B$5:$B$20000,"<"&$C$25)) -> 175701.86 | D28: =IF($B28="","",SUMIFS(数据录入!$F$5:$F$199999,数据录入!$C$5:$C$199999,$B28,数据录入!$B$5:$B$199999,$C$25)) -> 5054 | E28: =IF($B28="","",SUMIFS(数据录入!$G$5:$G$199999,数据录入!$C$5:$C$199999,$B28,数据录入!$B$5:$B$199999,$C$25)) -> 0 | F28: =IF($B28="","",C28+D28-E28) -> 180755.86 | H28: 2 | I28: 典当微信 | J28: =IF($I28="","",SUMIFS(数据录入!$H$5:$H$20000,数据录入!$C$5:$C$20000,$I28,数据录入!$E$5:$E$20000,"期初余额",数据录入!$B$5:$B$20000,"<="&DATE(YEAR($K$25),MONTH($K$25),1))+SUMIFS(数据录入!$F$5:$F$20000,数据录入!$C$5:$C$20000,$I28,数据录入!$B$5:$B$20000,"<"&DATE(YEAR($K$25),MONTH($K$25),1))-SUMIFS(数据录入!$G$5:$G$20000,数据录入!$C$5:$C$20000,$I28,数据录入!$B$5:$B$20000,"<"&DATE(YEAR($K$25),MONTH($K$25),1))) -> 108224.12 | K28: =IF($I28="","",SUMIFS(数据录入!$F$5:$F$20000,数据录入!$C$5:$C$20000,$I28,数据录入!$B$5:$B$20000,">="&DATE(YEAR($K$25),MONTH($K$25),1),数据录入!$B$5:$B$20000,"<="&DATE(YEAR($K$25),MONTH($K$25)+1,0))) -> 79330.74 | L28: =IF($I28="","",SUMIFS(数据录入!$G$5:$G$20000,数据录入!$C$5:$C$20000,$I28,数据录入!$B$5:$B$20000,">="&DATE(YEAR($K$25),MONTH($K$25),1),数据录入!$B$5:$B$20000,"<="&DATE(YEAR($K$25),MONTH($K$25)+1,0))) -> 6799 | M28: =IF($I28="","",J28+K28-L28) -> 180755.86 | P28: 46023
A29: 3 | B29: 林总浦发 | C29: =IF($B29="","",SUMIFS(数据录入!$H$5:$H$20000,数据录入!$C$5:$C$20000,$B29,数据录入!$E$5:$E$20000,"期初余额",数据录入!$B$5:$B$20000,"<="&$C$25)+SUMIFS(数据录入!$F$5:$F$20000,数据录入!$C$5:$C$20000,$B29,数据录入!$B$5:$B$20000,"<"&$C$25)-SUMIFS(数据录入!$G$5:$G$20000,数据录入!$C$5:$C$20000,$B29,数据录入!$B$5:$B$20000,"<"&$C$25)) -> 1624555 | D29: =IF($B29="","",SUMIFS(数据录入!$F$5:$F$199999,数据录入!$C$5:$C$199999,$B29,数据录入!$B$5:$B$199999,$C$25)) -> 0 | E29: =IF($B29="","",SUMIFS(数据录入!$G$5:$G$199999,数据录入!$C$5:$C$199999,$B29,数据录入!$B$5:$B$199999,$C$25)) -> 0 | F29: =IF($B29="","",C29+D29-E29) -> 1624555 | H29: 3 | I29: 林总浦发 | J29: =IF($I29="","",SUMIFS(数据录入!$H$5:$H$20000,数据录入!$C$5:$C$20000,$I29,数据录入!$E$5:$E$20000,"期初余额",数据录入!$B$5:$B$20000,"<="&DATE(YEAR($K$25),MONTH($K$25),1))+SUMIFS(数据录入!$F$5:$F$20000,数据录入!$C$5:$C$20000,$I29,数据录入!$B$5:$B$20000,"<"&DATE(YEAR($K$25),MONTH($K$25),1))-SUMIFS(数据录入!$G$5:$G$20000,数据录入!$C$5:$C$20000,$I29,数据录入!$B$5:$B$20000,"<"&DATE(YEAR($K$25),MONTH($K$25),1))) -> 21228.42 | K29: =IF($I29="","",SUMIFS(数据录入!$F$5:$F$20000,数据录入!$C$5:$C$20000,$I29,数据录入!$B$5:$B$20000,">="&DATE(YEAR($K$25),MONTH($K$25),1),数据录入!$B$5:$B$20000,"<="&DATE(YEAR($K$25),MONTH($K$25)+1,0))) -> 2213333.3 | L29: =IF($I29="","",SUMIFS(数据录入!$G$5:$G$20000,数据录入!$C$5:$C$20000,$I29,数据录入!$B$5:$B$20000,">="&DATE(YEAR($K$25),MONTH($K$25),1),数据录入!$B$5:$B$20000,"<="&DATE(YEAR($K$25),MONTH($K$25)+1,0))) -> 610006.74 | M29: =IF($I29="","",J29+K29-L29) -> 1624555 | P29: 46054
A30: 4 | B30: 吴姐建行 | C30: =IF($B30="","",SUMIFS(数据录入!$H$5:$H$20000,数据录入!$C$5:$C$20000,$B30,数据录入!$E$5:$E$20000,"期初余额",数据录入!$B$5:$B$20000,"<="&$C$25)+SUMIFS(数据录入!$F$5:$F$20000,数据录入!$C$5:$C$20000,$B30,数据录入!$B$5:$B$20000,"<"&$C$25)-SUMIFS(数据录入!$G$5:$G$20000,数据录入!$C$5:$C$20000,$B30,数据录入!$B$5:$B$20000,"<"&$C$25)) -> 119821.18 | D30: =IF($B30="","",SUMIFS(数据录入!$F$5:$F$199999,数据录入!$C$5:$C$199999,$B30,数据录入!$B$5:$B$199999,$C$25)) -> 0 | E30: =IF($B30="","",SUMIFS(数据录入!$G$5:$G$199999,数据录入!$C$5:$C$199999,$B30,数据录入!$B$5:$B$199999,$C$25)) -> 0 | F30: =IF($B30="","",C30+D30-E30) -> 119821.18 | H30: 4 | I30: 吴姐建行 | J30: =IF($I30="","",SUMIFS(数据录入!$H$5:$H$20000,数据录入!$C$5:$C$20000,$I30,数据录入!$E$5:$E$20000,"期初余额",数据录入!$B$5:$B$20000,"<="&DATE(YEAR($K$25),MONTH($K$25),1))+SUMIFS(数据录入!$F$5:$F$20000,数据录入!$C$5:$C$20000,$I30,数据录入!$B$5:$B$20000,"<"&DATE(YEAR($K$25),MONTH($K$25),1))-SUMIFS(数据录入!$G$5:$G$20000,数据录入!$C$5:$C$20000,$I30,数据录入!$B$5:$B$20000,"<"&DATE(YEAR($K$25),MONTH($K$25),1))) -> 77688.18 | K30: =IF($I30="","",SUMIFS(数据录入!$F$5:$F$20000,数据录入!$C$5:$C$20000,$I30,数据录入!$B$5:$B$20000,">="&DATE(YEAR($K$25),MONTH($K$25),1),数据录入!$B$5:$B$20000,"<="&DATE(YEAR($K$25),MONTH($K$25)+1,0))) -> 42133 | L30: =IF($I30="","",SUMIFS(数据录入!$G$5:$G$20000,数据录入!$C$5:$C$20000,$I30,数据录入!$B$5:$B$20000,">="&DATE(YEAR($K$25),MONTH($K$25),1),数据录入!$B$5:$B$20000,"<="&DATE(YEAR($K$25),MONTH($K$25)+1,0))) -> 0 | M30: =IF($I30="","",J30+K30-L30) -> 119821.18 | P30: 46082
A31: 5 | B31: 吴姐民生 | C31: =IF($B31="","",SUMIFS(数据录入!$H$5:$H$20000,数据录入!$C$5:$C$20000,$B31,数据录入!$E$5:$E$20000,"期初余额",数据录入!$B$5:$B$20000,"<="&$C$25)+SUMIFS(数据录入!$F$5:$F$20000,数据录入!$C$5:$C$20000,$B31,数据录入!$B$5:$B$20000,"<"&$C$25)-SUMIFS(数据录入!$G$5:$G$20000,数据录入!$C$5:$C$20000,$B31,数据录入!$B$5:$B$20000,"<"&$C$25)) -> 9278.44 | D31: =IF($B31="","",SUMIFS(数据录入!$F$5:$F$199999,数据录入!$C$5:$C$199999,$B31,数据录入!$B$5:$B$199999,$C$25)) -> 2500 | E31: =IF($B31="","",SUMIFS(数据录入!$G$5:$G$199999,数据录入!$C$5:$C$199999,$B31,数据录入!$B$5:$B$199999,$C$25)) -> 0 | F31: =IF($B31="","",C31+D31-E31) -> 11778.44 | H31: 5 | I31: 吴姐民生 | J31: =IF($I31="","",SUMIFS(数据录入!$H$5:$H$20000,数据录入!$C$5:$C$20000,$I31,数据录入!$E$5:$E$20000,"期初余额",数据录入!$B$5:$B$20000,"<="&DATE(YEAR($K$25),MONTH($K$25),1))+SUMIFS(数据录入!$F$5:$F$20000,数据录入!$C$5:$C$20000,$I31,数据录入!$B$5:$B$20000,"<"&DATE(YEAR($K$25),MONTH($K$25),1))-SUMIFS(数据录入!$G$5:$G$20000,数据录入!$C$5:$C$20000,$I31,数据录入!$B$5:$B$20000,"<"&DATE(YEAR($K$25),MONTH($K$25),1))) -> 2803.44 | K31: =IF($I31="","",SUMIFS(数据录入!$F$5:$F$20000,数据录入!$C$5:$C$20000,$I31,数据录入!$B$5:$B$20000,">="&DATE(YEAR($K$25),MONTH($K$25),1),数据录入!$B$5:$B$20000,"<="&DATE(YEAR($K$25),MONTH($K$25)+1,0))) -> 8975 | L31: =IF($I31="","",SUMIFS(数据录入!$G$5:$G$20000,数据录入!$C$5:$C$20000,$I31,数据录入!$B$5:$B$20000,">="&DATE(YEAR($K$25),MONTH($K$25),1),数据录入!$B$5:$B$20000,"<="&DATE(YEAR($K$25),MONTH($K$25)+1,0))) -> 0 | M31: =IF($I31="","",J31+K31-L31) -> 11778.44 | P31: 46113
A32: 6 | B32: 吴建忠浦发 | C32: =IF($B32="","",SUMIFS(数据录入!$H$5:$H$20000,数据录入!$C$5:$C$20000,$B32,数据录入!$E$5:$E$20000,"期初余额",数据录入!$B$5:$B$20000,"<="&$C$25)+SUMIFS(数据录入!$F$5:$F$20000,数据录入!$C$5:$C$20000,$B32,数据录入!$B$5:$B$20000,"<"&$C$25)-SUMIFS(数据录入!$G$5:$G$20000,数据录入!$C$5:$C$20000,$B32,数据录入!$B$5:$B$20000,"<"&$C$25)) -> 382888.52 | D32: =IF($B32="","",SUMIFS(数据录入!$F$5:$F$199999,数据录入!$C$5:$C$199999,$B32,数据录入!$B$5:$B$199999,$C$25)) -> 0 | E32: =IF($B32="","",SUMIFS(数据录入!$G$5:$G$199999,数据录入!$C$5:$C$199999,$B32,数据录入!$B$5:$B$199999,$C$25)) -> 0 | F32: =IF($B32="","",C32+D32-E32) -> 382888.52 | H32: 6 | I32: 吴建忠浦发 | J32: =IF($I32="","",SUMIFS(数据录入!$H$5:$H$20000,数据录入!$C$5:$C$20000,$I32,数据录入!$E$5:$E$20000,"期初余额",数据录入!$B$5:$B$20000,"<="&DATE(YEAR($K$25),MONTH($K$25),1))+SUMIFS(数据录入!$F$5:$F$20000,数据录入!$C$5:$C$20000,$I32,数据录入!$B$5:$B$20000,"<"&DATE(YEAR($K$25),MONTH($K$25),1))-SUMIFS(数据录入!$G$5:$G$20000,数据录入!$C$5:$C$20000,$I32,数据录入!$B$5:$B$20000,"<"&DATE(YEAR($K$25),MONTH($K$25),1))) -> 43095.19 | K32: =IF($I32="","",SUMIFS(数据录入!$F$5:$F$20000,数据录入!$C$5:$C$20000,$I32,数据录入!$B$5:$B$20000,">="&DATE(YEAR($K$25),MONTH($K$25),1),数据录入!$B$5:$B$20000,"<="&DATE(YEAR($K$25),MONTH($K$25)+1,0))) -> 1906893.3 | L32: =IF($I32="","",SUMIFS(数据录入!$G$5:$G$20000,数据录入!$C$5:$C$20000,$I32,数据录入!$B$5:$B$20000,">="&DATE(YEAR($K$25),MONTH($K$25),1),数据录入!$B$5:$B$20000,"<="&DATE(YEAR($K$25),MONTH($K$25)+1,0))) -> 1567100 | M32: =IF($I32="","",J32+K32-L32) -> 382888.52 | P32: 46143
A33: 7 | B33: 吴姐兴业 | C33: =IF($B33="","",SUMIFS(数据录入!$H$5:$H$785,数据录入!$C$5:$C$785,$B33,数据录入!$E$5:$E$785,"期初余额",数据录入!$B$5:$B$785,"<="&$C$25)+SUMIFS(数据录入!$F$5:$F$785,数据录入!$C$5:$C$785,$B33,数据录入!$B$5:$B$785,"<"&$C$25)-SUMIFS(数据录入!$G$5:$G$785,数据录入!$C$5:$C$785,$B33,数据录入!$B$5:$B$785,"<"&$C$25)) -> 0 | D33: =IF($B33="","",SUMIFS(数据录入!$F$5:$F$785,数据录入!$C$5:$C$785,$B33,数据录入!$B$5:$B$785,$C$25)) -> 0 | E33: =IF($B33="","",SUMIFS(数据录入!$G$5:$G$785,数据录入!$C$5:$C$785,$B33,数据录入!$B$5:$B$785,$C$25)) -> 0 | F33: =IF($B33="","",C33+D33-E33) -> 0 | H33: 7 | I33: 吴姐兴业 | J33: =IF($I33="","",SUMIFS(数据录入!$H$5:$H$785,数据录入!$C$5:$C$785,$I33,数据录入!$E$5:$E$785,"期初余额",数据录入!$B$5:$B$785,"<="&DATE(YEAR($K$25),MONTH($K$25),1))+SUMIFS(数据录入!$F$5:$F$785,数据录入!$C$5:$C$785,$I33,数据录入!$B$5:$B$785,"<"&DATE(YEAR($K$25),MONTH($K$25),1))-SUMIFS(数据录入!$G$5:$G$785,数据录入!$C$5:$C$785,$I33,数据录入!$B$5:$B$785,"<"&DATE(YEAR($K$25),MONTH($K$25),1))) -> 0 | K33: =IF($I33="","",SUMIFS(数据录入!$F$5:$F$785,数据录入!$C$5:$C$785,$I33,数据录入!$B$5:$B$785,">="&DATE(YEAR($K$25),MONTH($K$25),1),数据录入!$B$5:$B$785,"<="&DATE(YEAR($K$25),MONTH($K$25)+1,0))) -> 0 | L33: =IF($I33="","",SUMIFS(数据录入!$G$5:$G$20000,数据录入!$C$5:$C$20000,$I33,数据录入!$B$5:$B$20000,">="&DATE(YEAR($K$25),MONTH($K$25),1),数据录入!$B$5:$B$20000,"<="&DATE(YEAR($K$25),MONTH($K$25)+1,0))) -> 0 | M33: =IF($I33="","",J33+K33-L33) -> 0 | P33: 46174
A34: 8 | B34: 明道对公 | C34: =IF($B34="","",SUMIFS(数据录入!$H$5:$H$785,数据录入!$C$5:$C$785,$B34,数据录入!$E$5:$E$785,"期初余额",数据录入!$B$5:$B$785,"<="&$C$25)+SUMIFS(数据录入!$F$5:$F$785,数据录入!$C$5:$C$785,$B34,数据录入!$B$5:$B$785,"<"&$C$25)-SUMIFS(数据录入!$G$5:$G$785,数据录入!$C$5:$C$785,$B34,数据录入!$B$5:$B$785,"<"&$C$25)) -> 0 | D34: =IF($B34="","",SUMIFS(数据录入!$F$5:$F$785,数据录入!$C$5:$C$785,$B34,数据录入!$B$5:$B$785,$C$25)) -> 0 | E34: =IF($B34="","",SUMIFS(数据录入!$G$5:$G$785,数据录入!$C$5:$C$785,$B34,数据录入!$B$5:$B$785,$C$25)) -> 0 | F34: =IF($B34="","",C34+D34-E34) -> 0 | H34: 8 | I34: 明道对公 | J34: =IF($I34="","",SUMIFS(数据录入!$H$5:$H$785,数据录入!$C$5:$C$785,$I34,数据录入!$E$5:$E$785,"期初余额",数据录入!$B$5:$B$785,"<="&DATE(YEAR($K$25),MONTH($K$25),1))+SUMIFS(数据录入!$F$5:$F$785,数据录入!$C$5:$C$785,$I34,数据录入!$B$5:$B$785,"<"&DATE(YEAR($K$25),MONTH($K$25),1))-SUMIFS(数据录入!$G$5:$G$785,数据录入!$C$5:$C$785,$I34,数据录入!$B$5:$B$785,"<"&DATE(YEAR($K$25),MONTH($K$25),1))) -> 0 | K34: =IF($I34="","",SUMIFS(数据录入!$F$5:$F$785,数据录入!$C$5:$C$785,$I34,数据录入!$B$5:$B$785,">="&DATE(YEAR($K$25),MONTH($K$25),1),数据录入!$B$5:$B$785,"<="&DATE(YEAR($K$25),MONTH($K$25)+1,0))) -> 0 | L34: =IF($I34="","",SUMIFS(数据录入!$G$5:$G$20000,数据录入!$C$5:$C$20000,$I34,数据录入!$B$5:$B$20000,">="&DATE(YEAR($K$25),MONTH($K$25),1),数据录入!$B$5:$B$20000,"<="&DATE(YEAR($K$25),MONTH($K$25)+1,0))) -> 0 | M34: =IF($I34="","",J34+K34-L34) -> 0 | P34: 46204
A35: 9 | B35: 金辉对公 | C35: =IF($B35="","",SUMIFS(数据录入!$H$5:$H$785,数据录入!$C$5:$C$785,$B35,数据录入!$E$5:$E$785,"期初余额",数据录入!$B$5:$B$785,"<="&$C$25)+SUMIFS(数据录入!$F$5:$F$785,数据录入!$C$5:$C$785,$B35,数据录入!$B$5:$B$785,"<"&$C$25)-SUMIFS(数据录入!$G$5:$G$785,数据录入!$C$5:$C$785,$B35,数据录入!$B$5:$B$785,"<"&$C$25)) -> 0 | D35: =IF($B35="","",SUMIFS(数据录入!$F$5:$F$785,数据录入!$C$5:$C$785,$B35,数据录入!$B$5:$B$785,$C$25)) -> 0 | E35: =IF($B35="","",SUMIFS(数据录入!$G$5:$G$785,数据录入!$C$5:$C$785,$B35,数据录入!$B$5:$B$785,$C$25)) -> 0 | F35: =IF($B35="","",C35+D35-E35) -> 0 | H35: 9 | I35: 金辉对公 | J35: =IF($I35="","",SUMIFS(数据录入!$H$5:$H$785,数据录入!$C$5:$C$785,$I35,数据录入!$E$5:$E$785,"期初余额",数据录入!$B$5:$B$785,"<="&DATE(YEAR($K$25),MONTH($K$25),1))+SUMIFS(数据录入!$F$5:$F$785,数据录入!$C$5:$C$785,$I35,数据录入!$B$5:$B$785,"<"&DATE(YEAR($K$25),MONTH($K$25),1))-SUMIFS(数据录入!$G$5:$G$785,数据录入!$C$5:$C$785,$I35,数据录入!$B$5:$B$785,"<"&DATE(YEAR($K$25),MONTH($K$25),1))) -> 0 | K35: =IF($I35="","",SUMIFS(数据录入!$F$5:$F$785,数据录入!$C$5:$C$785,$I35,数据录入!$B$5:$B$785,">="&DATE(YEAR($K$25),MONTH($K$25),1),数据录入!$B$5:$B$785,"<="&DATE(YEAR($K$25),MONTH($K$25)+1,0))) -> 0 | L35: =IF($I35="","",SUMIFS(数据录入!$G$5:$G$20000,数据录入!$C$5:$C$20000,$I35,数据录入!$B$5:$B$20000,">="&DATE(YEAR($K$25),MONTH($K$25),1),数据录入!$B$5:$B$20000,"<="&DATE(YEAR($K$25),MONTH($K$25)+1,0))) -> 0 | M35: =IF($I35="","",J35+K35-L35) -> 0 | P35: 46235
A36: 10 | B36: 吴姐微信 | C36: =IF($B36="","",SUMIFS(数据录入!$H$5:$H$785,数据录入!$C$5:$C$785,$B36,数据录入!$E$5:$E$785,"期初余额",数据录入!$B$5:$B$785,"<="&$C$25)+SUMIFS(数据录入!$F$5:$F$785,数据录入!$C$5:$C$785,$B36,数据录入!$B$5:$B$785,"<"&$C$25)-SUMIFS(数据录入!$G$5:$G$785,数据录入!$C$5:$C$785,$B36,数据录入!$B$5:$B$785,"<"&$C$25)) -> 0 | D36: =IF($B36="","",SUMIFS(数据录入!$F$5:$F$785,数据录入!$C$5:$C$785,$B36,数据录入!$B$5:$B$785,$C$25)) -> 0 | E36: =IF($B36="","",SUMIFS(数据录入!$G$5:$G$785,数据录入!$C$5:$C$785,$B36,数据录入!$B$5:$B$785,$C$25)) -> 0 | F36: =IF($B36="","",C36+D36-E36) -> 0 | H36: 10 | I36: 吴姐微信 | J36: =IF($I36="","",SUMIFS(数据录入!$H$5:$H$785,数据录入!$C$5:$C$785,$I36,数据录入!$E$5:$E$785,"期初余额",数据录入!$B$5:$B$785,"<="&DATE(YEAR($K$25),MONTH($K$25),1))+SUMIFS(数据录入!$F$5:$F$785,数据录入!$C$5:$C$785,$I36,数据录入!$B$5:$B$785,"<"&DATE(YEAR($K$25),MONTH($K$25),1))-SUMIFS(数据录入!$G$5:$G$785,数据录入!$C$5:$C$785,$I36,数据录入!$B$5:$B$785,"<"&DATE(YEAR($K$25),MONTH($K$25),1))) -> 0 | K36: =IF($I36="","",SUMIFS(数据录入!$F$5:$F$785,数据录入!$C$5:$C$785,$I36,数据录入!$B$5:$B$785,">="&DATE(YEAR($K$25),MONTH($K$25),1),数据录入!$B$5:$B$785,"<="&DATE(YEAR($K$25),MONTH($K$25)+1,0))) -> 0 | L36: =IF($I36="","",SUMIFS(数据录入!$G$5:$G$20000,数据录入!$C$5:$C$20000,$I36,数据录入!$B$5:$B$20000,">="&DATE(YEAR($K$25),MONTH($K$25),1),数据录入!$B$5:$B$20000,"<="&DATE(YEAR($K$25),MONTH($K$25)+1,0))) -> 0 | M36: =IF($I36="","",J36+K36-L36) -> 0 | P36: 46266
A37: 11 | B37: 备用1 | C37: =IF($B37="","",SUMIFS(数据录入!$H$5:$H$785,数据录入!$C$5:$C$785,$B37,数据录入!$E$5:$E$785,"期初余额",数据录入!$B$5:$B$785,"<="&$C$25)+SUMIFS(数据录入!$F$5:$F$785,数据录入!$C$5:$C$785,$B37,数据录入!$B$5:$B$785,"<"&$C$25)-SUMIFS(数据录入!$G$5:$G$785,数据录入!$C$5:$C$785,$B37,数据录入!$B$5:$B$785,"<"&$C$25)) -> 0 | D37: =IF($B37="","",SUMIFS(数据录入!$F$5:$F$785,数据录入!$C$5:$C$785,$B37,数据录入!$B$5:$B$785,$C$25)) -> 0 | E37: =IF($B37="","",SUMIFS(数据录入!$G$5:$G$785,数据录入!$C$5:$C$785,$B37,数据录入!$B$5:$B$785,$C$25)) -> 0 | F37: =IF($B37="","",C37+D37-E37) -> 0 | H37: 11 | I37: 备用1 | J37: =IF($I37="","",SUMIFS(数据录入!$H$5:$H$785,数据录入!$C$5:$C$785,$I37,数据录入!$E$5:$E$785,"期初余额",数据录入!$B$5:$B$785,"<="&DATE(YEAR($K$25),MONTH($K$25),1))+SUMIFS(数据录入!$F$5:$F$785,数据录入!$C$5:$C$785,$I37,数据录入!$B$5:$B$785,"<"&DATE(YEAR($K$25),MONTH($K$25),1))-SUMIFS(数据录入!$G$5:$G$785,数据录入!$C$5:$C$785,$I37,数据录入!$B$5:$B$785,"<"&DATE(YEAR($K$25),MONTH($K$25),1))) -> 0 | K37: =IF($I37="","",SUMIFS(数据录入!$F$5:$F$785,数据录入!$C$5:$C$785,$I37,数据录入!$B$5:$B$785,">="&DATE(YEAR($K$25),MONTH($K$25),1),数据录入!$B$5:$B$785,"<="&DATE(YEAR($K$25),MONTH($K$25)+1,0))) -> 0 | L37: =IF($I37="","",SUMIFS(数据录入!$G$5:$G$20000,数据录入!$C$5:$C$20000,$I37,数据录入!$B$5:$B$20000,">="&DATE(YEAR($K$25),MONTH($K$25),1),数据录入!$B$5:$B$20000,"<="&DATE(YEAR($K$25),MONTH($K$25)+1,0))) -> 0 | M37: =IF($I37="","",J37+K37-L37) -> 0 | P37: 46296
A38: 12 | B38: 备用2 | C38: =IF($B38="","",SUMIFS(数据录入!$H$5:$H$785,数据录入!$C$5:$C$785,$B38,数据录入!$E$5:$E$785,"期初余额",数据录入!$B$5:$B$785,"<="&$C$25)+SUMIFS(数据录入!$F$5:$F$785,数据录入!$C$5:$C$785,$B38,数据录入!$B$5:$B$785,"<"&$C$25)-SUMIFS(数据录入!$G$5:$G$785,数据录入!$C$5:$C$785,$B38,数据录入!$B$5:$B$785,"<"&$C$25)) -> 0 | D38: =IF($B38="","",SUMIFS(数据录入!$F$5:$F$785,数据录入!$C$5:$C$785,$B38,数据录入!$B$5:$B$785,$C$25)) -> 0 | E38: =IF($B38="","",SUMIFS(数据录入!$G$5:$G$785,数据录入!$C$5:$C$785,$B38,数据录入!$B$5:$B$785,$C$25)) -> 0 | F38: =IF($B38="","",C38+D38-E38) -> 0 | H38: 12 | I38: 备用2 | J38: =IF($I38="","",SUMIFS(数据录入!$H$5:$H$785,数据录入!$C$5:$C$785,$I38,数据录入!$E$5:$E$785,"期初余额",数据录入!$B$5:$B$785,"<="&DATE(YEAR($K$25),MONTH($K$25),1))+SUMIFS(数据录入!$F$5:$F$785,数据录入!$C$5:$C$785,$I38,数据录入!$B$5:$B$785,"<"&DATE(YEAR($K$25),MONTH($K$25),1))-SUMIFS(数据录入!$G$5:$G$785,数据录入!$C$5:$C$785,$I38,数据录入!$B$5:$B$785,"<"&DATE(YEAR($K$25),MONTH($K$25),1))) -> 0 | K38: =IF($I38="","",SUMIFS(数据录入!$F$5:$F$785,数据录入!$C$5:$C$785,$I38,数据录入!$B$5:$B$785,">="&DATE(YEAR($K$25),MONTH($K$25),1),数据录入!$B$5:$B$785,"<="&DATE(YEAR($K$25),MONTH($K$25)+1,0))) -> 0 | L38: =IF($I38="","",SUMIFS(数据录入!$G$5:$G$20000,数据录入!$C$5:$C$20000,$I38,数据录入!$B$5:$B$20000,">="&DATE(YEAR($K$25),MONTH($K$25),1),数据录入!$B$5:$B$20000,"<="&DATE(YEAR($K$25),MONTH($K$25)+1,0))) -> 0 | M38: =IF($I38="","",J38+K38-L38) -> 0 | P38: 46327
A39: 13 | B39: 备用3 | C39: =IF($B39="","",SUMIFS(数据录入!$H$5:$H$785,数据录入!$C$5:$C$785,$B39,数据录入!$E$5:$E$785,"期初余额",数据录入!$B$5:$B$785,"<="&$C$25)+SUMIFS(数据录入!$F$5:$F$785,数据录入!$C$5:$C$785,$B39,数据录入!$B$5:$B$785,"<"&$C$25)-SUMIFS(数据录入!$G$5:$G$785,数据录入!$C$5:$C$785,$B39,数据录入!$B$5:$B$785,"<"&$C$25)) -> 0 | D39: =IF($B39="","",SUMIFS(数据录入!$F$5:$F$785,数据录入!$C$5:$C$785,$B39,数据录入!$B$5:$B$785,$C$25)) -> 0 | E39: =IF($B39="","",SUMIFS(数据录入!$G$5:$G$785,数据录入!$C$5:$C$785,$B39,数据录入!$B$5:$B$785,$C$25)) -> 0 | F39: =IF($B39="","",C39+D39-E39) -> 0 | H39: 13 | I39: 备用3 | J39: =IF($I39="","",SUMIFS(数据录入!$H$5:$H$785,数据录入!$C$5:$C$785,$I39,数据录入!$E$5:$E$785,"期初余额",数据录入!$B$5:$B$785,"<="&DATE(YEAR($K$25),MONTH($K$25),1))+SUMIFS(数据录入!$F$5:$F$785,数据录入!$C$5:$C$785,$I39,数据录入!$B$5:$B$785,"<"&DATE(YEAR($K$25),MONTH($K$25),1))-SUMIFS(数据录入!$G$5:$G$785,数据录入!$C$5:$C$785,$I39,数据录入!$B$5:$B$785,"<"&DATE(YEAR($K$25),MONTH($K$25),1))) -> 0 | K39: =IF($I39="","",SUMIFS(数据录入!$F$5:$F$785,数据录入!$C$5:$C$785,$I39,数据录入!$B$5:$B$785,">="&DATE(YEAR($K$25),MONTH($K$25),1),数据录入!$B$5:$B$785,"<="&DATE(YEAR($K$25),MONTH($K$25)+1,0))) -> 0 | L39: =IF($I39="","",SUMIFS(数据录入!$G$5:$G$20000,数据录入!$C$5:$C$20000,$I39,数据录入!$B$5:$B$20000,">="&DATE(YEAR($K$25),MONTH($K$25),1),数据录入!$B$5:$B$20000,"<="&DATE(YEAR($K$25),MONTH($K$25)+1,0))) -> 0 | M39: =IF($I39="","",J39+K39-L39) -> 0 | P39: 46357
A40: 14 | B40: 备用4 | C40: =IF($B40="","",SUMIFS(数据录入!$H$5:$H$785,数据录入!$C$5:$C$785,$B40,数据录入!$E$5:$E$785,"期初余额",数据录入!$B$5:$B$785,"<="&$C$25)+SUMIFS(数据录入!$F$5:$F$785,数据录入!$C$5:$C$785,$B40,数据录入!$B$5:$B$785,"<"&$C$25)-SUMIFS(数据录入!$G$5:$G$785,数据录入!$C$5:$C$785,$B40,数据录入!$B$5:$B$785,"<"&$C$25)) -> 0 | D40: =IF($B40="","",SUMIFS(数据录入!$F$5:$F$785,数据录入!$C$5:$C$785,$B40,数据录入!$B$5:$B$785,$C$25)) -> 0 | E40: =IF($B40="","",SUMIFS(数据录入!$G$5:$G$785,数据录入!$C$5:$C$785,$B40,数据录入!$B$5:$B$785,$C$25)) -> 0 | F40: =IF($B40="","",C40+D40-E40) -> 0 | H40: 14 | I40: 备用4 | J40: =IF($I40="","",SUMIFS(数据录入!$H$5:$H$785,数据录入!$C$5:$C$785,$I40,数据录入!$E$5:$E$785,"期初余额",数据录入!$B$5:$B$785,"<="&DATE(YEAR($K$25),MONTH($K$25),1))+SUMIFS(数据录入!$F$5:$F$785,数据录入!$C$5:$C$785,$I40,数据录入!$B$5:$B$785,"<"&DATE(YEAR($K$25),MONTH($K$25),1))-SUMIFS(数据录入!$G$5:$G$785,数据录入!$C$5:$C$785,$I40,数据录入!$B$5:$B$785,"<"&DATE(YEAR($K$25),MONTH($K$25),1))) -> 0 | K40: =IF($I40="","",SUMIFS(数据录入!$F$5:$F$785,数据录入!$C$5:$C$785,$I40,数据录入!$B$5:$B$785,">="&DATE(YEAR($K$25),MONTH($K$25),1),数据录入!$B$5:$B$785,"<="&DATE(YEAR($K$25),MONTH($K$25)+1,0))) -> 0 | L40: =IF($I40="","",SUMIFS(数据录入!$G$5:$G$20000,数据录入!$C$5:$C$20000,$I40,数据录入!$B$5:$B$20000,">="&DATE(YEAR($K$25),MONTH($K$25),1),数据录入!$B$5:$B$20000,"<="&DATE(YEAR($K$25),MONTH($K$25)+1,0))) -> 0 | M40: =IF($I40="","",J40+K40-L40) -> 0
A41: 合计 | C41: =SUM(C27:C40) -> 2395225.2 | D41: =SUM(D27:D40) -> 11474 | E41: =SUM(E27:E40) -> 26236.61 | F41: =SUM(F27:F40) -> 2380462.6 | I41: 合计 | J41: =SUM(J27:J40) -> 805085.59 | K41: =SUM(K27:K40) -> 4978725.4 | L41: =SUM(L27:L40) -> 3403348.4 | M41: =SUM(M27:M40) -> 2380462.6

Sheet 任意时间段收支报表
B1: 任意时间段收支盈亏查询 | J1: 说明：修改黄色日期即可查询；支持单日或任意连续日期
B2: 开始日期 | C2: 46266 | D2: 收入总额 | E2: =IF(OR($C$2="",$C$3=""),"",SUMIFS([1]数据录入!$J$4:$J$9999,[1]数据录入!$B$4:$B$9999,">="&$C$2,[1]数据录入!$B$4:$B$9999,"<="&$C$3)) -> #VALUE! | F2: =SUM(C5:C500) -> 19130 | G2: 盈亏 | H2: =IF(OR(F2="",F3=""),"",F2-F3) -> -124262.74
B3: 结束日期 | C3: 46266 | D3: 支出总额 | E3: =IF(OR($C$2="",$C$3=""),"",SUMIFS([1]数据录入!$K$4:$K$9999,[1]数据录入!$B$4:$B$9999,">="&$C$2,[1]数据录入!$B$4:$B$9999,"<="&$C$3)) -> #VALUE! | F3: =SUM(G5:G500) -> 143392.74
B4: 资金收入 | C4: 金额 | D4: 收入占比 | E4: 序号 | F4: 资金支出 | G4: 金额 | H4: 支出占比
B5: 曹泰宁 | C5: =IF($B5="","",SUMIFS(数据录入!$F$4:$F$5077,数据录入!$I$4:$I$5077,$B5,数据录入!$B$4:$B$5077,">="&$C$2,数据录入!$B$4:$B$5077,"<="&$C$3)) -> 0 | D5: =IF(OR($B5="",$F$2=0),"",C5/$F$2) -> 0 | E5: 1 | F5: 借款本金 | G5: =IF($F5="","",SUMIFS(数据录入!$G$4:$G$5077,数据录入!$D$4:$D$5077,$F5,数据录入!$B$4:$B$5077,">="&$C$2,数据录入!$B$4:$B$5077,"<="&$C$3)) -> 0 | H5: =IF(OR($F5="",$F$3=0),"",G5/$F$3) -> 0
B6: 曹玉洁 | C6: =IF($B6="","",SUMIFS(数据录入!$F$4:$F$5077,数据录入!$I$4:$I$5077,$B6,数据录入!$B$4:$B$5077,">="&$C$2,数据录入!$B$4:$B$5077,"<="&$C$3)) -> 0 | D6: =IF(OR($B6="",$F$2=0),"",C6/$F$2) -> 0 | E6: 2 | F6: 借款利息 | G6: =IF($F6="","",SUMIFS(数据录入!$G$4:$G$5077,数据录入!$D$4:$D$5077,$F6,数据录入!$B$4:$B$5077,">="&$C$2,数据录入!$B$4:$B$5077,"<="&$C$3)) -> 0 | H6: =IF(OR($F6="",$F$3=0),"",G6/$F$3) -> 0
B7: 曾光雄 | C7: =IF($B7="","",SUMIFS(数据录入!$F$4:$F$5077,数据录入!$I$4:$I$5077,$B7,数据录入!$B$4:$B$5077,">="&$C$2,数据录入!$B$4:$B$5077,"<="&$C$3)) -> 0 | D7: =IF(OR($B7="",$F$2=0),"",C7/$F$2) -> 0 | E7: 3 | F7: 借款滞纳金 | G7: =IF($F7="","",SUMIFS(数据录入!$G$4:$G$5077,数据录入!$D$4:$D$5077,$F7,数据录入!$B$4:$B$5077,">="&$C$2,数据录入!$B$4:$B$5077,"<="&$C$3)) -> 0 | H7: =IF(OR($F7="",$F$3=0),"",G7/$F$3) -> 0
B8: 曾云 | C8: =IF($B8="","",SUMIFS(数据录入!$F$4:$F$5077,数据录入!$I$4:$I$5077,$B8,数据录入!$B$4:$B$5077,">="&$C$2,数据录入!$B$4:$B$5077,"<="&$C$3)) -> 0 | D8: =IF(OR($B8="",$F$2=0),"",C8/$F$2) -> 0 | E8: 4 | F8: 银行结息 | G8: =IF($F8="","",SUMIFS(数据录入!$G$4:$G$5077,数据录入!$D$4:$D$5077,$F8,数据录入!$B$4:$B$5077,">="&$C$2,数据录入!$B$4:$B$5077,"<="&$C$3)) -> 0 | H8: =IF(OR($F8="",$F$3=0),"",G8/$F$3) -> 0
B9: 常虹 | C9: =IF($B9="","",SUMIFS(数据录入!$F$4:$F$5077,数据录入!$I$4:$I$5077,$B9,数据录入!$B$4:$B$5077,">="&$C$2,数据录入!$B$4:$B$5077,"<="&$C$3)) -> 0 | D9: =IF(OR($B9="",$F$2=0),"",C9/$F$2) -> 0 | E9: 5 | F9: 员工工资 | G9: =IF($F9="","",SUMIFS(数据录入!$G$4:$G$5077,数据录入!$D$4:$D$5077,$F9,数据录入!$B$4:$B$5077,">="&$C$2,数据录入!$B$4:$B$5077,"<="&$C$3)) -> 0 | H9: =IF(OR($F9="",$F$3=0),"",G9/$F$3) -> 0
B10: 陈滨 | C10: =IF($B10="","",SUMIFS(数据录入!$F$4:$F$5077,数据录入!$I$4:$I$5077,$B10,数据录入!$B$4:$B$5077,">="&$C$2,数据录入!$B$4:$B$5077,"<="&$C$3)) -> 0 | D10: =IF(OR($B10="",$F$2=0),"",C10/$F$2) -> 0 | E10: 6 | F10: 水电费 | G10: =IF($F10="","",SUMIFS(数据录入!$G$4:$G$5077,数据录入!$D$4:$D$5077,$F10,数据录入!$B$4:$B$5077,">="&$C$2,数据录入!$B$4:$B$5077,"<="&$C$3)) -> 0 | H10: =IF(OR($F10="",$F$3=0),"",G10/$F$3) -> 0
B11: 陈承辉 | C11: =IF($B11="","",SUMIFS(数据录入!$F$4:$F$5077,数据录入!$I$4:$I$5077,$B11,数据录入!$B$4:$B$5077,">="&$C$2,数据录入!$B$4:$B$5077,"<="&$C$3)) -> 0 | D11: =IF(OR($B11="",$F$2=0),"",C11/$F$2) -> 0 | E11: 7 | F11: 房租 | G11: =IF($F11="","",SUMIFS(数据录入!$G$4:$G$5077,数据录入!$D$4:$D$5077,$F11,数据录入!$B$4:$B$5077,">="&$C$2,数据录入!$B$4:$B$5077,"<="&$C$3)) -> 45000 | H11: =IF(OR($F11="",$F$3=0),"",G11/$F$3) -> 0.31382342
B12: 陈大鑫 | C12: =IF($B12="","",SUMIFS(数据录入!$F$4:$F$5077,数据录入!$I$4:$I$5077,$B12,数据录入!$B$4:$B$5077,">="&$C$2,数据录入!$B$4:$B$5077,"<="&$C$3)) -> 0 | D12: =IF(OR($B12="",$F$2=0),"",C12/$F$2) -> 0 | E12: 8 | F12: 办公费用 | G12: =IF($F12="","",SUMIFS(数据录入!$G$4:$G$5077,数据录入!$D$4:$D$5077,$F12,数据录入!$B$4:$B$5077,">="&$C$2,数据录入!$B$4:$B$5077,"<="&$C$3)) -> 3000 | H12: =IF(OR($F12="",$F$3=0),"",G12/$F$3) -> 0.020921561
B13: 陈东 | C13: =IF($B13="","",SUMIFS(数据录入!$F$4:$F$5077,数据录入!$I$4:$I$5077,$B13,数据录入!$B$4:$B$5077,">="&$C$2,数据录入!$B$4:$B$5077,"<="&$C$3)) -> 0 | D13: =IF(OR($B13="",$F$2=0),"",C13/$F$2) -> 0 | E13: 9 | F13: 招待费 | G13: =IF($F13="","",SUMIFS(数据录入!$G$4:$G$5077,数据录入!$D$4:$D$5077,$F13,数据录入!$B$4:$B$5077,">="&$C$2,数据录入!$B$4:$B$5077,"<="&$C$3)) -> 0 | H13: =IF(OR($F13="",$F$3=0),"",G13/$F$3) -> 0
B14: 陈福荣 | C14: =IF($B14="","",SUMIFS(数据录入!$F$4:$F$5077,数据录入!$I$4:$I$5077,$B14,数据录入!$B$4:$B$5077,">="&$C$2,数据录入!$B$4:$B$5077,"<="&$C$3)) -> 0 | D14: =IF(OR($B14="",$F$2=0),"",C14/$F$2) -> 0 | E14: 10 | F14: 渠道费用 | G14: =IF($F14="","",SUMIFS(数据录入!$G$4:$G$5077,数据录入!$D$4:$D$5077,$F14,数据录入!$B$4:$B$5077,">="&$C$2,数据录入!$B$4:$B$5077,"<="&$C$3)) -> 3280 | H14: =IF(OR($F14="",$F$3=0),"",G14/$F$3) -> 0.02287424
B15: 陈国宝 | C15: =IF($B15="","",SUMIFS(数据录入!$F$4:$F$5077,数据录入!$I$4:$I$5077,$B15,数据录入!$B$4:$B$5077,">="&$C$2,数据录入!$B$4:$B$5077,"<="&$C$3)) -> 0 | D15: =IF(OR($B15="",$F$2=0),"",C15/$F$2) -> 0 | E15: 11 | F15: 手续费-收 | G15: =IF($F15="","",SUMIFS(数据录入!$G$4:$G$5077,数据录入!$D$4:$D$5077,$F15,数据录入!$B$4:$B$5077,">="&$C$2,数据录入!$B$4:$B$5077,"<="&$C$3)) -> 0 | H15: =IF(OR($F15="",$F$3=0),"",G15/$F$3) -> 0
B16: 陈建华 | C16: =IF($B16="","",SUMIFS(数据录入!$F$4:$F$5077,数据录入!$I$4:$I$5077,$B16,数据录入!$B$4:$B$5077,">="&$C$2,数据录入!$B$4:$B$5077,"<="&$C$3)) -> 5000 | D16: =IF(OR($B16="",$F$2=0),"",C16/$F$2) -> 0.26136958 | E16: 12 | F16: 过桥/解押本金 | G16: =IF($F16="","",SUMIFS(数据录入!$G$4:$G$5077,数据录入!$D$4:$D$5077,$F16,数据录入!$B$4:$B$5077,">="&$C$2,数据录入!$B$4:$B$5077,"<="&$C$3)) -> 0 | H16: =IF(OR($F16="",$F$3=0),"",G16/$F$3) -> 0
... B28: 池鸿 | C28: =IF($B28="","",SUMIFS(数据录入!$F$4:$F$5077,数据录入!$I$4:$I$5077,$B28,数据录入!$B$4:$B$5077,">="&$C$2,数据录入!$B$4:$B$5077,"<="&$C$3)) -> 0 | D28: =IF(OR($B28="",$F$2=0),"",C28/$F$2) -> 0 | E28: 24 | F28: 明道本金 | G28: =IF($F28="","",SUMIFS(数据录入!$G$4:$G$5077,数据录入!$D$4:$D$5077,$F28,数据录入!$B$4:$B$5077,">="&$C$2,数据录入!$B$4:$B$5077,"<="&$C$3)) -> 0 | H28: =IF(OR($F28="",$F$3=0),"",G28/$F$3) -> 0
B29: 典当微信 | C29: =IF($B29="","",SUMIFS(数据录入!$F$4:$F$5077,数据录入!$I$4:$I$5077,$B29,数据录入!$B$4:$B$5077,">="&$C$2,数据录入!$B$4:$B$5077,"<="&$C$3)) -> 0 | D29: =IF(OR($B29="",$F$2=0),"",C29/$F$2) -> 0 | E29: 25 | G29: =IF($F29="","",SUMIFS(数据录入!$G$4:$G$5077,数据录入!$D$4:$D$5077,$F29,数据录入!$B$4:$B$5077,">="&$C$2,数据录入!$B$4:$B$5077,"<="&$C$3)) | H29: =IF(OR($F29="",$F$3=0),"",G29/$F$3)
B30: 董智宇 | C30: =IF($B30="","",SUMIFS(数据录入!$F$4:$F$5077,数据录入!$I$4:$I$5077,$B30,数据录入!$B$4:$B$5077,">="&$C$2,数据录入!$B$4:$B$5077,"<="&$C$3)) -> 0 | D30: =IF(OR($B30="",$F$2=0),"",C30/$F$2) -> 0 | E30: 26 | G30: =IF($F30="","",SUMIFS(数据录入!$G$4:$G$5077,数据录入!$D$4:$D$5077,$F30,数据录入!$B$4:$B$5077,">="&$C$2,数据录入!$B$4:$B$5077,"<="&$C$3)) | H30: =IF(OR($F30="",$F$3=0),"",G30/$F$3)
B31: 杜若 | C31: =IF($B31="","",SUMIFS(数据录入!$F$4:$F$5077,数据录入!$I$4:$I$5077,$B31,数据录入!$B$4:$B$5077,">="&$C$2,数据录入!$B$4:$B$5077,"<="&$C$3)) -> 0 | D31: =IF(OR($B31="",$F$2=0),"",C31/$F$2) -> 0 | E31: 27 | G31: =IF($F31="","",SUMIFS(数据录入!$G$4:$G$5077,数据录入!$D$4:$D$5077,$F31,数据录入!$B$4:$B$5077,">="&$C$2,数据录入!$B$4:$B$5077,"<="&$C$3)) | H31: =IF(OR($F31="",$F$3=0),"",G31/$F$3)
B32: 段乐 | C32: =IF($B32="","",SUMIFS(数据录入!$F$4:$F$5077,数据录入!$I$4:$I$5077,$B32,数据录入!$B$4:$B$5077,">="&$C$2,数据录入!$B$4:$B$5077,"<="&$C$3)) -> 0 | D32: =IF(OR($B32="",$F$2=0),"",C32/$F$2) -> 0 | E32: 28 | G32: =IF($F32="","",SUMIFS(数据录入!$G$4:$G$5077,数据录入!$D$4:$D$5077,$F32,数据录入!$B$4:$B$5077,">="&$C$2,数据录入!$B$4:$B$5077,"<="&$C$3)) | H32: =IF(OR($F32="",$F$3=0),"",G32/$F$3)
B33: 方楚钰 | C33: =IF($B33="","",SUMIFS(数据录入!$F$4:$F$5077,数据录入!$I$4:$I$5077,$B33,数据录入!$B$4:$B$5077,">="&$C$2,数据录入!$B$4:$B$5077,"<="&$C$3)) -> 0 | D33: =IF(OR($B33="",$F$2=0),"",C33/$F$2) -> 0 | E33: 29 | G33: =IF($F33="","",SUMIFS(数据录入!$G$4:$G$5077,数据录入!$D$4:$D$5077,$F33,数据录入!$B$4:$B$5077,">="&$C$2,数据录入!$B$4:$B$5077,"<="&$C$3)) | H33: =IF(OR($F33="",$F$3=0),"",G33/$F$3)
B34: 方士雯 | C34: =IF($B34="","",SUMIFS(数据录入!$F$4:$F$5077,数据录入!$I$4:$I$5077,$B34,数据录入!$B$4:$B$5077,">="&$C$2,数据录入!$B$4:$B$5077,"<="&$C$3)) -> 0 | D34: =IF(OR($B34="",$F$2=0),"",C34/$F$2) -> 0 | E34: 30 | G34: =IF($F34="","",SUMIFS(数据录入!$G$4:$G$5077,数据录入!$D$4:$D$5077,$F34,数据录入!$B$4:$B$5077,">="&$C$2,数据录入!$B$4:$B$5077,"<="&$C$3)) | H34: =IF(OR($F34="",$F$3=0),"",G34/$F$3)
B35: 方秀全 | C35: =IF($B35="","",SUMIFS(数据录入!$F$4:$F$5077,数据录入!$I$4:$I$5077,$B35,数据录入!$B$4:$B$5077,">="&$C$2,数据录入!$B$4:$B$5077,"<="&$C$3)) -> 0 | D35: =IF(OR($B35="",$F$2=0),"",C35/$F$2) -> 0 | E35: 31 | G35: =IF($F35="","",SUMIFS(数据录入!$G$4:$G$5077,数据录入!$D$4:$D$5077,$F35,数据录入!$B$4:$B$5077,">="&$C$2,数据录入!$B$4:$B$5077,"<="&$C$3)) | H35: =IF(OR($F35="",$F$3=0),"",G35/$F$3)
B36: 高文玉 | C36: =IF($B36="","",SUMIFS(数据录入!$F$4:$F$5077,数据录入!$I$4:$I$5077,$B36,数据录入!$B$4:$B$5077,">="&$C$2,数据录入!$B$4:$B$5077,"<="&$C$3)) -> 0 | D36: =IF(OR($B36="",$F$2=0),"",C36/$F$2) -> 0 | E36: 32 | G36: =IF($F36="","",SUMIFS(数据录入!$G$4:$G$5077,数据录入!$D$4:$D$5077,$F36,数据录入!$B$4:$B$5077,">="&$C$2,数据录入!$B$4:$B$5077,"<="&$C$3)) | H36: =IF(OR($F36="",$F$3=0),"",G36/$F$3)
B37: 郭宝龙 | C37: =IF($B37="","",SUMIFS(数据录入!$F$4:$F$5077,数据录入!$I$4:$I$5077,$B37,数据录入!$B$4:$B$5077,">="&$C$2,数据录入!$B$4:$B$5077,"<="&$C$3)) -> 0 | D37: =IF(OR($B37="",$F$2=0),"",C37/$F$2) -> 0 | E37: 33 | G37: =IF($F37="","",SUMIFS(数据录入!$G$4:$G$5077,数据录入!$D$4:$D$5077,$F37,数据录入!$B$4:$B$5077,">="&$C$2,数据录入!$B$4:$B$5077,"<="&$C$3)) | H37: =IF(OR($F37="",$F$3=0),"",G37/$F$3)
B38: 郭联兵 | C38: =IF($B38="","",SUMIFS(数据录入!$F$4:$F$5077,数据录入!$I$4:$I$5077,$B38,数据录入!$B$4:$B$5077,">="&$C$2,数据录入!$B$4:$B$5077,"<="&$C$3)) -> 0 | D38: =IF(OR($B38="",$F$2=0),"",C38/$F$2) -> 0 | E38: 34 | G38: =IF($F38="","",SUMIFS(数据录入!$G$4:$G$5077,数据录入!$D$4:$D$5077,$F38,数据录入!$B$4:$B$5077,">="&$C$2,数据录入!$B$4:$B$5077,"<="&$C$3)) | H38: =IF(OR($F38="",$F$3=0),"",G38/$F$3)
B39: 何博文 | C39: =IF($B39="","",SUMIFS(数据录入!$F$4:$F$5077,数据录入!$I$4:$I$5077,$B39,数据录入!$B$4:$B$5077,">="&$C$2,数据录入!$B$4:$B$5077,"<="&$C$3)) -> 0 | D39: =IF(OR($B39="",$F$2=0),"",C39/$F$2) -> 0 | E39: 35 | G39: =IF($F39="","",SUMIFS(数据录入!$G$4:$G$5077,数据录入!$D$4:$D$5077,$F39,数据录入!$B$4:$B$5077,">="&$C$2,数据录入!$B$4:$B$5077,"<="&$C$3)) | H39: =IF(OR($F39="",$F$3=0),"",G39/$F$3)
B40: 胡建通 | C40: =IF($B40="","",SUMIFS(数据录入!$F$4:$F$5077,数据录入!$I$4:$I$5077,$B40,数据录入!$B$4:$B$5077,">="&$C$2,数据录入!$B$4:$B$5077,"<="&$C$3)) -> 0 | D40: =IF(OR($B40="",$F$2=0),"",C40/$F$2) -> 0 | E40: 36
B41: 胡小丽 | C41: =IF($B41="","",SUMIFS(数据录入!$F$4:$F$5077,数据录入!$I$4:$I$5077,$B41,数据录入!$B$4:$B$5077,">="&$C$2,数据录入!$B$4:$B$5077,"<="&$C$3)) -> 0 | D41: =IF(OR($B41="",$F$2=0),"",C41/$F$2) -> 0 | E41: 37
B42: 黄发锦 | C42: =IF($B42="","",SUMIFS(数据录入!$F$4:$F$5077,数据录入!$I$4:$I$5077,$B42,数据录入!$B$4:$B$5077,">="&$C$2,数据录入!$B$4:$B$5077,"<="&$C$3)) -> 0 | D42: =IF(OR($B42="",$F$2=0),"",C42/$F$2) -> 0 | E42: 38
B43: 黄飞 | C43: =IF($B43="","",SUMIFS(数据录入!$F$4:$F$5077,数据录入!$I$4:$I$5077,$B43,数据录入!$B$4:$B$5077,">="&$C$2,数据录入!$B$4:$B$5077,"<="&$C$3)) -> 0 | D43: =IF(OR($B43="",$F$2=0),"",C43/$F$2) -> 0 | E43: 39
B44: 黄福恩 | C44: =IF($B44="","",SUMIFS(数据录入!$F$4:$F$5077,数据录入!$I$4:$I$5077,$B44,数据录入!$B$4:$B$5077,">="&$C$2,数据录入!$B$4:$B$5077,"<="&$C$3)) -> 0 | D44: =IF(OR($B44="",$F$2=0),"",C44/$F$2) -> 0 | E44: 40
B45: 黄节山 | C45: =IF($B45="","",SUMIFS(数据录入!$F$4:$F$5077,数据录入!$I$4:$I$5077,$B45,数据录入!$B$4:$B$5077,">="&$C$2,数据录入!$B$4:$B$5077,"<="&$C$3)) -> 0 | D45: =IF(OR($B45="",$F$2=0),"",C45/$F$2) -> 0 | E45: 41
B46: 黄军 | C46: =IF($B46="","",SUMIFS(数据录入!$F$4:$F$5077,数据录入!$I$4:$I$5077,$B46,数据录入!$B$4:$B$5077,">="&$C$2,数据录入!$B$4:$B$5077,"<="&$C$3)) -> 0 | D46: =IF(OR($B46="",$F$2=0),"",C46/$F$2) -> 0 | E46: 42
B47: 黄远枝 | C47: =IF($B47="","",SUMIFS(数据录入!$F$4:$F$5077,数据录入!$I$4:$I$5077,$B47,数据录入!$B$4:$B$5077,">="&$C$2,数据录入!$B$4:$B$5077,"<="&$C$3)) -> 0 | D47: =IF(OR($B47="",$F$2=0),"",C47/$F$2) -> 0 | E47: 43
B48: 黄长燕 | C48: =IF($B48="","",SUMIFS(数据录入!$F$4:$F$5077,数据录入!$I$4:$I$5077,$B48,数据录入!$B$4:$B$5077,">="&$C$2,数据录入!$B$4:$B$5077,"<="&$C$3)) -> 0 | D48: =IF(OR($B48="",$F$2=0),"",C48/$F$2) -> 0 | E48: 44
B49: 纪昌杰 | C49: =IF($B49="","",SUMIFS(数据录入!$F$4:$F$5077,数据录入!$I$4:$I$5077,$B49,数据录入!$B$4:$B$5077,">="&$C$2,数据录入!$B$4:$B$5077,"<="&$C$3)) -> 0 | D49: =IF(OR($B49="",$F$2=0),"",C49/$F$2) -> 0 | E49: 45
B50: 姜玉枝 | C50: =IF($B50="","",SUMIFS(数据录入!$F$4:$F$5077,数据录入!$I$4:$I$5077,$B50,数据录入!$B$4:$B$5077,">="&$C$2,数据录入!$B$4:$B$5077,"<="&$C$3)) -> 2250 | D50: =IF(OR($B50="",$F$2=0),"",C50/$F$2) -> 0.11761631 | E50: 46
B51: 金辉稠州 | C51: =IF($B51="","",SUMIFS(数据录入!$F$4:$F$5077,数据录入!$I$4:$I$5077,$B51,数据录入!$B$4:$B$5077,">="&$C$2,数据录入!$B$4:$B$5077,"<="&$C$3)) -> 0 | D51: =IF(OR($B51="",$F$2=0),"",C51/$F$2) -> 0 | E51: 47
... B175: 朱俊良 | C175: =IF($B175="","",SUMIFS(数据录入!$F$4:$F$5077,数据录入!$I$4:$I$5077,$B175,数据录入!$B$4:$B$5077,">="&$C$2,数据录入!$B$4:$B$5077,"<="&$C$3)) -> 0 | D175: =IF(OR($B175="",$F$2=0),"",C175/$F$2) -> 0 | E175: 171

Sheet 收支报表
A1: 收支报表
B3: 收支盈亏 | C3: =C42-C4 -> 0 | D3: =D42-D4 -> 0 | E3: =E42-E4 -> 0 | F3: =F42-F4 -> 0 | G3: =G42-G4 -> 0 | H3: =H42-H4 -> 0 | I3: =I42-I4 -> -109321.61 | J3: =J42-J4 -> -311625.47 | ... O3: =O42-O4 -> 1595315.8
B4: 支出总额 | C4: =SUM(C6:C40) -> 0 | D4: =SUM(D6:D40) -> 0 | E4: =SUM(E6:E40) -> 0 | F4: =SUM(F6:F40) -> 0 | G4: =SUM(G6:G40) -> 0 | H4: =SUM(H6:H40) -> 0 | I4: =SUM(I6:I40) -> 14220327 | J4: =SUM(J6:J40) -> 19005987 | ... N4: =SUM(N6:N40) -> 0 | O4: =SUM(C4:N4) -> 36167426 | P4: =IF($O$4=0,"",1) -> 1
A5: 序 | B5: 资金支出 | C5: 202601 | D5: 202602 | E5: 202603 | F5: 202604 | G5: 202605 | H5: 202606 | I5: 202607 | J5: 202608 | K5: 202609 | L5: 202610 | M5: 202611 | N5: 202612 | O5: 合计 | P5: 总支出占比
A6: 1 | B6: 借款本金 | C6: =IF($B6="","",SUMIFS(数据录入!$G$5:$G$785,数据录入!$D$5:$D$785,$B6,数据录入!$K$5:$K$785,C$5)) -> 0 | D6: =IF($B6="","",SUMIFS(数据录入!$G$5:$G$785,数据录入!$D$5:$D$785,$B6,数据录入!$K$5:$K$785,D$5)) -> 0 | E6: =IF($B6="","",SUMIFS(数据录入!$G$5:$G$785,数据录入!$D$5:$D$785,$B6,数据录入!$K$5:$K$785,E$5)) -> 0 | F6: =IF($B6="","",SUMIFS(数据录入!$G$5:$G$785,数据录入!$D$5:$D$785,$B6,数据录入!$K$5:$K$785,F$5)) -> 0 | G6: =IF($B6="","",SUMIFS(数据录入!$G$5:$G$785,数据录入!$D$5:$D$785,$B6,数据录入!$K$5:$K$785,G$5)) -> 0 | H6: =IF($B6="","",SUMIFS(数据录入!$G$5:$G$785,数据录入!$D$5:$D$785,$B6,数据录入!$K$5:$K$785,H$5)) -> 0 | I6: =IF($B6="","",SUMIFS(数据录入!$G$5:$G$785,数据录入!$D$5:$D$785,$B6,数据录入!$K$5:$K$785,I$5)) -> 4891050 | J6: =IF($B6="","",SUMIFS(数据录入!$G$5:$G$785,数据录入!$D$5:$D$785,$B6,数据录入!$K$5:$K$785,J$5)) -> 6099600 | ... N6: =IF($B6="","",SUMIFS(数据录入!$G$5:$G$785,数据录入!$D$5:$D$785,$B6,数据录入!$K$5:$K$785,N$5)) -> 0 | O6: =SUM(C6:N6) -> 11868150 | P6: =IF($O$4=0,"",O6/$O$4) -> 0.32814473
A7: 2 | B7: 借款利息 | C7: =IF($B7="","",SUMIFS(数据录入!$G$5:$G$785,数据录入!$D$5:$D$785,$B7,数据录入!$K$5:$K$785,C$5)) -> 0 | D7: =IF($B7="","",SUMIFS(数据录入!$G$5:$G$785,数据录入!$D$5:$D$785,$B7,数据录入!$K$5:$K$785,D$5)) -> 0 | E7: =IF($B7="","",SUMIFS(数据录入!$G$5:$G$785,数据录入!$D$5:$D$785,$B7,数据录入!$K$5:$K$785,E$5)) -> 0 | F7: =IF($B7="","",SUMIFS(数据录入!$G$5:$G$785,数据录入!$D$5:$D$785,$B7,数据录入!$K$5:$K$785,F$5)) -> 0 | G7: =IF($B7="","",SUMIFS(数据录入!$G$5:$G$785,数据录入!$D$5:$D$785,$B7,数据录入!$K$5:$K$785,G$5)) -> 0 | H7: =IF($B7="","",SUMIFS(数据录入!$G$5:$G$785,数据录入!$D$5:$D$785,$B7,数据录入!$K$5:$K$785,H$5)) -> 0 | I7: =IF($B7="","",SUMIFS(数据录入!$G$5:$G$785,数据录入!$D$5:$D$785,$B7,数据录入!$K$5:$K$785,I$5)) -> 19400 | J7: =IF($B7="","",SUMIFS(数据录入!$G$5:$G$785,数据录入!$D$5:$D$785,$B7,数据录入!$K$5:$K$785,J$5)) -> 24900 | ... N7: =IF($B7="","",SUMIFS(数据录入!$G$5:$G$785,数据录入!$D$5:$D$785,$B7,数据录入!$K$5:$K$785,N$5)) -> 0 | O7: =SUM(C7:N7) -> 44300 | P7: =IF($O$4=0,"",O7/$O$4) -> 0.0012248591
A8: 3 | B8: 借款滞纳金 | C8: =IF($B8="","",SUMIFS(数据录入!$G$5:$G$785,数据录入!$D$5:$D$785,$B8,数据录入!$K$5:$K$785,C$5)) -> 0 | D8: =IF($B8="","",SUMIFS(数据录入!$G$5:$G$785,数据录入!$D$5:$D$785,$B8,数据录入!$K$5:$K$785,D$5)) -> 0 | E8: =IF($B8="","",SUMIFS(数据录入!$G$5:$G$785,数据录入!$D$5:$D$785,$B8,数据录入!$K$5:$K$785,E$5)) -> 0 | F8: =IF($B8="","",SUMIFS(数据录入!$G$5:$G$785,数据录入!$D$5:$D$785,$B8,数据录入!$K$5:$K$785,F$5)) -> 0 | G8: =IF($B8="","",SUMIFS(数据录入!$G$5:$G$785,数据录入!$D$5:$D$785,$B8,数据录入!$K$5:$K$785,G$5)) -> 0 | H8: =IF($B8="","",SUMIFS(数据录入!$G$5:$G$785,数据录入!$D$5:$D$785,$B8,数据录入!$K$5:$K$785,H$5)) -> 0 | I8: =IF($B8="","",SUMIFS(数据录入!$G$5:$G$785,数据录入!$D$5:$D$785,$B8,数据录入!$K$5:$K$785,I$5)) -> 0 | J8: =IF($B8="","",SUMIFS(数据录入!$G$5:$G$785,数据录入!$D$5:$D$785,$B8,数据录入!$K$5:$K$785,J$5)) -> 0 | ... N8: =IF($B8="","",SUMIFS(数据录入!$G$5:$G$785,数据录入!$D$5:$D$785,$B8,数据录入!$K$5:$K$785,N$5)) -> 0 | O8: =SUM(C8:N8) -> 0 | P8: =IF($O$4=0,"",O8/$O$4) -> 0
A9: 4 | B9: 银行结息 | C9: =IF($B9="","",SUMIFS(数据录入!$G$5:$G$785,数据录入!$D$5:$D$785,$B9,数据录入!$K$5:$K$785,C$5)) -> 0 | D9: =IF($B9="","",SUMIFS(数据录入!$G$5:$G$785,数据录入!$D$5:$D$785,$B9,数据录入!$K$5:$K$785,D$5)) -> 0 | E9: =IF($B9="","",SUMIFS(数据录入!$G$5:$G$785,数据录入!$D$5:$D$785,$B9,数据录入!$K$5:$K$785,E$5)) -> 0 | F9: =IF($B9="","",SUMIFS(数据录入!$G$5:$G$785,数据录入!$D$5:$D$785,$B9,数据录入!$K$5:$K$785,F$5)) -> 0 | G9: =IF($B9="","",SUMIFS(数据录入!$G$5:$G$785,数据录入!$D$5:$D$785,$B9,数据录入!$K$5:$K$785,G$5)) -> 0 | H9: =IF($B9="","",SUMIFS(数据录入!$G$5:$G$785,数据录入!$D$5:$D$785,$B9,数据录入!$K$5:$K$785,H$5)) -> 0 | I9: =IF($B9="","",SUMIFS(数据录入!$G$5:$G$785,数据录入!$D$5:$D$785,$B9,数据录入!$K$5:$K$785,I$5)) -> 0 | J9: =IF($B9="","",SUMIFS(数据录入!$G$5:$G$785,数据录入!$D$5:$D$785,$B9,数据录入!$K$5:$K$785,J$5)) -> 0 | ... N9: =IF($B9="","",SUMIFS(数据录入!$G$5:$G$785,数据录入!$D$5:$D$785,$B9,数据录入!$K$5:$K$785,N$5)) -> 0 | O9: =SUM(C9:N9) -> 0 | P9: =IF($O$4=0,"",O9/$O$4) -> 0
A10: 5 | B10: 员工工资 | C10: =IF($B10="","",SUMIFS(数据录入!$G$5:$G$785,数据录入!$D$5:$D$785,$B10,数据录入!$K$5:$K$785,C$5)) -> 0 | D10: =IF($B10="","",SUMIFS(数据录入!$G$5:$G$785,数据录入!$D$5:$D$785,$B10,数据录入!$K$5:$K$785,D$5)) -> 0 | E10: =IF($B10="","",SUMIFS(数据录入!$G$5:$G$785,数据录入!$D$5:$D$785,$B10,数据录入!$K$5:$K$785,E$5)) -> 0 | F10: =IF($B10="","",SUMIFS(数据录入!$G$5:$G$785,数据录入!$D$5:$D$785,$B10,数据录入!$K$5:$K$785,F$5)) -> 0 | G10: =IF($B10="","",SUMIFS(数据录入!$G$5:$G$785,数据录入!$D$5:$D$785,$B10,数据录入!$K$5:$K$785,G$5)) -> 0 | H10: =IF($B10="","",SUMIFS(数据录入!$G$5:$G$785,数据录入!$D$5:$D$785,$B10,数据录入!$K$5:$K$785,H$5)) -> 0 | I10: =IF($B10="","",SUMIFS(数据录入!$G$5:$G$785,数据录入!$D$5:$D$785,$B10,数据录入!$K$5:$K$785,I$5)) -> 35187.36 | J10: =IF($B10="","",SUMIFS(数据录入!$G$5:$G$785,数据录入!$D$5:$D$785,$B10,数据录入!$K$5:$K$785,J$5)) -> 32721.45 | ... N10: =IF($B10="","",SUMIFS(数据录入!$G$5:$G$785,数据录入!$D$5:$D$785,$B10,数据录入!$K$5:$K$785,N$5)) -> 0 | O10: =SUM(C10:N10) -> 73408.81 | P10: =IF($O$4=0,"",O10/$O$4) -> 0.0020296941
A11: 6 | B11: 水电费 | C11: =IF($B11="","",SUMIFS(数据录入!$G$5:$G$785,数据录入!$D$5:$D$785,$B11,数据录入!$K$5:$K$785,C$5)) -> 0 | D11: =IF($B11="","",SUMIFS(数据录入!$G$5:$G$785,数据录入!$D$5:$D$785,$B11,数据录入!$K$5:$K$785,D$5)) -> 0 | E11: =IF($B11="","",SUMIFS(数据录入!$G$5:$G$785,数据录入!$D$5:$D$785,$B11,数据录入!$K$5:$K$785,E$5)) -> 0 | F11: =IF($B11="","",SUMIFS(数据录入!$G$5:$G$785,数据录入!$D$5:$D$785,$B11,数据录入!$K$5:$K$785,F$5)) -> 0 | G11: =IF($B11="","",SUMIFS(数据录入!$G$5:$G$785,数据录入!$D$5:$D$785,$B11,数据录入!$K$5:$K$785,G$5)) -> 0 | H11: =IF($B11="","",SUMIFS(数据录入!$G$5:$G$785,数据录入!$D$5:$D$785,$B11,数据录入!$K$5:$K$785,H$5)) -> 0 | I11: =IF($B11="","",SUMIFS(数据录入!$G$5:$G$785,数据录入!$D$5:$D$785,$B11,数据录入!$K$5:$K$785,I$5)) -> 1550 | J11: =IF($B11="","",SUMIFS(数据录入!$G$5:$G$785,数据录入!$D$5:$D$785,$B11,数据录入!$K$5:$K$785,J$5)) -> 2150 | ... N11: =IF($B11="","",SUMIFS(数据录入!$G$5:$G$785,数据录入!$D$5:$D$785,$B11,数据录入!$K$5:$K$785,N$5)) -> 0 | O11: =SUM(C11:N11) -> 5200 | P11: =IF($O$4=0,"",O11/$O$4) -> 0.00014377578
A12: 7 | B12: 房租 | C12: =IF($B12="","",SUMIFS(数据录入!$G$5:$G$785,数据录入!$D$5:$D$785,$B12,数据录入!$K$5:$K$785,C$5)) -> 0 | D12: =IF($B12="","",SUMIFS(数据录入!$G$5:$G$785,数据录入!$D$5:$D$785,$B12,数据录入!$K$5:$K$785,D$5)) -> 0 | E12: =IF($B12="","",SUMIFS(数据录入!$G$5:$G$785,数据录入!$D$5:$D$785,$B12,数据录入!$K$5:$K$785,E$5)) -> 0 | F12: =IF($B12="","",SUMIFS(数据录入!$G$5:$G$785,数据录入!$D$5:$D$785,$B12,数据录入!$K$5:$K$785,F$5)) -> 0 | G12: =IF($B12="","",SUMIFS(数据录入!$G$5:$G$785,数据录入!$D$5:$D$785,$B12,数据录入!$K$5:$K$785,G$5)) -> 0 | H12: =IF($B12="","",SUMIFS(数据录入!$G$5:$G$785,数据录入!$D$5:$D$785,$B12,数据录入!$K$5:$K$785,H$5)) -> 0 | I12: =IF($B12="","",SUMIFS(数据录入!$G$5:$G$785,数据录入!$D$5:$D$785,$B12,数据录入!$K$5:$K$785,I$5)) -> 0 | J12: =IF($B12="","",SUMIFS(数据录入!$G$5:$G$785,数据录入!$D$5:$D$785,$B12,数据录入!$K$5:$K$785,J$5)) -> 0 | ... N12: =IF($B12="","",SUMIFS(数据录入!$G$5:$G$785,数据录入!$D$5:$D$785,$B12,数据录入!$K$5:$K$785,N$5)) -> 0 | O12: =SUM(C12:N12) -> 45000 | P12: =IF($O$4=0,"",O12/$O$4) -> 0.0012442135
A13: 8 | B13: 办公费用 | C13: =IF($B13="","",SUMIFS(数据录入!$G$5:$G$785,数据录入!$D$5:$D$785,$B13,数据录入!$K$5:$K$785,C$5)) -> 0 | D13: =IF($B13="","",SUMIFS(数据录入!$G$5:$G$785,数据录入!$D$5:$D$785,$B13,数据录入!$K$5:$K$785,D$5)) -> 0 | E13: =IF($B13="","",SUMIFS(数据录入!$G$5:$G$785,数据录入!$D$5:$D$785,$B13,数据录入!$K$5:$K$785,E$5)) -> 0 | F13: =IF($B13="","",SUMIFS(数据录入!$G$5:$G$785,数据录入!$D$5:$D$785,$B13,数据录入!$K$5:$K$785,F$5)) -> 0 | G13: =IF($B13="","",SUMIFS(数据录入!$G$5:$G$785,数据录入!$D$5:$D$785,$B13,数据录入!$K$5:$K$785,G$5)) -> 0 | H13: =IF($B13="","",SUMIFS(数据录入!$G$5:$G$785,数据录入!$D$5:$D$785,$B13,数据录入!$K$5:$K$785,H$5)) -> 0 | I13: =IF($B13="","",SUMIFS(数据录入!$G$5:$G$785,数据录入!$D$5:$D$785,$B13,数据录入!$K$5:$K$785,I$5)) -> 4493.3 | J13: =IF($B13="","",SUMIFS(数据录入!$G$5:$G$785,数据录入!$D$5:$D$785,$B13,数据录入!$K$5:$K$785,J$5)) -> 1905.8 | ... N13: =IF($B13="","",SUMIFS(数据录入!$G$5:$G$785,数据录入!$D$5:$D$785,$B13,数据录入!$K$5:$K$785,N$5)) -> 0 | O13: =SUM(C13:N13) -> 10908.4 | P13: =IF($O$4=0,"",O13/$O$4) -> 0.00030160842
A14: 9 | B14: 招待费 | C14: =IF($B14="","",SUMIFS(数据录入!$G$5:$G$785,数据录入!$D$5:$D$785,$B14,数据录入!$K$5:$K$785,C$5)) -> 0 | D14: =IF($B14="","",SUMIFS(数据录入!$G$5:$G$785,数据录入!$D$5:$D$785,$B14,数据录入!$K$5:$K$785,D$5)) -> 0 | E14: =IF($B14="","",SUMIFS(数据录入!$G$5:$G$785,数据录入!$D$5:$D$785,$B14,数据录入!$K$5:$K$785,E$5)) -> 0 | F14: =IF($B14="","",SUMIFS(数据录入!$G$5:$G$785,数据录入!$D$5:$D$785,$B14,数据录入!$K$5:$K$785,F$5)) -> 0 | G14: =IF($B14="","",SUMIFS(数据录入!$G$5:$G$785,数据录入!$D$5:$D$785,$B14,数据录入!$K$5:$K$785,G$5)) -> 0 | H14: =IF($B14="","",SUMIFS(数据录入!$G$5:$G$785,数据录入!$D$5:$D$785,$B14,数据录入!$K$5:$K$785,H$5)) -> 0 | I14: =IF($B14="","",SUMIFS(数据录入!$G$5:$G$785,数据录入!$D$5:$D$785,$B14,数据录入!$K$5:$K$785,I$5)) -> 0 | J14: =IF($B14="","",SUMIFS(数据录入!$G$5:$G$785,数据录入!$D$5:$D$785,$B14,数据录入!$K$5:$K$785,J$5)) -> 0 | ... N14: =IF($B14="","",SUMIFS(数据录入!$G$5:$G$785,数据录入!$D$5:$D$785,$B14,数据录入!$K$5:$K$785,N$5)) -> 0 | O14: =SUM(C14:N14) -> 0 | P14: =IF($O$4=0,"",O14/$O$4) -> 0
A15: 10 | B15: 渠道费用 | C15: =IF($B15="","",SUMIFS(数据录入!$G$5:$G$785,数据录入!$D$5:$D$785,$B15,数据录入!$K$5:$K$785,C$5)) -> 0 | D15: =IF($B15="","",SUMIFS(数据录入!$G$5:$G$785,数据录入!$D$5:$D$785,$B15,数据录入!$K$5:$K$785,D$5)) -> 0 | E15: =IF($B15="","",SUMIFS(数据录入!$G$5:$G$785,数据录入!$D$5:$D$785,$B15,数据录入!$K$5:$K$785,E$5)) -> 0 | F15: =IF($B15="","",SUMIFS(数据录入!$G$5:$G$785,数据录入!$D$5:$D$785,$B15,数据录入!$K$5:$K$785,F$5)) -> 0 | G15: =IF($B15="","",SUMIFS(数据录入!$G$5:$G$785,数据录入!$D$5:$D$785,$B15,数据录入!$K$5:$K$785,G$5)) -> 0 | H15: =IF($B15="","",SUMIFS(数据录入!$G$5:$G$785,数据录入!$D$5:$D$785,$B15,数据录入!$K$5:$K$785,H$5)) -> 0 | I15: =IF($B15="","",SUMIFS(数据录入!$G$5:$G$785,数据录入!$D$5:$D$785,$B15,数据录入!$K$5:$K$785,I$5)) -> 83470 | J15: =IF($B15="","",SUMIFS(数据录入!$G$5:$G$785,数据录入!$D$5:$D$785,$B15,数据录入!$K$5:$K$785,J$5)) -> 45690 | ... N15: =IF($B15="","",SUMIFS(数据录入!$G$5:$G$785,数据录入!$D$5:$D$785,$B15,数据录入!$K$5:$K$785,N$5)) -> 0 | O15: =SUM(C15:N15) -> 154340 | P15: =IF($O$4=0,"",O15/$O$4) -> 0.0042673759
A16: 11 | B16: 手续费-收 | C16: =IF($B16="","",SUMIFS(数据录入!$G$5:$G$785,数据录入!$D$5:$D$785,$B16,数据录入!$K$5:$K$785,C$5)) -> 0 | D16: =IF($B16="","",SUMIFS(数据录入!$G$5:$G$785,数据录入!$D$5:$D$785,$B16,数据录入!$K$5:$K$785,D$5)) -> 0 | E16: =IF($B16="","",SUMIFS(数据录入!$G$5:$G$785,数据录入!$D$5:$D$785,$B16,数据录入!$K$5:$K$785,E$5)) -> 0 | F16: =IF($B16="","",SUMIFS(数据录入!$G$5:$G$785,数据录入!$D$5:$D$785,$B16,数据录入!$K$5:$K$785,F$5)) -> 0 | G16: =IF($B16="","",SUMIFS(数据录入!$G$5:$G$785,数据录入!$D$5:$D$785,$B16,数据录入!$K$5:$K$785,G$5)) -> 0 | H16: =IF($B16="","",SUMIFS(数据录入!$G$5:$G$785,数据录入!$D$5:$D$785,$B16,数据录入!$K$5:$K$785,H$5)) -> 0 | I16: =IF($B16="","",SUMIFS(数据录入!$G$5:$G$785,数据录入!$D$5:$D$785,$B16,数据录入!$K$5:$K$785,I$5)) -> 0 | J16: =IF($B16="","",SUMIFS(数据录入!$G$5:$G$785,数据录入!$D$5:$D$785,$B16,数据录入!$K$5:$K$785,J$5)) -> 0 | ... N16: =IF($B16="","",SUMIFS(数据录入!$G$5:$G$785,数据录入!$D$5:$D$785,$B16,数据录入!$K$5:$K$785,N$5)) -> 0 | O16: =SUM(C16:N16) -> 0 | P16: =IF($O$4=0,"",O16/$O$4) -> 0
A17: 12 | B17: 过桥/解押本金 | C17: =IF($B17="","",SUMIFS(数据录入!$G$5:$G$785,数据录入!$D$5:$D$785,$B17,数据录入!$K$5:$K$785,C$5)) -> 0 | D17: =IF($B17="","",SUMIFS(数据录入!$G$5:$G$785,数据录入!$D$5:$D$785,$B17,数据录入!$K$5:$K$785,D$5)) -> 0 | E17: =IF($B17="","",SUMIFS(数据录入!$G$5:$G$785,数据录入!$D$5:$D$785,$B17,数据录入!$K$5:$K$785,E$5)) -> 0 | F17: =IF($B17="","",SUMIFS(数据录入!$G$5:$G$785,数据录入!$D$5:$D$785,$B17,数据录入!$K$5:$K$785,F$5)) -> 0 | G17: =IF($B17="","",SUMIFS(数据录入!$G$5:$G$785,数据录入!$D$5:$D$785,$B17,数据录入!$K$5:$K$785,G$5)) -> 0 | H17: =IF($B17="","",SUMIFS(数据录入!$G$5:$G$785,数据录入!$D$5:$D$785,$B17,数据录入!$K$5:$K$785,H$5)) -> 0 | I17: =IF($B17="","",SUMIFS(数据录入!$G$5:$G$785,数据录入!$D$5:$D$785,$B17,数据录入!$K$5:$K$785,I$5)) -> 0 | J17: =IF($B17="","",SUMIFS(数据录入!$G$5:$G$785,数据录入!$D$5:$D$785,$B17,数据录入!$K$5:$K$785,J$5)) -> 0 | ... N17: =IF($B17="","",SUMIFS(数据录入!$G$5:$G$785,数据录入!$D$5:$D$785,$B17,数据录入!$K$5:$K$785,N$5)) -> 0 | O17: =SUM(C17:N17) -> 0 | P17: =IF($O$4=0,"",O17/$O$4) -> 0
... A29: 24 | B29: 明道本金 | C29: =IF($B29="","",SUMIFS(数据录入!$G$5:$G$785,数据录入!$D$5:$D$785,$B29,数据录入!$K$5:$K$785,C$5)) -> 0 | D29: =IF($B29="","",SUMIFS(数据录入!$G$5:$G$785,数据录入!$D$5:$D$785,$B29,数据录入!$K$5:$K$785,D$5)) -> 0 | E29: =IF($B29="","",SUMIFS(数据录入!$G$5:$G$785,数据录入!$D$5:$D$785,$B29,数据录入!$K$5:$K$785,E$5)) -> 0 | F29: =IF($B29="","",SUMIFS(数据录入!$G$5:$G$785,数据录入!$D$5:$D$785,$B29,数据录入!$K$5:$K$785,F$5)) -> 0 | G29: =IF($B29="","",SUMIFS(数据录入!$G$5:$G$785,数据录入!$D$5:$D$785,$B29,数据录入!$K$5:$K$785,G$5)) -> 0 | H29: =IF($B29="","",SUMIFS(数据录入!$G$5:$G$785,数据录入!$D$5:$D$785,$B29,数据录入!$K$5:$K$785,H$5)) -> 0 | I29: =IF($B29="","",SUMIFS(数据录入!$G$5:$G$785,数据录入!$D$5:$D$785,$B29,数据录入!$K$5:$K$785,I$5)) -> 400000 | J29: =IF($B29="","",SUMIFS(数据录入!$G$5:$G$785,数据录入!$D$5:$D$785,$B29,数据录入!$K$5:$K$785,J$5)) -> 3800000 | ... N29: =IF($B29="","",SUMIFS(数据录入!$G$5:$G$785,数据录入!$D$5:$D$785,$B29,数据录入!$K$5:$K$785,N$5)) -> 0 | O29: =SUM(C29:N29) -> 4200000 | P29: =IF($O$4=0,"",O29/$O$4) -> 0.1161266
A30: 25 | C30: =IF($B30="","",SUMIFS(数据录入!$G$5:$G$785,数据录入!$D$5:$D$785,$B30,数据录入!$K$5:$K$785,C$5)) | D30: =IF($B30="","",SUMIFS(数据录入!$G$5:$G$785,数据录入!$D$5:$D$785,$B30,数据录入!$K$5:$K$785,D$5)) | E30: =IF($B30="","",SUMIFS(数据录入!$G$5:$G$785,数据录入!$D$5:$D$785,$B30,数据录入!$K$5:$K$785,E$5)) | F30: =IF($B30="","",SUMIFS(数据录入!$G$5:$G$785,数据录入!$D$5:$D$785,$B30,数据录入!$K$5:$K$785,F$5)) | G30: =IF($B30="","",SUMIFS(数据录入!$G$5:$G$785,数据录入!$D$5:$D$785,$B30,数据录入!$K$5:$K$785,G$5)) | H30: =IF($B30="","",SUMIFS(数据录入!$G$5:$G$785,数据录入!$D$5:$D$785,$B30,数据录入!$K$5:$K$785,H$5)) | I30: =IF($B30="","",SUMIFS(数据录入!$G$5:$G$785,数据录入!$D$5:$D$785,$B30,数据录入!$K$5:$K$785,I$5)) | J30: =IF($B30="","",SUMIFS(数据录入!$G$5:$G$785,数据录入!$D$5:$D$785,$B30,数据录入!$K$5:$K$785,J$5)) | ... N30: =IF($B30="","",SUMIFS(数据录入!$G$5:$G$785,数据录入!$D$5:$D$785,$B30,数据录入!$K$5:$K$785,N$5)) | O30: =SUM(C30:N30) -> 0 | P30: =IF($O$4=0,"",O30/$O$4) -> 0
A31: 26 | C31: =IF($B31="","",SUMIFS(数据录入!$G$5:$G$785,数据录入!$D$5:$D$785,$B31,数据录入!$K$5:$K$785,C$5)) | D31: =IF($B31="","",SUMIFS(数据录入!$G$5:$G$785,数据录入!$D$5:$D$785,$B31,数据录入!$K$5:$K$785,D$5)) | E31: =IF($B31="","",SUMIFS(数据录入!$G$5:$G$785,数据录入!$D$5:$D$785,$B31,数据录入!$K$5:$K$785,E$5)) | F31: =IF($B31="","",SUMIFS(数据录入!$G$5:$G$785,数据录入!$D$5:$D$785,$B31,数据录入!$K$5:$K$785,F$5)) | G31: =IF($B31="","",SUMIFS(数据录入!$G$5:$G$785,数据录入!$D$5:$D$785,$B31,数据录入!$K$5:$K$785,G$5)) | H31: =IF($B31="","",SUMIFS(数据录入!$G$5:$G$785,数据录入!$D$5:$D$785,$B31,数据录入!$K$5:$K$785,H$5)) | I31: =IF($B31="","",SUMIFS(数据录入!$G$5:$G$785,数据录入!$D$5:$D$785,$B31,数据录入!$K$5:$K$785,I$5)) | J31: =IF($B31="","",SUMIFS(数据录入!$G$5:$G$785,数据录入!$D$5:$D$785,$B31,数据录入!$K$5:$K$785,J$5)) | ... N31: =IF($B31="","",SUMIFS(数据录入!$G$5:$G$785,数据录入!$D$5:$D$785,$B31,数据录入!$K$5:$K$785,N$5)) | O31: =SUM(C31:N31) -> 0 | P31: =IF($O$4=0,"",O31/$O$4) -> 0
A32: 27 | C32: =IF($B32="","",SUMIFS(数据录入!$G$5:$G$785,数据录入!$D$5:$D$785,$B32,数据录入!$K$5:$K$785,C$5)) | D32: =IF($B32="","",SUMIFS(数据录入!$G$5:$G$785,数据录入!$D$5:$D$785,$B32,数据录入!$K$5:$K$785,D$5)) | E32: =IF($B32="","",SUMIFS(数据录入!$G$5:$G$785,数据录入!$D$5:$D$785,$B32,数据录入!$K$5:$K$785,E$5)) | F32: =IF($B32="","",SUMIFS(数据录入!$G$5:$G$785,数据录入!$D$5:$D$785,$B32,数据录入!$K$5:$K$785,F$5)) | G32: =IF($B32="","",SUMIFS(数据录入!$G$5:$G$785,数据录入!$D$5:$D$785,$B32,数据录入!$K$5:$K$785,G$5)) | H32: =IF($B32="","",SUMIFS(数据录入!$G$5:$G$785,数据录入!$D$5:$D$785,$B32,数据录入!$K$5:$K$785,H$5)) | I32: =IF($B32="","",SUMIFS(数据录入!$G$5:$G$785,数据录入!$D$5:$D$785,$B32,数据录入!$K$5:$K$785,I$5)) | J32: =IF($B32="","",SUMIFS(数据录入!$G$5:$G$785,数据录入!$D$5:$D$785,$B32,数据录入!$K$5:$K$785,J$5)) | ... N32: =IF($B32="","",SUMIFS(数据录入!$G$5:$G$785,数据录入!$D$5:$D$785,$B32,数据录入!$K$5:$K$785,N$5)) | O32: =SUM(C32:N32) -> 0 | P32: =IF($O$4=0,"",O32/$O$4) -> 0
A33: 28 | C33: =IF($B33="","",SUMIFS(数据录入!$G$5:$G$785,数据录入!$D$5:$D$785,$B33,数据录入!$K$5:$K$785,C$5)) | D33: =IF($B33="","",SUMIFS(数据录入!$G$5:$G$785,数据录入!$D$5:$D$785,$B33,数据录入!$K$5:$K$785,D$5)) | E33: =IF($B33="","",SUMIFS(数据录入!$G$5:$G$785,数据录入!$D$5:$D$785,$B33,数据录入!$K$5:$K$785,E$5)) | F33: =IF($B33="","",SUMIFS(数据录入!$G$5:$G$785,数据录入!$D$5:$D$785,$B33,数据录入!$K$5:$K$785,F$5)) | G33: =IF($B33="","",SUMIFS(数据录入!$G$5:$G$785,数据录入!$D$5:$D$785,$B33,数据录入!$K$5:$K$785,G$5)) | H33: =IF($B33="","",SUMIFS(数据录入!$G$5:$G$785,数据录入!$D$5:$D$785,$B33,数据录入!$K$5:$K$785,H$5)) | I33: =IF($B33="","",SUMIFS(数据录入!$G$5:$G$785,数据录入!$D$5:$D$785,$B33,数据录入!$K$5:$K$785,I$5)) | J33: =IF($B33="","",SUMIFS(数据录入!$G$5:$G$785,数据录入!$D$5:$D$785,$B33,数据录入!$K$5:$K$785,J$5)) | ... N33: =IF($B33="","",SUMIFS(数据录入!$G$5:$G$785,数据录入!$D$5:$D$785,$B33,数据录入!$K$5:$K$785,N$5)) | O33: =SUM(C33:N33) -> 0 | P33: =IF($O$4=0,"",O33/$O$4) -> 0
A34: 29 | C34: =IF($B34="","",SUMIFS(数据录入!$G$5:$G$785,数据录入!$D$5:$D$785,$B34,数据录入!$K$5:$K$785,C$5)) | D34: =IF($B34="","",SUMIFS(数据录入!$G$5:$G$785,数据录入!$D$5:$D$785,$B34,数据录入!$K$5:$K$785,D$5)) | E34: =IF($B34="","",SUMIFS(数据录入!$G$5:$G$785,数据录入!$D$5:$D$785,$B34,数据录入!$K$5:$K$785,E$5)) | F34: =IF($B34="","",SUMIFS(数据录入!$G$5:$G$785,数据录入!$D$5:$D$785,$B34,数据录入!$K$5:$K$785,F$5)) | G34: =IF($B34="","",SUMIFS(数据录入!$G$5:$G$785,数据录入!$D$5:$D$785,$B34,数据录入!$K$5:$K$785,G$5)) | H34: =IF($B34="","",SUMIFS(数据录入!$G$5:$G$785,数据录入!$D$5:$D$785,$B34,数据录入!$K$5:$K$785,H$5)) | I34: =IF($B34="","",SUMIFS(数据录入!$G$5:$G$785,数据录入!$D$5:$D$785,$B34,数据录入!$K$5:$K$785,I$5)) | J34: =IF($B34="","",SUMIFS(数据录入!$G$5:$G$785,数据录入!$D$5:$D$785,$B34,数据录入!$K$5:$K$785,J$5)) | ... N34: =IF($B34="","",SUMIFS(数据录入!$G$5:$G$785,数据录入!$D$5:$D$785,$B34,数据录入!$K$5:$K$785,N$5)) | O34: =SUM(C34:N34) -> 0 | P34: =IF($O$4=0,"",O34/$O$4) -> 0
A35: 30 | C35: =IF($B35="","",SUMIFS(数据录入!$G$5:$G$785,数据录入!$D$5:$D$785,$B35,数据录入!$K$5:$K$785,C$5)) | D35: =IF($B35="","",SUMIFS(数据录入!$G$5:$G$785,数据录入!$D$5:$D$785,$B35,数据录入!$K$5:$K$785,D$5)) | E35: =IF($B35="","",SUMIFS(数据录入!$G$5:$G$785,数据录入!$D$5:$D$785,$B35,数据录入!$K$5:$K$785,E$5)) | F35: =IF($B35="","",SUMIFS(数据录入!$G$5:$G$785,数据录入!$D$5:$D$785,$B35,数据录入!$K$5:$K$785,F$5)) | G35: =IF($B35="","",SUMIFS(数据录入!$G$5:$G$785,数据录入!$D$5:$D$785,$B35,数据录入!$K$5:$K$785,G$5)) | H35: =IF($B35="","",SUMIFS(数据录入!$G$5:$G$785,数据录入!$D$5:$D$785,$B35,数据录入!$K$5:$K$785,H$5)) | I35: =IF($B35="","",SUMIFS(数据录入!$G$5:$G$785,数据录入!$D$5:$D$785,$B35,数据录入!$K$5:$K$785,I$5)) | J35: =IF($B35="","",SUMIFS(数据录入!$G$5:$G$785,数据录入!$D$5:$D$785,$B35,数据录入!$K$5:$K$785,J$5)) | ... N35: =IF($B35="","",SUMIFS(数据录入!$G$5:$G$785,数据录入!$D$5:$D$785,$B35,数据录入!$K$5:$K$785,N$5)) | O35: =SUM(C35:N35) -> 0 | P35: =IF($O$4=0,"",O35/$O$4) -> 0
A36: 31 | C36: =IF($B36="","",SUMIFS(数据录入!$G$5:$G$785,数据录入!$D$5:$D$785,$B36,数据录入!$K$5:$K$785,C$5)) | D36: =IF($B36="","",SUMIFS(数据录入!$G$5:$G$785,数据录入!$D$5:$D$785,$B36,数据录入!$K$5:$K$785,D$5)) | E36: =IF($B36="","",SUMIFS(数据录入!$G$5:$G$785,数据录入!$D$5:$D$785,$B36,数据录入!$K$5:$K$785,E$5)) | F36: =IF($B36="","",SUMIFS(数据录入!$G$5:$G$785,数据录入!$D$5:$D$785,$B36,数据录入!$K$5:$K$785,F$5)) | G36: =IF($B36="","",SUMIFS(数据录入!$G$5:$G$785,数据录入!$D$5:$D$785,$B36,数据录入!$K$5:$K$785,G$5)) | H36: =IF($B36="","",SUMIFS(数据录入!$G$5:$G$785,数据录入!$D$5:$D$785,$B36,数据录入!$K$5:$K$785,H$5)) | I36: =IF($B36="","",SUMIFS(数据录入!$G$5:$G$785,数据录入!$D$5:$D$785,$B36,数据录入!$K$5:$K$785,I$5)) | J36: =IF($B36="","",SUMIFS(数据录入!$G$5:$G$785,数据录入!$D$5:$D$785,$B36,数据录入!$K$5:$K$785,J$5)) | ... N36: =IF($B36="","",SUMIFS(数据录入!$G$5:$G$785,数据录入!$D$5:$D$785,$B36,数据录入!$K$5:$K$785,N$5)) | O36: =SUM(C36:N36) -> 0 | P36: =IF($O$4=0,"",O36/$O$4) -> 0
A37: 32 | C37: =IF($B37="","",SUMIFS(数据录入!$G$5:$G$785,数据录入!$D$5:$D$785,$B37,数据录入!$K$5:$K$785,C$5)) | D37: =IF($B37="","",SUMIFS(数据录入!$G$5:$G$785,数据录入!$D$5:$D$785,$B37,数据录入!$K$5:$K$785,D$5)) | E37: =IF($B37="","",SUMIFS(数据录入!$G$5:$G$785,数据录入!$D$5:$D$785,$B37,数据录入!$K$5:$K$785,E$5)) | F37: =IF($B37="","",SUMIFS(数据录入!$G$5:$G$785,数据录入!$D$5:$D$785,$B37,数据录入!$K$5:$K$785,F$5)) | G37: =IF($B37="","",SUMIFS(数据录入!$G$5:$G$785,数据录入!$D$5:$D$785,$B37,数据录入!$K$5:$K$785,G$5)) | H37: =IF($B37="","",SUMIFS(数据录入!$G$5:$G$785,数据录入!$D$5:$D$785,$B37,数据录入!$K$5:$K$785,H$5)) | I37: =IF($B37="","",SUMIFS(数据录入!$G$5:$G$785,数据录入!$D$5:$D$785,$B37,数据录入!$K$5:$K$785,I$5)) | J37: =IF($B37="","",SUMIFS(数据录入!$G$5:$G$785,数据录入!$D$5:$D$785,$B37,数据录入!$K$5:$K$785,J$5)) | ... N37: =IF($B37="","",SUMIFS(数据录入!$G$5:$G$785,数据录入!$D$5:$D$785,$B37,数据录入!$K$5:$K$785,N$5)) | O37: =SUM(C37:N37) -> 0 | P37: =IF($O$4=0,"",O37/$O$4) -> 0
A38: 33 | C38: =IF($B38="","",SUMIFS(数据录入!$G$5:$G$785,数据录入!$D$5:$D$785,$B38,数据录入!$K$5:$K$785,C$5)) | D38: =IF($B38="","",SUMIFS(数据录入!$G$5:$G$785,数据录入!$D$5:$D$785,$B38,数据录入!$K$5:$K$785,D$5)) | E38: =IF($B38="","",SUMIFS(数据录入!$G$5:$G$785,数据录入!$D$5:$D$785,$B38,数据录入!$K$5:$K$785,E$5)) | F38: =IF($B38="","",SUMIFS(数据录入!$G$5:$G$785,数据录入!$D$5:$D$785,$B38,数据录入!$K$5:$K$785,F$5)) | G38: =IF($B38="","",SUMIFS(数据录入!$G$5:$G$785,数据录入!$D$5:$D$785,$B38,数据录入!$K$5:$K$785,G$5)) | H38: =IF($B38="","",SUMIFS(数据录入!$G$5:$G$785,数据录入!$D$5:$D$785,$B38,数据录入!$K$5:$K$785,H$5)) | I38: =IF($B38="","",SUMIFS(数据录入!$G$5:$G$785,数据录入!$D$5:$D$785,$B38,数据录入!$K$5:$K$785,I$5)) | J38: =IF($B38="","",SUMIFS(数据录入!$G$5:$G$785,数据录入!$D$5:$D$785,$B38,数据录入!$K$5:$K$785,J$5)) | ... N38: =IF($B38="","",SUMIFS(数据录入!$G$5:$G$785,数据录入!$D$5:$D$785,$B38,数据录入!$K$5:$K$785,N$5)) | O38: =SUM(C38:N38) -> 0 | P38: =IF($O$4=0,"",O38/$O$4) -> 0
A39: 34 | C39: =IF($B39="","",SUMIFS(数据录入!$G$5:$G$785,数据录入!$D$5:$D$785,$B39,数据录入!$K$5:$K$785,C$5)) | D39: =IF($B39="","",SUMIFS(数据录入!$G$5:$G$785,数据录入!$D$5:$D$785,$B39,数据录入!$K$5:$K$785,D$5)) | E39: =IF($B39="","",SUMIFS(数据录入!$G$5:$G$785,数据录入!$D$5:$D$785,$B39,数据录入!$K$5:$K$785,E$5)) | F39: =IF($B39="","",SUMIFS(数据录入!$G$5:$G$785,数据录入!$D$5:$D$785,$B39,数据录入!$K$5:$K$785,F$5)) | G39: =IF($B39="","",SUMIFS(数据录入!$G$5:$G$785,数据录入!$D$5:$D$785,$B39,数据录入!$K$5:$K$785,G$5)) | H39: =IF($B39="","",SUMIFS(数据录入!$G$5:$G$785,数据录入!$D$5:$D$785,$B39,数据录入!$K$5:$K$785,H$5)) | I39: =IF($B39="","",SUMIFS(数据录入!$G$5:$G$785,数据录入!$D$5:$D$785,$B39,数据录入!$K$5:$K$785,I$5)) | J39: =IF($B39="","",SUMIFS(数据录入!$G$5:$G$785,数据录入!$D$5:$D$785,$B39,数据录入!$K$5:$K$785,J$5)) | ... N39: =IF($B39="","",SUMIFS(数据录入!$G$5:$G$785,数据录入!$D$5:$D$785,$B39,数据录入!$K$5:$K$785,N$5)) | O39: =SUM(C39:N39) -> 0 | P39: =IF($O$4=0,"",O39/$O$4) -> 0
