Workbook

Sheet 说明
B1: 记账凭证自动生成器
B3: 【每月只做 4 件事】
B4: 1. 把海典零售导出的“日报明细”整表（含表头）粘到 输入海典 页签的 A1（最后那行“总计”不要粘）；
B5: 2. 把聚合支付平台导出的门店汇总填到 输入聚合 （编码 / 交易金额 / 服务费）；
B6: 3. 把各店网银现金合计填到 输入现金 ；回款表填到 输入回款 ；报销单填到 输入报销 ；
B7: 4. 到 参数 页签改一下会计日期和摘要 —— 三套凭证就自动出来了。
B9: 【凭证在这三个页签】
B10: 凭证收入 凭证回款 凭证报销 （版式和你现在手写的记账凭证一致，每页 6 行分录，超过自动接下一页，合计只出现在最后一页）
B11: 每张凭证已设好分页符（A5 横向 = 标准凭证纸）：打印时选“页码范围 1 到 N”，N 见 参数 页签的“共几页”。
B13: 【换月份怎么做】
B14: 先把上个月的数据整行删掉（输入海典 / 输入聚合 / 输入现金 / 输入回款 / 输入报销 这 5 页），再粘新的；
B15: 删的时候选中行号右键“删除”，不要只按 Delete 键留下空行——留空行不影响结果，但看着乱。
... B70: 想改回“把号直接印出来”，到 参数 页把“凭证号是否打印”选成 是 就行。

Sheet 参数
A1: 参数设置
A2: 会计日期 | B2: 46234
A3: 收入凭证摘要 | B3: 7月收入
A4: 回款凭证摘要 | B4: 回款
A5: 报销凭证摘要（缺省） | B5: 报销费用 | C5: 输入报销里没写摘要时用这个
A6: 贷方科目1 | B6: 库存现金 | C6: 报销单“付款方式”可选项
A7: 贷方科目2 | B7: 银行存款
A8: 贷方科目3 | B8: 其他应付款
A9: 凭证号是否打印 | B9: 否 | C9: 选「否」＝凭证右上角留空，打印出来自己手写号；选「是」＝把自动排的号直接印出来
A10: 收入凭证 共几页 | B10: =助手收入!$V$1 -> 78 | C10: 打印时选：页码 1 到 这个数 | D10: =IF(助手收入!$V$1>280,"⚠ 凭证页不够，请找我加","")
A11: 回款凭证 共几页 | B11: =助手回款!$V$1 -> 46 | D11: =IF(助手回款!$V$1>210,"⚠ 凭证页不够，请找我加","")
A12: 报销凭证 共几页 | B12: =助手报销!$V$1 -> 39 | D12: =IF(助手报销!$V$1>200,"⚠ 凭证页不够，请找我加","")
A14: 粘进来的海典明细 最早会计日 | B14: =IFERROR(MIN(INDEX(输入海典!$A$1:$AN$20000,0,IFERROR(MATCH("会计日",输入海典!$1:$1,0),1))),"") -> 46204 | C14: ← 这两个日期要落在同一个月内，否则说明粘进去的不止一个月
A15: 粘进来的海典明细 最晚会计日 | B15: =IFERROR(MAX(INDEX(输入海典!$A$1:$AN$20000,0,IFERROR(MATCH("会计日",输入海典!$1:$1,0),1))),"") -> 46234
A17: 海典明细里“销售合计”列合计 | B17: =IFERROR(SUM(INDEX(输入海典!$A$1:$AN$20000,0,MATCH("销售合计",输入海典!$1:$1,0))),0) -> 2818376.6
A18: 按门店汇总后的合计 | B18: =ROUND(SUM(海典汇总!$AE$3:$AE$67),2) -> 2818376.6
A19: 差异（应为 0） | B19: =ROUND($B$17-$B$18,2) -> 0 | C19: 不为 0 常见两个原因：粘进来的明细带了“总计/合计”行；或者有门店没写进 门店对照

Sheet 门店对照
A1: 门店编码 | B1: 海典门店名称 | C1: 凭证简称 | D1: 启用(自动) | F1: 【备用门店位】灰色那 10 行是留给以后新开门店的。
A2: 2001 | B2: 柏人商城分店（1店） | C2: 柏人商城店 | D2: =IF(OR($A2="",$C2=""),0,IF(ISNUMBER(FIND("备用",$B2&$C2)),0,1)) -> 1 | F2: 名称里带“备用”两个字、或者门店编码是空的，启用列就是 0 —— 不出凭证、也不占凭证号。
A3: 2002 | B3: 新隆分店（2分店） | C3: 新隆店 | D3: =IF(OR($A3="",$C3=""),0,IF(ISNUMBER(FIND("备用",$B3&$C3)),0,1)) -> 1 | F3: 新开一家店：把其中一行的 门店编码 / 海典门店名称 / 凭证简称 三格改成真的，启用列会自动变 1。
A4: 2003 | B4: 康庄东路分店（3店） | C4: 康庄路店 | D4: =IF(OR($A4="",$C4=""),0,IF(ISNUMBER(FIND("备用",$B4&$C4)),0,1)) -> 1 | F4: 不用的老店想停掉：把凭证简称改成“备用X”，或者把门店编码清空就行。
A5: 2004 | B5: 东关分店（4分店） | C5: 东关店 | D5: =IF(OR($A5="",$C5=""),0,IF(ISNUMBER(FIND("备用",$B5&$C5)),0,1)) -> 1 | F5: 启用列是公式自动算的，不要手工改。
A6: 2005 | B6: 象城街分店（5店） | C6: 象城街店 | D6: =IF(OR($A6="",$C6=""),0,IF(ISNUMBER(FIND("备用",$B6&$C6)),0,1)) -> 1
A7: 2006 | B7: 博荣分店（6分店） | C7: 博荣店 | D7: =IF(OR($A7="",$C7=""),0,IF(ISNUMBER(FIND("备用",$B7&$C7)),0,1)) -> 1
A8: 2007 | B8: 华鑫分店（7店） | C8: 华鑫店 | D8: =IF(OR($A8="",$C8=""),0,IF(ISNUMBER(FIND("备用",$B8&$C8)),0,1)) -> 1
A9: 2008 | B9: 博昭分店（8分店） | C9: 博昭店 | D9: =IF(OR($A9="",$C9=""),0,IF(ISNUMBER(FIND("备用",$B9&$C9)),0,1)) -> 1
A10: 2009 | B10: 大霍分店（9分店） | C10: 大霍店 | D10: =IF(OR($A10="",$C10=""),0,IF(ISNUMBER(FIND("备用",$B10&$C10)),0,1)) -> 1
A11: 2010 | B11: 莲子镇分店(10分店) | C11: 莲子镇店 | D11: =IF(OR($A11="",$C11=""),0,IF(ISNUMBER(FIND("备用",$B11&$C11)),0,1)) -> 1
A12: 2011 | B12: 毛尔寨分店(11分店) | C12: 毛尔寨店 | D12: =IF(OR($A12="",$C12=""),0,IF(ISNUMBER(FIND("备用",$B12&$C12)),0,1)) -> 1
A13: 2012 | B13: 泽畔分店（12分店） | C13: 泽畔店 | D13: =IF(OR($A13="",$C13=""),0,IF(ISNUMBER(FIND("备用",$B13&$C13)),0,1)) -> 1
A14: 2014 | B14: 博桥分店（14分店） | C14: 博桥店 | D14: =IF(OR($A14="",$C14=""),0,IF(ISNUMBER(FIND("备用",$B14&$C14)),0,1)) -> 1
A15: 2015 | B15: 齐村分店（15分店） | C15: 齐村店 | D15: =IF(OR($A15="",$C15=""),0,IF(ISNUMBER(FIND("备用",$B15&$C15)),0,1)) -> 1
A16: 2017 | B16: 博天分店（17分店） | C16: 博天店 | D16: =IF(OR($A16="",$C16=""),0,IF(ISNUMBER(FIND("备用",$B16&$C16)),0,1)) -> 1
A17: 2018 | B17: 魏家庄分店（18分店） | C17: 魏家庄店 | D17: =IF(OR($A17="",$C17=""),0,IF(ISNUMBER(FIND("备用",$B17&$C17)),0,1)) -> 1
... A46: 2069 | B46: 博东分店（69店） | C46: 博东店 | D46: =IF(OR($A46="",$C46=""),0,IF(ISNUMBER(FIND("备用",$B46&$C46)),0,1)) -> 1
B47: 备用1 | C47: 备用1 | D47: =IF(OR($A47="",$C47=""),0,IF(ISNUMBER(FIND("备用",$B47&$C47)),0,1)) -> 0
B48: 备用2 | C48: 备用2 | D48: =IF(OR($A48="",$C48=""),0,IF(ISNUMBER(FIND("备用",$B48&$C48)),0,1)) -> 0
B49: 备用3 | C49: 备用3 | D49: =IF(OR($A49="",$C49=""),0,IF(ISNUMBER(FIND("备用",$B49&$C49)),0,1)) -> 0
B50: 备用4 | C50: 备用4 | D50: =IF(OR($A50="",$C50=""),0,IF(ISNUMBER(FIND("备用",$B50&$C50)),0,1)) -> 0
B51: 备用5 | C51: 备用5 | D51: =IF(OR($A51="",$C51=""),0,IF(ISNUMBER(FIND("备用",$B51&$C51)),0,1)) -> 0
B52: 备用6 | C52: 备用6 | D52: =IF(OR($A52="",$C52=""),0,IF(ISNUMBER(FIND("备用",$B52&$C52)),0,1)) -> 0
B53: 备用7 | C53: 备用7 | D53: =IF(OR($A53="",$C53=""),0,IF(ISNUMBER(FIND("备用",$B53&$C53)),0,1)) -> 0
B54: 备用8 | C54: 备用8 | D54: =IF(OR($A54="",$C54=""),0,IF(ISNUMBER(FIND("备用",$B54&$C54)),0,1)) -> 0
B55: 备用9 | C55: 备用9 | D55: =IF(OR($A55="",$C55=""),0,IF(ISNUMBER(FIND("备用",$B55&$C55)),0,1)) -> 0
B56: 备用10 | C56: 备用10 | D56: =IF(OR($A56="",$C56=""),0,IF(ISNUMBER(FIND("备用",$B56&$C56)),0,1)) -> 0
B57: 备用11 | C57: 备用11 | D57: =IF(OR($A57="",$C57=""),0,IF(ISNUMBER(FIND("备用",$B57&$C57)),0,1)) -> 0
B58: 备用12 | C58: 备用12 | D58: =IF(OR($A58="",$C58=""),0,IF(ISNUMBER(FIND("备用",$B58&$C58)),0,1)) -> 0
... B66: 备用20 | C66: 备用20 | D66: =IF(OR($A66="",$C66=""),0,IF(ISNUMBER(FIND("备用",$B66&$C66)),0,1)) -> 0

Sheet 科目对照收入
A1: 序 | B1: 项目 | C1: 总账科目 | D1: 明细科目 | E1: 取数来源 | F1: 海典列1 | G1: 海典列2 | H1: 海典列3 | I1: 海典列4 | J1: 海典列5 | K1: 海典列6 | L1: 负数时总账科目 | M1: 负数时明细科目 | O1: 【黄色 = 按平台金额入账】
A2: 1 | B2: 库存现金 | C2: 库存现金 | E2: 现金+补差 | O2: 海典列1 涂黄的这些渠道（医保、健e卡、医卡通、企健网、亲情卡、24小时、美团、饿了么、京东秒送、银联、小镇外卖、OMS、平安药卡），
A3: 2 | B3: 聚合支付 | C3: 应收账款 | D3: 聚合支付 | E3: 聚合净额 | O3: 凭证金额优先取 输入平台 页里你填的平台金额；那一行没填才回退到海典金额。平台和海典的差，仍旧走“少钱补现金 / 多钱记营业外”。
A4: 3 | B4: 医保 | C4: 应收账款 | D4: 医保 | E4: 平台优先 | F4: 医保 | G4: 医保统筹
A5: 4 | B5: 健e卡 | C5: 应收账款 | D5: 健e卡 | E5: 平台优先 | F5: 健e卡 | O5: 【负数时总账科目 / 负数时明细科目】
A6: 5 | B6: 医卡通 | C6: 应收账款 | D6: 医卡通 | E6: 平台优先 | F6: 医卡通 | O6: 填了这两格，金额算出来是负数时就换成这个科目、并记到贷方。
A7: 6 | B7: 企健网 | C7: 应收账款 | D7: 企健网 | E7: 平台优先 | F7: 企健网 | O7: 会员零钱包已按你的批注设好：正数 → 借 其他应收款—会员零钱包；负数 → 贷 其他应付款—会员零钱包。
A8: 7 | B8: 亲情卡 | C8: 应收账款 | D8: 亲情卡 | E8: 平台优先 | F8: 亲情卡
A9: 8 | B9: 24小时 | C9: 应收账款 | D9: 24小时 | E9: 平台优先 | F9: 二十四小时 | O9: 【促销费 / 积分】
A10: 9 | B10: 美团 | C10: 应收账款 | D10: 美团 | E10: 平台优先 | F10: 美团 | O10: 促销费 = 微信平台优惠券 + 微信平台礼品券 + 代金券；积分抵现 已单独拆成 销售费用—积分。
A11: 10 | B11: 饿了么 | C11: 应收账款 | D11: 饿了么 | E11: 平台优先 | F11: 饿了么 | O11: 京东LOC券、收银兑换损失 按你的批注去掉了，不再进促销费；万一某月有金额，核对 页会提醒你（想加回来就填进空的海典列里）。
A12: 11 | B12: 京东秒送 | C12: 应收账款 | D12: 京东秒送 | E12: 平台优先 | F12: 京东秒送
A13: 12 | B13: 银联 | C13: 应收账款 | D13: 银联 | E13: 平台优先 | F13: 银联 | O13: 总账科目 / 明细科目（黄底）可以直接改，改完凭证自动跟着变；取数来源和海典列是引擎用的，不要改。
A14: 13 | B14: 小镇外卖 | C14: 应收账款 | D14: 小镇外卖 | E14: 平台优先 | F14: 小镇外卖
A15: 14 | B15: OMS线上支付 | C15: 应收账款 | D15: OMS线上 | E15: 平台优先 | F15: OMS线上支付
A16: 15 | B16: 平安药卡 | C16: 应收账款 | D16: 平安 | E16: 平台优先 | F16: 平安药卡组合支付
A17: 16 | B17: 储值卡 | C17: 其他应收款 | D17: 储值卡 | E17: 海典 | F17: 储值卡
A18: 17 | B18: 会员零钱包 | C18: 其他应收款 | D18: 会员零钱包 | E18: 海典 | F18: 会员零钱包 | L18: 其他应付款 | M18: 会员零钱包
A19: 18 | B19: 促销费 | C19: 销售费用 | D19: 促销费 | E19: 海典 | F19: 微信平台优惠券 | G19: 微信平台礼品券 | H19: 代金券
A20: 19 | B20: 积分 | C20: 销售费用 | D20: 积分 | E20: 海典 | F20: 积分抵现
A21: 20 | B21: 手续费 | C21: 财务费用 | D21: 手续费 | E21: 聚合手续费
A22: 21 | B22: 主营业务收入 | C22: 主营业务收入 | E22: 销售合计
A23: 22 | B23: 营业外收入 | C23: 营业外收入 | E23: 差额

Sheet 科目对照回款
A1: 序 | B1: 项目 | C1: 总账科目 | D1: 明细科目 | E1: 方向 | F1: 收款方式别名1 | G1: 收款方式别名2 | H1: 收款方式别名3 | J1: “收款方式别名”＝ 输入回款 里你写的收款方式名称，写全就能自动归到同一个科目。
A2: 1 | B2: 库存现金 | C2: 库存现金 | E2: 借-回款合计
A3: 2 | B3: 手续费 | C3: 财务费用 | D3: 手续费 | E3: 借-手续费合计
A4: 3 | B4: 聚合支付 | C4: 应收账款 | D4: 聚合支付 | E4: 贷 | F4: 聚合支付
A5: 4 | B5: 医保 | C5: 应收账款 | D5: 医保 | E5: 贷 | F5: 医保 | G5: 医保即时拨付 | H5: 即时拨付
A6: 5 | B6: 美团 | C6: 应收账款 | D6: 美团 | E6: 贷 | F6: 美团
A7: 6 | B7: 饿了么 | C7: 应收账款 | D7: 饿了么 | E7: 贷 | F7: 饿了么
A8: 7 | B8: 24小时 | C8: 应收账款 | D8: 24小时 | E8: 贷 | F8: 24小时 | G8: 二十四小时
A9: 8 | B9: 健E卡 | C9: 应收账款 | D9: 健E卡 | E9: 贷 | F9: 健E卡
A10: 9 | B10: 医卡通 | C10: 应收账款 | D10: 医卡通 | E10: 贷 | F10: 医卡通
A11: 10 | B11: 企健网 | C11: 应收账款 | D11: 企健网 | E11: 贷 | F11: 企健网
A12: 11 | B12: 亲情卡 | C12: 应收账款 | D12: 亲情卡 | E12: 贷 | F12: 亲情卡
A13: 12 | B13: 银联 | C13: 应收账款 | D13: 银联 | E13: 贷 | F13: 银联
A14: 13 | B14: 代金券 | C14: 应收账款 | D14: 代金券 | E14: 贷 | F14: 代金券
A15: 14 | B15: 药机微信 | C15: 应收账款 | D15: 药机微信 | E15: 贷 | F15: 药机微信
A16: 15 | B16: 储值卡 | C16: 其他应收款 | D16: 储值卡 | E16: 贷 | F16: 储值卡

Sheet 输入海典
A1: 序 | B1: 门店代码 | C1: 门店名称 | D1: 会计日 | E1: 现金 | F1: 现11金 | G1: 海典聚合支付 | H1: 医保 | I1: 医保统筹 | J1: 健e卡 | K1: 医卡通 | L1: 企健网 | M1: 二十四小时 | N1: OMS线上支付 | O1: 美团 | P1: 饿了么 | Q1: 京东秒送 | R1: 会员零钱包 | S1: 储值卡 | T1: 积分抵现 | U1: 代金券 | V1: 微信平台礼品券 | W1: 微信平台优惠券 | X1: 银联 | Y1: 微信 | Z1: 支付宝 | AA1: 支付宝_老 | AB1: 亲情卡 | AC1: 京东LOC劵 | AD1: 平安药卡组合支付 | AE1: 小镇外卖 | AF1: 收银兑换损失 | AG1: 销售合计 | AH1: 合计 | AI1: 客流量
A2: 1 | B2: 2001 | C2: 柏人商城分店（1店） | D2: 46208 | E2: 179.2 | F2: 0 | G2: 362.3 | H2: 116 | I2: 0 | J2: 0 | K2: 0 | L2: 0 | M2: 0 | N2: 0 | O2: 0 | P2: 0 | Q2: 0 | R2: 0 | S2: 0 | T2: 0 | U2: 0 | V2: 0 | W2: 0 | X2: 0 | Y2: 0 | Z2: 0 | AA2: 0 | AB2: 0 | AC2: 0 | AD2: 0 | AE2: 0 | AF2: 0 | AG2: 657.5 | AH2: 657.5 | AI2: 20
A3: 2 | B3: 2001 | C3: 柏人商城分店（1店） | D3: 46233 | E3: 54.2 | F3: 0 | G3: 1159.2 | H3: 136 | I3: 0 | J3: 0 | K3: 0 | L3: 0 | M3: 0 | N3: 0 | O3: 0 | P3: 0 | Q3: 0 | R3: 0 | S3: 0 | T3: 0 | U3: 0 | V3: 9.9 | W3: 85.1 | X3: 0 | Y3: 0 | Z3: 0 | AA3: 0 | AB3: 0 | AC3: 0 | AD3: 0 | AE3: 0 | AF3: 0 | AG3: 1444.4 | AH3: 1444.4 | AI3: 26
A4: 3 | B4: 2001 | C4: 柏人商城分店（1店） | D4: 46232 | E4: 159.8 | F4: 0 | G4: 880.2 | H4: 126.4 | I4: 0 | J4: 0 | K4: 0 | L4: 0 | M4: 0 | N4: 0 | O4: 0 | P4: 0 | Q4: 0 | R4: 0 | S4: 0 | T4: 0 | U4: 0 | V4: 0 | W4: 65 | X4: 0 | Y4: 0 | Z4: 0 | AA4: 0 | AB4: 0 | AC4: 0 | AD4: 0 | AE4: 0 | AF4: 0 | AG4: 1231.4 | AH4: 1231.4 | AI4: 28
A5: 4 | B5: 2001 | C5: 柏人商城分店（1店） | D5: 46204 | E5: 840.31 | F5: 0 | G5: 631.81 | H5: 261.16 | I5: 0 | J5: 0 | K5: 0 | L5: 0 | M5: 0 | N5: 0 | O5: 0 | P5: 0 | Q5: 0 | R5: 0 | S5: 0 | T5: 0 | U5: 0 | V5: 3 | W5: 0 | X5: 0 | Y5: 0 | Z5: 0 | AA5: 0 | AB5: 0 | AC5: 0 | AD5: 0 | AE5: 0 | AF5: 0 | AG5: 1736.28 | AH5: 1736.28 | AI5: 37
A6: 5 | B6: 2001 | C6: 柏人商城分店（1店） | D6: 46234 | E6: 74.35 | F6: 0 | G6: 367.75 | H6: 448.9 | I6: 0 | J6: 0 | K6: 0 | L6: 0 | M6: 0 | N6: 0 | O6: 0 | P6: 0 | Q6: 0 | R6: 0 | S6: 0 | T6: 0 | U6: 0 | V6: 0 | W6: 40 | X6: 0 | Y6: 0 | Z6: 0 | AA6: 0 | AB6: 0 | AC6: 0 | AD6: 0 | AE6: 0 | AF6: 0 | AG6: 931 | AH6: 931 | AI6: 20
A7: 6 | B7: 2001 | C7: 柏人商城分店（1店） | D7: 46231 | E7: 127.4 | F7: 0 | G7: 574.05 | H7: 204.8 | I7: 0 | J7: 0 | K7: 0 | L7: 0 | M7: 0 | N7: 0 | O7: 0 | P7: 0 | Q7: 0 | R7: 0 | S7: 0 | T7: 0 | U7: 0 | V7: 0 | W7: 65 | X7: 0 | Y7: 0 | Z7: 0 | AA7: 0 | AB7: 0 | AC7: 0 | AD7: 0 | AE7: 0 | AF7: 0 | AG7: 971.25 | AH7: 971.25 | AI7: 21
A8: 7 | B8: 2001 | C8: 柏人商城分店（1店） | D8: 46220 | E8: 40.8 | F8: 0 | G8: 661.7 | H8: 47.8 | I8: 0 | J8: 0 | K8: 0 | L8: 0 | M8: 0 | N8: 0 | O8: 26 | P8: 0 | Q8: 0 | R8: 0 | S8: 0 | T8: 0 | U8: 0 | V8: 0 | W8: 5 | X8: 0 | Y8: 0 | Z8: 0 | AA8: 0 | AB8: 0 | AC8: 0 | AD8: 0 | AE8: 0 | AF8: 0 | AG8: 781.3 | AH8: 781.3 | AI8: 18
A9: 8 | B9: 2001 | C9: 柏人商城分店（1店） | D9: 46221 | E9: 138.3 | F9: 0 | G9: 510 | H9: 182 | I9: 0 | J9: 0 | K9: 0 | L9: 0 | M9: 0 | N9: 0 | O9: 0 | P9: 0 | Q9: 0 | R9: 0 | S9: 0 | T9: 0 | U9: 0 | V9: 0 | W9: 16 | X9: 0 | Y9: 0 | Z9: 0 | AA9: 0 | AB9: 0 | AC9: 0 | AD9: 0 | AE9: 0 | AF9: 0 | AG9: 846.3 | AH9: 846.3 | AI9: 19
A10: 9 | B10: 2001 | C10: 柏人商城分店（1店） | D10: 46209 | E10: 970.94 | F10: 0 | G10: 1261.58 | H10: 211.84 | I10: 0 | J10: 0 | K10: 0 | L10: 0 | M10: 0 | N10: 0 | O10: 0 | P10: 0 | Q10: 0 | R10: 0 | S10: 0 | T10: 0 | U10: 0 | V10: 3.8 | W10: 21 | X10: 0 | Y10: 0 | Z10: 0 | AA10: 0 | AB10: 0 | AC10: 0 | AD10: 0 | AE10: 0 | AF10: 0 | AG10: 2469.16 | AH10: 2469.16 | AI10: 40
A11: 10 | B11: 2001 | C11: 柏人商城分店（1店） | D11: 46212 | E11: 114.6 | F11: 0 | G11: 581.22 | H11: 35.6 | I11: 0 | J11: 0 | K11: 0 | L11: 0 | M11: 0 | N11: 0 | O11: 0 | P11: 0 | Q11: 0 | R11: 0 | S11: 0 | T11: 0 | U11: 0 | V11: 0 | W11: 0 | X11: 0 | Y11: 0 | Z11: 0 | AA11: 0 | AB11: 0 | AC11: 0 | AD11: 0 | AE11: 0 | AF11: 0 | AG11: 731.42 | AH11: 731.42 | AI11: 18
A12: 11 | B12: 2001 | C12: 柏人商城分店（1店） | D12: 46227 | E12: 253.4 | F12: 0 | G12: 570.5 | H12: 220 | I12: 0 | J12: 0 | K12: 0 | L12: 0 | M12: 0 | N12: 0 | O12: 0 | P12: 0 | Q12: 0 | R12: 0 | S12: 0 | T12: 0 | U12: 0 | V12: 0 | W12: 0 | X12: 0 | Y12: 0 | Z12: 0 | AA12: 0 | AB12: 0 | AC12: 0 | AD12: 0 | AE12: 0 | AF12: 0 | AG12: 1043.9 | AH12: 1043.9 | AI12: 26
A13: 12 | B13: 2001 | C13: 柏人商城分店（1店） | D13: 46222 | E13: 51 | F13: 0 | G13: 707.65 | H13: 194.5 | I13: 0 | J13: 0 | K13: 0 | L13: 0 | M13: 0 | N13: 0 | O13: 0 | P13: 0 | Q13: 0 | R13: 0 | S13: 0 | T13: 0 | U13: 0 | V13: 0 | W13: 5 | X13: 0 | Y13: 0 | Z13: 0 | AA13: 0 | AB13: 0 | AC13: 0 | AD13: 0 | AE13: 0 | AF13: 0 | AG13: 958.15 | AH13: 958.15 | AI13: 23
... A1305: 1304 | B1305: 2069 | C1305: 博东分店（69店） | D1305: 46227 | E1305: 0 | F1305: 0 | G1305: 0 | H1305: 0 | I1305: 0 | J1305: 0 | K1305: 0 | L1305: 0 | M1305: 0 | N1305: 0 | O1305: 0 | P1305: 0 | Q1305: 0 | R1305: 0 | S1305: 0 | T1305: 0 | U1305: 0 | V1305: 0 | W1305: 0 | X1305: 0 | Y1305: 0 | Z1305: 0 | AA1305: 0 | AB1305: 0 | AC1305: 0 | AD1305: 0 | AE1305: 0 | AF1305: 0 | AG1305: 0 | AH1305: 0 | AI1305: 3

Sheet 输入聚合
A1: 门店编码 | B1: 门店名称 | C1: 交易金额 | D1: 服务费 | F1: 聚合支付平台导出的门店汇总：交易金额＝含手续费的总额，服务费＝手续费。
A2: 2001 | B2: 柏人商城分店（1店） | C2: 22768.52 | D2: 61.48
A3: 2002 | B3: 新隆分店（2分店） | C3: 103203.75 | D3: 278.65
A4: 2003 | B4: 康庄东路分店（3店） | C4: 9808.79 | D4: 26.48
A5: 2004 | B5: 东关分店（4分店） | C5: 5004.6 | D5: 13.51
A6: 2005 | B6: 象城街分店（5店） | C6: 18036.9 | D6: 48.7
A7: 2006 | B7: 博荣分店（6分店） | C7: 33428.3 | D7: 90.26
A8: 2007 | B8: 华鑫分店（7店） | C8: 33811.43 | D8: 91.29
A9: 2008 | B9: 博昭分店（8分店） | C9: 53118.64 | D9: 143.42
A10: 2009 | B10: 大霍分店（9分店） | C10: 22410.18 | D10: 60.51
A11: 2010 | B11: 莲子镇分店(10分店) | C11: 67547.35 | D11: 182.38
A12: 2011 | B12: 毛尔寨分店(11分店) | C12: 14193.02 | D12: 38.32
A13: 2012 | B13: 泽畔分店（12分店） | C13: 20343.83 | D13: 54.93
... A42: 2068 | B42: 博山分店（68分店） | C42: 39370.79 | D42: 106.3

Sheet 输入平台
A1: 门店编码 | B1: 渠道 | C1: 平台金额 | D1: 海典金额(自动) | E1: 差额 平台−海典(自动) | F1: 校验 | H1: 【平台金额填这里】
D2: =IF(OR($A2="",$B2=""),"",ROUND(IFERROR(INDEX(海典汇总!$C$3:$AE$67,MATCH($A2,海典汇总!$A$3:$A$67,0),MATCH(INDEX(科目对照收入!$F$2:$F$23,MATCH($B2,科目对照收入!$B$2:$B$23,0)),海典汇总!$C$1:$AE$1,0)),0)+IFERROR(INDEX(海典汇总!$C$3:$AE$67,MATCH($A2,海典汇总!$A$3:$A$67,0),MATCH(INDEX(科目对照收入!$G$2:$G$23,MATCH($B2,科目对照收入!$B$2:$B$23,0)),海典汇总!$C$1:$AE$1,0)),0)+IFERROR(INDEX(海典汇总!$C$3:$AE$67,MATCH($A2,海典汇总!$A$3:$A$67,0),MATCH(INDEX(科目对照收入!$H$2:$H$23,MATCH($B2,科目对照收入!$B$2:$B$23,0)),海典汇总!$C$1:$AE$1,0)),0),2)) | E2: =IF($D2="","",ROUND($C2-$D2,2)) | F2: =IF($A2&$B2="","",IF(COUNTIF(门店对照!$A$2:$A$66,$A2)=0,"× 门店编码不对",IF(COUNTIF(科目对照收入!$B$2:$B$23,$B2)=0,"× 渠道名不对",IF(INDEX(科目对照收入!$E$2:$E$23,MATCH($B2,科目对照收入!$B$2:$B$23,0))<>"平台优先","× 该项目不按平台金额",IF(COUNTIFS($A$2:$A$601,$A2,$B$2:$B$601,$B2)>1,"× 同店同渠道重复","√"))))) | H2: 一行一个“门店＋渠道”。渠道点单元格有下拉框，只有走平台金额的那几个渠道能选。
D3: =IF(OR($A3="",$B3=""),"",ROUND(IFERROR(INDEX(海典汇总!$C$3:$AE$67,MATCH($A3,海典汇总!$A$3:$A$67,0),MATCH(INDEX(科目对照收入!$F$2:$F$23,MATCH($B3,科目对照收入!$B$2:$B$23,0)),海典汇总!$C$1:$AE$1,0)),0)+IFERROR(INDEX(海典汇总!$C$3:$AE$67,MATCH($A3,海典汇总!$A$3:$A$67,0),MATCH(INDEX(科目对照收入!$G$2:$G$23,MATCH($B3,科目对照收入!$B$2:$B$23,0)),海典汇总!$C$1:$AE$1,0)),0)+IFERROR(INDEX(海典汇总!$C$3:$AE$67,MATCH($A3,海典汇总!$A$3:$A$67,0),MATCH(INDEX(科目对照收入!$H$2:$H$23,MATCH($B3,科目对照收入!$B$2:$B$23,0)),海典汇总!$C$1:$AE$1,0)),0),2)) | E3: =IF($D3="","",ROUND($C3-$D3,2)) | F3: =IF($A3&$B3="","",IF(COUNTIF(门店对照!$A$2:$A$66,$A3)=0,"× 门店编码不对",IF(COUNTIF(科目对照收入!$B$2:$B$23,$B3)=0,"× 渠道名不对",IF(INDEX(科目对照收入!$E$2:$E$23,MATCH($B3,科目对照收入!$B$2:$B$23,0))<>"平台优先","× 该项目不按平台金额",IF(COUNTIFS($A$2:$A$601,$A3,$B$2:$B$601,$B3)>1,"× 同店同渠道重复","√"))))) | H3: 平台金额填“不扣手续费的总额”（美团填商品总价、饿了么填商品金额），手续费在回款时再冲。
D4: =IF(OR($A4="",$B4=""),"",ROUND(IFERROR(INDEX(海典汇总!$C$3:$AE$67,MATCH($A4,海典汇总!$A$3:$A$67,0),MATCH(INDEX(科目对照收入!$F$2:$F$23,MATCH($B4,科目对照收入!$B$2:$B$23,0)),海典汇总!$C$1:$AE$1,0)),0)+IFERROR(INDEX(海典汇总!$C$3:$AE$67,MATCH($A4,海典汇总!$A$3:$A$67,0),MATCH(INDEX(科目对照收入!$G$2:$G$23,MATCH($B4,科目对照收入!$B$2:$B$23,0)),海典汇总!$C$1:$AE$1,0)),0)+IFERROR(INDEX(海典汇总!$C$3:$AE$67,MATCH($A4,海典汇总!$A$3:$A$67,0),MATCH(INDEX(科目对照收入!$H$2:$H$23,MATCH($B4,科目对照收入!$B$2:$B$23,0)),海典汇总!$C$1:$AE$1,0)),0),2)) | E4: =IF($D4="","",ROUND($C4-$D4,2)) | F4: =IF($A4&$B4="","",IF(COUNTIF(门店对照!$A$2:$A$66,$A4)=0,"× 门店编码不对",IF(COUNTIF(科目对照收入!$B$2:$B$23,$B4)=0,"× 渠道名不对",IF(INDEX(科目对照收入!$E$2:$E$23,MATCH($B4,科目对照收入!$B$2:$B$23,0))<>"平台优先","× 该项目不按平台金额",IF(COUNTIFS($A$2:$A$601,$A4,$B$2:$B$601,$B4)>1,"× 同店同渠道重复","√"))))) | H4: 某个店某个渠道这里没填 → 凭证自动用海典金额，不会漏账。
D5: =IF(OR($A5="",$B5=""),"",ROUND(IFERROR(INDEX(海典汇总!$C$3:$AE$67,MATCH($A5,海典汇总!$A$3:$A$67,0),MATCH(INDEX(科目对照收入!$F$2:$F$23,MATCH($B5,科目对照收入!$B$2:$B$23,0)),海典汇总!$C$1:$AE$1,0)),0)+IFERROR(INDEX(海典汇总!$C$3:$AE$67,MATCH($A5,海典汇总!$A$3:$A$67,0),MATCH(INDEX(科目对照收入!$G$2:$G$23,MATCH($B5,科目对照收入!$B$2:$B$23,0)),海典汇总!$C$1:$AE$1,0)),0)+IFERROR(INDEX(海典汇总!$C$3:$AE$67,MATCH($A5,海典汇总!$A$3:$A$67,0),MATCH(INDEX(科目对照收入!$H$2:$H$23,MATCH($B5,科目对照收入!$B$2:$B$23,0)),海典汇总!$C$1:$AE$1,0)),0),2)) | E5: =IF($D5="","",ROUND($C5-$D5,2)) | F5: =IF($A5&$B5="","",IF(COUNTIF(门店对照!$A$2:$A$66,$A5)=0,"× 门店编码不对",IF(COUNTIF(科目对照收入!$B$2:$B$23,$B5)=0,"× 渠道名不对",IF(INDEX(科目对照收入!$E$2:$E$23,MATCH($B5,科目对照收入!$B$2:$B$23,0))<>"平台优先","× 该项目不按平台金额",IF(COUNTIFS($A$2:$A$601,$A5,$B$2:$B$601,$B5)>1,"× 同店同渠道重复","√"))))) | H5: 填 0 和不填不一样：填了 0 就按 0 入账（相当于本月这个渠道平台确认为 0）。
D6: =IF(OR($A6="",$B6=""),"",ROUND(IFERROR(INDEX(海典汇总!$C$3:$AE$67,MATCH($A6,海典汇总!$A$3:$A$67,0),MATCH(INDEX(科目对照收入!$F$2:$F$23,MATCH($B6,科目对照收入!$B$2:$B$23,0)),海典汇总!$C$1:$AE$1,0)),0)+IFERROR(INDEX(海典汇总!$C$3:$AE$67,MATCH($A6,海典汇总!$A$3:$A$67,0),MATCH(INDEX(科目对照收入!$G$2:$G$23,MATCH($B6,科目对照收入!$B$2:$B$23,0)),海典汇总!$C$1:$AE$1,0)),0)+IFERROR(INDEX(海典汇总!$C$3:$AE$67,MATCH($A6,海典汇总!$A$3:$A$67,0),MATCH(INDEX(科目对照收入!$H$2:$H$23,MATCH($B6,科目对照收入!$B$2:$B$23,0)),海典汇总!$C$1:$AE$1,0)),0),2)) | E6: =IF($D6="","",ROUND($C6-$D6,2)) | F6: =IF($A6&$B6="","",IF(COUNTIF(门店对照!$A$2:$A$66,$A6)=0,"× 门店编码不对",IF(COUNTIF(科目对照收入!$B$2:$B$23,$B6)=0,"× 渠道名不对",IF(INDEX(科目对照收入!$E$2:$E$23,MATCH($B6,科目对照收入!$B$2:$B$23,0))<>"平台优先","× 该项目不按平台金额",IF(COUNTIFS($A$2:$A$601,$A6,$B$2:$B$601,$B6)>1,"× 同店同渠道重复","√"))))) | H6: 右边两列会自动带出海典金额和差额，方便你核对；差额最后会走“少钱补现金 / 多钱记营业外”。
D7: =IF(OR($A7="",$B7=""),"",ROUND(IFERROR(INDEX(海典汇总!$C$3:$AE$67,MATCH($A7,海典汇总!$A$3:$A$67,0),MATCH(INDEX(科目对照收入!$F$2:$F$23,MATCH($B7,科目对照收入!$B$2:$B$23,0)),海典汇总!$C$1:$AE$1,0)),0)+IFERROR(INDEX(海典汇总!$C$3:$AE$67,MATCH($A7,海典汇总!$A$3:$A$67,0),MATCH(INDEX(科目对照收入!$G$2:$G$23,MATCH($B7,科目对照收入!$B$2:$B$23,0)),海典汇总!$C$1:$AE$1,0)),0)+IFERROR(INDEX(海典汇总!$C$3:$AE$67,MATCH($A7,海典汇总!$A$3:$A$67,0),MATCH(INDEX(科目对照收入!$H$2:$H$23,MATCH($B7,科目对照收入!$B$2:$B$23,0)),海典汇总!$C$1:$AE$1,0)),0),2)) | E7: =IF($D7="","",ROUND($C7-$D7,2)) | F7: =IF($A7&$B7="","",IF(COUNTIF(门店对照!$A$2:$A$66,$A7)=0,"× 门店编码不对",IF(COUNTIF(科目对照收入!$B$2:$B$23,$B7)=0,"× 渠道名不对",IF(INDEX(科目对照收入!$E$2:$E$23,MATCH($B7,科目对照收入!$B$2:$B$23,0))<>"平台优先","× 该项目不按平台金额",IF(COUNTIFS($A$2:$A$601,$A7,$B$2:$B$601,$B7)>1,"× 同店同渠道重复","√")))))
D8: =IF(OR($A8="",$B8=""),"",ROUND(IFERROR(INDEX(海典汇总!$C$3:$AE$67,MATCH($A8,海典汇总!$A$3:$A$67,0),MATCH(INDEX(科目对照收入!$F$2:$F$23,MATCH($B8,科目对照收入!$B$2:$B$23,0)),海典汇总!$C$1:$AE$1,0)),0)+IFERROR(INDEX(海典汇总!$C$3:$AE$67,MATCH($A8,海典汇总!$A$3:$A$67,0),MATCH(INDEX(科目对照收入!$G$2:$G$23,MATCH($B8,科目对照收入!$B$2:$B$23,0)),海典汇总!$C$1:$AE$1,0)),0)+IFERROR(INDEX(海典汇总!$C$3:$AE$67,MATCH($A8,海典汇总!$A$3:$A$67,0),MATCH(INDEX(科目对照收入!$H$2:$H$23,MATCH($B8,科目对照收入!$B$2:$B$23,0)),海典汇总!$C$1:$AE$1,0)),0),2)) | E8: =IF($D8="","",ROUND($C8-$D8,2)) | F8: =IF($A8&$B8="","",IF(COUNTIF(门店对照!$A$2:$A$66,$A8)=0,"× 门店编码不对",IF(COUNTIF(科目对照收入!$B$2:$B$23,$B8)=0,"× 渠道名不对",IF(INDEX(科目对照收入!$E$2:$E$23,MATCH($B8,科目对照收入!$B$2:$B$23,0))<>"平台优先","× 该项目不按平台金额",IF(COUNTIFS($A$2:$A$601,$A8,$B$2:$B$601,$B8)>1,"× 同店同渠道重复","√")))))
D9: =IF(OR($A9="",$B9=""),"",ROUND(IFERROR(INDEX(海典汇总!$C$3:$AE$67,MATCH($A9,海典汇总!$A$3:$A$67,0),MATCH(INDEX(科目对照收入!$F$2:$F$23,MATCH($B9,科目对照收入!$B$2:$B$23,0)),海典汇总!$C$1:$AE$1,0)),0)+IFERROR(INDEX(海典汇总!$C$3:$AE$67,MATCH($A9,海典汇总!$A$3:$A$67,0),MATCH(INDEX(科目对照收入!$G$2:$G$23,MATCH($B9,科目对照收入!$B$2:$B$23,0)),海典汇总!$C$1:$AE$1,0)),0)+IFERROR(INDEX(海典汇总!$C$3:$AE$67,MATCH($A9,海典汇总!$A$3:$A$67,0),MATCH(INDEX(科目对照收入!$H$2:$H$23,MATCH($B9,科目对照收入!$B$2:$B$23,0)),海典汇总!$C$1:$AE$1,0)),0),2)) | E9: =IF($D9="","",ROUND($C9-$D9,2)) | F9: =IF($A9&$B9="","",IF(COUNTIF(门店对照!$A$2:$A$66,$A9)=0,"× 门店编码不对",IF(COUNTIF(科目对照收入!$B$2:$B$23,$B9)=0,"× 渠道名不对",IF(INDEX(科目对照收入!$E$2:$E$23,MATCH($B9,科目对照收入!$B$2:$B$23,0))<>"平台优先","× 该项目不按平台金额",IF(COUNTIFS($A$2:$A$601,$A9,$B$2:$B$601,$B9)>1,"× 同店同渠道重复","√")))))
D10: =IF(OR($A10="",$B10=""),"",ROUND(IFERROR(INDEX(海典汇总!$C$3:$AE$67,MATCH($A10,海典汇总!$A$3:$A$67,0),MATCH(INDEX(科目对照收入!$F$2:$F$23,MATCH($B10,科目对照收入!$B$2:$B$23,0)),海典汇总!$C$1:$AE$1,0)),0)+IFERROR(INDEX(海典汇总!$C$3:$AE$67,MATCH($A10,海典汇总!$A$3:$A$67,0),MATCH(INDEX(科目对照收入!$G$2:$G$23,MATCH($B10,科目对照收入!$B$2:$B$23,0)),海典汇总!$C$1:$AE$1,0)),0)+IFERROR(INDEX(海典汇总!$C$3:$AE$67,MATCH($A10,海典汇总!$A$3:$A$67,0),MATCH(INDEX(科目对照收入!$H$2:$H$23,MATCH($B10,科目对照收入!$B$2:$B$23,0)),海典汇总!$C$1:$AE$1,0)),0),2)) | E10: =IF($D10="","",ROUND($C10-$D10,2)) | F10: =IF($A10&$B10="","",IF(COUNTIF(门店对照!$A$2:$A$66,$A10)=0,"× 门店编码不对",IF(COUNTIF(科目对照收入!$B$2:$B$23,$B10)=0,"× 渠道名不对",IF(INDEX(科目对照收入!$E$2:$E$23,MATCH($B10,科目对照收入!$B$2:$B$23,0))<>"平台优先","× 该项目不按平台金额",IF(COUNTIFS($A$2:$A$601,$A10,$B$2:$B$601,$B10)>1,"× 同店同渠道重复","√")))))
D11: =IF(OR($A11="",$B11=""),"",ROUND(IFERROR(INDEX(海典汇总!$C$3:$AE$67,MATCH($A11,海典汇总!$A$3:$A$67,0),MATCH(INDEX(科目对照收入!$F$2:$F$23,MATCH($B11,科目对照收入!$B$2:$B$23,0)),海典汇总!$C$1:$AE$1,0)),0)+IFERROR(INDEX(海典汇总!$C$3:$AE$67,MATCH($A11,海典汇总!$A$3:$A$67,0),MATCH(INDEX(科目对照收入!$G$2:$G$23,MATCH($B11,科目对照收入!$B$2:$B$23,0)),海典汇总!$C$1:$AE$1,0)),0)+IFERROR(INDEX(海典汇总!$C$3:$AE$67,MATCH($A11,海典汇总!$A$3:$A$67,0),MATCH(INDEX(科目对照收入!$H$2:$H$23,MATCH($B11,科目对照收入!$B$2:$B$23,0)),海典汇总!$C$1:$AE$1,0)),0),2)) | E11: =IF($D11="","",ROUND($C11-$D11,2)) | F11: =IF($A11&$B11="","",IF(COUNTIF(门店对照!$A$2:$A$66,$A11)=0,"× 门店编码不对",IF(COUNTIF(科目对照收入!$B$2:$B$23,$B11)=0,"× 渠道名不对",IF(INDEX(科目对照收入!$E$2:$E$23,MATCH($B11,科目对照收入!$B$2:$B$23,0))<>"平台优先","× 该项目不按平台金额",IF(COUNTIFS($A$2:$A$601,$A11,$B$2:$B$601,$B11)>1,"× 同店同渠道重复","√")))))
D12: =IF(OR($A12="",$B12=""),"",ROUND(IFERROR(INDEX(海典汇总!$C$3:$AE$67,MATCH($A12,海典汇总!$A$3:$A$67,0),MATCH(INDEX(科目对照收入!$F$2:$F$23,MATCH($B12,科目对照收入!$B$2:$B$23,0)),海典汇总!$C$1:$AE$1,0)),0)+IFERROR(INDEX(海典汇总!$C$3:$AE$67,MATCH($A12,海典汇总!$A$3:$A$67,0),MATCH(INDEX(科目对照收入!$G$2:$G$23,MATCH($B12,科目对照收入!$B$2:$B$23,0)),海典汇总!$C$1:$AE$1,0)),0)+IFERROR(INDEX(海典汇总!$C$3:$AE$67,MATCH($A12,海典汇总!$A$3:$A$67,0),MATCH(INDEX(科目对照收入!$H$2:$H$23,MATCH($B12,科目对照收入!$B$2:$B$23,0)),海典汇总!$C$1:$AE$1,0)),0),2)) | E12: =IF($D12="","",ROUND($C12-$D12,2)) | F12: =IF($A12&$B12="","",IF(COUNTIF(门店对照!$A$2:$A$66,$A12)=0,"× 门店编码不对",IF(COUNTIF(科目对照收入!$B$2:$B$23,$B12)=0,"× 渠道名不对",IF(INDEX(科目对照收入!$E$2:$E$23,MATCH($B12,科目对照收入!$B$2:$B$23,0))<>"平台优先","× 该项目不按平台金额",IF(COUNTIFS($A$2:$A$601,$A12,$B$2:$B$601,$B12)>1,"× 同店同渠道重复","√")))))
D13: =IF(OR($A13="",$B13=""),"",ROUND(IFERROR(INDEX(海典汇总!$C$3:$AE$67,MATCH($A13,海典汇总!$A$3:$A$67,0),MATCH(INDEX(科目对照收入!$F$2:$F$23,MATCH($B13,科目对照收入!$B$2:$B$23,0)),海典汇总!$C$1:$AE$1,0)),0)+IFERROR(INDEX(海典汇总!$C$3:$AE$67,MATCH($A13,海典汇总!$A$3:$A$67,0),MATCH(INDEX(科目对照收入!$G$2:$G$23,MATCH($B13,科目对照收入!$B$2:$B$23,0)),海典汇总!$C$1:$AE$1,0)),0)+IFERROR(INDEX(海典汇总!$C$3:$AE$67,MATCH($A13,海典汇总!$A$3:$A$67,0),MATCH(INDEX(科目对照收入!$H$2:$H$23,MATCH($B13,科目对照收入!$B$2:$B$23,0)),海典汇总!$C$1:$AE$1,0)),0),2)) | E13: =IF($D13="","",ROUND($C13-$D13,2)) | F13: =IF($A13&$B13="","",IF(COUNTIF(门店对照!$A$2:$A$66,$A13)=0,"× 门店编码不对",IF(COUNTIF(科目对照收入!$B$2:$B$23,$B13)=0,"× 渠道名不对",IF(INDEX(科目对照收入!$E$2:$E$23,MATCH($B13,科目对照收入!$B$2:$B$23,0))<>"平台优先","× 该项目不按平台金额",IF(COUNTIFS($A$2:$A$601,$A13,$B$2:$B$601,$B13)>1,"× 同店同渠道重复","√")))))
D14: =IF(OR($A14="",$B14=""),"",ROUND(IFERROR(INDEX(海典汇总!$C$3:$AE$67,MATCH($A14,海典汇总!$A$3:$A$67,0),MATCH(INDEX(科目对照收入!$F$2:$F$23,MATCH($B14,科目对照收入!$B$2:$B$23,0)),海典汇总!$C$1:$AE$1,0)),0)+IFERROR(INDEX(海典汇总!$C$3:$AE$67,MATCH($A14,海典汇总!$A$3:$A$67,0),MATCH(INDEX(科目对照收入!$G$2:$G$23,MATCH($B14,科目对照收入!$B$2:$B$23,0)),海典汇总!$C$1:$AE$1,0)),0)+IFERROR(INDEX(海典汇总!$C$3:$AE$67,MATCH($A14,海典汇总!$A$3:$A$67,0),MATCH(INDEX(科目对照收入!$H$2:$H$23,MATCH($B14,科目对照收入!$B$2:$B$23,0)),海典汇总!$C$1:$AE$1,0)),0),2)) | E14: =IF($D14="","",ROUND($C14-$D14,2)) | F14: =IF($A14&$B14="","",IF(COUNTIF(门店对照!$A$2:$A$66,$A14)=0,"× 门店编码不对",IF(COUNTIF(科目对照收入!$B$2:$B$23,$B14)=0,"× 渠道名不对",IF(INDEX(科目对照收入!$E$2:$E$23,MATCH($B14,科目对照收入!$B$2:$B$23,0))<>"平台优先","× 该项目不按平台金额",IF(COUNTIFS($A$2:$A$601,$A14,$B$2:$B$601,$B14)>1,"× 同店同渠道重复","√")))))
D15: =IF(OR($A15="",$B15=""),"",ROUND(IFERROR(INDEX(海典汇总!$C$3:$AE$67,MATCH($A15,海典汇总!$A$3:$A$67,0),MATCH(INDEX(科目对照收入!$F$2:$F$23,MATCH($B15,科目对照收入!$B$2:$B$23,0)),海典汇总!$C$1:$AE$1,0)),0)+IFERROR(INDEX(海典汇总!$C$3:$AE$67,MATCH($A15,海典汇总!$A$3:$A$67,0),MATCH(INDEX(科目对照收入!$G$2:$G$23,MATCH($B15,科目对照收入!$B$2:$B$23,0)),海典汇总!$C$1:$AE$1,0)),0)+IFERROR(INDEX(海典汇总!$C$3:$AE$67,MATCH($A15,海典汇总!$A$3:$A$67,0),MATCH(INDEX(科目对照收入!$H$2:$H$23,MATCH($B15,科目对照收入!$B$2:$B$23,0)),海典汇总!$C$1:$AE$1,0)),0),2)) | E15: =IF($D15="","",ROUND($C15-$D15,2)) | F15: =IF($A15&$B15="","",IF(COUNTIF(门店对照!$A$2:$A$66,$A15)=0,"× 门店编码不对",IF(COUNTIF(科目对照收入!$B$2:$B$23,$B15)=0,"× 渠道名不对",IF(INDEX(科目对照收入!$E$2:$E$23,MATCH($B15,科目对照收入!$B$2:$B$23,0))<>"平台优先","× 该项目不按平台金额",IF(COUNTIFS($A$2:$A$601,$A15,$B$2:$B$601,$B15)>1,"× 同店同渠道重复","√")))))
D16: =IF(OR($A16="",$B16=""),"",ROUND(IFERROR(INDEX(海典汇总!$C$3:$AE$67,MATCH($A16,海典汇总!$A$3:$A$67,0),MATCH(INDEX(科目对照收入!$F$2:$F$23,MATCH($B16,科目对照收入!$B$2:$B$23,0)),海典汇总!$C$1:$AE$1,0)),0)+IFERROR(INDEX(海典汇总!$C$3:$AE$67,MATCH($A16,海典汇总!$A$3:$A$67,0),MATCH(INDEX(科目对照收入!$G$2:$G$23,MATCH($B16,科目对照收入!$B$2:$B$23,0)),海典汇总!$C$1:$AE$1,0)),0)+IFERROR(INDEX(海典汇总!$C$3:$AE$67,MATCH($A16,海典汇总!$A$3:$A$67,0),MATCH(INDEX(科目对照收入!$H$2:$H$23,MATCH($B16,科目对照收入!$B$2:$B$23,0)),海典汇总!$C$1:$AE$1,0)),0),2)) | E16: =IF($D16="","",ROUND($C16-$D16,2)) | F16: =IF($A16&$B16="","",IF(COUNTIF(门店对照!$A$2:$A$66,$A16)=0,"× 门店编码不对",IF(COUNTIF(科目对照收入!$B$2:$B$23,$B16)=0,"× 渠道名不对",IF(INDEX(科目对照收入!$E$2:$E$23,MATCH($B16,科目对照收入!$B$2:$B$23,0))<>"平台优先","× 该项目不按平台金额",IF(COUNTIFS($A$2:$A$601,$A16,$B$2:$B$601,$B16)>1,"× 同店同渠道重复","√")))))
D17: =IF(OR($A17="",$B17=""),"",ROUND(IFERROR(INDEX(海典汇总!$C$3:$AE$67,MATCH($A17,海典汇总!$A$3:$A$67,0),MATCH(INDEX(科目对照收入!$F$2:$F$23,MATCH($B17,科目对照收入!$B$2:$B$23,0)),海典汇总!$C$1:$AE$1,0)),0)+IFERROR(INDEX(海典汇总!$C$3:$AE$67,MATCH($A17,海典汇总!$A$3:$A$67,0),MATCH(INDEX(科目对照收入!$G$2:$G$23,MATCH($B17,科目对照收入!$B$2:$B$23,0)),海典汇总!$C$1:$AE$1,0)),0)+IFERROR(INDEX(海典汇总!$C$3:$AE$67,MATCH($A17,海典汇总!$A$3:$A$67,0),MATCH(INDEX(科目对照收入!$H$2:$H$23,MATCH($B17,科目对照收入!$B$2:$B$23,0)),海典汇总!$C$1:$AE$1,0)),0),2)) | E17: =IF($D17="","",ROUND($C17-$D17,2)) | F17: =IF($A17&$B17="","",IF(COUNTIF(门店对照!$A$2:$A$66,$A17)=0,"× 门店编码不对",IF(COUNTIF(科目对照收入!$B$2:$B$23,$B17)=0,"× 渠道名不对",IF(INDEX(科目对照收入!$E$2:$E$23,MATCH($B17,科目对照收入!$B$2:$B$23,0))<>"平台优先","× 该项目不按平台金额",IF(COUNTIFS($A$2:$A$601,$A17,$B$2:$B$601,$B17)>1,"× 同店同渠道重复","√")))))
D18: =IF(OR($A18="",$B18=""),"",ROUND(IFERROR(INDEX(海典汇总!$C$3:$AE$67,MATCH($A18,海典汇总!$A$3:$A$67,0),MATCH(INDEX(科目对照收入!$F$2:$F$23,MATCH($B18,科目对照收入!$B$2:$B$23,0)),海典汇总!$C$1:$AE$1,0)),0)+IFERROR(INDEX(海典汇总!$C$3:$AE$67,MATCH($A18,海典汇总!$A$3:$A$67,0),MATCH(INDEX(科目对照收入!$G$2:$G$23,MATCH($B18,科目对照收入!$B$2:$B$23,0)),海典汇总!$C$1:$AE$1,0)),0)+IFERROR(INDEX(海典汇总!$C$3:$AE$67,MATCH($A18,海典汇总!$A$3:$A$67,0),MATCH(INDEX(科目对照收入!$H$2:$H$23,MATCH($B18,科目对照收入!$B$2:$B$23,0)),海典汇总!$C$1:$AE$1,0)),0),2)) | E18: =IF($D18="","",ROUND($C18-$D18,2)) | F18: =IF($A18&$B18="","",IF(COUNTIF(门店对照!$A$2:$A$66,$A18)=0,"× 门店编码不对",IF(COUNTIF(科目对照收入!$B$2:$B$23,$B18)=0,"× 渠道名不对",IF(INDEX(科目对照收入!$E$2:$E$23,MATCH($B18,科目对照收入!$B$2:$B$23,0))<>"平台优先","× 该项目不按平台金额",IF(COUNTIFS($A$2:$A$601,$A18,$B$2:$B$601,$B18)>1,"× 同店同渠道重复","√")))))
... D601: =IF(OR($A601="",$B601=""),"",ROUND(IFERROR(INDEX(海典汇总!$C$3:$AE$67,MATCH($A601,海典汇总!$A$3:$A$67,0),MATCH(INDEX(科目对照收入!$F$2:$F$23,MATCH($B601,科目对照收入!$B$2:$B$23,0)),海典汇总!$C$1:$AE$1,0)),0)+IFERROR(INDEX(海典汇总!$C$3:$AE$67,MATCH($A601,海典汇总!$A$3:$A$67,0),MATCH(INDEX(科目对照收入!$G$2:$G$23,MATCH($B601,科目对照收入!$B$2:$B$23,0)),海典汇总!$C$1:$AE$1,0)),0)+IFERROR(INDEX(海典汇总!$C$3:$AE$67,MATCH($A601,海典汇总!$A$3:$A$67,0),MATCH(INDEX(科目对照收入!$H$2:$H$23,MATCH($B601,科目对照收入!$B$2:$B$23,0)),海典汇总!$C$1:$AE$1,0)),0),2)) | E601: =IF($D601="","",ROUND($C601-$D601,2)) | F601: =IF($A601&$B601="","",IF(COUNTIF(门店对照!$A$2:$A$66,$A601)=0,"× 门店编码不对",IF(COUNTIF(科目对照收入!$B$2:$B$23,$B601)=0,"× 渠道名不对",IF(INDEX(科目对照收入!$E$2:$E$23,MATCH($B601,科目对照收入!$B$2:$B$23,0))<>"平台优先","× 该项目不按平台金额",IF(COUNTIFS($A$2:$A$601,$A601,$B$2:$B$601,$B601)>1,"× 同店同渠道重复","√")))))

Sheet 输入现金
A1: 门店编码 | B1: 网银现金合计 | C1: 备注 | E1: 各店本月网银（存款）合计。库存现金按这个数入账，差多少自动补现金。
A2: 2001 | B2: 6428.43 | C2: 示例数字，请换成本店网银合计
A3: 2002 | B3: 290970.85 | C3: 示例数字，请换成本店网银合计
A4: 2003 | B4: 50121.42 | C4: 示例数字，请换成本店网银合计
A5: 2004 | B5: 67171.51 | C5: 示例数字，请换成本店网银合计
A6: 2005 | B6: 63058.21 | C6: 示例数字，请换成本店网银合计
A7: 2006 | B7: 4575.05 | C7: 示例数字，请换成本店网银合计
A8: 2007 | B8: 12722.01 | C8: 示例数字，请换成本店网银合计
A9: 2008 | B9: 8028.82 | C9: 示例数字，请换成本店网银合计
A10: 2009 | B10: 9880.5 | C10: 示例数字，请换成本店网银合计
A11: 2010 | B11: 23656.79 | C11: 示例数字，请换成本店网银合计
A12: 2011 | B12: 24370.58 | C12: 示例数字，请换成本店网银合计
A13: 2012 | B13: 25649.6 | C13: 示例数字，请换成本店网银合计
... A56: 9010 | B56: 0 | C56: 示例数字，请换成本店网银合计

Sheet 输入回款
A1: 门店编码 | B1: 收款方式 | C1: 回款金额 | D1: 手续费 | E1: 备注 | F1: 识别 | G1: 一行一笔：哪个店、什么方式、收到多少（不含手续费的净额）、手续费多少。
A2: 2001 | B2: 聚合支付 | C2: 24279.15 | D2: 0 | F2: =IF($B2="","",IF(COUNTIF(科目对照回款!$F$2:$H$16,$B2)>0,"√","× 未识别")) -> √ | G2: 收款方式请写成 科目对照回款 里的别名，例如 聚合支付 / 医保 / 医保即时拨付 / 美团 / 健E卡 …
A3: 2001 | B3: 医保 | C3: 3786.22 | D3: 0 | F3: =IF($B3="","",IF(COUNTIF(科目对照回款!$F$2:$H$16,$B3)>0,"√","× 未识别")) -> √
A4: 2001 | B4: 医保即时拨付 | C4: 3757.87 | D4: 0 | F4: =IF($B4="","",IF(COUNTIF(科目对照回款!$F$2:$H$16,$B4)>0,"√","× 未识别")) -> √
A5: 2001 | B5: 美团 | C5: 227.07 | D5: 54.73 | F5: =IF($B5="","",IF(COUNTIF(科目对照回款!$F$2:$H$16,$B5)>0,"√","× 未识别")) -> √
A6: 2063 | B6: 聚合支付 | C6: 12424.88 | D6: 0 | F6: =IF($B6="","",IF(COUNTIF(科目对照回款!$F$2:$H$16,$B6)>0,"√","× 未识别")) -> √
A7: 2063 | B7: 医保 | C7: 14089.95 | D7: 0 | F7: =IF($B7="","",IF(COUNTIF(科目对照回款!$F$2:$H$16,$B7)>0,"√","× 未识别")) -> √
A8: 2063 | B8: 医保即时拨付 | C8: 16273.82 | D8: 0 | F8: =IF($B8="","",IF(COUNTIF(科目对照回款!$F$2:$H$16,$B8)>0,"√","× 未识别")) -> √
A9: 2063 | B9: 24小时 | C9: 2678.9 | D9: 244.7 | F9: =IF($B9="","",IF(COUNTIF(科目对照回款!$F$2:$H$16,$B9)>0,"√","× 未识别")) -> √
A10: 2063 | B10: 健E卡 | C10: 111102.61 | D10: 0 | F10: =IF($B10="","",IF(COUNTIF(科目对照回款!$F$2:$H$16,$B10)>0,"√","× 未识别")) -> √
A11: 2003 | B11: 聚合支付 | C11: 7997.23 | D11: 0 | F11: =IF($B11="","",IF(COUNTIF(科目对照回款!$F$2:$H$16,$B11)>0,"√","× 未识别")) -> √
A12: 2003 | B12: 医保 | C12: 15114.33 | D12: 0 | F12: =IF($B12="","",IF(COUNTIF(科目对照回款!$F$2:$H$16,$B12)>0,"√","× 未识别")) -> √
A13: 2003 | B13: 医保即时拨付 | C13: 14098.73 | D13: 0 | F13: =IF($B13="","",IF(COUNTIF(科目对照回款!$F$2:$H$16,$B13)>0,"√","× 未识别")) -> √
A14: 2003 | B14: 美团 | C14: 186.49 | D14: 51.51 | F14: =IF($B14="","",IF(COUNTIF(科目对照回款!$F$2:$H$16,$B14)>0,"√","× 未识别")) -> √
... A149: 2069 | B149: 聚合支付 | C149: 14270.85 | D149: 0 | F149: =IF($B149="","",IF(COUNTIF(科目对照回款!$F$2:$H$16,$B149)>0,"√","× 未识别")) -> √
F150: =IF($B150="","",IF(COUNTIF(科目对照回款!$F$2:$H$16,$B150)>0,"√","× 未识别"))
F151: =IF($B151="","",IF(COUNTIF(科目对照回款!$F$2:$H$16,$B151)>0,"√","× 未识别"))
F152: =IF($B152="","",IF(COUNTIF(科目对照回款!$F$2:$H$16,$B152)>0,"√","× 未识别"))
F153: =IF($B153="","",IF(COUNTIF(科目对照回款!$F$2:$H$16,$B153)>0,"√","× 未识别"))
F154: =IF($B154="","",IF(COUNTIF(科目对照回款!$F$2:$H$16,$B154)>0,"√","× 未识别"))
F155: =IF($B155="","",IF(COUNTIF(科目对照回款!$F$2:$H$16,$B155)>0,"√","× 未识别"))
F156: =IF($B156="","",IF(COUNTIF(科目对照回款!$F$2:$H$16,$B156)>0,"√","× 未识别"))
F157: =IF($B157="","",IF(COUNTIF(科目对照回款!$F$2:$H$16,$B157)>0,"√","× 未识别"))
F158: =IF($B158="","",IF(COUNTIF(科目对照回款!$F$2:$H$16,$B158)>0,"√","× 未识别"))
F159: =IF($B159="","",IF(COUNTIF(科目对照回款!$F$2:$H$16,$B159)>0,"√","× 未识别"))
F160: =IF($B160="","",IF(COUNTIF(科目对照回款!$F$2:$H$16,$B160)>0,"√","× 未识别"))
F161: =IF($B161="","",IF(COUNTIF(科目对照回款!$F$2:$H$16,$B161)>0,"√","× 未识别"))
... F619: =IF($B619="","",IF(COUNTIF(科目对照回款!$F$2:$H$16,$B619)>0,"√","× 未识别"))

Sheet 输入报销
A1: 单号 | B1: 日期 | C1: 门店简称 | D1: 摘要 | E1: 借方总账科目 | F1: 借方明细科目 | G1: 金额 | H1: 付款方式(贷方科目) | I1: 行序(自动) | J1: 键(自动) | K1: 校验 | L1: 同一张报销单用同一个单号；单号请从 1 开始连续编号。
A2: 1 | B2: 46265 | C2: 柏人商城店 | D2: 电费 | E2: 销售费用 | F2: 电费 | G2: 300 | H2: 库存现金 | I2: =IF($A2="","",COUNTIFS($A$2:$A2,$A2)) -> 1 | J2: =IF($A2="","",$A2&"-"&$I2) -> 1-1 | K2: =IF($A2="","",IF(COUNTIF(参数!$B$6:$B$8,$H2)=0,"× 付款方式","√")) -> √ | L2: 一行一个费用科目，金额填正数。付款方式填 库存现金 / 银行存款 / 其他应付款（见 参数 页签）。
A3: 1 | B3: 46265 | C3: 柏人商城店 | D3: 慢病用品 | E3: 销售费用 | F3: 办公费 | G3: 31.7 | H3: 库存现金 | I3: =IF($A3="","",COUNTIFS($A$2:$A3,$A3)) -> 2 | J3: =IF($A3="","",$A3&"-"&$I3) -> 1-2 | K3: =IF($A3="","",IF(COUNTIF(参数!$B$6:$B$8,$H3)=0,"× 付款方式","√")) -> √
A4: 1 | B4: 46265 | C4: 柏人商城店 | D4: 水费 | E4: 销售费用 | F4: 水费 | G4: 5 | H4: 库存现金 | I4: =IF($A4="","",COUNTIFS($A$2:$A4,$A4)) -> 3 | J4: =IF($A4="","",$A4&"-"&$I4) -> 1-3 | K4: =IF($A4="","",IF(COUNTIF(参数!$B$6:$B$8,$H4)=0,"× 付款方式","√")) -> √ | N4: 销售费用 | P4: 电费
A5: 2 | B5: 46265 | C5: 新隆店 | D5: 电费 | E5: 销售费用 | F5: 电费 | G5: 1000 | H5: 库存现金 | I5: =IF($A5="","",COUNTIFS($A$2:$A5,$A5)) -> 1 | J5: =IF($A5="","",$A5&"-"&$I5) -> 2-1 | K5: =IF($A5="","",IF(COUNTIF(参数!$B$6:$B$8,$H5)=0,"× 付款方式","√")) -> √ | N5: 财务费用 | P5: 办公费
A6: 2 | B6: 46265 | C6: 新隆店 | D6: 微信提现费 | E6: 财务费用 | F6: 手续费 | G6: 65 | H6: 库存现金 | I6: =IF($A6="","",COUNTIFS($A$2:$A6,$A6)) -> 2 | J6: =IF($A6="","",$A6&"-"&$I6) -> 2-2 | K6: =IF($A6="","",IF(COUNTIF(参数!$B$6:$B$8,$H6)=0,"× 付款方式","√")) -> √ | N6: 待摊费用 | P6: 水费
A7: 3 | B7: 46265 | C7: 康庄路店 | D7: 电费 | E7: 销售费用 | F7: 电费 | G7: 1000 | H7: 库存现金 | I7: =IF($A7="","",COUNTIFS($A$2:$A7,$A7)) -> 1 | J7: =IF($A7="","",$A7&"-"&$I7) -> 3-1 | K7: =IF($A7="","",IF(COUNTIF(参数!$B$6:$B$8,$H7)=0,"× 付款方式","√")) -> √ | P7: 手续费
A8: 3 | B8: 46265 | C8: 康庄路店 | D8: 灯锁胶布护套线 | E8: 销售费用 | F8: 办公费 | G8: =630+15+17 -> 662 | H8: 库存现金 | I8: =IF($A8="","",COUNTIFS($A$2:$A8,$A8)) -> 2 | J8: =IF($A8="","",$A8&"-"&$I8) -> 3-2 | K8: =IF($A8="","",IF(COUNTIF(参数!$B$6:$B$8,$H8)=0,"× 付款方式","√")) -> √ | P8: 物业费
A9: 3 | B9: 46265 | C9: 康庄路店 | D9: 微信提现费 | E9: 财务费用 | F9: 手续费 | G9: 43.38 | H9: 库存现金 | I9: =IF($A9="","",COUNTIFS($A$2:$A9,$A9)) -> 3 | J9: =IF($A9="","",$A9&"-"&$I9) -> 3-3 | K9: =IF($A9="","",IF(COUNTIF(参数!$B$6:$B$8,$H9)=0,"× 付款方式","√")) -> √ | P9: 电话费
A10: 4 | B10: 46265 | C10: 东关店 | D10: 色带慢病用品 | E10: 销售费用 | F10: 办公费 | G10: 99.7 | H10: 库存现金 | I10: =IF($A10="","",COUNTIFS($A$2:$A10,$A10)) -> 1 | J10: =IF($A10="","",$A10&"-"&$I10) -> 4-1 | K10: =IF($A10="","",IF(COUNTIF(参数!$B$6:$B$8,$H10)=0,"× 付款方式","√")) -> √ | P10: 促销费
A11: 4 | B11: 46265 | C11: 东关店 | D11: 微信提现费 | E11: 财务费用 | F11: 手续费 | G11: 48.05 | H11: 库存现金 | I11: =IF($A11="","",COUNTIFS($A$2:$A11,$A11)) -> 2 | J11: =IF($A11="","",$A11&"-"&$I11) -> 4-2 | K11: =IF($A11="","",IF(COUNTIF(参数!$B$6:$B$8,$H11)=0,"× 付款方式","√")) -> √ | P11: 福利费
A12: 5 | B12: 46265 | C12: 象城街店 | D12: 电费 | E12: 销售费用 | F12: 电费 | G12: 800 | H12: 库存现金 | I12: =IF($A12="","",COUNTIFS($A$2:$A12,$A12)) -> 1 | J12: =IF($A12="","",$A12&"-"&$I12) -> 5-1 | K12: =IF($A12="","",IF(COUNTIF(参数!$B$6:$B$8,$H12)=0,"× 付款方式","√")) -> √
A13: 5 | B13: 46265 | C13: 象城街店 | D13: 慢病用品 | E13: 销售费用 | F13: 办公费 | G13: 59.8 | H13: 库存现金 | I13: =IF($A13="","",COUNTIFS($A$2:$A13,$A13)) -> 2 | J13: =IF($A13="","",$A13&"-"&$I13) -> 5-2 | K13: =IF($A13="","",IF(COUNTIF(参数!$B$6:$B$8,$H13)=0,"× 付款方式","√")) -> √
A14: 5 | B14: 46265 | C14: 象城街店 | D14: 色带 | E14: 销售费用 | F14: 办公费 | G14: 10 | H14: 库存现金 | I14: =IF($A14="","",COUNTIFS($A$2:$A14,$A14)) -> 3 | J14: =IF($A14="","",$A14&"-"&$I14) -> 5-3 | K14: =IF($A14="","",IF(COUNTIF(参数!$B$6:$B$8,$H14)=0,"× 付款方式","√")) -> √
A15: 6 | B15: 46265 | C15: 博荣店 | D15: 电费 | E15: 销售费用 | F15: 电费 | G15: 500.48 | H15: 库存现金 | I15: =IF($A15="","",COUNTIFS($A$2:$A15,$A15)) -> 1 | J15: =IF($A15="","",$A15&"-"&$I15) -> 6-1 | K15: =IF($A15="","",IF(COUNTIF(参数!$B$6:$B$8,$H15)=0,"× 付款方式","√")) -> √
A16: 6 | B16: 46265 | C16: 博荣店 | D16: 物业费 | E16: 待摊费用 | F16: 物业费 | G16: 1314.7 | H16: 库存现金 | I16: =IF($A16="","",COUNTIFS($A$2:$A16,$A16)) -> 2 | J16: =IF($A16="","",$A16&"-"&$I16) -> 6-2 | K16: =IF($A16="","",IF(COUNTIF(参数!$B$6:$B$8,$H16)=0,"× 付款方式","√")) -> √
A17: 7 | B17: 46265 | C17: 华鑫店 | D17: 慢病用品 | E17: 销售费用 | F17: 办公费 | G17: 61.4 | H17: 库存现金 | I17: =IF($A17="","",COUNTIFS($A$2:$A17,$A17)) -> 1 | J17: =IF($A17="","",$A17&"-"&$I17) -> 7-1 | K17: =IF($A17="","",IF(COUNTIF(参数!$B$6:$B$8,$H17)=0,"× 付款方式","√")) -> √
A18: 7 | B18: 46265 | C18: 华鑫店 | D18: 水费 | E18: 销售费用 | F18: 水费 | G18: 20 | H18: 库存现金 | I18: =IF($A18="","",COUNTIFS($A$2:$A18,$A18)) -> 2 | J18: =IF($A18="","",$A18&"-"&$I18) -> 7-2 | K18: =IF($A18="","",IF(COUNTIF(参数!$B$6:$B$8,$H18)=0,"× 付款方式","√")) -> √
A19: 7 | B19: 46265 | C19: 华鑫店 | D19: 电费 | E19: 销售费用 | F19: 电费 | G19: 800 | H19: 库存现金 | I19: =IF($A19="","",COUNTIFS($A$2:$A19,$A19)) -> 3 | J19: =IF($A19="","",$A19&"-"&$I19) -> 7-3 | K19: =IF($A19="","",IF(COUNTIF(参数!$B$6:$B$8,$H19)=0,"× 付款方式","√")) -> √
A20: 8 | B20: 46265 | C20: 大霍店 | D20: 水费 | E20: 销售费用 | F20: 水费 | G20: 15 | H20: 库存现金 | I20: =IF($A20="","",COUNTIFS($A$2:$A20,$A20)) -> 1 | J20: =IF($A20="","",$A20&"-"&$I20) -> 8-1 | K20: =IF($A20="","",IF(COUNTIF(参数!$B$6:$B$8,$H20)=0,"× 付款方式","√")) -> √
A21: 9 | B21: 46265 | C21: 莲子镇店 | D21: 电费 | E21: 销售费用 | F21: 电费 | G21: 600 | H21: 库存现金 | I21: =IF($A21="","",COUNTIFS($A$2:$A21,$A21)) -> 1 | J21: =IF($A21="","",$A21&"-"&$I21) -> 9-1 | K21: =IF($A21="","",IF(COUNTIF(参数!$B$6:$B$8,$H21)=0,"× 付款方式","√")) -> √
A22: 9 | B22: 46265 | C22: 莲子镇店 | D22: 插排饮水机阀 | E22: 销售费用 | F22: 办公费 | G22: 50 | H22: 库存现金 | I22: =IF($A22="","",COUNTIFS($A$2:$A22,$A22)) -> 2 | J22: =IF($A22="","",$A22&"-"&$I22) -> 9-2 | K22: =IF($A22="","",IF(COUNTIF(参数!$B$6:$B$8,$H22)=0,"× 付款方式","√")) -> √
A23: 9 | B23: 46265 | C23: 莲子镇店 | D23: 水费 | E23: 销售费用 | F23: 水费 | G23: 40 | H23: 库存现金 | I23: =IF($A23="","",COUNTIFS($A$2:$A23,$A23)) -> 3 | J23: =IF($A23="","",$A23&"-"&$I23) -> 9-3 | K23: =IF($A23="","",IF(COUNTIF(参数!$B$6:$B$8,$H23)=0,"× 付款方式","√")) -> √
... A108: 37 | B108: 46265 | C108: 博山店 | D108: 电费 | E108: 销售费用 | F108: 电费 | G108: 4000 | H108: 库存现金 | I108: =IF($A108="","",COUNTIFS($A$2:$A108,$A108)) -> 1 | J108: =IF($A108="","",$A108&"-"&$I108) -> 37-1 | K108: =IF($A108="","",IF(COUNTIF(参数!$B$6:$B$8,$H108)=0,"× 付款方式","√")) -> √
A109: 37 | B109: 46265 | C109: 博山店 | D109: 慢病用品 | E109: 销售费用 | G109: 36.9 | H109: 库存现金 | I109: =IF($A109="","",COUNTIFS($A$2:$A109,$A109)) -> 2 | J109: =IF($A109="","",$A109&"-"&$I109) -> 37-2 | K109: =IF($A109="","",IF(COUNTIF(参数!$B$6:$B$8,$H109)=0,"× 付款方式","√")) -> √
I110: =IF($A110="","",COUNTIFS($A$2:$A110,$A110)) | J110: =IF($A110="","",$A110&"-"&$I110) | K110: =IF($A110="","",IF(COUNTIF(参数!$B$6:$B$8,$H110)=0,"× 付款方式","√"))
I111: =IF($A111="","",COUNTIFS($A$2:$A111,$A111)) | J111: =IF($A111="","",$A111&"-"&$I111) | K111: =IF($A111="","",IF(COUNTIF(参数!$B$6:$B$8,$H111)=0,"× 付款方式","√"))
I112: =IF($A112="","",COUNTIFS($A$2:$A112,$A112)) | J112: =IF($A112="","",$A112&"-"&$I112) | K112: =IF($A112="","",IF(COUNTIF(参数!$B$6:$B$8,$H112)=0,"× 付款方式","√"))
I113: =IF($A113="","",COUNTIFS($A$2:$A113,$A113)) | J113: =IF($A113="","",$A113&"-"&$I113) | K113: =IF($A113="","",IF(COUNTIF(参数!$B$6:$B$8,$H113)=0,"× 付款方式","√"))
I114: =IF($A114="","",COUNTIFS($A$2:$A114,$A114)) | J114: =IF($A114="","",$A114&"-"&$I114) | K114: =IF($A114="","",IF(COUNTIF(参数!$B$6:$B$8,$H114)=0,"× 付款方式","√"))
I115: =IF($A115="","",COUNTIFS($A$2:$A115,$A115)) | J115: =IF($A115="","",$A115&"-"&$I115) | K115: =IF($A115="","",IF(COUNTIF(参数!$B$6:$B$8,$H115)=0,"× 付款方式","√"))
I116: =IF($A116="","",COUNTIFS($A$2:$A116,$A116)) | J116: =IF($A116="","",$A116&"-"&$I116) | K116: =IF($A116="","",IF(COUNTIF(参数!$B$6:$B$8,$H116)=0,"× 付款方式","√"))
I117: =IF($A117="","",COUNTIFS($A$2:$A117,$A117)) | J117: =IF($A117="","",$A117&"-"&$I117) | K117: =IF($A117="","",IF(COUNTIF(参数!$B$6:$B$8,$H117)=0,"× 付款方式","√"))
I118: =IF($A118="","",COUNTIFS($A$2:$A118,$A118)) | J118: =IF($A118="","",$A118&"-"&$I118) | K118: =IF($A118="","",IF(COUNTIF(参数!$B$6:$B$8,$H118)=0,"× 付款方式","√"))
I119: =IF($A119="","",COUNTIFS($A$2:$A119,$A119)) | J119: =IF($A119="","",$A119&"-"&$I119) | K119: =IF($A119="","",IF(COUNTIF(参数!$B$6:$B$8,$H119)=0,"× 付款方式","√"))
I120: =IF($A120="","",COUNTIFS($A$2:$A120,$A120)) | J120: =IF($A120="","",$A120&"-"&$I120) | K120: =IF($A120="","",IF(COUNTIF(参数!$B$6:$B$8,$H120)=0,"× 付款方式","√"))
I121: =IF($A121="","",COUNTIFS($A$2:$A121,$A121)) | J121: =IF($A121="","",$A121&"-"&$I121) | K121: =IF($A121="","",IF(COUNTIF(参数!$B$6:$B$8,$H121)=0,"× 付款方式","√"))
... I1201: =IF($A1201="","",COUNTIFS($A$2:$A1201,$A1201)) | J1201: =IF($A1201="","",$A1201&"-"&$I1201) | K1201: =IF($A1201="","",IF(COUNTIF(参数!$B$6:$B$8,$H1201)=0,"× 付款方式","√"))

Sheet 海典汇总
A1: 门店编码 | B1: 门店名称 | C1: 现金 | D1: 现11金 | E1: 海典聚合支付 | F1: 医保 | G1: 医保统筹 | H1: 健e卡 | I1: 医卡通 | J1: 企健网 | K1: 二十四小时 | L1: OMS线上支付 | M1: 美团 | N1: 饿了么 | O1: 京东秒送 | P1: 会员零钱包 | Q1: 储值卡 | R1: 积分抵现 | S1: 代金券 | T1: 微信平台礼品券 | U1: 微信平台优惠券 | V1: 银联 | W1: 微信 | X1: 支付宝 | Y1: 支付宝_老 | Z1: 亲情卡 | AA1: 京东LOC劵 | AB1: 平安药卡组合支付 | AC1: 小镇外卖 | AD1: 收银兑换损失 | AE1: 销售合计
A2: =IFERROR(MATCH("门店代码",输入海典!$1:$1,0),0) -> 2 | B2: =IF($A$2=0,FALSE(),ISTEXT(INDEX(INDEX(输入海典!$A$1:$AN$20000,0,$A$2),2))) -> TRUE | C2: =IFERROR(MATCH(C$1,输入海典!$1:$1,0),0) -> 5 | D2: =IFERROR(MATCH(D$1,输入海典!$1:$1,0),0) -> 6 | E2: =IFERROR(MATCH(E$1,输入海典!$1:$1,0),0) -> 7 | F2: =IFERROR(MATCH(F$1,输入海典!$1:$1,0),0) -> 8 | G2: =IFERROR(MATCH(G$1,输入海典!$1:$1,0),0) -> 9 | H2: =IFERROR(MATCH(H$1,输入海典!$1:$1,0),0) -> 10 | I2: =IFERROR(MATCH(I$1,输入海典!$1:$1,0),0) -> 11 | J2: =IFERROR(MATCH(J$1,输入海典!$1:$1,0),0) -> 12 | ... AE2: =IFERROR(MATCH(AE$1,输入海典!$1:$1,0),0) -> 33
A3: =IF(门店对照!$D2=1,门店对照!$A2,"#未启用#") -> 2001 | B3: =IF(门店对照!$B2="","",门店对照!$B2) -> 柏人商城分店（1店） | C3: =IF(OR(C$2=0,$A$2=0),0,SUMIFS(INDEX(输入海典!$A$1:$AN$20000,0,C$2),INDEX(输入海典!$A$1:$AN$20000,0,$A$2),IF($B$2,""&$A3,$A3))) -> 6428.43 | D3: =IF(OR(D$2=0,$A$2=0),0,SUMIFS(INDEX(输入海典!$A$1:$AN$20000,0,D$2),INDEX(输入海典!$A$1:$AN$20000,0,$A$2),IF($B$2,""&$A3,$A3))) -> 0 | E3: =IF(OR(E$2=0,$A$2=0),0,SUMIFS(INDEX(输入海典!$A$1:$AN$20000,0,E$2),INDEX(输入海典!$A$1:$AN$20000,0,$A$2),IF($B$2,""&$A3,$A3))) -> 22768.52 | F3: =IF(OR(F$2=0,$A$2=0),0,SUMIFS(INDEX(输入海典!$A$1:$AN$20000,0,F$2),INDEX(输入海典!$A$1:$AN$20000,0,$A$2),IF($B$2,""&$A3,$A3))) -> 6716.34 | G3: =IF(OR(G$2=0,$A$2=0),0,SUMIFS(INDEX(输入海典!$A$1:$AN$20000,0,G$2),INDEX(输入海典!$A$1:$AN$20000,0,$A$2),IF($B$2,""&$A3,$A3))) -> 0 | H3: =IF(OR(H$2=0,$A$2=0),0,SUMIFS(INDEX(输入海典!$A$1:$AN$20000,0,H$2),INDEX(输入海典!$A$1:$AN$20000,0,$A$2),IF($B$2,""&$A3,$A3))) -> 0 | I3: =IF(OR(I$2=0,$A$2=0),0,SUMIFS(INDEX(输入海典!$A$1:$AN$20000,0,I$2),INDEX(输入海典!$A$1:$AN$20000,0,$A$2),IF($B$2,""&$A3,$A3))) -> 0 | J3: =IF(OR(J$2=0,$A$2=0),0,SUMIFS(INDEX(输入海典!$A$1:$AN$20000,0,J$2),INDEX(输入海典!$A$1:$AN$20000,0,$A$2),IF($B$2,""&$A3,$A3))) -> 0 | ... AE3: =IF(OR(AE$2=0,$A$2=0),0,SUMIFS(INDEX(输入海典!$A$1:$AN$20000,0,AE$2),INDEX(输入海典!$A$1:$AN$20000,0,$A$2),IF($B$2,""&$A3,$A3))) -> 36409.51
A4: =IF(门店对照!$D3=1,门店对照!$A3,"#未启用#") -> 2002 | B4: =IF(门店对照!$B3="","",门店对照!$B3) -> 新隆分店（2分店） | C4: =IF(OR(C$2=0,$A$2=0),0,SUMIFS(INDEX(输入海典!$A$1:$AN$20000,0,C$2),INDEX(输入海典!$A$1:$AN$20000,0,$A$2),IF($B$2,""&$A4,$A4))) -> 40649.83 | D4: =IF(OR(D$2=0,$A$2=0),0,SUMIFS(INDEX(输入海典!$A$1:$AN$20000,0,D$2),INDEX(输入海典!$A$1:$AN$20000,0,$A$2),IF($B$2,""&$A4,$A4))) -> 250321.02 | E4: =IF(OR(E$2=0,$A$2=0),0,SUMIFS(INDEX(输入海典!$A$1:$AN$20000,0,E$2),INDEX(输入海典!$A$1:$AN$20000,0,$A$2),IF($B$2,""&$A4,$A4))) -> 103203.75 | F4: =IF(OR(F$2=0,$A$2=0),0,SUMIFS(INDEX(输入海典!$A$1:$AN$20000,0,F$2),INDEX(输入海典!$A$1:$AN$20000,0,$A$2),IF($B$2,""&$A4,$A4))) -> 44535.92 | G4: =IF(OR(G$2=0,$A$2=0),0,SUMIFS(INDEX(输入海典!$A$1:$AN$20000,0,G$2),INDEX(输入海典!$A$1:$AN$20000,0,$A$2),IF($B$2,""&$A4,$A4))) -> 485.45 | H4: =IF(OR(H$2=0,$A$2=0),0,SUMIFS(INDEX(输入海典!$A$1:$AN$20000,0,H$2),INDEX(输入海典!$A$1:$AN$20000,0,$A$2),IF($B$2,""&$A4,$A4))) -> 0 | I4: =IF(OR(I$2=0,$A$2=0),0,SUMIFS(INDEX(输入海典!$A$1:$AN$20000,0,I$2),INDEX(输入海典!$A$1:$AN$20000,0,$A$2),IF($B$2,""&$A4,$A4))) -> 0 | J4: =IF(OR(J$2=0,$A$2=0),0,SUMIFS(INDEX(输入海典!$A$1:$AN$20000,0,J$2),INDEX(输入海典!$A$1:$AN$20000,0,$A$2),IF($B$2,""&$A4,$A4))) -> 0 | ... AE4: =IF(OR(AE$2=0,$A$2=0),0,SUMIFS(INDEX(输入海典!$A$1:$AN$20000,0,AE$2),INDEX(输入海典!$A$1:$AN$20000,0,$A$2),IF($B$2,""&$A4,$A4))) -> 444121.45
A5: =IF(门店对照!$D4=1,门店对照!$A4,"#未启用#") -> 2003 | B5: =IF(门店对照!$B4="","",门店对照!$B4) -> 康庄东路分店（3店） | C5: =IF(OR(C$2=0,$A$2=0),0,SUMIFS(INDEX(输入海典!$A$1:$AN$20000,0,C$2),INDEX(输入海典!$A$1:$AN$20000,0,$A$2),IF($B$2,""&$A5,$A5))) -> 10963.03 | D5: =IF(OR(D$2=0,$A$2=0),0,SUMIFS(INDEX(输入海典!$A$1:$AN$20000,0,D$2),INDEX(输入海典!$A$1:$AN$20000,0,$A$2),IF($B$2,""&$A5,$A5))) -> 39158.39 | E5: =IF(OR(E$2=0,$A$2=0),0,SUMIFS(INDEX(输入海典!$A$1:$AN$20000,0,E$2),INDEX(输入海典!$A$1:$AN$20000,0,$A$2),IF($B$2,""&$A5,$A5))) -> 9808.79 | F5: =IF(OR(F$2=0,$A$2=0),0,SUMIFS(INDEX(输入海典!$A$1:$AN$20000,0,F$2),INDEX(输入海典!$A$1:$AN$20000,0,$A$2),IF($B$2,""&$A5,$A5))) -> 30706.84 | G5: =IF(OR(G$2=0,$A$2=0),0,SUMIFS(INDEX(输入海典!$A$1:$AN$20000,0,G$2),INDEX(输入海典!$A$1:$AN$20000,0,$A$2),IF($B$2,""&$A5,$A5))) -> 144 | H5: =IF(OR(H$2=0,$A$2=0),0,SUMIFS(INDEX(输入海典!$A$1:$AN$20000,0,H$2),INDEX(输入海典!$A$1:$AN$20000,0,$A$2),IF($B$2,""&$A5,$A5))) -> 30700.31 | I5: =IF(OR(I$2=0,$A$2=0),0,SUMIFS(INDEX(输入海典!$A$1:$AN$20000,0,I$2),INDEX(输入海典!$A$1:$AN$20000,0,$A$2),IF($B$2,""&$A5,$A5))) -> 586.28 | J5: =IF(OR(J$2=0,$A$2=0),0,SUMIFS(INDEX(输入海典!$A$1:$AN$20000,0,J$2),INDEX(输入海典!$A$1:$AN$20000,0,$A$2),IF($B$2,""&$A5,$A5))) -> 0 | ... AE5: =IF(OR(AE$2=0,$A$2=0),0,SUMIFS(INDEX(输入海典!$A$1:$AN$20000,0,AE$2),INDEX(输入海典!$A$1:$AN$20000,0,$A$2),IF($B$2,""&$A5,$A5))) -> 128377.96
A6: =IF(门店对照!$D5=1,门店对照!$A5,"#未启用#") -> 2004 | B6: =IF(门店对照!$B5="","",门店对照!$B5) -> 东关分店（4分店） | C6: =IF(OR(C$2=0,$A$2=0),0,SUMIFS(INDEX(输入海典!$A$1:$AN$20000,0,C$2),INDEX(输入海典!$A$1:$AN$20000,0,$A$2),IF($B$2,""&$A6,$A6))) -> 13679.31 | D6: =IF(OR(D$2=0,$A$2=0),0,SUMIFS(INDEX(输入海典!$A$1:$AN$20000,0,D$2),INDEX(输入海典!$A$1:$AN$20000,0,$A$2),IF($B$2,""&$A6,$A6))) -> 53492.2 | E6: =IF(OR(E$2=0,$A$2=0),0,SUMIFS(INDEX(输入海典!$A$1:$AN$20000,0,E$2),INDEX(输入海典!$A$1:$AN$20000,0,$A$2),IF($B$2,""&$A6,$A6))) -> 5004.6 | F6: =IF(OR(F$2=0,$A$2=0),0,SUMIFS(INDEX(输入海典!$A$1:$AN$20000,0,F$2),INDEX(输入海典!$A$1:$AN$20000,0,$A$2),IF($B$2,""&$A6,$A6))) -> 21335.84 | G6: =IF(OR(G$2=0,$A$2=0),0,SUMIFS(INDEX(输入海典!$A$1:$AN$20000,0,G$2),INDEX(输入海典!$A$1:$AN$20000,0,$A$2),IF($B$2,""&$A6,$A6))) -> 0 | H6: =IF(OR(H$2=0,$A$2=0),0,SUMIFS(INDEX(输入海典!$A$1:$AN$20000,0,H$2),INDEX(输入海典!$A$1:$AN$20000,0,$A$2),IF($B$2,""&$A6,$A6))) -> 4415.97 | I6: =IF(OR(I$2=0,$A$2=0),0,SUMIFS(INDEX(输入海典!$A$1:$AN$20000,0,I$2),INDEX(输入海典!$A$1:$AN$20000,0,$A$2),IF($B$2,""&$A6,$A6))) -> 0 | J6: =IF(OR(J$2=0,$A$2=0),0,SUMIFS(INDEX(输入海典!$A$1:$AN$20000,0,J$2),INDEX(输入海典!$A$1:$AN$20000,0,$A$2),IF($B$2,""&$A6,$A6))) -> 0 | ... AE6: =IF(OR(AE$2=0,$A$2=0),0,SUMIFS(INDEX(输入海典!$A$1:$AN$20000,0,AE$2),INDEX(输入海典!$A$1:$AN$20000,0,$A$2),IF($B$2,""&$A6,$A6))) -> 108041.04
A7: =IF(门店对照!$D6=1,门店对照!$A6,"#未启用#") -> 2005 | B7: =IF(门店对照!$B6="","",门店对照!$B6) -> 象城街分店（5店） | C7: =IF(OR(C$2=0,$A$2=0),0,SUMIFS(INDEX(输入海典!$A$1:$AN$20000,0,C$2),INDEX(输入海典!$A$1:$AN$20000,0,$A$2),IF($B$2,""&$A7,$A7))) -> 12662.26 | D7: =IF(OR(D$2=0,$A$2=0),0,SUMIFS(INDEX(输入海典!$A$1:$AN$20000,0,D$2),INDEX(输入海典!$A$1:$AN$20000,0,$A$2),IF($B$2,""&$A7,$A7))) -> 50395.95 | E7: =IF(OR(E$2=0,$A$2=0),0,SUMIFS(INDEX(输入海典!$A$1:$AN$20000,0,E$2),INDEX(输入海典!$A$1:$AN$20000,0,$A$2),IF($B$2,""&$A7,$A7))) -> 18036.9 | F7: =IF(OR(F$2=0,$A$2=0),0,SUMIFS(INDEX(输入海典!$A$1:$AN$20000,0,F$2),INDEX(输入海典!$A$1:$AN$20000,0,$A$2),IF($B$2,""&$A7,$A7))) -> 28845.65 | G7: =IF(OR(G$2=0,$A$2=0),0,SUMIFS(INDEX(输入海典!$A$1:$AN$20000,0,G$2),INDEX(输入海典!$A$1:$AN$20000,0,$A$2),IF($B$2,""&$A7,$A7))) -> 0 | H7: =IF(OR(H$2=0,$A$2=0),0,SUMIFS(INDEX(输入海典!$A$1:$AN$20000,0,H$2),INDEX(输入海典!$A$1:$AN$20000,0,$A$2),IF($B$2,""&$A7,$A7))) -> 0 | I7: =IF(OR(I$2=0,$A$2=0),0,SUMIFS(INDEX(输入海典!$A$1:$AN$20000,0,I$2),INDEX(输入海典!$A$1:$AN$20000,0,$A$2),IF($B$2,""&$A7,$A7))) -> 2583.12 | J7: =IF(OR(J$2=0,$A$2=0),0,SUMIFS(INDEX(输入海典!$A$1:$AN$20000,0,J$2),INDEX(输入海典!$A$1:$AN$20000,0,$A$2),IF($B$2,""&$A7,$A7))) -> 0 | ... AE7: =IF(OR(AE$2=0,$A$2=0),0,SUMIFS(INDEX(输入海典!$A$1:$AN$20000,0,AE$2),INDEX(输入海典!$A$1:$AN$20000,0,$A$2),IF($B$2,""&$A7,$A7))) -> 116657.9
A8: =IF(门店对照!$D7=1,门店对照!$A7,"#未启用#") -> 2006 | B8: =IF(门店对照!$B7="","",门店对照!$B7) -> 博荣分店（6分店） | C8: =IF(OR(C$2=0,$A$2=0),0,SUMIFS(INDEX(输入海典!$A$1:$AN$20000,0,C$2),INDEX(输入海典!$A$1:$AN$20000,0,$A$2),IF($B$2,""&$A8,$A8))) -> 4575.05 | D8: =IF(OR(D$2=0,$A$2=0),0,SUMIFS(INDEX(输入海典!$A$1:$AN$20000,0,D$2),INDEX(输入海典!$A$1:$AN$20000,0,$A$2),IF($B$2,""&$A8,$A8))) -> 0 | E8: =IF(OR(E$2=0,$A$2=0),0,SUMIFS(INDEX(输入海典!$A$1:$AN$20000,0,E$2),INDEX(输入海典!$A$1:$AN$20000,0,$A$2),IF($B$2,""&$A8,$A8))) -> 33428.3 | F8: =IF(OR(F$2=0,$A$2=0),0,SUMIFS(INDEX(输入海典!$A$1:$AN$20000,0,F$2),INDEX(输入海典!$A$1:$AN$20000,0,$A$2),IF($B$2,""&$A8,$A8))) -> 21770.57 | G8: =IF(OR(G$2=0,$A$2=0),0,SUMIFS(INDEX(输入海典!$A$1:$AN$20000,0,G$2),INDEX(输入海典!$A$1:$AN$20000,0,$A$2),IF($B$2,""&$A8,$A8))) -> 291.52 | H8: =IF(OR(H$2=0,$A$2=0),0,SUMIFS(INDEX(输入海典!$A$1:$AN$20000,0,H$2),INDEX(输入海典!$A$1:$AN$20000,0,$A$2),IF($B$2,""&$A8,$A8))) -> 3402.37 | I8: =IF(OR(I$2=0,$A$2=0),0,SUMIFS(INDEX(输入海典!$A$1:$AN$20000,0,I$2),INDEX(输入海典!$A$1:$AN$20000,0,$A$2),IF($B$2,""&$A8,$A8))) -> 0 | J8: =IF(OR(J$2=0,$A$2=0),0,SUMIFS(INDEX(输入海典!$A$1:$AN$20000,0,J$2),INDEX(输入海典!$A$1:$AN$20000,0,$A$2),IF($B$2,""&$A8,$A8))) -> 0 | ... AE8: =IF(OR(AE$2=0,$A$2=0),0,SUMIFS(INDEX(输入海典!$A$1:$AN$20000,0,AE$2),INDEX(输入海典!$A$1:$AN$20000,0,$A$2),IF($B$2,""&$A8,$A8))) -> 65353.62
A9: =IF(门店对照!$D8=1,门店对照!$A8,"#未启用#") -> 2007 | B9: =IF(门店对照!$B8="","",门店对照!$B8) -> 华鑫分店（7店） | C9: =IF(OR(C$2=0,$A$2=0),0,SUMIFS(INDEX(输入海典!$A$1:$AN$20000,0,C$2),INDEX(输入海典!$A$1:$AN$20000,0,$A$2),IF($B$2,""&$A9,$A9))) -> 12722.01 | D9: =IF(OR(D$2=0,$A$2=0),0,SUMIFS(INDEX(输入海典!$A$1:$AN$20000,0,D$2),INDEX(输入海典!$A$1:$AN$20000,0,$A$2),IF($B$2,""&$A9,$A9))) -> 0 | E9: =IF(OR(E$2=0,$A$2=0),0,SUMIFS(INDEX(输入海典!$A$1:$AN$20000,0,E$2),INDEX(输入海典!$A$1:$AN$20000,0,$A$2),IF($B$2,""&$A9,$A9))) -> 33811.43 | F9: =IF(OR(F$2=0,$A$2=0),0,SUMIFS(INDEX(输入海典!$A$1:$AN$20000,0,F$2),INDEX(输入海典!$A$1:$AN$20000,0,$A$2),IF($B$2,""&$A9,$A9))) -> 11838.8 | G9: =IF(OR(G$2=0,$A$2=0),0,SUMIFS(INDEX(输入海典!$A$1:$AN$20000,0,G$2),INDEX(输入海典!$A$1:$AN$20000,0,$A$2),IF($B$2,""&$A9,$A9))) -> 0 | H9: =IF(OR(H$2=0,$A$2=0),0,SUMIFS(INDEX(输入海典!$A$1:$AN$20000,0,H$2),INDEX(输入海典!$A$1:$AN$20000,0,$A$2),IF($B$2,""&$A9,$A9))) -> 0 | I9: =IF(OR(I$2=0,$A$2=0),0,SUMIFS(INDEX(输入海典!$A$1:$AN$20000,0,I$2),INDEX(输入海典!$A$1:$AN$20000,0,$A$2),IF($B$2,""&$A9,$A9))) -> 0 | J9: =IF(OR(J$2=0,$A$2=0),0,SUMIFS(INDEX(输入海典!$A$1:$AN$20000,0,J$2),INDEX(输入海典!$A$1:$AN$20000,0,$A$2),IF($B$2,""&$A9,$A9))) -> 2189.3 | ... AE9: =IF(OR(AE$2=0,$A$2=0),0,SUMIFS(INDEX(输入海典!$A$1:$AN$20000,0,AE$2),INDEX(输入海典!$A$1:$AN$20000,0,$A$2),IF($B$2,""&$A9,$A9))) -> 64343.02
A10: =IF(门店对照!$D9=1,门店对照!$A9,"#未启用#") -> 2008 | B10: =IF(门店对照!$B9="","",门店对照!$B9) -> 博昭分店（8分店） | C10: =IF(OR(C$2=0,$A$2=0),0,SUMIFS(INDEX(输入海典!$A$1:$AN$20000,0,C$2),INDEX(输入海典!$A$1:$AN$20000,0,$A$2),IF($B$2,""&$A10,$A10))) -> 8028.82 | D10: =IF(OR(D$2=0,$A$2=0),0,SUMIFS(INDEX(输入海典!$A$1:$AN$20000,0,D$2),INDEX(输入海典!$A$1:$AN$20000,0,$A$2),IF($B$2,""&$A10,$A10))) -> 0 | E10: =IF(OR(E$2=0,$A$2=0),0,SUMIFS(INDEX(输入海典!$A$1:$AN$20000,0,E$2),INDEX(输入海典!$A$1:$AN$20000,0,$A$2),IF($B$2,""&$A10,$A10))) -> 53118.64 | F10: =IF(OR(F$2=0,$A$2=0),0,SUMIFS(INDEX(输入海典!$A$1:$AN$20000,0,F$2),INDEX(输入海典!$A$1:$AN$20000,0,$A$2),IF($B$2,""&$A10,$A10))) -> 10758.32 | G10: =IF(OR(G$2=0,$A$2=0),0,SUMIFS(INDEX(输入海典!$A$1:$AN$20000,0,G$2),INDEX(输入海典!$A$1:$AN$20000,0,$A$2),IF($B$2,""&$A10,$A10))) -> 0 | H10: =IF(OR(H$2=0,$A$2=0),0,SUMIFS(INDEX(输入海典!$A$1:$AN$20000,0,H$2),INDEX(输入海典!$A$1:$AN$20000,0,$A$2),IF($B$2,""&$A10,$A10))) -> 0 | I10: =IF(OR(I$2=0,$A$2=0),0,SUMIFS(INDEX(输入海典!$A$1:$AN$20000,0,I$2),INDEX(输入海典!$A$1:$AN$20000,0,$A$2),IF($B$2,""&$A10,$A10))) -> 0 | J10: =IF(OR(J$2=0,$A$2=0),0,SUMIFS(INDEX(输入海典!$A$1:$AN$20000,0,J$2),INDEX(输入海典!$A$1:$AN$20000,0,$A$2),IF($B$2,""&$A10,$A10))) -> 0 | ... AE10: =IF(OR(AE$2=0,$A$2=0),0,SUMIFS(INDEX(输入海典!$A$1:$AN$20000,0,AE$2),INDEX(输入海典!$A$1:$AN$20000,0,$A$2),IF($B$2,""&$A10,$A10))) -> 75943.14
A11: =IF(门店对照!$D10=1,门店对照!$A10,"#未启用#") -> 2009 | B11: =IF(门店对照!$B10="","",门店对照!$B10) -> 大霍分店（9分店） | C11: =IF(OR(C$2=0,$A$2=0),0,SUMIFS(INDEX(输入海典!$A$1:$AN$20000,0,C$2),INDEX(输入海典!$A$1:$AN$20000,0,$A$2),IF($B$2,""&$A11,$A11))) -> 9880.5 | D11: =IF(OR(D$2=0,$A$2=0),0,SUMIFS(INDEX(输入海典!$A$1:$AN$20000,0,D$2),INDEX(输入海典!$A$1:$AN$20000,0,$A$2),IF($B$2,""&$A11,$A11))) -> 0 | E11: =IF(OR(E$2=0,$A$2=0),0,SUMIFS(INDEX(输入海典!$A$1:$AN$20000,0,E$2),INDEX(输入海典!$A$1:$AN$20000,0,$A$2),IF($B$2,""&$A11,$A11))) -> 22410.18 | F11: =IF(OR(F$2=0,$A$2=0),0,SUMIFS(INDEX(输入海典!$A$1:$AN$20000,0,F$2),INDEX(输入海典!$A$1:$AN$20000,0,$A$2),IF($B$2,""&$A11,$A11))) -> 3361.43 | G11: =IF(OR(G$2=0,$A$2=0),0,SUMIFS(INDEX(输入海典!$A$1:$AN$20000,0,G$2),INDEX(输入海典!$A$1:$AN$20000,0,$A$2),IF($B$2,""&$A11,$A11))) -> 0 | H11: =IF(OR(H$2=0,$A$2=0),0,SUMIFS(INDEX(输入海典!$A$1:$AN$20000,0,H$2),INDEX(输入海典!$A$1:$AN$20000,0,$A$2),IF($B$2,""&$A11,$A11))) -> 0 | I11: =IF(OR(I$2=0,$A$2=0),0,SUMIFS(INDEX(输入海典!$A$1:$AN$20000,0,I$2),INDEX(输入海典!$A$1:$AN$20000,0,$A$2),IF($B$2,""&$A11,$A11))) -> 0 | J11: =IF(OR(J$2=0,$A$2=0),0,SUMIFS(INDEX(输入海典!$A$1:$AN$20000,0,J$2),INDEX(输入海典!$A$1:$AN$20000,0,$A$2),IF($B$2,""&$A11,$A11))) -> 0 | ... AE11: =IF(OR(AE$2=0,$A$2=0),0,SUMIFS(INDEX(输入海典!$A$1:$AN$20000,0,AE$2),INDEX(输入海典!$A$1:$AN$20000,0,$A$2),IF($B$2,""&$A11,$A11))) -> 36619.7
A12: =IF(门店对照!$D11=1,门店对照!$A11,"#未启用#") -> 2010 | B12: =IF(门店对照!$B11="","",门店对照!$B11) -> 莲子镇分店(10分店) | C12: =IF(OR(C$2=0,$A$2=0),0,SUMIFS(INDEX(输入海典!$A$1:$AN$20000,0,C$2),INDEX(输入海典!$A$1:$AN$20000,0,$A$2),IF($B$2,""&$A12,$A12))) -> 23656.79 | D12: =IF(OR(D$2=0,$A$2=0),0,SUMIFS(INDEX(输入海典!$A$1:$AN$20000,0,D$2),INDEX(输入海典!$A$1:$AN$20000,0,$A$2),IF($B$2,""&$A12,$A12))) -> 0 | E12: =IF(OR(E$2=0,$A$2=0),0,SUMIFS(INDEX(输入海典!$A$1:$AN$20000,0,E$2),INDEX(输入海典!$A$1:$AN$20000,0,$A$2),IF($B$2,""&$A12,$A12))) -> 67547.35 | F12: =IF(OR(F$2=0,$A$2=0),0,SUMIFS(INDEX(输入海典!$A$1:$AN$20000,0,F$2),INDEX(输入海典!$A$1:$AN$20000,0,$A$2),IF($B$2,""&$A12,$A12))) -> 14875.36 | G12: =IF(OR(G$2=0,$A$2=0),0,SUMIFS(INDEX(输入海典!$A$1:$AN$20000,0,G$2),INDEX(输入海典!$A$1:$AN$20000,0,$A$2),IF($B$2,""&$A12,$A12))) -> 0 | H12: =IF(OR(H$2=0,$A$2=0),0,SUMIFS(INDEX(输入海典!$A$1:$AN$20000,0,H$2),INDEX(输入海典!$A$1:$AN$20000,0,$A$2),IF($B$2,""&$A12,$A12))) -> 0 | I12: =IF(OR(I$2=0,$A$2=0),0,SUMIFS(INDEX(输入海典!$A$1:$AN$20000,0,I$2),INDEX(输入海典!$A$1:$AN$20000,0,$A$2),IF($B$2,""&$A12,$A12))) -> 0 | J12: =IF(OR(J$2=0,$A$2=0),0,SUMIFS(INDEX(输入海典!$A$1:$AN$20000,0,J$2),INDEX(输入海典!$A$1:$AN$20000,0,$A$2),IF($B$2,""&$A12,$A12))) -> 0 | ... AE12: =IF(OR(AE$2=0,$A$2=0),0,SUMIFS(INDEX(输入海典!$A$1:$AN$20000,0,AE$2),INDEX(输入海典!$A$1:$AN$20000,0,$A$2),IF($B$2,""&$A12,$A12))) -> 107280.2
A13: =IF(门店对照!$D12=1,门店对照!$A12,"#未启用#") -> 2011 | B13: =IF(门店对照!$B12="","",门店对照!$B12) -> 毛尔寨分店(11分店) | C13: =IF(OR(C$2=0,$A$2=0),0,SUMIFS(INDEX(输入海典!$A$1:$AN$20000,0,C$2),INDEX(输入海典!$A$1:$AN$20000,0,$A$2),IF($B$2,""&$A13,$A13))) -> 24370.58 | D13: =IF(OR(D$2=0,$A$2=0),0,SUMIFS(INDEX(输入海典!$A$1:$AN$20000,0,D$2),INDEX(输入海典!$A$1:$AN$20000,0,$A$2),IF($B$2,""&$A13,$A13))) -> 0 | E13: =IF(OR(E$2=0,$A$2=0),0,SUMIFS(INDEX(输入海典!$A$1:$AN$20000,0,E$2),INDEX(输入海典!$A$1:$AN$20000,0,$A$2),IF($B$2,""&$A13,$A13))) -> 14193.02 | F13: =IF(OR(F$2=0,$A$2=0),0,SUMIFS(INDEX(输入海典!$A$1:$AN$20000,0,F$2),INDEX(输入海典!$A$1:$AN$20000,0,$A$2),IF($B$2,""&$A13,$A13))) -> 2921.49 | G13: =IF(OR(G$2=0,$A$2=0),0,SUMIFS(INDEX(输入海典!$A$1:$AN$20000,0,G$2),INDEX(输入海典!$A$1:$AN$20000,0,$A$2),IF($B$2,""&$A13,$A13))) -> 0 | H13: =IF(OR(H$2=0,$A$2=0),0,SUMIFS(INDEX(输入海典!$A$1:$AN$20000,0,H$2),INDEX(输入海典!$A$1:$AN$20000,0,$A$2),IF($B$2,""&$A13,$A13))) -> 0 | I13: =IF(OR(I$2=0,$A$2=0),0,SUMIFS(INDEX(输入海典!$A$1:$AN$20000,0,I$2),INDEX(输入海典!$A$1:$AN$20000,0,$A$2),IF($B$2,""&$A13,$A13))) -> 0 | J13: =IF(OR(J$2=0,$A$2=0),0,SUMIFS(INDEX(输入海典!$A$1:$AN$20000,0,J$2),INDEX(输入海典!$A$1:$AN$20000,0,$A$2),IF($B$2,""&$A13,$A13))) -> 0 | ... AE13: =IF(OR(AE$2=0,$A$2=0),0,SUMIFS(INDEX(输入海典!$A$1:$AN$20000,0,AE$2),INDEX(输入海典!$A$1:$AN$20000,0,$A$2),IF($B$2,""&$A13,$A13))) -> 42823.36
A14: =IF(门店对照!$D13=1,门店对照!$A13,"#未启用#") -> 2012 | B14: =IF(门店对照!$B13="","",门店对照!$B13) -> 泽畔分店（12分店） | C14: =IF(OR(C$2=0,$A$2=0),0,SUMIFS(INDEX(输入海典!$A$1:$AN$20000,0,C$2),INDEX(输入海典!$A$1:$AN$20000,0,$A$2),IF($B$2,""&$A14,$A14))) -> 25649.6 | D14: =IF(OR(D$2=0,$A$2=0),0,SUMIFS(INDEX(输入海典!$A$1:$AN$20000,0,D$2),INDEX(输入海典!$A$1:$AN$20000,0,$A$2),IF($B$2,""&$A14,$A14))) -> 0 | E14: =IF(OR(E$2=0,$A$2=0),0,SUMIFS(INDEX(输入海典!$A$1:$AN$20000,0,E$2),INDEX(输入海典!$A$1:$AN$20000,0,$A$2),IF($B$2,""&$A14,$A14))) -> 20343.83 | F14: =IF(OR(F$2=0,$A$2=0),0,SUMIFS(INDEX(输入海典!$A$1:$AN$20000,0,F$2),INDEX(输入海典!$A$1:$AN$20000,0,$A$2),IF($B$2,""&$A14,$A14))) -> 3187.38 | G14: =IF(OR(G$2=0,$A$2=0),0,SUMIFS(INDEX(输入海典!$A$1:$AN$20000,0,G$2),INDEX(输入海典!$A$1:$AN$20000,0,$A$2),IF($B$2,""&$A14,$A14))) -> 0 | H14: =IF(OR(H$2=0,$A$2=0),0,SUMIFS(INDEX(输入海典!$A$1:$AN$20000,0,H$2),INDEX(输入海典!$A$1:$AN$20000,0,$A$2),IF($B$2,""&$A14,$A14))) -> 0 | I14: =IF(OR(I$2=0,$A$2=0),0,SUMIFS(INDEX(输入海典!$A$1:$AN$20000,0,I$2),INDEX(输入海典!$A$1:$AN$20000,0,$A$2),IF($B$2,""&$A14,$A14))) -> 0 | J14: =IF(OR(J$2=0,$A$2=0),0,SUMIFS(INDEX(输入海典!$A$1:$AN$20000,0,J$2),INDEX(输入海典!$A$1:$AN$20000,0,$A$2),IF($B$2,""&$A14,$A14))) -> 0 | ... AE14: =IF(OR(AE$2=0,$A$2=0),0,SUMIFS(INDEX(输入海典!$A$1:$AN$20000,0,AE$2),INDEX(输入海典!$A$1:$AN$20000,0,$A$2),IF($B$2,""&$A14,$A14))) -> 50656.25
... A67: =IF(门店对照!$D66=1,门店对照!$A66,"#未启用#") -> #未启用# | B67: =IF(门店对照!$B66="","",门店对照!$B66) -> 备用20 | C67: =IF(OR(C$2=0,$A$2=0),0,SUMIFS(INDEX(输入海典!$A$1:$AN$20000,0,C$2),INDEX(输入海典!$A$1:$AN$20000,0,$A$2),IF($B$2,""&$A67,$A67))) -> 0 | D67: =IF(OR(D$2=0,$A$2=0),0,SUMIFS(INDEX(输入海典!$A$1:$AN$20000,0,D$2),INDEX(输入海典!$A$1:$AN$20000,0,$A$2),IF($B$2,""&$A67,$A67))) -> 0 | E67: =IF(OR(E$2=0,$A$2=0),0,SUMIFS(INDEX(输入海典!$A$1:$AN$20000,0,E$2),INDEX(输入海典!$A$1:$AN$20000,0,$A$2),IF($B$2,""&$A67,$A67))) -> 0 | F67: =IF(OR(F$2=0,$A$2=0),0,SUMIFS(INDEX(输入海典!$A$1:$AN$20000,0,F$2),INDEX(输入海典!$A$1:$AN$20000,0,$A$2),IF($B$2,""&$A67,$A67))) -> 0 | G67: =IF(OR(G$2=0,$A$2=0),0,SUMIFS(INDEX(输入海典!$A$1:$AN$20000,0,G$2),INDEX(输入海典!$A$1:$AN$20000,0,$A$2),IF($B$2,""&$A67,$A67))) -> 0 | H67: =IF(OR(H$2=0,$A$2=0),0,SUMIFS(INDEX(输入海典!$A$1:$AN$20000,0,H$2),INDEX(输入海典!$A$1:$AN$20000,0,$A$2),IF($B$2,""&$A67,$A67))) -> 0 | I67: =IF(OR(I$2=0,$A$2=0),0,SUMIFS(INDEX(输入海典!$A$1:$AN$20000,0,I$2),INDEX(输入海典!$A$1:$AN$20000,0,$A$2),IF($B$2,""&$A67,$A67))) -> 0 | J67: =IF(OR(J$2=0,$A$2=0),0,SUMIFS(INDEX(输入海典!$A$1:$AN$20000,0,J$2),INDEX(输入海典!$A$1:$AN$20000,0,$A$2),IF($B$2,""&$A67,$A67))) -> 0 | ... AE67: =IF(OR(AE$2=0,$A$2=0),0,SUMIFS(INDEX(输入海典!$A$1:$AN$20000,0,AE$2),INDEX(输入海典!$A$1:$AN$20000,0,$A$2),IF($B$2,""&$A67,$A67))) -> 0

Sheet 分录收入
A1: 店序 | B1: 门店编码 | C1: 门店简称 | D1: 项目 | E1: 总账科目 | F1: 明细科目 | G1: 净额(+借-贷) | H1: 借方 | I1: 贷方 | J1: 有效 | K1: 店内序 | L1: 键 | M1: 摘要
A2: 1 | B2: =助手收入!$B2 -> 2001 | C2: =助手收入!$C2 -> 柏人商城店 | D2: =科目对照收入!$B2&"" -> 库存现金 | E2: =IF(AND(ROUND($G2,2)<0,科目对照收入!$L2<>""),科目对照收入!$L2,科目对照收入!$C2)&"" -> 库存现金 | F2: =IF(AND(ROUND($G2,2)<0,科目对照收入!$L2<>""),科目对照收入!$M2,科目对照收入!$D2)&"" | G2: =助手收入!$I2 -> 6428.43 | H2: =IF(ROUND($G2,2)>0,ROUND($G2,2),"") -> 6428.43 | I2: =IF(ROUND($G2,2)<0,-ROUND($G2,2),"") | J2: =IF(ROUND($G2,2)=0,0,1) -> 1 | K2: =IF($J2=0,"",SUM($J$2:$J2)) -> 1 | L2: =IF($K2="","",$A2*100+$K2) -> 101 | M2: =参数!$B$3 -> 7月收入
A3: 1 | B3: =助手收入!$B2 -> 2001 | C3: =助手收入!$C2 -> 柏人商城店 | D3: =科目对照收入!$B3&"" -> 聚合支付 | E3: =IF(AND(ROUND($G3,2)<0,科目对照收入!$L3<>""),科目对照收入!$L3,科目对照收入!$C3)&"" -> 应收账款 | F3: =IF(AND(ROUND($G3,2)<0,科目对照收入!$L3<>""),科目对照收入!$M3,科目对照收入!$D3)&"" -> 聚合支付 | G3: =ROUND(SUMIFS(输入聚合!$C:$C,输入聚合!$A:$A,助手收入!$X2)-SUMIFS(输入聚合!$D:$D,输入聚合!$A:$A,助手收入!$X2),2) -> 22707.04 | H3: =IF(ROUND($G3,2)>0,ROUND($G3,2),"") -> 22707.04 | I3: =IF(ROUND($G3,2)<0,-ROUND($G3,2),"") | J3: =IF(ROUND($G3,2)=0,0,1) -> 1 | K3: =IF($J3=0,"",SUM($J$2:$J3)) -> 2 | L3: =IF($K3="","",$A3*100+$K3) -> 102 | M3: =参数!$B$3 -> 7月收入
A4: 1 | B4: =助手收入!$B2 -> 2001 | C4: =助手收入!$C2 -> 柏人商城店 | D4: =科目对照收入!$B4&"" -> 医保 | E4: =IF(AND(ROUND($G4,2)<0,科目对照收入!$L4<>""),科目对照收入!$L4,科目对照收入!$C4)&"" -> 应收账款 | F4: =IF(AND(ROUND($G4,2)<0,科目对照收入!$L4<>""),科目对照收入!$M4,科目对照收入!$D4)&"" -> 医保 | G4: =IF(COUNTIFS(输入平台!$A:$A,助手收入!$X2,输入平台!$B:$B,科目对照收入!$B4)>0,ROUND(SUMIFS(输入平台!$C:$C,输入平台!$A:$A,助手收入!$X2,输入平台!$B:$B,科目对照收入!$B4),2),ROUND(海典汇总!$F$3+海典汇总!$G$3,2)) -> 6716.34 | H4: =IF(ROUND($G4,2)>0,ROUND($G4,2),"") -> 6716.34 | I4: =IF(ROUND($G4,2)<0,-ROUND($G4,2),"") | J4: =IF(ROUND($G4,2)=0,0,1) -> 1 | K4: =IF($J4=0,"",SUM($J$2:$J4)) -> 3 | L4: =IF($K4="","",$A4*100+$K4) -> 103 | M4: =参数!$B$3 -> 7月收入
A5: 1 | B5: =助手收入!$B2 -> 2001 | C5: =助手收入!$C2 -> 柏人商城店 | D5: =科目对照收入!$B5&"" -> 健e卡 | E5: =IF(AND(ROUND($G5,2)<0,科目对照收入!$L5<>""),科目对照收入!$L5,科目对照收入!$C5)&"" -> 应收账款 | F5: =IF(AND(ROUND($G5,2)<0,科目对照收入!$L5<>""),科目对照收入!$M5,科目对照收入!$D5)&"" -> 健e卡 | G5: =IF(COUNTIFS(输入平台!$A:$A,助手收入!$X2,输入平台!$B:$B,科目对照收入!$B5)>0,ROUND(SUMIFS(输入平台!$C:$C,输入平台!$A:$A,助手收入!$X2,输入平台!$B:$B,科目对照收入!$B5),2),ROUND(海典汇总!$H$3,2)) -> 0 | H5: =IF(ROUND($G5,2)>0,ROUND($G5,2),"") | I5: =IF(ROUND($G5,2)<0,-ROUND($G5,2),"") | J5: =IF(ROUND($G5,2)=0,0,1) -> 0 | K5: =IF($J5=0,"",SUM($J$2:$J5)) | L5: =IF($K5="","",$A5*100+$K5) | M5: =参数!$B$3 -> 7月收入
A6: 1 | B6: =助手收入!$B2 -> 2001 | C6: =助手收入!$C2 -> 柏人商城店 | D6: =科目对照收入!$B6&"" -> 医卡通 | E6: =IF(AND(ROUND($G6,2)<0,科目对照收入!$L6<>""),科目对照收入!$L6,科目对照收入!$C6)&"" -> 应收账款 | F6: =IF(AND(ROUND($G6,2)<0,科目对照收入!$L6<>""),科目对照收入!$M6,科目对照收入!$D6)&"" -> 医卡通 | G6: =IF(COUNTIFS(输入平台!$A:$A,助手收入!$X2,输入平台!$B:$B,科目对照收入!$B6)>0,ROUND(SUMIFS(输入平台!$C:$C,输入平台!$A:$A,助手收入!$X2,输入平台!$B:$B,科目对照收入!$B6),2),ROUND(海典汇总!$I$3,2)) -> 0 | H6: =IF(ROUND($G6,2)>0,ROUND($G6,2),"") | I6: =IF(ROUND($G6,2)<0,-ROUND($G6,2),"") | J6: =IF(ROUND($G6,2)=0,0,1) -> 0 | K6: =IF($J6=0,"",SUM($J$2:$J6)) | L6: =IF($K6="","",$A6*100+$K6) | M6: =参数!$B$3 -> 7月收入
A7: 1 | B7: =助手收入!$B2 -> 2001 | C7: =助手收入!$C2 -> 柏人商城店 | D7: =科目对照收入!$B7&"" -> 企健网 | E7: =IF(AND(ROUND($G7,2)<0,科目对照收入!$L7<>""),科目对照收入!$L7,科目对照收入!$C7)&"" -> 应收账款 | F7: =IF(AND(ROUND($G7,2)<0,科目对照收入!$L7<>""),科目对照收入!$M7,科目对照收入!$D7)&"" -> 企健网 | G7: =IF(COUNTIFS(输入平台!$A:$A,助手收入!$X2,输入平台!$B:$B,科目对照收入!$B7)>0,ROUND(SUMIFS(输入平台!$C:$C,输入平台!$A:$A,助手收入!$X2,输入平台!$B:$B,科目对照收入!$B7),2),ROUND(海典汇总!$J$3,2)) -> 0 | H7: =IF(ROUND($G7,2)>0,ROUND($G7,2),"") | I7: =IF(ROUND($G7,2)<0,-ROUND($G7,2),"") | J7: =IF(ROUND($G7,2)=0,0,1) -> 0 | K7: =IF($J7=0,"",SUM($J$2:$J7)) | L7: =IF($K7="","",$A7*100+$K7) | M7: =参数!$B$3 -> 7月收入
A8: 1 | B8: =助手收入!$B2 -> 2001 | C8: =助手收入!$C2 -> 柏人商城店 | D8: =科目对照收入!$B8&"" -> 亲情卡 | E8: =IF(AND(ROUND($G8,2)<0,科目对照收入!$L8<>""),科目对照收入!$L8,科目对照收入!$C8)&"" -> 应收账款 | F8: =IF(AND(ROUND($G8,2)<0,科目对照收入!$L8<>""),科目对照收入!$M8,科目对照收入!$D8)&"" -> 亲情卡 | G8: =IF(COUNTIFS(输入平台!$A:$A,助手收入!$X2,输入平台!$B:$B,科目对照收入!$B8)>0,ROUND(SUMIFS(输入平台!$C:$C,输入平台!$A:$A,助手收入!$X2,输入平台!$B:$B,科目对照收入!$B8),2),ROUND(海典汇总!$Z$3,2)) -> 0 | H8: =IF(ROUND($G8,2)>0,ROUND($G8,2),"") | I8: =IF(ROUND($G8,2)<0,-ROUND($G8,2),"") | J8: =IF(ROUND($G8,2)=0,0,1) -> 0 | K8: =IF($J8=0,"",SUM($J$2:$J8)) | L8: =IF($K8="","",$A8*100+$K8) | M8: =参数!$B$3 -> 7月收入
A9: 1 | B9: =助手收入!$B2 -> 2001 | C9: =助手收入!$C2 -> 柏人商城店 | D9: =科目对照收入!$B9&"" -> 24小时 | E9: =IF(AND(ROUND($G9,2)<0,科目对照收入!$L9<>""),科目对照收入!$L9,科目对照收入!$C9)&"" -> 应收账款 | F9: =IF(AND(ROUND($G9,2)<0,科目对照收入!$L9<>""),科目对照收入!$M9,科目对照收入!$D9)&"" -> 24小时 | G9: =IF(COUNTIFS(输入平台!$A:$A,助手收入!$X2,输入平台!$B:$B,科目对照收入!$B9)>0,ROUND(SUMIFS(输入平台!$C:$C,输入平台!$A:$A,助手收入!$X2,输入平台!$B:$B,科目对照收入!$B9),2),ROUND(海典汇总!$K$3,2)) -> 0 | H9: =IF(ROUND($G9,2)>0,ROUND($G9,2),"") | I9: =IF(ROUND($G9,2)<0,-ROUND($G9,2),"") | J9: =IF(ROUND($G9,2)=0,0,1) -> 0 | K9: =IF($J9=0,"",SUM($J$2:$J9)) | L9: =IF($K9="","",$A9*100+$K9) | M9: =参数!$B$3 -> 7月收入
A10: 1 | B10: =助手收入!$B2 -> 2001 | C10: =助手收入!$C2 -> 柏人商城店 | D10: =科目对照收入!$B10&"" -> 美团 | E10: =IF(AND(ROUND($G10,2)<0,科目对照收入!$L10<>""),科目对照收入!$L10,科目对照收入!$C10)&"" -> 应收账款 | F10: =IF(AND(ROUND($G10,2)<0,科目对照收入!$L10<>""),科目对照收入!$M10,科目对照收入!$D10)&"" -> 美团 | G10: =IF(COUNTIFS(输入平台!$A:$A,助手收入!$X2,输入平台!$B:$B,科目对照收入!$B10)>0,ROUND(SUMIFS(输入平台!$C:$C,输入平台!$A:$A,助手收入!$X2,输入平台!$B:$B,科目对照收入!$B10),2),ROUND(海典汇总!$M$3,2)) -> 47.5 | H10: =IF(ROUND($G10,2)>0,ROUND($G10,2),"") -> 47.5 | I10: =IF(ROUND($G10,2)<0,-ROUND($G10,2),"") | J10: =IF(ROUND($G10,2)=0,0,1) -> 1 | K10: =IF($J10=0,"",SUM($J$2:$J10)) -> 4 | L10: =IF($K10="","",$A10*100+$K10) -> 104 | M10: =参数!$B$3 -> 7月收入
A11: 1 | B11: =助手收入!$B2 -> 2001 | C11: =助手收入!$C2 -> 柏人商城店 | D11: =科目对照收入!$B11&"" -> 饿了么 | E11: =IF(AND(ROUND($G11,2)<0,科目对照收入!$L11<>""),科目对照收入!$L11,科目对照收入!$C11)&"" -> 应收账款 | F11: =IF(AND(ROUND($G11,2)<0,科目对照收入!$L11<>""),科目对照收入!$M11,科目对照收入!$D11)&"" -> 饿了么 | G11: =IF(COUNTIFS(输入平台!$A:$A,助手收入!$X2,输入平台!$B:$B,科目对照收入!$B11)>0,ROUND(SUMIFS(输入平台!$C:$C,输入平台!$A:$A,助手收入!$X2,输入平台!$B:$B,科目对照收入!$B11),2),ROUND(海典汇总!$N$3,2)) -> 0 | H11: =IF(ROUND($G11,2)>0,ROUND($G11,2),"") | I11: =IF(ROUND($G11,2)<0,-ROUND($G11,2),"") | J11: =IF(ROUND($G11,2)=0,0,1) -> 0 | K11: =IF($J11=0,"",SUM($J$2:$J11)) | L11: =IF($K11="","",$A11*100+$K11) | M11: =参数!$B$3 -> 7月收入
A12: 1 | B12: =助手收入!$B2 -> 2001 | C12: =助手收入!$C2 -> 柏人商城店 | D12: =科目对照收入!$B12&"" -> 京东秒送 | E12: =IF(AND(ROUND($G12,2)<0,科目对照收入!$L12<>""),科目对照收入!$L12,科目对照收入!$C12)&"" -> 应收账款 | F12: =IF(AND(ROUND($G12,2)<0,科目对照收入!$L12<>""),科目对照收入!$M12,科目对照收入!$D12)&"" -> 京东秒送 | G12: =IF(COUNTIFS(输入平台!$A:$A,助手收入!$X2,输入平台!$B:$B,科目对照收入!$B12)>0,ROUND(SUMIFS(输入平台!$C:$C,输入平台!$A:$A,助手收入!$X2,输入平台!$B:$B,科目对照收入!$B12),2),ROUND(海典汇总!$O$3,2)) -> 0 | H12: =IF(ROUND($G12,2)>0,ROUND($G12,2),"") | I12: =IF(ROUND($G12,2)<0,-ROUND($G12,2),"") | J12: =IF(ROUND($G12,2)=0,0,1) -> 0 | K12: =IF($J12=0,"",SUM($J$2:$J12)) | L12: =IF($K12="","",$A12*100+$K12) | M12: =参数!$B$3 -> 7月收入
A13: 1 | B13: =助手收入!$B2 -> 2001 | C13: =助手收入!$C2 -> 柏人商城店 | D13: =科目对照收入!$B13&"" -> 银联 | E13: =IF(AND(ROUND($G13,2)<0,科目对照收入!$L13<>""),科目对照收入!$L13,科目对照收入!$C13)&"" -> 应收账款 | F13: =IF(AND(ROUND($G13,2)<0,科目对照收入!$L13<>""),科目对照收入!$M13,科目对照收入!$D13)&"" -> 银联 | G13: =IF(COUNTIFS(输入平台!$A:$A,助手收入!$X2,输入平台!$B:$B,科目对照收入!$B13)>0,ROUND(SUMIFS(输入平台!$C:$C,输入平台!$A:$A,助手收入!$X2,输入平台!$B:$B,科目对照收入!$B13),2),ROUND(海典汇总!$V$3,2)) -> 0 | H13: =IF(ROUND($G13,2)>0,ROUND($G13,2),"") | I13: =IF(ROUND($G13,2)<0,-ROUND($G13,2),"") | J13: =IF(ROUND($G13,2)=0,0,1) -> 0 | K13: =IF($J13=0,"",SUM($J$2:$J13)) | L13: =IF($K13="","",$A13*100+$K13) | M13: =参数!$B$3 -> 7月收入
A14: 1 | B14: =助手收入!$B2 -> 2001 | C14: =助手收入!$C2 -> 柏人商城店 | D14: =科目对照收入!$B14&"" -> 小镇外卖 | E14: =IF(AND(ROUND($G14,2)<0,科目对照收入!$L14<>""),科目对照收入!$L14,科目对照收入!$C14)&"" -> 应收账款 | F14: =IF(AND(ROUND($G14,2)<0,科目对照收入!$L14<>""),科目对照收入!$M14,科目对照收入!$D14)&"" -> 小镇外卖 | G14: =IF(COUNTIFS(输入平台!$A:$A,助手收入!$X2,输入平台!$B:$B,科目对照收入!$B14)>0,ROUND(SUMIFS(输入平台!$C:$C,输入平台!$A:$A,助手收入!$X2,输入平台!$B:$B,科目对照收入!$B14),2),ROUND(海典汇总!$AC$3,2)) -> 0 | H14: =IF(ROUND($G14,2)>0,ROUND($G14,2),"") | I14: =IF(ROUND($G14,2)<0,-ROUND($G14,2),"") | J14: =IF(ROUND($G14,2)=0,0,1) -> 0 | K14: =IF($J14=0,"",SUM($J$2:$J14)) | L14: =IF($K14="","",$A14*100+$K14) | M14: =参数!$B$3 -> 7月收入
A15: 1 | B15: =助手收入!$B2 -> 2001 | C15: =助手收入!$C2 -> 柏人商城店 | D15: =科目对照收入!$B15&"" -> OMS线上支付 | E15: =IF(AND(ROUND($G15,2)<0,科目对照收入!$L15<>""),科目对照收入!$L15,科目对照收入!$C15)&"" -> 应收账款 | F15: =IF(AND(ROUND($G15,2)<0,科目对照收入!$L15<>""),科目对照收入!$M15,科目对照收入!$D15)&"" -> OMS线上 | G15: =IF(COUNTIFS(输入平台!$A:$A,助手收入!$X2,输入平台!$B:$B,科目对照收入!$B15)>0,ROUND(SUMIFS(输入平台!$C:$C,输入平台!$A:$A,助手收入!$X2,输入平台!$B:$B,科目对照收入!$B15),2),ROUND(海典汇总!$L$3,2)) -> 0 | H15: =IF(ROUND($G15,2)>0,ROUND($G15,2),"") | I15: =IF(ROUND($G15,2)<0,-ROUND($G15,2),"") | J15: =IF(ROUND($G15,2)=0,0,1) -> 0 | K15: =IF($J15=0,"",SUM($J$2:$J15)) | L15: =IF($K15="","",$A15*100+$K15) | M15: =参数!$B$3 -> 7月收入
A16: 1 | B16: =助手收入!$B2 -> 2001 | C16: =助手收入!$C2 -> 柏人商城店 | D16: =科目对照收入!$B16&"" -> 平安药卡 | E16: =IF(AND(ROUND($G16,2)<0,科目对照收入!$L16<>""),科目对照收入!$L16,科目对照收入!$C16)&"" -> 应收账款 | F16: =IF(AND(ROUND($G16,2)<0,科目对照收入!$L16<>""),科目对照收入!$M16,科目对照收入!$D16)&"" -> 平安 | G16: =IF(COUNTIFS(输入平台!$A:$A,助手收入!$X2,输入平台!$B:$B,科目对照收入!$B16)>0,ROUND(SUMIFS(输入平台!$C:$C,输入平台!$A:$A,助手收入!$X2,输入平台!$B:$B,科目对照收入!$B16),2),ROUND(海典汇总!$AB$3,2)) -> 0 | H16: =IF(ROUND($G16,2)>0,ROUND($G16,2),"") | I16: =IF(ROUND($G16,2)<0,-ROUND($G16,2),"") | J16: =IF(ROUND($G16,2)=0,0,1) -> 0 | K16: =IF($J16=0,"",SUM($J$2:$J16)) | L16: =IF($K16="","",$A16*100+$K16) | M16: =参数!$B$3 -> 7月收入
A17: 1 | B17: =助手收入!$B2 -> 2001 | C17: =助手收入!$C2 -> 柏人商城店 | D17: =科目对照收入!$B17&"" -> 储值卡 | E17: =IF(AND(ROUND($G17,2)<0,科目对照收入!$L17<>""),科目对照收入!$L17,科目对照收入!$C17)&"" -> 其他应收款 | F17: =IF(AND(ROUND($G17,2)<0,科目对照收入!$L17<>""),科目对照收入!$M17,科目对照收入!$D17)&"" -> 储值卡 | G17: =ROUND(海典汇总!$Q$3,2) -> 0 | H17: =IF(ROUND($G17,2)>0,ROUND($G17,2),"") | I17: =IF(ROUND($G17,2)<0,-ROUND($G17,2),"") | J17: =IF(ROUND($G17,2)=0,0,1) -> 0 | K17: =IF($J17=0,"",SUM($J$2:$J17)) | L17: =IF($K17="","",$A17*100+$K17) | M17: =参数!$B$3 -> 7月收入
A18: 1 | B18: =助手收入!$B2 -> 2001 | C18: =助手收入!$C2 -> 柏人商城店 | D18: =科目对照收入!$B18&"" -> 会员零钱包 | E18: =IF(AND(ROUND($G18,2)<0,科目对照收入!$L18<>""),科目对照收入!$L18,科目对照收入!$C18)&"" -> 其他应收款 | F18: =IF(AND(ROUND($G18,2)<0,科目对照收入!$L18<>""),科目对照收入!$M18,科目对照收入!$D18)&"" -> 会员零钱包 | G18: =ROUND(海典汇总!$P$3,2) -> 0 | H18: =IF(ROUND($G18,2)>0,ROUND($G18,2),"") | I18: =IF(ROUND($G18,2)<0,-ROUND($G18,2),"") | J18: =IF(ROUND($G18,2)=0,0,1) -> 0 | K18: =IF($J18=0,"",SUM($J$2:$J18)) | L18: =IF($K18="","",$A18*100+$K18) | M18: =参数!$B$3 -> 7月收入
A19: 1 | B19: =助手收入!$B2 -> 2001 | C19: =助手收入!$C2 -> 柏人商城店 | D19: =科目对照收入!$B19&"" -> 促销费 | E19: =IF(AND(ROUND($G19,2)<0,科目对照收入!$L19<>""),科目对照收入!$L19,科目对照收入!$C19)&"" -> 销售费用 | F19: =IF(AND(ROUND($G19,2)<0,科目对照收入!$L19<>""),科目对照收入!$M19,科目对照收入!$D19)&"" -> 促销费 | G19: =ROUND(海典汇总!$U$3+海典汇总!$T$3+海典汇总!$S$3,2) -> 448.72 | H19: =IF(ROUND($G19,2)>0,ROUND($G19,2),"") -> 448.72 | I19: =IF(ROUND($G19,2)<0,-ROUND($G19,2),"") | J19: =IF(ROUND($G19,2)=0,0,1) -> 1 | K19: =IF($J19=0,"",SUM($J$2:$J19)) -> 5 | L19: =IF($K19="","",$A19*100+$K19) -> 105 | M19: =参数!$B$3 -> 7月收入
A20: 1 | B20: =助手收入!$B2 -> 2001 | C20: =助手收入!$C2 -> 柏人商城店 | D20: =科目对照收入!$B20&"" -> 积分 | E20: =IF(AND(ROUND($G20,2)<0,科目对照收入!$L20<>""),科目对照收入!$L20,科目对照收入!$C20)&"" -> 销售费用 | F20: =IF(AND(ROUND($G20,2)<0,科目对照收入!$L20<>""),科目对照收入!$M20,科目对照收入!$D20)&"" -> 积分 | G20: =ROUND(海典汇总!$R$3,2) -> 0 | H20: =IF(ROUND($G20,2)>0,ROUND($G20,2),"") | I20: =IF(ROUND($G20,2)<0,-ROUND($G20,2),"") | J20: =IF(ROUND($G20,2)=0,0,1) -> 0 | K20: =IF($J20=0,"",SUM($J$2:$J20)) | L20: =IF($K20="","",$A20*100+$K20) | M20: =参数!$B$3 -> 7月收入
A21: 1 | B21: =助手收入!$B2 -> 2001 | C21: =助手收入!$C2 -> 柏人商城店 | D21: =科目对照收入!$B21&"" -> 手续费 | E21: =IF(AND(ROUND($G21,2)<0,科目对照收入!$L21<>""),科目对照收入!$L21,科目对照收入!$C21)&"" -> 财务费用 | F21: =IF(AND(ROUND($G21,2)<0,科目对照收入!$L21<>""),科目对照收入!$M21,科目对照收入!$D21)&"" -> 手续费 | G21: =ROUND(SUMIFS(输入聚合!$D:$D,输入聚合!$A:$A,助手收入!$X2),2) -> 61.48 | H21: =IF(ROUND($G21,2)>0,ROUND($G21,2),"") -> 61.48 | I21: =IF(ROUND($G21,2)<0,-ROUND($G21,2),"") | J21: =IF(ROUND($G21,2)=0,0,1) -> 1 | K21: =IF($J21=0,"",SUM($J$2:$J21)) -> 6 | L21: =IF($K21="","",$A21*100+$K21) -> 106 | M21: =参数!$B$3 -> 7月收入
A22: 1 | B22: =助手收入!$B2 -> 2001 | C22: =助手收入!$C2 -> 柏人商城店 | D22: =科目对照收入!$B22&"" -> 主营业务收入 | E22: =IF(AND(ROUND($G22,2)<0,科目对照收入!$L22<>""),科目对照收入!$L22,科目对照收入!$C22)&"" -> 主营业务收入 | F22: =IF(AND(ROUND($G22,2)<0,科目对照收入!$L22<>""),科目对照收入!$M22,科目对照收入!$D22)&"" | G22: =-ROUND(助手收入!$G2,2) -> -36409.51 | H22: =IF(ROUND($G22,2)>0,ROUND($G22,2),"") | I22: =IF(ROUND($G22,2)<0,-ROUND($G22,2),"") -> 36409.51 | J22: =IF(ROUND($G22,2)=0,0,1) -> 1 | K22: =IF($J22=0,"",SUM($J$2:$J22)) -> 7 | L22: =IF($K22="","",$A22*100+$K22) -> 107 | M22: =参数!$B$3 -> 7月收入
A23: 1 | B23: =助手收入!$B2 -> 2001 | C23: =助手收入!$C2 -> 柏人商城店 | D23: =科目对照收入!$B23&"" -> 营业外收入 | E23: =IF(AND(ROUND($G23,2)<0,科目对照收入!$L23<>""),科目对照收入!$L23,科目对照收入!$C23)&"" -> 营业外收入 | F23: =IF(AND(ROUND($G23,2)<0,科目对照收入!$L23<>""),科目对照收入!$M23,科目对照收入!$D23)&"" | G23: =-ROUND(助手收入!$J2,2) -> 0 | H23: =IF(ROUND($G23,2)>0,ROUND($G23,2),"") | I23: =IF(ROUND($G23,2)<0,-ROUND($G23,2),"") | J23: =IF(ROUND($G23,2)=0,0,1) -> 0 | K23: =IF($J23=0,"",SUM($J$2:$J23)) | L23: =IF($K23="","",$A23*100+$K23) | M23: =参数!$B$3 -> 7月收入
A24: 2 | B24: =助手收入!$B3 -> 2002 | C24: =助手收入!$C3 -> 新隆店 | D24: =科目对照收入!$B2&"" -> 库存现金 | E24: =IF(AND(ROUND($G24,2)<0,科目对照收入!$L2<>""),科目对照收入!$L2,科目对照收入!$C2)&"" -> 库存现金 | F24: =IF(AND(ROUND($G24,2)<0,科目对照收入!$L2<>""),科目对照收入!$M2,科目对照收入!$D2)&"" | G24: =助手收入!$I3 -> 290970.85 | H24: =IF(ROUND($G24,2)>0,ROUND($G24,2),"") -> 290970.85 | I24: =IF(ROUND($G24,2)<0,-ROUND($G24,2),"") | J24: =IF(ROUND($G24,2)=0,0,1) -> 1 | K24: =IF($J24=0,"",SUM($J$24:$J24)) -> 1 | L24: =IF($K24="","",$A24*100+$K24) -> 201 | M24: =参数!$B$3 -> 7月收入
A25: 2 | B25: =助手收入!$B3 -> 2002 | C25: =助手收入!$C3 -> 新隆店 | D25: =科目对照收入!$B3&"" -> 聚合支付 | E25: =IF(AND(ROUND($G25,2)<0,科目对照收入!$L3<>""),科目对照收入!$L3,科目对照收入!$C3)&"" -> 应收账款 | F25: =IF(AND(ROUND($G25,2)<0,科目对照收入!$L3<>""),科目对照收入!$M3,科目对照收入!$D3)&"" -> 聚合支付 | G25: =ROUND(SUMIFS(输入聚合!$C:$C,输入聚合!$A:$A,助手收入!$X3)-SUMIFS(输入聚合!$D:$D,输入聚合!$A:$A,助手收入!$X3),2) -> 102925.1 | H25: =IF(ROUND($G25,2)>0,ROUND($G25,2),"") -> 102925.1 | I25: =IF(ROUND($G25,2)<0,-ROUND($G25,2),"") | J25: =IF(ROUND($G25,2)=0,0,1) -> 1 | K25: =IF($J25=0,"",SUM($J$24:$J25)) -> 2 | L25: =IF($K25="","",$A25*100+$K25) -> 202 | M25: =参数!$B$3 -> 7月收入
A26: 2 | B26: =助手收入!$B3 -> 2002 | C26: =助手收入!$C3 -> 新隆店 | D26: =科目对照收入!$B4&"" -> 医保 | E26: =IF(AND(ROUND($G26,2)<0,科目对照收入!$L4<>""),科目对照收入!$L4,科目对照收入!$C4)&"" -> 应收账款 | F26: =IF(AND(ROUND($G26,2)<0,科目对照收入!$L4<>""),科目对照收入!$M4,科目对照收入!$D4)&"" -> 医保 | G26: =IF(COUNTIFS(输入平台!$A:$A,助手收入!$X3,输入平台!$B:$B,科目对照收入!$B4)>0,ROUND(SUMIFS(输入平台!$C:$C,输入平台!$A:$A,助手收入!$X3,输入平台!$B:$B,科目对照收入!$B4),2),ROUND(海典汇总!$F$4+海典汇总!$G$4,2)) -> 45021.37 | H26: =IF(ROUND($G26,2)>0,ROUND($G26,2),"") -> 45021.37 | I26: =IF(ROUND($G26,2)<0,-ROUND($G26,2),"") | J26: =IF(ROUND($G26,2)=0,0,1) -> 1 | K26: =IF($J26=0,"",SUM($J$24:$J26)) -> 3 | L26: =IF($K26="","",$A26*100+$K26) -> 203 | M26: =参数!$B$3 -> 7月收入
A27: 2 | B27: =助手收入!$B3 -> 2002 | C27: =助手收入!$C3 -> 新隆店 | D27: =科目对照收入!$B5&"" -> 健e卡 | E27: =IF(AND(ROUND($G27,2)<0,科目对照收入!$L5<>""),科目对照收入!$L5,科目对照收入!$C5)&"" -> 应收账款 | F27: =IF(AND(ROUND($G27,2)<0,科目对照收入!$L5<>""),科目对照收入!$M5,科目对照收入!$D5)&"" -> 健e卡 | G27: =IF(COUNTIFS(输入平台!$A:$A,助手收入!$X3,输入平台!$B:$B,科目对照收入!$B5)>0,ROUND(SUMIFS(输入平台!$C:$C,输入平台!$A:$A,助手收入!$X3,输入平台!$B:$B,科目对照收入!$B5),2),ROUND(海典汇总!$H$4,2)) -> 0 | H27: =IF(ROUND($G27,2)>0,ROUND($G27,2),"") | I27: =IF(ROUND($G27,2)<0,-ROUND($G27,2),"") | J27: =IF(ROUND($G27,2)=0,0,1) -> 0 | K27: =IF($J27=0,"",SUM($J$24:$J27)) | L27: =IF($K27="","",$A27*100+$K27) | M27: =参数!$B$3 -> 7月收入
A28: 2 | B28: =助手收入!$B3 -> 2002 | C28: =助手收入!$C3 -> 新隆店 | D28: =科目对照收入!$B6&"" -> 医卡通 | E28: =IF(AND(ROUND($G28,2)<0,科目对照收入!$L6<>""),科目对照收入!$L6,科目对照收入!$C6)&"" -> 应收账款 | F28: =IF(AND(ROUND($G28,2)<0,科目对照收入!$L6<>""),科目对照收入!$M6,科目对照收入!$D6)&"" -> 医卡通 | G28: =IF(COUNTIFS(输入平台!$A:$A,助手收入!$X3,输入平台!$B:$B,科目对照收入!$B6)>0,ROUND(SUMIFS(输入平台!$C:$C,输入平台!$A:$A,助手收入!$X3,输入平台!$B:$B,科目对照收入!$B6),2),ROUND(海典汇总!$I$4,2)) -> 0 | H28: =IF(ROUND($G28,2)>0,ROUND($G28,2),"") | I28: =IF(ROUND($G28,2)<0,-ROUND($G28,2),"") | J28: =IF(ROUND($G28,2)=0,0,1) -> 0 | K28: =IF($J28=0,"",SUM($J$24:$J28)) | L28: =IF($K28="","",$A28*100+$K28) | M28: =参数!$B$3 -> 7月收入
A29: 2 | B29: =助手收入!$B3 -> 2002 | C29: =助手收入!$C3 -> 新隆店 | D29: =科目对照收入!$B7&"" -> 企健网 | E29: =IF(AND(ROUND($G29,2)<0,科目对照收入!$L7<>""),科目对照收入!$L7,科目对照收入!$C7)&"" -> 应收账款 | F29: =IF(AND(ROUND($G29,2)<0,科目对照收入!$L7<>""),科目对照收入!$M7,科目对照收入!$D7)&"" -> 企健网 | G29: =IF(COUNTIFS(输入平台!$A:$A,助手收入!$X3,输入平台!$B:$B,科目对照收入!$B7)>0,ROUND(SUMIFS(输入平台!$C:$C,输入平台!$A:$A,助手收入!$X3,输入平台!$B:$B,科目对照收入!$B7),2),ROUND(海典汇总!$J$4,2)) -> 0 | H29: =IF(ROUND($G29,2)>0,ROUND($G29,2),"") | I29: =IF(ROUND($G29,2)<0,-ROUND($G29,2),"") | J29: =IF(ROUND($G29,2)=0,0,1) -> 0 | K29: =IF($J29=0,"",SUM($J$24:$J29)) | L29: =IF($K29="","",$A29*100+$K29) | M29: =参数!$B$3 -> 7月收入
A30: 2 | B30: =助手收入!$B3 -> 2002 | C30: =助手收入!$C3 -> 新隆店 | D30: =科目对照收入!$B8&"" -> 亲情卡 | E30: =IF(AND(ROUND($G30,2)<0,科目对照收入!$L8<>""),科目对照收入!$L8,科目对照收入!$C8)&"" -> 应收账款 | F30: =IF(AND(ROUND($G30,2)<0,科目对照收入!$L8<>""),科目对照收入!$M8,科目对照收入!$D8)&"" -> 亲情卡 | G30: =IF(COUNTIFS(输入平台!$A:$A,助手收入!$X3,输入平台!$B:$B,科目对照收入!$B8)>0,ROUND(SUMIFS(输入平台!$C:$C,输入平台!$A:$A,助手收入!$X3,输入平台!$B:$B,科目对照收入!$B8),2),ROUND(海典汇总!$Z$4,2)) -> 0 | H30: =IF(ROUND($G30,2)>0,ROUND($G30,2),"") | I30: =IF(ROUND($G30,2)<0,-ROUND($G30,2),"") | J30: =IF(ROUND($G30,2)=0,0,1) -> 0 | K30: =IF($J30=0,"",SUM($J$24:$J30)) | L30: =IF($K30="","",$A30*100+$K30) | M30: =参数!$B$3 -> 7月收入
A31: 2 | B31: =助手收入!$B3 -> 2002 | C31: =助手收入!$C3 -> 新隆店 | D31: =科目对照收入!$B9&"" -> 24小时 | E31: =IF(AND(ROUND($G31,2)<0,科目对照收入!$L9<>""),科目对照收入!$L9,科目对照收入!$C9)&"" -> 应收账款 | F31: =IF(AND(ROUND($G31,2)<0,科目对照收入!$L9<>""),科目对照收入!$M9,科目对照收入!$D9)&"" -> 24小时 | G31: =IF(COUNTIFS(输入平台!$A:$A,助手收入!$X3,输入平台!$B:$B,科目对照收入!$B9)>0,ROUND(SUMIFS(输入平台!$C:$C,输入平台!$A:$A,助手收入!$X3,输入平台!$B:$B,科目对照收入!$B9),2),ROUND(海典汇总!$K$4,2)) -> 0 | H31: =IF(ROUND($G31,2)>0,ROUND($G31,2),"") | I31: =IF(ROUND($G31,2)<0,-ROUND($G31,2),"") | J31: =IF(ROUND($G31,2)=0,0,1) -> 0 | K31: =IF($J31=0,"",SUM($J$24:$J31)) | L31: =IF($K31="","",$A31*100+$K31) | M31: =参数!$B$3 -> 7月收入
A32: 2 | B32: =助手收入!$B3 -> 2002 | C32: =助手收入!$C3 -> 新隆店 | D32: =科目对照收入!$B10&"" -> 美团 | E32: =IF(AND(ROUND($G32,2)<0,科目对照收入!$L10<>""),科目对照收入!$L10,科目对照收入!$C10)&"" -> 应收账款 | F32: =IF(AND(ROUND($G32,2)<0,科目对照收入!$L10<>""),科目对照收入!$M10,科目对照收入!$D10)&"" -> 美团 | G32: =IF(COUNTIFS(输入平台!$A:$A,助手收入!$X3,输入平台!$B:$B,科目对照收入!$B10)>0,ROUND(SUMIFS(输入平台!$C:$C,输入平台!$A:$A,助手收入!$X3,输入平台!$B:$B,科目对照收入!$B10),2),ROUND(海典汇总!$M$4,2)) -> 0 | H32: =IF(ROUND($G32,2)>0,ROUND($G32,2),"") | I32: =IF(ROUND($G32,2)<0,-ROUND($G32,2),"") | J32: =IF(ROUND($G32,2)=0,0,1) -> 0 | K32: =IF($J32=0,"",SUM($J$24:$J32)) | L32: =IF($K32="","",$A32*100+$K32) | M32: =参数!$B$3 -> 7月收入
A33: 2 | B33: =助手收入!$B3 -> 2002 | C33: =助手收入!$C3 -> 新隆店 | D33: =科目对照收入!$B11&"" -> 饿了么 | E33: =IF(AND(ROUND($G33,2)<0,科目对照收入!$L11<>""),科目对照收入!$L11,科目对照收入!$C11)&"" -> 应收账款 | F33: =IF(AND(ROUND($G33,2)<0,科目对照收入!$L11<>""),科目对照收入!$M11,科目对照收入!$D11)&"" -> 饿了么 | G33: =IF(COUNTIFS(输入平台!$A:$A,助手收入!$X3,输入平台!$B:$B,科目对照收入!$B11)>0,ROUND(SUMIFS(输入平台!$C:$C,输入平台!$A:$A,助手收入!$X3,输入平台!$B:$B,科目对照收入!$B11),2),ROUND(海典汇总!$N$4,2)) -> 0 | H33: =IF(ROUND($G33,2)>0,ROUND($G33,2),"") | I33: =IF(ROUND($G33,2)<0,-ROUND($G33,2),"") | J33: =IF(ROUND($G33,2)=0,0,1) -> 0 | K33: =IF($J33=0,"",SUM($J$24:$J33)) | L33: =IF($K33="","",$A33*100+$K33) | M33: =参数!$B$3 -> 7月收入
A34: 2 | B34: =助手收入!$B3 -> 2002 | C34: =助手收入!$C3 -> 新隆店 | D34: =科目对照收入!$B12&"" -> 京东秒送 | E34: =IF(AND(ROUND($G34,2)<0,科目对照收入!$L12<>""),科目对照收入!$L12,科目对照收入!$C12)&"" -> 应收账款 | F34: =IF(AND(ROUND($G34,2)<0,科目对照收入!$L12<>""),科目对照收入!$M12,科目对照收入!$D12)&"" -> 京东秒送 | G34: =IF(COUNTIFS(输入平台!$A:$A,助手收入!$X3,输入平台!$B:$B,科目对照收入!$B12)>0,ROUND(SUMIFS(输入平台!$C:$C,输入平台!$A:$A,助手收入!$X3,输入平台!$B:$B,科目对照收入!$B12),2),ROUND(海典汇总!$O$4,2)) -> 0 | H34: =IF(ROUND($G34,2)>0,ROUND($G34,2),"") | I34: =IF(ROUND($G34,2)<0,-ROUND($G34,2),"") | J34: =IF(ROUND($G34,2)=0,0,1) -> 0 | K34: =IF($J34=0,"",SUM($J$24:$J34)) | L34: =IF($K34="","",$A34*100+$K34) | M34: =参数!$B$3 -> 7月收入
A35: 2 | B35: =助手收入!$B3 -> 2002 | C35: =助手收入!$C3 -> 新隆店 | D35: =科目对照收入!$B13&"" -> 银联 | E35: =IF(AND(ROUND($G35,2)<0,科目对照收入!$L13<>""),科目对照收入!$L13,科目对照收入!$C13)&"" -> 应收账款 | F35: =IF(AND(ROUND($G35,2)<0,科目对照收入!$L13<>""),科目对照收入!$M13,科目对照收入!$D13)&"" -> 银联 | G35: =IF(COUNTIFS(输入平台!$A:$A,助手收入!$X3,输入平台!$B:$B,科目对照收入!$B13)>0,ROUND(SUMIFS(输入平台!$C:$C,输入平台!$A:$A,助手收入!$X3,输入平台!$B:$B,科目对照收入!$B13),2),ROUND(海典汇总!$V$4,2)) -> 0 | H35: =IF(ROUND($G35,2)>0,ROUND($G35,2),"") | I35: =IF(ROUND($G35,2)<0,-ROUND($G35,2),"") | J35: =IF(ROUND($G35,2)=0,0,1) -> 0 | K35: =IF($J35=0,"",SUM($J$24:$J35)) | L35: =IF($K35="","",$A35*100+$K35) | M35: =参数!$B$3 -> 7月收入
A36: 2 | B36: =助手收入!$B3 -> 2002 | C36: =助手收入!$C3 -> 新隆店 | D36: =科目对照收入!$B14&"" -> 小镇外卖 | E36: =IF(AND(ROUND($G36,2)<0,科目对照收入!$L14<>""),科目对照收入!$L14,科目对照收入!$C14)&"" -> 应收账款 | F36: =IF(AND(ROUND($G36,2)<0,科目对照收入!$L14<>""),科目对照收入!$M14,科目对照收入!$D14)&"" -> 小镇外卖 | G36: =IF(COUNTIFS(输入平台!$A:$A,助手收入!$X3,输入平台!$B:$B,科目对照收入!$B14)>0,ROUND(SUMIFS(输入平台!$C:$C,输入平台!$A:$A,助手收入!$X3,输入平台!$B:$B,科目对照收入!$B14),2),ROUND(海典汇总!$AC$4,2)) -> 0 | H36: =IF(ROUND($G36,2)>0,ROUND($G36,2),"") | I36: =IF(ROUND($G36,2)<0,-ROUND($G36,2),"") | J36: =IF(ROUND($G36,2)=0,0,1) -> 0 | K36: =IF($J36=0,"",SUM($J$24:$J36)) | L36: =IF($K36="","",$A36*100+$K36) | M36: =参数!$B$3 -> 7月收入
A37: 2 | B37: =助手收入!$B3 -> 2002 | C37: =助手收入!$C3 -> 新隆店 | D37: =科目对照收入!$B15&"" -> OMS线上支付 | E37: =IF(AND(ROUND($G37,2)<0,科目对照收入!$L15<>""),科目对照收入!$L15,科目对照收入!$C15)&"" -> 应收账款 | F37: =IF(AND(ROUND($G37,2)<0,科目对照收入!$L15<>""),科目对照收入!$M15,科目对照收入!$D15)&"" -> OMS线上 | G37: =IF(COUNTIFS(输入平台!$A:$A,助手收入!$X3,输入平台!$B:$B,科目对照收入!$B15)>0,ROUND(SUMIFS(输入平台!$C:$C,输入平台!$A:$A,助手收入!$X3,输入平台!$B:$B,科目对照收入!$B15),2),ROUND(海典汇总!$L$4,2)) -> 0 | H37: =IF(ROUND($G37,2)>0,ROUND($G37,2),"") | I37: =IF(ROUND($G37,2)<0,-ROUND($G37,2),"") | J37: =IF(ROUND($G37,2)=0,0,1) -> 0 | K37: =IF($J37=0,"",SUM($J$24:$J37)) | L37: =IF($K37="","",$A37*100+$K37) | M37: =参数!$B$3 -> 7月收入
A38: 2 | B38: =助手收入!$B3 -> 2002 | C38: =助手收入!$C3 -> 新隆店 | D38: =科目对照收入!$B16&"" -> 平安药卡 | E38: =IF(AND(ROUND($G38,2)<0,科目对照收入!$L16<>""),科目对照收入!$L16,科目对照收入!$C16)&"" -> 应收账款 | F38: =IF(AND(ROUND($G38,2)<0,科目对照收入!$L16<>""),科目对照收入!$M16,科目对照收入!$D16)&"" -> 平安 | G38: =IF(COUNTIFS(输入平台!$A:$A,助手收入!$X3,输入平台!$B:$B,科目对照收入!$B16)>0,ROUND(SUMIFS(输入平台!$C:$C,输入平台!$A:$A,助手收入!$X3,输入平台!$B:$B,科目对照收入!$B16),2),ROUND(海典汇总!$AB$4,2)) -> 0 | H38: =IF(ROUND($G38,2)>0,ROUND($G38,2),"") | I38: =IF(ROUND($G38,2)<0,-ROUND($G38,2),"") | J38: =IF(ROUND($G38,2)=0,0,1) -> 0 | K38: =IF($J38=0,"",SUM($J$24:$J38)) | L38: =IF($K38="","",$A38*100+$K38) | M38: =参数!$B$3 -> 7月收入
A39: 2 | B39: =助手收入!$B3 -> 2002 | C39: =助手收入!$C3 -> 新隆店 | D39: =科目对照收入!$B17&"" -> 储值卡 | E39: =IF(AND(ROUND($G39,2)<0,科目对照收入!$L17<>""),科目对照收入!$L17,科目对照收入!$C17)&"" -> 其他应收款 | F39: =IF(AND(ROUND($G39,2)<0,科目对照收入!$L17<>""),科目对照收入!$M17,科目对照收入!$D17)&"" -> 储值卡 | G39: =ROUND(海典汇总!$Q$4,2) -> 2656.85 | H39: =IF(ROUND($G39,2)>0,ROUND($G39,2),"") -> 2656.85 | I39: =IF(ROUND($G39,2)<0,-ROUND($G39,2),"") | J39: =IF(ROUND($G39,2)=0,0,1) -> 1 | K39: =IF($J39=0,"",SUM($J$24:$J39)) -> 4 | L39: =IF($K39="","",$A39*100+$K39) -> 204 | M39: =参数!$B$3 -> 7月收入
A40: 2 | B40: =助手收入!$B3 -> 2002 | C40: =助手收入!$C3 -> 新隆店 | D40: =科目对照收入!$B18&"" -> 会员零钱包 | E40: =IF(AND(ROUND($G40,2)<0,科目对照收入!$L18<>""),科目对照收入!$L18,科目对照收入!$C18)&"" -> 其他应收款 | F40: =IF(AND(ROUND($G40,2)<0,科目对照收入!$L18<>""),科目对照收入!$M18,科目对照收入!$D18)&"" -> 会员零钱包 | G40: =ROUND(海典汇总!$P$4,2) -> 0 | H40: =IF(ROUND($G40,2)>0,ROUND($G40,2),"") | I40: =IF(ROUND($G40,2)<0,-ROUND($G40,2),"") | J40: =IF(ROUND($G40,2)=0,0,1) -> 0 | K40: =IF($J40=0,"",SUM($J$24:$J40)) | L40: =IF($K40="","",$A40*100+$K40) | M40: =参数!$B$3 -> 7月收入
A41: 2 | B41: =助手收入!$B3 -> 2002 | C41: =助手收入!$C3 -> 新隆店 | D41: =科目对照收入!$B19&"" -> 促销费 | E41: =IF(AND(ROUND($G41,2)<0,科目对照收入!$L19<>""),科目对照收入!$L19,科目对照收入!$C19)&"" -> 销售费用 | F41: =IF(AND(ROUND($G41,2)<0,科目对照收入!$L19<>""),科目对照收入!$M19,科目对照收入!$D19)&"" -> 促销费 | G41: =ROUND(海典汇总!$U$4+海典汇总!$T$4+海典汇总!$S$4,2) -> 2268.63 | H41: =IF(ROUND($G41,2)>0,ROUND($G41,2),"") -> 2268.63 | I41: =IF(ROUND($G41,2)<0,-ROUND($G41,2),"") | J41: =IF(ROUND($G41,2)=0,0,1) -> 1 | K41: =IF($J41=0,"",SUM($J$24:$J41)) -> 5 | L41: =IF($K41="","",$A41*100+$K41) -> 205 | M41: =参数!$B$3 -> 7月收入
A42: 2 | B42: =助手收入!$B3 -> 2002 | C42: =助手收入!$C3 -> 新隆店 | D42: =科目对照收入!$B20&"" -> 积分 | E42: =IF(AND(ROUND($G42,2)<0,科目对照收入!$L20<>""),科目对照收入!$L20,科目对照收入!$C20)&"" -> 销售费用 | F42: =IF(AND(ROUND($G42,2)<0,科目对照收入!$L20<>""),科目对照收入!$M20,科目对照收入!$D20)&"" -> 积分 | G42: =ROUND(海典汇总!$R$4,2) -> 0 | H42: =IF(ROUND($G42,2)>0,ROUND($G42,2),"") | I42: =IF(ROUND($G42,2)<0,-ROUND($G42,2),"") | J42: =IF(ROUND($G42,2)=0,0,1) -> 0 | K42: =IF($J42=0,"",SUM($J$24:$J42)) | L42: =IF($K42="","",$A42*100+$K42) | M42: =参数!$B$3 -> 7月收入
A43: 2 | B43: =助手收入!$B3 -> 2002 | C43: =助手收入!$C3 -> 新隆店 | D43: =科目对照收入!$B21&"" -> 手续费 | E43: =IF(AND(ROUND($G43,2)<0,科目对照收入!$L21<>""),科目对照收入!$L21,科目对照收入!$C21)&"" -> 财务费用 | F43: =IF(AND(ROUND($G43,2)<0,科目对照收入!$L21<>""),科目对照收入!$M21,科目对照收入!$D21)&"" -> 手续费 | G43: =ROUND(SUMIFS(输入聚合!$D:$D,输入聚合!$A:$A,助手收入!$X3),2) -> 278.65 | H43: =IF(ROUND($G43,2)>0,ROUND($G43,2),"") -> 278.65 | I43: =IF(ROUND($G43,2)<0,-ROUND($G43,2),"") | J43: =IF(ROUND($G43,2)=0,0,1) -> 1 | K43: =IF($J43=0,"",SUM($J$24:$J43)) -> 6 | L43: =IF($K43="","",$A43*100+$K43) -> 206 | M43: =参数!$B$3 -> 7月收入
A44: 2 | B44: =助手收入!$B3 -> 2002 | C44: =助手收入!$C3 -> 新隆店 | D44: =科目对照收入!$B22&"" -> 主营业务收入 | E44: =IF(AND(ROUND($G44,2)<0,科目对照收入!$L22<>""),科目对照收入!$L22,科目对照收入!$C22)&"" -> 主营业务收入 | F44: =IF(AND(ROUND($G44,2)<0,科目对照收入!$L22<>""),科目对照收入!$M22,科目对照收入!$D22)&"" | G44: =-ROUND(助手收入!$G3,2) -> -444121.45 | H44: =IF(ROUND($G44,2)>0,ROUND($G44,2),"") | I44: =IF(ROUND($G44,2)<0,-ROUND($G44,2),"") -> 444121.45 | J44: =IF(ROUND($G44,2)=0,0,1) -> 1 | K44: =IF($J44=0,"",SUM($J$24:$J44)) -> 7 | L44: =IF($K44="","",$A44*100+$K44) -> 207 | M44: =参数!$B$3 -> 7月收入
A45: 2 | B45: =助手收入!$B3 -> 2002 | C45: =助手收入!$C3 -> 新隆店 | D45: =科目对照收入!$B23&"" -> 营业外收入 | E45: =IF(AND(ROUND($G45,2)<0,科目对照收入!$L23<>""),科目对照收入!$L23,科目对照收入!$C23)&"" -> 营业外收入 | F45: =IF(AND(ROUND($G45,2)<0,科目对照收入!$L23<>""),科目对照收入!$M23,科目对照收入!$D23)&"" | G45: =-ROUND(助手收入!$J3,2) -> 0 | H45: =IF(ROUND($G45,2)>0,ROUND($G45,2),"") | I45: =IF(ROUND($G45,2)<0,-ROUND($G45,2),"") | J45: =IF(ROUND($G45,2)=0,0,1) -> 0 | K45: =IF($J45=0,"",SUM($J$24:$J45)) | L45: =IF($K45="","",$A45*100+$K45) | M45: =参数!$B$3 -> 7月收入
A46: 3 | B46: =助手收入!$B4 -> 2003 | C46: =助手收入!$C4 -> 康庄路店 | D46: =科目对照收入!$B2&"" -> 库存现金 | E46: =IF(AND(ROUND($G46,2)<0,科目对照收入!$L2<>""),科目对照收入!$L2,科目对照收入!$C2)&"" -> 库存现金 | F46: =IF(AND(ROUND($G46,2)<0,科目对照收入!$L2<>""),科目对照收入!$M2,科目对照收入!$D2)&"" | G46: =助手收入!$I4 -> 50121.42 | H46: =IF(ROUND($G46,2)>0,ROUND($G46,2),"") -> 50121.42 | I46: =IF(ROUND($G46,2)<0,-ROUND($G46,2),"") | J46: =IF(ROUND($G46,2)=0,0,1) -> 1 | K46: =IF($J46=0,"",SUM($J$46:$J46)) -> 1 | L46: =IF($K46="","",$A46*100+$K46) -> 301 | M46: =参数!$B$3 -> 7月收入
A47: 3 | B47: =助手收入!$B4 -> 2003 | C47: =助手收入!$C4 -> 康庄路店 | D47: =科目对照收入!$B3&"" -> 聚合支付 | E47: =IF(AND(ROUND($G47,2)<0,科目对照收入!$L3<>""),科目对照收入!$L3,科目对照收入!$C3)&"" -> 应收账款 | F47: =IF(AND(ROUND($G47,2)<0,科目对照收入!$L3<>""),科目对照收入!$M3,科目对照收入!$D3)&"" -> 聚合支付 | G47: =ROUND(SUMIFS(输入聚合!$C:$C,输入聚合!$A:$A,助手收入!$X4)-SUMIFS(输入聚合!$D:$D,输入聚合!$A:$A,助手收入!$X4),2) -> 9782.31 | H47: =IF(ROUND($G47,2)>0,ROUND($G47,2),"") -> 9782.31 | I47: =IF(ROUND($G47,2)<0,-ROUND($G47,2),"") | J47: =IF(ROUND($G47,2)=0,0,1) -> 1 | K47: =IF($J47=0,"",SUM($J$46:$J47)) -> 2 | L47: =IF($K47="","",$A47*100+$K47) -> 302 | M47: =参数!$B$3 -> 7月收入
A48: 3 | B48: =助手收入!$B4 -> 2003 | C48: =助手收入!$C4 -> 康庄路店 | D48: =科目对照收入!$B4&"" -> 医保 | E48: =IF(AND(ROUND($G48,2)<0,科目对照收入!$L4<>""),科目对照收入!$L4,科目对照收入!$C4)&"" -> 应收账款 | F48: =IF(AND(ROUND($G48,2)<0,科目对照收入!$L4<>""),科目对照收入!$M4,科目对照收入!$D4)&"" -> 医保 | G48: =IF(COUNTIFS(输入平台!$A:$A,助手收入!$X4,输入平台!$B:$B,科目对照收入!$B4)>0,ROUND(SUMIFS(输入平台!$C:$C,输入平台!$A:$A,助手收入!$X4,输入平台!$B:$B,科目对照收入!$B4),2),ROUND(海典汇总!$F$5+海典汇总!$G$5,2)) -> 30850.84 | H48: =IF(ROUND($G48,2)>0,ROUND($G48,2),"") -> 30850.84 | I48: =IF(ROUND($G48,2)<0,-ROUND($G48,2),"") | J48: =IF(ROUND($G48,2)=0,0,1) -> 1 | K48: =IF($J48=0,"",SUM($J$46:$J48)) -> 3 | L48: =IF($K48="","",$A48*100+$K48) -> 303 | M48: =参数!$B$3 -> 7月收入
A49: 3 | B49: =助手收入!$B4 -> 2003 | C49: =助手收入!$C4 -> 康庄路店 | D49: =科目对照收入!$B5&"" -> 健e卡 | E49: =IF(AND(ROUND($G49,2)<0,科目对照收入!$L5<>""),科目对照收入!$L5,科目对照收入!$C5)&"" -> 应收账款 | F49: =IF(AND(ROUND($G49,2)<0,科目对照收入!$L5<>""),科目对照收入!$M5,科目对照收入!$D5)&"" -> 健e卡 | G49: =IF(COUNTIFS(输入平台!$A:$A,助手收入!$X4,输入平台!$B:$B,科目对照收入!$B5)>0,ROUND(SUMIFS(输入平台!$C:$C,输入平台!$A:$A,助手收入!$X4,输入平台!$B:$B,科目对照收入!$B5),2),ROUND(海典汇总!$H$5,2)) -> 30700.31 | H49: =IF(ROUND($G49,2)>0,ROUND($G49,2),"") -> 30700.31 | I49: =IF(ROUND($G49,2)<0,-ROUND($G49,2),"") | J49: =IF(ROUND($G49,2)=0,0,1) -> 1 | K49: =IF($J49=0,"",SUM($J$46:$J49)) -> 4 | L49: =IF($K49="","",$A49*100+$K49) -> 304 | M49: =参数!$B$3 -> 7月收入
A50: 3 | B50: =助手收入!$B4 -> 2003 | C50: =助手收入!$C4 -> 康庄路店 | D50: =科目对照收入!$B6&"" -> 医卡通 | E50: =IF(AND(ROUND($G50,2)<0,科目对照收入!$L6<>""),科目对照收入!$L6,科目对照收入!$C6)&"" -> 应收账款 | F50: =IF(AND(ROUND($G50,2)<0,科目对照收入!$L6<>""),科目对照收入!$M6,科目对照收入!$D6)&"" -> 医卡通 | G50: =IF(COUNTIFS(输入平台!$A:$A,助手收入!$X4,输入平台!$B:$B,科目对照收入!$B6)>0,ROUND(SUMIFS(输入平台!$C:$C,输入平台!$A:$A,助手收入!$X4,输入平台!$B:$B,科目对照收入!$B6),2),ROUND(海典汇总!$I$5,2)) -> 586.28 | H50: =IF(ROUND($G50,2)>0,ROUND($G50,2),"") -> 586.28 | I50: =IF(ROUND($G50,2)<0,-ROUND($G50,2),"") | J50: =IF(ROUND($G50,2)=0,0,1) -> 1 | K50: =IF($J50=0,"",SUM($J$46:$J50)) -> 5 | L50: =IF($K50="","",$A50*100+$K50) -> 305 | M50: =参数!$B$3 -> 7月收入
A51: 3 | B51: =助手收入!$B4 -> 2003 | C51: =助手收入!$C4 -> 康庄路店 | D51: =科目对照收入!$B7&"" -> 企健网 | E51: =IF(AND(ROUND($G51,2)<0,科目对照收入!$L7<>""),科目对照收入!$L7,科目对照收入!$C7)&"" -> 应收账款 | F51: =IF(AND(ROUND($G51,2)<0,科目对照收入!$L7<>""),科目对照收入!$M7,科目对照收入!$D7)&"" -> 企健网 | G51: =IF(COUNTIFS(输入平台!$A:$A,助手收入!$X4,输入平台!$B:$B,科目对照收入!$B7)>0,ROUND(SUMIFS(输入平台!$C:$C,输入平台!$A:$A,助手收入!$X4,输入平台!$B:$B,科目对照收入!$B7),2),ROUND(海典汇总!$J$5,2)) -> 0 | H51: =IF(ROUND($G51,2)>0,ROUND($G51,2),"") | I51: =IF(ROUND($G51,2)<0,-ROUND($G51,2),"") | J51: =IF(ROUND($G51,2)=0,0,1) -> 0 | K51: =IF($J51=0,"",SUM($J$46:$J51)) | L51: =IF($K51="","",$A51*100+$K51) | M51: =参数!$B$3 -> 7月收入
A52: 3 | B52: =助手收入!$B4 -> 2003 | C52: =助手收入!$C4 -> 康庄路店 | D52: =科目对照收入!$B8&"" -> 亲情卡 | E52: =IF(AND(ROUND($G52,2)<0,科目对照收入!$L8<>""),科目对照收入!$L8,科目对照收入!$C8)&"" -> 应收账款 | F52: =IF(AND(ROUND($G52,2)<0,科目对照收入!$L8<>""),科目对照收入!$M8,科目对照收入!$D8)&"" -> 亲情卡 | G52: =IF(COUNTIFS(输入平台!$A:$A,助手收入!$X4,输入平台!$B:$B,科目对照收入!$B8)>0,ROUND(SUMIFS(输入平台!$C:$C,输入平台!$A:$A,助手收入!$X4,输入平台!$B:$B,科目对照收入!$B8),2),ROUND(海典汇总!$Z$5,2)) -> 0 | H52: =IF(ROUND($G52,2)>0,ROUND($G52,2),"") | I52: =IF(ROUND($G52,2)<0,-ROUND($G52,2),"") | J52: =IF(ROUND($G52,2)=0,0,1) -> 0 | K52: =IF($J52=0,"",SUM($J$46:$J52)) | L52: =IF($K52="","",$A52*100+$K52) | M52: =参数!$B$3 -> 7月收入
A53: 3 | B53: =助手收入!$B4 -> 2003 | C53: =助手收入!$C4 -> 康庄路店 | D53: =科目对照收入!$B9&"" -> 24小时 | E53: =IF(AND(ROUND($G53,2)<0,科目对照收入!$L9<>""),科目对照收入!$L9,科目对照收入!$C9)&"" -> 应收账款 | F53: =IF(AND(ROUND($G53,2)<0,科目对照收入!$L9<>""),科目对照收入!$M9,科目对照收入!$D9)&"" -> 24小时 | G53: =IF(COUNTIFS(输入平台!$A:$A,助手收入!$X4,输入平台!$B:$B,科目对照收入!$B9)>0,ROUND(SUMIFS(输入平台!$C:$C,输入平台!$A:$A,助手收入!$X4,输入平台!$B:$B,科目对照收入!$B9),2),ROUND(海典汇总!$K$5,2)) -> 0 | H53: =IF(ROUND($G53,2)>0,ROUND($G53,2),"") | I53: =IF(ROUND($G53,2)<0,-ROUND($G53,2),"") | J53: =IF(ROUND($G53,2)=0,0,1) -> 0 | K53: =IF($J53=0,"",SUM($J$46:$J53)) | L53: =IF($K53="","",$A53*100+$K53) | M53: =参数!$B$3 -> 7月收入
A54: 3 | B54: =助手收入!$B4 -> 2003 | C54: =助手收入!$C4 -> 康庄路店 | D54: =科目对照收入!$B10&"" -> 美团 | E54: =IF(AND(ROUND($G54,2)<0,科目对照收入!$L10<>""),科目对照收入!$L10,科目对照收入!$C10)&"" -> 应收账款 | F54: =IF(AND(ROUND($G54,2)<0,科目对照收入!$L10<>""),科目对照收入!$M10,科目对照收入!$D10)&"" -> 美团 | G54: =IF(COUNTIFS(输入平台!$A:$A,助手收入!$X4,输入平台!$B:$B,科目对照收入!$B10)>0,ROUND(SUMIFS(输入平台!$C:$C,输入平台!$A:$A,助手收入!$X4,输入平台!$B:$B,科目对照收入!$B10),2),ROUND(海典汇总!$M$5,2)) -> 92.2 | H54: =IF(ROUND($G54,2)>0,ROUND($G54,2),"") -> 92.2 | I54: =IF(ROUND($G54,2)<0,-ROUND($G54,2),"") | J54: =IF(ROUND($G54,2)=0,0,1) -> 1 | K54: =IF($J54=0,"",SUM($J$46:$J54)) -> 6 | L54: =IF($K54="","",$A54*100+$K54) -> 306 | M54: =参数!$B$3 -> 7月收入
A55: 3 | B55: =助手收入!$B4 -> 2003 | C55: =助手收入!$C4 -> 康庄路店 | D55: =科目对照收入!$B11&"" -> 饿了么 | E55: =IF(AND(ROUND($G55,2)<0,科目对照收入!$L11<>""),科目对照收入!$L11,科目对照收入!$C11)&"" -> 应收账款 | F55: =IF(AND(ROUND($G55,2)<0,科目对照收入!$L11<>""),科目对照收入!$M11,科目对照收入!$D11)&"" -> 饿了么 | G55: =IF(COUNTIFS(输入平台!$A:$A,助手收入!$X4,输入平台!$B:$B,科目对照收入!$B11)>0,ROUND(SUMIFS(输入平台!$C:$C,输入平台!$A:$A,助手收入!$X4,输入平台!$B:$B,科目对照收入!$B11),2),ROUND(海典汇总!$N$5,2)) -> 0 | H55: =IF(ROUND($G55,2)>0,ROUND($G55,2),"") | I55: =IF(ROUND($G55,2)<0,-ROUND($G55,2),"") | J55: =IF(ROUND($G55,2)=0,0,1) -> 0 | K55: =IF($J55=0,"",SUM($J$46:$J55)) | L55: =IF($K55="","",$A55*100+$K55) | M55: =参数!$B$3 -> 7月收入
A56: 3 | B56: =助手收入!$B4 -> 2003 | C56: =助手收入!$C4 -> 康庄路店 | D56: =科目对照收入!$B12&"" -> 京东秒送 | E56: =IF(AND(ROUND($G56,2)<0,科目对照收入!$L12<>""),科目对照收入!$L12,科目对照收入!$C12)&"" -> 应收账款 | F56: =IF(AND(ROUND($G56,2)<0,科目对照收入!$L12<>""),科目对照收入!$M12,科目对照收入!$D12)&"" -> 京东秒送 | G56: =IF(COUNTIFS(输入平台!$A:$A,助手收入!$X4,输入平台!$B:$B,科目对照收入!$B12)>0,ROUND(SUMIFS(输入平台!$C:$C,输入平台!$A:$A,助手收入!$X4,输入平台!$B:$B,科目对照收入!$B12),2),ROUND(海典汇总!$O$5,2)) -> 0 | H56: =IF(ROUND($G56,2)>0,ROUND($G56,2),"") | I56: =IF(ROUND($G56,2)<0,-ROUND($G56,2),"") | J56: =IF(ROUND($G56,2)=0,0,1) -> 0 | K56: =IF($J56=0,"",SUM($J$46:$J56)) | L56: =IF($K56="","",$A56*100+$K56) | M56: =参数!$B$3 -> 7月收入
A57: 3 | B57: =助手收入!$B4 -> 2003 | C57: =助手收入!$C4 -> 康庄路店 | D57: =科目对照收入!$B13&"" -> 银联 | E57: =IF(AND(ROUND($G57,2)<0,科目对照收入!$L13<>""),科目对照收入!$L13,科目对照收入!$C13)&"" -> 应收账款 | F57: =IF(AND(ROUND($G57,2)<0,科目对照收入!$L13<>""),科目对照收入!$M13,科目对照收入!$D13)&"" -> 银联 | G57: =IF(COUNTIFS(输入平台!$A:$A,助手收入!$X4,输入平台!$B:$B,科目对照收入!$B13)>0,ROUND(SUMIFS(输入平台!$C:$C,输入平台!$A:$A,助手收入!$X4,输入平台!$B:$B,科目对照收入!$B13),2),ROUND(海典汇总!$V$5,2)) -> 0 | H57: =IF(ROUND($G57,2)>0,ROUND($G57,2),"") | I57: =IF(ROUND($G57,2)<0,-ROUND($G57,2),"") | J57: =IF(ROUND($G57,2)=0,0,1) -> 0 | K57: =IF($J57=0,"",SUM($J$46:$J57)) | L57: =IF($K57="","",$A57*100+$K57) | M57: =参数!$B$3 -> 7月收入
A58: 3 | B58: =助手收入!$B4 -> 2003 | C58: =助手收入!$C4 -> 康庄路店 | D58: =科目对照收入!$B14&"" -> 小镇外卖 | E58: =IF(AND(ROUND($G58,2)<0,科目对照收入!$L14<>""),科目对照收入!$L14,科目对照收入!$C14)&"" -> 应收账款 | F58: =IF(AND(ROUND($G58,2)<0,科目对照收入!$L14<>""),科目对照收入!$M14,科目对照收入!$D14)&"" -> 小镇外卖 | G58: =IF(COUNTIFS(输入平台!$A:$A,助手收入!$X4,输入平台!$B:$B,科目对照收入!$B14)>0,ROUND(SUMIFS(输入平台!$C:$C,输入平台!$A:$A,助手收入!$X4,输入平台!$B:$B,科目对照收入!$B14),2),ROUND(海典汇总!$AC$5,2)) -> 0 | H58: =IF(ROUND($G58,2)>0,ROUND($G58,2),"") | I58: =IF(ROUND($G58,2)<0,-ROUND($G58,2),"") | J58: =IF(ROUND($G58,2)=0,0,1) -> 0 | K58: =IF($J58=0,"",SUM($J$46:$J58)) | L58: =IF($K58="","",$A58*100+$K58) | M58: =参数!$B$3 -> 7月收入
A59: 3 | B59: =助手收入!$B4 -> 2003 | C59: =助手收入!$C4 -> 康庄路店 | D59: =科目对照收入!$B15&"" -> OMS线上支付 | E59: =IF(AND(ROUND($G59,2)<0,科目对照收入!$L15<>""),科目对照收入!$L15,科目对照收入!$C15)&"" -> 应收账款 | F59: =IF(AND(ROUND($G59,2)<0,科目对照收入!$L15<>""),科目对照收入!$M15,科目对照收入!$D15)&"" -> OMS线上 | G59: =IF(COUNTIFS(输入平台!$A:$A,助手收入!$X4,输入平台!$B:$B,科目对照收入!$B15)>0,ROUND(SUMIFS(输入平台!$C:$C,输入平台!$A:$A,助手收入!$X4,输入平台!$B:$B,科目对照收入!$B15),2),ROUND(海典汇总!$L$5,2)) -> 0 | H59: =IF(ROUND($G59,2)>0,ROUND($G59,2),"") | I59: =IF(ROUND($G59,2)<0,-ROUND($G59,2),"") | J59: =IF(ROUND($G59,2)=0,0,1) -> 0 | K59: =IF($J59=0,"",SUM($J$46:$J59)) | L59: =IF($K59="","",$A59*100+$K59) | M59: =参数!$B$3 -> 7月收入
A60: 3 | B60: =助手收入!$B4 -> 2003 | C60: =助手收入!$C4 -> 康庄路店 | D60: =科目对照收入!$B16&"" -> 平安药卡 | E60: =IF(AND(ROUND($G60,2)<0,科目对照收入!$L16<>""),科目对照收入!$L16,科目对照收入!$C16)&"" -> 应收账款 | F60: =IF(AND(ROUND($G60,2)<0,科目对照收入!$L16<>""),科目对照收入!$M16,科目对照收入!$D16)&"" -> 平安 | G60: =IF(COUNTIFS(输入平台!$A:$A,助手收入!$X4,输入平台!$B:$B,科目对照收入!$B16)>0,ROUND(SUMIFS(输入平台!$C:$C,输入平台!$A:$A,助手收入!$X4,输入平台!$B:$B,科目对照收入!$B16),2),ROUND(海典汇总!$AB$5,2)) -> 0 | H60: =IF(ROUND($G60,2)>0,ROUND($G60,2),"") | I60: =IF(ROUND($G60,2)<0,-ROUND($G60,2),"") | J60: =IF(ROUND($G60,2)=0,0,1) -> 0 | K60: =IF($J60=0,"",SUM($J$46:$J60)) | L60: =IF($K60="","",$A60*100+$K60) | M60: =参数!$B$3 -> 7月收入
A61: 3 | B61: =助手收入!$B4 -> 2003 | C61: =助手收入!$C4 -> 康庄路店 | D61: =科目对照收入!$B17&"" -> 储值卡 | E61: =IF(AND(ROUND($G61,2)<0,科目对照收入!$L17<>""),科目对照收入!$L17,科目对照收入!$C17)&"" -> 其他应收款 | F61: =IF(AND(ROUND($G61,2)<0,科目对照收入!$L17<>""),科目对照收入!$M17,科目对照收入!$D17)&"" -> 储值卡 | G61: =ROUND(海典汇总!$Q$5,2) -> 4183.84 | H61: =IF(ROUND($G61,2)>0,ROUND($G61,2),"") -> 4183.84 | I61: =IF(ROUND($G61,2)<0,-ROUND($G61,2),"") | J61: =IF(ROUND($G61,2)=0,0,1) -> 1 | K61: =IF($J61=0,"",SUM($J$46:$J61)) -> 7 | L61: =IF($K61="","",$A61*100+$K61) -> 307 | M61: =参数!$B$3 -> 7月收入
A62: 3 | B62: =助手收入!$B4 -> 2003 | C62: =助手收入!$C4 -> 康庄路店 | D62: =科目对照收入!$B18&"" -> 会员零钱包 | E62: =IF(AND(ROUND($G62,2)<0,科目对照收入!$L18<>""),科目对照收入!$L18,科目对照收入!$C18)&"" -> 其他应收款 | F62: =IF(AND(ROUND($G62,2)<0,科目对照收入!$L18<>""),科目对照收入!$M18,科目对照收入!$D18)&"" -> 会员零钱包 | G62: =ROUND(海典汇总!$P$5,2) -> 0 | H62: =IF(ROUND($G62,2)>0,ROUND($G62,2),"") | I62: =IF(ROUND($G62,2)<0,-ROUND($G62,2),"") | J62: =IF(ROUND($G62,2)=0,0,1) -> 0 | K62: =IF($J62=0,"",SUM($J$46:$J62)) | L62: =IF($K62="","",$A62*100+$K62) | M62: =参数!$B$3 -> 7月收入
A63: 3 | B63: =助手收入!$B4 -> 2003 | C63: =助手收入!$C4 -> 康庄路店 | D63: =科目对照收入!$B19&"" -> 促销费 | E63: =IF(AND(ROUND($G63,2)<0,科目对照收入!$L19<>""),科目对照收入!$L19,科目对照收入!$C19)&"" -> 销售费用 | F63: =IF(AND(ROUND($G63,2)<0,科目对照收入!$L19<>""),科目对照收入!$M19,科目对照收入!$D19)&"" -> 促销费 | G63: =ROUND(海典汇总!$U$5+海典汇总!$T$5+海典汇总!$S$5,2) -> 2034.28 | H63: =IF(ROUND($G63,2)>0,ROUND($G63,2),"") -> 2034.28 | I63: =IF(ROUND($G63,2)<0,-ROUND($G63,2),"") | J63: =IF(ROUND($G63,2)=0,0,1) -> 1 | K63: =IF($J63=0,"",SUM($J$46:$J63)) -> 8 | L63: =IF($K63="","",$A63*100+$K63) -> 308 | M63: =参数!$B$3 -> 7月收入
A64: 3 | B64: =助手收入!$B4 -> 2003 | C64: =助手收入!$C4 -> 康庄路店 | D64: =科目对照收入!$B20&"" -> 积分 | E64: =IF(AND(ROUND($G64,2)<0,科目对照收入!$L20<>""),科目对照收入!$L20,科目对照收入!$C20)&"" -> 销售费用 | F64: =IF(AND(ROUND($G64,2)<0,科目对照收入!$L20<>""),科目对照收入!$M20,科目对照收入!$D20)&"" -> 积分 | G64: =ROUND(海典汇总!$R$5,2) -> 0 | H64: =IF(ROUND($G64,2)>0,ROUND($G64,2),"") | I64: =IF(ROUND($G64,2)<0,-ROUND($G64,2),"") | J64: =IF(ROUND($G64,2)=0,0,1) -> 0 | K64: =IF($J64=0,"",SUM($J$46:$J64)) | L64: =IF($K64="","",$A64*100+$K64) | M64: =参数!$B$3 -> 7月收入
A65: 3 | B65: =助手收入!$B4 -> 2003 | C65: =助手收入!$C4 -> 康庄路店 | D65: =科目对照收入!$B21&"" -> 手续费 | E65: =IF(AND(ROUND($G65,2)<0,科目对照收入!$L21<>""),科目对照收入!$L21,科目对照收入!$C21)&"" -> 财务费用 | F65: =IF(AND(ROUND($G65,2)<0,科目对照收入!$L21<>""),科目对照收入!$M21,科目对照收入!$D21)&"" -> 手续费 | G65: =ROUND(SUMIFS(输入聚合!$D:$D,输入聚合!$A:$A,助手收入!$X4),2) -> 26.48 | H65: =IF(ROUND($G65,2)>0,ROUND($G65,2),"") -> 26.48 | I65: =IF(ROUND($G65,2)<0,-ROUND($G65,2),"") | J65: =IF(ROUND($G65,2)=0,0,1) -> 1 | K65: =IF($J65=0,"",SUM($J$46:$J65)) -> 9 | L65: =IF($K65="","",$A65*100+$K65) -> 309 | M65: =参数!$B$3 -> 7月收入
A66: 3 | B66: =助手收入!$B4 -> 2003 | C66: =助手收入!$C4 -> 康庄路店 | D66: =科目对照收入!$B22&"" -> 主营业务收入 | E66: =IF(AND(ROUND($G66,2)<0,科目对照收入!$L22<>""),科目对照收入!$L22,科目对照收入!$C22)&"" -> 主营业务收入 | F66: =IF(AND(ROUND($G66,2)<0,科目对照收入!$L22<>""),科目对照收入!$M22,科目对照收入!$D22)&"" | G66: =-ROUND(助手收入!$G4,2) -> -128377.96 | H66: =IF(ROUND($G66,2)>0,ROUND($G66,2),"") | I66: =IF(ROUND($G66,2)<0,-ROUND($G66,2),"") -> 128377.96 | J66: =IF(ROUND($G66,2)=0,0,1) -> 1 | K66: =IF($J66=0,"",SUM($J$46:$J66)) -> 10 | L66: =IF($K66="","",$A66*100+$K66) -> 310 | M66: =参数!$B$3 -> 7月收入
A67: 3 | B67: =助手收入!$B4 -> 2003 | C67: =助手收入!$C4 -> 康庄路店 | D67: =科目对照收入!$B23&"" -> 营业外收入 | E67: =IF(AND(ROUND($G67,2)<0,科目对照收入!$L23<>""),科目对照收入!$L23,科目对照收入!$C23)&"" -> 营业外收入 | F67: =IF(AND(ROUND($G67,2)<0,科目对照收入!$L23<>""),科目对照收入!$M23,科目对照收入!$D23)&"" | G67: =-ROUND(助手收入!$J4,2) -> 0 | H67: =IF(ROUND($G67,2)>0,ROUND($G67,2),"") | I67: =IF(ROUND($G67,2)<0,-ROUND($G67,2),"") | J67: =IF(ROUND($G67,2)=0,0,1) -> 0 | K67: =IF($J67=0,"",SUM($J$46:$J67)) | L67: =IF($K67="","",$A67*100+$K67) | M67: =参数!$B$3 -> 7月收入
A68: 4 | B68: =助手收入!$B5 -> 2004 | C68: =助手收入!$C5 -> 东关店 | D68: =科目对照收入!$B2&"" -> 库存现金 | E68: =IF(AND(ROUND($G68,2)<0,科目对照收入!$L2<>""),科目对照收入!$L2,科目对照收入!$C2)&"" -> 库存现金 | F68: =IF(AND(ROUND($G68,2)<0,科目对照收入!$L2<>""),科目对照收入!$M2,科目对照收入!$D2)&"" | G68: =助手收入!$I5 -> 67171.51 | H68: =IF(ROUND($G68,2)>0,ROUND($G68,2),"") -> 67171.51 | I68: =IF(ROUND($G68,2)<0,-ROUND($G68,2),"") | J68: =IF(ROUND($G68,2)=0,0,1) -> 1 | K68: =IF($J68=0,"",SUM($J$68:$J68)) -> 1 | L68: =IF($K68="","",$A68*100+$K68) -> 401 | M68: =参数!$B$3 -> 7月收入
A69: 4 | B69: =助手收入!$B5 -> 2004 | C69: =助手收入!$C5 -> 东关店 | D69: =科目对照收入!$B3&"" -> 聚合支付 | E69: =IF(AND(ROUND($G69,2)<0,科目对照收入!$L3<>""),科目对照收入!$L3,科目对照收入!$C3)&"" -> 应收账款 | F69: =IF(AND(ROUND($G69,2)<0,科目对照收入!$L3<>""),科目对照收入!$M3,科目对照收入!$D3)&"" -> 聚合支付 | G69: =ROUND(SUMIFS(输入聚合!$C:$C,输入聚合!$A:$A,助手收入!$X5)-SUMIFS(输入聚合!$D:$D,输入聚合!$A:$A,助手收入!$X5),2) -> 4991.09 | H69: =IF(ROUND($G69,2)>0,ROUND($G69,2),"") -> 4991.09 | I69: =IF(ROUND($G69,2)<0,-ROUND($G69,2),"") | J69: =IF(ROUND($G69,2)=0,0,1) -> 1 | K69: =IF($J69=0,"",SUM($J$68:$J69)) -> 2 | L69: =IF($K69="","",$A69*100+$K69) -> 402 | M69: =参数!$B$3 -> 7月收入
A70: 4 | B70: =助手收入!$B5 -> 2004 | C70: =助手收入!$C5 -> 东关店 | D70: =科目对照收入!$B4&"" -> 医保 | E70: =IF(AND(ROUND($G70,2)<0,科目对照收入!$L4<>""),科目对照收入!$L4,科目对照收入!$C4)&"" -> 应收账款 | F70: =IF(AND(ROUND($G70,2)<0,科目对照收入!$L4<>""),科目对照收入!$M4,科目对照收入!$D4)&"" -> 医保 | G70: =IF(COUNTIFS(输入平台!$A:$A,助手收入!$X5,输入平台!$B:$B,科目对照收入!$B4)>0,ROUND(SUMIFS(输入平台!$C:$C,输入平台!$A:$A,助手收入!$X5,输入平台!$B:$B,科目对照收入!$B4),2),ROUND(海典汇总!$F$6+海典汇总!$G$6,2)) -> 21335.84 | H70: =IF(ROUND($G70,2)>0,ROUND($G70,2),"") -> 21335.84 | I70: =IF(ROUND($G70,2)<0,-ROUND($G70,2),"") | J70: =IF(ROUND($G70,2)=0,0,1) -> 1 | K70: =IF($J70=0,"",SUM($J$68:$J70)) -> 3 | L70: =IF($K70="","",$A70*100+$K70) -> 403 | M70: =参数!$B$3 -> 7月收入
A71: 4 | B71: =助手收入!$B5 -> 2004 | C71: =助手收入!$C5 -> 东关店 | D71: =科目对照收入!$B5&"" -> 健e卡 | E71: =IF(AND(ROUND($G71,2)<0,科目对照收入!$L5<>""),科目对照收入!$L5,科目对照收入!$C5)&"" -> 应收账款 | F71: =IF(AND(ROUND($G71,2)<0,科目对照收入!$L5<>""),科目对照收入!$M5,科目对照收入!$D5)&"" -> 健e卡 | G71: =IF(COUNTIFS(输入平台!$A:$A,助手收入!$X5,输入平台!$B:$B,科目对照收入!$B5)>0,ROUND(SUMIFS(输入平台!$C:$C,输入平台!$A:$A,助手收入!$X5,输入平台!$B:$B,科目对照收入!$B5),2),ROUND(海典汇总!$H$6,2)) -> 4415.97 | H71: =IF(ROUND($G71,2)>0,ROUND($G71,2),"") -> 4415.97 | I71: =IF(ROUND($G71,2)<0,-ROUND($G71,2),"") | J71: =IF(ROUND($G71,2)=0,0,1) -> 1 | K71: =IF($J71=0,"",SUM($J$68:$J71)) -> 4 | L71: =IF($K71="","",$A71*100+$K71) -> 404 | M71: =参数!$B$3 -> 7月收入
A72: 4 | B72: =助手收入!$B5 -> 2004 | C72: =助手收入!$C5 -> 东关店 | D72: =科目对照收入!$B6&"" -> 医卡通 | E72: =IF(AND(ROUND($G72,2)<0,科目对照收入!$L6<>""),科目对照收入!$L6,科目对照收入!$C6)&"" -> 应收账款 | F72: =IF(AND(ROUND($G72,2)<0,科目对照收入!$L6<>""),科目对照收入!$M6,科目对照收入!$D6)&"" -> 医卡通 | G72: =IF(COUNTIFS(输入平台!$A:$A,助手收入!$X5,输入平台!$B:$B,科目对照收入!$B6)>0,ROUND(SUMIFS(输入平台!$C:$C,输入平台!$A:$A,助手收入!$X5,输入平台!$B:$B,科目对照收入!$B6),2),ROUND(海典汇总!$I$6,2)) -> 0 | H72: =IF(ROUND($G72,2)>0,ROUND($G72,2),"") | I72: =IF(ROUND($G72,2)<0,-ROUND($G72,2),"") | J72: =IF(ROUND($G72,2)=0,0,1) -> 0 | K72: =IF($J72=0,"",SUM($J$68:$J72)) | L72: =IF($K72="","",$A72*100+$K72) | M72: =参数!$B$3 -> 7月收入
A73: 4 | B73: =助手收入!$B5 -> 2004 | C73: =助手收入!$C5 -> 东关店 | D73: =科目对照收入!$B7&"" -> 企健网 | E73: =IF(AND(ROUND($G73,2)<0,科目对照收入!$L7<>""),科目对照收入!$L7,科目对照收入!$C7)&"" -> 应收账款 | F73: =IF(AND(ROUND($G73,2)<0,科目对照收入!$L7<>""),科目对照收入!$M7,科目对照收入!$D7)&"" -> 企健网 | G73: =IF(COUNTIFS(输入平台!$A:$A,助手收入!$X5,输入平台!$B:$B,科目对照收入!$B7)>0,ROUND(SUMIFS(输入平台!$C:$C,输入平台!$A:$A,助手收入!$X5,输入平台!$B:$B,科目对照收入!$B7),2),ROUND(海典汇总!$J$6,2)) -> 0 | H73: =IF(ROUND($G73,2)>0,ROUND($G73,2),"") | I73: =IF(ROUND($G73,2)<0,-ROUND($G73,2),"") | J73: =IF(ROUND($G73,2)=0,0,1) -> 0 | K73: =IF($J73=0,"",SUM($J$68:$J73)) | L73: =IF($K73="","",$A73*100+$K73) | M73: =参数!$B$3 -> 7月收入
A74: 4 | B74: =助手收入!$B5 -> 2004 | C74: =助手收入!$C5 -> 东关店 | D74: =科目对照收入!$B8&"" -> 亲情卡 | E74: =IF(AND(ROUND($G74,2)<0,科目对照收入!$L8<>""),科目对照收入!$L8,科目对照收入!$C8)&"" -> 应收账款 | F74: =IF(AND(ROUND($G74,2)<0,科目对照收入!$L8<>""),科目对照收入!$M8,科目对照收入!$D8)&"" -> 亲情卡 | G74: =IF(COUNTIFS(输入平台!$A:$A,助手收入!$X5,输入平台!$B:$B,科目对照收入!$B8)>0,ROUND(SUMIFS(输入平台!$C:$C,输入平台!$A:$A,助手收入!$X5,输入平台!$B:$B,科目对照收入!$B8),2),ROUND(海典汇总!$Z$6,2)) -> 0 | H74: =IF(ROUND($G74,2)>0,ROUND($G74,2),"") | I74: =IF(ROUND($G74,2)<0,-ROUND($G74,2),"") | J74: =IF(ROUND($G74,2)=0,0,1) -> 0 | K74: =IF($J74=0,"",SUM($J$68:$J74)) | L74: =IF($K74="","",$A74*100+$K74) | M74: =参数!$B$3 -> 7月收入
A75: 4 | B75: =助手收入!$B5 -> 2004 | C75: =助手收入!$C5 -> 东关店 | D75: =科目对照收入!$B9&"" -> 24小时 | E75: =IF(AND(ROUND($G75,2)<0,科目对照收入!$L9<>""),科目对照收入!$L9,科目对照收入!$C9)&"" -> 应收账款 | F75: =IF(AND(ROUND($G75,2)<0,科目对照收入!$L9<>""),科目对照收入!$M9,科目对照收入!$D9)&"" -> 24小时 | G75: =IF(COUNTIFS(输入平台!$A:$A,助手收入!$X5,输入平台!$B:$B,科目对照收入!$B9)>0,ROUND(SUMIFS(输入平台!$C:$C,输入平台!$A:$A,助手收入!$X5,输入平台!$B:$B,科目对照收入!$B9),2),ROUND(海典汇总!$K$6,2)) -> 0 | H75: =IF(ROUND($G75,2)>0,ROUND($G75,2),"") | I75: =IF(ROUND($G75,2)<0,-ROUND($G75,2),"") | J75: =IF(ROUND($G75,2)=0,0,1) -> 0 | K75: =IF($J75=0,"",SUM($J$68:$J75)) | L75: =IF($K75="","",$A75*100+$K75) | M75: =参数!$B$3 -> 7月收入
A76: 4 | B76: =助手收入!$B5 -> 2004 | C76: =助手收入!$C5 -> 东关店 | D76: =科目对照收入!$B10&"" -> 美团 | E76: =IF(AND(ROUND($G76,2)<0,科目对照收入!$L10<>""),科目对照收入!$L10,科目对照收入!$C10)&"" -> 应收账款 | F76: =IF(AND(ROUND($G76,2)<0,科目对照收入!$L10<>""),科目对照收入!$M10,科目对照收入!$D10)&"" -> 美团 | G76: =IF(COUNTIFS(输入平台!$A:$A,助手收入!$X5,输入平台!$B:$B,科目对照收入!$B10)>0,ROUND(SUMIFS(输入平台!$C:$C,输入平台!$A:$A,助手收入!$X5,输入平台!$B:$B,科目对照收入!$B10),2),ROUND(海典汇总!$M$6,2)) -> 716 | H76: =IF(ROUND($G76,2)>0,ROUND($G76,2),"") -> 716 | I76: =IF(ROUND($G76,2)<0,-ROUND($G76,2),"") | J76: =IF(ROUND($G76,2)=0,0,1) -> 1 | K76: =IF($J76=0,"",SUM($J$68:$J76)) -> 5 | L76: =IF($K76="","",$A76*100+$K76) -> 405 | M76: =参数!$B$3 -> 7月收入
A77: 4 | B77: =助手收入!$B5 -> 2004 | C77: =助手收入!$C5 -> 东关店 | D77: =科目对照收入!$B11&"" -> 饿了么 | E77: =IF(AND(ROUND($G77,2)<0,科目对照收入!$L11<>""),科目对照收入!$L11,科目对照收入!$C11)&"" -> 应收账款 | F77: =IF(AND(ROUND($G77,2)<0,科目对照收入!$L11<>""),科目对照收入!$M11,科目对照收入!$D11)&"" -> 饿了么 | G77: =IF(COUNTIFS(输入平台!$A:$A,助手收入!$X5,输入平台!$B:$B,科目对照收入!$B11)>0,ROUND(SUMIFS(输入平台!$C:$C,输入平台!$A:$A,助手收入!$X5,输入平台!$B:$B,科目对照收入!$B11),2),ROUND(海典汇总!$N$6,2)) -> 34.7 | H77: =IF(ROUND($G77,2)>0,ROUND($G77,2),"") -> 34.7 | I77: =IF(ROUND($G77,2)<0,-ROUND($G77,2),"") | J77: =IF(ROUND($G77,2)=0,0,1) -> 1 | K77: =IF($J77=0,"",SUM($J$68:$J77)) -> 6 | L77: =IF($K77="","",$A77*100+$K77) -> 406 | M77: =参数!$B$3 -> 7月收入
A78: 4 | B78: =助手收入!$B5 -> 2004 | C78: =助手收入!$C5 -> 东关店 | D78: =科目对照收入!$B12&"" -> 京东秒送 | E78: =IF(AND(ROUND($G78,2)<0,科目对照收入!$L12<>""),科目对照收入!$L12,科目对照收入!$C12)&"" -> 应收账款 | F78: =IF(AND(ROUND($G78,2)<0,科目对照收入!$L12<>""),科目对照收入!$M12,科目对照收入!$D12)&"" -> 京东秒送 | G78: =IF(COUNTIFS(输入平台!$A:$A,助手收入!$X5,输入平台!$B:$B,科目对照收入!$B12)>0,ROUND(SUMIFS(输入平台!$C:$C,输入平台!$A:$A,助手收入!$X5,输入平台!$B:$B,科目对照收入!$B12),2),ROUND(海典汇总!$O$6,2)) -> 0 | H78: =IF(ROUND($G78,2)>0,ROUND($G78,2),"") | I78: =IF(ROUND($G78,2)<0,-ROUND($G78,2),"") | J78: =IF(ROUND($G78,2)=0,0,1) -> 0 | K78: =IF($J78=0,"",SUM($J$68:$J78)) | L78: =IF($K78="","",$A78*100+$K78) | M78: =参数!$B$3 -> 7月收入
A79: 4 | B79: =助手收入!$B5 -> 2004 | C79: =助手收入!$C5 -> 东关店 | D79: =科目对照收入!$B13&"" -> 银联 | E79: =IF(AND(ROUND($G79,2)<0,科目对照收入!$L13<>""),科目对照收入!$L13,科目对照收入!$C13)&"" -> 应收账款 | F79: =IF(AND(ROUND($G79,2)<0,科目对照收入!$L13<>""),科目对照收入!$M13,科目对照收入!$D13)&"" -> 银联 | G79: =IF(COUNTIFS(输入平台!$A:$A,助手收入!$X5,输入平台!$B:$B,科目对照收入!$B13)>0,ROUND(SUMIFS(输入平台!$C:$C,输入平台!$A:$A,助手收入!$X5,输入平台!$B:$B,科目对照收入!$B13),2),ROUND(海典汇总!$V$6,2)) -> 0 | H79: =IF(ROUND($G79,2)>0,ROUND($G79,2),"") | I79: =IF(ROUND($G79,2)<0,-ROUND($G79,2),"") | J79: =IF(ROUND($G79,2)=0,0,1) -> 0 | K79: =IF($J79=0,"",SUM($J$68:$J79)) | L79: =IF($K79="","",$A79*100+$K79) | M79: =参数!$B$3 -> 7月收入
A80: 4 | B80: =助手收入!$B5 -> 2004 | C80: =助手收入!$C5 -> 东关店 | D80: =科目对照收入!$B14&"" -> 小镇外卖 | E80: =IF(AND(ROUND($G80,2)<0,科目对照收入!$L14<>""),科目对照收入!$L14,科目对照收入!$C14)&"" -> 应收账款 | F80: =IF(AND(ROUND($G80,2)<0,科目对照收入!$L14<>""),科目对照收入!$M14,科目对照收入!$D14)&"" -> 小镇外卖 | G80: =IF(COUNTIFS(输入平台!$A:$A,助手收入!$X5,输入平台!$B:$B,科目对照收入!$B14)>0,ROUND(SUMIFS(输入平台!$C:$C,输入平台!$A:$A,助手收入!$X5,输入平台!$B:$B,科目对照收入!$B14),2),ROUND(海典汇总!$AC$6,2)) -> 0 | H80: =IF(ROUND($G80,2)>0,ROUND($G80,2),"") | I80: =IF(ROUND($G80,2)<0,-ROUND($G80,2),"") | J80: =IF(ROUND($G80,2)=0,0,1) -> 0 | K80: =IF($J80=0,"",SUM($J$68:$J80)) | L80: =IF($K80="","",$A80*100+$K80) | M80: =参数!$B$3 -> 7月收入
A81: 4 | B81: =助手收入!$B5 -> 2004 | C81: =助手收入!$C5 -> 东关店 | D81: =科目对照收入!$B15&"" -> OMS线上支付 | E81: =IF(AND(ROUND($G81,2)<0,科目对照收入!$L15<>""),科目对照收入!$L15,科目对照收入!$C15)&"" -> 应收账款 | F81: =IF(AND(ROUND($G81,2)<0,科目对照收入!$L15<>""),科目对照收入!$M15,科目对照收入!$D15)&"" -> OMS线上 | G81: =IF(COUNTIFS(输入平台!$A:$A,助手收入!$X5,输入平台!$B:$B,科目对照收入!$B15)>0,ROUND(SUMIFS(输入平台!$C:$C,输入平台!$A:$A,助手收入!$X5,输入平台!$B:$B,科目对照收入!$B15),2),ROUND(海典汇总!$L$6,2)) -> 0 | H81: =IF(ROUND($G81,2)>0,ROUND($G81,2),"") | I81: =IF(ROUND($G81,2)<0,-ROUND($G81,2),"") | J81: =IF(ROUND($G81,2)=0,0,1) -> 0 | K81: =IF($J81=0,"",SUM($J$68:$J81)) | L81: =IF($K81="","",$A81*100+$K81) | M81: =参数!$B$3 -> 7月收入
A82: 4 | B82: =助手收入!$B5 -> 2004 | C82: =助手收入!$C5 -> 东关店 | D82: =科目对照收入!$B16&"" -> 平安药卡 | E82: =IF(AND(ROUND($G82,2)<0,科目对照收入!$L16<>""),科目对照收入!$L16,科目对照收入!$C16)&"" -> 应收账款 | F82: =IF(AND(ROUND($G82,2)<0,科目对照收入!$L16<>""),科目对照收入!$M16,科目对照收入!$D16)&"" -> 平安 | G82: =IF(COUNTIFS(输入平台!$A:$A,助手收入!$X5,输入平台!$B:$B,科目对照收入!$B16)>0,ROUND(SUMIFS(输入平台!$C:$C,输入平台!$A:$A,助手收入!$X5,输入平台!$B:$B,科目对照收入!$B16),2),ROUND(海典汇总!$AB$6,2)) -> 0 | H82: =IF(ROUND($G82,2)>0,ROUND($G82,2),"") | I82: =IF(ROUND($G82,2)<0,-ROUND($G82,2),"") | J82: =IF(ROUND($G82,2)=0,0,1) -> 0 | K82: =IF($J82=0,"",SUM($J$68:$J82)) | L82: =IF($K82="","",$A82*100+$K82) | M82: =参数!$B$3 -> 7月收入
A83: 4 | B83: =助手收入!$B5 -> 2004 | C83: =助手收入!$C5 -> 东关店 | D83: =科目对照收入!$B17&"" -> 储值卡 | E83: =IF(AND(ROUND($G83,2)<0,科目对照收入!$L17<>""),科目对照收入!$L17,科目对照收入!$C17)&"" -> 其他应收款 | F83: =IF(AND(ROUND($G83,2)<0,科目对照收入!$L17<>""),科目对照收入!$M17,科目对照收入!$D17)&"" -> 储值卡 | G83: =ROUND(海典汇总!$Q$6,2) -> 8394.24 | H83: =IF(ROUND($G83,2)>0,ROUND($G83,2),"") -> 8394.24 | I83: =IF(ROUND($G83,2)<0,-ROUND($G83,2),"") | J83: =IF(ROUND($G83,2)=0,0,1) -> 1 | K83: =IF($J83=0,"",SUM($J$68:$J83)) -> 7 | L83: =IF($K83="","",$A83*100+$K83) -> 407 | M83: =参数!$B$3 -> 7月收入
A84: 4 | B84: =助手收入!$B5 -> 2004 | C84: =助手收入!$C5 -> 东关店 | D84: =科目对照收入!$B18&"" -> 会员零钱包 | E84: =IF(AND(ROUND($G84,2)<0,科目对照收入!$L18<>""),科目对照收入!$L18,科目对照收入!$C18)&"" -> 其他应收款 | F84: =IF(AND(ROUND($G84,2)<0,科目对照收入!$L18<>""),科目对照收入!$M18,科目对照收入!$D18)&"" -> 会员零钱包 | G84: =ROUND(海典汇总!$P$6,2) -> 0 | H84: =IF(ROUND($G84,2)>0,ROUND($G84,2),"") | I84: =IF(ROUND($G84,2)<0,-ROUND($G84,2),"") | J84: =IF(ROUND($G84,2)=0,0,1) -> 0 | K84: =IF($J84=0,"",SUM($J$68:$J84)) | L84: =IF($K84="","",$A84*100+$K84) | M84: =参数!$B$3 -> 7月收入
A85: 4 | B85: =助手收入!$B5 -> 2004 | C85: =助手收入!$C5 -> 东关店 | D85: =科目对照收入!$B19&"" -> 促销费 | E85: =IF(AND(ROUND($G85,2)<0,科目对照收入!$L19<>""),科目对照收入!$L19,科目对照收入!$C19)&"" -> 销售费用 | F85: =IF(AND(ROUND($G85,2)<0,科目对照收入!$L19<>""),科目对照收入!$M19,科目对照收入!$D19)&"" -> 促销费 | G85: =ROUND(海典汇总!$U$6+海典汇总!$T$6+海典汇总!$S$6,2) -> 968.18 | H85: =IF(ROUND($G85,2)>0,ROUND($G85,2),"") -> 968.18 | I85: =IF(ROUND($G85,2)<0,-ROUND($G85,2),"") | J85: =IF(ROUND($G85,2)=0,0,1) -> 1 | K85: =IF($J85=0,"",SUM($J$68:$J85)) -> 8 | L85: =IF($K85="","",$A85*100+$K85) -> 408 | M85: =参数!$B$3 -> 7月收入
A86: 4 | B86: =助手收入!$B5 -> 2004 | C86: =助手收入!$C5 -> 东关店 | D86: =科目对照收入!$B20&"" -> 积分 | E86: =IF(AND(ROUND($G86,2)<0,科目对照收入!$L20<>""),科目对照收入!$L20,科目对照收入!$C20)&"" -> 销售费用 | F86: =IF(AND(ROUND($G86,2)<0,科目对照收入!$L20<>""),科目对照收入!$M20,科目对照收入!$D20)&"" -> 积分 | G86: =ROUND(海典汇总!$R$6,2) -> 0 | H86: =IF(ROUND($G86,2)>0,ROUND($G86,2),"") | I86: =IF(ROUND($G86,2)<0,-ROUND($G86,2),"") | J86: =IF(ROUND($G86,2)=0,0,1) -> 0 | K86: =IF($J86=0,"",SUM($J$68:$J86)) | L86: =IF($K86="","",$A86*100+$K86) | M86: =参数!$B$3 -> 7月收入
A87: 4 | B87: =助手收入!$B5 -> 2004 | C87: =助手收入!$C5 -> 东关店 | D87: =科目对照收入!$B21&"" -> 手续费 | E87: =IF(AND(ROUND($G87,2)<0,科目对照收入!$L21<>""),科目对照收入!$L21,科目对照收入!$C21)&"" -> 财务费用 | F87: =IF(AND(ROUND($G87,2)<0,科目对照收入!$L21<>""),科目对照收入!$M21,科目对照收入!$D21)&"" -> 手续费 | G87: =ROUND(SUMIFS(输入聚合!$D:$D,输入聚合!$A:$A,助手收入!$X5),2) -> 13.51 | H87: =IF(ROUND($G87,2)>0,ROUND($G87,2),"") -> 13.51 | I87: =IF(ROUND($G87,2)<0,-ROUND($G87,2),"") | J87: =IF(ROUND($G87,2)=0,0,1) -> 1 | K87: =IF($J87=0,"",SUM($J$68:$J87)) -> 9 | L87: =IF($K87="","",$A87*100+$K87) -> 409 | M87: =参数!$B$3 -> 7月收入
A88: 4 | B88: =助手收入!$B5 -> 2004 | C88: =助手收入!$C5 -> 东关店 | D88: =科目对照收入!$B22&"" -> 主营业务收入 | E88: =IF(AND(ROUND($G88,2)<0,科目对照收入!$L22<>""),科目对照收入!$L22,科目对照收入!$C22)&"" -> 主营业务收入 | F88: =IF(AND(ROUND($G88,2)<0,科目对照收入!$L22<>""),科目对照收入!$M22,科目对照收入!$D22)&"" | G88: =-ROUND(助手收入!$G5,2) -> -108041.04 | H88: =IF(ROUND($G88,2)>0,ROUND($G88,2),"") | I88: =IF(ROUND($G88,2)<0,-ROUND($G88,2),"") -> 108041.04 | J88: =IF(ROUND($G88,2)=0,0,1) -> 1 | K88: =IF($J88=0,"",SUM($J$68:$J88)) -> 10 | L88: =IF($K88="","",$A88*100+$K88) -> 410 | M88: =参数!$B$3 -> 7月收入
A89: 4 | B89: =助手收入!$B5 -> 2004 | C89: =助手收入!$C5 -> 东关店 | D89: =科目对照收入!$B23&"" -> 营业外收入 | E89: =IF(AND(ROUND($G89,2)<0,科目对照收入!$L23<>""),科目对照收入!$L23,科目对照收入!$C23)&"" -> 营业外收入 | F89: =IF(AND(ROUND($G89,2)<0,科目对照收入!$L23<>""),科目对照收入!$M23,科目对照收入!$D23)&"" | G89: =-ROUND(助手收入!$J5,2) -> 0 | H89: =IF(ROUND($G89,2)>0,ROUND($G89,2),"") | I89: =IF(ROUND($G89,2)<0,-ROUND($G89,2),"") | J89: =IF(ROUND($G89,2)=0,0,1) -> 0 | K89: =IF($J89=0,"",SUM($J$68:$J89)) | L89: =IF($K89="","",$A89*100+$K89) | M89: =参数!$B$3 -> 7月收入
A90: 5 | B90: =助手收入!$B6 -> 2005 | C90: =助手收入!$C6 -> 象城街店 | D90: =科目对照收入!$B2&"" -> 库存现金 | E90: =IF(AND(ROUND($G90,2)<0,科目对照收入!$L2<>""),科目对照收入!$L2,科目对照收入!$C2)&"" -> 库存现金 | F90: =IF(AND(ROUND($G90,2)<0,科目对照收入!$L2<>""),科目对照收入!$M2,科目对照收入!$D2)&"" | G90: =助手收入!$I6 -> 63058.21 | H90: =IF(ROUND($G90,2)>0,ROUND($G90,2),"") -> 63058.21 | I90: =IF(ROUND($G90,2)<0,-ROUND($G90,2),"") | J90: =IF(ROUND($G90,2)=0,0,1) -> 1 | K90: =IF($J90=0,"",SUM($J$90:$J90)) -> 1 | L90: =IF($K90="","",$A90*100+$K90) -> 501 | M90: =参数!$B$3 -> 7月收入
A91: 5 | B91: =助手收入!$B6 -> 2005 | C91: =助手收入!$C6 -> 象城街店 | D91: =科目对照收入!$B3&"" -> 聚合支付 | E91: =IF(AND(ROUND($G91,2)<0,科目对照收入!$L3<>""),科目对照收入!$L3,科目对照收入!$C3)&"" -> 应收账款 | F91: =IF(AND(ROUND($G91,2)<0,科目对照收入!$L3<>""),科目对照收入!$M3,科目对照收入!$D3)&"" -> 聚合支付 | G91: =ROUND(SUMIFS(输入聚合!$C:$C,输入聚合!$A:$A,助手收入!$X6)-SUMIFS(输入聚合!$D:$D,输入聚合!$A:$A,助手收入!$X6),2) -> 17988.2 | H91: =IF(ROUND($G91,2)>0,ROUND($G91,2),"") -> 17988.2 | I91: =IF(ROUND($G91,2)<0,-ROUND($G91,2),"") | J91: =IF(ROUND($G91,2)=0,0,1) -> 1 | K91: =IF($J91=0,"",SUM($J$90:$J91)) -> 2 | L91: =IF($K91="","",$A91*100+$K91) -> 502 | M91: =参数!$B$3 -> 7月收入
A92: 5 | B92: =助手收入!$B6 -> 2005 | C92: =助手收入!$C6 -> 象城街店 | D92: =科目对照收入!$B4&"" -> 医保 | E92: =IF(AND(ROUND($G92,2)<0,科目对照收入!$L4<>""),科目对照收入!$L4,科目对照收入!$C4)&"" -> 应收账款 | F92: =IF(AND(ROUND($G92,2)<0,科目对照收入!$L4<>""),科目对照收入!$M4,科目对照收入!$D4)&"" -> 医保 | G92: =IF(COUNTIFS(输入平台!$A:$A,助手收入!$X6,输入平台!$B:$B,科目对照收入!$B4)>0,ROUND(SUMIFS(输入平台!$C:$C,输入平台!$A:$A,助手收入!$X6,输入平台!$B:$B,科目对照收入!$B4),2),ROUND(海典汇总!$F$7+海典汇总!$G$7,2)) -> 28845.65 | H92: =IF(ROUND($G92,2)>0,ROUND($G92,2),"") -> 28845.65 | I92: =IF(ROUND($G92,2)<0,-ROUND($G92,2),"") | J92: =IF(ROUND($G92,2)=0,0,1) -> 1 | K92: =IF($J92=0,"",SUM($J$90:$J92)) -> 3 | L92: =IF($K92="","",$A92*100+$K92) -> 503 | M92: =参数!$B$3 -> 7月收入
A93: 5 | B93: =助手收入!$B6 -> 2005 | C93: =助手收入!$C6 -> 象城街店 | D93: =科目对照收入!$B5&"" -> 健e卡 | E93: =IF(AND(ROUND($G93,2)<0,科目对照收入!$L5<>""),科目对照收入!$L5,科目对照收入!$C5)&"" -> 应收账款 | F93: =IF(AND(ROUND($G93,2)<0,科目对照收入!$L5<>""),科目对照收入!$M5,科目对照收入!$D5)&"" -> 健e卡 | G93: =IF(COUNTIFS(输入平台!$A:$A,助手收入!$X6,输入平台!$B:$B,科目对照收入!$B5)>0,ROUND(SUMIFS(输入平台!$C:$C,输入平台!$A:$A,助手收入!$X6,输入平台!$B:$B,科目对照收入!$B5),2),ROUND(海典汇总!$H$7,2)) -> 0 | H93: =IF(ROUND($G93,2)>0,ROUND($G93,2),"") | I93: =IF(ROUND($G93,2)<0,-ROUND($G93,2),"") | J93: =IF(ROUND($G93,2)=0,0,1) -> 0 | K93: =IF($J93=0,"",SUM($J$90:$J93)) | L93: =IF($K93="","",$A93*100+$K93) | M93: =参数!$B$3 -> 7月收入
A94: 5 | B94: =助手收入!$B6 -> 2005 | C94: =助手收入!$C6 -> 象城街店 | D94: =科目对照收入!$B6&"" -> 医卡通 | E94: =IF(AND(ROUND($G94,2)<0,科目对照收入!$L6<>""),科目对照收入!$L6,科目对照收入!$C6)&"" -> 应收账款 | F94: =IF(AND(ROUND($G94,2)<0,科目对照收入!$L6<>""),科目对照收入!$M6,科目对照收入!$D6)&"" -> 医卡通 | G94: =IF(COUNTIFS(输入平台!$A:$A,助手收入!$X6,输入平台!$B:$B,科目对照收入!$B6)>0,ROUND(SUMIFS(输入平台!$C:$C,输入平台!$A:$A,助手收入!$X6,输入平台!$B:$B,科目对照收入!$B6),2),ROUND(海典汇总!$I$7,2)) -> 2583.12 | H94: =IF(ROUND($G94,2)>0,ROUND($G94,2),"") -> 2583.12 | I94: =IF(ROUND($G94,2)<0,-ROUND($G94,2),"") | J94: =IF(ROUND($G94,2)=0,0,1) -> 1 | K94: =IF($J94=0,"",SUM($J$90:$J94)) -> 4 | L94: =IF($K94="","",$A94*100+$K94) -> 504 | M94: =参数!$B$3 -> 7月收入
A95: 5 | B95: =助手收入!$B6 -> 2005 | C95: =助手收入!$C6 -> 象城街店 | D95: =科目对照收入!$B7&"" -> 企健网 | E95: =IF(AND(ROUND($G95,2)<0,科目对照收入!$L7<>""),科目对照收入!$L7,科目对照收入!$C7)&"" -> 应收账款 | F95: =IF(AND(ROUND($G95,2)<0,科目对照收入!$L7<>""),科目对照收入!$M7,科目对照收入!$D7)&"" -> 企健网 | G95: =IF(COUNTIFS(输入平台!$A:$A,助手收入!$X6,输入平台!$B:$B,科目对照收入!$B7)>0,ROUND(SUMIFS(输入平台!$C:$C,输入平台!$A:$A,助手收入!$X6,输入平台!$B:$B,科目对照收入!$B7),2),ROUND(海典汇总!$J$7,2)) -> 0 | H95: =IF(ROUND($G95,2)>0,ROUND($G95,2),"") | I95: =IF(ROUND($G95,2)<0,-ROUND($G95,2),"") | J95: =IF(ROUND($G95,2)=0,0,1) -> 0 | K95: =IF($J95=0,"",SUM($J$90:$J95)) | L95: =IF($K95="","",$A95*100+$K95) | M95: =参数!$B$3 -> 7月收入
A96: 5 | B96: =助手收入!$B6 -> 2005 | C96: =助手收入!$C6 -> 象城街店 | D96: =科目对照收入!$B8&"" -> 亲情卡 | E96: =IF(AND(ROUND($G96,2)<0,科目对照收入!$L8<>""),科目对照收入!$L8,科目对照收入!$C8)&"" -> 应收账款 | F96: =IF(AND(ROUND($G96,2)<0,科目对照收入!$L8<>""),科目对照收入!$M8,科目对照收入!$D8)&"" -> 亲情卡 | G96: =IF(COUNTIFS(输入平台!$A:$A,助手收入!$X6,输入平台!$B:$B,科目对照收入!$B8)>0,ROUND(SUMIFS(输入平台!$C:$C,输入平台!$A:$A,助手收入!$X6,输入平台!$B:$B,科目对照收入!$B8),2),ROUND(海典汇总!$Z$7,2)) -> 0 | H96: =IF(ROUND($G96,2)>0,ROUND($G96,2),"") | I96: =IF(ROUND($G96,2)<0,-ROUND($G96,2),"") | J96: =IF(ROUND($G96,2)=0,0,1) -> 0 | K96: =IF($J96=0,"",SUM($J$90:$J96)) | L96: =IF($K96="","",$A96*100+$K96) | M96: =参数!$B$3 -> 7月收入
A97: 5 | B97: =助手收入!$B6 -> 2005 | C97: =助手收入!$C6 -> 象城街店 | D97: =科目对照收入!$B9&"" -> 24小时 | E97: =IF(AND(ROUND($G97,2)<0,科目对照收入!$L9<>""),科目对照收入!$L9,科目对照收入!$C9)&"" -> 应收账款 | F97: =IF(AND(ROUND($G97,2)<0,科目对照收入!$L9<>""),科目对照收入!$M9,科目对照收入!$D9)&"" -> 24小时 | G97: =IF(COUNTIFS(输入平台!$A:$A,助手收入!$X6,输入平台!$B:$B,科目对照收入!$B9)>0,ROUND(SUMIFS(输入平台!$C:$C,输入平台!$A:$A,助手收入!$X6,输入平台!$B:$B,科目对照收入!$B9),2),ROUND(海典汇总!$K$7,2)) -> 0 | H97: =IF(ROUND($G97,2)>0,ROUND($G97,2),"") | I97: =IF(ROUND($G97,2)<0,-ROUND($G97,2),"") | J97: =IF(ROUND($G97,2)=0,0,1) -> 0 | K97: =IF($J97=0,"",SUM($J$90:$J97)) | L97: =IF($K97="","",$A97*100+$K97) | M97: =参数!$B$3 -> 7月收入
A98: 5 | B98: =助手收入!$B6 -> 2005 | C98: =助手收入!$C6 -> 象城街店 | D98: =科目对照收入!$B10&"" -> 美团 | E98: =IF(AND(ROUND($G98,2)<0,科目对照收入!$L10<>""),科目对照收入!$L10,科目对照收入!$C10)&"" -> 应收账款 | F98: =IF(AND(ROUND($G98,2)<0,科目对照收入!$L10<>""),科目对照收入!$M10,科目对照收入!$D10)&"" -> 美团 | G98: =IF(COUNTIFS(输入平台!$A:$A,助手收入!$X6,输入平台!$B:$B,科目对照收入!$B10)>0,ROUND(SUMIFS(输入平台!$C:$C,输入平台!$A:$A,助手收入!$X6,输入平台!$B:$B,科目对照收入!$B10),2),ROUND(海典汇总!$M$7,2)) -> 192.6 | H98: =IF(ROUND($G98,2)>0,ROUND($G98,2),"") -> 192.6 | I98: =IF(ROUND($G98,2)<0,-ROUND($G98,2),"") | J98: =IF(ROUND($G98,2)=0,0,1) -> 1 | K98: =IF($J98=0,"",SUM($J$90:$J98)) -> 5 | L98: =IF($K98="","",$A98*100+$K98) -> 505 | M98: =参数!$B$3 -> 7月收入
A99: 5 | B99: =助手收入!$B6 -> 2005 | C99: =助手收入!$C6 -> 象城街店 | D99: =科目对照收入!$B11&"" -> 饿了么 | E99: =IF(AND(ROUND($G99,2)<0,科目对照收入!$L11<>""),科目对照收入!$L11,科目对照收入!$C11)&"" -> 应收账款 | F99: =IF(AND(ROUND($G99,2)<0,科目对照收入!$L11<>""),科目对照收入!$M11,科目对照收入!$D11)&"" -> 饿了么 | G99: =IF(COUNTIFS(输入平台!$A:$A,助手收入!$X6,输入平台!$B:$B,科目对照收入!$B11)>0,ROUND(SUMIFS(输入平台!$C:$C,输入平台!$A:$A,助手收入!$X6,输入平台!$B:$B,科目对照收入!$B11),2),ROUND(海典汇总!$N$7,2)) -> 0 | H99: =IF(ROUND($G99,2)>0,ROUND($G99,2),"") | I99: =IF(ROUND($G99,2)<0,-ROUND($G99,2),"") | J99: =IF(ROUND($G99,2)=0,0,1) -> 0 | K99: =IF($J99=0,"",SUM($J$90:$J99)) | L99: =IF($K99="","",$A99*100+$K99) | M99: =参数!$B$3 -> 7月收入
A100: 5 | B100: =助手收入!$B6 -> 2005 | C100: =助手收入!$C6 -> 象城街店 | D100: =科目对照收入!$B12&"" -> 京东秒送 | E100: =IF(AND(ROUND($G100,2)<0,科目对照收入!$L12<>""),科目对照收入!$L12,科目对照收入!$C12)&"" -> 应收账款 | F100: =IF(AND(ROUND($G100,2)<0,科目对照收入!$L12<>""),科目对照收入!$M12,科目对照收入!$D12)&"" -> 京东秒送 | G100: =IF(COUNTIFS(输入平台!$A:$A,助手收入!$X6,输入平台!$B:$B,科目对照收入!$B12)>0,ROUND(SUMIFS(输入平台!$C:$C,输入平台!$A:$A,助手收入!$X6,输入平台!$B:$B,科目对照收入!$B12),2),ROUND(海典汇总!$O$7,2)) -> 0 | H100: =IF(ROUND($G100,2)>0,ROUND($G100,2),"") | I100: =IF(ROUND($G100,2)<0,-ROUND($G100,2),"") | J100: =IF(ROUND($G100,2)=0,0,1) -> 0 | K100: =IF($J100=0,"",SUM($J$90:$J100)) | L100: =IF($K100="","",$A100*100+$K100) | M100: =参数!$B$3 -> 7月收入
...

Sheet 助手收入
A1: 店序 | B1: 门店编码 | C1: 门店简称 | D1: 日期 | E1: 网银现金 | F1: 其他借方合计 | G1: 海典销售合计 | H1: 差额 | I1: 库存现金 | J1: 营业外收入 | K1: 分录行数 | L1: 页数 | M1: 累计页 | N1: 借方合计 | O1: 贷方合计 | P1: 凭证号 | Q1: 页码 | R1: 序号 | S1: 页内序 | T1: 末页 | U1: 总页数 | V1: =SUM($L$2:$L$66) -> 78 | W1: 启用 | X1: 匹配编码
A2: 1 | B2: =IF(门店对照!$A2="","",门店对照!$A2) -> 2001 | C2: =门店对照!$C2&"" -> 柏人商城店 | D2: =参数!$B$2 -> 46234 | E2: =ROUND(SUMIFS(输入现金!$B:$B,输入现金!$A:$A,$X2),2) -> 6428.43 | F2: =ROUND(SUM(分录收入!$G$3:$G$21),2) -> 29981.08 | G2: =ROUND(海典汇总!$AE$3,2) -> 36409.51 | H2: =ROUND($E2+$F2-$G2,2) -> 0 | I2: =ROUND($E2+MAX(0,-$H2),2) -> 6428.43 | J2: =ROUND(MAX(0,$H2),2) -> 0 | K2: =SUM(分录收入!$J$2:$J$23) -> 7 | L2: =IF(OR($K2=0,$W2=0),0,ROUNDUP($K2/6,0)) -> 2 | M2: =SUM($L$2:$L2) -> 2 | N2: =ROUND(SUM(分录收入!$H$2:$H$23),2) -> 36409.51 | O2: =ROUND(SUM(分录收入!$I$2:$I$23),2) -> 36409.51 | P2: =IF($L2=0,"",COUNTIF($L$2:$L2,">0")) -> 1 | Q2: 1 | R2: =IF(1>$V$1,"",COUNTIF($M$2:$M$66,"<"&1)+1) -> 1 | S2: =IF($R2="","",1-IF($R2=1,0,INDEX($M$2:$M$66,$R2-1))) -> 1 | T2: =IF($R2="",0,IF($S2=INDEX($L$2:$L$66,$R2),1,0)) -> 0 | W2: =门店对照!$D2 -> 1 | X2: =IF($W2=1,$B2,"#未启用#") -> 2001
A3: 2 | B3: =IF(门店对照!$A3="","",门店对照!$A3) -> 2002 | C3: =门店对照!$C3&"" -> 新隆店 | D3: =参数!$B$2 -> 46234 | E3: =ROUND(SUMIFS(输入现金!$B:$B,输入现金!$A:$A,$X3),2) -> 290970.85 | F3: =ROUND(SUM(分录收入!$G$25:$G$43),2) -> 153150.6 | G3: =ROUND(海典汇总!$AE$4,2) -> 444121.45 | H3: =ROUND($E3+$F3-$G3,2) -> 0 | I3: =ROUND($E3+MAX(0,-$H3),2) -> 290970.85 | J3: =ROUND(MAX(0,$H3),2) -> 0 | K3: =SUM(分录收入!$J$24:$J$45) -> 7 | L3: =IF(OR($K3=0,$W3=0),0,ROUNDUP($K3/6,0)) -> 2 | M3: =SUM($L$2:$L3) -> 4 | N3: =ROUND(SUM(分录收入!$H$24:$H$45),2) -> 444121.45 | O3: =ROUND(SUM(分录收入!$I$24:$I$45),2) -> 444121.45 | P3: =IF($L3=0,"",COUNTIF($L$2:$L3,">0")) -> 2 | Q3: 2 | R3: =IF(2>$V$1,"",COUNTIF($M$2:$M$66,"<"&2)+1) -> 1 | S3: =IF($R3="","",2-IF($R3=1,0,INDEX($M$2:$M$66,$R3-1))) -> 2 | T3: =IF($R3="",0,IF($S3=INDEX($L$2:$L$66,$R3),1,0)) -> 1 | W3: =门店对照!$D3 -> 1 | X3: =IF($W3=1,$B3,"#未启用#") -> 2002
A4: 3 | B4: =IF(门店对照!$A4="","",门店对照!$A4) -> 2003 | C4: =门店对照!$C4&"" -> 康庄路店 | D4: =参数!$B$2 -> 46234 | E4: =ROUND(SUMIFS(输入现金!$B:$B,输入现金!$A:$A,$X4),2) -> 50121.42 | F4: =ROUND(SUM(分录收入!$G$47:$G$65),2) -> 78256.54 | G4: =ROUND(海典汇总!$AE$5,2) -> 128377.96 | H4: =ROUND($E4+$F4-$G4,2) -> 0 | I4: =ROUND($E4+MAX(0,-$H4),2) -> 50121.42 | J4: =ROUND(MAX(0,$H4),2) -> 0 | K4: =SUM(分录收入!$J$46:$J$67) -> 10 | L4: =IF(OR($K4=0,$W4=0),0,ROUNDUP($K4/6,0)) -> 2 | M4: =SUM($L$2:$L4) -> 6 | N4: =ROUND(SUM(分录收入!$H$46:$H$67),2) -> 128377.96 | O4: =ROUND(SUM(分录收入!$I$46:$I$67),2) -> 128377.96 | P4: =IF($L4=0,"",COUNTIF($L$2:$L4,">0")) -> 3 | Q4: 3 | R4: =IF(3>$V$1,"",COUNTIF($M$2:$M$66,"<"&3)+1) -> 2 | S4: =IF($R4="","",3-IF($R4=1,0,INDEX($M$2:$M$66,$R4-1))) -> 1 | T4: =IF($R4="",0,IF($S4=INDEX($L$2:$L$66,$R4),1,0)) -> 0 | W4: =门店对照!$D4 -> 1 | X4: =IF($W4=1,$B4,"#未启用#") -> 2003
A5: 4 | B5: =IF(门店对照!$A5="","",门店对照!$A5) -> 2004 | C5: =门店对照!$C5&"" -> 东关店 | D5: =参数!$B$2 -> 46234 | E5: =ROUND(SUMIFS(输入现金!$B:$B,输入现金!$A:$A,$X5),2) -> 67171.51 | F5: =ROUND(SUM(分录收入!$G$69:$G$87),2) -> 40869.53 | G5: =ROUND(海典汇总!$AE$6,2) -> 108041.04 | H5: =ROUND($E5+$F5-$G5,2) -> 0 | I5: =ROUND($E5+MAX(0,-$H5),2) -> 67171.51 | J5: =ROUND(MAX(0,$H5),2) -> 0 | K5: =SUM(分录收入!$J$68:$J$89) -> 10 | L5: =IF(OR($K5=0,$W5=0),0,ROUNDUP($K5/6,0)) -> 2 | M5: =SUM($L$2:$L5) -> 8 | N5: =ROUND(SUM(分录收入!$H$68:$H$89),2) -> 108041.04 | O5: =ROUND(SUM(分录收入!$I$68:$I$89),2) -> 108041.04 | P5: =IF($L5=0,"",COUNTIF($L$2:$L5,">0")) -> 4 | Q5: 4 | R5: =IF(4>$V$1,"",COUNTIF($M$2:$M$66,"<"&4)+1) -> 2 | S5: =IF($R5="","",4-IF($R5=1,0,INDEX($M$2:$M$66,$R5-1))) -> 2 | T5: =IF($R5="",0,IF($S5=INDEX($L$2:$L$66,$R5),1,0)) -> 1 | W5: =门店对照!$D5 -> 1 | X5: =IF($W5=1,$B5,"#未启用#") -> 2004
A6: 5 | B6: =IF(门店对照!$A6="","",门店对照!$A6) -> 2005 | C6: =门店对照!$C6&"" -> 象城街店 | D6: =参数!$B$2 -> 46234 | E6: =ROUND(SUMIFS(输入现金!$B:$B,输入现金!$A:$A,$X6),2) -> 63058.21 | F6: =ROUND(SUM(分录收入!$G$91:$G$109),2) -> 53599.69 | G6: =ROUND(海典汇总!$AE$7,2) -> 116657.9 | H6: =ROUND($E6+$F6-$G6,2) -> 0 | I6: =ROUND($E6+MAX(0,-$H6),2) -> 63058.21 | J6: =ROUND(MAX(0,$H6),2) -> 0 | K6: =SUM(分录收入!$J$90:$J$111) -> 9 | L6: =IF(OR($K6=0,$W6=0),0,ROUNDUP($K6/6,0)) -> 2 | M6: =SUM($L$2:$L6) -> 10 | N6: =ROUND(SUM(分录收入!$H$90:$H$111),2) -> 116657.9 | O6: =ROUND(SUM(分录收入!$I$90:$I$111),2) -> 116657.9 | P6: =IF($L6=0,"",COUNTIF($L$2:$L6,">0")) -> 5 | Q6: 5 | R6: =IF(5>$V$1,"",COUNTIF($M$2:$M$66,"<"&5)+1) -> 3 | S6: =IF($R6="","",5-IF($R6=1,0,INDEX($M$2:$M$66,$R6-1))) -> 1 | T6: =IF($R6="",0,IF($S6=INDEX($L$2:$L$66,$R6),1,0)) -> 0 | W6: =门店对照!$D6 -> 1 | X6: =IF($W6=1,$B6,"#未启用#") -> 2005
A7: 6 | B7: =IF(门店对照!$A7="","",门店对照!$A7) -> 2006 | C7: =门店对照!$C7&"" -> 博荣店 | D7: =参数!$B$2 -> 46234 | E7: =ROUND(SUMIFS(输入现金!$B:$B,输入现金!$A:$A,$X7),2) -> 4575.05 | F7: =ROUND(SUM(分录收入!$G$113:$G$131),2) -> 60778.57 | G7: =ROUND(海典汇总!$AE$8,2) -> 65353.62 | H7: =ROUND($E7+$F7-$G7,2) -> 0 | I7: =ROUND($E7+MAX(0,-$H7),2) -> 4575.05 | J7: =ROUND(MAX(0,$H7),2) -> 0 | K7: =SUM(分录收入!$J$112:$J$133) -> 9 | L7: =IF(OR($K7=0,$W7=0),0,ROUNDUP($K7/6,0)) -> 2 | M7: =SUM($L$2:$L7) -> 12 | N7: =ROUND(SUM(分录收入!$H$112:$H$133),2) -> 65353.62 | O7: =ROUND(SUM(分录收入!$I$112:$I$133),2) -> 65353.62 | P7: =IF($L7=0,"",COUNTIF($L$2:$L7,">0")) -> 6 | Q7: 6 | R7: =IF(6>$V$1,"",COUNTIF($M$2:$M$66,"<"&6)+1) -> 3 | S7: =IF($R7="","",6-IF($R7=1,0,INDEX($M$2:$M$66,$R7-1))) -> 2 | T7: =IF($R7="",0,IF($S7=INDEX($L$2:$L$66,$R7),1,0)) -> 1 | W7: =门店对照!$D7 -> 1 | X7: =IF($W7=1,$B7,"#未启用#") -> 2006
A8: 7 | B8: =IF(门店对照!$A8="","",门店对照!$A8) -> 2007 | C8: =门店对照!$C8&"" -> 华鑫店 | D8: =参数!$B$2 -> 46234 | E8: =ROUND(SUMIFS(输入现金!$B:$B,输入现金!$A:$A,$X8),2) -> 12722.01 | F8: =ROUND(SUM(分录收入!$G$135:$G$153),2) -> 51621.01 | G8: =ROUND(海典汇总!$AE$9,2) -> 64343.02 | H8: =ROUND($E8+$F8-$G8,2) -> 0 | I8: =ROUND($E8+MAX(0,-$H8),2) -> 12722.01 | J8: =ROUND(MAX(0,$H8),2) -> 0 | K8: =SUM(分录收入!$J$134:$J$155) -> 10 | L8: =IF(OR($K8=0,$W8=0),0,ROUNDUP($K8/6,0)) -> 2 | M8: =SUM($L$2:$L8) -> 14 | N8: =ROUND(SUM(分录收入!$H$134:$H$155),2) -> 64343.02 | O8: =ROUND(SUM(分录收入!$I$134:$I$155),2) -> 64343.02 | P8: =IF($L8=0,"",COUNTIF($L$2:$L8,">0")) -> 7 | Q8: 7 | R8: =IF(7>$V$1,"",COUNTIF($M$2:$M$66,"<"&7)+1) -> 4 | S8: =IF($R8="","",7-IF($R8=1,0,INDEX($M$2:$M$66,$R8-1))) -> 1 | T8: =IF($R8="",0,IF($S8=INDEX($L$2:$L$66,$R8),1,0)) -> 0 | W8: =门店对照!$D8 -> 1 | X8: =IF($W8=1,$B8,"#未启用#") -> 2007
A9: 8 | B9: =IF(门店对照!$A9="","",门店对照!$A9) -> 2008 | C9: =门店对照!$C9&"" -> 博昭店 | D9: =参数!$B$2 -> 46234 | E9: =ROUND(SUMIFS(输入现金!$B:$B,输入现金!$A:$A,$X9),2) -> 8028.82 | F9: =ROUND(SUM(分录收入!$G$157:$G$175),2) -> 67914.32 | G9: =ROUND(海典汇总!$AE$10,2) -> 75943.14 | H9: =ROUND($E9+$F9-$G9,2) -> 0 | I9: =ROUND($E9+MAX(0,-$H9),2) -> 8028.82 | J9: =ROUND(MAX(0,$H9),2) -> 0 | K9: =SUM(分录收入!$J$156:$J$177) -> 8 | L9: =IF(OR($K9=0,$W9=0),0,ROUNDUP($K9/6,0)) -> 2 | M9: =SUM($L$2:$L9) -> 16 | N9: =ROUND(SUM(分录收入!$H$156:$H$177),2) -> 75943.14 | O9: =ROUND(SUM(分录收入!$I$156:$I$177),2) -> 75943.14 | P9: =IF($L9=0,"",COUNTIF($L$2:$L9,">0")) -> 8 | Q9: 8 | R9: =IF(8>$V$1,"",COUNTIF($M$2:$M$66,"<"&8)+1) -> 4 | S9: =IF($R9="","",8-IF($R9=1,0,INDEX($M$2:$M$66,$R9-1))) -> 2 | T9: =IF($R9="",0,IF($S9=INDEX($L$2:$L$66,$R9),1,0)) -> 1 | W9: =门店对照!$D9 -> 1 | X9: =IF($W9=1,$B9,"#未启用#") -> 2008
A10: 9 | B10: =IF(门店对照!$A10="","",门店对照!$A10) -> 2009 | C10: =门店对照!$C10&"" -> 大霍店 | D10: =参数!$B$2 -> 46234 | E10: =ROUND(SUMIFS(输入现金!$B:$B,输入现金!$A:$A,$X10),2) -> 9880.5 | F10: =ROUND(SUM(分录收入!$G$179:$G$197),2) -> 26739.2 | G10: =ROUND(海典汇总!$AE$11,2) -> 36619.7 | H10: =ROUND($E10+$F10-$G10,2) -> 0 | I10: =ROUND($E10+MAX(0,-$H10),2) -> 9880.5 | J10: =ROUND(MAX(0,$H10),2) -> 0 | K10: =SUM(分录收入!$J$178:$J$199) -> 7 | L10: =IF(OR($K10=0,$W10=0),0,ROUNDUP($K10/6,0)) -> 2 | M10: =SUM($L$2:$L10) -> 18 | N10: =ROUND(SUM(分录收入!$H$178:$H$199),2) -> 36619.7 | O10: =ROUND(SUM(分录收入!$I$178:$I$199),2) -> 36619.7 | P10: =IF($L10=0,"",COUNTIF($L$2:$L10,">0")) -> 9 | Q10: 9 | R10: =IF(9>$V$1,"",COUNTIF($M$2:$M$66,"<"&9)+1) -> 5 | S10: =IF($R10="","",9-IF($R10=1,0,INDEX($M$2:$M$66,$R10-1))) -> 1 | T10: =IF($R10="",0,IF($S10=INDEX($L$2:$L$66,$R10),1,0)) -> 0 | W10: =门店对照!$D10 -> 1 | X10: =IF($W10=1,$B10,"#未启用#") -> 2009
A11: 10 | B11: =IF(门店对照!$A11="","",门店对照!$A11) -> 2010 | C11: =门店对照!$C11&"" -> 莲子镇店 | D11: =参数!$B$2 -> 46234 | E11: =ROUND(SUMIFS(输入现金!$B:$B,输入现金!$A:$A,$X11),2) -> 23656.79 | F11: =ROUND(SUM(分录收入!$G$201:$G$219),2) -> 83623.41 | G11: =ROUND(海典汇总!$AE$12,2) -> 107280.2 | H11: =ROUND($E11+$F11-$G11,2) -> 0 | I11: =ROUND($E11+MAX(0,-$H11),2) -> 23656.79 | J11: =ROUND(MAX(0,$H11),2) -> 0 | K11: =SUM(分录收入!$J$200:$J$221) -> 7 | L11: =IF(OR($K11=0,$W11=0),0,ROUNDUP($K11/6,0)) -> 2 | M11: =SUM($L$2:$L11) -> 20 | N11: =ROUND(SUM(分录收入!$H$200:$H$221),2) -> 107280.2 | O11: =ROUND(SUM(分录收入!$I$200:$I$221),2) -> 107280.2 | P11: =IF($L11=0,"",COUNTIF($L$2:$L11,">0")) -> 10 | Q11: 10 | R11: =IF(10>$V$1,"",COUNTIF($M$2:$M$66,"<"&10)+1) -> 5 | S11: =IF($R11="","",10-IF($R11=1,0,INDEX($M$2:$M$66,$R11-1))) -> 2 | T11: =IF($R11="",0,IF($S11=INDEX($L$2:$L$66,$R11),1,0)) -> 1 | W11: =门店对照!$D11 -> 1 | X11: =IF($W11=1,$B11,"#未启用#") -> 2010
A12: 11 | B12: =IF(门店对照!$A12="","",门店对照!$A12) -> 2011 | C12: =门店对照!$C12&"" -> 毛尔寨店 | D12: =参数!$B$2 -> 46234 | E12: =ROUND(SUMIFS(输入现金!$B:$B,输入现金!$A:$A,$X12),2) -> 24370.58 | F12: =ROUND(SUM(分录收入!$G$223:$G$241),2) -> 18452.78 | G12: =ROUND(海典汇总!$AE$13,2) -> 42823.36 | H12: =ROUND($E12+$F12-$G12,2) -> 0 | I12: =ROUND($E12+MAX(0,-$H12),2) -> 24370.58 | J12: =ROUND(MAX(0,$H12),2) -> 0 | K12: =SUM(分录收入!$J$222:$J$243) -> 7 | L12: =IF(OR($K12=0,$W12=0),0,ROUNDUP($K12/6,0)) -> 2 | M12: =SUM($L$2:$L12) -> 22 | N12: =ROUND(SUM(分录收入!$H$222:$H$243),2) -> 42823.36 | O12: =ROUND(SUM(分录收入!$I$222:$I$243),2) -> 42823.36 | P12: =IF($L12=0,"",COUNTIF($L$2:$L12,">0")) -> 11 | Q12: 11 | R12: =IF(11>$V$1,"",COUNTIF($M$2:$M$66,"<"&11)+1) -> 6 | S12: =IF($R12="","",11-IF($R12=1,0,INDEX($M$2:$M$66,$R12-1))) -> 1 | T12: =IF($R12="",0,IF($S12=INDEX($L$2:$L$66,$R12),1,0)) -> 0 | W12: =门店对照!$D12 -> 1 | X12: =IF($W12=1,$B12,"#未启用#") -> 2011
A13: 12 | B13: =IF(门店对照!$A13="","",门店对照!$A13) -> 2012 | C13: =门店对照!$C13&"" -> 泽畔店 | D13: =参数!$B$2 -> 46234 | E13: =ROUND(SUMIFS(输入现金!$B:$B,输入现金!$A:$A,$X13),2) -> 25649.6 | F13: =ROUND(SUM(分录收入!$G$245:$G$263),2) -> 24949.27 | G13: =ROUND(海典汇总!$AE$14,2) -> 50656.25 | H13: =ROUND($E13+$F13-$G13,2) -> -57.38 | I13: =ROUND($E13+MAX(0,-$H13),2) -> 25706.98 | J13: =ROUND(MAX(0,$H13),2) -> 0 | K13: =SUM(分录收入!$J$244:$J$265) -> 7 | L13: =IF(OR($K13=0,$W13=0),0,ROUNDUP($K13/6,0)) -> 2 | M13: =SUM($L$2:$L13) -> 24 | N13: =ROUND(SUM(分录收入!$H$244:$H$265),2) -> 50656.25 | O13: =ROUND(SUM(分录收入!$I$244:$I$265),2) -> 50656.25 | P13: =IF($L13=0,"",COUNTIF($L$2:$L13,">0")) -> 12 | Q13: 12 | R13: =IF(12>$V$1,"",COUNTIF($M$2:$M$66,"<"&12)+1) -> 6 | S13: =IF($R13="","",12-IF($R13=1,0,INDEX($M$2:$M$66,$R13-1))) -> 2 | T13: =IF($R13="",0,IF($S13=INDEX($L$2:$L$66,$R13),1,0)) -> 1 | W13: =门店对照!$D13 -> 1 | X13: =IF($W13=1,$B13,"#未启用#") -> 2012
A14: 13 | B14: =IF(门店对照!$A14="","",门店对照!$A14) -> 2014 | C14: =门店对照!$C14&"" -> 博桥店 | D14: =参数!$B$2 -> 46234 | E14: =ROUND(SUMIFS(输入现金!$B:$B,输入现金!$A:$A,$X14),2) -> 21123.98 | F14: =ROUND(SUM(分录收入!$G$267:$G$285),2) -> 48304.83 | G14: =ROUND(海典汇总!$AE$15,2) -> 69428.81 | H14: =ROUND($E14+$F14-$G14,2) -> 0 | I14: =ROUND($E14+MAX(0,-$H14),2) -> 21123.98 | J14: =ROUND(MAX(0,$H14),2) -> 0 | K14: =SUM(分录收入!$J$266:$J$287) -> 7 | L14: =IF(OR($K14=0,$W14=0),0,ROUNDUP($K14/6,0)) -> 2 | M14: =SUM($L$2:$L14) -> 26 | N14: =ROUND(SUM(分录收入!$H$266:$H$287),2) -> 69430.99 | O14: =ROUND(SUM(分录收入!$I$266:$I$287),2) -> 69430.99 | P14: =IF($L14=0,"",COUNTIF($L$2:$L14,">0")) -> 13 | Q14: 13 | R14: =IF(13>$V$1,"",COUNTIF($M$2:$M$66,"<"&13)+1) -> 7 | S14: =IF($R14="","",13-IF($R14=1,0,INDEX($M$2:$M$66,$R14-1))) -> 1 | T14: =IF($R14="",0,IF($S14=INDEX($L$2:$L$66,$R14),1,0)) -> 0 | W14: =门店对照!$D14 -> 1 | X14: =IF($W14=1,$B14,"#未启用#") -> 2014
A15: 14 | B15: =IF(门店对照!$A15="","",门店对照!$A15) -> 2015 | C15: =门店对照!$C15&"" -> 齐村店 | D15: =参数!$B$2 -> 46234 | E15: =ROUND(SUMIFS(输入现金!$B:$B,输入现金!$A:$A,$X15),2) -> 28193.19 | F15: =ROUND(SUM(分录收入!$G$289:$G$307),2) -> 0 | G15: =ROUND(海典汇总!$AE$16,2) -> 28193.19 | H15: =ROUND($E15+$F15-$G15,2) -> 0 | I15: =ROUND($E15+MAX(0,-$H15),2) -> 28193.19 | J15: =ROUND(MAX(0,$H15),2) -> 0 | K15: =SUM(分录收入!$J$288:$J$309) -> 2 | L15: =IF(OR($K15=0,$W15=0),0,ROUNDUP($K15/6,0)) -> 1 | M15: =SUM($L$2:$L15) -> 27 | N15: =ROUND(SUM(分录收入!$H$288:$H$309),2) -> 28193.19 | O15: =ROUND(SUM(分录收入!$I$288:$I$309),2) -> 28193.19 | P15: =IF($L15=0,"",COUNTIF($L$2:$L15,">0")) -> 14 | Q15: 14 | R15: =IF(14>$V$1,"",COUNTIF($M$2:$M$66,"<"&14)+1) -> 7 | S15: =IF($R15="","",14-IF($R15=1,0,INDEX($M$2:$M$66,$R15-1))) -> 2 | T15: =IF($R15="",0,IF($S15=INDEX($L$2:$L$66,$R15),1,0)) -> 1 | W15: =门店对照!$D15 -> 1 | X15: =IF($W15=1,$B15,"#未启用#") -> 2015
A16: 15 | B16: =IF(门店对照!$A16="","",门店对照!$A16) -> 2017 | C16: =门店对照!$C16&"" -> 博天店 | D16: =参数!$B$2 -> 46234 | E16: =ROUND(SUMIFS(输入现金!$B:$B,输入现金!$A:$A,$X16),2) -> 2922.7 | F16: =ROUND(SUM(分录收入!$G$311:$G$329),2) -> 7073.13 | G16: =ROUND(海典汇总!$AE$17,2) -> 9995.83 | H16: =ROUND($E16+$F16-$G16,2) -> 0 | I16: =ROUND($E16+MAX(0,-$H16),2) -> 2922.7 | J16: =ROUND(MAX(0,$H16),2) -> 0 | K16: =SUM(分录收入!$J$310:$J$331) -> 6 | L16: =IF(OR($K16=0,$W16=0),0,ROUNDUP($K16/6,0)) -> 1 | M16: =SUM($L$2:$L16) -> 28 | N16: =ROUND(SUM(分录收入!$H$310:$H$331),2) -> 9995.83 | O16: =ROUND(SUM(分录收入!$I$310:$I$331),2) -> 9995.83 | P16: =IF($L16=0,"",COUNTIF($L$2:$L16,">0")) -> 15 | Q16: 15 | R16: =IF(15>$V$1,"",COUNTIF($M$2:$M$66,"<"&15)+1) -> 8 | S16: =IF($R16="","",15-IF($R16=1,0,INDEX($M$2:$M$66,$R16-1))) -> 1 | T16: =IF($R16="",0,IF($S16=INDEX($L$2:$L$66,$R16),1,0)) -> 0 | W16: =门店对照!$D16 -> 1 | X16: =IF($W16=1,$B16,"#未启用#") -> 2017
A17: 16 | B17: =IF(门店对照!$A17="","",门店对照!$A17) -> 2018 | C17: =门店对照!$C17&"" -> 魏家庄店 | D17: =参数!$B$2 -> 46234 | E17: =ROUND(SUMIFS(输入现金!$B:$B,输入现金!$A:$A,$X17),2) -> 10466.07 | F17: =ROUND(SUM(分录收入!$G$333:$G$351),2) -> 27923.84 | G17: =ROUND(海典汇总!$AE$18,2) -> 38389.91 | H17: =ROUND($E17+$F17-$G17,2) -> 0 | I17: =ROUND($E17+MAX(0,-$H17),2) -> 10466.07 | J17: =ROUND(MAX(0,$H17),2) -> 0 | K17: =SUM(分录收入!$J$332:$J$353) -> 6 | L17: =IF(OR($K17=0,$W17=0),0,ROUNDUP($K17/6,0)) -> 1 | M17: =SUM($L$2:$L17) -> 29 | N17: =ROUND(SUM(分录收入!$H$332:$H$353),2) -> 38389.91 | O17: =ROUND(SUM(分录收入!$I$332:$I$353),2) -> 38389.91 | P17: =IF($L17=0,"",COUNTIF($L$2:$L17,">0")) -> 16 | Q17: 16 | R17: =IF(16>$V$1,"",COUNTIF($M$2:$M$66,"<"&16)+1) -> 8 | S17: =IF($R17="","",16-IF($R17=1,0,INDEX($M$2:$M$66,$R17-1))) -> 2 | T17: =IF($R17="",0,IF($S17=INDEX($L$2:$L$66,$R17),1,0)) -> 1 | W17: =门店对照!$D17 -> 1 | X17: =IF($W17=1,$B17,"#未启用#") -> 2018
A18: 17 | B18: =IF(门店对照!$A18="","",门店对照!$A18) -> 2022 | C18: =门店对照!$C18&"" -> 北楼店 | D18: =参数!$B$2 -> 46234 | E18: =ROUND(SUMIFS(输入现金!$B:$B,输入现金!$A:$A,$X18),2) -> 14368.55 | F18: =ROUND(SUM(分录收入!$G$355:$G$373),2) -> 56350.4 | G18: =ROUND(海典汇总!$AE$19,2) -> 70718.95 | H18: =ROUND($E18+$F18-$G18,2) -> 0 | I18: =ROUND($E18+MAX(0,-$H18),2) -> 14368.55 | J18: =ROUND(MAX(0,$H18),2) -> 0 | K18: =SUM(分录收入!$J$354:$J$375) -> 7 | L18: =IF(OR($K18=0,$W18=0),0,ROUNDUP($K18/6,0)) -> 2 | M18: =SUM($L$2:$L18) -> 31 | N18: =ROUND(SUM(分录收入!$H$354:$H$375),2) -> 70718.95 | O18: =ROUND(SUM(分录收入!$I$354:$I$375),2) -> 70718.95 | P18: =IF($L18=0,"",COUNTIF($L$2:$L18,">0")) -> 17 | Q18: 17 | R18: =IF(17>$V$1,"",COUNTIF($M$2:$M$66,"<"&17)+1) -> 9 | S18: =IF($R18="","",17-IF($R18=1,0,INDEX($M$2:$M$66,$R18-1))) -> 1 | T18: =IF($R18="",0,IF($S18=INDEX($L$2:$L$66,$R18),1,0)) -> 0 | W18: =门店对照!$D18 -> 1 | X18: =IF($W18=1,$B18,"#未启用#") -> 2022
A19: 18 | B19: =IF(门店对照!$A19="","",门店对照!$A19) -> 2023 | C19: =门店对照!$C19&"" -> 尹村店 | D19: =参数!$B$2 -> 46234 | E19: =ROUND(SUMIFS(输入现金!$B:$B,输入现金!$A:$A,$X19),2) -> 10365.03 | F19: =ROUND(SUM(分录收入!$G$377:$G$395),2) -> 42104.09 | G19: =ROUND(海典汇总!$AE$20,2) -> 52469.12 | H19: =ROUND($E19+$F19-$G19,2) -> 0 | I19: =ROUND($E19+MAX(0,-$H19),2) -> 10365.03 | J19: =ROUND(MAX(0,$H19),2) -> 0 | K19: =SUM(分录收入!$J$376:$J$397) -> 7 | L19: =IF(OR($K19=0,$W19=0),0,ROUNDUP($K19/6,0)) -> 2 | M19: =SUM($L$2:$L19) -> 33 | N19: =ROUND(SUM(分录收入!$H$376:$H$397),2) -> 52469.12 | O19: =ROUND(SUM(分录收入!$I$376:$I$397),2) -> 52469.12 | P19: =IF($L19=0,"",COUNTIF($L$2:$L19,">0")) -> 18 | Q19: 18 | R19: =IF(18>$V$1,"",COUNTIF($M$2:$M$66,"<"&18)+1) -> 9 | S19: =IF($R19="","",18-IF($R19=1,0,INDEX($M$2:$M$66,$R19-1))) -> 2 | T19: =IF($R19="",0,IF($S19=INDEX($L$2:$L$66,$R19),1,0)) -> 1 | W19: =门店对照!$D19 -> 1 | X19: =IF($W19=1,$B19,"#未启用#") -> 2023
A20: 19 | B20: =IF(门店对照!$A20="","",门店对照!$A20) -> 2024 | C20: =门店对照!$C20&"" -> 高村店 | D20: =参数!$B$2 -> 46234 | E20: =ROUND(SUMIFS(输入现金!$B:$B,输入现金!$A:$A,$X20),2) -> 38459.74 | F20: =ROUND(SUM(分录收入!$G$399:$G$417),2) -> 63418.18 | G20: =ROUND(海典汇总!$AE$21,2) -> 101877.92 | H20: =ROUND($E20+$F20-$G20,2) -> 0 | I20: =ROUND($E20+MAX(0,-$H20),2) -> 38459.74 | J20: =ROUND(MAX(0,$H20),2) -> 0 | K20: =SUM(分录收入!$J$398:$J$419) -> 7 | L20: =IF(OR($K20=0,$W20=0),0,ROUNDUP($K20/6,0)) -> 2 | M20: =SUM($L$2:$L20) -> 35 | N20: =ROUND(SUM(分录收入!$H$398:$H$419),2) -> 101877.92 | O20: =ROUND(SUM(分录收入!$I$398:$I$419),2) -> 101877.92 | P20: =IF($L20=0,"",COUNTIF($L$2:$L20,">0")) -> 19 | Q20: 19 | R20: =IF(19>$V$1,"",COUNTIF($M$2:$M$66,"<"&19)+1) -> 10 | S20: =IF($R20="","",19-IF($R20=1,0,INDEX($M$2:$M$66,$R20-1))) -> 1 | T20: =IF($R20="",0,IF($S20=INDEX($L$2:$L$66,$R20),1,0)) -> 0 | W20: =门店对照!$D20 -> 1 | X20: =IF($W20=1,$B20,"#未启用#") -> 2024
A21: 20 | B21: =IF(门店对照!$A21="","",门店对照!$A21) -> 2026 | C21: =门店对照!$C21&"" -> 彭村店 | D21: =参数!$B$2 -> 46234 | E21: =ROUND(SUMIFS(输入现金!$B:$B,输入现金!$A:$A,$X21),2) -> 7900.28 | F21: =ROUND(SUM(分录收入!$G$421:$G$439),2) -> 27345.42 | G21: =ROUND(海典汇总!$AE$22,2) -> 35245.7 | H21: =ROUND($E21+$F21-$G21,2) -> 0 | I21: =ROUND($E21+MAX(0,-$H21),2) -> 7900.28 | J21: =ROUND(MAX(0,$H21),2) -> 0 | K21: =SUM(分录收入!$J$420:$J$441) -> 7 | L21: =IF(OR($K21=0,$W21=0),0,ROUNDUP($K21/6,0)) -> 2 | M21: =SUM($L$2:$L21) -> 37 | N21: =ROUND(SUM(分录收入!$H$420:$H$441),2) -> 35245.9 | O21: =ROUND(SUM(分录收入!$I$420:$I$441),2) -> 35245.9 | P21: =IF($L21=0,"",COUNTIF($L$2:$L21,">0")) -> 20 | Q21: 20 | R21: =IF(20>$V$1,"",COUNTIF($M$2:$M$66,"<"&20)+1) -> 10 | S21: =IF($R21="","",20-IF($R21=1,0,INDEX($M$2:$M$66,$R21-1))) -> 2 | T21: =IF($R21="",0,IF($S21=INDEX($L$2:$L$66,$R21),1,0)) -> 1 | W21: =门店对照!$D21 -> 1 | X21: =IF($W21=1,$B21,"#未启用#") -> 2026
A22: 21 | B22: =IF(门店对照!$A22="","",门店对照!$A22) -> 2030 | C22: =门店对照!$C22&"" -> 南位店 | D22: =参数!$B$2 -> 46234 | E22: =ROUND(SUMIFS(输入现金!$B:$B,输入现金!$A:$A,$X22),2) -> 10577.51 | F22: =ROUND(SUM(分录收入!$G$443:$G$461),2) -> 21300.54 | G22: =ROUND(海典汇总!$AE$23,2) -> 31878.05 | H22: =ROUND($E22+$F22-$G22,2) -> 0 | I22: =ROUND($E22+MAX(0,-$H22),2) -> 10577.51 | J22: =ROUND(MAX(0,$H22),2) -> 0 | K22: =SUM(分录收入!$J$442:$J$463) -> 8 | L22: =IF(OR($K22=0,$W22=0),0,ROUNDUP($K22/6,0)) -> 2 | M22: =SUM($L$2:$L22) -> 39 | N22: =ROUND(SUM(分录收入!$H$442:$H$463),2) -> 31878.75 | O22: =ROUND(SUM(分录收入!$I$442:$I$463),2) -> 31878.75 | P22: =IF($L22=0,"",COUNTIF($L$2:$L22,">0")) -> 21 | Q22: 21 | R22: =IF(21>$V$1,"",COUNTIF($M$2:$M$66,"<"&21)+1) -> 11 | S22: =IF($R22="","",21-IF($R22=1,0,INDEX($M$2:$M$66,$R22-1))) -> 1 | T22: =IF($R22="",0,IF($S22=INDEX($L$2:$L$66,$R22),1,0)) -> 0 | W22: =门店对照!$D22 -> 1 | X22: =IF($W22=1,$B22,"#未启用#") -> 2030
A23: 22 | B23: =IF(门店对照!$A23="","",门店对照!$A23) -> 2032 | C23: =门店对照!$C23&"" -> 博园店 | D23: =参数!$B$2 -> 46234 | E23: =ROUND(SUMIFS(输入现金!$B:$B,输入现金!$A:$A,$X23),2) -> 8260.86 | F23: =ROUND(SUM(分录收入!$G$465:$G$483),2) -> 35441.65 | G23: =ROUND(海典汇总!$AE$24,2) -> 43702.51 | H23: =ROUND($E23+$F23-$G23,2) -> 0 | I23: =ROUND($E23+MAX(0,-$H23),2) -> 8260.86 | J23: =ROUND(MAX(0,$H23),2) -> 0 | K23: =SUM(分录收入!$J$464:$J$485) -> 7 | L23: =IF(OR($K23=0,$W23=0),0,ROUNDUP($K23/6,0)) -> 2 | M23: =SUM($L$2:$L23) -> 41 | N23: =ROUND(SUM(分录收入!$H$464:$H$485),2) -> 43702.51 | O23: =ROUND(SUM(分录收入!$I$464:$I$485),2) -> 43702.51 | P23: =IF($L23=0,"",COUNTIF($L$2:$L23,">0")) -> 22 | Q23: 22 | R23: =IF(22>$V$1,"",COUNTIF($M$2:$M$66,"<"&22)+1) -> 11 | S23: =IF($R23="","",22-IF($R23=1,0,INDEX($M$2:$M$66,$R23-1))) -> 2 | T23: =IF($R23="",0,IF($S23=INDEX($L$2:$L$66,$R23),1,0)) -> 1 | W23: =门店对照!$D23 -> 1 | X23: =IF($W23=1,$B23,"#未启用#") -> 2032
A24: 23 | B24: =IF(门店对照!$A24="","",门店对照!$A24) -> 2036 | C24: =门店对照!$C24&"" -> 黑城店 | D24: =参数!$B$2 -> 46234 | E24: =ROUND(SUMIFS(输入现金!$B:$B,输入现金!$A:$A,$X24),2) -> 0 | F24: =ROUND(SUM(分录收入!$G$487:$G$505),2) -> 0 | G24: =ROUND(海典汇总!$AE$25,2) -> 0 | H24: =ROUND($E24+$F24-$G24,2) -> 0 | I24: =ROUND($E24+MAX(0,-$H24),2) -> 0 | J24: =ROUND(MAX(0,$H24),2) -> 0 | K24: =SUM(分录收入!$J$486:$J$507) -> 0 | L24: =IF(OR($K24=0,$W24=0),0,ROUNDUP($K24/6,0)) -> 0 | M24: =SUM($L$2:$L24) -> 41 | N24: =ROUND(SUM(分录收入!$H$486:$H$507),2) -> 0 | O24: =ROUND(SUM(分录收入!$I$486:$I$507),2) -> 0 | P24: =IF($L24=0,"",COUNTIF($L$2:$L24,">0")) | Q24: 23 | R24: =IF(23>$V$1,"",COUNTIF($M$2:$M$66,"<"&23)+1) -> 12 | S24: =IF($R24="","",23-IF($R24=1,0,INDEX($M$2:$M$66,$R24-1))) -> 1 | T24: =IF($R24="",0,IF($S24=INDEX($L$2:$L$66,$R24),1,0)) -> 0 | W24: =门店对照!$D24 -> 1 | X24: =IF($W24=1,$B24,"#未启用#") -> 2036
A25: 24 | B25: =IF(门店对照!$A25="","",门店对照!$A25) -> 2037 | C25: =门店对照!$C25&"" -> 新华路店 | D25: =参数!$B$2 -> 46234 | E25: =ROUND(SUMIFS(输入现金!$B:$B,输入现金!$A:$A,$X25),2) -> 9545.13 | F25: =ROUND(SUM(分录收入!$G$509:$G$527),2) -> 47574.63 | G25: =ROUND(海典汇总!$AE$26,2) -> 57119.76 | H25: =ROUND($E25+$F25-$G25,2) -> 0 | I25: =ROUND($E25+MAX(0,-$H25),2) -> 9545.13 | J25: =ROUND(MAX(0,$H25),2) -> 0 | K25: =SUM(分录收入!$J$508:$J$529) -> 12 | L25: =IF(OR($K25=0,$W25=0),0,ROUNDUP($K25/6,0)) -> 2 | M25: =SUM($L$2:$L25) -> 43 | N25: =ROUND(SUM(分录收入!$H$508:$H$529),2) -> 57119.76 | O25: =ROUND(SUM(分录收入!$I$508:$I$529),2) -> 57119.76 | P25: =IF($L25=0,"",COUNTIF($L$2:$L25,">0")) -> 23 | Q25: 24 | R25: =IF(24>$V$1,"",COUNTIF($M$2:$M$66,"<"&24)+1) -> 12 | S25: =IF($R25="","",24-IF($R25=1,0,INDEX($M$2:$M$66,$R25-1))) -> 2 | T25: =IF($R25="",0,IF($S25=INDEX($L$2:$L$66,$R25),1,0)) -> 1 | W25: =门店对照!$D25 -> 1 | X25: =IF($W25=1,$B25,"#未启用#") -> 2037
A26: 25 | B26: =IF(门店对照!$A26="","",门店对照!$A26) -> 2038 | C26: =门店对照!$C26&"" -> 杨村王街店 | D26: =参数!$B$2 -> 46234 | E26: =ROUND(SUMIFS(输入现金!$B:$B,输入现金!$A:$A,$X26),2) -> 9460.39 | F26: =ROUND(SUM(分录收入!$G$531:$G$549),2) -> 27522.01 | G26: =ROUND(海典汇总!$AE$27,2) -> 36982.4 | H26: =ROUND($E26+$F26-$G26,2) -> 0 | I26: =ROUND($E26+MAX(0,-$H26),2) -> 9460.39 | J26: =ROUND(MAX(0,$H26),2) -> 0 | K26: =SUM(分录收入!$J$530:$J$551) -> 7 | L26: =IF(OR($K26=0,$W26=0),0,ROUNDUP($K26/6,0)) -> 2 | M26: =SUM($L$2:$L26) -> 45 | N26: =ROUND(SUM(分录收入!$H$530:$H$551),2) -> 36982.4 | O26: =ROUND(SUM(分录收入!$I$530:$I$551),2) -> 36982.4 | P26: =IF($L26=0,"",COUNTIF($L$2:$L26,">0")) -> 24 | Q26: 25 | R26: =IF(25>$V$1,"",COUNTIF($M$2:$M$66,"<"&25)+1) -> 13 | S26: =IF($R26="","",25-IF($R26=1,0,INDEX($M$2:$M$66,$R26-1))) -> 1 | T26: =IF($R26="",0,IF($S26=INDEX($L$2:$L$66,$R26),1,0)) -> 0 | W26: =门店对照!$D26 -> 1 | X26: =IF($W26=1,$B26,"#未启用#") -> 2038
A27: 26 | B27: =IF(门店对照!$A27="","",门店对照!$A27) -> 2039 | C27: =门店对照!$C27&"" -> 千户营店 | D27: =参数!$B$2 -> 46234 | E27: =ROUND(SUMIFS(输入现金!$B:$B,输入现金!$A:$A,$X27),2) -> 27210.58 | F27: =ROUND(SUM(分录收入!$G$553:$G$571),2) -> 46706.84 | G27: =ROUND(海典汇总!$AE$28,2) -> 73917.42 | H27: =ROUND($E27+$F27-$G27,2) -> 0 | I27: =ROUND($E27+MAX(0,-$H27),2) -> 27210.58 | J27: =ROUND(MAX(0,$H27),2) -> 0 | K27: =SUM(分录收入!$J$552:$J$573) -> 7 | L27: =IF(OR($K27=0,$W27=0),0,ROUNDUP($K27/6,0)) -> 2 | M27: =SUM($L$2:$L27) -> 47 | N27: =ROUND(SUM(分录收入!$H$552:$H$573),2) -> 73917.68 | O27: =ROUND(SUM(分录收入!$I$552:$I$573),2) -> 73917.68 | P27: =IF($L27=0,"",COUNTIF($L$2:$L27,">0")) -> 25 | Q27: 26 | R27: =IF(26>$V$1,"",COUNTIF($M$2:$M$66,"<"&26)+1) -> 13 | S27: =IF($R27="","",26-IF($R27=1,0,INDEX($M$2:$M$66,$R27-1))) -> 2 | T27: =IF($R27="",0,IF($S27=INDEX($L$2:$L$66,$R27),1,0)) -> 1 | W27: =门店对照!$D27 -> 1 | X27: =IF($W27=1,$B27,"#未启用#") -> 2039
A28: 27 | B28: =IF(门店对照!$A28="","",门店对照!$A28) -> 2040 | C28: =门店对照!$C28&"" -> 大张庄店 | D28: =参数!$B$2 -> 46234 | E28: =ROUND(SUMIFS(输入现金!$B:$B,输入现金!$A:$A,$X28),2) -> 24616.18 | F28: =ROUND(SUM(分录收入!$G$575:$G$593),2) -> 67734.33 | G28: =ROUND(海典汇总!$AE$29,2) -> 92350.51 | H28: =ROUND($E28+$F28-$G28,2) -> 0 | I28: =ROUND($E28+MAX(0,-$H28),2) -> 24616.18 | J28: =ROUND(MAX(0,$H28),2) -> 0 | K28: =SUM(分录收入!$J$574:$J$595) -> 8 | L28: =IF(OR($K28=0,$W28=0),0,ROUNDUP($K28/6,0)) -> 2 | M28: =SUM($L$2:$L28) -> 49 | N28: =ROUND(SUM(分录收入!$H$574:$H$595),2) -> 92351.66 | O28: =ROUND(SUM(分录收入!$I$574:$I$595),2) -> 92351.66 | P28: =IF($L28=0,"",COUNTIF($L$2:$L28,">0")) -> 26 | Q28: 27 | R28: =IF(27>$V$1,"",COUNTIF($M$2:$M$66,"<"&27)+1) -> 14 | S28: =IF($R28="","",27-IF($R28=1,0,INDEX($M$2:$M$66,$R28-1))) -> 1 | T28: =IF($R28="",0,IF($S28=INDEX($L$2:$L$66,$R28),1,0)) -> 1 | W28: =门店对照!$D28 -> 1 | X28: =IF($W28=1,$B28,"#未启用#") -> 2040
A29: 28 | B29: =IF(门店对照!$A29="","",门店对照!$A29) -> 2041 | C29: =门店对照!$C29&"" -> 郝庄店 | D29: =参数!$B$2 -> 46234 | E29: =ROUND(SUMIFS(输入现金!$B:$B,输入现金!$A:$A,$X29),2) -> 14774.25 | F29: =ROUND(SUM(分录收入!$G$597:$G$615),2) -> 38859.27 | G29: =ROUND(海典汇总!$AE$30,2) -> 53633.52 | H29: =ROUND($E29+$F29-$G29,2) -> 0 | I29: =ROUND($E29+MAX(0,-$H29),2) -> 14774.25 | J29: =ROUND(MAX(0,$H29),2) -> 0 | K29: =SUM(分录收入!$J$596:$J$617) -> 7 | L29: =IF(OR($K29=0,$W29=0),0,ROUNDUP($K29/6,0)) -> 2 | M29: =SUM($L$2:$L29) -> 51 | N29: =ROUND(SUM(分录收入!$H$596:$H$617),2) -> 53642.88 | O29: =ROUND(SUM(分录收入!$I$596:$I$617),2) -> 53642.88 | P29: =IF($L29=0,"",COUNTIF($L$2:$L29,">0")) -> 27 | Q29: 28 | R29: =IF(28>$V$1,"",COUNTIF($M$2:$M$66,"<"&28)+1) -> 15 | S29: =IF($R29="","",28-IF($R29=1,0,INDEX($M$2:$M$66,$R29-1))) -> 1 | T29: =IF($R29="",0,IF($S29=INDEX($L$2:$L$66,$R29),1,0)) -> 1 | W29: =门店对照!$D29 -> 1 | X29: =IF($W29=1,$B29,"#未启用#") -> 2041
A30: 29 | B30: =IF(门店对照!$A30="","",门店对照!$A30) -> 2042 | C30: =门店对照!$C30&"" -> 白家寨店 | D30: =参数!$B$2 -> 46234 | E30: =ROUND(SUMIFS(输入现金!$B:$B,输入现金!$A:$A,$X30),2) -> 14901.93 | F30: =ROUND(SUM(分录收入!$G$619:$G$637),2) -> 34756.07 | G30: =ROUND(海典汇总!$AE$31,2) -> 49658 | H30: =ROUND($E30+$F30-$G30,2) -> 0 | I30: =ROUND($E30+MAX(0,-$H30),2) -> 14901.93 | J30: =ROUND(MAX(0,$H30),2) -> 0 | K30: =SUM(分录收入!$J$618:$J$639) -> 7 | L30: =IF(OR($K30=0,$W30=0),0,ROUNDUP($K30/6,0)) -> 2 | M30: =SUM($L$2:$L30) -> 53 | N30: =ROUND(SUM(分录收入!$H$618:$H$639),2) -> 49658 | O30: =ROUND(SUM(分录收入!$I$618:$I$639),2) -> 49658 | P30: =IF($L30=0,"",COUNTIF($L$2:$L30,">0")) -> 28 | Q30: 29 | R30: =IF(29>$V$1,"",COUNTIF($M$2:$M$66,"<"&29)+1) -> 16 | S30: =IF($R30="","",29-IF($R30=1,0,INDEX($M$2:$M$66,$R30-1))) -> 1 | T30: =IF($R30="",0,IF($S30=INDEX($L$2:$L$66,$R30),1,0)) -> 1 | W30: =门店对照!$D30 -> 1 | X30: =IF($W30=1,$B30,"#未启用#") -> 2042
A31: 30 | B31: =IF(门店对照!$A31="","",门店对照!$A31) -> 2043 | C31: =门店对照!$C31&"" -> 博福店 | D31: =参数!$B$2 -> 46234 | E31: =ROUND(SUMIFS(输入现金!$B:$B,输入现金!$A:$A,$X31),2) -> 5461.07 | F31: =ROUND(SUM(分录收入!$G$641:$G$659),2) -> 64744.68 | G31: =ROUND(海典汇总!$AE$32,2) -> 70205.75 | H31: =ROUND($E31+$F31-$G31,2) -> 0 | I31: =ROUND($E31+MAX(0,-$H31),2) -> 5461.07 | J31: =ROUND(MAX(0,$H31),2) -> 0 | K31: =SUM(分录收入!$J$640:$J$661) -> 10 | L31: =IF(OR($K31=0,$W31=0),0,ROUNDUP($K31/6,0)) -> 2 | M31: =SUM($L$2:$L31) -> 55 | N31: =ROUND(SUM(分录收入!$H$640:$H$661),2) -> 70205.75 | O31: =ROUND(SUM(分录收入!$I$640:$I$661),2) -> 70205.75 | P31: =IF($L31=0,"",COUNTIF($L$2:$L31,">0")) -> 29 | Q31: 30 | R31: =IF(30>$V$1,"",COUNTIF($M$2:$M$66,"<"&30)+1) -> 17 | S31: =IF($R31="","",30-IF($R31=1,0,INDEX($M$2:$M$66,$R31-1))) -> 1 | T31: =IF($R31="",0,IF($S31=INDEX($L$2:$L$66,$R31),1,0)) -> 0 | W31: =门店对照!$D31 -> 1 | X31: =IF($W31=1,$B31,"#未启用#") -> 2043
A32: 31 | B32: =IF(门店对照!$A32="","",门店对照!$A32) -> 2044 | C32: =门店对照!$C32&"" -> 博营店 | D32: =参数!$B$2 -> 46234 | E32: =ROUND(SUMIFS(输入现金!$B:$B,输入现金!$A:$A,$X32),2) -> 14656.89 | F32: =ROUND(SUM(分录收入!$G$663:$G$681),2) -> 22686.02 | G32: =ROUND(海典汇总!$AE$33,2) -> 37342.91 | H32: =ROUND($E32+$F32-$G32,2) -> 0 | I32: =ROUND($E32+MAX(0,-$H32),2) -> 14656.89 | J32: =ROUND(MAX(0,$H32),2) -> 0 | K32: =SUM(分录收入!$J$662:$J$683) -> 6 | L32: =IF(OR($K32=0,$W32=0),0,ROUNDUP($K32/6,0)) -> 1 | M32: =SUM($L$2:$L32) -> 56 | N32: =ROUND(SUM(分录收入!$H$662:$H$683),2) -> 37342.91 | O32: =ROUND(SUM(分录收入!$I$662:$I$683),2) -> 37342.91 | P32: =IF($L32=0,"",COUNTIF($L$2:$L32,">0")) -> 30 | Q32: 31 | R32: =IF(31>$V$1,"",COUNTIF($M$2:$M$66,"<"&31)+1) -> 17 | S32: =IF($R32="","",31-IF($R32=1,0,INDEX($M$2:$M$66,$R32-1))) -> 2 | T32: =IF($R32="",0,IF($S32=INDEX($L$2:$L$66,$R32),1,0)) -> 1 | W32: =门店对照!$D32 -> 1 | X32: =IF($W32=1,$B32,"#未启用#") -> 2044
A33: 32 | B33: =IF(门店对照!$A33="","",门店对照!$A33) -> 2046 | C33: =门店对照!$C33&"" -> 博康店 | D33: =参数!$B$2 -> 46234 | E33: =ROUND(SUMIFS(输入现金!$B:$B,输入现金!$A:$A,$X33),2) -> 5048.45 | F33: =ROUND(SUM(分录收入!$G$685:$G$703),2) -> 20380.25 | G33: =ROUND(海典汇总!$AE$34,2) -> 25428.7 | H33: =ROUND($E33+$F33-$G33,2) -> 0 | I33: =ROUND($E33+MAX(0,-$H33),2) -> 5048.45 | J33: =ROUND(MAX(0,$H33),2) -> 0 | K33: =SUM(分录收入!$J$684:$J$705) -> 8 | L33: =IF(OR($K33=0,$W33=0),0,ROUNDUP($K33/6,0)) -> 2 | M33: =SUM($L$2:$L33) -> 58 | N33: =ROUND(SUM(分录收入!$H$684:$H$705),2) -> 25428.7 | O33: =ROUND(SUM(分录收入!$I$684:$I$705),2) -> 25428.7 | P33: =IF($L33=0,"",COUNTIF($L$2:$L33,">0")) -> 31 | Q33: 32 | R33: =IF(32>$V$1,"",COUNTIF($M$2:$M$66,"<"&32)+1) -> 18 | S33: =IF($R33="","",32-IF($R33=1,0,INDEX($M$2:$M$66,$R33-1))) -> 1 | T33: =IF($R33="",0,IF($S33=INDEX($L$2:$L$66,$R33),1,0)) -> 0 | W33: =门店对照!$D33 -> 1 | X33: =IF($W33=1,$B33,"#未启用#") -> 2046
A34: 33 | B34: =IF(门店对照!$A34="","",门店对照!$A34) -> 2047 | C34: =门店对照!$C34&"" -> 博联店 | D34: =参数!$B$2 -> 46234 | E34: =ROUND(SUMIFS(输入现金!$B:$B,输入现金!$A:$A,$X34),2) -> 2872.93 | F34: =ROUND(SUM(分录收入!$G$707:$G$725),2) -> 18049.74 | G34: =ROUND(海典汇总!$AE$35,2) -> 20922.67 | H34: =ROUND($E34+$F34-$G34,2) -> 0 | I34: =ROUND($E34+MAX(0,-$H34),2) -> 2872.93 | J34: =ROUND(MAX(0,$H34),2) -> 0 | K34: =SUM(分录收入!$J$706:$J$727) -> 6 | L34: =IF(OR($K34=0,$W34=0),0,ROUNDUP($K34/6,0)) -> 1 | M34: =SUM($L$2:$L34) -> 59 | N34: =ROUND(SUM(分录收入!$H$706:$H$727),2) -> 20922.67 | O34: =ROUND(SUM(分录收入!$I$706:$I$727),2) -> 20922.67 | P34: =IF($L34=0,"",COUNTIF($L$2:$L34,">0")) -> 32 | Q34: 33 | R34: =IF(33>$V$1,"",COUNTIF($M$2:$M$66,"<"&33)+1) -> 18 | S34: =IF($R34="","",33-IF($R34=1,0,INDEX($M$2:$M$66,$R34-1))) -> 2 | T34: =IF($R34="",0,IF($S34=INDEX($L$2:$L$66,$R34),1,0)) -> 1 | W34: =门店对照!$D34 -> 1 | X34: =IF($W34=1,$B34,"#未启用#") -> 2047
A35: 34 | B35: =IF(门店对照!$A35="","",门店对照!$A35) -> 2050 | C35: =门店对照!$C35&"" -> 博尚店 | D35: =参数!$B$2 -> 46234 | E35: =ROUND(SUMIFS(输入现金!$B:$B,输入现金!$A:$A,$X35),2) -> 4767.69 | F35: =ROUND(SUM(分录收入!$G$729:$G$747),2) -> 27112.08 | G35: =ROUND(海典汇总!$AE$36,2) -> 31879.77 | H35: =ROUND($E35+$F35-$G35,2) -> 0 | I35: =ROUND($E35+MAX(0,-$H35),2) -> 4767.69 | J35: =ROUND(MAX(0,$H35),2) -> 0 | K35: =SUM(分录收入!$J$728:$J$749) -> 9 | L35: =IF(OR($K35=0,$W35=0),0,ROUNDUP($K35/6,0)) -> 2 | M35: =SUM($L$2:$L35) -> 61 | N35: =ROUND(SUM(分录收入!$H$728:$H$749),2) -> 31879.77 | O35: =ROUND(SUM(分录收入!$I$728:$I$749),2) -> 31879.77 | P35: =IF($L35=0,"",COUNTIF($L$2:$L35,">0")) -> 33 | Q35: 34 | R35: =IF(34>$V$1,"",COUNTIF($M$2:$M$66,"<"&34)+1) -> 19 | S35: =IF($R35="","",34-IF($R35=1,0,INDEX($M$2:$M$66,$R35-1))) -> 1 | T35: =IF($R35="",0,IF($S35=INDEX($L$2:$L$66,$R35),1,0)) -> 0 | W35: =门店对照!$D35 -> 1 | X35: =IF($W35=1,$B35,"#未启用#") -> 2050
A36: 35 | B36: =IF(门店对照!$A36="","",门店对照!$A36) -> 2053 | C36: =门店对照!$C36&"" -> 博鑫店 | D36: =参数!$B$2 -> 46234 | E36: =ROUND(SUMIFS(输入现金!$B:$B,输入现金!$A:$A,$X36),2) -> 6527.6 | F36: =ROUND(SUM(分录收入!$G$751:$G$769),2) -> 34704.99 | G36: =ROUND(海典汇总!$AE$37,2) -> 41232.59 | H36: =ROUND($E36+$F36-$G36,2) -> 0 | I36: =ROUND($E36+MAX(0,-$H36),2) -> 6527.6 | J36: =ROUND(MAX(0,$H36),2) -> 0 | K36: =SUM(分录收入!$J$750:$J$771) -> 9 | L36: =IF(OR($K36=0,$W36=0),0,ROUNDUP($K36/6,0)) -> 2 | M36: =SUM($L$2:$L36) -> 63 | N36: =ROUND(SUM(分录收入!$H$750:$H$771),2) -> 41233.43 | O36: =ROUND(SUM(分录收入!$I$750:$I$771),2) -> 41233.43 | P36: =IF($L36=0,"",COUNTIF($L$2:$L36,">0")) -> 34 | Q36: 35 | R36: =IF(35>$V$1,"",COUNTIF($M$2:$M$66,"<"&35)+1) -> 19 | S36: =IF($R36="","",35-IF($R36=1,0,INDEX($M$2:$M$66,$R36-1))) -> 2 | T36: =IF($R36="",0,IF($S36=INDEX($L$2:$L$66,$R36),1,0)) -> 1 | W36: =门店对照!$D36 -> 1 | X36: =IF($W36=1,$B36,"#未启用#") -> 2053
A37: 36 | B37: =IF(门店对照!$A37="","",门店对照!$A37) -> 2055 | C37: =门店对照!$C37&"" -> 博魏店 | D37: =参数!$B$2 -> 46234 | E37: =ROUND(SUMIFS(输入现金!$B:$B,输入现金!$A:$A,$X37),2) -> 10010.43 | F37: =ROUND(SUM(分录收入!$G$773:$G$791),2) -> 25702.02 | G37: =ROUND(海典汇总!$AE$38,2) -> 35712.45 | H37: =ROUND($E37+$F37-$G37,2) -> 0 | I37: =ROUND($E37+MAX(0,-$H37),2) -> 10010.43 | J37: =ROUND(MAX(0,$H37),2) -> 0 | K37: =SUM(分录收入!$J$772:$J$793) -> 6 | L37: =IF(OR($K37=0,$W37=0),0,ROUNDUP($K37/6,0)) -> 1 | M37: =SUM($L$2:$L37) -> 64 | N37: =ROUND(SUM(分录收入!$H$772:$H$793),2) -> 35712.45 | O37: =ROUND(SUM(分录收入!$I$772:$I$793),2) -> 35712.45 | P37: =IF($L37=0,"",COUNTIF($L$2:$L37,">0")) -> 35 | Q37: 36 | R37: =IF(36>$V$1,"",COUNTIF($M$2:$M$66,"<"&36)+1) -> 20 | S37: =IF($R37="","",36-IF($R37=1,0,INDEX($M$2:$M$66,$R37-1))) -> 1 | T37: =IF($R37="",0,IF($S37=INDEX($L$2:$L$66,$R37),1,0)) -> 0 | W37: =门店对照!$D37 -> 1 | X37: =IF($W37=1,$B37,"#未启用#") -> 2055
A38: 37 | B38: =IF(门店对照!$A38="","",门店对照!$A38) -> 2057 | C38: =门店对照!$C38&"" -> 博城店 | D38: =参数!$B$2 -> 46234 | E38: =ROUND(SUMIFS(输入现金!$B:$B,输入现金!$A:$A,$X38),2) -> 35773.47 | F38: =ROUND(SUM(分录收入!$G$795:$G$813),2) -> 16052.29 | G38: =ROUND(海典汇总!$AE$39,2) -> 51825.76 | H38: =ROUND($E38+$F38-$G38,2) -> 0 | I38: =ROUND($E38+MAX(0,-$H38),2) -> 35773.47 | J38: =ROUND(MAX(0,$H38),2) -> 0 | K38: =SUM(分录收入!$J$794:$J$815) -> 6 | L38: =IF(OR($K38=0,$W38=0),0,ROUNDUP($K38/6,0)) -> 1 | M38: =SUM($L$2:$L38) -> 65 | N38: =ROUND(SUM(分录收入!$H$794:$H$815),2) -> 51826.76 | O38: =ROUND(SUM(分录收入!$I$794:$I$815),2) -> 51826.76 | P38: =IF($L38=0,"",COUNTIF($L$2:$L38,">0")) -> 36 | Q38: 37 | R38: =IF(37>$V$1,"",COUNTIF($M$2:$M$66,"<"&37)+1) -> 20 | S38: =IF($R38="","",37-IF($R38=1,0,INDEX($M$2:$M$66,$R38-1))) -> 2 | T38: =IF($R38="",0,IF($S38=INDEX($L$2:$L$66,$R38),1,0)) -> 1 | W38: =门店对照!$D38 -> 1 | X38: =IF($W38=1,$B38,"#未启用#") -> 2057
A39: 38 | B39: =IF(门店对照!$A39="","",门店对照!$A39) -> 2060 | C39: =门店对照!$C39&"" -> 博景店 | D39: =参数!$B$2 -> 46234 | E39: =ROUND(SUMIFS(输入现金!$B:$B,输入现金!$A:$A,$X39),2) -> 4964.48 | F39: =ROUND(SUM(分录收入!$G$817:$G$835),2) -> 31543.33 | G39: =ROUND(海典汇总!$AE$40,2) -> 36507.81 | H39: =ROUND($E39+$F39-$G39,2) -> 0 | I39: =ROUND($E39+MAX(0,-$H39),2) -> 4964.48 | J39: =ROUND(MAX(0,$H39),2) -> 0 | K39: =SUM(分录收入!$J$816:$J$837) -> 9 | L39: =IF(OR($K39=0,$W39=0),0,ROUNDUP($K39/6,0)) -> 2 | M39: =SUM($L$2:$L39) -> 67 | N39: =ROUND(SUM(分录收入!$H$816:$H$837),2) -> 36507.81 | O39: =ROUND(SUM(分录收入!$I$816:$I$837),2) -> 36507.81 | P39: =IF($L39=0,"",COUNTIF($L$2:$L39,">0")) -> 37 | Q39: 38 | R39: =IF(38>$V$1,"",COUNTIF($M$2:$M$66,"<"&38)+1) -> 21 | S39: =IF($R39="","",38-IF($R39=1,0,INDEX($M$2:$M$66,$R39-1))) -> 1 | T39: =IF($R39="",0,IF($S39=INDEX($L$2:$L$66,$R39),1,0)) -> 0 | W39: =门店对照!$D39 -> 1 | X39: =IF($W39=1,$B39,"#未启用#") -> 2060
A40: 39 | B40: =IF(门店对照!$A40="","",门店对照!$A40) -> 2062 | C40: =门店对照!$C40&"" -> 西范村店 | D40: =参数!$B$2 -> 46234 | E40: =ROUND(SUMIFS(输入现金!$B:$B,输入现金!$A:$A,$X40),2) -> 6528.35 | F40: =ROUND(SUM(分录收入!$G$839:$G$857),2) -> 63376.1 | G40: =ROUND(海典汇总!$AE$41,2) -> 69904.45 | H40: =ROUND($E40+$F40-$G40,2) -> 0 | I40: =ROUND($E40+MAX(0,-$H40),2) -> 6528.35 | J40: =ROUND(MAX(0,$H40),2) -> 0 | K40: =SUM(分录收入!$J$838:$J$859) -> 7 | L40: =IF(OR($K40=0,$W40=0),0,ROUNDUP($K40/6,0)) -> 2 | M40: =SUM($L$2:$L40) -> 69 | N40: =ROUND(SUM(分录收入!$H$838:$H$859),2) -> 69904.45 | O40: =ROUND(SUM(分录收入!$I$838:$I$859),2) -> 69904.45 | P40: =IF($L40=0,"",COUNTIF($L$2:$L40,">0")) -> 38 | Q40: 39 | R40: =IF(39>$V$1,"",COUNTIF($M$2:$M$66,"<"&39)+1) -> 21 | S40: =IF($R40="","",39-IF($R40=1,0,INDEX($M$2:$M$66,$R40-1))) -> 2 | T40: =IF($R40="",0,IF($S40=INDEX($L$2:$L$66,$R40),1,0)) -> 1 | W40: =门店对照!$D40 -> 1 | X40: =IF($W40=1,$B40,"#未启用#") -> 2062
A41: 40 | B41: =IF(门店对照!$A41="","",门店对照!$A41) -> 2063 | C41: =门店对照!$C41&"" -> 博医店 | D41: =参数!$B$2 -> 46234 | E41: =ROUND(SUMIFS(输入现金!$B:$B,输入现金!$A:$A,$X41),2) -> 46487.34 | F41: =ROUND(SUM(分录收入!$G$861:$G$879),2) -> 72056.55 | G41: =ROUND(海典汇总!$AE$42,2) -> 118543.89 | H41: =ROUND($E41+$F41-$G41,2) -> 0 | I41: =ROUND($E41+MAX(0,-$H41),2) -> 46487.34 | J41: =ROUND(MAX(0,$H41),2) -> 0 | K41: =SUM(分录收入!$J$860:$J$881) -> 10 | L41: =IF(OR($K41=0,$W41=0),0,ROUNDUP($K41/6,0)) -> 2 | M41: =SUM($L$2:$L41) -> 71 | N41: =ROUND(SUM(分录收入!$H$860:$H$881),2) -> 118543.89 | O41: =ROUND(SUM(分录收入!$I$860:$I$881),2) -> 118543.89 | P41: =IF($L41=0,"",COUNTIF($L$2:$L41,">0")) -> 39 | Q41: 40 | R41: =IF(40>$V$1,"",COUNTIF($M$2:$M$66,"<"&40)+1) -> 22 | S41: =IF($R41="","",40-IF($R41=1,0,INDEX($M$2:$M$66,$R41-1))) -> 1 | T41: =IF($R41="",0,IF($S41=INDEX($L$2:$L$66,$R41),1,0)) -> 0 | W41: =门店对照!$D41 -> 1 | X41: =IF($W41=1,$B41,"#未启用#") -> 2063
A42: 41 | B42: =IF(门店对照!$A42="","",门店对照!$A42) -> 2064 | C42: =门店对照!$C42&"" -> 旗舰店 | D42: =参数!$B$2 -> 46234 | E42: =ROUND(SUMIFS(输入现金!$B:$B,输入现金!$A:$A,$X42),2) -> 699.75 | F42: =ROUND(SUM(分录收入!$G$883:$G$901),2) -> 0 | G42: =ROUND(海典汇总!$AE$43,2) -> 699.75 | H42: =ROUND($E42+$F42-$G42,2) -> 0 | I42: =ROUND($E42+MAX(0,-$H42),2) -> 699.75 | J42: =ROUND(MAX(0,$H42),2) -> 0 | K42: =SUM(分录收入!$J$882:$J$903) -> 2 | L42: =IF(OR($K42=0,$W42=0),0,ROUNDUP($K42/6,0)) -> 1 | M42: =SUM($L$2:$L42) -> 72 | N42: =ROUND(SUM(分录收入!$H$882:$H$903),2) -> 699.75 | O42: =ROUND(SUM(分录收入!$I$882:$I$903),2) -> 699.75 | P42: =IF($L42=0,"",COUNTIF($L$2:$L42,">0")) -> 40 | Q42: 41 | R42: =IF(41>$V$1,"",COUNTIF($M$2:$M$66,"<"&41)+1) -> 22 | S42: =IF($R42="","",41-IF($R42=1,0,INDEX($M$2:$M$66,$R42-1))) -> 2 | T42: =IF($R42="",0,IF($S42=INDEX($L$2:$L$66,$R42),1,0)) -> 1 | W42: =门店对照!$D42 -> 1 | X42: =IF($W42=1,$B42,"#未启用#") -> 2064
A43: 42 | B43: =IF(门店对照!$A43="","",门店对照!$A43) -> 2066 | C43: =门店对照!$C43&"" -> 博实店 | D43: =参数!$B$2 -> 46234 | E43: =ROUND(SUMIFS(输入现金!$B:$B,输入现金!$A:$A,$X43),2) -> 14896.88 | F43: =ROUND(SUM(分录收入!$G$905:$G$923),2) -> 48823.05 | G43: =ROUND(海典汇总!$AE$44,2) -> 63719.93 | H43: =ROUND($E43+$F43-$G43,2) -> 0 | I43: =ROUND($E43+MAX(0,-$H43),2) -> 14896.88 | J43: =ROUND(MAX(0,$H43),2) -> 0 | K43: =SUM(分录收入!$J$904:$J$925) -> 9 | L43: =IF(OR($K43=0,$W43=0),0,ROUNDUP($K43/6,0)) -> 2 | M43: =SUM($L$2:$L43) -> 74 | N43: =ROUND(SUM(分录收入!$H$904:$H$925),2) -> 63719.93 | O43: =ROUND(SUM(分录收入!$I$904:$I$925),2) -> 63719.93 | P43: =IF($L43=0,"",COUNTIF($L$2:$L43,">0")) -> 41 | Q43: 42 | R43: =IF(42>$V$1,"",COUNTIF($M$2:$M$66,"<"&42)+1) -> 24 | S43: =IF($R43="","",42-IF($R43=1,0,INDEX($M$2:$M$66,$R43-1))) -> 1 | T43: =IF($R43="",0,IF($S43=INDEX($L$2:$L$66,$R43),1,0)) -> 0 | W43: =门店对照!$D43 -> 1 | X43: =IF($W43=1,$B43,"#未启用#") -> 2066
A44: 43 | B44: =IF(门店对照!$A44="","",门店对照!$A44) -> 2067 | C44: =门店对照!$C44&"" -> 博亮店 | D44: =参数!$B$2 -> 46234 | E44: =ROUND(SUMIFS(输入现金!$B:$B,输入现金!$A:$A,$X44),2) -> 3632.88 | F44: =ROUND(SUM(分录收入!$G$927:$G$945),2) -> 25470.21 | G44: =ROUND(海典汇总!$AE$45,2) -> 29103.09 | H44: =ROUND($E44+$F44-$G44,2) -> 0 | I44: =ROUND($E44+MAX(0,-$H44),2) -> 3632.88 | J44: =ROUND(MAX(0,$H44),2) -> 0 | K44: =SUM(分录收入!$J$926:$J$947) -> 7 | L44: =IF(OR($K44=0,$W44=0),0,ROUNDUP($K44/6,0)) -> 2 | M44: =SUM($L$2:$L44) -> 76 | N44: =ROUND(SUM(分录收入!$H$926:$H$947),2) -> 29103.09 | O44: =ROUND(SUM(分录收入!$I$926:$I$947),2) -> 29103.09 | P44: =IF($L44=0,"",COUNTIF($L$2:$L44,">0")) -> 42 | Q44: 43 | R44: =IF(43>$V$1,"",COUNTIF($M$2:$M$66,"<"&43)+1) -> 24 | S44: =IF($R44="","",43-IF($R44=1,0,INDEX($M$2:$M$66,$R44-1))) -> 2 | T44: =IF($R44="",0,IF($S44=INDEX($L$2:$L$66,$R44),1,0)) -> 1 | W44: =门店对照!$D44 -> 1 | X44: =IF($W44=1,$B44,"#未启用#") -> 2067
A45: 44 | B45: =IF(门店对照!$A45="","",门店对照!$A45) -> 2068 | C45: =门店对照!$C45&"" -> 博山店 | D45: =参数!$B$2 -> 46234 | E45: =ROUND(SUMIFS(输入现金!$B:$B,输入现金!$A:$A,$X45),2) -> 9684.9 | F45: =ROUND(SUM(分录收入!$G$949:$G$967),2) -> 53473.46 | G45: =ROUND(海典汇总!$AE$46,2) -> 63158.36 | H45: =ROUND($E45+$F45-$G45,2) -> 0 | I45: =ROUND($E45+MAX(0,-$H45),2) -> 9684.9 | J45: =ROUND(MAX(0,$H45),2) -> 0 | K45: =SUM(分录收入!$J$948:$J$969) -> 8 | L45: =IF(OR($K45=0,$W45=0),0,ROUNDUP($K45/6,0)) -> 2 | M45: =SUM($L$2:$L45) -> 78 | N45: =ROUND(SUM(分录收入!$H$948:$H$969),2) -> 63158.46 | O45: =ROUND(SUM(分录收入!$I$948:$I$969),2) -> 63158.46 | P45: =IF($L45=0,"",COUNTIF($L$2:$L45,">0")) -> 43 | Q45: 44 | R45: =IF(44>$V$1,"",COUNTIF($M$2:$M$66,"<"&44)+1) -> 25 | S45: =IF($R45="","",44-IF($R45=1,0,INDEX($M$2:$M$66,$R45-1))) -> 1 | T45: =IF($R45="",0,IF($S45=INDEX($L$2:$L$66,$R45),1,0)) -> 0 | W45: =门店对照!$D45 -> 1 | X45: =IF($W45=1,$B45,"#未启用#") -> 2068
A46: 45 | B46: =IF(门店对照!$A46="","",门店对照!$A46) -> 2069 | C46: =门店对照!$C46&"" -> 博东店 | D46: =参数!$B$2 -> 46234 | E46: =ROUND(SUMIFS(输入现金!$B:$B,输入现金!$A:$A,$X46),2) -> 0 | F46: =ROUND(SUM(分录收入!$G$971:$G$989),2) -> 0 | G46: =ROUND(海典汇总!$AE$47,2) -> 0 | H46: =ROUND($E46+$F46-$G46,2) -> 0 | I46: =ROUND($E46+MAX(0,-$H46),2) -> 0 | J46: =ROUND(MAX(0,$H46),2) -> 0 | K46: =SUM(分录收入!$J$970:$J$991) -> 0 | L46: =IF(OR($K46=0,$W46=0),0,ROUNDUP($K46/6,0)) -> 0 | M46: =SUM($L$2:$L46) -> 78 | N46: =ROUND(SUM(分录收入!$H$970:$H$991),2) -> 0 | O46: =ROUND(SUM(分录收入!$I$970:$I$991),2) -> 0 | P46: =IF($L46=0,"",COUNTIF($L$2:$L46,">0")) | Q46: 45 | R46: =IF(45>$V$1,"",COUNTIF($M$2:$M$66,"<"&45)+1) -> 25 | S46: =IF($R46="","",45-IF($R46=1,0,INDEX($M$2:$M$66,$R46-1))) -> 2 | T46: =IF($R46="",0,IF($S46=INDEX($L$2:$L$66,$R46),1,0)) -> 1 | W46: =门店对照!$D46 -> 1 | X46: =IF($W46=1,$B46,"#未启用#") -> 2069
A47: 46 | B47: =IF(门店对照!$A47="","",门店对照!$A47) | C47: =门店对照!$C47&"" -> 备用1 | D47: =参数!$B$2 -> 46234 | E47: =ROUND(SUMIFS(输入现金!$B:$B,输入现金!$A:$A,$X47),2) -> 0 | F47: =ROUND(SUM(分录收入!$G$993:$G$1011),2) -> 0 | G47: =ROUND(海典汇总!$AE$48,2) -> 0 | H47: =ROUND($E47+$F47-$G47,2) -> 0 | I47: =ROUND($E47+MAX(0,-$H47),2) -> 0 | J47: =ROUND(MAX(0,$H47),2) -> 0 | K47: =SUM(分录收入!$J$992:$J$1013) -> 0 | L47: =IF(OR($K47=0,$W47=0),0,ROUNDUP($K47/6,0)) -> 0 | M47: =SUM($L$2:$L47) -> 78 | N47: =ROUND(SUM(分录收入!$H$992:$H$1013),2) -> 0 | O47: =ROUND(SUM(分录收入!$I$992:$I$1013),2) -> 0 | P47: =IF($L47=0,"",COUNTIF($L$2:$L47,">0")) | Q47: 46 | R47: =IF(46>$V$1,"",COUNTIF($M$2:$M$66,"<"&46)+1) -> 26 | S47: =IF($R47="","",46-IF($R47=1,0,INDEX($M$2:$M$66,$R47-1))) -> 1 | T47: =IF($R47="",0,IF($S47=INDEX($L$2:$L$66,$R47),1,0)) -> 0 | W47: =门店对照!$D47 -> 0 | X47: =IF($W47=1,$B47,"#未启用#") -> #未启用#
A48: 47 | B48: =IF(门店对照!$A48="","",门店对照!$A48) | C48: =门店对照!$C48&"" -> 备用2 | D48: =参数!$B$2 -> 46234 | E48: =ROUND(SUMIFS(输入现金!$B:$B,输入现金!$A:$A,$X48),2) -> 0 | F48: =ROUND(SUM(分录收入!$G$1015:$G$1033),2) -> 0 | G48: =ROUND(海典汇总!$AE$49,2) -> 0 | H48: =ROUND($E48+$F48-$G48,2) -> 0 | I48: =ROUND($E48+MAX(0,-$H48),2) -> 0 | J48: =ROUND(MAX(0,$H48),2) -> 0 | K48: =SUM(分录收入!$J$1014:$J$1035) -> 0 | L48: =IF(OR($K48=0,$W48=0),0,ROUNDUP($K48/6,0)) -> 0 | M48: =SUM($L$2:$L48) -> 78 | N48: =ROUND(SUM(分录收入!$H$1014:$H$1035),2) -> 0 | O48: =ROUND(SUM(分录收入!$I$1014:$I$1035),2) -> 0 | P48: =IF($L48=0,"",COUNTIF($L$2:$L48,">0")) | Q48: 47 | R48: =IF(47>$V$1,"",COUNTIF($M$2:$M$66,"<"&47)+1) -> 26 | S48: =IF($R48="","",47-IF($R48=1,0,INDEX($M$2:$M$66,$R48-1))) -> 2 | T48: =IF($R48="",0,IF($S48=INDEX($L$2:$L$66,$R48),1,0)) -> 1 | W48: =门店对照!$D48 -> 0 | X48: =IF($W48=1,$B48,"#未启用#") -> #未启用#
A49: 48 | B49: =IF(门店对照!$A49="","",门店对照!$A49) | C49: =门店对照!$C49&"" -> 备用3 | D49: =参数!$B$2 -> 46234 | E49: =ROUND(SUMIFS(输入现金!$B:$B,输入现金!$A:$A,$X49),2) -> 0 | F49: =ROUND(SUM(分录收入!$G$1037:$G$1055),2) -> 0 | G49: =ROUND(海典汇总!$AE$50,2) -> 0 | H49: =ROUND($E49+$F49-$G49,2) -> 0 | I49: =ROUND($E49+MAX(0,-$H49),2) -> 0 | J49: =ROUND(MAX(0,$H49),2) -> 0 | K49: =SUM(分录收入!$J$1036:$J$1057) -> 0 | L49: =IF(OR($K49=0,$W49=0),0,ROUNDUP($K49/6,0)) -> 0 | M49: =SUM($L$2:$L49) -> 78 | N49: =ROUND(SUM(分录收入!$H$1036:$H$1057),2) -> 0 | O49: =ROUND(SUM(分录收入!$I$1036:$I$1057),2) -> 0 | P49: =IF($L49=0,"",COUNTIF($L$2:$L49,">0")) | Q49: 48 | R49: =IF(48>$V$1,"",COUNTIF($M$2:$M$66,"<"&48)+1) -> 27 | S49: =IF($R49="","",48-IF($R49=1,0,INDEX($M$2:$M$66,$R49-1))) -> 1 | T49: =IF($R49="",0,IF($S49=INDEX($L$2:$L$66,$R49),1,0)) -> 0 | W49: =门店对照!$D49 -> 0 | X49: =IF($W49=1,$B49,"#未启用#") -> #未启用#
A50: 49 | B50: =IF(门店对照!$A50="","",门店对照!$A50) | C50: =门店对照!$C50&"" -> 备用4 | D50: =参数!$B$2 -> 46234 | E50: =ROUND(SUMIFS(输入现金!$B:$B,输入现金!$A:$A,$X50),2) -> 0 | F50: =ROUND(SUM(分录收入!$G$1059:$G$1077),2) -> 0 | G50: =ROUND(海典汇总!$AE$51,2) -> 0 | H50: =ROUND($E50+$F50-$G50,2) -> 0 | I50: =ROUND($E50+MAX(0,-$H50),2) -> 0 | J50: =ROUND(MAX(0,$H50),2) -> 0 | K50: =SUM(分录收入!$J$1058:$J$1079) -> 0 | L50: =IF(OR($K50=0,$W50=0),0,ROUNDUP($K50/6,0)) -> 0 | M50: =SUM($L$2:$L50) -> 78 | N50: =ROUND(SUM(分录收入!$H$1058:$H$1079),2) -> 0 | O50: =ROUND(SUM(分录收入!$I$1058:$I$1079),2) -> 0 | P50: =IF($L50=0,"",COUNTIF($L$2:$L50,">0")) | Q50: 49 | R50: =IF(49>$V$1,"",COUNTIF($M$2:$M$66,"<"&49)+1) -> 27 | S50: =IF($R50="","",49-IF($R50=1,0,INDEX($M$2:$M$66,$R50-1))) -> 2 | T50: =IF($R50="",0,IF($S50=INDEX($L$2:$L$66,$R50),1,0)) -> 1 | W50: =门店对照!$D50 -> 0 | X50: =IF($W50=1,$B50,"#未启用#") -> #未启用#
A51: 50 | B51: =IF(门店对照!$A51="","",门店对照!$A51) | C51: =门店对照!$C51&"" -> 备用5 | D51: =参数!$B$2 -> 46234 | E51: =ROUND(SUMIFS(输入现金!$B:$B,输入现金!$A:$A,$X51),2) -> 0 | F51: =ROUND(SUM(分录收入!$G$1081:$G$1099),2) -> 0 | G51: =ROUND(海典汇总!$AE$52,2) -> 0 | H51: =ROUND($E51+$F51-$G51,2) -> 0 | I51: =ROUND($E51+MAX(0,-$H51),2) -> 0 | J51: =ROUND(MAX(0,$H51),2) -> 0 | K51: =SUM(分录收入!$J$1080:$J$1101) -> 0 | L51: =IF(OR($K51=0,$W51=0),0,ROUNDUP($K51/6,0)) -> 0 | M51: =SUM($L$2:$L51) -> 78 | N51: =ROUND(SUM(分录收入!$H$1080:$H$1101),2) -> 0 | O51: =ROUND(SUM(分录收入!$I$1080:$I$1101),2) -> 0 | P51: =IF($L51=0,"",COUNTIF($L$2:$L51,">0")) | Q51: 50 | R51: =IF(50>$V$1,"",COUNTIF($M$2:$M$66,"<"&50)+1) -> 28 | S51: =IF($R51="","",50-IF($R51=1,0,INDEX($M$2:$M$66,$R51-1))) -> 1 | T51: =IF($R51="",0,IF($S51=INDEX($L$2:$L$66,$R51),1,0)) -> 0 | W51: =门店对照!$D51 -> 0 | X51: =IF($W51=1,$B51,"#未启用#") -> #未启用#
A52: 51 | B52: =IF(门店对照!$A52="","",门店对照!$A52) | C52: =门店对照!$C52&"" -> 备用6 | D52: =参数!$B$2 -> 46234 | E52: =ROUND(SUMIFS(输入现金!$B:$B,输入现金!$A:$A,$X52),2) -> 0 | F52: =ROUND(SUM(分录收入!$G$1103:$G$1121),2) -> 0 | G52: =ROUND(海典汇总!$AE$53,2) -> 0 | H52: =ROUND($E52+$F52-$G52,2) -> 0 | I52: =ROUND($E52+MAX(0,-$H52),2) -> 0 | J52: =ROUND(MAX(0,$H52),2) -> 0 | K52: =SUM(分录收入!$J$1102:$J$1123) -> 0 | L52: =IF(OR($K52=0,$W52=0),0,ROUNDUP($K52/6,0)) -> 0 | M52: =SUM($L$2:$L52) -> 78 | N52: =ROUND(SUM(分录收入!$H$1102:$H$1123),2) -> 0 | O52: =ROUND(SUM(分录收入!$I$1102:$I$1123),2) -> 0 | P52: =IF($L52=0,"",COUNTIF($L$2:$L52,">0")) | Q52: 51 | R52: =IF(51>$V$1,"",COUNTIF($M$2:$M$66,"<"&51)+1) -> 28 | S52: =IF($R52="","",51-IF($R52=1,0,INDEX($M$2:$M$66,$R52-1))) -> 2 | T52: =IF($R52="",0,IF($S52=INDEX($L$2:$L$66,$R52),1,0)) -> 1 | W52: =门店对照!$D52 -> 0 | X52: =IF($W52=1,$B52,"#未启用#") -> #未启用#
A53: 52 | B53: =IF(门店对照!$A53="","",门店对照!$A53) | C53: =门店对照!$C53&"" -> 备用7 | D53: =参数!$B$2 -> 46234 | E53: =ROUND(SUMIFS(输入现金!$B:$B,输入现金!$A:$A,$X53),2) -> 0 | F53: =ROUND(SUM(分录收入!$G$1125:$G$1143),2) -> 0 | G53: =ROUND(海典汇总!$AE$54,2) -> 0 | H53: =ROUND($E53+$F53-$G53,2) -> 0 | I53: =ROUND($E53+MAX(0,-$H53),2) -> 0 | J53: =ROUND(MAX(0,$H53),2) -> 0 | K53: =SUM(分录收入!$J$1124:$J$1145) -> 0 | L53: =IF(OR($K53=0,$W53=0),0,ROUNDUP($K53/6,0)) -> 0 | M53: =SUM($L$2:$L53) -> 78 | N53: =ROUND(SUM(分录收入!$H$1124:$H$1145),2) -> 0 | O53: =ROUND(SUM(分录收入!$I$1124:$I$1145),2) -> 0 | P53: =IF($L53=0,"",COUNTIF($L$2:$L53,">0")) | Q53: 52 | R53: =IF(52>$V$1,"",COUNTIF($M$2:$M$66,"<"&52)+1) -> 29 | S53: =IF($R53="","",52-IF($R53=1,0,INDEX($M$2:$M$66,$R53-1))) -> 1 | T53: =IF($R53="",0,IF($S53=INDEX($L$2:$L$66,$R53),1,0)) -> 0 | W53: =门店对照!$D53 -> 0 | X53: =IF($W53=1,$B53,"#未启用#") -> #未启用#
A54: 53 | B54: =IF(门店对照!$A54="","",门店对照!$A54) | C54: =门店对照!$C54&"" -> 备用8 | D54: =参数!$B$2 -> 46234 | E54: =ROUND(SUMIFS(输入现金!$B:$B,输入现金!$A:$A,$X54),2) -> 0 | F54: =ROUND(SUM(分录收入!$G$1147:$G$1165),2) -> 0 | G54: =ROUND(海典汇总!$AE$55,2) -> 0 | H54: =ROUND($E54+$F54-$G54,2) -> 0 | I54: =ROUND($E54+MAX(0,-$H54),2) -> 0 | J54: =ROUND(MAX(0,$H54),2) -> 0 | K54: =SUM(分录收入!$J$1146:$J$1167) -> 0 | L54: =IF(OR($K54=0,$W54=0),0,ROUNDUP($K54/6,0)) -> 0 | M54: =SUM($L$2:$L54) -> 78 | N54: =ROUND(SUM(分录收入!$H$1146:$H$1167),2) -> 0 | O54: =ROUND(SUM(分录收入!$I$1146:$I$1167),2) -> 0 | P54: =IF($L54=0,"",COUNTIF($L$2:$L54,">0")) | Q54: 53 | R54: =IF(53>$V$1,"",COUNTIF($M$2:$M$66,"<"&53)+1) -> 29 | S54: =IF($R54="","",53-IF($R54=1,0,INDEX($M$2:$M$66,$R54-1))) -> 2 | T54: =IF($R54="",0,IF($S54=INDEX($L$2:$L$66,$R54),1,0)) -> 1 | W54: =门店对照!$D54 -> 0 | X54: =IF($W54=1,$B54,"#未启用#") -> #未启用#
A55: 54 | B55: =IF(门店对照!$A55="","",门店对照!$A55) | C55: =门店对照!$C55&"" -> 备用9 | D55: =参数!$B$2 -> 46234 | E55: =ROUND(SUMIFS(输入现金!$B:$B,输入现金!$A:$A,$X55),2) -> 0 | F55: =ROUND(SUM(分录收入!$G$1169:$G$1187),2) -> 0 | G55: =ROUND(海典汇总!$AE$56,2) -> 0 | H55: =ROUND($E55+$F55-$G55,2) -> 0 | I55: =ROUND($E55+MAX(0,-$H55),2) -> 0 | J55: =ROUND(MAX(0,$H55),2) -> 0 | K55: =SUM(分录收入!$J$1168:$J$1189) -> 0 | L55: =IF(OR($K55=0,$W55=0),0,ROUNDUP($K55/6,0)) -> 0 | M55: =SUM($L$2:$L55) -> 78 | N55: =ROUND(SUM(分录收入!$H$1168:$H$1189),2) -> 0 | O55: =ROUND(SUM(分录收入!$I$1168:$I$1189),2) -> 0 | P55: =IF($L55=0,"",COUNTIF($L$2:$L55,">0")) | Q55: 54 | R55: =IF(54>$V$1,"",COUNTIF($M$2:$M$66,"<"&54)+1) -> 30 | S55: =IF($R55="","",54-IF($R55=1,0,INDEX($M$2:$M$66,$R55-1))) -> 1 | T55: =IF($R55="",0,IF($S55=INDEX($L$2:$L$66,$R55),1,0)) -> 0 | W55: =门店对照!$D55 -> 0 | X55: =IF($W55=1,$B55,"#未启用#") -> #未启用#
A56: 55 | B56: =IF(门店对照!$A56="","",门店对照!$A56) | C56: =门店对照!$C56&"" -> 备用10 | D56: =参数!$B$2 -> 46234 | E56: =ROUND(SUMIFS(输入现金!$B:$B,输入现金!$A:$A,$X56),2) -> 0 | F56: =ROUND(SUM(分录收入!$G$1191:$G$1209),2) -> 0 | G56: =ROUND(海典汇总!$AE$57,2) -> 0 | H56: =ROUND($E56+$F56-$G56,2) -> 0 | I56: =ROUND($E56+MAX(0,-$H56),2) -> 0 | J56: =ROUND(MAX(0,$H56),2) -> 0 | K56: =SUM(分录收入!$J$1190:$J$1211) -> 0 | L56: =IF(OR($K56=0,$W56=0),0,ROUNDUP($K56/6,0)) -> 0 | M56: =SUM($L$2:$L56) -> 78 | N56: =ROUND(SUM(分录收入!$H$1190:$H$1211),2) -> 0 | O56: =ROUND(SUM(分录收入!$I$1190:$I$1211),2) -> 0 | P56: =IF($L56=0,"",COUNTIF($L$2:$L56,">0")) | Q56: 55 | R56: =IF(55>$V$1,"",COUNTIF($M$2:$M$66,"<"&55)+1) -> 30 | S56: =IF($R56="","",55-IF($R56=1,0,INDEX($M$2:$M$66,$R56-1))) -> 2 | T56: =IF($R56="",0,IF($S56=INDEX($L$2:$L$66,$R56),1,0)) -> 1 | W56: =门店对照!$D56 -> 0 | X56: =IF($W56=1,$B56,"#未启用#") -> #未启用#
A57: 56 | B57: =IF(门店对照!$A57="","",门店对照!$A57) | C57: =门店对照!$C57&"" -> 备用11 | D57: =参数!$B$2 -> 46234 | E57: =ROUND(SUMIFS(输入现金!$B:$B,输入现金!$A:$A,$X57),2) -> 0 | F57: =ROUND(SUM(分录收入!$G$1213:$G$1231),2) -> 0 | G57: =ROUND(海典汇总!$AE$58,2) -> 0 | H57: =ROUND($E57+$F57-$G57,2) -> 0 | I57: =ROUND($E57+MAX(0,-$H57),2) -> 0 | J57: =ROUND(MAX(0,$H57),2) -> 0 | K57: =SUM(分录收入!$J$1212:$J$1233) -> 0 | L57: =IF(OR($K57=0,$W57=0),0,ROUNDUP($K57/6,0)) -> 0 | M57: =SUM($L$2:$L57) -> 78 | N57: =ROUND(SUM(分录收入!$H$1212:$H$1233),2) -> 0 | O57: =ROUND(SUM(分录收入!$I$1212:$I$1233),2) -> 0 | P57: =IF($L57=0,"",COUNTIF($L$2:$L57,">0")) | Q57: 56 | R57: =IF(56>$V$1,"",COUNTIF($M$2:$M$66,"<"&56)+1) -> 31 | S57: =IF($R57="","",56-IF($R57=1,0,INDEX($M$2:$M$66,$R57-1))) -> 1 | T57: =IF($R57="",0,IF($S57=INDEX($L$2:$L$66,$R57),1,0)) -> 1 | W57: =门店对照!$D57 -> 0 | X57: =IF($W57=1,$B57,"#未启用#") -> #未启用#
A58: 57 | B58: =IF(门店对照!$A58="","",门店对照!$A58) | C58: =门店对照!$C58&"" -> 备用12 | D58: =参数!$B$2 -> 46234 | E58: =ROUND(SUMIFS(输入现金!$B:$B,输入现金!$A:$A,$X58),2) -> 0 | F58: =ROUND(SUM(分录收入!$G$1235:$G$1253),2) -> 0 | G58: =ROUND(海典汇总!$AE$59,2) -> 0 | H58: =ROUND($E58+$F58-$G58,2) -> 0 | I58: =ROUND($E58+MAX(0,-$H58),2) -> 0 | J58: =ROUND(MAX(0,$H58),2) -> 0 | K58: =SUM(分录收入!$J$1234:$J$1255) -> 0 | L58: =IF(OR($K58=0,$W58=0),0,ROUNDUP($K58/6,0)) -> 0 | M58: =SUM($L$2:$L58) -> 78 | N58: =ROUND(SUM(分录收入!$H$1234:$H$1255),2) -> 0 | O58: =ROUND(SUM(分录收入!$I$1234:$I$1255),2) -> 0 | P58: =IF($L58=0,"",COUNTIF($L$2:$L58,">0")) | Q58: 57 | R58: =IF(57>$V$1,"",COUNTIF($M$2:$M$66,"<"&57)+1) -> 32 | S58: =IF($R58="","",57-IF($R58=1,0,INDEX($M$2:$M$66,$R58-1))) -> 1 | T58: =IF($R58="",0,IF($S58=INDEX($L$2:$L$66,$R58),1,0)) -> 0 | W58: =门店对照!$D58 -> 0 | X58: =IF($W58=1,$B58,"#未启用#") -> #未启用#
A59: 58 | B59: =IF(门店对照!$A59="","",门店对照!$A59) | C59: =门店对照!$C59&"" -> 备用13 | D59: =参数!$B$2 -> 46234 | E59: =ROUND(SUMIFS(输入现金!$B:$B,输入现金!$A:$A,$X59),2) -> 0 | F59: =ROUND(SUM(分录收入!$G$1257:$G$1275),2) -> 0 | G59: =ROUND(海典汇总!$AE$60,2) -> 0 | H59: =ROUND($E59+$F59-$G59,2) -> 0 | I59: =ROUND($E59+MAX(0,-$H59),2) -> 0 | J59: =ROUND(MAX(0,$H59),2) -> 0 | K59: =SUM(分录收入!$J$1256:$J$1277) -> 0 | L59: =IF(OR($K59=0,$W59=0),0,ROUNDUP($K59/6,0)) -> 0 | M59: =SUM($L$2:$L59) -> 78 | N59: =ROUND(SUM(分录收入!$H$1256:$H$1277),2) -> 0 | O59: =ROUND(SUM(分录收入!$I$1256:$I$1277),2) -> 0 | P59: =IF($L59=0,"",COUNTIF($L$2:$L59,">0")) | Q59: 58 | R59: =IF(58>$V$1,"",COUNTIF($M$2:$M$66,"<"&58)+1) -> 32 | S59: =IF($R59="","",58-IF($R59=1,0,INDEX($M$2:$M$66,$R59-1))) -> 2 | T59: =IF($R59="",0,IF($S59=INDEX($L$2:$L$66,$R59),1,0)) -> 1 | W59: =门店对照!$D59 -> 0 | X59: =IF($W59=1,$B59,"#未启用#") -> #未启用#
A60: 59 | B60: =IF(门店对照!$A60="","",门店对照!$A60) | C60: =门店对照!$C60&"" -> 备用14 | D60: =参数!$B$2 -> 46234 | E60: =ROUND(SUMIFS(输入现金!$B:$B,输入现金!$A:$A,$X60),2) -> 0 | F60: =ROUND(SUM(分录收入!$G$1279:$G$1297),2) -> 0 | G60: =ROUND(海典汇总!$AE$61,2) -> 0 | H60: =ROUND($E60+$F60-$G60,2) -> 0 | I60: =ROUND($E60+MAX(0,-$H60),2) -> 0 | J60: =ROUND(MAX(0,$H60),2) -> 0 | K60: =SUM(分录收入!$J$1278:$J$1299) -> 0 | L60: =IF(OR($K60=0,$W60=0),0,ROUNDUP($K60/6,0)) -> 0 | M60: =SUM($L$2:$L60) -> 78 | N60: =ROUND(SUM(分录收入!$H$1278:$H$1299),2) -> 0 | O60: =ROUND(SUM(分录收入!$I$1278:$I$1299),2) -> 0 | P60: =IF($L60=0,"",COUNTIF($L$2:$L60,">0")) | Q60: 59 | R60: =IF(59>$V$1,"",COUNTIF($M$2:$M$66,"<"&59)+1) -> 33 | S60: =IF($R60="","",59-IF($R60=1,0,INDEX($M$2:$M$66,$R60-1))) -> 1 | T60: =IF($R60="",0,IF($S60=INDEX($L$2:$L$66,$R60),1,0)) -> 1 | W60: =门店对照!$D60 -> 0 | X60: =IF($W60=1,$B60,"#未启用#") -> #未启用#
A61: 60 | B61: =IF(门店对照!$A61="","",门店对照!$A61) | C61: =门店对照!$C61&"" -> 备用15 | D61: =参数!$B$2 -> 46234 | E61: =ROUND(SUMIFS(输入现金!$B:$B,输入现金!$A:$A,$X61),2) -> 0 | F61: =ROUND(SUM(分录收入!$G$1301:$G$1319),2) -> 0 | G61: =ROUND(海典汇总!$AE$62,2) -> 0 | H61: =ROUND($E61+$F61-$G61,2) -> 0 | I61: =ROUND($E61+MAX(0,-$H61),2) -> 0 | J61: =ROUND(MAX(0,$H61),2) -> 0 | K61: =SUM(分录收入!$J$1300:$J$1321) -> 0 | L61: =IF(OR($K61=0,$W61=0),0,ROUNDUP($K61/6,0)) -> 0 | M61: =SUM($L$2:$L61) -> 78 | N61: =ROUND(SUM(分录收入!$H$1300:$H$1321),2) -> 0 | O61: =ROUND(SUM(分录收入!$I$1300:$I$1321),2) -> 0 | P61: =IF($L61=0,"",COUNTIF($L$2:$L61,">0")) | Q61: 60 | R61: =IF(60>$V$1,"",COUNTIF($M$2:$M$66,"<"&60)+1) -> 34 | S61: =IF($R61="","",60-IF($R61=1,0,INDEX($M$2:$M$66,$R61-1))) -> 1 | T61: =IF($R61="",0,IF($S61=INDEX($L$2:$L$66,$R61),1,0)) -> 0 | W61: =门店对照!$D61 -> 0 | X61: =IF($W61=1,$B61,"#未启用#") -> #未启用#
A62: 61 | B62: =IF(门店对照!$A62="","",门店对照!$A62) | C62: =门店对照!$C62&"" -> 备用16 | D62: =参数!$B$2 -> 46234 | E62: =ROUND(SUMIFS(输入现金!$B:$B,输入现金!$A:$A,$X62),2) -> 0 | F62: =ROUND(SUM(分录收入!$G$1323:$G$1341),2) -> 0 | G62: =ROUND(海典汇总!$AE$63,2) -> 0 | H62: =ROUND($E62+$F62-$G62,2) -> 0 | I62: =ROUND($E62+MAX(0,-$H62),2) -> 0 | J62: =ROUND(MAX(0,$H62),2) -> 0 | K62: =SUM(分录收入!$J$1322:$J$1343) -> 0 | L62: =IF(OR($K62=0,$W62=0),0,ROUNDUP($K62/6,0)) -> 0 | M62: =SUM($L$2:$L62) -> 78 | N62: =ROUND(SUM(分录收入!$H$1322:$H$1343),2) -> 0 | O62: =ROUND(SUM(分录收入!$I$1322:$I$1343),2) -> 0 | P62: =IF($L62=0,"",COUNTIF($L$2:$L62,">0")) | Q62: 61 | R62: =IF(61>$V$1,"",COUNTIF($M$2:$M$66,"<"&61)+1) -> 34 | S62: =IF($R62="","",61-IF($R62=1,0,INDEX($M$2:$M$66,$R62-1))) -> 2 | T62: =IF($R62="",0,IF($S62=INDEX($L$2:$L$66,$R62),1,0)) -> 1 | W62: =门店对照!$D62 -> 0 | X62: =IF($W62=1,$B62,"#未启用#") -> #未启用#
A63: 62 | B63: =IF(门店对照!$A63="","",门店对照!$A63) | C63: =门店对照!$C63&"" -> 备用17 | D63: =参数!$B$2 -> 46234 | E63: =ROUND(SUMIFS(输入现金!$B:$B,输入现金!$A:$A,$X63),2) -> 0 | F63: =ROUND(SUM(分录收入!$G$1345:$G$1363),2) -> 0 | G63: =ROUND(海典汇总!$AE$64,2) -> 0 | H63: =ROUND($E63+$F63-$G63,2) -> 0 | I63: =ROUND($E63+MAX(0,-$H63),2) -> 0 | J63: =ROUND(MAX(0,$H63),2) -> 0 | K63: =SUM(分录收入!$J$1344:$J$1365) -> 0 | L63: =IF(OR($K63=0,$W63=0),0,ROUNDUP($K63/6,0)) -> 0 | M63: =SUM($L$2:$L63) -> 78 | N63: =ROUND(SUM(分录收入!$H$1344:$H$1365),2) -> 0 | O63: =ROUND(SUM(分录收入!$I$1344:$I$1365),2) -> 0 | P63: =IF($L63=0,"",COUNTIF($L$2:$L63,">0")) | Q63: 62 | R63: =IF(62>$V$1,"",COUNTIF($M$2:$M$66,"<"&62)+1) -> 35 | S63: =IF($R63="","",62-IF($R63=1,0,INDEX($M$2:$M$66,$R63-1))) -> 1 | T63: =IF($R63="",0,IF($S63=INDEX($L$2:$L$66,$R63),1,0)) -> 0 | W63: =门店对照!$D63 -> 0 | X63: =IF($W63=1,$B63,"#未启用#") -> #未启用#
A64: 63 | B64: =IF(门店对照!$A64="","",门店对照!$A64) | C64: =门店对照!$C64&"" -> 备用18 | D64: =参数!$B$2 -> 46234 | E64: =ROUND(SUMIFS(输入现金!$B:$B,输入现金!$A:$A,$X64),2) -> 0 | F64: =ROUND(SUM(分录收入!$G$1367:$G$1385),2) -> 0 | G64: =ROUND(海典汇总!$AE$65,2) -> 0 | H64: =ROUND($E64+$F64-$G64,2) -> 0 | I64: =ROUND($E64+MAX(0,-$H64),2) -> 0 | J64: =ROUND(MAX(0,$H64),2) -> 0 | K64: =SUM(分录收入!$J$1366:$J$1387) -> 0 | L64: =IF(OR($K64=0,$W64=0),0,ROUNDUP($K64/6,0)) -> 0 | M64: =SUM($L$2:$L64) -> 78 | N64: =ROUND(SUM(分录收入!$H$1366:$H$1387),2) -> 0 | O64: =ROUND(SUM(分录收入!$I$1366:$I$1387),2) -> 0 | P64: =IF($L64=0,"",COUNTIF($L$2:$L64,">0")) | Q64: 63 | R64: =IF(63>$V$1,"",COUNTIF($M$2:$M$66,"<"&63)+1) -> 35 | S64: =IF($R64="","",63-IF($R64=1,0,INDEX($M$2:$M$66,$R64-1))) -> 2 | T64: =IF($R64="",0,IF($S64=INDEX($L$2:$L$66,$R64),1,0)) -> 1 | W64: =门店对照!$D64 -> 0 | X64: =IF($W64=1,$B64,"#未启用#") -> #未启用#
A65: 64 | B65: =IF(门店对照!$A65="","",门店对照!$A65) | C65: =门店对照!$C65&"" -> 备用19 | D65: =参数!$B$2 -> 46234 | E65: =ROUND(SUMIFS(输入现金!$B:$B,输入现金!$A:$A,$X65),2) -> 0 | F65: =ROUND(SUM(分录收入!$G$1389:$G$1407),2) -> 0 | G65: =ROUND(海典汇总!$AE$66,2) -> 0 | H65: =ROUND($E65+$F65-$G65,2) -> 0 | I65: =ROUND($E65+MAX(0,-$H65),2) -> 0 | J65: =ROUND(MAX(0,$H65),2) -> 0 | K65: =SUM(分录收入!$J$1388:$J$1409) -> 0 | L65: =IF(OR($K65=0,$W65=0),0,ROUNDUP($K65/6,0)) -> 0 | M65: =SUM($L$2:$L65) -> 78 | N65: =ROUND(SUM(分录收入!$H$1388:$H$1409),2) -> 0 | O65: =ROUND(SUM(分录收入!$I$1388:$I$1409),2) -> 0 | P65: =IF($L65=0,"",COUNTIF($L$2:$L65,">0")) | Q65: 64 | R65: =IF(64>$V$1,"",COUNTIF($M$2:$M$66,"<"&64)+1) -> 36 | S65: =IF($R65="","",64-IF($R65=1,0,INDEX($M$2:$M$66,$R65-1))) -> 1 | T65: =IF($R65="",0,IF($S65=INDEX($L$2:$L$66,$R65),1,0)) -> 1 | W65: =门店对照!$D65 -> 0 | X65: =IF($W65=1,$B65,"#未启用#") -> #未启用#
A66: 65 | B66: =IF(门店对照!$A66="","",门店对照!$A66) | C66: =门店对照!$C66&"" -> 备用20 | D66: =参数!$B$2 -> 46234 | E66: =ROUND(SUMIFS(输入现金!$B:$B,输入现金!$A:$A,$X66),2) -> 0 | F66: =ROUND(SUM(分录收入!$G$1411:$G$1429),2) -> 0 | G66: =ROUND(海典汇总!$AE$67,2) -> 0 | H66: =ROUND($E66+$F66-$G66,2) -> 0 | I66: =ROUND($E66+MAX(0,-$H66),2) -> 0 | J66: =ROUND(MAX(0,$H66),2) -> 0 | K66: =SUM(分录收入!$J$1410:$J$1431) -> 0 | L66: =IF(OR($K66=0,$W66=0),0,ROUNDUP($K66/6,0)) -> 0 | M66: =SUM($L$2:$L66) -> 78 | N66: =ROUND(SUM(分录收入!$H$1410:$H$1431),2) -> 0 | O66: =ROUND(SUM(分录收入!$I$1410:$I$1431),2) -> 0 | P66: =IF($L66=0,"",COUNTIF($L$2:$L66,">0")) | Q66: 65 | R66: =IF(65>$V$1,"",COUNTIF($M$2:$M$66,"<"&65)+1) -> 37 | S66: =IF($R66="","",65-IF($R66=1,0,INDEX($M$2:$M$66,$R66-1))) -> 1 | T66: =IF($R66="",0,IF($S66=INDEX($L$2:$L$66,$R66),1,0)) -> 1 | W66: =门店对照!$D66 -> 0 | X66: =IF($W66=1,$B66,"#未启用#") -> #未启用#
Q67: 66 | R67: =IF(66>$V$1,"",COUNTIF($M$2:$M$66,"<"&66)+1) -> 38 | S67: =IF($R67="","",66-IF($R67=1,0,INDEX($M$2:$M$66,$R67-1))) -> 1 | T67: =IF($R67="",0,IF($S67=INDEX($L$2:$L$66,$R67),1,0)) -> 0
Q68: 67 | R68: =IF(67>$V$1,"",COUNTIF($M$2:$M$66,"<"&67)+1) -> 38 | S68: =IF($R68="","",67-IF($R68=1,0,INDEX($M$2:$M$66,$R68-1))) -> 2 | T68: =IF($R68="",0,IF($S68=INDEX($L$2:$L$66,$R68),1,0)) -> 1
Q69: 68 | R69: =IF(68>$V$1,"",COUNTIF($M$2:$M$66,"<"&68)+1) -> 39 | S69: =IF($R69="","",68-IF($R69=1,0,INDEX($M$2:$M$66,$R69-1))) -> 1 | T69: =IF($R69="",0,IF($S69=INDEX($L$2:$L$66,$R69),1,0)) -> 0
Q70: 69 | R70: =IF(69>$V$1,"",COUNTIF($M$2:$M$66,"<"&69)+1) -> 39 | S70: =IF($R70="","",69-IF($R70=1,0,INDEX($M$2:$M$66,$R70-1))) -> 2 | T70: =IF($R70="",0,IF($S70=INDEX($L$2:$L$66,$R70),1,0)) -> 1
Q71: 70 | R71: =IF(70>$V$1,"",COUNTIF($M$2:$M$66,"<"&70)+1) -> 40 | S71: =IF($R71="","",70-IF($R71=1,0,INDEX($M$2:$M$66,$R71-1))) -> 1 | T71: =IF($R71="",0,IF($S71=INDEX($L$2:$L$66,$R71),1,0)) -> 0
Q72: 71 | R72: =IF(71>$V$1,"",COUNTIF($M$2:$M$66,"<"&71)+1) -> 40 | S72: =IF($R72="","",71-IF($R72=1,0,INDEX($M$2:$M$66,$R72-1))) -> 2 | T72: =IF($R72="",0,IF($S72=INDEX($L$2:$L$66,$R72),1,0)) -> 1
Q73: 72 | R73: =IF(72>$V$1,"",COUNTIF($M$2:$M$66,"<"&72)+1) -> 41 | S73: =IF($R73="","",72-IF($R73=1,0,INDEX($M$2:$M$66,$R73-1))) -> 1 | T73: =IF($R73="",0,IF($S73=INDEX($L$2:$L$66,$R73),1,0)) -> 1
Q74: 73 | R74: =IF(73>$V$1,"",COUNTIF($M$2:$M$66,"<"&73)+1) -> 42 | S74: =IF($R74="","",73-IF($R74=1,0,INDEX($M$2:$M$66,$R74-1))) -> 1 | T74: =IF($R74="",0,IF($S74=INDEX($L$2:$L$66,$R74),1,0)) -> 0
Q75: 74 | R75: =IF(74>$V$1,"",COUNTIF($M$2:$M$66,"<"&74)+1) -> 42 | S75: =IF($R75="","",74-IF($R75=1,0,INDEX($M$2:$M$66,$R75-1))) -> 2 | T75: =IF($R75="",0,IF($S75=INDEX($L$2:$L$66,$R75),1,0)) -> 1
Q76: 75 | R76: =IF(75>$V$1,"",COUNTIF($M$2:$M$66,"<"&75)+1) -> 43 | S76: =IF($R76="","",75-IF($R76=1,0,INDEX($M$2:$M$66,$R76-1))) -> 1 | T76: =IF($R76="",0,IF($S76=INDEX($L$2:$L$66,$R76),1,0)) -> 0
Q77: 76 | R77: =IF(76>$V$1,"",COUNTIF($M$2:$M$66,"<"&76)+1) -> 43 | S77: =IF($R77="","",76-IF($R77=1,0,INDEX($M$2:$M$66,$R77-1))) -> 2 | T77: =IF($R77="",0,IF($S77=INDEX($L$2:$L$66,$R77),1,0)) -> 1
Q78: 77 | R78: =IF(77>$V$1,"",COUNTIF($M$2:$M$66,"<"&77)+1) -> 44 | S78: =IF($R78="","",77-IF($R78=1,0,INDEX($M$2:$M$66,$R78-1))) -> 1 | T78: =IF($R78="",0,IF($S78=INDEX($L$2:$L$66,$R78),1,0)) -> 0
Q79: 78 | R79: =IF(78>$V$1,"",COUNTIF($M$2:$M$66,"<"&78)+1) -> 44 | S79: =IF($R79="","",78-IF($R79=1,0,INDEX($M$2:$M$66,$R79-1))) -> 2 | T79: =IF($R79="",0,IF($S79=INDEX($L$2:$L$66,$R79),1,0)) -> 1
Q80: 79 | R80: =IF(79>$V$1,"",COUNTIF($M$2:$M$66,"<"&79)+1) | S80: =IF($R80="","",79-IF($R80=1,0,INDEX($M$2:$M$66,$R80-1))) | T80: =IF($R80="",0,IF($S80=INDEX($L$2:$L$66,$R80),1,0)) -> 0
Q81: 80 | R81: =IF(80>$V$1,"",COUNTIF($M$2:$M$66,"<"&80)+1) | S81: =IF($R81="","",80-IF($R81=1,0,INDEX($M$2:$M$66,$R81-1))) | T81: =IF($R81="",0,IF($S81=INDEX($L$2:$L$66,$R81),1,0)) -> 0
Q82: 81 | R82: =IF(81>$V$1,"",COUNTIF($M$2:$M$66,"<"&81)+1) | S82: =IF($R82="","",81-IF($R82=1,0,INDEX($M$2:$M$66,$R82-1))) | T82: =IF($R82="",0,IF($S82=INDEX($L$2:$L$66,$R82),1,0)) -> 0
Q83: 82 | R83: =IF(82>$V$1,"",COUNTIF($M$2:$M$66,"<"&82)+1) | S83: =IF($R83="","",82-IF($R83=1,0,INDEX($M$2:$M$66,$R83-1))) | T83: =IF($R83="",0,IF($S83=INDEX($L$2:$L$66,$R83),1,0)) -> 0
Q84: 83 | R84: =IF(83>$V$1,"",COUNTIF($M$2:$M$66,"<"&83)+1) | S84: =IF($R84="","",83-IF($R84=1,0,INDEX($M$2:$M$66,$R84-1))) | T84: =IF($R84="",0,IF($S84=INDEX($L$2:$L$66,$R84),1,0)) -> 0
Q85: 84 | R85: =IF(84>$V$1,"",COUNTIF($M$2:$M$66,"<"&84)+1) | S85: =IF($R85="","",84-IF($R85=1,0,INDEX($M$2:$M$66,$R85-1))) | T85: =IF($R85="",0,IF($S85=INDEX($L$2:$L$66,$R85),1,0)) -> 0
Q86: 85 | R86: =IF(85>$V$1,"",COUNTIF($M$2:$M$66,"<"&85)+1) | S86: =IF($R86="","",85-IF($R86=1,0,INDEX($M$2:$M$66,$R86-1))) | T86: =IF($R86="",0,IF($S86=INDEX($L$2:$L$66,$R86),1,0)) -> 0
Q87: 86 | R87: =IF(86>$V$1,"",COUNTIF($M$2:$M$66,"<"&86)+1) | S87: =IF($R87="","",86-IF($R87=1,0,INDEX($M$2:$M$66,$R87-1))) | T87: =IF($R87="",0,IF($S87=INDEX($L$2:$L$66,$R87),1,0)) -> 0
Q88: 87 | R88: =IF(87>$V$1,"",COUNTIF($M$2:$M$66,"<"&87)+1) | S88: =IF($R88="","",87-IF($R88=1,0,INDEX($M$2:$M$66,$R88-1))) | T88: =IF($R88="",0,IF($S88=INDEX($L$2:$L$66,$R88),1,0)) -> 0
Q89: 88 | R89: =IF(88>$V$1,"",COUNTIF($M$2:$M$66,"<"&88)+1) | S89: =IF($R89="","",88-IF($R89=1,0,INDEX($M$2:$M$66,$R89-1))) | T89: =IF($R89="",0,IF($S89=INDEX($L$2:$L$66,$R89),1,0)) -> 0
Q90: 89 | R90: =IF(89>$V$1,"",COUNTIF($M$2:$M$66,"<"&89)+1) | S90: =IF($R90="","",89-IF($R90=1,0,INDEX($M$2:$M$66,$R90-1))) | T90: =IF($R90="",0,IF($S90=INDEX($L$2:$L$66,$R90),1,0)) -> 0
Q91: 90 | R91: =IF(90>$V$1,"",COUNTIF($M$2:$M$66,"<"&90)+1) | S91: =IF($R91="","",90-IF($R91=1,0,INDEX($M$2:$M$66,$R91-1))) | T91: =IF($R91="",0,IF($S91=INDEX($L$2:$L$66,$R91),1,0)) -> 0
Q92: 91 | R92: =IF(91>$V$1,"",COUNTIF($M$2:$M$66,"<"&91)+1) | S92: =IF($R92="","",91-IF($R92=1,0,INDEX($M$2:$M$66,$R92-1))) | T92: =IF($R92="",0,IF($S92=INDEX($L$2:$L$66,$R92),1,0)) -> 0
Q93: 92 | R93: =IF(92>$V$1,"",COUNTIF($M$2:$M$66,"<"&92)+1) | S93: =IF($R93="","",92-IF($R93=1,0,INDEX($M$2:$M$66,$R93-1))) | T93: =IF($R93="",0,IF($S93=INDEX($L$2:$L$66,$R93),1,0)) -> 0
Q94: 93 | R94: =IF(93>$V$1,"",COUNTIF($M$2:$M$66,"<"&93)+1) | S94: =IF($R94="","",93-IF($R94=1,0,INDEX($M$2:$M$66,$R94-1))) | T94: =IF($R94="",0,IF($S94=INDEX($L$2:$L$66,$R94),1,0)) -> 0
Q95: 94 | R95: =IF(94>$V$1,"",COUNTIF($M$2:$M$66,"<"&94)+1) | S95: =IF($R95="","",94-IF($R95=1,0,INDEX($M$2:$M$66,$R95-1))) | T95: =IF($R95="",0,IF($S95=INDEX($L$2:$L$66,$R95),1,0)) -> 0
Q96: 95 | R96: =IF(95>$V$1,"",COUNTIF($M$2:$M$66,"<"&95)+1) | S96: =IF($R96="","",95-IF($R96=1,0,INDEX($M$2:$M$66,$R96-1))) | T96: =IF($R96="",0,IF($S96=INDEX($L$2:$L$66,$R96),1,0)) -> 0
Q97: 96 | R97: =IF(96>$V$1,"",COUNTIF($M$2:$M$66,"<"&96)+1) | S97: =IF($R97="","",96-IF($R97=1,0,INDEX($M$2:$M$66,$R97-1))) | T97: =IF($R97="",0,IF($S97=INDEX($L$2:$L$66,$R97),1,0)) -> 0
Q98: 97 | R98: =IF(97>$V$1,"",COUNTIF($M$2:$M$66,"<"&97)+1) | S98: =IF($R98="","",97-IF($R98=1,0,INDEX($M$2:$M$66,$R98-1))) | T98: =IF($R98="",0,IF($S98=INDEX($L$2:$L$66,$R98),1,0)) -> 0
Q99: 98 | R99: =IF(98>$V$1,"",COUNTIF($M$2:$M$66,"<"&98)+1) | S99: =IF($R99="","",98-IF($R99=1,0,INDEX($M$2:$M$66,$R99-1))) | T99: =IF($R99="",0,IF($S99=INDEX($L$2:$L$66,$R99),1,0)) -> 0
Q100: 99 | R100: =IF(99>$V$1,"",COUNTIF($M$2:$M$66,"<"&99)+1) | S100: =IF($R100="","",99-IF($R100=1,0,INDEX($M$2:$M$66,$R100-1))) | T100: =IF($R100="",0,IF($S100=INDEX($L$2:$L$66,$R100),1,0)) -> 0
...

Sheet 凭证收入
B1: =IF(助手收入!$R$2<>"","记 账 凭 证","") -> 记 账 凭 证 | M1: 打印第几页 | N1: 凭证号 | O1: 凭证字号（核对用） | P1: ← 这三列是核对用的辅助列，打印区域已设成 B:I，印不出来
C3: =IF(助手收入!$R$2<>"",INDEX(助手收入!$B$2:$B$66,助手收入!$R$2),"") -> 2001 | D3: =IF(助手收入!$R$2<>"",参数!$B$2,"") -> 46234 | F3: =IF(助手收入!$R$2<>"",INDEX(助手收入!$C$2:$C$66,助手收入!$R$2)&" 字第 "&IF(参数!$B$9="是",INDEX(助手收入!$P$2:$P$66,助手收入!$R$2)," ")&" 号"&IF(INDEX(助手收入!$L$2:$L$66,助手收入!$R$2)>1," (共"&INDEX(助手收入!$L$2:$L$66,助手收入!$R$2)&"页 第"&助手收入!$S$2&"页)",""),"") -> 柏人商城店 字第 号 (共2页 第1页) | M3: =IF(助手收入!$R$2="","",助手收入!$Q$2) -> 1 | N3: =IF(助手收入!$R$2="","",INDEX(助手收入!$P$2:$P$66,助手收入!$R$2)) -> 1 | O3: =IF(助手收入!$R$2="","",INDEX(助手收入!$C$2:$C$66,助手收入!$R$2)&" 字第 "&INDEX(助手收入!$P$2:$P$66,助手收入!$R$2)&" 号"&IF(INDEX(助手收入!$L$2:$L$66,助手收入!$R$2)>1," (共"&INDEX(助手收入!$L$2:$L$66,助手收入!$R$2)&"页 第"&助手收入!$S$2&"页)","")) -> 柏人商城店 字第 1 号 (共2页 第1页)
B4: =IF(助手收入!$R$2<>"","摘 要","") -> 摘 要 | D4: =IF(助手收入!$R$2<>"","科 目","") -> 科 目 | F4: =IF(助手收入!$R$2<>"","借 方 金 额","") -> 借 方 金 额 | G4: =IF(助手收入!$R$2<>"","贷 方 金 额","") -> 贷 方 金 额 | H4: =IF(助手收入!$R$2<>"","√","") -> √ | I4: =IF(助手收入!$R$2<>"","附单据 张","") -> 附单据 张
D5: =IF(助手收入!$R$2<>"","总 账 科 目","") -> 总 账 科 目 | E5: =IF(助手收入!$R$2<>"","明 细 科 目","") -> 明 细 科 目
B6: =IFERROR(INDEX(分录收入!$M:$M,MATCH($L6,分录收入!$L:$L,0)),"") -> 7月收入 | D6: =IFERROR(INDEX(分录收入!$E:$E,MATCH($L6,分录收入!$L:$L,0)),"") -> 库存现金 | E6: =IFERROR(INDEX(分录收入!$F:$F,MATCH($L6,分录收入!$L:$L,0)),"") | F6: =IFERROR(INDEX(分录收入!$H:$H,MATCH($L6,分录收入!$L:$L,0)),"") -> 6428.43 | G6: =IFERROR(INDEX(分录收入!$I:$I,MATCH($L6,分录收入!$L:$L,0)),"") | L6: =IF(助手收入!$R$2="",-1,助手收入!$R$2*100+(助手收入!$S$2-1)*6+1) -> 101
B7: ="" | D7: =IFERROR(INDEX(分录收入!$E:$E,MATCH($L7,分录收入!$L:$L,0)),"") -> 应收账款 | E7: =IFERROR(INDEX(分录收入!$F:$F,MATCH($L7,分录收入!$L:$L,0)),"") -> 聚合支付 | F7: =IFERROR(INDEX(分录收入!$H:$H,MATCH($L7,分录收入!$L:$L,0)),"") -> 22707.04 | G7: =IFERROR(INDEX(分录收入!$I:$I,MATCH($L7,分录收入!$L:$L,0)),"") | L7: =IF(助手收入!$R$2="",-1,助手收入!$R$2*100+(助手收入!$S$2-1)*6+2) -> 102
B8: ="" | D8: =IFERROR(INDEX(分录收入!$E:$E,MATCH($L8,分录收入!$L:$L,0)),"") -> 应收账款 | E8: =IFERROR(INDEX(分录收入!$F:$F,MATCH($L8,分录收入!$L:$L,0)),"") -> 医保 | F8: =IFERROR(INDEX(分录收入!$H:$H,MATCH($L8,分录收入!$L:$L,0)),"") -> 6716.34 | G8: =IFERROR(INDEX(分录收入!$I:$I,MATCH($L8,分录收入!$L:$L,0)),"") | L8: =IF(助手收入!$R$2="",-1,助手收入!$R$2*100+(助手收入!$S$2-1)*6+3) -> 103
B9: ="" | D9: =IFERROR(INDEX(分录收入!$E:$E,MATCH($L9,分录收入!$L:$L,0)),"") -> 应收账款 | E9: =IFERROR(INDEX(分录收入!$F:$F,MATCH($L9,分录收入!$L:$L,0)),"") -> 美团 | F9: =IFERROR(INDEX(分录收入!$H:$H,MATCH($L9,分录收入!$L:$L,0)),"") -> 47.5 | G9: =IFERROR(INDEX(分录收入!$I:$I,MATCH($L9,分录收入!$L:$L,0)),"") | L9: =IF(助手收入!$R$2="",-1,助手收入!$R$2*100+(助手收入!$S$2-1)*6+4) -> 104
B10: ="" | D10: =IFERROR(INDEX(分录收入!$E:$E,MATCH($L10,分录收入!$L:$L,0)),"") -> 销售费用 | E10: =IFERROR(INDEX(分录收入!$F:$F,MATCH($L10,分录收入!$L:$L,0)),"") -> 促销费 | F10: =IFERROR(INDEX(分录收入!$H:$H,MATCH($L10,分录收入!$L:$L,0)),"") -> 448.72 | G10: =IFERROR(INDEX(分录收入!$I:$I,MATCH($L10,分录收入!$L:$L,0)),"") | L10: =IF(助手收入!$R$2="",-1,助手收入!$R$2*100+(助手收入!$S$2-1)*6+5) -> 105
B11: ="" | D11: =IFERROR(INDEX(分录收入!$E:$E,MATCH($L11,分录收入!$L:$L,0)),"") -> 财务费用 | E11: =IFERROR(INDEX(分录收入!$F:$F,MATCH($L11,分录收入!$L:$L,0)),"") -> 手续费 | F11: =IFERROR(INDEX(分录收入!$H:$H,MATCH($L11,分录收入!$L:$L,0)),"") -> 61.48 | G11: =IFERROR(INDEX(分录收入!$I:$I,MATCH($L11,分录收入!$L:$L,0)),"") | L11: =IF(助手收入!$R$2="",-1,助手收入!$R$2*100+(助手收入!$S$2-1)*6+6) -> 106
B12: =IF(助手收入!$T$2=1,"合计：","") | C12: =IF(助手收入!$T$2=1,$F12,"") | F12: =IF(助手收入!$T$2=1,INDEX(助手收入!$N$2:$N$66,助手收入!$R$2),"") | G12: =IF(助手收入!$T$2=1,INDEX(助手收入!$O$2:$O$66,助手收入!$R$2),"")
B14: =IF(助手收入!$R$2<>"","会计主管：","") -> 会计主管： | D14: =IF(助手收入!$R$2<>"","会计：","") -> 会计： | E14: =IF(助手收入!$R$2<>"","出纳：","") -> 出纳： | F14: =IF(助手收入!$R$2<>"","复核：","") -> 复核： | G14: =IF(助手收入!$R$2<>"","制单：","") -> 制单：
B16: =IF(助手收入!$R$3<>"","记 账 凭 证","") -> 记 账 凭 证
C18: =IF(助手收入!$R$3<>"",INDEX(助手收入!$B$2:$B$66,助手收入!$R$3),"") -> 2001 | D18: =IF(助手收入!$R$3<>"",参数!$B$2,"") -> 46234 | F18: =IF(助手收入!$R$3<>"",INDEX(助手收入!$C$2:$C$66,助手收入!$R$3)&" 字第 "&IF(参数!$B$9="是",INDEX(助手收入!$P$2:$P$66,助手收入!$R$3)," ")&" 号"&IF(INDEX(助手收入!$L$2:$L$66,助手收入!$R$3)>1," (共"&INDEX(助手收入!$L$2:$L$66,助手收入!$R$3)&"页 第"&助手收入!$S$3&"页)",""),"") -> 柏人商城店 字第 号 (共2页 第2页) | M18: =IF(助手收入!$R$3="","",助手收入!$Q$3) -> 2 | N18: =IF(助手收入!$R$3="","",INDEX(助手收入!$P$2:$P$66,助手收入!$R$3)) -> 1 | O18: =IF(助手收入!$R$3="","",INDEX(助手收入!$C$2:$C$66,助手收入!$R$3)&" 字第 "&INDEX(助手收入!$P$2:$P$66,助手收入!$R$3)&" 号"&IF(INDEX(助手收入!$L$2:$L$66,助手收入!$R$3)>1," (共"&INDEX(助手收入!$L$2:$L$66,助手收入!$R$3)&"页 第"&助手收入!$S$3&"页)","")) -> 柏人商城店 字第 1 号 (共2页 第2页)
B19: =IF(助手收入!$R$3<>"","摘 要","") -> 摘 要 | D19: =IF(助手收入!$R$3<>"","科 目","") -> 科 目 | F19: =IF(助手收入!$R$3<>"","借 方 金 额","") -> 借 方 金 额 | G19: =IF(助手收入!$R$3<>"","贷 方 金 额","") -> 贷 方 金 额 | H19: =IF(助手收入!$R$3<>"","√","") -> √ | I19: =IF(助手收入!$R$3<>"","附单据 张","") -> 附单据 张
D20: =IF(助手收入!$R$3<>"","总 账 科 目","") -> 总 账 科 目 | E20: =IF(助手收入!$R$3<>"","明 细 科 目","") -> 明 细 科 目
B21: =IFERROR(INDEX(分录收入!$M:$M,MATCH($L21,分录收入!$L:$L,0)),"") -> 7月收入 | D21: =IFERROR(INDEX(分录收入!$E:$E,MATCH($L21,分录收入!$L:$L,0)),"") -> 主营业务收入 | E21: =IFERROR(INDEX(分录收入!$F:$F,MATCH($L21,分录收入!$L:$L,0)),"") | F21: =IFERROR(INDEX(分录收入!$H:$H,MATCH($L21,分录收入!$L:$L,0)),"") | G21: =IFERROR(INDEX(分录收入!$I:$I,MATCH($L21,分录收入!$L:$L,0)),"") -> 36409.51 | L21: =IF(助手收入!$R$3="",-1,助手收入!$R$3*100+(助手收入!$S$3-1)*6+1) -> 107
B22: ="" | D22: =IFERROR(INDEX(分录收入!$E:$E,MATCH($L22,分录收入!$L:$L,0)),"") | E22: =IFERROR(INDEX(分录收入!$F:$F,MATCH($L22,分录收入!$L:$L,0)),"") | F22: =IFERROR(INDEX(分录收入!$H:$H,MATCH($L22,分录收入!$L:$L,0)),"") | G22: =IFERROR(INDEX(分录收入!$I:$I,MATCH($L22,分录收入!$L:$L,0)),"") | L22: =IF(助手收入!$R$3="",-1,助手收入!$R$3*100+(助手收入!$S$3-1)*6+2) -> 108
B23: ="" | D23: =IFERROR(INDEX(分录收入!$E:$E,MATCH($L23,分录收入!$L:$L,0)),"") | E23: =IFERROR(INDEX(分录收入!$F:$F,MATCH($L23,分录收入!$L:$L,0)),"") | F23: =IFERROR(INDEX(分录收入!$H:$H,MATCH($L23,分录收入!$L:$L,0)),"") | G23: =IFERROR(INDEX(分录收入!$I:$I,MATCH($L23,分录收入!$L:$L,0)),"") | L23: =IF(助手收入!$R$3="",-1,助手收入!$R$3*100+(助手收入!$S$3-1)*6+3) -> 109
B24: ="" | D24: =IFERROR(INDEX(分录收入!$E:$E,MATCH($L24,分录收入!$L:$L,0)),"") | E24: =IFERROR(INDEX(分录收入!$F:$F,MATCH($L24,分录收入!$L:$L,0)),"") | F24: =IFERROR(INDEX(分录收入!$H:$H,MATCH($L24,分录收入!$L:$L,0)),"") | G24: =IFERROR(INDEX(分录收入!$I:$I,MATCH($L24,分录收入!$L:$L,0)),"") | L24: =IF(助手收入!$R$3="",-1,助手收入!$R$3*100+(助手收入!$S$3-1)*6+4) -> 110
B25: ="" | D25: =IFERROR(INDEX(分录收入!$E:$E,MATCH($L25,分录收入!$L:$L,0)),"") | E25: =IFERROR(INDEX(分录收入!$F:$F,MATCH($L25,分录收入!$L:$L,0)),"") | F25: =IFERROR(INDEX(分录收入!$H:$H,MATCH($L25,分录收入!$L:$L,0)),"") | G25: =IFERROR(INDEX(分录收入!$I:$I,MATCH($L25,分录收入!$L:$L,0)),"") | L25: =IF(助手收入!$R$3="",-1,助手收入!$R$3*100+(助手收入!$S$3-1)*6+5) -> 111
B26: ="" | D26: =IFERROR(INDEX(分录收入!$E:$E,MATCH($L26,分录收入!$L:$L,0)),"") | E26: =IFERROR(INDEX(分录收入!$F:$F,MATCH($L26,分录收入!$L:$L,0)),"") | F26: =IFERROR(INDEX(分录收入!$H:$H,MATCH($L26,分录收入!$L:$L,0)),"") | G26: =IFERROR(INDEX(分录收入!$I:$I,MATCH($L26,分录收入!$L:$L,0)),"") | L26: =IF(助手收入!$R$3="",-1,助手收入!$R$3*100+(助手收入!$S$3-1)*6+6) -> 112
B27: =IF(助手收入!$T$3=1,"合计：","") -> 合计： | C27: =IF(助手收入!$T$3=1,$F27,"") -> 36409.51 | F27: =IF(助手收入!$T$3=1,INDEX(助手收入!$N$2:$N$66,助手收入!$R$3),"") -> 36409.51 | G27: =IF(助手收入!$T$3=1,INDEX(助手收入!$O$2:$O$66,助手收入!$R$3),"") -> 36409.51
B29: =IF(助手收入!$R$3<>"","会计主管：","") -> 会计主管： | D29: =IF(助手收入!$R$3<>"","会计：","") -> 会计： | E29: =IF(助手收入!$R$3<>"","出纳：","") -> 出纳： | F29: =IF(助手收入!$R$3<>"","复核：","") -> 复核： | G29: =IF(助手收入!$R$3<>"","制单：","") -> 制单：
B31: =IF(助手收入!$R$4<>"","记 账 凭 证","") -> 记 账 凭 证
C33: =IF(助手收入!$R$4<>"",INDEX(助手收入!$B$2:$B$66,助手收入!$R$4),"") -> 2002 | D33: =IF(助手收入!$R$4<>"",参数!$B$2,"") -> 46234 | F33: =IF(助手收入!$R$4<>"",INDEX(助手收入!$C$2:$C$66,助手收入!$R$4)&" 字第 "&IF(参数!$B$9="是",INDEX(助手收入!$P$2:$P$66,助手收入!$R$4)," ")&" 号"&IF(INDEX(助手收入!$L$2:$L$66,助手收入!$R$4)>1," (共"&INDEX(助手收入!$L$2:$L$66,助手收入!$R$4)&"页 第"&助手收入!$S$4&"页)",""),"") -> 新隆店 字第 号 (共2页 第1页) | M33: =IF(助手收入!$R$4="","",助手收入!$Q$4) -> 3 | N33: =IF(助手收入!$R$4="","",INDEX(助手收入!$P$2:$P$66,助手收入!$R$4)) -> 2 | O33: =IF(助手收入!$R$4="","",INDEX(助手收入!$C$2:$C$66,助手收入!$R$4)&" 字第 "&INDEX(助手收入!$P$2:$P$66,助手收入!$R$4)&" 号"&IF(INDEX(助手收入!$L$2:$L$66,助手收入!$R$4)>1," (共"&INDEX(助手收入!$L$2:$L$66,助手收入!$R$4)&"页 第"&助手收入!$S$4&"页)","")) -> 新隆店 字第 2 号 (共2页 第1页)
B34: =IF(助手收入!$R$4<>"","摘 要","") -> 摘 要 | D34: =IF(助手收入!$R$4<>"","科 目","") -> 科 目 | F34: =IF(助手收入!$R$4<>"","借 方 金 额","") -> 借 方 金 额 | G34: =IF(助手收入!$R$4<>"","贷 方 金 额","") -> 贷 方 金 额 | H34: =IF(助手收入!$R$4<>"","√","") -> √ | I34: =IF(助手收入!$R$4<>"","附单据 张","") -> 附单据 张
D35: =IF(助手收入!$R$4<>"","总 账 科 目","") -> 总 账 科 目 | E35: =IF(助手收入!$R$4<>"","明 细 科 目","") -> 明 细 科 目
B36: =IFERROR(INDEX(分录收入!$M:$M,MATCH($L36,分录收入!$L:$L,0)),"") -> 7月收入 | D36: =IFERROR(INDEX(分录收入!$E:$E,MATCH($L36,分录收入!$L:$L,0)),"") -> 库存现金 | E36: =IFERROR(INDEX(分录收入!$F:$F,MATCH($L36,分录收入!$L:$L,0)),"") | F36: =IFERROR(INDEX(分录收入!$H:$H,MATCH($L36,分录收入!$L:$L,0)),"") -> 290970.85 | G36: =IFERROR(INDEX(分录收入!$I:$I,MATCH($L36,分录收入!$L:$L,0)),"") | L36: =IF(助手收入!$R$4="",-1,助手收入!$R$4*100+(助手收入!$S$4-1)*6+1) -> 201
B37: ="" | D37: =IFERROR(INDEX(分录收入!$E:$E,MATCH($L37,分录收入!$L:$L,0)),"") -> 应收账款 | E37: =IFERROR(INDEX(分录收入!$F:$F,MATCH($L37,分录收入!$L:$L,0)),"") -> 聚合支付 | F37: =IFERROR(INDEX(分录收入!$H:$H,MATCH($L37,分录收入!$L:$L,0)),"") -> 102925.1 | G37: =IFERROR(INDEX(分录收入!$I:$I,MATCH($L37,分录收入!$L:$L,0)),"") | L37: =IF(助手收入!$R$4="",-1,助手收入!$R$4*100+(助手收入!$S$4-1)*6+2) -> 202
B38: ="" | D38: =IFERROR(INDEX(分录收入!$E:$E,MATCH($L38,分录收入!$L:$L,0)),"") -> 应收账款 | E38: =IFERROR(INDEX(分录收入!$F:$F,MATCH($L38,分录收入!$L:$L,0)),"") -> 医保 | F38: =IFERROR(INDEX(分录收入!$H:$H,MATCH($L38,分录收入!$L:$L,0)),"") -> 45021.37 | G38: =IFERROR(INDEX(分录收入!$I:$I,MATCH($L38,分录收入!$L:$L,0)),"") | L38: =IF(助手收入!$R$4="",-1,助手收入!$R$4*100+(助手收入!$S$4-1)*6+3) -> 203
B39: ="" | D39: =IFERROR(INDEX(分录收入!$E:$E,MATCH($L39,分录收入!$L:$L,0)),"") -> 其他应收款 | E39: =IFERROR(INDEX(分录收入!$F:$F,MATCH($L39,分录收入!$L:$L,0)),"") -> 储值卡 | F39: =IFERROR(INDEX(分录收入!$H:$H,MATCH($L39,分录收入!$L:$L,0)),"") -> 2656.85 | G39: =IFERROR(INDEX(分录收入!$I:$I,MATCH($L39,分录收入!$L:$L,0)),"") | L39: =IF(助手收入!$R$4="",-1,助手收入!$R$4*100+(助手收入!$S$4-1)*6+4) -> 204
B40: ="" | D40: =IFERROR(INDEX(分录收入!$E:$E,MATCH($L40,分录收入!$L:$L,0)),"") -> 销售费用 | E40: =IFERROR(INDEX(分录收入!$F:$F,MATCH($L40,分录收入!$L:$L,0)),"") -> 促销费 | F40: =IFERROR(INDEX(分录收入!$H:$H,MATCH($L40,分录收入!$L:$L,0)),"") -> 2268.63 | G40: =IFERROR(INDEX(分录收入!$I:$I,MATCH($L40,分录收入!$L:$L,0)),"") | L40: =IF(助手收入!$R$4="",-1,助手收入!$R$4*100+(助手收入!$S$4-1)*6+5) -> 205
B41: ="" | D41: =IFERROR(INDEX(分录收入!$E:$E,MATCH($L41,分录收入!$L:$L,0)),"") -> 财务费用 | E41: =IFERROR(INDEX(分录收入!$F:$F,MATCH($L41,分录收入!$L:$L,0)),"") -> 手续费 | F41: =IFERROR(INDEX(分录收入!$H:$H,MATCH($L41,分录收入!$L:$L,0)),"") -> 278.65 | G41: =IFERROR(INDEX(分录收入!$I:$I,MATCH($L41,分录收入!$L:$L,0)),"") | L41: =IF(助手收入!$R$4="",-1,助手收入!$R$4*100+(助手收入!$S$4-1)*6+6) -> 206
B42: =IF(助手收入!$T$4=1,"合计：","") | C42: =IF(助手收入!$T$4=1,$F42,"") | F42: =IF(助手收入!$T$4=1,INDEX(助手收入!$N$2:$N$66,助手收入!$R$4),"") | G42: =IF(助手收入!$T$4=1,INDEX(助手收入!$O$2:$O$66,助手收入!$R$4),"")
B44: =IF(助手收入!$R$4<>"","会计主管：","") -> 会计主管： | D44: =IF(助手收入!$R$4<>"","会计：","") -> 会计： | E44: =IF(助手收入!$R$4<>"","出纳：","") -> 出纳： | F44: =IF(助手收入!$R$4<>"","复核：","") -> 复核： | G44: =IF(助手收入!$R$4<>"","制单：","") -> 制单：
B46: =IF(助手收入!$R$5<>"","记 账 凭 证","") -> 记 账 凭 证
C48: =IF(助手收入!$R$5<>"",INDEX(助手收入!$B$2:$B$66,助手收入!$R$5),"") -> 2002 | D48: =IF(助手收入!$R$5<>"",参数!$B$2,"") -> 46234 | F48: =IF(助手收入!$R$5<>"",INDEX(助手收入!$C$2:$C$66,助手收入!$R$5)&" 字第 "&IF(参数!$B$9="是",INDEX(助手收入!$P$2:$P$66,助手收入!$R$5)," ")&" 号"&IF(INDEX(助手收入!$L$2:$L$66,助手收入!$R$5)>1," (共"&INDEX(助手收入!$L$2:$L$66,助手收入!$R$5)&"页 第"&助手收入!$S$5&"页)",""),"") -> 新隆店 字第 号 (共2页 第2页) | M48: =IF(助手收入!$R$5="","",助手收入!$Q$5) -> 4 | N48: =IF(助手收入!$R$5="","",INDEX(助手收入!$P$2:$P$66,助手收入!$R$5)) -> 2 | O48: =IF(助手收入!$R$5="","",INDEX(助手收入!$C$2:$C$66,助手收入!$R$5)&" 字第 "&INDEX(助手收入!$P$2:$P$66,助手收入!$R$5)&" 号"&IF(INDEX(助手收入!$L$2:$L$66,助手收入!$R$5)>1," (共"&INDEX(助手收入!$L$2:$L$66,助手收入!$R$5)&"页 第"&助手收入!$S$5&"页)","")) -> 新隆店 字第 2 号 (共2页 第2页)
B49: =IF(助手收入!$R$5<>"","摘 要","") -> 摘 要 | D49: =IF(助手收入!$R$5<>"","科 目","") -> 科 目 | F49: =IF(助手收入!$R$5<>"","借 方 金 额","") -> 借 方 金 额 | G49: =IF(助手收入!$R$5<>"","贷 方 金 额","") -> 贷 方 金 额 | H49: =IF(助手收入!$R$5<>"","√","") -> √ | I49: =IF(助手收入!$R$5<>"","附单据 张","") -> 附单据 张
D50: =IF(助手收入!$R$5<>"","总 账 科 目","") -> 总 账 科 目 | E50: =IF(助手收入!$R$5<>"","明 细 科 目","") -> 明 细 科 目
B51: =IFERROR(INDEX(分录收入!$M:$M,MATCH($L51,分录收入!$L:$L,0)),"") -> 7月收入 | D51: =IFERROR(INDEX(分录收入!$E:$E,MATCH($L51,分录收入!$L:$L,0)),"") -> 主营业务收入 | E51: =IFERROR(INDEX(分录收入!$F:$F,MATCH($L51,分录收入!$L:$L,0)),"") | F51: =IFERROR(INDEX(分录收入!$H:$H,MATCH($L51,分录收入!$L:$L,0)),"") | G51: =IFERROR(INDEX(分录收入!$I:$I,MATCH($L51,分录收入!$L:$L,0)),"") -> 444121.45 | L51: =IF(助手收入!$R$5="",-1,助手收入!$R$5*100+(助手收入!$S$5-1)*6+1) -> 207
B52: ="" | D52: =IFERROR(INDEX(分录收入!$E:$E,MATCH($L52,分录收入!$L:$L,0)),"") | E52: =IFERROR(INDEX(分录收入!$F:$F,MATCH($L52,分录收入!$L:$L,0)),"") | F52: =IFERROR(INDEX(分录收入!$H:$H,MATCH($L52,分录收入!$L:$L,0)),"") | G52: =IFERROR(INDEX(分录收入!$I:$I,MATCH($L52,分录收入!$L:$L,0)),"") | L52: =IF(助手收入!$R$5="",-1,助手收入!$R$5*100+(助手收入!$S$5-1)*6+2) -> 208
B53: ="" | D53: =IFERROR(INDEX(分录收入!$E:$E,MATCH($L53,分录收入!$L:$L,0)),"") | E53: =IFERROR(INDEX(分录收入!$F:$F,MATCH($L53,分录收入!$L:$L,0)),"") | F53: =IFERROR(INDEX(分录收入!$H:$H,MATCH($L53,分录收入!$L:$L,0)),"") | G53: =IFERROR(INDEX(分录收入!$I:$I,MATCH($L53,分录收入!$L:$L,0)),"") | L53: =IF(助手收入!$R$5="",-1,助手收入!$R$5*100+(助手收入!$S$5-1)*6+3) -> 209
B54: ="" | D54: =IFERROR(INDEX(分录收入!$E:$E,MATCH($L54,分录收入!$L:$L,0)),"") | E54: =IFERROR(INDEX(分录收入!$F:$F,MATCH($L54,分录收入!$L:$L,0)),"") | F54: =IFERROR(INDEX(分录收入!$H:$H,MATCH($L54,分录收入!$L:$L,0)),"") | G54: =IFERROR(INDEX(分录收入!$I:$I,MATCH($L54,分录收入!$L:$L,0)),"") | L54: =IF(助手收入!$R$5="",-1,助手收入!$R$5*100+(助手收入!$S$5-1)*6+4) -> 210
B55: ="" | D55: =IFERROR(INDEX(分录收入!$E:$E,MATCH($L55,分录收入!$L:$L,0)),"") | E55: =IFERROR(INDEX(分录收入!$F:$F,MATCH($L55,分录收入!$L:$L,0)),"") | F55: =IFERROR(INDEX(分录收入!$H:$H,MATCH($L55,分录收入!$L:$L,0)),"") | G55: =IFERROR(INDEX(分录收入!$I:$I,MATCH($L55,分录收入!$L:$L,0)),"") | L55: =IF(助手收入!$R$5="",-1,助手收入!$R$5*100+(助手收入!$S$5-1)*6+5) -> 211
B56: ="" | D56: =IFERROR(INDEX(分录收入!$E:$E,MATCH($L56,分录收入!$L:$L,0)),"") | E56: =IFERROR(INDEX(分录收入!$F:$F,MATCH($L56,分录收入!$L:$L,0)),"") | F56: =IFERROR(INDEX(分录收入!$H:$H,MATCH($L56,分录收入!$L:$L,0)),"") | G56: =IFERROR(INDEX(分录收入!$I:$I,MATCH($L56,分录收入!$L:$L,0)),"") | L56: =IF(助手收入!$R$5="",-1,助手收入!$R$5*100+(助手收入!$S$5-1)*6+6) -> 212
B57: =IF(助手收入!$T$5=1,"合计：","") -> 合计： | C57: =IF(助手收入!$T$5=1,$F57,"") -> 444121.45 | F57: =IF(助手收入!$T$5=1,INDEX(助手收入!$N$2:$N$66,助手收入!$R$5),"") -> 444121.45 | G57: =IF(助手收入!$T$5=1,INDEX(助手收入!$O$2:$O$66,助手收入!$R$5),"") -> 444121.45
B59: =IF(助手收入!$R$5<>"","会计主管：","") -> 会计主管： | D59: =IF(助手收入!$R$5<>"","会计：","") -> 会计： | E59: =IF(助手收入!$R$5<>"","出纳：","") -> 出纳： | F59: =IF(助手收入!$R$5<>"","复核：","") -> 复核： | G59: =IF(助手收入!$R$5<>"","制单：","") -> 制单：
B61: =IF(助手收入!$R$6<>"","记 账 凭 证","") -> 记 账 凭 证
C63: =IF(助手收入!$R$6<>"",INDEX(助手收入!$B$2:$B$66,助手收入!$R$6),"") -> 2003 | D63: =IF(助手收入!$R$6<>"",参数!$B$2,"") -> 46234 | F63: =IF(助手收入!$R$6<>"",INDEX(助手收入!$C$2:$C$66,助手收入!$R$6)&" 字第 "&IF(参数!$B$9="是",INDEX(助手收入!$P$2:$P$66,助手收入!$R$6)," ")&" 号"&IF(INDEX(助手收入!$L$2:$L$66,助手收入!$R$6)>1," (共"&INDEX(助手收入!$L$2:$L$66,助手收入!$R$6)&"页 第"&助手收入!$S$6&"页)",""),"") -> 康庄路店 字第 号 (共2页 第1页) | M63: =IF(助手收入!$R$6="","",助手收入!$Q$6) -> 5 | N63: =IF(助手收入!$R$6="","",INDEX(助手收入!$P$2:$P$66,助手收入!$R$6)) -> 3 | O63: =IF(助手收入!$R$6="","",INDEX(助手收入!$C$2:$C$66,助手收入!$R$6)&" 字第 "&INDEX(助手收入!$P$2:$P$66,助手收入!$R$6)&" 号"&IF(INDEX(助手收入!$L$2:$L$66,助手收入!$R$6)>1," (共"&INDEX(助手收入!$L$2:$L$66,助手收入!$R$6)&"页 第"&助手收入!$S$6&"页)","")) -> 康庄路店 字第 3 号 (共2页 第1页)
B64: =IF(助手收入!$R$6<>"","摘 要","") -> 摘 要 | D64: =IF(助手收入!$R$6<>"","科 目","") -> 科 目 | F64: =IF(助手收入!$R$6<>"","借 方 金 额","") -> 借 方 金 额 | G64: =IF(助手收入!$R$6<>"","贷 方 金 额","") -> 贷 方 金 额 | H64: =IF(助手收入!$R$6<>"","√","") -> √ | I64: =IF(助手收入!$R$6<>"","附单据 张","") -> 附单据 张
D65: =IF(助手收入!$R$6<>"","总 账 科 目","") -> 总 账 科 目 | E65: =IF(助手收入!$R$6<>"","明 细 科 目","") -> 明 细 科 目
