Workbook
Name 账户表: 基础资料!$B$5:$B$34
Name 账户类型表: 基础资料!$C$5:$C$34
Name 账户期初: 基础资料!$D$5:$D$34
Name 账户启用: 基础资料!$E$5:$E$34
Name 类别表: 基础资料!$H$5:$H$44
Name 类别属性: 基础资料!$I$5:$I$44
Name 客户表: 基础资料!$K$5:$K$204
Name 供应商表: 基础资料!$M$5:$M$204
Name 项目表: 基础资料!$O$5:$O$54
Name 管理年度: 基础资料!$R$5
Name 流水日期: 数据录入!$B$5:$B$5004
Name 流水账户: 数据录入!$C$5:$C$5004
Name 流水类别: 数据录入!$D$5:$D$5004
Name 流水收入: 数据录入!$F$5:$F$5004
Name 流水支出: 数据录入!$G$5:$G$5004
Name 流水月份: 数据录入!$K$5:$K$5004
Name 流水属性: 数据录入!$L$5:$L$5004
Name 流水对方: 数据录入!$M$5:$M$5004
Name 流水客户: 数据录入!$I$5:$I$5004
Name 流水供应商: 数据录入!$J$5:$J$5004
Name 流水项目: 数据录入!$N$5:$N$5004
Name 流水核对: 数据录入!$P$5:$P$5004
Name 日报期末合计: 汇报表!$BO$38
Name 月报收入合计: 月度汇报表!$B$17
Name 月报支出合计: 月度汇报表!$C$17
Name 月报转入合计: 月度汇报表!$E$17
Name 月报转出合计: 月度汇报表!$F$17
Name 分类收入合计: 收支分类报表!$O$5
Name 分类支出合计: 收支分类报表!$O$6
Name 分类转账净额: 收支分类报表!$O$7
Name 报表收入总额: 收支报表!$O$4
Name 报表支出总额: 收支报表!$O$48

Sheet 使用说明
A1: 资金日报表 · 混合录入版 ｜ 使用说明（单币种：人民币）
A3: 一、两步就能用起来
A4: 第 1 步 | B4: 【基础资料】 | C4: 把账户档案改成你们真实的账户：账户名称、类型、期初余额。收支类别、客户、供应商、项目也在这一页维护。
A5: 第 2 步 | B5: 【数据录入】 | C5: 每天在这一张录。选账户 → 余额自动结；收入和支出分两列，只填一个。其余所有表全自动。
A7: 二、账户之间互转怎么录
A8: 录两行 | B8: 转出一行、转入一行 | C8: 转出账户记一笔「支出」，转入账户记一笔「收入」，两行的「收/支类别」都选「内部转账」。
A9: 写上对方 | B9: 「对方账户」列 | C9: 转出那行写转入账户名，转入那行写转出账户名。核对列会盯着你有没有写。
A10: 报表里怎么显示 | B10: 单列，不进合计 | C10: 【月度汇报表】和【汇报表】③ 各有「内部转入 / 内部转出」两列；【收支分类报表】单列一行「内部转账净额」。收入合计、支出合计里都不含它。
A11: 净额应该是 0 | B11: 不是 0 = 漏了一头 | C11: 同一笔转账两头金额相等，净额自然是 0。
A13: 三、界面说明
A14: 表名 | B14: 哪一块 | C14: 说明
A15: 汇报表 ① | B15: 资金日报统计表 | C15: 改上面两个日期，最多 31 天，每天两列「收款 / 付款」。这一块是「账户口径」：内部划转也算进收款付款，因为账户余额确实动了。
A16: 汇报表 ② | B16: 货币资金日报表 | C16: 指定某一天，各账户的昨日余额 / 本日收入 / 本日支出 / 本日余额。也是账户口径。
A17: 汇报表 ③ | B17: 多帐户资金汇总表 | C17: 按月，这一块是「经营口径」：本月收入 / 本月支出不含内部划转，内部转入 / 内部转出另开两列。
A18: 收支报表 | B18: 12 个月 | C18: 收入按客户、支出按收支类别，上下两块分开列
A19: 任意时间段收支报表 | B19: 任意起止日期 | C19: 左右两栏收支分列
A20: 账户子表 | B20: 每个账户一张（现在 14 张） | C20: 自动从【数据录入】拆，不用填。B2 是拆分依据。
A22: 四、加东西怎么加
A23: 加一个账户 | B23: 两步 | C23: ① 【基础资料】账户档案接着写一行（记得填期初余额）； ② 右键复制任意一张账户子表，改表名，把 B2 改成新账户名。【汇报表】三块会自动多出这一行。
A24: 加一个收支类别 | B24: 一步 | C24: 【基础资料】收支类别接着写，「属性一定要填」（收入 / 支出 / 内部转账）。【收支分类报表】自动多一行。
A25: 加客户 / 供应商 / 项目 | B25: 一步 | C25: 【基础资料】对应清单接着写。【收支报表】和【任意时间段收支报表】的清单是手填的，记得把新客户也补到那两张表的空行里（不补也不会少数，会落到「未列示」那一行）。
A26: 行数 | C26: 流水预留 5000 行、账户 30 个、收支类别 40 个、客户和供应商各 200 个、子表每张 600 行。
A28: 五、颜色和符号
A29: 淡黄色格子 | B29: 要你填 | C29: 这是人工输入区。
A30: 灰色格子 | B30: 公式自动算 | C30: 别手动改，改了就把公式顶掉了。
A31: ※ 红字 | B31: 是错，必须改 | C31: 账户不在档案、收支同时填、金额填了负数、类别不在清单……
A32: △ 琥珀字 | B32: 待补的数据 | C32: 内部转账没写对方账户、余额成负数……不影响公式，补齐了数才准。

Sheet 基础资料
A1: 基础资料 · 账户、收支类别、客户、供应商都在这里维护
A2: 淡黄色格子是要你填的，灰色是公式算的。账户名称必须唯一。「收支类别」多一列「属性」：收入 / 支出 / 内部转账 —— 属性填「内部转账」的，不计入收入合计和支出合计，账户之间互转就靠它。
A3: 一、账户档案 —— 加一个账户：这里接着写一行，再复制一张账户子表改 B2 | H3: 二、收支类别（属性 = 内部转账的不计入收支合计） | K3: 三、客户 | M3: 四、供应商 | O3: 五、项目 / 部门 | Q3: 六、参数
A4: 序号 | B4: 账户名称 ★（唯一） | C4: 账户类型 | D4: 期初余额 | E4: 启用日期 | F4: 核对 | H4: 收/支类别 ★ | I4: 属性 ★ | K4: 客户 | M4: 供应商 | O4: 项目 / 部门 | Q4: 参数 | R4: 值
A5: =IF($B5="","",COUNTA($B$5:$B5)) -> 1 | B5: 现金 | C5: 现金 | D5: 5000 | E5: 46174 | F5: =IF($B5="","",IF(COUNTIF($B$5:$B$34,$B5)>1,"※账户名称重复了，后面按名字取数会串",IF($D5="","※期初余额没填（没有就填 0）",IF(AND($E5<>"",COUNTIFS(流水账户,$B5,流水日期,"<"&$E5)>0),"※有流水的日期早于启用日期，期初余额会重复计算","")))) | H5: 销售回款 | I5: 收入 | K5: 客户1 | M5: 供应商1 | O5: 主营业务 | Q5: 管理年度 | R5: 2026 | S5: 按月的三张报表（月度汇报表 / 收支分类报表 / 收支报表）看哪一年，改这里
A6: =IF($B6="","",COUNTA($B$5:$B6)) -> 2 | B6: 微信 | C6: 微信 | D6: 6000 | E6: 46174 | F6: =IF($B6="","",IF(COUNTIF($B$5:$B$34,$B6)>1,"※账户名称重复了，后面按名字取数会串",IF($D6="","※期初余额没填（没有就填 0）",IF(AND($E6<>"",COUNTIFS(流水账户,$B6,流水日期,"<"&$E6)>0),"※有流水的日期早于启用日期，期初余额会重复计算","")))) | H6: 其他业务收入 | I6: 收入 | K6: 客户2 | M6: 供应商2 | O6: 其他业务 | Q6: 本位币 | R6: 人民币 | S6: 这套表是单币种的
A7: =IF($B7="","",COUNTA($B$5:$B7)) -> 3 | B7: 工行 | C7: 银行 | D7: 7000 | E7: 46174 | F7: =IF($B7="","",IF(COUNTIF($B$5:$B$34,$B7)>1,"※账户名称重复了，后面按名字取数会串",IF($D7="","※期初余额没填（没有就填 0）",IF(AND($E7<>"",COUNTIFS(流水账户,$B7,流水日期,"<"&$E7)>0),"※有流水的日期早于启用日期，期初余额会重复计算","")))) | H7: 投资款 | I7: 收入 | K7: 客户3 | M7: 供应商3 | O7: 行政
A8: =IF($B8="","",COUNTA($B$5:$B8)) -> 4 | B8: 民生 | C8: 银行 | D8: 8000 | E8: 46174 | F8: =IF($B8="","",IF(COUNTIF($B$5:$B$34,$B8)>1,"※账户名称重复了，后面按名字取数会串",IF($D8="","※期初余额没填（没有就填 0）",IF(AND($E8<>"",COUNTIFS(流水账户,$B8,流水日期,"<"&$E8)>0),"※有流水的日期早于启用日期，期初余额会重复计算","")))) | H8: 借款 | I8: 收入 | K8: 客户4 | M8: 供应商4 | O8: 融资
A9: =IF($B9="","",COUNTA($B$5:$B9)) -> 5 | B9: 建行 | C9: 银行 | D9: 9000 | E9: 46174 | F9: =IF($B9="","",IF(COUNTIF($B$5:$B$34,$B9)>1,"※账户名称重复了，后面按名字取数会串",IF($D9="","※期初余额没填（没有就填 0）",IF(AND($E9<>"",COUNTIFS(流水账户,$B9,流水日期,"<"&$E9)>0),"※有流水的日期早于启用日期，期初余额会重复计算","")))) | H9: 利息收入 | I9: 收入 | K9: 客户5 | M9: 供应商5 | O9: 内部调拨
A10: =IF($B10="","",COUNTA($B$5:$B10)) -> 6 | B10: 农行 | C10: 银行 | D10: 10000 | E10: 46174 | F10: =IF($B10="","",IF(COUNTIF($B$5:$B$34,$B10)>1,"※账户名称重复了，后面按名字取数会串",IF($D10="","※期初余额没填（没有就填 0）",IF(AND($E10<>"",COUNTIFS(流水账户,$B10,流水日期,"<"&$E10)>0),"※有流水的日期早于启用日期，期初余额会重复计算","")))) | H10: 退款收回 | I10: 收入 | K10: 客户6 | M10: 供应商6
A11: =IF($B11="","",COUNTA($B$5:$B11)) -> 7 | B11: 中行 | C11: 银行 | D11: 11000 | E11: 46174 | F11: =IF($B11="","",IF(COUNTIF($B$5:$B$34,$B11)>1,"※账户名称重复了，后面按名字取数会串",IF($D11="","※期初余额没填（没有就填 0）",IF(AND($E11<>"",COUNTIFS(流水账户,$B11,流水日期,"<"&$E11)>0),"※有流水的日期早于启用日期，期初余额会重复计算","")))) | H11: 政府补助 | I11: 收入 | K11: 客户7 | M11: 供应商7
A12: =IF($B12="","",COUNTA($B$5:$B12)) -> 8 | B12: 支付宝 | C12: 第三方 | D12: 12000 | E12: 46174 | F12: =IF($B12="","",IF(COUNTIF($B$5:$B$34,$B12)>1,"※账户名称重复了，后面按名字取数会串",IF($D12="","※期初余额没填（没有就填 0）",IF(AND($E12<>"",COUNTIFS(流水账户,$B12,流水日期,"<"&$E12)>0),"※有流水的日期早于启用日期，期初余额会重复计算","")))) | H12: 供应商 | I12: 支出 | K12: 客户8 | M12: 供应商8
A13: =IF($B13="","",COUNTA($B$5:$B13)) -> 9 | B13: 农商行 | C13: 银行 | D13: 13000 | E13: 46174 | F13: =IF($B13="","",IF(COUNTIF($B$5:$B$34,$B13)>1,"※账户名称重复了，后面按名字取数会串",IF($D13="","※期初余额没填（没有就填 0）",IF(AND($E13<>"",COUNTIFS(流水账户,$B13,流水日期,"<"&$E13)>0),"※有流水的日期早于启用日期，期初余额会重复计算","")))) | H13: 办公费 | I13: 支出 | K13: 客户9 | M13: 供应商9
A14: =IF($B14="","",COUNTA($B$5:$B14)) -> 10 | B14: 备用 | C14: 备用 | D14: 14000 | E14: 46174 | F14: =IF($B14="","",IF(COUNTIF($B$5:$B$34,$B14)>1,"※账户名称重复了，后面按名字取数会串",IF($D14="","※期初余额没填（没有就填 0）",IF(AND($E14<>"",COUNTIFS(流水账户,$B14,流水日期,"<"&$E14)>0),"※有流水的日期早于启用日期，期初余额会重复计算","")))) | H14: 水费 | I14: 支出 | K14: 客户10 | M14: 供应商10
A15: =IF($B15="","",COUNTA($B$5:$B15)) -> 11 | B15: 备用1 | C15: 备用 | D15: 15000 | E15: 46174 | F15: =IF($B15="","",IF(COUNTIF($B$5:$B$34,$B15)>1,"※账户名称重复了，后面按名字取数会串",IF($D15="","※期初余额没填（没有就填 0）",IF(AND($E15<>"",COUNTIFS(流水账户,$B15,流水日期,"<"&$E15)>0),"※有流水的日期早于启用日期，期初余额会重复计算","")))) | H15: 电费 | I15: 支出 | K15: 客户11 | M15: 供应商11
A16: =IF($B16="","",COUNTA($B$5:$B16)) -> 12 | B16: 备用2 | C16: 备用 | D16: 16000 | E16: 46174 | F16: =IF($B16="","",IF(COUNTIF($B$5:$B$34,$B16)>1,"※账户名称重复了，后面按名字取数会串",IF($D16="","※期初余额没填（没有就填 0）",IF(AND($E16<>"",COUNTIFS(流水账户,$B16,流水日期,"<"&$E16)>0),"※有流水的日期早于启用日期，期初余额会重复计算","")))) | H16: 伙食费 | I16: 支出 | K16: 客户12 | M16: 供应商12
A17: =IF($B17="","",COUNTA($B$5:$B17)) -> 13 | B17: 备用3 | C17: 备用 | D17: 17000 | E17: 46174 | F17: =IF($B17="","",IF(COUNTIF($B$5:$B$34,$B17)>1,"※账户名称重复了，后面按名字取数会串",IF($D17="","※期初余额没填（没有就填 0）",IF(AND($E17<>"",COUNTIFS(流水账户,$B17,流水日期,"<"&$E17)>0),"※有流水的日期早于启用日期，期初余额会重复计算","")))) | H17: 工资 | I17: 支出 | K17: 客户13 | M17: 供应商13
A18: =IF($B18="","",COUNTA($B$5:$B18)) -> 14 | B18: 备用4 | C18: 备用 | D18: 18000 | E18: 46174 | F18: =IF($B18="","",IF(COUNTIF($B$5:$B$34,$B18)>1,"※账户名称重复了，后面按名字取数会串",IF($D18="","※期初余额没填（没有就填 0）",IF(AND($E18<>"",COUNTIFS(流水账户,$B18,流水日期,"<"&$E18)>0),"※有流水的日期早于启用日期，期初余额会重复计算","")))) | H18: 租赁费 | I18: 支出
A19: =IF($B19="","",COUNTA($B$5:$B19)) | F19: =IF($B19="","",IF(COUNTIF($B$5:$B$34,$B19)>1,"※账户名称重复了，后面按名字取数会串",IF($D19="","※期初余额没填（没有就填 0）",IF(AND($E19<>"",COUNTIFS(流水账户,$B19,流水日期,"<"&$E19)>0),"※有流水的日期早于启用日期，期初余额会重复计算","")))) | H19: 差旅费 | I19: 支出
A20: =IF($B20="","",COUNTA($B$5:$B20)) | F20: =IF($B20="","",IF(COUNTIF($B$5:$B$34,$B20)>1,"※账户名称重复了，后面按名字取数会串",IF($D20="","※期初余额没填（没有就填 0）",IF(AND($E20<>"",COUNTIFS(流水账户,$B20,流水日期,"<"&$E20)>0),"※有流水的日期早于启用日期，期初余额会重复计算","")))) | H20: 业务招待费 | I20: 支出
A21: =IF($B21="","",COUNTA($B$5:$B21)) | F21: =IF($B21="","",IF(COUNTIF($B$5:$B$34,$B21)>1,"※账户名称重复了，后面按名字取数会串",IF($D21="","※期初余额没填（没有就填 0）",IF(AND($E21<>"",COUNTIFS(流水账户,$B21,流水日期,"<"&$E21)>0),"※有流水的日期早于启用日期，期初余额会重复计算","")))) | H21: 车辆费用 | I21: 支出
A22: =IF($B22="","",COUNTA($B$5:$B22)) | F22: =IF($B22="","",IF(COUNTIF($B$5:$B$34,$B22)>1,"※账户名称重复了，后面按名字取数会串",IF($D22="","※期初余额没填（没有就填 0）",IF(AND($E22<>"",COUNTIFS(流水账户,$B22,流水日期,"<"&$E22)>0),"※有流水的日期早于启用日期，期初余额会重复计算","")))) | H22: 银行手续费 | I22: 支出
A23: =IF($B23="","",COUNTA($B$5:$B23)) | F23: =IF($B23="","",IF(COUNTIF($B$5:$B$34,$B23)>1,"※账户名称重复了，后面按名字取数会串",IF($D23="","※期初余额没填（没有就填 0）",IF(AND($E23<>"",COUNTIFS(流水账户,$B23,流水日期,"<"&$E23)>0),"※有流水的日期早于启用日期，期初余额会重复计算","")))) | H23: 税费 | I23: 支出
A24: =IF($B24="","",COUNTA($B$5:$B24)) | F24: =IF($B24="","",IF(COUNTIF($B$5:$B$34,$B24)>1,"※账户名称重复了，后面按名字取数会串",IF($D24="","※期初余额没填（没有就填 0）",IF(AND($E24<>"",COUNTIFS(流水账户,$B24,流水日期,"<"&$E24)>0),"※有流水的日期早于启用日期，期初余额会重复计算","")))) | H24: 还款 | I24: 支出
A25: =IF($B25="","",COUNTA($B$5:$B25)) | F25: =IF($B25="","",IF(COUNTIF($B$5:$B$34,$B25)>1,"※账户名称重复了，后面按名字取数会串",IF($D25="","※期初余额没填（没有就填 0）",IF(AND($E25<>"",COUNTIFS(流水账户,$B25,流水日期,"<"&$E25)>0),"※有流水的日期早于启用日期，期初余额会重复计算","")))) | H25: 资产购买 | I25: 支出
A26: =IF($B26="","",COUNTA($B$5:$B26)) | F26: =IF($B26="","",IF(COUNTIF($B$5:$B$34,$B26)>1,"※账户名称重复了，后面按名字取数会串",IF($D26="","※期初余额没填（没有就填 0）",IF(AND($E26<>"",COUNTIFS(流水账户,$B26,流水日期,"<"&$E26)>0),"※有流水的日期早于启用日期，期初余额会重复计算","")))) | H26: 利息支出 | I26: 支出
A27: =IF($B27="","",COUNTA($B$5:$B27)) | F27: =IF($B27="","",IF(COUNTIF($B$5:$B$34,$B27)>1,"※账户名称重复了，后面按名字取数会串",IF($D27="","※期初余额没填（没有就填 0）",IF(AND($E27<>"",COUNTIFS(流水账户,$B27,流水日期,"<"&$E27)>0),"※有流水的日期早于启用日期，期初余额会重复计算","")))) | H27: 内部转账 | I27: 内部转账
A28: =IF($B28="","",COUNTA($B$5:$B28)) | F28: =IF($B28="","",IF(COUNTIF($B$5:$B$34,$B28)>1,"※账户名称重复了，后面按名字取数会串",IF($D28="","※期初余额没填（没有就填 0）",IF(AND($E28<>"",COUNTIFS(流水账户,$B28,流水日期,"<"&$E28)>0),"※有流水的日期早于启用日期，期初余额会重复计算","")))) | H28: 备用金调拨 | I28: 内部转账
A29: =IF($B29="","",COUNTA($B$5:$B29)) | F29: =IF($B29="","",IF(COUNTIF($B$5:$B$34,$B29)>1,"※账户名称重复了，后面按名字取数会串",IF($D29="","※期初余额没填（没有就填 0）",IF(AND($E29<>"",COUNTIFS(流水账户,$B29,流水日期,"<"&$E29)>0),"※有流水的日期早于启用日期，期初余额会重复计算",""))))
A30: =IF($B30="","",COUNTA($B$5:$B30)) | F30: =IF($B30="","",IF(COUNTIF($B$5:$B$34,$B30)>1,"※账户名称重复了，后面按名字取数会串",IF($D30="","※期初余额没填（没有就填 0）",IF(AND($E30<>"",COUNTIFS(流水账户,$B30,流水日期,"<"&$E30)>0),"※有流水的日期早于启用日期，期初余额会重复计算",""))))
A31: =IF($B31="","",COUNTA($B$5:$B31)) | F31: =IF($B31="","",IF(COUNTIF($B$5:$B$34,$B31)>1,"※账户名称重复了，后面按名字取数会串",IF($D31="","※期初余额没填（没有就填 0）",IF(AND($E31<>"",COUNTIFS(流水账户,$B31,流水日期,"<"&$E31)>0),"※有流水的日期早于启用日期，期初余额会重复计算",""))))
A32: =IF($B32="","",COUNTA($B$5:$B32)) | F32: =IF($B32="","",IF(COUNTIF($B$5:$B$34,$B32)>1,"※账户名称重复了，后面按名字取数会串",IF($D32="","※期初余额没填（没有就填 0）",IF(AND($E32<>"",COUNTIFS(流水账户,$B32,流水日期,"<"&$E32)>0),"※有流水的日期早于启用日期，期初余额会重复计算",""))))
A33: =IF($B33="","",COUNTA($B$5:$B33)) | F33: =IF($B33="","",IF(COUNTIF($B$5:$B$34,$B33)>1,"※账户名称重复了，后面按名字取数会串",IF($D33="","※期初余额没填（没有就填 0）",IF(AND($E33<>"",COUNTIFS(流水账户,$B33,流水日期,"<"&$E33)>0),"※有流水的日期早于启用日期，期初余额会重复计算",""))))
A34: =IF($B34="","",COUNTA($B$5:$B34)) | F34: =IF($B34="","",IF(COUNTIF($B$5:$B$34,$B34)>1,"※账户名称重复了，后面按名字取数会串",IF($D34="","※期初余额没填（没有就填 0）",IF(AND($E34<>"",COUNTIFS(流水账户,$B34,流水日期,"<"&$E34)>0),"※有流水的日期早于启用日期，期初余额会重复计算",""))))

Sheet 数据录入
A1: 数据录入 · 全套表只有这一张要填
A2: 选账户 → 余额自动结；收入和支出分两列，只填一个。账户之间互转：转出账户记一笔支出、转入账户记一笔收入，类别都选「内部转账」，在「对方账户」写上另一头 —— 这样它就不会被算进收入和支出合计。期初余额挪到【基础资料】了，这里只放真实流水。最后一列「核对」会自己挑毛病。
A3: 收入总额 | B3: =ROUND(SUMIFS(流水收入,流水属性,"<>内部转账"),2) -> 16800 | C3: 支出总额 | D3: =ROUND(SUMIFS(流水支出,流水属性,"<>内部转账"),2) -> 22190 | E3: 经营净额 | F3: =ROUND($B$3-$D$3,2) -> -5390 | G3: 内部转账净额 | H3: =ROUND(SUMIFS(流水收入,流水属性,"内部转账")-SUMIFS(流水支出,流水属性,"内部转账"),2) -> 0 | I3: 资金总额 | J3: =ROUND(SUM(账户期初)+SUM(流水收入)-SUM(流水支出),2) -> 155610 | K3: 已用行数 | L3: =COUNTA($C$5:$C$5004)&" / 5000" -> 25 / 5000 | M3: 收入总额、支出总额都不含内部转账；内部转账净额应该是 0，不为 0 就是有一头没录
A4: 序号 | B4: 日期 ★ | C4: 公司账户 ★ | D4: 收/支类别 ★ | E4: 摘要内容 | F4: 收入 | G4: 支出 | H4: 账户余额 | I4: 客户 | J4: 供应商 | K4: 月份 | L4: 类别属性 | M4: 对方账户 (内部转账填) | N4: 项目/部门 | O4: 备注 | P4: 核对
A5: =IF($C5="","",COUNTA($C$5:$C5)) -> 1 | B5: 46175 | C5: 现金 | D5: 销售回款 | F5: 2000 | H5: =IFERROR(ROUND(VLOOKUP($C5,基础资料!$B$5:$E$34,3,0)+SUMIF($C$5:$C5,$C5,$F$5:$F5)-SUMIF($C$5:$C5,$C5,$G$5:$G5),2),"") -> 7000 | I5: 客户1 | K5: =IF(OR($B5="",NOT(ISNUMBER($B5))),"",--TEXT($B5,"yyyymm")) -> 202606 | L5: =IF($D5="","",IFERROR(INDEX(类别属性,MATCH($D5,类别表,0)),"")) -> 收入 | N5: 主营业务 | P5: =IF($C5="","",IF(ISNA(MATCH($C5,账户表,0)),"※这个账户不在【基础资料】的账户档案里",IF($B5="","※没填日期，这一笔不会进任何月份的报表",IF(NOT(ISNUMBER($B5)),"※日期是文本不是日期（像 2026.6.28 这种），按日期取数的报表全会漏掉这一笔",IF(AND($F5<>"",$G5<>""),"※收入和支出不能同时填",IF(AND(N($F5)=0,N($G5)=0),"※收入和支出都没填",IF(OR(N($F5)<0,N($G5)<0),"※金额不能填负数，方向反了就换一列填",IF($D5="","※没填收支类别，分类报表会漏掉这一笔",IF(ISNA(MATCH($D5,类别表,0)),"※收支类别不在【基础资料】的清单里",IF(AND($L5="内部转账",$M5=""),"△内部转账要在「对方账户」写上另一头",IF(AND($L5="内部转账",$M5=$C5),"※对方账户跟本账户是同一个",IF(AND($L5<>"内部转账",$M5<>""),"△填了对方账户，但类别不是内部转账",IF(YEAR($B5)<>管理年度,"△不是管理年度的单据，按月的三张报表里看不到",IF($H5<0,"△这一笔之后该账户余额成负数了，核一下",""))))))))))))))
A6: =IF($C6="","",COUNTA($C$5:$C6)) -> 2 | B6: 46176 | C6: 微信 | D6: 办公费 | G6: 200 | H6: =IFERROR(ROUND(VLOOKUP($C6,基础资料!$B$5:$E$34,3,0)+SUMIF($C$5:$C6,$C6,$F$5:$F6)-SUMIF($C$5:$C6,$C6,$G$5:$G6),2),"") -> 5800 | K6: =IF(OR($B6="",NOT(ISNUMBER($B6))),"",--TEXT($B6,"yyyymm")) -> 202606 | L6: =IF($D6="","",IFERROR(INDEX(类别属性,MATCH($D6,类别表,0)),"")) -> 支出 | N6: 行政 | P6: =IF($C6="","",IF(ISNA(MATCH($C6,账户表,0)),"※这个账户不在【基础资料】的账户档案里",IF($B6="","※没填日期，这一笔不会进任何月份的报表",IF(NOT(ISNUMBER($B6)),"※日期是文本不是日期（像 2026.6.28 这种），按日期取数的报表全会漏掉这一笔",IF(AND($F6<>"",$G6<>""),"※收入和支出不能同时填",IF(AND(N($F6)=0,N($G6)=0),"※收入和支出都没填",IF(OR(N($F6)<0,N($G6)<0),"※金额不能填负数，方向反了就换一列填",IF($D6="","※没填收支类别，分类报表会漏掉这一笔",IF(ISNA(MATCH($D6,类别表,0)),"※收支类别不在【基础资料】的清单里",IF(AND($L6="内部转账",$M6=""),"△内部转账要在「对方账户」写上另一头",IF(AND($L6="内部转账",$M6=$C6),"※对方账户跟本账户是同一个",IF(AND($L6<>"内部转账",$M6<>""),"△填了对方账户，但类别不是内部转账",IF(YEAR($B6)<>管理年度,"△不是管理年度的单据，按月的三张报表里看不到",IF($H6<0,"△这一笔之后该账户余额成负数了，核一下",""))))))))))))))
A7: =IF($C7="","",COUNTA($C$5:$C7)) -> 3 | B7: 46178 | C7: 工行 | D7: 电费 | G7: 300 | H7: =IFERROR(ROUND(VLOOKUP($C7,基础资料!$B$5:$E$34,3,0)+SUMIF($C$5:$C7,$C7,$F$5:$F7)-SUMIF($C$5:$C7,$C7,$G$5:$G7),2),"") -> 6700 | K7: =IF(OR($B7="",NOT(ISNUMBER($B7))),"",--TEXT($B7,"yyyymm")) -> 202606 | L7: =IF($D7="","",IFERROR(INDEX(类别属性,MATCH($D7,类别表,0)),"")) -> 支出 | N7: 行政 | P7: =IF($C7="","",IF(ISNA(MATCH($C7,账户表,0)),"※这个账户不在【基础资料】的账户档案里",IF($B7="","※没填日期，这一笔不会进任何月份的报表",IF(NOT(ISNUMBER($B7)),"※日期是文本不是日期（像 2026.6.28 这种），按日期取数的报表全会漏掉这一笔",IF(AND($F7<>"",$G7<>""),"※收入和支出不能同时填",IF(AND(N($F7)=0,N($G7)=0),"※收入和支出都没填",IF(OR(N($F7)<0,N($G7)<0),"※金额不能填负数，方向反了就换一列填",IF($D7="","※没填收支类别，分类报表会漏掉这一笔",IF(ISNA(MATCH($D7,类别表,0)),"※收支类别不在【基础资料】的清单里",IF(AND($L7="内部转账",$M7=""),"△内部转账要在「对方账户」写上另一头",IF(AND($L7="内部转账",$M7=$C7),"※对方账户跟本账户是同一个",IF(AND($L7<>"内部转账",$M7<>""),"△填了对方账户，但类别不是内部转账",IF(YEAR($B7)<>管理年度,"△不是管理年度的单据，按月的三张报表里看不到",IF($H7<0,"△这一笔之后该账户余额成负数了，核一下",""))))))))))))))
A8: =IF($C8="","",COUNTA($C$5:$C8)) -> 4 | B8: 46179 | C8: 民生 | D8: 差旅费 | G8: 500 | H8: =IFERROR(ROUND(VLOOKUP($C8,基础资料!$B$5:$E$34,3,0)+SUMIF($C$5:$C8,$C8,$F$5:$F8)-SUMIF($C$5:$C8,$C8,$G$5:$G8),2),"") -> 7500 | K8: =IF(OR($B8="",NOT(ISNUMBER($B8))),"",--TEXT($B8,"yyyymm")) -> 202606 | L8: =IF($D8="","",IFERROR(INDEX(类别属性,MATCH($D8,类别表,0)),"")) -> 支出 | N8: 行政 | P8: =IF($C8="","",IF(ISNA(MATCH($C8,账户表,0)),"※这个账户不在【基础资料】的账户档案里",IF($B8="","※没填日期，这一笔不会进任何月份的报表",IF(NOT(ISNUMBER($B8)),"※日期是文本不是日期（像 2026.6.28 这种），按日期取数的报表全会漏掉这一笔",IF(AND($F8<>"",$G8<>""),"※收入和支出不能同时填",IF(AND(N($F8)=0,N($G8)=0),"※收入和支出都没填",IF(OR(N($F8)<0,N($G8)<0),"※金额不能填负数，方向反了就换一列填",IF($D8="","※没填收支类别，分类报表会漏掉这一笔",IF(ISNA(MATCH($D8,类别表,0)),"※收支类别不在【基础资料】的清单里",IF(AND($L8="内部转账",$M8=""),"△内部转账要在「对方账户」写上另一头",IF(AND($L8="内部转账",$M8=$C8),"※对方账户跟本账户是同一个",IF(AND($L8<>"内部转账",$M8<>""),"△填了对方账户，但类别不是内部转账",IF(YEAR($B8)<>管理年度,"△不是管理年度的单据，按月的三张报表里看不到",IF($H8<0,"△这一笔之后该账户余额成负数了，核一下",""))))))))))))))
A9: =IF($C9="","",COUNTA($C$5:$C9)) -> 5 | B9: 46183 | C9: 建行 | D9: 销售回款 | F9: 2600 | H9: =IFERROR(ROUND(VLOOKUP($C9,基础资料!$B$5:$E$34,3,0)+SUMIF($C$5:$C9,$C9,$F$5:$F9)-SUMIF($C$5:$C9,$C9,$G$5:$G9),2),"") -> 11600 | I9: 客户2 | K9: =IF(OR($B9="",NOT(ISNUMBER($B9))),"",--TEXT($B9,"yyyymm")) -> 202606 | L9: =IF($D9="","",IFERROR(INDEX(类别属性,MATCH($D9,类别表,0)),"")) -> 收入 | N9: 主营业务 | P9: =IF($C9="","",IF(ISNA(MATCH($C9,账户表,0)),"※这个账户不在【基础资料】的账户档案里",IF($B9="","※没填日期，这一笔不会进任何月份的报表",IF(NOT(ISNUMBER($B9)),"※日期是文本不是日期（像 2026.6.28 这种），按日期取数的报表全会漏掉这一笔",IF(AND($F9<>"",$G9<>""),"※收入和支出不能同时填",IF(AND(N($F9)=0,N($G9)=0),"※收入和支出都没填",IF(OR(N($F9)<0,N($G9)<0),"※金额不能填负数，方向反了就换一列填",IF($D9="","※没填收支类别，分类报表会漏掉这一笔",IF(ISNA(MATCH($D9,类别表,0)),"※收支类别不在【基础资料】的清单里",IF(AND($L9="内部转账",$M9=""),"△内部转账要在「对方账户」写上另一头",IF(AND($L9="内部转账",$M9=$C9),"※对方账户跟本账户是同一个",IF(AND($L9<>"内部转账",$M9<>""),"△填了对方账户，但类别不是内部转账",IF(YEAR($B9)<>管理年度,"△不是管理年度的单据，按月的三张报表里看不到",IF($H9<0,"△这一笔之后该账户余额成负数了，核一下",""))))))))))))))
A10: =IF($C10="","",COUNTA($C$5:$C10)) -> 6 | B10: 46185 | C10: 农行 | D10: 供应商 | G10: 5000 | H10: =IFERROR(ROUND(VLOOKUP($C10,基础资料!$B$5:$E$34,3,0)+SUMIF($C$5:$C10,$C10,$F$5:$F10)-SUMIF($C$5:$C10,$C10,$G$5:$G10),2),"") -> 5000 | J10: 供应商1 | K10: =IF(OR($B10="",NOT(ISNUMBER($B10))),"",--TEXT($B10,"yyyymm")) -> 202606 | L10: =IF($D10="","",IFERROR(INDEX(类别属性,MATCH($D10,类别表,0)),"")) -> 支出 | N10: 主营业务 | P10: =IF($C10="","",IF(ISNA(MATCH($C10,账户表,0)),"※这个账户不在【基础资料】的账户档案里",IF($B10="","※没填日期，这一笔不会进任何月份的报表",IF(NOT(ISNUMBER($B10)),"※日期是文本不是日期（像 2026.6.28 这种），按日期取数的报表全会漏掉这一笔",IF(AND($F10<>"",$G10<>""),"※收入和支出不能同时填",IF(AND(N($F10)=0,N($G10)=0),"※收入和支出都没填",IF(OR(N($F10)<0,N($G10)<0),"※金额不能填负数，方向反了就换一列填",IF($D10="","※没填收支类别，分类报表会漏掉这一笔",IF(ISNA(MATCH($D10,类别表,0)),"※收支类别不在【基础资料】的清单里",IF(AND($L10="内部转账",$M10=""),"△内部转账要在「对方账户」写上另一头",IF(AND($L10="内部转账",$M10=$C10),"※对方账户跟本账户是同一个",IF(AND($L10<>"内部转账",$M10<>""),"△填了对方账户，但类别不是内部转账",IF(YEAR($B10)<>管理年度,"△不是管理年度的单据，按月的三张报表里看不到",IF($H10<0,"△这一笔之后该账户余额成负数了，核一下",""))))))))))))))
A11: =IF($C11="","",COUNTA($C$5:$C11)) -> 7 | B11: 46193 | C11: 中行 | D11: 伙食费 | G11: 200 | H11: =IFERROR(ROUND(VLOOKUP($C11,基础资料!$B$5:$E$34,3,0)+SUMIF($C$5:$C11,$C11,$F$5:$F11)-SUMIF($C$5:$C11,$C11,$G$5:$G11),2),"") -> 10800 | K11: =IF(OR($B11="",NOT(ISNUMBER($B11))),"",--TEXT($B11,"yyyymm")) -> 202606 | L11: =IF($D11="","",IFERROR(INDEX(类别属性,MATCH($D11,类别表,0)),"")) -> 支出 | N11: 行政 | P11: =IF($C11="","",IF(ISNA(MATCH($C11,账户表,0)),"※这个账户不在【基础资料】的账户档案里",IF($B11="","※没填日期，这一笔不会进任何月份的报表",IF(NOT(ISNUMBER($B11)),"※日期是文本不是日期（像 2026.6.28 这种），按日期取数的报表全会漏掉这一笔",IF(AND($F11<>"",$G11<>""),"※收入和支出不能同时填",IF(AND(N($F11)=0,N($G11)=0),"※收入和支出都没填",IF(OR(N($F11)<0,N($G11)<0),"※金额不能填负数，方向反了就换一列填",IF($D11="","※没填收支类别，分类报表会漏掉这一笔",IF(ISNA(MATCH($D11,类别表,0)),"※收支类别不在【基础资料】的清单里",IF(AND($L11="内部转账",$M11=""),"△内部转账要在「对方账户」写上另一头",IF(AND($L11="内部转账",$M11=$C11),"※对方账户跟本账户是同一个",IF(AND($L11<>"内部转账",$M11<>""),"△填了对方账户，但类别不是内部转账",IF(YEAR($B11)<>管理年度,"△不是管理年度的单据，按月的三张报表里看不到",IF($H11<0,"△这一笔之后该账户余额成负数了，核一下",""))))))))))))))
A12: =IF($C12="","",COUNTA($C$5:$C12)) -> 8 | B12: 46196 | C12: 支付宝 | D12: 办公费 | G12: 10 | H12: =IFERROR(ROUND(VLOOKUP($C12,基础资料!$B$5:$E$34,3,0)+SUMIF($C$5:$C12,$C12,$F$5:$F12)-SUMIF($C$5:$C12,$C12,$G$5:$G12),2),"") -> 11990 | K12: =IF(OR($B12="",NOT(ISNUMBER($B12))),"",--TEXT($B12,"yyyymm")) -> 202606 | L12: =IF($D12="","",IFERROR(INDEX(类别属性,MATCH($D12,类别表,0)),"")) -> 支出 | N12: 行政 | P12: =IF($C12="","",IF(ISNA(MATCH($C12,账户表,0)),"※这个账户不在【基础资料】的账户档案里",IF($B12="","※没填日期，这一笔不会进任何月份的报表",IF(NOT(ISNUMBER($B12)),"※日期是文本不是日期（像 2026.6.28 这种），按日期取数的报表全会漏掉这一笔",IF(AND($F12<>"",$G12<>""),"※收入和支出不能同时填",IF(AND(N($F12)=0,N($G12)=0),"※收入和支出都没填",IF(OR(N($F12)<0,N($G12)<0),"※金额不能填负数，方向反了就换一列填",IF($D12="","※没填收支类别，分类报表会漏掉这一笔",IF(ISNA(MATCH($D12,类别表,0)),"※收支类别不在【基础资料】的清单里",IF(AND($L12="内部转账",$M12=""),"△内部转账要在「对方账户」写上另一头",IF(AND($L12="内部转账",$M12=$C12),"※对方账户跟本账户是同一个",IF(AND($L12<>"内部转账",$M12<>""),"△填了对方账户，但类别不是内部转账",IF(YEAR($B12)<>管理年度,"△不是管理年度的单据，按月的三张报表里看不到",IF($H12<0,"△这一笔之后该账户余额成负数了，核一下",""))))))))))))))
A13: =IF($C13="","",COUNTA($C$5:$C13)) -> 9 | B13: 46197 | C13: 农商行 | D13: 车辆费用 | G13: 50 | H13: =IFERROR(ROUND(VLOOKUP($C13,基础资料!$B$5:$E$34,3,0)+SUMIF($C$5:$C13,$C13,$F$5:$F13)-SUMIF($C$5:$C13,$C13,$G$5:$G13),2),"") -> 12950 | K13: =IF(OR($B13="",NOT(ISNUMBER($B13))),"",--TEXT($B13,"yyyymm")) -> 202606 | L13: =IF($D13="","",IFERROR(INDEX(类别属性,MATCH($D13,类别表,0)),"")) -> 支出 | N13: 行政 | P13: =IF($C13="","",IF(ISNA(MATCH($C13,账户表,0)),"※这个账户不在【基础资料】的账户档案里",IF($B13="","※没填日期，这一笔不会进任何月份的报表",IF(NOT(ISNUMBER($B13)),"※日期是文本不是日期（像 2026.6.28 这种），按日期取数的报表全会漏掉这一笔",IF(AND($F13<>"",$G13<>""),"※收入和支出不能同时填",IF(AND(N($F13)=0,N($G13)=0),"※收入和支出都没填",IF(OR(N($F13)<0,N($G13)<0),"※金额不能填负数，方向反了就换一列填",IF($D13="","※没填收支类别，分类报表会漏掉这一笔",IF(ISNA(MATCH($D13,类别表,0)),"※收支类别不在【基础资料】的清单里",IF(AND($L13="内部转账",$M13=""),"△内部转账要在「对方账户」写上另一头",IF(AND($L13="内部转账",$M13=$C13),"※对方账户跟本账户是同一个",IF(AND($L13<>"内部转账",$M13<>""),"△填了对方账户，但类别不是内部转账",IF(YEAR($B13)<>管理年度,"△不是管理年度的单据，按月的三张报表里看不到",IF($H13<0,"△这一笔之后该账户余额成负数了，核一下",""))))))))))))))
A14: =IF($C14="","",COUNTA($C$5:$C14)) -> 10 | B14: 46198 | C14: 备用 | D14: 销售回款 | F14: 2100 | H14: =IFERROR(ROUND(VLOOKUP($C14,基础资料!$B$5:$E$34,3,0)+SUMIF($C$5:$C14,$C14,$F$5:$F14)-SUMIF($C$5:$C14,$C14,$G$5:$G14),2),"") -> 16100 | I14: 客户3 | K14: =IF(OR($B14="",NOT(ISNUMBER($B14))),"",--TEXT($B14,"yyyymm")) -> 202606 | L14: =IF($D14="","",IFERROR(INDEX(类别属性,MATCH($D14,类别表,0)),"")) -> 收入 | N14: 主营业务 | P14: =IF($C14="","",IF(ISNA(MATCH($C14,账户表,0)),"※这个账户不在【基础资料】的账户档案里",IF($B14="","※没填日期，这一笔不会进任何月份的报表",IF(NOT(ISNUMBER($B14)),"※日期是文本不是日期（像 2026.6.28 这种），按日期取数的报表全会漏掉这一笔",IF(AND($F14<>"",$G14<>""),"※收入和支出不能同时填",IF(AND(N($F14)=0,N($G14)=0),"※收入和支出都没填",IF(OR(N($F14)<0,N($G14)<0),"※金额不能填负数，方向反了就换一列填",IF($D14="","※没填收支类别，分类报表会漏掉这一笔",IF(ISNA(MATCH($D14,类别表,0)),"※收支类别不在【基础资料】的清单里",IF(AND($L14="内部转账",$M14=""),"△内部转账要在「对方账户」写上另一头",IF(AND($L14="内部转账",$M14=$C14),"※对方账户跟本账户是同一个",IF(AND($L14<>"内部转账",$M14<>""),"△填了对方账户，但类别不是内部转账",IF(YEAR($B14)<>管理年度,"△不是管理年度的单据，按月的三张报表里看不到",IF($H14<0,"△这一笔之后该账户余额成负数了，核一下",""))))))))))))))
A15: =IF($C15="","",COUNTA($C$5:$C15)) -> 11 | B15: 46198 | C15: 备用1 | D15: 租赁费 | G15: 2000 | H15: =IFERROR(ROUND(VLOOKUP($C15,基础资料!$B$5:$E$34,3,0)+SUMIF($C$5:$C15,$C15,$F$5:$F15)-SUMIF($C$5:$C15,$C15,$G$5:$G15),2),"") -> 13000 | K15: =IF(OR($B15="",NOT(ISNUMBER($B15))),"",--TEXT($B15,"yyyymm")) -> 202606 | L15: =IF($D15="","",IFERROR(INDEX(类别属性,MATCH($D15,类别表,0)),"")) -> 支出 | N15: 行政 | P15: =IF($C15="","",IF(ISNA(MATCH($C15,账户表,0)),"※这个账户不在【基础资料】的账户档案里",IF($B15="","※没填日期，这一笔不会进任何月份的报表",IF(NOT(ISNUMBER($B15)),"※日期是文本不是日期（像 2026.6.28 这种），按日期取数的报表全会漏掉这一笔",IF(AND($F15<>"",$G15<>""),"※收入和支出不能同时填",IF(AND(N($F15)=0,N($G15)=0),"※收入和支出都没填",IF(OR(N($F15)<0,N($G15)<0),"※金额不能填负数，方向反了就换一列填",IF($D15="","※没填收支类别，分类报表会漏掉这一笔",IF(ISNA(MATCH($D15,类别表,0)),"※收支类别不在【基础资料】的清单里",IF(AND($L15="内部转账",$M15=""),"△内部转账要在「对方账户」写上另一头",IF(AND($L15="内部转账",$M15=$C15),"※对方账户跟本账户是同一个",IF(AND($L15<>"内部转账",$M15<>""),"△填了对方账户，但类别不是内部转账",IF(YEAR($B15)<>管理年度,"△不是管理年度的单据，按月的三张报表里看不到",IF($H15<0,"△这一笔之后该账户余额成负数了，核一下",""))))))))))))))
A16: =IF($C16="","",COUNTA($C$5:$C16)) -> 12 | B16: 46198 | C16: 现金 | D16: 业务招待费 | G16: 200 | H16: =IFERROR(ROUND(VLOOKUP($C16,基础资料!$B$5:$E$34,3,0)+SUMIF($C$5:$C16,$C16,$F$5:$F16)-SUMIF($C$5:$C16,$C16,$G$5:$G16),2),"") -> 6800 | K16: =IF(OR($B16="",NOT(ISNUMBER($B16))),"",--TEXT($B16,"yyyymm")) -> 202606 | L16: =IF($D16="","",IFERROR(INDEX(类别属性,MATCH($D16,类别表,0)),"")) -> 支出 | N16: 行政 | P16: =IF($C16="","",IF(ISNA(MATCH($C16,账户表,0)),"※这个账户不在【基础资料】的账户档案里",IF($B16="","※没填日期，这一笔不会进任何月份的报表",IF(NOT(ISNUMBER($B16)),"※日期是文本不是日期（像 2026.6.28 这种），按日期取数的报表全会漏掉这一笔",IF(AND($F16<>"",$G16<>""),"※收入和支出不能同时填",IF(AND(N($F16)=0,N($G16)=0),"※收入和支出都没填",IF(OR(N($F16)<0,N($G16)<0),"※金额不能填负数，方向反了就换一列填",IF($D16="","※没填收支类别，分类报表会漏掉这一笔",IF(ISNA(MATCH($D16,类别表,0)),"※收支类别不在【基础资料】的清单里",IF(AND($L16="内部转账",$M16=""),"△内部转账要在「对方账户」写上另一头",IF(AND($L16="内部转账",$M16=$C16),"※对方账户跟本账户是同一个",IF(AND($L16<>"内部转账",$M16<>""),"△填了对方账户，但类别不是内部转账",IF(YEAR($B16)<>管理年度,"△不是管理年度的单据，按月的三张报表里看不到",IF($H16<0,"△这一笔之后该账户余额成负数了，核一下",""))))))))))))))
A17: =IF($C17="","",COUNTA($C$5:$C17)) -> 13 | B17: 46199 | C17: 备用2 | D17: 销售回款 | F17: 3000 | H17: =IFERROR(ROUND(VLOOKUP($C17,基础资料!$B$5:$E$34,3,0)+SUMIF($C$5:$C17,$C17,$F$5:$F17)-SUMIF($C$5:$C17,$C17,$G$5:$G17),2),"") -> 19000 | I17: 客户4 | K17: =IF(OR($B17="",NOT(ISNUMBER($B17))),"",--TEXT($B17,"yyyymm")) -> 202606 | L17: =IF($D17="","",IFERROR(INDEX(类别属性,MATCH($D17,类别表,0)),"")) -> 收入 | N17: 主营业务 | P17: =IF($C17="","",IF(ISNA(MATCH($C17,账户表,0)),"※这个账户不在【基础资料】的账户档案里",IF($B17="","※没填日期，这一笔不会进任何月份的报表",IF(NOT(ISNUMBER($B17)),"※日期是文本不是日期（像 2026.6.28 这种），按日期取数的报表全会漏掉这一笔",IF(AND($F17<>"",$G17<>""),"※收入和支出不能同时填",IF(AND(N($F17)=0,N($G17)=0),"※收入和支出都没填",IF(OR(N($F17)<0,N($G17)<0),"※金额不能填负数，方向反了就换一列填",IF($D17="","※没填收支类别，分类报表会漏掉这一笔",IF(ISNA(MATCH($D17,类别表,0)),"※收支类别不在【基础资料】的清单里",IF(AND($L17="内部转账",$M17=""),"△内部转账要在「对方账户」写上另一头",IF(AND($L17="内部转账",$M17=$C17),"※对方账户跟本账户是同一个",IF(AND($L17<>"内部转账",$M17<>""),"△填了对方账户，但类别不是内部转账",IF(YEAR($B17)<>管理年度,"△不是管理年度的单据，按月的三张报表里看不到",IF($H17<0,"△这一笔之后该账户余额成负数了，核一下",""))))))))))))))
A18: =IF($C18="","",COUNTA($C$5:$C18)) -> 14 | B18: 46199 | C18: 备用3 | D18: 工资 | G18: 8000 | H18: =IFERROR(ROUND(VLOOKUP($C18,基础资料!$B$5:$E$34,3,0)+SUMIF($C$5:$C18,$C18,$F$5:$F18)-SUMIF($C$5:$C18,$C18,$G$5:$G18),2),"") -> 9000 | K18: =IF(OR($B18="",NOT(ISNUMBER($B18))),"",--TEXT($B18,"yyyymm")) -> 202606 | L18: =IF($D18="","",IFERROR(INDEX(类别属性,MATCH($D18,类别表,0)),"")) -> 支出 | N18: 行政 | P18: =IF($C18="","",IF(ISNA(MATCH($C18,账户表,0)),"※这个账户不在【基础资料】的账户档案里",IF($B18="","※没填日期，这一笔不会进任何月份的报表",IF(NOT(ISNUMBER($B18)),"※日期是文本不是日期（像 2026.6.28 这种），按日期取数的报表全会漏掉这一笔",IF(AND($F18<>"",$G18<>""),"※收入和支出不能同时填",IF(AND(N($F18)=0,N($G18)=0),"※收入和支出都没填",IF(OR(N($F18)<0,N($G18)<0),"※金额不能填负数，方向反了就换一列填",IF($D18="","※没填收支类别，分类报表会漏掉这一笔",IF(ISNA(MATCH($D18,类别表,0)),"※收支类别不在【基础资料】的清单里",IF(AND($L18="内部转账",$M18=""),"△内部转账要在「对方账户」写上另一头",IF(AND($L18="内部转账",$M18=$C18),"※对方账户跟本账户是同一个",IF(AND($L18<>"内部转账",$M18<>""),"△填了对方账户，但类别不是内部转账",IF(YEAR($B18)<>管理年度,"△不是管理年度的单据，按月的三张报表里看不到",IF($H18<0,"△这一笔之后该账户余额成负数了，核一下",""))))))))))))))
A19: =IF($C19="","",COUNTA($C$5:$C19)) -> 15 | B19: 46200 | C19: 备用4 | D19: 销售回款 | F19: 1500 | H19: =IFERROR(ROUND(VLOOKUP($C19,基础资料!$B$5:$E$34,3,0)+SUMIF($C$5:$C19,$C19,$F$5:$F19)-SUMIF($C$5:$C19,$C19,$G$5:$G19),2),"") -> 19500 | I19: 客户5 | K19: =IF(OR($B19="",NOT(ISNUMBER($B19))),"",--TEXT($B19,"yyyymm")) -> 202606 | L19: =IF($D19="","",IFERROR(INDEX(类别属性,MATCH($D19,类别表,0)),"")) -> 收入 | N19: 主营业务 | P19: =IF($C19="","",IF(ISNA(MATCH($C19,账户表,0)),"※这个账户不在【基础资料】的账户档案里",IF($B19="","※没填日期，这一笔不会进任何月份的报表",IF(NOT(ISNUMBER($B19)),"※日期是文本不是日期（像 2026.6.28 这种），按日期取数的报表全会漏掉这一笔",IF(AND($F19<>"",$G19<>""),"※收入和支出不能同时填",IF(AND(N($F19)=0,N($G19)=0),"※收入和支出都没填",IF(OR(N($F19)<0,N($G19)<0),"※金额不能填负数，方向反了就换一列填",IF($D19="","※没填收支类别，分类报表会漏掉这一笔",IF(ISNA(MATCH($D19,类别表,0)),"※收支类别不在【基础资料】的清单里",IF(AND($L19="内部转账",$M19=""),"△内部转账要在「对方账户」写上另一头",IF(AND($L19="内部转账",$M19=$C19),"※对方账户跟本账户是同一个",IF(AND($L19<>"内部转账",$M19<>""),"△填了对方账户，但类别不是内部转账",IF(YEAR($B19)<>管理年度,"△不是管理年度的单据，按月的三张报表里看不到",IF($H19<0,"△这一笔之后该账户余额成负数了，核一下",""))))))))))))))
A20: =IF($C20="","",COUNTA($C$5:$C20)) -> 16 | B20: 46201 | C20: 工行 | D20: 供应商 | G20: 3000 | H20: =IFERROR(ROUND(VLOOKUP($C20,基础资料!$B$5:$E$34,3,0)+SUMIF($C$5:$C20,$C20,$F$5:$F20)-SUMIF($C$5:$C20,$C20,$G$5:$G20),2),"") -> 3700 | J20: 供应商2 | K20: =IF(OR($B20="",NOT(ISNUMBER($B20))),"",--TEXT($B20,"yyyymm")) -> 202606 | L20: =IF($D20="","",IFERROR(INDEX(类别属性,MATCH($D20,类别表,0)),"")) -> 支出 | N20: 主营业务 | P20: =IF($C20="","",IF(ISNA(MATCH($C20,账户表,0)),"※这个账户不在【基础资料】的账户档案里",IF($B20="","※没填日期，这一笔不会进任何月份的报表",IF(NOT(ISNUMBER($B20)),"※日期是文本不是日期（像 2026.6.28 这种），按日期取数的报表全会漏掉这一笔",IF(AND($F20<>"",$G20<>""),"※收入和支出不能同时填",IF(AND(N($F20)=0,N($G20)=0),"※收入和支出都没填",IF(OR(N($F20)<0,N($G20)<0),"※金额不能填负数，方向反了就换一列填",IF($D20="","※没填收支类别，分类报表会漏掉这一笔",IF(ISNA(MATCH($D20,类别表,0)),"※收支类别不在【基础资料】的清单里",IF(AND($L20="内部转账",$M20=""),"△内部转账要在「对方账户」写上另一头",IF(AND($L20="内部转账",$M20=$C20),"※对方账户跟本账户是同一个",IF(AND($L20<>"内部转账",$M20<>""),"△填了对方账户，但类别不是内部转账",IF(YEAR($B20)<>管理年度,"△不是管理年度的单据，按月的三张报表里看不到",IF($H20<0,"△这一笔之后该账户余额成负数了，核一下",""))))))))))))))
A21: =IF($C21="","",COUNTA($C$5:$C21)) -> 17 | B21: 46201 | C21: 微信 | D21: 销售回款 | F21: 800 | H21: =IFERROR(ROUND(VLOOKUP($C21,基础资料!$B$5:$E$34,3,0)+SUMIF($C$5:$C21,$C21,$F$5:$F21)-SUMIF($C$5:$C21,$C21,$G$5:$G21),2),"") -> 6600 | I21: 客户6 | K21: =IF(OR($B21="",NOT(ISNUMBER($B21))),"",--TEXT($B21,"yyyymm")) -> 202606 | L21: =IF($D21="","",IFERROR(INDEX(类别属性,MATCH($D21,类别表,0)),"")) -> 收入 | N21: 主营业务 | P21: =IF($C21="","",IF(ISNA(MATCH($C21,账户表,0)),"※这个账户不在【基础资料】的账户档案里",IF($B21="","※没填日期，这一笔不会进任何月份的报表",IF(NOT(ISNUMBER($B21)),"※日期是文本不是日期（像 2026.6.28 这种），按日期取数的报表全会漏掉这一笔",IF(AND($F21<>"",$G21<>""),"※收入和支出不能同时填",IF(AND(N($F21)=0,N($G21)=0),"※收入和支出都没填",IF(OR(N($F21)<0,N($G21)<0),"※金额不能填负数，方向反了就换一列填",IF($D21="","※没填收支类别，分类报表会漏掉这一笔",IF(ISNA(MATCH($D21,类别表,0)),"※收支类别不在【基础资料】的清单里",IF(AND($L21="内部转账",$M21=""),"△内部转账要在「对方账户」写上另一头",IF(AND($L21="内部转账",$M21=$C21),"※对方账户跟本账户是同一个",IF(AND($L21<>"内部转账",$M21<>""),"△填了对方账户，但类别不是内部转账",IF(YEAR($B21)<>管理年度,"△不是管理年度的单据，按月的三张报表里看不到",IF($H21<0,"△这一笔之后该账户余额成负数了，核一下",""))))))))))))))
A22: =IF($C22="","",COUNTA($C$5:$C22)) -> 18 | B22: 46202 | C22: 民生 | D22: 水费 | G22: 120 | H22: =IFERROR(ROUND(VLOOKUP($C22,基础资料!$B$5:$E$34,3,0)+SUMIF($C$5:$C22,$C22,$F$5:$F22)-SUMIF($C$5:$C22,$C22,$G$5:$G22),2),"") -> 7380 | K22: =IF(OR($B22="",NOT(ISNUMBER($B22))),"",--TEXT($B22,"yyyymm")) -> 202606 | L22: =IF($D22="","",IFERROR(INDEX(类别属性,MATCH($D22,类别表,0)),"")) -> 支出 | N22: 行政 | P22: =IF($C22="","",IF(ISNA(MATCH($C22,账户表,0)),"※这个账户不在【基础资料】的账户档案里",IF($B22="","※没填日期，这一笔不会进任何月份的报表",IF(NOT(ISNUMBER($B22)),"※日期是文本不是日期（像 2026.6.28 这种），按日期取数的报表全会漏掉这一笔",IF(AND($F22<>"",$G22<>""),"※收入和支出不能同时填",IF(AND(N($F22)=0,N($G22)=0),"※收入和支出都没填",IF(OR(N($F22)<0,N($G22)<0),"※金额不能填负数，方向反了就换一列填",IF($D22="","※没填收支类别，分类报表会漏掉这一笔",IF(ISNA(MATCH($D22,类别表,0)),"※收支类别不在【基础资料】的清单里",IF(AND($L22="内部转账",$M22=""),"△内部转账要在「对方账户」写上另一头",IF(AND($L22="内部转账",$M22=$C22),"※对方账户跟本账户是同一个",IF(AND($L22<>"内部转账",$M22<>""),"△填了对方账户，但类别不是内部转账",IF(YEAR($B22)<>管理年度,"△不是管理年度的单据，按月的三张报表里看不到",IF($H22<0,"△这一笔之后该账户余额成负数了，核一下",""))))))))))))))
A23: =IF($C23="","",COUNTA($C$5:$C23)) -> 19 | B23: 46202 | C23: 建行 | D23: 银行手续费 | G23: 30 | H23: =IFERROR(ROUND(VLOOKUP($C23,基础资料!$B$5:$E$34,3,0)+SUMIF($C$5:$C23,$C23,$F$5:$F23)-SUMIF($C$5:$C23,$C23,$G$5:$G23),2),"") -> 11570 | K23: =IF(OR($B23="",NOT(ISNUMBER($B23))),"",--TEXT($B23,"yyyymm")) -> 202606 | L23: =IF($D23="","",IFERROR(INDEX(类别属性,MATCH($D23,类别表,0)),"")) -> 支出 | N23: 行政 | P23: =IF($C23="","",IF(ISNA(MATCH($C23,账户表,0)),"※这个账户不在【基础资料】的账户档案里",IF($B23="","※没填日期，这一笔不会进任何月份的报表",IF(NOT(ISNUMBER($B23)),"※日期是文本不是日期（像 2026.6.28 这种），按日期取数的报表全会漏掉这一笔",IF(AND($F23<>"",$G23<>""),"※收入和支出不能同时填",IF(AND(N($F23)=0,N($G23)=0),"※收入和支出都没填",IF(OR(N($F23)<0,N($G23)<0),"※金额不能填负数，方向反了就换一列填",IF($D23="","※没填收支类别，分类报表会漏掉这一笔",IF(ISNA(MATCH($D23,类别表,0)),"※收支类别不在【基础资料】的清单里",IF(AND($L23="内部转账",$M23=""),"△内部转账要在「对方账户」写上另一头",IF(AND($L23="内部转账",$M23=$C23),"※对方账户跟本账户是同一个",IF(AND($L23<>"内部转账",$M23<>""),"△填了对方账户，但类别不是内部转账",IF(YEAR($B23)<>管理年度,"△不是管理年度的单据，按月的三张报表里看不到",IF($H23<0,"△这一笔之后该账户余额成负数了，核一下",""))))))))))))))
A24: =IF($C24="","",COUNTA($C$5:$C24)) -> 20 | B24: 46203 | C24: 农行 | D24: 销售回款 | F24: 4200 | H24: =IFERROR(ROUND(VLOOKUP($C24,基础资料!$B$5:$E$34,3,0)+SUMIF($C$5:$C24,$C24,$F$5:$F24)-SUMIF($C$5:$C24,$C24,$G$5:$G24),2),"") -> 9200 | I24: 客户7 | K24: =IF(OR($B24="",NOT(ISNUMBER($B24))),"",--TEXT($B24,"yyyymm")) -> 202606 | L24: =IF($D24="","",IFERROR(INDEX(类别属性,MATCH($D24,类别表,0)),"")) -> 收入 | N24: 主营业务 | P24: =IF($C24="","",IF(ISNA(MATCH($C24,账户表,0)),"※这个账户不在【基础资料】的账户档案里",IF($B24="","※没填日期，这一笔不会进任何月份的报表",IF(NOT(ISNUMBER($B24)),"※日期是文本不是日期（像 2026.6.28 这种），按日期取数的报表全会漏掉这一笔",IF(AND($F24<>"",$G24<>""),"※收入和支出不能同时填",IF(AND(N($F24)=0,N($G24)=0),"※收入和支出都没填",IF(OR(N($F24)<0,N($G24)<0),"※金额不能填负数，方向反了就换一列填",IF($D24="","※没填收支类别，分类报表会漏掉这一笔",IF(ISNA(MATCH($D24,类别表,0)),"※收支类别不在【基础资料】的清单里",IF(AND($L24="内部转账",$M24=""),"△内部转账要在「对方账户」写上另一头",IF(AND($L24="内部转账",$M24=$C24),"※对方账户跟本账户是同一个",IF(AND($L24<>"内部转账",$M24<>""),"△填了对方账户，但类别不是内部转账",IF(YEAR($B24)<>管理年度,"△不是管理年度的单据，按月的三张报表里看不到",IF($H24<0,"△这一笔之后该账户余额成负数了，核一下",""))))))))))))))
A25: =IF($C25="","",COUNTA($C$5:$C25)) -> 21 | B25: 46203 | C25: 中行 | D25: 供应商 | G25: 2500 | H25: =IFERROR(ROUND(VLOOKUP($C25,基础资料!$B$5:$E$34,3,0)+SUMIF($C$5:$C25,$C25,$F$5:$F25)-SUMIF($C$5:$C25,$C25,$G$5:$G25),2),"") -> 8300 | J25: 供应商3 | K25: =IF(OR($B25="",NOT(ISNUMBER($B25))),"",--TEXT($B25,"yyyymm")) -> 202606 | L25: =IF($D25="","",IFERROR(INDEX(类别属性,MATCH($D25,类别表,0)),"")) -> 支出 | N25: 主营业务 | P25: =IF($C25="","",IF(ISNA(MATCH($C25,账户表,0)),"※这个账户不在【基础资料】的账户档案里",IF($B25="","※没填日期，这一笔不会进任何月份的报表",IF(NOT(ISNUMBER($B25)),"※日期是文本不是日期（像 2026.6.28 这种），按日期取数的报表全会漏掉这一笔",IF(AND($F25<>"",$G25<>""),"※收入和支出不能同时填",IF(AND(N($F25)=0,N($G25)=0),"※收入和支出都没填",IF(OR(N($F25)<0,N($G25)<0),"※金额不能填负数，方向反了就换一列填",IF($D25="","※没填收支类别，分类报表会漏掉这一笔",IF(ISNA(MATCH($D25,类别表,0)),"※收支类别不在【基础资料】的清单里",IF(AND($L25="内部转账",$M25=""),"△内部转账要在「对方账户」写上另一头",IF(AND($L25="内部转账",$M25=$C25),"※对方账户跟本账户是同一个",IF(AND($L25<>"内部转账",$M25<>""),"△填了对方账户，但类别不是内部转账",IF(YEAR($B25)<>管理年度,"△不是管理年度的单据，按月的三张报表里看不到",IF($H25<0,"△这一笔之后该账户余额成负数了，核一下",""))))))))))))))
A26: =IF($C26="","",COUNTA($C$5:$C26)) -> 22 | B26: 46203 | C26: 支付宝 | D26: 销售回款 | F26: 600 | H26: =IFERROR(ROUND(VLOOKUP($C26,基础资料!$B$5:$E$34,3,0)+SUMIF($C$5:$C26,$C26,$F$5:$F26)-SUMIF($C$5:$C26,$C26,$G$5:$G26),2),"") -> 12590 | I26: 客户8 | K26: =IF(OR($B26="",NOT(ISNUMBER($B26))),"",--TEXT($B26,"yyyymm")) -> 202606 | L26: =IF($D26="","",IFERROR(INDEX(类别属性,MATCH($D26,类别表,0)),"")) -> 收入 | N26: 主营业务 | P26: =IF($C26="","",IF(ISNA(MATCH($C26,账户表,0)),"※这个账户不在【基础资料】的账户档案里",IF($B26="","※没填日期，这一笔不会进任何月份的报表",IF(NOT(ISNUMBER($B26)),"※日期是文本不是日期（像 2026.6.28 这种），按日期取数的报表全会漏掉这一笔",IF(AND($F26<>"",$G26<>""),"※收入和支出不能同时填",IF(AND(N($F26)=0,N($G26)=0),"※收入和支出都没填",IF(OR(N($F26)<0,N($G26)<0),"※金额不能填负数，方向反了就换一列填",IF($D26="","※没填收支类别，分类报表会漏掉这一笔",IF(ISNA(MATCH($D26,类别表,0)),"※收支类别不在【基础资料】的清单里",IF(AND($L26="内部转账",$M26=""),"△内部转账要在「对方账户」写上另一头",IF(AND($L26="内部转账",$M26=$C26),"※对方账户跟本账户是同一个",IF(AND($L26<>"内部转账",$M26<>""),"△填了对方账户，但类别不是内部转账",IF(YEAR($B26)<>管理年度,"△不是管理年度的单据，按月的三张报表里看不到",IF($H26<0,"△这一笔之后该账户余额成负数了，核一下",""))))))))))))))
A27: =IF($C27="","",COUNTA($C$5:$C27)) -> 23 | B27: 46203 | C27: 农商行 | D27: 办公费 | G27: 80 | H27: =IFERROR(ROUND(VLOOKUP($C27,基础资料!$B$5:$E$34,3,0)+SUMIF($C$5:$C27,$C27,$F$5:$F27)-SUMIF($C$5:$C27,$C27,$G$5:$G27),2),"") -> 12870 | K27: =IF(OR($B27="",NOT(ISNUMBER($B27))),"",--TEXT($B27,"yyyymm")) -> 202606 | L27: =IF($D27="","",IFERROR(INDEX(类别属性,MATCH($D27,类别表,0)),"")) -> 支出 | N27: 行政 | P27: =IF($C27="","",IF(ISNA(MATCH($C27,账户表,0)),"※这个账户不在【基础资料】的账户档案里",IF($B27="","※没填日期，这一笔不会进任何月份的报表",IF(NOT(ISNUMBER($B27)),"※日期是文本不是日期（像 2026.6.28 这种），按日期取数的报表全会漏掉这一笔",IF(AND($F27<>"",$G27<>""),"※收入和支出不能同时填",IF(AND(N($F27)=0,N($G27)=0),"※收入和支出都没填",IF(OR(N($F27)<0,N($G27)<0),"※金额不能填负数，方向反了就换一列填",IF($D27="","※没填收支类别，分类报表会漏掉这一笔",IF(ISNA(MATCH($D27,类别表,0)),"※收支类别不在【基础资料】的清单里",IF(AND($L27="内部转账",$M27=""),"△内部转账要在「对方账户」写上另一头",IF(AND($L27="内部转账",$M27=$C27),"※对方账户跟本账户是同一个",IF(AND($L27<>"内部转账",$M27<>""),"△填了对方账户，但类别不是内部转账",IF(YEAR($B27)<>管理年度,"△不是管理年度的单据，按月的三张报表里看不到",IF($H27<0,"△这一笔之后该账户余额成负数了，核一下",""))))))))))))))
A28: =IF($C28="","",COUNTA($C$5:$C28)) -> 24 | B28: 46203 | C28: 工行 | D28: 内部转账 | E28: 工行转现金备用 | G28: 2000 | H28: =IFERROR(ROUND(VLOOKUP($C28,基础资料!$B$5:$E$34,3,0)+SUMIF($C$5:$C28,$C28,$F$5:$F28)-SUMIF($C$5:$C28,$C28,$G$5:$G28),2),"") -> 1700 | K28: =IF(OR($B28="",NOT(ISNUMBER($B28))),"",--TEXT($B28,"yyyymm")) -> 202606 | L28: =IF($D28="","",IFERROR(INDEX(类别属性,MATCH($D28,类别表,0)),"")) -> 内部转账 | M28: 现金 | N28: 内部调拨 | P28: =IF($C28="","",IF(ISNA(MATCH($C28,账户表,0)),"※这个账户不在【基础资料】的账户档案里",IF($B28="","※没填日期，这一笔不会进任何月份的报表",IF(NOT(ISNUMBER($B28)),"※日期是文本不是日期（像 2026.6.28 这种），按日期取数的报表全会漏掉这一笔",IF(AND($F28<>"",$G28<>""),"※收入和支出不能同时填",IF(AND(N($F28)=0,N($G28)=0),"※收入和支出都没填",IF(OR(N($F28)<0,N($G28)<0),"※金额不能填负数，方向反了就换一列填",IF($D28="","※没填收支类别，分类报表会漏掉这一笔",IF(ISNA(MATCH($D28,类别表,0)),"※收支类别不在【基础资料】的清单里",IF(AND($L28="内部转账",$M28=""),"△内部转账要在「对方账户」写上另一头",IF(AND($L28="内部转账",$M28=$C28),"※对方账户跟本账户是同一个",IF(AND($L28<>"内部转账",$M28<>""),"△填了对方账户，但类别不是内部转账",IF(YEAR($B28)<>管理年度,"△不是管理年度的单据，按月的三张报表里看不到",IF($H28<0,"△这一笔之后该账户余额成负数了，核一下",""))))))))))))))
A29: =IF($C29="","",COUNTA($C$5:$C29)) -> 25 | B29: 46203 | C29: 现金 | D29: 内部转账 | E29: 收到工行转入 | F29: 2000 | H29: =IFERROR(ROUND(VLOOKUP($C29,基础资料!$B$5:$E$34,3,0)+SUMIF($C$5:$C29,$C29,$F$5:$F29)-SUMIF($C$5:$C29,$C29,$G$5:$G29),2),"") -> 8800 | K29: =IF(OR($B29="",NOT(ISNUMBER($B29))),"",--TEXT($B29,"yyyymm")) -> 202606 | L29: =IF($D29="","",IFERROR(INDEX(类别属性,MATCH($D29,类别表,0)),"")) -> 内部转账 | M29: 工行 | N29: 内部调拨 | P29: =IF($C29="","",IF(ISNA(MATCH($C29,账户表,0)),"※这个账户不在【基础资料】的账户档案里",IF($B29="","※没填日期，这一笔不会进任何月份的报表",IF(NOT(ISNUMBER($B29)),"※日期是文本不是日期（像 2026.6.28 这种），按日期取数的报表全会漏掉这一笔",IF(AND($F29<>"",$G29<>""),"※收入和支出不能同时填",IF(AND(N($F29)=0,N($G29)=0),"※收入和支出都没填",IF(OR(N($F29)<0,N($G29)<0),"※金额不能填负数，方向反了就换一列填",IF($D29="","※没填收支类别，分类报表会漏掉这一笔",IF(ISNA(MATCH($D29,类别表,0)),"※收支类别不在【基础资料】的清单里",IF(AND($L29="内部转账",$M29=""),"△内部转账要在「对方账户」写上另一头",IF(AND($L29="内部转账",$M29=$C29),"※对方账户跟本账户是同一个",IF(AND($L29<>"内部转账",$M29<>""),"△填了对方账户，但类别不是内部转账",IF(YEAR($B29)<>管理年度,"△不是管理年度的单据，按月的三张报表里看不到",IF($H29<0,"△这一笔之后该账户余额成负数了，核一下",""))))))))))))))
A30: =IF($C30="","",COUNTA($C$5:$C30)) | H30: =IFERROR(ROUND(VLOOKUP($C30,基础资料!$B$5:$E$34,3,0)+SUMIF($C$5:$C30,$C30,$F$5:$F30)-SUMIF($C$5:$C30,$C30,$G$5:$G30),2),"") | K30: =IF(OR($B30="",NOT(ISNUMBER($B30))),"",--TEXT($B30,"yyyymm")) | L30: =IF($D30="","",IFERROR(INDEX(类别属性,MATCH($D30,类别表,0)),"")) | P30: =IF($C30="","",IF(ISNA(MATCH($C30,账户表,0)),"※这个账户不在【基础资料】的账户档案里",IF($B30="","※没填日期，这一笔不会进任何月份的报表",IF(NOT(ISNUMBER($B30)),"※日期是文本不是日期（像 2026.6.28 这种），按日期取数的报表全会漏掉这一笔",IF(AND($F30<>"",$G30<>""),"※收入和支出不能同时填",IF(AND(N($F30)=0,N($G30)=0),"※收入和支出都没填",IF(OR(N($F30)<0,N($G30)<0),"※金额不能填负数，方向反了就换一列填",IF($D30="","※没填收支类别，分类报表会漏掉这一笔",IF(ISNA(MATCH($D30,类别表,0)),"※收支类别不在【基础资料】的清单里",IF(AND($L30="内部转账",$M30=""),"△内部转账要在「对方账户」写上另一头",IF(AND($L30="内部转账",$M30=$C30),"※对方账户跟本账户是同一个",IF(AND($L30<>"内部转账",$M30<>""),"△填了对方账户，但类别不是内部转账",IF(YEAR($B30)<>管理年度,"△不是管理年度的单据，按月的三张报表里看不到",IF($H30<0,"△这一笔之后该账户余额成负数了，核一下",""))))))))))))))
A31: =IF($C31="","",COUNTA($C$5:$C31)) | H31: =IFERROR(ROUND(VLOOKUP($C31,基础资料!$B$5:$E$34,3,0)+SUMIF($C$5:$C31,$C31,$F$5:$F31)-SUMIF($C$5:$C31,$C31,$G$5:$G31),2),"") | K31: =IF(OR($B31="",NOT(ISNUMBER($B31))),"",--TEXT($B31,"yyyymm")) | L31: =IF($D31="","",IFERROR(INDEX(类别属性,MATCH($D31,类别表,0)),"")) | P31: =IF($C31="","",IF(ISNA(MATCH($C31,账户表,0)),"※这个账户不在【基础资料】的账户档案里",IF($B31="","※没填日期，这一笔不会进任何月份的报表",IF(NOT(ISNUMBER($B31)),"※日期是文本不是日期（像 2026.6.28 这种），按日期取数的报表全会漏掉这一笔",IF(AND($F31<>"",$G31<>""),"※收入和支出不能同时填",IF(AND(N($F31)=0,N($G31)=0),"※收入和支出都没填",IF(OR(N($F31)<0,N($G31)<0),"※金额不能填负数，方向反了就换一列填",IF($D31="","※没填收支类别，分类报表会漏掉这一笔",IF(ISNA(MATCH($D31,类别表,0)),"※收支类别不在【基础资料】的清单里",IF(AND($L31="内部转账",$M31=""),"△内部转账要在「对方账户」写上另一头",IF(AND($L31="内部转账",$M31=$C31),"※对方账户跟本账户是同一个",IF(AND($L31<>"内部转账",$M31<>""),"△填了对方账户，但类别不是内部转账",IF(YEAR($B31)<>管理年度,"△不是管理年度的单据，按月的三张报表里看不到",IF($H31<0,"△这一笔之后该账户余额成负数了，核一下",""))))))))))))))
A32: =IF($C32="","",COUNTA($C$5:$C32)) | H32: =IFERROR(ROUND(VLOOKUP($C32,基础资料!$B$5:$E$34,3,0)+SUMIF($C$5:$C32,$C32,$F$5:$F32)-SUMIF($C$5:$C32,$C32,$G$5:$G32),2),"") | K32: =IF(OR($B32="",NOT(ISNUMBER($B32))),"",--TEXT($B32,"yyyymm")) | L32: =IF($D32="","",IFERROR(INDEX(类别属性,MATCH($D32,类别表,0)),"")) | P32: =IF($C32="","",IF(ISNA(MATCH($C32,账户表,0)),"※这个账户不在【基础资料】的账户档案里",IF($B32="","※没填日期，这一笔不会进任何月份的报表",IF(NOT(ISNUMBER($B32)),"※日期是文本不是日期（像 2026.6.28 这种），按日期取数的报表全会漏掉这一笔",IF(AND($F32<>"",$G32<>""),"※收入和支出不能同时填",IF(AND(N($F32)=0,N($G32)=0),"※收入和支出都没填",IF(OR(N($F32)<0,N($G32)<0),"※金额不能填负数，方向反了就换一列填",IF($D32="","※没填收支类别，分类报表会漏掉这一笔",IF(ISNA(MATCH($D32,类别表,0)),"※收支类别不在【基础资料】的清单里",IF(AND($L32="内部转账",$M32=""),"△内部转账要在「对方账户」写上另一头",IF(AND($L32="内部转账",$M32=$C32),"※对方账户跟本账户是同一个",IF(AND($L32<>"内部转账",$M32<>""),"△填了对方账户，但类别不是内部转账",IF(YEAR($B32)<>管理年度,"△不是管理年度的单据，按月的三张报表里看不到",IF($H32<0,"△这一笔之后该账户余额成负数了，核一下",""))))))))))))))
A33: =IF($C33="","",COUNTA($C$5:$C33)) | H33: =IFERROR(ROUND(VLOOKUP($C33,基础资料!$B$5:$E$34,3,0)+SUMIF($C$5:$C33,$C33,$F$5:$F33)-SUMIF($C$5:$C33,$C33,$G$5:$G33),2),"") | K33: =IF(OR($B33="",NOT(ISNUMBER($B33))),"",--TEXT($B33,"yyyymm")) | L33: =IF($D33="","",IFERROR(INDEX(类别属性,MATCH($D33,类别表,0)),"")) | P33: =IF($C33="","",IF(ISNA(MATCH($C33,账户表,0)),"※这个账户不在【基础资料】的账户档案里",IF($B33="","※没填日期，这一笔不会进任何月份的报表",IF(NOT(ISNUMBER($B33)),"※日期是文本不是日期（像 2026.6.28 这种），按日期取数的报表全会漏掉这一笔",IF(AND($F33<>"",$G33<>""),"※收入和支出不能同时填",IF(AND(N($F33)=0,N($G33)=0),"※收入和支出都没填",IF(OR(N($F33)<0,N($G33)<0),"※金额不能填负数，方向反了就换一列填",IF($D33="","※没填收支类别，分类报表会漏掉这一笔",IF(ISNA(MATCH($D33,类别表,0)),"※收支类别不在【基础资料】的清单里",IF(AND($L33="内部转账",$M33=""),"△内部转账要在「对方账户」写上另一头",IF(AND($L33="内部转账",$M33=$C33),"※对方账户跟本账户是同一个",IF(AND($L33<>"内部转账",$M33<>""),"△填了对方账户，但类别不是内部转账",IF(YEAR($B33)<>管理年度,"△不是管理年度的单据，按月的三张报表里看不到",IF($H33<0,"△这一笔之后该账户余额成负数了，核一下",""))))))))))))))
A34: =IF($C34="","",COUNTA($C$5:$C34)) | H34: =IFERROR(ROUND(VLOOKUP($C34,基础资料!$B$5:$E$34,3,0)+SUMIF($C$5:$C34,$C34,$F$5:$F34)-SUMIF($C$5:$C34,$C34,$G$5:$G34),2),"") | K34: =IF(OR($B34="",NOT(ISNUMBER($B34))),"",--TEXT($B34,"yyyymm")) | L34: =IF($D34="","",IFERROR(INDEX(类别属性,MATCH($D34,类别表,0)),"")) | P34: =IF($C34="","",IF(ISNA(MATCH($C34,账户表,0)),"※这个账户不在【基础资料】的账户档案里",IF($B34="","※没填日期，这一笔不会进任何月份的报表",IF(NOT(ISNUMBER($B34)),"※日期是文本不是日期（像 2026.6.28 这种），按日期取数的报表全会漏掉这一笔",IF(AND($F34<>"",$G34<>""),"※收入和支出不能同时填",IF(AND(N($F34)=0,N($G34)=0),"※收入和支出都没填",IF(OR(N($F34)<0,N($G34)<0),"※金额不能填负数，方向反了就换一列填",IF($D34="","※没填收支类别，分类报表会漏掉这一笔",IF(ISNA(MATCH($D34,类别表,0)),"※收支类别不在【基础资料】的清单里",IF(AND($L34="内部转账",$M34=""),"△内部转账要在「对方账户」写上另一头",IF(AND($L34="内部转账",$M34=$C34),"※对方账户跟本账户是同一个",IF(AND($L34<>"内部转账",$M34<>""),"△填了对方账户，但类别不是内部转账",IF(YEAR($B34)<>管理年度,"△不是管理年度的单据，按月的三张报表里看不到",IF($H34<0,"△这一笔之后该账户余额成负数了，核一下",""))))))))))))))
A35: =IF($C35="","",COUNTA($C$5:$C35)) | H35: =IFERROR(ROUND(VLOOKUP($C35,基础资料!$B$5:$E$34,3,0)+SUMIF($C$5:$C35,$C35,$F$5:$F35)-SUMIF($C$5:$C35,$C35,$G$5:$G35),2),"") | K35: =IF(OR($B35="",NOT(ISNUMBER($B35))),"",--TEXT($B35,"yyyymm")) | L35: =IF($D35="","",IFERROR(INDEX(类别属性,MATCH($D35,类别表,0)),"")) | P35: =IF($C35="","",IF(ISNA(MATCH($C35,账户表,0)),"※这个账户不在【基础资料】的账户档案里",IF($B35="","※没填日期，这一笔不会进任何月份的报表",IF(NOT(ISNUMBER($B35)),"※日期是文本不是日期（像 2026.6.28 这种），按日期取数的报表全会漏掉这一笔",IF(AND($F35<>"",$G35<>""),"※收入和支出不能同时填",IF(AND(N($F35)=0,N($G35)=0),"※收入和支出都没填",IF(OR(N($F35)<0,N($G35)<0),"※金额不能填负数，方向反了就换一列填",IF($D35="","※没填收支类别，分类报表会漏掉这一笔",IF(ISNA(MATCH($D35,类别表,0)),"※收支类别不在【基础资料】的清单里",IF(AND($L35="内部转账",$M35=""),"△内部转账要在「对方账户」写上另一头",IF(AND($L35="内部转账",$M35=$C35),"※对方账户跟本账户是同一个",IF(AND($L35<>"内部转账",$M35<>""),"△填了对方账户，但类别不是内部转账",IF(YEAR($B35)<>管理年度,"△不是管理年度的单据，按月的三张报表里看不到",IF($H35<0,"△这一笔之后该账户余额成负数了，核一下",""))))))))))))))
A36: =IF($C36="","",COUNTA($C$5:$C36)) | H36: =IFERROR(ROUND(VLOOKUP($C36,基础资料!$B$5:$E$34,3,0)+SUMIF($C$5:$C36,$C36,$F$5:$F36)-SUMIF($C$5:$C36,$C36,$G$5:$G36),2),"") | K36: =IF(OR($B36="",NOT(ISNUMBER($B36))),"",--TEXT($B36,"yyyymm")) | L36: =IF($D36="","",IFERROR(INDEX(类别属性,MATCH($D36,类别表,0)),"")) | P36: =IF($C36="","",IF(ISNA(MATCH($C36,账户表,0)),"※这个账户不在【基础资料】的账户档案里",IF($B36="","※没填日期，这一笔不会进任何月份的报表",IF(NOT(ISNUMBER($B36)),"※日期是文本不是日期（像 2026.6.28 这种），按日期取数的报表全会漏掉这一笔",IF(AND($F36<>"",$G36<>""),"※收入和支出不能同时填",IF(AND(N($F36)=0,N($G36)=0),"※收入和支出都没填",IF(OR(N($F36)<0,N($G36)<0),"※金额不能填负数，方向反了就换一列填",IF($D36="","※没填收支类别，分类报表会漏掉这一笔",IF(ISNA(MATCH($D36,类别表,0)),"※收支类别不在【基础资料】的清单里",IF(AND($L36="内部转账",$M36=""),"△内部转账要在「对方账户」写上另一头",IF(AND($L36="内部转账",$M36=$C36),"※对方账户跟本账户是同一个",IF(AND($L36<>"内部转账",$M36<>""),"△填了对方账户，但类别不是内部转账",IF(YEAR($B36)<>管理年度,"△不是管理年度的单据，按月的三张报表里看不到",IF($H36<0,"△这一笔之后该账户余额成负数了，核一下",""))))))))))))))
A37: =IF($C37="","",COUNTA($C$5:$C37)) | H37: =IFERROR(ROUND(VLOOKUP($C37,基础资料!$B$5:$E$34,3,0)+SUMIF($C$5:$C37,$C37,$F$5:$F37)-SUMIF($C$5:$C37,$C37,$G$5:$G37),2),"") | K37: =IF(OR($B37="",NOT(ISNUMBER($B37))),"",--TEXT($B37,"yyyymm")) | L37: =IF($D37="","",IFERROR(INDEX(类别属性,MATCH($D37,类别表,0)),"")) | P37: =IF($C37="","",IF(ISNA(MATCH($C37,账户表,0)),"※这个账户不在【基础资料】的账户档案里",IF($B37="","※没填日期，这一笔不会进任何月份的报表",IF(NOT(ISNUMBER($B37)),"※日期是文本不是日期（像 2026.6.28 这种），按日期取数的报表全会漏掉这一笔",IF(AND($F37<>"",$G37<>""),"※收入和支出不能同时填",IF(AND(N($F37)=0,N($G37)=0),"※收入和支出都没填",IF(OR(N($F37)<0,N($G37)<0),"※金额不能填负数，方向反了就换一列填",IF($D37="","※没填收支类别，分类报表会漏掉这一笔",IF(ISNA(MATCH($D37,类别表,0)),"※收支类别不在【基础资料】的清单里",IF(AND($L37="内部转账",$M37=""),"△内部转账要在「对方账户」写上另一头",IF(AND($L37="内部转账",$M37=$C37),"※对方账户跟本账户是同一个",IF(AND($L37<>"内部转账",$M37<>""),"△填了对方账户，但类别不是内部转账",IF(YEAR($B37)<>管理年度,"△不是管理年度的单据，按月的三张报表里看不到",IF($H37<0,"△这一笔之后该账户余额成负数了，核一下",""))))))))))))))
A38: =IF($C38="","",COUNTA($C$5:$C38)) | H38: =IFERROR(ROUND(VLOOKUP($C38,基础资料!$B$5:$E$34,3,0)+SUMIF($C$5:$C38,$C38,$F$5:$F38)-SUMIF($C$5:$C38,$C38,$G$5:$G38),2),"") | K38: =IF(OR($B38="",NOT(ISNUMBER($B38))),"",--TEXT($B38,"yyyymm")) | L38: =IF($D38="","",IFERROR(INDEX(类别属性,MATCH($D38,类别表,0)),"")) | P38: =IF($C38="","",IF(ISNA(MATCH($C38,账户表,0)),"※这个账户不在【基础资料】的账户档案里",IF($B38="","※没填日期，这一笔不会进任何月份的报表",IF(NOT(ISNUMBER($B38)),"※日期是文本不是日期（像 2026.6.28 这种），按日期取数的报表全会漏掉这一笔",IF(AND($F38<>"",$G38<>""),"※收入和支出不能同时填",IF(AND(N($F38)=0,N($G38)=0),"※收入和支出都没填",IF(OR(N($F38)<0,N($G38)<0),"※金额不能填负数，方向反了就换一列填",IF($D38="","※没填收支类别，分类报表会漏掉这一笔",IF(ISNA(MATCH($D38,类别表,0)),"※收支类别不在【基础资料】的清单里",IF(AND($L38="内部转账",$M38=""),"△内部转账要在「对方账户」写上另一头",IF(AND($L38="内部转账",$M38=$C38),"※对方账户跟本账户是同一个",IF(AND($L38<>"内部转账",$M38<>""),"△填了对方账户，但类别不是内部转账",IF(YEAR($B38)<>管理年度,"△不是管理年度的单据，按月的三张报表里看不到",IF($H38<0,"△这一笔之后该账户余额成负数了，核一下",""))))))))))))))
A39: =IF($C39="","",COUNTA($C$5:$C39)) | H39: =IFERROR(ROUND(VLOOKUP($C39,基础资料!$B$5:$E$34,3,0)+SUMIF($C$5:$C39,$C39,$F$5:$F39)-SUMIF($C$5:$C39,$C39,$G$5:$G39),2),"") | K39: =IF(OR($B39="",NOT(ISNUMBER($B39))),"",--TEXT($B39,"yyyymm")) | L39: =IF($D39="","",IFERROR(INDEX(类别属性,MATCH($D39,类别表,0)),"")) | P39: =IF($C39="","",IF(ISNA(MATCH($C39,账户表,0)),"※这个账户不在【基础资料】的账户档案里",IF($B39="","※没填日期，这一笔不会进任何月份的报表",IF(NOT(ISNUMBER($B39)),"※日期是文本不是日期（像 2026.6.28 这种），按日期取数的报表全会漏掉这一笔",IF(AND($F39<>"",$G39<>""),"※收入和支出不能同时填",IF(AND(N($F39)=0,N($G39)=0),"※收入和支出都没填",IF(OR(N($F39)<0,N($G39)<0),"※金额不能填负数，方向反了就换一列填",IF($D39="","※没填收支类别，分类报表会漏掉这一笔",IF(ISNA(MATCH($D39,类别表,0)),"※收支类别不在【基础资料】的清单里",IF(AND($L39="内部转账",$M39=""),"△内部转账要在「对方账户」写上另一头",IF(AND($L39="内部转账",$M39=$C39),"※对方账户跟本账户是同一个",IF(AND($L39<>"内部转账",$M39<>""),"△填了对方账户，但类别不是内部转账",IF(YEAR($B39)<>管理年度,"△不是管理年度的单据，按月的三张报表里看不到",IF($H39<0,"△这一笔之后该账户余额成负数了，核一下",""))))))))))))))
A40: =IF($C40="","",COUNTA($C$5:$C40)) | H40: =IFERROR(ROUND(VLOOKUP($C40,基础资料!$B$5:$E$34,3,0)+SUMIF($C$5:$C40,$C40,$F$5:$F40)-SUMIF($C$5:$C40,$C40,$G$5:$G40),2),"") | K40: =IF(OR($B40="",NOT(ISNUMBER($B40))),"",--TEXT($B40,"yyyymm")) | L40: =IF($D40="","",IFERROR(INDEX(类别属性,MATCH($D40,类别表,0)),"")) | P40: =IF($C40="","",IF(ISNA(MATCH($C40,账户表,0)),"※这个账户不在【基础资料】的账户档案里",IF($B40="","※没填日期，这一笔不会进任何月份的报表",IF(NOT(ISNUMBER($B40)),"※日期是文本不是日期（像 2026.6.28 这种），按日期取数的报表全会漏掉这一笔",IF(AND($F40<>"",$G40<>""),"※收入和支出不能同时填",IF(AND(N($F40)=0,N($G40)=0),"※收入和支出都没填",IF(OR(N($F40)<0,N($G40)<0),"※金额不能填负数，方向反了就换一列填",IF($D40="","※没填收支类别，分类报表会漏掉这一笔",IF(ISNA(MATCH($D40,类别表,0)),"※收支类别不在【基础资料】的清单里",IF(AND($L40="内部转账",$M40=""),"△内部转账要在「对方账户」写上另一头",IF(AND($L40="内部转账",$M40=$C40),"※对方账户跟本账户是同一个",IF(AND($L40<>"内部转账",$M40<>""),"△填了对方账户，但类别不是内部转账",IF(YEAR($B40)<>管理年度,"△不是管理年度的单据，按月的三张报表里看不到",IF($H40<0,"△这一笔之后该账户余额成负数了，核一下",""))))))))))))))
A41: =IF($C41="","",COUNTA($C$5:$C41)) | H41: =IFERROR(ROUND(VLOOKUP($C41,基础资料!$B$5:$E$34,3,0)+SUMIF($C$5:$C41,$C41,$F$5:$F41)-SUMIF($C$5:$C41,$C41,$G$5:$G41),2),"") | K41: =IF(OR($B41="",NOT(ISNUMBER($B41))),"",--TEXT($B41,"yyyymm")) | L41: =IF($D41="","",IFERROR(INDEX(类别属性,MATCH($D41,类别表,0)),"")) | P41: =IF($C41="","",IF(ISNA(MATCH($C41,账户表,0)),"※这个账户不在【基础资料】的账户档案里",IF($B41="","※没填日期，这一笔不会进任何月份的报表",IF(NOT(ISNUMBER($B41)),"※日期是文本不是日期（像 2026.6.28 这种），按日期取数的报表全会漏掉这一笔",IF(AND($F41<>"",$G41<>""),"※收入和支出不能同时填",IF(AND(N($F41)=0,N($G41)=0),"※收入和支出都没填",IF(OR(N($F41)<0,N($G41)<0),"※金额不能填负数，方向反了就换一列填",IF($D41="","※没填收支类别，分类报表会漏掉这一笔",IF(ISNA(MATCH($D41,类别表,0)),"※收支类别不在【基础资料】的清单里",IF(AND($L41="内部转账",$M41=""),"△内部转账要在「对方账户」写上另一头",IF(AND($L41="内部转账",$M41=$C41),"※对方账户跟本账户是同一个",IF(AND($L41<>"内部转账",$M41<>""),"△填了对方账户，但类别不是内部转账",IF(YEAR($B41)<>管理年度,"△不是管理年度的单据，按月的三张报表里看不到",IF($H41<0,"△这一笔之后该账户余额成负数了，核一下",""))))))))))))))
... A5071: =IF($C5071="","",COUNTA($C$5:$C5071)) | H5071: =IFERROR(ROUND(VLOOKUP($C5071,基础资料!$B$5:$E$34,3,0)+SUMIF($C$5:$C5071,$C5071,$F$5:$F5071)-SUMIF($C$5:$C5071,$C5071,$G$5:$G5071),2),"") | K5071: =IF(OR($B5071="",NOT(ISNUMBER($B5071))),"",--TEXT($B5071,"yyyymm")) | L5071: =IF($D5071="","",IFERROR(INDEX(类别属性,MATCH($D5071,类别表,0)),"")) | P5071: =IF($C5071="","",IF(ISNA(MATCH($C5071,账户表,0)),"※这个账户不在【基础资料】的账户档案里",IF($B5071="","※没填日期，这一笔不会进任何月份的报表",IF(NOT(ISNUMBER($B5071)),"※日期是文本不是日期（像 2026.6.28 这种），按日期取数的报表全会漏掉这一笔",IF(AND($F5071<>"",$G5071<>""),"※收入和支出不能同时填",IF(AND(N($F5071)=0,N($G5071)=0),"※收入和支出都没填",IF(OR(N($F5071)<0,N($G5071)<0),"※金额不能填负数，方向反了就换一列填",IF($D5071="","※没填收支类别，分类报表会漏掉这一笔",IF(ISNA(MATCH($D5071,类别表,0)),"※收支类别不在【基础资料】的清单里",IF(AND($L5071="内部转账",$M5071=""),"△内部转账要在「对方账户」写上另一头",IF(AND($L5071="内部转账",$M5071=$C5071),"※对方账户跟本账户是同一个",IF(AND($L5071<>"内部转账",$M5071<>""),"△填了对方账户，但类别不是内部转账",IF(YEAR($B5071)<>管理年度,"△不是管理年度的单据，按月的三张报表里看不到",IF($H5071<0,"△这一笔之后该账户余额成负数了，核一下",""))))))))))))))

Sheet 汇报表
A1: 汇报表 · 三块老界面原样保留（账户清单改成自动长，加账户不用再改三处）
A2: ① 资金日报统计表：改上面两个日期就行，最多 31 天。这一块是「账户口径」 ——收款/付款按钱进出账户算，内部划转也算在里面（因为账户余额确实动了）。② 货币资金日报表：指定某一天。③ 多帐户资金汇总表：按月，这一块是「经营口径」，内部转入/转出单独两列，不混进本月收入和本月支出。
A3: 起始日期 | B3: 46174 | D3: 截止日期 | E3: 46203 | G3: 查询天数 | H3: =IF(OR($B$3="",$E$3=""),"",IF($E$3<$B$3,"※截止早于起始",IF($E$3-$B$3+1>31,"※超过 31 天，请分段查",$E$3-$B$3+1))) -> 30
A4: 公司期初余额 | C4: 期间收款合计 | E4: 期间付款合计 | G4: 期末结余金额
B5: =ROUND(SUM(B8:B37),2) -> 161000 | D5: =ROUND(SUM(BM8:BM37),2) -> 18800 | F5: =ROUND(SUM(BN8:BN37),2) -> 24190 | H5: =ROUND(SUM(BO8:BO37),2) -> 155610
A6: ① 资金日报统计表（账户口径，含内部划转） | C6: =IF(NOT(ISNUMBER($H$3)),"",IF(1<=MIN($H$3,31),$B$3+0,"")) -> 46174 | D6: =IF(NOT(ISNUMBER($H$3)),"",IF(1<=MIN($H$3,31),$B$3+0,"")) -> 46174 | E6: =IF(NOT(ISNUMBER($H$3)),"",IF(2<=MIN($H$3,31),$B$3+1,"")) -> 46175 | F6: =IF(NOT(ISNUMBER($H$3)),"",IF(2<=MIN($H$3,31),$B$3+1,"")) -> 46175 | G6: =IF(NOT(ISNUMBER($H$3)),"",IF(3<=MIN($H$3,31),$B$3+2,"")) -> 46176 | H6: =IF(NOT(ISNUMBER($H$3)),"",IF(3<=MIN($H$3,31),$B$3+2,"")) -> 46176 | I6: =IF(NOT(ISNUMBER($H$3)),"",IF(4<=MIN($H$3,31),$B$3+3,"")) -> 46177 | J6: =IF(NOT(ISNUMBER($H$3)),"",IF(4<=MIN($H$3,31),$B$3+3,"")) -> 46177 | K6: =IF(NOT(ISNUMBER($H$3)),"",IF(5<=MIN($H$3,31),$B$3+4,"")) -> 46178 | L6: =IF(NOT(ISNUMBER($H$3)),"",IF(5<=MIN($H$3,31),$B$3+4,"")) -> 46178 | M6: =IF(NOT(ISNUMBER($H$3)),"",IF(6<=MIN($H$3,31),$B$3+5,"")) -> 46179 | N6: =IF(NOT(ISNUMBER($H$3)),"",IF(6<=MIN($H$3,31),$B$3+5,"")) -> 46179 | O6: =IF(NOT(ISNUMBER($H$3)),"",IF(7<=MIN($H$3,31),$B$3+6,"")) -> 46180 | P6: =IF(NOT(ISNUMBER($H$3)),"",IF(7<=MIN($H$3,31),$B$3+6,"")) -> 46180 | Q6: =IF(NOT(ISNUMBER($H$3)),"",IF(8<=MIN($H$3,31),$B$3+7,"")) -> 46181 | R6: =IF(NOT(ISNUMBER($H$3)),"",IF(8<=MIN($H$3,31),$B$3+7,"")) -> 46181 | S6: =IF(NOT(ISNUMBER($H$3)),"",IF(9<=MIN($H$3,31),$B$3+8,"")) -> 46182 | T6: =IF(NOT(ISNUMBER($H$3)),"",IF(9<=MIN($H$3,31),$B$3+8,"")) -> 46182 | U6: =IF(NOT(ISNUMBER($H$3)),"",IF(10<=MIN($H$3,31),$B$3+9,"")) -> 46183 | V6: =IF(NOT(ISNUMBER($H$3)),"",IF(10<=MIN($H$3,31),$B$3+9,"")) -> 46183 | W6: =IF(NOT(ISNUMBER($H$3)),"",IF(11<=MIN($H$3,31),$B$3+10,"")) -> 46184 | X6: =IF(NOT(ISNUMBER($H$3)),"",IF(11<=MIN($H$3,31),$B$3+10,"")) -> 46184 | Y6: =IF(NOT(ISNUMBER($H$3)),"",IF(12<=MIN($H$3,31),$B$3+11,"")) -> 46185 | Z6: =IF(NOT(ISNUMBER($H$3)),"",IF(12<=MIN($H$3,31),$B$3+11,"")) -> 46185 | AA6: =IF(NOT(ISNUMBER($H$3)),"",IF(13<=MIN($H$3,31),$B$3+12,"")) -> 46186 | AB6: =IF(NOT(ISNUMBER($H$3)),"",IF(13<=MIN($H$3,31),$B$3+12,"")) -> 46186 | AC6: =IF(NOT(ISNUMBER($H$3)),"",IF(14<=MIN($H$3,31),$B$3+13,"")) -> 46187 | AD6: =IF(NOT(ISNUMBER($H$3)),"",IF(14<=MIN($H$3,31),$B$3+13,"")) -> 46187 | AE6: =IF(NOT(ISNUMBER($H$3)),"",IF(15<=MIN($H$3,31),$B$3+14,"")) -> 46188 | AF6: =IF(NOT(ISNUMBER($H$3)),"",IF(15<=MIN($H$3,31),$B$3+14,"")) -> 46188 | AG6: =IF(NOT(ISNUMBER($H$3)),"",IF(16<=MIN($H$3,31),$B$3+15,"")) -> 46189 | AH6: =IF(NOT(ISNUMBER($H$3)),"",IF(16<=MIN($H$3,31),$B$3+15,"")) -> 46189 | AI6: =IF(NOT(ISNUMBER($H$3)),"",IF(17<=MIN($H$3,31),$B$3+16,"")) -> 46190 | AJ6: =IF(NOT(ISNUMBER($H$3)),"",IF(17<=MIN($H$3,31),$B$3+16,"")) -> 46190 | AK6: =IF(NOT(ISNUMBER($H$3)),"",IF(18<=MIN($H$3,31),$B$3+17,"")) -> 46191 | AL6: =IF(NOT(ISNUMBER($H$3)),"",IF(18<=MIN($H$3,31),$B$3+17,"")) -> 46191 | AM6: =IF(NOT(ISNUMBER($H$3)),"",IF(19<=MIN($H$3,31),$B$3+18,"")) -> 46192 | AN6: =IF(NOT(ISNUMBER($H$3)),"",IF(19<=MIN($H$3,31),$B$3+18,"")) -> 46192 | AO6: =IF(NOT(ISNUMBER($H$3)),"",IF(20<=MIN($H$3,31),$B$3+19,"")) -> 46193 | AP6: =IF(NOT(ISNUMBER($H$3)),"",IF(20<=MIN($H$3,31),$B$3+19,"")) -> 46193 | AQ6: =IF(NOT(ISNUMBER($H$3)),"",IF(21<=MIN($H$3,31),$B$3+20,"")) -> 46194 | AR6: =IF(NOT(ISNUMBER($H$3)),"",IF(21<=MIN($H$3,31),$B$3+20,"")) -> 46194 | AS6: =IF(NOT(ISNUMBER($H$3)),"",IF(22<=MIN($H$3,31),$B$3+21,"")) -> 46195 | AT6: =IF(NOT(ISNUMBER($H$3)),"",IF(22<=MIN($H$3,31),$B$3+21,"")) -> 46195 | AU6: =IF(NOT(ISNUMBER($H$3)),"",IF(23<=MIN($H$3,31),$B$3+22,"")) -> 46196 | AV6: =IF(NOT(ISNUMBER($H$3)),"",IF(23<=MIN($H$3,31),$B$3+22,"")) -> 46196 | AW6: =IF(NOT(ISNUMBER($H$3)),"",IF(24<=MIN($H$3,31),$B$3+23,"")) -> 46197 | AX6: =IF(NOT(ISNUMBER($H$3)),"",IF(24<=MIN($H$3,31),$B$3+23,"")) -> 46197 | AY6: =IF(NOT(ISNUMBER($H$3)),"",IF(25<=MIN($H$3,31),$B$3+24,"")) -> 46198 | AZ6: =IF(NOT(ISNUMBER($H$3)),"",IF(25<=MIN($H$3,31),$B$3+24,"")) -> 46198 | BA6: =IF(NOT(ISNUMBER($H$3)),"",IF(26<=MIN($H$3,31),$B$3+25,"")) -> 46199 | BB6: =IF(NOT(ISNUMBER($H$3)),"",IF(26<=MIN($H$3,31),$B$3+25,"")) -> 46199 | BC6: =IF(NOT(ISNUMBER($H$3)),"",IF(27<=MIN($H$3,31),$B$3+26,"")) -> 46200 | BD6: =IF(NOT(ISNUMBER($H$3)),"",IF(27<=MIN($H$3,31),$B$3+26,"")) -> 46200 | BE6: =IF(NOT(ISNUMBER($H$3)),"",IF(28<=MIN($H$3,31),$B$3+27,"")) -> 46201 | BF6: =IF(NOT(ISNUMBER($H$3)),"",IF(28<=MIN($H$3,31),$B$3+27,"")) -> 46201 | BG6: =IF(NOT(ISNUMBER($H$3)),"",IF(29<=MIN($H$3,31),$B$3+28,"")) -> 46202 | BH6: =IF(NOT(ISNUMBER($H$3)),"",IF(29<=MIN($H$3,31),$B$3+28,"")) -> 46202 | BI6: =IF(NOT(ISNUMBER($H$3)),"",IF(30<=MIN($H$3,31),$B$3+29,"")) -> 46203 | BJ6: =IF(NOT(ISNUMBER($H$3)),"",IF(30<=MIN($H$3,31),$B$3+29,"")) -> 46203 | BK6: =IF(NOT(ISNUMBER($H$3)),"",IF(31<=MIN($H$3,31),$B$3+30,"")) | BL6: =IF(NOT(ISNUMBER($H$3)),"",IF(31<=MIN($H$3,31),$B$3+30,""))
A7: 账户 | B7: 期初余额 | C7: =IF(C$6="","","收款") -> 收款 | D7: =IF(D$6="","","付款") -> 付款 | E7: =IF(E$6="","","收款") -> 收款 | F7: =IF(F$6="","","付款") -> 付款 | G7: =IF(G$6="","","收款") -> 收款 | H7: =IF(H$6="","","付款") -> 付款 | I7: =IF(I$6="","","收款") -> 收款 | J7: =IF(J$6="","","付款") -> 付款 | K7: =IF(K$6="","","收款") -> 收款 | L7: =IF(L$6="","","付款") -> 付款 | M7: =IF(M$6="","","收款") -> 收款 | N7: =IF(N$6="","","付款") -> 付款 | O7: =IF(O$6="","","收款") -> 收款 | P7: =IF(P$6="","","付款") -> 付款 | Q7: =IF(Q$6="","","收款") -> 收款 | R7: =IF(R$6="","","付款") -> 付款 | S7: =IF(S$6="","","收款") -> 收款 | T7: =IF(T$6="","","付款") -> 付款 | U7: =IF(U$6="","","收款") -> 收款 | V7: =IF(V$6="","","付款") -> 付款 | W7: =IF(W$6="","","收款") -> 收款 | X7: =IF(X$6="","","付款") -> 付款 | Y7: =IF(Y$6="","","收款") -> 收款 | Z7: =IF(Z$6="","","付款") -> 付款 | AA7: =IF(AA$6="","","收款") -> 收款 | AB7: =IF(AB$6="","","付款") -> 付款 | AC7: =IF(AC$6="","","收款") -> 收款 | AD7: =IF(AD$6="","","付款") -> 付款 | AE7: =IF(AE$6="","","收款") -> 收款 | AF7: =IF(AF$6="","","付款") -> 付款 | AG7: =IF(AG$6="","","收款") -> 收款 | AH7: =IF(AH$6="","","付款") -> 付款 | AI7: =IF(AI$6="","","收款") -> 收款 | AJ7: =IF(AJ$6="","","付款") -> 付款 | AK7: =IF(AK$6="","","收款") -> 收款 | AL7: =IF(AL$6="","","付款") -> 付款 | AM7: =IF(AM$6="","","收款") -> 收款 | AN7: =IF(AN$6="","","付款") -> 付款 | AO7: =IF(AO$6="","","收款") -> 收款 | AP7: =IF(AP$6="","","付款") -> 付款 | AQ7: =IF(AQ$6="","","收款") -> 收款 | AR7: =IF(AR$6="","","付款") -> 付款 | AS7: =IF(AS$6="","","收款") -> 收款 | AT7: =IF(AT$6="","","付款") -> 付款 | AU7: =IF(AU$6="","","收款") -> 收款 | AV7: =IF(AV$6="","","付款") -> 付款 | AW7: =IF(AW$6="","","收款") -> 收款 | AX7: =IF(AX$6="","","付款") -> 付款 | AY7: =IF(AY$6="","","收款") -> 收款 | AZ7: =IF(AZ$6="","","付款") -> 付款 | BA7: =IF(BA$6="","","收款") -> 收款 | BB7: =IF(BB$6="","","付款") -> 付款 | BC7: =IF(BC$6="","","收款") -> 收款 | BD7: =IF(BD$6="","","付款") -> 付款 | BE7: =IF(BE$6="","","收款") -> 收款 | BF7: =IF(BF$6="","","付款") -> 付款 | BG7: =IF(BG$6="","","收款") -> 收款 | BH7: =IF(BH$6="","","付款") -> 付款 | BI7: =IF(BI$6="","","收款") -> 收款 | BJ7: =IF(BJ$6="","","付款") -> 付款 | BK7: =IF(BK$6="","","收款") | BL7: =IF(BL$6="","","付款") | BM7: 期间收款 | BN7: 期间付款 | BO7: 期末余额
A8: =IF(基础资料!$B$5="","",基础资料!$B$5) -> 现金 | B8: =IF(OR($A8="",NOT(ISNUMBER($H$3))),"",ROUND(SUMIF(账户表,$A8,账户期初)+SUMIFS(流水收入,流水账户,$A8,流水日期,"<"&$B$3)-SUMIFS(流水支出,流水账户,$A8,流水日期,"<"&$B$3),2)) -> 5000 | C8: =IF(OR($A8="",C$6=""),"",ROUND(SUMIFS(流水收入,流水账户,$A8,流水日期,C$6),2)) -> 0 | D8: =IF(OR($A8="",D$6=""),"",ROUND(SUMIFS(流水支出,流水账户,$A8,流水日期,D$6),2)) -> 0 | E8: =IF(OR($A8="",E$6=""),"",ROUND(SUMIFS(流水收入,流水账户,$A8,流水日期,E$6),2)) -> 2000 | F8: =IF(OR($A8="",F$6=""),"",ROUND(SUMIFS(流水支出,流水账户,$A8,流水日期,F$6),2)) -> 0 | G8: =IF(OR($A8="",G$6=""),"",ROUND(SUMIFS(流水收入,流水账户,$A8,流水日期,G$6),2)) -> 0 | H8: =IF(OR($A8="",H$6=""),"",ROUND(SUMIFS(流水支出,流水账户,$A8,流水日期,H$6),2)) -> 0 | I8: =IF(OR($A8="",I$6=""),"",ROUND(SUMIFS(流水收入,流水账户,$A8,流水日期,I$6),2)) -> 0 | J8: =IF(OR($A8="",J$6=""),"",ROUND(SUMIFS(流水支出,流水账户,$A8,流水日期,J$6),2)) -> 0 | K8: =IF(OR($A8="",K$6=""),"",ROUND(SUMIFS(流水收入,流水账户,$A8,流水日期,K$6),2)) -> 0 | L8: =IF(OR($A8="",L$6=""),"",ROUND(SUMIFS(流水支出,流水账户,$A8,流水日期,L$6),2)) -> 0 | M8: =IF(OR($A8="",M$6=""),"",ROUND(SUMIFS(流水收入,流水账户,$A8,流水日期,M$6),2)) -> 0 | N8: =IF(OR($A8="",N$6=""),"",ROUND(SUMIFS(流水支出,流水账户,$A8,流水日期,N$6),2)) -> 0 | O8: =IF(OR($A8="",O$6=""),"",ROUND(SUMIFS(流水收入,流水账户,$A8,流水日期,O$6),2)) -> 0 | P8: =IF(OR($A8="",P$6=""),"",ROUND(SUMIFS(流水支出,流水账户,$A8,流水日期,P$6),2)) -> 0 | Q8: =IF(OR($A8="",Q$6=""),"",ROUND(SUMIFS(流水收入,流水账户,$A8,流水日期,Q$6),2)) -> 0 | R8: =IF(OR($A8="",R$6=""),"",ROUND(SUMIFS(流水支出,流水账户,$A8,流水日期,R$6),2)) -> 0 | S8: =IF(OR($A8="",S$6=""),"",ROUND(SUMIFS(流水收入,流水账户,$A8,流水日期,S$6),2)) -> 0 | T8: =IF(OR($A8="",T$6=""),"",ROUND(SUMIFS(流水支出,流水账户,$A8,流水日期,T$6),2)) -> 0 | U8: =IF(OR($A8="",U$6=""),"",ROUND(SUMIFS(流水收入,流水账户,$A8,流水日期,U$6),2)) -> 0 | V8: =IF(OR($A8="",V$6=""),"",ROUND(SUMIFS(流水支出,流水账户,$A8,流水日期,V$6),2)) -> 0 | W8: =IF(OR($A8="",W$6=""),"",ROUND(SUMIFS(流水收入,流水账户,$A8,流水日期,W$6),2)) -> 0 | X8: =IF(OR($A8="",X$6=""),"",ROUND(SUMIFS(流水支出,流水账户,$A8,流水日期,X$6),2)) -> 0 | Y8: =IF(OR($A8="",Y$6=""),"",ROUND(SUMIFS(流水收入,流水账户,$A8,流水日期,Y$6),2)) -> 0 | Z8: =IF(OR($A8="",Z$6=""),"",ROUND(SUMIFS(流水支出,流水账户,$A8,流水日期,Z$6),2)) -> 0 | AA8: =IF(OR($A8="",AA$6=""),"",ROUND(SUMIFS(流水收入,流水账户,$A8,流水日期,AA$6),2)) -> 0 | AB8: =IF(OR($A8="",AB$6=""),"",ROUND(SUMIFS(流水支出,流水账户,$A8,流水日期,AB$6),2)) -> 0 | AC8: =IF(OR($A8="",AC$6=""),"",ROUND(SUMIFS(流水收入,流水账户,$A8,流水日期,AC$6),2)) -> 0 | AD8: =IF(OR($A8="",AD$6=""),"",ROUND(SUMIFS(流水支出,流水账户,$A8,流水日期,AD$6),2)) -> 0 | AE8: =IF(OR($A8="",AE$6=""),"",ROUND(SUMIFS(流水收入,流水账户,$A8,流水日期,AE$6),2)) -> 0 | AF8: =IF(OR($A8="",AF$6=""),"",ROUND(SUMIFS(流水支出,流水账户,$A8,流水日期,AF$6),2)) -> 0 | AG8: =IF(OR($A8="",AG$6=""),"",ROUND(SUMIFS(流水收入,流水账户,$A8,流水日期,AG$6),2)) -> 0 | AH8: =IF(OR($A8="",AH$6=""),"",ROUND(SUMIFS(流水支出,流水账户,$A8,流水日期,AH$6),2)) -> 0 | AI8: =IF(OR($A8="",AI$6=""),"",ROUND(SUMIFS(流水收入,流水账户,$A8,流水日期,AI$6),2)) -> 0 | AJ8: =IF(OR($A8="",AJ$6=""),"",ROUND(SUMIFS(流水支出,流水账户,$A8,流水日期,AJ$6),2)) -> 0 | AK8: =IF(OR($A8="",AK$6=""),"",ROUND(SUMIFS(流水收入,流水账户,$A8,流水日期,AK$6),2)) -> 0 | AL8: =IF(OR($A8="",AL$6=""),"",ROUND(SUMIFS(流水支出,流水账户,$A8,流水日期,AL$6),2)) -> 0 | AM8: =IF(OR($A8="",AM$6=""),"",ROUND(SUMIFS(流水收入,流水账户,$A8,流水日期,AM$6),2)) -> 0 | AN8: =IF(OR($A8="",AN$6=""),"",ROUND(SUMIFS(流水支出,流水账户,$A8,流水日期,AN$6),2)) -> 0 | AO8: =IF(OR($A8="",AO$6=""),"",ROUND(SUMIFS(流水收入,流水账户,$A8,流水日期,AO$6),2)) -> 0 | AP8: =IF(OR($A8="",AP$6=""),"",ROUND(SUMIFS(流水支出,流水账户,$A8,流水日期,AP$6),2)) -> 0 | AQ8: =IF(OR($A8="",AQ$6=""),"",ROUND(SUMIFS(流水收入,流水账户,$A8,流水日期,AQ$6),2)) -> 0 | AR8: =IF(OR($A8="",AR$6=""),"",ROUND(SUMIFS(流水支出,流水账户,$A8,流水日期,AR$6),2)) -> 0 | AS8: =IF(OR($A8="",AS$6=""),"",ROUND(SUMIFS(流水收入,流水账户,$A8,流水日期,AS$6),2)) -> 0 | AT8: =IF(OR($A8="",AT$6=""),"",ROUND(SUMIFS(流水支出,流水账户,$A8,流水日期,AT$6),2)) -> 0 | AU8: =IF(OR($A8="",AU$6=""),"",ROUND(SUMIFS(流水收入,流水账户,$A8,流水日期,AU$6),2)) -> 0 | AV8: =IF(OR($A8="",AV$6=""),"",ROUND(SUMIFS(流水支出,流水账户,$A8,流水日期,AV$6),2)) -> 0 | AW8: =IF(OR($A8="",AW$6=""),"",ROUND(SUMIFS(流水收入,流水账户,$A8,流水日期,AW$6),2)) -> 0 | AX8: =IF(OR($A8="",AX$6=""),"",ROUND(SUMIFS(流水支出,流水账户,$A8,流水日期,AX$6),2)) -> 0 | AY8: =IF(OR($A8="",AY$6=""),"",ROUND(SUMIFS(流水收入,流水账户,$A8,流水日期,AY$6),2)) -> 0 | AZ8: =IF(OR($A8="",AZ$6=""),"",ROUND(SUMIFS(流水支出,流水账户,$A8,流水日期,AZ$6),2)) -> 200 | BA8: =IF(OR($A8="",BA$6=""),"",ROUND(SUMIFS(流水收入,流水账户,$A8,流水日期,BA$6),2)) -> 0 | BB8: =IF(OR($A8="",BB$6=""),"",ROUND(SUMIFS(流水支出,流水账户,$A8,流水日期,BB$6),2)) -> 0 | BC8: =IF(OR($A8="",BC$6=""),"",ROUND(SUMIFS(流水收入,流水账户,$A8,流水日期,BC$6),2)) -> 0 | BD8: =IF(OR($A8="",BD$6=""),"",ROUND(SUMIFS(流水支出,流水账户,$A8,流水日期,BD$6),2)) -> 0 | BE8: =IF(OR($A8="",BE$6=""),"",ROUND(SUMIFS(流水收入,流水账户,$A8,流水日期,BE$6),2)) -> 0 | BF8: =IF(OR($A8="",BF$6=""),"",ROUND(SUMIFS(流水支出,流水账户,$A8,流水日期,BF$6),2)) -> 0 | BG8: =IF(OR($A8="",BG$6=""),"",ROUND(SUMIFS(流水收入,流水账户,$A8,流水日期,BG$6),2)) -> 0 | BH8: =IF(OR($A8="",BH$6=""),"",ROUND(SUMIFS(流水支出,流水账户,$A8,流水日期,BH$6),2)) -> 0 | BI8: =IF(OR($A8="",BI$6=""),"",ROUND(SUMIFS(流水收入,流水账户,$A8,流水日期,BI$6),2)) -> 2000 | BJ8: =IF(OR($A8="",BJ$6=""),"",ROUND(SUMIFS(流水支出,流水账户,$A8,流水日期,BJ$6),2)) -> 0 | BK8: =IF(OR($A8="",BK$6=""),"",ROUND(SUMIFS(流水收入,流水账户,$A8,流水日期,BK$6),2)) | BL8: =IF(OR($A8="",BL$6=""),"",ROUND(SUMIFS(流水支出,流水账户,$A8,流水日期,BL$6),2)) | BM8: =IF($A8="","",ROUND(SUMIF($C$7:$BL$7,"收款",C8:BL8),2)) -> 4000 | BN8: =IF($A8="","",ROUND(SUMIF($C$7:$BL$7,"付款",C8:BL8),2)) -> 200 | BO8: =IF($A8="","",ROUND(N($B8)+N(BM8)-N(BN8),2)) -> 8800
A9: =IF(基础资料!$B$6="","",基础资料!$B$6) -> 微信 | B9: =IF(OR($A9="",NOT(ISNUMBER($H$3))),"",ROUND(SUMIF(账户表,$A9,账户期初)+SUMIFS(流水收入,流水账户,$A9,流水日期,"<"&$B$3)-SUMIFS(流水支出,流水账户,$A9,流水日期,"<"&$B$3),2)) -> 6000 | C9: =IF(OR($A9="",C$6=""),"",ROUND(SUMIFS(流水收入,流水账户,$A9,流水日期,C$6),2)) -> 0 | D9: =IF(OR($A9="",D$6=""),"",ROUND(SUMIFS(流水支出,流水账户,$A9,流水日期,D$6),2)) -> 0 | E9: =IF(OR($A9="",E$6=""),"",ROUND(SUMIFS(流水收入,流水账户,$A9,流水日期,E$6),2)) -> 0 | F9: =IF(OR($A9="",F$6=""),"",ROUND(SUMIFS(流水支出,流水账户,$A9,流水日期,F$6),2)) -> 0 | G9: =IF(OR($A9="",G$6=""),"",ROUND(SUMIFS(流水收入,流水账户,$A9,流水日期,G$6),2)) -> 0 | H9: =IF(OR($A9="",H$6=""),"",ROUND(SUMIFS(流水支出,流水账户,$A9,流水日期,H$6),2)) -> 200 | I9: =IF(OR($A9="",I$6=""),"",ROUND(SUMIFS(流水收入,流水账户,$A9,流水日期,I$6),2)) -> 0 | J9: =IF(OR($A9="",J$6=""),"",ROUND(SUMIFS(流水支出,流水账户,$A9,流水日期,J$6),2)) -> 0 | K9: =IF(OR($A9="",K$6=""),"",ROUND(SUMIFS(流水收入,流水账户,$A9,流水日期,K$6),2)) -> 0 | L9: =IF(OR($A9="",L$6=""),"",ROUND(SUMIFS(流水支出,流水账户,$A9,流水日期,L$6),2)) -> 0 | M9: =IF(OR($A9="",M$6=""),"",ROUND(SUMIFS(流水收入,流水账户,$A9,流水日期,M$6),2)) -> 0 | N9: =IF(OR($A9="",N$6=""),"",ROUND(SUMIFS(流水支出,流水账户,$A9,流水日期,N$6),2)) -> 0 | O9: =IF(OR($A9="",O$6=""),"",ROUND(SUMIFS(流水收入,流水账户,$A9,流水日期,O$6),2)) -> 0 | P9: =IF(OR($A9="",P$6=""),"",ROUND(SUMIFS(流水支出,流水账户,$A9,流水日期,P$6),2)) -> 0 | Q9: =IF(OR($A9="",Q$6=""),"",ROUND(SUMIFS(流水收入,流水账户,$A9,流水日期,Q$6),2)) -> 0 | R9: =IF(OR($A9="",R$6=""),"",ROUND(SUMIFS(流水支出,流水账户,$A9,流水日期,R$6),2)) -> 0 | S9: =IF(OR($A9="",S$6=""),"",ROUND(SUMIFS(流水收入,流水账户,$A9,流水日期,S$6),2)) -> 0 | T9: =IF(OR($A9="",T$6=""),"",ROUND(SUMIFS(流水支出,流水账户,$A9,流水日期,T$6),2)) -> 0 | U9: =IF(OR($A9="",U$6=""),"",ROUND(SUMIFS(流水收入,流水账户,$A9,流水日期,U$6),2)) -> 0 | V9: =IF(OR($A9="",V$6=""),"",ROUND(SUMIFS(流水支出,流水账户,$A9,流水日期,V$6),2)) -> 0 | W9: =IF(OR($A9="",W$6=""),"",ROUND(SUMIFS(流水收入,流水账户,$A9,流水日期,W$6),2)) -> 0 | X9: =IF(OR($A9="",X$6=""),"",ROUND(SUMIFS(流水支出,流水账户,$A9,流水日期,X$6),2)) -> 0 | Y9: =IF(OR($A9="",Y$6=""),"",ROUND(SUMIFS(流水收入,流水账户,$A9,流水日期,Y$6),2)) -> 0 | Z9: =IF(OR($A9="",Z$6=""),"",ROUND(SUMIFS(流水支出,流水账户,$A9,流水日期,Z$6),2)) -> 0 | AA9: =IF(OR($A9="",AA$6=""),"",ROUND(SUMIFS(流水收入,流水账户,$A9,流水日期,AA$6),2)) -> 0 | AB9: =IF(OR($A9="",AB$6=""),"",ROUND(SUMIFS(流水支出,流水账户,$A9,流水日期,AB$6),2)) -> 0 | AC9: =IF(OR($A9="",AC$6=""),"",ROUND(SUMIFS(流水收入,流水账户,$A9,流水日期,AC$6),2)) -> 0 | AD9: =IF(OR($A9="",AD$6=""),"",ROUND(SUMIFS(流水支出,流水账户,$A9,流水日期,AD$6),2)) -> 0 | AE9: =IF(OR($A9="",AE$6=""),"",ROUND(SUMIFS(流水收入,流水账户,$A9,流水日期,AE$6),2)) -> 0 | AF9: =IF(OR($A9="",AF$6=""),"",ROUND(SUMIFS(流水支出,流水账户,$A9,流水日期,AF$6),2)) -> 0 | AG9: =IF(OR($A9="",AG$6=""),"",ROUND(SUMIFS(流水收入,流水账户,$A9,流水日期,AG$6),2)) -> 0 | AH9: =IF(OR($A9="",AH$6=""),"",ROUND(SUMIFS(流水支出,流水账户,$A9,流水日期,AH$6),2)) -> 0 | AI9: =IF(OR($A9="",AI$6=""),"",ROUND(SUMIFS(流水收入,流水账户,$A9,流水日期,AI$6),2)) -> 0 | AJ9: =IF(OR($A9="",AJ$6=""),"",ROUND(SUMIFS(流水支出,流水账户,$A9,流水日期,AJ$6),2)) -> 0 | AK9: =IF(OR($A9="",AK$6=""),"",ROUND(SUMIFS(流水收入,流水账户,$A9,流水日期,AK$6),2)) -> 0 | AL9: =IF(OR($A9="",AL$6=""),"",ROUND(SUMIFS(流水支出,流水账户,$A9,流水日期,AL$6),2)) -> 0 | AM9: =IF(OR($A9="",AM$6=""),"",ROUND(SUMIFS(流水收入,流水账户,$A9,流水日期,AM$6),2)) -> 0 | AN9: =IF(OR($A9="",AN$6=""),"",ROUND(SUMIFS(流水支出,流水账户,$A9,流水日期,AN$6),2)) -> 0 | AO9: =IF(OR($A9="",AO$6=""),"",ROUND(SUMIFS(流水收入,流水账户,$A9,流水日期,AO$6),2)) -> 0 | AP9: =IF(OR($A9="",AP$6=""),"",ROUND(SUMIFS(流水支出,流水账户,$A9,流水日期,AP$6),2)) -> 0 | AQ9: =IF(OR($A9="",AQ$6=""),"",ROUND(SUMIFS(流水收入,流水账户,$A9,流水日期,AQ$6),2)) -> 0 | AR9: =IF(OR($A9="",AR$6=""),"",ROUND(SUMIFS(流水支出,流水账户,$A9,流水日期,AR$6),2)) -> 0 | AS9: =IF(OR($A9="",AS$6=""),"",ROUND(SUMIFS(流水收入,流水账户,$A9,流水日期,AS$6),2)) -> 0 | AT9: =IF(OR($A9="",AT$6=""),"",ROUND(SUMIFS(流水支出,流水账户,$A9,流水日期,AT$6),2)) -> 0 | AU9: =IF(OR($A9="",AU$6=""),"",ROUND(SUMIFS(流水收入,流水账户,$A9,流水日期,AU$6),2)) -> 0 | AV9: =IF(OR($A9="",AV$6=""),"",ROUND(SUMIFS(流水支出,流水账户,$A9,流水日期,AV$6),2)) -> 0 | AW9: =IF(OR($A9="",AW$6=""),"",ROUND(SUMIFS(流水收入,流水账户,$A9,流水日期,AW$6),2)) -> 0 | AX9: =IF(OR($A9="",AX$6=""),"",ROUND(SUMIFS(流水支出,流水账户,$A9,流水日期,AX$6),2)) -> 0 | AY9: =IF(OR($A9="",AY$6=""),"",ROUND(SUMIFS(流水收入,流水账户,$A9,流水日期,AY$6),2)) -> 0 | AZ9: =IF(OR($A9="",AZ$6=""),"",ROUND(SUMIFS(流水支出,流水账户,$A9,流水日期,AZ$6),2)) -> 0 | BA9: =IF(OR($A9="",BA$6=""),"",ROUND(SUMIFS(流水收入,流水账户,$A9,流水日期,BA$6),2)) -> 0 | BB9: =IF(OR($A9="",BB$6=""),"",ROUND(SUMIFS(流水支出,流水账户,$A9,流水日期,BB$6),2)) -> 0 | BC9: =IF(OR($A9="",BC$6=""),"",ROUND(SUMIFS(流水收入,流水账户,$A9,流水日期,BC$6),2)) -> 0 | BD9: =IF(OR($A9="",BD$6=""),"",ROUND(SUMIFS(流水支出,流水账户,$A9,流水日期,BD$6),2)) -> 0 | BE9: =IF(OR($A9="",BE$6=""),"",ROUND(SUMIFS(流水收入,流水账户,$A9,流水日期,BE$6),2)) -> 800 | BF9: =IF(OR($A9="",BF$6=""),"",ROUND(SUMIFS(流水支出,流水账户,$A9,流水日期,BF$6),2)) -> 0 | BG9: =IF(OR($A9="",BG$6=""),"",ROUND(SUMIFS(流水收入,流水账户,$A9,流水日期,BG$6),2)) -> 0 | BH9: =IF(OR($A9="",BH$6=""),"",ROUND(SUMIFS(流水支出,流水账户,$A9,流水日期,BH$6),2)) -> 0 | BI9: =IF(OR($A9="",BI$6=""),"",ROUND(SUMIFS(流水收入,流水账户,$A9,流水日期,BI$6),2)) -> 0 | BJ9: =IF(OR($A9="",BJ$6=""),"",ROUND(SUMIFS(流水支出,流水账户,$A9,流水日期,BJ$6),2)) -> 0 | BK9: =IF(OR($A9="",BK$6=""),"",ROUND(SUMIFS(流水收入,流水账户,$A9,流水日期,BK$6),2)) | BL9: =IF(OR($A9="",BL$6=""),"",ROUND(SUMIFS(流水支出,流水账户,$A9,流水日期,BL$6),2)) | BM9: =IF($A9="","",ROUND(SUMIF($C$7:$BL$7,"收款",C9:BL9),2)) -> 800 | BN9: =IF($A9="","",ROUND(SUMIF($C$7:$BL$7,"付款",C9:BL9),2)) -> 200 | BO9: =IF($A9="","",ROUND(N($B9)+N(BM9)-N(BN9),2)) -> 6600
A10: =IF(基础资料!$B$7="","",基础资料!$B$7) -> 工行 | B10: =IF(OR($A10="",NOT(ISNUMBER($H$3))),"",ROUND(SUMIF(账户表,$A10,账户期初)+SUMIFS(流水收入,流水账户,$A10,流水日期,"<"&$B$3)-SUMIFS(流水支出,流水账户,$A10,流水日期,"<"&$B$3),2)) -> 7000 | C10: =IF(OR($A10="",C$6=""),"",ROUND(SUMIFS(流水收入,流水账户,$A10,流水日期,C$6),2)) -> 0 | D10: =IF(OR($A10="",D$6=""),"",ROUND(SUMIFS(流水支出,流水账户,$A10,流水日期,D$6),2)) -> 0 | E10: =IF(OR($A10="",E$6=""),"",ROUND(SUMIFS(流水收入,流水账户,$A10,流水日期,E$6),2)) -> 0 | F10: =IF(OR($A10="",F$6=""),"",ROUND(SUMIFS(流水支出,流水账户,$A10,流水日期,F$6),2)) -> 0 | G10: =IF(OR($A10="",G$6=""),"",ROUND(SUMIFS(流水收入,流水账户,$A10,流水日期,G$6),2)) -> 0 | H10: =IF(OR($A10="",H$6=""),"",ROUND(SUMIFS(流水支出,流水账户,$A10,流水日期,H$6),2)) -> 0 | I10: =IF(OR($A10="",I$6=""),"",ROUND(SUMIFS(流水收入,流水账户,$A10,流水日期,I$6),2)) -> 0 | J10: =IF(OR($A10="",J$6=""),"",ROUND(SUMIFS(流水支出,流水账户,$A10,流水日期,J$6),2)) -> 0 | K10: =IF(OR($A10="",K$6=""),"",ROUND(SUMIFS(流水收入,流水账户,$A10,流水日期,K$6),2)) -> 0 | L10: =IF(OR($A10="",L$6=""),"",ROUND(SUMIFS(流水支出,流水账户,$A10,流水日期,L$6),2)) -> 300 | M10: =IF(OR($A10="",M$6=""),"",ROUND(SUMIFS(流水收入,流水账户,$A10,流水日期,M$6),2)) -> 0 | N10: =IF(OR($A10="",N$6=""),"",ROUND(SUMIFS(流水支出,流水账户,$A10,流水日期,N$6),2)) -> 0 | O10: =IF(OR($A10="",O$6=""),"",ROUND(SUMIFS(流水收入,流水账户,$A10,流水日期,O$6),2)) -> 0 | P10: =IF(OR($A10="",P$6=""),"",ROUND(SUMIFS(流水支出,流水账户,$A10,流水日期,P$6),2)) -> 0 | Q10: =IF(OR($A10="",Q$6=""),"",ROUND(SUMIFS(流水收入,流水账户,$A10,流水日期,Q$6),2)) -> 0 | R10: =IF(OR($A10="",R$6=""),"",ROUND(SUMIFS(流水支出,流水账户,$A10,流水日期,R$6),2)) -> 0 | S10: =IF(OR($A10="",S$6=""),"",ROUND(SUMIFS(流水收入,流水账户,$A10,流水日期,S$6),2)) -> 0 | T10: =IF(OR($A10="",T$6=""),"",ROUND(SUMIFS(流水支出,流水账户,$A10,流水日期,T$6),2)) -> 0 | U10: =IF(OR($A10="",U$6=""),"",ROUND(SUMIFS(流水收入,流水账户,$A10,流水日期,U$6),2)) -> 0 | V10: =IF(OR($A10="",V$6=""),"",ROUND(SUMIFS(流水支出,流水账户,$A10,流水日期,V$6),2)) -> 0 | W10: =IF(OR($A10="",W$6=""),"",ROUND(SUMIFS(流水收入,流水账户,$A10,流水日期,W$6),2)) -> 0 | X10: =IF(OR($A10="",X$6=""),"",ROUND(SUMIFS(流水支出,流水账户,$A10,流水日期,X$6),2)) -> 0 | Y10: =IF(OR($A10="",Y$6=""),"",ROUND(SUMIFS(流水收入,流水账户,$A10,流水日期,Y$6),2)) -> 0 | Z10: =IF(OR($A10="",Z$6=""),"",ROUND(SUMIFS(流水支出,流水账户,$A10,流水日期,Z$6),2)) -> 0 | AA10: =IF(OR($A10="",AA$6=""),"",ROUND(SUMIFS(流水收入,流水账户,$A10,流水日期,AA$6),2)) -> 0 | AB10: =IF(OR($A10="",AB$6=""),"",ROUND(SUMIFS(流水支出,流水账户,$A10,流水日期,AB$6),2)) -> 0 | AC10: =IF(OR($A10="",AC$6=""),"",ROUND(SUMIFS(流水收入,流水账户,$A10,流水日期,AC$6),2)) -> 0 | AD10: =IF(OR($A10="",AD$6=""),"",ROUND(SUMIFS(流水支出,流水账户,$A10,流水日期,AD$6),2)) -> 0 | AE10: =IF(OR($A10="",AE$6=""),"",ROUND(SUMIFS(流水收入,流水账户,$A10,流水日期,AE$6),2)) -> 0 | AF10: =IF(OR($A10="",AF$6=""),"",ROUND(SUMIFS(流水支出,流水账户,$A10,流水日期,AF$6),2)) -> 0 | AG10: =IF(OR($A10="",AG$6=""),"",ROUND(SUMIFS(流水收入,流水账户,$A10,流水日期,AG$6),2)) -> 0 | AH10: =IF(OR($A10="",AH$6=""),"",ROUND(SUMIFS(流水支出,流水账户,$A10,流水日期,AH$6),2)) -> 0 | AI10: =IF(OR($A10="",AI$6=""),"",ROUND(SUMIFS(流水收入,流水账户,$A10,流水日期,AI$6),2)) -> 0 | AJ10: =IF(OR($A10="",AJ$6=""),"",ROUND(SUMIFS(流水支出,流水账户,$A10,流水日期,AJ$6),2)) -> 0 | AK10: =IF(OR($A10="",AK$6=""),"",ROUND(SUMIFS(流水收入,流水账户,$A10,流水日期,AK$6),2)) -> 0 | AL10: =IF(OR($A10="",AL$6=""),"",ROUND(SUMIFS(流水支出,流水账户,$A10,流水日期,AL$6),2)) -> 0 | AM10: =IF(OR($A10="",AM$6=""),"",ROUND(SUMIFS(流水收入,流水账户,$A10,流水日期,AM$6),2)) -> 0 | AN10: =IF(OR($A10="",AN$6=""),"",ROUND(SUMIFS(流水支出,流水账户,$A10,流水日期,AN$6),2)) -> 0 | AO10: =IF(OR($A10="",AO$6=""),"",ROUND(SUMIFS(流水收入,流水账户,$A10,流水日期,AO$6),2)) -> 0 | AP10: =IF(OR($A10="",AP$6=""),"",ROUND(SUMIFS(流水支出,流水账户,$A10,流水日期,AP$6),2)) -> 0 | AQ10: =IF(OR($A10="",AQ$6=""),"",ROUND(SUMIFS(流水收入,流水账户,$A10,流水日期,AQ$6),2)) -> 0 | AR10: =IF(OR($A10="",AR$6=""),"",ROUND(SUMIFS(流水支出,流水账户,$A10,流水日期,AR$6),2)) -> 0 | AS10: =IF(OR($A10="",AS$6=""),"",ROUND(SUMIFS(流水收入,流水账户,$A10,流水日期,AS$6),2)) -> 0 | AT10: =IF(OR($A10="",AT$6=""),"",ROUND(SUMIFS(流水支出,流水账户,$A10,流水日期,AT$6),2)) -> 0 | AU10: =IF(OR($A10="",AU$6=""),"",ROUND(SUMIFS(流水收入,流水账户,$A10,流水日期,AU$6),2)) -> 0 | AV10: =IF(OR($A10="",AV$6=""),"",ROUND(SUMIFS(流水支出,流水账户,$A10,流水日期,AV$6),2)) -> 0 | AW10: =IF(OR($A10="",AW$6=""),"",ROUND(SUMIFS(流水收入,流水账户,$A10,流水日期,AW$6),2)) -> 0 | AX10: =IF(OR($A10="",AX$6=""),"",ROUND(SUMIFS(流水支出,流水账户,$A10,流水日期,AX$6),2)) -> 0 | AY10: =IF(OR($A10="",AY$6=""),"",ROUND(SUMIFS(流水收入,流水账户,$A10,流水日期,AY$6),2)) -> 0 | AZ10: =IF(OR($A10="",AZ$6=""),"",ROUND(SUMIFS(流水支出,流水账户,$A10,流水日期,AZ$6),2)) -> 0 | BA10: =IF(OR($A10="",BA$6=""),"",ROUND(SUMIFS(流水收入,流水账户,$A10,流水日期,BA$6),2)) -> 0 | BB10: =IF(OR($A10="",BB$6=""),"",ROUND(SUMIFS(流水支出,流水账户,$A10,流水日期,BB$6),2)) -> 0 | BC10: =IF(OR($A10="",BC$6=""),"",ROUND(SUMIFS(流水收入,流水账户,$A10,流水日期,BC$6),2)) -> 0 | BD10: =IF(OR($A10="",BD$6=""),"",ROUND(SUMIFS(流水支出,流水账户,$A10,流水日期,BD$6),2)) -> 0 | BE10: =IF(OR($A10="",BE$6=""),"",ROUND(SUMIFS(流水收入,流水账户,$A10,流水日期,BE$6),2)) -> 0 | BF10: =IF(OR($A10="",BF$6=""),"",ROUND(SUMIFS(流水支出,流水账户,$A10,流水日期,BF$6),2)) -> 3000 | BG10: =IF(OR($A10="",BG$6=""),"",ROUND(SUMIFS(流水收入,流水账户,$A10,流水日期,BG$6),2)) -> 0 | BH10: =IF(OR($A10="",BH$6=""),"",ROUND(SUMIFS(流水支出,流水账户,$A10,流水日期,BH$6),2)) -> 0 | BI10: =IF(OR($A10="",BI$6=""),"",ROUND(SUMIFS(流水收入,流水账户,$A10,流水日期,BI$6),2)) -> 0 | BJ10: =IF(OR($A10="",BJ$6=""),"",ROUND(SUMIFS(流水支出,流水账户,$A10,流水日期,BJ$6),2)) -> 2000 | BK10: =IF(OR($A10="",BK$6=""),"",ROUND(SUMIFS(流水收入,流水账户,$A10,流水日期,BK$6),2)) | BL10: =IF(OR($A10="",BL$6=""),"",ROUND(SUMIFS(流水支出,流水账户,$A10,流水日期,BL$6),2)) | BM10: =IF($A10="","",ROUND(SUMIF($C$7:$BL$7,"收款",C10:BL10),2)) -> 0 | BN10: =IF($A10="","",ROUND(SUMIF($C$7:$BL$7,"付款",C10:BL10),2)) -> 5300 | BO10: =IF($A10="","",ROUND(N($B10)+N(BM10)-N(BN10),2)) -> 1700
A11: =IF(基础资料!$B$8="","",基础资料!$B$8) -> 民生 | B11: =IF(OR($A11="",NOT(ISNUMBER($H$3))),"",ROUND(SUMIF(账户表,$A11,账户期初)+SUMIFS(流水收入,流水账户,$A11,流水日期,"<"&$B$3)-SUMIFS(流水支出,流水账户,$A11,流水日期,"<"&$B$3),2)) -> 8000 | C11: =IF(OR($A11="",C$6=""),"",ROUND(SUMIFS(流水收入,流水账户,$A11,流水日期,C$6),2)) -> 0 | D11: =IF(OR($A11="",D$6=""),"",ROUND(SUMIFS(流水支出,流水账户,$A11,流水日期,D$6),2)) -> 0 | E11: =IF(OR($A11="",E$6=""),"",ROUND(SUMIFS(流水收入,流水账户,$A11,流水日期,E$6),2)) -> 0 | F11: =IF(OR($A11="",F$6=""),"",ROUND(SUMIFS(流水支出,流水账户,$A11,流水日期,F$6),2)) -> 0 | G11: =IF(OR($A11="",G$6=""),"",ROUND(SUMIFS(流水收入,流水账户,$A11,流水日期,G$6),2)) -> 0 | H11: =IF(OR($A11="",H$6=""),"",ROUND(SUMIFS(流水支出,流水账户,$A11,流水日期,H$6),2)) -> 0 | I11: =IF(OR($A11="",I$6=""),"",ROUND(SUMIFS(流水收入,流水账户,$A11,流水日期,I$6),2)) -> 0 | J11: =IF(OR($A11="",J$6=""),"",ROUND(SUMIFS(流水支出,流水账户,$A11,流水日期,J$6),2)) -> 0 | K11: =IF(OR($A11="",K$6=""),"",ROUND(SUMIFS(流水收入,流水账户,$A11,流水日期,K$6),2)) -> 0 | L11: =IF(OR($A11="",L$6=""),"",ROUND(SUMIFS(流水支出,流水账户,$A11,流水日期,L$6),2)) -> 0 | M11: =IF(OR($A11="",M$6=""),"",ROUND(SUMIFS(流水收入,流水账户,$A11,流水日期,M$6),2)) -> 0 | N11: =IF(OR($A11="",N$6=""),"",ROUND(SUMIFS(流水支出,流水账户,$A11,流水日期,N$6),2)) -> 500 | O11: =IF(OR($A11="",O$6=""),"",ROUND(SUMIFS(流水收入,流水账户,$A11,流水日期,O$6),2)) -> 0 | P11: =IF(OR($A11="",P$6=""),"",ROUND(SUMIFS(流水支出,流水账户,$A11,流水日期,P$6),2)) -> 0 | Q11: =IF(OR($A11="",Q$6=""),"",ROUND(SUMIFS(流水收入,流水账户,$A11,流水日期,Q$6),2)) -> 0 | R11: =IF(OR($A11="",R$6=""),"",ROUND(SUMIFS(流水支出,流水账户,$A11,流水日期,R$6),2)) -> 0 | S11: =IF(OR($A11="",S$6=""),"",ROUND(SUMIFS(流水收入,流水账户,$A11,流水日期,S$6),2)) -> 0 | T11: =IF(OR($A11="",T$6=""),"",ROUND(SUMIFS(流水支出,流水账户,$A11,流水日期,T$6),2)) -> 0 | U11: =IF(OR($A11="",U$6=""),"",ROUND(SUMIFS(流水收入,流水账户,$A11,流水日期,U$6),2)) -> 0 | V11: =IF(OR($A11="",V$6=""),"",ROUND(SUMIFS(流水支出,流水账户,$A11,流水日期,V$6),2)) -> 0 | W11: =IF(OR($A11="",W$6=""),"",ROUND(SUMIFS(流水收入,流水账户,$A11,流水日期,W$6),2)) -> 0 | X11: =IF(OR($A11="",X$6=""),"",ROUND(SUMIFS(流水支出,流水账户,$A11,流水日期,X$6),2)) -> 0 | Y11: =IF(OR($A11="",Y$6=""),"",ROUND(SUMIFS(流水收入,流水账户,$A11,流水日期,Y$6),2)) -> 0 | Z11: =IF(OR($A11="",Z$6=""),"",ROUND(SUMIFS(流水支出,流水账户,$A11,流水日期,Z$6),2)) -> 0 | AA11: =IF(OR($A11="",AA$6=""),"",ROUND(SUMIFS(流水收入,流水账户,$A11,流水日期,AA$6),2)) -> 0 | AB11: =IF(OR($A11="",AB$6=""),"",ROUND(SUMIFS(流水支出,流水账户,$A11,流水日期,AB$6),2)) -> 0 | AC11: =IF(OR($A11="",AC$6=""),"",ROUND(SUMIFS(流水收入,流水账户,$A11,流水日期,AC$6),2)) -> 0 | AD11: =IF(OR($A11="",AD$6=""),"",ROUND(SUMIFS(流水支出,流水账户,$A11,流水日期,AD$6),2)) -> 0 | AE11: =IF(OR($A11="",AE$6=""),"",ROUND(SUMIFS(流水收入,流水账户,$A11,流水日期,AE$6),2)) -> 0 | AF11: =IF(OR($A11="",AF$6=""),"",ROUND(SUMIFS(流水支出,流水账户,$A11,流水日期,AF$6),2)) -> 0 | AG11: =IF(OR($A11="",AG$6=""),"",ROUND(SUMIFS(流水收入,流水账户,$A11,流水日期,AG$6),2)) -> 0 | AH11: =IF(OR($A11="",AH$6=""),"",ROUND(SUMIFS(流水支出,流水账户,$A11,流水日期,AH$6),2)) -> 0 | AI11: =IF(OR($A11="",AI$6=""),"",ROUND(SUMIFS(流水收入,流水账户,$A11,流水日期,AI$6),2)) -> 0 | AJ11: =IF(OR($A11="",AJ$6=""),"",ROUND(SUMIFS(流水支出,流水账户,$A11,流水日期,AJ$6),2)) -> 0 | AK11: =IF(OR($A11="",AK$6=""),"",ROUND(SUMIFS(流水收入,流水账户,$A11,流水日期,AK$6),2)) -> 0 | AL11: =IF(OR($A11="",AL$6=""),"",ROUND(SUMIFS(流水支出,流水账户,$A11,流水日期,AL$6),2)) -> 0 | AM11: =IF(OR($A11="",AM$6=""),"",ROUND(SUMIFS(流水收入,流水账户,$A11,流水日期,AM$6),2)) -> 0 | AN11: =IF(OR($A11="",AN$6=""),"",ROUND(SUMIFS(流水支出,流水账户,$A11,流水日期,AN$6),2)) -> 0 | AO11: =IF(OR($A11="",AO$6=""),"",ROUND(SUMIFS(流水收入,流水账户,$A11,流水日期,AO$6),2)) -> 0 | AP11: =IF(OR($A11="",AP$6=""),"",ROUND(SUMIFS(流水支出,流水账户,$A11,流水日期,AP$6),2)) -> 0 | AQ11: =IF(OR($A11="",AQ$6=""),"",ROUND(SUMIFS(流水收入,流水账户,$A11,流水日期,AQ$6),2)) -> 0 | AR11: =IF(OR($A11="",AR$6=""),"",ROUND(SUMIFS(流水支出,流水账户,$A11,流水日期,AR$6),2)) -> 0 | AS11: =IF(OR($A11="",AS$6=""),"",ROUND(SUMIFS(流水收入,流水账户,$A11,流水日期,AS$6),2)) -> 0 | AT11: =IF(OR($A11="",AT$6=""),"",ROUND(SUMIFS(流水支出,流水账户,$A11,流水日期,AT$6),2)) -> 0 | AU11: =IF(OR($A11="",AU$6=""),"",ROUND(SUMIFS(流水收入,流水账户,$A11,流水日期,AU$6),2)) -> 0 | AV11: =IF(OR($A11="",AV$6=""),"",ROUND(SUMIFS(流水支出,流水账户,$A11,流水日期,AV$6),2)) -> 0 | AW11: =IF(OR($A11="",AW$6=""),"",ROUND(SUMIFS(流水收入,流水账户,$A11,流水日期,AW$6),2)) -> 0 | AX11: =IF(OR($A11="",AX$6=""),"",ROUND(SUMIFS(流水支出,流水账户,$A11,流水日期,AX$6),2)) -> 0 | AY11: =IF(OR($A11="",AY$6=""),"",ROUND(SUMIFS(流水收入,流水账户,$A11,流水日期,AY$6),2)) -> 0 | AZ11: =IF(OR($A11="",AZ$6=""),"",ROUND(SUMIFS(流水支出,流水账户,$A11,流水日期,AZ$6),2)) -> 0 | BA11: =IF(OR($A11="",BA$6=""),"",ROUND(SUMIFS(流水收入,流水账户,$A11,流水日期,BA$6),2)) -> 0 | BB11: =IF(OR($A11="",BB$6=""),"",ROUND(SUMIFS(流水支出,流水账户,$A11,流水日期,BB$6),2)) -> 0 | BC11: =IF(OR($A11="",BC$6=""),"",ROUND(SUMIFS(流水收入,流水账户,$A11,流水日期,BC$6),2)) -> 0 | BD11: =IF(OR($A11="",BD$6=""),"",ROUND(SUMIFS(流水支出,流水账户,$A11,流水日期,BD$6),2)) -> 0 | BE11: =IF(OR($A11="",BE$6=""),"",ROUND(SUMIFS(流水收入,流水账户,$A11,流水日期,BE$6),2)) -> 0 | BF11: =IF(OR($A11="",BF$6=""),"",ROUND(SUMIFS(流水支出,流水账户,$A11,流水日期,BF$6),2)) -> 0 | BG11: =IF(OR($A11="",BG$6=""),"",ROUND(SUMIFS(流水收入,流水账户,$A11,流水日期,BG$6),2)) -> 0 | BH11: =IF(OR($A11="",BH$6=""),"",ROUND(SUMIFS(流水支出,流水账户,$A11,流水日期,BH$6),2)) -> 120 | BI11: =IF(OR($A11="",BI$6=""),"",ROUND(SUMIFS(流水收入,流水账户,$A11,流水日期,BI$6),2)) -> 0 | BJ11: =IF(OR($A11="",BJ$6=""),"",ROUND(SUMIFS(流水支出,流水账户,$A11,流水日期,BJ$6),2)) -> 0 | BK11: =IF(OR($A11="",BK$6=""),"",ROUND(SUMIFS(流水收入,流水账户,$A11,流水日期,BK$6),2)) | BL11: =IF(OR($A11="",BL$6=""),"",ROUND(SUMIFS(流水支出,流水账户,$A11,流水日期,BL$6),2)) | BM11: =IF($A11="","",ROUND(SUMIF($C$7:$BL$7,"收款",C11:BL11),2)) -> 0 | BN11: =IF($A11="","",ROUND(SUMIF($C$7:$BL$7,"付款",C11:BL11),2)) -> 620 | BO11: =IF($A11="","",ROUND(N($B11)+N(BM11)-N(BN11),2)) -> 7380
A12: =IF(基础资料!$B$9="","",基础资料!$B$9) -> 建行 | B12: =IF(OR($A12="",NOT(ISNUMBER($H$3))),"",ROUND(SUMIF(账户表,$A12,账户期初)+SUMIFS(流水收入,流水账户,$A12,流水日期,"<"&$B$3)-SUMIFS(流水支出,流水账户,$A12,流水日期,"<"&$B$3),2)) -> 9000 | C12: =IF(OR($A12="",C$6=""),"",ROUND(SUMIFS(流水收入,流水账户,$A12,流水日期,C$6),2)) -> 0 | D12: =IF(OR($A12="",D$6=""),"",ROUND(SUMIFS(流水支出,流水账户,$A12,流水日期,D$6),2)) -> 0 | E12: =IF(OR($A12="",E$6=""),"",ROUND(SUMIFS(流水收入,流水账户,$A12,流水日期,E$6),2)) -> 0 | F12: =IF(OR($A12="",F$6=""),"",ROUND(SUMIFS(流水支出,流水账户,$A12,流水日期,F$6),2)) -> 0 | G12: =IF(OR($A12="",G$6=""),"",ROUND(SUMIFS(流水收入,流水账户,$A12,流水日期,G$6),2)) -> 0 | H12: =IF(OR($A12="",H$6=""),"",ROUND(SUMIFS(流水支出,流水账户,$A12,流水日期,H$6),2)) -> 0 | I12: =IF(OR($A12="",I$6=""),"",ROUND(SUMIFS(流水收入,流水账户,$A12,流水日期,I$6),2)) -> 0 | J12: =IF(OR($A12="",J$6=""),"",ROUND(SUMIFS(流水支出,流水账户,$A12,流水日期,J$6),2)) -> 0 | K12: =IF(OR($A12="",K$6=""),"",ROUND(SUMIFS(流水收入,流水账户,$A12,流水日期,K$6),2)) -> 0 | L12: =IF(OR($A12="",L$6=""),"",ROUND(SUMIFS(流水支出,流水账户,$A12,流水日期,L$6),2)) -> 0 | M12: =IF(OR($A12="",M$6=""),"",ROUND(SUMIFS(流水收入,流水账户,$A12,流水日期,M$6),2)) -> 0 | N12: =IF(OR($A12="",N$6=""),"",ROUND(SUMIFS(流水支出,流水账户,$A12,流水日期,N$6),2)) -> 0 | O12: =IF(OR($A12="",O$6=""),"",ROUND(SUMIFS(流水收入,流水账户,$A12,流水日期,O$6),2)) -> 0 | P12: =IF(OR($A12="",P$6=""),"",ROUND(SUMIFS(流水支出,流水账户,$A12,流水日期,P$6),2)) -> 0 | Q12: =IF(OR($A12="",Q$6=""),"",ROUND(SUMIFS(流水收入,流水账户,$A12,流水日期,Q$6),2)) -> 0 | R12: =IF(OR($A12="",R$6=""),"",ROUND(SUMIFS(流水支出,流水账户,$A12,流水日期,R$6),2)) -> 0 | S12: =IF(OR($A12="",S$6=""),"",ROUND(SUMIFS(流水收入,流水账户,$A12,流水日期,S$6),2)) -> 0 | T12: =IF(OR($A12="",T$6=""),"",ROUND(SUMIFS(流水支出,流水账户,$A12,流水日期,T$6),2)) -> 0 | U12: =IF(OR($A12="",U$6=""),"",ROUND(SUMIFS(流水收入,流水账户,$A12,流水日期,U$6),2)) -> 2600 | V12: =IF(OR($A12="",V$6=""),"",ROUND(SUMIFS(流水支出,流水账户,$A12,流水日期,V$6),2)) -> 0 | W12: =IF(OR($A12="",W$6=""),"",ROUND(SUMIFS(流水收入,流水账户,$A12,流水日期,W$6),2)) -> 0 | X12: =IF(OR($A12="",X$6=""),"",ROUND(SUMIFS(流水支出,流水账户,$A12,流水日期,X$6),2)) -> 0 | Y12: =IF(OR($A12="",Y$6=""),"",ROUND(SUMIFS(流水收入,流水账户,$A12,流水日期,Y$6),2)) -> 0 | Z12: =IF(OR($A12="",Z$6=""),"",ROUND(SUMIFS(流水支出,流水账户,$A12,流水日期,Z$6),2)) -> 0 | AA12: =IF(OR($A12="",AA$6=""),"",ROUND(SUMIFS(流水收入,流水账户,$A12,流水日期,AA$6),2)) -> 0 | AB12: =IF(OR($A12="",AB$6=""),"",ROUND(SUMIFS(流水支出,流水账户,$A12,流水日期,AB$6),2)) -> 0 | AC12: =IF(OR($A12="",AC$6=""),"",ROUND(SUMIFS(流水收入,流水账户,$A12,流水日期,AC$6),2)) -> 0 | AD12: =IF(OR($A12="",AD$6=""),"",ROUND(SUMIFS(流水支出,流水账户,$A12,流水日期,AD$6),2)) -> 0 | AE12: =IF(OR($A12="",AE$6=""),"",ROUND(SUMIFS(流水收入,流水账户,$A12,流水日期,AE$6),2)) -> 0 | AF12: =IF(OR($A12="",AF$6=""),"",ROUND(SUMIFS(流水支出,流水账户,$A12,流水日期,AF$6),2)) -> 0 | AG12: =IF(OR($A12="",AG$6=""),"",ROUND(SUMIFS(流水收入,流水账户,$A12,流水日期,AG$6),2)) -> 0 | AH12: =IF(OR($A12="",AH$6=""),"",ROUND(SUMIFS(流水支出,流水账户,$A12,流水日期,AH$6),2)) -> 0 | AI12: =IF(OR($A12="",AI$6=""),"",ROUND(SUMIFS(流水收入,流水账户,$A12,流水日期,AI$6),2)) -> 0 | AJ12: =IF(OR($A12="",AJ$6=""),"",ROUND(SUMIFS(流水支出,流水账户,$A12,流水日期,AJ$6),2)) -> 0 | AK12: =IF(OR($A12="",AK$6=""),"",ROUND(SUMIFS(流水收入,流水账户,$A12,流水日期,AK$6),2)) -> 0 | AL12: =IF(OR($A12="",AL$6=""),"",ROUND(SUMIFS(流水支出,流水账户,$A12,流水日期,AL$6),2)) -> 0 | AM12: =IF(OR($A12="",AM$6=""),"",ROUND(SUMIFS(流水收入,流水账户,$A12,流水日期,AM$6),2)) -> 0 | AN12: =IF(OR($A12="",AN$6=""),"",ROUND(SUMIFS(流水支出,流水账户,$A12,流水日期,AN$6),2)) -> 0 | AO12: =IF(OR($A12="",AO$6=""),"",ROUND(SUMIFS(流水收入,流水账户,$A12,流水日期,AO$6),2)) -> 0 | AP12: =IF(OR($A12="",AP$6=""),"",ROUND(SUMIFS(流水支出,流水账户,$A12,流水日期,AP$6),2)) -> 0 | AQ12: =IF(OR($A12="",AQ$6=""),"",ROUND(SUMIFS(流水收入,流水账户,$A12,流水日期,AQ$6),2)) -> 0 | AR12: =IF(OR($A12="",AR$6=""),"",ROUND(SUMIFS(流水支出,流水账户,$A12,流水日期,AR$6),2)) -> 0 | AS12: =IF(OR($A12="",AS$6=""),"",ROUND(SUMIFS(流水收入,流水账户,$A12,流水日期,AS$6),2)) -> 0 | AT12: =IF(OR($A12="",AT$6=""),"",ROUND(SUMIFS(流水支出,流水账户,$A12,流水日期,AT$6),2)) -> 0 | AU12: =IF(OR($A12="",AU$6=""),"",ROUND(SUMIFS(流水收入,流水账户,$A12,流水日期,AU$6),2)) -> 0 | AV12: =IF(OR($A12="",AV$6=""),"",ROUND(SUMIFS(流水支出,流水账户,$A12,流水日期,AV$6),2)) -> 0 | AW12: =IF(OR($A12="",AW$6=""),"",ROUND(SUMIFS(流水收入,流水账户,$A12,流水日期,AW$6),2)) -> 0 | AX12: =IF(OR($A12="",AX$6=""),"",ROUND(SUMIFS(流水支出,流水账户,$A12,流水日期,AX$6),2)) -> 0 | AY12: =IF(OR($A12="",AY$6=""),"",ROUND(SUMIFS(流水收入,流水账户,$A12,流水日期,AY$6),2)) -> 0 | AZ12: =IF(OR($A12="",AZ$6=""),"",ROUND(SUMIFS(流水支出,流水账户,$A12,流水日期,AZ$6),2)) -> 0 | BA12: =IF(OR($A12="",BA$6=""),"",ROUND(SUMIFS(流水收入,流水账户,$A12,流水日期,BA$6),2)) -> 0 | BB12: =IF(OR($A12="",BB$6=""),"",ROUND(SUMIFS(流水支出,流水账户,$A12,流水日期,BB$6),2)) -> 0 | BC12: =IF(OR($A12="",BC$6=""),"",ROUND(SUMIFS(流水收入,流水账户,$A12,流水日期,BC$6),2)) -> 0 | BD12: =IF(OR($A12="",BD$6=""),"",ROUND(SUMIFS(流水支出,流水账户,$A12,流水日期,BD$6),2)) -> 0 | BE12: =IF(OR($A12="",BE$6=""),"",ROUND(SUMIFS(流水收入,流水账户,$A12,流水日期,BE$6),2)) -> 0 | BF12: =IF(OR($A12="",BF$6=""),"",ROUND(SUMIFS(流水支出,流水账户,$A12,流水日期,BF$6),2)) -> 0 | BG12: =IF(OR($A12="",BG$6=""),"",ROUND(SUMIFS(流水收入,流水账户,$A12,流水日期,BG$6),2)) -> 0 | BH12: =IF(OR($A12="",BH$6=""),"",ROUND(SUMIFS(流水支出,流水账户,$A12,流水日期,BH$6),2)) -> 30 | BI12: =IF(OR($A12="",BI$6=""),"",ROUND(SUMIFS(流水收入,流水账户,$A12,流水日期,BI$6),2)) -> 0 | BJ12: =IF(OR($A12="",BJ$6=""),"",ROUND(SUMIFS(流水支出,流水账户,$A12,流水日期,BJ$6),2)) -> 0 | BK12: =IF(OR($A12="",BK$6=""),"",ROUND(SUMIFS(流水收入,流水账户,$A12,流水日期,BK$6),2)) | BL12: =IF(OR($A12="",BL$6=""),"",ROUND(SUMIFS(流水支出,流水账户,$A12,流水日期,BL$6),2)) | BM12: =IF($A12="","",ROUND(SUMIF($C$7:$BL$7,"收款",C12:BL12),2)) -> 2600 | BN12: =IF($A12="","",ROUND(SUMIF($C$7:$BL$7,"付款",C12:BL12),2)) -> 30 | BO12: =IF($A12="","",ROUND(N($B12)+N(BM12)-N(BN12),2)) -> 11570
A13: =IF(基础资料!$B$10="","",基础资料!$B$10) -> 农行 | B13: =IF(OR($A13="",NOT(ISNUMBER($H$3))),"",ROUND(SUMIF(账户表,$A13,账户期初)+SUMIFS(流水收入,流水账户,$A13,流水日期,"<"&$B$3)-SUMIFS(流水支出,流水账户,$A13,流水日期,"<"&$B$3),2)) -> 10000 | C13: =IF(OR($A13="",C$6=""),"",ROUND(SUMIFS(流水收入,流水账户,$A13,流水日期,C$6),2)) -> 0 | D13: =IF(OR($A13="",D$6=""),"",ROUND(SUMIFS(流水支出,流水账户,$A13,流水日期,D$6),2)) -> 0 | E13: =IF(OR($A13="",E$6=""),"",ROUND(SUMIFS(流水收入,流水账户,$A13,流水日期,E$6),2)) -> 0 | F13: =IF(OR($A13="",F$6=""),"",ROUND(SUMIFS(流水支出,流水账户,$A13,流水日期,F$6),2)) -> 0 | G13: =IF(OR($A13="",G$6=""),"",ROUND(SUMIFS(流水收入,流水账户,$A13,流水日期,G$6),2)) -> 0 | H13: =IF(OR($A13="",H$6=""),"",ROUND(SUMIFS(流水支出,流水账户,$A13,流水日期,H$6),2)) -> 0 | I13: =IF(OR($A13="",I$6=""),"",ROUND(SUMIFS(流水收入,流水账户,$A13,流水日期,I$6),2)) -> 0 | J13: =IF(OR($A13="",J$6=""),"",ROUND(SUMIFS(流水支出,流水账户,$A13,流水日期,J$6),2)) -> 0 | K13: =IF(OR($A13="",K$6=""),"",ROUND(SUMIFS(流水收入,流水账户,$A13,流水日期,K$6),2)) -> 0 | L13: =IF(OR($A13="",L$6=""),"",ROUND(SUMIFS(流水支出,流水账户,$A13,流水日期,L$6),2)) -> 0 | M13: =IF(OR($A13="",M$6=""),"",ROUND(SUMIFS(流水收入,流水账户,$A13,流水日期,M$6),2)) -> 0 | N13: =IF(OR($A13="",N$6=""),"",ROUND(SUMIFS(流水支出,流水账户,$A13,流水日期,N$6),2)) -> 0 | O13: =IF(OR($A13="",O$6=""),"",ROUND(SUMIFS(流水收入,流水账户,$A13,流水日期,O$6),2)) -> 0 | P13: =IF(OR($A13="",P$6=""),"",ROUND(SUMIFS(流水支出,流水账户,$A13,流水日期,P$6),2)) -> 0 | Q13: =IF(OR($A13="",Q$6=""),"",ROUND(SUMIFS(流水收入,流水账户,$A13,流水日期,Q$6),2)) -> 0 | R13: =IF(OR($A13="",R$6=""),"",ROUND(SUMIFS(流水支出,流水账户,$A13,流水日期,R$6),2)) -> 0 | S13: =IF(OR($A13="",S$6=""),"",ROUND(SUMIFS(流水收入,流水账户,$A13,流水日期,S$6),2)) -> 0 | T13: =IF(OR($A13="",T$6=""),"",ROUND(SUMIFS(流水支出,流水账户,$A13,流水日期,T$6),2)) -> 0 | U13: =IF(OR($A13="",U$6=""),"",ROUND(SUMIFS(流水收入,流水账户,$A13,流水日期,U$6),2)) -> 0 | V13: =IF(OR($A13="",V$6=""),"",ROUND(SUMIFS(流水支出,流水账户,$A13,流水日期,V$6),2)) -> 0 | W13: =IF(OR($A13="",W$6=""),"",ROUND(SUMIFS(流水收入,流水账户,$A13,流水日期,W$6),2)) -> 0 | X13: =IF(OR($A13="",X$6=""),"",ROUND(SUMIFS(流水支出,流水账户,$A13,流水日期,X$6),2)) -> 0 | Y13: =IF(OR($A13="",Y$6=""),"",ROUND(SUMIFS(流水收入,流水账户,$A13,流水日期,Y$6),2)) -> 0 | Z13: =IF(OR($A13="",Z$6=""),"",ROUND(SUMIFS(流水支出,流水账户,$A13,流水日期,Z$6),2)) -> 5000 | AA13: =IF(OR($A13="",AA$6=""),"",ROUND(SUMIFS(流水收入,流水账户,$A13,流水日期,AA$6),2)) -> 0 | AB13: =IF(OR($A13="",AB$6=""),"",ROUND(SUMIFS(流水支出,流水账户,$A13,流水日期,AB$6),2)) -> 0 | AC13: =IF(OR($A13="",AC$6=""),"",ROUND(SUMIFS(流水收入,流水账户,$A13,流水日期,AC$6),2)) -> 0 | AD13: =IF(OR($A13="",AD$6=""),"",ROUND(SUMIFS(流水支出,流水账户,$A13,流水日期,AD$6),2)) -> 0 | AE13: =IF(OR($A13="",AE$6=""),"",ROUND(SUMIFS(流水收入,流水账户,$A13,流水日期,AE$6),2)) -> 0 | AF13: =IF(OR($A13="",AF$6=""),"",ROUND(SUMIFS(流水支出,流水账户,$A13,流水日期,AF$6),2)) -> 0 | AG13: =IF(OR($A13="",AG$6=""),"",ROUND(SUMIFS(流水收入,流水账户,$A13,流水日期,AG$6),2)) -> 0 | AH13: =IF(OR($A13="",AH$6=""),"",ROUND(SUMIFS(流水支出,流水账户,$A13,流水日期,AH$6),2)) -> 0 | AI13: =IF(OR($A13="",AI$6=""),"",ROUND(SUMIFS(流水收入,流水账户,$A13,流水日期,AI$6),2)) -> 0 | AJ13: =IF(OR($A13="",AJ$6=""),"",ROUND(SUMIFS(流水支出,流水账户,$A13,流水日期,AJ$6),2)) -> 0 | AK13: =IF(OR($A13="",AK$6=""),"",ROUND(SUMIFS(流水收入,流水账户,$A13,流水日期,AK$6),2)) -> 0 | AL13: =IF(OR($A13="",AL$6=""),"",ROUND(SUMIFS(流水支出,流水账户,$A13,流水日期,AL$6),2)) -> 0 | AM13: =IF(OR($A13="",AM$6=""),"",ROUND(SUMIFS(流水收入,流水账户,$A13,流水日期,AM$6),2)) -> 0 | AN13: =IF(OR($A13="",AN$6=""),"",ROUND(SUMIFS(流水支出,流水账户,$A13,流水日期,AN$6),2)) -> 0 | AO13: =IF(OR($A13="",AO$6=""),"",ROUND(SUMIFS(流水收入,流水账户,$A13,流水日期,AO$6),2)) -> 0 | AP13: =IF(OR($A13="",AP$6=""),"",ROUND(SUMIFS(流水支出,流水账户,$A13,流水日期,AP$6),2)) -> 0 | AQ13: =IF(OR($A13="",AQ$6=""),"",ROUND(SUMIFS(流水收入,流水账户,$A13,流水日期,AQ$6),2)) -> 0 | AR13: =IF(OR($A13="",AR$6=""),"",ROUND(SUMIFS(流水支出,流水账户,$A13,流水日期,AR$6),2)) -> 0 | AS13: =IF(OR($A13="",AS$6=""),"",ROUND(SUMIFS(流水收入,流水账户,$A13,流水日期,AS$6),2)) -> 0 | AT13: =IF(OR($A13="",AT$6=""),"",ROUND(SUMIFS(流水支出,流水账户,$A13,流水日期,AT$6),2)) -> 0 | AU13: =IF(OR($A13="",AU$6=""),"",ROUND(SUMIFS(流水收入,流水账户,$A13,流水日期,AU$6),2)) -> 0 | AV13: =IF(OR($A13="",AV$6=""),"",ROUND(SUMIFS(流水支出,流水账户,$A13,流水日期,AV$6),2)) -> 0 | AW13: =IF(OR($A13="",AW$6=""),"",ROUND(SUMIFS(流水收入,流水账户,$A13,流水日期,AW$6),2)) -> 0 | AX13: =IF(OR($A13="",AX$6=""),"",ROUND(SUMIFS(流水支出,流水账户,$A13,流水日期,AX$6),2)) -> 0 | AY13: =IF(OR($A13="",AY$6=""),"",ROUND(SUMIFS(流水收入,流水账户,$A13,流水日期,AY$6),2)) -> 0 | AZ13: =IF(OR($A13="",AZ$6=""),"",ROUND(SUMIFS(流水支出,流水账户,$A13,流水日期,AZ$6),2)) -> 0 | BA13: =IF(OR($A13="",BA$6=""),"",ROUND(SUMIFS(流水收入,流水账户,$A13,流水日期,BA$6),2)) -> 0 | BB13: =IF(OR($A13="",BB$6=""),"",ROUND(SUMIFS(流水支出,流水账户,$A13,流水日期,BB$6),2)) -> 0 | BC13: =IF(OR($A13="",BC$6=""),"",ROUND(SUMIFS(流水收入,流水账户,$A13,流水日期,BC$6),2)) -> 0 | BD13: =IF(OR($A13="",BD$6=""),"",ROUND(SUMIFS(流水支出,流水账户,$A13,流水日期,BD$6),2)) -> 0 | BE13: =IF(OR($A13="",BE$6=""),"",ROUND(SUMIFS(流水收入,流水账户,$A13,流水日期,BE$6),2)) -> 0 | BF13: =IF(OR($A13="",BF$6=""),"",ROUND(SUMIFS(流水支出,流水账户,$A13,流水日期,BF$6),2)) -> 0 | BG13: =IF(OR($A13="",BG$6=""),"",ROUND(SUMIFS(流水收入,流水账户,$A13,流水日期,BG$6),2)) -> 0 | BH13: =IF(OR($A13="",BH$6=""),"",ROUND(SUMIFS(流水支出,流水账户,$A13,流水日期,BH$6),2)) -> 0 | BI13: =IF(OR($A13="",BI$6=""),"",ROUND(SUMIFS(流水收入,流水账户,$A13,流水日期,BI$6),2)) -> 4200 | BJ13: =IF(OR($A13="",BJ$6=""),"",ROUND(SUMIFS(流水支出,流水账户,$A13,流水日期,BJ$6),2)) -> 0 | BK13: =IF(OR($A13="",BK$6=""),"",ROUND(SUMIFS(流水收入,流水账户,$A13,流水日期,BK$6),2)) | BL13: =IF(OR($A13="",BL$6=""),"",ROUND(SUMIFS(流水支出,流水账户,$A13,流水日期,BL$6),2)) | BM13: =IF($A13="","",ROUND(SUMIF($C$7:$BL$7,"收款",C13:BL13),2)) -> 4200 | BN13: =IF($A13="","",ROUND(SUMIF($C$7:$BL$7,"付款",C13:BL13),2)) -> 5000 | BO13: =IF($A13="","",ROUND(N($B13)+N(BM13)-N(BN13),2)) -> 9200
A14: =IF(基础资料!$B$11="","",基础资料!$B$11) -> 中行 | B14: =IF(OR($A14="",NOT(ISNUMBER($H$3))),"",ROUND(SUMIF(账户表,$A14,账户期初)+SUMIFS(流水收入,流水账户,$A14,流水日期,"<"&$B$3)-SUMIFS(流水支出,流水账户,$A14,流水日期,"<"&$B$3),2)) -> 11000 | C14: =IF(OR($A14="",C$6=""),"",ROUND(SUMIFS(流水收入,流水账户,$A14,流水日期,C$6),2)) -> 0 | D14: =IF(OR($A14="",D$6=""),"",ROUND(SUMIFS(流水支出,流水账户,$A14,流水日期,D$6),2)) -> 0 | E14: =IF(OR($A14="",E$6=""),"",ROUND(SUMIFS(流水收入,流水账户,$A14,流水日期,E$6),2)) -> 0 | F14: =IF(OR($A14="",F$6=""),"",ROUND(SUMIFS(流水支出,流水账户,$A14,流水日期,F$6),2)) -> 0 | G14: =IF(OR($A14="",G$6=""),"",ROUND(SUMIFS(流水收入,流水账户,$A14,流水日期,G$6),2)) -> 0 | H14: =IF(OR($A14="",H$6=""),"",ROUND(SUMIFS(流水支出,流水账户,$A14,流水日期,H$6),2)) -> 0 | I14: =IF(OR($A14="",I$6=""),"",ROUND(SUMIFS(流水收入,流水账户,$A14,流水日期,I$6),2)) -> 0 | J14: =IF(OR($A14="",J$6=""),"",ROUND(SUMIFS(流水支出,流水账户,$A14,流水日期,J$6),2)) -> 0 | K14: =IF(OR($A14="",K$6=""),"",ROUND(SUMIFS(流水收入,流水账户,$A14,流水日期,K$6),2)) -> 0 | L14: =IF(OR($A14="",L$6=""),"",ROUND(SUMIFS(流水支出,流水账户,$A14,流水日期,L$6),2)) -> 0 | M14: =IF(OR($A14="",M$6=""),"",ROUND(SUMIFS(流水收入,流水账户,$A14,流水日期,M$6),2)) -> 0 | N14: =IF(OR($A14="",N$6=""),"",ROUND(SUMIFS(流水支出,流水账户,$A14,流水日期,N$6),2)) -> 0 | O14: =IF(OR($A14="",O$6=""),"",ROUND(SUMIFS(流水收入,流水账户,$A14,流水日期,O$6),2)) -> 0 | P14: =IF(OR($A14="",P$6=""),"",ROUND(SUMIFS(流水支出,流水账户,$A14,流水日期,P$6),2)) -> 0 | Q14: =IF(OR($A14="",Q$6=""),"",ROUND(SUMIFS(流水收入,流水账户,$A14,流水日期,Q$6),2)) -> 0 | R14: =IF(OR($A14="",R$6=""),"",ROUND(SUMIFS(流水支出,流水账户,$A14,流水日期,R$6),2)) -> 0 | S14: =IF(OR($A14="",S$6=""),"",ROUND(SUMIFS(流水收入,流水账户,$A14,流水日期,S$6),2)) -> 0 | T14: =IF(OR($A14="",T$6=""),"",ROUND(SUMIFS(流水支出,流水账户,$A14,流水日期,T$6),2)) -> 0 | U14: =IF(OR($A14="",U$6=""),"",ROUND(SUMIFS(流水收入,流水账户,$A14,流水日期,U$6),2)) -> 0 | V14: =IF(OR($A14="",V$6=""),"",ROUND(SUMIFS(流水支出,流水账户,$A14,流水日期,V$6),2)) -> 0 | W14: =IF(OR($A14="",W$6=""),"",ROUND(SUMIFS(流水收入,流水账户,$A14,流水日期,W$6),2)) -> 0 | X14: =IF(OR($A14="",X$6=""),"",ROUND(SUMIFS(流水支出,流水账户,$A14,流水日期,X$6),2)) -> 0 | Y14: =IF(OR($A14="",Y$6=""),"",ROUND(SUMIFS(流水收入,流水账户,$A14,流水日期,Y$6),2)) -> 0 | Z14: =IF(OR($A14="",Z$6=""),"",ROUND(SUMIFS(流水支出,流水账户,$A14,流水日期,Z$6),2)) -> 0 | AA14: =IF(OR($A14="",AA$6=""),"",ROUND(SUMIFS(流水收入,流水账户,$A14,流水日期,AA$6),2)) -> 0 | AB14: =IF(OR($A14="",AB$6=""),"",ROUND(SUMIFS(流水支出,流水账户,$A14,流水日期,AB$6),2)) -> 0 | AC14: =IF(OR($A14="",AC$6=""),"",ROUND(SUMIFS(流水收入,流水账户,$A14,流水日期,AC$6),2)) -> 0 | AD14: =IF(OR($A14="",AD$6=""),"",ROUND(SUMIFS(流水支出,流水账户,$A14,流水日期,AD$6),2)) -> 0 | AE14: =IF(OR($A14="",AE$6=""),"",ROUND(SUMIFS(流水收入,流水账户,$A14,流水日期,AE$6),2)) -> 0 | AF14: =IF(OR($A14="",AF$6=""),"",ROUND(SUMIFS(流水支出,流水账户,$A14,流水日期,AF$6),2)) -> 0 | AG14: =IF(OR($A14="",AG$6=""),"",ROUND(SUMIFS(流水收入,流水账户,$A14,流水日期,AG$6),2)) -> 0 | AH14: =IF(OR($A14="",AH$6=""),"",ROUND(SUMIFS(流水支出,流水账户,$A14,流水日期,AH$6),2)) -> 0 | AI14: =IF(OR($A14="",AI$6=""),"",ROUND(SUMIFS(流水收入,流水账户,$A14,流水日期,AI$6),2)) -> 0 | AJ14: =IF(OR($A14="",AJ$6=""),"",ROUND(SUMIFS(流水支出,流水账户,$A14,流水日期,AJ$6),2)) -> 0 | AK14: =IF(OR($A14="",AK$6=""),"",ROUND(SUMIFS(流水收入,流水账户,$A14,流水日期,AK$6),2)) -> 0 | AL14: =IF(OR($A14="",AL$6=""),"",ROUND(SUMIFS(流水支出,流水账户,$A14,流水日期,AL$6),2)) -> 0 | AM14: =IF(OR($A14="",AM$6=""),"",ROUND(SUMIFS(流水收入,流水账户,$A14,流水日期,AM$6),2)) -> 0 | AN14: =IF(OR($A14="",AN$6=""),"",ROUND(SUMIFS(流水支出,流水账户,$A14,流水日期,AN$6),2)) -> 0 | AO14: =IF(OR($A14="",AO$6=""),"",ROUND(SUMIFS(流水收入,流水账户,$A14,流水日期,AO$6),2)) -> 0 | AP14: =IF(OR($A14="",AP$6=""),"",ROUND(SUMIFS(流水支出,流水账户,$A14,流水日期,AP$6),2)) -> 200 | AQ14: =IF(OR($A14="",AQ$6=""),"",ROUND(SUMIFS(流水收入,流水账户,$A14,流水日期,AQ$6),2)) -> 0 | AR14: =IF(OR($A14="",AR$6=""),"",ROUND(SUMIFS(流水支出,流水账户,$A14,流水日期,AR$6),2)) -> 0 | AS14: =IF(OR($A14="",AS$6=""),"",ROUND(SUMIFS(流水收入,流水账户,$A14,流水日期,AS$6),2)) -> 0 | AT14: =IF(OR($A14="",AT$6=""),"",ROUND(SUMIFS(流水支出,流水账户,$A14,流水日期,AT$6),2)) -> 0 | AU14: =IF(OR($A14="",AU$6=""),"",ROUND(SUMIFS(流水收入,流水账户,$A14,流水日期,AU$6),2)) -> 0 | AV14: =IF(OR($A14="",AV$6=""),"",ROUND(SUMIFS(流水支出,流水账户,$A14,流水日期,AV$6),2)) -> 0 | AW14: =IF(OR($A14="",AW$6=""),"",ROUND(SUMIFS(流水收入,流水账户,$A14,流水日期,AW$6),2)) -> 0 | AX14: =IF(OR($A14="",AX$6=""),"",ROUND(SUMIFS(流水支出,流水账户,$A14,流水日期,AX$6),2)) -> 0 | AY14: =IF(OR($A14="",AY$6=""),"",ROUND(SUMIFS(流水收入,流水账户,$A14,流水日期,AY$6),2)) -> 0 | AZ14: =IF(OR($A14="",AZ$6=""),"",ROUND(SUMIFS(流水支出,流水账户,$A14,流水日期,AZ$6),2)) -> 0 | BA14: =IF(OR($A14="",BA$6=""),"",ROUND(SUMIFS(流水收入,流水账户,$A14,流水日期,BA$6),2)) -> 0 | BB14: =IF(OR($A14="",BB$6=""),"",ROUND(SUMIFS(流水支出,流水账户,$A14,流水日期,BB$6),2)) -> 0 | BC14: =IF(OR($A14="",BC$6=""),"",ROUND(SUMIFS(流水收入,流水账户,$A14,流水日期,BC$6),2)) -> 0 | BD14: =IF(OR($A14="",BD$6=""),"",ROUND(SUMIFS(流水支出,流水账户,$A14,流水日期,BD$6),2)) -> 0 | BE14: =IF(OR($A14="",BE$6=""),"",ROUND(SUMIFS(流水收入,流水账户,$A14,流水日期,BE$6),2)) -> 0 | BF14: =IF(OR($A14="",BF$6=""),"",ROUND(SUMIFS(流水支出,流水账户,$A14,流水日期,BF$6),2)) -> 0 | BG14: =IF(OR($A14="",BG$6=""),"",ROUND(SUMIFS(流水收入,流水账户,$A14,流水日期,BG$6),2)) -> 0 | BH14: =IF(OR($A14="",BH$6=""),"",ROUND(SUMIFS(流水支出,流水账户,$A14,流水日期,BH$6),2)) -> 0 | BI14: =IF(OR($A14="",BI$6=""),"",ROUND(SUMIFS(流水收入,流水账户,$A14,流水日期,BI$6),2)) -> 0 | BJ14: =IF(OR($A14="",BJ$6=""),"",ROUND(SUMIFS(流水支出,流水账户,$A14,流水日期,BJ$6),2)) -> 2500 | BK14: =IF(OR($A14="",BK$6=""),"",ROUND(SUMIFS(流水收入,流水账户,$A14,流水日期,BK$6),2)) | BL14: =IF(OR($A14="",BL$6=""),"",ROUND(SUMIFS(流水支出,流水账户,$A14,流水日期,BL$6),2)) | BM14: =IF($A14="","",ROUND(SUMIF($C$7:$BL$7,"收款",C14:BL14),2)) -> 0 | BN14: =IF($A14="","",ROUND(SUMIF($C$7:$BL$7,"付款",C14:BL14),2)) -> 2700 | BO14: =IF($A14="","",ROUND(N($B14)+N(BM14)-N(BN14),2)) -> 8300
A15: =IF(基础资料!$B$12="","",基础资料!$B$12) -> 支付宝 | B15: =IF(OR($A15="",NOT(ISNUMBER($H$3))),"",ROUND(SUMIF(账户表,$A15,账户期初)+SUMIFS(流水收入,流水账户,$A15,流水日期,"<"&$B$3)-SUMIFS(流水支出,流水账户,$A15,流水日期,"<"&$B$3),2)) -> 12000 | C15: =IF(OR($A15="",C$6=""),"",ROUND(SUMIFS(流水收入,流水账户,$A15,流水日期,C$6),2)) -> 0 | D15: =IF(OR($A15="",D$6=""),"",ROUND(SUMIFS(流水支出,流水账户,$A15,流水日期,D$6),2)) -> 0 | E15: =IF(OR($A15="",E$6=""),"",ROUND(SUMIFS(流水收入,流水账户,$A15,流水日期,E$6),2)) -> 0 | F15: =IF(OR($A15="",F$6=""),"",ROUND(SUMIFS(流水支出,流水账户,$A15,流水日期,F$6),2)) -> 0 | G15: =IF(OR($A15="",G$6=""),"",ROUND(SUMIFS(流水收入,流水账户,$A15,流水日期,G$6),2)) -> 0 | H15: =IF(OR($A15="",H$6=""),"",ROUND(SUMIFS(流水支出,流水账户,$A15,流水日期,H$6),2)) -> 0 | I15: =IF(OR($A15="",I$6=""),"",ROUND(SUMIFS(流水收入,流水账户,$A15,流水日期,I$6),2)) -> 0 | J15: =IF(OR($A15="",J$6=""),"",ROUND(SUMIFS(流水支出,流水账户,$A15,流水日期,J$6),2)) -> 0 | K15: =IF(OR($A15="",K$6=""),"",ROUND(SUMIFS(流水收入,流水账户,$A15,流水日期,K$6),2)) -> 0 | L15: =IF(OR($A15="",L$6=""),"",ROUND(SUMIFS(流水支出,流水账户,$A15,流水日期,L$6),2)) -> 0 | M15: =IF(OR($A15="",M$6=""),"",ROUND(SUMIFS(流水收入,流水账户,$A15,流水日期,M$6),2)) -> 0 | N15: =IF(OR($A15="",N$6=""),"",ROUND(SUMIFS(流水支出,流水账户,$A15,流水日期,N$6),2)) -> 0 | O15: =IF(OR($A15="",O$6=""),"",ROUND(SUMIFS(流水收入,流水账户,$A15,流水日期,O$6),2)) -> 0 | P15: =IF(OR($A15="",P$6=""),"",ROUND(SUMIFS(流水支出,流水账户,$A15,流水日期,P$6),2)) -> 0 | Q15: =IF(OR($A15="",Q$6=""),"",ROUND(SUMIFS(流水收入,流水账户,$A15,流水日期,Q$6),2)) -> 0 | R15: =IF(OR($A15="",R$6=""),"",ROUND(SUMIFS(流水支出,流水账户,$A15,流水日期,R$6),2)) -> 0 | S15: =IF(OR($A15="",S$6=""),"",ROUND(SUMIFS(流水收入,流水账户,$A15,流水日期,S$6),2)) -> 0 | T15: =IF(OR($A15="",T$6=""),"",ROUND(SUMIFS(流水支出,流水账户,$A15,流水日期,T$6),2)) -> 0 | U15: =IF(OR($A15="",U$6=""),"",ROUND(SUMIFS(流水收入,流水账户,$A15,流水日期,U$6),2)) -> 0 | V15: =IF(OR($A15="",V$6=""),"",ROUND(SUMIFS(流水支出,流水账户,$A15,流水日期,V$6),2)) -> 0 | W15: =IF(OR($A15="",W$6=""),"",ROUND(SUMIFS(流水收入,流水账户,$A15,流水日期,W$6),2)) -> 0 | X15: =IF(OR($A15="",X$6=""),"",ROUND(SUMIFS(流水支出,流水账户,$A15,流水日期,X$6),2)) -> 0 | Y15: =IF(OR($A15="",Y$6=""),"",ROUND(SUMIFS(流水收入,流水账户,$A15,流水日期,Y$6),2)) -> 0 | Z15: =IF(OR($A15="",Z$6=""),"",ROUND(SUMIFS(流水支出,流水账户,$A15,流水日期,Z$6),2)) -> 0 | AA15: =IF(OR($A15="",AA$6=""),"",ROUND(SUMIFS(流水收入,流水账户,$A15,流水日期,AA$6),2)) -> 0 | AB15: =IF(OR($A15="",AB$6=""),"",ROUND(SUMIFS(流水支出,流水账户,$A15,流水日期,AB$6),2)) -> 0 | AC15: =IF(OR($A15="",AC$6=""),"",ROUND(SUMIFS(流水收入,流水账户,$A15,流水日期,AC$6),2)) -> 0 | AD15: =IF(OR($A15="",AD$6=""),"",ROUND(SUMIFS(流水支出,流水账户,$A15,流水日期,AD$6),2)) -> 0 | AE15: =IF(OR($A15="",AE$6=""),"",ROUND(SUMIFS(流水收入,流水账户,$A15,流水日期,AE$6),2)) -> 0 | AF15: =IF(OR($A15="",AF$6=""),"",ROUND(SUMIFS(流水支出,流水账户,$A15,流水日期,AF$6),2)) -> 0 | AG15: =IF(OR($A15="",AG$6=""),"",ROUND(SUMIFS(流水收入,流水账户,$A15,流水日期,AG$6),2)) -> 0 | AH15: =IF(OR($A15="",AH$6=""),"",ROUND(SUMIFS(流水支出,流水账户,$A15,流水日期,AH$6),2)) -> 0 | AI15: =IF(OR($A15="",AI$6=""),"",ROUND(SUMIFS(流水收入,流水账户,$A15,流水日期,AI$6),2)) -> 0 | AJ15: =IF(OR($A15="",AJ$6=""),"",ROUND(SUMIFS(流水支出,流水账户,$A15,流水日期,AJ$6),2)) -> 0 | AK15: =IF(OR($A15="",AK$6=""),"",ROUND(SUMIFS(流水收入,流水账户,$A15,流水日期,AK$6),2)) -> 0 | AL15: =IF(OR($A15="",AL$6=""),"",ROUND(SUMIFS(流水支出,流水账户,$A15,流水日期,AL$6),2)) -> 0 | AM15: =IF(OR($A15="",AM$6=""),"",ROUND(SUMIFS(流水收入,流水账户,$A15,流水日期,AM$6),2)) -> 0 | AN15: =IF(OR($A15="",AN$6=""),"",ROUND(SUMIFS(流水支出,流水账户,$A15,流水日期,AN$6),2)) -> 0 | AO15: =IF(OR($A15="",AO$6=""),"",ROUND(SUMIFS(流水收入,流水账户,$A15,流水日期,AO$6),2)) -> 0 | AP15: =IF(OR($A15="",AP$6=""),"",ROUND(SUMIFS(流水支出,流水账户,$A15,流水日期,AP$6),2)) -> 0 | AQ15: =IF(OR($A15="",AQ$6=""),"",ROUND(SUMIFS(流水收入,流水账户,$A15,流水日期,AQ$6),2)) -> 0 | AR15: =IF(OR($A15="",AR$6=""),"",ROUND(SUMIFS(流水支出,流水账户,$A15,流水日期,AR$6),2)) -> 0 | AS15: =IF(OR($A15="",AS$6=""),"",ROUND(SUMIFS(流水收入,流水账户,$A15,流水日期,AS$6),2)) -> 0 | AT15: =IF(OR($A15="",AT$6=""),"",ROUND(SUMIFS(流水支出,流水账户,$A15,流水日期,AT$6),2)) -> 0 | AU15: =IF(OR($A15="",AU$6=""),"",ROUND(SUMIFS(流水收入,流水账户,$A15,流水日期,AU$6),2)) -> 0 | AV15: =IF(OR($A15="",AV$6=""),"",ROUND(SUMIFS(流水支出,流水账户,$A15,流水日期,AV$6),2)) -> 10 | AW15: =IF(OR($A15="",AW$6=""),"",ROUND(SUMIFS(流水收入,流水账户,$A15,流水日期,AW$6),2)) -> 0 | AX15: =IF(OR($A15="",AX$6=""),"",ROUND(SUMIFS(流水支出,流水账户,$A15,流水日期,AX$6),2)) -> 0 | AY15: =IF(OR($A15="",AY$6=""),"",ROUND(SUMIFS(流水收入,流水账户,$A15,流水日期,AY$6),2)) -> 0 | AZ15: =IF(OR($A15="",AZ$6=""),"",ROUND(SUMIFS(流水支出,流水账户,$A15,流水日期,AZ$6),2)) -> 0 | BA15: =IF(OR($A15="",BA$6=""),"",ROUND(SUMIFS(流水收入,流水账户,$A15,流水日期,BA$6),2)) -> 0 | BB15: =IF(OR($A15="",BB$6=""),"",ROUND(SUMIFS(流水支出,流水账户,$A15,流水日期,BB$6),2)) -> 0 | BC15: =IF(OR($A15="",BC$6=""),"",ROUND(SUMIFS(流水收入,流水账户,$A15,流水日期,BC$6),2)) -> 0 | BD15: =IF(OR($A15="",BD$6=""),"",ROUND(SUMIFS(流水支出,流水账户,$A15,流水日期,BD$6),2)) -> 0 | BE15: =IF(OR($A15="",BE$6=""),"",ROUND(SUMIFS(流水收入,流水账户,$A15,流水日期,BE$6),2)) -> 0 | BF15: =IF(OR($A15="",BF$6=""),"",ROUND(SUMIFS(流水支出,流水账户,$A15,流水日期,BF$6),2)) -> 0 | BG15: =IF(OR($A15="",BG$6=""),"",ROUND(SUMIFS(流水收入,流水账户,$A15,流水日期,BG$6),2)) -> 0 | BH15: =IF(OR($A15="",BH$6=""),"",ROUND(SUMIFS(流水支出,流水账户,$A15,流水日期,BH$6),2)) -> 0 | BI15: =IF(OR($A15="",BI$6=""),"",ROUND(SUMIFS(流水收入,流水账户,$A15,流水日期,BI$6),2)) -> 600 | BJ15: =IF(OR($A15="",BJ$6=""),"",ROUND(SUMIFS(流水支出,流水账户,$A15,流水日期,BJ$6),2)) -> 0 | BK15: =IF(OR($A15="",BK$6=""),"",ROUND(SUMIFS(流水收入,流水账户,$A15,流水日期,BK$6),2)) | BL15: =IF(OR($A15="",BL$6=""),"",ROUND(SUMIFS(流水支出,流水账户,$A15,流水日期,BL$6),2)) | BM15: =IF($A15="","",ROUND(SUMIF($C$7:$BL$7,"收款",C15:BL15),2)) -> 600 | BN15: =IF($A15="","",ROUND(SUMIF($C$7:$BL$7,"付款",C15:BL15),2)) -> 10 | BO15: =IF($A15="","",ROUND(N($B15)+N(BM15)-N(BN15),2)) -> 12590
A16: =IF(基础资料!$B$13="","",基础资料!$B$13) -> 农商行 | B16: =IF(OR($A16="",NOT(ISNUMBER($H$3))),"",ROUND(SUMIF(账户表,$A16,账户期初)+SUMIFS(流水收入,流水账户,$A16,流水日期,"<"&$B$3)-SUMIFS(流水支出,流水账户,$A16,流水日期,"<"&$B$3),2)) -> 13000 | C16: =IF(OR($A16="",C$6=""),"",ROUND(SUMIFS(流水收入,流水账户,$A16,流水日期,C$6),2)) -> 0 | D16: =IF(OR($A16="",D$6=""),"",ROUND(SUMIFS(流水支出,流水账户,$A16,流水日期,D$6),2)) -> 0 | E16: =IF(OR($A16="",E$6=""),"",ROUND(SUMIFS(流水收入,流水账户,$A16,流水日期,E$6),2)) -> 0 | F16: =IF(OR($A16="",F$6=""),"",ROUND(SUMIFS(流水支出,流水账户,$A16,流水日期,F$6),2)) -> 0 | G16: =IF(OR($A16="",G$6=""),"",ROUND(SUMIFS(流水收入,流水账户,$A16,流水日期,G$6),2)) -> 0 | H16: =IF(OR($A16="",H$6=""),"",ROUND(SUMIFS(流水支出,流水账户,$A16,流水日期,H$6),2)) -> 0 | I16: =IF(OR($A16="",I$6=""),"",ROUND(SUMIFS(流水收入,流水账户,$A16,流水日期,I$6),2)) -> 0 | J16: =IF(OR($A16="",J$6=""),"",ROUND(SUMIFS(流水支出,流水账户,$A16,流水日期,J$6),2)) -> 0 | K16: =IF(OR($A16="",K$6=""),"",ROUND(SUMIFS(流水收入,流水账户,$A16,流水日期,K$6),2)) -> 0 | L16: =IF(OR($A16="",L$6=""),"",ROUND(SUMIFS(流水支出,流水账户,$A16,流水日期,L$6),2)) -> 0 | M16: =IF(OR($A16="",M$6=""),"",ROUND(SUMIFS(流水收入,流水账户,$A16,流水日期,M$6),2)) -> 0 | N16: =IF(OR($A16="",N$6=""),"",ROUND(SUMIFS(流水支出,流水账户,$A16,流水日期,N$6),2)) -> 0 | O16: =IF(OR($A16="",O$6=""),"",ROUND(SUMIFS(流水收入,流水账户,$A16,流水日期,O$6),2)) -> 0 | P16: =IF(OR($A16="",P$6=""),"",ROUND(SUMIFS(流水支出,流水账户,$A16,流水日期,P$6),2)) -> 0 | Q16: =IF(OR($A16="",Q$6=""),"",ROUND(SUMIFS(流水收入,流水账户,$A16,流水日期,Q$6),2)) -> 0 | R16: =IF(OR($A16="",R$6=""),"",ROUND(SUMIFS(流水支出,流水账户,$A16,流水日期,R$6),2)) -> 0 | S16: =IF(OR($A16="",S$6=""),"",ROUND(SUMIFS(流水收入,流水账户,$A16,流水日期,S$6),2)) -> 0 | T16: =IF(OR($A16="",T$6=""),"",ROUND(SUMIFS(流水支出,流水账户,$A16,流水日期,T$6),2)) -> 0 | U16: =IF(OR($A16="",U$6=""),"",ROUND(SUMIFS(流水收入,流水账户,$A16,流水日期,U$6),2)) -> 0 | V16: =IF(OR($A16="",V$6=""),"",ROUND(SUMIFS(流水支出,流水账户,$A16,流水日期,V$6),2)) -> 0 | W16: =IF(OR($A16="",W$6=""),"",ROUND(SUMIFS(流水收入,流水账户,$A16,流水日期,W$6),2)) -> 0 | X16: =IF(OR($A16="",X$6=""),"",ROUND(SUMIFS(流水支出,流水账户,$A16,流水日期,X$6),2)) -> 0 | Y16: =IF(OR($A16="",Y$6=""),"",ROUND(SUMIFS(流水收入,流水账户,$A16,流水日期,Y$6),2)) -> 0 | Z16: =IF(OR($A16="",Z$6=""),"",ROUND(SUMIFS(流水支出,流水账户,$A16,流水日期,Z$6),2)) -> 0 | AA16: =IF(OR($A16="",AA$6=""),"",ROUND(SUMIFS(流水收入,流水账户,$A16,流水日期,AA$6),2)) -> 0 | AB16: =IF(OR($A16="",AB$6=""),"",ROUND(SUMIFS(流水支出,流水账户,$A16,流水日期,AB$6),2)) -> 0 | AC16: =IF(OR($A16="",AC$6=""),"",ROUND(SUMIFS(流水收入,流水账户,$A16,流水日期,AC$6),2)) -> 0 | AD16: =IF(OR($A16="",AD$6=""),"",ROUND(SUMIFS(流水支出,流水账户,$A16,流水日期,AD$6),2)) -> 0 | AE16: =IF(OR($A16="",AE$6=""),"",ROUND(SUMIFS(流水收入,流水账户,$A16,流水日期,AE$6),2)) -> 0 | AF16: =IF(OR($A16="",AF$6=""),"",ROUND(SUMIFS(流水支出,流水账户,$A16,流水日期,AF$6),2)) -> 0 | AG16: =IF(OR($A16="",AG$6=""),"",ROUND(SUMIFS(流水收入,流水账户,$A16,流水日期,AG$6),2)) -> 0 | AH16: =IF(OR($A16="",AH$6=""),"",ROUND(SUMIFS(流水支出,流水账户,$A16,流水日期,AH$6),2)) -> 0 | AI16: =IF(OR($A16="",AI$6=""),"",ROUND(SUMIFS(流水收入,流水账户,$A16,流水日期,AI$6),2)) -> 0 | AJ16: =IF(OR($A16="",AJ$6=""),"",ROUND(SUMIFS(流水支出,流水账户,$A16,流水日期,AJ$6),2)) -> 0 | AK16: =IF(OR($A16="",AK$6=""),"",ROUND(SUMIFS(流水收入,流水账户,$A16,流水日期,AK$6),2)) -> 0 | AL16: =IF(OR($A16="",AL$6=""),"",ROUND(SUMIFS(流水支出,流水账户,$A16,流水日期,AL$6),2)) -> 0 | AM16: =IF(OR($A16="",AM$6=""),"",ROUND(SUMIFS(流水收入,流水账户,$A16,流水日期,AM$6),2)) -> 0 | AN16: =IF(OR($A16="",AN$6=""),"",ROUND(SUMIFS(流水支出,流水账户,$A16,流水日期,AN$6),2)) -> 0 | AO16: =IF(OR($A16="",AO$6=""),"",ROUND(SUMIFS(流水收入,流水账户,$A16,流水日期,AO$6),2)) -> 0 | AP16: =IF(OR($A16="",AP$6=""),"",ROUND(SUMIFS(流水支出,流水账户,$A16,流水日期,AP$6),2)) -> 0 | AQ16: =IF(OR($A16="",AQ$6=""),"",ROUND(SUMIFS(流水收入,流水账户,$A16,流水日期,AQ$6),2)) -> 0 | AR16: =IF(OR($A16="",AR$6=""),"",ROUND(SUMIFS(流水支出,流水账户,$A16,流水日期,AR$6),2)) -> 0 | AS16: =IF(OR($A16="",AS$6=""),"",ROUND(SUMIFS(流水收入,流水账户,$A16,流水日期,AS$6),2)) -> 0 | AT16: =IF(OR($A16="",AT$6=""),"",ROUND(SUMIFS(流水支出,流水账户,$A16,流水日期,AT$6),2)) -> 0 | AU16: =IF(OR($A16="",AU$6=""),"",ROUND(SUMIFS(流水收入,流水账户,$A16,流水日期,AU$6),2)) -> 0 | AV16: =IF(OR($A16="",AV$6=""),"",ROUND(SUMIFS(流水支出,流水账户,$A16,流水日期,AV$6),2)) -> 0 | AW16: =IF(OR($A16="",AW$6=""),"",ROUND(SUMIFS(流水收入,流水账户,$A16,流水日期,AW$6),2)) -> 0 | AX16: =IF(OR($A16="",AX$6=""),"",ROUND(SUMIFS(流水支出,流水账户,$A16,流水日期,AX$6),2)) -> 50 | AY16: =IF(OR($A16="",AY$6=""),"",ROUND(SUMIFS(流水收入,流水账户,$A16,流水日期,AY$6),2)) -> 0 | AZ16: =IF(OR($A16="",AZ$6=""),"",ROUND(SUMIFS(流水支出,流水账户,$A16,流水日期,AZ$6),2)) -> 0 | BA16: =IF(OR($A16="",BA$6=""),"",ROUND(SUMIFS(流水收入,流水账户,$A16,流水日期,BA$6),2)) -> 0 | BB16: =IF(OR($A16="",BB$6=""),"",ROUND(SUMIFS(流水支出,流水账户,$A16,流水日期,BB$6),2)) -> 0 | BC16: =IF(OR($A16="",BC$6=""),"",ROUND(SUMIFS(流水收入,流水账户,$A16,流水日期,BC$6),2)) -> 0 | BD16: =IF(OR($A16="",BD$6=""),"",ROUND(SUMIFS(流水支出,流水账户,$A16,流水日期,BD$6),2)) -> 0 | BE16: =IF(OR($A16="",BE$6=""),"",ROUND(SUMIFS(流水收入,流水账户,$A16,流水日期,BE$6),2)) -> 0 | BF16: =IF(OR($A16="",BF$6=""),"",ROUND(SUMIFS(流水支出,流水账户,$A16,流水日期,BF$6),2)) -> 0 | BG16: =IF(OR($A16="",BG$6=""),"",ROUND(SUMIFS(流水收入,流水账户,$A16,流水日期,BG$6),2)) -> 0 | BH16: =IF(OR($A16="",BH$6=""),"",ROUND(SUMIFS(流水支出,流水账户,$A16,流水日期,BH$6),2)) -> 0 | BI16: =IF(OR($A16="",BI$6=""),"",ROUND(SUMIFS(流水收入,流水账户,$A16,流水日期,BI$6),2)) -> 0 | BJ16: =IF(OR($A16="",BJ$6=""),"",ROUND(SUMIFS(流水支出,流水账户,$A16,流水日期,BJ$6),2)) -> 80 | BK16: =IF(OR($A16="",BK$6=""),"",ROUND(SUMIFS(流水收入,流水账户,$A16,流水日期,BK$6),2)) | BL16: =IF(OR($A16="",BL$6=""),"",ROUND(SUMIFS(流水支出,流水账户,$A16,流水日期,BL$6),2)) | BM16: =IF($A16="","",ROUND(SUMIF($C$7:$BL$7,"收款",C16:BL16),2)) -> 0 | BN16: =IF($A16="","",ROUND(SUMIF($C$7:$BL$7,"付款",C16:BL16),2)) -> 130 | BO16: =IF($A16="","",ROUND(N($B16)+N(BM16)-N(BN16),2)) -> 12870
A17: =IF(基础资料!$B$14="","",基础资料!$B$14) -> 备用 | B17: =IF(OR($A17="",NOT(ISNUMBER($H$3))),"",ROUND(SUMIF(账户表,$A17,账户期初)+SUMIFS(流水收入,流水账户,$A17,流水日期,"<"&$B$3)-SUMIFS(流水支出,流水账户,$A17,流水日期,"<"&$B$3),2)) -> 14000 | C17: =IF(OR($A17="",C$6=""),"",ROUND(SUMIFS(流水收入,流水账户,$A17,流水日期,C$6),2)) -> 0 | D17: =IF(OR($A17="",D$6=""),"",ROUND(SUMIFS(流水支出,流水账户,$A17,流水日期,D$6),2)) -> 0 | E17: =IF(OR($A17="",E$6=""),"",ROUND(SUMIFS(流水收入,流水账户,$A17,流水日期,E$6),2)) -> 0 | F17: =IF(OR($A17="",F$6=""),"",ROUND(SUMIFS(流水支出,流水账户,$A17,流水日期,F$6),2)) -> 0 | G17: =IF(OR($A17="",G$6=""),"",ROUND(SUMIFS(流水收入,流水账户,$A17,流水日期,G$6),2)) -> 0 | H17: =IF(OR($A17="",H$6=""),"",ROUND(SUMIFS(流水支出,流水账户,$A17,流水日期,H$6),2)) -> 0 | I17: =IF(OR($A17="",I$6=""),"",ROUND(SUMIFS(流水收入,流水账户,$A17,流水日期,I$6),2)) -> 0 | J17: =IF(OR($A17="",J$6=""),"",ROUND(SUMIFS(流水支出,流水账户,$A17,流水日期,J$6),2)) -> 0 | K17: =IF(OR($A17="",K$6=""),"",ROUND(SUMIFS(流水收入,流水账户,$A17,流水日期,K$6),2)) -> 0 | L17: =IF(OR($A17="",L$6=""),"",ROUND(SUMIFS(流水支出,流水账户,$A17,流水日期,L$6),2)) -> 0 | M17: =IF(OR($A17="",M$6=""),"",ROUND(SUMIFS(流水收入,流水账户,$A17,流水日期,M$6),2)) -> 0 | N17: =IF(OR($A17="",N$6=""),"",ROUND(SUMIFS(流水支出,流水账户,$A17,流水日期,N$6),2)) -> 0 | O17: =IF(OR($A17="",O$6=""),"",ROUND(SUMIFS(流水收入,流水账户,$A17,流水日期,O$6),2)) -> 0 | P17: =IF(OR($A17="",P$6=""),"",ROUND(SUMIFS(流水支出,流水账户,$A17,流水日期,P$6),2)) -> 0 | Q17: =IF(OR($A17="",Q$6=""),"",ROUND(SUMIFS(流水收入,流水账户,$A17,流水日期,Q$6),2)) -> 0 | R17: =IF(OR($A17="",R$6=""),"",ROUND(SUMIFS(流水支出,流水账户,$A17,流水日期,R$6),2)) -> 0 | S17: =IF(OR($A17="",S$6=""),"",ROUND(SUMIFS(流水收入,流水账户,$A17,流水日期,S$6),2)) -> 0 | T17: =IF(OR($A17="",T$6=""),"",ROUND(SUMIFS(流水支出,流水账户,$A17,流水日期,T$6),2)) -> 0 | U17: =IF(OR($A17="",U$6=""),"",ROUND(SUMIFS(流水收入,流水账户,$A17,流水日期,U$6),2)) -> 0 | V17: =IF(OR($A17="",V$6=""),"",ROUND(SUMIFS(流水支出,流水账户,$A17,流水日期,V$6),2)) -> 0 | W17: =IF(OR($A17="",W$6=""),"",ROUND(SUMIFS(流水收入,流水账户,$A17,流水日期,W$6),2)) -> 0 | X17: =IF(OR($A17="",X$6=""),"",ROUND(SUMIFS(流水支出,流水账户,$A17,流水日期,X$6),2)) -> 0 | Y17: =IF(OR($A17="",Y$6=""),"",ROUND(SUMIFS(流水收入,流水账户,$A17,流水日期,Y$6),2)) -> 0 | Z17: =IF(OR($A17="",Z$6=""),"",ROUND(SUMIFS(流水支出,流水账户,$A17,流水日期,Z$6),2)) -> 0 | AA17: =IF(OR($A17="",AA$6=""),"",ROUND(SUMIFS(流水收入,流水账户,$A17,流水日期,AA$6),2)) -> 0 | AB17: =IF(OR($A17="",AB$6=""),"",ROUND(SUMIFS(流水支出,流水账户,$A17,流水日期,AB$6),2)) -> 0 | AC17: =IF(OR($A17="",AC$6=""),"",ROUND(SUMIFS(流水收入,流水账户,$A17,流水日期,AC$6),2)) -> 0 | AD17: =IF(OR($A17="",AD$6=""),"",ROUND(SUMIFS(流水支出,流水账户,$A17,流水日期,AD$6),2)) -> 0 | AE17: =IF(OR($A17="",AE$6=""),"",ROUND(SUMIFS(流水收入,流水账户,$A17,流水日期,AE$6),2)) -> 0 | AF17: =IF(OR($A17="",AF$6=""),"",ROUND(SUMIFS(流水支出,流水账户,$A17,流水日期,AF$6),2)) -> 0 | AG17: =IF(OR($A17="",AG$6=""),"",ROUND(SUMIFS(流水收入,流水账户,$A17,流水日期,AG$6),2)) -> 0 | AH17: =IF(OR($A17="",AH$6=""),"",ROUND(SUMIFS(流水支出,流水账户,$A17,流水日期,AH$6),2)) -> 0 | AI17: =IF(OR($A17="",AI$6=""),"",ROUND(SUMIFS(流水收入,流水账户,$A17,流水日期,AI$6),2)) -> 0 | AJ17: =IF(OR($A17="",AJ$6=""),"",ROUND(SUMIFS(流水支出,流水账户,$A17,流水日期,AJ$6),2)) -> 0 | AK17: =IF(OR($A17="",AK$6=""),"",ROUND(SUMIFS(流水收入,流水账户,$A17,流水日期,AK$6),2)) -> 0 | AL17: =IF(OR($A17="",AL$6=""),"",ROUND(SUMIFS(流水支出,流水账户,$A17,流水日期,AL$6),2)) -> 0 | AM17: =IF(OR($A17="",AM$6=""),"",ROUND(SUMIFS(流水收入,流水账户,$A17,流水日期,AM$6),2)) -> 0 | AN17: =IF(OR($A17="",AN$6=""),"",ROUND(SUMIFS(流水支出,流水账户,$A17,流水日期,AN$6),2)) -> 0 | AO17: =IF(OR($A17="",AO$6=""),"",ROUND(SUMIFS(流水收入,流水账户,$A17,流水日期,AO$6),2)) -> 0 | AP17: =IF(OR($A17="",AP$6=""),"",ROUND(SUMIFS(流水支出,流水账户,$A17,流水日期,AP$6),2)) -> 0 | AQ17: =IF(OR($A17="",AQ$6=""),"",ROUND(SUMIFS(流水收入,流水账户,$A17,流水日期,AQ$6),2)) -> 0 | AR17: =IF(OR($A17="",AR$6=""),"",ROUND(SUMIFS(流水支出,流水账户,$A17,流水日期,AR$6),2)) -> 0 | AS17: =IF(OR($A17="",AS$6=""),"",ROUND(SUMIFS(流水收入,流水账户,$A17,流水日期,AS$6),2)) -> 0 | AT17: =IF(OR($A17="",AT$6=""),"",ROUND(SUMIFS(流水支出,流水账户,$A17,流水日期,AT$6),2)) -> 0 | AU17: =IF(OR($A17="",AU$6=""),"",ROUND(SUMIFS(流水收入,流水账户,$A17,流水日期,AU$6),2)) -> 0 | AV17: =IF(OR($A17="",AV$6=""),"",ROUND(SUMIFS(流水支出,流水账户,$A17,流水日期,AV$6),2)) -> 0 | AW17: =IF(OR($A17="",AW$6=""),"",ROUND(SUMIFS(流水收入,流水账户,$A17,流水日期,AW$6),2)) -> 0 | AX17: =IF(OR($A17="",AX$6=""),"",ROUND(SUMIFS(流水支出,流水账户,$A17,流水日期,AX$6),2)) -> 0 | AY17: =IF(OR($A17="",AY$6=""),"",ROUND(SUMIFS(流水收入,流水账户,$A17,流水日期,AY$6),2)) -> 2100 | AZ17: =IF(OR($A17="",AZ$6=""),"",ROUND(SUMIFS(流水支出,流水账户,$A17,流水日期,AZ$6),2)) -> 0 | BA17: =IF(OR($A17="",BA$6=""),"",ROUND(SUMIFS(流水收入,流水账户,$A17,流水日期,BA$6),2)) -> 0 | BB17: =IF(OR($A17="",BB$6=""),"",ROUND(SUMIFS(流水支出,流水账户,$A17,流水日期,BB$6),2)) -> 0 | BC17: =IF(OR($A17="",BC$6=""),"",ROUND(SUMIFS(流水收入,流水账户,$A17,流水日期,BC$6),2)) -> 0 | BD17: =IF(OR($A17="",BD$6=""),"",ROUND(SUMIFS(流水支出,流水账户,$A17,流水日期,BD$6),2)) -> 0 | BE17: =IF(OR($A17="",BE$6=""),"",ROUND(SUMIFS(流水收入,流水账户,$A17,流水日期,BE$6),2)) -> 0 | BF17: =IF(OR($A17="",BF$6=""),"",ROUND(SUMIFS(流水支出,流水账户,$A17,流水日期,BF$6),2)) -> 0 | BG17: =IF(OR($A17="",BG$6=""),"",ROUND(SUMIFS(流水收入,流水账户,$A17,流水日期,BG$6),2)) -> 0 | BH17: =IF(OR($A17="",BH$6=""),"",ROUND(SUMIFS(流水支出,流水账户,$A17,流水日期,BH$6),2)) -> 0 | BI17: =IF(OR($A17="",BI$6=""),"",ROUND(SUMIFS(流水收入,流水账户,$A17,流水日期,BI$6),2)) -> 0 | BJ17: =IF(OR($A17="",BJ$6=""),"",ROUND(SUMIFS(流水支出,流水账户,$A17,流水日期,BJ$6),2)) -> 0 | BK17: =IF(OR($A17="",BK$6=""),"",ROUND(SUMIFS(流水收入,流水账户,$A17,流水日期,BK$6),2)) | BL17: =IF(OR($A17="",BL$6=""),"",ROUND(SUMIFS(流水支出,流水账户,$A17,流水日期,BL$6),2)) | BM17: =IF($A17="","",ROUND(SUMIF($C$7:$BL$7,"收款",C17:BL17),2)) -> 2100 | BN17: =IF($A17="","",ROUND(SUMIF($C$7:$BL$7,"付款",C17:BL17),2)) -> 0 | BO17: =IF($A17="","",ROUND(N($B17)+N(BM17)-N(BN17),2)) -> 16100
A18: =IF(基础资料!$B$15="","",基础资料!$B$15) -> 备用1 | B18: =IF(OR($A18="",NOT(ISNUMBER($H$3))),"",ROUND(SUMIF(账户表,$A18,账户期初)+SUMIFS(流水收入,流水账户,$A18,流水日期,"<"&$B$3)-SUMIFS(流水支出,流水账户,$A18,流水日期,"<"&$B$3),2)) -> 15000 | C18: =IF(OR($A18="",C$6=""),"",ROUND(SUMIFS(流水收入,流水账户,$A18,流水日期,C$6),2)) -> 0 | D18: =IF(OR($A18="",D$6=""),"",ROUND(SUMIFS(流水支出,流水账户,$A18,流水日期,D$6),2)) -> 0 | E18: =IF(OR($A18="",E$6=""),"",ROUND(SUMIFS(流水收入,流水账户,$A18,流水日期,E$6),2)) -> 0 | F18: =IF(OR($A18="",F$6=""),"",ROUND(SUMIFS(流水支出,流水账户,$A18,流水日期,F$6),2)) -> 0 | G18: =IF(OR($A18="",G$6=""),"",ROUND(SUMIFS(流水收入,流水账户,$A18,流水日期,G$6),2)) -> 0 | H18: =IF(OR($A18="",H$6=""),"",ROUND(SUMIFS(流水支出,流水账户,$A18,流水日期,H$6),2)) -> 0 | I18: =IF(OR($A18="",I$6=""),"",ROUND(SUMIFS(流水收入,流水账户,$A18,流水日期,I$6),2)) -> 0 | J18: =IF(OR($A18="",J$6=""),"",ROUND(SUMIFS(流水支出,流水账户,$A18,流水日期,J$6),2)) -> 0 | K18: =IF(OR($A18="",K$6=""),"",ROUND(SUMIFS(流水收入,流水账户,$A18,流水日期,K$6),2)) -> 0 | L18: =IF(OR($A18="",L$6=""),"",ROUND(SUMIFS(流水支出,流水账户,$A18,流水日期,L$6),2)) -> 0 | M18: =IF(OR($A18="",M$6=""),"",ROUND(SUMIFS(流水收入,流水账户,$A18,流水日期,M$6),2)) -> 0 | N18: =IF(OR($A18="",N$6=""),"",ROUND(SUMIFS(流水支出,流水账户,$A18,流水日期,N$6),2)) -> 0 | O18: =IF(OR($A18="",O$6=""),"",ROUND(SUMIFS(流水收入,流水账户,$A18,流水日期,O$6),2)) -> 0 | P18: =IF(OR($A18="",P$6=""),"",ROUND(SUMIFS(流水支出,流水账户,$A18,流水日期,P$6),2)) -> 0 | Q18: =IF(OR($A18="",Q$6=""),"",ROUND(SUMIFS(流水收入,流水账户,$A18,流水日期,Q$6),2)) -> 0 | R18: =IF(OR($A18="",R$6=""),"",ROUND(SUMIFS(流水支出,流水账户,$A18,流水日期,R$6),2)) -> 0 | S18: =IF(OR($A18="",S$6=""),"",ROUND(SUMIFS(流水收入,流水账户,$A18,流水日期,S$6),2)) -> 0 | T18: =IF(OR($A18="",T$6=""),"",ROUND(SUMIFS(流水支出,流水账户,$A18,流水日期,T$6),2)) -> 0 | U18: =IF(OR($A18="",U$6=""),"",ROUND(SUMIFS(流水收入,流水账户,$A18,流水日期,U$6),2)) -> 0 | V18: =IF(OR($A18="",V$6=""),"",ROUND(SUMIFS(流水支出,流水账户,$A18,流水日期,V$6),2)) -> 0 | W18: =IF(OR($A18="",W$6=""),"",ROUND(SUMIFS(流水收入,流水账户,$A18,流水日期,W$6),2)) -> 0 | X18: =IF(OR($A18="",X$6=""),"",ROUND(SUMIFS(流水支出,流水账户,$A18,流水日期,X$6),2)) -> 0 | Y18: =IF(OR($A18="",Y$6=""),"",ROUND(SUMIFS(流水收入,流水账户,$A18,流水日期,Y$6),2)) -> 0 | Z18: =IF(OR($A18="",Z$6=""),"",ROUND(SUMIFS(流水支出,流水账户,$A18,流水日期,Z$6),2)) -> 0 | AA18: =IF(OR($A18="",AA$6=""),"",ROUND(SUMIFS(流水收入,流水账户,$A18,流水日期,AA$6),2)) -> 0 | AB18: =IF(OR($A18="",AB$6=""),"",ROUND(SUMIFS(流水支出,流水账户,$A18,流水日期,AB$6),2)) -> 0 | AC18: =IF(OR($A18="",AC$6=""),"",ROUND(SUMIFS(流水收入,流水账户,$A18,流水日期,AC$6),2)) -> 0 | AD18: =IF(OR($A18="",AD$6=""),"",ROUND(SUMIFS(流水支出,流水账户,$A18,流水日期,AD$6),2)) -> 0 | AE18: =IF(OR($A18="",AE$6=""),"",ROUND(SUMIFS(流水收入,流水账户,$A18,流水日期,AE$6),2)) -> 0 | AF18: =IF(OR($A18="",AF$6=""),"",ROUND(SUMIFS(流水支出,流水账户,$A18,流水日期,AF$6),2)) -> 0 | AG18: =IF(OR($A18="",AG$6=""),"",ROUND(SUMIFS(流水收入,流水账户,$A18,流水日期,AG$6),2)) -> 0 | AH18: =IF(OR($A18="",AH$6=""),"",ROUND(SUMIFS(流水支出,流水账户,$A18,流水日期,AH$6),2)) -> 0 | AI18: =IF(OR($A18="",AI$6=""),"",ROUND(SUMIFS(流水收入,流水账户,$A18,流水日期,AI$6),2)) -> 0 | AJ18: =IF(OR($A18="",AJ$6=""),"",ROUND(SUMIFS(流水支出,流水账户,$A18,流水日期,AJ$6),2)) -> 0 | AK18: =IF(OR($A18="",AK$6=""),"",ROUND(SUMIFS(流水收入,流水账户,$A18,流水日期,AK$6),2)) -> 0 | AL18: =IF(OR($A18="",AL$6=""),"",ROUND(SUMIFS(流水支出,流水账户,$A18,流水日期,AL$6),2)) -> 0 | AM18: =IF(OR($A18="",AM$6=""),"",ROUND(SUMIFS(流水收入,流水账户,$A18,流水日期,AM$6),2)) -> 0 | AN18: =IF(OR($A18="",AN$6=""),"",ROUND(SUMIFS(流水支出,流水账户,$A18,流水日期,AN$6),2)) -> 0 | AO18: =IF(OR($A18="",AO$6=""),"",ROUND(SUMIFS(流水收入,流水账户,$A18,流水日期,AO$6),2)) -> 0 | AP18: =IF(OR($A18="",AP$6=""),"",ROUND(SUMIFS(流水支出,流水账户,$A18,流水日期,AP$6),2)) -> 0 | AQ18: =IF(OR($A18="",AQ$6=""),"",ROUND(SUMIFS(流水收入,流水账户,$A18,流水日期,AQ$6),2)) -> 0 | AR18: =IF(OR($A18="",AR$6=""),"",ROUND(SUMIFS(流水支出,流水账户,$A18,流水日期,AR$6),2)) -> 0 | AS18: =IF(OR($A18="",AS$6=""),"",ROUND(SUMIFS(流水收入,流水账户,$A18,流水日期,AS$6),2)) -> 0 | AT18: =IF(OR($A18="",AT$6=""),"",ROUND(SUMIFS(流水支出,流水账户,$A18,流水日期,AT$6),2)) -> 0 | AU18: =IF(OR($A18="",AU$6=""),"",ROUND(SUMIFS(流水收入,流水账户,$A18,流水日期,AU$6),2)) -> 0 | AV18: =IF(OR($A18="",AV$6=""),"",ROUND(SUMIFS(流水支出,流水账户,$A18,流水日期,AV$6),2)) -> 0 | AW18: =IF(OR($A18="",AW$6=""),"",ROUND(SUMIFS(流水收入,流水账户,$A18,流水日期,AW$6),2)) -> 0 | AX18: =IF(OR($A18="",AX$6=""),"",ROUND(SUMIFS(流水支出,流水账户,$A18,流水日期,AX$6),2)) -> 0 | AY18: =IF(OR($A18="",AY$6=""),"",ROUND(SUMIFS(流水收入,流水账户,$A18,流水日期,AY$6),2)) -> 0 | AZ18: =IF(OR($A18="",AZ$6=""),"",ROUND(SUMIFS(流水支出,流水账户,$A18,流水日期,AZ$6),2)) -> 2000 | BA18: =IF(OR($A18="",BA$6=""),"",ROUND(SUMIFS(流水收入,流水账户,$A18,流水日期,BA$6),2)) -> 0 | BB18: =IF(OR($A18="",BB$6=""),"",ROUND(SUMIFS(流水支出,流水账户,$A18,流水日期,BB$6),2)) -> 0 | BC18: =IF(OR($A18="",BC$6=""),"",ROUND(SUMIFS(流水收入,流水账户,$A18,流水日期,BC$6),2)) -> 0 | BD18: =IF(OR($A18="",BD$6=""),"",ROUND(SUMIFS(流水支出,流水账户,$A18,流水日期,BD$6),2)) -> 0 | BE18: =IF(OR($A18="",BE$6=""),"",ROUND(SUMIFS(流水收入,流水账户,$A18,流水日期,BE$6),2)) -> 0 | BF18: =IF(OR($A18="",BF$6=""),"",ROUND(SUMIFS(流水支出,流水账户,$A18,流水日期,BF$6),2)) -> 0 | BG18: =IF(OR($A18="",BG$6=""),"",ROUND(SUMIFS(流水收入,流水账户,$A18,流水日期,BG$6),2)) -> 0 | BH18: =IF(OR($A18="",BH$6=""),"",ROUND(SUMIFS(流水支出,流水账户,$A18,流水日期,BH$6),2)) -> 0 | BI18: =IF(OR($A18="",BI$6=""),"",ROUND(SUMIFS(流水收入,流水账户,$A18,流水日期,BI$6),2)) -> 0 | BJ18: =IF(OR($A18="",BJ$6=""),"",ROUND(SUMIFS(流水支出,流水账户,$A18,流水日期,BJ$6),2)) -> 0 | BK18: =IF(OR($A18="",BK$6=""),"",ROUND(SUMIFS(流水收入,流水账户,$A18,流水日期,BK$6),2)) | BL18: =IF(OR($A18="",BL$6=""),"",ROUND(SUMIFS(流水支出,流水账户,$A18,流水日期,BL$6),2)) | BM18: =IF($A18="","",ROUND(SUMIF($C$7:$BL$7,"收款",C18:BL18),2)) -> 0 | BN18: =IF($A18="","",ROUND(SUMIF($C$7:$BL$7,"付款",C18:BL18),2)) -> 2000 | BO18: =IF($A18="","",ROUND(N($B18)+N(BM18)-N(BN18),2)) -> 13000
A19: =IF(基础资料!$B$16="","",基础资料!$B$16) -> 备用2 | B19: =IF(OR($A19="",NOT(ISNUMBER($H$3))),"",ROUND(SUMIF(账户表,$A19,账户期初)+SUMIFS(流水收入,流水账户,$A19,流水日期,"<"&$B$3)-SUMIFS(流水支出,流水账户,$A19,流水日期,"<"&$B$3),2)) -> 16000 | C19: =IF(OR($A19="",C$6=""),"",ROUND(SUMIFS(流水收入,流水账户,$A19,流水日期,C$6),2)) -> 0 | D19: =IF(OR($A19="",D$6=""),"",ROUND(SUMIFS(流水支出,流水账户,$A19,流水日期,D$6),2)) -> 0 | E19: =IF(OR($A19="",E$6=""),"",ROUND(SUMIFS(流水收入,流水账户,$A19,流水日期,E$6),2)) -> 0 | F19: =IF(OR($A19="",F$6=""),"",ROUND(SUMIFS(流水支出,流水账户,$A19,流水日期,F$6),2)) -> 0 | G19: =IF(OR($A19="",G$6=""),"",ROUND(SUMIFS(流水收入,流水账户,$A19,流水日期,G$6),2)) -> 0 | H19: =IF(OR($A19="",H$6=""),"",ROUND(SUMIFS(流水支出,流水账户,$A19,流水日期,H$6),2)) -> 0 | I19: =IF(OR($A19="",I$6=""),"",ROUND(SUMIFS(流水收入,流水账户,$A19,流水日期,I$6),2)) -> 0 | J19: =IF(OR($A19="",J$6=""),"",ROUND(SUMIFS(流水支出,流水账户,$A19,流水日期,J$6),2)) -> 0 | K19: =IF(OR($A19="",K$6=""),"",ROUND(SUMIFS(流水收入,流水账户,$A19,流水日期,K$6),2)) -> 0 | L19: =IF(OR($A19="",L$6=""),"",ROUND(SUMIFS(流水支出,流水账户,$A19,流水日期,L$6),2)) -> 0 | M19: =IF(OR($A19="",M$6=""),"",ROUND(SUMIFS(流水收入,流水账户,$A19,流水日期,M$6),2)) -> 0 | N19: =IF(OR($A19="",N$6=""),"",ROUND(SUMIFS(流水支出,流水账户,$A19,流水日期,N$6),2)) -> 0 | O19: =IF(OR($A19="",O$6=""),"",ROUND(SUMIFS(流水收入,流水账户,$A19,流水日期,O$6),2)) -> 0 | P19: =IF(OR($A19="",P$6=""),"",ROUND(SUMIFS(流水支出,流水账户,$A19,流水日期,P$6),2)) -> 0 | Q19: =IF(OR($A19="",Q$6=""),"",ROUND(SUMIFS(流水收入,流水账户,$A19,流水日期,Q$6),2)) -> 0 | R19: =IF(OR($A19="",R$6=""),"",ROUND(SUMIFS(流水支出,流水账户,$A19,流水日期,R$6),2)) -> 0 | S19: =IF(OR($A19="",S$6=""),"",ROUND(SUMIFS(流水收入,流水账户,$A19,流水日期,S$6),2)) -> 0 | T19: =IF(OR($A19="",T$6=""),"",ROUND(SUMIFS(流水支出,流水账户,$A19,流水日期,T$6),2)) -> 0 | U19: =IF(OR($A19="",U$6=""),"",ROUND(SUMIFS(流水收入,流水账户,$A19,流水日期,U$6),2)) -> 0 | V19: =IF(OR($A19="",V$6=""),"",ROUND(SUMIFS(流水支出,流水账户,$A19,流水日期,V$6),2)) -> 0 | W19: =IF(OR($A19="",W$6=""),"",ROUND(SUMIFS(流水收入,流水账户,$A19,流水日期,W$6),2)) -> 0 | X19: =IF(OR($A19="",X$6=""),"",ROUND(SUMIFS(流水支出,流水账户,$A19,流水日期,X$6),2)) -> 0 | Y19: =IF(OR($A19="",Y$6=""),"",ROUND(SUMIFS(流水收入,流水账户,$A19,流水日期,Y$6),2)) -> 0 | Z19: =IF(OR($A19="",Z$6=""),"",ROUND(SUMIFS(流水支出,流水账户,$A19,流水日期,Z$6),2)) -> 0 | AA19: =IF(OR($A19="",AA$6=""),"",ROUND(SUMIFS(流水收入,流水账户,$A19,流水日期,AA$6),2)) -> 0 | AB19: =IF(OR($A19="",AB$6=""),"",ROUND(SUMIFS(流水支出,流水账户,$A19,流水日期,AB$6),2)) -> 0 | AC19: =IF(OR($A19="",AC$6=""),"",ROUND(SUMIFS(流水收入,流水账户,$A19,流水日期,AC$6),2)) -> 0 | AD19: =IF(OR($A19="",AD$6=""),"",ROUND(SUMIFS(流水支出,流水账户,$A19,流水日期,AD$6),2)) -> 0 | AE19: =IF(OR($A19="",AE$6=""),"",ROUND(SUMIFS(流水收入,流水账户,$A19,流水日期,AE$6),2)) -> 0 | AF19: =IF(OR($A19="",AF$6=""),"",ROUND(SUMIFS(流水支出,流水账户,$A19,流水日期,AF$6),2)) -> 0 | AG19: =IF(OR($A19="",AG$6=""),"",ROUND(SUMIFS(流水收入,流水账户,$A19,流水日期,AG$6),2)) -> 0 | AH19: =IF(OR($A19="",AH$6=""),"",ROUND(SUMIFS(流水支出,流水账户,$A19,流水日期,AH$6),2)) -> 0 | AI19: =IF(OR($A19="",AI$6=""),"",ROUND(SUMIFS(流水收入,流水账户,$A19,流水日期,AI$6),2)) -> 0 | AJ19: =IF(OR($A19="",AJ$6=""),"",ROUND(SUMIFS(流水支出,流水账户,$A19,流水日期,AJ$6),2)) -> 0 | AK19: =IF(OR($A19="",AK$6=""),"",ROUND(SUMIFS(流水收入,流水账户,$A19,流水日期,AK$6),2)) -> 0 | AL19: =IF(OR($A19="",AL$6=""),"",ROUND(SUMIFS(流水支出,流水账户,$A19,流水日期,AL$6),2)) -> 0 | AM19: =IF(OR($A19="",AM$6=""),"",ROUND(SUMIFS(流水收入,流水账户,$A19,流水日期,AM$6),2)) -> 0 | AN19: =IF(OR($A19="",AN$6=""),"",ROUND(SUMIFS(流水支出,流水账户,$A19,流水日期,AN$6),2)) -> 0 | AO19: =IF(OR($A19="",AO$6=""),"",ROUND(SUMIFS(流水收入,流水账户,$A19,流水日期,AO$6),2)) -> 0 | AP19: =IF(OR($A19="",AP$6=""),"",ROUND(SUMIFS(流水支出,流水账户,$A19,流水日期,AP$6),2)) -> 0 | AQ19: =IF(OR($A19="",AQ$6=""),"",ROUND(SUMIFS(流水收入,流水账户,$A19,流水日期,AQ$6),2)) -> 0 | AR19: =IF(OR($A19="",AR$6=""),"",ROUND(SUMIFS(流水支出,流水账户,$A19,流水日期,AR$6),2)) -> 0 | AS19: =IF(OR($A19="",AS$6=""),"",ROUND(SUMIFS(流水收入,流水账户,$A19,流水日期,AS$6),2)) -> 0 | AT19: =IF(OR($A19="",AT$6=""),"",ROUND(SUMIFS(流水支出,流水账户,$A19,流水日期,AT$6),2)) -> 0 | AU19: =IF(OR($A19="",AU$6=""),"",ROUND(SUMIFS(流水收入,流水账户,$A19,流水日期,AU$6),2)) -> 0 | AV19: =IF(OR($A19="",AV$6=""),"",ROUND(SUMIFS(流水支出,流水账户,$A19,流水日期,AV$6),2)) -> 0 | AW19: =IF(OR($A19="",AW$6=""),"",ROUND(SUMIFS(流水收入,流水账户,$A19,流水日期,AW$6),2)) -> 0 | AX19: =IF(OR($A19="",AX$6=""),"",ROUND(SUMIFS(流水支出,流水账户,$A19,流水日期,AX$6),2)) -> 0 | AY19: =IF(OR($A19="",AY$6=""),"",ROUND(SUMIFS(流水收入,流水账户,$A19,流水日期,AY$6),2)) -> 0 | AZ19: =IF(OR($A19="",AZ$6=""),"",ROUND(SUMIFS(流水支出,流水账户,$A19,流水日期,AZ$6),2)) -> 0 | BA19: =IF(OR($A19="",BA$6=""),"",ROUND(SUMIFS(流水收入,流水账户,$A19,流水日期,BA$6),2)) -> 3000 | BB19: =IF(OR($A19="",BB$6=""),"",ROUND(SUMIFS(流水支出,流水账户,$A19,流水日期,BB$6),2)) -> 0 | BC19: =IF(OR($A19="",BC$6=""),"",ROUND(SUMIFS(流水收入,流水账户,$A19,流水日期,BC$6),2)) -> 0 | BD19: =IF(OR($A19="",BD$6=""),"",ROUND(SUMIFS(流水支出,流水账户,$A19,流水日期,BD$6),2)) -> 0 | BE19: =IF(OR($A19="",BE$6=""),"",ROUND(SUMIFS(流水收入,流水账户,$A19,流水日期,BE$6),2)) -> 0 | BF19: =IF(OR($A19="",BF$6=""),"",ROUND(SUMIFS(流水支出,流水账户,$A19,流水日期,BF$6),2)) -> 0 | BG19: =IF(OR($A19="",BG$6=""),"",ROUND(SUMIFS(流水收入,流水账户,$A19,流水日期,BG$6),2)) -> 0 | BH19: =IF(OR($A19="",BH$6=""),"",ROUND(SUMIFS(流水支出,流水账户,$A19,流水日期,BH$6),2)) -> 0 | BI19: =IF(OR($A19="",BI$6=""),"",ROUND(SUMIFS(流水收入,流水账户,$A19,流水日期,BI$6),2)) -> 0 | BJ19: =IF(OR($A19="",BJ$6=""),"",ROUND(SUMIFS(流水支出,流水账户,$A19,流水日期,BJ$6),2)) -> 0 | BK19: =IF(OR($A19="",BK$6=""),"",ROUND(SUMIFS(流水收入,流水账户,$A19,流水日期,BK$6),2)) | BL19: =IF(OR($A19="",BL$6=""),"",ROUND(SUMIFS(流水支出,流水账户,$A19,流水日期,BL$6),2)) | BM19: =IF($A19="","",ROUND(SUMIF($C$7:$BL$7,"收款",C19:BL19),2)) -> 3000 | BN19: =IF($A19="","",ROUND(SUMIF($C$7:$BL$7,"付款",C19:BL19),2)) -> 0 | BO19: =IF($A19="","",ROUND(N($B19)+N(BM19)-N(BN19),2)) -> 19000
A20: =IF(基础资料!$B$17="","",基础资料!$B$17) -> 备用3 | B20: =IF(OR($A20="",NOT(ISNUMBER($H$3))),"",ROUND(SUMIF(账户表,$A20,账户期初)+SUMIFS(流水收入,流水账户,$A20,流水日期,"<"&$B$3)-SUMIFS(流水支出,流水账户,$A20,流水日期,"<"&$B$3),2)) -> 17000 | C20: =IF(OR($A20="",C$6=""),"",ROUND(SUMIFS(流水收入,流水账户,$A20,流水日期,C$6),2)) -> 0 | D20: =IF(OR($A20="",D$6=""),"",ROUND(SUMIFS(流水支出,流水账户,$A20,流水日期,D$6),2)) -> 0 | E20: =IF(OR($A20="",E$6=""),"",ROUND(SUMIFS(流水收入,流水账户,$A20,流水日期,E$6),2)) -> 0 | F20: =IF(OR($A20="",F$6=""),"",ROUND(SUMIFS(流水支出,流水账户,$A20,流水日期,F$6),2)) -> 0 | G20: =IF(OR($A20="",G$6=""),"",ROUND(SUMIFS(流水收入,流水账户,$A20,流水日期,G$6),2)) -> 0 | H20: =IF(OR($A20="",H$6=""),"",ROUND(SUMIFS(流水支出,流水账户,$A20,流水日期,H$6),2)) -> 0 | I20: =IF(OR($A20="",I$6=""),"",ROUND(SUMIFS(流水收入,流水账户,$A20,流水日期,I$6),2)) -> 0 | J20: =IF(OR($A20="",J$6=""),"",ROUND(SUMIFS(流水支出,流水账户,$A20,流水日期,J$6),2)) -> 0 | K20: =IF(OR($A20="",K$6=""),"",ROUND(SUMIFS(流水收入,流水账户,$A20,流水日期,K$6),2)) -> 0 | L20: =IF(OR($A20="",L$6=""),"",ROUND(SUMIFS(流水支出,流水账户,$A20,流水日期,L$6),2)) -> 0 | M20: =IF(OR($A20="",M$6=""),"",ROUND(SUMIFS(流水收入,流水账户,$A20,流水日期,M$6),2)) -> 0 | N20: =IF(OR($A20="",N$6=""),"",ROUND(SUMIFS(流水支出,流水账户,$A20,流水日期,N$6),2)) -> 0 | O20: =IF(OR($A20="",O$6=""),"",ROUND(SUMIFS(流水收入,流水账户,$A20,流水日期,O$6),2)) -> 0 | P20: =IF(OR($A20="",P$6=""),"",ROUND(SUMIFS(流水支出,流水账户,$A20,流水日期,P$6),2)) -> 0 | Q20: =IF(OR($A20="",Q$6=""),"",ROUND(SUMIFS(流水收入,流水账户,$A20,流水日期,Q$6),2)) -> 0 | R20: =IF(OR($A20="",R$6=""),"",ROUND(SUMIFS(流水支出,流水账户,$A20,流水日期,R$6),2)) -> 0 | S20: =IF(OR($A20="",S$6=""),"",ROUND(SUMIFS(流水收入,流水账户,$A20,流水日期,S$6),2)) -> 0 | T20: =IF(OR($A20="",T$6=""),"",ROUND(SUMIFS(流水支出,流水账户,$A20,流水日期,T$6),2)) -> 0 | U20: =IF(OR($A20="",U$6=""),"",ROUND(SUMIFS(流水收入,流水账户,$A20,流水日期,U$6),2)) -> 0 | V20: =IF(OR($A20="",V$6=""),"",ROUND(SUMIFS(流水支出,流水账户,$A20,流水日期,V$6),2)) -> 0 | W20: =IF(OR($A20="",W$6=""),"",ROUND(SUMIFS(流水收入,流水账户,$A20,流水日期,W$6),2)) -> 0 | X20: =IF(OR($A20="",X$6=""),"",ROUND(SUMIFS(流水支出,流水账户,$A20,流水日期,X$6),2)) -> 0 | Y20: =IF(OR($A20="",Y$6=""),"",ROUND(SUMIFS(流水收入,流水账户,$A20,流水日期,Y$6),2)) -> 0 | Z20: =IF(OR($A20="",Z$6=""),"",ROUND(SUMIFS(流水支出,流水账户,$A20,流水日期,Z$6),2)) -> 0 | AA20: =IF(OR($A20="",AA$6=""),"",ROUND(SUMIFS(流水收入,流水账户,$A20,流水日期,AA$6),2)) -> 0 | AB20: =IF(OR($A20="",AB$6=""),"",ROUND(SUMIFS(流水支出,流水账户,$A20,流水日期,AB$6),2)) -> 0 | AC20: =IF(OR($A20="",AC$6=""),"",ROUND(SUMIFS(流水收入,流水账户,$A20,流水日期,AC$6),2)) -> 0 | AD20: =IF(OR($A20="",AD$6=""),"",ROUND(SUMIFS(流水支出,流水账户,$A20,流水日期,AD$6),2)) -> 0 | AE20: =IF(OR($A20="",AE$6=""),"",ROUND(SUMIFS(流水收入,流水账户,$A20,流水日期,AE$6),2)) -> 0 | AF20: =IF(OR($A20="",AF$6=""),"",ROUND(SUMIFS(流水支出,流水账户,$A20,流水日期,AF$6),2)) -> 0 | AG20: =IF(OR($A20="",AG$6=""),"",ROUND(SUMIFS(流水收入,流水账户,$A20,流水日期,AG$6),2)) -> 0 | AH20: =IF(OR($A20="",AH$6=""),"",ROUND(SUMIFS(流水支出,流水账户,$A20,流水日期,AH$6),2)) -> 0 | AI20: =IF(OR($A20="",AI$6=""),"",ROUND(SUMIFS(流水收入,流水账户,$A20,流水日期,AI$6),2)) -> 0 | AJ20: =IF(OR($A20="",AJ$6=""),"",ROUND(SUMIFS(流水支出,流水账户,$A20,流水日期,AJ$6),2)) -> 0 | AK20: =IF(OR($A20="",AK$6=""),"",ROUND(SUMIFS(流水收入,流水账户,$A20,流水日期,AK$6),2)) -> 0 | AL20: =IF(OR($A20="",AL$6=""),"",ROUND(SUMIFS(流水支出,流水账户,$A20,流水日期,AL$6),2)) -> 0 | AM20: =IF(OR($A20="",AM$6=""),"",ROUND(SUMIFS(流水收入,流水账户,$A20,流水日期,AM$6),2)) -> 0 | AN20: =IF(OR($A20="",AN$6=""),"",ROUND(SUMIFS(流水支出,流水账户,$A20,流水日期,AN$6),2)) -> 0 | AO20: =IF(OR($A20="",AO$6=""),"",ROUND(SUMIFS(流水收入,流水账户,$A20,流水日期,AO$6),2)) -> 0 | AP20: =IF(OR($A20="",AP$6=""),"",ROUND(SUMIFS(流水支出,流水账户,$A20,流水日期,AP$6),2)) -> 0 | AQ20: =IF(OR($A20="",AQ$6=""),"",ROUND(SUMIFS(流水收入,流水账户,$A20,流水日期,AQ$6),2)) -> 0 | AR20: =IF(OR($A20="",AR$6=""),"",ROUND(SUMIFS(流水支出,流水账户,$A20,流水日期,AR$6),2)) -> 0 | AS20: =IF(OR($A20="",AS$6=""),"",ROUND(SUMIFS(流水收入,流水账户,$A20,流水日期,AS$6),2)) -> 0 | AT20: =IF(OR($A20="",AT$6=""),"",ROUND(SUMIFS(流水支出,流水账户,$A20,流水日期,AT$6),2)) -> 0 | AU20: =IF(OR($A20="",AU$6=""),"",ROUND(SUMIFS(流水收入,流水账户,$A20,流水日期,AU$6),2)) -> 0 | AV20: =IF(OR($A20="",AV$6=""),"",ROUND(SUMIFS(流水支出,流水账户,$A20,流水日期,AV$6),2)) -> 0 | AW20: =IF(OR($A20="",AW$6=""),"",ROUND(SUMIFS(流水收入,流水账户,$A20,流水日期,AW$6),2)) -> 0 | AX20: =IF(OR($A20="",AX$6=""),"",ROUND(SUMIFS(流水支出,流水账户,$A20,流水日期,AX$6),2)) -> 0 | AY20: =IF(OR($A20="",AY$6=""),"",ROUND(SUMIFS(流水收入,流水账户,$A20,流水日期,AY$6),2)) -> 0 | AZ20: =IF(OR($A20="",AZ$6=""),"",ROUND(SUMIFS(流水支出,流水账户,$A20,流水日期,AZ$6),2)) -> 0 | BA20: =IF(OR($A20="",BA$6=""),"",ROUND(SUMIFS(流水收入,流水账户,$A20,流水日期,BA$6),2)) -> 0 | BB20: =IF(OR($A20="",BB$6=""),"",ROUND(SUMIFS(流水支出,流水账户,$A20,流水日期,BB$6),2)) -> 8000 | BC20: =IF(OR($A20="",BC$6=""),"",ROUND(SUMIFS(流水收入,流水账户,$A20,流水日期,BC$6),2)) -> 0 | BD20: =IF(OR($A20="",BD$6=""),"",ROUND(SUMIFS(流水支出,流水账户,$A20,流水日期,BD$6),2)) -> 0 | BE20: =IF(OR($A20="",BE$6=""),"",ROUND(SUMIFS(流水收入,流水账户,$A20,流水日期,BE$6),2)) -> 0 | BF20: =IF(OR($A20="",BF$6=""),"",ROUND(SUMIFS(流水支出,流水账户,$A20,流水日期,BF$6),2)) -> 0 | BG20: =IF(OR($A20="",BG$6=""),"",ROUND(SUMIFS(流水收入,流水账户,$A20,流水日期,BG$6),2)) -> 0 | BH20: =IF(OR($A20="",BH$6=""),"",ROUND(SUMIFS(流水支出,流水账户,$A20,流水日期,BH$6),2)) -> 0 | BI20: =IF(OR($A20="",BI$6=""),"",ROUND(SUMIFS(流水收入,流水账户,$A20,流水日期,BI$6),2)) -> 0 | BJ20: =IF(OR($A20="",BJ$6=""),"",ROUND(SUMIFS(流水支出,流水账户,$A20,流水日期,BJ$6),2)) -> 0 | BK20: =IF(OR($A20="",BK$6=""),"",ROUND(SUMIFS(流水收入,流水账户,$A20,流水日期,BK$6),2)) | BL20: =IF(OR($A20="",BL$6=""),"",ROUND(SUMIFS(流水支出,流水账户,$A20,流水日期,BL$6),2)) | BM20: =IF($A20="","",ROUND(SUMIF($C$7:$BL$7,"收款",C20:BL20),2)) -> 0 | BN20: =IF($A20="","",ROUND(SUMIF($C$7:$BL$7,"付款",C20:BL20),2)) -> 8000 | BO20: =IF($A20="","",ROUND(N($B20)+N(BM20)-N(BN20),2)) -> 9000
A21: =IF(基础资料!$B$18="","",基础资料!$B$18) -> 备用4 | B21: =IF(OR($A21="",NOT(ISNUMBER($H$3))),"",ROUND(SUMIF(账户表,$A21,账户期初)+SUMIFS(流水收入,流水账户,$A21,流水日期,"<"&$B$3)-SUMIFS(流水支出,流水账户,$A21,流水日期,"<"&$B$3),2)) -> 18000 | C21: =IF(OR($A21="",C$6=""),"",ROUND(SUMIFS(流水收入,流水账户,$A21,流水日期,C$6),2)) -> 0 | D21: =IF(OR($A21="",D$6=""),"",ROUND(SUMIFS(流水支出,流水账户,$A21,流水日期,D$6),2)) -> 0 | E21: =IF(OR($A21="",E$6=""),"",ROUND(SUMIFS(流水收入,流水账户,$A21,流水日期,E$6),2)) -> 0 | F21: =IF(OR($A21="",F$6=""),"",ROUND(SUMIFS(流水支出,流水账户,$A21,流水日期,F$6),2)) -> 0 | G21: =IF(OR($A21="",G$6=""),"",ROUND(SUMIFS(流水收入,流水账户,$A21,流水日期,G$6),2)) -> 0 | H21: =IF(OR($A21="",H$6=""),"",ROUND(SUMIFS(流水支出,流水账户,$A21,流水日期,H$6),2)) -> 0 | I21: =IF(OR($A21="",I$6=""),"",ROUND(SUMIFS(流水收入,流水账户,$A21,流水日期,I$6),2)) -> 0 | J21: =IF(OR($A21="",J$6=""),"",ROUND(SUMIFS(流水支出,流水账户,$A21,流水日期,J$6),2)) -> 0 | K21: =IF(OR($A21="",K$6=""),"",ROUND(SUMIFS(流水收入,流水账户,$A21,流水日期,K$6),2)) -> 0 | L21: =IF(OR($A21="",L$6=""),"",ROUND(SUMIFS(流水支出,流水账户,$A21,流水日期,L$6),2)) -> 0 | M21: =IF(OR($A21="",M$6=""),"",ROUND(SUMIFS(流水收入,流水账户,$A21,流水日期,M$6),2)) -> 0 | N21: =IF(OR($A21="",N$6=""),"",ROUND(SUMIFS(流水支出,流水账户,$A21,流水日期,N$6),2)) -> 0 | O21: =IF(OR($A21="",O$6=""),"",ROUND(SUMIFS(流水收入,流水账户,$A21,流水日期,O$6),2)) -> 0 | P21: =IF(OR($A21="",P$6=""),"",ROUND(SUMIFS(流水支出,流水账户,$A21,流水日期,P$6),2)) -> 0 | Q21: =IF(OR($A21="",Q$6=""),"",ROUND(SUMIFS(流水收入,流水账户,$A21,流水日期,Q$6),2)) -> 0 | R21: =IF(OR($A21="",R$6=""),"",ROUND(SUMIFS(流水支出,流水账户,$A21,流水日期,R$6),2)) -> 0 | S21: =IF(OR($A21="",S$6=""),"",ROUND(SUMIFS(流水收入,流水账户,$A21,流水日期,S$6),2)) -> 0 | T21: =IF(OR($A21="",T$6=""),"",ROUND(SUMIFS(流水支出,流水账户,$A21,流水日期,T$6),2)) -> 0 | U21: =IF(OR($A21="",U$6=""),"",ROUND(SUMIFS(流水收入,流水账户,$A21,流水日期,U$6),2)) -> 0 | V21: =IF(OR($A21="",V$6=""),"",ROUND(SUMIFS(流水支出,流水账户,$A21,流水日期,V$6),2)) -> 0 | W21: =IF(OR($A21="",W$6=""),"",ROUND(SUMIFS(流水收入,流水账户,$A21,流水日期,W$6),2)) -> 0 | X21: =IF(OR($A21="",X$6=""),"",ROUND(SUMIFS(流水支出,流水账户,$A21,流水日期,X$6),2)) -> 0 | Y21: =IF(OR($A21="",Y$6=""),"",ROUND(SUMIFS(流水收入,流水账户,$A21,流水日期,Y$6),2)) -> 0 | Z21: =IF(OR($A21="",Z$6=""),"",ROUND(SUMIFS(流水支出,流水账户,$A21,流水日期,Z$6),2)) -> 0 | AA21: =IF(OR($A21="",AA$6=""),"",ROUND(SUMIFS(流水收入,流水账户,$A21,流水日期,AA$6),2)) -> 0 | AB21: =IF(OR($A21="",AB$6=""),"",ROUND(SUMIFS(流水支出,流水账户,$A21,流水日期,AB$6),2)) -> 0 | AC21: =IF(OR($A21="",AC$6=""),"",ROUND(SUMIFS(流水收入,流水账户,$A21,流水日期,AC$6),2)) -> 0 | AD21: =IF(OR($A21="",AD$6=""),"",ROUND(SUMIFS(流水支出,流水账户,$A21,流水日期,AD$6),2)) -> 0 | AE21: =IF(OR($A21="",AE$6=""),"",ROUND(SUMIFS(流水收入,流水账户,$A21,流水日期,AE$6),2)) -> 0 | AF21: =IF(OR($A21="",AF$6=""),"",ROUND(SUMIFS(流水支出,流水账户,$A21,流水日期,AF$6),2)) -> 0 | AG21: =IF(OR($A21="",AG$6=""),"",ROUND(SUMIFS(流水收入,流水账户,$A21,流水日期,AG$6),2)) -> 0 | AH21: =IF(OR($A21="",AH$6=""),"",ROUND(SUMIFS(流水支出,流水账户,$A21,流水日期,AH$6),2)) -> 0 | AI21: =IF(OR($A21="",AI$6=""),"",ROUND(SUMIFS(流水收入,流水账户,$A21,流水日期,AI$6),2)) -> 0 | AJ21: =IF(OR($A21="",AJ$6=""),"",ROUND(SUMIFS(流水支出,流水账户,$A21,流水日期,AJ$6),2)) -> 0 | AK21: =IF(OR($A21="",AK$6=""),"",ROUND(SUMIFS(流水收入,流水账户,$A21,流水日期,AK$6),2)) -> 0 | AL21: =IF(OR($A21="",AL$6=""),"",ROUND(SUMIFS(流水支出,流水账户,$A21,流水日期,AL$6),2)) -> 0 | AM21: =IF(OR($A21="",AM$6=""),"",ROUND(SUMIFS(流水收入,流水账户,$A21,流水日期,AM$6),2)) -> 0 | AN21: =IF(OR($A21="",AN$6=""),"",ROUND(SUMIFS(流水支出,流水账户,$A21,流水日期,AN$6),2)) -> 0 | AO21: =IF(OR($A21="",AO$6=""),"",ROUND(SUMIFS(流水收入,流水账户,$A21,流水日期,AO$6),2)) -> 0 | AP21: =IF(OR($A21="",AP$6=""),"",ROUND(SUMIFS(流水支出,流水账户,$A21,流水日期,AP$6),2)) -> 0 | AQ21: =IF(OR($A21="",AQ$6=""),"",ROUND(SUMIFS(流水收入,流水账户,$A21,流水日期,AQ$6),2)) -> 0 | AR21: =IF(OR($A21="",AR$6=""),"",ROUND(SUMIFS(流水支出,流水账户,$A21,流水日期,AR$6),2)) -> 0 | AS21: =IF(OR($A21="",AS$6=""),"",ROUND(SUMIFS(流水收入,流水账户,$A21,流水日期,AS$6),2)) -> 0 | AT21: =IF(OR($A21="",AT$6=""),"",ROUND(SUMIFS(流水支出,流水账户,$A21,流水日期,AT$6),2)) -> 0 | AU21: =IF(OR($A21="",AU$6=""),"",ROUND(SUMIFS(流水收入,流水账户,$A21,流水日期,AU$6),2)) -> 0 | AV21: =IF(OR($A21="",AV$6=""),"",ROUND(SUMIFS(流水支出,流水账户,$A21,流水日期,AV$6),2)) -> 0 | AW21: =IF(OR($A21="",AW$6=""),"",ROUND(SUMIFS(流水收入,流水账户,$A21,流水日期,AW$6),2)) -> 0 | AX21: =IF(OR($A21="",AX$6=""),"",ROUND(SUMIFS(流水支出,流水账户,$A21,流水日期,AX$6),2)) -> 0 | AY21: =IF(OR($A21="",AY$6=""),"",ROUND(SUMIFS(流水收入,流水账户,$A21,流水日期,AY$6),2)) -> 0 | AZ21: =IF(OR($A21="",AZ$6=""),"",ROUND(SUMIFS(流水支出,流水账户,$A21,流水日期,AZ$6),2)) -> 0 | BA21: =IF(OR($A21="",BA$6=""),"",ROUND(SUMIFS(流水收入,流水账户,$A21,流水日期,BA$6),2)) -> 0 | BB21: =IF(OR($A21="",BB$6=""),"",ROUND(SUMIFS(流水支出,流水账户,$A21,流水日期,BB$6),2)) -> 0 | BC21: =IF(OR($A21="",BC$6=""),"",ROUND(SUMIFS(流水收入,流水账户,$A21,流水日期,BC$6),2)) -> 1500 | BD21: =IF(OR($A21="",BD$6=""),"",ROUND(SUMIFS(流水支出,流水账户,$A21,流水日期,BD$6),2)) -> 0 | BE21: =IF(OR($A21="",BE$6=""),"",ROUND(SUMIFS(流水收入,流水账户,$A21,流水日期,BE$6),2)) -> 0 | BF21: =IF(OR($A21="",BF$6=""),"",ROUND(SUMIFS(流水支出,流水账户,$A21,流水日期,BF$6),2)) -> 0 | BG21: =IF(OR($A21="",BG$6=""),"",ROUND(SUMIFS(流水收入,流水账户,$A21,流水日期,BG$6),2)) -> 0 | BH21: =IF(OR($A21="",BH$6=""),"",ROUND(SUMIFS(流水支出,流水账户,$A21,流水日期,BH$6),2)) -> 0 | BI21: =IF(OR($A21="",BI$6=""),"",ROUND(SUMIFS(流水收入,流水账户,$A21,流水日期,BI$6),2)) -> 0 | BJ21: =IF(OR($A21="",BJ$6=""),"",ROUND(SUMIFS(流水支出,流水账户,$A21,流水日期,BJ$6),2)) -> 0 | BK21: =IF(OR($A21="",BK$6=""),"",ROUND(SUMIFS(流水收入,流水账户,$A21,流水日期,BK$6),2)) | BL21: =IF(OR($A21="",BL$6=""),"",ROUND(SUMIFS(流水支出,流水账户,$A21,流水日期,BL$6),2)) | BM21: =IF($A21="","",ROUND(SUMIF($C$7:$BL$7,"收款",C21:BL21),2)) -> 1500 | BN21: =IF($A21="","",ROUND(SUMIF($C$7:$BL$7,"付款",C21:BL21),2)) -> 0 | BO21: =IF($A21="","",ROUND(N($B21)+N(BM21)-N(BN21),2)) -> 19500
A22: =IF(基础资料!$B$19="","",基础资料!$B$19) | B22: =IF(OR($A22="",NOT(ISNUMBER($H$3))),"",ROUND(SUMIF(账户表,$A22,账户期初)+SUMIFS(流水收入,流水账户,$A22,流水日期,"<"&$B$3)-SUMIFS(流水支出,流水账户,$A22,流水日期,"<"&$B$3),2)) | C22: =IF(OR($A22="",C$6=""),"",ROUND(SUMIFS(流水收入,流水账户,$A22,流水日期,C$6),2)) | D22: =IF(OR($A22="",D$6=""),"",ROUND(SUMIFS(流水支出,流水账户,$A22,流水日期,D$6),2)) | E22: =IF(OR($A22="",E$6=""),"",ROUND(SUMIFS(流水收入,流水账户,$A22,流水日期,E$6),2)) | F22: =IF(OR($A22="",F$6=""),"",ROUND(SUMIFS(流水支出,流水账户,$A22,流水日期,F$6),2)) | G22: =IF(OR($A22="",G$6=""),"",ROUND(SUMIFS(流水收入,流水账户,$A22,流水日期,G$6),2)) | H22: =IF(OR($A22="",H$6=""),"",ROUND(SUMIFS(流水支出,流水账户,$A22,流水日期,H$6),2)) | I22: =IF(OR($A22="",I$6=""),"",ROUND(SUMIFS(流水收入,流水账户,$A22,流水日期,I$6),2)) | J22: =IF(OR($A22="",J$6=""),"",ROUND(SUMIFS(流水支出,流水账户,$A22,流水日期,J$6),2)) | K22: =IF(OR($A22="",K$6=""),"",ROUND(SUMIFS(流水收入,流水账户,$A22,流水日期,K$6),2)) | L22: =IF(OR($A22="",L$6=""),"",ROUND(SUMIFS(流水支出,流水账户,$A22,流水日期,L$6),2)) | M22: =IF(OR($A22="",M$6=""),"",ROUND(SUMIFS(流水收入,流水账户,$A22,流水日期,M$6),2)) | N22: =IF(OR($A22="",N$6=""),"",ROUND(SUMIFS(流水支出,流水账户,$A22,流水日期,N$6),2)) | O22: =IF(OR($A22="",O$6=""),"",ROUND(SUMIFS(流水收入,流水账户,$A22,流水日期,O$6),2)) | P22: =IF(OR($A22="",P$6=""),"",ROUND(SUMIFS(流水支出,流水账户,$A22,流水日期,P$6),2)) | Q22: =IF(OR($A22="",Q$6=""),"",ROUND(SUMIFS(流水收入,流水账户,$A22,流水日期,Q$6),2)) | R22: =IF(OR($A22="",R$6=""),"",ROUND(SUMIFS(流水支出,流水账户,$A22,流水日期,R$6),2)) | S22: =IF(OR($A22="",S$6=""),"",ROUND(SUMIFS(流水收入,流水账户,$A22,流水日期,S$6),2)) | T22: =IF(OR($A22="",T$6=""),"",ROUND(SUMIFS(流水支出,流水账户,$A22,流水日期,T$6),2)) | U22: =IF(OR($A22="",U$6=""),"",ROUND(SUMIFS(流水收入,流水账户,$A22,流水日期,U$6),2)) | V22: =IF(OR($A22="",V$6=""),"",ROUND(SUMIFS(流水支出,流水账户,$A22,流水日期,V$6),2)) | W22: =IF(OR($A22="",W$6=""),"",ROUND(SUMIFS(流水收入,流水账户,$A22,流水日期,W$6),2)) | X22: =IF(OR($A22="",X$6=""),"",ROUND(SUMIFS(流水支出,流水账户,$A22,流水日期,X$6),2)) | Y22: =IF(OR($A22="",Y$6=""),"",ROUND(SUMIFS(流水收入,流水账户,$A22,流水日期,Y$6),2)) | Z22: =IF(OR($A22="",Z$6=""),"",ROUND(SUMIFS(流水支出,流水账户,$A22,流水日期,Z$6),2)) | AA22: =IF(OR($A22="",AA$6=""),"",ROUND(SUMIFS(流水收入,流水账户,$A22,流水日期,AA$6),2)) | AB22: =IF(OR($A22="",AB$6=""),"",ROUND(SUMIFS(流水支出,流水账户,$A22,流水日期,AB$6),2)) | AC22: =IF(OR($A22="",AC$6=""),"",ROUND(SUMIFS(流水收入,流水账户,$A22,流水日期,AC$6),2)) | AD22: =IF(OR($A22="",AD$6=""),"",ROUND(SUMIFS(流水支出,流水账户,$A22,流水日期,AD$6),2)) | AE22: =IF(OR($A22="",AE$6=""),"",ROUND(SUMIFS(流水收入,流水账户,$A22,流水日期,AE$6),2)) | AF22: =IF(OR($A22="",AF$6=""),"",ROUND(SUMIFS(流水支出,流水账户,$A22,流水日期,AF$6),2)) | AG22: =IF(OR($A22="",AG$6=""),"",ROUND(SUMIFS(流水收入,流水账户,$A22,流水日期,AG$6),2)) | AH22: =IF(OR($A22="",AH$6=""),"",ROUND(SUMIFS(流水支出,流水账户,$A22,流水日期,AH$6),2)) | AI22: =IF(OR($A22="",AI$6=""),"",ROUND(SUMIFS(流水收入,流水账户,$A22,流水日期,AI$6),2)) | AJ22: =IF(OR($A22="",AJ$6=""),"",ROUND(SUMIFS(流水支出,流水账户,$A22,流水日期,AJ$6),2)) | AK22: =IF(OR($A22="",AK$6=""),"",ROUND(SUMIFS(流水收入,流水账户,$A22,流水日期,AK$6),2)) | AL22: =IF(OR($A22="",AL$6=""),"",ROUND(SUMIFS(流水支出,流水账户,$A22,流水日期,AL$6),2)) | AM22: =IF(OR($A22="",AM$6=""),"",ROUND(SUMIFS(流水收入,流水账户,$A22,流水日期,AM$6),2)) | AN22: =IF(OR($A22="",AN$6=""),"",ROUND(SUMIFS(流水支出,流水账户,$A22,流水日期,AN$6),2)) | AO22: =IF(OR($A22="",AO$6=""),"",ROUND(SUMIFS(流水收入,流水账户,$A22,流水日期,AO$6),2)) | AP22: =IF(OR($A22="",AP$6=""),"",ROUND(SUMIFS(流水支出,流水账户,$A22,流水日期,AP$6),2)) | AQ22: =IF(OR($A22="",AQ$6=""),"",ROUND(SUMIFS(流水收入,流水账户,$A22,流水日期,AQ$6),2)) | AR22: =IF(OR($A22="",AR$6=""),"",ROUND(SUMIFS(流水支出,流水账户,$A22,流水日期,AR$6),2)) | AS22: =IF(OR($A22="",AS$6=""),"",ROUND(SUMIFS(流水收入,流水账户,$A22,流水日期,AS$6),2)) | AT22: =IF(OR($A22="",AT$6=""),"",ROUND(SUMIFS(流水支出,流水账户,$A22,流水日期,AT$6),2)) | AU22: =IF(OR($A22="",AU$6=""),"",ROUND(SUMIFS(流水收入,流水账户,$A22,流水日期,AU$6),2)) | AV22: =IF(OR($A22="",AV$6=""),"",ROUND(SUMIFS(流水支出,流水账户,$A22,流水日期,AV$6),2)) | AW22: =IF(OR($A22="",AW$6=""),"",ROUND(SUMIFS(流水收入,流水账户,$A22,流水日期,AW$6),2)) | AX22: =IF(OR($A22="",AX$6=""),"",ROUND(SUMIFS(流水支出,流水账户,$A22,流水日期,AX$6),2)) | AY22: =IF(OR($A22="",AY$6=""),"",ROUND(SUMIFS(流水收入,流水账户,$A22,流水日期,AY$6),2)) | AZ22: =IF(OR($A22="",AZ$6=""),"",ROUND(SUMIFS(流水支出,流水账户,$A22,流水日期,AZ$6),2)) | BA22: =IF(OR($A22="",BA$6=""),"",ROUND(SUMIFS(流水收入,流水账户,$A22,流水日期,BA$6),2)) | BB22: =IF(OR($A22="",BB$6=""),"",ROUND(SUMIFS(流水支出,流水账户,$A22,流水日期,BB$6),2)) | BC22: =IF(OR($A22="",BC$6=""),"",ROUND(SUMIFS(流水收入,流水账户,$A22,流水日期,BC$6),2)) | BD22: =IF(OR($A22="",BD$6=""),"",ROUND(SUMIFS(流水支出,流水账户,$A22,流水日期,BD$6),2)) | BE22: =IF(OR($A22="",BE$6=""),"",ROUND(SUMIFS(流水收入,流水账户,$A22,流水日期,BE$6),2)) | BF22: =IF(OR($A22="",BF$6=""),"",ROUND(SUMIFS(流水支出,流水账户,$A22,流水日期,BF$6),2)) | BG22: =IF(OR($A22="",BG$6=""),"",ROUND(SUMIFS(流水收入,流水账户,$A22,流水日期,BG$6),2)) | BH22: =IF(OR($A22="",BH$6=""),"",ROUND(SUMIFS(流水支出,流水账户,$A22,流水日期,BH$6),2)) | BI22: =IF(OR($A22="",BI$6=""),"",ROUND(SUMIFS(流水收入,流水账户,$A22,流水日期,BI$6),2)) | BJ22: =IF(OR($A22="",BJ$6=""),"",ROUND(SUMIFS(流水支出,流水账户,$A22,流水日期,BJ$6),2)) | BK22: =IF(OR($A22="",BK$6=""),"",ROUND(SUMIFS(流水收入,流水账户,$A22,流水日期,BK$6),2)) | BL22: =IF(OR($A22="",BL$6=""),"",ROUND(SUMIFS(流水支出,流水账户,$A22,流水日期,BL$6),2)) | BM22: =IF($A22="","",ROUND(SUMIF($C$7:$BL$7,"收款",C22:BL22),2)) | BN22: =IF($A22="","",ROUND(SUMIF($C$7:$BL$7,"付款",C22:BL22),2)) | BO22: =IF($A22="","",ROUND(N($B22)+N(BM22)-N(BN22),2))
A23: =IF(基础资料!$B$20="","",基础资料!$B$20) | B23: =IF(OR($A23="",NOT(ISNUMBER($H$3))),"",ROUND(SUMIF(账户表,$A23,账户期初)+SUMIFS(流水收入,流水账户,$A23,流水日期,"<"&$B$3)-SUMIFS(流水支出,流水账户,$A23,流水日期,"<"&$B$3),2)) | C23: =IF(OR($A23="",C$6=""),"",ROUND(SUMIFS(流水收入,流水账户,$A23,流水日期,C$6),2)) | D23: =IF(OR($A23="",D$6=""),"",ROUND(SUMIFS(流水支出,流水账户,$A23,流水日期,D$6),2)) | E23: =IF(OR($A23="",E$6=""),"",ROUND(SUMIFS(流水收入,流水账户,$A23,流水日期,E$6),2)) | F23: =IF(OR($A23="",F$6=""),"",ROUND(SUMIFS(流水支出,流水账户,$A23,流水日期,F$6),2)) | G23: =IF(OR($A23="",G$6=""),"",ROUND(SUMIFS(流水收入,流水账户,$A23,流水日期,G$6),2)) | H23: =IF(OR($A23="",H$6=""),"",ROUND(SUMIFS(流水支出,流水账户,$A23,流水日期,H$6),2)) | I23: =IF(OR($A23="",I$6=""),"",ROUND(SUMIFS(流水收入,流水账户,$A23,流水日期,I$6),2)) | J23: =IF(OR($A23="",J$6=""),"",ROUND(SUMIFS(流水支出,流水账户,$A23,流水日期,J$6),2)) | K23: =IF(OR($A23="",K$6=""),"",ROUND(SUMIFS(流水收入,流水账户,$A23,流水日期,K$6),2)) | L23: =IF(OR($A23="",L$6=""),"",ROUND(SUMIFS(流水支出,流水账户,$A23,流水日期,L$6),2)) | M23: =IF(OR($A23="",M$6=""),"",ROUND(SUMIFS(流水收入,流水账户,$A23,流水日期,M$6),2)) | N23: =IF(OR($A23="",N$6=""),"",ROUND(SUMIFS(流水支出,流水账户,$A23,流水日期,N$6),2)) | O23: =IF(OR($A23="",O$6=""),"",ROUND(SUMIFS(流水收入,流水账户,$A23,流水日期,O$6),2)) | P23: =IF(OR($A23="",P$6=""),"",ROUND(SUMIFS(流水支出,流水账户,$A23,流水日期,P$6),2)) | Q23: =IF(OR($A23="",Q$6=""),"",ROUND(SUMIFS(流水收入,流水账户,$A23,流水日期,Q$6),2)) | R23: =IF(OR($A23="",R$6=""),"",ROUND(SUMIFS(流水支出,流水账户,$A23,流水日期,R$6),2)) | S23: =IF(OR($A23="",S$6=""),"",ROUND(SUMIFS(流水收入,流水账户,$A23,流水日期,S$6),2)) | T23: =IF(OR($A23="",T$6=""),"",ROUND(SUMIFS(流水支出,流水账户,$A23,流水日期,T$6),2)) | U23: =IF(OR($A23="",U$6=""),"",ROUND(SUMIFS(流水收入,流水账户,$A23,流水日期,U$6),2)) | V23: =IF(OR($A23="",V$6=""),"",ROUND(SUMIFS(流水支出,流水账户,$A23,流水日期,V$6),2)) | W23: =IF(OR($A23="",W$6=""),"",ROUND(SUMIFS(流水收入,流水账户,$A23,流水日期,W$6),2)) | X23: =IF(OR($A23="",X$6=""),"",ROUND(SUMIFS(流水支出,流水账户,$A23,流水日期,X$6),2)) | Y23: =IF(OR($A23="",Y$6=""),"",ROUND(SUMIFS(流水收入,流水账户,$A23,流水日期,Y$6),2)) | Z23: =IF(OR($A23="",Z$6=""),"",ROUND(SUMIFS(流水支出,流水账户,$A23,流水日期,Z$6),2)) | AA23: =IF(OR($A23="",AA$6=""),"",ROUND(SUMIFS(流水收入,流水账户,$A23,流水日期,AA$6),2)) | AB23: =IF(OR($A23="",AB$6=""),"",ROUND(SUMIFS(流水支出,流水账户,$A23,流水日期,AB$6),2)) | AC23: =IF(OR($A23="",AC$6=""),"",ROUND(SUMIFS(流水收入,流水账户,$A23,流水日期,AC$6),2)) | AD23: =IF(OR($A23="",AD$6=""),"",ROUND(SUMIFS(流水支出,流水账户,$A23,流水日期,AD$6),2)) | AE23: =IF(OR($A23="",AE$6=""),"",ROUND(SUMIFS(流水收入,流水账户,$A23,流水日期,AE$6),2)) | AF23: =IF(OR($A23="",AF$6=""),"",ROUND(SUMIFS(流水支出,流水账户,$A23,流水日期,AF$6),2)) | AG23: =IF(OR($A23="",AG$6=""),"",ROUND(SUMIFS(流水收入,流水账户,$A23,流水日期,AG$6),2)) | AH23: =IF(OR($A23="",AH$6=""),"",ROUND(SUMIFS(流水支出,流水账户,$A23,流水日期,AH$6),2)) | AI23: =IF(OR($A23="",AI$6=""),"",ROUND(SUMIFS(流水收入,流水账户,$A23,流水日期,AI$6),2)) | AJ23: =IF(OR($A23="",AJ$6=""),"",ROUND(SUMIFS(流水支出,流水账户,$A23,流水日期,AJ$6),2)) | AK23: =IF(OR($A23="",AK$6=""),"",ROUND(SUMIFS(流水收入,流水账户,$A23,流水日期,AK$6),2)) | AL23: =IF(OR($A23="",AL$6=""),"",ROUND(SUMIFS(流水支出,流水账户,$A23,流水日期,AL$6),2)) | AM23: =IF(OR($A23="",AM$6=""),"",ROUND(SUMIFS(流水收入,流水账户,$A23,流水日期,AM$6),2)) | AN23: =IF(OR($A23="",AN$6=""),"",ROUND(SUMIFS(流水支出,流水账户,$A23,流水日期,AN$6),2)) | AO23: =IF(OR($A23="",AO$6=""),"",ROUND(SUMIFS(流水收入,流水账户,$A23,流水日期,AO$6),2)) | AP23: =IF(OR($A23="",AP$6=""),"",ROUND(SUMIFS(流水支出,流水账户,$A23,流水日期,AP$6),2)) | AQ23: =IF(OR($A23="",AQ$6=""),"",ROUND(SUMIFS(流水收入,流水账户,$A23,流水日期,AQ$6),2)) | AR23: =IF(OR($A23="",AR$6=""),"",ROUND(SUMIFS(流水支出,流水账户,$A23,流水日期,AR$6),2)) | AS23: =IF(OR($A23="",AS$6=""),"",ROUND(SUMIFS(流水收入,流水账户,$A23,流水日期,AS$6),2)) | AT23: =IF(OR($A23="",AT$6=""),"",ROUND(SUMIFS(流水支出,流水账户,$A23,流水日期,AT$6),2)) | AU23: =IF(OR($A23="",AU$6=""),"",ROUND(SUMIFS(流水收入,流水账户,$A23,流水日期,AU$6),2)) | AV23: =IF(OR($A23="",AV$6=""),"",ROUND(SUMIFS(流水支出,流水账户,$A23,流水日期,AV$6),2)) | AW23: =IF(OR($A23="",AW$6=""),"",ROUND(SUMIFS(流水收入,流水账户,$A23,流水日期,AW$6),2)) | AX23: =IF(OR($A23="",AX$6=""),"",ROUND(SUMIFS(流水支出,流水账户,$A23,流水日期,AX$6),2)) | AY23: =IF(OR($A23="",AY$6=""),"",ROUND(SUMIFS(流水收入,流水账户,$A23,流水日期,AY$6),2)) | AZ23: =IF(OR($A23="",AZ$6=""),"",ROUND(SUMIFS(流水支出,流水账户,$A23,流水日期,AZ$6),2)) | BA23: =IF(OR($A23="",BA$6=""),"",ROUND(SUMIFS(流水收入,流水账户,$A23,流水日期,BA$6),2)) | BB23: =IF(OR($A23="",BB$6=""),"",ROUND(SUMIFS(流水支出,流水账户,$A23,流水日期,BB$6),2)) | BC23: =IF(OR($A23="",BC$6=""),"",ROUND(SUMIFS(流水收入,流水账户,$A23,流水日期,BC$6),2)) | BD23: =IF(OR($A23="",BD$6=""),"",ROUND(SUMIFS(流水支出,流水账户,$A23,流水日期,BD$6),2)) | BE23: =IF(OR($A23="",BE$6=""),"",ROUND(SUMIFS(流水收入,流水账户,$A23,流水日期,BE$6),2)) | BF23: =IF(OR($A23="",BF$6=""),"",ROUND(SUMIFS(流水支出,流水账户,$A23,流水日期,BF$6),2)) | BG23: =IF(OR($A23="",BG$6=""),"",ROUND(SUMIFS(流水收入,流水账户,$A23,流水日期,BG$6),2)) | BH23: =IF(OR($A23="",BH$6=""),"",ROUND(SUMIFS(流水支出,流水账户,$A23,流水日期,BH$6),2)) | BI23: =IF(OR($A23="",BI$6=""),"",ROUND(SUMIFS(流水收入,流水账户,$A23,流水日期,BI$6),2)) | BJ23: =IF(OR($A23="",BJ$6=""),"",ROUND(SUMIFS(流水支出,流水账户,$A23,流水日期,BJ$6),2)) | BK23: =IF(OR($A23="",BK$6=""),"",ROUND(SUMIFS(流水收入,流水账户,$A23,流水日期,BK$6),2)) | BL23: =IF(OR($A23="",BL$6=""),"",ROUND(SUMIFS(流水支出,流水账户,$A23,流水日期,BL$6),2)) | BM23: =IF($A23="","",ROUND(SUMIF($C$7:$BL$7,"收款",C23:BL23),2)) | BN23: =IF($A23="","",ROUND(SUMIF($C$7:$BL$7,"付款",C23:BL23),2)) | BO23: =IF($A23="","",ROUND(N($B23)+N(BM23)-N(BN23),2))
A24: =IF(基础资料!$B$21="","",基础资料!$B$21) | B24: =IF(OR($A24="",NOT(ISNUMBER($H$3))),"",ROUND(SUMIF(账户表,$A24,账户期初)+SUMIFS(流水收入,流水账户,$A24,流水日期,"<"&$B$3)-SUMIFS(流水支出,流水账户,$A24,流水日期,"<"&$B$3),2)) | C24: =IF(OR($A24="",C$6=""),"",ROUND(SUMIFS(流水收入,流水账户,$A24,流水日期,C$6),2)) | D24: =IF(OR($A24="",D$6=""),"",ROUND(SUMIFS(流水支出,流水账户,$A24,流水日期,D$6),2)) | E24: =IF(OR($A24="",E$6=""),"",ROUND(SUMIFS(流水收入,流水账户,$A24,流水日期,E$6),2)) | F24: =IF(OR($A24="",F$6=""),"",ROUND(SUMIFS(流水支出,流水账户,$A24,流水日期,F$6),2)) | G24: =IF(OR($A24="",G$6=""),"",ROUND(SUMIFS(流水收入,流水账户,$A24,流水日期,G$6),2)) | H24: =IF(OR($A24="",H$6=""),"",ROUND(SUMIFS(流水支出,流水账户,$A24,流水日期,H$6),2)) | I24: =IF(OR($A24="",I$6=""),"",ROUND(SUMIFS(流水收入,流水账户,$A24,流水日期,I$6),2)) | J24: =IF(OR($A24="",J$6=""),"",ROUND(SUMIFS(流水支出,流水账户,$A24,流水日期,J$6),2)) | K24: =IF(OR($A24="",K$6=""),"",ROUND(SUMIFS(流水收入,流水账户,$A24,流水日期,K$6),2)) | L24: =IF(OR($A24="",L$6=""),"",ROUND(SUMIFS(流水支出,流水账户,$A24,流水日期,L$6),2)) | M24: =IF(OR($A24="",M$6=""),"",ROUND(SUMIFS(流水收入,流水账户,$A24,流水日期,M$6),2)) | N24: =IF(OR($A24="",N$6=""),"",ROUND(SUMIFS(流水支出,流水账户,$A24,流水日期,N$6),2)) | O24: =IF(OR($A24="",O$6=""),"",ROUND(SUMIFS(流水收入,流水账户,$A24,流水日期,O$6),2)) | P24: =IF(OR($A24="",P$6=""),"",ROUND(SUMIFS(流水支出,流水账户,$A24,流水日期,P$6),2)) | Q24: =IF(OR($A24="",Q$6=""),"",ROUND(SUMIFS(流水收入,流水账户,$A24,流水日期,Q$6),2)) | R24: =IF(OR($A24="",R$6=""),"",ROUND(SUMIFS(流水支出,流水账户,$A24,流水日期,R$6),2)) | S24: =IF(OR($A24="",S$6=""),"",ROUND(SUMIFS(流水收入,流水账户,$A24,流水日期,S$6),2)) | T24: =IF(OR($A24="",T$6=""),"",ROUND(SUMIFS(流水支出,流水账户,$A24,流水日期,T$6),2)) | U24: =IF(OR($A24="",U$6=""),"",ROUND(SUMIFS(流水收入,流水账户,$A24,流水日期,U$6),2)) | V24: =IF(OR($A24="",V$6=""),"",ROUND(SUMIFS(流水支出,流水账户,$A24,流水日期,V$6),2)) | W24: =IF(OR($A24="",W$6=""),"",ROUND(SUMIFS(流水收入,流水账户,$A24,流水日期,W$6),2)) | X24: =IF(OR($A24="",X$6=""),"",ROUND(SUMIFS(流水支出,流水账户,$A24,流水日期,X$6),2)) | Y24: =IF(OR($A24="",Y$6=""),"",ROUND(SUMIFS(流水收入,流水账户,$A24,流水日期,Y$6),2)) | Z24: =IF(OR($A24="",Z$6=""),"",ROUND(SUMIFS(流水支出,流水账户,$A24,流水日期,Z$6),2)) | AA24: =IF(OR($A24="",AA$6=""),"",ROUND(SUMIFS(流水收入,流水账户,$A24,流水日期,AA$6),2)) | AB24: =IF(OR($A24="",AB$6=""),"",ROUND(SUMIFS(流水支出,流水账户,$A24,流水日期,AB$6),2)) | AC24: =IF(OR($A24="",AC$6=""),"",ROUND(SUMIFS(流水收入,流水账户,$A24,流水日期,AC$6),2)) | AD24: =IF(OR($A24="",AD$6=""),"",ROUND(SUMIFS(流水支出,流水账户,$A24,流水日期,AD$6),2)) | AE24: =IF(OR($A24="",AE$6=""),"",ROUND(SUMIFS(流水收入,流水账户,$A24,流水日期,AE$6),2)) | AF24: =IF(OR($A24="",AF$6=""),"",ROUND(SUMIFS(流水支出,流水账户,$A24,流水日期,AF$6),2)) | AG24: =IF(OR($A24="",AG$6=""),"",ROUND(SUMIFS(流水收入,流水账户,$A24,流水日期,AG$6),2)) | AH24: =IF(OR($A24="",AH$6=""),"",ROUND(SUMIFS(流水支出,流水账户,$A24,流水日期,AH$6),2)) | AI24: =IF(OR($A24="",AI$6=""),"",ROUND(SUMIFS(流水收入,流水账户,$A24,流水日期,AI$6),2)) | AJ24: =IF(OR($A24="",AJ$6=""),"",ROUND(SUMIFS(流水支出,流水账户,$A24,流水日期,AJ$6),2)) | AK24: =IF(OR($A24="",AK$6=""),"",ROUND(SUMIFS(流水收入,流水账户,$A24,流水日期,AK$6),2)) | AL24: =IF(OR($A24="",AL$6=""),"",ROUND(SUMIFS(流水支出,流水账户,$A24,流水日期,AL$6),2)) | AM24: =IF(OR($A24="",AM$6=""),"",ROUND(SUMIFS(流水收入,流水账户,$A24,流水日期,AM$6),2)) | AN24: =IF(OR($A24="",AN$6=""),"",ROUND(SUMIFS(流水支出,流水账户,$A24,流水日期,AN$6),2)) | AO24: =IF(OR($A24="",AO$6=""),"",ROUND(SUMIFS(流水收入,流水账户,$A24,流水日期,AO$6),2)) | AP24: =IF(OR($A24="",AP$6=""),"",ROUND(SUMIFS(流水支出,流水账户,$A24,流水日期,AP$6),2)) | AQ24: =IF(OR($A24="",AQ$6=""),"",ROUND(SUMIFS(流水收入,流水账户,$A24,流水日期,AQ$6),2)) | AR24: =IF(OR($A24="",AR$6=""),"",ROUND(SUMIFS(流水支出,流水账户,$A24,流水日期,AR$6),2)) | AS24: =IF(OR($A24="",AS$6=""),"",ROUND(SUMIFS(流水收入,流水账户,$A24,流水日期,AS$6),2)) | AT24: =IF(OR($A24="",AT$6=""),"",ROUND(SUMIFS(流水支出,流水账户,$A24,流水日期,AT$6),2)) | AU24: =IF(OR($A24="",AU$6=""),"",ROUND(SUMIFS(流水收入,流水账户,$A24,流水日期,AU$6),2)) | AV24: =IF(OR($A24="",AV$6=""),"",ROUND(SUMIFS(流水支出,流水账户,$A24,流水日期,AV$6),2)) | AW24: =IF(OR($A24="",AW$6=""),"",ROUND(SUMIFS(流水收入,流水账户,$A24,流水日期,AW$6),2)) | AX24: =IF(OR($A24="",AX$6=""),"",ROUND(SUMIFS(流水支出,流水账户,$A24,流水日期,AX$6),2)) | AY24: =IF(OR($A24="",AY$6=""),"",ROUND(SUMIFS(流水收入,流水账户,$A24,流水日期,AY$6),2)) | AZ24: =IF(OR($A24="",AZ$6=""),"",ROUND(SUMIFS(流水支出,流水账户,$A24,流水日期,AZ$6),2)) | BA24: =IF(OR($A24="",BA$6=""),"",ROUND(SUMIFS(流水收入,流水账户,$A24,流水日期,BA$6),2)) | BB24: =IF(OR($A24="",BB$6=""),"",ROUND(SUMIFS(流水支出,流水账户,$A24,流水日期,BB$6),2)) | BC24: =IF(OR($A24="",BC$6=""),"",ROUND(SUMIFS(流水收入,流水账户,$A24,流水日期,BC$6),2)) | BD24: =IF(OR($A24="",BD$6=""),"",ROUND(SUMIFS(流水支出,流水账户,$A24,流水日期,BD$6),2)) | BE24: =IF(OR($A24="",BE$6=""),"",ROUND(SUMIFS(流水收入,流水账户,$A24,流水日期,BE$6),2)) | BF24: =IF(OR($A24="",BF$6=""),"",ROUND(SUMIFS(流水支出,流水账户,$A24,流水日期,BF$6),2)) | BG24: =IF(OR($A24="",BG$6=""),"",ROUND(SUMIFS(流水收入,流水账户,$A24,流水日期,BG$6),2)) | BH24: =IF(OR($A24="",BH$6=""),"",ROUND(SUMIFS(流水支出,流水账户,$A24,流水日期,BH$6),2)) | BI24: =IF(OR($A24="",BI$6=""),"",ROUND(SUMIFS(流水收入,流水账户,$A24,流水日期,BI$6),2)) | BJ24: =IF(OR($A24="",BJ$6=""),"",ROUND(SUMIFS(流水支出,流水账户,$A24,流水日期,BJ$6),2)) | BK24: =IF(OR($A24="",BK$6=""),"",ROUND(SUMIFS(流水收入,流水账户,$A24,流水日期,BK$6),2)) | BL24: =IF(OR($A24="",BL$6=""),"",ROUND(SUMIFS(流水支出,流水账户,$A24,流水日期,BL$6),2)) | BM24: =IF($A24="","",ROUND(SUMIF($C$7:$BL$7,"收款",C24:BL24),2)) | BN24: =IF($A24="","",ROUND(SUMIF($C$7:$BL$7,"付款",C24:BL24),2)) | BO24: =IF($A24="","",ROUND(N($B24)+N(BM24)-N(BN24),2))
A25: =IF(基础资料!$B$22="","",基础资料!$B$22) | B25: =IF(OR($A25="",NOT(ISNUMBER($H$3))),"",ROUND(SUMIF(账户表,$A25,账户期初)+SUMIFS(流水收入,流水账户,$A25,流水日期,"<"&$B$3)-SUMIFS(流水支出,流水账户,$A25,流水日期,"<"&$B$3),2)) | C25: =IF(OR($A25="",C$6=""),"",ROUND(SUMIFS(流水收入,流水账户,$A25,流水日期,C$6),2)) | D25: =IF(OR($A25="",D$6=""),"",ROUND(SUMIFS(流水支出,流水账户,$A25,流水日期,D$6),2)) | E25: =IF(OR($A25="",E$6=""),"",ROUND(SUMIFS(流水收入,流水账户,$A25,流水日期,E$6),2)) | F25: =IF(OR($A25="",F$6=""),"",ROUND(SUMIFS(流水支出,流水账户,$A25,流水日期,F$6),2)) | G25: =IF(OR($A25="",G$6=""),"",ROUND(SUMIFS(流水收入,流水账户,$A25,流水日期,G$6),2)) | H25: =IF(OR($A25="",H$6=""),"",ROUND(SUMIFS(流水支出,流水账户,$A25,流水日期,H$6),2)) | I25: =IF(OR($A25="",I$6=""),"",ROUND(SUMIFS(流水收入,流水账户,$A25,流水日期,I$6),2)) | J25: =IF(OR($A25="",J$6=""),"",ROUND(SUMIFS(流水支出,流水账户,$A25,流水日期,J$6),2)) | K25: =IF(OR($A25="",K$6=""),"",ROUND(SUMIFS(流水收入,流水账户,$A25,流水日期,K$6),2)) | L25: =IF(OR($A25="",L$6=""),"",ROUND(SUMIFS(流水支出,流水账户,$A25,流水日期,L$6),2)) | M25: =IF(OR($A25="",M$6=""),"",ROUND(SUMIFS(流水收入,流水账户,$A25,流水日期,M$6),2)) | N25: =IF(OR($A25="",N$6=""),"",ROUND(SUMIFS(流水支出,流水账户,$A25,流水日期,N$6),2)) | O25: =IF(OR($A25="",O$6=""),"",ROUND(SUMIFS(流水收入,流水账户,$A25,流水日期,O$6),2)) | P25: =IF(OR($A25="",P$6=""),"",ROUND(SUMIFS(流水支出,流水账户,$A25,流水日期,P$6),2)) | Q25: =IF(OR($A25="",Q$6=""),"",ROUND(SUMIFS(流水收入,流水账户,$A25,流水日期,Q$6),2)) | R25: =IF(OR($A25="",R$6=""),"",ROUND(SUMIFS(流水支出,流水账户,$A25,流水日期,R$6),2)) | S25: =IF(OR($A25="",S$6=""),"",ROUND(SUMIFS(流水收入,流水账户,$A25,流水日期,S$6),2)) | T25: =IF(OR($A25="",T$6=""),"",ROUND(SUMIFS(流水支出,流水账户,$A25,流水日期,T$6),2)) | U25: =IF(OR($A25="",U$6=""),"",ROUND(SUMIFS(流水收入,流水账户,$A25,流水日期,U$6),2)) | V25: =IF(OR($A25="",V$6=""),"",ROUND(SUMIFS(流水支出,流水账户,$A25,流水日期,V$6),2)) | W25: =IF(OR($A25="",W$6=""),"",ROUND(SUMIFS(流水收入,流水账户,$A25,流水日期,W$6),2)) | X25: =IF(OR($A25="",X$6=""),"",ROUND(SUMIFS(流水支出,流水账户,$A25,流水日期,X$6),2)) | Y25: =IF(OR($A25="",Y$6=""),"",ROUND(SUMIFS(流水收入,流水账户,$A25,流水日期,Y$6),2)) | Z25: =IF(OR($A25="",Z$6=""),"",ROUND(SUMIFS(流水支出,流水账户,$A25,流水日期,Z$6),2)) | AA25: =IF(OR($A25="",AA$6=""),"",ROUND(SUMIFS(流水收入,流水账户,$A25,流水日期,AA$6),2)) | AB25: =IF(OR($A25="",AB$6=""),"",ROUND(SUMIFS(流水支出,流水账户,$A25,流水日期,AB$6),2)) | AC25: =IF(OR($A25="",AC$6=""),"",ROUND(SUMIFS(流水收入,流水账户,$A25,流水日期,AC$6),2)) | AD25: =IF(OR($A25="",AD$6=""),"",ROUND(SUMIFS(流水支出,流水账户,$A25,流水日期,AD$6),2)) | AE25: =IF(OR($A25="",AE$6=""),"",ROUND(SUMIFS(流水收入,流水账户,$A25,流水日期,AE$6),2)) | AF25: =IF(OR($A25="",AF$6=""),"",ROUND(SUMIFS(流水支出,流水账户,$A25,流水日期,AF$6),2)) | AG25: =IF(OR($A25="",AG$6=""),"",ROUND(SUMIFS(流水收入,流水账户,$A25,流水日期,AG$6),2)) | AH25: =IF(OR($A25="",AH$6=""),"",ROUND(SUMIFS(流水支出,流水账户,$A25,流水日期,AH$6),2)) | AI25: =IF(OR($A25="",AI$6=""),"",ROUND(SUMIFS(流水收入,流水账户,$A25,流水日期,AI$6),2)) | AJ25: =IF(OR($A25="",AJ$6=""),"",ROUND(SUMIFS(流水支出,流水账户,$A25,流水日期,AJ$6),2)) | AK25: =IF(OR($A25="",AK$6=""),"",ROUND(SUMIFS(流水收入,流水账户,$A25,流水日期,AK$6),2)) | AL25: =IF(OR($A25="",AL$6=""),"",ROUND(SUMIFS(流水支出,流水账户,$A25,流水日期,AL$6),2)) | AM25: =IF(OR($A25="",AM$6=""),"",ROUND(SUMIFS(流水收入,流水账户,$A25,流水日期,AM$6),2)) | AN25: =IF(OR($A25="",AN$6=""),"",ROUND(SUMIFS(流水支出,流水账户,$A25,流水日期,AN$6),2)) | AO25: =IF(OR($A25="",AO$6=""),"",ROUND(SUMIFS(流水收入,流水账户,$A25,流水日期,AO$6),2)) | AP25: =IF(OR($A25="",AP$6=""),"",ROUND(SUMIFS(流水支出,流水账户,$A25,流水日期,AP$6),2)) | AQ25: =IF(OR($A25="",AQ$6=""),"",ROUND(SUMIFS(流水收入,流水账户,$A25,流水日期,AQ$6),2)) | AR25: =IF(OR($A25="",AR$6=""),"",ROUND(SUMIFS(流水支出,流水账户,$A25,流水日期,AR$6),2)) | AS25: =IF(OR($A25="",AS$6=""),"",ROUND(SUMIFS(流水收入,流水账户,$A25,流水日期,AS$6),2)) | AT25: =IF(OR($A25="",AT$6=""),"",ROUND(SUMIFS(流水支出,流水账户,$A25,流水日期,AT$6),2)) | AU25: =IF(OR($A25="",AU$6=""),"",ROUND(SUMIFS(流水收入,流水账户,$A25,流水日期,AU$6),2)) | AV25: =IF(OR($A25="",AV$6=""),"",ROUND(SUMIFS(流水支出,流水账户,$A25,流水日期,AV$6),2)) | AW25: =IF(OR($A25="",AW$6=""),"",ROUND(SUMIFS(流水收入,流水账户,$A25,流水日期,AW$6),2)) | AX25: =IF(OR($A25="",AX$6=""),"",ROUND(SUMIFS(流水支出,流水账户,$A25,流水日期,AX$6),2)) | AY25: =IF(OR($A25="",AY$6=""),"",ROUND(SUMIFS(流水收入,流水账户,$A25,流水日期,AY$6),2)) | AZ25: =IF(OR($A25="",AZ$6=""),"",ROUND(SUMIFS(流水支出,流水账户,$A25,流水日期,AZ$6),2)) | BA25: =IF(OR($A25="",BA$6=""),"",ROUND(SUMIFS(流水收入,流水账户,$A25,流水日期,BA$6),2)) | BB25: =IF(OR($A25="",BB$6=""),"",ROUND(SUMIFS(流水支出,流水账户,$A25,流水日期,BB$6),2)) | BC25: =IF(OR($A25="",BC$6=""),"",ROUND(SUMIFS(流水收入,流水账户,$A25,流水日期,BC$6),2)) | BD25: =IF(OR($A25="",BD$6=""),"",ROUND(SUMIFS(流水支出,流水账户,$A25,流水日期,BD$6),2)) | BE25: =IF(OR($A25="",BE$6=""),"",ROUND(SUMIFS(流水收入,流水账户,$A25,流水日期,BE$6),2)) | BF25: =IF(OR($A25="",BF$6=""),"",ROUND(SUMIFS(流水支出,流水账户,$A25,流水日期,BF$6),2)) | BG25: =IF(OR($A25="",BG$6=""),"",ROUND(SUMIFS(流水收入,流水账户,$A25,流水日期,BG$6),2)) | BH25: =IF(OR($A25="",BH$6=""),"",ROUND(SUMIFS(流水支出,流水账户,$A25,流水日期,BH$6),2)) | BI25: =IF(OR($A25="",BI$6=""),"",ROUND(SUMIFS(流水收入,流水账户,$A25,流水日期,BI$6),2)) | BJ25: =IF(OR($A25="",BJ$6=""),"",ROUND(SUMIFS(流水支出,流水账户,$A25,流水日期,BJ$6),2)) | BK25: =IF(OR($A25="",BK$6=""),"",ROUND(SUMIFS(流水收入,流水账户,$A25,流水日期,BK$6),2)) | BL25: =IF(OR($A25="",BL$6=""),"",ROUND(SUMIFS(流水支出,流水账户,$A25,流水日期,BL$6),2)) | BM25: =IF($A25="","",ROUND(SUMIF($C$7:$BL$7,"收款",C25:BL25),2)) | BN25: =IF($A25="","",ROUND(SUMIF($C$7:$BL$7,"付款",C25:BL25),2)) | BO25: =IF($A25="","",ROUND(N($B25)+N(BM25)-N(BN25),2))
A26: =IF(基础资料!$B$23="","",基础资料!$B$23) | B26: =IF(OR($A26="",NOT(ISNUMBER($H$3))),"",ROUND(SUMIF(账户表,$A26,账户期初)+SUMIFS(流水收入,流水账户,$A26,流水日期,"<"&$B$3)-SUMIFS(流水支出,流水账户,$A26,流水日期,"<"&$B$3),2)) | C26: =IF(OR($A26="",C$6=""),"",ROUND(SUMIFS(流水收入,流水账户,$A26,流水日期,C$6),2)) | D26: =IF(OR($A26="",D$6=""),"",ROUND(SUMIFS(流水支出,流水账户,$A26,流水日期,D$6),2)) | E26: =IF(OR($A26="",E$6=""),"",ROUND(SUMIFS(流水收入,流水账户,$A26,流水日期,E$6),2)) | F26: =IF(OR($A26="",F$6=""),"",ROUND(SUMIFS(流水支出,流水账户,$A26,流水日期,F$6),2)) | G26: =IF(OR($A26="",G$6=""),"",ROUND(SUMIFS(流水收入,流水账户,$A26,流水日期,G$6),2)) | H26: =IF(OR($A26="",H$6=""),"",ROUND(SUMIFS(流水支出,流水账户,$A26,流水日期,H$6),2)) | I26: =IF(OR($A26="",I$6=""),"",ROUND(SUMIFS(流水收入,流水账户,$A26,流水日期,I$6),2)) | J26: =IF(OR($A26="",J$6=""),"",ROUND(SUMIFS(流水支出,流水账户,$A26,流水日期,J$6),2)) | K26: =IF(OR($A26="",K$6=""),"",ROUND(SUMIFS(流水收入,流水账户,$A26,流水日期,K$6),2)) | L26: =IF(OR($A26="",L$6=""),"",ROUND(SUMIFS(流水支出,流水账户,$A26,流水日期,L$6),2)) | M26: =IF(OR($A26="",M$6=""),"",ROUND(SUMIFS(流水收入,流水账户,$A26,流水日期,M$6),2)) | N26: =IF(OR($A26="",N$6=""),"",ROUND(SUMIFS(流水支出,流水账户,$A26,流水日期,N$6),2)) | O26: =IF(OR($A26="",O$6=""),"",ROUND(SUMIFS(流水收入,流水账户,$A26,流水日期,O$6),2)) | P26: =IF(OR($A26="",P$6=""),"",ROUND(SUMIFS(流水支出,流水账户,$A26,流水日期,P$6),2)) | Q26: =IF(OR($A26="",Q$6=""),"",ROUND(SUMIFS(流水收入,流水账户,$A26,流水日期,Q$6),2)) | R26: =IF(OR($A26="",R$6=""),"",ROUND(SUMIFS(流水支出,流水账户,$A26,流水日期,R$6),2)) | S26: =IF(OR($A26="",S$6=""),"",ROUND(SUMIFS(流水收入,流水账户,$A26,流水日期,S$6),2)) | T26: =IF(OR($A26="",T$6=""),"",ROUND(SUMIFS(流水支出,流水账户,$A26,流水日期,T$6),2)) | U26: =IF(OR($A26="",U$6=""),"",ROUND(SUMIFS(流水收入,流水账户,$A26,流水日期,U$6),2)) | V26: =IF(OR($A26="",V$6=""),"",ROUND(SUMIFS(流水支出,流水账户,$A26,流水日期,V$6),2)) | W26: =IF(OR($A26="",W$6=""),"",ROUND(SUMIFS(流水收入,流水账户,$A26,流水日期,W$6),2)) | X26: =IF(OR($A26="",X$6=""),"",ROUND(SUMIFS(流水支出,流水账户,$A26,流水日期,X$6),2)) | Y26: =IF(OR($A26="",Y$6=""),"",ROUND(SUMIFS(流水收入,流水账户,$A26,流水日期,Y$6),2)) | Z26: =IF(OR($A26="",Z$6=""),"",ROUND(SUMIFS(流水支出,流水账户,$A26,流水日期,Z$6),2)) | AA26: =IF(OR($A26="",AA$6=""),"",ROUND(SUMIFS(流水收入,流水账户,$A26,流水日期,AA$6),2)) | AB26: =IF(OR($A26="",AB$6=""),"",ROUND(SUMIFS(流水支出,流水账户,$A26,流水日期,AB$6),2)) | AC26: =IF(OR($A26="",AC$6=""),"",ROUND(SUMIFS(流水收入,流水账户,$A26,流水日期,AC$6),2)) | AD26: =IF(OR($A26="",AD$6=""),"",ROUND(SUMIFS(流水支出,流水账户,$A26,流水日期,AD$6),2)) | AE26: =IF(OR($A26="",AE$6=""),"",ROUND(SUMIFS(流水收入,流水账户,$A26,流水日期,AE$6),2)) | AF26: =IF(OR($A26="",AF$6=""),"",ROUND(SUMIFS(流水支出,流水账户,$A26,流水日期,AF$6),2)) | AG26: =IF(OR($A26="",AG$6=""),"",ROUND(SUMIFS(流水收入,流水账户,$A26,流水日期,AG$6),2)) | AH26: =IF(OR($A26="",AH$6=""),"",ROUND(SUMIFS(流水支出,流水账户,$A26,流水日期,AH$6),2)) | AI26: =IF(OR($A26="",AI$6=""),"",ROUND(SUMIFS(流水收入,流水账户,$A26,流水日期,AI$6),2)) | AJ26: =IF(OR($A26="",AJ$6=""),"",ROUND(SUMIFS(流水支出,流水账户,$A26,流水日期,AJ$6),2)) | AK26: =IF(OR($A26="",AK$6=""),"",ROUND(SUMIFS(流水收入,流水账户,$A26,流水日期,AK$6),2)) | AL26: =IF(OR($A26="",AL$6=""),"",ROUND(SUMIFS(流水支出,流水账户,$A26,流水日期,AL$6),2)) | AM26: =IF(OR($A26="",AM$6=""),"",ROUND(SUMIFS(流水收入,流水账户,$A26,流水日期,AM$6),2)) | AN26: =IF(OR($A26="",AN$6=""),"",ROUND(SUMIFS(流水支出,流水账户,$A26,流水日期,AN$6),2)) | AO26: =IF(OR($A26="",AO$6=""),"",ROUND(SUMIFS(流水收入,流水账户,$A26,流水日期,AO$6),2)) | AP26: =IF(OR($A26="",AP$6=""),"",ROUND(SUMIFS(流水支出,流水账户,$A26,流水日期,AP$6),2)) | AQ26: =IF(OR($A26="",AQ$6=""),"",ROUND(SUMIFS(流水收入,流水账户,$A26,流水日期,AQ$6),2)) | AR26: =IF(OR($A26="",AR$6=""),"",ROUND(SUMIFS(流水支出,流水账户,$A26,流水日期,AR$6),2)) | AS26: =IF(OR($A26="",AS$6=""),"",ROUND(SUMIFS(流水收入,流水账户,$A26,流水日期,AS$6),2)) | AT26: =IF(OR($A26="",AT$6=""),"",ROUND(SUMIFS(流水支出,流水账户,$A26,流水日期,AT$6),2)) | AU26: =IF(OR($A26="",AU$6=""),"",ROUND(SUMIFS(流水收入,流水账户,$A26,流水日期,AU$6),2)) | AV26: =IF(OR($A26="",AV$6=""),"",ROUND(SUMIFS(流水支出,流水账户,$A26,流水日期,AV$6),2)) | AW26: =IF(OR($A26="",AW$6=""),"",ROUND(SUMIFS(流水收入,流水账户,$A26,流水日期,AW$6),2)) | AX26: =IF(OR($A26="",AX$6=""),"",ROUND(SUMIFS(流水支出,流水账户,$A26,流水日期,AX$6),2)) | AY26: =IF(OR($A26="",AY$6=""),"",ROUND(SUMIFS(流水收入,流水账户,$A26,流水日期,AY$6),2)) | AZ26: =IF(OR($A26="",AZ$6=""),"",ROUND(SUMIFS(流水支出,流水账户,$A26,流水日期,AZ$6),2)) | BA26: =IF(OR($A26="",BA$6=""),"",ROUND(SUMIFS(流水收入,流水账户,$A26,流水日期,BA$6),2)) | BB26: =IF(OR($A26="",BB$6=""),"",ROUND(SUMIFS(流水支出,流水账户,$A26,流水日期,BB$6),2)) | BC26: =IF(OR($A26="",BC$6=""),"",ROUND(SUMIFS(流水收入,流水账户,$A26,流水日期,BC$6),2)) | BD26: =IF(OR($A26="",BD$6=""),"",ROUND(SUMIFS(流水支出,流水账户,$A26,流水日期,BD$6),2)) | BE26: =IF(OR($A26="",BE$6=""),"",ROUND(SUMIFS(流水收入,流水账户,$A26,流水日期,BE$6),2)) | BF26: =IF(OR($A26="",BF$6=""),"",ROUND(SUMIFS(流水支出,流水账户,$A26,流水日期,BF$6),2)) | BG26: =IF(OR($A26="",BG$6=""),"",ROUND(SUMIFS(流水收入,流水账户,$A26,流水日期,BG$6),2)) | BH26: =IF(OR($A26="",BH$6=""),"",ROUND(SUMIFS(流水支出,流水账户,$A26,流水日期,BH$6),2)) | BI26: =IF(OR($A26="",BI$6=""),"",ROUND(SUMIFS(流水收入,流水账户,$A26,流水日期,BI$6),2)) | BJ26: =IF(OR($A26="",BJ$6=""),"",ROUND(SUMIFS(流水支出,流水账户,$A26,流水日期,BJ$6),2)) | BK26: =IF(OR($A26="",BK$6=""),"",ROUND(SUMIFS(流水收入,流水账户,$A26,流水日期,BK$6),2)) | BL26: =IF(OR($A26="",BL$6=""),"",ROUND(SUMIFS(流水支出,流水账户,$A26,流水日期,BL$6),2)) | BM26: =IF($A26="","",ROUND(SUMIF($C$7:$BL$7,"收款",C26:BL26),2)) | BN26: =IF($A26="","",ROUND(SUMIF($C$7:$BL$7,"付款",C26:BL26),2)) | BO26: =IF($A26="","",ROUND(N($B26)+N(BM26)-N(BN26),2))
A27: =IF(基础资料!$B$24="","",基础资料!$B$24) | B27: =IF(OR($A27="",NOT(ISNUMBER($H$3))),"",ROUND(SUMIF(账户表,$A27,账户期初)+SUMIFS(流水收入,流水账户,$A27,流水日期,"<"&$B$3)-SUMIFS(流水支出,流水账户,$A27,流水日期,"<"&$B$3),2)) | C27: =IF(OR($A27="",C$6=""),"",ROUND(SUMIFS(流水收入,流水账户,$A27,流水日期,C$6),2)) | D27: =IF(OR($A27="",D$6=""),"",ROUND(SUMIFS(流水支出,流水账户,$A27,流水日期,D$6),2)) | E27: =IF(OR($A27="",E$6=""),"",ROUND(SUMIFS(流水收入,流水账户,$A27,流水日期,E$6),2)) | F27: =IF(OR($A27="",F$6=""),"",ROUND(SUMIFS(流水支出,流水账户,$A27,流水日期,F$6),2)) | G27: =IF(OR($A27="",G$6=""),"",ROUND(SUMIFS(流水收入,流水账户,$A27,流水日期,G$6),2)) | H27: =IF(OR($A27="",H$6=""),"",ROUND(SUMIFS(流水支出,流水账户,$A27,流水日期,H$6),2)) | I27: =IF(OR($A27="",I$6=""),"",ROUND(SUMIFS(流水收入,流水账户,$A27,流水日期,I$6),2)) | J27: =IF(OR($A27="",J$6=""),"",ROUND(SUMIFS(流水支出,流水账户,$A27,流水日期,J$6),2)) | K27: =IF(OR($A27="",K$6=""),"",ROUND(SUMIFS(流水收入,流水账户,$A27,流水日期,K$6),2)) | L27: =IF(OR($A27="",L$6=""),"",ROUND(SUMIFS(流水支出,流水账户,$A27,流水日期,L$6),2)) | M27: =IF(OR($A27="",M$6=""),"",ROUND(SUMIFS(流水收入,流水账户,$A27,流水日期,M$6),2)) | N27: =IF(OR($A27="",N$6=""),"",ROUND(SUMIFS(流水支出,流水账户,$A27,流水日期,N$6),2)) | O27: =IF(OR($A27="",O$6=""),"",ROUND(SUMIFS(流水收入,流水账户,$A27,流水日期,O$6),2)) | P27: =IF(OR($A27="",P$6=""),"",ROUND(SUMIFS(流水支出,流水账户,$A27,流水日期,P$6),2)) | Q27: =IF(OR($A27="",Q$6=""),"",ROUND(SUMIFS(流水收入,流水账户,$A27,流水日期,Q$6),2)) | R27: =IF(OR($A27="",R$6=""),"",ROUND(SUMIFS(流水支出,流水账户,$A27,流水日期,R$6),2)) | S27: =IF(OR($A27="",S$6=""),"",ROUND(SUMIFS(流水收入,流水账户,$A27,流水日期,S$6),2)) | T27: =IF(OR($A27="",T$6=""),"",ROUND(SUMIFS(流水支出,流水账户,$A27,流水日期,T$6),2)) | U27: =IF(OR($A27="",U$6=""),"",ROUND(SUMIFS(流水收入,流水账户,$A27,流水日期,U$6),2)) | V27: =IF(OR($A27="",V$6=""),"",ROUND(SUMIFS(流水支出,流水账户,$A27,流水日期,V$6),2)) | W27: =IF(OR($A27="",W$6=""),"",ROUND(SUMIFS(流水收入,流水账户,$A27,流水日期,W$6),2)) | X27: =IF(OR($A27="",X$6=""),"",ROUND(SUMIFS(流水支出,流水账户,$A27,流水日期,X$6),2)) | Y27: =IF(OR($A27="",Y$6=""),"",ROUND(SUMIFS(流水收入,流水账户,$A27,流水日期,Y$6),2)) | Z27: =IF(OR($A27="",Z$6=""),"",ROUND(SUMIFS(流水支出,流水账户,$A27,流水日期,Z$6),2)) | AA27: =IF(OR($A27="",AA$6=""),"",ROUND(SUMIFS(流水收入,流水账户,$A27,流水日期,AA$6),2)) | AB27: =IF(OR($A27="",AB$6=""),"",ROUND(SUMIFS(流水支出,流水账户,$A27,流水日期,AB$6),2)) | AC27: =IF(OR($A27="",AC$6=""),"",ROUND(SUMIFS(流水收入,流水账户,$A27,流水日期,AC$6),2)) | AD27: =IF(OR($A27="",AD$6=""),"",ROUND(SUMIFS(流水支出,流水账户,$A27,流水日期,AD$6),2)) | AE27: =IF(OR($A27="",AE$6=""),"",ROUND(SUMIFS(流水收入,流水账户,$A27,流水日期,AE$6),2)) | AF27: =IF(OR($A27="",AF$6=""),"",ROUND(SUMIFS(流水支出,流水账户,$A27,流水日期,AF$6),2)) | AG27: =IF(OR($A27="",AG$6=""),"",ROUND(SUMIFS(流水收入,流水账户,$A27,流水日期,AG$6),2)) | AH27: =IF(OR($A27="",AH$6=""),"",ROUND(SUMIFS(流水支出,流水账户,$A27,流水日期,AH$6),2)) | AI27: =IF(OR($A27="",AI$6=""),"",ROUND(SUMIFS(流水收入,流水账户,$A27,流水日期,AI$6),2)) | AJ27: =IF(OR($A27="",AJ$6=""),"",ROUND(SUMIFS(流水支出,流水账户,$A27,流水日期,AJ$6),2)) | AK27: =IF(OR($A27="",AK$6=""),"",ROUND(SUMIFS(流水收入,流水账户,$A27,流水日期,AK$6),2)) | AL27: =IF(OR($A27="",AL$6=""),"",ROUND(SUMIFS(流水支出,流水账户,$A27,流水日期,AL$6),2)) | AM27: =IF(OR($A27="",AM$6=""),"",ROUND(SUMIFS(流水收入,流水账户,$A27,流水日期,AM$6),2)) | AN27: =IF(OR($A27="",AN$6=""),"",ROUND(SUMIFS(流水支出,流水账户,$A27,流水日期,AN$6),2)) | AO27: =IF(OR($A27="",AO$6=""),"",ROUND(SUMIFS(流水收入,流水账户,$A27,流水日期,AO$6),2)) | AP27: =IF(OR($A27="",AP$6=""),"",ROUND(SUMIFS(流水支出,流水账户,$A27,流水日期,AP$6),2)) | AQ27: =IF(OR($A27="",AQ$6=""),"",ROUND(SUMIFS(流水收入,流水账户,$A27,流水日期,AQ$6),2)) | AR27: =IF(OR($A27="",AR$6=""),"",ROUND(SUMIFS(流水支出,流水账户,$A27,流水日期,AR$6),2)) | AS27: =IF(OR($A27="",AS$6=""),"",ROUND(SUMIFS(流水收入,流水账户,$A27,流水日期,AS$6),2)) | AT27: =IF(OR($A27="",AT$6=""),"",ROUND(SUMIFS(流水支出,流水账户,$A27,流水日期,AT$6),2)) | AU27: =IF(OR($A27="",AU$6=""),"",ROUND(SUMIFS(流水收入,流水账户,$A27,流水日期,AU$6),2)) | AV27: =IF(OR($A27="",AV$6=""),"",ROUND(SUMIFS(流水支出,流水账户,$A27,流水日期,AV$6),2)) | AW27: =IF(OR($A27="",AW$6=""),"",ROUND(SUMIFS(流水收入,流水账户,$A27,流水日期,AW$6),2)) | AX27: =IF(OR($A27="",AX$6=""),"",ROUND(SUMIFS(流水支出,流水账户,$A27,流水日期,AX$6),2)) | AY27: =IF(OR($A27="",AY$6=""),"",ROUND(SUMIFS(流水收入,流水账户,$A27,流水日期,AY$6),2)) | AZ27: =IF(OR($A27="",AZ$6=""),"",ROUND(SUMIFS(流水支出,流水账户,$A27,流水日期,AZ$6),2)) | BA27: =IF(OR($A27="",BA$6=""),"",ROUND(SUMIFS(流水收入,流水账户,$A27,流水日期,BA$6),2)) | BB27: =IF(OR($A27="",BB$6=""),"",ROUND(SUMIFS(流水支出,流水账户,$A27,流水日期,BB$6),2)) | BC27: =IF(OR($A27="",BC$6=""),"",ROUND(SUMIFS(流水收入,流水账户,$A27,流水日期,BC$6),2)) | BD27: =IF(OR($A27="",BD$6=""),"",ROUND(SUMIFS(流水支出,流水账户,$A27,流水日期,BD$6),2)) | BE27: =IF(OR($A27="",BE$6=""),"",ROUND(SUMIFS(流水收入,流水账户,$A27,流水日期,BE$6),2)) | BF27: =IF(OR($A27="",BF$6=""),"",ROUND(SUMIFS(流水支出,流水账户,$A27,流水日期,BF$6),2)) | BG27: =IF(OR($A27="",BG$6=""),"",ROUND(SUMIFS(流水收入,流水账户,$A27,流水日期,BG$6),2)) | BH27: =IF(OR($A27="",BH$6=""),"",ROUND(SUMIFS(流水支出,流水账户,$A27,流水日期,BH$6),2)) | BI27: =IF(OR($A27="",BI$6=""),"",ROUND(SUMIFS(流水收入,流水账户,$A27,流水日期,BI$6),2)) | BJ27: =IF(OR($A27="",BJ$6=""),"",ROUND(SUMIFS(流水支出,流水账户,$A27,流水日期,BJ$6),2)) | BK27: =IF(OR($A27="",BK$6=""),"",ROUND(SUMIFS(流水收入,流水账户,$A27,流水日期,BK$6),2)) | BL27: =IF(OR($A27="",BL$6=""),"",ROUND(SUMIFS(流水支出,流水账户,$A27,流水日期,BL$6),2)) | BM27: =IF($A27="","",ROUND(SUMIF($C$7:$BL$7,"收款",C27:BL27),2)) | BN27: =IF($A27="","",ROUND(SUMIF($C$7:$BL$7,"付款",C27:BL27),2)) | BO27: =IF($A27="","",ROUND(N($B27)+N(BM27)-N(BN27),2))
A28: =IF(基础资料!$B$25="","",基础资料!$B$25) | B28: =IF(OR($A28="",NOT(ISNUMBER($H$3))),"",ROUND(SUMIF(账户表,$A28,账户期初)+SUMIFS(流水收入,流水账户,$A28,流水日期,"<"&$B$3)-SUMIFS(流水支出,流水账户,$A28,流水日期,"<"&$B$3),2)) | C28: =IF(OR($A28="",C$6=""),"",ROUND(SUMIFS(流水收入,流水账户,$A28,流水日期,C$6),2)) | D28: =IF(OR($A28="",D$6=""),"",ROUND(SUMIFS(流水支出,流水账户,$A28,流水日期,D$6),2)) | E28: =IF(OR($A28="",E$6=""),"",ROUND(SUMIFS(流水收入,流水账户,$A28,流水日期,E$6),2)) | F28: =IF(OR($A28="",F$6=""),"",ROUND(SUMIFS(流水支出,流水账户,$A28,流水日期,F$6),2)) | G28: =IF(OR($A28="",G$6=""),"",ROUND(SUMIFS(流水收入,流水账户,$A28,流水日期,G$6),2)) | H28: =IF(OR($A28="",H$6=""),"",ROUND(SUMIFS(流水支出,流水账户,$A28,流水日期,H$6),2)) | I28: =IF(OR($A28="",I$6=""),"",ROUND(SUMIFS(流水收入,流水账户,$A28,流水日期,I$6),2)) | J28: =IF(OR($A28="",J$6=""),"",ROUND(SUMIFS(流水支出,流水账户,$A28,流水日期,J$6),2)) | K28: =IF(OR($A28="",K$6=""),"",ROUND(SUMIFS(流水收入,流水账户,$A28,流水日期,K$6),2)) | L28: =IF(OR($A28="",L$6=""),"",ROUND(SUMIFS(流水支出,流水账户,$A28,流水日期,L$6),2)) | M28: =IF(OR($A28="",M$6=""),"",ROUND(SUMIFS(流水收入,流水账户,$A28,流水日期,M$6),2)) | N28: =IF(OR($A28="",N$6=""),"",ROUND(SUMIFS(流水支出,流水账户,$A28,流水日期,N$6),2)) | O28: =IF(OR($A28="",O$6=""),"",ROUND(SUMIFS(流水收入,流水账户,$A28,流水日期,O$6),2)) | P28: =IF(OR($A28="",P$6=""),"",ROUND(SUMIFS(流水支出,流水账户,$A28,流水日期,P$6),2)) | Q28: =IF(OR($A28="",Q$6=""),"",ROUND(SUMIFS(流水收入,流水账户,$A28,流水日期,Q$6),2)) | R28: =IF(OR($A28="",R$6=""),"",ROUND(SUMIFS(流水支出,流水账户,$A28,流水日期,R$6),2)) | S28: =IF(OR($A28="",S$6=""),"",ROUND(SUMIFS(流水收入,流水账户,$A28,流水日期,S$6),2)) | T28: =IF(OR($A28="",T$6=""),"",ROUND(SUMIFS(流水支出,流水账户,$A28,流水日期,T$6),2)) | U28: =IF(OR($A28="",U$6=""),"",ROUND(SUMIFS(流水收入,流水账户,$A28,流水日期,U$6),2)) | V28: =IF(OR($A28="",V$6=""),"",ROUND(SUMIFS(流水支出,流水账户,$A28,流水日期,V$6),2)) | W28: =IF(OR($A28="",W$6=""),"",ROUND(SUMIFS(流水收入,流水账户,$A28,流水日期,W$6),2)) | X28: =IF(OR($A28="",X$6=""),"",ROUND(SUMIFS(流水支出,流水账户,$A28,流水日期,X$6),2)) | Y28: =IF(OR($A28="",Y$6=""),"",ROUND(SUMIFS(流水收入,流水账户,$A28,流水日期,Y$6),2)) | Z28: =IF(OR($A28="",Z$6=""),"",ROUND(SUMIFS(流水支出,流水账户,$A28,流水日期,Z$6),2)) | AA28: =IF(OR($A28="",AA$6=""),"",ROUND(SUMIFS(流水收入,流水账户,$A28,流水日期,AA$6),2)) | AB28: =IF(OR($A28="",AB$6=""),"",ROUND(SUMIFS(流水支出,流水账户,$A28,流水日期,AB$6),2)) | AC28: =IF(OR($A28="",AC$6=""),"",ROUND(SUMIFS(流水收入,流水账户,$A28,流水日期,AC$6),2)) | AD28: =IF(OR($A28="",AD$6=""),"",ROUND(SUMIFS(流水支出,流水账户,$A28,流水日期,AD$6),2)) | AE28: =IF(OR($A28="",AE$6=""),"",ROUND(SUMIFS(流水收入,流水账户,$A28,流水日期,AE$6),2)) | AF28: =IF(OR($A28="",AF$6=""),"",ROUND(SUMIFS(流水支出,流水账户,$A28,流水日期,AF$6),2)) | AG28: =IF(OR($A28="",AG$6=""),"",ROUND(SUMIFS(流水收入,流水账户,$A28,流水日期,AG$6),2)) | AH28: =IF(OR($A28="",AH$6=""),"",ROUND(SUMIFS(流水支出,流水账户,$A28,流水日期,AH$6),2)) | AI28: =IF(OR($A28="",AI$6=""),"",ROUND(SUMIFS(流水收入,流水账户,$A28,流水日期,AI$6),2)) | AJ28: =IF(OR($A28="",AJ$6=""),"",ROUND(SUMIFS(流水支出,流水账户,$A28,流水日期,AJ$6),2)) | AK28: =IF(OR($A28="",AK$6=""),"",ROUND(SUMIFS(流水收入,流水账户,$A28,流水日期,AK$6),2)) | AL28: =IF(OR($A28="",AL$6=""),"",ROUND(SUMIFS(流水支出,流水账户,$A28,流水日期,AL$6),2)) | AM28: =IF(OR($A28="",AM$6=""),"",ROUND(SUMIFS(流水收入,流水账户,$A28,流水日期,AM$6),2)) | AN28: =IF(OR($A28="",AN$6=""),"",ROUND(SUMIFS(流水支出,流水账户,$A28,流水日期,AN$6),2)) | AO28: =IF(OR($A28="",AO$6=""),"",ROUND(SUMIFS(流水收入,流水账户,$A28,流水日期,AO$6),2)) | AP28: =IF(OR($A28="",AP$6=""),"",ROUND(SUMIFS(流水支出,流水账户,$A28,流水日期,AP$6),2)) | AQ28: =IF(OR($A28="",AQ$6=""),"",ROUND(SUMIFS(流水收入,流水账户,$A28,流水日期,AQ$6),2)) | AR28: =IF(OR($A28="",AR$6=""),"",ROUND(SUMIFS(流水支出,流水账户,$A28,流水日期,AR$6),2)) | AS28: =IF(OR($A28="",AS$6=""),"",ROUND(SUMIFS(流水收入,流水账户,$A28,流水日期,AS$6),2)) | AT28: =IF(OR($A28="",AT$6=""),"",ROUND(SUMIFS(流水支出,流水账户,$A28,流水日期,AT$6),2)) | AU28: =IF(OR($A28="",AU$6=""),"",ROUND(SUMIFS(流水收入,流水账户,$A28,流水日期,AU$6),2)) | AV28: =IF(OR($A28="",AV$6=""),"",ROUND(SUMIFS(流水支出,流水账户,$A28,流水日期,AV$6),2)) | AW28: =IF(OR($A28="",AW$6=""),"",ROUND(SUMIFS(流水收入,流水账户,$A28,流水日期,AW$6),2)) | AX28: =IF(OR($A28="",AX$6=""),"",ROUND(SUMIFS(流水支出,流水账户,$A28,流水日期,AX$6),2)) | AY28: =IF(OR($A28="",AY$6=""),"",ROUND(SUMIFS(流水收入,流水账户,$A28,流水日期,AY$6),2)) | AZ28: =IF(OR($A28="",AZ$6=""),"",ROUND(SUMIFS(流水支出,流水账户,$A28,流水日期,AZ$6),2)) | BA28: =IF(OR($A28="",BA$6=""),"",ROUND(SUMIFS(流水收入,流水账户,$A28,流水日期,BA$6),2)) | BB28: =IF(OR($A28="",BB$6=""),"",ROUND(SUMIFS(流水支出,流水账户,$A28,流水日期,BB$6),2)) | BC28: =IF(OR($A28="",BC$6=""),"",ROUND(SUMIFS(流水收入,流水账户,$A28,流水日期,BC$6),2)) | BD28: =IF(OR($A28="",BD$6=""),"",ROUND(SUMIFS(流水支出,流水账户,$A28,流水日期,BD$6),2)) | BE28: =IF(OR($A28="",BE$6=""),"",ROUND(SUMIFS(流水收入,流水账户,$A28,流水日期,BE$6),2)) | BF28: =IF(OR($A28="",BF$6=""),"",ROUND(SUMIFS(流水支出,流水账户,$A28,流水日期,BF$6),2)) | BG28: =IF(OR($A28="",BG$6=""),"",ROUND(SUMIFS(流水收入,流水账户,$A28,流水日期,BG$6),2)) | BH28: =IF(OR($A28="",BH$6=""),"",ROUND(SUMIFS(流水支出,流水账户,$A28,流水日期,BH$6),2)) | BI28: =IF(OR($A28="",BI$6=""),"",ROUND(SUMIFS(流水收入,流水账户,$A28,流水日期,BI$6),2)) | BJ28: =IF(OR($A28="",BJ$6=""),"",ROUND(SUMIFS(流水支出,流水账户,$A28,流水日期,BJ$6),2)) | BK28: =IF(OR($A28="",BK$6=""),"",ROUND(SUMIFS(流水收入,流水账户,$A28,流水日期,BK$6),2)) | BL28: =IF(OR($A28="",BL$6=""),"",ROUND(SUMIFS(流水支出,流水账户,$A28,流水日期,BL$6),2)) | BM28: =IF($A28="","",ROUND(SUMIF($C$7:$BL$7,"收款",C28:BL28),2)) | BN28: =IF($A28="","",ROUND(SUMIF($C$7:$BL$7,"付款",C28:BL28),2)) | BO28: =IF($A28="","",ROUND(N($B28)+N(BM28)-N(BN28),2))
A29: =IF(基础资料!$B$26="","",基础资料!$B$26) | B29: =IF(OR($A29="",NOT(ISNUMBER($H$3))),"",ROUND(SUMIF(账户表,$A29,账户期初)+SUMIFS(流水收入,流水账户,$A29,流水日期,"<"&$B$3)-SUMIFS(流水支出,流水账户,$A29,流水日期,"<"&$B$3),2)) | C29: =IF(OR($A29="",C$6=""),"",ROUND(SUMIFS(流水收入,流水账户,$A29,流水日期,C$6),2)) | D29: =IF(OR($A29="",D$6=""),"",ROUND(SUMIFS(流水支出,流水账户,$A29,流水日期,D$6),2)) | E29: =IF(OR($A29="",E$6=""),"",ROUND(SUMIFS(流水收入,流水账户,$A29,流水日期,E$6),2)) | F29: =IF(OR($A29="",F$6=""),"",ROUND(SUMIFS(流水支出,流水账户,$A29,流水日期,F$6),2)) | G29: =IF(OR($A29="",G$6=""),"",ROUND(SUMIFS(流水收入,流水账户,$A29,流水日期,G$6),2)) | H29: =IF(OR($A29="",H$6=""),"",ROUND(SUMIFS(流水支出,流水账户,$A29,流水日期,H$6),2)) | I29: =IF(OR($A29="",I$6=""),"",ROUND(SUMIFS(流水收入,流水账户,$A29,流水日期,I$6),2)) | J29: =IF(OR($A29="",J$6=""),"",ROUND(SUMIFS(流水支出,流水账户,$A29,流水日期,J$6),2)) | K29: =IF(OR($A29="",K$6=""),"",ROUND(SUMIFS(流水收入,流水账户,$A29,流水日期,K$6),2)) | L29: =IF(OR($A29="",L$6=""),"",ROUND(SUMIFS(流水支出,流水账户,$A29,流水日期,L$6),2)) | M29: =IF(OR($A29="",M$6=""),"",ROUND(SUMIFS(流水收入,流水账户,$A29,流水日期,M$6),2)) | N29: =IF(OR($A29="",N$6=""),"",ROUND(SUMIFS(流水支出,流水账户,$A29,流水日期,N$6),2)) | O29: =IF(OR($A29="",O$6=""),"",ROUND(SUMIFS(流水收入,流水账户,$A29,流水日期,O$6),2)) | P29: =IF(OR($A29="",P$6=""),"",ROUND(SUMIFS(流水支出,流水账户,$A29,流水日期,P$6),2)) | Q29: =IF(OR($A29="",Q$6=""),"",ROUND(SUMIFS(流水收入,流水账户,$A29,流水日期,Q$6),2)) | R29: =IF(OR($A29="",R$6=""),"",ROUND(SUMIFS(流水支出,流水账户,$A29,流水日期,R$6),2)) | S29: =IF(OR($A29="",S$6=""),"",ROUND(SUMIFS(流水收入,流水账户,$A29,流水日期,S$6),2)) | T29: =IF(OR($A29="",T$6=""),"",ROUND(SUMIFS(流水支出,流水账户,$A29,流水日期,T$6),2)) | U29: =IF(OR($A29="",U$6=""),"",ROUND(SUMIFS(流水收入,流水账户,$A29,流水日期,U$6),2)) | V29: =IF(OR($A29="",V$6=""),"",ROUND(SUMIFS(流水支出,流水账户,$A29,流水日期,V$6),2)) | W29: =IF(OR($A29="",W$6=""),"",ROUND(SUMIFS(流水收入,流水账户,$A29,流水日期,W$6),2)) | X29: =IF(OR($A29="",X$6=""),"",ROUND(SUMIFS(流水支出,流水账户,$A29,流水日期,X$6),2)) | Y29: =IF(OR($A29="",Y$6=""),"",ROUND(SUMIFS(流水收入,流水账户,$A29,流水日期,Y$6),2)) | Z29: =IF(OR($A29="",Z$6=""),"",ROUND(SUMIFS(流水支出,流水账户,$A29,流水日期,Z$6),2)) | AA29: =IF(OR($A29="",AA$6=""),"",ROUND(SUMIFS(流水收入,流水账户,$A29,流水日期,AA$6),2)) | AB29: =IF(OR($A29="",AB$6=""),"",ROUND(SUMIFS(流水支出,流水账户,$A29,流水日期,AB$6),2)) | AC29: =IF(OR($A29="",AC$6=""),"",ROUND(SUMIFS(流水收入,流水账户,$A29,流水日期,AC$6),2)) | AD29: =IF(OR($A29="",AD$6=""),"",ROUND(SUMIFS(流水支出,流水账户,$A29,流水日期,AD$6),2)) | AE29: =IF(OR($A29="",AE$6=""),"",ROUND(SUMIFS(流水收入,流水账户,$A29,流水日期,AE$6),2)) | AF29: =IF(OR($A29="",AF$6=""),"",ROUND(SUMIFS(流水支出,流水账户,$A29,流水日期,AF$6),2)) | AG29: =IF(OR($A29="",AG$6=""),"",ROUND(SUMIFS(流水收入,流水账户,$A29,流水日期,AG$6),2)) | AH29: =IF(OR($A29="",AH$6=""),"",ROUND(SUMIFS(流水支出,流水账户,$A29,流水日期,AH$6),2)) | AI29: =IF(OR($A29="",AI$6=""),"",ROUND(SUMIFS(流水收入,流水账户,$A29,流水日期,AI$6),2)) | AJ29: =IF(OR($A29="",AJ$6=""),"",ROUND(SUMIFS(流水支出,流水账户,$A29,流水日期,AJ$6),2)) | AK29: =IF(OR($A29="",AK$6=""),"",ROUND(SUMIFS(流水收入,流水账户,$A29,流水日期,AK$6),2)) | AL29: =IF(OR($A29="",AL$6=""),"",ROUND(SUMIFS(流水支出,流水账户,$A29,流水日期,AL$6),2)) | AM29: =IF(OR($A29="",AM$6=""),"",ROUND(SUMIFS(流水收入,流水账户,$A29,流水日期,AM$6),2)) | AN29: =IF(OR($A29="",AN$6=""),"",ROUND(SUMIFS(流水支出,流水账户,$A29,流水日期,AN$6),2)) | AO29: =IF(OR($A29="",AO$6=""),"",ROUND(SUMIFS(流水收入,流水账户,$A29,流水日期,AO$6),2)) | AP29: =IF(OR($A29="",AP$6=""),"",ROUND(SUMIFS(流水支出,流水账户,$A29,流水日期,AP$6),2)) | AQ29: =IF(OR($A29="",AQ$6=""),"",ROUND(SUMIFS(流水收入,流水账户,$A29,流水日期,AQ$6),2)) | AR29: =IF(OR($A29="",AR$6=""),"",ROUND(SUMIFS(流水支出,流水账户,$A29,流水日期,AR$6),2)) | AS29: =IF(OR($A29="",AS$6=""),"",ROUND(SUMIFS(流水收入,流水账户,$A29,流水日期,AS$6),2)) | AT29: =IF(OR($A29="",AT$6=""),"",ROUND(SUMIFS(流水支出,流水账户,$A29,流水日期,AT$6),2)) | AU29: =IF(OR($A29="",AU$6=""),"",ROUND(SUMIFS(流水收入,流水账户,$A29,流水日期,AU$6),2)) | AV29: =IF(OR($A29="",AV$6=""),"",ROUND(SUMIFS(流水支出,流水账户,$A29,流水日期,AV$6),2)) | AW29: =IF(OR($A29="",AW$6=""),"",ROUND(SUMIFS(流水收入,流水账户,$A29,流水日期,AW$6),2)) | AX29: =IF(OR($A29="",AX$6=""),"",ROUND(SUMIFS(流水支出,流水账户,$A29,流水日期,AX$6),2)) | AY29: =IF(OR($A29="",AY$6=""),"",ROUND(SUMIFS(流水收入,流水账户,$A29,流水日期,AY$6),2)) | AZ29: =IF(OR($A29="",AZ$6=""),"",ROUND(SUMIFS(流水支出,流水账户,$A29,流水日期,AZ$6),2)) | BA29: =IF(OR($A29="",BA$6=""),"",ROUND(SUMIFS(流水收入,流水账户,$A29,流水日期,BA$6),2)) | BB29: =IF(OR($A29="",BB$6=""),"",ROUND(SUMIFS(流水支出,流水账户,$A29,流水日期,BB$6),2)) | BC29: =IF(OR($A29="",BC$6=""),"",ROUND(SUMIFS(流水收入,流水账户,$A29,流水日期,BC$6),2)) | BD29: =IF(OR($A29="",BD$6=""),"",ROUND(SUMIFS(流水支出,流水账户,$A29,流水日期,BD$6),2)) | BE29: =IF(OR($A29="",BE$6=""),"",ROUND(SUMIFS(流水收入,流水账户,$A29,流水日期,BE$6),2)) | BF29: =IF(OR($A29="",BF$6=""),"",ROUND(SUMIFS(流水支出,流水账户,$A29,流水日期,BF$6),2)) | BG29: =IF(OR($A29="",BG$6=""),"",ROUND(SUMIFS(流水收入,流水账户,$A29,流水日期,BG$6),2)) | BH29: =IF(OR($A29="",BH$6=""),"",ROUND(SUMIFS(流水支出,流水账户,$A29,流水日期,BH$6),2)) | BI29: =IF(OR($A29="",BI$6=""),"",ROUND(SUMIFS(流水收入,流水账户,$A29,流水日期,BI$6),2)) | BJ29: =IF(OR($A29="",BJ$6=""),"",ROUND(SUMIFS(流水支出,流水账户,$A29,流水日期,BJ$6),2)) | BK29: =IF(OR($A29="",BK$6=""),"",ROUND(SUMIFS(流水收入,流水账户,$A29,流水日期,BK$6),2)) | BL29: =IF(OR($A29="",BL$6=""),"",ROUND(SUMIFS(流水支出,流水账户,$A29,流水日期,BL$6),2)) | BM29: =IF($A29="","",ROUND(SUMIF($C$7:$BL$7,"收款",C29:BL29),2)) | BN29: =IF($A29="","",ROUND(SUMIF($C$7:$BL$7,"付款",C29:BL29),2)) | BO29: =IF($A29="","",ROUND(N($B29)+N(BM29)-N(BN29),2))
A30: =IF(基础资料!$B$27="","",基础资料!$B$27) | B30: =IF(OR($A30="",NOT(ISNUMBER($H$3))),"",ROUND(SUMIF(账户表,$A30,账户期初)+SUMIFS(流水收入,流水账户,$A30,流水日期,"<"&$B$3)-SUMIFS(流水支出,流水账户,$A30,流水日期,"<"&$B$3),2)) | C30: =IF(OR($A30="",C$6=""),"",ROUND(SUMIFS(流水收入,流水账户,$A30,流水日期,C$6),2)) | D30: =IF(OR($A30="",D$6=""),"",ROUND(SUMIFS(流水支出,流水账户,$A30,流水日期,D$6),2)) | E30: =IF(OR($A30="",E$6=""),"",ROUND(SUMIFS(流水收入,流水账户,$A30,流水日期,E$6),2)) | F30: =IF(OR($A30="",F$6=""),"",ROUND(SUMIFS(流水支出,流水账户,$A30,流水日期,F$6),2)) | G30: =IF(OR($A30="",G$6=""),"",ROUND(SUMIFS(流水收入,流水账户,$A30,流水日期,G$6),2)) | H30: =IF(OR($A30="",H$6=""),"",ROUND(SUMIFS(流水支出,流水账户,$A30,流水日期,H$6),2)) | I30: =IF(OR($A30="",I$6=""),"",ROUND(SUMIFS(流水收入,流水账户,$A30,流水日期,I$6),2)) | J30: =IF(OR($A30="",J$6=""),"",ROUND(SUMIFS(流水支出,流水账户,$A30,流水日期,J$6),2)) | K30: =IF(OR($A30="",K$6=""),"",ROUND(SUMIFS(流水收入,流水账户,$A30,流水日期,K$6),2)) | L30: =IF(OR($A30="",L$6=""),"",ROUND(SUMIFS(流水支出,流水账户,$A30,流水日期,L$6),2)) | M30: =IF(OR($A30="",M$6=""),"",ROUND(SUMIFS(流水收入,流水账户,$A30,流水日期,M$6),2)) | N30: =IF(OR($A30="",N$6=""),"",ROUND(SUMIFS(流水支出,流水账户,$A30,流水日期,N$6),2)) | O30: =IF(OR($A30="",O$6=""),"",ROUND(SUMIFS(流水收入,流水账户,$A30,流水日期,O$6),2)) | P30: =IF(OR($A30="",P$6=""),"",ROUND(SUMIFS(流水支出,流水账户,$A30,流水日期,P$6),2)) | Q30: =IF(OR($A30="",Q$6=""),"",ROUND(SUMIFS(流水收入,流水账户,$A30,流水日期,Q$6),2)) | R30: =IF(OR($A30="",R$6=""),"",ROUND(SUMIFS(流水支出,流水账户,$A30,流水日期,R$6),2)) | S30: =IF(OR($A30="",S$6=""),"",ROUND(SUMIFS(流水收入,流水账户,$A30,流水日期,S$6),2)) | T30: =IF(OR($A30="",T$6=""),"",ROUND(SUMIFS(流水支出,流水账户,$A30,流水日期,T$6),2)) | U30: =IF(OR($A30="",U$6=""),"",ROUND(SUMIFS(流水收入,流水账户,$A30,流水日期,U$6),2)) | V30: =IF(OR($A30="",V$6=""),"",ROUND(SUMIFS(流水支出,流水账户,$A30,流水日期,V$6),2)) | W30: =IF(OR($A30="",W$6=""),"",ROUND(SUMIFS(流水收入,流水账户,$A30,流水日期,W$6),2)) | X30: =IF(OR($A30="",X$6=""),"",ROUND(SUMIFS(流水支出,流水账户,$A30,流水日期,X$6),2)) | Y30: =IF(OR($A30="",Y$6=""),"",ROUND(SUMIFS(流水收入,流水账户,$A30,流水日期,Y$6),2)) | Z30: =IF(OR($A30="",Z$6=""),"",ROUND(SUMIFS(流水支出,流水账户,$A30,流水日期,Z$6),2)) | AA30: =IF(OR($A30="",AA$6=""),"",ROUND(SUMIFS(流水收入,流水账户,$A30,流水日期,AA$6),2)) | AB30: =IF(OR($A30="",AB$6=""),"",ROUND(SUMIFS(流水支出,流水账户,$A30,流水日期,AB$6),2)) | AC30: =IF(OR($A30="",AC$6=""),"",ROUND(SUMIFS(流水收入,流水账户,$A30,流水日期,AC$6),2)) | AD30: =IF(OR($A30="",AD$6=""),"",ROUND(SUMIFS(流水支出,流水账户,$A30,流水日期,AD$6),2)) | AE30: =IF(OR($A30="",AE$6=""),"",ROUND(SUMIFS(流水收入,流水账户,$A30,流水日期,AE$6),2)) | AF30: =IF(OR($A30="",AF$6=""),"",ROUND(SUMIFS(流水支出,流水账户,$A30,流水日期,AF$6),2)) | AG30: =IF(OR($A30="",AG$6=""),"",ROUND(SUMIFS(流水收入,流水账户,$A30,流水日期,AG$6),2)) | AH30: =IF(OR($A30="",AH$6=""),"",ROUND(SUMIFS(流水支出,流水账户,$A30,流水日期,AH$6),2)) | AI30: =IF(OR($A30="",AI$6=""),"",ROUND(SUMIFS(流水收入,流水账户,$A30,流水日期,AI$6),2)) | AJ30: =IF(OR($A30="",AJ$6=""),"",ROUND(SUMIFS(流水支出,流水账户,$A30,流水日期,AJ$6),2)) | AK30: =IF(OR($A30="",AK$6=""),"",ROUND(SUMIFS(流水收入,流水账户,$A30,流水日期,AK$6),2)) | AL30: =IF(OR($A30="",AL$6=""),"",ROUND(SUMIFS(流水支出,流水账户,$A30,流水日期,AL$6),2)) | AM30: =IF(OR($A30="",AM$6=""),"",ROUND(SUMIFS(流水收入,流水账户,$A30,流水日期,AM$6),2)) | AN30: =IF(OR($A30="",AN$6=""),"",ROUND(SUMIFS(流水支出,流水账户,$A30,流水日期,AN$6),2)) | AO30: =IF(OR($A30="",AO$6=""),"",ROUND(SUMIFS(流水收入,流水账户,$A30,流水日期,AO$6),2)) | AP30: =IF(OR($A30="",AP$6=""),"",ROUND(SUMIFS(流水支出,流水账户,$A30,流水日期,AP$6),2)) | AQ30: =IF(OR($A30="",AQ$6=""),"",ROUND(SUMIFS(流水收入,流水账户,$A30,流水日期,AQ$6),2)) | AR30: =IF(OR($A30="",AR$6=""),"",ROUND(SUMIFS(流水支出,流水账户,$A30,流水日期,AR$6),2)) | AS30: =IF(OR($A30="",AS$6=""),"",ROUND(SUMIFS(流水收入,流水账户,$A30,流水日期,AS$6),2)) | AT30: =IF(OR($A30="",AT$6=""),"",ROUND(SUMIFS(流水支出,流水账户,$A30,流水日期,AT$6),2)) | AU30: =IF(OR($A30="",AU$6=""),"",ROUND(SUMIFS(流水收入,流水账户,$A30,流水日期,AU$6),2)) | AV30: =IF(OR($A30="",AV$6=""),"",ROUND(SUMIFS(流水支出,流水账户,$A30,流水日期,AV$6),2)) | AW30: =IF(OR($A30="",AW$6=""),"",ROUND(SUMIFS(流水收入,流水账户,$A30,流水日期,AW$6),2)) | AX30: =IF(OR($A30="",AX$6=""),"",ROUND(SUMIFS(流水支出,流水账户,$A30,流水日期,AX$6),2)) | AY30: =IF(OR($A30="",AY$6=""),"",ROUND(SUMIFS(流水收入,流水账户,$A30,流水日期,AY$6),2)) | AZ30: =IF(OR($A30="",AZ$6=""),"",ROUND(SUMIFS(流水支出,流水账户,$A30,流水日期,AZ$6),2)) | BA30: =IF(OR($A30="",BA$6=""),"",ROUND(SUMIFS(流水收入,流水账户,$A30,流水日期,BA$6),2)) | BB30: =IF(OR($A30="",BB$6=""),"",ROUND(SUMIFS(流水支出,流水账户,$A30,流水日期,BB$6),2)) | BC30: =IF(OR($A30="",BC$6=""),"",ROUND(SUMIFS(流水收入,流水账户,$A30,流水日期,BC$6),2)) | BD30: =IF(OR($A30="",BD$6=""),"",ROUND(SUMIFS(流水支出,流水账户,$A30,流水日期,BD$6),2)) | BE30: =IF(OR($A30="",BE$6=""),"",ROUND(SUMIFS(流水收入,流水账户,$A30,流水日期,BE$6),2)) | BF30: =IF(OR($A30="",BF$6=""),"",ROUND(SUMIFS(流水支出,流水账户,$A30,流水日期,BF$6),2)) | BG30: =IF(OR($A30="",BG$6=""),"",ROUND(SUMIFS(流水收入,流水账户,$A30,流水日期,BG$6),2)) | BH30: =IF(OR($A30="",BH$6=""),"",ROUND(SUMIFS(流水支出,流水账户,$A30,流水日期,BH$6),2)) | BI30: =IF(OR($A30="",BI$6=""),"",ROUND(SUMIFS(流水收入,流水账户,$A30,流水日期,BI$6),2)) | BJ30: =IF(OR($A30="",BJ$6=""),"",ROUND(SUMIFS(流水支出,流水账户,$A30,流水日期,BJ$6),2)) | BK30: =IF(OR($A30="",BK$6=""),"",ROUND(SUMIFS(流水收入,流水账户,$A30,流水日期,BK$6),2)) | BL30: =IF(OR($A30="",BL$6=""),"",ROUND(SUMIFS(流水支出,流水账户,$A30,流水日期,BL$6),2)) | BM30: =IF($A30="","",ROUND(SUMIF($C$7:$BL$7,"收款",C30:BL30),2)) | BN30: =IF($A30="","",ROUND(SUMIF($C$7:$BL$7,"付款",C30:BL30),2)) | BO30: =IF($A30="","",ROUND(N($B30)+N(BM30)-N(BN30),2))
A31: =IF(基础资料!$B$28="","",基础资料!$B$28) | B31: =IF(OR($A31="",NOT(ISNUMBER($H$3))),"",ROUND(SUMIF(账户表,$A31,账户期初)+SUMIFS(流水收入,流水账户,$A31,流水日期,"<"&$B$3)-SUMIFS(流水支出,流水账户,$A31,流水日期,"<"&$B$3),2)) | C31: =IF(OR($A31="",C$6=""),"",ROUND(SUMIFS(流水收入,流水账户,$A31,流水日期,C$6),2)) | D31: =IF(OR($A31="",D$6=""),"",ROUND(SUMIFS(流水支出,流水账户,$A31,流水日期,D$6),2)) | E31: =IF(OR($A31="",E$6=""),"",ROUND(SUMIFS(流水收入,流水账户,$A31,流水日期,E$6),2)) | F31: =IF(OR($A31="",F$6=""),"",ROUND(SUMIFS(流水支出,流水账户,$A31,流水日期,F$6),2)) | G31: =IF(OR($A31="",G$6=""),"",ROUND(SUMIFS(流水收入,流水账户,$A31,流水日期,G$6),2)) | H31: =IF(OR($A31="",H$6=""),"",ROUND(SUMIFS(流水支出,流水账户,$A31,流水日期,H$6),2)) | I31: =IF(OR($A31="",I$6=""),"",ROUND(SUMIFS(流水收入,流水账户,$A31,流水日期,I$6),2)) | J31: =IF(OR($A31="",J$6=""),"",ROUND(SUMIFS(流水支出,流水账户,$A31,流水日期,J$6),2)) | K31: =IF(OR($A31="",K$6=""),"",ROUND(SUMIFS(流水收入,流水账户,$A31,流水日期,K$6),2)) | L31: =IF(OR($A31="",L$6=""),"",ROUND(SUMIFS(流水支出,流水账户,$A31,流水日期,L$6),2)) | M31: =IF(OR($A31="",M$6=""),"",ROUND(SUMIFS(流水收入,流水账户,$A31,流水日期,M$6),2)) | N31: =IF(OR($A31="",N$6=""),"",ROUND(SUMIFS(流水支出,流水账户,$A31,流水日期,N$6),2)) | O31: =IF(OR($A31="",O$6=""),"",ROUND(SUMIFS(流水收入,流水账户,$A31,流水日期,O$6),2)) | P31: =IF(OR($A31="",P$6=""),"",ROUND(SUMIFS(流水支出,流水账户,$A31,流水日期,P$6),2)) | Q31: =IF(OR($A31="",Q$6=""),"",ROUND(SUMIFS(流水收入,流水账户,$A31,流水日期,Q$6),2)) | R31: =IF(OR($A31="",R$6=""),"",ROUND(SUMIFS(流水支出,流水账户,$A31,流水日期,R$6),2)) | S31: =IF(OR($A31="",S$6=""),"",ROUND(SUMIFS(流水收入,流水账户,$A31,流水日期,S$6),2)) | T31: =IF(OR($A31="",T$6=""),"",ROUND(SUMIFS(流水支出,流水账户,$A31,流水日期,T$6),2)) | U31: =IF(OR($A31="",U$6=""),"",ROUND(SUMIFS(流水收入,流水账户,$A31,流水日期,U$6),2)) | V31: =IF(OR($A31="",V$6=""),"",ROUND(SUMIFS(流水支出,流水账户,$A31,流水日期,V$6),2)) | W31: =IF(OR($A31="",W$6=""),"",ROUND(SUMIFS(流水收入,流水账户,$A31,流水日期,W$6),2)) | X31: =IF(OR($A31="",X$6=""),"",ROUND(SUMIFS(流水支出,流水账户,$A31,流水日期,X$6),2)) | Y31: =IF(OR($A31="",Y$6=""),"",ROUND(SUMIFS(流水收入,流水账户,$A31,流水日期,Y$6),2)) | Z31: =IF(OR($A31="",Z$6=""),"",ROUND(SUMIFS(流水支出,流水账户,$A31,流水日期,Z$6),2)) | AA31: =IF(OR($A31="",AA$6=""),"",ROUND(SUMIFS(流水收入,流水账户,$A31,流水日期,AA$6),2)) | AB31: =IF(OR($A31="",AB$6=""),"",ROUND(SUMIFS(流水支出,流水账户,$A31,流水日期,AB$6),2)) | AC31: =IF(OR($A31="",AC$6=""),"",ROUND(SUMIFS(流水收入,流水账户,$A31,流水日期,AC$6),2)) | AD31: =IF(OR($A31="",AD$6=""),"",ROUND(SUMIFS(流水支出,流水账户,$A31,流水日期,AD$6),2)) | AE31: =IF(OR($A31="",AE$6=""),"",ROUND(SUMIFS(流水收入,流水账户,$A31,流水日期,AE$6),2)) | AF31: =IF(OR($A31="",AF$6=""),"",ROUND(SUMIFS(流水支出,流水账户,$A31,流水日期,AF$6),2)) | AG31: =IF(OR($A31="",AG$6=""),"",ROUND(SUMIFS(流水收入,流水账户,$A31,流水日期,AG$6),2)) | AH31: =IF(OR($A31="",AH$6=""),"",ROUND(SUMIFS(流水支出,流水账户,$A31,流水日期,AH$6),2)) | AI31: =IF(OR($A31="",AI$6=""),"",ROUND(SUMIFS(流水收入,流水账户,$A31,流水日期,AI$6),2)) | AJ31: =IF(OR($A31="",AJ$6=""),"",ROUND(SUMIFS(流水支出,流水账户,$A31,流水日期,AJ$6),2)) | AK31: =IF(OR($A31="",AK$6=""),"",ROUND(SUMIFS(流水收入,流水账户,$A31,流水日期,AK$6),2)) | AL31: =IF(OR($A31="",AL$6=""),"",ROUND(SUMIFS(流水支出,流水账户,$A31,流水日期,AL$6),2)) | AM31: =IF(OR($A31="",AM$6=""),"",ROUND(SUMIFS(流水收入,流水账户,$A31,流水日期,AM$6),2)) | AN31: =IF(OR($A31="",AN$6=""),"",ROUND(SUMIFS(流水支出,流水账户,$A31,流水日期,AN$6),2)) | AO31: =IF(OR($A31="",AO$6=""),"",ROUND(SUMIFS(流水收入,流水账户,$A31,流水日期,AO$6),2)) | AP31: =IF(OR($A31="",AP$6=""),"",ROUND(SUMIFS(流水支出,流水账户,$A31,流水日期,AP$6),2)) | AQ31: =IF(OR($A31="",AQ$6=""),"",ROUND(SUMIFS(流水收入,流水账户,$A31,流水日期,AQ$6),2)) | AR31: =IF(OR($A31="",AR$6=""),"",ROUND(SUMIFS(流水支出,流水账户,$A31,流水日期,AR$6),2)) | AS31: =IF(OR($A31="",AS$6=""),"",ROUND(SUMIFS(流水收入,流水账户,$A31,流水日期,AS$6),2)) | AT31: =IF(OR($A31="",AT$6=""),"",ROUND(SUMIFS(流水支出,流水账户,$A31,流水日期,AT$6),2)) | AU31: =IF(OR($A31="",AU$6=""),"",ROUND(SUMIFS(流水收入,流水账户,$A31,流水日期,AU$6),2)) | AV31: =IF(OR($A31="",AV$6=""),"",ROUND(SUMIFS(流水支出,流水账户,$A31,流水日期,AV$6),2)) | AW31: =IF(OR($A31="",AW$6=""),"",ROUND(SUMIFS(流水收入,流水账户,$A31,流水日期,AW$6),2)) | AX31: =IF(OR($A31="",AX$6=""),"",ROUND(SUMIFS(流水支出,流水账户,$A31,流水日期,AX$6),2)) | AY31: =IF(OR($A31="",AY$6=""),"",ROUND(SUMIFS(流水收入,流水账户,$A31,流水日期,AY$6),2)) | AZ31: =IF(OR($A31="",AZ$6=""),"",ROUND(SUMIFS(流水支出,流水账户,$A31,流水日期,AZ$6),2)) | BA31: =IF(OR($A31="",BA$6=""),"",ROUND(SUMIFS(流水收入,流水账户,$A31,流水日期,BA$6),2)) | BB31: =IF(OR($A31="",BB$6=""),"",ROUND(SUMIFS(流水支出,流水账户,$A31,流水日期,BB$6),2)) | BC31: =IF(OR($A31="",BC$6=""),"",ROUND(SUMIFS(流水收入,流水账户,$A31,流水日期,BC$6),2)) | BD31: =IF(OR($A31="",BD$6=""),"",ROUND(SUMIFS(流水支出,流水账户,$A31,流水日期,BD$6),2)) | BE31: =IF(OR($A31="",BE$6=""),"",ROUND(SUMIFS(流水收入,流水账户,$A31,流水日期,BE$6),2)) | BF31: =IF(OR($A31="",BF$6=""),"",ROUND(SUMIFS(流水支出,流水账户,$A31,流水日期,BF$6),2)) | BG31: =IF(OR($A31="",BG$6=""),"",ROUND(SUMIFS(流水收入,流水账户,$A31,流水日期,BG$6),2)) | BH31: =IF(OR($A31="",BH$6=""),"",ROUND(SUMIFS(流水支出,流水账户,$A31,流水日期,BH$6),2)) | BI31: =IF(OR($A31="",BI$6=""),"",ROUND(SUMIFS(流水收入,流水账户,$A31,流水日期,BI$6),2)) | BJ31: =IF(OR($A31="",BJ$6=""),"",ROUND(SUMIFS(流水支出,流水账户,$A31,流水日期,BJ$6),2)) | BK31: =IF(OR($A31="",BK$6=""),"",ROUND(SUMIFS(流水收入,流水账户,$A31,流水日期,BK$6),2)) | BL31: =IF(OR($A31="",BL$6=""),"",ROUND(SUMIFS(流水支出,流水账户,$A31,流水日期,BL$6),2)) | BM31: =IF($A31="","",ROUND(SUMIF($C$7:$BL$7,"收款",C31:BL31),2)) | BN31: =IF($A31="","",ROUND(SUMIF($C$7:$BL$7,"付款",C31:BL31),2)) | BO31: =IF($A31="","",ROUND(N($B31)+N(BM31)-N(BN31),2))
A32: =IF(基础资料!$B$29="","",基础资料!$B$29) | B32: =IF(OR($A32="",NOT(ISNUMBER($H$3))),"",ROUND(SUMIF(账户表,$A32,账户期初)+SUMIFS(流水收入,流水账户,$A32,流水日期,"<"&$B$3)-SUMIFS(流水支出,流水账户,$A32,流水日期,"<"&$B$3),2)) | C32: =IF(OR($A32="",C$6=""),"",ROUND(SUMIFS(流水收入,流水账户,$A32,流水日期,C$6),2)) | D32: =IF(OR($A32="",D$6=""),"",ROUND(SUMIFS(流水支出,流水账户,$A32,流水日期,D$6),2)) | E32: =IF(OR($A32="",E$6=""),"",ROUND(SUMIFS(流水收入,流水账户,$A32,流水日期,E$6),2)) | F32: =IF(OR($A32="",F$6=""),"",ROUND(SUMIFS(流水支出,流水账户,$A32,流水日期,F$6),2)) | G32: =IF(OR($A32="",G$6=""),"",ROUND(SUMIFS(流水收入,流水账户,$A32,流水日期,G$6),2)) | H32: =IF(OR($A32="",H$6=""),"",ROUND(SUMIFS(流水支出,流水账户,$A32,流水日期,H$6),2)) | I32: =IF(OR($A32="",I$6=""),"",ROUND(SUMIFS(流水收入,流水账户,$A32,流水日期,I$6),2)) | J32: =IF(OR($A32="",J$6=""),"",ROUND(SUMIFS(流水支出,流水账户,$A32,流水日期,J$6),2)) | K32: =IF(OR($A32="",K$6=""),"",ROUND(SUMIFS(流水收入,流水账户,$A32,流水日期,K$6),2)) | L32: =IF(OR($A32="",L$6=""),"",ROUND(SUMIFS(流水支出,流水账户,$A32,流水日期,L$6),2)) | M32: =IF(OR($A32="",M$6=""),"",ROUND(SUMIFS(流水收入,流水账户,$A32,流水日期,M$6),2)) | N32: =IF(OR($A32="",N$6=""),"",ROUND(SUMIFS(流水支出,流水账户,$A32,流水日期,N$6),2)) | O32: =IF(OR($A32="",O$6=""),"",ROUND(SUMIFS(流水收入,流水账户,$A32,流水日期,O$6),2)) | P32: =IF(OR($A32="",P$6=""),"",ROUND(SUMIFS(流水支出,流水账户,$A32,流水日期,P$6),2)) | Q32: =IF(OR($A32="",Q$6=""),"",ROUND(SUMIFS(流水收入,流水账户,$A32,流水日期,Q$6),2)) | R32: =IF(OR($A32="",R$6=""),"",ROUND(SUMIFS(流水支出,流水账户,$A32,流水日期,R$6),2)) | S32: =IF(OR($A32="",S$6=""),"",ROUND(SUMIFS(流水收入,流水账户,$A32,流水日期,S$6),2)) | T32: =IF(OR($A32="",T$6=""),"",ROUND(SUMIFS(流水支出,流水账户,$A32,流水日期,T$6),2)) | U32: =IF(OR($A32="",U$6=""),"",ROUND(SUMIFS(流水收入,流水账户,$A32,流水日期,U$6),2)) | V32: =IF(OR($A32="",V$6=""),"",ROUND(SUMIFS(流水支出,流水账户,$A32,流水日期,V$6),2)) | W32: =IF(OR($A32="",W$6=""),"",ROUND(SUMIFS(流水收入,流水账户,$A32,流水日期,W$6),2)) | X32: =IF(OR($A32="",X$6=""),"",ROUND(SUMIFS(流水支出,流水账户,$A32,流水日期,X$6),2)) | Y32: =IF(OR($A32="",Y$6=""),"",ROUND(SUMIFS(流水收入,流水账户,$A32,流水日期,Y$6),2)) | Z32: =IF(OR($A32="",Z$6=""),"",ROUND(SUMIFS(流水支出,流水账户,$A32,流水日期,Z$6),2)) | AA32: =IF(OR($A32="",AA$6=""),"",ROUND(SUMIFS(流水收入,流水账户,$A32,流水日期,AA$6),2)) | AB32: =IF(OR($A32="",AB$6=""),"",ROUND(SUMIFS(流水支出,流水账户,$A32,流水日期,AB$6),2)) | AC32: =IF(OR($A32="",AC$6=""),"",ROUND(SUMIFS(流水收入,流水账户,$A32,流水日期,AC$6),2)) | AD32: =IF(OR($A32="",AD$6=""),"",ROUND(SUMIFS(流水支出,流水账户,$A32,流水日期,AD$6),2)) | AE32: =IF(OR($A32="",AE$6=""),"",ROUND(SUMIFS(流水收入,流水账户,$A32,流水日期,AE$6),2)) | AF32: =IF(OR($A32="",AF$6=""),"",ROUND(SUMIFS(流水支出,流水账户,$A32,流水日期,AF$6),2)) | AG32: =IF(OR($A32="",AG$6=""),"",ROUND(SUMIFS(流水收入,流水账户,$A32,流水日期,AG$6),2)) | AH32: =IF(OR($A32="",AH$6=""),"",ROUND(SUMIFS(流水支出,流水账户,$A32,流水日期,AH$6),2)) | AI32: =IF(OR($A32="",AI$6=""),"",ROUND(SUMIFS(流水收入,流水账户,$A32,流水日期,AI$6),2)) | AJ32: =IF(OR($A32="",AJ$6=""),"",ROUND(SUMIFS(流水支出,流水账户,$A32,流水日期,AJ$6),2)) | AK32: =IF(OR($A32="",AK$6=""),"",ROUND(SUMIFS(流水收入,流水账户,$A32,流水日期,AK$6),2)) | AL32: =IF(OR($A32="",AL$6=""),"",ROUND(SUMIFS(流水支出,流水账户,$A32,流水日期,AL$6),2)) | AM32: =IF(OR($A32="",AM$6=""),"",ROUND(SUMIFS(流水收入,流水账户,$A32,流水日期,AM$6),2)) | AN32: =IF(OR($A32="",AN$6=""),"",ROUND(SUMIFS(流水支出,流水账户,$A32,流水日期,AN$6),2)) | AO32: =IF(OR($A32="",AO$6=""),"",ROUND(SUMIFS(流水收入,流水账户,$A32,流水日期,AO$6),2)) | AP32: =IF(OR($A32="",AP$6=""),"",ROUND(SUMIFS(流水支出,流水账户,$A32,流水日期,AP$6),2)) | AQ32: =IF(OR($A32="",AQ$6=""),"",ROUND(SUMIFS(流水收入,流水账户,$A32,流水日期,AQ$6),2)) | AR32: =IF(OR($A32="",AR$6=""),"",ROUND(SUMIFS(流水支出,流水账户,$A32,流水日期,AR$6),2)) | AS32: =IF(OR($A32="",AS$6=""),"",ROUND(SUMIFS(流水收入,流水账户,$A32,流水日期,AS$6),2)) | AT32: =IF(OR($A32="",AT$6=""),"",ROUND(SUMIFS(流水支出,流水账户,$A32,流水日期,AT$6),2)) | AU32: =IF(OR($A32="",AU$6=""),"",ROUND(SUMIFS(流水收入,流水账户,$A32,流水日期,AU$6),2)) | AV32: =IF(OR($A32="",AV$6=""),"",ROUND(SUMIFS(流水支出,流水账户,$A32,流水日期,AV$6),2)) | AW32: =IF(OR($A32="",AW$6=""),"",ROUND(SUMIFS(流水收入,流水账户,$A32,流水日期,AW$6),2)) | AX32: =IF(OR($A32="",AX$6=""),"",ROUND(SUMIFS(流水支出,流水账户,$A32,流水日期,AX$6),2)) | AY32: =IF(OR($A32="",AY$6=""),"",ROUND(SUMIFS(流水收入,流水账户,$A32,流水日期,AY$6),2)) | AZ32: =IF(OR($A32="",AZ$6=""),"",ROUND(SUMIFS(流水支出,流水账户,$A32,流水日期,AZ$6),2)) | BA32: =IF(OR($A32="",BA$6=""),"",ROUND(SUMIFS(流水收入,流水账户,$A32,流水日期,BA$6),2)) | BB32: =IF(OR($A32="",BB$6=""),"",ROUND(SUMIFS(流水支出,流水账户,$A32,流水日期,BB$6),2)) | BC32: =IF(OR($A32="",BC$6=""),"",ROUND(SUMIFS(流水收入,流水账户,$A32,流水日期,BC$6),2)) | BD32: =IF(OR($A32="",BD$6=""),"",ROUND(SUMIFS(流水支出,流水账户,$A32,流水日期,BD$6),2)) | BE32: =IF(OR($A32="",BE$6=""),"",ROUND(SUMIFS(流水收入,流水账户,$A32,流水日期,BE$6),2)) | BF32: =IF(OR($A32="",BF$6=""),"",ROUND(SUMIFS(流水支出,流水账户,$A32,流水日期,BF$6),2)) | BG32: =IF(OR($A32="",BG$6=""),"",ROUND(SUMIFS(流水收入,流水账户,$A32,流水日期,BG$6),2)) | BH32: =IF(OR($A32="",BH$6=""),"",ROUND(SUMIFS(流水支出,流水账户,$A32,流水日期,BH$6),2)) | BI32: =IF(OR($A32="",BI$6=""),"",ROUND(SUMIFS(流水收入,流水账户,$A32,流水日期,BI$6),2)) | BJ32: =IF(OR($A32="",BJ$6=""),"",ROUND(SUMIFS(流水支出,流水账户,$A32,流水日期,BJ$6),2)) | BK32: =IF(OR($A32="",BK$6=""),"",ROUND(SUMIFS(流水收入,流水账户,$A32,流水日期,BK$6),2)) | BL32: =IF(OR($A32="",BL$6=""),"",ROUND(SUMIFS(流水支出,流水账户,$A32,流水日期,BL$6),2)) | BM32: =IF($A32="","",ROUND(SUMIF($C$7:$BL$7,"收款",C32:BL32),2)) | BN32: =IF($A32="","",ROUND(SUMIF($C$7:$BL$7,"付款",C32:BL32),2)) | BO32: =IF($A32="","",ROUND(N($B32)+N(BM32)-N(BN32),2))
A33: =IF(基础资料!$B$30="","",基础资料!$B$30) | B33: =IF(OR($A33="",NOT(ISNUMBER($H$3))),"",ROUND(SUMIF(账户表,$A33,账户期初)+SUMIFS(流水收入,流水账户,$A33,流水日期,"<"&$B$3)-SUMIFS(流水支出,流水账户,$A33,流水日期,"<"&$B$3),2)) | C33: =IF(OR($A33="",C$6=""),"",ROUND(SUMIFS(流水收入,流水账户,$A33,流水日期,C$6),2)) | D33: =IF(OR($A33="",D$6=""),"",ROUND(SUMIFS(流水支出,流水账户,$A33,流水日期,D$6),2)) | E33: =IF(OR($A33="",E$6=""),"",ROUND(SUMIFS(流水收入,流水账户,$A33,流水日期,E$6),2)) | F33: =IF(OR($A33="",F$6=""),"",ROUND(SUMIFS(流水支出,流水账户,$A33,流水日期,F$6),2)) | G33: =IF(OR($A33="",G$6=""),"",ROUND(SUMIFS(流水收入,流水账户,$A33,流水日期,G$6),2)) | H33: =IF(OR($A33="",H$6=""),"",ROUND(SUMIFS(流水支出,流水账户,$A33,流水日期,H$6),2)) | I33: =IF(OR($A33="",I$6=""),"",ROUND(SUMIFS(流水收入,流水账户,$A33,流水日期,I$6),2)) | J33: =IF(OR($A33="",J$6=""),"",ROUND(SUMIFS(流水支出,流水账户,$A33,流水日期,J$6),2)) | K33: =IF(OR($A33="",K$6=""),"",ROUND(SUMIFS(流水收入,流水账户,$A33,流水日期,K$6),2)) | L33: =IF(OR($A33="",L$6=""),"",ROUND(SUMIFS(流水支出,流水账户,$A33,流水日期,L$6),2)) | M33: =IF(OR($A33="",M$6=""),"",ROUND(SUMIFS(流水收入,流水账户,$A33,流水日期,M$6),2)) | N33: =IF(OR($A33="",N$6=""),"",ROUND(SUMIFS(流水支出,流水账户,$A33,流水日期,N$6),2)) | O33: =IF(OR($A33="",O$6=""),"",ROUND(SUMIFS(流水收入,流水账户,$A33,流水日期,O$6),2)) | P33: =IF(OR($A33="",P$6=""),"",ROUND(SUMIFS(流水支出,流水账户,$A33,流水日期,P$6),2)) | Q33: =IF(OR($A33="",Q$6=""),"",ROUND(SUMIFS(流水收入,流水账户,$A33,流水日期,Q$6),2)) | R33: =IF(OR($A33="",R$6=""),"",ROUND(SUMIFS(流水支出,流水账户,$A33,流水日期,R$6),2)) | S33: =IF(OR($A33="",S$6=""),"",ROUND(SUMIFS(流水收入,流水账户,$A33,流水日期,S$6),2)) | T33: =IF(OR($A33="",T$6=""),"",ROUND(SUMIFS(流水支出,流水账户,$A33,流水日期,T$6),2)) | U33: =IF(OR($A33="",U$6=""),"",ROUND(SUMIFS(流水收入,流水账户,$A33,流水日期,U$6),2)) | V33: =IF(OR($A33="",V$6=""),"",ROUND(SUMIFS(流水支出,流水账户,$A33,流水日期,V$6),2)) | W33: =IF(OR($A33="",W$6=""),"",ROUND(SUMIFS(流水收入,流水账户,$A33,流水日期,W$6),2)) | X33: =IF(OR($A33="",X$6=""),"",ROUND(SUMIFS(流水支出,流水账户,$A33,流水日期,X$6),2)) | Y33: =IF(OR($A33="",Y$6=""),"",ROUND(SUMIFS(流水收入,流水账户,$A33,流水日期,Y$6),2)) | Z33: =IF(OR($A33="",Z$6=""),"",ROUND(SUMIFS(流水支出,流水账户,$A33,流水日期,Z$6),2)) | AA33: =IF(OR($A33="",AA$6=""),"",ROUND(SUMIFS(流水收入,流水账户,$A33,流水日期,AA$6),2)) | AB33: =IF(OR($A33="",AB$6=""),"",ROUND(SUMIFS(流水支出,流水账户,$A33,流水日期,AB$6),2)) | AC33: =IF(OR($A33="",AC$6=""),"",ROUND(SUMIFS(流水收入,流水账户,$A33,流水日期,AC$6),2)) | AD33: =IF(OR($A33="",AD$6=""),"",ROUND(SUMIFS(流水支出,流水账户,$A33,流水日期,AD$6),2)) | AE33: =IF(OR($A33="",AE$6=""),"",ROUND(SUMIFS(流水收入,流水账户,$A33,流水日期,AE$6),2)) | AF33: =IF(OR($A33="",AF$6=""),"",ROUND(SUMIFS(流水支出,流水账户,$A33,流水日期,AF$6),2)) | AG33: =IF(OR($A33="",AG$6=""),"",ROUND(SUMIFS(流水收入,流水账户,$A33,流水日期,AG$6),2)) | AH33: =IF(OR($A33="",AH$6=""),"",ROUND(SUMIFS(流水支出,流水账户,$A33,流水日期,AH$6),2)) | AI33: =IF(OR($A33="",AI$6=""),"",ROUND(SUMIFS(流水收入,流水账户,$A33,流水日期,AI$6),2)) | AJ33: =IF(OR($A33="",AJ$6=""),"",ROUND(SUMIFS(流水支出,流水账户,$A33,流水日期,AJ$6),2)) | AK33: =IF(OR($A33="",AK$6=""),"",ROUND(SUMIFS(流水收入,流水账户,$A33,流水日期,AK$6),2)) | AL33: =IF(OR($A33="",AL$6=""),"",ROUND(SUMIFS(流水支出,流水账户,$A33,流水日期,AL$6),2)) | AM33: =IF(OR($A33="",AM$6=""),"",ROUND(SUMIFS(流水收入,流水账户,$A33,流水日期,AM$6),2)) | AN33: =IF(OR($A33="",AN$6=""),"",ROUND(SUMIFS(流水支出,流水账户,$A33,流水日期,AN$6),2)) | AO33: =IF(OR($A33="",AO$6=""),"",ROUND(SUMIFS(流水收入,流水账户,$A33,流水日期,AO$6),2)) | AP33: =IF(OR($A33="",AP$6=""),"",ROUND(SUMIFS(流水支出,流水账户,$A33,流水日期,AP$6),2)) | AQ33: =IF(OR($A33="",AQ$6=""),"",ROUND(SUMIFS(流水收入,流水账户,$A33,流水日期,AQ$6),2)) | AR33: =IF(OR($A33="",AR$6=""),"",ROUND(SUMIFS(流水支出,流水账户,$A33,流水日期,AR$6),2)) | AS33: =IF(OR($A33="",AS$6=""),"",ROUND(SUMIFS(流水收入,流水账户,$A33,流水日期,AS$6),2)) | AT33: =IF(OR($A33="",AT$6=""),"",ROUND(SUMIFS(流水支出,流水账户,$A33,流水日期,AT$6),2)) | AU33: =IF(OR($A33="",AU$6=""),"",ROUND(SUMIFS(流水收入,流水账户,$A33,流水日期,AU$6),2)) | AV33: =IF(OR($A33="",AV$6=""),"",ROUND(SUMIFS(流水支出,流水账户,$A33,流水日期,AV$6),2)) | AW33: =IF(OR($A33="",AW$6=""),"",ROUND(SUMIFS(流水收入,流水账户,$A33,流水日期,AW$6),2)) | AX33: =IF(OR($A33="",AX$6=""),"",ROUND(SUMIFS(流水支出,流水账户,$A33,流水日期,AX$6),2)) | AY33: =IF(OR($A33="",AY$6=""),"",ROUND(SUMIFS(流水收入,流水账户,$A33,流水日期,AY$6),2)) | AZ33: =IF(OR($A33="",AZ$6=""),"",ROUND(SUMIFS(流水支出,流水账户,$A33,流水日期,AZ$6),2)) | BA33: =IF(OR($A33="",BA$6=""),"",ROUND(SUMIFS(流水收入,流水账户,$A33,流水日期,BA$6),2)) | BB33: =IF(OR($A33="",BB$6=""),"",ROUND(SUMIFS(流水支出,流水账户,$A33,流水日期,BB$6),2)) | BC33: =IF(OR($A33="",BC$6=""),"",ROUND(SUMIFS(流水收入,流水账户,$A33,流水日期,BC$6),2)) | BD33: =IF(OR($A33="",BD$6=""),"",ROUND(SUMIFS(流水支出,流水账户,$A33,流水日期,BD$6),2)) | BE33: =IF(OR($A33="",BE$6=""),"",ROUND(SUMIFS(流水收入,流水账户,$A33,流水日期,BE$6),2)) | BF33: =IF(OR($A33="",BF$6=""),"",ROUND(SUMIFS(流水支出,流水账户,$A33,流水日期,BF$6),2)) | BG33: =IF(OR($A33="",BG$6=""),"",ROUND(SUMIFS(流水收入,流水账户,$A33,流水日期,BG$6),2)) | BH33: =IF(OR($A33="",BH$6=""),"",ROUND(SUMIFS(流水支出,流水账户,$A33,流水日期,BH$6),2)) | BI33: =IF(OR($A33="",BI$6=""),"",ROUND(SUMIFS(流水收入,流水账户,$A33,流水日期,BI$6),2)) | BJ33: =IF(OR($A33="",BJ$6=""),"",ROUND(SUMIFS(流水支出,流水账户,$A33,流水日期,BJ$6),2)) | BK33: =IF(OR($A33="",BK$6=""),"",ROUND(SUMIFS(流水收入,流水账户,$A33,流水日期,BK$6),2)) | BL33: =IF(OR($A33="",BL$6=""),"",ROUND(SUMIFS(流水支出,流水账户,$A33,流水日期,BL$6),2)) | BM33: =IF($A33="","",ROUND(SUMIF($C$7:$BL$7,"收款",C33:BL33),2)) | BN33: =IF($A33="","",ROUND(SUMIF($C$7:$BL$7,"付款",C33:BL33),2)) | BO33: =IF($A33="","",ROUND(N($B33)+N(BM33)-N(BN33),2))
A34: =IF(基础资料!$B$31="","",基础资料!$B$31) | B34: =IF(OR($A34="",NOT(ISNUMBER($H$3))),"",ROUND(SUMIF(账户表,$A34,账户期初)+SUMIFS(流水收入,流水账户,$A34,流水日期,"<"&$B$3)-SUMIFS(流水支出,流水账户,$A34,流水日期,"<"&$B$3),2)) | C34: =IF(OR($A34="",C$6=""),"",ROUND(SUMIFS(流水收入,流水账户,$A34,流水日期,C$6),2)) | D34: =IF(OR($A34="",D$6=""),"",ROUND(SUMIFS(流水支出,流水账户,$A34,流水日期,D$6),2)) | E34: =IF(OR($A34="",E$6=""),"",ROUND(SUMIFS(流水收入,流水账户,$A34,流水日期,E$6),2)) | F34: =IF(OR($A34="",F$6=""),"",ROUND(SUMIFS(流水支出,流水账户,$A34,流水日期,F$6),2)) | G34: =IF(OR($A34="",G$6=""),"",ROUND(SUMIFS(流水收入,流水账户,$A34,流水日期,G$6),2)) | H34: =IF(OR($A34="",H$6=""),"",ROUND(SUMIFS(流水支出,流水账户,$A34,流水日期,H$6),2)) | I34: =IF(OR($A34="",I$6=""),"",ROUND(SUMIFS(流水收入,流水账户,$A34,流水日期,I$6),2)) | J34: =IF(OR($A34="",J$6=""),"",ROUND(SUMIFS(流水支出,流水账户,$A34,流水日期,J$6),2)) | K34: =IF(OR($A34="",K$6=""),"",ROUND(SUMIFS(流水收入,流水账户,$A34,流水日期,K$6),2)) | L34: =IF(OR($A34="",L$6=""),"",ROUND(SUMIFS(流水支出,流水账户,$A34,流水日期,L$6),2)) | M34: =IF(OR($A34="",M$6=""),"",ROUND(SUMIFS(流水收入,流水账户,$A34,流水日期,M$6),2)) | N34: =IF(OR($A34="",N$6=""),"",ROUND(SUMIFS(流水支出,流水账户,$A34,流水日期,N$6),2)) | O34: =IF(OR($A34="",O$6=""),"",ROUND(SUMIFS(流水收入,流水账户,$A34,流水日期,O$6),2)) | P34: =IF(OR($A34="",P$6=""),"",ROUND(SUMIFS(流水支出,流水账户,$A34,流水日期,P$6),2)) | Q34: =IF(OR($A34="",Q$6=""),"",ROUND(SUMIFS(流水收入,流水账户,$A34,流水日期,Q$6),2)) | R34: =IF(OR($A34="",R$6=""),"",ROUND(SUMIFS(流水支出,流水账户,$A34,流水日期,R$6),2)) | S34: =IF(OR($A34="",S$6=""),"",ROUND(SUMIFS(流水收入,流水账户,$A34,流水日期,S$6),2)) | T34: =IF(OR($A34="",T$6=""),"",ROUND(SUMIFS(流水支出,流水账户,$A34,流水日期,T$6),2)) | U34: =IF(OR($A34="",U$6=""),"",ROUND(SUMIFS(流水收入,流水账户,$A34,流水日期,U$6),2)) | V34: =IF(OR($A34="",V$6=""),"",ROUND(SUMIFS(流水支出,流水账户,$A34,流水日期,V$6),2)) | W34: =IF(OR($A34="",W$6=""),"",ROUND(SUMIFS(流水收入,流水账户,$A34,流水日期,W$6),2)) | X34: =IF(OR($A34="",X$6=""),"",ROUND(SUMIFS(流水支出,流水账户,$A34,流水日期,X$6),2)) | Y34: =IF(OR($A34="",Y$6=""),"",ROUND(SUMIFS(流水收入,流水账户,$A34,流水日期,Y$6),2)) | Z34: =IF(OR($A34="",Z$6=""),"",ROUND(SUMIFS(流水支出,流水账户,$A34,流水日期,Z$6),2)) | AA34: =IF(OR($A34="",AA$6=""),"",ROUND(SUMIFS(流水收入,流水账户,$A34,流水日期,AA$6),2)) | AB34: =IF(OR($A34="",AB$6=""),"",ROUND(SUMIFS(流水支出,流水账户,$A34,流水日期,AB$6),2)) | AC34: =IF(OR($A34="",AC$6=""),"",ROUND(SUMIFS(流水收入,流水账户,$A34,流水日期,AC$6),2)) | AD34: =IF(OR($A34="",AD$6=""),"",ROUND(SUMIFS(流水支出,流水账户,$A34,流水日期,AD$6),2)) | AE34: =IF(OR($A34="",AE$6=""),"",ROUND(SUMIFS(流水收入,流水账户,$A34,流水日期,AE$6),2)) | AF34: =IF(OR($A34="",AF$6=""),"",ROUND(SUMIFS(流水支出,流水账户,$A34,流水日期,AF$6),2)) | AG34: =IF(OR($A34="",AG$6=""),"",ROUND(SUMIFS(流水收入,流水账户,$A34,流水日期,AG$6),2)) | AH34: =IF(OR($A34="",AH$6=""),"",ROUND(SUMIFS(流水支出,流水账户,$A34,流水日期,AH$6),2)) | AI34: =IF(OR($A34="",AI$6=""),"",ROUND(SUMIFS(流水收入,流水账户,$A34,流水日期,AI$6),2)) | AJ34: =IF(OR($A34="",AJ$6=""),"",ROUND(SUMIFS(流水支出,流水账户,$A34,流水日期,AJ$6),2)) | AK34: =IF(OR($A34="",AK$6=""),"",ROUND(SUMIFS(流水收入,流水账户,$A34,流水日期,AK$6),2)) | AL34: =IF(OR($A34="",AL$6=""),"",ROUND(SUMIFS(流水支出,流水账户,$A34,流水日期,AL$6),2)) | AM34: =IF(OR($A34="",AM$6=""),"",ROUND(SUMIFS(流水收入,流水账户,$A34,流水日期,AM$6),2)) | AN34: =IF(OR($A34="",AN$6=""),"",ROUND(SUMIFS(流水支出,流水账户,$A34,流水日期,AN$6),2)) | AO34: =IF(OR($A34="",AO$6=""),"",ROUND(SUMIFS(流水收入,流水账户,$A34,流水日期,AO$6),2)) | AP34: =IF(OR($A34="",AP$6=""),"",ROUND(SUMIFS(流水支出,流水账户,$A34,流水日期,AP$6),2)) | AQ34: =IF(OR($A34="",AQ$6=""),"",ROUND(SUMIFS(流水收入,流水账户,$A34,流水日期,AQ$6),2)) | AR34: =IF(OR($A34="",AR$6=""),"",ROUND(SUMIFS(流水支出,流水账户,$A34,流水日期,AR$6),2)) | AS34: =IF(OR($A34="",AS$6=""),"",ROUND(SUMIFS(流水收入,流水账户,$A34,流水日期,AS$6),2)) | AT34: =IF(OR($A34="",AT$6=""),"",ROUND(SUMIFS(流水支出,流水账户,$A34,流水日期,AT$6),2)) | AU34: =IF(OR($A34="",AU$6=""),"",ROUND(SUMIFS(流水收入,流水账户,$A34,流水日期,AU$6),2)) | AV34: =IF(OR($A34="",AV$6=""),"",ROUND(SUMIFS(流水支出,流水账户,$A34,流水日期,AV$6),2)) | AW34: =IF(OR($A34="",AW$6=""),"",ROUND(SUMIFS(流水收入,流水账户,$A34,流水日期,AW$6),2)) | AX34: =IF(OR($A34="",AX$6=""),"",ROUND(SUMIFS(流水支出,流水账户,$A34,流水日期,AX$6),2)) | AY34: =IF(OR($A34="",AY$6=""),"",ROUND(SUMIFS(流水收入,流水账户,$A34,流水日期,AY$6),2)) | AZ34: =IF(OR($A34="",AZ$6=""),"",ROUND(SUMIFS(流水支出,流水账户,$A34,流水日期,AZ$6),2)) | BA34: =IF(OR($A34="",BA$6=""),"",ROUND(SUMIFS(流水收入,流水账户,$A34,流水日期,BA$6),2)) | BB34: =IF(OR($A34="",BB$6=""),"",ROUND(SUMIFS(流水支出,流水账户,$A34,流水日期,BB$6),2)) | BC34: =IF(OR($A34="",BC$6=""),"",ROUND(SUMIFS(流水收入,流水账户,$A34,流水日期,BC$6),2)) | BD34: =IF(OR($A34="",BD$6=""),"",ROUND(SUMIFS(流水支出,流水账户,$A34,流水日期,BD$6),2)) | BE34: =IF(OR($A34="",BE$6=""),"",ROUND(SUMIFS(流水收入,流水账户,$A34,流水日期,BE$6),2)) | BF34: =IF(OR($A34="",BF$6=""),"",ROUND(SUMIFS(流水支出,流水账户,$A34,流水日期,BF$6),2)) | BG34: =IF(OR($A34="",BG$6=""),"",ROUND(SUMIFS(流水收入,流水账户,$A34,流水日期,BG$6),2)) | BH34: =IF(OR($A34="",BH$6=""),"",ROUND(SUMIFS(流水支出,流水账户,$A34,流水日期,BH$6),2)) | BI34: =IF(OR($A34="",BI$6=""),"",ROUND(SUMIFS(流水收入,流水账户,$A34,流水日期,BI$6),2)) | BJ34: =IF(OR($A34="",BJ$6=""),"",ROUND(SUMIFS(流水支出,流水账户,$A34,流水日期,BJ$6),2)) | BK34: =IF(OR($A34="",BK$6=""),"",ROUND(SUMIFS(流水收入,流水账户,$A34,流水日期,BK$6),2)) | BL34: =IF(OR($A34="",BL$6=""),"",ROUND(SUMIFS(流水支出,流水账户,$A34,流水日期,BL$6),2)) | BM34: =IF($A34="","",ROUND(SUMIF($C$7:$BL$7,"收款",C34:BL34),2)) | BN34: =IF($A34="","",ROUND(SUMIF($C$7:$BL$7,"付款",C34:BL34),2)) | BO34: =IF($A34="","",ROUND(N($B34)+N(BM34)-N(BN34),2))
