Workbook
Name 本位币: 参数设置!$B$4
Name 管理年度: 参数设置!$B$5
Name 报表月份: 参数设置!$B$6
Name 重估基准日: 参数设置!$B$7
Name 账户银行: 参数设置!$B$11:$B$40
Name 账户名: 参数设置!$C$11:$C$40
Name 账户币种: 参数设置!$E$11:$E$40
Name 账户期初: 参数设置!$G$11:$G$40
Name 账户期初本位: 参数设置!$I$11:$I$40
Name 币种表: 参数设置!$L$11:$L$18
Name 类别表: 参数设置!$O$11:$O$40
Name 类别属性: 参数设置!$P$11:$P$40
Name 项目表: 参数设置!$R$11:$R$50
Name 单位表: 参数设置!$T$11:$T$210
Name 汇率月份: 月度汇率!$A$6:$A$17
Name 记账汇率区: 月度汇率!$B$6:$I$17
Name 汇率币种头: 月度汇率!$B$5:$I$5
Name 月末汇率区: 月度汇率!$K$6:$R$17
Name 流水日期: 流水录入!$A$6:$A$2005
Name 流水账户: 流水录入!$B$6:$B$2005
Name 流水币种: 流水录入!$D$6:$D$2005
Name 流水类别: 流水录入!$E$6:$E$2005
Name 流水属性: 流水录入!$F$6:$F$2005
Name 流水收入: 流水录入!$G$6:$G$2005
Name 流水支出: 流水录入!$H$6:$H$2005
Name 流水净额: 流水录入!$K$6:$K$2005
Name 流水本位: 流水录入!$L$6:$L$2005
Name 流水项目: 流水录入!$P$6:$P$2005
Name 流水单位: 流水录入!$Q$6:$Q$2005
Name 资金总额本位: 账户余额表!$J$36
Name 月报收入合计: 月度汇报表!$B$18
Name 月报支出合计: 月度汇报表!$C$18
Name 分类收入合计: 收支分类报表!$O$5
Name 分类支出合计: 收支分类报表!$O$6
Name 汇率填写数: 月度汇率!$T$6:$T$17
Name 外币流水数: 月度汇率!$U$6:$U$17
Name 汇率列计数: 月度汇率!$B$18:$I$18
Name 流水核对: 流水录入!$S$6:$S$2005
Name 档案核对: 参数设置!$J$11:$J$40

Sheet 使用说明
A1: 外汇资金台账 · 使用说明（本位币：人民币）
A3: 一、三步就能用起来
A4: 第 1 步 | B4: 【参数设置】 | C4: 把账户档案改成你们真实的账户：银行、账户名称（唯一）、币种、期初余额。外币账户把「期初汇率」也填上 —— 那是这笔期初余额当初入账的汇率。
A5: 第 2 步 | B5: 【月度汇率】 | C5: 每月填一次当月记账汇率。只填你们在用的币种（美元、港币、欧元）就行。
A6: 第 3 步 | B6: 【流水录入】 | C6: 每天在这一张录。选账户名称 → 银行、币种、汇率自动带出来；收入和支出分两列，只填一个。其余所有表全自动。
A8: 二、表都干什么用
A9: 表名 | B9: 谁用 | C9: 干什么
A10: 参数设置 | B10: 管理员 | C10: 账户档案、币种、收支类别、项目、往来单位。这一页改了，后面全部跟着变。
A11: 月度汇率 | B11: 财务 | C11: 每月一行。左边记账汇率（流水折人民币用），右边月末汇率（月末重估用，空着=用左边）。
A12: 流水录入 | B12: 出纳 | C12: ★ 全套表唯一要填的一张。最后一列「核对」会自己挑毛病。
A13: 银行子表（每账户一张） | B13: 看 | C13: 自动从流水拆出来，不用填。表头 B2 是拆分依据。
A14: 账户余额表 | B14: 财务 | C14: 每账户一行：期末原币、期末人民币、账面成本、汇兑损益；下面还有按币种小计。
A15: 月度汇报表 | B15: 老板 | C15: 按月的人民币收入/支出/净流入/月末资金总额；下半张是报表月份的各账户明细。
A16: 收支分类报表 | B16: 老板 | C16: 收支类别 × 12 个月，人民币。支出显示成正数，好读。
A17: 资金日报表 | B17: 出纳/老板 | C17: 上半张按日走势（最多 31 天），下半张是某一天的出纳日报。
A18: 区间查询 | B18: 财务 | C18: 任意起止日期 → 按类别、按项目、按币种、按往来单位四块。
A19: 核对表 | B19: 所有人 | C19: 录完看这一张就够了。勾稽必须全 0，待办是数据没填齐。
A21: 三、汇率是怎么取的（这是外汇台账的核心）
A22: 优先级 1 | B22: 实际成交汇率 | C22: 流水里填了「实际成交汇率」就用它。购汇、结汇、银行有实际成交价的都填这个。
A23: 优先级 2 | B23: 当月记账汇率 | C23: 按交易日期所在的月份，去【月度汇率】取。
A24: 优先级 3 | B24: 往前最近一个月 | C24: 当月还没填？自动往前找最近一个填过的月份
A26: 四、两套人民币口径，各算各的，千万别混着加
A27: 账面人民币成本 | B27: 历史成本 | C27: ＝期初人民币成本 + 每一笔原币 × 该笔当时的汇率。钱进来时值多少就是多少，以后汇率怎么变都不动它。
A28: 期末人民币(重估) | B28: 现在值多少 | C28: ＝期末原币余额 × 期末汇率。
A29: 汇兑损益 | B29: 两者之差 | C29: ＝重估 − 账面成本。外币放着不动，汇率涨了就是赚、跌了就是亏，这一栏就是那个数。
A31: 五、内部转账不算收入也不算支出
A32: 怎么录 | B32: 两头都录 | C32: 转出账户记一笔支出，转入账户记一笔收入，类别都选「内部转账」。购汇结汇选「购汇/结汇」，也是内部转账属性。
A33: 报表里怎么处理 | B33: 单列，不进合计 | C33: 月度汇报表单列「内部转入 / 内部转出」两列；分类报表单列一行「内部转账净额」。收入合计、支出合计里都不含它。
A34: 净额不是 0 怎么办 | B34: 那是换汇价差 | C34: 同币种之间调头寸净额应该是 0。购汇结汇跨币种，净额就是买卖价差，正常。
A36: 六、加东西怎么加
A37: 加一个账户 | B37: 两步 | C37: ① 在【参数设置】账户档案接着写一行；② 右键复制任意一张银行子表，改表名，把 B2 改成新账户名
A38: 加一个币种 | B38: 一步 | C38: 在【参数设置】币种清单加一行，再去【月度汇率】填它的汇率。（汇率表预留了 8 个币种的列）
A39: 加类别 / 项目 / 往来单位 | B39: 一步 | C39: 在【参数设置】对应清单接着写，所有报表自动跟着长。注意别写重复
A40: 预留行数 | C40: 流水预留 2000 行、账户 30 个。
A42: 七、颜色和符号
A43: 淡黄色格子 | B43: 要你填 | C43: 这是人工输入区。
A44: 灰色格子 | B44: 公式自动算 | C44: 别手动改，改了就把公式顶掉了。
A45: ※ 红字 | B45: 是错，必须改 | C45: 账户不在档案、收支同时填、类别不在清单……
A46: △ 琥珀字 | B46: 待补的数据 | C46: 汇率没填、内部转账没写对方账户……不影响公式，补齐了数才准。
A48: 八、示例数据
A49: · 【流水录入】第 6 ~ 23 行是示例（原模板那 15 笔 + 3 笔补充），正式用之前整段选中删掉即可。删了之后所有报表会自动归零。
A50: · 【月度汇率】只填了 2026 年 8 月的美元 7.18、港币 0.92 ，其余月份都空着，等你填。
A51: · 示例里如果欧元汇率空着，你可以看到「△EUR 还没填汇率」的提示
A52: · 顺带说清楚：某个币种一个汇率都没填时，它的余额**进不了人民币合计数**（宁可不算，也不瞎算），那个账户的人民币几列会是空白而不是 0。
A53: · 示例账户里有 1 个欧元户、2 个美元户、1 个港币户、2 个人民币户

Sheet 参数设置
A1: 参数设置 · 账户、币种、类别、项目都在这里维护
A2: 淡黄色格子是要你填的，灰色是公式算的。账户名称必须唯一，建议写成「银行 + 用途 + 账号尾号」。这一页改了，后面所有表跟着变。
A4: 本位币 | B4: CNY | C4: 所有汇报表都折算成它。改成别的币种，整套跟着走。
A5: 管理年度 | B5: 2026 | C5: 【月度汇率】和各张年报按这个年度展开。
A6: 报表月份 | B6: 46235 | C6: 汇报表默认看哪个月。填该月 1 号。
A7: 期末重估基准日 | B7: =IF($B$6="","",EOMONTH($B$6,0)) -> 46265 | C7: 自动 = 报表月份的月末。外币余额按这一天的汇率重估。
A9: 一、账户档案 —— 加一个账户：在这里接着写一行，再复制一张银行子表改 B2 | L9: 二、币种 | O9: 三、收支类别（属性=内部转账的，不计入收入/支出合计） | R9: 四、项目 | T9: 五、往来单位
A10: 序号 | B10: 银行 ★ | C10: 账户名称 ★（唯一） | D10: 账号（可不填） | E10: 币种 ★ | F10: 账户类型 | G10: 期初余额(原币) | H10: 期初汇率 | I10: 期初人民币成本 | J10: 核对 | L10: 币种代码 | M10: 币种名称 | O10: 收/支类别 | P10: 属性 ★ | R10: 项目 / 业务 | T10: 往来单位
A11: =IF($C11="","",COUNTA($C$11:$C11)) -> 1 | B11: 工商银行 | C11: 工商银行基本户-8888 | D11: 1202...8888 | E11: CNY | F11: 基本户 | G11: 500000 | I11: =IF($C11="","",IFERROR(ROUND(N($G11)*IF($H11<>"",$H11,IF($E11=本位币,1,IFERROR(LOOKUP(2,1/((汇率月份<=重估基准日)*(INDEX(月末汇率区,0,MATCH($E11,汇率币种头,0))<>"")),INDEX(月末汇率区,0,MATCH($E11,汇率币种头,0))),IFERROR(LOOKUP(2,1/((汇率月份<=重估基准日)*(INDEX(记账汇率区,0,MATCH($E11,汇率币种头,0))<>"")),INDEX(记账汇率区,0,MATCH($E11,汇率币种头,0))),"")))),2),"")) -> 500000 | J11: =IF($C11="","",IF(COUNTIF($C$11:$C$40,$C11)>1,"※账户名称重复了，后面按名字取数会串",IF(AND($E11<>"",COUNTIF(币种表,$E11)=0),"※币种不在右边币种清单里",IF($G11="","※期初余额没填（没有就填 0）",IF(AND($E11<>本位币,$H11="",$I11=""),"△这个币种一个汇率都没填，期初人民币成本算不出来",IF(AND($E11<>本位币,$H11=""),"△没填期初汇率，先拿期末汇率折的","")))))) | L11: CNY | M11: 人民币 | O11: 销售回款 | P11: 收入 | R11: 项目A | T11: 华东客户A
A12: =IF($C12="","",COUNTA($C$11:$C12)) -> 2 | B12: 中国银行 | C12: 中国银行美元结算户-6688 | D12: 4567...6688 | E12: USD | F12: 外币结算户 | G12: 800000 | H12: 7.15 | I12: =IF($C12="","",IFERROR(ROUND(N($G12)*IF($H12<>"",$H12,IF($E12=本位币,1,IFERROR(LOOKUP(2,1/((汇率月份<=重估基准日)*(INDEX(月末汇率区,0,MATCH($E12,汇率币种头,0))<>"")),INDEX(月末汇率区,0,MATCH($E12,汇率币种头,0))),IFERROR(LOOKUP(2,1/((汇率月份<=重估基准日)*(INDEX(记账汇率区,0,MATCH($E12,汇率币种头,0))<>"")),INDEX(记账汇率区,0,MATCH($E12,汇率币种头,0))),"")))),2),"")) -> 5720000 | J12: =IF($C12="","",IF(COUNTIF($C$11:$C$40,$C12)>1,"※账户名称重复了，后面按名字取数会串",IF(AND($E12<>"",COUNTIF(币种表,$E12)=0),"※币种不在右边币种清单里",IF($G12="","※期初余额没填（没有就填 0）",IF(AND($E12<>本位币,$H12="",$I12=""),"△这个币种一个汇率都没填，期初人民币成本算不出来",IF(AND($E12<>本位币,$H12=""),"△没填期初汇率，先拿期末汇率折的","")))))) | L12: USD | M12: 美元 | O12: 其他业务收入 | P12: 收入 | R12: 出口业务 | T12: Overseas Client A
A13: =IF($C13="","",COUNTA($C$11:$C13)) -> 3 | B13: 汇丰银行 | C13: 汇丰银行港币结算户-5566 | D13: 0048...5566 | E13: HKD | F13: 外币结算户 | G13: 300000 | H13: 0.915 | I13: =IF($C13="","",IFERROR(ROUND(N($G13)*IF($H13<>"",$H13,IF($E13=本位币,1,IFERROR(LOOKUP(2,1/((汇率月份<=重估基准日)*(INDEX(月末汇率区,0,MATCH($E13,汇率币种头,0))<>"")),INDEX(月末汇率区,0,MATCH($E13,汇率币种头,0))),IFERROR(LOOKUP(2,1/((汇率月份<=重估基准日)*(INDEX(记账汇率区,0,MATCH($E13,汇率币种头,0))<>"")),INDEX(记账汇率区,0,MATCH($E13,汇率币种头,0))),"")))),2),"")) -> 274500 | J13: =IF($C13="","",IF(COUNTIF($C$11:$C$40,$C13)>1,"※账户名称重复了，后面按名字取数会串",IF(AND($E13<>"",COUNTIF(币种表,$E13)=0),"※币种不在右边币种清单里",IF($G13="","※期初余额没填（没有就填 0）",IF(AND($E13<>本位币,$H13="",$I13=""),"△这个币种一个汇率都没填，期初人民币成本算不出来",IF(AND($E13<>本位币,$H13=""),"△没填期初汇率，先拿期末汇率折的","")))))) | L13: HKD | M13: 港币 | O13: 投资款 | P13: 收入 | R13: 进口业务 | T13: Overseas Client C
A14: =IF($C14="","",COUNTA($C$11:$C14)) -> 4 | B14: 招商银行 | C14: 招商银行一般户-2388 | D14: 7712...2388 | E14: CNY | F14: 一般户 | G14: 200000 | I14: =IF($C14="","",IFERROR(ROUND(N($G14)*IF($H14<>"",$H14,IF($E14=本位币,1,IFERROR(LOOKUP(2,1/((汇率月份<=重估基准日)*(INDEX(月末汇率区,0,MATCH($E14,汇率币种头,0))<>"")),INDEX(月末汇率区,0,MATCH($E14,汇率币种头,0))),IFERROR(LOOKUP(2,1/((汇率月份<=重估基准日)*(INDEX(记账汇率区,0,MATCH($E14,汇率币种头,0))<>"")),INDEX(记账汇率区,0,MATCH($E14,汇率币种头,0))),"")))),2),"")) -> 200000 | J14: =IF($C14="","",IF(COUNTIF($C$11:$C$40,$C14)>1,"※账户名称重复了，后面按名字取数会串",IF(AND($E14<>"",COUNTIF(币种表,$E14)=0),"※币种不在右边币种清单里",IF($G14="","※期初余额没填（没有就填 0）",IF(AND($E14<>本位币,$H14="",$I14=""),"△这个币种一个汇率都没填，期初人民币成本算不出来",IF(AND($E14<>本位币,$H14=""),"△没填期初汇率，先拿期末汇率折的","")))))) | L14: EUR | M14: 欧元 | O14: 借款 | P14: 收入 | R14: 香港业务 | T14: 香港客户B
A15: =IF($C15="","",COUNTA($C$11:$C15)) -> 5 | B15: 汇丰银行 | C15: 汇丰银行美元结算户-7788 | D15: 0048...7788 | E15: USD | F15: 外币结算户 | G15: 500000 | H15: 7.15 | I15: =IF($C15="","",IFERROR(ROUND(N($G15)*IF($H15<>"",$H15,IF($E15=本位币,1,IFERROR(LOOKUP(2,1/((汇率月份<=重估基准日)*(INDEX(月末汇率区,0,MATCH($E15,汇率币种头,0))<>"")),INDEX(月末汇率区,0,MATCH($E15,汇率币种头,0))),IFERROR(LOOKUP(2,1/((汇率月份<=重估基准日)*(INDEX(记账汇率区,0,MATCH($E15,汇率币种头,0))<>"")),INDEX(记账汇率区,0,MATCH($E15,汇率币种头,0))),"")))),2),"")) -> 3575000 | J15: =IF($C15="","",IF(COUNTIF($C$11:$C$40,$C15)>1,"※账户名称重复了，后面按名字取数会串",IF(AND($E15<>"",COUNTIF(币种表,$E15)=0),"※币种不在右边币种清单里",IF($G15="","※期初余额没填（没有就填 0）",IF(AND($E15<>本位币,$H15="",$I15=""),"△这个币种一个汇率都没填，期初人民币成本算不出来",IF(AND($E15<>本位币,$H15=""),"△没填期初汇率，先拿期末汇率折的","")))))) | L15: JPY | M15: 日元 | O15: 利息收入 | P15: 收入 | R15: 欧洲业务 | T15: 欧洲客户D
A16: =IF($C16="","",COUNTA($C$11:$C16)) -> 6 | B16: 中国银行 | C16: 中国银行欧元结算户-9900 | D16: 4567...9900 | E16: EUR | F16: 外币结算户 | G16: 120000 | I16: =IF($C16="","",IFERROR(ROUND(N($G16)*IF($H16<>"",$H16,IF($E16=本位币,1,IFERROR(LOOKUP(2,1/((汇率月份<=重估基准日)*(INDEX(月末汇率区,0,MATCH($E16,汇率币种头,0))<>"")),INDEX(月末汇率区,0,MATCH($E16,汇率币种头,0))),IFERROR(LOOKUP(2,1/((汇率月份<=重估基准日)*(INDEX(记账汇率区,0,MATCH($E16,汇率币种头,0))<>"")),INDEX(记账汇率区,0,MATCH($E16,汇率币种头,0))),"")))),2),"")) -> 922800 | J16: =IF($C16="","",IF(COUNTIF($C$11:$C$40,$C16)>1,"※账户名称重复了，后面按名字取数会串",IF(AND($E16<>"",COUNTIF(币种表,$E16)=0),"※币种不在右边币种清单里",IF($G16="","※期初余额没填（没有就填 0）",IF(AND($E16<>本位币,$H16="",$I16=""),"△这个币种一个汇率都没填，期初人民币成本算不出来",IF(AND($E16<>本位币,$H16=""),"△没填期初汇率，先拿期末汇率折的","")))))) -> △没填期初汇率，先拿期末汇率折的 | L16: GBP | M16: 英镑 | O16: 退款收回 | P16: 收入 | R16: 融资 | T16: 香港供应商A
A17: =IF($C17="","",COUNTA($C$11:$C17)) | I17: =IF($C17="","",IFERROR(ROUND(N($G17)*IF($H17<>"",$H17,IF($E17=本位币,1,IFERROR(LOOKUP(2,1/((汇率月份<=重估基准日)*(INDEX(月末汇率区,0,MATCH($E17,汇率币种头,0))<>"")),INDEX(月末汇率区,0,MATCH($E17,汇率币种头,0))),IFERROR(LOOKUP(2,1/((汇率月份<=重估基准日)*(INDEX(记账汇率区,0,MATCH($E17,汇率币种头,0))<>"")),INDEX(记账汇率区,0,MATCH($E17,汇率币种头,0))),"")))),2),"")) | J17: =IF($C17="","",IF(COUNTIF($C$11:$C$40,$C17)>1,"※账户名称重复了，后面按名字取数会串",IF(AND($E17<>"",COUNTIF(币种表,$E17)=0),"※币种不在右边币种清单里",IF($G17="","※期初余额没填（没有就填 0）",IF(AND($E17<>本位币,$H17="",$I17=""),"△这个币种一个汇率都没填，期初人民币成本算不出来",IF(AND($E17<>本位币,$H17=""),"△没填期初汇率，先拿期末汇率折的","")))))) | L17: SGD | M17: 新加坡元 | O17: 采购付款 | P17: 支出 | R17: 行政 | T17: Overseas Supplier B
A18: =IF($C18="","",COUNTA($C$11:$C18)) | I18: =IF($C18="","",IFERROR(ROUND(N($G18)*IF($H18<>"",$H18,IF($E18=本位币,1,IFERROR(LOOKUP(2,1/((汇率月份<=重估基准日)*(INDEX(月末汇率区,0,MATCH($E18,汇率币种头,0))<>"")),INDEX(月末汇率区,0,MATCH($E18,汇率币种头,0))),IFERROR(LOOKUP(2,1/((汇率月份<=重估基准日)*(INDEX(记账汇率区,0,MATCH($E18,汇率币种头,0))<>"")),INDEX(记账汇率区,0,MATCH($E18,汇率币种头,0))),"")))),2),"")) | J18: =IF($C18="","",IF(COUNTIF($C$11:$C$40,$C18)>1,"※账户名称重复了，后面按名字取数会串",IF(AND($E18<>"",COUNTIF(币种表,$E18)=0),"※币种不在右边币种清单里",IF($G18="","※期初余额没填（没有就填 0）",IF(AND($E18<>本位币,$H18="",$I18=""),"△这个币种一个汇率都没填，期初人民币成本算不出来",IF(AND($E18<>本位币,$H18=""),"△没填期初汇率，先拿期末汇率折的","")))))) | L18: AUD | M18: 澳元 | O18: 工资 | P18: 支出 | R18: 税务 | T18: 欧洲供应商E
A19: =IF($C19="","",COUNTA($C$11:$C19)) | I19: =IF($C19="","",IFERROR(ROUND(N($G19)*IF($H19<>"",$H19,IF($E19=本位币,1,IFERROR(LOOKUP(2,1/((汇率月份<=重估基准日)*(INDEX(月末汇率区,0,MATCH($E19,汇率币种头,0))<>"")),INDEX(月末汇率区,0,MATCH($E19,汇率币种头,0))),IFERROR(LOOKUP(2,1/((汇率月份<=重估基准日)*(INDEX(记账汇率区,0,MATCH($E19,汇率币种头,0))<>"")),INDEX(记账汇率区,0,MATCH($E19,汇率币种头,0))),"")))),2),"")) | J19: =IF($C19="","",IF(COUNTIF($C$11:$C$40,$C19)>1,"※账户名称重复了，后面按名字取数会串",IF(AND($E19<>"",COUNTIF(币种表,$E19)=0),"※币种不在右边币种清单里",IF($G19="","※期初余额没填（没有就填 0）",IF(AND($E19<>本位币,$H19="",$I19=""),"△这个币种一个汇率都没填，期初人民币成本算不出来",IF(AND($E19<>本位币,$H19=""),"△没填期初汇率，先拿期末汇率折的","")))))) | O19: 运营费用 | P19: 支出 | R19: 海外服务 | T19: 员工薪酬
A20: =IF($C20="","",COUNTA($C$11:$C20)) | I20: =IF($C20="","",IFERROR(ROUND(N($G20)*IF($H20<>"",$H20,IF($E20=本位币,1,IFERROR(LOOKUP(2,1/((汇率月份<=重估基准日)*(INDEX(月末汇率区,0,MATCH($E20,汇率币种头,0))<>"")),INDEX(月末汇率区,0,MATCH($E20,汇率币种头,0))),IFERROR(LOOKUP(2,1/((汇率月份<=重估基准日)*(INDEX(记账汇率区,0,MATCH($E20,汇率币种头,0))<>"")),INDEX(记账汇率区,0,MATCH($E20,汇率币种头,0))),"")))),2),"")) | J20: =IF($C20="","",IF(COUNTIF($C$11:$C$40,$C20)>1,"※账户名称重复了，后面按名字取数会串",IF(AND($E20<>"",COUNTIF(币种表,$E20)=0),"※币种不在右边币种清单里",IF($G20="","※期初余额没填（没有就填 0）",IF(AND($E20<>本位币,$H20="",$I20=""),"△这个币种一个汇率都没填，期初人民币成本算不出来",IF(AND($E20<>本位币,$H20=""),"△没填期初汇率，先拿期末汇率折的","")))))) | O20: 税费 | P20: 支出 | R20: 内部调拨 | T20: 税务机关
A21: =IF($C21="","",COUNTA($C$11:$C21)) | I21: =IF($C21="","",IFERROR(ROUND(N($G21)*IF($H21<>"",$H21,IF($E21=本位币,1,IFERROR(LOOKUP(2,1/((汇率月份<=重估基准日)*(INDEX(月末汇率区,0,MATCH($E21,汇率币种头,0))<>"")),INDEX(月末汇率区,0,MATCH($E21,汇率币种头,0))),IFERROR(LOOKUP(2,1/((汇率月份<=重估基准日)*(INDEX(记账汇率区,0,MATCH($E21,汇率币种头,0))<>"")),INDEX(记账汇率区,0,MATCH($E21,汇率币种头,0))),"")))),2),"")) | J21: =IF($C21="","",IF(COUNTIF($C$11:$C$40,$C21)>1,"※账户名称重复了，后面按名字取数会串",IF(AND($E21<>"",COUNTIF(币种表,$E21)=0),"※币种不在右边币种清单里",IF($G21="","※期初余额没填（没有就填 0）",IF(AND($E21<>本位币,$H21="",$I21=""),"△这个币种一个汇率都没填，期初人民币成本算不出来",IF(AND($E21<>本位币,$H21=""),"△没填期初汇率，先拿期末汇率折的","")))))) | O21: 手续费 | P21: 支出 | R21: 其他业务 | T21: 银行借款
A22: =IF($C22="","",COUNTA($C$11:$C22)) | I22: =IF($C22="","",IFERROR(ROUND(N($G22)*IF($H22<>"",$H22,IF($E22=本位币,1,IFERROR(LOOKUP(2,1/((汇率月份<=重估基准日)*(INDEX(月末汇率区,0,MATCH($E22,汇率币种头,0))<>"")),INDEX(月末汇率区,0,MATCH($E22,汇率币种头,0))),IFERROR(LOOKUP(2,1/((汇率月份<=重估基准日)*(INDEX(记账汇率区,0,MATCH($E22,汇率币种头,0))<>"")),INDEX(记账汇率区,0,MATCH($E22,汇率币种头,0))),"")))),2),"")) | J22: =IF($C22="","",IF(COUNTIF($C$11:$C$40,$C22)>1,"※账户名称重复了，后面按名字取数会串",IF(AND($E22<>"",COUNTIF(币种表,$E22)=0),"※币种不在右边币种清单里",IF($G22="","※期初余额没填（没有就填 0）",IF(AND($E22<>本位币,$H22="",$I22=""),"△这个币种一个汇率都没填，期初人民币成本算不出来",IF(AND($E22<>本位币,$H22=""),"△没填期初汇率，先拿期末汇率折的","")))))) | O22: 利息支出 | P22: 支出 | T22: 股东A
A23: =IF($C23="","",COUNTA($C$11:$C23)) | I23: =IF($C23="","",IFERROR(ROUND(N($G23)*IF($H23<>"",$H23,IF($E23=本位币,1,IFERROR(LOOKUP(2,1/((汇率月份<=重估基准日)*(INDEX(月末汇率区,0,MATCH($E23,汇率币种头,0))<>"")),INDEX(月末汇率区,0,MATCH($E23,汇率币种头,0))),IFERROR(LOOKUP(2,1/((汇率月份<=重估基准日)*(INDEX(记账汇率区,0,MATCH($E23,汇率币种头,0))<>"")),INDEX(记账汇率区,0,MATCH($E23,汇率币种头,0))),"")))),2),"")) | J23: =IF($C23="","",IF(COUNTIF($C$11:$C$40,$C23)>1,"※账户名称重复了，后面按名字取数会串",IF(AND($E23<>"",COUNTIF(币种表,$E23)=0),"※币种不在右边币种清单里",IF($G23="","※期初余额没填（没有就填 0）",IF(AND($E23<>本位币,$H23="",$I23=""),"△这个币种一个汇率都没填，期初人民币成本算不出来",IF(AND($E23<>本位币,$H23=""),"△没填期初汇率，先拿期末汇率折的","")))))) | O23: 还款 | P23: 支出 | T23: Service Provider
A24: =IF($C24="","",COUNTA($C$11:$C24)) | I24: =IF($C24="","",IFERROR(ROUND(N($G24)*IF($H24<>"",$H24,IF($E24=本位币,1,IFERROR(LOOKUP(2,1/((汇率月份<=重估基准日)*(INDEX(月末汇率区,0,MATCH($E24,汇率币种头,0))<>"")),INDEX(月末汇率区,0,MATCH($E24,汇率币种头,0))),IFERROR(LOOKUP(2,1/((汇率月份<=重估基准日)*(INDEX(记账汇率区,0,MATCH($E24,汇率币种头,0))<>"")),INDEX(记账汇率区,0,MATCH($E24,汇率币种头,0))),"")))),2),"")) | J24: =IF($C24="","",IF(COUNTIF($C$11:$C$40,$C24)>1,"※账户名称重复了，后面按名字取数会串",IF(AND($E24<>"",COUNTIF(币种表,$E24)=0),"※币种不在右边币种清单里",IF($G24="","※期初余额没填（没有就填 0）",IF(AND($E24<>本位币,$H24="",$I24=""),"△这个币种一个汇率都没填，期初人民币成本算不出来",IF(AND($E24<>本位币,$H24=""),"△没填期初汇率，先拿期末汇率折的","")))))) | O24: 资产购买 | P24: 支出 | T24: 香港办公室
A25: =IF($C25="","",COUNTA($C$11:$C25)) | I25: =IF($C25="","",IFERROR(ROUND(N($G25)*IF($H25<>"",$H25,IF($E25=本位币,1,IFERROR(LOOKUP(2,1/((汇率月份<=重估基准日)*(INDEX(月末汇率区,0,MATCH($E25,汇率币种头,0))<>"")),INDEX(月末汇率区,0,MATCH($E25,汇率币种头,0))),IFERROR(LOOKUP(2,1/((汇率月份<=重估基准日)*(INDEX(记账汇率区,0,MATCH($E25,汇率币种头,0))<>"")),INDEX(记账汇率区,0,MATCH($E25,汇率币种头,0))),"")))),2),"")) | J25: =IF($C25="","",IF(COUNTIF($C$11:$C$40,$C25)>1,"※账户名称重复了，后面按名字取数会串",IF(AND($E25<>"",COUNTIF(币种表,$E25)=0),"※币种不在右边币种清单里",IF($G25="","※期初余额没填（没有就填 0）",IF(AND($E25<>本位币,$H25="",$I25=""),"△这个币种一个汇率都没填，期初人民币成本算不出来",IF(AND($E25<>本位币,$H25=""),"△没填期初汇率，先拿期末汇率折的","")))))) | O25: 股利分配 | P25: 支出 | T25: 其他客户
A26: =IF($C26="","",COUNTA($C$11:$C26)) | I26: =IF($C26="","",IFERROR(ROUND(N($G26)*IF($H26<>"",$H26,IF($E26=本位币,1,IFERROR(LOOKUP(2,1/((汇率月份<=重估基准日)*(INDEX(月末汇率区,0,MATCH($E26,汇率币种头,0))<>"")),INDEX(月末汇率区,0,MATCH($E26,汇率币种头,0))),IFERROR(LOOKUP(2,1/((汇率月份<=重估基准日)*(INDEX(记账汇率区,0,MATCH($E26,汇率币种头,0))<>"")),INDEX(记账汇率区,0,MATCH($E26,汇率币种头,0))),"")))),2),"")) | J26: =IF($C26="","",IF(COUNTIF($C$11:$C$40,$C26)>1,"※账户名称重复了，后面按名字取数会串",IF(AND($E26<>"",COUNTIF(币种表,$E26)=0),"※币种不在右边币种清单里",IF($G26="","※期初余额没填（没有就填 0）",IF(AND($E26<>本位币,$H26="",$I26=""),"△这个币种一个汇率都没填，期初人民币成本算不出来",IF(AND($E26<>本位币,$H26=""),"△没填期初汇率，先拿期末汇率折的","")))))) | O26: 内部转账 | P26: 内部转账
A27: =IF($C27="","",COUNTA($C$11:$C27)) | I27: =IF($C27="","",IFERROR(ROUND(N($G27)*IF($H27<>"",$H27,IF($E27=本位币,1,IFERROR(LOOKUP(2,1/((汇率月份<=重估基准日)*(INDEX(月末汇率区,0,MATCH($E27,汇率币种头,0))<>"")),INDEX(月末汇率区,0,MATCH($E27,汇率币种头,0))),IFERROR(LOOKUP(2,1/((汇率月份<=重估基准日)*(INDEX(记账汇率区,0,MATCH($E27,汇率币种头,0))<>"")),INDEX(记账汇率区,0,MATCH($E27,汇率币种头,0))),"")))),2),"")) | J27: =IF($C27="","",IF(COUNTIF($C$11:$C$40,$C27)>1,"※账户名称重复了，后面按名字取数会串",IF(AND($E27<>"",COUNTIF(币种表,$E27)=0),"※币种不在右边币种清单里",IF($G27="","※期初余额没填（没有就填 0）",IF(AND($E27<>本位币,$H27="",$I27=""),"△这个币种一个汇率都没填，期初人民币成本算不出来",IF(AND($E27<>本位币,$H27=""),"△没填期初汇率，先拿期末汇率折的","")))))) | O27: 购汇/结汇 | P27: 内部转账
A28: =IF($C28="","",COUNTA($C$11:$C28)) | I28: =IF($C28="","",IFERROR(ROUND(N($G28)*IF($H28<>"",$H28,IF($E28=本位币,1,IFERROR(LOOKUP(2,1/((汇率月份<=重估基准日)*(INDEX(月末汇率区,0,MATCH($E28,汇率币种头,0))<>"")),INDEX(月末汇率区,0,MATCH($E28,汇率币种头,0))),IFERROR(LOOKUP(2,1/((汇率月份<=重估基准日)*(INDEX(记账汇率区,0,MATCH($E28,汇率币种头,0))<>"")),INDEX(记账汇率区,0,MATCH($E28,汇率币种头,0))),"")))),2),"")) | J28: =IF($C28="","",IF(COUNTIF($C$11:$C$40,$C28)>1,"※账户名称重复了，后面按名字取数会串",IF(AND($E28<>"",COUNTIF(币种表,$E28)=0),"※币种不在右边币种清单里",IF($G28="","※期初余额没填（没有就填 0）",IF(AND($E28<>本位币,$H28="",$I28=""),"△这个币种一个汇率都没填，期初人民币成本算不出来",IF(AND($E28<>本位币,$H28=""),"△没填期初汇率，先拿期末汇率折的",""))))))
A29: =IF($C29="","",COUNTA($C$11:$C29)) | I29: =IF($C29="","",IFERROR(ROUND(N($G29)*IF($H29<>"",$H29,IF($E29=本位币,1,IFERROR(LOOKUP(2,1/((汇率月份<=重估基准日)*(INDEX(月末汇率区,0,MATCH($E29,汇率币种头,0))<>"")),INDEX(月末汇率区,0,MATCH($E29,汇率币种头,0))),IFERROR(LOOKUP(2,1/((汇率月份<=重估基准日)*(INDEX(记账汇率区,0,MATCH($E29,汇率币种头,0))<>"")),INDEX(记账汇率区,0,MATCH($E29,汇率币种头,0))),"")))),2),"")) | J29: =IF($C29="","",IF(COUNTIF($C$11:$C$40,$C29)>1,"※账户名称重复了，后面按名字取数会串",IF(AND($E29<>"",COUNTIF(币种表,$E29)=0),"※币种不在右边币种清单里",IF($G29="","※期初余额没填（没有就填 0）",IF(AND($E29<>本位币,$H29="",$I29=""),"△这个币种一个汇率都没填，期初人民币成本算不出来",IF(AND($E29<>本位币,$H29=""),"△没填期初汇率，先拿期末汇率折的",""))))))
A30: =IF($C30="","",COUNTA($C$11:$C30)) | I30: =IF($C30="","",IFERROR(ROUND(N($G30)*IF($H30<>"",$H30,IF($E30=本位币,1,IFERROR(LOOKUP(2,1/((汇率月份<=重估基准日)*(INDEX(月末汇率区,0,MATCH($E30,汇率币种头,0))<>"")),INDEX(月末汇率区,0,MATCH($E30,汇率币种头,0))),IFERROR(LOOKUP(2,1/((汇率月份<=重估基准日)*(INDEX(记账汇率区,0,MATCH($E30,汇率币种头,0))<>"")),INDEX(记账汇率区,0,MATCH($E30,汇率币种头,0))),"")))),2),"")) | J30: =IF($C30="","",IF(COUNTIF($C$11:$C$40,$C30)>1,"※账户名称重复了，后面按名字取数会串",IF(AND($E30<>"",COUNTIF(币种表,$E30)=0),"※币种不在右边币种清单里",IF($G30="","※期初余额没填（没有就填 0）",IF(AND($E30<>本位币,$H30="",$I30=""),"△这个币种一个汇率都没填，期初人民币成本算不出来",IF(AND($E30<>本位币,$H30=""),"△没填期初汇率，先拿期末汇率折的",""))))))
A31: =IF($C31="","",COUNTA($C$11:$C31)) | I31: =IF($C31="","",IFERROR(ROUND(N($G31)*IF($H31<>"",$H31,IF($E31=本位币,1,IFERROR(LOOKUP(2,1/((汇率月份<=重估基准日)*(INDEX(月末汇率区,0,MATCH($E31,汇率币种头,0))<>"")),INDEX(月末汇率区,0,MATCH($E31,汇率币种头,0))),IFERROR(LOOKUP(2,1/((汇率月份<=重估基准日)*(INDEX(记账汇率区,0,MATCH($E31,汇率币种头,0))<>"")),INDEX(记账汇率区,0,MATCH($E31,汇率币种头,0))),"")))),2),"")) | J31: =IF($C31="","",IF(COUNTIF($C$11:$C$40,$C31)>1,"※账户名称重复了，后面按名字取数会串",IF(AND($E31<>"",COUNTIF(币种表,$E31)=0),"※币种不在右边币种清单里",IF($G31="","※期初余额没填（没有就填 0）",IF(AND($E31<>本位币,$H31="",$I31=""),"△这个币种一个汇率都没填，期初人民币成本算不出来",IF(AND($E31<>本位币,$H31=""),"△没填期初汇率，先拿期末汇率折的",""))))))
A32: =IF($C32="","",COUNTA($C$11:$C32)) | I32: =IF($C32="","",IFERROR(ROUND(N($G32)*IF($H32<>"",$H32,IF($E32=本位币,1,IFERROR(LOOKUP(2,1/((汇率月份<=重估基准日)*(INDEX(月末汇率区,0,MATCH($E32,汇率币种头,0))<>"")),INDEX(月末汇率区,0,MATCH($E32,汇率币种头,0))),IFERROR(LOOKUP(2,1/((汇率月份<=重估基准日)*(INDEX(记账汇率区,0,MATCH($E32,汇率币种头,0))<>"")),INDEX(记账汇率区,0,MATCH($E32,汇率币种头,0))),"")))),2),"")) | J32: =IF($C32="","",IF(COUNTIF($C$11:$C$40,$C32)>1,"※账户名称重复了，后面按名字取数会串",IF(AND($E32<>"",COUNTIF(币种表,$E32)=0),"※币种不在右边币种清单里",IF($G32="","※期初余额没填（没有就填 0）",IF(AND($E32<>本位币,$H32="",$I32=""),"△这个币种一个汇率都没填，期初人民币成本算不出来",IF(AND($E32<>本位币,$H32=""),"△没填期初汇率，先拿期末汇率折的",""))))))
A33: =IF($C33="","",COUNTA($C$11:$C33)) | I33: =IF($C33="","",IFERROR(ROUND(N($G33)*IF($H33<>"",$H33,IF($E33=本位币,1,IFERROR(LOOKUP(2,1/((汇率月份<=重估基准日)*(INDEX(月末汇率区,0,MATCH($E33,汇率币种头,0))<>"")),INDEX(月末汇率区,0,MATCH($E33,汇率币种头,0))),IFERROR(LOOKUP(2,1/((汇率月份<=重估基准日)*(INDEX(记账汇率区,0,MATCH($E33,汇率币种头,0))<>"")),INDEX(记账汇率区,0,MATCH($E33,汇率币种头,0))),"")))),2),"")) | J33: =IF($C33="","",IF(COUNTIF($C$11:$C$40,$C33)>1,"※账户名称重复了，后面按名字取数会串",IF(AND($E33<>"",COUNTIF(币种表,$E33)=0),"※币种不在右边币种清单里",IF($G33="","※期初余额没填（没有就填 0）",IF(AND($E33<>本位币,$H33="",$I33=""),"△这个币种一个汇率都没填，期初人民币成本算不出来",IF(AND($E33<>本位币,$H33=""),"△没填期初汇率，先拿期末汇率折的",""))))))
A34: =IF($C34="","",COUNTA($C$11:$C34)) | I34: =IF($C34="","",IFERROR(ROUND(N($G34)*IF($H34<>"",$H34,IF($E34=本位币,1,IFERROR(LOOKUP(2,1/((汇率月份<=重估基准日)*(INDEX(月末汇率区,0,MATCH($E34,汇率币种头,0))<>"")),INDEX(月末汇率区,0,MATCH($E34,汇率币种头,0))),IFERROR(LOOKUP(2,1/((汇率月份<=重估基准日)*(INDEX(记账汇率区,0,MATCH($E34,汇率币种头,0))<>"")),INDEX(记账汇率区,0,MATCH($E34,汇率币种头,0))),"")))),2),"")) | J34: =IF($C34="","",IF(COUNTIF($C$11:$C$40,$C34)>1,"※账户名称重复了，后面按名字取数会串",IF(AND($E34<>"",COUNTIF(币种表,$E34)=0),"※币种不在右边币种清单里",IF($G34="","※期初余额没填（没有就填 0）",IF(AND($E34<>本位币,$H34="",$I34=""),"△这个币种一个汇率都没填，期初人民币成本算不出来",IF(AND($E34<>本位币,$H34=""),"△没填期初汇率，先拿期末汇率折的",""))))))
A35: =IF($C35="","",COUNTA($C$11:$C35)) | I35: =IF($C35="","",IFERROR(ROUND(N($G35)*IF($H35<>"",$H35,IF($E35=本位币,1,IFERROR(LOOKUP(2,1/((汇率月份<=重估基准日)*(INDEX(月末汇率区,0,MATCH($E35,汇率币种头,0))<>"")),INDEX(月末汇率区,0,MATCH($E35,汇率币种头,0))),IFERROR(LOOKUP(2,1/((汇率月份<=重估基准日)*(INDEX(记账汇率区,0,MATCH($E35,汇率币种头,0))<>"")),INDEX(记账汇率区,0,MATCH($E35,汇率币种头,0))),"")))),2),"")) | J35: =IF($C35="","",IF(COUNTIF($C$11:$C$40,$C35)>1,"※账户名称重复了，后面按名字取数会串",IF(AND($E35<>"",COUNTIF(币种表,$E35)=0),"※币种不在右边币种清单里",IF($G35="","※期初余额没填（没有就填 0）",IF(AND($E35<>本位币,$H35="",$I35=""),"△这个币种一个汇率都没填，期初人民币成本算不出来",IF(AND($E35<>本位币,$H35=""),"△没填期初汇率，先拿期末汇率折的",""))))))
A36: =IF($C36="","",COUNTA($C$11:$C36)) | I36: =IF($C36="","",IFERROR(ROUND(N($G36)*IF($H36<>"",$H36,IF($E36=本位币,1,IFERROR(LOOKUP(2,1/((汇率月份<=重估基准日)*(INDEX(月末汇率区,0,MATCH($E36,汇率币种头,0))<>"")),INDEX(月末汇率区,0,MATCH($E36,汇率币种头,0))),IFERROR(LOOKUP(2,1/((汇率月份<=重估基准日)*(INDEX(记账汇率区,0,MATCH($E36,汇率币种头,0))<>"")),INDEX(记账汇率区,0,MATCH($E36,汇率币种头,0))),"")))),2),"")) | J36: =IF($C36="","",IF(COUNTIF($C$11:$C$40,$C36)>1,"※账户名称重复了，后面按名字取数会串",IF(AND($E36<>"",COUNTIF(币种表,$E36)=0),"※币种不在右边币种清单里",IF($G36="","※期初余额没填（没有就填 0）",IF(AND($E36<>本位币,$H36="",$I36=""),"△这个币种一个汇率都没填，期初人民币成本算不出来",IF(AND($E36<>本位币,$H36=""),"△没填期初汇率，先拿期末汇率折的",""))))))
A37: =IF($C37="","",COUNTA($C$11:$C37)) | I37: =IF($C37="","",IFERROR(ROUND(N($G37)*IF($H37<>"",$H37,IF($E37=本位币,1,IFERROR(LOOKUP(2,1/((汇率月份<=重估基准日)*(INDEX(月末汇率区,0,MATCH($E37,汇率币种头,0))<>"")),INDEX(月末汇率区,0,MATCH($E37,汇率币种头,0))),IFERROR(LOOKUP(2,1/((汇率月份<=重估基准日)*(INDEX(记账汇率区,0,MATCH($E37,汇率币种头,0))<>"")),INDEX(记账汇率区,0,MATCH($E37,汇率币种头,0))),"")))),2),"")) | J37: =IF($C37="","",IF(COUNTIF($C$11:$C$40,$C37)>1,"※账户名称重复了，后面按名字取数会串",IF(AND($E37<>"",COUNTIF(币种表,$E37)=0),"※币种不在右边币种清单里",IF($G37="","※期初余额没填（没有就填 0）",IF(AND($E37<>本位币,$H37="",$I37=""),"△这个币种一个汇率都没填，期初人民币成本算不出来",IF(AND($E37<>本位币,$H37=""),"△没填期初汇率，先拿期末汇率折的",""))))))
A38: =IF($C38="","",COUNTA($C$11:$C38)) | I38: =IF($C38="","",IFERROR(ROUND(N($G38)*IF($H38<>"",$H38,IF($E38=本位币,1,IFERROR(LOOKUP(2,1/((汇率月份<=重估基准日)*(INDEX(月末汇率区,0,MATCH($E38,汇率币种头,0))<>"")),INDEX(月末汇率区,0,MATCH($E38,汇率币种头,0))),IFERROR(LOOKUP(2,1/((汇率月份<=重估基准日)*(INDEX(记账汇率区,0,MATCH($E38,汇率币种头,0))<>"")),INDEX(记账汇率区,0,MATCH($E38,汇率币种头,0))),"")))),2),"")) | J38: =IF($C38="","",IF(COUNTIF($C$11:$C$40,$C38)>1,"※账户名称重复了，后面按名字取数会串",IF(AND($E38<>"",COUNTIF(币种表,$E38)=0),"※币种不在右边币种清单里",IF($G38="","※期初余额没填（没有就填 0）",IF(AND($E38<>本位币,$H38="",$I38=""),"△这个币种一个汇率都没填，期初人民币成本算不出来",IF(AND($E38<>本位币,$H38=""),"△没填期初汇率，先拿期末汇率折的",""))))))
A39: =IF($C39="","",COUNTA($C$11:$C39)) | I39: =IF($C39="","",IFERROR(ROUND(N($G39)*IF($H39<>"",$H39,IF($E39=本位币,1,IFERROR(LOOKUP(2,1/((汇率月份<=重估基准日)*(INDEX(月末汇率区,0,MATCH($E39,汇率币种头,0))<>"")),INDEX(月末汇率区,0,MATCH($E39,汇率币种头,0))),IFERROR(LOOKUP(2,1/((汇率月份<=重估基准日)*(INDEX(记账汇率区,0,MATCH($E39,汇率币种头,0))<>"")),INDEX(记账汇率区,0,MATCH($E39,汇率币种头,0))),"")))),2),"")) | J39: =IF($C39="","",IF(COUNTIF($C$11:$C$40,$C39)>1,"※账户名称重复了，后面按名字取数会串",IF(AND($E39<>"",COUNTIF(币种表,$E39)=0),"※币种不在右边币种清单里",IF($G39="","※期初余额没填（没有就填 0）",IF(AND($E39<>本位币,$H39="",$I39=""),"△这个币种一个汇率都没填，期初人民币成本算不出来",IF(AND($E39<>本位币,$H39=""),"△没填期初汇率，先拿期末汇率折的",""))))))
A40: =IF($C40="","",COUNTA($C$11:$C40)) | I40: =IF($C40="","",IFERROR(ROUND(N($G40)*IF($H40<>"",$H40,IF($E40=本位币,1,IFERROR(LOOKUP(2,1/((汇率月份<=重估基准日)*(INDEX(月末汇率区,0,MATCH($E40,汇率币种头,0))<>"")),INDEX(月末汇率区,0,MATCH($E40,汇率币种头,0))),IFERROR(LOOKUP(2,1/((汇率月份<=重估基准日)*(INDEX(记账汇率区,0,MATCH($E40,汇率币种头,0))<>"")),INDEX(记账汇率区,0,MATCH($E40,汇率币种头,0))),"")))),2),"")) | J40: =IF($C40="","",IF(COUNTIF($C$11:$C$40,$C40)>1,"※账户名称重复了，后面按名字取数会串",IF(AND($E40<>"",COUNTIF(币种表,$E40)=0),"※币种不在右边币种清单里",IF($G40="","※期初余额没填（没有就填 0）",IF(AND($E40<>本位币,$H40="",$I40=""),"△这个币种一个汇率都没填，期初人民币成本算不出来",IF(AND($E40<>本位币,$H40=""),"△没填期初汇率，先拿期末汇率折的",""))))))

Sheet 月度汇率
A1: 月度汇率 · 每月填一次，填了就不用再动
A2: 左边【记账汇率】是流水折人民币用的；右边【月末汇率】是月末重估用的，空着就自动用左边那个。某月没填？自动往前找最近一个填过的月份，并在核对表点名。
A4: 记账汇率 —— 流水按「交易日期所在月」自动匹配 | K4: 月末汇率 —— 月末重估用；空着=用左边记账汇率
A5: 月份 | B5: CNY | C5: USD | D5: HKD | E5: EUR | F5: JPY | G5: GBP | H5: SGD | I5: AUD | K5: CNY | L5: USD | M5: HKD | N5: EUR | O5: JPY | P5: GBP | Q5: SGD | R5: AUD | T5: 这一列别删：给核对表数「哪几个月还没填」用的 | U5: 本月外币流水笔数
A6: =DATE(管理年度,1,1) -> 46023 | B6: 1 | K6: 1 | T6: =IF($A6="","",COUNTA($C6:$I6)) -> 0 | U6: =IF($A6="","",COUNTIFS(流水日期,">="&$A6,流水日期,"<="&EOMONTH($A6,0),流水币种,"<>"&本位币)) -> 0
A7: =EDATE(A6,1) -> 46054 | B7: 1 | K7: 1 | T7: =IF($A7="","",COUNTA($C7:$I7)) -> 0 | U7: =IF($A7="","",COUNTIFS(流水日期,">="&$A7,流水日期,"<="&EOMONTH($A7,0),流水币种,"<>"&本位币)) -> 0
A8: =EDATE(A7,1) -> 46082 | B8: 1 | K8: 1 | T8: =IF($A8="","",COUNTA($C8:$I8)) -> 0 | U8: =IF($A8="","",COUNTIFS(流水日期,">="&$A8,流水日期,"<="&EOMONTH($A8,0),流水币种,"<>"&本位币)) -> 0
A9: =EDATE(A8,1) -> 46113 | B9: 1 | K9: 1 | T9: =IF($A9="","",COUNTA($C9:$I9)) -> 0 | U9: =IF($A9="","",COUNTIFS(流水日期,">="&$A9,流水日期,"<="&EOMONTH($A9,0),流水币种,"<>"&本位币)) -> 0
A10: =EDATE(A9,1) -> 46143 | B10: 1 | K10: 1 | T10: =IF($A10="","",COUNTA($C10:$I10)) -> 0 | U10: =IF($A10="","",COUNTIFS(流水日期,">="&$A10,流水日期,"<="&EOMONTH($A10,0),流水币种,"<>"&本位币)) -> 0
A11: =EDATE(A10,1) -> 46174 | B11: 1 | K11: 1 | T11: =IF($A11="","",COUNTA($C11:$I11)) -> 0 | U11: =IF($A11="","",COUNTIFS(流水日期,">="&$A11,流水日期,"<="&EOMONTH($A11,0),流水币种,"<>"&本位币)) -> 0
A12: =EDATE(A11,1) -> 46204 | B12: 1 | K12: 1 | T12: =IF($A12="","",COUNTA($C12:$I12)) -> 0 | U12: =IF($A12="","",COUNTIFS(流水日期,">="&$A12,流水日期,"<="&EOMONTH($A12,0),流水币种,"<>"&本位币)) -> 0
A13: =EDATE(A12,1) -> 46235 | B13: 1 | C13: 7.18 | D13: 0.92 | E13: 7.69 | K13: 1 | T13: =IF($A13="","",COUNTA($C13:$I13)) -> 3 | U13: =IF($A13="","",COUNTIFS(流水日期,">="&$A13,流水日期,"<="&EOMONTH($A13,0),流水币种,"<>"&本位币)) -> 10
A14: =EDATE(A13,1) -> 46266 | B14: 1 | K14: 1 | T14: =IF($A14="","",COUNTA($C14:$I14)) -> 0 | U14: =IF($A14="","",COUNTIFS(流水日期,">="&$A14,流水日期,"<="&EOMONTH($A14,0),流水币种,"<>"&本位币)) -> 0
A15: =EDATE(A14,1) -> 46296 | B15: 1 | K15: 1 | T15: =IF($A15="","",COUNTA($C15:$I15)) -> 0 | U15: =IF($A15="","",COUNTIFS(流水日期,">="&$A15,流水日期,"<="&EOMONTH($A15,0),流水币种,"<>"&本位币)) -> 0
A16: =EDATE(A15,1) -> 46327 | B16: 1 | K16: 1 | T16: =IF($A16="","",COUNTA($C16:$I16)) -> 0 | U16: =IF($A16="","",COUNTIFS(流水日期,">="&$A16,流水日期,"<="&EOMONTH($A16,0),流水币种,"<>"&本位币)) -> 0
A17: =EDATE(A16,1) -> 46357 | B17: 1 | K17: 1 | T17: =IF($A17="","",COUNTA($C17:$I17)) -> 0 | U17: =IF($A17="","",COUNTIFS(流水日期,">="&$A17,流水日期,"<="&EOMONTH($A17,0),流水币种,"<>"&本位币)) -> 0
A18: 全年填了几个月 | B18: =COUNT(B6:B17) -> 12 | C18: =COUNT(C6:C17) -> 1 | D18: =COUNT(D6:D17) -> 1 | E18: =COUNT(E6:E17) -> 1 | F18: =COUNT(F6:F17) -> 0 | G18: =COUNT(G6:G17) -> 0 | H18: =COUNT(H6:H17) -> 0 | I18: =COUNT(I6:I17) -> 0

Sheet 流水录入
A1: 流水录入 · 全套表只有这一张要填
A2: 选账户名称 → 银行、币种、汇率自动带出来；收入和支出分两列，只填一个。银行有实际成交价（购汇、结汇）就填「实际成交汇率」，它优先于当月记账汇率。最后一列「核对」会自己挑毛病，红字是错、琥珀字是待办。
A5: 日期 ★ | B5: 账户名称 ★ | C5: 银行 | D5: 币种 | E5: 收/支类别 ★ | F5: 类别属性 | G5: 收入金额(原币) | H5: 支出金额(原币) | I5: 实际成交汇率 (选填) | J5: 应用汇率 | K5: 原币净额 | L5: 折人民币 | M5: 账户余额(原币) | N5: 账面人民币余额 | O5: 摘要 | P5: 项目/业务 | Q5: 往来单位 | R5: 备注 | S5: 核对
A6: 46237 | B6: 工商银行基本户-8888 | C6: =IF($B6="","",IFERROR(INDEX(账户银行,MATCH($B6,账户名,0)),"")) -> 工商银行 | D6: =IF($B6="","",IFERROR(INDEX(账户币种,MATCH($B6,账户名,0)),"")) -> CNY | E6: 销售回款 | F6: =IF($E6="","",IFERROR(INDEX(类别属性,MATCH($E6,类别表,0)),"")) -> 收入 | G6: 120000 | J6: =IF(OR($A6="",$B6=""),"",IF($I6<>"",$I6,IF($D6=本位币,1,IFERROR(LOOKUP(2,1/((汇率月份<=$A6)*(INDEX(记账汇率区,0,MATCH($D6,汇率币种头,0))<>"")),INDEX(记账汇率区,0,MATCH($D6,汇率币种头,0))),"")))) -> 1 | K6: =IF(AND($G6="",$H6=""),"",ROUND(N($G6)-N($H6),2)) -> 120000 | L6: =IF(OR($K6="",$J6=""),"",ROUND($K6*$J6,2)) -> 120000 | M6: =IF($B6="","",ROUND(SUMIF(账户名,$B6,账户期初)+SUMIFS($K$6:K6,$B$6:B6,$B6),2)) -> 620000 | N6: =IF($B6="","",IFERROR(ROUND(INDEX(账户期初本位,MATCH($B6,账户名,0))+SUMIFS($L$6:L6,$B$6:B6,$B6),2),"")) -> 620000 | O6: 销售回款 | P6: 项目A | Q6: 华东客户A | S6: =IF($B6="","",IF(ISNA(MATCH($B6,账户名,0)),"※这个账户不在【参数设置】的账户档案里",IF($A6="","※没填日期，这一笔不会进任何月份的报表",IF(AND($G6<>"",$H6<>""),"※收入和支出不能同时填",IF(AND(N($G6)=0,N($H6)=0),"※收入和支出都没填",IF($E6="","※没填收支类别，分类报表会漏掉这一笔",IF(ISNA(MATCH($E6,类别表,0)),"※收支类别不在【参数设置】的清单里",IF($J6="","△"&$D6&" 还没填汇率，去【月度汇率】补上就自动算了",IF(YEAR($A6)<>管理年度,"△不是管理年度的单据，年报里看不到",IF(AND($F6="内部转账",$Q6=""),"△内部转账建议在「往来单位」写上对方账户",IF($M6<0,"△这一笔之后该账户余额成负数了，核一下","")))))))))))
A7: 46238 | B7: 中国银行美元结算户-6688 | C7: =IF($B7="","",IFERROR(INDEX(账户银行,MATCH($B7,账户名,0)),"")) -> 中国银行 | D7: =IF($B7="","",IFERROR(INDEX(账户币种,MATCH($B7,账户名,0)),"")) -> USD | E7: 销售回款 | F7: =IF($E7="","",IFERROR(INDEX(类别属性,MATCH($E7,类别表,0)),"")) -> 收入 | G7: 25000 | J7: =IF(OR($A7="",$B7=""),"",IF($I7<>"",$I7,IF($D7=本位币,1,IFERROR(LOOKUP(2,1/((汇率月份<=$A7)*(INDEX(记账汇率区,0,MATCH($D7,汇率币种头,0))<>"")),INDEX(记账汇率区,0,MATCH($D7,汇率币种头,0))),"")))) -> 7.18 | K7: =IF(AND($G7="",$H7=""),"",ROUND(N($G7)-N($H7),2)) -> 25000 | L7: =IF(OR($K7="",$J7=""),"",ROUND($K7*$J7,2)) -> 179500 | M7: =IF($B7="","",ROUND(SUMIF(账户名,$B7,账户期初)+SUMIFS($K$6:K7,$B$6:B7,$B7),2)) -> 825000 | N7: =IF($B7="","",IFERROR(ROUND(INDEX(账户期初本位,MATCH($B7,账户名,0))+SUMIFS($L$6:L7,$B$6:B7,$B7),2),"")) -> 5899500 | O7: 美元货款 | P7: 出口业务 | Q7: Overseas Client A | S7: =IF($B7="","",IF(ISNA(MATCH($B7,账户名,0)),"※这个账户不在【参数设置】的账户档案里",IF($A7="","※没填日期，这一笔不会进任何月份的报表",IF(AND($G7<>"",$H7<>""),"※收入和支出不能同时填",IF(AND(N($G7)=0,N($H7)=0),"※收入和支出都没填",IF($E7="","※没填收支类别，分类报表会漏掉这一笔",IF(ISNA(MATCH($E7,类别表,0)),"※收支类别不在【参数设置】的清单里",IF($J7="","△"&$D7&" 还没填汇率，去【月度汇率】补上就自动算了",IF(YEAR($A7)<>管理年度,"△不是管理年度的单据，年报里看不到",IF(AND($F7="内部转账",$Q7=""),"△内部转账建议在「往来单位」写上对方账户",IF($M7<0,"△这一笔之后该账户余额成负数了，核一下","")))))))))))
A8: 46239 | B8: 汇丰银行港币结算户-5566 | C8: =IF($B8="","",IFERROR(INDEX(账户银行,MATCH($B8,账户名,0)),"")) -> 汇丰银行 | D8: =IF($B8="","",IFERROR(INDEX(账户币种,MATCH($B8,账户名,0)),"")) -> HKD | E8: 采购付款 | F8: =IF($E8="","",IFERROR(INDEX(类别属性,MATCH($E8,类别表,0)),"")) -> 支出 | H8: 4500 | J8: =IF(OR($A8="",$B8=""),"",IF($I8<>"",$I8,IF($D8=本位币,1,IFERROR(LOOKUP(2,1/((汇率月份<=$A8)*(INDEX(记账汇率区,0,MATCH($D8,汇率币种头,0))<>"")),INDEX(记账汇率区,0,MATCH($D8,汇率币种头,0))),"")))) -> 0.92 | K8: =IF(AND($G8="",$H8=""),"",ROUND(N($G8)-N($H8),2)) -> -4500 | L8: =IF(OR($K8="",$J8=""),"",ROUND($K8*$J8,2)) -> -4140 | M8: =IF($B8="","",ROUND(SUMIF(账户名,$B8,账户期初)+SUMIFS($K$6:K8,$B$6:B8,$B8),2)) -> 295500 | N8: =IF($B8="","",IFERROR(ROUND(INDEX(账户期初本位,MATCH($B8,账户名,0))+SUMIFS($L$6:L8,$B$6:B8,$B8),2),"")) -> 270360 | O8: 港币采购付款 | P8: 进口业务 | Q8: 香港供应商A | S8: =IF($B8="","",IF(ISNA(MATCH($B8,账户名,0)),"※这个账户不在【参数设置】的账户档案里",IF($A8="","※没填日期，这一笔不会进任何月份的报表",IF(AND($G8<>"",$H8<>""),"※收入和支出不能同时填",IF(AND(N($G8)=0,N($H8)=0),"※收入和支出都没填",IF($E8="","※没填收支类别，分类报表会漏掉这一笔",IF(ISNA(MATCH($E8,类别表,0)),"※收支类别不在【参数设置】的清单里",IF($J8="","△"&$D8&" 还没填汇率，去【月度汇率】补上就自动算了",IF(YEAR($A8)<>管理年度,"△不是管理年度的单据，年报里看不到",IF(AND($F8="内部转账",$Q8=""),"△内部转账建议在「往来单位」写上对方账户",IF($M8<0,"△这一笔之后该账户余额成负数了，核一下","")))))))))))
A9: 46240 | B9: 招商银行一般户-2388 | C9: =IF($B9="","",IFERROR(INDEX(账户银行,MATCH($B9,账户名,0)),"")) -> 招商银行 | D9: =IF($B9="","",IFERROR(INDEX(账户币种,MATCH($B9,账户名,0)),"")) -> CNY | E9: 工资 | F9: =IF($E9="","",IFERROR(INDEX(类别属性,MATCH($E9,类别表,0)),"")) -> 支出 | H9: 30000 | J9: =IF(OR($A9="",$B9=""),"",IF($I9<>"",$I9,IF($D9=本位币,1,IFERROR(LOOKUP(2,1/((汇率月份<=$A9)*(INDEX(记账汇率区,0,MATCH($D9,汇率币种头,0))<>"")),INDEX(记账汇率区,0,MATCH($D9,汇率币种头,0))),"")))) -> 1 | K9: =IF(AND($G9="",$H9=""),"",ROUND(N($G9)-N($H9),2)) -> -30000 | L9: =IF(OR($K9="",$J9=""),"",ROUND($K9*$J9,2)) -> -30000 | M9: =IF($B9="","",ROUND(SUMIF(账户名,$B9,账户期初)+SUMIFS($K$6:K9,$B$6:B9,$B9),2)) -> 170000 | N9: =IF($B9="","",IFERROR(ROUND(INDEX(账户期初本位,MATCH($B9,账户名,0))+SUMIFS($L$6:L9,$B$6:B9,$B9),2),"")) -> 170000 | O9: 工资发放 | P9: 行政 | Q9: 员工薪酬 | S9: =IF($B9="","",IF(ISNA(MATCH($B9,账户名,0)),"※这个账户不在【参数设置】的账户档案里",IF($A9="","※没填日期，这一笔不会进任何月份的报表",IF(AND($G9<>"",$H9<>""),"※收入和支出不能同时填",IF(AND(N($G9)=0,N($H9)=0),"※收入和支出都没填",IF($E9="","※没填收支类别，分类报表会漏掉这一笔",IF(ISNA(MATCH($E9,类别表,0)),"※收支类别不在【参数设置】的清单里",IF($J9="","△"&$D9&" 还没填汇率，去【月度汇率】补上就自动算了",IF(YEAR($A9)<>管理年度,"△不是管理年度的单据，年报里看不到",IF(AND($F9="内部转账",$Q9=""),"△内部转账建议在「往来单位」写上对方账户",IF($M9<0,"△这一笔之后该账户余额成负数了，核一下","")))))))))))
A10: 46241 | B10: 汇丰银行美元结算户-7788 | C10: =IF($B10="","",IFERROR(INDEX(账户银行,MATCH($B10,账户名,0)),"")) -> 汇丰银行 | D10: =IF($B10="","",IFERROR(INDEX(账户币种,MATCH($B10,账户名,0)),"")) -> USD | E10: 投资款 | F10: =IF($E10="","",IFERROR(INDEX(类别属性,MATCH($E10,类别表,0)),"")) -> 收入 | G10: 12000 | J10: =IF(OR($A10="",$B10=""),"",IF($I10<>"",$I10,IF($D10=本位币,1,IFERROR(LOOKUP(2,1/((汇率月份<=$A10)*(INDEX(记账汇率区,0,MATCH($D10,汇率币种头,0))<>"")),INDEX(记账汇率区,0,MATCH($D10,汇率币种头,0))),"")))) -> 7.18 | K10: =IF(AND($G10="",$H10=""),"",ROUND(N($G10)-N($H10),2)) -> 12000 | L10: =IF(OR($K10="",$J10=""),"",ROUND($K10*$J10,2)) -> 86160 | M10: =IF($B10="","",ROUND(SUMIF(账户名,$B10,账户期初)+SUMIFS($K$6:K10,$B$6:B10,$B10),2)) -> 512000 | N10: =IF($B10="","",IFERROR(ROUND(INDEX(账户期初本位,MATCH($B10,账户名,0))+SUMIFS($L$6:L10,$B$6:B10,$B10),2),"")) -> 3661160 | O10: 美元投资款 | P10: 融资 | Q10: 股东A | S10: =IF($B10="","",IF(ISNA(MATCH($B10,账户名,0)),"※这个账户不在【参数设置】的账户档案里",IF($A10="","※没填日期，这一笔不会进任何月份的报表",IF(AND($G10<>"",$H10<>""),"※收入和支出不能同时填",IF(AND(N($G10)=0,N($H10)=0),"※收入和支出都没填",IF($E10="","※没填收支类别，分类报表会漏掉这一笔",IF(ISNA(MATCH($E10,类别表,0)),"※收支类别不在【参数设置】的清单里",IF($J10="","△"&$D10&" 还没填汇率，去【月度汇率】补上就自动算了",IF(YEAR($A10)<>管理年度,"△不是管理年度的单据，年报里看不到",IF(AND($F10="内部转账",$Q10=""),"△内部转账建议在「往来单位」写上对方账户",IF($M10<0,"△这一笔之后该账户余额成负数了，核一下","")))))))))))
A11: 46242 | B11: 工商银行基本户-8888 | C11: =IF($B11="","",IFERROR(INDEX(账户银行,MATCH($B11,账户名,0)),"")) -> 工商银行 | D11: =IF($B11="","",IFERROR(INDEX(账户币种,MATCH($B11,账户名,0)),"")) -> CNY | E11: 税费 | F11: =IF($E11="","",IFERROR(INDEX(类别属性,MATCH($E11,类别表,0)),"")) -> 支出 | H11: 18000 | J11: =IF(OR($A11="",$B11=""),"",IF($I11<>"",$I11,IF($D11=本位币,1,IFERROR(LOOKUP(2,1/((汇率月份<=$A11)*(INDEX(记账汇率区,0,MATCH($D11,汇率币种头,0))<>"")),INDEX(记账汇率区,0,MATCH($D11,汇率币种头,0))),"")))) -> 1 | K11: =IF(AND($G11="",$H11=""),"",ROUND(N($G11)-N($H11),2)) -> -18000 | L11: =IF(OR($K11="",$J11=""),"",ROUND($K11*$J11,2)) -> -18000 | M11: =IF($B11="","",ROUND(SUMIF(账户名,$B11,账户期初)+SUMIFS($K$6:K11,$B$6:B11,$B11),2)) -> 602000 | N11: =IF($B11="","",IFERROR(ROUND(INDEX(账户期初本位,MATCH($B11,账户名,0))+SUMIFS($L$6:L11,$B$6:B11,$B11),2),"")) -> 602000 | O11: 税费缴纳 | P11: 税务 | Q11: 税务机关 | S11: =IF($B11="","",IF(ISNA(MATCH($B11,账户名,0)),"※这个账户不在【参数设置】的账户档案里",IF($A11="","※没填日期，这一笔不会进任何月份的报表",IF(AND($G11<>"",$H11<>""),"※收入和支出不能同时填",IF(AND(N($G11)=0,N($H11)=0),"※收入和支出都没填",IF($E11="","※没填收支类别，分类报表会漏掉这一笔",IF(ISNA(MATCH($E11,类别表,0)),"※收支类别不在【参数设置】的清单里",IF($J11="","△"&$D11&" 还没填汇率，去【月度汇率】补上就自动算了",IF(YEAR($A11)<>管理年度,"△不是管理年度的单据，年报里看不到",IF(AND($F11="内部转账",$Q11=""),"△内部转账建议在「往来单位」写上对方账户",IF($M11<0,"△这一笔之后该账户余额成负数了，核一下","")))))))))))
A12: 46244 | B12: 中国银行美元结算户-6688 | C12: =IF($B12="","",IFERROR(INDEX(账户银行,MATCH($B12,账户名,0)),"")) -> 中国银行 | D12: =IF($B12="","",IFERROR(INDEX(账户币种,MATCH($B12,账户名,0)),"")) -> USD | E12: 采购付款 | F12: =IF($E12="","",IFERROR(INDEX(类别属性,MATCH($E12,类别表,0)),"")) -> 支出 | H12: 8000 | I12: 7.16 | J12: =IF(OR($A12="",$B12=""),"",IF($I12<>"",$I12,IF($D12=本位币,1,IFERROR(LOOKUP(2,1/((汇率月份<=$A12)*(INDEX(记账汇率区,0,MATCH($D12,汇率币种头,0))<>"")),INDEX(记账汇率区,0,MATCH($D12,汇率币种头,0))),"")))) -> 7.16 | K12: =IF(AND($G12="",$H12=""),"",ROUND(N($G12)-N($H12),2)) -> -8000 | L12: =IF(OR($K12="",$J12=""),"",ROUND($K12*$J12,2)) -> -57280 | M12: =IF($B12="","",ROUND(SUMIF(账户名,$B12,账户期初)+SUMIFS($K$6:K12,$B$6:B12,$B12),2)) -> 817000 | N12: =IF($B12="","",IFERROR(ROUND(INDEX(账户期初本位,MATCH($B12,账户名,0))+SUMIFS($L$6:L12,$B$6:B12,$B12),2),"")) -> 5842220 | O12: 美元采购款（银行实际成交价） | P12: 进口业务 | Q12: Overseas Supplier B | S12: =IF($B12="","",IF(ISNA(MATCH($B12,账户名,0)),"※这个账户不在【参数设置】的账户档案里",IF($A12="","※没填日期，这一笔不会进任何月份的报表",IF(AND($G12<>"",$H12<>""),"※收入和支出不能同时填",IF(AND(N($G12)=0,N($H12)=0),"※收入和支出都没填",IF($E12="","※没填收支类别，分类报表会漏掉这一笔",IF(ISNA(MATCH($E12,类别表,0)),"※收支类别不在【参数设置】的清单里",IF($J12="","△"&$D12&" 还没填汇率，去【月度汇率】补上就自动算了",IF(YEAR($A12)<>管理年度,"△不是管理年度的单据，年报里看不到",IF(AND($F12="内部转账",$Q12=""),"△内部转账建议在「往来单位」写上对方账户",IF($M12<0,"△这一笔之后该账户余额成负数了，核一下","")))))))))))
A13: 46245 | B13: 汇丰银行港币结算户-5566 | C13: =IF($B13="","",IFERROR(INDEX(账户银行,MATCH($B13,账户名,0)),"")) -> 汇丰银行 | D13: =IF($B13="","",IFERROR(INDEX(账户币种,MATCH($B13,账户名,0)),"")) -> HKD | E13: 销售回款 | F13: =IF($E13="","",IFERROR(INDEX(类别属性,MATCH($E13,类别表,0)),"")) -> 收入 | G13: 80000 | J13: =IF(OR($A13="",$B13=""),"",IF($I13<>"",$I13,IF($D13=本位币,1,IFERROR(LOOKUP(2,1/((汇率月份<=$A13)*(INDEX(记账汇率区,0,MATCH($D13,汇率币种头,0))<>"")),INDEX(记账汇率区,0,MATCH($D13,汇率币种头,0))),"")))) -> 0.92 | K13: =IF(AND($G13="",$H13=""),"",ROUND(N($G13)-N($H13),2)) -> 80000 | L13: =IF(OR($K13="",$J13=""),"",ROUND($K13*$J13,2)) -> 73600 | M13: =IF($B13="","",ROUND(SUMIF(账户名,$B13,账户期初)+SUMIFS($K$6:K13,$B$6:B13,$B13),2)) -> 375500 | N13: =IF($B13="","",IFERROR(ROUND(INDEX(账户期初本位,MATCH($B13,账户名,0))+SUMIFS($L$6:L13,$B$6:B13,$B13),2),"")) -> 343960 | O13: 港币销售回款 | P13: 香港业务 | Q13: 香港客户B | S13: =IF($B13="","",IF(ISNA(MATCH($B13,账户名,0)),"※这个账户不在【参数设置】的账户档案里",IF($A13="","※没填日期，这一笔不会进任何月份的报表",IF(AND($G13<>"",$H13<>""),"※收入和支出不能同时填",IF(AND(N($G13)=0,N($H13)=0),"※收入和支出都没填",IF($E13="","※没填收支类别，分类报表会漏掉这一笔",IF(ISNA(MATCH($E13,类别表,0)),"※收支类别不在【参数设置】的清单里",IF($J13="","△"&$D13&" 还没填汇率，去【月度汇率】补上就自动算了",IF(YEAR($A13)<>管理年度,"△不是管理年度的单据，年报里看不到",IF(AND($F13="内部转账",$Q13=""),"△内部转账建议在「往来单位」写上对方账户",IF($M13<0,"△这一笔之后该账户余额成负数了，核一下","")))))))))))
A14: 46246 | B14: 招商银行一般户-2388 | C14: =IF($B14="","",IFERROR(INDEX(账户银行,MATCH($B14,账户名,0)),"")) -> 招商银行 | D14: =IF($B14="","",IFERROR(INDEX(账户币种,MATCH($B14,账户名,0)),"")) -> CNY | E14: 借款 | F14: =IF($E14="","",IFERROR(INDEX(类别属性,MATCH($E14,类别表,0)),"")) -> 收入 | G14: 60000 | J14: =IF(OR($A14="",$B14=""),"",IF($I14<>"",$I14,IF($D14=本位币,1,IFERROR(LOOKUP(2,1/((汇率月份<=$A14)*(INDEX(记账汇率区,0,MATCH($D14,汇率币种头,0))<>"")),INDEX(记账汇率区,0,MATCH($D14,汇率币种头,0))),"")))) -> 1 | K14: =IF(AND($G14="",$H14=""),"",ROUND(N($G14)-N($H14),2)) -> 60000 | L14: =IF(OR($K14="",$J14=""),"",ROUND($K14*$J14,2)) -> 60000 | M14: =IF($B14="","",ROUND(SUMIF(账户名,$B14,账户期初)+SUMIFS($K$6:K14,$B$6:B14,$B14),2)) -> 230000 | N14: =IF($B14="","",IFERROR(ROUND(INDEX(账户期初本位,MATCH($B14,账户名,0))+SUMIFS($L$6:L14,$B$6:B14,$B14),2),"")) -> 230000 | O14: 短期借款到账 | P14: 融资 | Q14: 银行借款 | S14: =IF($B14="","",IF(ISNA(MATCH($B14,账户名,0)),"※这个账户不在【参数设置】的账户档案里",IF($A14="","※没填日期，这一笔不会进任何月份的报表",IF(AND($G14<>"",$H14<>""),"※收入和支出不能同时填",IF(AND(N($G14)=0,N($H14)=0),"※收入和支出都没填",IF($E14="","※没填收支类别，分类报表会漏掉这一笔",IF(ISNA(MATCH($E14,类别表,0)),"※收支类别不在【参数设置】的清单里",IF($J14="","△"&$D14&" 还没填汇率，去【月度汇率】补上就自动算了",IF(YEAR($A14)<>管理年度,"△不是管理年度的单据，年报里看不到",IF(AND($F14="内部转账",$Q14=""),"△内部转账建议在「往来单位」写上对方账户",IF($M14<0,"△这一笔之后该账户余额成负数了，核一下","")))))))))))
A15: 46247 | B15: 汇丰银行美元结算户-7788 | C15: =IF($B15="","",IFERROR(INDEX(账户银行,MATCH($B15,账户名,0)),"")) -> 汇丰银行 | D15: =IF($B15="","",IFERROR(INDEX(账户币种,MATCH($B15,账户名,0)),"")) -> USD | E15: 运营费用 | F15: =IF($E15="","",IFERROR(INDEX(类别属性,MATCH($E15,类别表,0)),"")) -> 支出 | H15: 5000 | J15: =IF(OR($A15="",$B15=""),"",IF($I15<>"",$I15,IF($D15=本位币,1,IFERROR(LOOKUP(2,1/((汇率月份<=$A15)*(INDEX(记账汇率区,0,MATCH($D15,汇率币种头,0))<>"")),INDEX(记账汇率区,0,MATCH($D15,汇率币种头,0))),"")))) -> 7.18 | K15: =IF(AND($G15="",$H15=""),"",ROUND(N($G15)-N($H15),2)) -> -5000 | L15: =IF(OR($K15="",$J15=""),"",ROUND($K15*$J15,2)) -> -35900 | M15: =IF($B15="","",ROUND(SUMIF(账户名,$B15,账户期初)+SUMIFS($K$6:K15,$B$6:B15,$B15),2)) -> 507000 | N15: =IF($B15="","",IFERROR(ROUND(INDEX(账户期初本位,MATCH($B15,账户名,0))+SUMIFS($L$6:L15,$B$6:B15,$B15),2),"")) -> 3625260 | O15: 美元服务费 | P15: 海外服务 | Q15: Service Provider | S15: =IF($B15="","",IF(ISNA(MATCH($B15,账户名,0)),"※这个账户不在【参数设置】的账户档案里",IF($A15="","※没填日期，这一笔不会进任何月份的报表",IF(AND($G15<>"",$H15<>""),"※收入和支出不能同时填",IF(AND(N($G15)=0,N($H15)=0),"※收入和支出都没填",IF($E15="","※没填收支类别，分类报表会漏掉这一笔",IF(ISNA(MATCH($E15,类别表,0)),"※收支类别不在【参数设置】的清单里",IF($J15="","△"&$D15&" 还没填汇率，去【月度汇率】补上就自动算了",IF(YEAR($A15)<>管理年度,"△不是管理年度的单据，年报里看不到",IF(AND($F15="内部转账",$Q15=""),"△内部转账建议在「往来单位」写上对方账户",IF($M15<0,"△这一笔之后该账户余额成负数了，核一下","")))))))))))
A16: 46248 | B16: 工商银行基本户-8888 | C16: =IF($B16="","",IFERROR(INDEX(账户银行,MATCH($B16,账户名,0)),"")) -> 工商银行 | D16: =IF($B16="","",IFERROR(INDEX(账户币种,MATCH($B16,账户名,0)),"")) -> CNY | E16: 内部转账 | F16: =IF($E16="","",IFERROR(INDEX(类别属性,MATCH($E16,类别表,0)),"")) -> 内部转账 | H16: 50000 | J16: =IF(OR($A16="",$B16=""),"",IF($I16<>"",$I16,IF($D16=本位币,1,IFERROR(LOOKUP(2,1/((汇率月份<=$A16)*(INDEX(记账汇率区,0,MATCH($D16,汇率币种头,0))<>"")),INDEX(记账汇率区,0,MATCH($D16,汇率币种头,0))),"")))) -> 1 | K16: =IF(AND($G16="",$H16=""),"",ROUND(N($G16)-N($H16),2)) -> -50000 | L16: =IF(OR($K16="",$J16=""),"",ROUND($K16*$J16,2)) -> -50000 | M16: =IF($B16="","",ROUND(SUMIF(账户名,$B16,账户期初)+SUMIFS($K$6:K16,$B$6:B16,$B16),2)) -> 552000 | N16: =IF($B16="","",IFERROR(ROUND(INDEX(账户期初本位,MATCH($B16,账户名,0))+SUMIFS($L$6:L16,$B$6:B16,$B16),2),"")) -> 552000 | O16: 转至招商银行 | P16: 内部调拨 | Q16: 招商银行一般户-2388 | S16: =IF($B16="","",IF(ISNA(MATCH($B16,账户名,0)),"※这个账户不在【参数设置】的账户档案里",IF($A16="","※没填日期，这一笔不会进任何月份的报表",IF(AND($G16<>"",$H16<>""),"※收入和支出不能同时填",IF(AND(N($G16)=0,N($H16)=0),"※收入和支出都没填",IF($E16="","※没填收支类别，分类报表会漏掉这一笔",IF(ISNA(MATCH($E16,类别表,0)),"※收支类别不在【参数设置】的清单里",IF($J16="","△"&$D16&" 还没填汇率，去【月度汇率】补上就自动算了",IF(YEAR($A16)<>管理年度,"△不是管理年度的单据，年报里看不到",IF(AND($F16="内部转账",$Q16=""),"△内部转账建议在「往来单位」写上对方账户",IF($M16<0,"△这一笔之后该账户余额成负数了，核一下","")))))))))))
A17: 46248 | B17: 招商银行一般户-2388 | C17: =IF($B17="","",IFERROR(INDEX(账户银行,MATCH($B17,账户名,0)),"")) -> 招商银行 | D17: =IF($B17="","",IFERROR(INDEX(账户币种,MATCH($B17,账户名,0)),"")) -> CNY | E17: 内部转账 | F17: =IF($E17="","",IFERROR(INDEX(类别属性,MATCH($E17,类别表,0)),"")) -> 内部转账 | G17: 50000 | J17: =IF(OR($A17="",$B17=""),"",IF($I17<>"",$I17,IF($D17=本位币,1,IFERROR(LOOKUP(2,1/((汇率月份<=$A17)*(INDEX(记账汇率区,0,MATCH($D17,汇率币种头,0))<>"")),INDEX(记账汇率区,0,MATCH($D17,汇率币种头,0))),"")))) -> 1 | K17: =IF(AND($G17="",$H17=""),"",ROUND(N($G17)-N($H17),2)) -> 50000 | L17: =IF(OR($K17="",$J17=""),"",ROUND($K17*$J17,2)) -> 50000 | M17: =IF($B17="","",ROUND(SUMIF(账户名,$B17,账户期初)+SUMIFS($K$6:K17,$B$6:B17,$B17),2)) -> 280000 | N17: =IF($B17="","",IFERROR(ROUND(INDEX(账户期初本位,MATCH($B17,账户名,0))+SUMIFS($L$6:L17,$B$6:B17,$B17),2),"")) -> 280000 | O17: 收到工商银行转入 | P17: 内部调拨 | Q17: 工商银行基本户-8888 | S17: =IF($B17="","",IF(ISNA(MATCH($B17,账户名,0)),"※这个账户不在【参数设置】的账户档案里",IF($A17="","※没填日期，这一笔不会进任何月份的报表",IF(AND($G17<>"",$H17<>""),"※收入和支出不能同时填",IF(AND(N($G17)=0,N($H17)=0),"※收入和支出都没填",IF($E17="","※没填收支类别，分类报表会漏掉这一笔",IF(ISNA(MATCH($E17,类别表,0)),"※收支类别不在【参数设置】的清单里",IF($J17="","△"&$D17&" 还没填汇率，去【月度汇率】补上就自动算了",IF(YEAR($A17)<>管理年度,"△不是管理年度的单据，年报里看不到",IF(AND($F17="内部转账",$Q17=""),"△内部转账建议在「往来单位」写上对方账户",IF($M17<0,"△这一笔之后该账户余额成负数了，核一下","")))))))))))
A18: 46252 | B18: 中国银行美元结算户-6688 | C18: =IF($B18="","",IFERROR(INDEX(账户银行,MATCH($B18,账户名,0)),"")) -> 中国银行 | D18: =IF($B18="","",IFERROR(INDEX(账户币种,MATCH($B18,账户名,0)),"")) -> USD | E18: 销售回款 | F18: =IF($E18="","",IFERROR(INDEX(类别属性,MATCH($E18,类别表,0)),"")) -> 收入 | G18: 15000 | J18: =IF(OR($A18="",$B18=""),"",IF($I18<>"",$I18,IF($D18=本位币,1,IFERROR(LOOKUP(2,1/((汇率月份<=$A18)*(INDEX(记账汇率区,0,MATCH($D18,汇率币种头,0))<>"")),INDEX(记账汇率区,0,MATCH($D18,汇率币种头,0))),"")))) -> 7.18 | K18: =IF(AND($G18="",$H18=""),"",ROUND(N($G18)-N($H18),2)) -> 15000 | L18: =IF(OR($K18="",$J18=""),"",ROUND($K18*$J18,2)) -> 107700 | M18: =IF($B18="","",ROUND(SUMIF(账户名,$B18,账户期初)+SUMIFS($K$6:K18,$B$6:B18,$B18),2)) -> 832000 | N18: =IF($B18="","",IFERROR(ROUND(INDEX(账户期初本位,MATCH($B18,账户名,0))+SUMIFS($L$6:L18,$B$6:B18,$B18),2),"")) -> 5949920 | O18: 第二笔美元回款 | P18: 出口业务 | Q18: Overseas Client C | S18: =IF($B18="","",IF(ISNA(MATCH($B18,账户名,0)),"※这个账户不在【参数设置】的账户档案里",IF($A18="","※没填日期，这一笔不会进任何月份的报表",IF(AND($G18<>"",$H18<>""),"※收入和支出不能同时填",IF(AND(N($G18)=0,N($H18)=0),"※收入和支出都没填",IF($E18="","※没填收支类别，分类报表会漏掉这一笔",IF(ISNA(MATCH($E18,类别表,0)),"※收支类别不在【参数设置】的清单里",IF($J18="","△"&$D18&" 还没填汇率，去【月度汇率】补上就自动算了",IF(YEAR($A18)<>管理年度,"△不是管理年度的单据，年报里看不到",IF(AND($F18="内部转账",$Q18=""),"△内部转账建议在「往来单位」写上对方账户",IF($M18<0,"△这一笔之后该账户余额成负数了，核一下","")))))))))))
A19: 46253 | B19: 汇丰银行港币结算户-5566 | C19: =IF($B19="","",IFERROR(INDEX(账户银行,MATCH($B19,账户名,0)),"")) -> 汇丰银行 | D19: =IF($B19="","",IFERROR(INDEX(账户币种,MATCH($B19,账户名,0)),"")) -> HKD | E19: 运营费用 | F19: =IF($E19="","",IFERROR(INDEX(类别属性,MATCH($E19,类别表,0)),"")) -> 支出 | H19: 20000 | J19: =IF(OR($A19="",$B19=""),"",IF($I19<>"",$I19,IF($D19=本位币,1,IFERROR(LOOKUP(2,1/((汇率月份<=$A19)*(INDEX(记账汇率区,0,MATCH($D19,汇率币种头,0))<>"")),INDEX(记账汇率区,0,MATCH($D19,汇率币种头,0))),"")))) -> 0.92 | K19: =IF(AND($G19="",$H19=""),"",ROUND(N($G19)-N($H19),2)) -> -20000 | L19: =IF(OR($K19="",$J19=""),"",ROUND($K19*$J19,2)) -> -18400 | M19: =IF($B19="","",ROUND(SUMIF(账户名,$B19,账户期初)+SUMIFS($K$6:K19,$B$6:B19,$B19),2)) -> 355500 | N19: =IF($B19="","",IFERROR(ROUND(INDEX(账户期初本位,MATCH($B19,账户名,0))+SUMIFS($L$6:L19,$B$6:B19,$B19),2),"")) -> 325560 | O19: 香港运营费 | P19: 行政 | Q19: 香港办公室 | S19: =IF($B19="","",IF(ISNA(MATCH($B19,账户名,0)),"※这个账户不在【参数设置】的账户档案里",IF($A19="","※没填日期，这一笔不会进任何月份的报表",IF(AND($G19<>"",$H19<>""),"※收入和支出不能同时填",IF(AND(N($G19)=0,N($H19)=0),"※收入和支出都没填",IF($E19="","※没填收支类别，分类报表会漏掉这一笔",IF(ISNA(MATCH($E19,类别表,0)),"※收支类别不在【参数设置】的清单里",IF($J19="","△"&$D19&" 还没填汇率，去【月度汇率】补上就自动算了",IF(YEAR($A19)<>管理年度,"△不是管理年度的单据，年报里看不到",IF(AND($F19="内部转账",$Q19=""),"△内部转账建议在「往来单位」写上对方账户",IF($M19<0,"△这一笔之后该账户余额成负数了，核一下","")))))))))))
A20: 46254 | B20: 中国银行欧元结算户-9900 | C20: =IF($B20="","",IFERROR(INDEX(账户银行,MATCH($B20,账户名,0)),"")) -> 中国银行 | D20: =IF($B20="","",IFERROR(INDEX(账户币种,MATCH($B20,账户名,0)),"")) -> EUR | E20: 销售回款 | F20: =IF($E20="","",IFERROR(INDEX(类别属性,MATCH($E20,类别表,0)),"")) -> 收入 | G20: 30000 | J20: =IF(OR($A20="",$B20=""),"",IF($I20<>"",$I20,IF($D20=本位币,1,IFERROR(LOOKUP(2,1/((汇率月份<=$A20)*(INDEX(记账汇率区,0,MATCH($D20,汇率币种头,0))<>"")),INDEX(记账汇率区,0,MATCH($D20,汇率币种头,0))),"")))) -> 7.69 | K20: =IF(AND($G20="",$H20=""),"",ROUND(N($G20)-N($H20),2)) -> 30000 | L20: =IF(OR($K20="",$J20=""),"",ROUND($K20*$J20,2)) -> 230700 | M20: =IF($B20="","",ROUND(SUMIF(账户名,$B20,账户期初)+SUMIFS($K$6:K20,$B$6:B20,$B20),2)) -> 150000 | N20: =IF($B20="","",IFERROR(ROUND(INDEX(账户期初本位,MATCH($B20,账户名,0))+SUMIFS($L$6:L20,$B$6:B20,$B20),2),"")) -> 1153500 | O20: 欧元货款（欧元汇率还没填，看核对列） | P20: 欧洲业务 | Q20: 欧洲客户D | S20: =IF($B20="","",IF(ISNA(MATCH($B20,账户名,0)),"※这个账户不在【参数设置】的账户档案里",IF($A20="","※没填日期，这一笔不会进任何月份的报表",IF(AND($G20<>"",$H20<>""),"※收入和支出不能同时填",IF(AND(N($G20)=0,N($H20)=0),"※收入和支出都没填",IF($E20="","※没填收支类别，分类报表会漏掉这一笔",IF(ISNA(MATCH($E20,类别表,0)),"※收支类别不在【参数设置】的清单里",IF($J20="","△"&$D20&" 还没填汇率，去【月度汇率】补上就自动算了",IF(YEAR($A20)<>管理年度,"△不是管理年度的单据，年报里看不到",IF(AND($F20="内部转账",$Q20=""),"△内部转账建议在「往来单位」写上对方账户",IF($M20<0,"△这一笔之后该账户余额成负数了，核一下","")))))))))))
A21: 46255 | B21: 工商银行基本户-8888 | C21: =IF($B21="","",IFERROR(INDEX(账户银行,MATCH($B21,账户名,0)),"")) -> 工商银行 | D21: =IF($B21="","",IFERROR(INDEX(账户币种,MATCH($B21,账户名,0)),"")) -> CNY | E21: 其他业务收入 | F21: =IF($E21="","",IFERROR(INDEX(类别属性,MATCH($E21,类别表,0)),"")) -> 收入 | G21: 35000 | J21: =IF(OR($A21="",$B21=""),"",IF($I21<>"",$I21,IF($D21=本位币,1,IFERROR(LOOKUP(2,1/((汇率月份<=$A21)*(INDEX(记账汇率区,0,MATCH($D21,汇率币种头,0))<>"")),INDEX(记账汇率区,0,MATCH($D21,汇率币种头,0))),"")))) -> 1 | K21: =IF(AND($G21="",$H21=""),"",ROUND(N($G21)-N($H21),2)) -> 35000 | L21: =IF(OR($K21="",$J21=""),"",ROUND($K21*$J21,2)) -> 35000 | M21: =IF($B21="","",ROUND(SUMIF(账户名,$B21,账户期初)+SUMIFS($K$6:K21,$B$6:B21,$B21),2)) -> 587000 | N21: =IF($B21="","",IFERROR(ROUND(INDEX(账户期初本位,MATCH($B21,账户名,0))+SUMIFS($L$6:L21,$B$6:B21,$B21),2),"")) -> 587000 | O21: 其他经营收入 | P21: 其他业务 | Q21: 其他客户 | S21: =IF($B21="","",IF(ISNA(MATCH($B21,账户名,0)),"※这个账户不在【参数设置】的账户档案里",IF($A21="","※没填日期，这一笔不会进任何月份的报表",IF(AND($G21<>"",$H21<>""),"※收入和支出不能同时填",IF(AND(N($G21)=0,N($H21)=0),"※收入和支出都没填",IF($E21="","※没填收支类别，分类报表会漏掉这一笔",IF(ISNA(MATCH($E21,类别表,0)),"※收支类别不在【参数设置】的清单里",IF($J21="","△"&$D21&" 还没填汇率，去【月度汇率】补上就自动算了",IF(YEAR($A21)<>管理年度,"△不是管理年度的单据，年报里看不到",IF(AND($F21="内部转账",$Q21=""),"△内部转账建议在「往来单位」写上对方账户",IF($M21<0,"△这一笔之后该账户余额成负数了，核一下","")))))))))))
A22: 46259 | B22: 中国银行美元结算户-6688 | C22: =IF($B22="","",IFERROR(INDEX(账户银行,MATCH($B22,账户名,0)),"")) -> 中国银行 | D22: =IF($B22="","",IFERROR(INDEX(账户币种,MATCH($B22,账户名,0)),"")) -> USD | E22: 购汇/结汇 | F22: =IF($E22="","",IFERROR(INDEX(类别属性,MATCH($E22,类别表,0)),"")) -> 内部转账 | H22: 20000 | I22: 7.17 | J22: =IF(OR($A22="",$B22=""),"",IF($I22<>"",$I22,IF($D22=本位币,1,IFERROR(LOOKUP(2,1/((汇率月份<=$A22)*(INDEX(记账汇率区,0,MATCH($D22,汇率币种头,0))<>"")),INDEX(记账汇率区,0,MATCH($D22,汇率币种头,0))),"")))) -> 7.17 | K22: =IF(AND($G22="",$H22=""),"",ROUND(N($G22)-N($H22),2)) -> -20000 | L22: =IF(OR($K22="",$J22=""),"",ROUND($K22*$J22,2)) -> -143400 | M22: {=IF($B22="","",ROUND(SUMIF(账户名,$B22,账户期初)+SUMIFS($K$6:K22,$B$6:B22,$B22),2))} -> 812000 | N22: =IF($B22="","",IFERROR(ROUND(INDEX(账户期初本位,MATCH($B22,账户名,0))+SUMIFS($L$6:L22,$B$6:B22,$B22),2),"")) -> 5806520 | O22: 结汇：美元转出 | P22: 内部调拨 | Q22: 工商银行基本户-8888 | S22: =IF($B22="","",IF(ISNA(MATCH($B22,账户名,0)),"※这个账户不在【参数设置】的账户档案里",IF($A22="","※没填日期，这一笔不会进任何月份的报表",IF(AND($G22<>"",$H22<>""),"※收入和支出不能同时填",IF(AND(N($G22)=0,N($H22)=0),"※收入和支出都没填",IF($E22="","※没填收支类别，分类报表会漏掉这一笔",IF(ISNA(MATCH($E22,类别表,0)),"※收支类别不在【参数设置】的清单里",IF($J22="","△"&$D22&" 还没填汇率，去【月度汇率】补上就自动算了",IF(YEAR($A22)<>管理年度,"△不是管理年度的单据，年报里看不到",IF(AND($F22="内部转账",$Q22=""),"△内部转账建议在「往来单位」写上对方账户",IF($M22<0,"△这一笔之后该账户余额成负数了，核一下","")))))))))))
A23: 46259 | B23: 工商银行基本户-8888 | C23: =IF($B23="","",IFERROR(INDEX(账户银行,MATCH($B23,账户名,0)),"")) -> 工商银行 | D23: =IF($B23="","",IFERROR(INDEX(账户币种,MATCH($B23,账户名,0)),"")) -> CNY | E23: 购汇/结汇 | F23: =IF($E23="","",IFERROR(INDEX(类别属性,MATCH($E23,类别表,0)),"")) -> 内部转账 | G23: 143400 | J23: =IF(OR($A23="",$B23=""),"",IF($I23<>"",$I23,IF($D23=本位币,1,IFERROR(LOOKUP(2,1/((汇率月份<=$A23)*(INDEX(记账汇率区,0,MATCH($D23,汇率币种头,0))<>"")),INDEX(记账汇率区,0,MATCH($D23,汇率币种头,0))),"")))) -> 1 | K23: =IF(AND($G23="",$H23=""),"",ROUND(N($G23)-N($H23),2)) -> 143400 | L23: =IF(OR($K23="",$J23=""),"",ROUND($K23*$J23,2)) -> 143400 | M23: =IF($B23="","",ROUND(SUMIF(账户名,$B23,账户期初)+SUMIFS($K$6:K23,$B$6:B23,$B23),2)) -> 730400 | N23: =IF($B23="","",IFERROR(ROUND(INDEX(账户期初本位,MATCH($B23,账户名,0))+SUMIFS($L$6:L23,$B$6:B23,$B23),2),"")) -> 730400 | O23: 结汇：人民币到账 | P23: 内部调拨 | Q23: 中国银行美元结算户-6688 | S23: =IF($B23="","",IF(ISNA(MATCH($B23,账户名,0)),"※这个账户不在【参数设置】的账户档案里",IF($A23="","※没填日期，这一笔不会进任何月份的报表",IF(AND($G23<>"",$H23<>""),"※收入和支出不能同时填",IF(AND(N($G23)=0,N($H23)=0),"※收入和支出都没填",IF($E23="","※没填收支类别，分类报表会漏掉这一笔",IF(ISNA(MATCH($E23,类别表,0)),"※收支类别不在【参数设置】的清单里",IF($J23="","△"&$D23&" 还没填汇率，去【月度汇率】补上就自动算了",IF(YEAR($A23)<>管理年度,"△不是管理年度的单据，年报里看不到",IF(AND($F23="内部转账",$Q23=""),"△内部转账建议在「往来单位」写上对方账户",IF($M23<0,"△这一笔之后该账户余额成负数了，核一下","")))))))))))
C24: =IF($B24="","",IFERROR(INDEX(账户银行,MATCH($B24,账户名,0)),"")) | D24: =IF($B24="","",IFERROR(INDEX(账户币种,MATCH($B24,账户名,0)),"")) | F24: =IF($E24="","",IFERROR(INDEX(类别属性,MATCH($E24,类别表,0)),"")) | J24: =IF(OR($A24="",$B24=""),"",IF($I24<>"",$I24,IF($D24=本位币,1,IFERROR(LOOKUP(2,1/((汇率月份<=$A24)*(INDEX(记账汇率区,0,MATCH($D24,汇率币种头,0))<>"")),INDEX(记账汇率区,0,MATCH($D24,汇率币种头,0))),"")))) | K24: =IF(AND($G24="",$H24=""),"",ROUND(N($G24)-N($H24),2)) | L24: =IF(OR($K24="",$J24=""),"",ROUND($K24*$J24,2)) | M24: =IF($B24="","",ROUND(SUMIF(账户名,$B24,账户期初)+SUMIFS($K$6:K24,$B$6:B24,$B24),2)) | N24: =IF($B24="","",IFERROR(ROUND(INDEX(账户期初本位,MATCH($B24,账户名,0))+SUMIFS($L$6:L24,$B$6:B24,$B24),2),"")) | S24: =IF($B24="","",IF(ISNA(MATCH($B24,账户名,0)),"※这个账户不在【参数设置】的账户档案里",IF($A24="","※没填日期，这一笔不会进任何月份的报表",IF(AND($G24<>"",$H24<>""),"※收入和支出不能同时填",IF(AND(N($G24)=0,N($H24)=0),"※收入和支出都没填",IF($E24="","※没填收支类别，分类报表会漏掉这一笔",IF(ISNA(MATCH($E24,类别表,0)),"※收支类别不在【参数设置】的清单里",IF($J24="","△"&$D24&" 还没填汇率，去【月度汇率】补上就自动算了",IF(YEAR($A24)<>管理年度,"△不是管理年度的单据，年报里看不到",IF(AND($F24="内部转账",$Q24=""),"△内部转账建议在「往来单位」写上对方账户",IF($M24<0,"△这一笔之后该账户余额成负数了，核一下","")))))))))))
C25: =IF($B25="","",IFERROR(INDEX(账户银行,MATCH($B25,账户名,0)),"")) | D25: =IF($B25="","",IFERROR(INDEX(账户币种,MATCH($B25,账户名,0)),"")) | F25: =IF($E25="","",IFERROR(INDEX(类别属性,MATCH($E25,类别表,0)),"")) | J25: =IF(OR($A25="",$B25=""),"",IF($I25<>"",$I25,IF($D25=本位币,1,IFERROR(LOOKUP(2,1/((汇率月份<=$A25)*(INDEX(记账汇率区,0,MATCH($D25,汇率币种头,0))<>"")),INDEX(记账汇率区,0,MATCH($D25,汇率币种头,0))),"")))) | K25: =IF(AND($G25="",$H25=""),"",ROUND(N($G25)-N($H25),2)) | L25: =IF(OR($K25="",$J25=""),"",ROUND($K25*$J25,2)) | M25: =IF($B25="","",ROUND(SUMIF(账户名,$B25,账户期初)+SUMIFS($K$6:K25,$B$6:B25,$B25),2)) | N25: =IF($B25="","",IFERROR(ROUND(INDEX(账户期初本位,MATCH($B25,账户名,0))+SUMIFS($L$6:L25,$B$6:B25,$B25),2),"")) | S25: =IF($B25="","",IF(ISNA(MATCH($B25,账户名,0)),"※这个账户不在【参数设置】的账户档案里",IF($A25="","※没填日期，这一笔不会进任何月份的报表",IF(AND($G25<>"",$H25<>""),"※收入和支出不能同时填",IF(AND(N($G25)=0,N($H25)=0),"※收入和支出都没填",IF($E25="","※没填收支类别，分类报表会漏掉这一笔",IF(ISNA(MATCH($E25,类别表,0)),"※收支类别不在【参数设置】的清单里",IF($J25="","△"&$D25&" 还没填汇率，去【月度汇率】补上就自动算了",IF(YEAR($A25)<>管理年度,"△不是管理年度的单据，年报里看不到",IF(AND($F25="内部转账",$Q25=""),"△内部转账建议在「往来单位」写上对方账户",IF($M25<0,"△这一笔之后该账户余额成负数了，核一下","")))))))))))
C26: =IF($B26="","",IFERROR(INDEX(账户银行,MATCH($B26,账户名,0)),"")) | D26: =IF($B26="","",IFERROR(INDEX(账户币种,MATCH($B26,账户名,0)),"")) | F26: =IF($E26="","",IFERROR(INDEX(类别属性,MATCH($E26,类别表,0)),"")) | J26: =IF(OR($A26="",$B26=""),"",IF($I26<>"",$I26,IF($D26=本位币,1,IFERROR(LOOKUP(2,1/((汇率月份<=$A26)*(INDEX(记账汇率区,0,MATCH($D26,汇率币种头,0))<>"")),INDEX(记账汇率区,0,MATCH($D26,汇率币种头,0))),"")))) | K26: =IF(AND($G26="",$H26=""),"",ROUND(N($G26)-N($H26),2)) | L26: =IF(OR($K26="",$J26=""),"",ROUND($K26*$J26,2)) | M26: =IF($B26="","",ROUND(SUMIF(账户名,$B26,账户期初)+SUMIFS($K$6:K26,$B$6:B26,$B26),2)) | N26: =IF($B26="","",IFERROR(ROUND(INDEX(账户期初本位,MATCH($B26,账户名,0))+SUMIFS($L$6:L26,$B$6:B26,$B26),2),"")) | S26: =IF($B26="","",IF(ISNA(MATCH($B26,账户名,0)),"※这个账户不在【参数设置】的账户档案里",IF($A26="","※没填日期，这一笔不会进任何月份的报表",IF(AND($G26<>"",$H26<>""),"※收入和支出不能同时填",IF(AND(N($G26)=0,N($H26)=0),"※收入和支出都没填",IF($E26="","※没填收支类别，分类报表会漏掉这一笔",IF(ISNA(MATCH($E26,类别表,0)),"※收支类别不在【参数设置】的清单里",IF($J26="","△"&$D26&" 还没填汇率，去【月度汇率】补上就自动算了",IF(YEAR($A26)<>管理年度,"△不是管理年度的单据，年报里看不到",IF(AND($F26="内部转账",$Q26=""),"△内部转账建议在「往来单位」写上对方账户",IF($M26<0,"△这一笔之后该账户余额成负数了，核一下","")))))))))))
C27: =IF($B27="","",IFERROR(INDEX(账户银行,MATCH($B27,账户名,0)),"")) | D27: =IF($B27="","",IFERROR(INDEX(账户币种,MATCH($B27,账户名,0)),"")) | F27: =IF($E27="","",IFERROR(INDEX(类别属性,MATCH($E27,类别表,0)),"")) | J27: =IF(OR($A27="",$B27=""),"",IF($I27<>"",$I27,IF($D27=本位币,1,IFERROR(LOOKUP(2,1/((汇率月份<=$A27)*(INDEX(记账汇率区,0,MATCH($D27,汇率币种头,0))<>"")),INDEX(记账汇率区,0,MATCH($D27,汇率币种头,0))),"")))) | K27: =IF(AND($G27="",$H27=""),"",ROUND(N($G27)-N($H27),2)) | L27: =IF(OR($K27="",$J27=""),"",ROUND($K27*$J27,2)) | M27: =IF($B27="","",ROUND(SUMIF(账户名,$B27,账户期初)+SUMIFS($K$6:K27,$B$6:B27,$B27),2)) | N27: =IF($B27="","",IFERROR(ROUND(INDEX(账户期初本位,MATCH($B27,账户名,0))+SUMIFS($L$6:L27,$B$6:B27,$B27),2),"")) | S27: =IF($B27="","",IF(ISNA(MATCH($B27,账户名,0)),"※这个账户不在【参数设置】的账户档案里",IF($A27="","※没填日期，这一笔不会进任何月份的报表",IF(AND($G27<>"",$H27<>""),"※收入和支出不能同时填",IF(AND(N($G27)=0,N($H27)=0),"※收入和支出都没填",IF($E27="","※没填收支类别，分类报表会漏掉这一笔",IF(ISNA(MATCH($E27,类别表,0)),"※收支类别不在【参数设置】的清单里",IF($J27="","△"&$D27&" 还没填汇率，去【月度汇率】补上就自动算了",IF(YEAR($A27)<>管理年度,"△不是管理年度的单据，年报里看不到",IF(AND($F27="内部转账",$Q27=""),"△内部转账建议在「往来单位」写上对方账户",IF($M27<0,"△这一笔之后该账户余额成负数了，核一下","")))))))))))
C28: =IF($B28="","",IFERROR(INDEX(账户银行,MATCH($B28,账户名,0)),"")) | D28: =IF($B28="","",IFERROR(INDEX(账户币种,MATCH($B28,账户名,0)),"")) | F28: =IF($E28="","",IFERROR(INDEX(类别属性,MATCH($E28,类别表,0)),"")) | J28: =IF(OR($A28="",$B28=""),"",IF($I28<>"",$I28,IF($D28=本位币,1,IFERROR(LOOKUP(2,1/((汇率月份<=$A28)*(INDEX(记账汇率区,0,MATCH($D28,汇率币种头,0))<>"")),INDEX(记账汇率区,0,MATCH($D28,汇率币种头,0))),"")))) | K28: =IF(AND($G28="",$H28=""),"",ROUND(N($G28)-N($H28),2)) | L28: =IF(OR($K28="",$J28=""),"",ROUND($K28*$J28,2)) | M28: =IF($B28="","",ROUND(SUMIF(账户名,$B28,账户期初)+SUMIFS($K$6:K28,$B$6:B28,$B28),2)) | N28: =IF($B28="","",IFERROR(ROUND(INDEX(账户期初本位,MATCH($B28,账户名,0))+SUMIFS($L$6:L28,$B$6:B28,$B28),2),"")) | S28: =IF($B28="","",IF(ISNA(MATCH($B28,账户名,0)),"※这个账户不在【参数设置】的账户档案里",IF($A28="","※没填日期，这一笔不会进任何月份的报表",IF(AND($G28<>"",$H28<>""),"※收入和支出不能同时填",IF(AND(N($G28)=0,N($H28)=0),"※收入和支出都没填",IF($E28="","※没填收支类别，分类报表会漏掉这一笔",IF(ISNA(MATCH($E28,类别表,0)),"※收支类别不在【参数设置】的清单里",IF($J28="","△"&$D28&" 还没填汇率，去【月度汇率】补上就自动算了",IF(YEAR($A28)<>管理年度,"△不是管理年度的单据，年报里看不到",IF(AND($F28="内部转账",$Q28=""),"△内部转账建议在「往来单位」写上对方账户",IF($M28<0,"△这一笔之后该账户余额成负数了，核一下","")))))))))))
C29: =IF($B29="","",IFERROR(INDEX(账户银行,MATCH($B29,账户名,0)),"")) | D29: =IF($B29="","",IFERROR(INDEX(账户币种,MATCH($B29,账户名,0)),"")) | F29: =IF($E29="","",IFERROR(INDEX(类别属性,MATCH($E29,类别表,0)),"")) | J29: =IF(OR($A29="",$B29=""),"",IF($I29<>"",$I29,IF($D29=本位币,1,IFERROR(LOOKUP(2,1/((汇率月份<=$A29)*(INDEX(记账汇率区,0,MATCH($D29,汇率币种头,0))<>"")),INDEX(记账汇率区,0,MATCH($D29,汇率币种头,0))),"")))) | K29: =IF(AND($G29="",$H29=""),"",ROUND(N($G29)-N($H29),2)) | L29: =IF(OR($K29="",$J29=""),"",ROUND($K29*$J29,2)) | M29: =IF($B29="","",ROUND(SUMIF(账户名,$B29,账户期初)+SUMIFS($K$6:K29,$B$6:B29,$B29),2)) | N29: =IF($B29="","",IFERROR(ROUND(INDEX(账户期初本位,MATCH($B29,账户名,0))+SUMIFS($L$6:L29,$B$6:B29,$B29),2),"")) | S29: =IF($B29="","",IF(ISNA(MATCH($B29,账户名,0)),"※这个账户不在【参数设置】的账户档案里",IF($A29="","※没填日期，这一笔不会进任何月份的报表",IF(AND($G29<>"",$H29<>""),"※收入和支出不能同时填",IF(AND(N($G29)=0,N($H29)=0),"※收入和支出都没填",IF($E29="","※没填收支类别，分类报表会漏掉这一笔",IF(ISNA(MATCH($E29,类别表,0)),"※收支类别不在【参数设置】的清单里",IF($J29="","△"&$D29&" 还没填汇率，去【月度汇率】补上就自动算了",IF(YEAR($A29)<>管理年度,"△不是管理年度的单据，年报里看不到",IF(AND($F29="内部转账",$Q29=""),"△内部转账建议在「往来单位」写上对方账户",IF($M29<0,"△这一笔之后该账户余额成负数了，核一下","")))))))))))
C30: =IF($B30="","",IFERROR(INDEX(账户银行,MATCH($B30,账户名,0)),"")) | D30: =IF($B30="","",IFERROR(INDEX(账户币种,MATCH($B30,账户名,0)),"")) | F30: =IF($E30="","",IFERROR(INDEX(类别属性,MATCH($E30,类别表,0)),"")) | J30: =IF(OR($A30="",$B30=""),"",IF($I30<>"",$I30,IF($D30=本位币,1,IFERROR(LOOKUP(2,1/((汇率月份<=$A30)*(INDEX(记账汇率区,0,MATCH($D30,汇率币种头,0))<>"")),INDEX(记账汇率区,0,MATCH($D30,汇率币种头,0))),"")))) | K30: =IF(AND($G30="",$H30=""),"",ROUND(N($G30)-N($H30),2)) | L30: =IF(OR($K30="",$J30=""),"",ROUND($K30*$J30,2)) | M30: =IF($B30="","",ROUND(SUMIF(账户名,$B30,账户期初)+SUMIFS($K$6:K30,$B$6:B30,$B30),2)) | N30: =IF($B30="","",IFERROR(ROUND(INDEX(账户期初本位,MATCH($B30,账户名,0))+SUMIFS($L$6:L30,$B$6:B30,$B30),2),"")) | S30: =IF($B30="","",IF(ISNA(MATCH($B30,账户名,0)),"※这个账户不在【参数设置】的账户档案里",IF($A30="","※没填日期，这一笔不会进任何月份的报表",IF(AND($G30<>"",$H30<>""),"※收入和支出不能同时填",IF(AND(N($G30)=0,N($H30)=0),"※收入和支出都没填",IF($E30="","※没填收支类别，分类报表会漏掉这一笔",IF(ISNA(MATCH($E30,类别表,0)),"※收支类别不在【参数设置】的清单里",IF($J30="","△"&$D30&" 还没填汇率，去【月度汇率】补上就自动算了",IF(YEAR($A30)<>管理年度,"△不是管理年度的单据，年报里看不到",IF(AND($F30="内部转账",$Q30=""),"△内部转账建议在「往来单位」写上对方账户",IF($M30<0,"△这一笔之后该账户余额成负数了，核一下","")))))))))))
C31: =IF($B31="","",IFERROR(INDEX(账户银行,MATCH($B31,账户名,0)),"")) | D31: =IF($B31="","",IFERROR(INDEX(账户币种,MATCH($B31,账户名,0)),"")) | F31: =IF($E31="","",IFERROR(INDEX(类别属性,MATCH($E31,类别表,0)),"")) | J31: =IF(OR($A31="",$B31=""),"",IF($I31<>"",$I31,IF($D31=本位币,1,IFERROR(LOOKUP(2,1/((汇率月份<=$A31)*(INDEX(记账汇率区,0,MATCH($D31,汇率币种头,0))<>"")),INDEX(记账汇率区,0,MATCH($D31,汇率币种头,0))),"")))) | K31: =IF(AND($G31="",$H31=""),"",ROUND(N($G31)-N($H31),2)) | L31: =IF(OR($K31="",$J31=""),"",ROUND($K31*$J31,2)) | M31: =IF($B31="","",ROUND(SUMIF(账户名,$B31,账户期初)+SUMIFS($K$6:K31,$B$6:B31,$B31),2)) | N31: =IF($B31="","",IFERROR(ROUND(INDEX(账户期初本位,MATCH($B31,账户名,0))+SUMIFS($L$6:L31,$B$6:B31,$B31),2),"")) | S31: =IF($B31="","",IF(ISNA(MATCH($B31,账户名,0)),"※这个账户不在【参数设置】的账户档案里",IF($A31="","※没填日期，这一笔不会进任何月份的报表",IF(AND($G31<>"",$H31<>""),"※收入和支出不能同时填",IF(AND(N($G31)=0,N($H31)=0),"※收入和支出都没填",IF($E31="","※没填收支类别，分类报表会漏掉这一笔",IF(ISNA(MATCH($E31,类别表,0)),"※收支类别不在【参数设置】的清单里",IF($J31="","△"&$D31&" 还没填汇率，去【月度汇率】补上就自动算了",IF(YEAR($A31)<>管理年度,"△不是管理年度的单据，年报里看不到",IF(AND($F31="内部转账",$Q31=""),"△内部转账建议在「往来单位」写上对方账户",IF($M31<0,"△这一笔之后该账户余额成负数了，核一下","")))))))))))
C32: =IF($B32="","",IFERROR(INDEX(账户银行,MATCH($B32,账户名,0)),"")) | D32: =IF($B32="","",IFERROR(INDEX(账户币种,MATCH($B32,账户名,0)),"")) | F32: =IF($E32="","",IFERROR(INDEX(类别属性,MATCH($E32,类别表,0)),"")) | J32: =IF(OR($A32="",$B32=""),"",IF($I32<>"",$I32,IF($D32=本位币,1,IFERROR(LOOKUP(2,1/((汇率月份<=$A32)*(INDEX(记账汇率区,0,MATCH($D32,汇率币种头,0))<>"")),INDEX(记账汇率区,0,MATCH($D32,汇率币种头,0))),"")))) | K32: =IF(AND($G32="",$H32=""),"",ROUND(N($G32)-N($H32),2)) | L32: =IF(OR($K32="",$J32=""),"",ROUND($K32*$J32,2)) | M32: =IF($B32="","",ROUND(SUMIF(账户名,$B32,账户期初)+SUMIFS($K$6:K32,$B$6:B32,$B32),2)) | N32: =IF($B32="","",IFERROR(ROUND(INDEX(账户期初本位,MATCH($B32,账户名,0))+SUMIFS($L$6:L32,$B$6:B32,$B32),2),"")) | S32: =IF($B32="","",IF(ISNA(MATCH($B32,账户名,0)),"※这个账户不在【参数设置】的账户档案里",IF($A32="","※没填日期，这一笔不会进任何月份的报表",IF(AND($G32<>"",$H32<>""),"※收入和支出不能同时填",IF(AND(N($G32)=0,N($H32)=0),"※收入和支出都没填",IF($E32="","※没填收支类别，分类报表会漏掉这一笔",IF(ISNA(MATCH($E32,类别表,0)),"※收支类别不在【参数设置】的清单里",IF($J32="","△"&$D32&" 还没填汇率，去【月度汇率】补上就自动算了",IF(YEAR($A32)<>管理年度,"△不是管理年度的单据，年报里看不到",IF(AND($F32="内部转账",$Q32=""),"△内部转账建议在「往来单位」写上对方账户",IF($M32<0,"△这一笔之后该账户余额成负数了，核一下","")))))))))))
C33: =IF($B33="","",IFERROR(INDEX(账户银行,MATCH($B33,账户名,0)),"")) | D33: =IF($B33="","",IFERROR(INDEX(账户币种,MATCH($B33,账户名,0)),"")) | F33: =IF($E33="","",IFERROR(INDEX(类别属性,MATCH($E33,类别表,0)),"")) | J33: =IF(OR($A33="",$B33=""),"",IF($I33<>"",$I33,IF($D33=本位币,1,IFERROR(LOOKUP(2,1/((汇率月份<=$A33)*(INDEX(记账汇率区,0,MATCH($D33,汇率币种头,0))<>"")),INDEX(记账汇率区,0,MATCH($D33,汇率币种头,0))),"")))) | K33: =IF(AND($G33="",$H33=""),"",ROUND(N($G33)-N($H33),2)) | L33: =IF(OR($K33="",$J33=""),"",ROUND($K33*$J33,2)) | M33: =IF($B33="","",ROUND(SUMIF(账户名,$B33,账户期初)+SUMIFS($K$6:K33,$B$6:B33,$B33),2)) | N33: =IF($B33="","",IFERROR(ROUND(INDEX(账户期初本位,MATCH($B33,账户名,0))+SUMIFS($L$6:L33,$B$6:B33,$B33),2),"")) | S33: =IF($B33="","",IF(ISNA(MATCH($B33,账户名,0)),"※这个账户不在【参数设置】的账户档案里",IF($A33="","※没填日期，这一笔不会进任何月份的报表",IF(AND($G33<>"",$H33<>""),"※收入和支出不能同时填",IF(AND(N($G33)=0,N($H33)=0),"※收入和支出都没填",IF($E33="","※没填收支类别，分类报表会漏掉这一笔",IF(ISNA(MATCH($E33,类别表,0)),"※收支类别不在【参数设置】的清单里",IF($J33="","△"&$D33&" 还没填汇率，去【月度汇率】补上就自动算了",IF(YEAR($A33)<>管理年度,"△不是管理年度的单据，年报里看不到",IF(AND($F33="内部转账",$Q33=""),"△内部转账建议在「往来单位」写上对方账户",IF($M33<0,"△这一笔之后该账户余额成负数了，核一下","")))))))))))
C34: =IF($B34="","",IFERROR(INDEX(账户银行,MATCH($B34,账户名,0)),"")) | D34: =IF($B34="","",IFERROR(INDEX(账户币种,MATCH($B34,账户名,0)),"")) | F34: =IF($E34="","",IFERROR(INDEX(类别属性,MATCH($E34,类别表,0)),"")) | J34: =IF(OR($A34="",$B34=""),"",IF($I34<>"",$I34,IF($D34=本位币,1,IFERROR(LOOKUP(2,1/((汇率月份<=$A34)*(INDEX(记账汇率区,0,MATCH($D34,汇率币种头,0))<>"")),INDEX(记账汇率区,0,MATCH($D34,汇率币种头,0))),"")))) | K34: =IF(AND($G34="",$H34=""),"",ROUND(N($G34)-N($H34),2)) | L34: =IF(OR($K34="",$J34=""),"",ROUND($K34*$J34,2)) | M34: =IF($B34="","",ROUND(SUMIF(账户名,$B34,账户期初)+SUMIFS($K$6:K34,$B$6:B34,$B34),2)) | N34: =IF($B34="","",IFERROR(ROUND(INDEX(账户期初本位,MATCH($B34,账户名,0))+SUMIFS($L$6:L34,$B$6:B34,$B34),2),"")) | S34: =IF($B34="","",IF(ISNA(MATCH($B34,账户名,0)),"※这个账户不在【参数设置】的账户档案里",IF($A34="","※没填日期，这一笔不会进任何月份的报表",IF(AND($G34<>"",$H34<>""),"※收入和支出不能同时填",IF(AND(N($G34)=0,N($H34)=0),"※收入和支出都没填",IF($E34="","※没填收支类别，分类报表会漏掉这一笔",IF(ISNA(MATCH($E34,类别表,0)),"※收支类别不在【参数设置】的清单里",IF($J34="","△"&$D34&" 还没填汇率，去【月度汇率】补上就自动算了",IF(YEAR($A34)<>管理年度,"△不是管理年度的单据，年报里看不到",IF(AND($F34="内部转账",$Q34=""),"△内部转账建议在「往来单位」写上对方账户",IF($M34<0,"△这一笔之后该账户余额成负数了，核一下","")))))))))))
C35: =IF($B35="","",IFERROR(INDEX(账户银行,MATCH($B35,账户名,0)),"")) | D35: =IF($B35="","",IFERROR(INDEX(账户币种,MATCH($B35,账户名,0)),"")) | F35: =IF($E35="","",IFERROR(INDEX(类别属性,MATCH($E35,类别表,0)),"")) | J35: =IF(OR($A35="",$B35=""),"",IF($I35<>"",$I35,IF($D35=本位币,1,IFERROR(LOOKUP(2,1/((汇率月份<=$A35)*(INDEX(记账汇率区,0,MATCH($D35,汇率币种头,0))<>"")),INDEX(记账汇率区,0,MATCH($D35,汇率币种头,0))),"")))) | K35: =IF(AND($G35="",$H35=""),"",ROUND(N($G35)-N($H35),2)) | L35: =IF(OR($K35="",$J35=""),"",ROUND($K35*$J35,2)) | M35: =IF($B35="","",ROUND(SUMIF(账户名,$B35,账户期初)+SUMIFS($K$6:K35,$B$6:B35,$B35),2)) | N35: =IF($B35="","",IFERROR(ROUND(INDEX(账户期初本位,MATCH($B35,账户名,0))+SUMIFS($L$6:L35,$B$6:B35,$B35),2),"")) | S35: =IF($B35="","",IF(ISNA(MATCH($B35,账户名,0)),"※这个账户不在【参数设置】的账户档案里",IF($A35="","※没填日期，这一笔不会进任何月份的报表",IF(AND($G35<>"",$H35<>""),"※收入和支出不能同时填",IF(AND(N($G35)=0,N($H35)=0),"※收入和支出都没填",IF($E35="","※没填收支类别，分类报表会漏掉这一笔",IF(ISNA(MATCH($E35,类别表,0)),"※收支类别不在【参数设置】的清单里",IF($J35="","△"&$D35&" 还没填汇率，去【月度汇率】补上就自动算了",IF(YEAR($A35)<>管理年度,"△不是管理年度的单据，年报里看不到",IF(AND($F35="内部转账",$Q35=""),"△内部转账建议在「往来单位」写上对方账户",IF($M35<0,"△这一笔之后该账户余额成负数了，核一下","")))))))))))
... C2005: =IF($B2005="","",IFERROR(INDEX(账户银行,MATCH($B2005,账户名,0)),"")) | D2005: =IF($B2005="","",IFERROR(INDEX(账户币种,MATCH($B2005,账户名,0)),"")) | F2005: =IF($E2005="","",IFERROR(INDEX(类别属性,MATCH($E2005,类别表,0)),"")) | J2005: =IF(OR($A2005="",$B2005=""),"",IF($I2005<>"",$I2005,IF($D2005=本位币,1,IFERROR(LOOKUP(2,1/((汇率月份<=$A2005)*(INDEX(记账汇率区,0,MATCH($D2005,汇率币种头,0))<>"")),INDEX(记账汇率区,0,MATCH($D2005,汇率币种头,0))),"")))) | K2005: =IF(AND($G2005="",$H2005=""),"",ROUND(N($G2005)-N($H2005),2)) | L2005: =IF(OR($K2005="",$J2005=""),"",ROUND($K2005*$J2005,2)) | M2005: =IF($B2005="","",ROUND(SUMIF(账户名,$B2005,账户期初)+SUMIFS($K$6:K2005,$B$6:B2005,$B2005),2)) | N2005: =IF($B2005="","",IFERROR(ROUND(INDEX(账户期初本位,MATCH($B2005,账户名,0))+SUMIFS($L$6:L2005,$B$6:B2005,$B2005),2),"")) | S2005: =IF($B2005="","",IF(ISNA(MATCH($B2005,账户名,0)),"※这个账户不在【参数设置】的账户档案里",IF($A2005="","※没填日期，这一笔不会进任何月份的报表",IF(AND($G2005<>"",$H2005<>""),"※收入和支出不能同时填",IF(AND(N($G2005)=0,N($H2005)=0),"※收入和支出都没填",IF($E2005="","※没填收支类别，分类报表会漏掉这一笔",IF(ISNA(MATCH($E2005,类别表,0)),"※收支类别不在【参数设置】的清单里",IF($J2005="","△"&$D2005&" 还没填汇率，去【月度汇率】补上就自动算了",IF(YEAR($A2005)<>管理年度,"△不是管理年度的单据，年报里看不到",IF(AND($F2005="内部转账",$Q2005=""),"△内部转账建议在「往来单位」写上对方账户",IF($M2005<0,"△这一笔之后该账户余额成负数了，核一下","")))))))))))

Sheet 账户余额表
A1: 账户余额表 · 每个账户一行，原币和人民币各算各的
A2: 「账面人民币成本」= 期初成本 + 每笔按当时汇率折的人民币；「期末人民币(重估)」= 期末原币 × 期末汇率。两者之差就是汇兑损益 —— 这是外汇台账跟普通资金台账唯一的区别，别把两个口径混着加。
A5: 序号 | B5: 银行 | C5: 账户名称 | D5: 币种 | E5: 期初余额(原币) | F5: 累计收入(原币) | G5: 累计支出(原币) | H5: 期末余额(原币) | I5: 期末汇率 | J5: 期末人民币(重估) | K5: 账面人民币成本 | L5: 汇兑损益 | M5: 核对
A6: =IF($C6="","",1) -> 1 | B6: =IF($C6="","",参数设置!$B$11) -> 工商银行 | C6: =IF(参数设置!$C$11="","",参数设置!$C$11) -> 工商银行基本户-8888 | D6: =IF($C6="","",参数设置!$E$11) -> CNY | E6: =IF($C6="","",ROUND(N(参数设置!$G$11),2)) -> 500000 | F6: =IF($C6="","",ROUND(SUMIF(流水账户,$C6,流水收入),2)) -> 298400 | G6: =IF($C6="","",ROUND(SUMIF(流水账户,$C6,流水支出),2)) -> 68000 | H6: =IF($C6="","",ROUND($E6+$F6-$G6,2)) -> 730400 | I6: =IF($C6="","",IFERROR(IF($D6=本位币,1,IFERROR(LOOKUP(2,1/((汇率月份<=重估基准日)*(INDEX(月末汇率区,0,MATCH($D6,汇率币种头,0))<>"")),INDEX(月末汇率区,0,MATCH($D6,汇率币种头,0))),IFERROR(LOOKUP(2,1/((汇率月份<=重估基准日)*(INDEX(记账汇率区,0,MATCH($D6,汇率币种头,0))<>"")),INDEX(记账汇率区,0,MATCH($D6,汇率币种头,0))),""))),"")) -> 1 | J6: =IF(OR($C6="",$I6=""),"",ROUND($H6*$I6,2)) -> 730400 | K6: =IF($C6="","",IFERROR(ROUND(参数设置!$I$11+SUMIF(流水账户,$C6,流水本位),2),"")) -> 730400 | L6: =IF(OR($C6="",$J6=""),"",ROUND($J6-$K6,2)) -> 0 | M6: =IF($C6="","",IF($H6<0,"※期末余额是负数，查一下是不是漏记了收入",IF($I6="","△"&$D6&" 还没填汇率，人民币这几列算不出来",IF(AND($D6<>本位币,ABS($L6)>ABS($K6)*0.2),"△汇兑损益超过账面成本 20%，核一下汇率",""))))
A7: =IF($C7="","",2) -> 2 | B7: =IF($C7="","",参数设置!$B$12) -> 中国银行 | C7: =IF(参数设置!$C$12="","",参数设置!$C$12) -> 中国银行美元结算户-6688 | D7: =IF($C7="","",参数设置!$E$12) -> USD | E7: =IF($C7="","",ROUND(N(参数设置!$G$12),2)) -> 800000 | F7: =IF($C7="","",ROUND(SUMIF(流水账户,$C7,流水收入),2)) -> 40000 | G7: =IF($C7="","",ROUND(SUMIF(流水账户,$C7,流水支出),2)) -> 28000 | H7: =IF($C7="","",ROUND($E7+$F7-$G7,2)) -> 812000 | I7: =IF($C7="","",IFERROR(IF($D7=本位币,1,IFERROR(LOOKUP(2,1/((汇率月份<=重估基准日)*(INDEX(月末汇率区,0,MATCH($D7,汇率币种头,0))<>"")),INDEX(月末汇率区,0,MATCH($D7,汇率币种头,0))),IFERROR(LOOKUP(2,1/((汇率月份<=重估基准日)*(INDEX(记账汇率区,0,MATCH($D7,汇率币种头,0))<>"")),INDEX(记账汇率区,0,MATCH($D7,汇率币种头,0))),""))),"")) -> 7.18 | J7: =IF(OR($C7="",$I7=""),"",ROUND($H7*$I7,2)) -> 5830160 | K7: =IF($C7="","",IFERROR(ROUND(参数设置!$I$12+SUMIF(流水账户,$C7,流水本位),2),"")) -> 5806520 | L7: =IF(OR($C7="",$J7=""),"",ROUND($J7-$K7,2)) -> 23640 | M7: =IF($C7="","",IF($H7<0,"※期末余额是负数，查一下是不是漏记了收入",IF($I7="","△"&$D7&" 还没填汇率，人民币这几列算不出来",IF(AND($D7<>本位币,ABS($L7)>ABS($K7)*0.2),"△汇兑损益超过账面成本 20%，核一下汇率",""))))
A8: =IF($C8="","",3) -> 3 | B8: =IF($C8="","",参数设置!$B$13) -> 汇丰银行 | C8: =IF(参数设置!$C$13="","",参数设置!$C$13) -> 汇丰银行港币结算户-5566 | D8: =IF($C8="","",参数设置!$E$13) -> HKD | E8: =IF($C8="","",ROUND(N(参数设置!$G$13),2)) -> 300000 | F8: =IF($C8="","",ROUND(SUMIF(流水账户,$C8,流水收入),2)) -> 80000 | G8: =IF($C8="","",ROUND(SUMIF(流水账户,$C8,流水支出),2)) -> 24500 | H8: =IF($C8="","",ROUND($E8+$F8-$G8,2)) -> 355500 | I8: =IF($C8="","",IFERROR(IF($D8=本位币,1,IFERROR(LOOKUP(2,1/((汇率月份<=重估基准日)*(INDEX(月末汇率区,0,MATCH($D8,汇率币种头,0))<>"")),INDEX(月末汇率区,0,MATCH($D8,汇率币种头,0))),IFERROR(LOOKUP(2,1/((汇率月份<=重估基准日)*(INDEX(记账汇率区,0,MATCH($D8,汇率币种头,0))<>"")),INDEX(记账汇率区,0,MATCH($D8,汇率币种头,0))),""))),"")) -> 0.92 | J8: =IF(OR($C8="",$I8=""),"",ROUND($H8*$I8,2)) -> 327060 | K8: =IF($C8="","",IFERROR(ROUND(参数设置!$I$13+SUMIF(流水账户,$C8,流水本位),2),"")) -> 325560 | L8: =IF(OR($C8="",$J8=""),"",ROUND($J8-$K8,2)) -> 1500 | M8: =IF($C8="","",IF($H8<0,"※期末余额是负数，查一下是不是漏记了收入",IF($I8="","△"&$D8&" 还没填汇率，人民币这几列算不出来",IF(AND($D8<>本位币,ABS($L8)>ABS($K8)*0.2),"△汇兑损益超过账面成本 20%，核一下汇率",""))))
A9: =IF($C9="","",4) -> 4 | B9: =IF($C9="","",参数设置!$B$14) -> 招商银行 | C9: =IF(参数设置!$C$14="","",参数设置!$C$14) -> 招商银行一般户-2388 | D9: =IF($C9="","",参数设置!$E$14) -> CNY | E9: =IF($C9="","",ROUND(N(参数设置!$G$14),2)) -> 200000 | F9: =IF($C9="","",ROUND(SUMIF(流水账户,$C9,流水收入),2)) -> 110000 | G9: =IF($C9="","",ROUND(SUMIF(流水账户,$C9,流水支出),2)) -> 30000 | H9: =IF($C9="","",ROUND($E9+$F9-$G9,2)) -> 280000 | I9: =IF($C9="","",IFERROR(IF($D9=本位币,1,IFERROR(LOOKUP(2,1/((汇率月份<=重估基准日)*(INDEX(月末汇率区,0,MATCH($D9,汇率币种头,0))<>"")),INDEX(月末汇率区,0,MATCH($D9,汇率币种头,0))),IFERROR(LOOKUP(2,1/((汇率月份<=重估基准日)*(INDEX(记账汇率区,0,MATCH($D9,汇率币种头,0))<>"")),INDEX(记账汇率区,0,MATCH($D9,汇率币种头,0))),""))),"")) -> 1 | J9: =IF(OR($C9="",$I9=""),"",ROUND($H9*$I9,2)) -> 280000 | K9: =IF($C9="","",IFERROR(ROUND(参数设置!$I$14+SUMIF(流水账户,$C9,流水本位),2),"")) -> 280000 | L9: =IF(OR($C9="",$J9=""),"",ROUND($J9-$K9,2)) -> 0 | M9: =IF($C9="","",IF($H9<0,"※期末余额是负数，查一下是不是漏记了收入",IF($I9="","△"&$D9&" 还没填汇率，人民币这几列算不出来",IF(AND($D9<>本位币,ABS($L9)>ABS($K9)*0.2),"△汇兑损益超过账面成本 20%，核一下汇率",""))))
A10: =IF($C10="","",5) -> 5 | B10: =IF($C10="","",参数设置!$B$15) -> 汇丰银行 | C10: =IF(参数设置!$C$15="","",参数设置!$C$15) -> 汇丰银行美元结算户-7788 | D10: =IF($C10="","",参数设置!$E$15) -> USD | E10: =IF($C10="","",ROUND(N(参数设置!$G$15),2)) -> 500000 | F10: =IF($C10="","",ROUND(SUMIF(流水账户,$C10,流水收入),2)) -> 12000 | G10: =IF($C10="","",ROUND(SUMIF(流水账户,$C10,流水支出),2)) -> 5000 | H10: =IF($C10="","",ROUND($E10+$F10-$G10,2)) -> 507000 | I10: =IF($C10="","",IFERROR(IF($D10=本位币,1,IFERROR(LOOKUP(2,1/((汇率月份<=重估基准日)*(INDEX(月末汇率区,0,MATCH($D10,汇率币种头,0))<>"")),INDEX(月末汇率区,0,MATCH($D10,汇率币种头,0))),IFERROR(LOOKUP(2,1/((汇率月份<=重估基准日)*(INDEX(记账汇率区,0,MATCH($D10,汇率币种头,0))<>"")),INDEX(记账汇率区,0,MATCH($D10,汇率币种头,0))),""))),"")) -> 7.18 | J10: =IF(OR($C10="",$I10=""),"",ROUND($H10*$I10,2)) -> 3640260 | K10: =IF($C10="","",IFERROR(ROUND(参数设置!$I$15+SUMIF(流水账户,$C10,流水本位),2),"")) -> 3625260 | L10: =IF(OR($C10="",$J10=""),"",ROUND($J10-$K10,2)) -> 15000 | M10: =IF($C10="","",IF($H10<0,"※期末余额是负数，查一下是不是漏记了收入",IF($I10="","△"&$D10&" 还没填汇率，人民币这几列算不出来",IF(AND($D10<>本位币,ABS($L10)>ABS($K10)*0.2),"△汇兑损益超过账面成本 20%，核一下汇率",""))))
A11: =IF($C11="","",6) -> 6 | B11: =IF($C11="","",参数设置!$B$16) -> 中国银行 | C11: =IF(参数设置!$C$16="","",参数设置!$C$16) -> 中国银行欧元结算户-9900 | D11: =IF($C11="","",参数设置!$E$16) -> EUR | E11: =IF($C11="","",ROUND(N(参数设置!$G$16),2)) -> 120000 | F11: =IF($C11="","",ROUND(SUMIF(流水账户,$C11,流水收入),2)) -> 30000 | G11: =IF($C11="","",ROUND(SUMIF(流水账户,$C11,流水支出),2)) -> 0 | H11: =IF($C11="","",ROUND($E11+$F11-$G11,2)) -> 150000 | I11: =IF($C11="","",IFERROR(IF($D11=本位币,1,IFERROR(LOOKUP(2,1/((汇率月份<=重估基准日)*(INDEX(月末汇率区,0,MATCH($D11,汇率币种头,0))<>"")),INDEX(月末汇率区,0,MATCH($D11,汇率币种头,0))),IFERROR(LOOKUP(2,1/((汇率月份<=重估基准日)*(INDEX(记账汇率区,0,MATCH($D11,汇率币种头,0))<>"")),INDEX(记账汇率区,0,MATCH($D11,汇率币种头,0))),""))),"")) -> 7.69 | J11: =IF(OR($C11="",$I11=""),"",ROUND($H11*$I11,2)) -> 1153500 | K11: =IF($C11="","",IFERROR(ROUND(参数设置!$I$16+SUMIF(流水账户,$C11,流水本位),2),"")) -> 1153500 | L11: =IF(OR($C11="",$J11=""),"",ROUND($J11-$K11,2)) -> 0 | M11: =IF($C11="","",IF($H11<0,"※期末余额是负数，查一下是不是漏记了收入",IF($I11="","△"&$D11&" 还没填汇率，人民币这几列算不出来",IF(AND($D11<>本位币,ABS($L11)>ABS($K11)*0.2),"△汇兑损益超过账面成本 20%，核一下汇率",""))))
A12: =IF($C12="","",7) | B12: =IF($C12="","",参数设置!$B$17) | C12: =IF(参数设置!$C$17="","",参数设置!$C$17) | D12: =IF($C12="","",参数设置!$E$17) | E12: =IF($C12="","",ROUND(N(参数设置!$G$17),2)) | F12: =IF($C12="","",ROUND(SUMIF(流水账户,$C12,流水收入),2)) | G12: =IF($C12="","",ROUND(SUMIF(流水账户,$C12,流水支出),2)) | H12: =IF($C12="","",ROUND($E12+$F12-$G12,2)) | I12: =IF($C12="","",IFERROR(IF($D12=本位币,1,IFERROR(LOOKUP(2,1/((汇率月份<=重估基准日)*(INDEX(月末汇率区,0,MATCH($D12,汇率币种头,0))<>"")),INDEX(月末汇率区,0,MATCH($D12,汇率币种头,0))),IFERROR(LOOKUP(2,1/((汇率月份<=重估基准日)*(INDEX(记账汇率区,0,MATCH($D12,汇率币种头,0))<>"")),INDEX(记账汇率区,0,MATCH($D12,汇率币种头,0))),""))),"")) | J12: =IF(OR($C12="",$I12=""),"",ROUND($H12*$I12,2)) | K12: =IF($C12="","",IFERROR(ROUND(参数设置!$I$17+SUMIF(流水账户,$C12,流水本位),2),"")) | L12: =IF(OR($C12="",$J12=""),"",ROUND($J12-$K12,2)) | M12: =IF($C12="","",IF($H12<0,"※期末余额是负数，查一下是不是漏记了收入",IF($I12="","△"&$D12&" 还没填汇率，人民币这几列算不出来",IF(AND($D12<>本位币,ABS($L12)>ABS($K12)*0.2),"△汇兑损益超过账面成本 20%，核一下汇率",""))))
A13: =IF($C13="","",8) | B13: =IF($C13="","",参数设置!$B$18) | C13: =IF(参数设置!$C$18="","",参数设置!$C$18) | D13: =IF($C13="","",参数设置!$E$18) | E13: =IF($C13="","",ROUND(N(参数设置!$G$18),2)) | F13: =IF($C13="","",ROUND(SUMIF(流水账户,$C13,流水收入),2)) | G13: =IF($C13="","",ROUND(SUMIF(流水账户,$C13,流水支出),2)) | H13: =IF($C13="","",ROUND($E13+$F13-$G13,2)) | I13: =IF($C13="","",IFERROR(IF($D13=本位币,1,IFERROR(LOOKUP(2,1/((汇率月份<=重估基准日)*(INDEX(月末汇率区,0,MATCH($D13,汇率币种头,0))<>"")),INDEX(月末汇率区,0,MATCH($D13,汇率币种头,0))),IFERROR(LOOKUP(2,1/((汇率月份<=重估基准日)*(INDEX(记账汇率区,0,MATCH($D13,汇率币种头,0))<>"")),INDEX(记账汇率区,0,MATCH($D13,汇率币种头,0))),""))),"")) | J13: =IF(OR($C13="",$I13=""),"",ROUND($H13*$I13,2)) | K13: =IF($C13="","",IFERROR(ROUND(参数设置!$I$18+SUMIF(流水账户,$C13,流水本位),2),"")) | L13: =IF(OR($C13="",$J13=""),"",ROUND($J13-$K13,2)) | M13: =IF($C13="","",IF($H13<0,"※期末余额是负数，查一下是不是漏记了收入",IF($I13="","△"&$D13&" 还没填汇率，人民币这几列算不出来",IF(AND($D13<>本位币,ABS($L13)>ABS($K13)*0.2),"△汇兑损益超过账面成本 20%，核一下汇率",""))))
A14: =IF($C14="","",9) | B14: =IF($C14="","",参数设置!$B$19) | C14: =IF(参数设置!$C$19="","",参数设置!$C$19) | D14: =IF($C14="","",参数设置!$E$19) | E14: =IF($C14="","",ROUND(N(参数设置!$G$19),2)) | F14: =IF($C14="","",ROUND(SUMIF(流水账户,$C14,流水收入),2)) | G14: =IF($C14="","",ROUND(SUMIF(流水账户,$C14,流水支出),2)) | H14: =IF($C14="","",ROUND($E14+$F14-$G14,2)) | I14: =IF($C14="","",IFERROR(IF($D14=本位币,1,IFERROR(LOOKUP(2,1/((汇率月份<=重估基准日)*(INDEX(月末汇率区,0,MATCH($D14,汇率币种头,0))<>"")),INDEX(月末汇率区,0,MATCH($D14,汇率币种头,0))),IFERROR(LOOKUP(2,1/((汇率月份<=重估基准日)*(INDEX(记账汇率区,0,MATCH($D14,汇率币种头,0))<>"")),INDEX(记账汇率区,0,MATCH($D14,汇率币种头,0))),""))),"")) | J14: =IF(OR($C14="",$I14=""),"",ROUND($H14*$I14,2)) | K14: =IF($C14="","",IFERROR(ROUND(参数设置!$I$19+SUMIF(流水账户,$C14,流水本位),2),"")) | L14: =IF(OR($C14="",$J14=""),"",ROUND($J14-$K14,2)) | M14: =IF($C14="","",IF($H14<0,"※期末余额是负数，查一下是不是漏记了收入",IF($I14="","△"&$D14&" 还没填汇率，人民币这几列算不出来",IF(AND($D14<>本位币,ABS($L14)>ABS($K14)*0.2),"△汇兑损益超过账面成本 20%，核一下汇率",""))))
A15: =IF($C15="","",10) | B15: =IF($C15="","",参数设置!$B$20) | C15: =IF(参数设置!$C$20="","",参数设置!$C$20) | D15: =IF($C15="","",参数设置!$E$20) | E15: =IF($C15="","",ROUND(N(参数设置!$G$20),2)) | F15: =IF($C15="","",ROUND(SUMIF(流水账户,$C15,流水收入),2)) | G15: =IF($C15="","",ROUND(SUMIF(流水账户,$C15,流水支出),2)) | H15: =IF($C15="","",ROUND($E15+$F15-$G15,2)) | I15: =IF($C15="","",IFERROR(IF($D15=本位币,1,IFERROR(LOOKUP(2,1/((汇率月份<=重估基准日)*(INDEX(月末汇率区,0,MATCH($D15,汇率币种头,0))<>"")),INDEX(月末汇率区,0,MATCH($D15,汇率币种头,0))),IFERROR(LOOKUP(2,1/((汇率月份<=重估基准日)*(INDEX(记账汇率区,0,MATCH($D15,汇率币种头,0))<>"")),INDEX(记账汇率区,0,MATCH($D15,汇率币种头,0))),""))),"")) | J15: =IF(OR($C15="",$I15=""),"",ROUND($H15*$I15,2)) | K15: =IF($C15="","",IFERROR(ROUND(参数设置!$I$20+SUMIF(流水账户,$C15,流水本位),2),"")) | L15: =IF(OR($C15="",$J15=""),"",ROUND($J15-$K15,2)) | M15: =IF($C15="","",IF($H15<0,"※期末余额是负数，查一下是不是漏记了收入",IF($I15="","△"&$D15&" 还没填汇率，人民币这几列算不出来",IF(AND($D15<>本位币,ABS($L15)>ABS($K15)*0.2),"△汇兑损益超过账面成本 20%，核一下汇率",""))))
A16: =IF($C16="","",11) | B16: =IF($C16="","",参数设置!$B$21) | C16: =IF(参数设置!$C$21="","",参数设置!$C$21) | D16: =IF($C16="","",参数设置!$E$21) | E16: =IF($C16="","",ROUND(N(参数设置!$G$21),2)) | F16: =IF($C16="","",ROUND(SUMIF(流水账户,$C16,流水收入),2)) | G16: =IF($C16="","",ROUND(SUMIF(流水账户,$C16,流水支出),2)) | H16: =IF($C16="","",ROUND($E16+$F16-$G16,2)) | I16: =IF($C16="","",IFERROR(IF($D16=本位币,1,IFERROR(LOOKUP(2,1/((汇率月份<=重估基准日)*(INDEX(月末汇率区,0,MATCH($D16,汇率币种头,0))<>"")),INDEX(月末汇率区,0,MATCH($D16,汇率币种头,0))),IFERROR(LOOKUP(2,1/((汇率月份<=重估基准日)*(INDEX(记账汇率区,0,MATCH($D16,汇率币种头,0))<>"")),INDEX(记账汇率区,0,MATCH($D16,汇率币种头,0))),""))),"")) | J16: =IF(OR($C16="",$I16=""),"",ROUND($H16*$I16,2)) | K16: =IF($C16="","",IFERROR(ROUND(参数设置!$I$21+SUMIF(流水账户,$C16,流水本位),2),"")) | L16: =IF(OR($C16="",$J16=""),"",ROUND($J16-$K16,2)) | M16: =IF($C16="","",IF($H16<0,"※期末余额是负数，查一下是不是漏记了收入",IF($I16="","△"&$D16&" 还没填汇率，人民币这几列算不出来",IF(AND($D16<>本位币,ABS($L16)>ABS($K16)*0.2),"△汇兑损益超过账面成本 20%，核一下汇率",""))))
A17: =IF($C17="","",12) | B17: =IF($C17="","",参数设置!$B$22) | C17: =IF(参数设置!$C$22="","",参数设置!$C$22) | D17: =IF($C17="","",参数设置!$E$22) | E17: =IF($C17="","",ROUND(N(参数设置!$G$22),2)) | F17: =IF($C17="","",ROUND(SUMIF(流水账户,$C17,流水收入),2)) | G17: =IF($C17="","",ROUND(SUMIF(流水账户,$C17,流水支出),2)) | H17: =IF($C17="","",ROUND($E17+$F17-$G17,2)) | I17: =IF($C17="","",IFERROR(IF($D17=本位币,1,IFERROR(LOOKUP(2,1/((汇率月份<=重估基准日)*(INDEX(月末汇率区,0,MATCH($D17,汇率币种头,0))<>"")),INDEX(月末汇率区,0,MATCH($D17,汇率币种头,0))),IFERROR(LOOKUP(2,1/((汇率月份<=重估基准日)*(INDEX(记账汇率区,0,MATCH($D17,汇率币种头,0))<>"")),INDEX(记账汇率区,0,MATCH($D17,汇率币种头,0))),""))),"")) | J17: =IF(OR($C17="",$I17=""),"",ROUND($H17*$I17,2)) | K17: =IF($C17="","",IFERROR(ROUND(参数设置!$I$22+SUMIF(流水账户,$C17,流水本位),2),"")) | L17: =IF(OR($C17="",$J17=""),"",ROUND($J17-$K17,2)) | M17: =IF($C17="","",IF($H17<0,"※期末余额是负数，查一下是不是漏记了收入",IF($I17="","△"&$D17&" 还没填汇率，人民币这几列算不出来",IF(AND($D17<>本位币,ABS($L17)>ABS($K17)*0.2),"△汇兑损益超过账面成本 20%，核一下汇率",""))))
A18: =IF($C18="","",13) | B18: =IF($C18="","",参数设置!$B$23) | C18: =IF(参数设置!$C$23="","",参数设置!$C$23) | D18: =IF($C18="","",参数设置!$E$23) | E18: =IF($C18="","",ROUND(N(参数设置!$G$23),2)) | F18: =IF($C18="","",ROUND(SUMIF(流水账户,$C18,流水收入),2)) | G18: =IF($C18="","",ROUND(SUMIF(流水账户,$C18,流水支出),2)) | H18: =IF($C18="","",ROUND($E18+$F18-$G18,2)) | I18: =IF($C18="","",IFERROR(IF($D18=本位币,1,IFERROR(LOOKUP(2,1/((汇率月份<=重估基准日)*(INDEX(月末汇率区,0,MATCH($D18,汇率币种头,0))<>"")),INDEX(月末汇率区,0,MATCH($D18,汇率币种头,0))),IFERROR(LOOKUP(2,1/((汇率月份<=重估基准日)*(INDEX(记账汇率区,0,MATCH($D18,汇率币种头,0))<>"")),INDEX(记账汇率区,0,MATCH($D18,汇率币种头,0))),""))),"")) | J18: =IF(OR($C18="",$I18=""),"",ROUND($H18*$I18,2)) | K18: =IF($C18="","",IFERROR(ROUND(参数设置!$I$23+SUMIF(流水账户,$C18,流水本位),2),"")) | L18: =IF(OR($C18="",$J18=""),"",ROUND($J18-$K18,2)) | M18: =IF($C18="","",IF($H18<0,"※期末余额是负数，查一下是不是漏记了收入",IF($I18="","△"&$D18&" 还没填汇率，人民币这几列算不出来",IF(AND($D18<>本位币,ABS($L18)>ABS($K18)*0.2),"△汇兑损益超过账面成本 20%，核一下汇率",""))))
A19: =IF($C19="","",14) | B19: =IF($C19="","",参数设置!$B$24) | C19: =IF(参数设置!$C$24="","",参数设置!$C$24) | D19: =IF($C19="","",参数设置!$E$24) | E19: =IF($C19="","",ROUND(N(参数设置!$G$24),2)) | F19: =IF($C19="","",ROUND(SUMIF(流水账户,$C19,流水收入),2)) | G19: =IF($C19="","",ROUND(SUMIF(流水账户,$C19,流水支出),2)) | H19: =IF($C19="","",ROUND($E19+$F19-$G19,2)) | I19: =IF($C19="","",IFERROR(IF($D19=本位币,1,IFERROR(LOOKUP(2,1/((汇率月份<=重估基准日)*(INDEX(月末汇率区,0,MATCH($D19,汇率币种头,0))<>"")),INDEX(月末汇率区,0,MATCH($D19,汇率币种头,0))),IFERROR(LOOKUP(2,1/((汇率月份<=重估基准日)*(INDEX(记账汇率区,0,MATCH($D19,汇率币种头,0))<>"")),INDEX(记账汇率区,0,MATCH($D19,汇率币种头,0))),""))),"")) | J19: =IF(OR($C19="",$I19=""),"",ROUND($H19*$I19,2)) | K19: =IF($C19="","",IFERROR(ROUND(参数设置!$I$24+SUMIF(流水账户,$C19,流水本位),2),"")) | L19: =IF(OR($C19="",$J19=""),"",ROUND($J19-$K19,2)) | M19: =IF($C19="","",IF($H19<0,"※期末余额是负数，查一下是不是漏记了收入",IF($I19="","△"&$D19&" 还没填汇率，人民币这几列算不出来",IF(AND($D19<>本位币,ABS($L19)>ABS($K19)*0.2),"△汇兑损益超过账面成本 20%，核一下汇率",""))))
A20: =IF($C20="","",15) | B20: =IF($C20="","",参数设置!$B$25) | C20: =IF(参数设置!$C$25="","",参数设置!$C$25) | D20: =IF($C20="","",参数设置!$E$25) | E20: =IF($C20="","",ROUND(N(参数设置!$G$25),2)) | F20: =IF($C20="","",ROUND(SUMIF(流水账户,$C20,流水收入),2)) | G20: =IF($C20="","",ROUND(SUMIF(流水账户,$C20,流水支出),2)) | H20: =IF($C20="","",ROUND($E20+$F20-$G20,2)) | I20: =IF($C20="","",IFERROR(IF($D20=本位币,1,IFERROR(LOOKUP(2,1/((汇率月份<=重估基准日)*(INDEX(月末汇率区,0,MATCH($D20,汇率币种头,0))<>"")),INDEX(月末汇率区,0,MATCH($D20,汇率币种头,0))),IFERROR(LOOKUP(2,1/((汇率月份<=重估基准日)*(INDEX(记账汇率区,0,MATCH($D20,汇率币种头,0))<>"")),INDEX(记账汇率区,0,MATCH($D20,汇率币种头,0))),""))),"")) | J20: =IF(OR($C20="",$I20=""),"",ROUND($H20*$I20,2)) | K20: =IF($C20="","",IFERROR(ROUND(参数设置!$I$25+SUMIF(流水账户,$C20,流水本位),2),"")) | L20: =IF(OR($C20="",$J20=""),"",ROUND($J20-$K20,2)) | M20: =IF($C20="","",IF($H20<0,"※期末余额是负数，查一下是不是漏记了收入",IF($I20="","△"&$D20&" 还没填汇率，人民币这几列算不出来",IF(AND($D20<>本位币,ABS($L20)>ABS($K20)*0.2),"△汇兑损益超过账面成本 20%，核一下汇率",""))))
A21: =IF($C21="","",16) | B21: =IF($C21="","",参数设置!$B$26) | C21: =IF(参数设置!$C$26="","",参数设置!$C$26) | D21: =IF($C21="","",参数设置!$E$26) | E21: =IF($C21="","",ROUND(N(参数设置!$G$26),2)) | F21: =IF($C21="","",ROUND(SUMIF(流水账户,$C21,流水收入),2)) | G21: =IF($C21="","",ROUND(SUMIF(流水账户,$C21,流水支出),2)) | H21: =IF($C21="","",ROUND($E21+$F21-$G21,2)) | I21: =IF($C21="","",IFERROR(IF($D21=本位币,1,IFERROR(LOOKUP(2,1/((汇率月份<=重估基准日)*(INDEX(月末汇率区,0,MATCH($D21,汇率币种头,0))<>"")),INDEX(月末汇率区,0,MATCH($D21,汇率币种头,0))),IFERROR(LOOKUP(2,1/((汇率月份<=重估基准日)*(INDEX(记账汇率区,0,MATCH($D21,汇率币种头,0))<>"")),INDEX(记账汇率区,0,MATCH($D21,汇率币种头,0))),""))),"")) | J21: =IF(OR($C21="",$I21=""),"",ROUND($H21*$I21,2)) | K21: =IF($C21="","",IFERROR(ROUND(参数设置!$I$26+SUMIF(流水账户,$C21,流水本位),2),"")) | L21: =IF(OR($C21="",$J21=""),"",ROUND($J21-$K21,2)) | M21: =IF($C21="","",IF($H21<0,"※期末余额是负数，查一下是不是漏记了收入",IF($I21="","△"&$D21&" 还没填汇率，人民币这几列算不出来",IF(AND($D21<>本位币,ABS($L21)>ABS($K21)*0.2),"△汇兑损益超过账面成本 20%，核一下汇率",""))))
A22: =IF($C22="","",17) | B22: =IF($C22="","",参数设置!$B$27) | C22: =IF(参数设置!$C$27="","",参数设置!$C$27) | D22: =IF($C22="","",参数设置!$E$27) | E22: =IF($C22="","",ROUND(N(参数设置!$G$27),2)) | F22: =IF($C22="","",ROUND(SUMIF(流水账户,$C22,流水收入),2)) | G22: =IF($C22="","",ROUND(SUMIF(流水账户,$C22,流水支出),2)) | H22: =IF($C22="","",ROUND($E22+$F22-$G22,2)) | I22: =IF($C22="","",IFERROR(IF($D22=本位币,1,IFERROR(LOOKUP(2,1/((汇率月份<=重估基准日)*(INDEX(月末汇率区,0,MATCH($D22,汇率币种头,0))<>"")),INDEX(月末汇率区,0,MATCH($D22,汇率币种头,0))),IFERROR(LOOKUP(2,1/((汇率月份<=重估基准日)*(INDEX(记账汇率区,0,MATCH($D22,汇率币种头,0))<>"")),INDEX(记账汇率区,0,MATCH($D22,汇率币种头,0))),""))),"")) | J22: =IF(OR($C22="",$I22=""),"",ROUND($H22*$I22,2)) | K22: =IF($C22="","",IFERROR(ROUND(参数设置!$I$27+SUMIF(流水账户,$C22,流水本位),2),"")) | L22: =IF(OR($C22="",$J22=""),"",ROUND($J22-$K22,2)) | M22: =IF($C22="","",IF($H22<0,"※期末余额是负数，查一下是不是漏记了收入",IF($I22="","△"&$D22&" 还没填汇率，人民币这几列算不出来",IF(AND($D22<>本位币,ABS($L22)>ABS($K22)*0.2),"△汇兑损益超过账面成本 20%，核一下汇率",""))))
A23: =IF($C23="","",18) | B23: =IF($C23="","",参数设置!$B$28) | C23: =IF(参数设置!$C$28="","",参数设置!$C$28) | D23: =IF($C23="","",参数设置!$E$28) | E23: =IF($C23="","",ROUND(N(参数设置!$G$28),2)) | F23: =IF($C23="","",ROUND(SUMIF(流水账户,$C23,流水收入),2)) | G23: =IF($C23="","",ROUND(SUMIF(流水账户,$C23,流水支出),2)) | H23: =IF($C23="","",ROUND($E23+$F23-$G23,2)) | I23: =IF($C23="","",IFERROR(IF($D23=本位币,1,IFERROR(LOOKUP(2,1/((汇率月份<=重估基准日)*(INDEX(月末汇率区,0,MATCH($D23,汇率币种头,0))<>"")),INDEX(月末汇率区,0,MATCH($D23,汇率币种头,0))),IFERROR(LOOKUP(2,1/((汇率月份<=重估基准日)*(INDEX(记账汇率区,0,MATCH($D23,汇率币种头,0))<>"")),INDEX(记账汇率区,0,MATCH($D23,汇率币种头,0))),""))),"")) | J23: =IF(OR($C23="",$I23=""),"",ROUND($H23*$I23,2)) | K23: =IF($C23="","",IFERROR(ROUND(参数设置!$I$28+SUMIF(流水账户,$C23,流水本位),2),"")) | L23: =IF(OR($C23="",$J23=""),"",ROUND($J23-$K23,2)) | M23: =IF($C23="","",IF($H23<0,"※期末余额是负数，查一下是不是漏记了收入",IF($I23="","△"&$D23&" 还没填汇率，人民币这几列算不出来",IF(AND($D23<>本位币,ABS($L23)>ABS($K23)*0.2),"△汇兑损益超过账面成本 20%，核一下汇率",""))))
A24: =IF($C24="","",19) | B24: =IF($C24="","",参数设置!$B$29) | C24: =IF(参数设置!$C$29="","",参数设置!$C$29) | D24: =IF($C24="","",参数设置!$E$29) | E24: =IF($C24="","",ROUND(N(参数设置!$G$29),2)) | F24: =IF($C24="","",ROUND(SUMIF(流水账户,$C24,流水收入),2)) | G24: =IF($C24="","",ROUND(SUMIF(流水账户,$C24,流水支出),2)) | H24: =IF($C24="","",ROUND($E24+$F24-$G24,2)) | I24: =IF($C24="","",IFERROR(IF($D24=本位币,1,IFERROR(LOOKUP(2,1/((汇率月份<=重估基准日)*(INDEX(月末汇率区,0,MATCH($D24,汇率币种头,0))<>"")),INDEX(月末汇率区,0,MATCH($D24,汇率币种头,0))),IFERROR(LOOKUP(2,1/((汇率月份<=重估基准日)*(INDEX(记账汇率区,0,MATCH($D24,汇率币种头,0))<>"")),INDEX(记账汇率区,0,MATCH($D24,汇率币种头,0))),""))),"")) | J24: =IF(OR($C24="",$I24=""),"",ROUND($H24*$I24,2)) | K24: =IF($C24="","",IFERROR(ROUND(参数设置!$I$29+SUMIF(流水账户,$C24,流水本位),2),"")) | L24: =IF(OR($C24="",$J24=""),"",ROUND($J24-$K24,2)) | M24: =IF($C24="","",IF($H24<0,"※期末余额是负数，查一下是不是漏记了收入",IF($I24="","△"&$D24&" 还没填汇率，人民币这几列算不出来",IF(AND($D24<>本位币,ABS($L24)>ABS($K24)*0.2),"△汇兑损益超过账面成本 20%，核一下汇率",""))))
A25: =IF($C25="","",20) | B25: =IF($C25="","",参数设置!$B$30) | C25: =IF(参数设置!$C$30="","",参数设置!$C$30) | D25: =IF($C25="","",参数设置!$E$30) | E25: =IF($C25="","",ROUND(N(参数设置!$G$30),2)) | F25: =IF($C25="","",ROUND(SUMIF(流水账户,$C25,流水收入),2)) | G25: =IF($C25="","",ROUND(SUMIF(流水账户,$C25,流水支出),2)) | H25: =IF($C25="","",ROUND($E25+$F25-$G25,2)) | I25: =IF($C25="","",IFERROR(IF($D25=本位币,1,IFERROR(LOOKUP(2,1/((汇率月份<=重估基准日)*(INDEX(月末汇率区,0,MATCH($D25,汇率币种头,0))<>"")),INDEX(月末汇率区,0,MATCH($D25,汇率币种头,0))),IFERROR(LOOKUP(2,1/((汇率月份<=重估基准日)*(INDEX(记账汇率区,0,MATCH($D25,汇率币种头,0))<>"")),INDEX(记账汇率区,0,MATCH($D25,汇率币种头,0))),""))),"")) | J25: =IF(OR($C25="",$I25=""),"",ROUND($H25*$I25,2)) | K25: =IF($C25="","",IFERROR(ROUND(参数设置!$I$30+SUMIF(流水账户,$C25,流水本位),2),"")) | L25: =IF(OR($C25="",$J25=""),"",ROUND($J25-$K25,2)) | M25: =IF($C25="","",IF($H25<0,"※期末余额是负数，查一下是不是漏记了收入",IF($I25="","△"&$D25&" 还没填汇率，人民币这几列算不出来",IF(AND($D25<>本位币,ABS($L25)>ABS($K25)*0.2),"△汇兑损益超过账面成本 20%，核一下汇率",""))))
A26: =IF($C26="","",21) | B26: =IF($C26="","",参数设置!$B$31) | C26: =IF(参数设置!$C$31="","",参数设置!$C$31) | D26: =IF($C26="","",参数设置!$E$31) | E26: =IF($C26="","",ROUND(N(参数设置!$G$31),2)) | F26: =IF($C26="","",ROUND(SUMIF(流水账户,$C26,流水收入),2)) | G26: =IF($C26="","",ROUND(SUMIF(流水账户,$C26,流水支出),2)) | H26: =IF($C26="","",ROUND($E26+$F26-$G26,2)) | I26: =IF($C26="","",IFERROR(IF($D26=本位币,1,IFERROR(LOOKUP(2,1/((汇率月份<=重估基准日)*(INDEX(月末汇率区,0,MATCH($D26,汇率币种头,0))<>"")),INDEX(月末汇率区,0,MATCH($D26,汇率币种头,0))),IFERROR(LOOKUP(2,1/((汇率月份<=重估基准日)*(INDEX(记账汇率区,0,MATCH($D26,汇率币种头,0))<>"")),INDEX(记账汇率区,0,MATCH($D26,汇率币种头,0))),""))),"")) | J26: =IF(OR($C26="",$I26=""),"",ROUND($H26*$I26,2)) | K26: =IF($C26="","",IFERROR(ROUND(参数设置!$I$31+SUMIF(流水账户,$C26,流水本位),2),"")) | L26: =IF(OR($C26="",$J26=""),"",ROUND($J26-$K26,2)) | M26: =IF($C26="","",IF($H26<0,"※期末余额是负数，查一下是不是漏记了收入",IF($I26="","△"&$D26&" 还没填汇率，人民币这几列算不出来",IF(AND($D26<>本位币,ABS($L26)>ABS($K26)*0.2),"△汇兑损益超过账面成本 20%，核一下汇率",""))))
A27: =IF($C27="","",22) | B27: =IF($C27="","",参数设置!$B$32) | C27: =IF(参数设置!$C$32="","",参数设置!$C$32) | D27: =IF($C27="","",参数设置!$E$32) | E27: =IF($C27="","",ROUND(N(参数设置!$G$32),2)) | F27: =IF($C27="","",ROUND(SUMIF(流水账户,$C27,流水收入),2)) | G27: =IF($C27="","",ROUND(SUMIF(流水账户,$C27,流水支出),2)) | H27: =IF($C27="","",ROUND($E27+$F27-$G27,2)) | I27: =IF($C27="","",IFERROR(IF($D27=本位币,1,IFERROR(LOOKUP(2,1/((汇率月份<=重估基准日)*(INDEX(月末汇率区,0,MATCH($D27,汇率币种头,0))<>"")),INDEX(月末汇率区,0,MATCH($D27,汇率币种头,0))),IFERROR(LOOKUP(2,1/((汇率月份<=重估基准日)*(INDEX(记账汇率区,0,MATCH($D27,汇率币种头,0))<>"")),INDEX(记账汇率区,0,MATCH($D27,汇率币种头,0))),""))),"")) | J27: =IF(OR($C27="",$I27=""),"",ROUND($H27*$I27,2)) | K27: =IF($C27="","",IFERROR(ROUND(参数设置!$I$32+SUMIF(流水账户,$C27,流水本位),2),"")) | L27: =IF(OR($C27="",$J27=""),"",ROUND($J27-$K27,2)) | M27: =IF($C27="","",IF($H27<0,"※期末余额是负数，查一下是不是漏记了收入",IF($I27="","△"&$D27&" 还没填汇率，人民币这几列算不出来",IF(AND($D27<>本位币,ABS($L27)>ABS($K27)*0.2),"△汇兑损益超过账面成本 20%，核一下汇率",""))))
A28: =IF($C28="","",23) | B28: =IF($C28="","",参数设置!$B$33) | C28: =IF(参数设置!$C$33="","",参数设置!$C$33) | D28: =IF($C28="","",参数设置!$E$33) | E28: =IF($C28="","",ROUND(N(参数设置!$G$33),2)) | F28: =IF($C28="","",ROUND(SUMIF(流水账户,$C28,流水收入),2)) | G28: =IF($C28="","",ROUND(SUMIF(流水账户,$C28,流水支出),2)) | H28: =IF($C28="","",ROUND($E28+$F28-$G28,2)) | I28: =IF($C28="","",IFERROR(IF($D28=本位币,1,IFERROR(LOOKUP(2,1/((汇率月份<=重估基准日)*(INDEX(月末汇率区,0,MATCH($D28,汇率币种头,0))<>"")),INDEX(月末汇率区,0,MATCH($D28,汇率币种头,0))),IFERROR(LOOKUP(2,1/((汇率月份<=重估基准日)*(INDEX(记账汇率区,0,MATCH($D28,汇率币种头,0))<>"")),INDEX(记账汇率区,0,MATCH($D28,汇率币种头,0))),""))),"")) | J28: =IF(OR($C28="",$I28=""),"",ROUND($H28*$I28,2)) | K28: =IF($C28="","",IFERROR(ROUND(参数设置!$I$33+SUMIF(流水账户,$C28,流水本位),2),"")) | L28: =IF(OR($C28="",$J28=""),"",ROUND($J28-$K28,2)) | M28: =IF($C28="","",IF($H28<0,"※期末余额是负数，查一下是不是漏记了收入",IF($I28="","△"&$D28&" 还没填汇率，人民币这几列算不出来",IF(AND($D28<>本位币,ABS($L28)>ABS($K28)*0.2),"△汇兑损益超过账面成本 20%，核一下汇率",""))))
A29: =IF($C29="","",24) | B29: =IF($C29="","",参数设置!$B$34) | C29: =IF(参数设置!$C$34="","",参数设置!$C$34) | D29: =IF($C29="","",参数设置!$E$34) | E29: =IF($C29="","",ROUND(N(参数设置!$G$34),2)) | F29: =IF($C29="","",ROUND(SUMIF(流水账户,$C29,流水收入),2)) | G29: =IF($C29="","",ROUND(SUMIF(流水账户,$C29,流水支出),2)) | H29: =IF($C29="","",ROUND($E29+$F29-$G29,2)) | I29: =IF($C29="","",IFERROR(IF($D29=本位币,1,IFERROR(LOOKUP(2,1/((汇率月份<=重估基准日)*(INDEX(月末汇率区,0,MATCH($D29,汇率币种头,0))<>"")),INDEX(月末汇率区,0,MATCH($D29,汇率币种头,0))),IFERROR(LOOKUP(2,1/((汇率月份<=重估基准日)*(INDEX(记账汇率区,0,MATCH($D29,汇率币种头,0))<>"")),INDEX(记账汇率区,0,MATCH($D29,汇率币种头,0))),""))),"")) | J29: =IF(OR($C29="",$I29=""),"",ROUND($H29*$I29,2)) | K29: =IF($C29="","",IFERROR(ROUND(参数设置!$I$34+SUMIF(流水账户,$C29,流水本位),2),"")) | L29: =IF(OR($C29="",$J29=""),"",ROUND($J29-$K29,2)) | M29: =IF($C29="","",IF($H29<0,"※期末余额是负数，查一下是不是漏记了收入",IF($I29="","△"&$D29&" 还没填汇率，人民币这几列算不出来",IF(AND($D29<>本位币,ABS($L29)>ABS($K29)*0.2),"△汇兑损益超过账面成本 20%，核一下汇率",""))))
A30: =IF($C30="","",25) | B30: =IF($C30="","",参数设置!$B$35) | C30: =IF(参数设置!$C$35="","",参数设置!$C$35) | D30: =IF($C30="","",参数设置!$E$35) | E30: =IF($C30="","",ROUND(N(参数设置!$G$35),2)) | F30: =IF($C30="","",ROUND(SUMIF(流水账户,$C30,流水收入),2)) | G30: =IF($C30="","",ROUND(SUMIF(流水账户,$C30,流水支出),2)) | H30: =IF($C30="","",ROUND($E30+$F30-$G30,2)) | I30: =IF($C30="","",IFERROR(IF($D30=本位币,1,IFERROR(LOOKUP(2,1/((汇率月份<=重估基准日)*(INDEX(月末汇率区,0,MATCH($D30,汇率币种头,0))<>"")),INDEX(月末汇率区,0,MATCH($D30,汇率币种头,0))),IFERROR(LOOKUP(2,1/((汇率月份<=重估基准日)*(INDEX(记账汇率区,0,MATCH($D30,汇率币种头,0))<>"")),INDEX(记账汇率区,0,MATCH($D30,汇率币种头,0))),""))),"")) | J30: =IF(OR($C30="",$I30=""),"",ROUND($H30*$I30,2)) | K30: =IF($C30="","",IFERROR(ROUND(参数设置!$I$35+SUMIF(流水账户,$C30,流水本位),2),"")) | L30: =IF(OR($C30="",$J30=""),"",ROUND($J30-$K30,2)) | M30: =IF($C30="","",IF($H30<0,"※期末余额是负数，查一下是不是漏记了收入",IF($I30="","△"&$D30&" 还没填汇率，人民币这几列算不出来",IF(AND($D30<>本位币,ABS($L30)>ABS($K30)*0.2),"△汇兑损益超过账面成本 20%，核一下汇率",""))))
A31: =IF($C31="","",26) | B31: =IF($C31="","",参数设置!$B$36) | C31: =IF(参数设置!$C$36="","",参数设置!$C$36) | D31: =IF($C31="","",参数设置!$E$36) | E31: =IF($C31="","",ROUND(N(参数设置!$G$36),2)) | F31: =IF($C31="","",ROUND(SUMIF(流水账户,$C31,流水收入),2)) | G31: =IF($C31="","",ROUND(SUMIF(流水账户,$C31,流水支出),2)) | H31: =IF($C31="","",ROUND($E31+$F31-$G31,2)) | I31: =IF($C31="","",IFERROR(IF($D31=本位币,1,IFERROR(LOOKUP(2,1/((汇率月份<=重估基准日)*(INDEX(月末汇率区,0,MATCH($D31,汇率币种头,0))<>"")),INDEX(月末汇率区,0,MATCH($D31,汇率币种头,0))),IFERROR(LOOKUP(2,1/((汇率月份<=重估基准日)*(INDEX(记账汇率区,0,MATCH($D31,汇率币种头,0))<>"")),INDEX(记账汇率区,0,MATCH($D31,汇率币种头,0))),""))),"")) | J31: =IF(OR($C31="",$I31=""),"",ROUND($H31*$I31,2)) | K31: =IF($C31="","",IFERROR(ROUND(参数设置!$I$36+SUMIF(流水账户,$C31,流水本位),2),"")) | L31: =IF(OR($C31="",$J31=""),"",ROUND($J31-$K31,2)) | M31: =IF($C31="","",IF($H31<0,"※期末余额是负数，查一下是不是漏记了收入",IF($I31="","△"&$D31&" 还没填汇率，人民币这几列算不出来",IF(AND($D31<>本位币,ABS($L31)>ABS($K31)*0.2),"△汇兑损益超过账面成本 20%，核一下汇率",""))))
A32: =IF($C32="","",27) | B32: =IF($C32="","",参数设置!$B$37) | C32: =IF(参数设置!$C$37="","",参数设置!$C$37) | D32: =IF($C32="","",参数设置!$E$37) | E32: =IF($C32="","",ROUND(N(参数设置!$G$37),2)) | F32: =IF($C32="","",ROUND(SUMIF(流水账户,$C32,流水收入),2)) | G32: =IF($C32="","",ROUND(SUMIF(流水账户,$C32,流水支出),2)) | H32: =IF($C32="","",ROUND($E32+$F32-$G32,2)) | I32: =IF($C32="","",IFERROR(IF($D32=本位币,1,IFERROR(LOOKUP(2,1/((汇率月份<=重估基准日)*(INDEX(月末汇率区,0,MATCH($D32,汇率币种头,0))<>"")),INDEX(月末汇率区,0,MATCH($D32,汇率币种头,0))),IFERROR(LOOKUP(2,1/((汇率月份<=重估基准日)*(INDEX(记账汇率区,0,MATCH($D32,汇率币种头,0))<>"")),INDEX(记账汇率区,0,MATCH($D32,汇率币种头,0))),""))),"")) | J32: =IF(OR($C32="",$I32=""),"",ROUND($H32*$I32,2)) | K32: =IF($C32="","",IFERROR(ROUND(参数设置!$I$37+SUMIF(流水账户,$C32,流水本位),2),"")) | L32: =IF(OR($C32="",$J32=""),"",ROUND($J32-$K32,2)) | M32: =IF($C32="","",IF($H32<0,"※期末余额是负数，查一下是不是漏记了收入",IF($I32="","△"&$D32&" 还没填汇率，人民币这几列算不出来",IF(AND($D32<>本位币,ABS($L32)>ABS($K32)*0.2),"△汇兑损益超过账面成本 20%，核一下汇率",""))))
A33: =IF($C33="","",28) | B33: =IF($C33="","",参数设置!$B$38) | C33: =IF(参数设置!$C$38="","",参数设置!$C$38) | D33: =IF($C33="","",参数设置!$E$38) | E33: =IF($C33="","",ROUND(N(参数设置!$G$38),2)) | F33: =IF($C33="","",ROUND(SUMIF(流水账户,$C33,流水收入),2)) | G33: =IF($C33="","",ROUND(SUMIF(流水账户,$C33,流水支出),2)) | H33: =IF($C33="","",ROUND($E33+$F33-$G33,2)) | I33: =IF($C33="","",IFERROR(IF($D33=本位币,1,IFERROR(LOOKUP(2,1/((汇率月份<=重估基准日)*(INDEX(月末汇率区,0,MATCH($D33,汇率币种头,0))<>"")),INDEX(月末汇率区,0,MATCH($D33,汇率币种头,0))),IFERROR(LOOKUP(2,1/((汇率月份<=重估基准日)*(INDEX(记账汇率区,0,MATCH($D33,汇率币种头,0))<>"")),INDEX(记账汇率区,0,MATCH($D33,汇率币种头,0))),""))),"")) | J33: =IF(OR($C33="",$I33=""),"",ROUND($H33*$I33,2)) | K33: =IF($C33="","",IFERROR(ROUND(参数设置!$I$38+SUMIF(流水账户,$C33,流水本位),2),"")) | L33: =IF(OR($C33="",$J33=""),"",ROUND($J33-$K33,2)) | M33: =IF($C33="","",IF($H33<0,"※期末余额是负数，查一下是不是漏记了收入",IF($I33="","△"&$D33&" 还没填汇率，人民币这几列算不出来",IF(AND($D33<>本位币,ABS($L33)>ABS($K33)*0.2),"△汇兑损益超过账面成本 20%，核一下汇率",""))))
A34: =IF($C34="","",29) | B34: =IF($C34="","",参数设置!$B$39) | C34: =IF(参数设置!$C$39="","",参数设置!$C$39) | D34: =IF($C34="","",参数设置!$E$39) | E34: =IF($C34="","",ROUND(N(参数设置!$G$39),2)) | F34: =IF($C34="","",ROUND(SUMIF(流水账户,$C34,流水收入),2)) | G34: =IF($C34="","",ROUND(SUMIF(流水账户,$C34,流水支出),2)) | H34: =IF($C34="","",ROUND($E34+$F34-$G34,2)) | I34: =IF($C34="","",IFERROR(IF($D34=本位币,1,IFERROR(LOOKUP(2,1/((汇率月份<=重估基准日)*(INDEX(月末汇率区,0,MATCH($D34,汇率币种头,0))<>"")),INDEX(月末汇率区,0,MATCH($D34,汇率币种头,0))),IFERROR(LOOKUP(2,1/((汇率月份<=重估基准日)*(INDEX(记账汇率区,0,MATCH($D34,汇率币种头,0))<>"")),INDEX(记账汇率区,0,MATCH($D34,汇率币种头,0))),""))),"")) | J34: =IF(OR($C34="",$I34=""),"",ROUND($H34*$I34,2)) | K34: =IF($C34="","",IFERROR(ROUND(参数设置!$I$39+SUMIF(流水账户,$C34,流水本位),2),"")) | L34: =IF(OR($C34="",$J34=""),"",ROUND($J34-$K34,2)) | M34: =IF($C34="","",IF($H34<0,"※期末余额是负数，查一下是不是漏记了收入",IF($I34="","△"&$D34&" 还没填汇率，人民币这几列算不出来",IF(AND($D34<>本位币,ABS($L34)>ABS($K34)*0.2),"△汇兑损益超过账面成本 20%，核一下汇率",""))))
A35: =IF($C35="","",30) | B35: =IF($C35="","",参数设置!$B$40) | C35: =IF(参数设置!$C$40="","",参数设置!$C$40) | D35: =IF($C35="","",参数设置!$E$40) | E35: =IF($C35="","",ROUND(N(参数设置!$G$40),2)) | F35: =IF($C35="","",ROUND(SUMIF(流水账户,$C35,流水收入),2)) | G35: =IF($C35="","",ROUND(SUMIF(流水账户,$C35,流水支出),2)) | H35: =IF($C35="","",ROUND($E35+$F35-$G35,2)) | I35: =IF($C35="","",IFERROR(IF($D35=本位币,1,IFERROR(LOOKUP(2,1/((汇率月份<=重估基准日)*(INDEX(月末汇率区,0,MATCH($D35,汇率币种头,0))<>"")),INDEX(月末汇率区,0,MATCH($D35,汇率币种头,0))),IFERROR(LOOKUP(2,1/((汇率月份<=重估基准日)*(INDEX(记账汇率区,0,MATCH($D35,汇率币种头,0))<>"")),INDEX(记账汇率区,0,MATCH($D35,汇率币种头,0))),""))),"")) | J35: =IF(OR($C35="",$I35=""),"",ROUND($H35*$I35,2)) | K35: =IF($C35="","",IFERROR(ROUND(参数设置!$I$40+SUMIF(流水账户,$C35,流水本位),2),"")) | L35: =IF(OR($C35="",$J35=""),"",ROUND($J35-$K35,2)) | M35: =IF($C35="","",IF($H35<0,"※期末余额是负数，查一下是不是漏记了收入",IF($I35="","△"&$D35&" 还没填汇率，人民币这几列算不出来",IF(AND($D35<>本位币,ABS($L35)>ABS($K35)*0.2),"△汇兑损益超过账面成本 20%，核一下汇率",""))))
A36: 合计 | D36: 原币不同，不能相加 | J36: =ROUND(SUM(J6:J35),2) -> 11961380 | K36: =ROUND(SUM(K6:K35),2) -> 11921240 | L36: =ROUND(SUM(L6:L35),2) -> 40140 | M36: 「期末人民币合计」就是公司的资金总额（人民币口径）
A38: 按币种小计 —— 外币敞口一眼看完
A39: 币种 | B39: 账户数 | C39: 期末余额(原币) | D39: 期末汇率 | E39: 折人民币 | F39: 账面人民币成本 | G39: 汇兑损益 | H39: 占资金比重
A40: =IF(参数设置!$L$11="","",参数设置!$L$11) -> CNY | B40: =IF($A40="","",COUNTIF($D$6:$D$35,$A40)) -> 2 | C40: =IF($A40="","",ROUND(SUMIF($D$6:$D$35,$A40,$H$6:$H$35),2)) -> 1010400 | D40: =IF($A40="","",IFERROR(IF($A40=本位币,1,IFERROR(LOOKUP(2,1/((汇率月份<=重估基准日)*(INDEX(月末汇率区,0,MATCH($A40,汇率币种头,0))<>"")),INDEX(月末汇率区,0,MATCH($A40,汇率币种头,0))),IFERROR(LOOKUP(2,1/((汇率月份<=重估基准日)*(INDEX(记账汇率区,0,MATCH($A40,汇率币种头,0))<>"")),INDEX(记账汇率区,0,MATCH($A40,汇率币种头,0))),""))),"")) -> 1 | E40: =IF($A40="","",ROUND(SUMIF($D$6:$D$35,$A40,$J$6:$J$35),2)) -> 1010400 | F40: =IF($A40="","",ROUND(SUMIF($D$6:$D$35,$A40,$K$6:$K$35),2)) -> 1010400 | G40: =IF($A40="","",ROUND($E40-$F40,2)) -> 0 | H40: =IF(OR($A40="",N($J$36)=0),"",$E40/$J$36) -> 0.084471859
A41: =IF(参数设置!$L$12="","",参数设置!$L$12) -> USD | B41: =IF($A41="","",COUNTIF($D$6:$D$35,$A41)) -> 2 | C41: =IF($A41="","",ROUND(SUMIF($D$6:$D$35,$A41,$H$6:$H$35),2)) -> 1319000 | D41: =IF($A41="","",IFERROR(IF($A41=本位币,1,IFERROR(LOOKUP(2,1/((汇率月份<=重估基准日)*(INDEX(月末汇率区,0,MATCH($A41,汇率币种头,0))<>"")),INDEX(月末汇率区,0,MATCH($A41,汇率币种头,0))),IFERROR(LOOKUP(2,1/((汇率月份<=重估基准日)*(INDEX(记账汇率区,0,MATCH($A41,汇率币种头,0))<>"")),INDEX(记账汇率区,0,MATCH($A41,汇率币种头,0))),""))),"")) -> 7.18 | E41: =IF($A41="","",ROUND(SUMIF($D$6:$D$35,$A41,$J$6:$J$35),2)) -> 9470420 | F41: =IF($A41="","",ROUND(SUMIF($D$6:$D$35,$A41,$K$6:$K$35),2)) -> 9431780 | G41: =IF($A41="","",ROUND($E41-$F41,2)) -> 38640 | H41: =IF(OR($A41="",N($J$36)=0),"",$E41/$J$36) -> 0.79174978
A42: =IF(参数设置!$L$13="","",参数设置!$L$13) -> HKD | B42: =IF($A42="","",COUNTIF($D$6:$D$35,$A42)) -> 1 | C42: =IF($A42="","",ROUND(SUMIF($D$6:$D$35,$A42,$H$6:$H$35),2)) -> 355500 | D42: =IF($A42="","",IFERROR(IF($A42=本位币,1,IFERROR(LOOKUP(2,1/((汇率月份<=重估基准日)*(INDEX(月末汇率区,0,MATCH($A42,汇率币种头,0))<>"")),INDEX(月末汇率区,0,MATCH($A42,汇率币种头,0))),IFERROR(LOOKUP(2,1/((汇率月份<=重估基准日)*(INDEX(记账汇率区,0,MATCH($A42,汇率币种头,0))<>"")),INDEX(记账汇率区,0,MATCH($A42,汇率币种头,0))),""))),"")) -> 0.92 | E42: =IF($A42="","",ROUND(SUMIF($D$6:$D$35,$A42,$J$6:$J$35),2)) -> 327060 | F42: =IF($A42="","",ROUND(SUMIF($D$6:$D$35,$A42,$K$6:$K$35),2)) -> 325560 | G42: =IF($A42="","",ROUND($E42-$F42,2)) -> 1500 | H42: =IF(OR($A42="",N($J$36)=0),"",$E42/$J$36) -> 0.027342999
A43: =IF(参数设置!$L$14="","",参数设置!$L$14) -> EUR | B43: =IF($A43="","",COUNTIF($D$6:$D$35,$A43)) -> 1 | C43: =IF($A43="","",ROUND(SUMIF($D$6:$D$35,$A43,$H$6:$H$35),2)) -> 150000 | D43: =IF($A43="","",IFERROR(IF($A43=本位币,1,IFERROR(LOOKUP(2,1/((汇率月份<=重估基准日)*(INDEX(月末汇率区,0,MATCH($A43,汇率币种头,0))<>"")),INDEX(月末汇率区,0,MATCH($A43,汇率币种头,0))),IFERROR(LOOKUP(2,1/((汇率月份<=重估基准日)*(INDEX(记账汇率区,0,MATCH($A43,汇率币种头,0))<>"")),INDEX(记账汇率区,0,MATCH($A43,汇率币种头,0))),""))),"")) -> 7.69 | E43: =IF($A43="","",ROUND(SUMIF($D$6:$D$35,$A43,$J$6:$J$35),2)) -> 1153500 | F43: =IF($A43="","",ROUND(SUMIF($D$6:$D$35,$A43,$K$6:$K$35),2)) -> 1153500 | G43: =IF($A43="","",ROUND($E43-$F43,2)) -> 0 | H43: =IF(OR($A43="",N($J$36)=0),"",$E43/$J$36) -> 0.096435361
A44: =IF(参数设置!$L$15="","",参数设置!$L$15) -> JPY | B44: =IF($A44="","",COUNTIF($D$6:$D$35,$A44)) -> 0 | C44: =IF($A44="","",ROUND(SUMIF($D$6:$D$35,$A44,$H$6:$H$35),2)) -> 0 | D44: =IF($A44="","",IFERROR(IF($A44=本位币,1,IFERROR(LOOKUP(2,1/((汇率月份<=重估基准日)*(INDEX(月末汇率区,0,MATCH($A44,汇率币种头,0))<>"")),INDEX(月末汇率区,0,MATCH($A44,汇率币种头,0))),IFERROR(LOOKUP(2,1/((汇率月份<=重估基准日)*(INDEX(记账汇率区,0,MATCH($A44,汇率币种头,0))<>"")),INDEX(记账汇率区,0,MATCH($A44,汇率币种头,0))),""))),"")) | E44: =IF($A44="","",ROUND(SUMIF($D$6:$D$35,$A44,$J$6:$J$35),2)) -> 0 | F44: =IF($A44="","",ROUND(SUMIF($D$6:$D$35,$A44,$K$6:$K$35),2)) -> 0 | G44: =IF($A44="","",ROUND($E44-$F44,2)) -> 0 | H44: =IF(OR($A44="",N($J$36)=0),"",$E44/$J$36) -> 0
A45: =IF(参数设置!$L$16="","",参数设置!$L$16) -> GBP | B45: =IF($A45="","",COUNTIF($D$6:$D$35,$A45)) -> 0 | C45: =IF($A45="","",ROUND(SUMIF($D$6:$D$35,$A45,$H$6:$H$35),2)) -> 0 | D45: =IF($A45="","",IFERROR(IF($A45=本位币,1,IFERROR(LOOKUP(2,1/((汇率月份<=重估基准日)*(INDEX(月末汇率区,0,MATCH($A45,汇率币种头,0))<>"")),INDEX(月末汇率区,0,MATCH($A45,汇率币种头,0))),IFERROR(LOOKUP(2,1/((汇率月份<=重估基准日)*(INDEX(记账汇率区,0,MATCH($A45,汇率币种头,0))<>"")),INDEX(记账汇率区,0,MATCH($A45,汇率币种头,0))),""))),"")) | E45: =IF($A45="","",ROUND(SUMIF($D$6:$D$35,$A45,$J$6:$J$35),2)) -> 0 | F45: =IF($A45="","",ROUND(SUMIF($D$6:$D$35,$A45,$K$6:$K$35),2)) -> 0 | G45: =IF($A45="","",ROUND($E45-$F45,2)) -> 0 | H45: =IF(OR($A45="",N($J$36)=0),"",$E45/$J$36) -> 0
A46: =IF(参数设置!$L$17="","",参数设置!$L$17) -> SGD | B46: =IF($A46="","",COUNTIF($D$6:$D$35,$A46)) -> 0 | C46: =IF($A46="","",ROUND(SUMIF($D$6:$D$35,$A46,$H$6:$H$35),2)) -> 0 | D46: =IF($A46="","",IFERROR(IF($A46=本位币,1,IFERROR(LOOKUP(2,1/((汇率月份<=重估基准日)*(INDEX(月末汇率区,0,MATCH($A46,汇率币种头,0))<>"")),INDEX(月末汇率区,0,MATCH($A46,汇率币种头,0))),IFERROR(LOOKUP(2,1/((汇率月份<=重估基准日)*(INDEX(记账汇率区,0,MATCH($A46,汇率币种头,0))<>"")),INDEX(记账汇率区,0,MATCH($A46,汇率币种头,0))),""))),"")) | E46: =IF($A46="","",ROUND(SUMIF($D$6:$D$35,$A46,$J$6:$J$35),2)) -> 0 | F46: =IF($A46="","",ROUND(SUMIF($D$6:$D$35,$A46,$K$6:$K$35),2)) -> 0 | G46: =IF($A46="","",ROUND($E46-$F46,2)) -> 0 | H46: =IF(OR($A46="",N($J$36)=0),"",$E46/$J$36) -> 0
A47: =IF(参数设置!$L$18="","",参数设置!$L$18) -> AUD | B47: =IF($A47="","",COUNTIF($D$6:$D$35,$A47)) -> 0 | C47: =IF($A47="","",ROUND(SUMIF($D$6:$D$35,$A47,$H$6:$H$35),2)) -> 0 | D47: =IF($A47="","",IFERROR(IF($A47=本位币,1,IFERROR(LOOKUP(2,1/((汇率月份<=重估基准日)*(INDEX(月末汇率区,0,MATCH($A47,汇率币种头,0))<>"")),INDEX(月末汇率区,0,MATCH($A47,汇率币种头,0))),IFERROR(LOOKUP(2,1/((汇率月份<=重估基准日)*(INDEX(记账汇率区,0,MATCH($A47,汇率币种头,0))<>"")),INDEX(记账汇率区,0,MATCH($A47,汇率币种头,0))),""))),"")) | E47: =IF($A47="","",ROUND(SUMIF($D$6:$D$35,$A47,$J$6:$J$35),2)) -> 0 | F47: =IF($A47="","",ROUND(SUMIF($D$6:$D$35,$A47,$K$6:$K$35),2)) -> 0 | G47: =IF($A47="","",ROUND($E47-$F47,2)) -> 0 | H47: =IF(OR($A47="",N($J$36)=0),"",$E47/$J$36) -> 0
A48: 合计 | B48: =SUM(B40:B47) -> 6 | C48: — | D48: — | E48: =ROUND(SUM(E40:E47),2) -> 11961380 | F48: =ROUND(SUM(F40:F47),2) -> 11921240 | G48: =ROUND(SUM(G40:G47),2) -> 40140 | H48: =IF(N($J$36)=0,"",SUM(H40:H47)) -> 1

Sheet 月度汇报表
A1: 月度汇报表 · 全部折成人民币
A2: 收入/支出按「钱的方向」认（折人民币为正=收，为负=支），内部转账（账户之间调头寸、购汇结汇）单独两列列出来，不算进收入和支出
A4: 一、按月汇总（人民币）
A5: 月份 | B5: 收入(人民币) | C5: 支出(人民币) | D5: 净流入(人民币) | E5: 内部转入 | F5: 内部转出 | G5: 月末资金总额(人民币账面) | H5: 说明
A6: =DATE(管理年度,1,1) -> 46023 | B6: =ROUND(SUMIFS(流水本位,流水日期,">="&DATE(管理年度,1,1),流水日期,"<="&EOMONTH(DATE(管理年度,1,1),0),流水属性,"<>内部转账",流水本位,">0"),2) -> 0 | C6: =-ROUND(SUMIFS(流水本位,流水日期,">="&DATE(管理年度,1,1),流水日期,"<="&EOMONTH(DATE(管理年度,1,1),0),流水属性,"<>内部转账",流水本位,"<0"),2) -> 0 | D6: =ROUND($B6-$C6,2) -> 0 | E6: =ROUND(SUMIFS(流水本位,流水日期,">="&DATE(管理年度,1,1),流水日期,"<="&EOMONTH(DATE(管理年度,1,1),0),流水属性,"内部转账",流水本位,">0"),2) -> 0 | F6: =-ROUND(SUMIFS(流水本位,流水日期,">="&DATE(管理年度,1,1),流水日期,"<="&EOMONTH(DATE(管理年度,1,1),0),流水属性,"内部转账",流水本位,"<0"),2) -> 0 | G6: =ROUND(SUM(账户期初本位)+SUMIFS(流水本位,流水日期,"<="&EOMONTH(DATE(管理年度,1,1),0)),2) -> 11192300 | H6: =IF(ROUND($E6-$F6,2)=0,"","内部转账净额 "&TEXT($E6-$F6,"#,##0.00")&"，是换汇价差")
A7: =DATE(管理年度,2,1) -> 46054 | B7: =ROUND(SUMIFS(流水本位,流水日期,">="&DATE(管理年度,2,1),流水日期,"<="&EOMONTH(DATE(管理年度,2,1),0),流水属性,"<>内部转账",流水本位,">0"),2) -> 0 | C7: =-ROUND(SUMIFS(流水本位,流水日期,">="&DATE(管理年度,2,1),流水日期,"<="&EOMONTH(DATE(管理年度,2,1),0),流水属性,"<>内部转账",流水本位,"<0"),2) -> 0 | D7: =ROUND($B7-$C7,2) -> 0 | E7: =ROUND(SUMIFS(流水本位,流水日期,">="&DATE(管理年度,2,1),流水日期,"<="&EOMONTH(DATE(管理年度,2,1),0),流水属性,"内部转账",流水本位,">0"),2) -> 0 | F7: =-ROUND(SUMIFS(流水本位,流水日期,">="&DATE(管理年度,2,1),流水日期,"<="&EOMONTH(DATE(管理年度,2,1),0),流水属性,"内部转账",流水本位,"<0"),2) -> 0 | G7: =ROUND(SUM(账户期初本位)+SUMIFS(流水本位,流水日期,"<="&EOMONTH(DATE(管理年度,2,1),0)),2) -> 11192300 | H7: =IF(ROUND($E7-$F7,2)=0,"","内部转账净额 "&TEXT($E7-$F7,"#,##0.00")&"，是换汇价差")
A8: =DATE(管理年度,3,1) -> 46082 | B8: =ROUND(SUMIFS(流水本位,流水日期,">="&DATE(管理年度,3,1),流水日期,"<="&EOMONTH(DATE(管理年度,3,1),0),流水属性,"<>内部转账",流水本位,">0"),2) -> 0 | C8: =-ROUND(SUMIFS(流水本位,流水日期,">="&DATE(管理年度,3,1),流水日期,"<="&EOMONTH(DATE(管理年度,3,1),0),流水属性,"<>内部转账",流水本位,"<0"),2) -> 0 | D8: =ROUND($B8-$C8,2) -> 0 | E8: =ROUND(SUMIFS(流水本位,流水日期,">="&DATE(管理年度,3,1),流水日期,"<="&EOMONTH(DATE(管理年度,3,1),0),流水属性,"内部转账",流水本位,">0"),2) -> 0 | F8: =-ROUND(SUMIFS(流水本位,流水日期,">="&DATE(管理年度,3,1),流水日期,"<="&EOMONTH(DATE(管理年度,3,1),0),流水属性,"内部转账",流水本位,"<0"),2) -> 0 | G8: =ROUND(SUM(账户期初本位)+SUMIFS(流水本位,流水日期,"<="&EOMONTH(DATE(管理年度,3,1),0)),2) -> 11192300 | H8: =IF(ROUND($E8-$F8,2)=0,"","内部转账净额 "&TEXT($E8-$F8,"#,##0.00")&"，是换汇价差")
A9: =DATE(管理年度,4,1) -> 46113 | B9: =ROUND(SUMIFS(流水本位,流水日期,">="&DATE(管理年度,4,1),流水日期,"<="&EOMONTH(DATE(管理年度,4,1),0),流水属性,"<>内部转账",流水本位,">0"),2) -> 0 | C9: =-ROUND(SUMIFS(流水本位,流水日期,">="&DATE(管理年度,4,1),流水日期,"<="&EOMONTH(DATE(管理年度,4,1),0),流水属性,"<>内部转账",流水本位,"<0"),2) -> 0 | D9: =ROUND($B9-$C9,2) -> 0 | E9: =ROUND(SUMIFS(流水本位,流水日期,">="&DATE(管理年度,4,1),流水日期,"<="&EOMONTH(DATE(管理年度,4,1),0),流水属性,"内部转账",流水本位,">0"),2) -> 0 | F9: =-ROUND(SUMIFS(流水本位,流水日期,">="&DATE(管理年度,4,1),流水日期,"<="&EOMONTH(DATE(管理年度,4,1),0),流水属性,"内部转账",流水本位,"<0"),2) -> 0 | G9: =ROUND(SUM(账户期初本位)+SUMIFS(流水本位,流水日期,"<="&EOMONTH(DATE(管理年度,4,1),0)),2) -> 11192300 | H9: =IF(ROUND($E9-$F9,2)=0,"","内部转账净额 "&TEXT($E9-$F9,"#,##0.00")&"，是换汇价差")
A10: =DATE(管理年度,5,1) -> 46143 | B10: =ROUND(SUMIFS(流水本位,流水日期,">="&DATE(管理年度,5,1),流水日期,"<="&EOMONTH(DATE(管理年度,5,1),0),流水属性,"<>内部转账",流水本位,">0"),2) -> 0 | C10: =-ROUND(SUMIFS(流水本位,流水日期,">="&DATE(管理年度,5,1),流水日期,"<="&EOMONTH(DATE(管理年度,5,1),0),流水属性,"<>内部转账",流水本位,"<0"),2) -> 0 | D10: =ROUND($B10-$C10,2) -> 0 | E10: =ROUND(SUMIFS(流水本位,流水日期,">="&DATE(管理年度,5,1),流水日期,"<="&EOMONTH(DATE(管理年度,5,1),0),流水属性,"内部转账",流水本位,">0"),2) -> 0 | F10: =-ROUND(SUMIFS(流水本位,流水日期,">="&DATE(管理年度,5,1),流水日期,"<="&EOMONTH(DATE(管理年度,5,1),0),流水属性,"内部转账",流水本位,"<0"),2) -> 0 | G10: =ROUND(SUM(账户期初本位)+SUMIFS(流水本位,流水日期,"<="&EOMONTH(DATE(管理年度,5,1),0)),2) -> 11192300 | H10: =IF(ROUND($E10-$F10,2)=0,"","内部转账净额 "&TEXT($E10-$F10,"#,##0.00")&"，是换汇价差")
A11: =DATE(管理年度,6,1) -> 46174 | B11: =ROUND(SUMIFS(流水本位,流水日期,">="&DATE(管理年度,6,1),流水日期,"<="&EOMONTH(DATE(管理年度,6,1),0),流水属性,"<>内部转账",流水本位,">0"),2) -> 0 | C11: =-ROUND(SUMIFS(流水本位,流水日期,">="&DATE(管理年度,6,1),流水日期,"<="&EOMONTH(DATE(管理年度,6,1),0),流水属性,"<>内部转账",流水本位,"<0"),2) -> 0 | D11: =ROUND($B11-$C11,2) -> 0 | E11: =ROUND(SUMIFS(流水本位,流水日期,">="&DATE(管理年度,6,1),流水日期,"<="&EOMONTH(DATE(管理年度,6,1),0),流水属性,"内部转账",流水本位,">0"),2) -> 0 | F11: =-ROUND(SUMIFS(流水本位,流水日期,">="&DATE(管理年度,6,1),流水日期,"<="&EOMONTH(DATE(管理年度,6,1),0),流水属性,"内部转账",流水本位,"<0"),2) -> 0 | G11: =ROUND(SUM(账户期初本位)+SUMIFS(流水本位,流水日期,"<="&EOMONTH(DATE(管理年度,6,1),0)),2) -> 11192300 | H11: =IF(ROUND($E11-$F11,2)=0,"","内部转账净额 "&TEXT($E11-$F11,"#,##0.00")&"，是换汇价差")
A12: =DATE(管理年度,7,1) -> 46204 | B12: =ROUND(SUMIFS(流水本位,流水日期,">="&DATE(管理年度,7,1),流水日期,"<="&EOMONTH(DATE(管理年度,7,1),0),流水属性,"<>内部转账",流水本位,">0"),2) -> 0 | C12: =-ROUND(SUMIFS(流水本位,流水日期,">="&DATE(管理年度,7,1),流水日期,"<="&EOMONTH(DATE(管理年度,7,1),0),流水属性,"<>内部转账",流水本位,"<0"),2) -> 0 | D12: =ROUND($B12-$C12,2) -> 0 | E12: =ROUND(SUMIFS(流水本位,流水日期,">="&DATE(管理年度,7,1),流水日期,"<="&EOMONTH(DATE(管理年度,7,1),0),流水属性,"内部转账",流水本位,">0"),2) -> 0 | F12: =-ROUND(SUMIFS(流水本位,流水日期,">="&DATE(管理年度,7,1),流水日期,"<="&EOMONTH(DATE(管理年度,7,1),0),流水属性,"内部转账",流水本位,"<0"),2) -> 0 | G12: =ROUND(SUM(账户期初本位)+SUMIFS(流水本位,流水日期,"<="&EOMONTH(DATE(管理年度,7,1),0)),2) -> 11192300 | H12: =IF(ROUND($E12-$F12,2)=0,"","内部转账净额 "&TEXT($E12-$F12,"#,##0.00")&"，是换汇价差")
A13: =DATE(管理年度,8,1) -> 46235 | B13: =ROUND(SUMIFS(流水本位,流水日期,">="&DATE(管理年度,8,1),流水日期,"<="&EOMONTH(DATE(管理年度,8,1),0),流水属性,"<>内部转账",流水本位,">0"),2) -> 892660 | C13: =-ROUND(SUMIFS(流水本位,流水日期,">="&DATE(管理年度,8,1),流水日期,"<="&EOMONTH(DATE(管理年度,8,1),0),流水属性,"<>内部转账",流水本位,"<0"),2) -> 163720 | D13: =ROUND($B13-$C13,2) -> 728940 | E13: =ROUND(SUMIFS(流水本位,流水日期,">="&DATE(管理年度,8,1),流水日期,"<="&EOMONTH(DATE(管理年度,8,1),0),流水属性,"内部转账",流水本位,">0"),2) -> 193400 | F13: =-ROUND(SUMIFS(流水本位,流水日期,">="&DATE(管理年度,8,1),流水日期,"<="&EOMONTH(DATE(管理年度,8,1),0),流水属性,"内部转账",流水本位,"<0"),2) -> 193400 | G13: =ROUND(SUM(账户期初本位)+SUMIFS(流水本位,流水日期,"<="&EOMONTH(DATE(管理年度,8,1),0)),2) -> 11921240 | H13: =IF(ROUND($E13-$F13,2)=0,"","内部转账净额 "&TEXT($E13-$F13,"#,##0.00")&"，是换汇价差")
A14: =DATE(管理年度,9,1) -> 46266 | B14: =ROUND(SUMIFS(流水本位,流水日期,">="&DATE(管理年度,9,1),流水日期,"<="&EOMONTH(DATE(管理年度,9,1),0),流水属性,"<>内部转账",流水本位,">0"),2) -> 0 | C14: =-ROUND(SUMIFS(流水本位,流水日期,">="&DATE(管理年度,9,1),流水日期,"<="&EOMONTH(DATE(管理年度,9,1),0),流水属性,"<>内部转账",流水本位,"<0"),2) -> 0 | D14: =ROUND($B14-$C14,2) -> 0 | E14: =ROUND(SUMIFS(流水本位,流水日期,">="&DATE(管理年度,9,1),流水日期,"<="&EOMONTH(DATE(管理年度,9,1),0),流水属性,"内部转账",流水本位,">0"),2) -> 0 | F14: =-ROUND(SUMIFS(流水本位,流水日期,">="&DATE(管理年度,9,1),流水日期,"<="&EOMONTH(DATE(管理年度,9,1),0),流水属性,"内部转账",流水本位,"<0"),2) -> 0 | G14: =ROUND(SUM(账户期初本位)+SUMIFS(流水本位,流水日期,"<="&EOMONTH(DATE(管理年度,9,1),0)),2) -> 11921240 | H14: =IF(ROUND($E14-$F14,2)=0,"","内部转账净额 "&TEXT($E14-$F14,"#,##0.00")&"，是换汇价差")
A15: =DATE(管理年度,10,1) -> 46296 | B15: =ROUND(SUMIFS(流水本位,流水日期,">="&DATE(管理年度,10,1),流水日期,"<="&EOMONTH(DATE(管理年度,10,1),0),流水属性,"<>内部转账",流水本位,">0"),2) -> 0 | C15: =-ROUND(SUMIFS(流水本位,流水日期,">="&DATE(管理年度,10,1),流水日期,"<="&EOMONTH(DATE(管理年度,10,1),0),流水属性,"<>内部转账",流水本位,"<0"),2) -> 0 | D15: =ROUND($B15-$C15,2) -> 0 | E15: =ROUND(SUMIFS(流水本位,流水日期,">="&DATE(管理年度,10,1),流水日期,"<="&EOMONTH(DATE(管理年度,10,1),0),流水属性,"内部转账",流水本位,">0"),2) -> 0 | F15: =-ROUND(SUMIFS(流水本位,流水日期,">="&DATE(管理年度,10,1),流水日期,"<="&EOMONTH(DATE(管理年度,10,1),0),流水属性,"内部转账",流水本位,"<0"),2) -> 0 | G15: =ROUND(SUM(账户期初本位)+SUMIFS(流水本位,流水日期,"<="&EOMONTH(DATE(管理年度,10,1),0)),2) -> 11921240 | H15: =IF(ROUND($E15-$F15,2)=0,"","内部转账净额 "&TEXT($E15-$F15,"#,##0.00")&"，是换汇价差")
A16: =DATE(管理年度,11,1) -> 46327 | B16: =ROUND(SUMIFS(流水本位,流水日期,">="&DATE(管理年度,11,1),流水日期,"<="&EOMONTH(DATE(管理年度,11,1),0),流水属性,"<>内部转账",流水本位,">0"),2) -> 0 | C16: =-ROUND(SUMIFS(流水本位,流水日期,">="&DATE(管理年度,11,1),流水日期,"<="&EOMONTH(DATE(管理年度,11,1),0),流水属性,"<>内部转账",流水本位,"<0"),2) -> 0 | D16: =ROUND($B16-$C16,2) -> 0 | E16: =ROUND(SUMIFS(流水本位,流水日期,">="&DATE(管理年度,11,1),流水日期,"<="&EOMONTH(DATE(管理年度,11,1),0),流水属性,"内部转账",流水本位,">0"),2) -> 0 | F16: =-ROUND(SUMIFS(流水本位,流水日期,">="&DATE(管理年度,11,1),流水日期,"<="&EOMONTH(DATE(管理年度,11,1),0),流水属性,"内部转账",流水本位,"<0"),2) -> 0 | G16: =ROUND(SUM(账户期初本位)+SUMIFS(流水本位,流水日期,"<="&EOMONTH(DATE(管理年度,11,1),0)),2) -> 11921240 | H16: =IF(ROUND($E16-$F16,2)=0,"","内部转账净额 "&TEXT($E16-$F16,"#,##0.00")&"，是换汇价差")
A17: =DATE(管理年度,12,1) -> 46357 | B17: =ROUND(SUMIFS(流水本位,流水日期,">="&DATE(管理年度,12,1),流水日期,"<="&EOMONTH(DATE(管理年度,12,1),0),流水属性,"<>内部转账",流水本位,">0"),2) -> 0 | C17: =-ROUND(SUMIFS(流水本位,流水日期,">="&DATE(管理年度,12,1),流水日期,"<="&EOMONTH(DATE(管理年度,12,1),0),流水属性,"<>内部转账",流水本位,"<0"),2) -> 0 | D17: =ROUND($B17-$C17,2) -> 0 | E17: =ROUND(SUMIFS(流水本位,流水日期,">="&DATE(管理年度,12,1),流水日期,"<="&EOMONTH(DATE(管理年度,12,1),0),流水属性,"内部转账",流水本位,">0"),2) -> 0 | F17: =-ROUND(SUMIFS(流水本位,流水日期,">="&DATE(管理年度,12,1),流水日期,"<="&EOMONTH(DATE(管理年度,12,1),0),流水属性,"内部转账",流水本位,"<0"),2) -> 0 | G17: =ROUND(SUM(账户期初本位)+SUMIFS(流水本位,流水日期,"<="&EOMONTH(DATE(管理年度,12,1),0)),2) -> 11921240 | H17: =IF(ROUND($E17-$F17,2)=0,"","内部转账净额 "&TEXT($E17-$F17,"#,##0.00")&"，是换汇价差")
A18: 全年合计 | B18: =ROUND(SUM(B6:B17),2) -> 892660 | C18: =ROUND(SUM(C6:C17),2) -> 163720 | D18: =ROUND(SUM(D6:D17),2) -> 728940 | E18: =ROUND(SUM(E6:E17),2) -> 193400 | F18: =ROUND(SUM(F6:F17),2) -> 193400 | G18: =G17 -> 11921240 | H18: 年末资金总额 = 12 月那一行
A20: 二、报表月份 · 各账户（报表月份在【参数设置】B6 改）
A21: 账户名称 | B21: 币种 | C21: 月初余额(原币) | D21: 本月收入(原币) | E21: 本月支出(原币) | F21: 月末余额(原币) | G21: 本月收入(人民币) | H21: 本月支出(人民币) | I21: 月末余额(人民币账面)
A22: =IF(参数设置!$C$11="","",参数设置!$C$11) -> 工商银行基本户-8888 | B22: =IF($A22="","",参数设置!$E$11) -> CNY | C22: =IF($A22="","",ROUND(N(参数设置!$G$11)+SUMIFS(流水净额,流水账户,$A22,流水日期,"<"&报表月份),2)) -> 500000 | D22: =IF($A22="","",ROUND(SUMIFS(流水收入,流水账户,$A22,流水日期,">="&报表月份,流水日期,"<="&EOMONTH(报表月份,0)),2)) -> 298400 | E22: =IF($A22="","",ROUND(SUMIFS(流水支出,流水账户,$A22,流水日期,">="&报表月份,流水日期,"<="&EOMONTH(报表月份,0)),2)) -> 68000 | F22: =IF($A22="","",ROUND($C22+$D22-$E22,2)) -> 730400 | G22: =IF($A22="","",ROUND(SUMIFS(流水本位,流水账户,$A22,流水日期,">="&报表月份,流水日期,"<="&EOMONTH(报表月份,0),流水本位,">0"),2)) -> 298400 | H22: =IF($A22="","",-ROUND(SUMIFS(流水本位,流水账户,$A22,流水日期,">="&报表月份,流水日期,"<="&EOMONTH(报表月份,0),流水本位,"<0"),2)) -> 68000 | I22: =IF($A22="","",IFERROR(ROUND(参数设置!$I$11+SUMIFS(流水本位,流水账户,$A22,流水日期,"<="&EOMONTH(报表月份,0)),2),"")) -> 730400
A23: =IF(参数设置!$C$12="","",参数设置!$C$12) -> 中国银行美元结算户-6688 | B23: =IF($A23="","",参数设置!$E$12) -> USD | C23: =IF($A23="","",ROUND(N(参数设置!$G$12)+SUMIFS(流水净额,流水账户,$A23,流水日期,"<"&报表月份),2)) -> 800000 | D23: =IF($A23="","",ROUND(SUMIFS(流水收入,流水账户,$A23,流水日期,">="&报表月份,流水日期,"<="&EOMONTH(报表月份,0)),2)) -> 40000 | E23: =IF($A23="","",ROUND(SUMIFS(流水支出,流水账户,$A23,流水日期,">="&报表月份,流水日期,"<="&EOMONTH(报表月份,0)),2)) -> 28000 | F23: =IF($A23="","",ROUND($C23+$D23-$E23,2)) -> 812000 | G23: =IF($A23="","",ROUND(SUMIFS(流水本位,流水账户,$A23,流水日期,">="&报表月份,流水日期,"<="&EOMONTH(报表月份,0),流水本位,">0"),2)) -> 287200 | H23: =IF($A23="","",-ROUND(SUMIFS(流水本位,流水账户,$A23,流水日期,">="&报表月份,流水日期,"<="&EOMONTH(报表月份,0),流水本位,"<0"),2)) -> 200680 | I23: =IF($A23="","",IFERROR(ROUND(参数设置!$I$12+SUMIFS(流水本位,流水账户,$A23,流水日期,"<="&EOMONTH(报表月份,0)),2),"")) -> 5806520
A24: =IF(参数设置!$C$13="","",参数设置!$C$13) -> 汇丰银行港币结算户-5566 | B24: =IF($A24="","",参数设置!$E$13) -> HKD | C24: =IF($A24="","",ROUND(N(参数设置!$G$13)+SUMIFS(流水净额,流水账户,$A24,流水日期,"<"&报表月份),2)) -> 300000 | D24: =IF($A24="","",ROUND(SUMIFS(流水收入,流水账户,$A24,流水日期,">="&报表月份,流水日期,"<="&EOMONTH(报表月份,0)),2)) -> 80000 | E24: =IF($A24="","",ROUND(SUMIFS(流水支出,流水账户,$A24,流水日期,">="&报表月份,流水日期,"<="&EOMONTH(报表月份,0)),2)) -> 24500 | F24: =IF($A24="","",ROUND($C24+$D24-$E24,2)) -> 355500 | G24: =IF($A24="","",ROUND(SUMIFS(流水本位,流水账户,$A24,流水日期,">="&报表月份,流水日期,"<="&EOMONTH(报表月份,0),流水本位,">0"),2)) -> 73600 | H24: =IF($A24="","",-ROUND(SUMIFS(流水本位,流水账户,$A24,流水日期,">="&报表月份,流水日期,"<="&EOMONTH(报表月份,0),流水本位,"<0"),2)) -> 22540 | I24: =IF($A24="","",IFERROR(ROUND(参数设置!$I$13+SUMIFS(流水本位,流水账户,$A24,流水日期,"<="&EOMONTH(报表月份,0)),2),"")) -> 325560
A25: =IF(参数设置!$C$14="","",参数设置!$C$14) -> 招商银行一般户-2388 | B25: =IF($A25="","",参数设置!$E$14) -> CNY | C25: =IF($A25="","",ROUND(N(参数设置!$G$14)+SUMIFS(流水净额,流水账户,$A25,流水日期,"<"&报表月份),2)) -> 200000 | D25: =IF($A25="","",ROUND(SUMIFS(流水收入,流水账户,$A25,流水日期,">="&报表月份,流水日期,"<="&EOMONTH(报表月份,0)),2)) -> 110000 | E25: =IF($A25="","",ROUND(SUMIFS(流水支出,流水账户,$A25,流水日期,">="&报表月份,流水日期,"<="&EOMONTH(报表月份,0)),2)) -> 30000 | F25: =IF($A25="","",ROUND($C25+$D25-$E25,2)) -> 280000 | G25: =IF($A25="","",ROUND(SUMIFS(流水本位,流水账户,$A25,流水日期,">="&报表月份,流水日期,"<="&EOMONTH(报表月份,0),流水本位,">0"),2)) -> 110000 | H25: =IF($A25="","",-ROUND(SUMIFS(流水本位,流水账户,$A25,流水日期,">="&报表月份,流水日期,"<="&EOMONTH(报表月份,0),流水本位,"<0"),2)) -> 30000 | I25: =IF($A25="","",IFERROR(ROUND(参数设置!$I$14+SUMIFS(流水本位,流水账户,$A25,流水日期,"<="&EOMONTH(报表月份,0)),2),"")) -> 280000
A26: =IF(参数设置!$C$15="","",参数设置!$C$15) -> 汇丰银行美元结算户-7788 | B26: =IF($A26="","",参数设置!$E$15) -> USD | C26: =IF($A26="","",ROUND(N(参数设置!$G$15)+SUMIFS(流水净额,流水账户,$A26,流水日期,"<"&报表月份),2)) -> 500000 | D26: =IF($A26="","",ROUND(SUMIFS(流水收入,流水账户,$A26,流水日期,">="&报表月份,流水日期,"<="&EOMONTH(报表月份,0)),2)) -> 12000 | E26: =IF($A26="","",ROUND(SUMIFS(流水支出,流水账户,$A26,流水日期,">="&报表月份,流水日期,"<="&EOMONTH(报表月份,0)),2)) -> 5000 | F26: =IF($A26="","",ROUND($C26+$D26-$E26,2)) -> 507000 | G26: =IF($A26="","",ROUND(SUMIFS(流水本位,流水账户,$A26,流水日期,">="&报表月份,流水日期,"<="&EOMONTH(报表月份,0),流水本位,">0"),2)) -> 86160 | H26: =IF($A26="","",-ROUND(SUMIFS(流水本位,流水账户,$A26,流水日期,">="&报表月份,流水日期,"<="&EOMONTH(报表月份,0),流水本位,"<0"),2)) -> 35900 | I26: =IF($A26="","",IFERROR(ROUND(参数设置!$I$15+SUMIFS(流水本位,流水账户,$A26,流水日期,"<="&EOMONTH(报表月份,0)),2),"")) -> 3625260
A27: =IF(参数设置!$C$16="","",参数设置!$C$16) -> 中国银行欧元结算户-9900 | B27: =IF($A27="","",参数设置!$E$16) -> EUR | C27: =IF($A27="","",ROUND(N(参数设置!$G$16)+SUMIFS(流水净额,流水账户,$A27,流水日期,"<"&报表月份),2)) -> 120000 | D27: =IF($A27="","",ROUND(SUMIFS(流水收入,流水账户,$A27,流水日期,">="&报表月份,流水日期,"<="&EOMONTH(报表月份,0)),2)) -> 30000 | E27: =IF($A27="","",ROUND(SUMIFS(流水支出,流水账户,$A27,流水日期,">="&报表月份,流水日期,"<="&EOMONTH(报表月份,0)),2)) -> 0 | F27: =IF($A27="","",ROUND($C27+$D27-$E27,2)) -> 150000 | G27: =IF($A27="","",ROUND(SUMIFS(流水本位,流水账户,$A27,流水日期,">="&报表月份,流水日期,"<="&EOMONTH(报表月份,0),流水本位,">0"),2)) -> 230700 | H27: =IF($A27="","",-ROUND(SUMIFS(流水本位,流水账户,$A27,流水日期,">="&报表月份,流水日期,"<="&EOMONTH(报表月份,0),流水本位,"<0"),2)) -> 0 | I27: =IF($A27="","",IFERROR(ROUND(参数设置!$I$16+SUMIFS(流水本位,流水账户,$A27,流水日期,"<="&EOMONTH(报表月份,0)),2),"")) -> 1153500
A28: =IF(参数设置!$C$17="","",参数设置!$C$17) | B28: =IF($A28="","",参数设置!$E$17) | C28: =IF($A28="","",ROUND(N(参数设置!$G$17)+SUMIFS(流水净额,流水账户,$A28,流水日期,"<"&报表月份),2)) | D28: =IF($A28="","",ROUND(SUMIFS(流水收入,流水账户,$A28,流水日期,">="&报表月份,流水日期,"<="&EOMONTH(报表月份,0)),2)) | E28: =IF($A28="","",ROUND(SUMIFS(流水支出,流水账户,$A28,流水日期,">="&报表月份,流水日期,"<="&EOMONTH(报表月份,0)),2)) | F28: =IF($A28="","",ROUND($C28+$D28-$E28,2)) | G28: =IF($A28="","",ROUND(SUMIFS(流水本位,流水账户,$A28,流水日期,">="&报表月份,流水日期,"<="&EOMONTH(报表月份,0),流水本位,">0"),2)) | H28: =IF($A28="","",-ROUND(SUMIFS(流水本位,流水账户,$A28,流水日期,">="&报表月份,流水日期,"<="&EOMONTH(报表月份,0),流水本位,"<0"),2)) | I28: =IF($A28="","",IFERROR(ROUND(参数设置!$I$17+SUMIFS(流水本位,流水账户,$A28,流水日期,"<="&EOMONTH(报表月份,0)),2),""))
A29: =IF(参数设置!$C$18="","",参数设置!$C$18) | B29: =IF($A29="","",参数设置!$E$18) | C29: =IF($A29="","",ROUND(N(参数设置!$G$18)+SUMIFS(流水净额,流水账户,$A29,流水日期,"<"&报表月份),2)) | D29: =IF($A29="","",ROUND(SUMIFS(流水收入,流水账户,$A29,流水日期,">="&报表月份,流水日期,"<="&EOMONTH(报表月份,0)),2)) | E29: =IF($A29="","",ROUND(SUMIFS(流水支出,流水账户,$A29,流水日期,">="&报表月份,流水日期,"<="&EOMONTH(报表月份,0)),2)) | F29: =IF($A29="","",ROUND($C29+$D29-$E29,2)) | G29: =IF($A29="","",ROUND(SUMIFS(流水本位,流水账户,$A29,流水日期,">="&报表月份,流水日期,"<="&EOMONTH(报表月份,0),流水本位,">0"),2)) | H29: =IF($A29="","",-ROUND(SUMIFS(流水本位,流水账户,$A29,流水日期,">="&报表月份,流水日期,"<="&EOMONTH(报表月份,0),流水本位,"<0"),2)) | I29: =IF($A29="","",IFERROR(ROUND(参数设置!$I$18+SUMIFS(流水本位,流水账户,$A29,流水日期,"<="&EOMONTH(报表月份,0)),2),""))
A30: =IF(参数设置!$C$19="","",参数设置!$C$19) | B30: =IF($A30="","",参数设置!$E$19) | C30: =IF($A30="","",ROUND(N(参数设置!$G$19)+SUMIFS(流水净额,流水账户,$A30,流水日期,"<"&报表月份),2)) | D30: =IF($A30="","",ROUND(SUMIFS(流水收入,流水账户,$A30,流水日期,">="&报表月份,流水日期,"<="&EOMONTH(报表月份,0)),2)) | E30: =IF($A30="","",ROUND(SUMIFS(流水支出,流水账户,$A30,流水日期,">="&报表月份,流水日期,"<="&EOMONTH(报表月份,0)),2)) | F30: =IF($A30="","",ROUND($C30+$D30-$E30,2)) | G30: =IF($A30="","",ROUND(SUMIFS(流水本位,流水账户,$A30,流水日期,">="&报表月份,流水日期,"<="&EOMONTH(报表月份,0),流水本位,">0"),2)) | H30: =IF($A30="","",-ROUND(SUMIFS(流水本位,流水账户,$A30,流水日期,">="&报表月份,流水日期,"<="&EOMONTH(报表月份,0),流水本位,"<0"),2)) | I30: =IF($A30="","",IFERROR(ROUND(参数设置!$I$19+SUMIFS(流水本位,流水账户,$A30,流水日期,"<="&EOMONTH(报表月份,0)),2),""))
A31: =IF(参数设置!$C$20="","",参数设置!$C$20) | B31: =IF($A31="","",参数设置!$E$20) | C31: =IF($A31="","",ROUND(N(参数设置!$G$20)+SUMIFS(流水净额,流水账户,$A31,流水日期,"<"&报表月份),2)) | D31: =IF($A31="","",ROUND(SUMIFS(流水收入,流水账户,$A31,流水日期,">="&报表月份,流水日期,"<="&EOMONTH(报表月份,0)),2)) | E31: =IF($A31="","",ROUND(SUMIFS(流水支出,流水账户,$A31,流水日期,">="&报表月份,流水日期,"<="&EOMONTH(报表月份,0)),2)) | F31: =IF($A31="","",ROUND($C31+$D31-$E31,2)) | G31: =IF($A31="","",ROUND(SUMIFS(流水本位,流水账户,$A31,流水日期,">="&报表月份,流水日期,"<="&EOMONTH(报表月份,0),流水本位,">0"),2)) | H31: =IF($A31="","",-ROUND(SUMIFS(流水本位,流水账户,$A31,流水日期,">="&报表月份,流水日期,"<="&EOMONTH(报表月份,0),流水本位,"<0"),2)) | I31: =IF($A31="","",IFERROR(ROUND(参数设置!$I$20+SUMIFS(流水本位,流水账户,$A31,流水日期,"<="&EOMONTH(报表月份,0)),2),""))
A32: =IF(参数设置!$C$21="","",参数设置!$C$21) | B32: =IF($A32="","",参数设置!$E$21) | C32: =IF($A32="","",ROUND(N(参数设置!$G$21)+SUMIFS(流水净额,流水账户,$A32,流水日期,"<"&报表月份),2)) | D32: =IF($A32="","",ROUND(SUMIFS(流水收入,流水账户,$A32,流水日期,">="&报表月份,流水日期,"<="&EOMONTH(报表月份,0)),2)) | E32: =IF($A32="","",ROUND(SUMIFS(流水支出,流水账户,$A32,流水日期,">="&报表月份,流水日期,"<="&EOMONTH(报表月份,0)),2)) | F32: =IF($A32="","",ROUND($C32+$D32-$E32,2)) | G32: =IF($A32="","",ROUND(SUMIFS(流水本位,流水账户,$A32,流水日期,">="&报表月份,流水日期,"<="&EOMONTH(报表月份,0),流水本位,">0"),2)) | H32: =IF($A32="","",-ROUND(SUMIFS(流水本位,流水账户,$A32,流水日期,">="&报表月份,流水日期,"<="&EOMONTH(报表月份,0),流水本位,"<0"),2)) | I32: =IF($A32="","",IFERROR(ROUND(参数设置!$I$21+SUMIFS(流水本位,流水账户,$A32,流水日期,"<="&EOMONTH(报表月份,0)),2),""))
A33: =IF(参数设置!$C$22="","",参数设置!$C$22) | B33: =IF($A33="","",参数设置!$E$22) | C33: =IF($A33="","",ROUND(N(参数设置!$G$22)+SUMIFS(流水净额,流水账户,$A33,流水日期,"<"&报表月份),2)) | D33: =IF($A33="","",ROUND(SUMIFS(流水收入,流水账户,$A33,流水日期,">="&报表月份,流水日期,"<="&EOMONTH(报表月份,0)),2)) | E33: =IF($A33="","",ROUND(SUMIFS(流水支出,流水账户,$A33,流水日期,">="&报表月份,流水日期,"<="&EOMONTH(报表月份,0)),2)) | F33: =IF($A33="","",ROUND($C33+$D33-$E33,2)) | G33: =IF($A33="","",ROUND(SUMIFS(流水本位,流水账户,$A33,流水日期,">="&报表月份,流水日期,"<="&EOMONTH(报表月份,0),流水本位,">0"),2)) | H33: =IF($A33="","",-ROUND(SUMIFS(流水本位,流水账户,$A33,流水日期,">="&报表月份,流水日期,"<="&EOMONTH(报表月份,0),流水本位,"<0"),2)) | I33: =IF($A33="","",IFERROR(ROUND(参数设置!$I$22+SUMIFS(流水本位,流水账户,$A33,流水日期,"<="&EOMONTH(报表月份,0)),2),""))
A34: =IF(参数设置!$C$23="","",参数设置!$C$23) | B34: =IF($A34="","",参数设置!$E$23) | C34: =IF($A34="","",ROUND(N(参数设置!$G$23)+SUMIFS(流水净额,流水账户,$A34,流水日期,"<"&报表月份),2)) | D34: =IF($A34="","",ROUND(SUMIFS(流水收入,流水账户,$A34,流水日期,">="&报表月份,流水日期,"<="&EOMONTH(报表月份,0)),2)) | E34: =IF($A34="","",ROUND(SUMIFS(流水支出,流水账户,$A34,流水日期,">="&报表月份,流水日期,"<="&EOMONTH(报表月份,0)),2)) | F34: =IF($A34="","",ROUND($C34+$D34-$E34,2)) | G34: =IF($A34="","",ROUND(SUMIFS(流水本位,流水账户,$A34,流水日期,">="&报表月份,流水日期,"<="&EOMONTH(报表月份,0),流水本位,">0"),2)) | H34: =IF($A34="","",-ROUND(SUMIFS(流水本位,流水账户,$A34,流水日期,">="&报表月份,流水日期,"<="&EOMONTH(报表月份,0),流水本位,"<0"),2)) | I34: =IF($A34="","",IFERROR(ROUND(参数设置!$I$23+SUMIFS(流水本位,流水账户,$A34,流水日期,"<="&EOMONTH(报表月份,0)),2),""))
A35: =IF(参数设置!$C$24="","",参数设置!$C$24) | B35: =IF($A35="","",参数设置!$E$24) | C35: =IF($A35="","",ROUND(N(参数设置!$G$24)+SUMIFS(流水净额,流水账户,$A35,流水日期,"<"&报表月份),2)) | D35: =IF($A35="","",ROUND(SUMIFS(流水收入,流水账户,$A35,流水日期,">="&报表月份,流水日期,"<="&EOMONTH(报表月份,0)),2)) | E35: =IF($A35="","",ROUND(SUMIFS(流水支出,流水账户,$A35,流水日期,">="&报表月份,流水日期,"<="&EOMONTH(报表月份,0)),2)) | F35: =IF($A35="","",ROUND($C35+$D35-$E35,2)) | G35: =IF($A35="","",ROUND(SUMIFS(流水本位,流水账户,$A35,流水日期,">="&报表月份,流水日期,"<="&EOMONTH(报表月份,0),流水本位,">0"),2)) | H35: =IF($A35="","",-ROUND(SUMIFS(流水本位,流水账户,$A35,流水日期,">="&报表月份,流水日期,"<="&EOMONTH(报表月份,0),流水本位,"<0"),2)) | I35: =IF($A35="","",IFERROR(ROUND(参数设置!$I$24+SUMIFS(流水本位,流水账户,$A35,流水日期,"<="&EOMONTH(报表月份,0)),2),""))
A36: =IF(参数设置!$C$25="","",参数设置!$C$25) | B36: =IF($A36="","",参数设置!$E$25) | C36: =IF($A36="","",ROUND(N(参数设置!$G$25)+SUMIFS(流水净额,流水账户,$A36,流水日期,"<"&报表月份),2)) | D36: =IF($A36="","",ROUND(SUMIFS(流水收入,流水账户,$A36,流水日期,">="&报表月份,流水日期,"<="&EOMONTH(报表月份,0)),2)) | E36: =IF($A36="","",ROUND(SUMIFS(流水支出,流水账户,$A36,流水日期,">="&报表月份,流水日期,"<="&EOMONTH(报表月份,0)),2)) | F36: =IF($A36="","",ROUND($C36+$D36-$E36,2)) | G36: =IF($A36="","",ROUND(SUMIFS(流水本位,流水账户,$A36,流水日期,">="&报表月份,流水日期,"<="&EOMONTH(报表月份,0),流水本位,">0"),2)) | H36: =IF($A36="","",-ROUND(SUMIFS(流水本位,流水账户,$A36,流水日期,">="&报表月份,流水日期,"<="&EOMONTH(报表月份,0),流水本位,"<0"),2)) | I36: =IF($A36="","",IFERROR(ROUND(参数设置!$I$25+SUMIFS(流水本位,流水账户,$A36,流水日期,"<="&EOMONTH(报表月份,0)),2),""))
A37: =IF(参数设置!$C$26="","",参数设置!$C$26) | B37: =IF($A37="","",参数设置!$E$26) | C37: =IF($A37="","",ROUND(N(参数设置!$G$26)+SUMIFS(流水净额,流水账户,$A37,流水日期,"<"&报表月份),2)) | D37: =IF($A37="","",ROUND(SUMIFS(流水收入,流水账户,$A37,流水日期,">="&报表月份,流水日期,"<="&EOMONTH(报表月份,0)),2)) | E37: =IF($A37="","",ROUND(SUMIFS(流水支出,流水账户,$A37,流水日期,">="&报表月份,流水日期,"<="&EOMONTH(报表月份,0)),2)) | F37: =IF($A37="","",ROUND($C37+$D37-$E37,2)) | G37: =IF($A37="","",ROUND(SUMIFS(流水本位,流水账户,$A37,流水日期,">="&报表月份,流水日期,"<="&EOMONTH(报表月份,0),流水本位,">0"),2)) | H37: =IF($A37="","",-ROUND(SUMIFS(流水本位,流水账户,$A37,流水日期,">="&报表月份,流水日期,"<="&EOMONTH(报表月份,0),流水本位,"<0"),2)) | I37: =IF($A37="","",IFERROR(ROUND(参数设置!$I$26+SUMIFS(流水本位,流水账户,$A37,流水日期,"<="&EOMONTH(报表月份,0)),2),""))
A38: =IF(参数设置!$C$27="","",参数设置!$C$27) | B38: =IF($A38="","",参数设置!$E$27) | C38: =IF($A38="","",ROUND(N(参数设置!$G$27)+SUMIFS(流水净额,流水账户,$A38,流水日期,"<"&报表月份),2)) | D38: =IF($A38="","",ROUND(SUMIFS(流水收入,流水账户,$A38,流水日期,">="&报表月份,流水日期,"<="&EOMONTH(报表月份,0)),2)) | E38: =IF($A38="","",ROUND(SUMIFS(流水支出,流水账户,$A38,流水日期,">="&报表月份,流水日期,"<="&EOMONTH(报表月份,0)),2)) | F38: =IF($A38="","",ROUND($C38+$D38-$E38,2)) | G38: =IF($A38="","",ROUND(SUMIFS(流水本位,流水账户,$A38,流水日期,">="&报表月份,流水日期,"<="&EOMONTH(报表月份,0),流水本位,">0"),2)) | H38: =IF($A38="","",-ROUND(SUMIFS(流水本位,流水账户,$A38,流水日期,">="&报表月份,流水日期,"<="&EOMONTH(报表月份,0),流水本位,"<0"),2)) | I38: =IF($A38="","",IFERROR(ROUND(参数设置!$I$27+SUMIFS(流水本位,流水账户,$A38,流水日期,"<="&EOMONTH(报表月份,0)),2),""))
A39: =IF(参数设置!$C$28="","",参数设置!$C$28) | B39: =IF($A39="","",参数设置!$E$28) | C39: =IF($A39="","",ROUND(N(参数设置!$G$28)+SUMIFS(流水净额,流水账户,$A39,流水日期,"<"&报表月份),2)) | D39: =IF($A39="","",ROUND(SUMIFS(流水收入,流水账户,$A39,流水日期,">="&报表月份,流水日期,"<="&EOMONTH(报表月份,0)),2)) | E39: =IF($A39="","",ROUND(SUMIFS(流水支出,流水账户,$A39,流水日期,">="&报表月份,流水日期,"<="&EOMONTH(报表月份,0)),2)) | F39: =IF($A39="","",ROUND($C39+$D39-$E39,2)) | G39: =IF($A39="","",ROUND(SUMIFS(流水本位,流水账户,$A39,流水日期,">="&报表月份,流水日期,"<="&EOMONTH(报表月份,0),流水本位,">0"),2)) | H39: =IF($A39="","",-ROUND(SUMIFS(流水本位,流水账户,$A39,流水日期,">="&报表月份,流水日期,"<="&EOMONTH(报表月份,0),流水本位,"<0"),2)) | I39: =IF($A39="","",IFERROR(ROUND(参数设置!$I$28+SUMIFS(流水本位,流水账户,$A39,流水日期,"<="&EOMONTH(报表月份,0)),2),""))
A40: =IF(参数设置!$C$29="","",参数设置!$C$29) | B40: =IF($A40="","",参数设置!$E$29) | C40: =IF($A40="","",ROUND(N(参数设置!$G$29)+SUMIFS(流水净额,流水账户,$A40,流水日期,"<"&报表月份),2)) | D40: =IF($A40="","",ROUND(SUMIFS(流水收入,流水账户,$A40,流水日期,">="&报表月份,流水日期,"<="&EOMONTH(报表月份,0)),2)) | E40: =IF($A40="","",ROUND(SUMIFS(流水支出,流水账户,$A40,流水日期,">="&报表月份,流水日期,"<="&EOMONTH(报表月份,0)),2)) | F40: =IF($A40="","",ROUND($C40+$D40-$E40,2)) | G40: =IF($A40="","",ROUND(SUMIFS(流水本位,流水账户,$A40,流水日期,">="&报表月份,流水日期,"<="&EOMONTH(报表月份,0),流水本位,">0"),2)) | H40: =IF($A40="","",-ROUND(SUMIFS(流水本位,流水账户,$A40,流水日期,">="&报表月份,流水日期,"<="&EOMONTH(报表月份,0),流水本位,"<0"),2)) | I40: =IF($A40="","",IFERROR(ROUND(参数设置!$I$29+SUMIFS(流水本位,流水账户,$A40,流水日期,"<="&EOMONTH(报表月份,0)),2),""))
A41: =IF(参数设置!$C$30="","",参数设置!$C$30) | B41: =IF($A41="","",参数设置!$E$30) | C41: =IF($A41="","",ROUND(N(参数设置!$G$30)+SUMIFS(流水净额,流水账户,$A41,流水日期,"<"&报表月份),2)) | D41: =IF($A41="","",ROUND(SUMIFS(流水收入,流水账户,$A41,流水日期,">="&报表月份,流水日期,"<="&EOMONTH(报表月份,0)),2)) | E41: =IF($A41="","",ROUND(SUMIFS(流水支出,流水账户,$A41,流水日期,">="&报表月份,流水日期,"<="&EOMONTH(报表月份,0)),2)) | F41: =IF($A41="","",ROUND($C41+$D41-$E41,2)) | G41: =IF($A41="","",ROUND(SUMIFS(流水本位,流水账户,$A41,流水日期,">="&报表月份,流水日期,"<="&EOMONTH(报表月份,0),流水本位,">0"),2)) | H41: =IF($A41="","",-ROUND(SUMIFS(流水本位,流水账户,$A41,流水日期,">="&报表月份,流水日期,"<="&EOMONTH(报表月份,0),流水本位,"<0"),2)) | I41: =IF($A41="","",IFERROR(ROUND(参数设置!$I$30+SUMIFS(流水本位,流水账户,$A41,流水日期,"<="&EOMONTH(报表月份,0)),2),""))
A42: =IF(参数设置!$C$31="","",参数设置!$C$31) | B42: =IF($A42="","",参数设置!$E$31) | C42: =IF($A42="","",ROUND(N(参数设置!$G$31)+SUMIFS(流水净额,流水账户,$A42,流水日期,"<"&报表月份),2)) | D42: =IF($A42="","",ROUND(SUMIFS(流水收入,流水账户,$A42,流水日期,">="&报表月份,流水日期,"<="&EOMONTH(报表月份,0)),2)) | E42: =IF($A42="","",ROUND(SUMIFS(流水支出,流水账户,$A42,流水日期,">="&报表月份,流水日期,"<="&EOMONTH(报表月份,0)),2)) | F42: =IF($A42="","",ROUND($C42+$D42-$E42,2)) | G42: =IF($A42="","",ROUND(SUMIFS(流水本位,流水账户,$A42,流水日期,">="&报表月份,流水日期,"<="&EOMONTH(报表月份,0),流水本位,">0"),2)) | H42: =IF($A42="","",-ROUND(SUMIFS(流水本位,流水账户,$A42,流水日期,">="&报表月份,流水日期,"<="&EOMONTH(报表月份,0),流水本位,"<0"),2)) | I42: =IF($A42="","",IFERROR(ROUND(参数设置!$I$31+SUMIFS(流水本位,流水账户,$A42,流水日期,"<="&EOMONTH(报表月份,0)),2),""))
A43: =IF(参数设置!$C$32="","",参数设置!$C$32) | B43: =IF($A43="","",参数设置!$E$32) | C43: =IF($A43="","",ROUND(N(参数设置!$G$32)+SUMIFS(流水净额,流水账户,$A43,流水日期,"<"&报表月份),2)) | D43: =IF($A43="","",ROUND(SUMIFS(流水收入,流水账户,$A43,流水日期,">="&报表月份,流水日期,"<="&EOMONTH(报表月份,0)),2)) | E43: =IF($A43="","",ROUND(SUMIFS(流水支出,流水账户,$A43,流水日期,">="&报表月份,流水日期,"<="&EOMONTH(报表月份,0)),2)) | F43: =IF($A43="","",ROUND($C43+$D43-$E43,2)) | G43: =IF($A43="","",ROUND(SUMIFS(流水本位,流水账户,$A43,流水日期,">="&报表月份,流水日期,"<="&EOMONTH(报表月份,0),流水本位,">0"),2)) | H43: =IF($A43="","",-ROUND(SUMIFS(流水本位,流水账户,$A43,流水日期,">="&报表月份,流水日期,"<="&EOMONTH(报表月份,0),流水本位,"<0"),2)) | I43: =IF($A43="","",IFERROR(ROUND(参数设置!$I$32+SUMIFS(流水本位,流水账户,$A43,流水日期,"<="&EOMONTH(报表月份,0)),2),""))
A44: =IF(参数设置!$C$33="","",参数设置!$C$33) | B44: =IF($A44="","",参数设置!$E$33) | C44: =IF($A44="","",ROUND(N(参数设置!$G$33)+SUMIFS(流水净额,流水账户,$A44,流水日期,"<"&报表月份),2)) | D44: =IF($A44="","",ROUND(SUMIFS(流水收入,流水账户,$A44,流水日期,">="&报表月份,流水日期,"<="&EOMONTH(报表月份,0)),2)) | E44: =IF($A44="","",ROUND(SUMIFS(流水支出,流水账户,$A44,流水日期,">="&报表月份,流水日期,"<="&EOMONTH(报表月份,0)),2)) | F44: =IF($A44="","",ROUND($C44+$D44-$E44,2)) | G44: =IF($A44="","",ROUND(SUMIFS(流水本位,流水账户,$A44,流水日期,">="&报表月份,流水日期,"<="&EOMONTH(报表月份,0),流水本位,">0"),2)) | H44: =IF($A44="","",-ROUND(SUMIFS(流水本位,流水账户,$A44,流水日期,">="&报表月份,流水日期,"<="&EOMONTH(报表月份,0),流水本位,"<0"),2)) | I44: =IF($A44="","",IFERROR(ROUND(参数设置!$I$33+SUMIFS(流水本位,流水账户,$A44,流水日期,"<="&EOMONTH(报表月份,0)),2),""))
A45: =IF(参数设置!$C$34="","",参数设置!$C$34) | B45: =IF($A45="","",参数设置!$E$34) | C45: =IF($A45="","",ROUND(N(参数设置!$G$34)+SUMIFS(流水净额,流水账户,$A45,流水日期,"<"&报表月份),2)) | D45: =IF($A45="","",ROUND(SUMIFS(流水收入,流水账户,$A45,流水日期,">="&报表月份,流水日期,"<="&EOMONTH(报表月份,0)),2)) | E45: =IF($A45="","",ROUND(SUMIFS(流水支出,流水账户,$A45,流水日期,">="&报表月份,流水日期,"<="&EOMONTH(报表月份,0)),2)) | F45: =IF($A45="","",ROUND($C45+$D45-$E45,2)) | G45: =IF($A45="","",ROUND(SUMIFS(流水本位,流水账户,$A45,流水日期,">="&报表月份,流水日期,"<="&EOMONTH(报表月份,0),流水本位,">0"),2)) | H45: =IF($A45="","",-ROUND(SUMIFS(流水本位,流水账户,$A45,流水日期,">="&报表月份,流水日期,"<="&EOMONTH(报表月份,0),流水本位,"<0"),2)) | I45: =IF($A45="","",IFERROR(ROUND(参数设置!$I$34+SUMIFS(流水本位,流水账户,$A45,流水日期,"<="&EOMONTH(报表月份,0)),2),""))
A46: =IF(参数设置!$C$35="","",参数设置!$C$35) | B46: =IF($A46="","",参数设置!$E$35) | C46: =IF($A46="","",ROUND(N(参数设置!$G$35)+SUMIFS(流水净额,流水账户,$A46,流水日期,"<"&报表月份),2)) | D46: =IF($A46="","",ROUND(SUMIFS(流水收入,流水账户,$A46,流水日期,">="&报表月份,流水日期,"<="&EOMONTH(报表月份,0)),2)) | E46: =IF($A46="","",ROUND(SUMIFS(流水支出,流水账户,$A46,流水日期,">="&报表月份,流水日期,"<="&EOMONTH(报表月份,0)),2)) | F46: =IF($A46="","",ROUND($C46+$D46-$E46,2)) | G46: =IF($A46="","",ROUND(SUMIFS(流水本位,流水账户,$A46,流水日期,">="&报表月份,流水日期,"<="&EOMONTH(报表月份,0),流水本位,">0"),2)) | H46: =IF($A46="","",-ROUND(SUMIFS(流水本位,流水账户,$A46,流水日期,">="&报表月份,流水日期,"<="&EOMONTH(报表月份,0),流水本位,"<0"),2)) | I46: =IF($A46="","",IFERROR(ROUND(参数设置!$I$35+SUMIFS(流水本位,流水账户,$A46,流水日期,"<="&EOMONTH(报表月份,0)),2),""))
A47: =IF(参数设置!$C$36="","",参数设置!$C$36) | B47: =IF($A47="","",参数设置!$E$36) | C47: =IF($A47="","",ROUND(N(参数设置!$G$36)+SUMIFS(流水净额,流水账户,$A47,流水日期,"<"&报表月份),2)) | D47: =IF($A47="","",ROUND(SUMIFS(流水收入,流水账户,$A47,流水日期,">="&报表月份,流水日期,"<="&EOMONTH(报表月份,0)),2)) | E47: =IF($A47="","",ROUND(SUMIFS(流水支出,流水账户,$A47,流水日期,">="&报表月份,流水日期,"<="&EOMONTH(报表月份,0)),2)) | F47: =IF($A47="","",ROUND($C47+$D47-$E47,2)) | G47: =IF($A47="","",ROUND(SUMIFS(流水本位,流水账户,$A47,流水日期,">="&报表月份,流水日期,"<="&EOMONTH(报表月份,0),流水本位,">0"),2)) | H47: =IF($A47="","",-ROUND(SUMIFS(流水本位,流水账户,$A47,流水日期,">="&报表月份,流水日期,"<="&EOMONTH(报表月份,0),流水本位,"<0"),2)) | I47: =IF($A47="","",IFERROR(ROUND(参数设置!$I$36+SUMIFS(流水本位,流水账户,$A47,流水日期,"<="&EOMONTH(报表月份,0)),2),""))
A48: =IF(参数设置!$C$37="","",参数设置!$C$37) | B48: =IF($A48="","",参数设置!$E$37) | C48: =IF($A48="","",ROUND(N(参数设置!$G$37)+SUMIFS(流水净额,流水账户,$A48,流水日期,"<"&报表月份),2)) | D48: =IF($A48="","",ROUND(SUMIFS(流水收入,流水账户,$A48,流水日期,">="&报表月份,流水日期,"<="&EOMONTH(报表月份,0)),2)) | E48: =IF($A48="","",ROUND(SUMIFS(流水支出,流水账户,$A48,流水日期,">="&报表月份,流水日期,"<="&EOMONTH(报表月份,0)),2)) | F48: =IF($A48="","",ROUND($C48+$D48-$E48,2)) | G48: =IF($A48="","",ROUND(SUMIFS(流水本位,流水账户,$A48,流水日期,">="&报表月份,流水日期,"<="&EOMONTH(报表月份,0),流水本位,">0"),2)) | H48: =IF($A48="","",-ROUND(SUMIFS(流水本位,流水账户,$A48,流水日期,">="&报表月份,流水日期,"<="&EOMONTH(报表月份,0),流水本位,"<0"),2)) | I48: =IF($A48="","",IFERROR(ROUND(参数设置!$I$37+SUMIFS(流水本位,流水账户,$A48,流水日期,"<="&EOMONTH(报表月份,0)),2),""))
A49: =IF(参数设置!$C$38="","",参数设置!$C$38) | B49: =IF($A49="","",参数设置!$E$38) | C49: =IF($A49="","",ROUND(N(参数设置!$G$38)+SUMIFS(流水净额,流水账户,$A49,流水日期,"<"&报表月份),2)) | D49: =IF($A49="","",ROUND(SUMIFS(流水收入,流水账户,$A49,流水日期,">="&报表月份,流水日期,"<="&EOMONTH(报表月份,0)),2)) | E49: =IF($A49="","",ROUND(SUMIFS(流水支出,流水账户,$A49,流水日期,">="&报表月份,流水日期,"<="&EOMONTH(报表月份,0)),2)) | F49: =IF($A49="","",ROUND($C49+$D49-$E49,2)) | G49: =IF($A49="","",ROUND(SUMIFS(流水本位,流水账户,$A49,流水日期,">="&报表月份,流水日期,"<="&EOMONTH(报表月份,0),流水本位,">0"),2)) | H49: =IF($A49="","",-ROUND(SUMIFS(流水本位,流水账户,$A49,流水日期,">="&报表月份,流水日期,"<="&EOMONTH(报表月份,0),流水本位,"<0"),2)) | I49: =IF($A49="","",IFERROR(ROUND(参数设置!$I$38+SUMIFS(流水本位,流水账户,$A49,流水日期,"<="&EOMONTH(报表月份,0)),2),""))
A50: =IF(参数设置!$C$39="","",参数设置!$C$39) | B50: =IF($A50="","",参数设置!$E$39) | C50: =IF($A50="","",ROUND(N(参数设置!$G$39)+SUMIFS(流水净额,流水账户,$A50,流水日期,"<"&报表月份),2)) | D50: =IF($A50="","",ROUND(SUMIFS(流水收入,流水账户,$A50,流水日期,">="&报表月份,流水日期,"<="&EOMONTH(报表月份,0)),2)) | E50: =IF($A50="","",ROUND(SUMIFS(流水支出,流水账户,$A50,流水日期,">="&报表月份,流水日期,"<="&EOMONTH(报表月份,0)),2)) | F50: =IF($A50="","",ROUND($C50+$D50-$E50,2)) | G50: =IF($A50="","",ROUND(SUMIFS(流水本位,流水账户,$A50,流水日期,">="&报表月份,流水日期,"<="&EOMONTH(报表月份,0),流水本位,">0"),2)) | H50: =IF($A50="","",-ROUND(SUMIFS(流水本位,流水账户,$A50,流水日期,">="&报表月份,流水日期,"<="&EOMONTH(报表月份,0),流水本位,"<0"),2)) | I50: =IF($A50="","",IFERROR(ROUND(参数设置!$I$39+SUMIFS(流水本位,流水账户,$A50,流水日期,"<="&EOMONTH(报表月份,0)),2),""))
A51: =IF(参数设置!$C$40="","",参数设置!$C$40) | B51: =IF($A51="","",参数设置!$E$40) | C51: =IF($A51="","",ROUND(N(参数设置!$G$40)+SUMIFS(流水净额,流水账户,$A51,流水日期,"<"&报表月份),2)) | D51: =IF($A51="","",ROUND(SUMIFS(流水收入,流水账户,$A51,流水日期,">="&报表月份,流水日期,"<="&EOMONTH(报表月份,0)),2)) | E51: =IF($A51="","",ROUND(SUMIFS(流水支出,流水账户,$A51,流水日期,">="&报表月份,流水日期,"<="&EOMONTH(报表月份,0)),2)) | F51: =IF($A51="","",ROUND($C51+$D51-$E51,2)) | G51: =IF($A51="","",ROUND(SUMIFS(流水本位,流水账户,$A51,流水日期,">="&报表月份,流水日期,"<="&EOMONTH(报表月份,0),流水本位,">0"),2)) | H51: =IF($A51="","",-ROUND(SUMIFS(流水本位,流水账户,$A51,流水日期,">="&报表月份,流水日期,"<="&EOMONTH(报表月份,0),流水本位,"<0"),2)) | I51: =IF($A51="","",IFERROR(ROUND(参数设置!$I$40+SUMIFS(流水本位,流水账户,$A51,流水日期,"<="&EOMONTH(报表月份,0)),2),""))
A52: 合计 | B52: 原币不能加 | G52: =ROUND(SUM(G22:G51),2) -> 1086060 | H52: =ROUND(SUM(H22:H51),2) -> 357120 | I52: =ROUND(SUM(I22:I51),2) -> 11921240

Sheet 收支分类报表
A1: 收支分类报表 · 按收支类别，全部折成人民币
A2: 支出类别显示为正数（好读）。内部转账单独一行，不进收入/支出合计；它的净额如果不是 0，那就是购汇结汇的价差。
A4: 收/支类别 | B4: 属性 | C4: 1月 | D4: 2月 | E4: 3月 | F4: 4月 | G4: 5月 | H4: 6月 | I4: 7月 | J4: 8月 | K4: 9月 | L4: 10月 | M4: 11月 | N4: 12月 | O4: 全年合计 | P4: 占比
A5: 收入合计 | B5: 收入 | C5: =ROUND(SUMIF($B$12:$B$41,"收入",C$12:C$41),2) -> 0 | D5: =ROUND(SUMIF($B$12:$B$41,"收入",D$12:D$41),2) -> 0 | E5: =ROUND(SUMIF($B$12:$B$41,"收入",E$12:E$41),2) -> 0 | F5: =ROUND(SUMIF($B$12:$B$41,"收入",F$12:F$41),2) -> 0 | G5: =ROUND(SUMIF($B$12:$B$41,"收入",G$12:G$41),2) -> 0 | H5: =ROUND(SUMIF($B$12:$B$41,"收入",H$12:H$41),2) -> 0 | I5: =ROUND(SUMIF($B$12:$B$41,"收入",I$12:I$41),2) -> 0 | J5: =ROUND(SUMIF($B$12:$B$41,"收入",J$12:J$41),2) -> 892660 | ... N5: =ROUND(SUMIF($B$12:$B$41,"收入",N$12:N$41),2) -> 0 | O5: =ROUND(SUM(C5:N5),2) -> 892660
A6: 支出合计 | B6: 支出 | C6: =ROUND(SUMIF($B$12:$B$41,"支出",C$12:C$41),2) -> 0 | D6: =ROUND(SUMIF($B$12:$B$41,"支出",D$12:D$41),2) -> 0 | E6: =ROUND(SUMIF($B$12:$B$41,"支出",E$12:E$41),2) -> 0 | F6: =ROUND(SUMIF($B$12:$B$41,"支出",F$12:F$41),2) -> 0 | G6: =ROUND(SUMIF($B$12:$B$41,"支出",G$12:G$41),2) -> 0 | H6: =ROUND(SUMIF($B$12:$B$41,"支出",H$12:H$41),2) -> 0 | I6: =ROUND(SUMIF($B$12:$B$41,"支出",I$12:I$41),2) -> 0 | J6: =ROUND(SUMIF($B$12:$B$41,"支出",J$12:J$41),2) -> 163720 | ... N6: =ROUND(SUMIF($B$12:$B$41,"支出",N$12:N$41),2) -> 0 | O6: =ROUND(SUM(C6:N6),2) -> 163720
A7: 内部转账净额 | B7: 内部转账 | C7: =ROUND(SUMIF($B$12:$B$41,"内部转账",C$12:C$41),2) -> 0 | D7: =ROUND(SUMIF($B$12:$B$41,"内部转账",D$12:D$41),2) -> 0 | E7: =ROUND(SUMIF($B$12:$B$41,"内部转账",E$12:E$41),2) -> 0 | F7: =ROUND(SUMIF($B$12:$B$41,"内部转账",F$12:F$41),2) -> 0 | G7: =ROUND(SUMIF($B$12:$B$41,"内部转账",G$12:G$41),2) -> 0 | H7: =ROUND(SUMIF($B$12:$B$41,"内部转账",H$12:H$41),2) -> 0 | I7: =ROUND(SUMIF($B$12:$B$41,"内部转账",I$12:I$41),2) -> 0 | J7: =ROUND(SUMIF($B$12:$B$41,"内部转账",J$12:J$41),2) -> 0 | ... N7: =ROUND(SUMIF($B$12:$B$41,"内部转账",N$12:N$41),2) -> 0 | O7: =ROUND(SUM(C7:N7),2) -> 0
A8: 经营净额 | B8: 收入−支出 | C8: =ROUND(C5-C6,2) -> 0 | D8: =ROUND(D5-D6,2) -> 0 | E8: =ROUND(E5-E6,2) -> 0 | F8: =ROUND(F5-F6,2) -> 0 | G8: =ROUND(G5-G6,2) -> 0 | H8: =ROUND(H5-H6,2) -> 0 | I8: =ROUND(I5-I6,2) -> 0 | J8: =ROUND(J5-J6,2) -> 728940 | ... N8: =ROUND(N5-N6,2) -> 0 | O8: =ROUND(SUM(C8:N8),2) -> 728940
A10: 按类别明细 —— 类别清单在【参数设置】维护，这里自动跟着走
A11: 收/支类别 | B11: 属性 | C11: 1月 | D11: 2月 | E11: 3月 | F11: 4月 | G11: 5月 | H11: 6月 | I11: 7月 | J11: 8月 | K11: 9月 | L11: 10月 | M11: 11月 | N11: 12月 | O11: 全年合计 | P11: 占比
A12: =IF(参数设置!$O$11="","",参数设置!$O$11) -> 销售回款 | B12: =IF($A12="","",参数设置!$P$11) -> 收入 | C12: =IF($A12="","",ROUND(IF($B12="支出",-1,1)*SUMIFS(流水本位,流水类别,$A12,流水日期,">="&DATE(管理年度,1,1),流水日期,"<="&EOMONTH(DATE(管理年度,1,1),0)),2)) -> 0 | D12: =IF($A12="","",ROUND(IF($B12="支出",-1,1)*SUMIFS(流水本位,流水类别,$A12,流水日期,">="&DATE(管理年度,2,1),流水日期,"<="&EOMONTH(DATE(管理年度,2,1),0)),2)) -> 0 | E12: =IF($A12="","",ROUND(IF($B12="支出",-1,1)*SUMIFS(流水本位,流水类别,$A12,流水日期,">="&DATE(管理年度,3,1),流水日期,"<="&EOMONTH(DATE(管理年度,3,1),0)),2)) -> 0 | F12: =IF($A12="","",ROUND(IF($B12="支出",-1,1)*SUMIFS(流水本位,流水类别,$A12,流水日期,">="&DATE(管理年度,4,1),流水日期,"<="&EOMONTH(DATE(管理年度,4,1),0)),2)) -> 0 | G12: =IF($A12="","",ROUND(IF($B12="支出",-1,1)*SUMIFS(流水本位,流水类别,$A12,流水日期,">="&DATE(管理年度,5,1),流水日期,"<="&EOMONTH(DATE(管理年度,5,1),0)),2)) -> 0 | H12: =IF($A12="","",ROUND(IF($B12="支出",-1,1)*SUMIFS(流水本位,流水类别,$A12,流水日期,">="&DATE(管理年度,6,1),流水日期,"<="&EOMONTH(DATE(管理年度,6,1),0)),2)) -> 0 | I12: =IF($A12="","",ROUND(IF($B12="支出",-1,1)*SUMIFS(流水本位,流水类别,$A12,流水日期,">="&DATE(管理年度,7,1),流水日期,"<="&EOMONTH(DATE(管理年度,7,1),0)),2)) -> 0 | J12: =IF($A12="","",ROUND(IF($B12="支出",-1,1)*SUMIFS(流水本位,流水类别,$A12,流水日期,">="&DATE(管理年度,8,1),流水日期,"<="&EOMONTH(DATE(管理年度,8,1),0)),2)) -> 711500 | K12: =IF($A12="","",ROUND(IF($B12="支出",-1,1)*SUMIFS(流水本位,流水类别,$A12,流水日期,">="&DATE(管理年度,9,1),流水日期,"<="&EOMONTH(DATE(管理年度,9,1),0)),2)) -> 0 | L12: =IF($A12="","",ROUND(IF($B12="支出",-1,1)*SUMIFS(流水本位,流水类别,$A12,流水日期,">="&DATE(管理年度,10,1),流水日期,"<="&EOMONTH(DATE(管理年度,10,1),0)),2)) -> 0 | M12: =IF($A12="","",ROUND(IF($B12="支出",-1,1)*SUMIFS(流水本位,流水类别,$A12,流水日期,">="&DATE(管理年度,11,1),流水日期,"<="&EOMONTH(DATE(管理年度,11,1),0)),2)) -> 0 | N12: =IF($A12="","",ROUND(IF($B12="支出",-1,1)*SUMIFS(流水本位,流水类别,$A12,流水日期,">="&DATE(管理年度,12,1),流水日期,"<="&EOMONTH(DATE(管理年度,12,1),0)),2)) -> 0 | O12: =IF($A12="","",ROUND(SUM(C12:N12),2)) -> 711500 | P12: =IF(OR($A12="",$B12="内部转账"),"",IFERROR($O12/IF($B12="收入",$O$5,$O$6),"")) -> 0.79705599
A13: =IF(参数设置!$O$12="","",参数设置!$O$12) -> 其他业务收入 | B13: =IF($A13="","",参数设置!$P$12) -> 收入 | C13: =IF($A13="","",ROUND(IF($B13="支出",-1,1)*SUMIFS(流水本位,流水类别,$A13,流水日期,">="&DATE(管理年度,1,1),流水日期,"<="&EOMONTH(DATE(管理年度,1,1),0)),2)) -> 0 | D13: =IF($A13="","",ROUND(IF($B13="支出",-1,1)*SUMIFS(流水本位,流水类别,$A13,流水日期,">="&DATE(管理年度,2,1),流水日期,"<="&EOMONTH(DATE(管理年度,2,1),0)),2)) -> 0 | E13: =IF($A13="","",ROUND(IF($B13="支出",-1,1)*SUMIFS(流水本位,流水类别,$A13,流水日期,">="&DATE(管理年度,3,1),流水日期,"<="&EOMONTH(DATE(管理年度,3,1),0)),2)) -> 0 | F13: =IF($A13="","",ROUND(IF($B13="支出",-1,1)*SUMIFS(流水本位,流水类别,$A13,流水日期,">="&DATE(管理年度,4,1),流水日期,"<="&EOMONTH(DATE(管理年度,4,1),0)),2)) -> 0 | G13: =IF($A13="","",ROUND(IF($B13="支出",-1,1)*SUMIFS(流水本位,流水类别,$A13,流水日期,">="&DATE(管理年度,5,1),流水日期,"<="&EOMONTH(DATE(管理年度,5,1),0)),2)) -> 0 | H13: =IF($A13="","",ROUND(IF($B13="支出",-1,1)*SUMIFS(流水本位,流水类别,$A13,流水日期,">="&DATE(管理年度,6,1),流水日期,"<="&EOMONTH(DATE(管理年度,6,1),0)),2)) -> 0 | I13: =IF($A13="","",ROUND(IF($B13="支出",-1,1)*SUMIFS(流水本位,流水类别,$A13,流水日期,">="&DATE(管理年度,7,1),流水日期,"<="&EOMONTH(DATE(管理年度,7,1),0)),2)) -> 0 | J13: =IF($A13="","",ROUND(IF($B13="支出",-1,1)*SUMIFS(流水本位,流水类别,$A13,流水日期,">="&DATE(管理年度,8,1),流水日期,"<="&EOMONTH(DATE(管理年度,8,1),0)),2)) -> 35000 | K13: =IF($A13="","",ROUND(IF($B13="支出",-1,1)*SUMIFS(流水本位,流水类别,$A13,流水日期,">="&DATE(管理年度,9,1),流水日期,"<="&EOMONTH(DATE(管理年度,9,1),0)),2)) -> 0 | L13: =IF($A13="","",ROUND(IF($B13="支出",-1,1)*SUMIFS(流水本位,流水类别,$A13,流水日期,">="&DATE(管理年度,10,1),流水日期,"<="&EOMONTH(DATE(管理年度,10,1),0)),2)) -> 0 | M13: =IF($A13="","",ROUND(IF($B13="支出",-1,1)*SUMIFS(流水本位,流水类别,$A13,流水日期,">="&DATE(管理年度,11,1),流水日期,"<="&EOMONTH(DATE(管理年度,11,1),0)),2)) -> 0 | N13: =IF($A13="","",ROUND(IF($B13="支出",-1,1)*SUMIFS(流水本位,流水类别,$A13,流水日期,">="&DATE(管理年度,12,1),流水日期,"<="&EOMONTH(DATE(管理年度,12,1),0)),2)) -> 0 | O13: =IF($A13="","",ROUND(SUM(C13:N13),2)) -> 35000 | P13: =IF(OR($A13="",$B13="内部转账"),"",IFERROR($O13/IF($B13="收入",$O$5,$O$6),"")) -> 0.039208657
A14: =IF(参数设置!$O$13="","",参数设置!$O$13) -> 投资款 | B14: =IF($A14="","",参数设置!$P$13) -> 收入 | C14: =IF($A14="","",ROUND(IF($B14="支出",-1,1)*SUMIFS(流水本位,流水类别,$A14,流水日期,">="&DATE(管理年度,1,1),流水日期,"<="&EOMONTH(DATE(管理年度,1,1),0)),2)) -> 0 | D14: =IF($A14="","",ROUND(IF($B14="支出",-1,1)*SUMIFS(流水本位,流水类别,$A14,流水日期,">="&DATE(管理年度,2,1),流水日期,"<="&EOMONTH(DATE(管理年度,2,1),0)),2)) -> 0 | E14: =IF($A14="","",ROUND(IF($B14="支出",-1,1)*SUMIFS(流水本位,流水类别,$A14,流水日期,">="&DATE(管理年度,3,1),流水日期,"<="&EOMONTH(DATE(管理年度,3,1),0)),2)) -> 0 | F14: =IF($A14="","",ROUND(IF($B14="支出",-1,1)*SUMIFS(流水本位,流水类别,$A14,流水日期,">="&DATE(管理年度,4,1),流水日期,"<="&EOMONTH(DATE(管理年度,4,1),0)),2)) -> 0 | G14: =IF($A14="","",ROUND(IF($B14="支出",-1,1)*SUMIFS(流水本位,流水类别,$A14,流水日期,">="&DATE(管理年度,5,1),流水日期,"<="&EOMONTH(DATE(管理年度,5,1),0)),2)) -> 0 | H14: =IF($A14="","",ROUND(IF($B14="支出",-1,1)*SUMIFS(流水本位,流水类别,$A14,流水日期,">="&DATE(管理年度,6,1),流水日期,"<="&EOMONTH(DATE(管理年度,6,1),0)),2)) -> 0 | I14: =IF($A14="","",ROUND(IF($B14="支出",-1,1)*SUMIFS(流水本位,流水类别,$A14,流水日期,">="&DATE(管理年度,7,1),流水日期,"<="&EOMONTH(DATE(管理年度,7,1),0)),2)) -> 0 | J14: =IF($A14="","",ROUND(IF($B14="支出",-1,1)*SUMIFS(流水本位,流水类别,$A14,流水日期,">="&DATE(管理年度,8,1),流水日期,"<="&EOMONTH(DATE(管理年度,8,1),0)),2)) -> 86160 | K14: =IF($A14="","",ROUND(IF($B14="支出",-1,1)*SUMIFS(流水本位,流水类别,$A14,流水日期,">="&DATE(管理年度,9,1),流水日期,"<="&EOMONTH(DATE(管理年度,9,1),0)),2)) -> 0 | L14: =IF($A14="","",ROUND(IF($B14="支出",-1,1)*SUMIFS(流水本位,流水类别,$A14,流水日期,">="&DATE(管理年度,10,1),流水日期,"<="&EOMONTH(DATE(管理年度,10,1),0)),2)) -> 0 | M14: =IF($A14="","",ROUND(IF($B14="支出",-1,1)*SUMIFS(流水本位,流水类别,$A14,流水日期,">="&DATE(管理年度,11,1),流水日期,"<="&EOMONTH(DATE(管理年度,11,1),0)),2)) -> 0 | N14: =IF($A14="","",ROUND(IF($B14="支出",-1,1)*SUMIFS(流水本位,流水类别,$A14,流水日期,">="&DATE(管理年度,12,1),流水日期,"<="&EOMONTH(DATE(管理年度,12,1),0)),2)) -> 0 | O14: =IF($A14="","",ROUND(SUM(C14:N14),2)) -> 86160 | P14: =IF(OR($A14="",$B14="内部转账"),"",IFERROR($O14/IF($B14="收入",$O$5,$O$6),"")) -> 0.096520512
A15: =IF(参数设置!$O$14="","",参数设置!$O$14) -> 借款 | B15: =IF($A15="","",参数设置!$P$14) -> 收入 | C15: =IF($A15="","",ROUND(IF($B15="支出",-1,1)*SUMIFS(流水本位,流水类别,$A15,流水日期,">="&DATE(管理年度,1,1),流水日期,"<="&EOMONTH(DATE(管理年度,1,1),0)),2)) -> 0 | D15: =IF($A15="","",ROUND(IF($B15="支出",-1,1)*SUMIFS(流水本位,流水类别,$A15,流水日期,">="&DATE(管理年度,2,1),流水日期,"<="&EOMONTH(DATE(管理年度,2,1),0)),2)) -> 0 | E15: =IF($A15="","",ROUND(IF($B15="支出",-1,1)*SUMIFS(流水本位,流水类别,$A15,流水日期,">="&DATE(管理年度,3,1),流水日期,"<="&EOMONTH(DATE(管理年度,3,1),0)),2)) -> 0 | F15: =IF($A15="","",ROUND(IF($B15="支出",-1,1)*SUMIFS(流水本位,流水类别,$A15,流水日期,">="&DATE(管理年度,4,1),流水日期,"<="&EOMONTH(DATE(管理年度,4,1),0)),2)) -> 0 | G15: =IF($A15="","",ROUND(IF($B15="支出",-1,1)*SUMIFS(流水本位,流水类别,$A15,流水日期,">="&DATE(管理年度,5,1),流水日期,"<="&EOMONTH(DATE(管理年度,5,1),0)),2)) -> 0 | H15: =IF($A15="","",ROUND(IF($B15="支出",-1,1)*SUMIFS(流水本位,流水类别,$A15,流水日期,">="&DATE(管理年度,6,1),流水日期,"<="&EOMONTH(DATE(管理年度,6,1),0)),2)) -> 0 | I15: =IF($A15="","",ROUND(IF($B15="支出",-1,1)*SUMIFS(流水本位,流水类别,$A15,流水日期,">="&DATE(管理年度,7,1),流水日期,"<="&EOMONTH(DATE(管理年度,7,1),0)),2)) -> 0 | J15: =IF($A15="","",ROUND(IF($B15="支出",-1,1)*SUMIFS(流水本位,流水类别,$A15,流水日期,">="&DATE(管理年度,8,1),流水日期,"<="&EOMONTH(DATE(管理年度,8,1),0)),2)) -> 60000 | K15: =IF($A15="","",ROUND(IF($B15="支出",-1,1)*SUMIFS(流水本位,流水类别,$A15,流水日期,">="&DATE(管理年度,9,1),流水日期,"<="&EOMONTH(DATE(管理年度,9,1),0)),2)) -> 0 | L15: =IF($A15="","",ROUND(IF($B15="支出",-1,1)*SUMIFS(流水本位,流水类别,$A15,流水日期,">="&DATE(管理年度,10,1),流水日期,"<="&EOMONTH(DATE(管理年度,10,1),0)),2)) -> 0 | M15: =IF($A15="","",ROUND(IF($B15="支出",-1,1)*SUMIFS(流水本位,流水类别,$A15,流水日期,">="&DATE(管理年度,11,1),流水日期,"<="&EOMONTH(DATE(管理年度,11,1),0)),2)) -> 0 | N15: =IF($A15="","",ROUND(IF($B15="支出",-1,1)*SUMIFS(流水本位,流水类别,$A15,流水日期,">="&DATE(管理年度,12,1),流水日期,"<="&EOMONTH(DATE(管理年度,12,1),0)),2)) -> 0 | O15: =IF($A15="","",ROUND(SUM(C15:N15),2)) -> 60000 | P15: =IF(OR($A15="",$B15="内部转账"),"",IFERROR($O15/IF($B15="收入",$O$5,$O$6),"")) -> 0.067214841
A16: =IF(参数设置!$O$15="","",参数设置!$O$15) -> 利息收入 | B16: =IF($A16="","",参数设置!$P$15) -> 收入 | C16: =IF($A16="","",ROUND(IF($B16="支出",-1,1)*SUMIFS(流水本位,流水类别,$A16,流水日期,">="&DATE(管理年度,1,1),流水日期,"<="&EOMONTH(DATE(管理年度,1,1),0)),2)) -> 0 | D16: =IF($A16="","",ROUND(IF($B16="支出",-1,1)*SUMIFS(流水本位,流水类别,$A16,流水日期,">="&DATE(管理年度,2,1),流水日期,"<="&EOMONTH(DATE(管理年度,2,1),0)),2)) -> 0 | E16: =IF($A16="","",ROUND(IF($B16="支出",-1,1)*SUMIFS(流水本位,流水类别,$A16,流水日期,">="&DATE(管理年度,3,1),流水日期,"<="&EOMONTH(DATE(管理年度,3,1),0)),2)) -> 0 | F16: =IF($A16="","",ROUND(IF($B16="支出",-1,1)*SUMIFS(流水本位,流水类别,$A16,流水日期,">="&DATE(管理年度,4,1),流水日期,"<="&EOMONTH(DATE(管理年度,4,1),0)),2)) -> 0 | G16: =IF($A16="","",ROUND(IF($B16="支出",-1,1)*SUMIFS(流水本位,流水类别,$A16,流水日期,">="&DATE(管理年度,5,1),流水日期,"<="&EOMONTH(DATE(管理年度,5,1),0)),2)) -> 0 | H16: =IF($A16="","",ROUND(IF($B16="支出",-1,1)*SUMIFS(流水本位,流水类别,$A16,流水日期,">="&DATE(管理年度,6,1),流水日期,"<="&EOMONTH(DATE(管理年度,6,1),0)),2)) -> 0 | I16: =IF($A16="","",ROUND(IF($B16="支出",-1,1)*SUMIFS(流水本位,流水类别,$A16,流水日期,">="&DATE(管理年度,7,1),流水日期,"<="&EOMONTH(DATE(管理年度,7,1),0)),2)) -> 0 | J16: =IF($A16="","",ROUND(IF($B16="支出",-1,1)*SUMIFS(流水本位,流水类别,$A16,流水日期,">="&DATE(管理年度,8,1),流水日期,"<="&EOMONTH(DATE(管理年度,8,1),0)),2)) -> 0 | K16: =IF($A16="","",ROUND(IF($B16="支出",-1,1)*SUMIFS(流水本位,流水类别,$A16,流水日期,">="&DATE(管理年度,9,1),流水日期,"<="&EOMONTH(DATE(管理年度,9,1),0)),2)) -> 0 | L16: =IF($A16="","",ROUND(IF($B16="支出",-1,1)*SUMIFS(流水本位,流水类别,$A16,流水日期,">="&DATE(管理年度,10,1),流水日期,"<="&EOMONTH(DATE(管理年度,10,1),0)),2)) -> 0 | M16: =IF($A16="","",ROUND(IF($B16="支出",-1,1)*SUMIFS(流水本位,流水类别,$A16,流水日期,">="&DATE(管理年度,11,1),流水日期,"<="&EOMONTH(DATE(管理年度,11,1),0)),2)) -> 0 | N16: =IF($A16="","",ROUND(IF($B16="支出",-1,1)*SUMIFS(流水本位,流水类别,$A16,流水日期,">="&DATE(管理年度,12,1),流水日期,"<="&EOMONTH(DATE(管理年度,12,1),0)),2)) -> 0 | O16: =IF($A16="","",ROUND(SUM(C16:N16),2)) -> 0 | P16: =IF(OR($A16="",$B16="内部转账"),"",IFERROR($O16/IF($B16="收入",$O$5,$O$6),"")) -> 0
A17: =IF(参数设置!$O$16="","",参数设置!$O$16) -> 退款收回 | B17: =IF($A17="","",参数设置!$P$16) -> 收入 | C17: =IF($A17="","",ROUND(IF($B17="支出",-1,1)*SUMIFS(流水本位,流水类别,$A17,流水日期,">="&DATE(管理年度,1,1),流水日期,"<="&EOMONTH(DATE(管理年度,1,1),0)),2)) -> 0 | D17: =IF($A17="","",ROUND(IF($B17="支出",-1,1)*SUMIFS(流水本位,流水类别,$A17,流水日期,">="&DATE(管理年度,2,1),流水日期,"<="&EOMONTH(DATE(管理年度,2,1),0)),2)) -> 0 | E17: =IF($A17="","",ROUND(IF($B17="支出",-1,1)*SUMIFS(流水本位,流水类别,$A17,流水日期,">="&DATE(管理年度,3,1),流水日期,"<="&EOMONTH(DATE(管理年度,3,1),0)),2)) -> 0 | F17: =IF($A17="","",ROUND(IF($B17="支出",-1,1)*SUMIFS(流水本位,流水类别,$A17,流水日期,">="&DATE(管理年度,4,1),流水日期,"<="&EOMONTH(DATE(管理年度,4,1),0)),2)) -> 0 | G17: =IF($A17="","",ROUND(IF($B17="支出",-1,1)*SUMIFS(流水本位,流水类别,$A17,流水日期,">="&DATE(管理年度,5,1),流水日期,"<="&EOMONTH(DATE(管理年度,5,1),0)),2)) -> 0 | H17: =IF($A17="","",ROUND(IF($B17="支出",-1,1)*SUMIFS(流水本位,流水类别,$A17,流水日期,">="&DATE(管理年度,6,1),流水日期,"<="&EOMONTH(DATE(管理年度,6,1),0)),2)) -> 0 | I17: =IF($A17="","",ROUND(IF($B17="支出",-1,1)*SUMIFS(流水本位,流水类别,$A17,流水日期,">="&DATE(管理年度,7,1),流水日期,"<="&EOMONTH(DATE(管理年度,7,1),0)),2)) -> 0 | J17: =IF($A17="","",ROUND(IF($B17="支出",-1,1)*SUMIFS(流水本位,流水类别,$A17,流水日期,">="&DATE(管理年度,8,1),流水日期,"<="&EOMONTH(DATE(管理年度,8,1),0)),2)) -> 0 | K17: =IF($A17="","",ROUND(IF($B17="支出",-1,1)*SUMIFS(流水本位,流水类别,$A17,流水日期,">="&DATE(管理年度,9,1),流水日期,"<="&EOMONTH(DATE(管理年度,9,1),0)),2)) -> 0 | L17: =IF($A17="","",ROUND(IF($B17="支出",-1,1)*SUMIFS(流水本位,流水类别,$A17,流水日期,">="&DATE(管理年度,10,1),流水日期,"<="&EOMONTH(DATE(管理年度,10,1),0)),2)) -> 0 | M17: =IF($A17="","",ROUND(IF($B17="支出",-1,1)*SUMIFS(流水本位,流水类别,$A17,流水日期,">="&DATE(管理年度,11,1),流水日期,"<="&EOMONTH(DATE(管理年度,11,1),0)),2)) -> 0 | N17: =IF($A17="","",ROUND(IF($B17="支出",-1,1)*SUMIFS(流水本位,流水类别,$A17,流水日期,">="&DATE(管理年度,12,1),流水日期,"<="&EOMONTH(DATE(管理年度,12,1),0)),2)) -> 0 | O17: =IF($A17="","",ROUND(SUM(C17:N17),2)) -> 0 | P17: =IF(OR($A17="",$B17="内部转账"),"",IFERROR($O17/IF($B17="收入",$O$5,$O$6),"")) -> 0
A18: =IF(参数设置!$O$17="","",参数设置!$O$17) -> 采购付款 | B18: =IF($A18="","",参数设置!$P$17) -> 支出 | C18: =IF($A18="","",ROUND(IF($B18="支出",-1,1)*SUMIFS(流水本位,流水类别,$A18,流水日期,">="&DATE(管理年度,1,1),流水日期,"<="&EOMONTH(DATE(管理年度,1,1),0)),2)) -> 0 | D18: =IF($A18="","",ROUND(IF($B18="支出",-1,1)*SUMIFS(流水本位,流水类别,$A18,流水日期,">="&DATE(管理年度,2,1),流水日期,"<="&EOMONTH(DATE(管理年度,2,1),0)),2)) -> 0 | E18: =IF($A18="","",ROUND(IF($B18="支出",-1,1)*SUMIFS(流水本位,流水类别,$A18,流水日期,">="&DATE(管理年度,3,1),流水日期,"<="&EOMONTH(DATE(管理年度,3,1),0)),2)) -> 0 | F18: =IF($A18="","",ROUND(IF($B18="支出",-1,1)*SUMIFS(流水本位,流水类别,$A18,流水日期,">="&DATE(管理年度,4,1),流水日期,"<="&EOMONTH(DATE(管理年度,4,1),0)),2)) -> 0 | G18: =IF($A18="","",ROUND(IF($B18="支出",-1,1)*SUMIFS(流水本位,流水类别,$A18,流水日期,">="&DATE(管理年度,5,1),流水日期,"<="&EOMONTH(DATE(管理年度,5,1),0)),2)) -> 0 | H18: =IF($A18="","",ROUND(IF($B18="支出",-1,1)*SUMIFS(流水本位,流水类别,$A18,流水日期,">="&DATE(管理年度,6,1),流水日期,"<="&EOMONTH(DATE(管理年度,6,1),0)),2)) -> 0 | I18: =IF($A18="","",ROUND(IF($B18="支出",-1,1)*SUMIFS(流水本位,流水类别,$A18,流水日期,">="&DATE(管理年度,7,1),流水日期,"<="&EOMONTH(DATE(管理年度,7,1),0)),2)) -> 0 | J18: =IF($A18="","",ROUND(IF($B18="支出",-1,1)*SUMIFS(流水本位,流水类别,$A18,流水日期,">="&DATE(管理年度,8,1),流水日期,"<="&EOMONTH(DATE(管理年度,8,1),0)),2)) -> 61420 | K18: =IF($A18="","",ROUND(IF($B18="支出",-1,1)*SUMIFS(流水本位,流水类别,$A18,流水日期,">="&DATE(管理年度,9,1),流水日期,"<="&EOMONTH(DATE(管理年度,9,1),0)),2)) -> 0 | L18: =IF($A18="","",ROUND(IF($B18="支出",-1,1)*SUMIFS(流水本位,流水类别,$A18,流水日期,">="&DATE(管理年度,10,1),流水日期,"<="&EOMONTH(DATE(管理年度,10,1),0)),2)) -> 0 | M18: =IF($A18="","",ROUND(IF($B18="支出",-1,1)*SUMIFS(流水本位,流水类别,$A18,流水日期,">="&DATE(管理年度,11,1),流水日期,"<="&EOMONTH(DATE(管理年度,11,1),0)),2)) -> 0 | N18: =IF($A18="","",ROUND(IF($B18="支出",-1,1)*SUMIFS(流水本位,流水类别,$A18,流水日期,">="&DATE(管理年度,12,1),流水日期,"<="&EOMONTH(DATE(管理年度,12,1),0)),2)) -> 0 | O18: =IF($A18="","",ROUND(SUM(C18:N18),2)) -> 61420 | P18: =IF(OR($A18="",$B18="内部转账"),"",IFERROR($O18/IF($B18="收入",$O$5,$O$6),"")) -> 0.3751527
A19: =IF(参数设置!$O$18="","",参数设置!$O$18) -> 工资 | B19: =IF($A19="","",参数设置!$P$18) -> 支出 | C19: =IF($A19="","",ROUND(IF($B19="支出",-1,1)*SUMIFS(流水本位,流水类别,$A19,流水日期,">="&DATE(管理年度,1,1),流水日期,"<="&EOMONTH(DATE(管理年度,1,1),0)),2)) -> 0 | D19: =IF($A19="","",ROUND(IF($B19="支出",-1,1)*SUMIFS(流水本位,流水类别,$A19,流水日期,">="&DATE(管理年度,2,1),流水日期,"<="&EOMONTH(DATE(管理年度,2,1),0)),2)) -> 0 | E19: =IF($A19="","",ROUND(IF($B19="支出",-1,1)*SUMIFS(流水本位,流水类别,$A19,流水日期,">="&DATE(管理年度,3,1),流水日期,"<="&EOMONTH(DATE(管理年度,3,1),0)),2)) -> 0 | F19: =IF($A19="","",ROUND(IF($B19="支出",-1,1)*SUMIFS(流水本位,流水类别,$A19,流水日期,">="&DATE(管理年度,4,1),流水日期,"<="&EOMONTH(DATE(管理年度,4,1),0)),2)) -> 0 | G19: =IF($A19="","",ROUND(IF($B19="支出",-1,1)*SUMIFS(流水本位,流水类别,$A19,流水日期,">="&DATE(管理年度,5,1),流水日期,"<="&EOMONTH(DATE(管理年度,5,1),0)),2)) -> 0 | H19: =IF($A19="","",ROUND(IF($B19="支出",-1,1)*SUMIFS(流水本位,流水类别,$A19,流水日期,">="&DATE(管理年度,6,1),流水日期,"<="&EOMONTH(DATE(管理年度,6,1),0)),2)) -> 0 | I19: =IF($A19="","",ROUND(IF($B19="支出",-1,1)*SUMIFS(流水本位,流水类别,$A19,流水日期,">="&DATE(管理年度,7,1),流水日期,"<="&EOMONTH(DATE(管理年度,7,1),0)),2)) -> 0 | J19: =IF($A19="","",ROUND(IF($B19="支出",-1,1)*SUMIFS(流水本位,流水类别,$A19,流水日期,">="&DATE(管理年度,8,1),流水日期,"<="&EOMONTH(DATE(管理年度,8,1),0)),2)) -> 30000 | K19: =IF($A19="","",ROUND(IF($B19="支出",-1,1)*SUMIFS(流水本位,流水类别,$A19,流水日期,">="&DATE(管理年度,9,1),流水日期,"<="&EOMONTH(DATE(管理年度,9,1),0)),2)) -> 0 | L19: =IF($A19="","",ROUND(IF($B19="支出",-1,1)*SUMIFS(流水本位,流水类别,$A19,流水日期,">="&DATE(管理年度,10,1),流水日期,"<="&EOMONTH(DATE(管理年度,10,1),0)),2)) -> 0 | M19: =IF($A19="","",ROUND(IF($B19="支出",-1,1)*SUMIFS(流水本位,流水类别,$A19,流水日期,">="&DATE(管理年度,11,1),流水日期,"<="&EOMONTH(DATE(管理年度,11,1),0)),2)) -> 0 | N19: =IF($A19="","",ROUND(IF($B19="支出",-1,1)*SUMIFS(流水本位,流水类别,$A19,流水日期,">="&DATE(管理年度,12,1),流水日期,"<="&EOMONTH(DATE(管理年度,12,1),0)),2)) -> 0 | O19: =IF($A19="","",ROUND(SUM(C19:N19),2)) -> 30000 | P19: =IF(OR($A19="",$B19="内部转账"),"",IFERROR($O19/IF($B19="收入",$O$5,$O$6),"")) -> 0.18323968
A20: =IF(参数设置!$O$19="","",参数设置!$O$19) -> 运营费用 | B20: =IF($A20="","",参数设置!$P$19) -> 支出 | C20: =IF($A20="","",ROUND(IF($B20="支出",-1,1)*SUMIFS(流水本位,流水类别,$A20,流水日期,">="&DATE(管理年度,1,1),流水日期,"<="&EOMONTH(DATE(管理年度,1,1),0)),2)) -> 0 | D20: =IF($A20="","",ROUND(IF($B20="支出",-1,1)*SUMIFS(流水本位,流水类别,$A20,流水日期,">="&DATE(管理年度,2,1),流水日期,"<="&EOMONTH(DATE(管理年度,2,1),0)),2)) -> 0 | E20: =IF($A20="","",ROUND(IF($B20="支出",-1,1)*SUMIFS(流水本位,流水类别,$A20,流水日期,">="&DATE(管理年度,3,1),流水日期,"<="&EOMONTH(DATE(管理年度,3,1),0)),2)) -> 0 | F20: =IF($A20="","",ROUND(IF($B20="支出",-1,1)*SUMIFS(流水本位,流水类别,$A20,流水日期,">="&DATE(管理年度,4,1),流水日期,"<="&EOMONTH(DATE(管理年度,4,1),0)),2)) -> 0 | G20: =IF($A20="","",ROUND(IF($B20="支出",-1,1)*SUMIFS(流水本位,流水类别,$A20,流水日期,">="&DATE(管理年度,5,1),流水日期,"<="&EOMONTH(DATE(管理年度,5,1),0)),2)) -> 0 | H20: =IF($A20="","",ROUND(IF($B20="支出",-1,1)*SUMIFS(流水本位,流水类别,$A20,流水日期,">="&DATE(管理年度,6,1),流水日期,"<="&EOMONTH(DATE(管理年度,6,1),0)),2)) -> 0 | I20: =IF($A20="","",ROUND(IF($B20="支出",-1,1)*SUMIFS(流水本位,流水类别,$A20,流水日期,">="&DATE(管理年度,7,1),流水日期,"<="&EOMONTH(DATE(管理年度,7,1),0)),2)) -> 0 | J20: =IF($A20="","",ROUND(IF($B20="支出",-1,1)*SUMIFS(流水本位,流水类别,$A20,流水日期,">="&DATE(管理年度,8,1),流水日期,"<="&EOMONTH(DATE(管理年度,8,1),0)),2)) -> 54300 | K20: =IF($A20="","",ROUND(IF($B20="支出",-1,1)*SUMIFS(流水本位,流水类别,$A20,流水日期,">="&DATE(管理年度,9,1),流水日期,"<="&EOMONTH(DATE(管理年度,9,1),0)),2)) -> 0 | L20: =IF($A20="","",ROUND(IF($B20="支出",-1,1)*SUMIFS(流水本位,流水类别,$A20,流水日期,">="&DATE(管理年度,10,1),流水日期,"<="&EOMONTH(DATE(管理年度,10,1),0)),2)) -> 0 | M20: =IF($A20="","",ROUND(IF($B20="支出",-1,1)*SUMIFS(流水本位,流水类别,$A20,流水日期,">="&DATE(管理年度,11,1),流水日期,"<="&EOMONTH(DATE(管理年度,11,1),0)),2)) -> 0 | N20: =IF($A20="","",ROUND(IF($B20="支出",-1,1)*SUMIFS(流水本位,流水类别,$A20,流水日期,">="&DATE(管理年度,12,1),流水日期,"<="&EOMONTH(DATE(管理年度,12,1),0)),2)) -> 0 | O20: =IF($A20="","",ROUND(SUM(C20:N20),2)) -> 54300 | P20: =IF(OR($A20="",$B20="内部转账"),"",IFERROR($O20/IF($B20="收入",$O$5,$O$6),"")) -> 0.33166382
A21: =IF(参数设置!$O$20="","",参数设置!$O$20) -> 税费 | B21: =IF($A21="","",参数设置!$P$20) -> 支出 | C21: =IF($A21="","",ROUND(IF($B21="支出",-1,1)*SUMIFS(流水本位,流水类别,$A21,流水日期,">="&DATE(管理年度,1,1),流水日期,"<="&EOMONTH(DATE(管理年度,1,1),0)),2)) -> 0 | D21: =IF($A21="","",ROUND(IF($B21="支出",-1,1)*SUMIFS(流水本位,流水类别,$A21,流水日期,">="&DATE(管理年度,2,1),流水日期,"<="&EOMONTH(DATE(管理年度,2,1),0)),2)) -> 0 | E21: =IF($A21="","",ROUND(IF($B21="支出",-1,1)*SUMIFS(流水本位,流水类别,$A21,流水日期,">="&DATE(管理年度,3,1),流水日期,"<="&EOMONTH(DATE(管理年度,3,1),0)),2)) -> 0 | F21: =IF($A21="","",ROUND(IF($B21="支出",-1,1)*SUMIFS(流水本位,流水类别,$A21,流水日期,">="&DATE(管理年度,4,1),流水日期,"<="&EOMONTH(DATE(管理年度,4,1),0)),2)) -> 0 | G21: =IF($A21="","",ROUND(IF($B21="支出",-1,1)*SUMIFS(流水本位,流水类别,$A21,流水日期,">="&DATE(管理年度,5,1),流水日期,"<="&EOMONTH(DATE(管理年度,5,1),0)),2)) -> 0 | H21: =IF($A21="","",ROUND(IF($B21="支出",-1,1)*SUMIFS(流水本位,流水类别,$A21,流水日期,">="&DATE(管理年度,6,1),流水日期,"<="&EOMONTH(DATE(管理年度,6,1),0)),2)) -> 0 | I21: =IF($A21="","",ROUND(IF($B21="支出",-1,1)*SUMIFS(流水本位,流水类别,$A21,流水日期,">="&DATE(管理年度,7,1),流水日期,"<="&EOMONTH(DATE(管理年度,7,1),0)),2)) -> 0 | J21: =IF($A21="","",ROUND(IF($B21="支出",-1,1)*SUMIFS(流水本位,流水类别,$A21,流水日期,">="&DATE(管理年度,8,1),流水日期,"<="&EOMONTH(DATE(管理年度,8,1),0)),2)) -> 18000 | K21: =IF($A21="","",ROUND(IF($B21="支出",-1,1)*SUMIFS(流水本位,流水类别,$A21,流水日期,">="&DATE(管理年度,9,1),流水日期,"<="&EOMONTH(DATE(管理年度,9,1),0)),2)) -> 0 | L21: =IF($A21="","",ROUND(IF($B21="支出",-1,1)*SUMIFS(流水本位,流水类别,$A21,流水日期,">="&DATE(管理年度,10,1),流水日期,"<="&EOMONTH(DATE(管理年度,10,1),0)),2)) -> 0 | M21: =IF($A21="","",ROUND(IF($B21="支出",-1,1)*SUMIFS(流水本位,流水类别,$A21,流水日期,">="&DATE(管理年度,11,1),流水日期,"<="&EOMONTH(DATE(管理年度,11,1),0)),2)) -> 0 | N21: =IF($A21="","",ROUND(IF($B21="支出",-1,1)*SUMIFS(流水本位,流水类别,$A21,流水日期,">="&DATE(管理年度,12,1),流水日期,"<="&EOMONTH(DATE(管理年度,12,1),0)),2)) -> 0 | O21: =IF($A21="","",ROUND(SUM(C21:N21),2)) -> 18000 | P21: =IF(OR($A21="",$B21="内部转账"),"",IFERROR($O21/IF($B21="收入",$O$5,$O$6),"")) -> 0.10994381
A22: =IF(参数设置!$O$21="","",参数设置!$O$21) -> 手续费 | B22: =IF($A22="","",参数设置!$P$21) -> 支出 | C22: =IF($A22="","",ROUND(IF($B22="支出",-1,1)*SUMIFS(流水本位,流水类别,$A22,流水日期,">="&DATE(管理年度,1,1),流水日期,"<="&EOMONTH(DATE(管理年度,1,1),0)),2)) -> 0 | D22: =IF($A22="","",ROUND(IF($B22="支出",-1,1)*SUMIFS(流水本位,流水类别,$A22,流水日期,">="&DATE(管理年度,2,1),流水日期,"<="&EOMONTH(DATE(管理年度,2,1),0)),2)) -> 0 | E22: =IF($A22="","",ROUND(IF($B22="支出",-1,1)*SUMIFS(流水本位,流水类别,$A22,流水日期,">="&DATE(管理年度,3,1),流水日期,"<="&EOMONTH(DATE(管理年度,3,1),0)),2)) -> 0 | F22: =IF($A22="","",ROUND(IF($B22="支出",-1,1)*SUMIFS(流水本位,流水类别,$A22,流水日期,">="&DATE(管理年度,4,1),流水日期,"<="&EOMONTH(DATE(管理年度,4,1),0)),2)) -> 0 | G22: =IF($A22="","",ROUND(IF($B22="支出",-1,1)*SUMIFS(流水本位,流水类别,$A22,流水日期,">="&DATE(管理年度,5,1),流水日期,"<="&EOMONTH(DATE(管理年度,5,1),0)),2)) -> 0 | H22: =IF($A22="","",ROUND(IF($B22="支出",-1,1)*SUMIFS(流水本位,流水类别,$A22,流水日期,">="&DATE(管理年度,6,1),流水日期,"<="&EOMONTH(DATE(管理年度,6,1),0)),2)) -> 0 | I22: =IF($A22="","",ROUND(IF($B22="支出",-1,1)*SUMIFS(流水本位,流水类别,$A22,流水日期,">="&DATE(管理年度,7,1),流水日期,"<="&EOMONTH(DATE(管理年度,7,1),0)),2)) -> 0 | J22: =IF($A22="","",ROUND(IF($B22="支出",-1,1)*SUMIFS(流水本位,流水类别,$A22,流水日期,">="&DATE(管理年度,8,1),流水日期,"<="&EOMONTH(DATE(管理年度,8,1),0)),2)) -> 0 | K22: =IF($A22="","",ROUND(IF($B22="支出",-1,1)*SUMIFS(流水本位,流水类别,$A22,流水日期,">="&DATE(管理年度,9,1),流水日期,"<="&EOMONTH(DATE(管理年度,9,1),0)),2)) -> 0 | L22: =IF($A22="","",ROUND(IF($B22="支出",-1,1)*SUMIFS(流水本位,流水类别,$A22,流水日期,">="&DATE(管理年度,10,1),流水日期,"<="&EOMONTH(DATE(管理年度,10,1),0)),2)) -> 0 | M22: =IF($A22="","",ROUND(IF($B22="支出",-1,1)*SUMIFS(流水本位,流水类别,$A22,流水日期,">="&DATE(管理年度,11,1),流水日期,"<="&EOMONTH(DATE(管理年度,11,1),0)),2)) -> 0 | N22: =IF($A22="","",ROUND(IF($B22="支出",-1,1)*SUMIFS(流水本位,流水类别,$A22,流水日期,">="&DATE(管理年度,12,1),流水日期,"<="&EOMONTH(DATE(管理年度,12,1),0)),2)) -> 0 | O22: =IF($A22="","",ROUND(SUM(C22:N22),2)) -> 0 | P22: =IF(OR($A22="",$B22="内部转账"),"",IFERROR($O22/IF($B22="收入",$O$5,$O$6),"")) -> 0
A23: =IF(参数设置!$O$22="","",参数设置!$O$22) -> 利息支出 | B23: =IF($A23="","",参数设置!$P$22) -> 支出 | C23: =IF($A23="","",ROUND(IF($B23="支出",-1,1)*SUMIFS(流水本位,流水类别,$A23,流水日期,">="&DATE(管理年度,1,1),流水日期,"<="&EOMONTH(DATE(管理年度,1,1),0)),2)) -> 0 | D23: =IF($A23="","",ROUND(IF($B23="支出",-1,1)*SUMIFS(流水本位,流水类别,$A23,流水日期,">="&DATE(管理年度,2,1),流水日期,"<="&EOMONTH(DATE(管理年度,2,1),0)),2)) -> 0 | E23: =IF($A23="","",ROUND(IF($B23="支出",-1,1)*SUMIFS(流水本位,流水类别,$A23,流水日期,">="&DATE(管理年度,3,1),流水日期,"<="&EOMONTH(DATE(管理年度,3,1),0)),2)) -> 0 | F23: =IF($A23="","",ROUND(IF($B23="支出",-1,1)*SUMIFS(流水本位,流水类别,$A23,流水日期,">="&DATE(管理年度,4,1),流水日期,"<="&EOMONTH(DATE(管理年度,4,1),0)),2)) -> 0 | G23: =IF($A23="","",ROUND(IF($B23="支出",-1,1)*SUMIFS(流水本位,流水类别,$A23,流水日期,">="&DATE(管理年度,5,1),流水日期,"<="&EOMONTH(DATE(管理年度,5,1),0)),2)) -> 0 | H23: =IF($A23="","",ROUND(IF($B23="支出",-1,1)*SUMIFS(流水本位,流水类别,$A23,流水日期,">="&DATE(管理年度,6,1),流水日期,"<="&EOMONTH(DATE(管理年度,6,1),0)),2)) -> 0 | I23: =IF($A23="","",ROUND(IF($B23="支出",-1,1)*SUMIFS(流水本位,流水类别,$A23,流水日期,">="&DATE(管理年度,7,1),流水日期,"<="&EOMONTH(DATE(管理年度,7,1),0)),2)) -> 0 | J23: =IF($A23="","",ROUND(IF($B23="支出",-1,1)*SUMIFS(流水本位,流水类别,$A23,流水日期,">="&DATE(管理年度,8,1),流水日期,"<="&EOMONTH(DATE(管理年度,8,1),0)),2)) -> 0 | K23: =IF($A23="","",ROUND(IF($B23="支出",-1,1)*SUMIFS(流水本位,流水类别,$A23,流水日期,">="&DATE(管理年度,9,1),流水日期,"<="&EOMONTH(DATE(管理年度,9,1),0)),2)) -> 0 | L23: =IF($A23="","",ROUND(IF($B23="支出",-1,1)*SUMIFS(流水本位,流水类别,$A23,流水日期,">="&DATE(管理年度,10,1),流水日期,"<="&EOMONTH(DATE(管理年度,10,1),0)),2)) -> 0 | M23: =IF($A23="","",ROUND(IF($B23="支出",-1,1)*SUMIFS(流水本位,流水类别,$A23,流水日期,">="&DATE(管理年度,11,1),流水日期,"<="&EOMONTH(DATE(管理年度,11,1),0)),2)) -> 0 | N23: =IF($A23="","",ROUND(IF($B23="支出",-1,1)*SUMIFS(流水本位,流水类别,$A23,流水日期,">="&DATE(管理年度,12,1),流水日期,"<="&EOMONTH(DATE(管理年度,12,1),0)),2)) -> 0 | O23: =IF($A23="","",ROUND(SUM(C23:N23),2)) -> 0 | P23: =IF(OR($A23="",$B23="内部转账"),"",IFERROR($O23/IF($B23="收入",$O$5,$O$6),"")) -> 0
A24: =IF(参数设置!$O$23="","",参数设置!$O$23) -> 还款 | B24: =IF($A24="","",参数设置!$P$23) -> 支出 | C24: =IF($A24="","",ROUND(IF($B24="支出",-1,1)*SUMIFS(流水本位,流水类别,$A24,流水日期,">="&DATE(管理年度,1,1),流水日期,"<="&EOMONTH(DATE(管理年度,1,1),0)),2)) -> 0 | D24: =IF($A24="","",ROUND(IF($B24="支出",-1,1)*SUMIFS(流水本位,流水类别,$A24,流水日期,">="&DATE(管理年度,2,1),流水日期,"<="&EOMONTH(DATE(管理年度,2,1),0)),2)) -> 0 | E24: =IF($A24="","",ROUND(IF($B24="支出",-1,1)*SUMIFS(流水本位,流水类别,$A24,流水日期,">="&DATE(管理年度,3,1),流水日期,"<="&EOMONTH(DATE(管理年度,3,1),0)),2)) -> 0 | F24: =IF($A24="","",ROUND(IF($B24="支出",-1,1)*SUMIFS(流水本位,流水类别,$A24,流水日期,">="&DATE(管理年度,4,1),流水日期,"<="&EOMONTH(DATE(管理年度,4,1),0)),2)) -> 0 | G24: =IF($A24="","",ROUND(IF($B24="支出",-1,1)*SUMIFS(流水本位,流水类别,$A24,流水日期,">="&DATE(管理年度,5,1),流水日期,"<="&EOMONTH(DATE(管理年度,5,1),0)),2)) -> 0 | H24: =IF($A24="","",ROUND(IF($B24="支出",-1,1)*SUMIFS(流水本位,流水类别,$A24,流水日期,">="&DATE(管理年度,6,1),流水日期,"<="&EOMONTH(DATE(管理年度,6,1),0)),2)) -> 0 | I24: =IF($A24="","",ROUND(IF($B24="支出",-1,1)*SUMIFS(流水本位,流水类别,$A24,流水日期,">="&DATE(管理年度,7,1),流水日期,"<="&EOMONTH(DATE(管理年度,7,1),0)),2)) -> 0 | J24: =IF($A24="","",ROUND(IF($B24="支出",-1,1)*SUMIFS(流水本位,流水类别,$A24,流水日期,">="&DATE(管理年度,8,1),流水日期,"<="&EOMONTH(DATE(管理年度,8,1),0)),2)) -> 0 | K24: =IF($A24="","",ROUND(IF($B24="支出",-1,1)*SUMIFS(流水本位,流水类别,$A24,流水日期,">="&DATE(管理年度,9,1),流水日期,"<="&EOMONTH(DATE(管理年度,9,1),0)),2)) -> 0 | L24: =IF($A24="","",ROUND(IF($B24="支出",-1,1)*SUMIFS(流水本位,流水类别,$A24,流水日期,">="&DATE(管理年度,10,1),流水日期,"<="&EOMONTH(DATE(管理年度,10,1),0)),2)) -> 0 | M24: =IF($A24="","",ROUND(IF($B24="支出",-1,1)*SUMIFS(流水本位,流水类别,$A24,流水日期,">="&DATE(管理年度,11,1),流水日期,"<="&EOMONTH(DATE(管理年度,11,1),0)),2)) -> 0 | N24: =IF($A24="","",ROUND(IF($B24="支出",-1,1)*SUMIFS(流水本位,流水类别,$A24,流水日期,">="&DATE(管理年度,12,1),流水日期,"<="&EOMONTH(DATE(管理年度,12,1),0)),2)) -> 0 | O24: =IF($A24="","",ROUND(SUM(C24:N24),2)) -> 0 | P24: =IF(OR($A24="",$B24="内部转账"),"",IFERROR($O24/IF($B24="收入",$O$5,$O$6),"")) -> 0
A25: =IF(参数设置!$O$24="","",参数设置!$O$24) -> 资产购买 | B25: =IF($A25="","",参数设置!$P$24) -> 支出 | C25: =IF($A25="","",ROUND(IF($B25="支出",-1,1)*SUMIFS(流水本位,流水类别,$A25,流水日期,">="&DATE(管理年度,1,1),流水日期,"<="&EOMONTH(DATE(管理年度,1,1),0)),2)) -> 0 | D25: =IF($A25="","",ROUND(IF($B25="支出",-1,1)*SUMIFS(流水本位,流水类别,$A25,流水日期,">="&DATE(管理年度,2,1),流水日期,"<="&EOMONTH(DATE(管理年度,2,1),0)),2)) -> 0 | E25: =IF($A25="","",ROUND(IF($B25="支出",-1,1)*SUMIFS(流水本位,流水类别,$A25,流水日期,">="&DATE(管理年度,3,1),流水日期,"<="&EOMONTH(DATE(管理年度,3,1),0)),2)) -> 0 | F25: =IF($A25="","",ROUND(IF($B25="支出",-1,1)*SUMIFS(流水本位,流水类别,$A25,流水日期,">="&DATE(管理年度,4,1),流水日期,"<="&EOMONTH(DATE(管理年度,4,1),0)),2)) -> 0 | G25: =IF($A25="","",ROUND(IF($B25="支出",-1,1)*SUMIFS(流水本位,流水类别,$A25,流水日期,">="&DATE(管理年度,5,1),流水日期,"<="&EOMONTH(DATE(管理年度,5,1),0)),2)) -> 0 | H25: =IF($A25="","",ROUND(IF($B25="支出",-1,1)*SUMIFS(流水本位,流水类别,$A25,流水日期,">="&DATE(管理年度,6,1),流水日期,"<="&EOMONTH(DATE(管理年度,6,1),0)),2)) -> 0 | I25: =IF($A25="","",ROUND(IF($B25="支出",-1,1)*SUMIFS(流水本位,流水类别,$A25,流水日期,">="&DATE(管理年度,7,1),流水日期,"<="&EOMONTH(DATE(管理年度,7,1),0)),2)) -> 0 | J25: =IF($A25="","",ROUND(IF($B25="支出",-1,1)*SUMIFS(流水本位,流水类别,$A25,流水日期,">="&DATE(管理年度,8,1),流水日期,"<="&EOMONTH(DATE(管理年度,8,1),0)),2)) -> 0 | K25: =IF($A25="","",ROUND(IF($B25="支出",-1,1)*SUMIFS(流水本位,流水类别,$A25,流水日期,">="&DATE(管理年度,9,1),流水日期,"<="&EOMONTH(DATE(管理年度,9,1),0)),2)) -> 0 | L25: =IF($A25="","",ROUND(IF($B25="支出",-1,1)*SUMIFS(流水本位,流水类别,$A25,流水日期,">="&DATE(管理年度,10,1),流水日期,"<="&EOMONTH(DATE(管理年度,10,1),0)),2)) -> 0 | M25: =IF($A25="","",ROUND(IF($B25="支出",-1,1)*SUMIFS(流水本位,流水类别,$A25,流水日期,">="&DATE(管理年度,11,1),流水日期,"<="&EOMONTH(DATE(管理年度,11,1),0)),2)) -> 0 | N25: =IF($A25="","",ROUND(IF($B25="支出",-1,1)*SUMIFS(流水本位,流水类别,$A25,流水日期,">="&DATE(管理年度,12,1),流水日期,"<="&EOMONTH(DATE(管理年度,12,1),0)),2)) -> 0 | O25: =IF($A25="","",ROUND(SUM(C25:N25),2)) -> 0 | P25: =IF(OR($A25="",$B25="内部转账"),"",IFERROR($O25/IF($B25="收入",$O$5,$O$6),"")) -> 0
A26: =IF(参数设置!$O$25="","",参数设置!$O$25) -> 股利分配 | B26: =IF($A26="","",参数设置!$P$25) -> 支出 | C26: =IF($A26="","",ROUND(IF($B26="支出",-1,1)*SUMIFS(流水本位,流水类别,$A26,流水日期,">="&DATE(管理年度,1,1),流水日期,"<="&EOMONTH(DATE(管理年度,1,1),0)),2)) -> 0 | D26: =IF($A26="","",ROUND(IF($B26="支出",-1,1)*SUMIFS(流水本位,流水类别,$A26,流水日期,">="&DATE(管理年度,2,1),流水日期,"<="&EOMONTH(DATE(管理年度,2,1),0)),2)) -> 0 | E26: =IF($A26="","",ROUND(IF($B26="支出",-1,1)*SUMIFS(流水本位,流水类别,$A26,流水日期,">="&DATE(管理年度,3,1),流水日期,"<="&EOMONTH(DATE(管理年度,3,1),0)),2)) -> 0 | F26: =IF($A26="","",ROUND(IF($B26="支出",-1,1)*SUMIFS(流水本位,流水类别,$A26,流水日期,">="&DATE(管理年度,4,1),流水日期,"<="&EOMONTH(DATE(管理年度,4,1),0)),2)) -> 0 | G26: =IF($A26="","",ROUND(IF($B26="支出",-1,1)*SUMIFS(流水本位,流水类别,$A26,流水日期,">="&DATE(管理年度,5,1),流水日期,"<="&EOMONTH(DATE(管理年度,5,1),0)),2)) -> 0 | H26: =IF($A26="","",ROUND(IF($B26="支出",-1,1)*SUMIFS(流水本位,流水类别,$A26,流水日期,">="&DATE(管理年度,6,1),流水日期,"<="&EOMONTH(DATE(管理年度,6,1),0)),2)) -> 0 | I26: =IF($A26="","",ROUND(IF($B26="支出",-1,1)*SUMIFS(流水本位,流水类别,$A26,流水日期,">="&DATE(管理年度,7,1),流水日期,"<="&EOMONTH(DATE(管理年度,7,1),0)),2)) -> 0 | J26: =IF($A26="","",ROUND(IF($B26="支出",-1,1)*SUMIFS(流水本位,流水类别,$A26,流水日期,">="&DATE(管理年度,8,1),流水日期,"<="&EOMONTH(DATE(管理年度,8,1),0)),2)) -> 0 | K26: =IF($A26="","",ROUND(IF($B26="支出",-1,1)*SUMIFS(流水本位,流水类别,$A26,流水日期,">="&DATE(管理年度,9,1),流水日期,"<="&EOMONTH(DATE(管理年度,9,1),0)),2)) -> 0 | L26: =IF($A26="","",ROUND(IF($B26="支出",-1,1)*SUMIFS(流水本位,流水类别,$A26,流水日期,">="&DATE(管理年度,10,1),流水日期,"<="&EOMONTH(DATE(管理年度,10,1),0)),2)) -> 0 | M26: =IF($A26="","",ROUND(IF($B26="支出",-1,1)*SUMIFS(流水本位,流水类别,$A26,流水日期,">="&DATE(管理年度,11,1),流水日期,"<="&EOMONTH(DATE(管理年度,11,1),0)),2)) -> 0 | N26: =IF($A26="","",ROUND(IF($B26="支出",-1,1)*SUMIFS(流水本位,流水类别,$A26,流水日期,">="&DATE(管理年度,12,1),流水日期,"<="&EOMONTH(DATE(管理年度,12,1),0)),2)) -> 0 | O26: =IF($A26="","",ROUND(SUM(C26:N26),2)) -> 0 | P26: =IF(OR($A26="",$B26="内部转账"),"",IFERROR($O26/IF($B26="收入",$O$5,$O$6),"")) -> 0
A27: =IF(参数设置!$O$26="","",参数设置!$O$26) -> 内部转账 | B27: =IF($A27="","",参数设置!$P$26) -> 内部转账 | C27: =IF($A27="","",ROUND(IF($B27="支出",-1,1)*SUMIFS(流水本位,流水类别,$A27,流水日期,">="&DATE(管理年度,1,1),流水日期,"<="&EOMONTH(DATE(管理年度,1,1),0)),2)) -> 0 | D27: =IF($A27="","",ROUND(IF($B27="支出",-1,1)*SUMIFS(流水本位,流水类别,$A27,流水日期,">="&DATE(管理年度,2,1),流水日期,"<="&EOMONTH(DATE(管理年度,2,1),0)),2)) -> 0 | E27: =IF($A27="","",ROUND(IF($B27="支出",-1,1)*SUMIFS(流水本位,流水类别,$A27,流水日期,">="&DATE(管理年度,3,1),流水日期,"<="&EOMONTH(DATE(管理年度,3,1),0)),2)) -> 0 | F27: =IF($A27="","",ROUND(IF($B27="支出",-1,1)*SUMIFS(流水本位,流水类别,$A27,流水日期,">="&DATE(管理年度,4,1),流水日期,"<="&EOMONTH(DATE(管理年度,4,1),0)),2)) -> 0 | G27: =IF($A27="","",ROUND(IF($B27="支出",-1,1)*SUMIFS(流水本位,流水类别,$A27,流水日期,">="&DATE(管理年度,5,1),流水日期,"<="&EOMONTH(DATE(管理年度,5,1),0)),2)) -> 0 | H27: =IF($A27="","",ROUND(IF($B27="支出",-1,1)*SUMIFS(流水本位,流水类别,$A27,流水日期,">="&DATE(管理年度,6,1),流水日期,"<="&EOMONTH(DATE(管理年度,6,1),0)),2)) -> 0 | I27: =IF($A27="","",ROUND(IF($B27="支出",-1,1)*SUMIFS(流水本位,流水类别,$A27,流水日期,">="&DATE(管理年度,7,1),流水日期,"<="&EOMONTH(DATE(管理年度,7,1),0)),2)) -> 0 | J27: =IF($A27="","",ROUND(IF($B27="支出",-1,1)*SUMIFS(流水本位,流水类别,$A27,流水日期,">="&DATE(管理年度,8,1),流水日期,"<="&EOMONTH(DATE(管理年度,8,1),0)),2)) -> 0 | K27: =IF($A27="","",ROUND(IF($B27="支出",-1,1)*SUMIFS(流水本位,流水类别,$A27,流水日期,">="&DATE(管理年度,9,1),流水日期,"<="&EOMONTH(DATE(管理年度,9,1),0)),2)) -> 0 | L27: =IF($A27="","",ROUND(IF($B27="支出",-1,1)*SUMIFS(流水本位,流水类别,$A27,流水日期,">="&DATE(管理年度,10,1),流水日期,"<="&EOMONTH(DATE(管理年度,10,1),0)),2)) -> 0 | M27: =IF($A27="","",ROUND(IF($B27="支出",-1,1)*SUMIFS(流水本位,流水类别,$A27,流水日期,">="&DATE(管理年度,11,1),流水日期,"<="&EOMONTH(DATE(管理年度,11,1),0)),2)) -> 0 | N27: =IF($A27="","",ROUND(IF($B27="支出",-1,1)*SUMIFS(流水本位,流水类别,$A27,流水日期,">="&DATE(管理年度,12,1),流水日期,"<="&EOMONTH(DATE(管理年度,12,1),0)),2)) -> 0 | O27: =IF($A27="","",ROUND(SUM(C27:N27),2)) -> 0 | P27: =IF(OR($A27="",$B27="内部转账"),"",IFERROR($O27/IF($B27="收入",$O$5,$O$6),""))
A28: =IF(参数设置!$O$27="","",参数设置!$O$27) -> 购汇/结汇 | B28: =IF($A28="","",参数设置!$P$27) -> 内部转账 | C28: =IF($A28="","",ROUND(IF($B28="支出",-1,1)*SUMIFS(流水本位,流水类别,$A28,流水日期,">="&DATE(管理年度,1,1),流水日期,"<="&EOMONTH(DATE(管理年度,1,1),0)),2)) -> 0 | D28: =IF($A28="","",ROUND(IF($B28="支出",-1,1)*SUMIFS(流水本位,流水类别,$A28,流水日期,">="&DATE(管理年度,2,1),流水日期,"<="&EOMONTH(DATE(管理年度,2,1),0)),2)) -> 0 | E28: =IF($A28="","",ROUND(IF($B28="支出",-1,1)*SUMIFS(流水本位,流水类别,$A28,流水日期,">="&DATE(管理年度,3,1),流水日期,"<="&EOMONTH(DATE(管理年度,3,1),0)),2)) -> 0 | F28: =IF($A28="","",ROUND(IF($B28="支出",-1,1)*SUMIFS(流水本位,流水类别,$A28,流水日期,">="&DATE(管理年度,4,1),流水日期,"<="&EOMONTH(DATE(管理年度,4,1),0)),2)) -> 0 | G28: =IF($A28="","",ROUND(IF($B28="支出",-1,1)*SUMIFS(流水本位,流水类别,$A28,流水日期,">="&DATE(管理年度,5,1),流水日期,"<="&EOMONTH(DATE(管理年度,5,1),0)),2)) -> 0 | H28: =IF($A28="","",ROUND(IF($B28="支出",-1,1)*SUMIFS(流水本位,流水类别,$A28,流水日期,">="&DATE(管理年度,6,1),流水日期,"<="&EOMONTH(DATE(管理年度,6,1),0)),2)) -> 0 | I28: =IF($A28="","",ROUND(IF($B28="支出",-1,1)*SUMIFS(流水本位,流水类别,$A28,流水日期,">="&DATE(管理年度,7,1),流水日期,"<="&EOMONTH(DATE(管理年度,7,1),0)),2)) -> 0 | J28: =IF($A28="","",ROUND(IF($B28="支出",-1,1)*SUMIFS(流水本位,流水类别,$A28,流水日期,">="&DATE(管理年度,8,1),流水日期,"<="&EOMONTH(DATE(管理年度,8,1),0)),2)) -> 0 | K28: =IF($A28="","",ROUND(IF($B28="支出",-1,1)*SUMIFS(流水本位,流水类别,$A28,流水日期,">="&DATE(管理年度,9,1),流水日期,"<="&EOMONTH(DATE(管理年度,9,1),0)),2)) -> 0 | L28: =IF($A28="","",ROUND(IF($B28="支出",-1,1)*SUMIFS(流水本位,流水类别,$A28,流水日期,">="&DATE(管理年度,10,1),流水日期,"<="&EOMONTH(DATE(管理年度,10,1),0)),2)) -> 0 | M28: =IF($A28="","",ROUND(IF($B28="支出",-1,1)*SUMIFS(流水本位,流水类别,$A28,流水日期,">="&DATE(管理年度,11,1),流水日期,"<="&EOMONTH(DATE(管理年度,11,1),0)),2)) -> 0 | N28: =IF($A28="","",ROUND(IF($B28="支出",-1,1)*SUMIFS(流水本位,流水类别,$A28,流水日期,">="&DATE(管理年度,12,1),流水日期,"<="&EOMONTH(DATE(管理年度,12,1),0)),2)) -> 0 | O28: =IF($A28="","",ROUND(SUM(C28:N28),2)) -> 0 | P28: =IF(OR($A28="",$B28="内部转账"),"",IFERROR($O28/IF($B28="收入",$O$5,$O$6),""))
A29: =IF(参数设置!$O$28="","",参数设置!$O$28) | B29: =IF($A29="","",参数设置!$P$28) | C29: =IF($A29="","",ROUND(IF($B29="支出",-1,1)*SUMIFS(流水本位,流水类别,$A29,流水日期,">="&DATE(管理年度,1,1),流水日期,"<="&EOMONTH(DATE(管理年度,1,1),0)),2)) | D29: =IF($A29="","",ROUND(IF($B29="支出",-1,1)*SUMIFS(流水本位,流水类别,$A29,流水日期,">="&DATE(管理年度,2,1),流水日期,"<="&EOMONTH(DATE(管理年度,2,1),0)),2)) | E29: =IF($A29="","",ROUND(IF($B29="支出",-1,1)*SUMIFS(流水本位,流水类别,$A29,流水日期,">="&DATE(管理年度,3,1),流水日期,"<="&EOMONTH(DATE(管理年度,3,1),0)),2)) | F29: =IF($A29="","",ROUND(IF($B29="支出",-1,1)*SUMIFS(流水本位,流水类别,$A29,流水日期,">="&DATE(管理年度,4,1),流水日期,"<="&EOMONTH(DATE(管理年度,4,1),0)),2)) | G29: =IF($A29="","",ROUND(IF($B29="支出",-1,1)*SUMIFS(流水本位,流水类别,$A29,流水日期,">="&DATE(管理年度,5,1),流水日期,"<="&EOMONTH(DATE(管理年度,5,1),0)),2)) | H29: =IF($A29="","",ROUND(IF($B29="支出",-1,1)*SUMIFS(流水本位,流水类别,$A29,流水日期,">="&DATE(管理年度,6,1),流水日期,"<="&EOMONTH(DATE(管理年度,6,1),0)),2)) | I29: =IF($A29="","",ROUND(IF($B29="支出",-1,1)*SUMIFS(流水本位,流水类别,$A29,流水日期,">="&DATE(管理年度,7,1),流水日期,"<="&EOMONTH(DATE(管理年度,7,1),0)),2)) | J29: =IF($A29="","",ROUND(IF($B29="支出",-1,1)*SUMIFS(流水本位,流水类别,$A29,流水日期,">="&DATE(管理年度,8,1),流水日期,"<="&EOMONTH(DATE(管理年度,8,1),0)),2)) | K29: =IF($A29="","",ROUND(IF($B29="支出",-1,1)*SUMIFS(流水本位,流水类别,$A29,流水日期,">="&DATE(管理年度,9,1),流水日期,"<="&EOMONTH(DATE(管理年度,9,1),0)),2)) | L29: =IF($A29="","",ROUND(IF($B29="支出",-1,1)*SUMIFS(流水本位,流水类别,$A29,流水日期,">="&DATE(管理年度,10,1),流水日期,"<="&EOMONTH(DATE(管理年度,10,1),0)),2)) | M29: =IF($A29="","",ROUND(IF($B29="支出",-1,1)*SUMIFS(流水本位,流水类别,$A29,流水日期,">="&DATE(管理年度,11,1),流水日期,"<="&EOMONTH(DATE(管理年度,11,1),0)),2)) | N29: =IF($A29="","",ROUND(IF($B29="支出",-1,1)*SUMIFS(流水本位,流水类别,$A29,流水日期,">="&DATE(管理年度,12,1),流水日期,"<="&EOMONTH(DATE(管理年度,12,1),0)),2)) | O29: =IF($A29="","",ROUND(SUM(C29:N29),2)) | P29: =IF(OR($A29="",$B29="内部转账"),"",IFERROR($O29/IF($B29="收入",$O$5,$O$6),""))
A30: =IF(参数设置!$O$29="","",参数设置!$O$29) | B30: =IF($A30="","",参数设置!$P$29) | C30: =IF($A30="","",ROUND(IF($B30="支出",-1,1)*SUMIFS(流水本位,流水类别,$A30,流水日期,">="&DATE(管理年度,1,1),流水日期,"<="&EOMONTH(DATE(管理年度,1,1),0)),2)) | D30: =IF($A30="","",ROUND(IF($B30="支出",-1,1)*SUMIFS(流水本位,流水类别,$A30,流水日期,">="&DATE(管理年度,2,1),流水日期,"<="&EOMONTH(DATE(管理年度,2,1),0)),2)) | E30: =IF($A30="","",ROUND(IF($B30="支出",-1,1)*SUMIFS(流水本位,流水类别,$A30,流水日期,">="&DATE(管理年度,3,1),流水日期,"<="&EOMONTH(DATE(管理年度,3,1),0)),2)) | F30: =IF($A30="","",ROUND(IF($B30="支出",-1,1)*SUMIFS(流水本位,流水类别,$A30,流水日期,">="&DATE(管理年度,4,1),流水日期,"<="&EOMONTH(DATE(管理年度,4,1),0)),2)) | G30: =IF($A30="","",ROUND(IF($B30="支出",-1,1)*SUMIFS(流水本位,流水类别,$A30,流水日期,">="&DATE(管理年度,5,1),流水日期,"<="&EOMONTH(DATE(管理年度,5,1),0)),2)) | H30: =IF($A30="","",ROUND(IF($B30="支出",-1,1)*SUMIFS(流水本位,流水类别,$A30,流水日期,">="&DATE(管理年度,6,1),流水日期,"<="&EOMONTH(DATE(管理年度,6,1),0)),2)) | I30: =IF($A30="","",ROUND(IF($B30="支出",-1,1)*SUMIFS(流水本位,流水类别,$A30,流水日期,">="&DATE(管理年度,7,1),流水日期,"<="&EOMONTH(DATE(管理年度,7,1),0)),2)) | J30: =IF($A30="","",ROUND(IF($B30="支出",-1,1)*SUMIFS(流水本位,流水类别,$A30,流水日期,">="&DATE(管理年度,8,1),流水日期,"<="&EOMONTH(DATE(管理年度,8,1),0)),2)) | K30: =IF($A30="","",ROUND(IF($B30="支出",-1,1)*SUMIFS(流水本位,流水类别,$A30,流水日期,">="&DATE(管理年度,9,1),流水日期,"<="&EOMONTH(DATE(管理年度,9,1),0)),2)) | L30: =IF($A30="","",ROUND(IF($B30="支出",-1,1)*SUMIFS(流水本位,流水类别,$A30,流水日期,">="&DATE(管理年度,10,1),流水日期,"<="&EOMONTH(DATE(管理年度,10,1),0)),2)) | M30: =IF($A30="","",ROUND(IF($B30="支出",-1,1)*SUMIFS(流水本位,流水类别,$A30,流水日期,">="&DATE(管理年度,11,1),流水日期,"<="&EOMONTH(DATE(管理年度,11,1),0)),2)) | N30: =IF($A30="","",ROUND(IF($B30="支出",-1,1)*SUMIFS(流水本位,流水类别,$A30,流水日期,">="&DATE(管理年度,12,1),流水日期,"<="&EOMONTH(DATE(管理年度,12,1),0)),2)) | O30: =IF($A30="","",ROUND(SUM(C30:N30),2)) | P30: =IF(OR($A30="",$B30="内部转账"),"",IFERROR($O30/IF($B30="收入",$O$5,$O$6),""))
A31: =IF(参数设置!$O$30="","",参数设置!$O$30) | B31: =IF($A31="","",参数设置!$P$30) | C31: =IF($A31="","",ROUND(IF($B31="支出",-1,1)*SUMIFS(流水本位,流水类别,$A31,流水日期,">="&DATE(管理年度,1,1),流水日期,"<="&EOMONTH(DATE(管理年度,1,1),0)),2)) | D31: =IF($A31="","",ROUND(IF($B31="支出",-1,1)*SUMIFS(流水本位,流水类别,$A31,流水日期,">="&DATE(管理年度,2,1),流水日期,"<="&EOMONTH(DATE(管理年度,2,1),0)),2)) | E31: =IF($A31="","",ROUND(IF($B31="支出",-1,1)*SUMIFS(流水本位,流水类别,$A31,流水日期,">="&DATE(管理年度,3,1),流水日期,"<="&EOMONTH(DATE(管理年度,3,1),0)),2)) | F31: =IF($A31="","",ROUND(IF($B31="支出",-1,1)*SUMIFS(流水本位,流水类别,$A31,流水日期,">="&DATE(管理年度,4,1),流水日期,"<="&EOMONTH(DATE(管理年度,4,1),0)),2)) | G31: =IF($A31="","",ROUND(IF($B31="支出",-1,1)*SUMIFS(流水本位,流水类别,$A31,流水日期,">="&DATE(管理年度,5,1),流水日期,"<="&EOMONTH(DATE(管理年度,5,1),0)),2)) | H31: =IF($A31="","",ROUND(IF($B31="支出",-1,1)*SUMIFS(流水本位,流水类别,$A31,流水日期,">="&DATE(管理年度,6,1),流水日期,"<="&EOMONTH(DATE(管理年度,6,1),0)),2)) | I31: =IF($A31="","",ROUND(IF($B31="支出",-1,1)*SUMIFS(流水本位,流水类别,$A31,流水日期,">="&DATE(管理年度,7,1),流水日期,"<="&EOMONTH(DATE(管理年度,7,1),0)),2)) | J31: =IF($A31="","",ROUND(IF($B31="支出",-1,1)*SUMIFS(流水本位,流水类别,$A31,流水日期,">="&DATE(管理年度,8,1),流水日期,"<="&EOMONTH(DATE(管理年度,8,1),0)),2)) | K31: =IF($A31="","",ROUND(IF($B31="支出",-1,1)*SUMIFS(流水本位,流水类别,$A31,流水日期,">="&DATE(管理年度,9,1),流水日期,"<="&EOMONTH(DATE(管理年度,9,1),0)),2)) | L31: =IF($A31="","",ROUND(IF($B31="支出",-1,1)*SUMIFS(流水本位,流水类别,$A31,流水日期,">="&DATE(管理年度,10,1),流水日期,"<="&EOMONTH(DATE(管理年度,10,1),0)),2)) | M31: =IF($A31="","",ROUND(IF($B31="支出",-1,1)*SUMIFS(流水本位,流水类别,$A31,流水日期,">="&DATE(管理年度,11,1),流水日期,"<="&EOMONTH(DATE(管理年度,11,1),0)),2)) | N31: =IF($A31="","",ROUND(IF($B31="支出",-1,1)*SUMIFS(流水本位,流水类别,$A31,流水日期,">="&DATE(管理年度,12,1),流水日期,"<="&EOMONTH(DATE(管理年度,12,1),0)),2)) | O31: =IF($A31="","",ROUND(SUM(C31:N31),2)) | P31: =IF(OR($A31="",$B31="内部转账"),"",IFERROR($O31/IF($B31="收入",$O$5,$O$6),""))
A32: =IF(参数设置!$O$31="","",参数设置!$O$31) | B32: =IF($A32="","",参数设置!$P$31) | C32: =IF($A32="","",ROUND(IF($B32="支出",-1,1)*SUMIFS(流水本位,流水类别,$A32,流水日期,">="&DATE(管理年度,1,1),流水日期,"<="&EOMONTH(DATE(管理年度,1,1),0)),2)) | D32: =IF($A32="","",ROUND(IF($B32="支出",-1,1)*SUMIFS(流水本位,流水类别,$A32,流水日期,">="&DATE(管理年度,2,1),流水日期,"<="&EOMONTH(DATE(管理年度,2,1),0)),2)) | E32: =IF($A32="","",ROUND(IF($B32="支出",-1,1)*SUMIFS(流水本位,流水类别,$A32,流水日期,">="&DATE(管理年度,3,1),流水日期,"<="&EOMONTH(DATE(管理年度,3,1),0)),2)) | F32: =IF($A32="","",ROUND(IF($B32="支出",-1,1)*SUMIFS(流水本位,流水类别,$A32,流水日期,">="&DATE(管理年度,4,1),流水日期,"<="&EOMONTH(DATE(管理年度,4,1),0)),2)) | G32: =IF($A32="","",ROUND(IF($B32="支出",-1,1)*SUMIFS(流水本位,流水类别,$A32,流水日期,">="&DATE(管理年度,5,1),流水日期,"<="&EOMONTH(DATE(管理年度,5,1),0)),2)) | H32: =IF($A32="","",ROUND(IF($B32="支出",-1,1)*SUMIFS(流水本位,流水类别,$A32,流水日期,">="&DATE(管理年度,6,1),流水日期,"<="&EOMONTH(DATE(管理年度,6,1),0)),2)) | I32: =IF($A32="","",ROUND(IF($B32="支出",-1,1)*SUMIFS(流水本位,流水类别,$A32,流水日期,">="&DATE(管理年度,7,1),流水日期,"<="&EOMONTH(DATE(管理年度,7,1),0)),2)) | J32: =IF($A32="","",ROUND(IF($B32="支出",-1,1)*SUMIFS(流水本位,流水类别,$A32,流水日期,">="&DATE(管理年度,8,1),流水日期,"<="&EOMONTH(DATE(管理年度,8,1),0)),2)) | K32: =IF($A32="","",ROUND(IF($B32="支出",-1,1)*SUMIFS(流水本位,流水类别,$A32,流水日期,">="&DATE(管理年度,9,1),流水日期,"<="&EOMONTH(DATE(管理年度,9,1),0)),2)) | L32: =IF($A32="","",ROUND(IF($B32="支出",-1,1)*SUMIFS(流水本位,流水类别,$A32,流水日期,">="&DATE(管理年度,10,1),流水日期,"<="&EOMONTH(DATE(管理年度,10,1),0)),2)) | M32: =IF($A32="","",ROUND(IF($B32="支出",-1,1)*SUMIFS(流水本位,流水类别,$A32,流水日期,">="&DATE(管理年度,11,1),流水日期,"<="&EOMONTH(DATE(管理年度,11,1),0)),2)) | N32: =IF($A32="","",ROUND(IF($B32="支出",-1,1)*SUMIFS(流水本位,流水类别,$A32,流水日期,">="&DATE(管理年度,12,1),流水日期,"<="&EOMONTH(DATE(管理年度,12,1),0)),2)) | O32: =IF($A32="","",ROUND(SUM(C32:N32),2)) | P32: =IF(OR($A32="",$B32="内部转账"),"",IFERROR($O32/IF($B32="收入",$O$5,$O$6),""))
A33: =IF(参数设置!$O$32="","",参数设置!$O$32) | B33: =IF($A33="","",参数设置!$P$32) | C33: =IF($A33="","",ROUND(IF($B33="支出",-1,1)*SUMIFS(流水本位,流水类别,$A33,流水日期,">="&DATE(管理年度,1,1),流水日期,"<="&EOMONTH(DATE(管理年度,1,1),0)),2)) | D33: =IF($A33="","",ROUND(IF($B33="支出",-1,1)*SUMIFS(流水本位,流水类别,$A33,流水日期,">="&DATE(管理年度,2,1),流水日期,"<="&EOMONTH(DATE(管理年度,2,1),0)),2)) | E33: =IF($A33="","",ROUND(IF($B33="支出",-1,1)*SUMIFS(流水本位,流水类别,$A33,流水日期,">="&DATE(管理年度,3,1),流水日期,"<="&EOMONTH(DATE(管理年度,3,1),0)),2)) | F33: =IF($A33="","",ROUND(IF($B33="支出",-1,1)*SUMIFS(流水本位,流水类别,$A33,流水日期,">="&DATE(管理年度,4,1),流水日期,"<="&EOMONTH(DATE(管理年度,4,1),0)),2)) | G33: =IF($A33="","",ROUND(IF($B33="支出",-1,1)*SUMIFS(流水本位,流水类别,$A33,流水日期,">="&DATE(管理年度,5,1),流水日期,"<="&EOMONTH(DATE(管理年度,5,1),0)),2)) | H33: =IF($A33="","",ROUND(IF($B33="支出",-1,1)*SUMIFS(流水本位,流水类别,$A33,流水日期,">="&DATE(管理年度,6,1),流水日期,"<="&EOMONTH(DATE(管理年度,6,1),0)),2)) | I33: =IF($A33="","",ROUND(IF($B33="支出",-1,1)*SUMIFS(流水本位,流水类别,$A33,流水日期,">="&DATE(管理年度,7,1),流水日期,"<="&EOMONTH(DATE(管理年度,7,1),0)),2)) | J33: =IF($A33="","",ROUND(IF($B33="支出",-1,1)*SUMIFS(流水本位,流水类别,$A33,流水日期,">="&DATE(管理年度,8,1),流水日期,"<="&EOMONTH(DATE(管理年度,8,1),0)),2)) | K33: =IF($A33="","",ROUND(IF($B33="支出",-1,1)*SUMIFS(流水本位,流水类别,$A33,流水日期,">="&DATE(管理年度,9,1),流水日期,"<="&EOMONTH(DATE(管理年度,9,1),0)),2)) | L33: =IF($A33="","",ROUND(IF($B33="支出",-1,1)*SUMIFS(流水本位,流水类别,$A33,流水日期,">="&DATE(管理年度,10,1),流水日期,"<="&EOMONTH(DATE(管理年度,10,1),0)),2)) | M33: =IF($A33="","",ROUND(IF($B33="支出",-1,1)*SUMIFS(流水本位,流水类别,$A33,流水日期,">="&DATE(管理年度,11,1),流水日期,"<="&EOMONTH(DATE(管理年度,11,1),0)),2)) | N33: =IF($A33="","",ROUND(IF($B33="支出",-1,1)*SUMIFS(流水本位,流水类别,$A33,流水日期,">="&DATE(管理年度,12,1),流水日期,"<="&EOMONTH(DATE(管理年度,12,1),0)),2)) | O33: =IF($A33="","",ROUND(SUM(C33:N33),2)) | P33: =IF(OR($A33="",$B33="内部转账"),"",IFERROR($O33/IF($B33="收入",$O$5,$O$6),""))
A34: =IF(参数设置!$O$33="","",参数设置!$O$33) | B34: =IF($A34="","",参数设置!$P$33) | C34: =IF($A34="","",ROUND(IF($B34="支出",-1,1)*SUMIFS(流水本位,流水类别,$A34,流水日期,">="&DATE(管理年度,1,1),流水日期,"<="&EOMONTH(DATE(管理年度,1,1),0)),2)) | D34: =IF($A34="","",ROUND(IF($B34="支出",-1,1)*SUMIFS(流水本位,流水类别,$A34,流水日期,">="&DATE(管理年度,2,1),流水日期,"<="&EOMONTH(DATE(管理年度,2,1),0)),2)) | E34: =IF($A34="","",ROUND(IF($B34="支出",-1,1)*SUMIFS(流水本位,流水类别,$A34,流水日期,">="&DATE(管理年度,3,1),流水日期,"<="&EOMONTH(DATE(管理年度,3,1),0)),2)) | F34: =IF($A34="","",ROUND(IF($B34="支出",-1,1)*SUMIFS(流水本位,流水类别,$A34,流水日期,">="&DATE(管理年度,4,1),流水日期,"<="&EOMONTH(DATE(管理年度,4,1),0)),2)) | G34: =IF($A34="","",ROUND(IF($B34="支出",-1,1)*SUMIFS(流水本位,流水类别,$A34,流水日期,">="&DATE(管理年度,5,1),流水日期,"<="&EOMONTH(DATE(管理年度,5,1),0)),2)) | H34: =IF($A34="","",ROUND(IF($B34="支出",-1,1)*SUMIFS(流水本位,流水类别,$A34,流水日期,">="&DATE(管理年度,6,1),流水日期,"<="&EOMONTH(DATE(管理年度,6,1),0)),2)) | I34: =IF($A34="","",ROUND(IF($B34="支出",-1,1)*SUMIFS(流水本位,流水类别,$A34,流水日期,">="&DATE(管理年度,7,1),流水日期,"<="&EOMONTH(DATE(管理年度,7,1),0)),2)) | J34: =IF($A34="","",ROUND(IF($B34="支出",-1,1)*SUMIFS(流水本位,流水类别,$A34,流水日期,">="&DATE(管理年度,8,1),流水日期,"<="&EOMONTH(DATE(管理年度,8,1),0)),2)) | K34: =IF($A34="","",ROUND(IF($B34="支出",-1,1)*SUMIFS(流水本位,流水类别,$A34,流水日期,">="&DATE(管理年度,9,1),流水日期,"<="&EOMONTH(DATE(管理年度,9,1),0)),2)) | L34: =IF($A34="","",ROUND(IF($B34="支出",-1,1)*SUMIFS(流水本位,流水类别,$A34,流水日期,">="&DATE(管理年度,10,1),流水日期,"<="&EOMONTH(DATE(管理年度,10,1),0)),2)) | M34: =IF($A34="","",ROUND(IF($B34="支出",-1,1)*SUMIFS(流水本位,流水类别,$A34,流水日期,">="&DATE(管理年度,11,1),流水日期,"<="&EOMONTH(DATE(管理年度,11,1),0)),2)) | N34: =IF($A34="","",ROUND(IF($B34="支出",-1,1)*SUMIFS(流水本位,流水类别,$A34,流水日期,">="&DATE(管理年度,12,1),流水日期,"<="&EOMONTH(DATE(管理年度,12,1),0)),2)) | O34: =IF($A34="","",ROUND(SUM(C34:N34),2)) | P34: =IF(OR($A34="",$B34="内部转账"),"",IFERROR($O34/IF($B34="收入",$O$5,$O$6),""))
A35: =IF(参数设置!$O$34="","",参数设置!$O$34) | B35: =IF($A35="","",参数设置!$P$34) | C35: =IF($A35="","",ROUND(IF($B35="支出",-1,1)*SUMIFS(流水本位,流水类别,$A35,流水日期,">="&DATE(管理年度,1,1),流水日期,"<="&EOMONTH(DATE(管理年度,1,1),0)),2)) | D35: =IF($A35="","",ROUND(IF($B35="支出",-1,1)*SUMIFS(流水本位,流水类别,$A35,流水日期,">="&DATE(管理年度,2,1),流水日期,"<="&EOMONTH(DATE(管理年度,2,1),0)),2)) | E35: =IF($A35="","",ROUND(IF($B35="支出",-1,1)*SUMIFS(流水本位,流水类别,$A35,流水日期,">="&DATE(管理年度,3,1),流水日期,"<="&EOMONTH(DATE(管理年度,3,1),0)),2)) | F35: =IF($A35="","",ROUND(IF($B35="支出",-1,1)*SUMIFS(流水本位,流水类别,$A35,流水日期,">="&DATE(管理年度,4,1),流水日期,"<="&EOMONTH(DATE(管理年度,4,1),0)),2)) | G35: =IF($A35="","",ROUND(IF($B35="支出",-1,1)*SUMIFS(流水本位,流水类别,$A35,流水日期,">="&DATE(管理年度,5,1),流水日期,"<="&EOMONTH(DATE(管理年度,5,1),0)),2)) | H35: =IF($A35="","",ROUND(IF($B35="支出",-1,1)*SUMIFS(流水本位,流水类别,$A35,流水日期,">="&DATE(管理年度,6,1),流水日期,"<="&EOMONTH(DATE(管理年度,6,1),0)),2)) | I35: =IF($A35="","",ROUND(IF($B35="支出",-1,1)*SUMIFS(流水本位,流水类别,$A35,流水日期,">="&DATE(管理年度,7,1),流水日期,"<="&EOMONTH(DATE(管理年度,7,1),0)),2)) | J35: =IF($A35="","",ROUND(IF($B35="支出",-1,1)*SUMIFS(流水本位,流水类别,$A35,流水日期,">="&DATE(管理年度,8,1),流水日期,"<="&EOMONTH(DATE(管理年度,8,1),0)),2)) | K35: =IF($A35="","",ROUND(IF($B35="支出",-1,1)*SUMIFS(流水本位,流水类别,$A35,流水日期,">="&DATE(管理年度,9,1),流水日期,"<="&EOMONTH(DATE(管理年度,9,1),0)),2)) | L35: =IF($A35="","",ROUND(IF($B35="支出",-1,1)*SUMIFS(流水本位,流水类别,$A35,流水日期,">="&DATE(管理年度,10,1),流水日期,"<="&EOMONTH(DATE(管理年度,10,1),0)),2)) | M35: =IF($A35="","",ROUND(IF($B35="支出",-1,1)*SUMIFS(流水本位,流水类别,$A35,流水日期,">="&DATE(管理年度,11,1),流水日期,"<="&EOMONTH(DATE(管理年度,11,1),0)),2)) | N35: =IF($A35="","",ROUND(IF($B35="支出",-1,1)*SUMIFS(流水本位,流水类别,$A35,流水日期,">="&DATE(管理年度,12,1),流水日期,"<="&EOMONTH(DATE(管理年度,12,1),0)),2)) | O35: =IF($A35="","",ROUND(SUM(C35:N35),2)) | P35: =IF(OR($A35="",$B35="内部转账"),"",IFERROR($O35/IF($B35="收入",$O$5,$O$6),""))
A36: =IF(参数设置!$O$35="","",参数设置!$O$35) | B36: =IF($A36="","",参数设置!$P$35) | C36: =IF($A36="","",ROUND(IF($B36="支出",-1,1)*SUMIFS(流水本位,流水类别,$A36,流水日期,">="&DATE(管理年度,1,1),流水日期,"<="&EOMONTH(DATE(管理年度,1,1),0)),2)) | D36: =IF($A36="","",ROUND(IF($B36="支出",-1,1)*SUMIFS(流水本位,流水类别,$A36,流水日期,">="&DATE(管理年度,2,1),流水日期,"<="&EOMONTH(DATE(管理年度,2,1),0)),2)) | E36: =IF($A36="","",ROUND(IF($B36="支出",-1,1)*SUMIFS(流水本位,流水类别,$A36,流水日期,">="&DATE(管理年度,3,1),流水日期,"<="&EOMONTH(DATE(管理年度,3,1),0)),2)) | F36: =IF($A36="","",ROUND(IF($B36="支出",-1,1)*SUMIFS(流水本位,流水类别,$A36,流水日期,">="&DATE(管理年度,4,1),流水日期,"<="&EOMONTH(DATE(管理年度,4,1),0)),2)) | G36: =IF($A36="","",ROUND(IF($B36="支出",-1,1)*SUMIFS(流水本位,流水类别,$A36,流水日期,">="&DATE(管理年度,5,1),流水日期,"<="&EOMONTH(DATE(管理年度,5,1),0)),2)) | H36: =IF($A36="","",ROUND(IF($B36="支出",-1,1)*SUMIFS(流水本位,流水类别,$A36,流水日期,">="&DATE(管理年度,6,1),流水日期,"<="&EOMONTH(DATE(管理年度,6,1),0)),2)) | I36: =IF($A36="","",ROUND(IF($B36="支出",-1,1)*SUMIFS(流水本位,流水类别,$A36,流水日期,">="&DATE(管理年度,7,1),流水日期,"<="&EOMONTH(DATE(管理年度,7,1),0)),2)) | J36: =IF($A36="","",ROUND(IF($B36="支出",-1,1)*SUMIFS(流水本位,流水类别,$A36,流水日期,">="&DATE(管理年度,8,1),流水日期,"<="&EOMONTH(DATE(管理年度,8,1),0)),2)) | K36: =IF($A36="","",ROUND(IF($B36="支出",-1,1)*SUMIFS(流水本位,流水类别,$A36,流水日期,">="&DATE(管理年度,9,1),流水日期,"<="&EOMONTH(DATE(管理年度,9,1),0)),2)) | L36: =IF($A36="","",ROUND(IF($B36="支出",-1,1)*SUMIFS(流水本位,流水类别,$A36,流水日期,">="&DATE(管理年度,10,1),流水日期,"<="&EOMONTH(DATE(管理年度,10,1),0)),2)) | M36: =IF($A36="","",ROUND(IF($B36="支出",-1,1)*SUMIFS(流水本位,流水类别,$A36,流水日期,">="&DATE(管理年度,11,1),流水日期,"<="&EOMONTH(DATE(管理年度,11,1),0)),2)) | N36: =IF($A36="","",ROUND(IF($B36="支出",-1,1)*SUMIFS(流水本位,流水类别,$A36,流水日期,">="&DATE(管理年度,12,1),流水日期,"<="&EOMONTH(DATE(管理年度,12,1),0)),2)) | O36: =IF($A36="","",ROUND(SUM(C36:N36),2)) | P36: =IF(OR($A36="",$B36="内部转账"),"",IFERROR($O36/IF($B36="收入",$O$5,$O$6),""))
A37: =IF(参数设置!$O$36="","",参数设置!$O$36) | B37: =IF($A37="","",参数设置!$P$36) | C37: =IF($A37="","",ROUND(IF($B37="支出",-1,1)*SUMIFS(流水本位,流水类别,$A37,流水日期,">="&DATE(管理年度,1,1),流水日期,"<="&EOMONTH(DATE(管理年度,1,1),0)),2)) | D37: =IF($A37="","",ROUND(IF($B37="支出",-1,1)*SUMIFS(流水本位,流水类别,$A37,流水日期,">="&DATE(管理年度,2,1),流水日期,"<="&EOMONTH(DATE(管理年度,2,1),0)),2)) | E37: =IF($A37="","",ROUND(IF($B37="支出",-1,1)*SUMIFS(流水本位,流水类别,$A37,流水日期,">="&DATE(管理年度,3,1),流水日期,"<="&EOMONTH(DATE(管理年度,3,1),0)),2)) | F37: =IF($A37="","",ROUND(IF($B37="支出",-1,1)*SUMIFS(流水本位,流水类别,$A37,流水日期,">="&DATE(管理年度,4,1),流水日期,"<="&EOMONTH(DATE(管理年度,4,1),0)),2)) | G37: =IF($A37="","",ROUND(IF($B37="支出",-1,1)*SUMIFS(流水本位,流水类别,$A37,流水日期,">="&DATE(管理年度,5,1),流水日期,"<="&EOMONTH(DATE(管理年度,5,1),0)),2)) | H37: =IF($A37="","",ROUND(IF($B37="支出",-1,1)*SUMIFS(流水本位,流水类别,$A37,流水日期,">="&DATE(管理年度,6,1),流水日期,"<="&EOMONTH(DATE(管理年度,6,1),0)),2)) | I37: =IF($A37="","",ROUND(IF($B37="支出",-1,1)*SUMIFS(流水本位,流水类别,$A37,流水日期,">="&DATE(管理年度,7,1),流水日期,"<="&EOMONTH(DATE(管理年度,7,1),0)),2)) | J37: =IF($A37="","",ROUND(IF($B37="支出",-1,1)*SUMIFS(流水本位,流水类别,$A37,流水日期,">="&DATE(管理年度,8,1),流水日期,"<="&EOMONTH(DATE(管理年度,8,1),0)),2)) | K37: =IF($A37="","",ROUND(IF($B37="支出",-1,1)*SUMIFS(流水本位,流水类别,$A37,流水日期,">="&DATE(管理年度,9,1),流水日期,"<="&EOMONTH(DATE(管理年度,9,1),0)),2)) | L37: =IF($A37="","",ROUND(IF($B37="支出",-1,1)*SUMIFS(流水本位,流水类别,$A37,流水日期,">="&DATE(管理年度,10,1),流水日期,"<="&EOMONTH(DATE(管理年度,10,1),0)),2)) | M37: =IF($A37="","",ROUND(IF($B37="支出",-1,1)*SUMIFS(流水本位,流水类别,$A37,流水日期,">="&DATE(管理年度,11,1),流水日期,"<="&EOMONTH(DATE(管理年度,11,1),0)),2)) | N37: =IF($A37="","",ROUND(IF($B37="支出",-1,1)*SUMIFS(流水本位,流水类别,$A37,流水日期,">="&DATE(管理年度,12,1),流水日期,"<="&EOMONTH(DATE(管理年度,12,1),0)),2)) | O37: =IF($A37="","",ROUND(SUM(C37:N37),2)) | P37: =IF(OR($A37="",$B37="内部转账"),"",IFERROR($O37/IF($B37="收入",$O$5,$O$6),""))
A38: =IF(参数设置!$O$37="","",参数设置!$O$37) | B38: =IF($A38="","",参数设置!$P$37) | C38: =IF($A38="","",ROUND(IF($B38="支出",-1,1)*SUMIFS(流水本位,流水类别,$A38,流水日期,">="&DATE(管理年度,1,1),流水日期,"<="&EOMONTH(DATE(管理年度,1,1),0)),2)) | D38: =IF($A38="","",ROUND(IF($B38="支出",-1,1)*SUMIFS(流水本位,流水类别,$A38,流水日期,">="&DATE(管理年度,2,1),流水日期,"<="&EOMONTH(DATE(管理年度,2,1),0)),2)) | E38: =IF($A38="","",ROUND(IF($B38="支出",-1,1)*SUMIFS(流水本位,流水类别,$A38,流水日期,">="&DATE(管理年度,3,1),流水日期,"<="&EOMONTH(DATE(管理年度,3,1),0)),2)) | F38: =IF($A38="","",ROUND(IF($B38="支出",-1,1)*SUMIFS(流水本位,流水类别,$A38,流水日期,">="&DATE(管理年度,4,1),流水日期,"<="&EOMONTH(DATE(管理年度,4,1),0)),2)) | G38: =IF($A38="","",ROUND(IF($B38="支出",-1,1)*SUMIFS(流水本位,流水类别,$A38,流水日期,">="&DATE(管理年度,5,1),流水日期,"<="&EOMONTH(DATE(管理年度,5,1),0)),2)) | H38: =IF($A38="","",ROUND(IF($B38="支出",-1,1)*SUMIFS(流水本位,流水类别,$A38,流水日期,">="&DATE(管理年度,6,1),流水日期,"<="&EOMONTH(DATE(管理年度,6,1),0)),2)) | I38: =IF($A38="","",ROUND(IF($B38="支出",-1,1)*SUMIFS(流水本位,流水类别,$A38,流水日期,">="&DATE(管理年度,7,1),流水日期,"<="&EOMONTH(DATE(管理年度,7,1),0)),2)) | J38: =IF($A38="","",ROUND(IF($B38="支出",-1,1)*SUMIFS(流水本位,流水类别,$A38,流水日期,">="&DATE(管理年度,8,1),流水日期,"<="&EOMONTH(DATE(管理年度,8,1),0)),2)) | K38: =IF($A38="","",ROUND(IF($B38="支出",-1,1)*SUMIFS(流水本位,流水类别,$A38,流水日期,">="&DATE(管理年度,9,1),流水日期,"<="&EOMONTH(DATE(管理年度,9,1),0)),2)) | L38: =IF($A38="","",ROUND(IF($B38="支出",-1,1)*SUMIFS(流水本位,流水类别,$A38,流水日期,">="&DATE(管理年度,10,1),流水日期,"<="&EOMONTH(DATE(管理年度,10,1),0)),2)) | M38: =IF($A38="","",ROUND(IF($B38="支出",-1,1)*SUMIFS(流水本位,流水类别,$A38,流水日期,">="&DATE(管理年度,11,1),流水日期,"<="&EOMONTH(DATE(管理年度,11,1),0)),2)) | N38: =IF($A38="","",ROUND(IF($B38="支出",-1,1)*SUMIFS(流水本位,流水类别,$A38,流水日期,">="&DATE(管理年度,12,1),流水日期,"<="&EOMONTH(DATE(管理年度,12,1),0)),2)) | O38: =IF($A38="","",ROUND(SUM(C38:N38),2)) | P38: =IF(OR($A38="",$B38="内部转账"),"",IFERROR($O38/IF($B38="收入",$O$5,$O$6),""))
A39: =IF(参数设置!$O$38="","",参数设置!$O$38) | B39: =IF($A39="","",参数设置!$P$38) | C39: =IF($A39="","",ROUND(IF($B39="支出",-1,1)*SUMIFS(流水本位,流水类别,$A39,流水日期,">="&DATE(管理年度,1,1),流水日期,"<="&EOMONTH(DATE(管理年度,1,1),0)),2)) | D39: =IF($A39="","",ROUND(IF($B39="支出",-1,1)*SUMIFS(流水本位,流水类别,$A39,流水日期,">="&DATE(管理年度,2,1),流水日期,"<="&EOMONTH(DATE(管理年度,2,1),0)),2)) | E39: =IF($A39="","",ROUND(IF($B39="支出",-1,1)*SUMIFS(流水本位,流水类别,$A39,流水日期,">="&DATE(管理年度,3,1),流水日期,"<="&EOMONTH(DATE(管理年度,3,1),0)),2)) | F39: =IF($A39="","",ROUND(IF($B39="支出",-1,1)*SUMIFS(流水本位,流水类别,$A39,流水日期,">="&DATE(管理年度,4,1),流水日期,"<="&EOMONTH(DATE(管理年度,4,1),0)),2)) | G39: =IF($A39="","",ROUND(IF($B39="支出",-1,1)*SUMIFS(流水本位,流水类别,$A39,流水日期,">="&DATE(管理年度,5,1),流水日期,"<="&EOMONTH(DATE(管理年度,5,1),0)),2)) | H39: =IF($A39="","",ROUND(IF($B39="支出",-1,1)*SUMIFS(流水本位,流水类别,$A39,流水日期,">="&DATE(管理年度,6,1),流水日期,"<="&EOMONTH(DATE(管理年度,6,1),0)),2)) | I39: =IF($A39="","",ROUND(IF($B39="支出",-1,1)*SUMIFS(流水本位,流水类别,$A39,流水日期,">="&DATE(管理年度,7,1),流水日期,"<="&EOMONTH(DATE(管理年度,7,1),0)),2)) | J39: =IF($A39="","",ROUND(IF($B39="支出",-1,1)*SUMIFS(流水本位,流水类别,$A39,流水日期,">="&DATE(管理年度,8,1),流水日期,"<="&EOMONTH(DATE(管理年度,8,1),0)),2)) | K39: =IF($A39="","",ROUND(IF($B39="支出",-1,1)*SUMIFS(流水本位,流水类别,$A39,流水日期,">="&DATE(管理年度,9,1),流水日期,"<="&EOMONTH(DATE(管理年度,9,1),0)),2)) | L39: =IF($A39="","",ROUND(IF($B39="支出",-1,1)*SUMIFS(流水本位,流水类别,$A39,流水日期,">="&DATE(管理年度,10,1),流水日期,"<="&EOMONTH(DATE(管理年度,10,1),0)),2)) | M39: =IF($A39="","",ROUND(IF($B39="支出",-1,1)*SUMIFS(流水本位,流水类别,$A39,流水日期,">="&DATE(管理年度,11,1),流水日期,"<="&EOMONTH(DATE(管理年度,11,1),0)),2)) | N39: =IF($A39="","",ROUND(IF($B39="支出",-1,1)*SUMIFS(流水本位,流水类别,$A39,流水日期,">="&DATE(管理年度,12,1),流水日期,"<="&EOMONTH(DATE(管理年度,12,1),0)),2)) | O39: =IF($A39="","",ROUND(SUM(C39:N39),2)) | P39: =IF(OR($A39="",$B39="内部转账"),"",IFERROR($O39/IF($B39="收入",$O$5,$O$6),""))
A40: =IF(参数设置!$O$39="","",参数设置!$O$39) | B40: =IF($A40="","",参数设置!$P$39) | C40: =IF($A40="","",ROUND(IF($B40="支出",-1,1)*SUMIFS(流水本位,流水类别,$A40,流水日期,">="&DATE(管理年度,1,1),流水日期,"<="&EOMONTH(DATE(管理年度,1,1),0)),2)) | D40: =IF($A40="","",ROUND(IF($B40="支出",-1,1)*SUMIFS(流水本位,流水类别,$A40,流水日期,">="&DATE(管理年度,2,1),流水日期,"<="&EOMONTH(DATE(管理年度,2,1),0)),2)) | E40: =IF($A40="","",ROUND(IF($B40="支出",-1,1)*SUMIFS(流水本位,流水类别,$A40,流水日期,">="&DATE(管理年度,3,1),流水日期,"<="&EOMONTH(DATE(管理年度,3,1),0)),2)) | F40: =IF($A40="","",ROUND(IF($B40="支出",-1,1)*SUMIFS(流水本位,流水类别,$A40,流水日期,">="&DATE(管理年度,4,1),流水日期,"<="&EOMONTH(DATE(管理年度,4,1),0)),2)) | G40: =IF($A40="","",ROUND(IF($B40="支出",-1,1)*SUMIFS(流水本位,流水类别,$A40,流水日期,">="&DATE(管理年度,5,1),流水日期,"<="&EOMONTH(DATE(管理年度,5,1),0)),2)) | H40: =IF($A40="","",ROUND(IF($B40="支出",-1,1)*SUMIFS(流水本位,流水类别,$A40,流水日期,">="&DATE(管理年度,6,1),流水日期,"<="&EOMONTH(DATE(管理年度,6,1),0)),2)) | I40: =IF($A40="","",ROUND(IF($B40="支出",-1,1)*SUMIFS(流水本位,流水类别,$A40,流水日期,">="&DATE(管理年度,7,1),流水日期,"<="&EOMONTH(DATE(管理年度,7,1),0)),2)) | J40: =IF($A40="","",ROUND(IF($B40="支出",-1,1)*SUMIFS(流水本位,流水类别,$A40,流水日期,">="&DATE(管理年度,8,1),流水日期,"<="&EOMONTH(DATE(管理年度,8,1),0)),2)) | K40: =IF($A40="","",ROUND(IF($B40="支出",-1,1)*SUMIFS(流水本位,流水类别,$A40,流水日期,">="&DATE(管理年度,9,1),流水日期,"<="&EOMONTH(DATE(管理年度,9,1),0)),2)) | L40: =IF($A40="","",ROUND(IF($B40="支出",-1,1)*SUMIFS(流水本位,流水类别,$A40,流水日期,">="&DATE(管理年度,10,1),流水日期,"<="&EOMONTH(DATE(管理年度,10,1),0)),2)) | M40: =IF($A40="","",ROUND(IF($B40="支出",-1,1)*SUMIFS(流水本位,流水类别,$A40,流水日期,">="&DATE(管理年度,11,1),流水日期,"<="&EOMONTH(DATE(管理年度,11,1),0)),2)) | N40: =IF($A40="","",ROUND(IF($B40="支出",-1,1)*SUMIFS(流水本位,流水类别,$A40,流水日期,">="&DATE(管理年度,12,1),流水日期,"<="&EOMONTH(DATE(管理年度,12,1),0)),2)) | O40: =IF($A40="","",ROUND(SUM(C40:N40),2)) | P40: =IF(OR($A40="",$B40="内部转账"),"",IFERROR($O40/IF($B40="收入",$O$5,$O$6),""))
A41: =IF(参数设置!$O$40="","",参数设置!$O$40) | B41: =IF($A41="","",参数设置!$P$40) | C41: =IF($A41="","",ROUND(IF($B41="支出",-1,1)*SUMIFS(流水本位,流水类别,$A41,流水日期,">="&DATE(管理年度,1,1),流水日期,"<="&EOMONTH(DATE(管理年度,1,1),0)),2)) | D41: =IF($A41="","",ROUND(IF($B41="支出",-1,1)*SUMIFS(流水本位,流水类别,$A41,流水日期,">="&DATE(管理年度,2,1),流水日期,"<="&EOMONTH(DATE(管理年度,2,1),0)),2)) | E41: =IF($A41="","",ROUND(IF($B41="支出",-1,1)*SUMIFS(流水本位,流水类别,$A41,流水日期,">="&DATE(管理年度,3,1),流水日期,"<="&EOMONTH(DATE(管理年度,3,1),0)),2)) | F41: =IF($A41="","",ROUND(IF($B41="支出",-1,1)*SUMIFS(流水本位,流水类别,$A41,流水日期,">="&DATE(管理年度,4,1),流水日期,"<="&EOMONTH(DATE(管理年度,4,1),0)),2)) | G41: =IF($A41="","",ROUND(IF($B41="支出",-1,1)*SUMIFS(流水本位,流水类别,$A41,流水日期,">="&DATE(管理年度,5,1),流水日期,"<="&EOMONTH(DATE(管理年度,5,1),0)),2)) | H41: =IF($A41="","",ROUND(IF($B41="支出",-1,1)*SUMIFS(流水本位,流水类别,$A41,流水日期,">="&DATE(管理年度,6,1),流水日期,"<="&EOMONTH(DATE(管理年度,6,1),0)),2)) | I41: =IF($A41="","",ROUND(IF($B41="支出",-1,1)*SUMIFS(流水本位,流水类别,$A41,流水日期,">="&DATE(管理年度,7,1),流水日期,"<="&EOMONTH(DATE(管理年度,7,1),0)),2)) | J41: =IF($A41="","",ROUND(IF($B41="支出",-1,1)*SUMIFS(流水本位,流水类别,$A41,流水日期,">="&DATE(管理年度,8,1),流水日期,"<="&EOMONTH(DATE(管理年度,8,1),0)),2)) | K41: =IF($A41="","",ROUND(IF($B41="支出",-1,1)*SUMIFS(流水本位,流水类别,$A41,流水日期,">="&DATE(管理年度,9,1),流水日期,"<="&EOMONTH(DATE(管理年度,9,1),0)),2)) | L41: =IF($A41="","",ROUND(IF($B41="支出",-1,1)*SUMIFS(流水本位,流水类别,$A41,流水日期,">="&DATE(管理年度,10,1),流水日期,"<="&EOMONTH(DATE(管理年度,10,1),0)),2)) | M41: =IF($A41="","",ROUND(IF($B41="支出",-1,1)*SUMIFS(流水本位,流水类别,$A41,流水日期,">="&DATE(管理年度,11,1),流水日期,"<="&EOMONTH(DATE(管理年度,11,1),0)),2)) | N41: =IF($A41="","",ROUND(IF($B41="支出",-1,1)*SUMIFS(流水本位,流水类别,$A41,流水日期,">="&DATE(管理年度,12,1),流水日期,"<="&EOMONTH(DATE(管理年度,12,1),0)),2)) | O41: =IF($A41="","",ROUND(SUM(C41:N41),2)) | P41: =IF(OR($A41="",$B41="内部转账"),"",IFERROR($O41/IF($B41="收入",$O$5,$O$6),""))

Sheet 资金日报表
A1: 资金日报表 · 改上面两个日期就行
A2: 上半张是按日走势（最多 31 天），下半张是某一天的出纳日报。收付都不含内部转账。账户余额列按原币显示，列头带币种。
A3: 起始日期 | B3: 46235 | C3: 截止日期 | D3: 46265 | E3: 天数 | F3: =IF(OR($B$3="",$D$3=""),"",IF($D$3<$B$3,"※截止早于起始",IF($D$3-$B$3+1>31,"※超过 31 天，请分段查",$D$3-$B$3+1))) -> 31 | G3: 超过 31 天就按月分段查；月度数据直接看【月度汇报表】。
A5: 一、按日走势（人民币，不含内部转账）
A6: 日期 | B6: 当日收款(人民币) | C6: 当日付款(人民币) | D6: 当日净额 | E6: 当日资金总额(人民币账面) | F6: =IF(IF(参数设置!$C$11="","",参数设置!$C$11)="","",参数设置!$C$11&"("&参数设置!$E$11&")") -> 工商银行基本户-8888(CNY) | G6: =IF(IF(参数设置!$C$12="","",参数设置!$C$12)="","",参数设置!$C$12&"("&参数设置!$E$12&")") -> 中国银行美元结算户-6688(USD) | H6: =IF(IF(参数设置!$C$13="","",参数设置!$C$13)="","",参数设置!$C$13&"("&参数设置!$E$13&")") -> 汇丰银行港币结算户-5566(HKD) | I6: =IF(IF(参数设置!$C$14="","",参数设置!$C$14)="","",参数设置!$C$14&"("&参数设置!$E$14&")") -> 招商银行一般户-2388(CNY) | J6: =IF(IF(参数设置!$C$15="","",参数设置!$C$15)="","",参数设置!$C$15&"("&参数设置!$E$15&")") -> 汇丰银行美元结算户-7788(USD) | K6: =IF(IF(参数设置!$C$16="","",参数设置!$C$16)="","",参数设置!$C$16&"("&参数设置!$E$16&")") -> 中国银行欧元结算户-9900(EUR) | L6: =IF(IF(参数设置!$C$17="","",参数设置!$C$17)="","",参数设置!$C$17&"("&参数设置!$E$17&")") | M6: =IF(IF(参数设置!$C$18="","",参数设置!$C$18)="","",参数设置!$C$18&"("&参数设置!$E$18&")") | N6: =IF(IF(参数设置!$C$19="","",参数设置!$C$19)="","",参数设置!$C$19&"("&参数设置!$E$19&")") | O6: =IF(IF(参数设置!$C$20="","",参数设置!$C$20)="","",参数设置!$C$20&"("&参数设置!$E$20&")") | P6: =IF(IF(参数设置!$C$21="","",参数设置!$C$21)="","",参数设置!$C$21&"("&参数设置!$E$21&")") | Q6: =IF(IF(参数设置!$C$22="","",参数设置!$C$22)="","",参数设置!$C$22&"("&参数设置!$E$22&")") | R6: =IF(IF(参数设置!$C$23="","",参数设置!$C$23)="","",参数设置!$C$23&"("&参数设置!$E$23&")") | S6: =IF(IF(参数设置!$C$24="","",参数设置!$C$24)="","",参数设置!$C$24&"("&参数设置!$E$24&")") | T6: =IF(IF(参数设置!$C$25="","",参数设置!$C$25)="","",参数设置!$C$25&"("&参数设置!$E$25&")")
A7: =IF(OR($B$3="",NOT(ISNUMBER($F$3))),"",IF(1>$F$3,"",$B$3+0)) -> 46235 | B7: =IF($A7="","",ROUND(SUMIFS(流水本位,流水日期,$A7,流水属性,"<>内部转账",流水本位,">0"),2)) -> 0 | C7: =IF($A7="","",-ROUND(SUMIFS(流水本位,流水日期,$A7,流水属性,"<>内部转账",流水本位,"<0"),2)) -> 0 | D7: =IF($A7="","",ROUND($B7-$C7,2)) -> 0 | E7: =IF($A7="","",ROUND(SUM(账户期初本位)+SUMIFS(流水本位,流水日期,"<="&$A7),2)) -> 11192300 | F7: =IF(OR($A7="",IF(参数设置!$C$11="","",参数设置!$C$11)=""),"",ROUND(N(参数设置!$G$11)+SUMIFS(流水净额,流水账户,参数设置!$C$11,流水日期,"<="&$A7),2)) -> 500000 | G7: =IF(OR($A7="",IF(参数设置!$C$12="","",参数设置!$C$12)=""),"",ROUND(N(参数设置!$G$12)+SUMIFS(流水净额,流水账户,参数设置!$C$12,流水日期,"<="&$A7),2)) -> 800000 | H7: =IF(OR($A7="",IF(参数设置!$C$13="","",参数设置!$C$13)=""),"",ROUND(N(参数设置!$G$13)+SUMIFS(流水净额,流水账户,参数设置!$C$13,流水日期,"<="&$A7),2)) -> 300000 | I7: =IF(OR($A7="",IF(参数设置!$C$14="","",参数设置!$C$14)=""),"",ROUND(N(参数设置!$G$14)+SUMIFS(流水净额,流水账户,参数设置!$C$14,流水日期,"<="&$A7),2)) -> 200000 | J7: =IF(OR($A7="",IF(参数设置!$C$15="","",参数设置!$C$15)=""),"",ROUND(N(参数设置!$G$15)+SUMIFS(流水净额,流水账户,参数设置!$C$15,流水日期,"<="&$A7),2)) -> 500000 | K7: =IF(OR($A7="",IF(参数设置!$C$16="","",参数设置!$C$16)=""),"",ROUND(N(参数设置!$G$16)+SUMIFS(流水净额,流水账户,参数设置!$C$16,流水日期,"<="&$A7),2)) -> 120000 | L7: =IF(OR($A7="",IF(参数设置!$C$17="","",参数设置!$C$17)=""),"",ROUND(N(参数设置!$G$17)+SUMIFS(流水净额,流水账户,参数设置!$C$17,流水日期,"<="&$A7),2)) | M7: =IF(OR($A7="",IF(参数设置!$C$18="","",参数设置!$C$18)=""),"",ROUND(N(参数设置!$G$18)+SUMIFS(流水净额,流水账户,参数设置!$C$18,流水日期,"<="&$A7),2)) | N7: =IF(OR($A7="",IF(参数设置!$C$19="","",参数设置!$C$19)=""),"",ROUND(N(参数设置!$G$19)+SUMIFS(流水净额,流水账户,参数设置!$C$19,流水日期,"<="&$A7),2)) | O7: =IF(OR($A7="",IF(参数设置!$C$20="","",参数设置!$C$20)=""),"",ROUND(N(参数设置!$G$20)+SUMIFS(流水净额,流水账户,参数设置!$C$20,流水日期,"<="&$A7),2)) | P7: =IF(OR($A7="",IF(参数设置!$C$21="","",参数设置!$C$21)=""),"",ROUND(N(参数设置!$G$21)+SUMIFS(流水净额,流水账户,参数设置!$C$21,流水日期,"<="&$A7),2)) | Q7: =IF(OR($A7="",IF(参数设置!$C$22="","",参数设置!$C$22)=""),"",ROUND(N(参数设置!$G$22)+SUMIFS(流水净额,流水账户,参数设置!$C$22,流水日期,"<="&$A7),2)) | R7: =IF(OR($A7="",IF(参数设置!$C$23="","",参数设置!$C$23)=""),"",ROUND(N(参数设置!$G$23)+SUMIFS(流水净额,流水账户,参数设置!$C$23,流水日期,"<="&$A7),2)) | S7: =IF(OR($A7="",IF(参数设置!$C$24="","",参数设置!$C$24)=""),"",ROUND(N(参数设置!$G$24)+SUMIFS(流水净额,流水账户,参数设置!$C$24,流水日期,"<="&$A7),2)) | T7: =IF(OR($A7="",IF(参数设置!$C$25="","",参数设置!$C$25)=""),"",ROUND(N(参数设置!$G$25)+SUMIFS(流水净额,流水账户,参数设置!$C$25,流水日期,"<="&$A7),2))
A8: =IF(OR($B$3="",NOT(ISNUMBER($F$3))),"",IF(2>$F$3,"",$B$3+1)) -> 46236 | B8: =IF($A8="","",ROUND(SUMIFS(流水本位,流水日期,$A8,流水属性,"<>内部转账",流水本位,">0"),2)) -> 0 | C8: =IF($A8="","",-ROUND(SUMIFS(流水本位,流水日期,$A8,流水属性,"<>内部转账",流水本位,"<0"),2)) -> 0 | D8: =IF($A8="","",ROUND($B8-$C8,2)) -> 0 | E8: =IF($A8="","",ROUND(SUM(账户期初本位)+SUMIFS(流水本位,流水日期,"<="&$A8),2)) -> 11192300 | F8: =IF(OR($A8="",IF(参数设置!$C$11="","",参数设置!$C$11)=""),"",ROUND(N(参数设置!$G$11)+SUMIFS(流水净额,流水账户,参数设置!$C$11,流水日期,"<="&$A8),2)) -> 500000 | G8: =IF(OR($A8="",IF(参数设置!$C$12="","",参数设置!$C$12)=""),"",ROUND(N(参数设置!$G$12)+SUMIFS(流水净额,流水账户,参数设置!$C$12,流水日期,"<="&$A8),2)) -> 800000 | H8: =IF(OR($A8="",IF(参数设置!$C$13="","",参数设置!$C$13)=""),"",ROUND(N(参数设置!$G$13)+SUMIFS(流水净额,流水账户,参数设置!$C$13,流水日期,"<="&$A8),2)) -> 300000 | I8: =IF(OR($A8="",IF(参数设置!$C$14="","",参数设置!$C$14)=""),"",ROUND(N(参数设置!$G$14)+SUMIFS(流水净额,流水账户,参数设置!$C$14,流水日期,"<="&$A8),2)) -> 200000 | J8: =IF(OR($A8="",IF(参数设置!$C$15="","",参数设置!$C$15)=""),"",ROUND(N(参数设置!$G$15)+SUMIFS(流水净额,流水账户,参数设置!$C$15,流水日期,"<="&$A8),2)) -> 500000 | K8: =IF(OR($A8="",IF(参数设置!$C$16="","",参数设置!$C$16)=""),"",ROUND(N(参数设置!$G$16)+SUMIFS(流水净额,流水账户,参数设置!$C$16,流水日期,"<="&$A8),2)) -> 120000 | L8: =IF(OR($A8="",IF(参数设置!$C$17="","",参数设置!$C$17)=""),"",ROUND(N(参数设置!$G$17)+SUMIFS(流水净额,流水账户,参数设置!$C$17,流水日期,"<="&$A8),2)) | M8: =IF(OR($A8="",IF(参数设置!$C$18="","",参数设置!$C$18)=""),"",ROUND(N(参数设置!$G$18)+SUMIFS(流水净额,流水账户,参数设置!$C$18,流水日期,"<="&$A8),2)) | N8: =IF(OR($A8="",IF(参数设置!$C$19="","",参数设置!$C$19)=""),"",ROUND(N(参数设置!$G$19)+SUMIFS(流水净额,流水账户,参数设置!$C$19,流水日期,"<="&$A8),2)) | O8: =IF(OR($A8="",IF(参数设置!$C$20="","",参数设置!$C$20)=""),"",ROUND(N(参数设置!$G$20)+SUMIFS(流水净额,流水账户,参数设置!$C$20,流水日期,"<="&$A8),2)) | P8: =IF(OR($A8="",IF(参数设置!$C$21="","",参数设置!$C$21)=""),"",ROUND(N(参数设置!$G$21)+SUMIFS(流水净额,流水账户,参数设置!$C$21,流水日期,"<="&$A8),2)) | Q8: =IF(OR($A8="",IF(参数设置!$C$22="","",参数设置!$C$22)=""),"",ROUND(N(参数设置!$G$22)+SUMIFS(流水净额,流水账户,参数设置!$C$22,流水日期,"<="&$A8),2)) | R8: =IF(OR($A8="",IF(参数设置!$C$23="","",参数设置!$C$23)=""),"",ROUND(N(参数设置!$G$23)+SUMIFS(流水净额,流水账户,参数设置!$C$23,流水日期,"<="&$A8),2)) | S8: =IF(OR($A8="",IF(参数设置!$C$24="","",参数设置!$C$24)=""),"",ROUND(N(参数设置!$G$24)+SUMIFS(流水净额,流水账户,参数设置!$C$24,流水日期,"<="&$A8),2)) | T8: =IF(OR($A8="",IF(参数设置!$C$25="","",参数设置!$C$25)=""),"",ROUND(N(参数设置!$G$25)+SUMIFS(流水净额,流水账户,参数设置!$C$25,流水日期,"<="&$A8),2))
A9: =IF(OR($B$3="",NOT(ISNUMBER($F$3))),"",IF(3>$F$3,"",$B$3+2)) -> 46237 | B9: =IF($A9="","",ROUND(SUMIFS(流水本位,流水日期,$A9,流水属性,"<>内部转账",流水本位,">0"),2)) -> 120000 | C9: =IF($A9="","",-ROUND(SUMIFS(流水本位,流水日期,$A9,流水属性,"<>内部转账",流水本位,"<0"),2)) -> 0 | D9: =IF($A9="","",ROUND($B9-$C9,2)) -> 120000 | E9: =IF($A9="","",ROUND(SUM(账户期初本位)+SUMIFS(流水本位,流水日期,"<="&$A9),2)) -> 11312300 | F9: =IF(OR($A9="",IF(参数设置!$C$11="","",参数设置!$C$11)=""),"",ROUND(N(参数设置!$G$11)+SUMIFS(流水净额,流水账户,参数设置!$C$11,流水日期,"<="&$A9),2)) -> 620000 | G9: =IF(OR($A9="",IF(参数设置!$C$12="","",参数设置!$C$12)=""),"",ROUND(N(参数设置!$G$12)+SUMIFS(流水净额,流水账户,参数设置!$C$12,流水日期,"<="&$A9),2)) -> 800000 | H9: =IF(OR($A9="",IF(参数设置!$C$13="","",参数设置!$C$13)=""),"",ROUND(N(参数设置!$G$13)+SUMIFS(流水净额,流水账户,参数设置!$C$13,流水日期,"<="&$A9),2)) -> 300000 | I9: =IF(OR($A9="",IF(参数设置!$C$14="","",参数设置!$C$14)=""),"",ROUND(N(参数设置!$G$14)+SUMIFS(流水净额,流水账户,参数设置!$C$14,流水日期,"<="&$A9),2)) -> 200000 | J9: =IF(OR($A9="",IF(参数设置!$C$15="","",参数设置!$C$15)=""),"",ROUND(N(参数设置!$G$15)+SUMIFS(流水净额,流水账户,参数设置!$C$15,流水日期,"<="&$A9),2)) -> 500000 | K9: =IF(OR($A9="",IF(参数设置!$C$16="","",参数设置!$C$16)=""),"",ROUND(N(参数设置!$G$16)+SUMIFS(流水净额,流水账户,参数设置!$C$16,流水日期,"<="&$A9),2)) -> 120000 | L9: =IF(OR($A9="",IF(参数设置!$C$17="","",参数设置!$C$17)=""),"",ROUND(N(参数设置!$G$17)+SUMIFS(流水净额,流水账户,参数设置!$C$17,流水日期,"<="&$A9),2)) | M9: =IF(OR($A9="",IF(参数设置!$C$18="","",参数设置!$C$18)=""),"",ROUND(N(参数设置!$G$18)+SUMIFS(流水净额,流水账户,参数设置!$C$18,流水日期,"<="&$A9),2)) | N9: =IF(OR($A9="",IF(参数设置!$C$19="","",参数设置!$C$19)=""),"",ROUND(N(参数设置!$G$19)+SUMIFS(流水净额,流水账户,参数设置!$C$19,流水日期,"<="&$A9),2)) | O9: =IF(OR($A9="",IF(参数设置!$C$20="","",参数设置!$C$20)=""),"",ROUND(N(参数设置!$G$20)+SUMIFS(流水净额,流水账户,参数设置!$C$20,流水日期,"<="&$A9),2)) | P9: =IF(OR($A9="",IF(参数设置!$C$21="","",参数设置!$C$21)=""),"",ROUND(N(参数设置!$G$21)+SUMIFS(流水净额,流水账户,参数设置!$C$21,流水日期,"<="&$A9),2)) | Q9: =IF(OR($A9="",IF(参数设置!$C$22="","",参数设置!$C$22)=""),"",ROUND(N(参数设置!$G$22)+SUMIFS(流水净额,流水账户,参数设置!$C$22,流水日期,"<="&$A9),2)) | R9: =IF(OR($A9="",IF(参数设置!$C$23="","",参数设置!$C$23)=""),"",ROUND(N(参数设置!$G$23)+SUMIFS(流水净额,流水账户,参数设置!$C$23,流水日期,"<="&$A9),2)) | S9: =IF(OR($A9="",IF(参数设置!$C$24="","",参数设置!$C$24)=""),"",ROUND(N(参数设置!$G$24)+SUMIFS(流水净额,流水账户,参数设置!$C$24,流水日期,"<="&$A9),2)) | T9: =IF(OR($A9="",IF(参数设置!$C$25="","",参数设置!$C$25)=""),"",ROUND(N(参数设置!$G$25)+SUMIFS(流水净额,流水账户,参数设置!$C$25,流水日期,"<="&$A9),2))
