Workbook

Sheet 主页
A1: 03 财 务 账 套 与 报 表
A2: 小企业会计准则 ｜ 全部按含税金额记账 ｜ 与 01、02 两本业务册跨文件自动联动 ｜ 点下面蓝色表名可直接跳转
A3: =IF(N(对接源_01水果!$T$1)+N(对接源_02物料!$T$1)=0,"联动状态：★★ 两本业务册的数据都没接进来 —— 请打开对接源表按提示修复链接",IF(N(对接源_01水果!$T$4)*N(对接源_02物料!$T$4)*N(对接源_01入库吨位!$V$4)=0,"联动状态：⚠ 有业务册在用【应急备份】数据（不是实时数），请尽快修复链接","联动状态：✔ 正常 —— 01水果 "&N(对接源_01水果!$T$1)&" 行 ＋ 02物料 "&N(对接源_02物料!$T$1)&" 行 ＋ 01入库吨位 "&N(对接源_01入库吨位!$V$1)&" 行已自动接入")) -> 联动状态：✔ 正常 —— 01水果 11 行 ＋ 02物料 5 行 ＋ 01入库吨位 22 行已自动接入
A5: 一、跨册对接（自动取数，勿手工填）
A6: 序号 | B6: 子表名称 | C6: 用途说明 | D6: 属性
A7: 1 | B7: 对接源_01水果 | C7: 跨文件取《01》财务取数接口（24 个月收入成本 ＋ 按客户往来） | D7: 自动
A8: 2 | B8: 对接源_02物料 | C8: 跨文件取《02》财务取数接口 | D8: 自动
A9: 3 | B9: 对接源_01入库吨位 | C9: 跨文件取《01》入库吨位汇总：周转打冷／仓储加工的筐数、总重、吨位 | D9: 自动
A10: 4 | B10: 进销存对接 | C10: 合并两张对接源，配科目；全部按含税金额记账 | D10: 自动
A12: 二、日常录入
A13: 序号 | B13: 子表名称 | C13: 用途说明 | D13: 属性
A14: 5 | B14: 原料入库计价 | C14: ★全展开：每个货主＋品种自动拆 周转打冷/仓储加工/装卸费 三行，只填计价方式与单价 | D14: 录入+自动
A15: 6 | B15: 资金日记账 | C15: 出纳每天记收付款（已去掉凭证字号/票据/经办人）；支出选费用项目就自动进成本 | D15: 录入
A16: 7 | B16: 成本费用登记表 | C16: 费用发生额与本单已付金额，差额＝应付账款 | D16: 录入
A17: 8 | B17: 对账补充行 | C17: 借款、还款、优惠、抹零等台账里没有、对账单要体现的行 | D17: 录入
A18: 9 | B18: 期初余额 | C18: 建账时填一次 | D18: 录入
A20: 三、账簿 · 往来 · 成本（全部自动）
A21: 序号 | B21: 子表名称 | C21: 用途说明 | D21: 属性
A22: 10 | B22: 记账凭证 | C22: 按进销存对接、资金日记账、成本费用表自动生成，手工区在 3010 行以后 | D22: 自动
A23: 11 | B23: 资金与往来余额表 | C23: 资金账户结存与往来单位余额 | D23: 自动
A24: 12 | B24: 应收应付汇总表 | C24: 每家单位的应收、应付、净往来 | D24: 自动
A25: 13 | B25: 收入月度汇总 | C25: ★按【资金日记账】往来单位 × 24 个月统计收入 | D25: 自动
A26: 14 | B26: 费用月度汇总 | C26: 成本项目 × 24 个月，含合计发生额、已付、应付余额 | D26: 自动
A27: 15 | B27: 应付账款明细 | C27: 按供应商/对象看发生额、已付、还欠多少 | D27: 自动
A28: 16 | B28: 往来对账单 | C28: ★50 行分项汇总：仓储费/周转费/装卸费/成品销售/筐子款/物料款 ＋ 购买果品款（负数抵扣） | D28: 录入+自动
A29: 17 | B29: 科目余额表 | C29: ★起止日期总开关：期初＋本期发生＋期末 | D29: 录入+自动
A30: 18 | B30: 资产负债表 | C30: 跟科目余额表的日期走 | D30: 自动
A31: 19 | B31: 利润表 | C31: 本期与本年累计两套日期 | D31: 录入+自动
A33: 四、规则与码表
A34: 序号 | B34: 子表名称 | C34: 用途说明 | D34: 属性
A35: 20 | B35: 自动规则 | C35: 业务类型 → 收付款科目 | D35: 码表
A36: 21 | B36: 收入成本映射 | C36: 项目 → 记账类别与借贷科目（税率一律 0%，全部含税记账） | D36: 码表
A37: 22 | B37: 科目表 | C37: 会计科目 ＋ 往来单位/业务类型/收入项目/费用项目/费用对应科目 | D37: 码表
A38: 23 | B38: 常用分录参考 | C38: 常见业务的借贷科目参考 | D38: 码表
A40: 图例：浅绿＝公式自动生成，请勿覆盖 ｜ 浅蓝＝需要手工录入 ｜ 浅黄＝码表/规则，偶尔维护
A42: 本 轮 新 增
A43: 序号 | B43: 子表名称 | C43: 用途说明 | D43: 属性
A44: 1 | B44: =HYPERLINK("#'对接源_01库存'!A1","对接源_01库存") -> 对接源_01库存 | C44: 跨文件取《01》库存等级接口 | D44: 自动
A45: 2 | B45: =HYPERLINK("#'库存价值与欠款比对'!A1","库存价值与欠款比对") -> 库存价值与欠款比对 | C45: ★下半部分按等级填单价算库存价值，上半部分按客户比对「库存价值 ↔ 应收款 ↔ 差额」 | D45: 录入+自动

Sheet 使用说明
A1: 财 务 账 套 与 报 表 使 用 说 明
A2: 口径：小企业会计准则 ｜ 一般纳税人（价税分离）｜ 与两本业务册跨文件自动联动
B4: 一、三个文件必须放在同一个文件夹
B6: 01_水果进销存台账模板.xlsx
B7: 02_物料与周转物台账模板.xlsx
B8: 03_财务账套与报表模板.xlsx
B9: 文件名一个字都不要改，也不要分开存放，否则链接会断，单元格会变成错误值。
B10: 万一断了：Excel 顶部菜单【数据】→【编辑链接】→【更改源】，重新指向那两个文件即可，只需修一次。
B12: 二、每次打开要点“更新”
B14: 打开本文件时 Excel/WPS 会问“是否更新链接”，点【更新】，两本业务册的数就进来了。
B15: 如果没弹窗：【数据】→【编辑链接】→【立即更新值】。三个文件都打开时会实时联动。
B17: 三、数据怎么自动进来的
B19: 业务册明细（仓管每天录）→ 业务册【财务取数接口】按月自动汇总
B20: → 本册【对接源_01水果】/【对接源_02物料】各自跨文件取一本册子，来源册不用手工区分
... B73: 押金是欠客户的钱，不算收入；只有客户明确不退筐、押金转成赔偿时，才手工做一笔转其他业务收入。
A75: ★ 本 次 更 新（2026-09）
A76: 1、新增【原料入库计价】：原料入库的单价放在本册。上半部「原料入库单价表」按 货主＋品种 填计价方式与单价（货主填「通用」表示该品种通用价）；下半部自动按《01》的入库筐数/总重算出入库金额。计价方式三选一：按筐数×单价、按总重KG×单价、按吨位×单价。
A77: 2、新增【对接源_01入库吨位】：跨文件取《01》的入库吨位汇总（货主＋品种的筐数、总重、吨位），供上表计价用，断链时同样有应急备份区。
A78: 3、新增【对账补充行】：借款、还款、优惠、抹零、未退筐等台账里没有、但对账单要体现的行填在这里；金额自动＝数量×单价，也可用「金额手工覆盖」列直接写死（优惠、抹零填负数）。
A79: 4、【往来对账单】改成对账单版式：抬头＋客户/品类/电话，列为 日期｜摘要｜单位｜入库毛重｜单价｜金额（元）｜已付款｜备注；底部三行显示 对账日期／对账时段／是否含税 与 合计金额／已付款／应收款，最后一行黄底显示中文大写欠款金额，可直接打印。
A80: 5、对账单取数＝【原料入库计价】＋【资金日记账】＋【成本费用登记表】＋【对账补充行】四张表，按客户与起止日期自动筛选；「品类」栏自动汇总该客户的全部品种。
A82: ★ 本 次 更 新（2026-09 · 第三版）
A83: 1、【原料入库计价】重做：上表只填 货主/客户、品种、项目类别（周转打冷／仓储加工／装卸费／其他服务费）、计价方式，再填单价，数量与合计金额自动算；货主填「通用」＝该品种所有客户同价。下表按「货主＋品种＋项目类别」自动展开全部入库并套用单价，最下面还有按货主的汇总。
A84: 2、【对接源_01入库吨位】跟着 01 改版：新增「周转打冷入库总筐数」「仓储加工入库总筐数」以及两类各自的总重KG。
A85: 3、★应付账款怎么做：一切费用（工资、装卸费、电费、水费、差旅、维修、招待…）都在【成本费用登记表】登记，「价税合计」填本次发生额（＝成本），「本单已付金额」填已经付掉的钱，差额就是应付账款。例：本月电费 10000 元只付了 5000，就填 10000 和 5000，应付余额自动显示 5000。付款那笔现金流同时记到【资金日记账】。
A86: 4、★当场付清、不挂账的小额支出：可以只记【资金日记账】，在 W 列选「费用类别」、X 列填「否」，也会自动算进成本；如果这笔已经在成本费用表登记过，X 列填「是」，避免重复计算。
A87: 5、新增【费用月度汇总】：成本项目 × 24 个月的交叉表（只填 F2 起始年月），每月各项费用一目了然，右边还有合计发生额、其中已付、应付余额。
... A121: 5、装卸费怎么做账：收客户的那头在【原料入库计价】里按「装卸费」这一行填单价（比如 50 元/吨），自动进往来对账单的应收；付给装卸工的那头在【成本费用登记表】登记（费用项目＝装卸费，对象＝装卸队/员工，本单已付金额填实付），差额就是应付账款。两头都进【费用月度汇总】和利润表，毛利自动出来。

Sheet 对接源_01水果
A1: 对 接 源 · 01 水果进销存台账（跨文件自动取数 · 断链时自动改用应急备份） | S1: 有效行数 | T1: =MAX($Q$5:$Q$507) -> 11
A2: =IF($T$4=1,"✔ 链接正常，已自动取到 "&$T$1&" 行（只算有金额/数量的行） ｜ 本表 1:1 对应《01 水果进销存台账》的【财务取数接口】第 4～356 行，两本业务册必须和本文件放在同一个文件夹","★★ 链接没接上！当前取数来源："&$T$5&" → 见 S6 修复说明") -> ✔ 链接正常，已自动取到 11 行（只算有金额/数量的行） ｜ 本表 1:1 对应《01 水果进销存台账》的【财务取数接口】第 4～356 行，两本业务册必须和本文件放在同一个文件夹 | S2: 链接探针 | T2: =IFERROR(IF([1]财务取数接口!$C$4=0,"未更新",[1]财务取数接口!$C$4),"断开") -> 仓储费
A3: 一、实 际 使 用 值（链接正常时＝自动取数；链接断了自动切到右边备份） | I3: 二、应 急 备 份 区（手工粘贴数值） | P3: 状态 | S3: 备份行数 | T3: =COUNTIF($J$5:$J$507,"?*")-COUNTIF($J$5:$J$507,"项目") -> 0
A4: 源行 | B4: 年月 / 往来单位 | C4: 项目 | D4: 计费数量 / 应收发生额 | E4: 单位 / 应付发生额 | F4: 价税合计金额 | G4: 已收金额 | H4: 备注 | I4: 备份-年月 | J4: 备份-项目 | K4: 备份-数量 | L4: 备份-单位 | M4: 备份-金额 | N4: 备份-已收 | O4: 备份-备注 | P4: 有效 | Q4: 累计 | S4: 链接可用 | T4: =IF(OR($T$2="断开",$T$2="未更新"),0,1) -> 1
A5: 4 | B5: =IF($T$4=0,IF($I5="","",$I5),IFERROR(IF([1]财务取数接口!$B$4=0,"",[1]财务取数接口!$B$4),"")) -> 46235 | C5: =IF($T$4=0,IF($J5="","",$J5),IFERROR(IF([1]财务取数接口!$C$4=0,"",[1]财务取数接口!$C$4),"")) -> 仓储费 | D5: =IF($T$4=0,IF($K5="","",$K5),IFERROR(IF([1]财务取数接口!$D$4=0,"",[1]财务取数接口!$D$4),"")) | E5: =IF($T$4=0,IF($L5="","",$L5),IFERROR(IF([1]财务取数接口!$E$4=0,"",[1]财务取数接口!$E$4),"")) -> 筐 | F5: =IF($T$4=0,IF($M5="","",$M5),IFERROR(IF([1]财务取数接口!$G$4=0,"",[1]财务取数接口!$G$4),"")) | G5: =IF($T$4=0,IF($N5="","",$N5),IFERROR(IF([1]财务取数接口!$H$4=0,"",[1]财务取数接口!$H$4),"")) | H5: =IF($T$4=0,IF($O5="","",$O5),IFERROR(IF([1]财务取数接口!$I$4=0,"",[1]财务取数接口!$I$4),"")) | P5: =IF(AND($C5<>"",$C5<>"项目",OR(N($D5)<>0,N($E5)<>0,N($F5)<>0)),1,0) -> 0 | Q5: =N(Q4)+$P5 -> 0 | S5: 当前取数来源 | T5: =IF($T$4=1,"自动（跨文件链接）",IF($T$3>0,"应急备份","无数据")) -> 自动（跨文件链接）
A6: 5 | B6: =IF($T$4=0,IF($I6="","",$I6),IFERROR(IF([1]财务取数接口!$B$5=0,"",[1]财务取数接口!$B$5),"")) -> 46266 | C6: =IF($T$4=0,IF($J6="","",$J6),IFERROR(IF([1]财务取数接口!$C$5=0,"",[1]财务取数接口!$C$5),"")) -> 仓储费 | D6: =IF($T$4=0,IF($K6="","",$K6),IFERROR(IF([1]财务取数接口!$D$5=0,"",[1]财务取数接口!$D$5),"")) -> 20169 | E6: =IF($T$4=0,IF($L6="","",$L6),IFERROR(IF([1]财务取数接口!$E$5=0,"",[1]财务取数接口!$E$5),"")) -> 筐 | F6: =IF($T$4=0,IF($M6="","",$M6),IFERROR(IF([1]财务取数接口!$G$5=0,"",[1]财务取数接口!$G$5),"")) | G6: =IF($T$4=0,IF($N6="","",$N6),IFERROR(IF([1]财务取数接口!$H$5=0,"",[1]财务取数接口!$H$5),"")) | H6: =IF($T$4=0,IF($O6="","",$O6),IFERROR(IF([1]财务取数接口!$I$5=0,"",[1]财务取数接口!$I$5),"")) | P6: =IF(AND($C6<>"",$C6<>"项目",OR(N($D6)<>0,N($E6)<>0,N($F6)<>0)),1,0) -> 1 | Q6: =N(Q5)+$P6 -> 1 | S6: =IF($T$2="断开",IF($T$3>0,"✘ 链接已断开，正在用【应急备份区】的 "&$T$3&" 行数据出账（不是实时数）。修复：菜单【数据】→【编辑链接】→【更改源】，重新指向《01_水果进销存台账模板.xlsx》","✘ 链接已断开，而且应急备份区是空的，本册报表将缺少这本业务册的全部数据。修复：菜单【数据】→【编辑链接】→【更改源】，重新指向《01_水果进销存台账模板.xlsx》"),IF($T$2="未更新",IF($T$3>0,"★ 链接还没更新，或者那两个文件被改名、挪走了。正在用【应急备份区】的 "&$T$3&" 行数据出账（不是实时数）。修复：菜单【数据】→【编辑链接】→先点【立即更新值】；还是取不到数就点【更改源】重新指向《01_水果进销存台账模板.xlsx》","★ 链接还没更新，或者那两个文件被改名、挪走了，而且没有应急备份，本册报表会缺少这本业务册的全部数据。修复：菜单【数据】→【编辑链接】→先点【立即更新值】；还是取不到数就点【更改源】重新指向《01_水果进销存台账模板.xlsx》"),"✔ 链接正常，已自动取到 "&$T$1&" 行。备份区现有 "&$T$3&" 行。建议每月底把 B5:H168 复制→选择性粘贴【数值】到 I5，作为断链时的兜底")) -> ✔ 链接正常，已自动取到 11 行。备份区现有 0 行。建议每月底把 B5:H168 复制→选择性粘贴【数值】到 I5，作为断链时的兜底
A7: 6 | B7: =IF($T$4=0,IF($I7="","",$I7),IFERROR(IF([1]财务取数接口!$B$6=0,"",[1]财务取数接口!$B$6),"")) -> 46296 | C7: =IF($T$4=0,IF($J7="","",$J7),IFERROR(IF([1]财务取数接口!$C$6=0,"",[1]财务取数接口!$C$6),"")) -> 仓储费 | D7: =IF($T$4=0,IF($K7="","",$K7),IFERROR(IF([1]财务取数接口!$D$6=0,"",[1]财务取数接口!$D$6),"")) | E7: =IF($T$4=0,IF($L7="","",$L7),IFERROR(IF([1]财务取数接口!$E$6=0,"",[1]财务取数接口!$E$6),"")) -> 筐 | F7: =IF($T$4=0,IF($M7="","",$M7),IFERROR(IF([1]财务取数接口!$G$6=0,"",[1]财务取数接口!$G$6),"")) | G7: =IF($T$4=0,IF($N7="","",$N7),IFERROR(IF([1]财务取数接口!$H$6=0,"",[1]财务取数接口!$H$6),"")) | H7: =IF($T$4=0,IF($O7="","",$O7),IFERROR(IF([1]财务取数接口!$I$6=0,"",[1]财务取数接口!$I$6),"")) | P7: =IF(AND($C7<>"",$C7<>"项目",OR(N($D7)<>0,N($E7)<>0,N($F7)<>0)),1,0) -> 0 | Q7: =N(Q6)+$P7 -> 1
A8: 7 | B8: =IF($T$4=0,IF($I8="","",$I8),IFERROR(IF([1]财务取数接口!$B$7=0,"",[1]财务取数接口!$B$7),"")) -> 46327 | C8: =IF($T$4=0,IF($J8="","",$J8),IFERROR(IF([1]财务取数接口!$C$7=0,"",[1]财务取数接口!$C$7),"")) -> 仓储费 | D8: =IF($T$4=0,IF($K8="","",$K8),IFERROR(IF([1]财务取数接口!$D$7=0,"",[1]财务取数接口!$D$7),"")) | E8: =IF($T$4=0,IF($L8="","",$L8),IFERROR(IF([1]财务取数接口!$E$7=0,"",[1]财务取数接口!$E$7),"")) -> 筐 | F8: =IF($T$4=0,IF($M8="","",$M8),IFERROR(IF([1]财务取数接口!$G$7=0,"",[1]财务取数接口!$G$7),"")) | G8: =IF($T$4=0,IF($N8="","",$N8),IFERROR(IF([1]财务取数接口!$H$7=0,"",[1]财务取数接口!$H$7),"")) | H8: =IF($T$4=0,IF($O8="","",$O8),IFERROR(IF([1]财务取数接口!$I$7=0,"",[1]财务取数接口!$I$7),"")) | P8: =IF(AND($C8<>"",$C8<>"项目",OR(N($D8)<>0,N($E8)<>0,N($F8)<>0)),1,0) -> 0 | Q8: =N(Q7)+$P8 -> 1
A9: 8 | B9: =IF($T$4=0,IF($I9="","",$I9),IFERROR(IF([1]财务取数接口!$B$8=0,"",[1]财务取数接口!$B$8),"")) -> 46357 | C9: =IF($T$4=0,IF($J9="","",$J9),IFERROR(IF([1]财务取数接口!$C$8=0,"",[1]财务取数接口!$C$8),"")) -> 仓储费 | D9: =IF($T$4=0,IF($K9="","",$K9),IFERROR(IF([1]财务取数接口!$D$8=0,"",[1]财务取数接口!$D$8),"")) | E9: =IF($T$4=0,IF($L9="","",$L9),IFERROR(IF([1]财务取数接口!$E$8=0,"",[1]财务取数接口!$E$8),"")) -> 筐 | F9: =IF($T$4=0,IF($M9="","",$M9),IFERROR(IF([1]财务取数接口!$G$8=0,"",[1]财务取数接口!$G$8),"")) | G9: =IF($T$4=0,IF($N9="","",$N9),IFERROR(IF([1]财务取数接口!$H$8=0,"",[1]财务取数接口!$H$8),"")) | H9: =IF($T$4=0,IF($O9="","",$O9),IFERROR(IF([1]财务取数接口!$I$8=0,"",[1]财务取数接口!$I$8),"")) | P9: =IF(AND($C9<>"",$C9<>"项目",OR(N($D9)<>0,N($E9)<>0,N($F9)<>0)),1,0) -> 0 | Q9: =N(Q8)+$P9 -> 1
A10: 9 | B10: =IF($T$4=0,IF($I10="","",$I10),IFERROR(IF([1]财务取数接口!$B$9=0,"",[1]财务取数接口!$B$9),"")) -> 46388 | C10: =IF($T$4=0,IF($J10="","",$J10),IFERROR(IF([1]财务取数接口!$C$9=0,"",[1]财务取数接口!$C$9),"")) -> 仓储费 | D10: =IF($T$4=0,IF($K10="","",$K10),IFERROR(IF([1]财务取数接口!$D$9=0,"",[1]财务取数接口!$D$9),"")) | E10: =IF($T$4=0,IF($L10="","",$L10),IFERROR(IF([1]财务取数接口!$E$9=0,"",[1]财务取数接口!$E$9),"")) -> 筐 | F10: =IF($T$4=0,IF($M10="","",$M10),IFERROR(IF([1]财务取数接口!$G$9=0,"",[1]财务取数接口!$G$9),"")) | G10: =IF($T$4=0,IF($N10="","",$N10),IFERROR(IF([1]财务取数接口!$H$9=0,"",[1]财务取数接口!$H$9),"")) | H10: =IF($T$4=0,IF($O10="","",$O10),IFERROR(IF([1]财务取数接口!$I$9=0,"",[1]财务取数接口!$I$9),"")) | P10: =IF(AND($C10<>"",$C10<>"项目",OR(N($D10)<>0,N($E10)<>0,N($F10)<>0)),1,0) -> 0 | Q10: =N(Q9)+$P10 -> 1
A11: 10 | B11: =IF($T$4=0,IF($I11="","",$I11),IFERROR(IF([1]财务取数接口!$B$10=0,"",[1]财务取数接口!$B$10),"")) -> 46419 | C11: =IF($T$4=0,IF($J11="","",$J11),IFERROR(IF([1]财务取数接口!$C$10=0,"",[1]财务取数接口!$C$10),"")) -> 仓储费 | D11: =IF($T$4=0,IF($K11="","",$K11),IFERROR(IF([1]财务取数接口!$D$10=0,"",[1]财务取数接口!$D$10),"")) | E11: =IF($T$4=0,IF($L11="","",$L11),IFERROR(IF([1]财务取数接口!$E$10=0,"",[1]财务取数接口!$E$10),"")) -> 筐 | F11: =IF($T$4=0,IF($M11="","",$M11),IFERROR(IF([1]财务取数接口!$G$10=0,"",[1]财务取数接口!$G$10),"")) | G11: =IF($T$4=0,IF($N11="","",$N11),IFERROR(IF([1]财务取数接口!$H$10=0,"",[1]财务取数接口!$H$10),"")) | H11: =IF($T$4=0,IF($O11="","",$O11),IFERROR(IF([1]财务取数接口!$I$10=0,"",[1]财务取数接口!$I$10),"")) | P11: =IF(AND($C11<>"",$C11<>"项目",OR(N($D11)<>0,N($E11)<>0,N($F11)<>0)),1,0) -> 0 | Q11: =N(Q10)+$P11 -> 1
A12: 11 | B12: =IF($T$4=0,IF($I12="","",$I12),IFERROR(IF([1]财务取数接口!$B$11=0,"",[1]财务取数接口!$B$11),"")) -> 46447 | C12: =IF($T$4=0,IF($J12="","",$J12),IFERROR(IF([1]财务取数接口!$C$11=0,"",[1]财务取数接口!$C$11),"")) -> 仓储费 | D12: =IF($T$4=0,IF($K12="","",$K12),IFERROR(IF([1]财务取数接口!$D$11=0,"",[1]财务取数接口!$D$11),"")) | E12: =IF($T$4=0,IF($L12="","",$L12),IFERROR(IF([1]财务取数接口!$E$11=0,"",[1]财务取数接口!$E$11),"")) -> 筐 | F12: =IF($T$4=0,IF($M12="","",$M12),IFERROR(IF([1]财务取数接口!$G$11=0,"",[1]财务取数接口!$G$11),"")) | G12: =IF($T$4=0,IF($N12="","",$N12),IFERROR(IF([1]财务取数接口!$H$11=0,"",[1]财务取数接口!$H$11),"")) | H12: =IF($T$4=0,IF($O12="","",$O12),IFERROR(IF([1]财务取数接口!$I$11=0,"",[1]财务取数接口!$I$11),"")) | P12: =IF(AND($C12<>"",$C12<>"项目",OR(N($D12)<>0,N($E12)<>0,N($F12)<>0)),1,0) -> 0 | Q12: =N(Q11)+$P12 -> 1
A13: 12 | B13: =IF($T$4=0,IF($I13="","",$I13),IFERROR(IF([1]财务取数接口!$B$12=0,"",[1]财务取数接口!$B$12),"")) -> 46478 | C13: =IF($T$4=0,IF($J13="","",$J13),IFERROR(IF([1]财务取数接口!$C$12=0,"",[1]财务取数接口!$C$12),"")) -> 仓储费 | D13: =IF($T$4=0,IF($K13="","",$K13),IFERROR(IF([1]财务取数接口!$D$12=0,"",[1]财务取数接口!$D$12),"")) | E13: =IF($T$4=0,IF($L13="","",$L13),IFERROR(IF([1]财务取数接口!$E$12=0,"",[1]财务取数接口!$E$12),"")) -> 筐 | F13: =IF($T$4=0,IF($M13="","",$M13),IFERROR(IF([1]财务取数接口!$G$12=0,"",[1]财务取数接口!$G$12),"")) | G13: =IF($T$4=0,IF($N13="","",$N13),IFERROR(IF([1]财务取数接口!$H$12=0,"",[1]财务取数接口!$H$12),"")) | H13: =IF($T$4=0,IF($O13="","",$O13),IFERROR(IF([1]财务取数接口!$I$12=0,"",[1]财务取数接口!$I$12),"")) | P13: =IF(AND($C13<>"",$C13<>"项目",OR(N($D13)<>0,N($E13)<>0,N($F13)<>0)),1,0) -> 0 | Q13: =N(Q12)+$P13 -> 1
A14: 13 | B14: =IF($T$4=0,IF($I14="","",$I14),IFERROR(IF([1]财务取数接口!$B$13=0,"",[1]财务取数接口!$B$13),"")) -> 46508 | C14: =IF($T$4=0,IF($J14="","",$J14),IFERROR(IF([1]财务取数接口!$C$13=0,"",[1]财务取数接口!$C$13),"")) -> 仓储费 | D14: =IF($T$4=0,IF($K14="","",$K14),IFERROR(IF([1]财务取数接口!$D$13=0,"",[1]财务取数接口!$D$13),"")) | E14: =IF($T$4=0,IF($L14="","",$L14),IFERROR(IF([1]财务取数接口!$E$13=0,"",[1]财务取数接口!$E$13),"")) -> 筐 | F14: =IF($T$4=0,IF($M14="","",$M14),IFERROR(IF([1]财务取数接口!$G$13=0,"",[1]财务取数接口!$G$13),"")) | G14: =IF($T$4=0,IF($N14="","",$N14),IFERROR(IF([1]财务取数接口!$H$13=0,"",[1]财务取数接口!$H$13),"")) | H14: =IF($T$4=0,IF($O14="","",$O14),IFERROR(IF([1]财务取数接口!$I$13=0,"",[1]财务取数接口!$I$13),"")) | P14: =IF(AND($C14<>"",$C14<>"项目",OR(N($D14)<>0,N($E14)<>0,N($F14)<>0)),1,0) -> 0 | Q14: =N(Q13)+$P14 -> 1
A15: 14 | B15: =IF($T$4=0,IF($I15="","",$I15),IFERROR(IF([1]财务取数接口!$B$14=0,"",[1]财务取数接口!$B$14),"")) -> 46539 | C15: =IF($T$4=0,IF($J15="","",$J15),IFERROR(IF([1]财务取数接口!$C$14=0,"",[1]财务取数接口!$C$14),"")) -> 仓储费 | D15: =IF($T$4=0,IF($K15="","",$K15),IFERROR(IF([1]财务取数接口!$D$14=0,"",[1]财务取数接口!$D$14),"")) | E15: =IF($T$4=0,IF($L15="","",$L15),IFERROR(IF([1]财务取数接口!$E$14=0,"",[1]财务取数接口!$E$14),"")) -> 筐 | F15: =IF($T$4=0,IF($M15="","",$M15),IFERROR(IF([1]财务取数接口!$G$14=0,"",[1]财务取数接口!$G$14),"")) | G15: =IF($T$4=0,IF($N15="","",$N15),IFERROR(IF([1]财务取数接口!$H$14=0,"",[1]财务取数接口!$H$14),"")) | H15: =IF($T$4=0,IF($O15="","",$O15),IFERROR(IF([1]财务取数接口!$I$14=0,"",[1]财务取数接口!$I$14),"")) | P15: =IF(AND($C15<>"",$C15<>"项目",OR(N($D15)<>0,N($E15)<>0,N($F15)<>0)),1,0) -> 0 | Q15: =N(Q14)+$P15 -> 1
A16: 15 | B16: =IF($T$4=0,IF($I16="","",$I16),IFERROR(IF([1]财务取数接口!$B$15=0,"",[1]财务取数接口!$B$15),"")) -> 46569 | C16: =IF($T$4=0,IF($J16="","",$J16),IFERROR(IF([1]财务取数接口!$C$15=0,"",[1]财务取数接口!$C$15),"")) -> 仓储费 | D16: =IF($T$4=0,IF($K16="","",$K16),IFERROR(IF([1]财务取数接口!$D$15=0,"",[1]财务取数接口!$D$15),"")) | E16: =IF($T$4=0,IF($L16="","",$L16),IFERROR(IF([1]财务取数接口!$E$15=0,"",[1]财务取数接口!$E$15),"")) -> 筐 | F16: =IF($T$4=0,IF($M16="","",$M16),IFERROR(IF([1]财务取数接口!$G$15=0,"",[1]财务取数接口!$G$15),"")) | G16: =IF($T$4=0,IF($N16="","",$N16),IFERROR(IF([1]财务取数接口!$H$15=0,"",[1]财务取数接口!$H$15),"")) | H16: =IF($T$4=0,IF($O16="","",$O16),IFERROR(IF([1]财务取数接口!$I$15=0,"",[1]财务取数接口!$I$15),"")) | P16: =IF(AND($C16<>"",$C16<>"项目",OR(N($D16)<>0,N($E16)<>0,N($F16)<>0)),1,0) -> 0 | Q16: =N(Q15)+$P16 -> 1
A17: 16 | B17: =IF($T$4=0,IF($I17="","",$I17),IFERROR(IF([1]财务取数接口!$B$16=0,"",[1]财务取数接口!$B$16),"")) -> 46600 | C17: =IF($T$4=0,IF($J17="","",$J17),IFERROR(IF([1]财务取数接口!$C$16=0,"",[1]财务取数接口!$C$16),"")) -> 仓储费 | D17: =IF($T$4=0,IF($K17="","",$K17),IFERROR(IF([1]财务取数接口!$D$16=0,"",[1]财务取数接口!$D$16),"")) | E17: =IF($T$4=0,IF($L17="","",$L17),IFERROR(IF([1]财务取数接口!$E$16=0,"",[1]财务取数接口!$E$16),"")) -> 筐 | F17: =IF($T$4=0,IF($M17="","",$M17),IFERROR(IF([1]财务取数接口!$G$16=0,"",[1]财务取数接口!$G$16),"")) | G17: =IF($T$4=0,IF($N17="","",$N17),IFERROR(IF([1]财务取数接口!$H$16=0,"",[1]财务取数接口!$H$16),"")) | H17: =IF($T$4=0,IF($O17="","",$O17),IFERROR(IF([1]财务取数接口!$I$16=0,"",[1]财务取数接口!$I$16),"")) | P17: =IF(AND($C17<>"",$C17<>"项目",OR(N($D17)<>0,N($E17)<>0,N($F17)<>0)),1,0) -> 0 | Q17: =N(Q16)+$P17 -> 1
A18: 17 | B18: =IF($T$4=0,IF($I18="","",$I18),IFERROR(IF([1]财务取数接口!$B$17=0,"",[1]财务取数接口!$B$17),"")) -> 46631 | C18: =IF($T$4=0,IF($J18="","",$J18),IFERROR(IF([1]财务取数接口!$C$17=0,"",[1]财务取数接口!$C$17),"")) -> 仓储费 | D18: =IF($T$4=0,IF($K18="","",$K18),IFERROR(IF([1]财务取数接口!$D$17=0,"",[1]财务取数接口!$D$17),"")) | E18: =IF($T$4=0,IF($L18="","",$L18),IFERROR(IF([1]财务取数接口!$E$17=0,"",[1]财务取数接口!$E$17),"")) -> 筐 | F18: =IF($T$4=0,IF($M18="","",$M18),IFERROR(IF([1]财务取数接口!$G$17=0,"",[1]财务取数接口!$G$17),"")) | G18: =IF($T$4=0,IF($N18="","",$N18),IFERROR(IF([1]财务取数接口!$H$17=0,"",[1]财务取数接口!$H$17),"")) | H18: =IF($T$4=0,IF($O18="","",$O18),IFERROR(IF([1]财务取数接口!$I$17=0,"",[1]财务取数接口!$I$17),"")) | P18: =IF(AND($C18<>"",$C18<>"项目",OR(N($D18)<>0,N($E18)<>0,N($F18)<>0)),1,0) -> 0 | Q18: =N(Q17)+$P18 -> 1
A19: 18 | B19: =IF($T$4=0,IF($I19="","",$I19),IFERROR(IF([1]财务取数接口!$B$18=0,"",[1]财务取数接口!$B$18),"")) -> 46661 | C19: =IF($T$4=0,IF($J19="","",$J19),IFERROR(IF([1]财务取数接口!$C$18=0,"",[1]财务取数接口!$C$18),"")) -> 仓储费 | D19: =IF($T$4=0,IF($K19="","",$K19),IFERROR(IF([1]财务取数接口!$D$18=0,"",[1]财务取数接口!$D$18),"")) | E19: =IF($T$4=0,IF($L19="","",$L19),IFERROR(IF([1]财务取数接口!$E$18=0,"",[1]财务取数接口!$E$18),"")) -> 筐 | F19: =IF($T$4=0,IF($M19="","",$M19),IFERROR(IF([1]财务取数接口!$G$18=0,"",[1]财务取数接口!$G$18),"")) | G19: =IF($T$4=0,IF($N19="","",$N19),IFERROR(IF([1]财务取数接口!$H$18=0,"",[1]财务取数接口!$H$18),"")) | H19: =IF($T$4=0,IF($O19="","",$O19),IFERROR(IF([1]财务取数接口!$I$18=0,"",[1]财务取数接口!$I$18),"")) | P19: =IF(AND($C19<>"",$C19<>"项目",OR(N($D19)<>0,N($E19)<>0,N($F19)<>0)),1,0) -> 0 | Q19: =N(Q18)+$P19 -> 1
A20: 19 | B20: =IF($T$4=0,IF($I20="","",$I20),IFERROR(IF([1]财务取数接口!$B$19=0,"",[1]财务取数接口!$B$19),"")) -> 46692 | C20: =IF($T$4=0,IF($J20="","",$J20),IFERROR(IF([1]财务取数接口!$C$19=0,"",[1]财务取数接口!$C$19),"")) -> 仓储费 | D20: =IF($T$4=0,IF($K20="","",$K20),IFERROR(IF([1]财务取数接口!$D$19=0,"",[1]财务取数接口!$D$19),"")) | E20: =IF($T$4=0,IF($L20="","",$L20),IFERROR(IF([1]财务取数接口!$E$19=0,"",[1]财务取数接口!$E$19),"")) -> 筐 | F20: =IF($T$4=0,IF($M20="","",$M20),IFERROR(IF([1]财务取数接口!$G$19=0,"",[1]财务取数接口!$G$19),"")) | G20: =IF($T$4=0,IF($N20="","",$N20),IFERROR(IF([1]财务取数接口!$H$19=0,"",[1]财务取数接口!$H$19),"")) | H20: =IF($T$4=0,IF($O20="","",$O20),IFERROR(IF([1]财务取数接口!$I$19=0,"",[1]财务取数接口!$I$19),"")) | P20: =IF(AND($C20<>"",$C20<>"项目",OR(N($D20)<>0,N($E20)<>0,N($F20)<>0)),1,0) -> 0 | Q20: =N(Q19)+$P20 -> 1
A21: 20 | B21: =IF($T$4=0,IF($I21="","",$I21),IFERROR(IF([1]财务取数接口!$B$20=0,"",[1]财务取数接口!$B$20),"")) -> 46722 | C21: =IF($T$4=0,IF($J21="","",$J21),IFERROR(IF([1]财务取数接口!$C$20=0,"",[1]财务取数接口!$C$20),"")) -> 仓储费 | D21: =IF($T$4=0,IF($K21="","",$K21),IFERROR(IF([1]财务取数接口!$D$20=0,"",[1]财务取数接口!$D$20),"")) | E21: =IF($T$4=0,IF($L21="","",$L21),IFERROR(IF([1]财务取数接口!$E$20=0,"",[1]财务取数接口!$E$20),"")) -> 筐 | F21: =IF($T$4=0,IF($M21="","",$M21),IFERROR(IF([1]财务取数接口!$G$20=0,"",[1]财务取数接口!$G$20),"")) | G21: =IF($T$4=0,IF($N21="","",$N21),IFERROR(IF([1]财务取数接口!$H$20=0,"",[1]财务取数接口!$H$20),"")) | H21: =IF($T$4=0,IF($O21="","",$O21),IFERROR(IF([1]财务取数接口!$I$20=0,"",[1]财务取数接口!$I$20),"")) | P21: =IF(AND($C21<>"",$C21<>"项目",OR(N($D21)<>0,N($E21)<>0,N($F21)<>0)),1,0) -> 0 | Q21: =N(Q20)+$P21 -> 1
A22: 21 | B22: =IF($T$4=0,IF($I22="","",$I22),IFERROR(IF([1]财务取数接口!$B$21=0,"",[1]财务取数接口!$B$21),"")) -> 46753 | C22: =IF($T$4=0,IF($J22="","",$J22),IFERROR(IF([1]财务取数接口!$C$21=0,"",[1]财务取数接口!$C$21),"")) -> 仓储费 | D22: =IF($T$4=0,IF($K22="","",$K22),IFERROR(IF([1]财务取数接口!$D$21=0,"",[1]财务取数接口!$D$21),"")) | E22: =IF($T$4=0,IF($L22="","",$L22),IFERROR(IF([1]财务取数接口!$E$21=0,"",[1]财务取数接口!$E$21),"")) -> 筐 | F22: =IF($T$4=0,IF($M22="","",$M22),IFERROR(IF([1]财务取数接口!$G$21=0,"",[1]财务取数接口!$G$21),"")) | G22: =IF($T$4=0,IF($N22="","",$N22),IFERROR(IF([1]财务取数接口!$H$21=0,"",[1]财务取数接口!$H$21),"")) | H22: =IF($T$4=0,IF($O22="","",$O22),IFERROR(IF([1]财务取数接口!$I$21=0,"",[1]财务取数接口!$I$21),"")) | P22: =IF(AND($C22<>"",$C22<>"项目",OR(N($D22)<>0,N($E22)<>0,N($F22)<>0)),1,0) -> 0 | Q22: =N(Q21)+$P22 -> 1
A23: 22 | B23: =IF($T$4=0,IF($I23="","",$I23),IFERROR(IF([1]财务取数接口!$B$22=0,"",[1]财务取数接口!$B$22),"")) -> 46784 | C23: =IF($T$4=0,IF($J23="","",$J23),IFERROR(IF([1]财务取数接口!$C$22=0,"",[1]财务取数接口!$C$22),"")) -> 仓储费 | D23: =IF($T$4=0,IF($K23="","",$K23),IFERROR(IF([1]财务取数接口!$D$22=0,"",[1]财务取数接口!$D$22),"")) | E23: =IF($T$4=0,IF($L23="","",$L23),IFERROR(IF([1]财务取数接口!$E$22=0,"",[1]财务取数接口!$E$22),"")) -> 筐 | F23: =IF($T$4=0,IF($M23="","",$M23),IFERROR(IF([1]财务取数接口!$G$22=0,"",[1]财务取数接口!$G$22),"")) | G23: =IF($T$4=0,IF($N23="","",$N23),IFERROR(IF([1]财务取数接口!$H$22=0,"",[1]财务取数接口!$H$22),"")) | H23: =IF($T$4=0,IF($O23="","",$O23),IFERROR(IF([1]财务取数接口!$I$22=0,"",[1]财务取数接口!$I$22),"")) | P23: =IF(AND($C23<>"",$C23<>"项目",OR(N($D23)<>0,N($E23)<>0,N($F23)<>0)),1,0) -> 0 | Q23: =N(Q22)+$P23 -> 1
A24: 23 | B24: =IF($T$4=0,IF($I24="","",$I24),IFERROR(IF([1]财务取数接口!$B$23=0,"",[1]财务取数接口!$B$23),"")) -> 46813 | C24: =IF($T$4=0,IF($J24="","",$J24),IFERROR(IF([1]财务取数接口!$C$23=0,"",[1]财务取数接口!$C$23),"")) -> 仓储费 | D24: =IF($T$4=0,IF($K24="","",$K24),IFERROR(IF([1]财务取数接口!$D$23=0,"",[1]财务取数接口!$D$23),"")) | E24: =IF($T$4=0,IF($L24="","",$L24),IFERROR(IF([1]财务取数接口!$E$23=0,"",[1]财务取数接口!$E$23),"")) -> 筐 | F24: =IF($T$4=0,IF($M24="","",$M24),IFERROR(IF([1]财务取数接口!$G$23=0,"",[1]财务取数接口!$G$23),"")) | G24: =IF($T$4=0,IF($N24="","",$N24),IFERROR(IF([1]财务取数接口!$H$23=0,"",[1]财务取数接口!$H$23),"")) | H24: =IF($T$4=0,IF($O24="","",$O24),IFERROR(IF([1]财务取数接口!$I$23=0,"",[1]财务取数接口!$I$23),"")) | P24: =IF(AND($C24<>"",$C24<>"项目",OR(N($D24)<>0,N($E24)<>0,N($F24)<>0)),1,0) -> 0 | Q24: =N(Q23)+$P24 -> 1
A25: 24 | B25: =IF($T$4=0,IF($I25="","",$I25),IFERROR(IF([1]财务取数接口!$B$24=0,"",[1]财务取数接口!$B$24),"")) -> 46844 | C25: =IF($T$4=0,IF($J25="","",$J25),IFERROR(IF([1]财务取数接口!$C$24=0,"",[1]财务取数接口!$C$24),"")) -> 仓储费 | D25: =IF($T$4=0,IF($K25="","",$K25),IFERROR(IF([1]财务取数接口!$D$24=0,"",[1]财务取数接口!$D$24),"")) | E25: =IF($T$4=0,IF($L25="","",$L25),IFERROR(IF([1]财务取数接口!$E$24=0,"",[1]财务取数接口!$E$24),"")) -> 筐 | F25: =IF($T$4=0,IF($M25="","",$M25),IFERROR(IF([1]财务取数接口!$G$24=0,"",[1]财务取数接口!$G$24),"")) | G25: =IF($T$4=0,IF($N25="","",$N25),IFERROR(IF([1]财务取数接口!$H$24=0,"",[1]财务取数接口!$H$24),"")) | H25: =IF($T$4=0,IF($O25="","",$O25),IFERROR(IF([1]财务取数接口!$I$24=0,"",[1]财务取数接口!$I$24),"")) | P25: =IF(AND($C25<>"",$C25<>"项目",OR(N($D25)<>0,N($E25)<>0,N($F25)<>0)),1,0) -> 0 | Q25: =N(Q24)+$P25 -> 1
A26: 25 | B26: =IF($T$4=0,IF($I26="","",$I26),IFERROR(IF([1]财务取数接口!$B$25=0,"",[1]财务取数接口!$B$25),"")) -> 46874 | C26: =IF($T$4=0,IF($J26="","",$J26),IFERROR(IF([1]财务取数接口!$C$25=0,"",[1]财务取数接口!$C$25),"")) -> 仓储费 | D26: =IF($T$4=0,IF($K26="","",$K26),IFERROR(IF([1]财务取数接口!$D$25=0,"",[1]财务取数接口!$D$25),"")) | E26: =IF($T$4=0,IF($L26="","",$L26),IFERROR(IF([1]财务取数接口!$E$25=0,"",[1]财务取数接口!$E$25),"")) -> 筐 | F26: =IF($T$4=0,IF($M26="","",$M26),IFERROR(IF([1]财务取数接口!$G$25=0,"",[1]财务取数接口!$G$25),"")) | G26: =IF($T$4=0,IF($N26="","",$N26),IFERROR(IF([1]财务取数接口!$H$25=0,"",[1]财务取数接口!$H$25),"")) | H26: =IF($T$4=0,IF($O26="","",$O26),IFERROR(IF([1]财务取数接口!$I$25=0,"",[1]财务取数接口!$I$25),"")) | P26: =IF(AND($C26<>"",$C26<>"项目",OR(N($D26)<>0,N($E26)<>0,N($F26)<>0)),1,0) -> 0 | Q26: =N(Q25)+$P26 -> 1
A27: 26 | B27: =IF($T$4=0,IF($I27="","",$I27),IFERROR(IF([1]财务取数接口!$B$26=0,"",[1]财务取数接口!$B$26),"")) -> 46905 | C27: =IF($T$4=0,IF($J27="","",$J27),IFERROR(IF([1]财务取数接口!$C$26=0,"",[1]财务取数接口!$C$26),"")) -> 仓储费 | D27: =IF($T$4=0,IF($K27="","",$K27),IFERROR(IF([1]财务取数接口!$D$26=0,"",[1]财务取数接口!$D$26),"")) | E27: =IF($T$4=0,IF($L27="","",$L27),IFERROR(IF([1]财务取数接口!$E$26=0,"",[1]财务取数接口!$E$26),"")) -> 筐 | F27: =IF($T$4=0,IF($M27="","",$M27),IFERROR(IF([1]财务取数接口!$G$26=0,"",[1]财务取数接口!$G$26),"")) | G27: =IF($T$4=0,IF($N27="","",$N27),IFERROR(IF([1]财务取数接口!$H$26=0,"",[1]财务取数接口!$H$26),"")) | H27: =IF($T$4=0,IF($O27="","",$O27),IFERROR(IF([1]财务取数接口!$I$26=0,"",[1]财务取数接口!$I$26),"")) | P27: =IF(AND($C27<>"",$C27<>"项目",OR(N($D27)<>0,N($E27)<>0,N($F27)<>0)),1,0) -> 0 | Q27: =N(Q26)+$P27 -> 1
A28: 27 | B28: =IF($T$4=0,IF($I28="","",$I28),IFERROR(IF([1]财务取数接口!$B$27=0,"",[1]财务取数接口!$B$27),"")) -> 46935 | C28: =IF($T$4=0,IF($J28="","",$J28),IFERROR(IF([1]财务取数接口!$C$27=0,"",[1]财务取数接口!$C$27),"")) -> 仓储费 | D28: =IF($T$4=0,IF($K28="","",$K28),IFERROR(IF([1]财务取数接口!$D$27=0,"",[1]财务取数接口!$D$27),"")) | E28: =IF($T$4=0,IF($L28="","",$L28),IFERROR(IF([1]财务取数接口!$E$27=0,"",[1]财务取数接口!$E$27),"")) -> 筐 | F28: =IF($T$4=0,IF($M28="","",$M28),IFERROR(IF([1]财务取数接口!$G$27=0,"",[1]财务取数接口!$G$27),"")) | G28: =IF($T$4=0,IF($N28="","",$N28),IFERROR(IF([1]财务取数接口!$H$27=0,"",[1]财务取数接口!$H$27),"")) | H28: =IF($T$4=0,IF($O28="","",$O28),IFERROR(IF([1]财务取数接口!$I$27=0,"",[1]财务取数接口!$I$27),"")) | P28: =IF(AND($C28<>"",$C28<>"项目",OR(N($D28)<>0,N($E28)<>0,N($F28)<>0)),1,0) -> 0 | Q28: =N(Q27)+$P28 -> 1
A29: 28 | B29: =IF($T$4=0,IF($I29="","",$I29),IFERROR(IF([1]财务取数接口!$B$28=0,"",[1]财务取数接口!$B$28),"")) -> 46235 | C29: =IF($T$4=0,IF($J29="","",$J29),IFERROR(IF([1]财务取数接口!$C$28=0,"",[1]财务取数接口!$C$28),"")) -> 周转费 | D29: =IF($T$4=0,IF($K29="","",$K29),IFERROR(IF([1]财务取数接口!$D$28=0,"",[1]财务取数接口!$D$28),"")) -> 13104 | E29: =IF($T$4=0,IF($L29="","",$L29),IFERROR(IF([1]财务取数接口!$E$28=0,"",[1]财务取数接口!$E$28),"")) -> 筐 | F29: =IF($T$4=0,IF($M29="","",$M29),IFERROR(IF([1]财务取数接口!$G$28=0,"",[1]财务取数接口!$G$28),"")) | G29: =IF($T$4=0,IF($N29="","",$N29),IFERROR(IF([1]财务取数接口!$H$28=0,"",[1]财务取数接口!$H$28),"")) | H29: =IF($T$4=0,IF($O29="","",$O29),IFERROR(IF([1]财务取数接口!$I$28=0,"",[1]财务取数接口!$I$28),"")) | P29: =IF(AND($C29<>"",$C29<>"项目",OR(N($D29)<>0,N($E29)<>0,N($F29)<>0)),1,0) -> 1 | Q29: =N(Q28)+$P29 -> 2
A30: 29 | B30: =IF($T$4=0,IF($I30="","",$I30),IFERROR(IF([1]财务取数接口!$B$29=0,"",[1]财务取数接口!$B$29),"")) -> 46266 | C30: =IF($T$4=0,IF($J30="","",$J30),IFERROR(IF([1]财务取数接口!$C$29=0,"",[1]财务取数接口!$C$29),"")) -> 周转费 | D30: =IF($T$4=0,IF($K30="","",$K30),IFERROR(IF([1]财务取数接口!$D$29=0,"",[1]财务取数接口!$D$29),"")) -> 5597 | E30: =IF($T$4=0,IF($L30="","",$L30),IFERROR(IF([1]财务取数接口!$E$29=0,"",[1]财务取数接口!$E$29),"")) -> 筐 | F30: =IF($T$4=0,IF($M30="","",$M30),IFERROR(IF([1]财务取数接口!$G$29=0,"",[1]财务取数接口!$G$29),"")) | G30: =IF($T$4=0,IF($N30="","",$N30),IFERROR(IF([1]财务取数接口!$H$29=0,"",[1]财务取数接口!$H$29),"")) | H30: =IF($T$4=0,IF($O30="","",$O30),IFERROR(IF([1]财务取数接口!$I$29=0,"",[1]财务取数接口!$I$29),"")) | P30: =IF(AND($C30<>"",$C30<>"项目",OR(N($D30)<>0,N($E30)<>0,N($F30)<>0)),1,0) -> 1 | Q30: =N(Q29)+$P30 -> 3
A31: 30 | B31: =IF($T$4=0,IF($I31="","",$I31),IFERROR(IF([1]财务取数接口!$B$30=0,"",[1]财务取数接口!$B$30),"")) -> 46296 | C31: =IF($T$4=0,IF($J31="","",$J31),IFERROR(IF([1]财务取数接口!$C$30=0,"",[1]财务取数接口!$C$30),"")) -> 周转费 | D31: =IF($T$4=0,IF($K31="","",$K31),IFERROR(IF([1]财务取数接口!$D$30=0,"",[1]财务取数接口!$D$30),"")) | E31: =IF($T$4=0,IF($L31="","",$L31),IFERROR(IF([1]财务取数接口!$E$30=0,"",[1]财务取数接口!$E$30),"")) -> 筐 | F31: =IF($T$4=0,IF($M31="","",$M31),IFERROR(IF([1]财务取数接口!$G$30=0,"",[1]财务取数接口!$G$30),"")) | G31: =IF($T$4=0,IF($N31="","",$N31),IFERROR(IF([1]财务取数接口!$H$30=0,"",[1]财务取数接口!$H$30),"")) | H31: =IF($T$4=0,IF($O31="","",$O31),IFERROR(IF([1]财务取数接口!$I$30=0,"",[1]财务取数接口!$I$30),"")) | P31: =IF(AND($C31<>"",$C31<>"项目",OR(N($D31)<>0,N($E31)<>0,N($F31)<>0)),1,0) -> 0 | Q31: =N(Q30)+$P31 -> 3
A32: 31 | B32: =IF($T$4=0,IF($I32="","",$I32),IFERROR(IF([1]财务取数接口!$B$31=0,"",[1]财务取数接口!$B$31),"")) -> 46327 | C32: =IF($T$4=0,IF($J32="","",$J32),IFERROR(IF([1]财务取数接口!$C$31=0,"",[1]财务取数接口!$C$31),"")) -> 周转费 | D32: =IF($T$4=0,IF($K32="","",$K32),IFERROR(IF([1]财务取数接口!$D$31=0,"",[1]财务取数接口!$D$31),"")) | E32: =IF($T$4=0,IF($L32="","",$L32),IFERROR(IF([1]财务取数接口!$E$31=0,"",[1]财务取数接口!$E$31),"")) -> 筐 | F32: =IF($T$4=0,IF($M32="","",$M32),IFERROR(IF([1]财务取数接口!$G$31=0,"",[1]财务取数接口!$G$31),"")) | G32: =IF($T$4=0,IF($N32="","",$N32),IFERROR(IF([1]财务取数接口!$H$31=0,"",[1]财务取数接口!$H$31),"")) | H32: =IF($T$4=0,IF($O32="","",$O32),IFERROR(IF([1]财务取数接口!$I$31=0,"",[1]财务取数接口!$I$31),"")) | P32: =IF(AND($C32<>"",$C32<>"项目",OR(N($D32)<>0,N($E32)<>0,N($F32)<>0)),1,0) -> 0 | Q32: =N(Q31)+$P32 -> 3
A33: 32 | B33: =IF($T$4=0,IF($I33="","",$I33),IFERROR(IF([1]财务取数接口!$B$32=0,"",[1]财务取数接口!$B$32),"")) -> 46357 | C33: =IF($T$4=0,IF($J33="","",$J33),IFERROR(IF([1]财务取数接口!$C$32=0,"",[1]财务取数接口!$C$32),"")) -> 周转费 | D33: =IF($T$4=0,IF($K33="","",$K33),IFERROR(IF([1]财务取数接口!$D$32=0,"",[1]财务取数接口!$D$32),"")) | E33: =IF($T$4=0,IF($L33="","",$L33),IFERROR(IF([1]财务取数接口!$E$32=0,"",[1]财务取数接口!$E$32),"")) -> 筐 | F33: =IF($T$4=0,IF($M33="","",$M33),IFERROR(IF([1]财务取数接口!$G$32=0,"",[1]财务取数接口!$G$32),"")) | G33: =IF($T$4=0,IF($N33="","",$N33),IFERROR(IF([1]财务取数接口!$H$32=0,"",[1]财务取数接口!$H$32),"")) | H33: =IF($T$4=0,IF($O33="","",$O33),IFERROR(IF([1]财务取数接口!$I$32=0,"",[1]财务取数接口!$I$32),"")) | P33: =IF(AND($C33<>"",$C33<>"项目",OR(N($D33)<>0,N($E33)<>0,N($F33)<>0)),1,0) -> 0 | Q33: =N(Q32)+$P33 -> 3
A34: 33 | B34: =IF($T$4=0,IF($I34="","",$I34),IFERROR(IF([1]财务取数接口!$B$33=0,"",[1]财务取数接口!$B$33),"")) -> 46388 | C34: =IF($T$4=0,IF($J34="","",$J34),IFERROR(IF([1]财务取数接口!$C$33=0,"",[1]财务取数接口!$C$33),"")) -> 周转费 | D34: =IF($T$4=0,IF($K34="","",$K34),IFERROR(IF([1]财务取数接口!$D$33=0,"",[1]财务取数接口!$D$33),"")) | E34: =IF($T$4=0,IF($L34="","",$L34),IFERROR(IF([1]财务取数接口!$E$33=0,"",[1]财务取数接口!$E$33),"")) -> 筐 | F34: =IF($T$4=0,IF($M34="","",$M34),IFERROR(IF([1]财务取数接口!$G$33=0,"",[1]财务取数接口!$G$33),"")) | G34: =IF($T$4=0,IF($N34="","",$N34),IFERROR(IF([1]财务取数接口!$H$33=0,"",[1]财务取数接口!$H$33),"")) | H34: =IF($T$4=0,IF($O34="","",$O34),IFERROR(IF([1]财务取数接口!$I$33=0,"",[1]财务取数接口!$I$33),"")) | P34: =IF(AND($C34<>"",$C34<>"项目",OR(N($D34)<>0,N($E34)<>0,N($F34)<>0)),1,0) -> 0 | Q34: =N(Q33)+$P34 -> 3
A35: 34 | B35: =IF($T$4=0,IF($I35="","",$I35),IFERROR(IF([1]财务取数接口!$B$34=0,"",[1]财务取数接口!$B$34),"")) -> 46419 | C35: =IF($T$4=0,IF($J35="","",$J35),IFERROR(IF([1]财务取数接口!$C$34=0,"",[1]财务取数接口!$C$34),"")) -> 周转费 | D35: =IF($T$4=0,IF($K35="","",$K35),IFERROR(IF([1]财务取数接口!$D$34=0,"",[1]财务取数接口!$D$34),"")) | E35: =IF($T$4=0,IF($L35="","",$L35),IFERROR(IF([1]财务取数接口!$E$34=0,"",[1]财务取数接口!$E$34),"")) -> 筐 | F35: =IF($T$4=0,IF($M35="","",$M35),IFERROR(IF([1]财务取数接口!$G$34=0,"",[1]财务取数接口!$G$34),"")) | G35: =IF($T$4=0,IF($N35="","",$N35),IFERROR(IF([1]财务取数接口!$H$34=0,"",[1]财务取数接口!$H$34),"")) | H35: =IF($T$4=0,IF($O35="","",$O35),IFERROR(IF([1]财务取数接口!$I$34=0,"",[1]财务取数接口!$I$34),"")) | P35: =IF(AND($C35<>"",$C35<>"项目",OR(N($D35)<>0,N($E35)<>0,N($F35)<>0)),1,0) -> 0 | Q35: =N(Q34)+$P35 -> 3
A36: 35 | B36: =IF($T$4=0,IF($I36="","",$I36),IFERROR(IF([1]财务取数接口!$B$35=0,"",[1]财务取数接口!$B$35),"")) -> 46447 | C36: =IF($T$4=0,IF($J36="","",$J36),IFERROR(IF([1]财务取数接口!$C$35=0,"",[1]财务取数接口!$C$35),"")) -> 周转费 | D36: =IF($T$4=0,IF($K36="","",$K36),IFERROR(IF([1]财务取数接口!$D$35=0,"",[1]财务取数接口!$D$35),"")) | E36: =IF($T$4=0,IF($L36="","",$L36),IFERROR(IF([1]财务取数接口!$E$35=0,"",[1]财务取数接口!$E$35),"")) -> 筐 | F36: =IF($T$4=0,IF($M36="","",$M36),IFERROR(IF([1]财务取数接口!$G$35=0,"",[1]财务取数接口!$G$35),"")) | G36: =IF($T$4=0,IF($N36="","",$N36),IFERROR(IF([1]财务取数接口!$H$35=0,"",[1]财务取数接口!$H$35),"")) | H36: =IF($T$4=0,IF($O36="","",$O36),IFERROR(IF([1]财务取数接口!$I$35=0,"",[1]财务取数接口!$I$35),"")) | P36: =IF(AND($C36<>"",$C36<>"项目",OR(N($D36)<>0,N($E36)<>0,N($F36)<>0)),1,0) -> 0 | Q36: =N(Q35)+$P36 -> 3
A37: 36 | B37: =IF($T$4=0,IF($I37="","",$I37),IFERROR(IF([1]财务取数接口!$B$36=0,"",[1]财务取数接口!$B$36),"")) -> 46478 | C37: =IF($T$4=0,IF($J37="","",$J37),IFERROR(IF([1]财务取数接口!$C$36=0,"",[1]财务取数接口!$C$36),"")) -> 周转费 | D37: =IF($T$4=0,IF($K37="","",$K37),IFERROR(IF([1]财务取数接口!$D$36=0,"",[1]财务取数接口!$D$36),"")) | E37: =IF($T$4=0,IF($L37="","",$L37),IFERROR(IF([1]财务取数接口!$E$36=0,"",[1]财务取数接口!$E$36),"")) -> 筐 | F37: =IF($T$4=0,IF($M37="","",$M37),IFERROR(IF([1]财务取数接口!$G$36=0,"",[1]财务取数接口!$G$36),"")) | G37: =IF($T$4=0,IF($N37="","",$N37),IFERROR(IF([1]财务取数接口!$H$36=0,"",[1]财务取数接口!$H$36),"")) | H37: =IF($T$4=0,IF($O37="","",$O37),IFERROR(IF([1]财务取数接口!$I$36=0,"",[1]财务取数接口!$I$36),"")) | P37: =IF(AND($C37<>"",$C37<>"项目",OR(N($D37)<>0,N($E37)<>0,N($F37)<>0)),1,0) -> 0 | Q37: =N(Q36)+$P37 -> 3
A38: 37 | B38: =IF($T$4=0,IF($I38="","",$I38),IFERROR(IF([1]财务取数接口!$B$37=0,"",[1]财务取数接口!$B$37),"")) -> 46508 | C38: =IF($T$4=0,IF($J38="","",$J38),IFERROR(IF([1]财务取数接口!$C$37=0,"",[1]财务取数接口!$C$37),"")) -> 周转费 | D38: =IF($T$4=0,IF($K38="","",$K38),IFERROR(IF([1]财务取数接口!$D$37=0,"",[1]财务取数接口!$D$37),"")) | E38: =IF($T$4=0,IF($L38="","",$L38),IFERROR(IF([1]财务取数接口!$E$37=0,"",[1]财务取数接口!$E$37),"")) -> 筐 | F38: =IF($T$4=0,IF($M38="","",$M38),IFERROR(IF([1]财务取数接口!$G$37=0,"",[1]财务取数接口!$G$37),"")) | G38: =IF($T$4=0,IF($N38="","",$N38),IFERROR(IF([1]财务取数接口!$H$37=0,"",[1]财务取数接口!$H$37),"")) | H38: =IF($T$4=0,IF($O38="","",$O38),IFERROR(IF([1]财务取数接口!$I$37=0,"",[1]财务取数接口!$I$37),"")) | P38: =IF(AND($C38<>"",$C38<>"项目",OR(N($D38)<>0,N($E38)<>0,N($F38)<>0)),1,0) -> 0 | Q38: =N(Q37)+$P38 -> 3
A39: 38 | B39: =IF($T$4=0,IF($I39="","",$I39),IFERROR(IF([1]财务取数接口!$B$38=0,"",[1]财务取数接口!$B$38),"")) -> 46539 | C39: =IF($T$4=0,IF($J39="","",$J39),IFERROR(IF([1]财务取数接口!$C$38=0,"",[1]财务取数接口!$C$38),"")) -> 周转费 | D39: =IF($T$4=0,IF($K39="","",$K39),IFERROR(IF([1]财务取数接口!$D$38=0,"",[1]财务取数接口!$D$38),"")) | E39: =IF($T$4=0,IF($L39="","",$L39),IFERROR(IF([1]财务取数接口!$E$38=0,"",[1]财务取数接口!$E$38),"")) -> 筐 | F39: =IF($T$4=0,IF($M39="","",$M39),IFERROR(IF([1]财务取数接口!$G$38=0,"",[1]财务取数接口!$G$38),"")) | G39: =IF($T$4=0,IF($N39="","",$N39),IFERROR(IF([1]财务取数接口!$H$38=0,"",[1]财务取数接口!$H$38),"")) | H39: =IF($T$4=0,IF($O39="","",$O39),IFERROR(IF([1]财务取数接口!$I$38=0,"",[1]财务取数接口!$I$38),"")) | P39: =IF(AND($C39<>"",$C39<>"项目",OR(N($D39)<>0,N($E39)<>0,N($F39)<>0)),1,0) -> 0 | Q39: =N(Q38)+$P39 -> 3
A40: 39 | B40: =IF($T$4=0,IF($I40="","",$I40),IFERROR(IF([1]财务取数接口!$B$39=0,"",[1]财务取数接口!$B$39),"")) -> 46569 | C40: =IF($T$4=0,IF($J40="","",$J40),IFERROR(IF([1]财务取数接口!$C$39=0,"",[1]财务取数接口!$C$39),"")) -> 周转费 | D40: =IF($T$4=0,IF($K40="","",$K40),IFERROR(IF([1]财务取数接口!$D$39=0,"",[1]财务取数接口!$D$39),"")) | E40: =IF($T$4=0,IF($L40="","",$L40),IFERROR(IF([1]财务取数接口!$E$39=0,"",[1]财务取数接口!$E$39),"")) -> 筐 | F40: =IF($T$4=0,IF($M40="","",$M40),IFERROR(IF([1]财务取数接口!$G$39=0,"",[1]财务取数接口!$G$39),"")) | G40: =IF($T$4=0,IF($N40="","",$N40),IFERROR(IF([1]财务取数接口!$H$39=0,"",[1]财务取数接口!$H$39),"")) | H40: =IF($T$4=0,IF($O40="","",$O40),IFERROR(IF([1]财务取数接口!$I$39=0,"",[1]财务取数接口!$I$39),"")) | P40: =IF(AND($C40<>"",$C40<>"项目",OR(N($D40)<>0,N($E40)<>0,N($F40)<>0)),1,0) -> 0 | Q40: =N(Q39)+$P40 -> 3
A41: 40 | B41: =IF($T$4=0,IF($I41="","",$I41),IFERROR(IF([1]财务取数接口!$B$40=0,"",[1]财务取数接口!$B$40),"")) -> 46600 | C41: =IF($T$4=0,IF($J41="","",$J41),IFERROR(IF([1]财务取数接口!$C$40=0,"",[1]财务取数接口!$C$40),"")) -> 周转费 | D41: =IF($T$4=0,IF($K41="","",$K41),IFERROR(IF([1]财务取数接口!$D$40=0,"",[1]财务取数接口!$D$40),"")) | E41: =IF($T$4=0,IF($L41="","",$L41),IFERROR(IF([1]财务取数接口!$E$40=0,"",[1]财务取数接口!$E$40),"")) -> 筐 | F41: =IF($T$4=0,IF($M41="","",$M41),IFERROR(IF([1]财务取数接口!$G$40=0,"",[1]财务取数接口!$G$40),"")) | G41: =IF($T$4=0,IF($N41="","",$N41),IFERROR(IF([1]财务取数接口!$H$40=0,"",[1]财务取数接口!$H$40),"")) | H41: =IF($T$4=0,IF($O41="","",$O41),IFERROR(IF([1]财务取数接口!$I$40=0,"",[1]财务取数接口!$I$40),"")) | P41: =IF(AND($C41<>"",$C41<>"项目",OR(N($D41)<>0,N($E41)<>0,N($F41)<>0)),1,0) -> 0 | Q41: =N(Q40)+$P41 -> 3
A42: 41 | B42: =IF($T$4=0,IF($I42="","",$I42),IFERROR(IF([1]财务取数接口!$B$41=0,"",[1]财务取数接口!$B$41),"")) -> 46631 | C42: =IF($T$4=0,IF($J42="","",$J42),IFERROR(IF([1]财务取数接口!$C$41=0,"",[1]财务取数接口!$C$41),"")) -> 周转费 | D42: =IF($T$4=0,IF($K42="","",$K42),IFERROR(IF([1]财务取数接口!$D$41=0,"",[1]财务取数接口!$D$41),"")) | E42: =IF($T$4=0,IF($L42="","",$L42),IFERROR(IF([1]财务取数接口!$E$41=0,"",[1]财务取数接口!$E$41),"")) -> 筐 | F42: =IF($T$4=0,IF($M42="","",$M42),IFERROR(IF([1]财务取数接口!$G$41=0,"",[1]财务取数接口!$G$41),"")) | G42: =IF($T$4=0,IF($N42="","",$N42),IFERROR(IF([1]财务取数接口!$H$41=0,"",[1]财务取数接口!$H$41),"")) | H42: =IF($T$4=0,IF($O42="","",$O42),IFERROR(IF([1]财务取数接口!$I$41=0,"",[1]财务取数接口!$I$41),"")) | P42: =IF(AND($C42<>"",$C42<>"项目",OR(N($D42)<>0,N($E42)<>0,N($F42)<>0)),1,0) -> 0 | Q42: =N(Q41)+$P42 -> 3
A43: 42 | B43: =IF($T$4=0,IF($I43="","",$I43),IFERROR(IF([1]财务取数接口!$B$42=0,"",[1]财务取数接口!$B$42),"")) -> 46661 | C43: =IF($T$4=0,IF($J43="","",$J43),IFERROR(IF([1]财务取数接口!$C$42=0,"",[1]财务取数接口!$C$42),"")) -> 周转费 | D43: =IF($T$4=0,IF($K43="","",$K43),IFERROR(IF([1]财务取数接口!$D$42=0,"",[1]财务取数接口!$D$42),"")) | E43: =IF($T$4=0,IF($L43="","",$L43),IFERROR(IF([1]财务取数接口!$E$42=0,"",[1]财务取数接口!$E$42),"")) -> 筐 | F43: =IF($T$4=0,IF($M43="","",$M43),IFERROR(IF([1]财务取数接口!$G$42=0,"",[1]财务取数接口!$G$42),"")) | G43: =IF($T$4=0,IF($N43="","",$N43),IFERROR(IF([1]财务取数接口!$H$42=0,"",[1]财务取数接口!$H$42),"")) | H43: =IF($T$4=0,IF($O43="","",$O43),IFERROR(IF([1]财务取数接口!$I$42=0,"",[1]财务取数接口!$I$42),"")) | P43: =IF(AND($C43<>"",$C43<>"项目",OR(N($D43)<>0,N($E43)<>0,N($F43)<>0)),1,0) -> 0 | Q43: =N(Q42)+$P43 -> 3
A44: 43 | B44: =IF($T$4=0,IF($I44="","",$I44),IFERROR(IF([1]财务取数接口!$B$43=0,"",[1]财务取数接口!$B$43),"")) -> 46692 | C44: =IF($T$4=0,IF($J44="","",$J44),IFERROR(IF([1]财务取数接口!$C$43=0,"",[1]财务取数接口!$C$43),"")) -> 周转费 | D44: =IF($T$4=0,IF($K44="","",$K44),IFERROR(IF([1]财务取数接口!$D$43=0,"",[1]财务取数接口!$D$43),"")) | E44: =IF($T$4=0,IF($L44="","",$L44),IFERROR(IF([1]财务取数接口!$E$43=0,"",[1]财务取数接口!$E$43),"")) -> 筐 | F44: =IF($T$4=0,IF($M44="","",$M44),IFERROR(IF([1]财务取数接口!$G$43=0,"",[1]财务取数接口!$G$43),"")) | G44: =IF($T$4=0,IF($N44="","",$N44),IFERROR(IF([1]财务取数接口!$H$43=0,"",[1]财务取数接口!$H$43),"")) | H44: =IF($T$4=0,IF($O44="","",$O44),IFERROR(IF([1]财务取数接口!$I$43=0,"",[1]财务取数接口!$I$43),"")) | P44: =IF(AND($C44<>"",$C44<>"项目",OR(N($D44)<>0,N($E44)<>0,N($F44)<>0)),1,0) -> 0 | Q44: =N(Q43)+$P44 -> 3
A45: 44 | B45: =IF($T$4=0,IF($I45="","",$I45),IFERROR(IF([1]财务取数接口!$B$44=0,"",[1]财务取数接口!$B$44),"")) -> 46722 | C45: =IF($T$4=0,IF($J45="","",$J45),IFERROR(IF([1]财务取数接口!$C$44=0,"",[1]财务取数接口!$C$44),"")) -> 周转费 | D45: =IF($T$4=0,IF($K45="","",$K45),IFERROR(IF([1]财务取数接口!$D$44=0,"",[1]财务取数接口!$D$44),"")) | E45: =IF($T$4=0,IF($L45="","",$L45),IFERROR(IF([1]财务取数接口!$E$44=0,"",[1]财务取数接口!$E$44),"")) -> 筐 | F45: =IF($T$4=0,IF($M45="","",$M45),IFERROR(IF([1]财务取数接口!$G$44=0,"",[1]财务取数接口!$G$44),"")) | G45: =IF($T$4=0,IF($N45="","",$N45),IFERROR(IF([1]财务取数接口!$H$44=0,"",[1]财务取数接口!$H$44),"")) | H45: =IF($T$4=0,IF($O45="","",$O45),IFERROR(IF([1]财务取数接口!$I$44=0,"",[1]财务取数接口!$I$44),"")) | P45: =IF(AND($C45<>"",$C45<>"项目",OR(N($D45)<>0,N($E45)<>0,N($F45)<>0)),1,0) -> 0 | Q45: =N(Q44)+$P45 -> 3
A46: 45 | B46: =IF($T$4=0,IF($I46="","",$I46),IFERROR(IF([1]财务取数接口!$B$45=0,"",[1]财务取数接口!$B$45),"")) -> 46753 | C46: =IF($T$4=0,IF($J46="","",$J46),IFERROR(IF([1]财务取数接口!$C$45=0,"",[1]财务取数接口!$C$45),"")) -> 周转费 | D46: =IF($T$4=0,IF($K46="","",$K46),IFERROR(IF([1]财务取数接口!$D$45=0,"",[1]财务取数接口!$D$45),"")) | E46: =IF($T$4=0,IF($L46="","",$L46),IFERROR(IF([1]财务取数接口!$E$45=0,"",[1]财务取数接口!$E$45),"")) -> 筐 | F46: =IF($T$4=0,IF($M46="","",$M46),IFERROR(IF([1]财务取数接口!$G$45=0,"",[1]财务取数接口!$G$45),"")) | G46: =IF($T$4=0,IF($N46="","",$N46),IFERROR(IF([1]财务取数接口!$H$45=0,"",[1]财务取数接口!$H$45),"")) | H46: =IF($T$4=0,IF($O46="","",$O46),IFERROR(IF([1]财务取数接口!$I$45=0,"",[1]财务取数接口!$I$45),"")) | P46: =IF(AND($C46<>"",$C46<>"项目",OR(N($D46)<>0,N($E46)<>0,N($F46)<>0)),1,0) -> 0 | Q46: =N(Q45)+$P46 -> 3
A47: 46 | B47: =IF($T$4=0,IF($I47="","",$I47),IFERROR(IF([1]财务取数接口!$B$46=0,"",[1]财务取数接口!$B$46),"")) -> 46784 | C47: =IF($T$4=0,IF($J47="","",$J47),IFERROR(IF([1]财务取数接口!$C$46=0,"",[1]财务取数接口!$C$46),"")) -> 周转费 | D47: =IF($T$4=0,IF($K47="","",$K47),IFERROR(IF([1]财务取数接口!$D$46=0,"",[1]财务取数接口!$D$46),"")) | E47: =IF($T$4=0,IF($L47="","",$L47),IFERROR(IF([1]财务取数接口!$E$46=0,"",[1]财务取数接口!$E$46),"")) -> 筐 | F47: =IF($T$4=0,IF($M47="","",$M47),IFERROR(IF([1]财务取数接口!$G$46=0,"",[1]财务取数接口!$G$46),"")) | G47: =IF($T$4=0,IF($N47="","",$N47),IFERROR(IF([1]财务取数接口!$H$46=0,"",[1]财务取数接口!$H$46),"")) | H47: =IF($T$4=0,IF($O47="","",$O47),IFERROR(IF([1]财务取数接口!$I$46=0,"",[1]财务取数接口!$I$46),"")) | P47: =IF(AND($C47<>"",$C47<>"项目",OR(N($D47)<>0,N($E47)<>0,N($F47)<>0)),1,0) -> 0 | Q47: =N(Q46)+$P47 -> 3
A48: 47 | B48: =IF($T$4=0,IF($I48="","",$I48),IFERROR(IF([1]财务取数接口!$B$47=0,"",[1]财务取数接口!$B$47),"")) -> 46813 | C48: =IF($T$4=0,IF($J48="","",$J48),IFERROR(IF([1]财务取数接口!$C$47=0,"",[1]财务取数接口!$C$47),"")) -> 周转费 | D48: =IF($T$4=0,IF($K48="","",$K48),IFERROR(IF([1]财务取数接口!$D$47=0,"",[1]财务取数接口!$D$47),"")) | E48: =IF($T$4=0,IF($L48="","",$L48),IFERROR(IF([1]财务取数接口!$E$47=0,"",[1]财务取数接口!$E$47),"")) -> 筐 | F48: =IF($T$4=0,IF($M48="","",$M48),IFERROR(IF([1]财务取数接口!$G$47=0,"",[1]财务取数接口!$G$47),"")) | G48: =IF($T$4=0,IF($N48="","",$N48),IFERROR(IF([1]财务取数接口!$H$47=0,"",[1]财务取数接口!$H$47),"")) | H48: =IF($T$4=0,IF($O48="","",$O48),IFERROR(IF([1]财务取数接口!$I$47=0,"",[1]财务取数接口!$I$47),"")) | P48: =IF(AND($C48<>"",$C48<>"项目",OR(N($D48)<>0,N($E48)<>0,N($F48)<>0)),1,0) -> 0 | Q48: =N(Q47)+$P48 -> 3
A49: 48 | B49: =IF($T$4=0,IF($I49="","",$I49),IFERROR(IF([1]财务取数接口!$B$48=0,"",[1]财务取数接口!$B$48),"")) -> 46844 | C49: =IF($T$4=0,IF($J49="","",$J49),IFERROR(IF([1]财务取数接口!$C$48=0,"",[1]财务取数接口!$C$48),"")) -> 周转费 | D49: =IF($T$4=0,IF($K49="","",$K49),IFERROR(IF([1]财务取数接口!$D$48=0,"",[1]财务取数接口!$D$48),"")) | E49: =IF($T$4=0,IF($L49="","",$L49),IFERROR(IF([1]财务取数接口!$E$48=0,"",[1]财务取数接口!$E$48),"")) -> 筐 | F49: =IF($T$4=0,IF($M49="","",$M49),IFERROR(IF([1]财务取数接口!$G$48=0,"",[1]财务取数接口!$G$48),"")) | G49: =IF($T$4=0,IF($N49="","",$N49),IFERROR(IF([1]财务取数接口!$H$48=0,"",[1]财务取数接口!$H$48),"")) | H49: =IF($T$4=0,IF($O49="","",$O49),IFERROR(IF([1]财务取数接口!$I$48=0,"",[1]财务取数接口!$I$48),"")) | P49: =IF(AND($C49<>"",$C49<>"项目",OR(N($D49)<>0,N($E49)<>0,N($F49)<>0)),1,0) -> 0 | Q49: =N(Q48)+$P49 -> 3
A50: 49 | B50: =IF($T$4=0,IF($I50="","",$I50),IFERROR(IF([1]财务取数接口!$B$49=0,"",[1]财务取数接口!$B$49),"")) -> 46874 | C50: =IF($T$4=0,IF($J50="","",$J50),IFERROR(IF([1]财务取数接口!$C$49=0,"",[1]财务取数接口!$C$49),"")) -> 周转费 | D50: =IF($T$4=0,IF($K50="","",$K50),IFERROR(IF([1]财务取数接口!$D$49=0,"",[1]财务取数接口!$D$49),"")) | E50: =IF($T$4=0,IF($L50="","",$L50),IFERROR(IF([1]财务取数接口!$E$49=0,"",[1]财务取数接口!$E$49),"")) -> 筐 | F50: =IF($T$4=0,IF($M50="","",$M50),IFERROR(IF([1]财务取数接口!$G$49=0,"",[1]财务取数接口!$G$49),"")) | G50: =IF($T$4=0,IF($N50="","",$N50),IFERROR(IF([1]财务取数接口!$H$49=0,"",[1]财务取数接口!$H$49),"")) | H50: =IF($T$4=0,IF($O50="","",$O50),IFERROR(IF([1]财务取数接口!$I$49=0,"",[1]财务取数接口!$I$49),"")) | P50: =IF(AND($C50<>"",$C50<>"项目",OR(N($D50)<>0,N($E50)<>0,N($F50)<>0)),1,0) -> 0 | Q50: =N(Q49)+$P50 -> 3
A51: 50 | B51: =IF($T$4=0,IF($I51="","",$I51),IFERROR(IF([1]财务取数接口!$B$50=0,"",[1]财务取数接口!$B$50),"")) -> 46905 | C51: =IF($T$4=0,IF($J51="","",$J51),IFERROR(IF([1]财务取数接口!$C$50=0,"",[1]财务取数接口!$C$50),"")) -> 周转费 | D51: =IF($T$4=0,IF($K51="","",$K51),IFERROR(IF([1]财务取数接口!$D$50=0,"",[1]财务取数接口!$D$50),"")) | E51: =IF($T$4=0,IF($L51="","",$L51),IFERROR(IF([1]财务取数接口!$E$50=0,"",[1]财务取数接口!$E$50),"")) -> 筐 | F51: =IF($T$4=0,IF($M51="","",$M51),IFERROR(IF([1]财务取数接口!$G$50=0,"",[1]财务取数接口!$G$50),"")) | G51: =IF($T$4=0,IF($N51="","",$N51),IFERROR(IF([1]财务取数接口!$H$50=0,"",[1]财务取数接口!$H$50),"")) | H51: =IF($T$4=0,IF($O51="","",$O51),IFERROR(IF([1]财务取数接口!$I$50=0,"",[1]财务取数接口!$I$50),"")) | P51: =IF(AND($C51<>"",$C51<>"项目",OR(N($D51)<>0,N($E51)<>0,N($F51)<>0)),1,0) -> 0 | Q51: =N(Q50)+$P51 -> 3
A52: 51 | B52: =IF($T$4=0,IF($I52="","",$I52),IFERROR(IF([1]财务取数接口!$B$51=0,"",[1]财务取数接口!$B$51),"")) -> 46935 | C52: =IF($T$4=0,IF($J52="","",$J52),IFERROR(IF([1]财务取数接口!$C$51=0,"",[1]财务取数接口!$C$51),"")) -> 周转费 | D52: =IF($T$4=0,IF($K52="","",$K52),IFERROR(IF([1]财务取数接口!$D$51=0,"",[1]财务取数接口!$D$51),"")) | E52: =IF($T$4=0,IF($L52="","",$L52),IFERROR(IF([1]财务取数接口!$E$51=0,"",[1]财务取数接口!$E$51),"")) -> 筐 | F52: =IF($T$4=0,IF($M52="","",$M52),IFERROR(IF([1]财务取数接口!$G$51=0,"",[1]财务取数接口!$G$51),"")) | G52: =IF($T$4=0,IF($N52="","",$N52),IFERROR(IF([1]财务取数接口!$H$51=0,"",[1]财务取数接口!$H$51),"")) | H52: =IF($T$4=0,IF($O52="","",$O52),IFERROR(IF([1]财务取数接口!$I$51=0,"",[1]财务取数接口!$I$51),"")) | P52: =IF(AND($C52<>"",$C52<>"项目",OR(N($D52)<>0,N($E52)<>0,N($F52)<>0)),1,0) -> 0 | Q52: =N(Q51)+$P52 -> 3
A53: 52 | B53: =IF($T$4=0,IF($I53="","",$I53),IFERROR(IF([1]财务取数接口!$B$52=0,"",[1]财务取数接口!$B$52),"")) -> 46235 | C53: =IF($T$4=0,IF($J53="","",$J53),IFERROR(IF([1]财务取数接口!$C$52=0,"",[1]财务取数接口!$C$52),"")) -> 装卸费 | D53: =IF($T$4=0,IF($K53="","",$K53),IFERROR(IF([1]财务取数接口!$D$52=0,"",[1]财务取数接口!$D$52),"")) -> 14523 | E53: =IF($T$4=0,IF($L53="","",$L53),IFERROR(IF([1]财务取数接口!$E$52=0,"",[1]财务取数接口!$E$52),"")) -> 筐 | F53: =IF($T$4=0,IF($M53="","",$M53),IFERROR(IF([1]财务取数接口!$G$52=0,"",[1]财务取数接口!$G$52),"")) | G53: =IF($T$4=0,IF($N53="","",$N53),IFERROR(IF([1]财务取数接口!$H$52=0,"",[1]财务取数接口!$H$52),"")) | H53: =IF($T$4=0,IF($O53="","",$O53),IFERROR(IF([1]财务取数接口!$I$52=0,"",[1]财务取数接口!$I$52),"")) | P53: =IF(AND($C53<>"",$C53<>"项目",OR(N($D53)<>0,N($E53)<>0,N($F53)<>0)),1,0) -> 1 | Q53: =N(Q52)+$P53 -> 4
A54: 53 | B54: =IF($T$4=0,IF($I54="","",$I54),IFERROR(IF([1]财务取数接口!$B$53=0,"",[1]财务取数接口!$B$53),"")) -> 46266 | C54: =IF($T$4=0,IF($J54="","",$J54),IFERROR(IF([1]财务取数接口!$C$53=0,"",[1]财务取数接口!$C$53),"")) -> 装卸费 | D54: =IF($T$4=0,IF($K54="","",$K54),IFERROR(IF([1]财务取数接口!$D$53=0,"",[1]财务取数接口!$D$53),"")) -> 31420 | E54: =IF($T$4=0,IF($L54="","",$L54),IFERROR(IF([1]财务取数接口!$E$53=0,"",[1]财务取数接口!$E$53),"")) -> 筐 | F54: =IF($T$4=0,IF($M54="","",$M54),IFERROR(IF([1]财务取数接口!$G$53=0,"",[1]财务取数接口!$G$53),"")) | G54: =IF($T$4=0,IF($N54="","",$N54),IFERROR(IF([1]财务取数接口!$H$53=0,"",[1]财务取数接口!$H$53),"")) | H54: =IF($T$4=0,IF($O54="","",$O54),IFERROR(IF([1]财务取数接口!$I$53=0,"",[1]财务取数接口!$I$53),"")) | P54: =IF(AND($C54<>"",$C54<>"项目",OR(N($D54)<>0,N($E54)<>0,N($F54)<>0)),1,0) -> 1 | Q54: =N(Q53)+$P54 -> 5
A55: 54 | B55: =IF($T$4=0,IF($I55="","",$I55),IFERROR(IF([1]财务取数接口!$B$54=0,"",[1]财务取数接口!$B$54),"")) -> 46296 | C55: =IF($T$4=0,IF($J55="","",$J55),IFERROR(IF([1]财务取数接口!$C$54=0,"",[1]财务取数接口!$C$54),"")) -> 装卸费 | D55: =IF($T$4=0,IF($K55="","",$K55),IFERROR(IF([1]财务取数接口!$D$54=0,"",[1]财务取数接口!$D$54),"")) | E55: =IF($T$4=0,IF($L55="","",$L55),IFERROR(IF([1]财务取数接口!$E$54=0,"",[1]财务取数接口!$E$54),"")) -> 筐 | F55: =IF($T$4=0,IF($M55="","",$M55),IFERROR(IF([1]财务取数接口!$G$54=0,"",[1]财务取数接口!$G$54),"")) | G55: =IF($T$4=0,IF($N55="","",$N55),IFERROR(IF([1]财务取数接口!$H$54=0,"",[1]财务取数接口!$H$54),"")) | H55: =IF($T$4=0,IF($O55="","",$O55),IFERROR(IF([1]财务取数接口!$I$54=0,"",[1]财务取数接口!$I$54),"")) | P55: =IF(AND($C55<>"",$C55<>"项目",OR(N($D55)<>0,N($E55)<>0,N($F55)<>0)),1,0) -> 0 | Q55: =N(Q54)+$P55 -> 5
A56: 55 | B56: =IF($T$4=0,IF($I56="","",$I56),IFERROR(IF([1]财务取数接口!$B$55=0,"",[1]财务取数接口!$B$55),"")) -> 46327 | C56: =IF($T$4=0,IF($J56="","",$J56),IFERROR(IF([1]财务取数接口!$C$55=0,"",[1]财务取数接口!$C$55),"")) -> 装卸费 | D56: =IF($T$4=0,IF($K56="","",$K56),IFERROR(IF([1]财务取数接口!$D$55=0,"",[1]财务取数接口!$D$55),"")) | E56: =IF($T$4=0,IF($L56="","",$L56),IFERROR(IF([1]财务取数接口!$E$55=0,"",[1]财务取数接口!$E$55),"")) -> 筐 | F56: =IF($T$4=0,IF($M56="","",$M56),IFERROR(IF([1]财务取数接口!$G$55=0,"",[1]财务取数接口!$G$55),"")) | G56: =IF($T$4=0,IF($N56="","",$N56),IFERROR(IF([1]财务取数接口!$H$55=0,"",[1]财务取数接口!$H$55),"")) | H56: =IF($T$4=0,IF($O56="","",$O56),IFERROR(IF([1]财务取数接口!$I$55=0,"",[1]财务取数接口!$I$55),"")) | P56: =IF(AND($C56<>"",$C56<>"项目",OR(N($D56)<>0,N($E56)<>0,N($F56)<>0)),1,0) -> 0 | Q56: =N(Q55)+$P56 -> 5
A57: 56 | B57: =IF($T$4=0,IF($I57="","",$I57),IFERROR(IF([1]财务取数接口!$B$56=0,"",[1]财务取数接口!$B$56),"")) -> 46357 | C57: =IF($T$4=0,IF($J57="","",$J57),IFERROR(IF([1]财务取数接口!$C$56=0,"",[1]财务取数接口!$C$56),"")) -> 装卸费 | D57: =IF($T$4=0,IF($K57="","",$K57),IFERROR(IF([1]财务取数接口!$D$56=0,"",[1]财务取数接口!$D$56),"")) | E57: =IF($T$4=0,IF($L57="","",$L57),IFERROR(IF([1]财务取数接口!$E$56=0,"",[1]财务取数接口!$E$56),"")) -> 筐 | F57: =IF($T$4=0,IF($M57="","",$M57),IFERROR(IF([1]财务取数接口!$G$56=0,"",[1]财务取数接口!$G$56),"")) | G57: =IF($T$4=0,IF($N57="","",$N57),IFERROR(IF([1]财务取数接口!$H$56=0,"",[1]财务取数接口!$H$56),"")) | H57: =IF($T$4=0,IF($O57="","",$O57),IFERROR(IF([1]财务取数接口!$I$56=0,"",[1]财务取数接口!$I$56),"")) | P57: =IF(AND($C57<>"",$C57<>"项目",OR(N($D57)<>0,N($E57)<>0,N($F57)<>0)),1,0) -> 0 | Q57: =N(Q56)+$P57 -> 5
A58: 57 | B58: =IF($T$4=0,IF($I58="","",$I58),IFERROR(IF([1]财务取数接口!$B$57=0,"",[1]财务取数接口!$B$57),"")) -> 46388 | C58: =IF($T$4=0,IF($J58="","",$J58),IFERROR(IF([1]财务取数接口!$C$57=0,"",[1]财务取数接口!$C$57),"")) -> 装卸费 | D58: =IF($T$4=0,IF($K58="","",$K58),IFERROR(IF([1]财务取数接口!$D$57=0,"",[1]财务取数接口!$D$57),"")) | E58: =IF($T$4=0,IF($L58="","",$L58),IFERROR(IF([1]财务取数接口!$E$57=0,"",[1]财务取数接口!$E$57),"")) -> 筐 | F58: =IF($T$4=0,IF($M58="","",$M58),IFERROR(IF([1]财务取数接口!$G$57=0,"",[1]财务取数接口!$G$57),"")) | G58: =IF($T$4=0,IF($N58="","",$N58),IFERROR(IF([1]财务取数接口!$H$57=0,"",[1]财务取数接口!$H$57),"")) | H58: =IF($T$4=0,IF($O58="","",$O58),IFERROR(IF([1]财务取数接口!$I$57=0,"",[1]财务取数接口!$I$57),"")) | P58: =IF(AND($C58<>"",$C58<>"项目",OR(N($D58)<>0,N($E58)<>0,N($F58)<>0)),1,0) -> 0 | Q58: =N(Q57)+$P58 -> 5
A59: 58 | B59: =IF($T$4=0,IF($I59="","",$I59),IFERROR(IF([1]财务取数接口!$B$58=0,"",[1]财务取数接口!$B$58),"")) -> 46419 | C59: =IF($T$4=0,IF($J59="","",$J59),IFERROR(IF([1]财务取数接口!$C$58=0,"",[1]财务取数接口!$C$58),"")) -> 装卸费 | D59: =IF($T$4=0,IF($K59="","",$K59),IFERROR(IF([1]财务取数接口!$D$58=0,"",[1]财务取数接口!$D$58),"")) | E59: =IF($T$4=0,IF($L59="","",$L59),IFERROR(IF([1]财务取数接口!$E$58=0,"",[1]财务取数接口!$E$58),"")) -> 筐 | F59: =IF($T$4=0,IF($M59="","",$M59),IFERROR(IF([1]财务取数接口!$G$58=0,"",[1]财务取数接口!$G$58),"")) | G59: =IF($T$4=0,IF($N59="","",$N59),IFERROR(IF([1]财务取数接口!$H$58=0,"",[1]财务取数接口!$H$58),"")) | H59: =IF($T$4=0,IF($O59="","",$O59),IFERROR(IF([1]财务取数接口!$I$58=0,"",[1]财务取数接口!$I$58),"")) | P59: =IF(AND($C59<>"",$C59<>"项目",OR(N($D59)<>0,N($E59)<>0,N($F59)<>0)),1,0) -> 0 | Q59: =N(Q58)+$P59 -> 5
A60: 59 | B60: =IF($T$4=0,IF($I60="","",$I60),IFERROR(IF([1]财务取数接口!$B$59=0,"",[1]财务取数接口!$B$59),"")) -> 46447 | C60: =IF($T$4=0,IF($J60="","",$J60),IFERROR(IF([1]财务取数接口!$C$59=0,"",[1]财务取数接口!$C$59),"")) -> 装卸费 | D60: =IF($T$4=0,IF($K60="","",$K60),IFERROR(IF([1]财务取数接口!$D$59=0,"",[1]财务取数接口!$D$59),"")) | E60: =IF($T$4=0,IF($L60="","",$L60),IFERROR(IF([1]财务取数接口!$E$59=0,"",[1]财务取数接口!$E$59),"")) -> 筐 | F60: =IF($T$4=0,IF($M60="","",$M60),IFERROR(IF([1]财务取数接口!$G$59=0,"",[1]财务取数接口!$G$59),"")) | G60: =IF($T$4=0,IF($N60="","",$N60),IFERROR(IF([1]财务取数接口!$H$59=0,"",[1]财务取数接口!$H$59),"")) | H60: =IF($T$4=0,IF($O60="","",$O60),IFERROR(IF([1]财务取数接口!$I$59=0,"",[1]财务取数接口!$I$59),"")) | P60: =IF(AND($C60<>"",$C60<>"项目",OR(N($D60)<>0,N($E60)<>0,N($F60)<>0)),1,0) -> 0 | Q60: =N(Q59)+$P60 -> 5
A61: 60 | B61: =IF($T$4=0,IF($I61="","",$I61),IFERROR(IF([1]财务取数接口!$B$60=0,"",[1]财务取数接口!$B$60),"")) -> 46478 | C61: =IF($T$4=0,IF($J61="","",$J61),IFERROR(IF([1]财务取数接口!$C$60=0,"",[1]财务取数接口!$C$60),"")) -> 装卸费 | D61: =IF($T$4=0,IF($K61="","",$K61),IFERROR(IF([1]财务取数接口!$D$60=0,"",[1]财务取数接口!$D$60),"")) | E61: =IF($T$4=0,IF($L61="","",$L61),IFERROR(IF([1]财务取数接口!$E$60=0,"",[1]财务取数接口!$E$60),"")) -> 筐 | F61: =IF($T$4=0,IF($M61="","",$M61),IFERROR(IF([1]财务取数接口!$G$60=0,"",[1]财务取数接口!$G$60),"")) | G61: =IF($T$4=0,IF($N61="","",$N61),IFERROR(IF([1]财务取数接口!$H$60=0,"",[1]财务取数接口!$H$60),"")) | H61: =IF($T$4=0,IF($O61="","",$O61),IFERROR(IF([1]财务取数接口!$I$60=0,"",[1]财务取数接口!$I$60),"")) | P61: =IF(AND($C61<>"",$C61<>"项目",OR(N($D61)<>0,N($E61)<>0,N($F61)<>0)),1,0) -> 0 | Q61: =N(Q60)+$P61 -> 5
A62: 61 | B62: =IF($T$4=0,IF($I62="","",$I62),IFERROR(IF([1]财务取数接口!$B$61=0,"",[1]财务取数接口!$B$61),"")) -> 46508 | C62: =IF($T$4=0,IF($J62="","",$J62),IFERROR(IF([1]财务取数接口!$C$61=0,"",[1]财务取数接口!$C$61),"")) -> 装卸费 | D62: =IF($T$4=0,IF($K62="","",$K62),IFERROR(IF([1]财务取数接口!$D$61=0,"",[1]财务取数接口!$D$61),"")) | E62: =IF($T$4=0,IF($L62="","",$L62),IFERROR(IF([1]财务取数接口!$E$61=0,"",[1]财务取数接口!$E$61),"")) -> 筐 | F62: =IF($T$4=0,IF($M62="","",$M62),IFERROR(IF([1]财务取数接口!$G$61=0,"",[1]财务取数接口!$G$61),"")) | G62: =IF($T$4=0,IF($N62="","",$N62),IFERROR(IF([1]财务取数接口!$H$61=0,"",[1]财务取数接口!$H$61),"")) | H62: =IF($T$4=0,IF($O62="","",$O62),IFERROR(IF([1]财务取数接口!$I$61=0,"",[1]财务取数接口!$I$61),"")) | P62: =IF(AND($C62<>"",$C62<>"项目",OR(N($D62)<>0,N($E62)<>0,N($F62)<>0)),1,0) -> 0 | Q62: =N(Q61)+$P62 -> 5
A63: 62 | B63: =IF($T$4=0,IF($I63="","",$I63),IFERROR(IF([1]财务取数接口!$B$62=0,"",[1]财务取数接口!$B$62),"")) -> 46539 | C63: =IF($T$4=0,IF($J63="","",$J63),IFERROR(IF([1]财务取数接口!$C$62=0,"",[1]财务取数接口!$C$62),"")) -> 装卸费 | D63: =IF($T$4=0,IF($K63="","",$K63),IFERROR(IF([1]财务取数接口!$D$62=0,"",[1]财务取数接口!$D$62),"")) | E63: =IF($T$4=0,IF($L63="","",$L63),IFERROR(IF([1]财务取数接口!$E$62=0,"",[1]财务取数接口!$E$62),"")) -> 筐 | F63: =IF($T$4=0,IF($M63="","",$M63),IFERROR(IF([1]财务取数接口!$G$62=0,"",[1]财务取数接口!$G$62),"")) | G63: =IF($T$4=0,IF($N63="","",$N63),IFERROR(IF([1]财务取数接口!$H$62=0,"",[1]财务取数接口!$H$62),"")) | H63: =IF($T$4=0,IF($O63="","",$O63),IFERROR(IF([1]财务取数接口!$I$62=0,"",[1]财务取数接口!$I$62),"")) | P63: =IF(AND($C63<>"",$C63<>"项目",OR(N($D63)<>0,N($E63)<>0,N($F63)<>0)),1,0) -> 0 | Q63: =N(Q62)+$P63 -> 5
A64: 63 | B64: =IF($T$4=0,IF($I64="","",$I64),IFERROR(IF([1]财务取数接口!$B$63=0,"",[1]财务取数接口!$B$63),"")) -> 46569 | C64: =IF($T$4=0,IF($J64="","",$J64),IFERROR(IF([1]财务取数接口!$C$63=0,"",[1]财务取数接口!$C$63),"")) -> 装卸费 | D64: =IF($T$4=0,IF($K64="","",$K64),IFERROR(IF([1]财务取数接口!$D$63=0,"",[1]财务取数接口!$D$63),"")) | E64: =IF($T$4=0,IF($L64="","",$L64),IFERROR(IF([1]财务取数接口!$E$63=0,"",[1]财务取数接口!$E$63),"")) -> 筐 | F64: =IF($T$4=0,IF($M64="","",$M64),IFERROR(IF([1]财务取数接口!$G$63=0,"",[1]财务取数接口!$G$63),"")) | G64: =IF($T$4=0,IF($N64="","",$N64),IFERROR(IF([1]财务取数接口!$H$63=0,"",[1]财务取数接口!$H$63),"")) | H64: =IF($T$4=0,IF($O64="","",$O64),IFERROR(IF([1]财务取数接口!$I$63=0,"",[1]财务取数接口!$I$63),"")) | P64: =IF(AND($C64<>"",$C64<>"项目",OR(N($D64)<>0,N($E64)<>0,N($F64)<>0)),1,0) -> 0 | Q64: =N(Q63)+$P64 -> 5
A65: 64 | B65: =IF($T$4=0,IF($I65="","",$I65),IFERROR(IF([1]财务取数接口!$B$64=0,"",[1]财务取数接口!$B$64),"")) -> 46600 | C65: =IF($T$4=0,IF($J65="","",$J65),IFERROR(IF([1]财务取数接口!$C$64=0,"",[1]财务取数接口!$C$64),"")) -> 装卸费 | D65: =IF($T$4=0,IF($K65="","",$K65),IFERROR(IF([1]财务取数接口!$D$64=0,"",[1]财务取数接口!$D$64),"")) | E65: =IF($T$4=0,IF($L65="","",$L65),IFERROR(IF([1]财务取数接口!$E$64=0,"",[1]财务取数接口!$E$64),"")) -> 筐 | F65: =IF($T$4=0,IF($M65="","",$M65),IFERROR(IF([1]财务取数接口!$G$64=0,"",[1]财务取数接口!$G$64),"")) | G65: =IF($T$4=0,IF($N65="","",$N65),IFERROR(IF([1]财务取数接口!$H$64=0,"",[1]财务取数接口!$H$64),"")) | H65: =IF($T$4=0,IF($O65="","",$O65),IFERROR(IF([1]财务取数接口!$I$64=0,"",[1]财务取数接口!$I$64),"")) | P65: =IF(AND($C65<>"",$C65<>"项目",OR(N($D65)<>0,N($E65)<>0,N($F65)<>0)),1,0) -> 0 | Q65: =N(Q64)+$P65 -> 5
A66: 65 | B66: =IF($T$4=0,IF($I66="","",$I66),IFERROR(IF([1]财务取数接口!$B$65=0,"",[1]财务取数接口!$B$65),"")) -> 46631 | C66: =IF($T$4=0,IF($J66="","",$J66),IFERROR(IF([1]财务取数接口!$C$65=0,"",[1]财务取数接口!$C$65),"")) -> 装卸费 | D66: =IF($T$4=0,IF($K66="","",$K66),IFERROR(IF([1]财务取数接口!$D$65=0,"",[1]财务取数接口!$D$65),"")) | E66: =IF($T$4=0,IF($L66="","",$L66),IFERROR(IF([1]财务取数接口!$E$65=0,"",[1]财务取数接口!$E$65),"")) -> 筐 | F66: =IF($T$4=0,IF($M66="","",$M66),IFERROR(IF([1]财务取数接口!$G$65=0,"",[1]财务取数接口!$G$65),"")) | G66: =IF($T$4=0,IF($N66="","",$N66),IFERROR(IF([1]财务取数接口!$H$65=0,"",[1]财务取数接口!$H$65),"")) | H66: =IF($T$4=0,IF($O66="","",$O66),IFERROR(IF([1]财务取数接口!$I$65=0,"",[1]财务取数接口!$I$65),"")) | P66: =IF(AND($C66<>"",$C66<>"项目",OR(N($D66)<>0,N($E66)<>0,N($F66)<>0)),1,0) -> 0 | Q66: =N(Q65)+$P66 -> 5
A67: 66 | B67: =IF($T$4=0,IF($I67="","",$I67),IFERROR(IF([1]财务取数接口!$B$66=0,"",[1]财务取数接口!$B$66),"")) -> 46661 | C67: =IF($T$4=0,IF($J67="","",$J67),IFERROR(IF([1]财务取数接口!$C$66=0,"",[1]财务取数接口!$C$66),"")) -> 装卸费 | D67: =IF($T$4=0,IF($K67="","",$K67),IFERROR(IF([1]财务取数接口!$D$66=0,"",[1]财务取数接口!$D$66),"")) | E67: =IF($T$4=0,IF($L67="","",$L67),IFERROR(IF([1]财务取数接口!$E$66=0,"",[1]财务取数接口!$E$66),"")) -> 筐 | F67: =IF($T$4=0,IF($M67="","",$M67),IFERROR(IF([1]财务取数接口!$G$66=0,"",[1]财务取数接口!$G$66),"")) | G67: =IF($T$4=0,IF($N67="","",$N67),IFERROR(IF([1]财务取数接口!$H$66=0,"",[1]财务取数接口!$H$66),"")) | H67: =IF($T$4=0,IF($O67="","",$O67),IFERROR(IF([1]财务取数接口!$I$66=0,"",[1]财务取数接口!$I$66),"")) | P67: =IF(AND($C67<>"",$C67<>"项目",OR(N($D67)<>0,N($E67)<>0,N($F67)<>0)),1,0) -> 0 | Q67: =N(Q66)+$P67 -> 5
A68: 67 | B68: =IF($T$4=0,IF($I68="","",$I68),IFERROR(IF([1]财务取数接口!$B$67=0,"",[1]财务取数接口!$B$67),"")) -> 46692 | C68: =IF($T$4=0,IF($J68="","",$J68),IFERROR(IF([1]财务取数接口!$C$67=0,"",[1]财务取数接口!$C$67),"")) -> 装卸费 | D68: =IF($T$4=0,IF($K68="","",$K68),IFERROR(IF([1]财务取数接口!$D$67=0,"",[1]财务取数接口!$D$67),"")) | E68: =IF($T$4=0,IF($L68="","",$L68),IFERROR(IF([1]财务取数接口!$E$67=0,"",[1]财务取数接口!$E$67),"")) -> 筐 | F68: =IF($T$4=0,IF($M68="","",$M68),IFERROR(IF([1]财务取数接口!$G$67=0,"",[1]财务取数接口!$G$67),"")) | G68: =IF($T$4=0,IF($N68="","",$N68),IFERROR(IF([1]财务取数接口!$H$67=0,"",[1]财务取数接口!$H$67),"")) | H68: =IF($T$4=0,IF($O68="","",$O68),IFERROR(IF([1]财务取数接口!$I$67=0,"",[1]财务取数接口!$I$67),"")) | P68: =IF(AND($C68<>"",$C68<>"项目",OR(N($D68)<>0,N($E68)<>0,N($F68)<>0)),1,0) -> 0 | Q68: =N(Q67)+$P68 -> 5
A69: 68 | B69: =IF($T$4=0,IF($I69="","",$I69),IFERROR(IF([1]财务取数接口!$B$68=0,"",[1]财务取数接口!$B$68),"")) -> 46722 | C69: =IF($T$4=0,IF($J69="","",$J69),IFERROR(IF([1]财务取数接口!$C$68=0,"",[1]财务取数接口!$C$68),"")) -> 装卸费 | D69: =IF($T$4=0,IF($K69="","",$K69),IFERROR(IF([1]财务取数接口!$D$68=0,"",[1]财务取数接口!$D$68),"")) | E69: =IF($T$4=0,IF($L69="","",$L69),IFERROR(IF([1]财务取数接口!$E$68=0,"",[1]财务取数接口!$E$68),"")) -> 筐 | F69: =IF($T$4=0,IF($M69="","",$M69),IFERROR(IF([1]财务取数接口!$G$68=0,"",[1]财务取数接口!$G$68),"")) | G69: =IF($T$4=0,IF($N69="","",$N69),IFERROR(IF([1]财务取数接口!$H$68=0,"",[1]财务取数接口!$H$68),"")) | H69: =IF($T$4=0,IF($O69="","",$O69),IFERROR(IF([1]财务取数接口!$I$68=0,"",[1]财务取数接口!$I$68),"")) | P69: =IF(AND($C69<>"",$C69<>"项目",OR(N($D69)<>0,N($E69)<>0,N($F69)<>0)),1,0) -> 0 | Q69: =N(Q68)+$P69 -> 5
A70: 69 | B70: =IF($T$4=0,IF($I70="","",$I70),IFERROR(IF([1]财务取数接口!$B$69=0,"",[1]财务取数接口!$B$69),"")) -> 46753 | C70: =IF($T$4=0,IF($J70="","",$J70),IFERROR(IF([1]财务取数接口!$C$69=0,"",[1]财务取数接口!$C$69),"")) -> 装卸费 | D70: =IF($T$4=0,IF($K70="","",$K70),IFERROR(IF([1]财务取数接口!$D$69=0,"",[1]财务取数接口!$D$69),"")) | E70: =IF($T$4=0,IF($L70="","",$L70),IFERROR(IF([1]财务取数接口!$E$69=0,"",[1]财务取数接口!$E$69),"")) -> 筐 | F70: =IF($T$4=0,IF($M70="","",$M70),IFERROR(IF([1]财务取数接口!$G$69=0,"",[1]财务取数接口!$G$69),"")) | G70: =IF($T$4=0,IF($N70="","",$N70),IFERROR(IF([1]财务取数接口!$H$69=0,"",[1]财务取数接口!$H$69),"")) | H70: =IF($T$4=0,IF($O70="","",$O70),IFERROR(IF([1]财务取数接口!$I$69=0,"",[1]财务取数接口!$I$69),"")) | P70: =IF(AND($C70<>"",$C70<>"项目",OR(N($D70)<>0,N($E70)<>0,N($F70)<>0)),1,0) -> 0 | Q70: =N(Q69)+$P70 -> 5
A71: 70 | B71: =IF($T$4=0,IF($I71="","",$I71),IFERROR(IF([1]财务取数接口!$B$70=0,"",[1]财务取数接口!$B$70),"")) -> 46784 | C71: =IF($T$4=0,IF($J71="","",$J71),IFERROR(IF([1]财务取数接口!$C$70=0,"",[1]财务取数接口!$C$70),"")) -> 装卸费 | D71: =IF($T$4=0,IF($K71="","",$K71),IFERROR(IF([1]财务取数接口!$D$70=0,"",[1]财务取数接口!$D$70),"")) | E71: =IF($T$4=0,IF($L71="","",$L71),IFERROR(IF([1]财务取数接口!$E$70=0,"",[1]财务取数接口!$E$70),"")) -> 筐 | F71: =IF($T$4=0,IF($M71="","",$M71),IFERROR(IF([1]财务取数接口!$G$70=0,"",[1]财务取数接口!$G$70),"")) | G71: =IF($T$4=0,IF($N71="","",$N71),IFERROR(IF([1]财务取数接口!$H$70=0,"",[1]财务取数接口!$H$70),"")) | H71: =IF($T$4=0,IF($O71="","",$O71),IFERROR(IF([1]财务取数接口!$I$70=0,"",[1]财务取数接口!$I$70),"")) | P71: =IF(AND($C71<>"",$C71<>"项目",OR(N($D71)<>0,N($E71)<>0,N($F71)<>0)),1,0) -> 0 | Q71: =N(Q70)+$P71 -> 5
A72: 71 | B72: =IF($T$4=0,IF($I72="","",$I72),IFERROR(IF([1]财务取数接口!$B$71=0,"",[1]财务取数接口!$B$71),"")) -> 46813 | C72: =IF($T$4=0,IF($J72="","",$J72),IFERROR(IF([1]财务取数接口!$C$71=0,"",[1]财务取数接口!$C$71),"")) -> 装卸费 | D72: =IF($T$4=0,IF($K72="","",$K72),IFERROR(IF([1]财务取数接口!$D$71=0,"",[1]财务取数接口!$D$71),"")) | E72: =IF($T$4=0,IF($L72="","",$L72),IFERROR(IF([1]财务取数接口!$E$71=0,"",[1]财务取数接口!$E$71),"")) -> 筐 | F72: =IF($T$4=0,IF($M72="","",$M72),IFERROR(IF([1]财务取数接口!$G$71=0,"",[1]财务取数接口!$G$71),"")) | G72: =IF($T$4=0,IF($N72="","",$N72),IFERROR(IF([1]财务取数接口!$H$71=0,"",[1]财务取数接口!$H$71),"")) | H72: =IF($T$4=0,IF($O72="","",$O72),IFERROR(IF([1]财务取数接口!$I$71=0,"",[1]财务取数接口!$I$71),"")) | P72: =IF(AND($C72<>"",$C72<>"项目",OR(N($D72)<>0,N($E72)<>0,N($F72)<>0)),1,0) -> 0 | Q72: =N(Q71)+$P72 -> 5
A73: 72 | B73: =IF($T$4=0,IF($I73="","",$I73),IFERROR(IF([1]财务取数接口!$B$72=0,"",[1]财务取数接口!$B$72),"")) -> 46844 | C73: =IF($T$4=0,IF($J73="","",$J73),IFERROR(IF([1]财务取数接口!$C$72=0,"",[1]财务取数接口!$C$72),"")) -> 装卸费 | D73: =IF($T$4=0,IF($K73="","",$K73),IFERROR(IF([1]财务取数接口!$D$72=0,"",[1]财务取数接口!$D$72),"")) | E73: =IF($T$4=0,IF($L73="","",$L73),IFERROR(IF([1]财务取数接口!$E$72=0,"",[1]财务取数接口!$E$72),"")) -> 筐 | F73: =IF($T$4=0,IF($M73="","",$M73),IFERROR(IF([1]财务取数接口!$G$72=0,"",[1]财务取数接口!$G$72),"")) | G73: =IF($T$4=0,IF($N73="","",$N73),IFERROR(IF([1]财务取数接口!$H$72=0,"",[1]财务取数接口!$H$72),"")) | H73: =IF($T$4=0,IF($O73="","",$O73),IFERROR(IF([1]财务取数接口!$I$72=0,"",[1]财务取数接口!$I$72),"")) | P73: =IF(AND($C73<>"",$C73<>"项目",OR(N($D73)<>0,N($E73)<>0,N($F73)<>0)),1,0) -> 0 | Q73: =N(Q72)+$P73 -> 5
A74: 73 | B74: =IF($T$4=0,IF($I74="","",$I74),IFERROR(IF([1]财务取数接口!$B$73=0,"",[1]财务取数接口!$B$73),"")) -> 46874 | C74: =IF($T$4=0,IF($J74="","",$J74),IFERROR(IF([1]财务取数接口!$C$73=0,"",[1]财务取数接口!$C$73),"")) -> 装卸费 | D74: =IF($T$4=0,IF($K74="","",$K74),IFERROR(IF([1]财务取数接口!$D$73=0,"",[1]财务取数接口!$D$73),"")) | E74: =IF($T$4=0,IF($L74="","",$L74),IFERROR(IF([1]财务取数接口!$E$73=0,"",[1]财务取数接口!$E$73),"")) -> 筐 | F74: =IF($T$4=0,IF($M74="","",$M74),IFERROR(IF([1]财务取数接口!$G$73=0,"",[1]财务取数接口!$G$73),"")) | G74: =IF($T$4=0,IF($N74="","",$N74),IFERROR(IF([1]财务取数接口!$H$73=0,"",[1]财务取数接口!$H$73),"")) | H74: =IF($T$4=0,IF($O74="","",$O74),IFERROR(IF([1]财务取数接口!$I$73=0,"",[1]财务取数接口!$I$73),"")) | P74: =IF(AND($C74<>"",$C74<>"项目",OR(N($D74)<>0,N($E74)<>0,N($F74)<>0)),1,0) -> 0 | Q74: =N(Q73)+$P74 -> 5
A75: 74 | B75: =IF($T$4=0,IF($I75="","",$I75),IFERROR(IF([1]财务取数接口!$B$74=0,"",[1]财务取数接口!$B$74),"")) -> 46905 | C75: =IF($T$4=0,IF($J75="","",$J75),IFERROR(IF([1]财务取数接口!$C$74=0,"",[1]财务取数接口!$C$74),"")) -> 装卸费 | D75: =IF($T$4=0,IF($K75="","",$K75),IFERROR(IF([1]财务取数接口!$D$74=0,"",[1]财务取数接口!$D$74),"")) | E75: =IF($T$4=0,IF($L75="","",$L75),IFERROR(IF([1]财务取数接口!$E$74=0,"",[1]财务取数接口!$E$74),"")) -> 筐 | F75: =IF($T$4=0,IF($M75="","",$M75),IFERROR(IF([1]财务取数接口!$G$74=0,"",[1]财务取数接口!$G$74),"")) | G75: =IF($T$4=0,IF($N75="","",$N75),IFERROR(IF([1]财务取数接口!$H$74=0,"",[1]财务取数接口!$H$74),"")) | H75: =IF($T$4=0,IF($O75="","",$O75),IFERROR(IF([1]财务取数接口!$I$74=0,"",[1]财务取数接口!$I$74),"")) | P75: =IF(AND($C75<>"",$C75<>"项目",OR(N($D75)<>0,N($E75)<>0,N($F75)<>0)),1,0) -> 0 | Q75: =N(Q74)+$P75 -> 5
A76: 75 | B76: =IF($T$4=0,IF($I76="","",$I76),IFERROR(IF([1]财务取数接口!$B$75=0,"",[1]财务取数接口!$B$75),"")) -> 46935 | C76: =IF($T$4=0,IF($J76="","",$J76),IFERROR(IF([1]财务取数接口!$C$75=0,"",[1]财务取数接口!$C$75),"")) -> 装卸费 | D76: =IF($T$4=0,IF($K76="","",$K76),IFERROR(IF([1]财务取数接口!$D$75=0,"",[1]财务取数接口!$D$75),"")) | E76: =IF($T$4=0,IF($L76="","",$L76),IFERROR(IF([1]财务取数接口!$E$75=0,"",[1]财务取数接口!$E$75),"")) -> 筐 | F76: =IF($T$4=0,IF($M76="","",$M76),IFERROR(IF([1]财务取数接口!$G$75=0,"",[1]财务取数接口!$G$75),"")) | G76: =IF($T$4=0,IF($N76="","",$N76),IFERROR(IF([1]财务取数接口!$H$75=0,"",[1]财务取数接口!$H$75),"")) | H76: =IF($T$4=0,IF($O76="","",$O76),IFERROR(IF([1]财务取数接口!$I$75=0,"",[1]财务取数接口!$I$75),"")) | P76: =IF(AND($C76<>"",$C76<>"项目",OR(N($D76)<>0,N($E76)<>0,N($F76)<>0)),1,0) -> 0 | Q76: =N(Q75)+$P76 -> 5
A77: 76 | B77: =IF($T$4=0,IF($I77="","",$I77),IFERROR(IF([1]财务取数接口!$B$76=0,"",[1]财务取数接口!$B$76),"")) -> 46235 | C77: =IF($T$4=0,IF($J77="","",$J77),IFERROR(IF([1]财务取数接口!$C$76=0,"",[1]财务取数接口!$C$76),"")) -> 水果销售 | D77: =IF($T$4=0,IF($K77="","",$K77),IFERROR(IF([1]财务取数接口!$D$76=0,"",[1]财务取数接口!$D$76),"")) | E77: =IF($T$4=0,IF($L77="","",$L77),IFERROR(IF([1]财务取数接口!$E$76=0,"",[1]财务取数接口!$E$76),"")) -> 箱 | F77: =IF($T$4=0,IF($M77="","",$M77),IFERROR(IF([1]财务取数接口!$G$76=0,"",[1]财务取数接口!$G$76),"")) | G77: =IF($T$4=0,IF($N77="","",$N77),IFERROR(IF([1]财务取数接口!$H$76=0,"",[1]财务取数接口!$H$76),"")) | H77: =IF($T$4=0,IF($O77="","",$O77),IFERROR(IF([1]财务取数接口!$I$76=0,"",[1]财务取数接口!$I$76),"")) | P77: =IF(AND($C77<>"",$C77<>"项目",OR(N($D77)<>0,N($E77)<>0,N($F77)<>0)),1,0) -> 0 | Q77: =N(Q76)+$P77 -> 5
A78: 77 | B78: =IF($T$4=0,IF($I78="","",$I78),IFERROR(IF([1]财务取数接口!$B$77=0,"",[1]财务取数接口!$B$77),"")) -> 46266 | C78: =IF($T$4=0,IF($J78="","",$J78),IFERROR(IF([1]财务取数接口!$C$77=0,"",[1]财务取数接口!$C$77),"")) -> 水果销售 | D78: =IF($T$4=0,IF($K78="","",$K78),IFERROR(IF([1]财务取数接口!$D$77=0,"",[1]财务取数接口!$D$77),"")) -> 1 | E78: =IF($T$4=0,IF($L78="","",$L78),IFERROR(IF([1]财务取数接口!$E$77=0,"",[1]财务取数接口!$E$77),"")) -> 箱 | F78: =IF($T$4=0,IF($M78="","",$M78),IFERROR(IF([1]财务取数接口!$G$77=0,"",[1]财务取数接口!$G$77),"")) -> 40 | G78: =IF($T$4=0,IF($N78="","",$N78),IFERROR(IF([1]财务取数接口!$H$77=0,"",[1]财务取数接口!$H$77),"")) -> 300 | H78: =IF($T$4=0,IF($O78="","",$O78),IFERROR(IF([1]财务取数接口!$I$77=0,"",[1]财务取数接口!$I$77),"")) | P78: =IF(AND($C78<>"",$C78<>"项目",OR(N($D78)<>0,N($E78)<>0,N($F78)<>0)),1,0) -> 1 | Q78: =N(Q77)+$P78 -> 6
A79: 78 | B79: =IF($T$4=0,IF($I79="","",$I79),IFERROR(IF([1]财务取数接口!$B$78=0,"",[1]财务取数接口!$B$78),"")) -> 46296 | C79: =IF($T$4=0,IF($J79="","",$J79),IFERROR(IF([1]财务取数接口!$C$78=0,"",[1]财务取数接口!$C$78),"")) -> 水果销售 | D79: =IF($T$4=0,IF($K79="","",$K79),IFERROR(IF([1]财务取数接口!$D$78=0,"",[1]财务取数接口!$D$78),"")) | E79: =IF($T$4=0,IF($L79="","",$L79),IFERROR(IF([1]财务取数接口!$E$78=0,"",[1]财务取数接口!$E$78),"")) -> 箱 | F79: =IF($T$4=0,IF($M79="","",$M79),IFERROR(IF([1]财务取数接口!$G$78=0,"",[1]财务取数接口!$G$78),"")) | G79: =IF($T$4=0,IF($N79="","",$N79),IFERROR(IF([1]财务取数接口!$H$78=0,"",[1]财务取数接口!$H$78),"")) | H79: =IF($T$4=0,IF($O79="","",$O79),IFERROR(IF([1]财务取数接口!$I$78=0,"",[1]财务取数接口!$I$78),"")) | P79: =IF(AND($C79<>"",$C79<>"项目",OR(N($D79)<>0,N($E79)<>0,N($F79)<>0)),1,0) -> 0 | Q79: =N(Q78)+$P79 -> 6
A80: 79 | B80: =IF($T$4=0,IF($I80="","",$I80),IFERROR(IF([1]财务取数接口!$B$79=0,"",[1]财务取数接口!$B$79),"")) -> 46327 | C80: =IF($T$4=0,IF($J80="","",$J80),IFERROR(IF([1]财务取数接口!$C$79=0,"",[1]财务取数接口!$C$79),"")) -> 水果销售 | D80: =IF($T$4=0,IF($K80="","",$K80),IFERROR(IF([1]财务取数接口!$D$79=0,"",[1]财务取数接口!$D$79),"")) | E80: =IF($T$4=0,IF($L80="","",$L80),IFERROR(IF([1]财务取数接口!$E$79=0,"",[1]财务取数接口!$E$79),"")) -> 箱 | F80: =IF($T$4=0,IF($M80="","",$M80),IFERROR(IF([1]财务取数接口!$G$79=0,"",[1]财务取数接口!$G$79),"")) | G80: =IF($T$4=0,IF($N80="","",$N80),IFERROR(IF([1]财务取数接口!$H$79=0,"",[1]财务取数接口!$H$79),"")) | H80: =IF($T$4=0,IF($O80="","",$O80),IFERROR(IF([1]财务取数接口!$I$79=0,"",[1]财务取数接口!$I$79),"")) | P80: =IF(AND($C80<>"",$C80<>"项目",OR(N($D80)<>0,N($E80)<>0,N($F80)<>0)),1,0) -> 0 | Q80: =N(Q79)+$P80 -> 6
A81: 80 | B81: =IF($T$4=0,IF($I81="","",$I81),IFERROR(IF([1]财务取数接口!$B$80=0,"",[1]财务取数接口!$B$80),"")) -> 46357 | C81: =IF($T$4=0,IF($J81="","",$J81),IFERROR(IF([1]财务取数接口!$C$80=0,"",[1]财务取数接口!$C$80),"")) -> 水果销售 | D81: =IF($T$4=0,IF($K81="","",$K81),IFERROR(IF([1]财务取数接口!$D$80=0,"",[1]财务取数接口!$D$80),"")) | E81: =IF($T$4=0,IF($L81="","",$L81),IFERROR(IF([1]财务取数接口!$E$80=0,"",[1]财务取数接口!$E$80),"")) -> 箱 | F81: =IF($T$4=0,IF($M81="","",$M81),IFERROR(IF([1]财务取数接口!$G$80=0,"",[1]财务取数接口!$G$80),"")) | G81: =IF($T$4=0,IF($N81="","",$N81),IFERROR(IF([1]财务取数接口!$H$80=0,"",[1]财务取数接口!$H$80),"")) | H81: =IF($T$4=0,IF($O81="","",$O81),IFERROR(IF([1]财务取数接口!$I$80=0,"",[1]财务取数接口!$I$80),"")) | P81: =IF(AND($C81<>"",$C81<>"项目",OR(N($D81)<>0,N($E81)<>0,N($F81)<>0)),1,0) -> 0 | Q81: =N(Q80)+$P81 -> 6
A82: 81 | B82: =IF($T$4=0,IF($I82="","",$I82),IFERROR(IF([1]财务取数接口!$B$81=0,"",[1]财务取数接口!$B$81),"")) -> 46388 | C82: =IF($T$4=0,IF($J82="","",$J82),IFERROR(IF([1]财务取数接口!$C$81=0,"",[1]财务取数接口!$C$81),"")) -> 水果销售 | D82: =IF($T$4=0,IF($K82="","",$K82),IFERROR(IF([1]财务取数接口!$D$81=0,"",[1]财务取数接口!$D$81),"")) | E82: =IF($T$4=0,IF($L82="","",$L82),IFERROR(IF([1]财务取数接口!$E$81=0,"",[1]财务取数接口!$E$81),"")) -> 箱 | F82: =IF($T$4=0,IF($M82="","",$M82),IFERROR(IF([1]财务取数接口!$G$81=0,"",[1]财务取数接口!$G$81),"")) | G82: =IF($T$4=0,IF($N82="","",$N82),IFERROR(IF([1]财务取数接口!$H$81=0,"",[1]财务取数接口!$H$81),"")) | H82: =IF($T$4=0,IF($O82="","",$O82),IFERROR(IF([1]财务取数接口!$I$81=0,"",[1]财务取数接口!$I$81),"")) | P82: =IF(AND($C82<>"",$C82<>"项目",OR(N($D82)<>0,N($E82)<>0,N($F82)<>0)),1,0) -> 0 | Q82: =N(Q81)+$P82 -> 6
A83: 82 | B83: =IF($T$4=0,IF($I83="","",$I83),IFERROR(IF([1]财务取数接口!$B$82=0,"",[1]财务取数接口!$B$82),"")) -> 46419 | C83: =IF($T$4=0,IF($J83="","",$J83),IFERROR(IF([1]财务取数接口!$C$82=0,"",[1]财务取数接口!$C$82),"")) -> 水果销售 | D83: =IF($T$4=0,IF($K83="","",$K83),IFERROR(IF([1]财务取数接口!$D$82=0,"",[1]财务取数接口!$D$82),"")) | E83: =IF($T$4=0,IF($L83="","",$L83),IFERROR(IF([1]财务取数接口!$E$82=0,"",[1]财务取数接口!$E$82),"")) -> 箱 | F83: =IF($T$4=0,IF($M83="","",$M83),IFERROR(IF([1]财务取数接口!$G$82=0,"",[1]财务取数接口!$G$82),"")) | G83: =IF($T$4=0,IF($N83="","",$N83),IFERROR(IF([1]财务取数接口!$H$82=0,"",[1]财务取数接口!$H$82),"")) | H83: =IF($T$4=0,IF($O83="","",$O83),IFERROR(IF([1]财务取数接口!$I$82=0,"",[1]财务取数接口!$I$82),"")) | P83: =IF(AND($C83<>"",$C83<>"项目",OR(N($D83)<>0,N($E83)<>0,N($F83)<>0)),1,0) -> 0 | Q83: =N(Q82)+$P83 -> 6
A84: 83 | B84: =IF($T$4=0,IF($I84="","",$I84),IFERROR(IF([1]财务取数接口!$B$83=0,"",[1]财务取数接口!$B$83),"")) -> 46447 | C84: =IF($T$4=0,IF($J84="","",$J84),IFERROR(IF([1]财务取数接口!$C$83=0,"",[1]财务取数接口!$C$83),"")) -> 水果销售 | D84: =IF($T$4=0,IF($K84="","",$K84),IFERROR(IF([1]财务取数接口!$D$83=0,"",[1]财务取数接口!$D$83),"")) | E84: =IF($T$4=0,IF($L84="","",$L84),IFERROR(IF([1]财务取数接口!$E$83=0,"",[1]财务取数接口!$E$83),"")) -> 箱 | F84: =IF($T$4=0,IF($M84="","",$M84),IFERROR(IF([1]财务取数接口!$G$83=0,"",[1]财务取数接口!$G$83),"")) | G84: =IF($T$4=0,IF($N84="","",$N84),IFERROR(IF([1]财务取数接口!$H$83=0,"",[1]财务取数接口!$H$83),"")) | H84: =IF($T$4=0,IF($O84="","",$O84),IFERROR(IF([1]财务取数接口!$I$83=0,"",[1]财务取数接口!$I$83),"")) | P84: =IF(AND($C84<>"",$C84<>"项目",OR(N($D84)<>0,N($E84)<>0,N($F84)<>0)),1,0) -> 0 | Q84: =N(Q83)+$P84 -> 6
A85: 84 | B85: =IF($T$4=0,IF($I85="","",$I85),IFERROR(IF([1]财务取数接口!$B$84=0,"",[1]财务取数接口!$B$84),"")) -> 46478 | C85: =IF($T$4=0,IF($J85="","",$J85),IFERROR(IF([1]财务取数接口!$C$84=0,"",[1]财务取数接口!$C$84),"")) -> 水果销售 | D85: =IF($T$4=0,IF($K85="","",$K85),IFERROR(IF([1]财务取数接口!$D$84=0,"",[1]财务取数接口!$D$84),"")) | E85: =IF($T$4=0,IF($L85="","",$L85),IFERROR(IF([1]财务取数接口!$E$84=0,"",[1]财务取数接口!$E$84),"")) -> 箱 | F85: =IF($T$4=0,IF($M85="","",$M85),IFERROR(IF([1]财务取数接口!$G$84=0,"",[1]财务取数接口!$G$84),"")) | G85: =IF($T$4=0,IF($N85="","",$N85),IFERROR(IF([1]财务取数接口!$H$84=0,"",[1]财务取数接口!$H$84),"")) | H85: =IF($T$4=0,IF($O85="","",$O85),IFERROR(IF([1]财务取数接口!$I$84=0,"",[1]财务取数接口!$I$84),"")) | P85: =IF(AND($C85<>"",$C85<>"项目",OR(N($D85)<>0,N($E85)<>0,N($F85)<>0)),1,0) -> 0 | Q85: =N(Q84)+$P85 -> 6
A86: 85 | B86: =IF($T$4=0,IF($I86="","",$I86),IFERROR(IF([1]财务取数接口!$B$85=0,"",[1]财务取数接口!$B$85),"")) -> 46508 | C86: =IF($T$4=0,IF($J86="","",$J86),IFERROR(IF([1]财务取数接口!$C$85=0,"",[1]财务取数接口!$C$85),"")) -> 水果销售 | D86: =IF($T$4=0,IF($K86="","",$K86),IFERROR(IF([1]财务取数接口!$D$85=0,"",[1]财务取数接口!$D$85),"")) | E86: =IF($T$4=0,IF($L86="","",$L86),IFERROR(IF([1]财务取数接口!$E$85=0,"",[1]财务取数接口!$E$85),"")) -> 箱 | F86: =IF($T$4=0,IF($M86="","",$M86),IFERROR(IF([1]财务取数接口!$G$85=0,"",[1]财务取数接口!$G$85),"")) | G86: =IF($T$4=0,IF($N86="","",$N86),IFERROR(IF([1]财务取数接口!$H$85=0,"",[1]财务取数接口!$H$85),"")) | H86: =IF($T$4=0,IF($O86="","",$O86),IFERROR(IF([1]财务取数接口!$I$85=0,"",[1]财务取数接口!$I$85),"")) | P86: =IF(AND($C86<>"",$C86<>"项目",OR(N($D86)<>0,N($E86)<>0,N($F86)<>0)),1,0) -> 0 | Q86: =N(Q85)+$P86 -> 6
A87: 86 | B87: =IF($T$4=0,IF($I87="","",$I87),IFERROR(IF([1]财务取数接口!$B$86=0,"",[1]财务取数接口!$B$86),"")) -> 46539 | C87: =IF($T$4=0,IF($J87="","",$J87),IFERROR(IF([1]财务取数接口!$C$86=0,"",[1]财务取数接口!$C$86),"")) -> 水果销售 | D87: =IF($T$4=0,IF($K87="","",$K87),IFERROR(IF([1]财务取数接口!$D$86=0,"",[1]财务取数接口!$D$86),"")) | E87: =IF($T$4=0,IF($L87="","",$L87),IFERROR(IF([1]财务取数接口!$E$86=0,"",[1]财务取数接口!$E$86),"")) -> 箱 | F87: =IF($T$4=0,IF($M87="","",$M87),IFERROR(IF([1]财务取数接口!$G$86=0,"",[1]财务取数接口!$G$86),"")) | G87: =IF($T$4=0,IF($N87="","",$N87),IFERROR(IF([1]财务取数接口!$H$86=0,"",[1]财务取数接口!$H$86),"")) | H87: =IF($T$4=0,IF($O87="","",$O87),IFERROR(IF([1]财务取数接口!$I$86=0,"",[1]财务取数接口!$I$86),"")) | P87: =IF(AND($C87<>"",$C87<>"项目",OR(N($D87)<>0,N($E87)<>0,N($F87)<>0)),1,0) -> 0 | Q87: =N(Q86)+$P87 -> 6
A88: 87 | B88: =IF($T$4=0,IF($I88="","",$I88),IFERROR(IF([1]财务取数接口!$B$87=0,"",[1]财务取数接口!$B$87),"")) -> 46569 | C88: =IF($T$4=0,IF($J88="","",$J88),IFERROR(IF([1]财务取数接口!$C$87=0,"",[1]财务取数接口!$C$87),"")) -> 水果销售 | D88: =IF($T$4=0,IF($K88="","",$K88),IFERROR(IF([1]财务取数接口!$D$87=0,"",[1]财务取数接口!$D$87),"")) | E88: =IF($T$4=0,IF($L88="","",$L88),IFERROR(IF([1]财务取数接口!$E$87=0,"",[1]财务取数接口!$E$87),"")) -> 箱 | F88: =IF($T$4=0,IF($M88="","",$M88),IFERROR(IF([1]财务取数接口!$G$87=0,"",[1]财务取数接口!$G$87),"")) | G88: =IF($T$4=0,IF($N88="","",$N88),IFERROR(IF([1]财务取数接口!$H$87=0,"",[1]财务取数接口!$H$87),"")) | H88: =IF($T$4=0,IF($O88="","",$O88),IFERROR(IF([1]财务取数接口!$I$87=0,"",[1]财务取数接口!$I$87),"")) | P88: =IF(AND($C88<>"",$C88<>"项目",OR(N($D88)<>0,N($E88)<>0,N($F88)<>0)),1,0) -> 0 | Q88: =N(Q87)+$P88 -> 6
A89: 88 | B89: =IF($T$4=0,IF($I89="","",$I89),IFERROR(IF([1]财务取数接口!$B$88=0,"",[1]财务取数接口!$B$88),"")) -> 46600 | C89: =IF($T$4=0,IF($J89="","",$J89),IFERROR(IF([1]财务取数接口!$C$88=0,"",[1]财务取数接口!$C$88),"")) -> 水果销售 | D89: =IF($T$4=0,IF($K89="","",$K89),IFERROR(IF([1]财务取数接口!$D$88=0,"",[1]财务取数接口!$D$88),"")) | E89: =IF($T$4=0,IF($L89="","",$L89),IFERROR(IF([1]财务取数接口!$E$88=0,"",[1]财务取数接口!$E$88),"")) -> 箱 | F89: =IF($T$4=0,IF($M89="","",$M89),IFERROR(IF([1]财务取数接口!$G$88=0,"",[1]财务取数接口!$G$88),"")) | G89: =IF($T$4=0,IF($N89="","",$N89),IFERROR(IF([1]财务取数接口!$H$88=0,"",[1]财务取数接口!$H$88),"")) | H89: =IF($T$4=0,IF($O89="","",$O89),IFERROR(IF([1]财务取数接口!$I$88=0,"",[1]财务取数接口!$I$88),"")) | P89: =IF(AND($C89<>"",$C89<>"项目",OR(N($D89)<>0,N($E89)<>0,N($F89)<>0)),1,0) -> 0 | Q89: =N(Q88)+$P89 -> 6
A90: 89 | B90: =IF($T$4=0,IF($I90="","",$I90),IFERROR(IF([1]财务取数接口!$B$89=0,"",[1]财务取数接口!$B$89),"")) -> 46631 | C90: =IF($T$4=0,IF($J90="","",$J90),IFERROR(IF([1]财务取数接口!$C$89=0,"",[1]财务取数接口!$C$89),"")) -> 水果销售 | D90: =IF($T$4=0,IF($K90="","",$K90),IFERROR(IF([1]财务取数接口!$D$89=0,"",[1]财务取数接口!$D$89),"")) | E90: =IF($T$4=0,IF($L90="","",$L90),IFERROR(IF([1]财务取数接口!$E$89=0,"",[1]财务取数接口!$E$89),"")) -> 箱 | F90: =IF($T$4=0,IF($M90="","",$M90),IFERROR(IF([1]财务取数接口!$G$89=0,"",[1]财务取数接口!$G$89),"")) | G90: =IF($T$4=0,IF($N90="","",$N90),IFERROR(IF([1]财务取数接口!$H$89=0,"",[1]财务取数接口!$H$89),"")) | H90: =IF($T$4=0,IF($O90="","",$O90),IFERROR(IF([1]财务取数接口!$I$89=0,"",[1]财务取数接口!$I$89),"")) | P90: =IF(AND($C90<>"",$C90<>"项目",OR(N($D90)<>0,N($E90)<>0,N($F90)<>0)),1,0) -> 0 | Q90: =N(Q89)+$P90 -> 6
A91: 90 | B91: =IF($T$4=0,IF($I91="","",$I91),IFERROR(IF([1]财务取数接口!$B$90=0,"",[1]财务取数接口!$B$90),"")) -> 46661 | C91: =IF($T$4=0,IF($J91="","",$J91),IFERROR(IF([1]财务取数接口!$C$90=0,"",[1]财务取数接口!$C$90),"")) -> 水果销售 | D91: =IF($T$4=0,IF($K91="","",$K91),IFERROR(IF([1]财务取数接口!$D$90=0,"",[1]财务取数接口!$D$90),"")) | E91: =IF($T$4=0,IF($L91="","",$L91),IFERROR(IF([1]财务取数接口!$E$90=0,"",[1]财务取数接口!$E$90),"")) -> 箱 | F91: =IF($T$4=0,IF($M91="","",$M91),IFERROR(IF([1]财务取数接口!$G$90=0,"",[1]财务取数接口!$G$90),"")) | G91: =IF($T$4=0,IF($N91="","",$N91),IFERROR(IF([1]财务取数接口!$H$90=0,"",[1]财务取数接口!$H$90),"")) | H91: =IF($T$4=0,IF($O91="","",$O91),IFERROR(IF([1]财务取数接口!$I$90=0,"",[1]财务取数接口!$I$90),"")) | P91: =IF(AND($C91<>"",$C91<>"项目",OR(N($D91)<>0,N($E91)<>0,N($F91)<>0)),1,0) -> 0 | Q91: =N(Q90)+$P91 -> 6
A92: 91 | B92: =IF($T$4=0,IF($I92="","",$I92),IFERROR(IF([1]财务取数接口!$B$91=0,"",[1]财务取数接口!$B$91),"")) -> 46692 | C92: =IF($T$4=0,IF($J92="","",$J92),IFERROR(IF([1]财务取数接口!$C$91=0,"",[1]财务取数接口!$C$91),"")) -> 水果销售 | D92: =IF($T$4=0,IF($K92="","",$K92),IFERROR(IF([1]财务取数接口!$D$91=0,"",[1]财务取数接口!$D$91),"")) | E92: =IF($T$4=0,IF($L92="","",$L92),IFERROR(IF([1]财务取数接口!$E$91=0,"",[1]财务取数接口!$E$91),"")) -> 箱 | F92: =IF($T$4=0,IF($M92="","",$M92),IFERROR(IF([1]财务取数接口!$G$91=0,"",[1]财务取数接口!$G$91),"")) | G92: =IF($T$4=0,IF($N92="","",$N92),IFERROR(IF([1]财务取数接口!$H$91=0,"",[1]财务取数接口!$H$91),"")) | H92: =IF($T$4=0,IF($O92="","",$O92),IFERROR(IF([1]财务取数接口!$I$91=0,"",[1]财务取数接口!$I$91),"")) | P92: =IF(AND($C92<>"",$C92<>"项目",OR(N($D92)<>0,N($E92)<>0,N($F92)<>0)),1,0) -> 0 | Q92: =N(Q91)+$P92 -> 6
A93: 92 | B93: =IF($T$4=0,IF($I93="","",$I93),IFERROR(IF([1]财务取数接口!$B$92=0,"",[1]财务取数接口!$B$92),"")) -> 46722 | C93: =IF($T$4=0,IF($J93="","",$J93),IFERROR(IF([1]财务取数接口!$C$92=0,"",[1]财务取数接口!$C$92),"")) -> 水果销售 | D93: =IF($T$4=0,IF($K93="","",$K93),IFERROR(IF([1]财务取数接口!$D$92=0,"",[1]财务取数接口!$D$92),"")) | E93: =IF($T$4=0,IF($L93="","",$L93),IFERROR(IF([1]财务取数接口!$E$92=0,"",[1]财务取数接口!$E$92),"")) -> 箱 | F93: =IF($T$4=0,IF($M93="","",$M93),IFERROR(IF([1]财务取数接口!$G$92=0,"",[1]财务取数接口!$G$92),"")) | G93: =IF($T$4=0,IF($N93="","",$N93),IFERROR(IF([1]财务取数接口!$H$92=0,"",[1]财务取数接口!$H$92),"")) | H93: =IF($T$4=0,IF($O93="","",$O93),IFERROR(IF([1]财务取数接口!$I$92=0,"",[1]财务取数接口!$I$92),"")) | P93: =IF(AND($C93<>"",$C93<>"项目",OR(N($D93)<>0,N($E93)<>0,N($F93)<>0)),1,0) -> 0 | Q93: =N(Q92)+$P93 -> 6
A94: 93 | B94: =IF($T$4=0,IF($I94="","",$I94),IFERROR(IF([1]财务取数接口!$B$93=0,"",[1]财务取数接口!$B$93),"")) -> 46753 | C94: =IF($T$4=0,IF($J94="","",$J94),IFERROR(IF([1]财务取数接口!$C$93=0,"",[1]财务取数接口!$C$93),"")) -> 水果销售 | D94: =IF($T$4=0,IF($K94="","",$K94),IFERROR(IF([1]财务取数接口!$D$93=0,"",[1]财务取数接口!$D$93),"")) | E94: =IF($T$4=0,IF($L94="","",$L94),IFERROR(IF([1]财务取数接口!$E$93=0,"",[1]财务取数接口!$E$93),"")) -> 箱 | F94: =IF($T$4=0,IF($M94="","",$M94),IFERROR(IF([1]财务取数接口!$G$93=0,"",[1]财务取数接口!$G$93),"")) | G94: =IF($T$4=0,IF($N94="","",$N94),IFERROR(IF([1]财务取数接口!$H$93=0,"",[1]财务取数接口!$H$93),"")) | H94: =IF($T$4=0,IF($O94="","",$O94),IFERROR(IF([1]财务取数接口!$I$93=0,"",[1]财务取数接口!$I$93),"")) | P94: =IF(AND($C94<>"",$C94<>"项目",OR(N($D94)<>0,N($E94)<>0,N($F94)<>0)),1,0) -> 0 | Q94: =N(Q93)+$P94 -> 6
A95: 94 | B95: =IF($T$4=0,IF($I95="","",$I95),IFERROR(IF([1]财务取数接口!$B$94=0,"",[1]财务取数接口!$B$94),"")) -> 46784 | C95: =IF($T$4=0,IF($J95="","",$J95),IFERROR(IF([1]财务取数接口!$C$94=0,"",[1]财务取数接口!$C$94),"")) -> 水果销售 | D95: =IF($T$4=0,IF($K95="","",$K95),IFERROR(IF([1]财务取数接口!$D$94=0,"",[1]财务取数接口!$D$94),"")) | E95: =IF($T$4=0,IF($L95="","",$L95),IFERROR(IF([1]财务取数接口!$E$94=0,"",[1]财务取数接口!$E$94),"")) -> 箱 | F95: =IF($T$4=0,IF($M95="","",$M95),IFERROR(IF([1]财务取数接口!$G$94=0,"",[1]财务取数接口!$G$94),"")) | G95: =IF($T$4=0,IF($N95="","",$N95),IFERROR(IF([1]财务取数接口!$H$94=0,"",[1]财务取数接口!$H$94),"")) | H95: =IF($T$4=0,IF($O95="","",$O95),IFERROR(IF([1]财务取数接口!$I$94=0,"",[1]财务取数接口!$I$94),"")) | P95: =IF(AND($C95<>"",$C95<>"项目",OR(N($D95)<>0,N($E95)<>0,N($F95)<>0)),1,0) -> 0 | Q95: =N(Q94)+$P95 -> 6
A96: 95 | B96: =IF($T$4=0,IF($I96="","",$I96),IFERROR(IF([1]财务取数接口!$B$95=0,"",[1]财务取数接口!$B$95),"")) -> 46813 | C96: =IF($T$4=0,IF($J96="","",$J96),IFERROR(IF([1]财务取数接口!$C$95=0,"",[1]财务取数接口!$C$95),"")) -> 水果销售 | D96: =IF($T$4=0,IF($K96="","",$K96),IFERROR(IF([1]财务取数接口!$D$95=0,"",[1]财务取数接口!$D$95),"")) | E96: =IF($T$4=0,IF($L96="","",$L96),IFERROR(IF([1]财务取数接口!$E$95=0,"",[1]财务取数接口!$E$95),"")) -> 箱 | F96: =IF($T$4=0,IF($M96="","",$M96),IFERROR(IF([1]财务取数接口!$G$95=0,"",[1]财务取数接口!$G$95),"")) | G96: =IF($T$4=0,IF($N96="","",$N96),IFERROR(IF([1]财务取数接口!$H$95=0,"",[1]财务取数接口!$H$95),"")) | H96: =IF($T$4=0,IF($O96="","",$O96),IFERROR(IF([1]财务取数接口!$I$95=0,"",[1]财务取数接口!$I$95),"")) | P96: =IF(AND($C96<>"",$C96<>"项目",OR(N($D96)<>0,N($E96)<>0,N($F96)<>0)),1,0) -> 0 | Q96: =N(Q95)+$P96 -> 6
A97: 96 | B97: =IF($T$4=0,IF($I97="","",$I97),IFERROR(IF([1]财务取数接口!$B$96=0,"",[1]财务取数接口!$B$96),"")) -> 46844 | C97: =IF($T$4=0,IF($J97="","",$J97),IFERROR(IF([1]财务取数接口!$C$96=0,"",[1]财务取数接口!$C$96),"")) -> 水果销售 | D97: =IF($T$4=0,IF($K97="","",$K97),IFERROR(IF([1]财务取数接口!$D$96=0,"",[1]财务取数接口!$D$96),"")) | E97: =IF($T$4=0,IF($L97="","",$L97),IFERROR(IF([1]财务取数接口!$E$96=0,"",[1]财务取数接口!$E$96),"")) -> 箱 | F97: =IF($T$4=0,IF($M97="","",$M97),IFERROR(IF([1]财务取数接口!$G$96=0,"",[1]财务取数接口!$G$96),"")) | G97: =IF($T$4=0,IF($N97="","",$N97),IFERROR(IF([1]财务取数接口!$H$96=0,"",[1]财务取数接口!$H$96),"")) | H97: =IF($T$4=0,IF($O97="","",$O97),IFERROR(IF([1]财务取数接口!$I$96=0,"",[1]财务取数接口!$I$96),"")) | P97: =IF(AND($C97<>"",$C97<>"项目",OR(N($D97)<>0,N($E97)<>0,N($F97)<>0)),1,0) -> 0 | Q97: =N(Q96)+$P97 -> 6
A98: 97 | B98: =IF($T$4=0,IF($I98="","",$I98),IFERROR(IF([1]财务取数接口!$B$97=0,"",[1]财务取数接口!$B$97),"")) -> 46874 | C98: =IF($T$4=0,IF($J98="","",$J98),IFERROR(IF([1]财务取数接口!$C$97=0,"",[1]财务取数接口!$C$97),"")) -> 水果销售 | D98: =IF($T$4=0,IF($K98="","",$K98),IFERROR(IF([1]财务取数接口!$D$97=0,"",[1]财务取数接口!$D$97),"")) | E98: =IF($T$4=0,IF($L98="","",$L98),IFERROR(IF([1]财务取数接口!$E$97=0,"",[1]财务取数接口!$E$97),"")) -> 箱 | F98: =IF($T$4=0,IF($M98="","",$M98),IFERROR(IF([1]财务取数接口!$G$97=0,"",[1]财务取数接口!$G$97),"")) | G98: =IF($T$4=0,IF($N98="","",$N98),IFERROR(IF([1]财务取数接口!$H$97=0,"",[1]财务取数接口!$H$97),"")) | H98: =IF($T$4=0,IF($O98="","",$O98),IFERROR(IF([1]财务取数接口!$I$97=0,"",[1]财务取数接口!$I$97),"")) | P98: =IF(AND($C98<>"",$C98<>"项目",OR(N($D98)<>0,N($E98)<>0,N($F98)<>0)),1,0) -> 0 | Q98: =N(Q97)+$P98 -> 6
A99: 98 | B99: =IF($T$4=0,IF($I99="","",$I99),IFERROR(IF([1]财务取数接口!$B$98=0,"",[1]财务取数接口!$B$98),"")) -> 46905 | C99: =IF($T$4=0,IF($J99="","",$J99),IFERROR(IF([1]财务取数接口!$C$98=0,"",[1]财务取数接口!$C$98),"")) -> 水果销售 | D99: =IF($T$4=0,IF($K99="","",$K99),IFERROR(IF([1]财务取数接口!$D$98=0,"",[1]财务取数接口!$D$98),"")) | E99: =IF($T$4=0,IF($L99="","",$L99),IFERROR(IF([1]财务取数接口!$E$98=0,"",[1]财务取数接口!$E$98),"")) -> 箱 | F99: =IF($T$4=0,IF($M99="","",$M99),IFERROR(IF([1]财务取数接口!$G$98=0,"",[1]财务取数接口!$G$98),"")) | G99: =IF($T$4=0,IF($N99="","",$N99),IFERROR(IF([1]财务取数接口!$H$98=0,"",[1]财务取数接口!$H$98),"")) | H99: =IF($T$4=0,IF($O99="","",$O99),IFERROR(IF([1]财务取数接口!$I$98=0,"",[1]财务取数接口!$I$98),"")) | P99: =IF(AND($C99<>"",$C99<>"项目",OR(N($D99)<>0,N($E99)<>0,N($F99)<>0)),1,0) -> 0 | Q99: =N(Q98)+$P99 -> 6
A100: 99 | B100: =IF($T$4=0,IF($I100="","",$I100),IFERROR(IF([1]财务取数接口!$B$99=0,"",[1]财务取数接口!$B$99),"")) -> 46935 | C100: =IF($T$4=0,IF($J100="","",$J100),IFERROR(IF([1]财务取数接口!$C$99=0,"",[1]财务取数接口!$C$99),"")) -> 水果销售 | D100: =IF($T$4=0,IF($K100="","",$K100),IFERROR(IF([1]财务取数接口!$D$99=0,"",[1]财务取数接口!$D$99),"")) | E100: =IF($T$4=0,IF($L100="","",$L100),IFERROR(IF([1]财务取数接口!$E$99=0,"",[1]财务取数接口!$E$99),"")) -> 箱 | F100: =IF($T$4=0,IF($M100="","",$M100),IFERROR(IF([1]财务取数接口!$G$99=0,"",[1]财务取数接口!$G$99),"")) | G100: =IF($T$4=0,IF($N100="","",$N100),IFERROR(IF([1]财务取数接口!$H$99=0,"",[1]财务取数接口!$H$99),"")) | H100: =IF($T$4=0,IF($O100="","",$O100),IFERROR(IF([1]财务取数接口!$I$99=0,"",[1]财务取数接口!$I$99),"")) | P100: =IF(AND($C100<>"",$C100<>"项目",OR(N($D100)<>0,N($E100)<>0,N($F100)<>0)),1,0) -> 0 | Q100: =N(Q99)+$P100 -> 6
...

Sheet 对接源_02物料
A1: 对 接 源 · 02 物料与周转物台账（跨文件自动取数 · 断链时自动改用应急备份） | S1: 有效行数 | T1: =MAX($Q$5:$Q$460) -> 5
A2: =IF($T$4=1,"✔ 链接正常，已自动取到 "&$T$1&" 行（只算有金额/数量的行） ｜ 本表 1:1 对应《02 物料与周转物台账》的【财务取数接口】第 4～309 行","★★ 链接没接上！当前取数来源："&$T$5&" → 见 S6 修复说明") -> ✔ 链接正常，已自动取到 5 行（只算有金额/数量的行） ｜ 本表 1:1 对应《02 物料与周转物台账》的【财务取数接口】第 4～309 行 | S2: 链接探针 | T2: =IFERROR(IF([2]财务取数接口!$C$4=0,"未更新",[2]财务取数接口!$C$4),"断开") -> 筐子销售
A3: 一、实 际 使 用 值（链接正常时＝自动取数；链接断了自动切到右边备份） | I3: 二、应 急 备 份 区（手工粘贴数值） | P3: 状态 | S3: 备份行数 | T3: =COUNTIF($J$5:$J$460,"?*")-COUNTIF($J$5:$J$460,"项目") -> 0
A4: 源行 | B4: 年月 / 往来单位 | C4: 项目 | D4: 计费数量 / 应收发生额 | E4: 单位 / 应付发生额 | F4: 价税合计金额 | G4: 已收金额 | H4: 备注 | I4: 备份-年月 | J4: 备份-项目 | K4: 备份-数量 | L4: 备份-单位 | M4: 备份-金额 | N4: 备份-已收 | O4: 备份-备注 | P4: 有效 | Q4: 累计 | S4: 链接可用 | T4: =IF(OR($T$2="断开",$T$2="未更新"),0,1) -> 1
A5: 4 | B5: =IF($T$4=0,IF($I5="","",$I5),IFERROR(IF([2]财务取数接口!$B$4=0,"",[2]财务取数接口!$B$4),"")) | C5: =IF($T$4=0,IF($J5="","",$J5),IFERROR(IF([2]财务取数接口!$C$4=0,"",[2]财务取数接口!$C$4),"")) -> 筐子销售 | D5: =IF($T$4=0,IF($K5="","",$K5),IFERROR(IF([2]财务取数接口!$D$4=0,"",[2]财务取数接口!$D$4),"")) | E5: =IF($T$4=0,IF($L5="","",$L5),IFERROR(IF([2]财务取数接口!$E$4=0,"",[2]财务取数接口!$E$4),"")) -> 个 | F5: =IF($T$4=0,IF($M5="","",$M5),IFERROR(IF([2]财务取数接口!$G$4=0,"",[2]财务取数接口!$G$4),"")) | G5: =IF($T$4=0,IF($N5="","",$N5),IFERROR(IF([2]财务取数接口!$H$4=0,"",[2]财务取数接口!$H$4),"")) | H5: =IF($T$4=0,IF($O5="","",$O5),IFERROR(IF([2]财务取数接口!$I$4=0,"",[2]财务取数接口!$I$4),"")) | P5: =IF(AND($C5<>"",$C5<>"项目",OR(N($D5)<>0,N($E5)<>0,N($F5)<>0)),1,0) -> 0 | Q5: =N(Q4)+$P5 -> 0 | S5: 当前取数来源 | T5: =IF($T$4=1,"自动（跨文件链接）",IF($T$3>0,"应急备份","无数据")) -> 自动（跨文件链接）
A6: 5 | B6: =IF($T$4=0,IF($I6="","",$I6),IFERROR(IF([2]财务取数接口!$B$5=0,"",[2]财务取数接口!$B$5),"")) | C6: =IF($T$4=0,IF($J6="","",$J6),IFERROR(IF([2]财务取数接口!$C$5=0,"",[2]财务取数接口!$C$5),"")) -> 筐子销售 | D6: =IF($T$4=0,IF($K6="","",$K6),IFERROR(IF([2]财务取数接口!$D$5=0,"",[2]财务取数接口!$D$5),"")) | E6: =IF($T$4=0,IF($L6="","",$L6),IFERROR(IF([2]财务取数接口!$E$5=0,"",[2]财务取数接口!$E$5),"")) -> 个 | F6: =IF($T$4=0,IF($M6="","",$M6),IFERROR(IF([2]财务取数接口!$G$5=0,"",[2]财务取数接口!$G$5),"")) | G6: =IF($T$4=0,IF($N6="","",$N6),IFERROR(IF([2]财务取数接口!$H$5=0,"",[2]财务取数接口!$H$5),"")) | H6: =IF($T$4=0,IF($O6="","",$O6),IFERROR(IF([2]财务取数接口!$I$5=0,"",[2]财务取数接口!$I$5),"")) | P6: =IF(AND($C6<>"",$C6<>"项目",OR(N($D6)<>0,N($E6)<>0,N($F6)<>0)),1,0) -> 0 | Q6: =N(Q5)+$P6 -> 0 | S6: =IF($T$2="断开",IF($T$3>0,"✘ 链接已断开，正在用【应急备份区】的 "&$T$3&" 行数据出账（不是实时数）。修复：菜单【数据】→【编辑链接】→【更改源】，重新指向《02_物料与周转物台账模板.xlsx》","✘ 链接已断开，而且应急备份区是空的，本册报表将缺少这本业务册的全部数据。修复：菜单【数据】→【编辑链接】→【更改源】，重新指向《02_物料与周转物台账模板.xlsx》"),IF($T$2="未更新",IF($T$3>0,"★ 链接还没更新，或者那两个文件被改名、挪走了。正在用【应急备份区】的 "&$T$3&" 行数据出账（不是实时数）。修复：菜单【数据】→【编辑链接】→先点【立即更新值】；还是取不到数就点【更改源】重新指向《02_物料与周转物台账模板.xlsx》","★ 链接还没更新，或者那两个文件被改名、挪走了，而且没有应急备份，本册报表会缺少这本业务册的全部数据。修复：菜单【数据】→【编辑链接】→先点【立即更新值】；还是取不到数就点【更改源】重新指向《02_物料与周转物台账模板.xlsx》"),"✔ 链接正常，已自动取到 "&$T$1&" 行。备份区现有 "&$T$3&" 行。建议每月底把 B5:H156 复制→选择性粘贴【数值】到 I5，作为断链时的兜底")) -> ✔ 链接正常，已自动取到 5 行。备份区现有 0 行。建议每月底把 B5:H156 复制→选择性粘贴【数值】到 I5，作为断链时的兜底
A7: 6 | B7: =IF($T$4=0,IF($I7="","",$I7),IFERROR(IF([2]财务取数接口!$B$6=0,"",[2]财务取数接口!$B$6),"")) | C7: =IF($T$4=0,IF($J7="","",$J7),IFERROR(IF([2]财务取数接口!$C$6=0,"",[2]财务取数接口!$C$6),"")) -> 筐子销售 | D7: =IF($T$4=0,IF($K7="","",$K7),IFERROR(IF([2]财务取数接口!$D$6=0,"",[2]财务取数接口!$D$6),"")) | E7: =IF($T$4=0,IF($L7="","",$L7),IFERROR(IF([2]财务取数接口!$E$6=0,"",[2]财务取数接口!$E$6),"")) -> 个 | F7: =IF($T$4=0,IF($M7="","",$M7),IFERROR(IF([2]财务取数接口!$G$6=0,"",[2]财务取数接口!$G$6),"")) | G7: =IF($T$4=0,IF($N7="","",$N7),IFERROR(IF([2]财务取数接口!$H$6=0,"",[2]财务取数接口!$H$6),"")) | H7: =IF($T$4=0,IF($O7="","",$O7),IFERROR(IF([2]财务取数接口!$I$6=0,"",[2]财务取数接口!$I$6),"")) | P7: =IF(AND($C7<>"",$C7<>"项目",OR(N($D7)<>0,N($E7)<>0,N($F7)<>0)),1,0) -> 0 | Q7: =N(Q6)+$P7 -> 0
A8: 7 | B8: =IF($T$4=0,IF($I8="","",$I8),IFERROR(IF([2]财务取数接口!$B$7=0,"",[2]财务取数接口!$B$7),"")) | C8: =IF($T$4=0,IF($J8="","",$J8),IFERROR(IF([2]财务取数接口!$C$7=0,"",[2]财务取数接口!$C$7),"")) -> 筐子销售 | D8: =IF($T$4=0,IF($K8="","",$K8),IFERROR(IF([2]财务取数接口!$D$7=0,"",[2]财务取数接口!$D$7),"")) | E8: =IF($T$4=0,IF($L8="","",$L8),IFERROR(IF([2]财务取数接口!$E$7=0,"",[2]财务取数接口!$E$7),"")) -> 个 | F8: =IF($T$4=0,IF($M8="","",$M8),IFERROR(IF([2]财务取数接口!$G$7=0,"",[2]财务取数接口!$G$7),"")) | G8: =IF($T$4=0,IF($N8="","",$N8),IFERROR(IF([2]财务取数接口!$H$7=0,"",[2]财务取数接口!$H$7),"")) | H8: =IF($T$4=0,IF($O8="","",$O8),IFERROR(IF([2]财务取数接口!$I$7=0,"",[2]财务取数接口!$I$7),"")) | P8: =IF(AND($C8<>"",$C8<>"项目",OR(N($D8)<>0,N($E8)<>0,N($F8)<>0)),1,0) -> 0 | Q8: =N(Q7)+$P8 -> 0
A9: 8 | B9: =IF($T$4=0,IF($I9="","",$I9),IFERROR(IF([2]财务取数接口!$B$8=0,"",[2]财务取数接口!$B$8),"")) | C9: =IF($T$4=0,IF($J9="","",$J9),IFERROR(IF([2]财务取数接口!$C$8=0,"",[2]财务取数接口!$C$8),"")) -> 筐子销售 | D9: =IF($T$4=0,IF($K9="","",$K9),IFERROR(IF([2]财务取数接口!$D$8=0,"",[2]财务取数接口!$D$8),"")) | E9: =IF($T$4=0,IF($L9="","",$L9),IFERROR(IF([2]财务取数接口!$E$8=0,"",[2]财务取数接口!$E$8),"")) -> 个 | F9: =IF($T$4=0,IF($M9="","",$M9),IFERROR(IF([2]财务取数接口!$G$8=0,"",[2]财务取数接口!$G$8),"")) | G9: =IF($T$4=0,IF($N9="","",$N9),IFERROR(IF([2]财务取数接口!$H$8=0,"",[2]财务取数接口!$H$8),"")) | H9: =IF($T$4=0,IF($O9="","",$O9),IFERROR(IF([2]财务取数接口!$I$8=0,"",[2]财务取数接口!$I$8),"")) | P9: =IF(AND($C9<>"",$C9<>"项目",OR(N($D9)<>0,N($E9)<>0,N($F9)<>0)),1,0) -> 0 | Q9: =N(Q8)+$P9 -> 0
A10: 9 | B10: =IF($T$4=0,IF($I10="","",$I10),IFERROR(IF([2]财务取数接口!$B$9=0,"",[2]财务取数接口!$B$9),"")) | C10: =IF($T$4=0,IF($J10="","",$J10),IFERROR(IF([2]财务取数接口!$C$9=0,"",[2]财务取数接口!$C$9),"")) -> 筐子销售 | D10: =IF($T$4=0,IF($K10="","",$K10),IFERROR(IF([2]财务取数接口!$D$9=0,"",[2]财务取数接口!$D$9),"")) | E10: =IF($T$4=0,IF($L10="","",$L10),IFERROR(IF([2]财务取数接口!$E$9=0,"",[2]财务取数接口!$E$9),"")) -> 个 | F10: =IF($T$4=0,IF($M10="","",$M10),IFERROR(IF([2]财务取数接口!$G$9=0,"",[2]财务取数接口!$G$9),"")) | G10: =IF($T$4=0,IF($N10="","",$N10),IFERROR(IF([2]财务取数接口!$H$9=0,"",[2]财务取数接口!$H$9),"")) | H10: =IF($T$4=0,IF($O10="","",$O10),IFERROR(IF([2]财务取数接口!$I$9=0,"",[2]财务取数接口!$I$9),"")) | P10: =IF(AND($C10<>"",$C10<>"项目",OR(N($D10)<>0,N($E10)<>0,N($F10)<>0)),1,0) -> 0 | Q10: =N(Q9)+$P10 -> 0
A11: 10 | B11: =IF($T$4=0,IF($I11="","",$I11),IFERROR(IF([2]财务取数接口!$B$10=0,"",[2]财务取数接口!$B$10),"")) | C11: =IF($T$4=0,IF($J11="","",$J11),IFERROR(IF([2]财务取数接口!$C$10=0,"",[2]财务取数接口!$C$10),"")) -> 筐子销售 | D11: =IF($T$4=0,IF($K11="","",$K11),IFERROR(IF([2]财务取数接口!$D$10=0,"",[2]财务取数接口!$D$10),"")) | E11: =IF($T$4=0,IF($L11="","",$L11),IFERROR(IF([2]财务取数接口!$E$10=0,"",[2]财务取数接口!$E$10),"")) -> 个 | F11: =IF($T$4=0,IF($M11="","",$M11),IFERROR(IF([2]财务取数接口!$G$10=0,"",[2]财务取数接口!$G$10),"")) | G11: =IF($T$4=0,IF($N11="","",$N11),IFERROR(IF([2]财务取数接口!$H$10=0,"",[2]财务取数接口!$H$10),"")) | H11: =IF($T$4=0,IF($O11="","",$O11),IFERROR(IF([2]财务取数接口!$I$10=0,"",[2]财务取数接口!$I$10),"")) | P11: =IF(AND($C11<>"",$C11<>"项目",OR(N($D11)<>0,N($E11)<>0,N($F11)<>0)),1,0) -> 0 | Q11: =N(Q10)+$P11 -> 0
A12: 11 | B12: =IF($T$4=0,IF($I12="","",$I12),IFERROR(IF([2]财务取数接口!$B$11=0,"",[2]财务取数接口!$B$11),"")) | C12: =IF($T$4=0,IF($J12="","",$J12),IFERROR(IF([2]财务取数接口!$C$11=0,"",[2]财务取数接口!$C$11),"")) -> 筐子销售 | D12: =IF($T$4=0,IF($K12="","",$K12),IFERROR(IF([2]财务取数接口!$D$11=0,"",[2]财务取数接口!$D$11),"")) | E12: =IF($T$4=0,IF($L12="","",$L12),IFERROR(IF([2]财务取数接口!$E$11=0,"",[2]财务取数接口!$E$11),"")) -> 个 | F12: =IF($T$4=0,IF($M12="","",$M12),IFERROR(IF([2]财务取数接口!$G$11=0,"",[2]财务取数接口!$G$11),"")) | G12: =IF($T$4=0,IF($N12="","",$N12),IFERROR(IF([2]财务取数接口!$H$11=0,"",[2]财务取数接口!$H$11),"")) | H12: =IF($T$4=0,IF($O12="","",$O12),IFERROR(IF([2]财务取数接口!$I$11=0,"",[2]财务取数接口!$I$11),"")) | P12: =IF(AND($C12<>"",$C12<>"项目",OR(N($D12)<>0,N($E12)<>0,N($F12)<>0)),1,0) -> 0 | Q12: =N(Q11)+$P12 -> 0
A13: 12 | B13: =IF($T$4=0,IF($I13="","",$I13),IFERROR(IF([2]财务取数接口!$B$12=0,"",[2]财务取数接口!$B$12),"")) | C13: =IF($T$4=0,IF($J13="","",$J13),IFERROR(IF([2]财务取数接口!$C$12=0,"",[2]财务取数接口!$C$12),"")) -> 筐子销售 | D13: =IF($T$4=0,IF($K13="","",$K13),IFERROR(IF([2]财务取数接口!$D$12=0,"",[2]财务取数接口!$D$12),"")) | E13: =IF($T$4=0,IF($L13="","",$L13),IFERROR(IF([2]财务取数接口!$E$12=0,"",[2]财务取数接口!$E$12),"")) -> 个 | F13: =IF($T$4=0,IF($M13="","",$M13),IFERROR(IF([2]财务取数接口!$G$12=0,"",[2]财务取数接口!$G$12),"")) | G13: =IF($T$4=0,IF($N13="","",$N13),IFERROR(IF([2]财务取数接口!$H$12=0,"",[2]财务取数接口!$H$12),"")) | H13: =IF($T$4=0,IF($O13="","",$O13),IFERROR(IF([2]财务取数接口!$I$12=0,"",[2]财务取数接口!$I$12),"")) | P13: =IF(AND($C13<>"",$C13<>"项目",OR(N($D13)<>0,N($E13)<>0,N($F13)<>0)),1,0) -> 0 | Q13: =N(Q12)+$P13 -> 0
A14: 13 | B14: =IF($T$4=0,IF($I14="","",$I14),IFERROR(IF([2]财务取数接口!$B$13=0,"",[2]财务取数接口!$B$13),"")) | C14: =IF($T$4=0,IF($J14="","",$J14),IFERROR(IF([2]财务取数接口!$C$13=0,"",[2]财务取数接口!$C$13),"")) -> 筐子销售 | D14: =IF($T$4=0,IF($K14="","",$K14),IFERROR(IF([2]财务取数接口!$D$13=0,"",[2]财务取数接口!$D$13),"")) | E14: =IF($T$4=0,IF($L14="","",$L14),IFERROR(IF([2]财务取数接口!$E$13=0,"",[2]财务取数接口!$E$13),"")) -> 个 | F14: =IF($T$4=0,IF($M14="","",$M14),IFERROR(IF([2]财务取数接口!$G$13=0,"",[2]财务取数接口!$G$13),"")) | G14: =IF($T$4=0,IF($N14="","",$N14),IFERROR(IF([2]财务取数接口!$H$13=0,"",[2]财务取数接口!$H$13),"")) | H14: =IF($T$4=0,IF($O14="","",$O14),IFERROR(IF([2]财务取数接口!$I$13=0,"",[2]财务取数接口!$I$13),"")) | P14: =IF(AND($C14<>"",$C14<>"项目",OR(N($D14)<>0,N($E14)<>0,N($F14)<>0)),1,0) -> 0 | Q14: =N(Q13)+$P14 -> 0
A15: 14 | B15: =IF($T$4=0,IF($I15="","",$I15),IFERROR(IF([2]财务取数接口!$B$14=0,"",[2]财务取数接口!$B$14),"")) | C15: =IF($T$4=0,IF($J15="","",$J15),IFERROR(IF([2]财务取数接口!$C$14=0,"",[2]财务取数接口!$C$14),"")) -> 筐子销售 | D15: =IF($T$4=0,IF($K15="","",$K15),IFERROR(IF([2]财务取数接口!$D$14=0,"",[2]财务取数接口!$D$14),"")) | E15: =IF($T$4=0,IF($L15="","",$L15),IFERROR(IF([2]财务取数接口!$E$14=0,"",[2]财务取数接口!$E$14),"")) -> 个 | F15: =IF($T$4=0,IF($M15="","",$M15),IFERROR(IF([2]财务取数接口!$G$14=0,"",[2]财务取数接口!$G$14),"")) | G15: =IF($T$4=0,IF($N15="","",$N15),IFERROR(IF([2]财务取数接口!$H$14=0,"",[2]财务取数接口!$H$14),"")) | H15: =IF($T$4=0,IF($O15="","",$O15),IFERROR(IF([2]财务取数接口!$I$14=0,"",[2]财务取数接口!$I$14),"")) | P15: =IF(AND($C15<>"",$C15<>"项目",OR(N($D15)<>0,N($E15)<>0,N($F15)<>0)),1,0) -> 0 | Q15: =N(Q14)+$P15 -> 0
A16: 15 | B16: =IF($T$4=0,IF($I16="","",$I16),IFERROR(IF([2]财务取数接口!$B$15=0,"",[2]财务取数接口!$B$15),"")) | C16: =IF($T$4=0,IF($J16="","",$J16),IFERROR(IF([2]财务取数接口!$C$15=0,"",[2]财务取数接口!$C$15),"")) -> 筐子销售 | D16: =IF($T$4=0,IF($K16="","",$K16),IFERROR(IF([2]财务取数接口!$D$15=0,"",[2]财务取数接口!$D$15),"")) | E16: =IF($T$4=0,IF($L16="","",$L16),IFERROR(IF([2]财务取数接口!$E$15=0,"",[2]财务取数接口!$E$15),"")) -> 个 | F16: =IF($T$4=0,IF($M16="","",$M16),IFERROR(IF([2]财务取数接口!$G$15=0,"",[2]财务取数接口!$G$15),"")) | G16: =IF($T$4=0,IF($N16="","",$N16),IFERROR(IF([2]财务取数接口!$H$15=0,"",[2]财务取数接口!$H$15),"")) | H16: =IF($T$4=0,IF($O16="","",$O16),IFERROR(IF([2]财务取数接口!$I$15=0,"",[2]财务取数接口!$I$15),"")) | P16: =IF(AND($C16<>"",$C16<>"项目",OR(N($D16)<>0,N($E16)<>0,N($F16)<>0)),1,0) -> 0 | Q16: =N(Q15)+$P16 -> 0
A17: 16 | B17: =IF($T$4=0,IF($I17="","",$I17),IFERROR(IF([2]财务取数接口!$B$16=0,"",[2]财务取数接口!$B$16),"")) | C17: =IF($T$4=0,IF($J17="","",$J17),IFERROR(IF([2]财务取数接口!$C$16=0,"",[2]财务取数接口!$C$16),"")) -> 筐子销售 | D17: =IF($T$4=0,IF($K17="","",$K17),IFERROR(IF([2]财务取数接口!$D$16=0,"",[2]财务取数接口!$D$16),"")) | E17: =IF($T$4=0,IF($L17="","",$L17),IFERROR(IF([2]财务取数接口!$E$16=0,"",[2]财务取数接口!$E$16),"")) -> 个 | F17: =IF($T$4=0,IF($M17="","",$M17),IFERROR(IF([2]财务取数接口!$G$16=0,"",[2]财务取数接口!$G$16),"")) | G17: =IF($T$4=0,IF($N17="","",$N17),IFERROR(IF([2]财务取数接口!$H$16=0,"",[2]财务取数接口!$H$16),"")) | H17: =IF($T$4=0,IF($O17="","",$O17),IFERROR(IF([2]财务取数接口!$I$16=0,"",[2]财务取数接口!$I$16),"")) | P17: =IF(AND($C17<>"",$C17<>"项目",OR(N($D17)<>0,N($E17)<>0,N($F17)<>0)),1,0) -> 0 | Q17: =N(Q16)+$P17 -> 0
A18: 17 | B18: =IF($T$4=0,IF($I18="","",$I18),IFERROR(IF([2]财务取数接口!$B$17=0,"",[2]财务取数接口!$B$17),"")) | C18: =IF($T$4=0,IF($J18="","",$J18),IFERROR(IF([2]财务取数接口!$C$17=0,"",[2]财务取数接口!$C$17),"")) -> 筐子销售 | D18: =IF($T$4=0,IF($K18="","",$K18),IFERROR(IF([2]财务取数接口!$D$17=0,"",[2]财务取数接口!$D$17),"")) | E18: =IF($T$4=0,IF($L18="","",$L18),IFERROR(IF([2]财务取数接口!$E$17=0,"",[2]财务取数接口!$E$17),"")) -> 个 | F18: =IF($T$4=0,IF($M18="","",$M18),IFERROR(IF([2]财务取数接口!$G$17=0,"",[2]财务取数接口!$G$17),"")) | G18: =IF($T$4=0,IF($N18="","",$N18),IFERROR(IF([2]财务取数接口!$H$17=0,"",[2]财务取数接口!$H$17),"")) | H18: =IF($T$4=0,IF($O18="","",$O18),IFERROR(IF([2]财务取数接口!$I$17=0,"",[2]财务取数接口!$I$17),"")) | P18: =IF(AND($C18<>"",$C18<>"项目",OR(N($D18)<>0,N($E18)<>0,N($F18)<>0)),1,0) -> 0 | Q18: =N(Q17)+$P18 -> 0
A19: 18 | B19: =IF($T$4=0,IF($I19="","",$I19),IFERROR(IF([2]财务取数接口!$B$18=0,"",[2]财务取数接口!$B$18),"")) | C19: =IF($T$4=0,IF($J19="","",$J19),IFERROR(IF([2]财务取数接口!$C$18=0,"",[2]财务取数接口!$C$18),"")) -> 筐子销售 | D19: =IF($T$4=0,IF($K19="","",$K19),IFERROR(IF([2]财务取数接口!$D$18=0,"",[2]财务取数接口!$D$18),"")) | E19: =IF($T$4=0,IF($L19="","",$L19),IFERROR(IF([2]财务取数接口!$E$18=0,"",[2]财务取数接口!$E$18),"")) -> 个 | F19: =IF($T$4=0,IF($M19="","",$M19),IFERROR(IF([2]财务取数接口!$G$18=0,"",[2]财务取数接口!$G$18),"")) | G19: =IF($T$4=0,IF($N19="","",$N19),IFERROR(IF([2]财务取数接口!$H$18=0,"",[2]财务取数接口!$H$18),"")) | H19: =IF($T$4=0,IF($O19="","",$O19),IFERROR(IF([2]财务取数接口!$I$18=0,"",[2]财务取数接口!$I$18),"")) | P19: =IF(AND($C19<>"",$C19<>"项目",OR(N($D19)<>0,N($E19)<>0,N($F19)<>0)),1,0) -> 0 | Q19: =N(Q18)+$P19 -> 0
A20: 19 | B20: =IF($T$4=0,IF($I20="","",$I20),IFERROR(IF([2]财务取数接口!$B$19=0,"",[2]财务取数接口!$B$19),"")) | C20: =IF($T$4=0,IF($J20="","",$J20),IFERROR(IF([2]财务取数接口!$C$19=0,"",[2]财务取数接口!$C$19),"")) -> 筐子销售 | D20: =IF($T$4=0,IF($K20="","",$K20),IFERROR(IF([2]财务取数接口!$D$19=0,"",[2]财务取数接口!$D$19),"")) | E20: =IF($T$4=0,IF($L20="","",$L20),IFERROR(IF([2]财务取数接口!$E$19=0,"",[2]财务取数接口!$E$19),"")) -> 个 | F20: =IF($T$4=0,IF($M20="","",$M20),IFERROR(IF([2]财务取数接口!$G$19=0,"",[2]财务取数接口!$G$19),"")) | G20: =IF($T$4=0,IF($N20="","",$N20),IFERROR(IF([2]财务取数接口!$H$19=0,"",[2]财务取数接口!$H$19),"")) | H20: =IF($T$4=0,IF($O20="","",$O20),IFERROR(IF([2]财务取数接口!$I$19=0,"",[2]财务取数接口!$I$19),"")) | P20: =IF(AND($C20<>"",$C20<>"项目",OR(N($D20)<>0,N($E20)<>0,N($F20)<>0)),1,0) -> 0 | Q20: =N(Q19)+$P20 -> 0
A21: 20 | B21: =IF($T$4=0,IF($I21="","",$I21),IFERROR(IF([2]财务取数接口!$B$20=0,"",[2]财务取数接口!$B$20),"")) | C21: =IF($T$4=0,IF($J21="","",$J21),IFERROR(IF([2]财务取数接口!$C$20=0,"",[2]财务取数接口!$C$20),"")) -> 筐子销售 | D21: =IF($T$4=0,IF($K21="","",$K21),IFERROR(IF([2]财务取数接口!$D$20=0,"",[2]财务取数接口!$D$20),"")) | E21: =IF($T$4=0,IF($L21="","",$L21),IFERROR(IF([2]财务取数接口!$E$20=0,"",[2]财务取数接口!$E$20),"")) -> 个 | F21: =IF($T$4=0,IF($M21="","",$M21),IFERROR(IF([2]财务取数接口!$G$20=0,"",[2]财务取数接口!$G$20),"")) | G21: =IF($T$4=0,IF($N21="","",$N21),IFERROR(IF([2]财务取数接口!$H$20=0,"",[2]财务取数接口!$H$20),"")) | H21: =IF($T$4=0,IF($O21="","",$O21),IFERROR(IF([2]财务取数接口!$I$20=0,"",[2]财务取数接口!$I$20),"")) | P21: =IF(AND($C21<>"",$C21<>"项目",OR(N($D21)<>0,N($E21)<>0,N($F21)<>0)),1,0) -> 0 | Q21: =N(Q20)+$P21 -> 0
A22: 21 | B22: =IF($T$4=0,IF($I22="","",$I22),IFERROR(IF([2]财务取数接口!$B$21=0,"",[2]财务取数接口!$B$21),"")) | C22: =IF($T$4=0,IF($J22="","",$J22),IFERROR(IF([2]财务取数接口!$C$21=0,"",[2]财务取数接口!$C$21),"")) -> 筐子销售 | D22: =IF($T$4=0,IF($K22="","",$K22),IFERROR(IF([2]财务取数接口!$D$21=0,"",[2]财务取数接口!$D$21),"")) | E22: =IF($T$4=0,IF($L22="","",$L22),IFERROR(IF([2]财务取数接口!$E$21=0,"",[2]财务取数接口!$E$21),"")) -> 个 | F22: =IF($T$4=0,IF($M22="","",$M22),IFERROR(IF([2]财务取数接口!$G$21=0,"",[2]财务取数接口!$G$21),"")) | G22: =IF($T$4=0,IF($N22="","",$N22),IFERROR(IF([2]财务取数接口!$H$21=0,"",[2]财务取数接口!$H$21),"")) | H22: =IF($T$4=0,IF($O22="","",$O22),IFERROR(IF([2]财务取数接口!$I$21=0,"",[2]财务取数接口!$I$21),"")) | P22: =IF(AND($C22<>"",$C22<>"项目",OR(N($D22)<>0,N($E22)<>0,N($F22)<>0)),1,0) -> 0 | Q22: =N(Q21)+$P22 -> 0
A23: 22 | B23: =IF($T$4=0,IF($I23="","",$I23),IFERROR(IF([2]财务取数接口!$B$22=0,"",[2]财务取数接口!$B$22),"")) | C23: =IF($T$4=0,IF($J23="","",$J23),IFERROR(IF([2]财务取数接口!$C$22=0,"",[2]财务取数接口!$C$22),"")) -> 筐子销售 | D23: =IF($T$4=0,IF($K23="","",$K23),IFERROR(IF([2]财务取数接口!$D$22=0,"",[2]财务取数接口!$D$22),"")) | E23: =IF($T$4=0,IF($L23="","",$L23),IFERROR(IF([2]财务取数接口!$E$22=0,"",[2]财务取数接口!$E$22),"")) -> 个 | F23: =IF($T$4=0,IF($M23="","",$M23),IFERROR(IF([2]财务取数接口!$G$22=0,"",[2]财务取数接口!$G$22),"")) | G23: =IF($T$4=0,IF($N23="","",$N23),IFERROR(IF([2]财务取数接口!$H$22=0,"",[2]财务取数接口!$H$22),"")) | H23: =IF($T$4=0,IF($O23="","",$O23),IFERROR(IF([2]财务取数接口!$I$22=0,"",[2]财务取数接口!$I$22),"")) | P23: =IF(AND($C23<>"",$C23<>"项目",OR(N($D23)<>0,N($E23)<>0,N($F23)<>0)),1,0) -> 0 | Q23: =N(Q22)+$P23 -> 0
A24: 23 | B24: =IF($T$4=0,IF($I24="","",$I24),IFERROR(IF([2]财务取数接口!$B$23=0,"",[2]财务取数接口!$B$23),"")) | C24: =IF($T$4=0,IF($J24="","",$J24),IFERROR(IF([2]财务取数接口!$C$23=0,"",[2]财务取数接口!$C$23),"")) -> 筐子销售 | D24: =IF($T$4=0,IF($K24="","",$K24),IFERROR(IF([2]财务取数接口!$D$23=0,"",[2]财务取数接口!$D$23),"")) | E24: =IF($T$4=0,IF($L24="","",$L24),IFERROR(IF([2]财务取数接口!$E$23=0,"",[2]财务取数接口!$E$23),"")) -> 个 | F24: =IF($T$4=0,IF($M24="","",$M24),IFERROR(IF([2]财务取数接口!$G$23=0,"",[2]财务取数接口!$G$23),"")) | G24: =IF($T$4=0,IF($N24="","",$N24),IFERROR(IF([2]财务取数接口!$H$23=0,"",[2]财务取数接口!$H$23),"")) | H24: =IF($T$4=0,IF($O24="","",$O24),IFERROR(IF([2]财务取数接口!$I$23=0,"",[2]财务取数接口!$I$23),"")) | P24: =IF(AND($C24<>"",$C24<>"项目",OR(N($D24)<>0,N($E24)<>0,N($F24)<>0)),1,0) -> 0 | Q24: =N(Q23)+$P24 -> 0
A25: 24 | B25: =IF($T$4=0,IF($I25="","",$I25),IFERROR(IF([2]财务取数接口!$B$24=0,"",[2]财务取数接口!$B$24),"")) | C25: =IF($T$4=0,IF($J25="","",$J25),IFERROR(IF([2]财务取数接口!$C$24=0,"",[2]财务取数接口!$C$24),"")) -> 筐子销售 | D25: =IF($T$4=0,IF($K25="","",$K25),IFERROR(IF([2]财务取数接口!$D$24=0,"",[2]财务取数接口!$D$24),"")) | E25: =IF($T$4=0,IF($L25="","",$L25),IFERROR(IF([2]财务取数接口!$E$24=0,"",[2]财务取数接口!$E$24),"")) -> 个 | F25: =IF($T$4=0,IF($M25="","",$M25),IFERROR(IF([2]财务取数接口!$G$24=0,"",[2]财务取数接口!$G$24),"")) | G25: =IF($T$4=0,IF($N25="","",$N25),IFERROR(IF([2]财务取数接口!$H$24=0,"",[2]财务取数接口!$H$24),"")) | H25: =IF($T$4=0,IF($O25="","",$O25),IFERROR(IF([2]财务取数接口!$I$24=0,"",[2]财务取数接口!$I$24),"")) | P25: =IF(AND($C25<>"",$C25<>"项目",OR(N($D25)<>0,N($E25)<>0,N($F25)<>0)),1,0) -> 0 | Q25: =N(Q24)+$P25 -> 0
A26: 25 | B26: =IF($T$4=0,IF($I26="","",$I26),IFERROR(IF([2]财务取数接口!$B$25=0,"",[2]财务取数接口!$B$25),"")) | C26: =IF($T$4=0,IF($J26="","",$J26),IFERROR(IF([2]财务取数接口!$C$25=0,"",[2]财务取数接口!$C$25),"")) -> 筐子销售 | D26: =IF($T$4=0,IF($K26="","",$K26),IFERROR(IF([2]财务取数接口!$D$25=0,"",[2]财务取数接口!$D$25),"")) | E26: =IF($T$4=0,IF($L26="","",$L26),IFERROR(IF([2]财务取数接口!$E$25=0,"",[2]财务取数接口!$E$25),"")) -> 个 | F26: =IF($T$4=0,IF($M26="","",$M26),IFERROR(IF([2]财务取数接口!$G$25=0,"",[2]财务取数接口!$G$25),"")) | G26: =IF($T$4=0,IF($N26="","",$N26),IFERROR(IF([2]财务取数接口!$H$25=0,"",[2]财务取数接口!$H$25),"")) | H26: =IF($T$4=0,IF($O26="","",$O26),IFERROR(IF([2]财务取数接口!$I$25=0,"",[2]财务取数接口!$I$25),"")) | P26: =IF(AND($C26<>"",$C26<>"项目",OR(N($D26)<>0,N($E26)<>0,N($F26)<>0)),1,0) -> 0 | Q26: =N(Q25)+$P26 -> 0
A27: 26 | B27: =IF($T$4=0,IF($I27="","",$I27),IFERROR(IF([2]财务取数接口!$B$26=0,"",[2]财务取数接口!$B$26),"")) | C27: =IF($T$4=0,IF($J27="","",$J27),IFERROR(IF([2]财务取数接口!$C$26=0,"",[2]财务取数接口!$C$26),"")) -> 筐子销售 | D27: =IF($T$4=0,IF($K27="","",$K27),IFERROR(IF([2]财务取数接口!$D$26=0,"",[2]财务取数接口!$D$26),"")) | E27: =IF($T$4=0,IF($L27="","",$L27),IFERROR(IF([2]财务取数接口!$E$26=0,"",[2]财务取数接口!$E$26),"")) -> 个 | F27: =IF($T$4=0,IF($M27="","",$M27),IFERROR(IF([2]财务取数接口!$G$26=0,"",[2]财务取数接口!$G$26),"")) | G27: =IF($T$4=0,IF($N27="","",$N27),IFERROR(IF([2]财务取数接口!$H$26=0,"",[2]财务取数接口!$H$26),"")) | H27: =IF($T$4=0,IF($O27="","",$O27),IFERROR(IF([2]财务取数接口!$I$26=0,"",[2]财务取数接口!$I$26),"")) | P27: =IF(AND($C27<>"",$C27<>"项目",OR(N($D27)<>0,N($E27)<>0,N($F27)<>0)),1,0) -> 0 | Q27: =N(Q26)+$P27 -> 0
A28: 27 | B28: =IF($T$4=0,IF($I28="","",$I28),IFERROR(IF([2]财务取数接口!$B$27=0,"",[2]财务取数接口!$B$27),"")) | C28: =IF($T$4=0,IF($J28="","",$J28),IFERROR(IF([2]财务取数接口!$C$27=0,"",[2]财务取数接口!$C$27),"")) -> 筐子销售 | D28: =IF($T$4=0,IF($K28="","",$K28),IFERROR(IF([2]财务取数接口!$D$27=0,"",[2]财务取数接口!$D$27),"")) | E28: =IF($T$4=0,IF($L28="","",$L28),IFERROR(IF([2]财务取数接口!$E$27=0,"",[2]财务取数接口!$E$27),"")) -> 个 | F28: =IF($T$4=0,IF($M28="","",$M28),IFERROR(IF([2]财务取数接口!$G$27=0,"",[2]财务取数接口!$G$27),"")) | G28: =IF($T$4=0,IF($N28="","",$N28),IFERROR(IF([2]财务取数接口!$H$27=0,"",[2]财务取数接口!$H$27),"")) | H28: =IF($T$4=0,IF($O28="","",$O28),IFERROR(IF([2]财务取数接口!$I$27=0,"",[2]财务取数接口!$I$27),"")) | P28: =IF(AND($C28<>"",$C28<>"项目",OR(N($D28)<>0,N($E28)<>0,N($F28)<>0)),1,0) -> 0 | Q28: =N(Q27)+$P28 -> 0
A29: 28 | B29: =IF($T$4=0,IF($I29="","",$I29),IFERROR(IF([2]财务取数接口!$B$28=0,"",[2]财务取数接口!$B$28),"")) | C29: =IF($T$4=0,IF($J29="","",$J29),IFERROR(IF([2]财务取数接口!$C$28=0,"",[2]财务取数接口!$C$28),"")) -> 物料销售 | D29: =IF($T$4=0,IF($K29="","",$K29),IFERROR(IF([2]财务取数接口!$D$28=0,"",[2]财务取数接口!$D$28),"")) | E29: =IF($T$4=0,IF($L29="","",$L29),IFERROR(IF([2]财务取数接口!$E$28=0,"",[2]财务取数接口!$E$28),"")) -> 包 | F29: =IF($T$4=0,IF($M29="","",$M29),IFERROR(IF([2]财务取数接口!$G$28=0,"",[2]财务取数接口!$G$28),"")) | G29: =IF($T$4=0,IF($N29="","",$N29),IFERROR(IF([2]财务取数接口!$H$28=0,"",[2]财务取数接口!$H$28),"")) | H29: =IF($T$4=0,IF($O29="","",$O29),IFERROR(IF([2]财务取数接口!$I$28=0,"",[2]财务取数接口!$I$28),"")) | P29: =IF(AND($C29<>"",$C29<>"项目",OR(N($D29)<>0,N($E29)<>0,N($F29)<>0)),1,0) -> 0 | Q29: =N(Q28)+$P29 -> 0
A30: 29 | B30: =IF($T$4=0,IF($I30="","",$I30),IFERROR(IF([2]财务取数接口!$B$29=0,"",[2]财务取数接口!$B$29),"")) | C30: =IF($T$4=0,IF($J30="","",$J30),IFERROR(IF([2]财务取数接口!$C$29=0,"",[2]财务取数接口!$C$29),"")) -> 物料销售 | D30: =IF($T$4=0,IF($K30="","",$K30),IFERROR(IF([2]财务取数接口!$D$29=0,"",[2]财务取数接口!$D$29),"")) | E30: =IF($T$4=0,IF($L30="","",$L30),IFERROR(IF([2]财务取数接口!$E$29=0,"",[2]财务取数接口!$E$29),"")) -> 包 | F30: =IF($T$4=0,IF($M30="","",$M30),IFERROR(IF([2]财务取数接口!$G$29=0,"",[2]财务取数接口!$G$29),"")) | G30: =IF($T$4=0,IF($N30="","",$N30),IFERROR(IF([2]财务取数接口!$H$29=0,"",[2]财务取数接口!$H$29),"")) | H30: =IF($T$4=0,IF($O30="","",$O30),IFERROR(IF([2]财务取数接口!$I$29=0,"",[2]财务取数接口!$I$29),"")) | P30: =IF(AND($C30<>"",$C30<>"项目",OR(N($D30)<>0,N($E30)<>0,N($F30)<>0)),1,0) -> 0 | Q30: =N(Q29)+$P30 -> 0
A31: 30 | B31: =IF($T$4=0,IF($I31="","",$I31),IFERROR(IF([2]财务取数接口!$B$30=0,"",[2]财务取数接口!$B$30),"")) | C31: =IF($T$4=0,IF($J31="","",$J31),IFERROR(IF([2]财务取数接口!$C$30=0,"",[2]财务取数接口!$C$30),"")) -> 物料销售 | D31: =IF($T$4=0,IF($K31="","",$K31),IFERROR(IF([2]财务取数接口!$D$30=0,"",[2]财务取数接口!$D$30),"")) | E31: =IF($T$4=0,IF($L31="","",$L31),IFERROR(IF([2]财务取数接口!$E$30=0,"",[2]财务取数接口!$E$30),"")) -> 包 | F31: =IF($T$4=0,IF($M31="","",$M31),IFERROR(IF([2]财务取数接口!$G$30=0,"",[2]财务取数接口!$G$30),"")) | G31: =IF($T$4=0,IF($N31="","",$N31),IFERROR(IF([2]财务取数接口!$H$30=0,"",[2]财务取数接口!$H$30),"")) | H31: =IF($T$4=0,IF($O31="","",$O31),IFERROR(IF([2]财务取数接口!$I$30=0,"",[2]财务取数接口!$I$30),"")) | P31: =IF(AND($C31<>"",$C31<>"项目",OR(N($D31)<>0,N($E31)<>0,N($F31)<>0)),1,0) -> 0 | Q31: =N(Q30)+$P31 -> 0
A32: 31 | B32: =IF($T$4=0,IF($I32="","",$I32),IFERROR(IF([2]财务取数接口!$B$31=0,"",[2]财务取数接口!$B$31),"")) | C32: =IF($T$4=0,IF($J32="","",$J32),IFERROR(IF([2]财务取数接口!$C$31=0,"",[2]财务取数接口!$C$31),"")) -> 物料销售 | D32: =IF($T$4=0,IF($K32="","",$K32),IFERROR(IF([2]财务取数接口!$D$31=0,"",[2]财务取数接口!$D$31),"")) | E32: =IF($T$4=0,IF($L32="","",$L32),IFERROR(IF([2]财务取数接口!$E$31=0,"",[2]财务取数接口!$E$31),"")) -> 包 | F32: =IF($T$4=0,IF($M32="","",$M32),IFERROR(IF([2]财务取数接口!$G$31=0,"",[2]财务取数接口!$G$31),"")) | G32: =IF($T$4=0,IF($N32="","",$N32),IFERROR(IF([2]财务取数接口!$H$31=0,"",[2]财务取数接口!$H$31),"")) | H32: =IF($T$4=0,IF($O32="","",$O32),IFERROR(IF([2]财务取数接口!$I$31=0,"",[2]财务取数接口!$I$31),"")) | P32: =IF(AND($C32<>"",$C32<>"项目",OR(N($D32)<>0,N($E32)<>0,N($F32)<>0)),1,0) -> 0 | Q32: =N(Q31)+$P32 -> 0
A33: 32 | B33: =IF($T$4=0,IF($I33="","",$I33),IFERROR(IF([2]财务取数接口!$B$32=0,"",[2]财务取数接口!$B$32),"")) | C33: =IF($T$4=0,IF($J33="","",$J33),IFERROR(IF([2]财务取数接口!$C$32=0,"",[2]财务取数接口!$C$32),"")) -> 物料销售 | D33: =IF($T$4=0,IF($K33="","",$K33),IFERROR(IF([2]财务取数接口!$D$32=0,"",[2]财务取数接口!$D$32),"")) | E33: =IF($T$4=0,IF($L33="","",$L33),IFERROR(IF([2]财务取数接口!$E$32=0,"",[2]财务取数接口!$E$32),"")) -> 包 | F33: =IF($T$4=0,IF($M33="","",$M33),IFERROR(IF([2]财务取数接口!$G$32=0,"",[2]财务取数接口!$G$32),"")) | G33: =IF($T$4=0,IF($N33="","",$N33),IFERROR(IF([2]财务取数接口!$H$32=0,"",[2]财务取数接口!$H$32),"")) | H33: =IF($T$4=0,IF($O33="","",$O33),IFERROR(IF([2]财务取数接口!$I$32=0,"",[2]财务取数接口!$I$32),"")) | P33: =IF(AND($C33<>"",$C33<>"项目",OR(N($D33)<>0,N($E33)<>0,N($F33)<>0)),1,0) -> 0 | Q33: =N(Q32)+$P33 -> 0
A34: 33 | B34: =IF($T$4=0,IF($I34="","",$I34),IFERROR(IF([2]财务取数接口!$B$33=0,"",[2]财务取数接口!$B$33),"")) | C34: =IF($T$4=0,IF($J34="","",$J34),IFERROR(IF([2]财务取数接口!$C$33=0,"",[2]财务取数接口!$C$33),"")) -> 物料销售 | D34: =IF($T$4=0,IF($K34="","",$K34),IFERROR(IF([2]财务取数接口!$D$33=0,"",[2]财务取数接口!$D$33),"")) | E34: =IF($T$4=0,IF($L34="","",$L34),IFERROR(IF([2]财务取数接口!$E$33=0,"",[2]财务取数接口!$E$33),"")) -> 包 | F34: =IF($T$4=0,IF($M34="","",$M34),IFERROR(IF([2]财务取数接口!$G$33=0,"",[2]财务取数接口!$G$33),"")) | G34: =IF($T$4=0,IF($N34="","",$N34),IFERROR(IF([2]财务取数接口!$H$33=0,"",[2]财务取数接口!$H$33),"")) | H34: =IF($T$4=0,IF($O34="","",$O34),IFERROR(IF([2]财务取数接口!$I$33=0,"",[2]财务取数接口!$I$33),"")) | P34: =IF(AND($C34<>"",$C34<>"项目",OR(N($D34)<>0,N($E34)<>0,N($F34)<>0)),1,0) -> 0 | Q34: =N(Q33)+$P34 -> 0
A35: 34 | B35: =IF($T$4=0,IF($I35="","",$I35),IFERROR(IF([2]财务取数接口!$B$34=0,"",[2]财务取数接口!$B$34),"")) | C35: =IF($T$4=0,IF($J35="","",$J35),IFERROR(IF([2]财务取数接口!$C$34=0,"",[2]财务取数接口!$C$34),"")) -> 物料销售 | D35: =IF($T$4=0,IF($K35="","",$K35),IFERROR(IF([2]财务取数接口!$D$34=0,"",[2]财务取数接口!$D$34),"")) | E35: =IF($T$4=0,IF($L35="","",$L35),IFERROR(IF([2]财务取数接口!$E$34=0,"",[2]财务取数接口!$E$34),"")) -> 包 | F35: =IF($T$4=0,IF($M35="","",$M35),IFERROR(IF([2]财务取数接口!$G$34=0,"",[2]财务取数接口!$G$34),"")) | G35: =IF($T$4=0,IF($N35="","",$N35),IFERROR(IF([2]财务取数接口!$H$34=0,"",[2]财务取数接口!$H$34),"")) | H35: =IF($T$4=0,IF($O35="","",$O35),IFERROR(IF([2]财务取数接口!$I$34=0,"",[2]财务取数接口!$I$34),"")) | P35: =IF(AND($C35<>"",$C35<>"项目",OR(N($D35)<>0,N($E35)<>0,N($F35)<>0)),1,0) -> 0 | Q35: =N(Q34)+$P35 -> 0
A36: 35 | B36: =IF($T$4=0,IF($I36="","",$I36),IFERROR(IF([2]财务取数接口!$B$35=0,"",[2]财务取数接口!$B$35),"")) | C36: =IF($T$4=0,IF($J36="","",$J36),IFERROR(IF([2]财务取数接口!$C$35=0,"",[2]财务取数接口!$C$35),"")) -> 物料销售 | D36: =IF($T$4=0,IF($K36="","",$K36),IFERROR(IF([2]财务取数接口!$D$35=0,"",[2]财务取数接口!$D$35),"")) | E36: =IF($T$4=0,IF($L36="","",$L36),IFERROR(IF([2]财务取数接口!$E$35=0,"",[2]财务取数接口!$E$35),"")) -> 包 | F36: =IF($T$4=0,IF($M36="","",$M36),IFERROR(IF([2]财务取数接口!$G$35=0,"",[2]财务取数接口!$G$35),"")) | G36: =IF($T$4=0,IF($N36="","",$N36),IFERROR(IF([2]财务取数接口!$H$35=0,"",[2]财务取数接口!$H$35),"")) | H36: =IF($T$4=0,IF($O36="","",$O36),IFERROR(IF([2]财务取数接口!$I$35=0,"",[2]财务取数接口!$I$35),"")) | P36: =IF(AND($C36<>"",$C36<>"项目",OR(N($D36)<>0,N($E36)<>0,N($F36)<>0)),1,0) -> 0 | Q36: =N(Q35)+$P36 -> 0
A37: 36 | B37: =IF($T$4=0,IF($I37="","",$I37),IFERROR(IF([2]财务取数接口!$B$36=0,"",[2]财务取数接口!$B$36),"")) | C37: =IF($T$4=0,IF($J37="","",$J37),IFERROR(IF([2]财务取数接口!$C$36=0,"",[2]财务取数接口!$C$36),"")) -> 物料销售 | D37: =IF($T$4=0,IF($K37="","",$K37),IFERROR(IF([2]财务取数接口!$D$36=0,"",[2]财务取数接口!$D$36),"")) | E37: =IF($T$4=0,IF($L37="","",$L37),IFERROR(IF([2]财务取数接口!$E$36=0,"",[2]财务取数接口!$E$36),"")) -> 包 | F37: =IF($T$4=0,IF($M37="","",$M37),IFERROR(IF([2]财务取数接口!$G$36=0,"",[2]财务取数接口!$G$36),"")) | G37: =IF($T$4=0,IF($N37="","",$N37),IFERROR(IF([2]财务取数接口!$H$36=0,"",[2]财务取数接口!$H$36),"")) | H37: =IF($T$4=0,IF($O37="","",$O37),IFERROR(IF([2]财务取数接口!$I$36=0,"",[2]财务取数接口!$I$36),"")) | P37: =IF(AND($C37<>"",$C37<>"项目",OR(N($D37)<>0,N($E37)<>0,N($F37)<>0)),1,0) -> 0 | Q37: =N(Q36)+$P37 -> 0
A38: 37 | B38: =IF($T$4=0,IF($I38="","",$I38),IFERROR(IF([2]财务取数接口!$B$37=0,"",[2]财务取数接口!$B$37),"")) | C38: =IF($T$4=0,IF($J38="","",$J38),IFERROR(IF([2]财务取数接口!$C$37=0,"",[2]财务取数接口!$C$37),"")) -> 物料销售 | D38: =IF($T$4=0,IF($K38="","",$K38),IFERROR(IF([2]财务取数接口!$D$37=0,"",[2]财务取数接口!$D$37),"")) | E38: =IF($T$4=0,IF($L38="","",$L38),IFERROR(IF([2]财务取数接口!$E$37=0,"",[2]财务取数接口!$E$37),"")) -> 包 | F38: =IF($T$4=0,IF($M38="","",$M38),IFERROR(IF([2]财务取数接口!$G$37=0,"",[2]财务取数接口!$G$37),"")) | G38: =IF($T$4=0,IF($N38="","",$N38),IFERROR(IF([2]财务取数接口!$H$37=0,"",[2]财务取数接口!$H$37),"")) | H38: =IF($T$4=0,IF($O38="","",$O38),IFERROR(IF([2]财务取数接口!$I$37=0,"",[2]财务取数接口!$I$37),"")) | P38: =IF(AND($C38<>"",$C38<>"项目",OR(N($D38)<>0,N($E38)<>0,N($F38)<>0)),1,0) -> 0 | Q38: =N(Q37)+$P38 -> 0
A39: 38 | B39: =IF($T$4=0,IF($I39="","",$I39),IFERROR(IF([2]财务取数接口!$B$38=0,"",[2]财务取数接口!$B$38),"")) | C39: =IF($T$4=0,IF($J39="","",$J39),IFERROR(IF([2]财务取数接口!$C$38=0,"",[2]财务取数接口!$C$38),"")) -> 物料销售 | D39: =IF($T$4=0,IF($K39="","",$K39),IFERROR(IF([2]财务取数接口!$D$38=0,"",[2]财务取数接口!$D$38),"")) | E39: =IF($T$4=0,IF($L39="","",$L39),IFERROR(IF([2]财务取数接口!$E$38=0,"",[2]财务取数接口!$E$38),"")) -> 包 | F39: =IF($T$4=0,IF($M39="","",$M39),IFERROR(IF([2]财务取数接口!$G$38=0,"",[2]财务取数接口!$G$38),"")) | G39: =IF($T$4=0,IF($N39="","",$N39),IFERROR(IF([2]财务取数接口!$H$38=0,"",[2]财务取数接口!$H$38),"")) | H39: =IF($T$4=0,IF($O39="","",$O39),IFERROR(IF([2]财务取数接口!$I$38=0,"",[2]财务取数接口!$I$38),"")) | P39: =IF(AND($C39<>"",$C39<>"项目",OR(N($D39)<>0,N($E39)<>0,N($F39)<>0)),1,0) -> 0 | Q39: =N(Q38)+$P39 -> 0
A40: 39 | B40: =IF($T$4=0,IF($I40="","",$I40),IFERROR(IF([2]财务取数接口!$B$39=0,"",[2]财务取数接口!$B$39),"")) | C40: =IF($T$4=0,IF($J40="","",$J40),IFERROR(IF([2]财务取数接口!$C$39=0,"",[2]财务取数接口!$C$39),"")) -> 物料销售 | D40: =IF($T$4=0,IF($K40="","",$K40),IFERROR(IF([2]财务取数接口!$D$39=0,"",[2]财务取数接口!$D$39),"")) | E40: =IF($T$4=0,IF($L40="","",$L40),IFERROR(IF([2]财务取数接口!$E$39=0,"",[2]财务取数接口!$E$39),"")) -> 包 | F40: =IF($T$4=0,IF($M40="","",$M40),IFERROR(IF([2]财务取数接口!$G$39=0,"",[2]财务取数接口!$G$39),"")) | G40: =IF($T$4=0,IF($N40="","",$N40),IFERROR(IF([2]财务取数接口!$H$39=0,"",[2]财务取数接口!$H$39),"")) | H40: =IF($T$4=0,IF($O40="","",$O40),IFERROR(IF([2]财务取数接口!$I$39=0,"",[2]财务取数接口!$I$39),"")) | P40: =IF(AND($C40<>"",$C40<>"项目",OR(N($D40)<>0,N($E40)<>0,N($F40)<>0)),1,0) -> 0 | Q40: =N(Q39)+$P40 -> 0
A41: 40 | B41: =IF($T$4=0,IF($I41="","",$I41),IFERROR(IF([2]财务取数接口!$B$40=0,"",[2]财务取数接口!$B$40),"")) | C41: =IF($T$4=0,IF($J41="","",$J41),IFERROR(IF([2]财务取数接口!$C$40=0,"",[2]财务取数接口!$C$40),"")) -> 物料销售 | D41: =IF($T$4=0,IF($K41="","",$K41),IFERROR(IF([2]财务取数接口!$D$40=0,"",[2]财务取数接口!$D$40),"")) | E41: =IF($T$4=0,IF($L41="","",$L41),IFERROR(IF([2]财务取数接口!$E$40=0,"",[2]财务取数接口!$E$40),"")) -> 包 | F41: =IF($T$4=0,IF($M41="","",$M41),IFERROR(IF([2]财务取数接口!$G$40=0,"",[2]财务取数接口!$G$40),"")) | G41: =IF($T$4=0,IF($N41="","",$N41),IFERROR(IF([2]财务取数接口!$H$40=0,"",[2]财务取数接口!$H$40),"")) | H41: =IF($T$4=0,IF($O41="","",$O41),IFERROR(IF([2]财务取数接口!$I$40=0,"",[2]财务取数接口!$I$40),"")) | P41: =IF(AND($C41<>"",$C41<>"项目",OR(N($D41)<>0,N($E41)<>0,N($F41)<>0)),1,0) -> 0 | Q41: =N(Q40)+$P41 -> 0
A42: 41 | B42: =IF($T$4=0,IF($I42="","",$I42),IFERROR(IF([2]财务取数接口!$B$41=0,"",[2]财务取数接口!$B$41),"")) | C42: =IF($T$4=0,IF($J42="","",$J42),IFERROR(IF([2]财务取数接口!$C$41=0,"",[2]财务取数接口!$C$41),"")) -> 物料销售 | D42: =IF($T$4=0,IF($K42="","",$K42),IFERROR(IF([2]财务取数接口!$D$41=0,"",[2]财务取数接口!$D$41),"")) | E42: =IF($T$4=0,IF($L42="","",$L42),IFERROR(IF([2]财务取数接口!$E$41=0,"",[2]财务取数接口!$E$41),"")) -> 包 | F42: =IF($T$4=0,IF($M42="","",$M42),IFERROR(IF([2]财务取数接口!$G$41=0,"",[2]财务取数接口!$G$41),"")) | G42: =IF($T$4=0,IF($N42="","",$N42),IFERROR(IF([2]财务取数接口!$H$41=0,"",[2]财务取数接口!$H$41),"")) | H42: =IF($T$4=0,IF($O42="","",$O42),IFERROR(IF([2]财务取数接口!$I$41=0,"",[2]财务取数接口!$I$41),"")) | P42: =IF(AND($C42<>"",$C42<>"项目",OR(N($D42)<>0,N($E42)<>0,N($F42)<>0)),1,0) -> 0 | Q42: =N(Q41)+$P42 -> 0
A43: 42 | B43: =IF($T$4=0,IF($I43="","",$I43),IFERROR(IF([2]财务取数接口!$B$42=0,"",[2]财务取数接口!$B$42),"")) | C43: =IF($T$4=0,IF($J43="","",$J43),IFERROR(IF([2]财务取数接口!$C$42=0,"",[2]财务取数接口!$C$42),"")) -> 物料销售 | D43: =IF($T$4=0,IF($K43="","",$K43),IFERROR(IF([2]财务取数接口!$D$42=0,"",[2]财务取数接口!$D$42),"")) | E43: =IF($T$4=0,IF($L43="","",$L43),IFERROR(IF([2]财务取数接口!$E$42=0,"",[2]财务取数接口!$E$42),"")) -> 包 | F43: =IF($T$4=0,IF($M43="","",$M43),IFERROR(IF([2]财务取数接口!$G$42=0,"",[2]财务取数接口!$G$42),"")) | G43: =IF($T$4=0,IF($N43="","",$N43),IFERROR(IF([2]财务取数接口!$H$42=0,"",[2]财务取数接口!$H$42),"")) | H43: =IF($T$4=0,IF($O43="","",$O43),IFERROR(IF([2]财务取数接口!$I$42=0,"",[2]财务取数接口!$I$42),"")) | P43: =IF(AND($C43<>"",$C43<>"项目",OR(N($D43)<>0,N($E43)<>0,N($F43)<>0)),1,0) -> 0 | Q43: =N(Q42)+$P43 -> 0
A44: 43 | B44: =IF($T$4=0,IF($I44="","",$I44),IFERROR(IF([2]财务取数接口!$B$43=0,"",[2]财务取数接口!$B$43),"")) | C44: =IF($T$4=0,IF($J44="","",$J44),IFERROR(IF([2]财务取数接口!$C$43=0,"",[2]财务取数接口!$C$43),"")) -> 物料销售 | D44: =IF($T$4=0,IF($K44="","",$K44),IFERROR(IF([2]财务取数接口!$D$43=0,"",[2]财务取数接口!$D$43),"")) | E44: =IF($T$4=0,IF($L44="","",$L44),IFERROR(IF([2]财务取数接口!$E$43=0,"",[2]财务取数接口!$E$43),"")) -> 包 | F44: =IF($T$4=0,IF($M44="","",$M44),IFERROR(IF([2]财务取数接口!$G$43=0,"",[2]财务取数接口!$G$43),"")) | G44: =IF($T$4=0,IF($N44="","",$N44),IFERROR(IF([2]财务取数接口!$H$43=0,"",[2]财务取数接口!$H$43),"")) | H44: =IF($T$4=0,IF($O44="","",$O44),IFERROR(IF([2]财务取数接口!$I$43=0,"",[2]财务取数接口!$I$43),"")) | P44: =IF(AND($C44<>"",$C44<>"项目",OR(N($D44)<>0,N($E44)<>0,N($F44)<>0)),1,0) -> 0 | Q44: =N(Q43)+$P44 -> 0
A45: 44 | B45: =IF($T$4=0,IF($I45="","",$I45),IFERROR(IF([2]财务取数接口!$B$44=0,"",[2]财务取数接口!$B$44),"")) | C45: =IF($T$4=0,IF($J45="","",$J45),IFERROR(IF([2]财务取数接口!$C$44=0,"",[2]财务取数接口!$C$44),"")) -> 物料销售 | D45: =IF($T$4=0,IF($K45="","",$K45),IFERROR(IF([2]财务取数接口!$D$44=0,"",[2]财务取数接口!$D$44),"")) | E45: =IF($T$4=0,IF($L45="","",$L45),IFERROR(IF([2]财务取数接口!$E$44=0,"",[2]财务取数接口!$E$44),"")) -> 包 | F45: =IF($T$4=0,IF($M45="","",$M45),IFERROR(IF([2]财务取数接口!$G$44=0,"",[2]财务取数接口!$G$44),"")) | G45: =IF($T$4=0,IF($N45="","",$N45),IFERROR(IF([2]财务取数接口!$H$44=0,"",[2]财务取数接口!$H$44),"")) | H45: =IF($T$4=0,IF($O45="","",$O45),IFERROR(IF([2]财务取数接口!$I$44=0,"",[2]财务取数接口!$I$44),"")) | P45: =IF(AND($C45<>"",$C45<>"项目",OR(N($D45)<>0,N($E45)<>0,N($F45)<>0)),1,0) -> 0 | Q45: =N(Q44)+$P45 -> 0
A46: 45 | B46: =IF($T$4=0,IF($I46="","",$I46),IFERROR(IF([2]财务取数接口!$B$45=0,"",[2]财务取数接口!$B$45),"")) | C46: =IF($T$4=0,IF($J46="","",$J46),IFERROR(IF([2]财务取数接口!$C$45=0,"",[2]财务取数接口!$C$45),"")) -> 物料销售 | D46: =IF($T$4=0,IF($K46="","",$K46),IFERROR(IF([2]财务取数接口!$D$45=0,"",[2]财务取数接口!$D$45),"")) | E46: =IF($T$4=0,IF($L46="","",$L46),IFERROR(IF([2]财务取数接口!$E$45=0,"",[2]财务取数接口!$E$45),"")) -> 包 | F46: =IF($T$4=0,IF($M46="","",$M46),IFERROR(IF([2]财务取数接口!$G$45=0,"",[2]财务取数接口!$G$45),"")) | G46: =IF($T$4=0,IF($N46="","",$N46),IFERROR(IF([2]财务取数接口!$H$45=0,"",[2]财务取数接口!$H$45),"")) | H46: =IF($T$4=0,IF($O46="","",$O46),IFERROR(IF([2]财务取数接口!$I$45=0,"",[2]财务取数接口!$I$45),"")) | P46: =IF(AND($C46<>"",$C46<>"项目",OR(N($D46)<>0,N($E46)<>0,N($F46)<>0)),1,0) -> 0 | Q46: =N(Q45)+$P46 -> 0
A47: 46 | B47: =IF($T$4=0,IF($I47="","",$I47),IFERROR(IF([2]财务取数接口!$B$46=0,"",[2]财务取数接口!$B$46),"")) | C47: =IF($T$4=0,IF($J47="","",$J47),IFERROR(IF([2]财务取数接口!$C$46=0,"",[2]财务取数接口!$C$46),"")) -> 物料销售 | D47: =IF($T$4=0,IF($K47="","",$K47),IFERROR(IF([2]财务取数接口!$D$46=0,"",[2]财务取数接口!$D$46),"")) | E47: =IF($T$4=0,IF($L47="","",$L47),IFERROR(IF([2]财务取数接口!$E$46=0,"",[2]财务取数接口!$E$46),"")) -> 包 | F47: =IF($T$4=0,IF($M47="","",$M47),IFERROR(IF([2]财务取数接口!$G$46=0,"",[2]财务取数接口!$G$46),"")) | G47: =IF($T$4=0,IF($N47="","",$N47),IFERROR(IF([2]财务取数接口!$H$46=0,"",[2]财务取数接口!$H$46),"")) | H47: =IF($T$4=0,IF($O47="","",$O47),IFERROR(IF([2]财务取数接口!$I$46=0,"",[2]财务取数接口!$I$46),"")) | P47: =IF(AND($C47<>"",$C47<>"项目",OR(N($D47)<>0,N($E47)<>0,N($F47)<>0)),1,0) -> 0 | Q47: =N(Q46)+$P47 -> 0
A48: 47 | B48: =IF($T$4=0,IF($I48="","",$I48),IFERROR(IF([2]财务取数接口!$B$47=0,"",[2]财务取数接口!$B$47),"")) | C48: =IF($T$4=0,IF($J48="","",$J48),IFERROR(IF([2]财务取数接口!$C$47=0,"",[2]财务取数接口!$C$47),"")) -> 物料销售 | D48: =IF($T$4=0,IF($K48="","",$K48),IFERROR(IF([2]财务取数接口!$D$47=0,"",[2]财务取数接口!$D$47),"")) | E48: =IF($T$4=0,IF($L48="","",$L48),IFERROR(IF([2]财务取数接口!$E$47=0,"",[2]财务取数接口!$E$47),"")) -> 包 | F48: =IF($T$4=0,IF($M48="","",$M48),IFERROR(IF([2]财务取数接口!$G$47=0,"",[2]财务取数接口!$G$47),"")) | G48: =IF($T$4=0,IF($N48="","",$N48),IFERROR(IF([2]财务取数接口!$H$47=0,"",[2]财务取数接口!$H$47),"")) | H48: =IF($T$4=0,IF($O48="","",$O48),IFERROR(IF([2]财务取数接口!$I$47=0,"",[2]财务取数接口!$I$47),"")) | P48: =IF(AND($C48<>"",$C48<>"项目",OR(N($D48)<>0,N($E48)<>0,N($F48)<>0)),1,0) -> 0 | Q48: =N(Q47)+$P48 -> 0
A49: 48 | B49: =IF($T$4=0,IF($I49="","",$I49),IFERROR(IF([2]财务取数接口!$B$48=0,"",[2]财务取数接口!$B$48),"")) | C49: =IF($T$4=0,IF($J49="","",$J49),IFERROR(IF([2]财务取数接口!$C$48=0,"",[2]财务取数接口!$C$48),"")) -> 物料销售 | D49: =IF($T$4=0,IF($K49="","",$K49),IFERROR(IF([2]财务取数接口!$D$48=0,"",[2]财务取数接口!$D$48),"")) | E49: =IF($T$4=0,IF($L49="","",$L49),IFERROR(IF([2]财务取数接口!$E$48=0,"",[2]财务取数接口!$E$48),"")) -> 包 | F49: =IF($T$4=0,IF($M49="","",$M49),IFERROR(IF([2]财务取数接口!$G$48=0,"",[2]财务取数接口!$G$48),"")) | G49: =IF($T$4=0,IF($N49="","",$N49),IFERROR(IF([2]财务取数接口!$H$48=0,"",[2]财务取数接口!$H$48),"")) | H49: =IF($T$4=0,IF($O49="","",$O49),IFERROR(IF([2]财务取数接口!$I$48=0,"",[2]财务取数接口!$I$48),"")) | P49: =IF(AND($C49<>"",$C49<>"项目",OR(N($D49)<>0,N($E49)<>0,N($F49)<>0)),1,0) -> 0 | Q49: =N(Q48)+$P49 -> 0
A50: 49 | B50: =IF($T$4=0,IF($I50="","",$I50),IFERROR(IF([2]财务取数接口!$B$49=0,"",[2]财务取数接口!$B$49),"")) | C50: =IF($T$4=0,IF($J50="","",$J50),IFERROR(IF([2]财务取数接口!$C$49=0,"",[2]财务取数接口!$C$49),"")) -> 物料销售 | D50: =IF($T$4=0,IF($K50="","",$K50),IFERROR(IF([2]财务取数接口!$D$49=0,"",[2]财务取数接口!$D$49),"")) | E50: =IF($T$4=0,IF($L50="","",$L50),IFERROR(IF([2]财务取数接口!$E$49=0,"",[2]财务取数接口!$E$49),"")) -> 包 | F50: =IF($T$4=0,IF($M50="","",$M50),IFERROR(IF([2]财务取数接口!$G$49=0,"",[2]财务取数接口!$G$49),"")) | G50: =IF($T$4=0,IF($N50="","",$N50),IFERROR(IF([2]财务取数接口!$H$49=0,"",[2]财务取数接口!$H$49),"")) | H50: =IF($T$4=0,IF($O50="","",$O50),IFERROR(IF([2]财务取数接口!$I$49=0,"",[2]财务取数接口!$I$49),"")) | P50: =IF(AND($C50<>"",$C50<>"项目",OR(N($D50)<>0,N($E50)<>0,N($F50)<>0)),1,0) -> 0 | Q50: =N(Q49)+$P50 -> 0
A51: 50 | B51: =IF($T$4=0,IF($I51="","",$I51),IFERROR(IF([2]财务取数接口!$B$50=0,"",[2]财务取数接口!$B$50),"")) | C51: =IF($T$4=0,IF($J51="","",$J51),IFERROR(IF([2]财务取数接口!$C$50=0,"",[2]财务取数接口!$C$50),"")) -> 物料销售 | D51: =IF($T$4=0,IF($K51="","",$K51),IFERROR(IF([2]财务取数接口!$D$50=0,"",[2]财务取数接口!$D$50),"")) | E51: =IF($T$4=0,IF($L51="","",$L51),IFERROR(IF([2]财务取数接口!$E$50=0,"",[2]财务取数接口!$E$50),"")) -> 包 | F51: =IF($T$4=0,IF($M51="","",$M51),IFERROR(IF([2]财务取数接口!$G$50=0,"",[2]财务取数接口!$G$50),"")) | G51: =IF($T$4=0,IF($N51="","",$N51),IFERROR(IF([2]财务取数接口!$H$50=0,"",[2]财务取数接口!$H$50),"")) | H51: =IF($T$4=0,IF($O51="","",$O51),IFERROR(IF([2]财务取数接口!$I$50=0,"",[2]财务取数接口!$I$50),"")) | P51: =IF(AND($C51<>"",$C51<>"项目",OR(N($D51)<>0,N($E51)<>0,N($F51)<>0)),1,0) -> 0 | Q51: =N(Q50)+$P51 -> 0
A52: 51 | B52: =IF($T$4=0,IF($I52="","",$I52),IFERROR(IF([2]财务取数接口!$B$51=0,"",[2]财务取数接口!$B$51),"")) | C52: =IF($T$4=0,IF($J52="","",$J52),IFERROR(IF([2]财务取数接口!$C$51=0,"",[2]财务取数接口!$C$51),"")) -> 物料销售 | D52: =IF($T$4=0,IF($K52="","",$K52),IFERROR(IF([2]财务取数接口!$D$51=0,"",[2]财务取数接口!$D$51),"")) | E52: =IF($T$4=0,IF($L52="","",$L52),IFERROR(IF([2]财务取数接口!$E$51=0,"",[2]财务取数接口!$E$51),"")) -> 包 | F52: =IF($T$4=0,IF($M52="","",$M52),IFERROR(IF([2]财务取数接口!$G$51=0,"",[2]财务取数接口!$G$51),"")) | G52: =IF($T$4=0,IF($N52="","",$N52),IFERROR(IF([2]财务取数接口!$H$51=0,"",[2]财务取数接口!$H$51),"")) | H52: =IF($T$4=0,IF($O52="","",$O52),IFERROR(IF([2]财务取数接口!$I$51=0,"",[2]财务取数接口!$I$51),"")) | P52: =IF(AND($C52<>"",$C52<>"项目",OR(N($D52)<>0,N($E52)<>0,N($F52)<>0)),1,0) -> 0 | Q52: =N(Q51)+$P52 -> 0
A53: 52 | B53: =IF($T$4=0,IF($I53="","",$I53),IFERROR(IF([2]财务取数接口!$B$52=0,"",[2]财务取数接口!$B$52),"")) | C53: =IF($T$4=0,IF($J53="","",$J53),IFERROR(IF([2]财务取数接口!$C$52=0,"",[2]财务取数接口!$C$52),"")) -> 押金收取 | D53: =IF($T$4=0,IF($K53="","",$K53),IFERROR(IF([2]财务取数接口!$D$52=0,"",[2]财务取数接口!$D$52),"")) | E53: =IF($T$4=0,IF($L53="","",$L53),IFERROR(IF([2]财务取数接口!$E$52=0,"",[2]财务取数接口!$E$52),"")) -> 元 | F53: =IF($T$4=0,IF($M53="","",$M53),IFERROR(IF([2]财务取数接口!$G$52=0,"",[2]财务取数接口!$G$52),"")) | G53: =IF($T$4=0,IF($N53="","",$N53),IFERROR(IF([2]财务取数接口!$H$52=0,"",[2]财务取数接口!$H$52),"")) | H53: =IF($T$4=0,IF($O53="","",$O53),IFERROR(IF([2]财务取数接口!$I$52=0,"",[2]财务取数接口!$I$52),"")) | P53: =IF(AND($C53<>"",$C53<>"项目",OR(N($D53)<>0,N($E53)<>0,N($F53)<>0)),1,0) -> 0 | Q53: =N(Q52)+$P53 -> 0
A54: 53 | B54: =IF($T$4=0,IF($I54="","",$I54),IFERROR(IF([2]财务取数接口!$B$53=0,"",[2]财务取数接口!$B$53),"")) | C54: =IF($T$4=0,IF($J54="","",$J54),IFERROR(IF([2]财务取数接口!$C$53=0,"",[2]财务取数接口!$C$53),"")) -> 押金收取 | D54: =IF($T$4=0,IF($K54="","",$K54),IFERROR(IF([2]财务取数接口!$D$53=0,"",[2]财务取数接口!$D$53),"")) | E54: =IF($T$4=0,IF($L54="","",$L54),IFERROR(IF([2]财务取数接口!$E$53=0,"",[2]财务取数接口!$E$53),"")) -> 元 | F54: =IF($T$4=0,IF($M54="","",$M54),IFERROR(IF([2]财务取数接口!$G$53=0,"",[2]财务取数接口!$G$53),"")) | G54: =IF($T$4=0,IF($N54="","",$N54),IFERROR(IF([2]财务取数接口!$H$53=0,"",[2]财务取数接口!$H$53),"")) | H54: =IF($T$4=0,IF($O54="","",$O54),IFERROR(IF([2]财务取数接口!$I$53=0,"",[2]财务取数接口!$I$53),"")) | P54: =IF(AND($C54<>"",$C54<>"项目",OR(N($D54)<>0,N($E54)<>0,N($F54)<>0)),1,0) -> 0 | Q54: =N(Q53)+$P54 -> 0
A55: 54 | B55: =IF($T$4=0,IF($I55="","",$I55),IFERROR(IF([2]财务取数接口!$B$54=0,"",[2]财务取数接口!$B$54),"")) | C55: =IF($T$4=0,IF($J55="","",$J55),IFERROR(IF([2]财务取数接口!$C$54=0,"",[2]财务取数接口!$C$54),"")) -> 押金收取 | D55: =IF($T$4=0,IF($K55="","",$K55),IFERROR(IF([2]财务取数接口!$D$54=0,"",[2]财务取数接口!$D$54),"")) | E55: =IF($T$4=0,IF($L55="","",$L55),IFERROR(IF([2]财务取数接口!$E$54=0,"",[2]财务取数接口!$E$54),"")) -> 元 | F55: =IF($T$4=0,IF($M55="","",$M55),IFERROR(IF([2]财务取数接口!$G$54=0,"",[2]财务取数接口!$G$54),"")) | G55: =IF($T$4=0,IF($N55="","",$N55),IFERROR(IF([2]财务取数接口!$H$54=0,"",[2]财务取数接口!$H$54),"")) | H55: =IF($T$4=0,IF($O55="","",$O55),IFERROR(IF([2]财务取数接口!$I$54=0,"",[2]财务取数接口!$I$54),"")) | P55: =IF(AND($C55<>"",$C55<>"项目",OR(N($D55)<>0,N($E55)<>0,N($F55)<>0)),1,0) -> 0 | Q55: =N(Q54)+$P55 -> 0
A56: 55 | B56: =IF($T$4=0,IF($I56="","",$I56),IFERROR(IF([2]财务取数接口!$B$55=0,"",[2]财务取数接口!$B$55),"")) | C56: =IF($T$4=0,IF($J56="","",$J56),IFERROR(IF([2]财务取数接口!$C$55=0,"",[2]财务取数接口!$C$55),"")) -> 押金收取 | D56: =IF($T$4=0,IF($K56="","",$K56),IFERROR(IF([2]财务取数接口!$D$55=0,"",[2]财务取数接口!$D$55),"")) | E56: =IF($T$4=0,IF($L56="","",$L56),IFERROR(IF([2]财务取数接口!$E$55=0,"",[2]财务取数接口!$E$55),"")) -> 元 | F56: =IF($T$4=0,IF($M56="","",$M56),IFERROR(IF([2]财务取数接口!$G$55=0,"",[2]财务取数接口!$G$55),"")) | G56: =IF($T$4=0,IF($N56="","",$N56),IFERROR(IF([2]财务取数接口!$H$55=0,"",[2]财务取数接口!$H$55),"")) | H56: =IF($T$4=0,IF($O56="","",$O56),IFERROR(IF([2]财务取数接口!$I$55=0,"",[2]财务取数接口!$I$55),"")) | P56: =IF(AND($C56<>"",$C56<>"项目",OR(N($D56)<>0,N($E56)<>0,N($F56)<>0)),1,0) -> 0 | Q56: =N(Q55)+$P56 -> 0
A57: 56 | B57: =IF($T$4=0,IF($I57="","",$I57),IFERROR(IF([2]财务取数接口!$B$56=0,"",[2]财务取数接口!$B$56),"")) | C57: =IF($T$4=0,IF($J57="","",$J57),IFERROR(IF([2]财务取数接口!$C$56=0,"",[2]财务取数接口!$C$56),"")) -> 押金收取 | D57: =IF($T$4=0,IF($K57="","",$K57),IFERROR(IF([2]财务取数接口!$D$56=0,"",[2]财务取数接口!$D$56),"")) | E57: =IF($T$4=0,IF($L57="","",$L57),IFERROR(IF([2]财务取数接口!$E$56=0,"",[2]财务取数接口!$E$56),"")) -> 元 | F57: =IF($T$4=0,IF($M57="","",$M57),IFERROR(IF([2]财务取数接口!$G$56=0,"",[2]财务取数接口!$G$56),"")) | G57: =IF($T$4=0,IF($N57="","",$N57),IFERROR(IF([2]财务取数接口!$H$56=0,"",[2]财务取数接口!$H$56),"")) | H57: =IF($T$4=0,IF($O57="","",$O57),IFERROR(IF([2]财务取数接口!$I$56=0,"",[2]财务取数接口!$I$56),"")) | P57: =IF(AND($C57<>"",$C57<>"项目",OR(N($D57)<>0,N($E57)<>0,N($F57)<>0)),1,0) -> 0 | Q57: =N(Q56)+$P57 -> 0
A58: 57 | B58: =IF($T$4=0,IF($I58="","",$I58),IFERROR(IF([2]财务取数接口!$B$57=0,"",[2]财务取数接口!$B$57),"")) | C58: =IF($T$4=0,IF($J58="","",$J58),IFERROR(IF([2]财务取数接口!$C$57=0,"",[2]财务取数接口!$C$57),"")) -> 押金收取 | D58: =IF($T$4=0,IF($K58="","",$K58),IFERROR(IF([2]财务取数接口!$D$57=0,"",[2]财务取数接口!$D$57),"")) | E58: =IF($T$4=0,IF($L58="","",$L58),IFERROR(IF([2]财务取数接口!$E$57=0,"",[2]财务取数接口!$E$57),"")) -> 元 | F58: =IF($T$4=0,IF($M58="","",$M58),IFERROR(IF([2]财务取数接口!$G$57=0,"",[2]财务取数接口!$G$57),"")) | G58: =IF($T$4=0,IF($N58="","",$N58),IFERROR(IF([2]财务取数接口!$H$57=0,"",[2]财务取数接口!$H$57),"")) | H58: =IF($T$4=0,IF($O58="","",$O58),IFERROR(IF([2]财务取数接口!$I$57=0,"",[2]财务取数接口!$I$57),"")) | P58: =IF(AND($C58<>"",$C58<>"项目",OR(N($D58)<>0,N($E58)<>0,N($F58)<>0)),1,0) -> 0 | Q58: =N(Q57)+$P58 -> 0
A59: 58 | B59: =IF($T$4=0,IF($I59="","",$I59),IFERROR(IF([2]财务取数接口!$B$58=0,"",[2]财务取数接口!$B$58),"")) | C59: =IF($T$4=0,IF($J59="","",$J59),IFERROR(IF([2]财务取数接口!$C$58=0,"",[2]财务取数接口!$C$58),"")) -> 押金收取 | D59: =IF($T$4=0,IF($K59="","",$K59),IFERROR(IF([2]财务取数接口!$D$58=0,"",[2]财务取数接口!$D$58),"")) | E59: =IF($T$4=0,IF($L59="","",$L59),IFERROR(IF([2]财务取数接口!$E$58=0,"",[2]财务取数接口!$E$58),"")) -> 元 | F59: =IF($T$4=0,IF($M59="","",$M59),IFERROR(IF([2]财务取数接口!$G$58=0,"",[2]财务取数接口!$G$58),"")) | G59: =IF($T$4=0,IF($N59="","",$N59),IFERROR(IF([2]财务取数接口!$H$58=0,"",[2]财务取数接口!$H$58),"")) | H59: =IF($T$4=0,IF($O59="","",$O59),IFERROR(IF([2]财务取数接口!$I$58=0,"",[2]财务取数接口!$I$58),"")) | P59: =IF(AND($C59<>"",$C59<>"项目",OR(N($D59)<>0,N($E59)<>0,N($F59)<>0)),1,0) -> 0 | Q59: =N(Q58)+$P59 -> 0
A60: 59 | B60: =IF($T$4=0,IF($I60="","",$I60),IFERROR(IF([2]财务取数接口!$B$59=0,"",[2]财务取数接口!$B$59),"")) | C60: =IF($T$4=0,IF($J60="","",$J60),IFERROR(IF([2]财务取数接口!$C$59=0,"",[2]财务取数接口!$C$59),"")) -> 押金收取 | D60: =IF($T$4=0,IF($K60="","",$K60),IFERROR(IF([2]财务取数接口!$D$59=0,"",[2]财务取数接口!$D$59),"")) | E60: =IF($T$4=0,IF($L60="","",$L60),IFERROR(IF([2]财务取数接口!$E$59=0,"",[2]财务取数接口!$E$59),"")) -> 元 | F60: =IF($T$4=0,IF($M60="","",$M60),IFERROR(IF([2]财务取数接口!$G$59=0,"",[2]财务取数接口!$G$59),"")) | G60: =IF($T$4=0,IF($N60="","",$N60),IFERROR(IF([2]财务取数接口!$H$59=0,"",[2]财务取数接口!$H$59),"")) | H60: =IF($T$4=0,IF($O60="","",$O60),IFERROR(IF([2]财务取数接口!$I$59=0,"",[2]财务取数接口!$I$59),"")) | P60: =IF(AND($C60<>"",$C60<>"项目",OR(N($D60)<>0,N($E60)<>0,N($F60)<>0)),1,0) -> 0 | Q60: =N(Q59)+$P60 -> 0
A61: 60 | B61: =IF($T$4=0,IF($I61="","",$I61),IFERROR(IF([2]财务取数接口!$B$60=0,"",[2]财务取数接口!$B$60),"")) | C61: =IF($T$4=0,IF($J61="","",$J61),IFERROR(IF([2]财务取数接口!$C$60=0,"",[2]财务取数接口!$C$60),"")) -> 押金收取 | D61: =IF($T$4=0,IF($K61="","",$K61),IFERROR(IF([2]财务取数接口!$D$60=0,"",[2]财务取数接口!$D$60),"")) | E61: =IF($T$4=0,IF($L61="","",$L61),IFERROR(IF([2]财务取数接口!$E$60=0,"",[2]财务取数接口!$E$60),"")) -> 元 | F61: =IF($T$4=0,IF($M61="","",$M61),IFERROR(IF([2]财务取数接口!$G$60=0,"",[2]财务取数接口!$G$60),"")) | G61: =IF($T$4=0,IF($N61="","",$N61),IFERROR(IF([2]财务取数接口!$H$60=0,"",[2]财务取数接口!$H$60),"")) | H61: =IF($T$4=0,IF($O61="","",$O61),IFERROR(IF([2]财务取数接口!$I$60=0,"",[2]财务取数接口!$I$60),"")) | P61: =IF(AND($C61<>"",$C61<>"项目",OR(N($D61)<>0,N($E61)<>0,N($F61)<>0)),1,0) -> 0 | Q61: =N(Q60)+$P61 -> 0
A62: 61 | B62: =IF($T$4=0,IF($I62="","",$I62),IFERROR(IF([2]财务取数接口!$B$61=0,"",[2]财务取数接口!$B$61),"")) | C62: =IF($T$4=0,IF($J62="","",$J62),IFERROR(IF([2]财务取数接口!$C$61=0,"",[2]财务取数接口!$C$61),"")) -> 押金收取 | D62: =IF($T$4=0,IF($K62="","",$K62),IFERROR(IF([2]财务取数接口!$D$61=0,"",[2]财务取数接口!$D$61),"")) | E62: =IF($T$4=0,IF($L62="","",$L62),IFERROR(IF([2]财务取数接口!$E$61=0,"",[2]财务取数接口!$E$61),"")) -> 元 | F62: =IF($T$4=0,IF($M62="","",$M62),IFERROR(IF([2]财务取数接口!$G$61=0,"",[2]财务取数接口!$G$61),"")) | G62: =IF($T$4=0,IF($N62="","",$N62),IFERROR(IF([2]财务取数接口!$H$61=0,"",[2]财务取数接口!$H$61),"")) | H62: =IF($T$4=0,IF($O62="","",$O62),IFERROR(IF([2]财务取数接口!$I$61=0,"",[2]财务取数接口!$I$61),"")) | P62: =IF(AND($C62<>"",$C62<>"项目",OR(N($D62)<>0,N($E62)<>0,N($F62)<>0)),1,0) -> 0 | Q62: =N(Q61)+$P62 -> 0
A63: 62 | B63: =IF($T$4=0,IF($I63="","",$I63),IFERROR(IF([2]财务取数接口!$B$62=0,"",[2]财务取数接口!$B$62),"")) | C63: =IF($T$4=0,IF($J63="","",$J63),IFERROR(IF([2]财务取数接口!$C$62=0,"",[2]财务取数接口!$C$62),"")) -> 押金收取 | D63: =IF($T$4=0,IF($K63="","",$K63),IFERROR(IF([2]财务取数接口!$D$62=0,"",[2]财务取数接口!$D$62),"")) | E63: =IF($T$4=0,IF($L63="","",$L63),IFERROR(IF([2]财务取数接口!$E$62=0,"",[2]财务取数接口!$E$62),"")) -> 元 | F63: =IF($T$4=0,IF($M63="","",$M63),IFERROR(IF([2]财务取数接口!$G$62=0,"",[2]财务取数接口!$G$62),"")) | G63: =IF($T$4=0,IF($N63="","",$N63),IFERROR(IF([2]财务取数接口!$H$62=0,"",[2]财务取数接口!$H$62),"")) | H63: =IF($T$4=0,IF($O63="","",$O63),IFERROR(IF([2]财务取数接口!$I$62=0,"",[2]财务取数接口!$I$62),"")) | P63: =IF(AND($C63<>"",$C63<>"项目",OR(N($D63)<>0,N($E63)<>0,N($F63)<>0)),1,0) -> 0 | Q63: =N(Q62)+$P63 -> 0
A64: 63 | B64: =IF($T$4=0,IF($I64="","",$I64),IFERROR(IF([2]财务取数接口!$B$63=0,"",[2]财务取数接口!$B$63),"")) | C64: =IF($T$4=0,IF($J64="","",$J64),IFERROR(IF([2]财务取数接口!$C$63=0,"",[2]财务取数接口!$C$63),"")) -> 押金收取 | D64: =IF($T$4=0,IF($K64="","",$K64),IFERROR(IF([2]财务取数接口!$D$63=0,"",[2]财务取数接口!$D$63),"")) | E64: =IF($T$4=0,IF($L64="","",$L64),IFERROR(IF([2]财务取数接口!$E$63=0,"",[2]财务取数接口!$E$63),"")) -> 元 | F64: =IF($T$4=0,IF($M64="","",$M64),IFERROR(IF([2]财务取数接口!$G$63=0,"",[2]财务取数接口!$G$63),"")) | G64: =IF($T$4=0,IF($N64="","",$N64),IFERROR(IF([2]财务取数接口!$H$63=0,"",[2]财务取数接口!$H$63),"")) | H64: =IF($T$4=0,IF($O64="","",$O64),IFERROR(IF([2]财务取数接口!$I$63=0,"",[2]财务取数接口!$I$63),"")) | P64: =IF(AND($C64<>"",$C64<>"项目",OR(N($D64)<>0,N($E64)<>0,N($F64)<>0)),1,0) -> 0 | Q64: =N(Q63)+$P64 -> 0
A65: 64 | B65: =IF($T$4=0,IF($I65="","",$I65),IFERROR(IF([2]财务取数接口!$B$64=0,"",[2]财务取数接口!$B$64),"")) | C65: =IF($T$4=0,IF($J65="","",$J65),IFERROR(IF([2]财务取数接口!$C$64=0,"",[2]财务取数接口!$C$64),"")) -> 押金收取 | D65: =IF($T$4=0,IF($K65="","",$K65),IFERROR(IF([2]财务取数接口!$D$64=0,"",[2]财务取数接口!$D$64),"")) | E65: =IF($T$4=0,IF($L65="","",$L65),IFERROR(IF([2]财务取数接口!$E$64=0,"",[2]财务取数接口!$E$64),"")) -> 元 | F65: =IF($T$4=0,IF($M65="","",$M65),IFERROR(IF([2]财务取数接口!$G$64=0,"",[2]财务取数接口!$G$64),"")) | G65: =IF($T$4=0,IF($N65="","",$N65),IFERROR(IF([2]财务取数接口!$H$64=0,"",[2]财务取数接口!$H$64),"")) | H65: =IF($T$4=0,IF($O65="","",$O65),IFERROR(IF([2]财务取数接口!$I$64=0,"",[2]财务取数接口!$I$64),"")) | P65: =IF(AND($C65<>"",$C65<>"项目",OR(N($D65)<>0,N($E65)<>0,N($F65)<>0)),1,0) -> 0 | Q65: =N(Q64)+$P65 -> 0
A66: 65 | B66: =IF($T$4=0,IF($I66="","",$I66),IFERROR(IF([2]财务取数接口!$B$65=0,"",[2]财务取数接口!$B$65),"")) | C66: =IF($T$4=0,IF($J66="","",$J66),IFERROR(IF([2]财务取数接口!$C$65=0,"",[2]财务取数接口!$C$65),"")) -> 押金收取 | D66: =IF($T$4=0,IF($K66="","",$K66),IFERROR(IF([2]财务取数接口!$D$65=0,"",[2]财务取数接口!$D$65),"")) | E66: =IF($T$4=0,IF($L66="","",$L66),IFERROR(IF([2]财务取数接口!$E$65=0,"",[2]财务取数接口!$E$65),"")) -> 元 | F66: =IF($T$4=0,IF($M66="","",$M66),IFERROR(IF([2]财务取数接口!$G$65=0,"",[2]财务取数接口!$G$65),"")) | G66: =IF($T$4=0,IF($N66="","",$N66),IFERROR(IF([2]财务取数接口!$H$65=0,"",[2]财务取数接口!$H$65),"")) | H66: =IF($T$4=0,IF($O66="","",$O66),IFERROR(IF([2]财务取数接口!$I$65=0,"",[2]财务取数接口!$I$65),"")) | P66: =IF(AND($C66<>"",$C66<>"项目",OR(N($D66)<>0,N($E66)<>0,N($F66)<>0)),1,0) -> 0 | Q66: =N(Q65)+$P66 -> 0
A67: 66 | B67: =IF($T$4=0,IF($I67="","",$I67),IFERROR(IF([2]财务取数接口!$B$66=0,"",[2]财务取数接口!$B$66),"")) | C67: =IF($T$4=0,IF($J67="","",$J67),IFERROR(IF([2]财务取数接口!$C$66=0,"",[2]财务取数接口!$C$66),"")) -> 押金收取 | D67: =IF($T$4=0,IF($K67="","",$K67),IFERROR(IF([2]财务取数接口!$D$66=0,"",[2]财务取数接口!$D$66),"")) | E67: =IF($T$4=0,IF($L67="","",$L67),IFERROR(IF([2]财务取数接口!$E$66=0,"",[2]财务取数接口!$E$66),"")) -> 元 | F67: =IF($T$4=0,IF($M67="","",$M67),IFERROR(IF([2]财务取数接口!$G$66=0,"",[2]财务取数接口!$G$66),"")) | G67: =IF($T$4=0,IF($N67="","",$N67),IFERROR(IF([2]财务取数接口!$H$66=0,"",[2]财务取数接口!$H$66),"")) | H67: =IF($T$4=0,IF($O67="","",$O67),IFERROR(IF([2]财务取数接口!$I$66=0,"",[2]财务取数接口!$I$66),"")) | P67: =IF(AND($C67<>"",$C67<>"项目",OR(N($D67)<>0,N($E67)<>0,N($F67)<>0)),1,0) -> 0 | Q67: =N(Q66)+$P67 -> 0
A68: 67 | B68: =IF($T$4=0,IF($I68="","",$I68),IFERROR(IF([2]财务取数接口!$B$67=0,"",[2]财务取数接口!$B$67),"")) | C68: =IF($T$4=0,IF($J68="","",$J68),IFERROR(IF([2]财务取数接口!$C$67=0,"",[2]财务取数接口!$C$67),"")) -> 押金收取 | D68: =IF($T$4=0,IF($K68="","",$K68),IFERROR(IF([2]财务取数接口!$D$67=0,"",[2]财务取数接口!$D$67),"")) | E68: =IF($T$4=0,IF($L68="","",$L68),IFERROR(IF([2]财务取数接口!$E$67=0,"",[2]财务取数接口!$E$67),"")) -> 元 | F68: =IF($T$4=0,IF($M68="","",$M68),IFERROR(IF([2]财务取数接口!$G$67=0,"",[2]财务取数接口!$G$67),"")) | G68: =IF($T$4=0,IF($N68="","",$N68),IFERROR(IF([2]财务取数接口!$H$67=0,"",[2]财务取数接口!$H$67),"")) | H68: =IF($T$4=0,IF($O68="","",$O68),IFERROR(IF([2]财务取数接口!$I$67=0,"",[2]财务取数接口!$I$67),"")) | P68: =IF(AND($C68<>"",$C68<>"项目",OR(N($D68)<>0,N($E68)<>0,N($F68)<>0)),1,0) -> 0 | Q68: =N(Q67)+$P68 -> 0
A69: 68 | B69: =IF($T$4=0,IF($I69="","",$I69),IFERROR(IF([2]财务取数接口!$B$68=0,"",[2]财务取数接口!$B$68),"")) | C69: =IF($T$4=0,IF($J69="","",$J69),IFERROR(IF([2]财务取数接口!$C$68=0,"",[2]财务取数接口!$C$68),"")) -> 押金收取 | D69: =IF($T$4=0,IF($K69="","",$K69),IFERROR(IF([2]财务取数接口!$D$68=0,"",[2]财务取数接口!$D$68),"")) | E69: =IF($T$4=0,IF($L69="","",$L69),IFERROR(IF([2]财务取数接口!$E$68=0,"",[2]财务取数接口!$E$68),"")) -> 元 | F69: =IF($T$4=0,IF($M69="","",$M69),IFERROR(IF([2]财务取数接口!$G$68=0,"",[2]财务取数接口!$G$68),"")) | G69: =IF($T$4=0,IF($N69="","",$N69),IFERROR(IF([2]财务取数接口!$H$68=0,"",[2]财务取数接口!$H$68),"")) | H69: =IF($T$4=0,IF($O69="","",$O69),IFERROR(IF([2]财务取数接口!$I$68=0,"",[2]财务取数接口!$I$68),"")) | P69: =IF(AND($C69<>"",$C69<>"项目",OR(N($D69)<>0,N($E69)<>0,N($F69)<>0)),1,0) -> 0 | Q69: =N(Q68)+$P69 -> 0
A70: 69 | B70: =IF($T$4=0,IF($I70="","",$I70),IFERROR(IF([2]财务取数接口!$B$69=0,"",[2]财务取数接口!$B$69),"")) | C70: =IF($T$4=0,IF($J70="","",$J70),IFERROR(IF([2]财务取数接口!$C$69=0,"",[2]财务取数接口!$C$69),"")) -> 押金收取 | D70: =IF($T$4=0,IF($K70="","",$K70),IFERROR(IF([2]财务取数接口!$D$69=0,"",[2]财务取数接口!$D$69),"")) | E70: =IF($T$4=0,IF($L70="","",$L70),IFERROR(IF([2]财务取数接口!$E$69=0,"",[2]财务取数接口!$E$69),"")) -> 元 | F70: =IF($T$4=0,IF($M70="","",$M70),IFERROR(IF([2]财务取数接口!$G$69=0,"",[2]财务取数接口!$G$69),"")) | G70: =IF($T$4=0,IF($N70="","",$N70),IFERROR(IF([2]财务取数接口!$H$69=0,"",[2]财务取数接口!$H$69),"")) | H70: =IF($T$4=0,IF($O70="","",$O70),IFERROR(IF([2]财务取数接口!$I$69=0,"",[2]财务取数接口!$I$69),"")) | P70: =IF(AND($C70<>"",$C70<>"项目",OR(N($D70)<>0,N($E70)<>0,N($F70)<>0)),1,0) -> 0 | Q70: =N(Q69)+$P70 -> 0
A71: 70 | B71: =IF($T$4=0,IF($I71="","",$I71),IFERROR(IF([2]财务取数接口!$B$70=0,"",[2]财务取数接口!$B$70),"")) | C71: =IF($T$4=0,IF($J71="","",$J71),IFERROR(IF([2]财务取数接口!$C$70=0,"",[2]财务取数接口!$C$70),"")) -> 押金收取 | D71: =IF($T$4=0,IF($K71="","",$K71),IFERROR(IF([2]财务取数接口!$D$70=0,"",[2]财务取数接口!$D$70),"")) | E71: =IF($T$4=0,IF($L71="","",$L71),IFERROR(IF([2]财务取数接口!$E$70=0,"",[2]财务取数接口!$E$70),"")) -> 元 | F71: =IF($T$4=0,IF($M71="","",$M71),IFERROR(IF([2]财务取数接口!$G$70=0,"",[2]财务取数接口!$G$70),"")) | G71: =IF($T$4=0,IF($N71="","",$N71),IFERROR(IF([2]财务取数接口!$H$70=0,"",[2]财务取数接口!$H$70),"")) | H71: =IF($T$4=0,IF($O71="","",$O71),IFERROR(IF([2]财务取数接口!$I$70=0,"",[2]财务取数接口!$I$70),"")) | P71: =IF(AND($C71<>"",$C71<>"项目",OR(N($D71)<>0,N($E71)<>0,N($F71)<>0)),1,0) -> 0 | Q71: =N(Q70)+$P71 -> 0
A72: 71 | B72: =IF($T$4=0,IF($I72="","",$I72),IFERROR(IF([2]财务取数接口!$B$71=0,"",[2]财务取数接口!$B$71),"")) | C72: =IF($T$4=0,IF($J72="","",$J72),IFERROR(IF([2]财务取数接口!$C$71=0,"",[2]财务取数接口!$C$71),"")) -> 押金收取 | D72: =IF($T$4=0,IF($K72="","",$K72),IFERROR(IF([2]财务取数接口!$D$71=0,"",[2]财务取数接口!$D$71),"")) | E72: =IF($T$4=0,IF($L72="","",$L72),IFERROR(IF([2]财务取数接口!$E$71=0,"",[2]财务取数接口!$E$71),"")) -> 元 | F72: =IF($T$4=0,IF($M72="","",$M72),IFERROR(IF([2]财务取数接口!$G$71=0,"",[2]财务取数接口!$G$71),"")) | G72: =IF($T$4=0,IF($N72="","",$N72),IFERROR(IF([2]财务取数接口!$H$71=0,"",[2]财务取数接口!$H$71),"")) | H72: =IF($T$4=0,IF($O72="","",$O72),IFERROR(IF([2]财务取数接口!$I$71=0,"",[2]财务取数接口!$I$71),"")) | P72: =IF(AND($C72<>"",$C72<>"项目",OR(N($D72)<>0,N($E72)<>0,N($F72)<>0)),1,0) -> 0 | Q72: =N(Q71)+$P72 -> 0
A73: 72 | B73: =IF($T$4=0,IF($I73="","",$I73),IFERROR(IF([2]财务取数接口!$B$72=0,"",[2]财务取数接口!$B$72),"")) | C73: =IF($T$4=0,IF($J73="","",$J73),IFERROR(IF([2]财务取数接口!$C$72=0,"",[2]财务取数接口!$C$72),"")) -> 押金收取 | D73: =IF($T$4=0,IF($K73="","",$K73),IFERROR(IF([2]财务取数接口!$D$72=0,"",[2]财务取数接口!$D$72),"")) | E73: =IF($T$4=0,IF($L73="","",$L73),IFERROR(IF([2]财务取数接口!$E$72=0,"",[2]财务取数接口!$E$72),"")) -> 元 | F73: =IF($T$4=0,IF($M73="","",$M73),IFERROR(IF([2]财务取数接口!$G$72=0,"",[2]财务取数接口!$G$72),"")) | G73: =IF($T$4=0,IF($N73="","",$N73),IFERROR(IF([2]财务取数接口!$H$72=0,"",[2]财务取数接口!$H$72),"")) | H73: =IF($T$4=0,IF($O73="","",$O73),IFERROR(IF([2]财务取数接口!$I$72=0,"",[2]财务取数接口!$I$72),"")) | P73: =IF(AND($C73<>"",$C73<>"项目",OR(N($D73)<>0,N($E73)<>0,N($F73)<>0)),1,0) -> 0 | Q73: =N(Q72)+$P73 -> 0
A74: 73 | B74: =IF($T$4=0,IF($I74="","",$I74),IFERROR(IF([2]财务取数接口!$B$73=0,"",[2]财务取数接口!$B$73),"")) | C74: =IF($T$4=0,IF($J74="","",$J74),IFERROR(IF([2]财务取数接口!$C$73=0,"",[2]财务取数接口!$C$73),"")) -> 押金收取 | D74: =IF($T$4=0,IF($K74="","",$K74),IFERROR(IF([2]财务取数接口!$D$73=0,"",[2]财务取数接口!$D$73),"")) | E74: =IF($T$4=0,IF($L74="","",$L74),IFERROR(IF([2]财务取数接口!$E$73=0,"",[2]财务取数接口!$E$73),"")) -> 元 | F74: =IF($T$4=0,IF($M74="","",$M74),IFERROR(IF([2]财务取数接口!$G$73=0,"",[2]财务取数接口!$G$73),"")) | G74: =IF($T$4=0,IF($N74="","",$N74),IFERROR(IF([2]财务取数接口!$H$73=0,"",[2]财务取数接口!$H$73),"")) | H74: =IF($T$4=0,IF($O74="","",$O74),IFERROR(IF([2]财务取数接口!$I$73=0,"",[2]财务取数接口!$I$73),"")) | P74: =IF(AND($C74<>"",$C74<>"项目",OR(N($D74)<>0,N($E74)<>0,N($F74)<>0)),1,0) -> 0 | Q74: =N(Q73)+$P74 -> 0
A75: 74 | B75: =IF($T$4=0,IF($I75="","",$I75),IFERROR(IF([2]财务取数接口!$B$74=0,"",[2]财务取数接口!$B$74),"")) | C75: =IF($T$4=0,IF($J75="","",$J75),IFERROR(IF([2]财务取数接口!$C$74=0,"",[2]财务取数接口!$C$74),"")) -> 押金收取 | D75: =IF($T$4=0,IF($K75="","",$K75),IFERROR(IF([2]财务取数接口!$D$74=0,"",[2]财务取数接口!$D$74),"")) | E75: =IF($T$4=0,IF($L75="","",$L75),IFERROR(IF([2]财务取数接口!$E$74=0,"",[2]财务取数接口!$E$74),"")) -> 元 | F75: =IF($T$4=0,IF($M75="","",$M75),IFERROR(IF([2]财务取数接口!$G$74=0,"",[2]财务取数接口!$G$74),"")) | G75: =IF($T$4=0,IF($N75="","",$N75),IFERROR(IF([2]财务取数接口!$H$74=0,"",[2]财务取数接口!$H$74),"")) | H75: =IF($T$4=0,IF($O75="","",$O75),IFERROR(IF([2]财务取数接口!$I$74=0,"",[2]财务取数接口!$I$74),"")) | P75: =IF(AND($C75<>"",$C75<>"项目",OR(N($D75)<>0,N($E75)<>0,N($F75)<>0)),1,0) -> 0 | Q75: =N(Q74)+$P75 -> 0
A76: 75 | B76: =IF($T$4=0,IF($I76="","",$I76),IFERROR(IF([2]财务取数接口!$B$75=0,"",[2]财务取数接口!$B$75),"")) | C76: =IF($T$4=0,IF($J76="","",$J76),IFERROR(IF([2]财务取数接口!$C$75=0,"",[2]财务取数接口!$C$75),"")) -> 押金收取 | D76: =IF($T$4=0,IF($K76="","",$K76),IFERROR(IF([2]财务取数接口!$D$75=0,"",[2]财务取数接口!$D$75),"")) | E76: =IF($T$4=0,IF($L76="","",$L76),IFERROR(IF([2]财务取数接口!$E$75=0,"",[2]财务取数接口!$E$75),"")) -> 元 | F76: =IF($T$4=0,IF($M76="","",$M76),IFERROR(IF([2]财务取数接口!$G$75=0,"",[2]财务取数接口!$G$75),"")) | G76: =IF($T$4=0,IF($N76="","",$N76),IFERROR(IF([2]财务取数接口!$H$75=0,"",[2]财务取数接口!$H$75),"")) | H76: =IF($T$4=0,IF($O76="","",$O76),IFERROR(IF([2]财务取数接口!$I$75=0,"",[2]财务取数接口!$I$75),"")) | P76: =IF(AND($C76<>"",$C76<>"项目",OR(N($D76)<>0,N($E76)<>0,N($F76)<>0)),1,0) -> 0 | Q76: =N(Q75)+$P76 -> 0
A77: 76 | B77: =IF($T$4=0,IF($I77="","",$I77),IFERROR(IF([2]财务取数接口!$B$76=0,"",[2]财务取数接口!$B$76),"")) | C77: =IF($T$4=0,IF($J77="","",$J77),IFERROR(IF([2]财务取数接口!$C$76=0,"",[2]财务取数接口!$C$76),"")) -> 押金退还 | D77: =IF($T$4=0,IF($K77="","",$K77),IFERROR(IF([2]财务取数接口!$D$76=0,"",[2]财务取数接口!$D$76),"")) | E77: =IF($T$4=0,IF($L77="","",$L77),IFERROR(IF([2]财务取数接口!$E$76=0,"",[2]财务取数接口!$E$76),"")) -> 元 | F77: =IF($T$4=0,IF($M77="","",$M77),IFERROR(IF([2]财务取数接口!$G$76=0,"",[2]财务取数接口!$G$76),"")) | G77: =IF($T$4=0,IF($N77="","",$N77),IFERROR(IF([2]财务取数接口!$H$76=0,"",[2]财务取数接口!$H$76),"")) | H77: =IF($T$4=0,IF($O77="","",$O77),IFERROR(IF([2]财务取数接口!$I$76=0,"",[2]财务取数接口!$I$76),"")) | P77: =IF(AND($C77<>"",$C77<>"项目",OR(N($D77)<>0,N($E77)<>0,N($F77)<>0)),1,0) -> 0 | Q77: =N(Q76)+$P77 -> 0
A78: 77 | B78: =IF($T$4=0,IF($I78="","",$I78),IFERROR(IF([2]财务取数接口!$B$77=0,"",[2]财务取数接口!$B$77),"")) | C78: =IF($T$4=0,IF($J78="","",$J78),IFERROR(IF([2]财务取数接口!$C$77=0,"",[2]财务取数接口!$C$77),"")) -> 押金退还 | D78: =IF($T$4=0,IF($K78="","",$K78),IFERROR(IF([2]财务取数接口!$D$77=0,"",[2]财务取数接口!$D$77),"")) | E78: =IF($T$4=0,IF($L78="","",$L78),IFERROR(IF([2]财务取数接口!$E$77=0,"",[2]财务取数接口!$E$77),"")) -> 元 | F78: =IF($T$4=0,IF($M78="","",$M78),IFERROR(IF([2]财务取数接口!$G$77=0,"",[2]财务取数接口!$G$77),"")) | G78: =IF($T$4=0,IF($N78="","",$N78),IFERROR(IF([2]财务取数接口!$H$77=0,"",[2]财务取数接口!$H$77),"")) | H78: =IF($T$4=0,IF($O78="","",$O78),IFERROR(IF([2]财务取数接口!$I$77=0,"",[2]财务取数接口!$I$77),"")) | P78: =IF(AND($C78<>"",$C78<>"项目",OR(N($D78)<>0,N($E78)<>0,N($F78)<>0)),1,0) -> 0 | Q78: =N(Q77)+$P78 -> 0
A79: 78 | B79: =IF($T$4=0,IF($I79="","",$I79),IFERROR(IF([2]财务取数接口!$B$78=0,"",[2]财务取数接口!$B$78),"")) | C79: =IF($T$4=0,IF($J79="","",$J79),IFERROR(IF([2]财务取数接口!$C$78=0,"",[2]财务取数接口!$C$78),"")) -> 押金退还 | D79: =IF($T$4=0,IF($K79="","",$K79),IFERROR(IF([2]财务取数接口!$D$78=0,"",[2]财务取数接口!$D$78),"")) | E79: =IF($T$4=0,IF($L79="","",$L79),IFERROR(IF([2]财务取数接口!$E$78=0,"",[2]财务取数接口!$E$78),"")) -> 元 | F79: =IF($T$4=0,IF($M79="","",$M79),IFERROR(IF([2]财务取数接口!$G$78=0,"",[2]财务取数接口!$G$78),"")) | G79: =IF($T$4=0,IF($N79="","",$N79),IFERROR(IF([2]财务取数接口!$H$78=0,"",[2]财务取数接口!$H$78),"")) | H79: =IF($T$4=0,IF($O79="","",$O79),IFERROR(IF([2]财务取数接口!$I$78=0,"",[2]财务取数接口!$I$78),"")) | P79: =IF(AND($C79<>"",$C79<>"项目",OR(N($D79)<>0,N($E79)<>0,N($F79)<>0)),1,0) -> 0 | Q79: =N(Q78)+$P79 -> 0
A80: 79 | B80: =IF($T$4=0,IF($I80="","",$I80),IFERROR(IF([2]财务取数接口!$B$79=0,"",[2]财务取数接口!$B$79),"")) | C80: =IF($T$4=0,IF($J80="","",$J80),IFERROR(IF([2]财务取数接口!$C$79=0,"",[2]财务取数接口!$C$79),"")) -> 押金退还 | D80: =IF($T$4=0,IF($K80="","",$K80),IFERROR(IF([2]财务取数接口!$D$79=0,"",[2]财务取数接口!$D$79),"")) | E80: =IF($T$4=0,IF($L80="","",$L80),IFERROR(IF([2]财务取数接口!$E$79=0,"",[2]财务取数接口!$E$79),"")) -> 元 | F80: =IF($T$4=0,IF($M80="","",$M80),IFERROR(IF([2]财务取数接口!$G$79=0,"",[2]财务取数接口!$G$79),"")) | G80: =IF($T$4=0,IF($N80="","",$N80),IFERROR(IF([2]财务取数接口!$H$79=0,"",[2]财务取数接口!$H$79),"")) | H80: =IF($T$4=0,IF($O80="","",$O80),IFERROR(IF([2]财务取数接口!$I$79=0,"",[2]财务取数接口!$I$79),"")) | P80: =IF(AND($C80<>"",$C80<>"项目",OR(N($D80)<>0,N($E80)<>0,N($F80)<>0)),1,0) -> 0 | Q80: =N(Q79)+$P80 -> 0
A81: 80 | B81: =IF($T$4=0,IF($I81="","",$I81),IFERROR(IF([2]财务取数接口!$B$80=0,"",[2]财务取数接口!$B$80),"")) | C81: =IF($T$4=0,IF($J81="","",$J81),IFERROR(IF([2]财务取数接口!$C$80=0,"",[2]财务取数接口!$C$80),"")) -> 押金退还 | D81: =IF($T$4=0,IF($K81="","",$K81),IFERROR(IF([2]财务取数接口!$D$80=0,"",[2]财务取数接口!$D$80),"")) | E81: =IF($T$4=0,IF($L81="","",$L81),IFERROR(IF([2]财务取数接口!$E$80=0,"",[2]财务取数接口!$E$80),"")) -> 元 | F81: =IF($T$4=0,IF($M81="","",$M81),IFERROR(IF([2]财务取数接口!$G$80=0,"",[2]财务取数接口!$G$80),"")) | G81: =IF($T$4=0,IF($N81="","",$N81),IFERROR(IF([2]财务取数接口!$H$80=0,"",[2]财务取数接口!$H$80),"")) | H81: =IF($T$4=0,IF($O81="","",$O81),IFERROR(IF([2]财务取数接口!$I$80=0,"",[2]财务取数接口!$I$80),"")) | P81: =IF(AND($C81<>"",$C81<>"项目",OR(N($D81)<>0,N($E81)<>0,N($F81)<>0)),1,0) -> 0 | Q81: =N(Q80)+$P81 -> 0
A82: 81 | B82: =IF($T$4=0,IF($I82="","",$I82),IFERROR(IF([2]财务取数接口!$B$81=0,"",[2]财务取数接口!$B$81),"")) | C82: =IF($T$4=0,IF($J82="","",$J82),IFERROR(IF([2]财务取数接口!$C$81=0,"",[2]财务取数接口!$C$81),"")) -> 押金退还 | D82: =IF($T$4=0,IF($K82="","",$K82),IFERROR(IF([2]财务取数接口!$D$81=0,"",[2]财务取数接口!$D$81),"")) | E82: =IF($T$4=0,IF($L82="","",$L82),IFERROR(IF([2]财务取数接口!$E$81=0,"",[2]财务取数接口!$E$81),"")) -> 元 | F82: =IF($T$4=0,IF($M82="","",$M82),IFERROR(IF([2]财务取数接口!$G$81=0,"",[2]财务取数接口!$G$81),"")) | G82: =IF($T$4=0,IF($N82="","",$N82),IFERROR(IF([2]财务取数接口!$H$81=0,"",[2]财务取数接口!$H$81),"")) | H82: =IF($T$4=0,IF($O82="","",$O82),IFERROR(IF([2]财务取数接口!$I$81=0,"",[2]财务取数接口!$I$81),"")) | P82: =IF(AND($C82<>"",$C82<>"项目",OR(N($D82)<>0,N($E82)<>0,N($F82)<>0)),1,0) -> 0 | Q82: =N(Q81)+$P82 -> 0
A83: 82 | B83: =IF($T$4=0,IF($I83="","",$I83),IFERROR(IF([2]财务取数接口!$B$82=0,"",[2]财务取数接口!$B$82),"")) | C83: =IF($T$4=0,IF($J83="","",$J83),IFERROR(IF([2]财务取数接口!$C$82=0,"",[2]财务取数接口!$C$82),"")) -> 押金退还 | D83: =IF($T$4=0,IF($K83="","",$K83),IFERROR(IF([2]财务取数接口!$D$82=0,"",[2]财务取数接口!$D$82),"")) | E83: =IF($T$4=0,IF($L83="","",$L83),IFERROR(IF([2]财务取数接口!$E$82=0,"",[2]财务取数接口!$E$82),"")) -> 元 | F83: =IF($T$4=0,IF($M83="","",$M83),IFERROR(IF([2]财务取数接口!$G$82=0,"",[2]财务取数接口!$G$82),"")) | G83: =IF($T$4=0,IF($N83="","",$N83),IFERROR(IF([2]财务取数接口!$H$82=0,"",[2]财务取数接口!$H$82),"")) | H83: =IF($T$4=0,IF($O83="","",$O83),IFERROR(IF([2]财务取数接口!$I$82=0,"",[2]财务取数接口!$I$82),"")) | P83: =IF(AND($C83<>"",$C83<>"项目",OR(N($D83)<>0,N($E83)<>0,N($F83)<>0)),1,0) -> 0 | Q83: =N(Q82)+$P83 -> 0
A84: 83 | B84: =IF($T$4=0,IF($I84="","",$I84),IFERROR(IF([2]财务取数接口!$B$83=0,"",[2]财务取数接口!$B$83),"")) | C84: =IF($T$4=0,IF($J84="","",$J84),IFERROR(IF([2]财务取数接口!$C$83=0,"",[2]财务取数接口!$C$83),"")) -> 押金退还 | D84: =IF($T$4=0,IF($K84="","",$K84),IFERROR(IF([2]财务取数接口!$D$83=0,"",[2]财务取数接口!$D$83),"")) | E84: =IF($T$4=0,IF($L84="","",$L84),IFERROR(IF([2]财务取数接口!$E$83=0,"",[2]财务取数接口!$E$83),"")) -> 元 | F84: =IF($T$4=0,IF($M84="","",$M84),IFERROR(IF([2]财务取数接口!$G$83=0,"",[2]财务取数接口!$G$83),"")) | G84: =IF($T$4=0,IF($N84="","",$N84),IFERROR(IF([2]财务取数接口!$H$83=0,"",[2]财务取数接口!$H$83),"")) | H84: =IF($T$4=0,IF($O84="","",$O84),IFERROR(IF([2]财务取数接口!$I$83=0,"",[2]财务取数接口!$I$83),"")) | P84: =IF(AND($C84<>"",$C84<>"项目",OR(N($D84)<>0,N($E84)<>0,N($F84)<>0)),1,0) -> 0 | Q84: =N(Q83)+$P84 -> 0
A85: 84 | B85: =IF($T$4=0,IF($I85="","",$I85),IFERROR(IF([2]财务取数接口!$B$84=0,"",[2]财务取数接口!$B$84),"")) | C85: =IF($T$4=0,IF($J85="","",$J85),IFERROR(IF([2]财务取数接口!$C$84=0,"",[2]财务取数接口!$C$84),"")) -> 押金退还 | D85: =IF($T$4=0,IF($K85="","",$K85),IFERROR(IF([2]财务取数接口!$D$84=0,"",[2]财务取数接口!$D$84),"")) | E85: =IF($T$4=0,IF($L85="","",$L85),IFERROR(IF([2]财务取数接口!$E$84=0,"",[2]财务取数接口!$E$84),"")) -> 元 | F85: =IF($T$4=0,IF($M85="","",$M85),IFERROR(IF([2]财务取数接口!$G$84=0,"",[2]财务取数接口!$G$84),"")) | G85: =IF($T$4=0,IF($N85="","",$N85),IFERROR(IF([2]财务取数接口!$H$84=0,"",[2]财务取数接口!$H$84),"")) | H85: =IF($T$4=0,IF($O85="","",$O85),IFERROR(IF([2]财务取数接口!$I$84=0,"",[2]财务取数接口!$I$84),"")) | P85: =IF(AND($C85<>"",$C85<>"项目",OR(N($D85)<>0,N($E85)<>0,N($F85)<>0)),1,0) -> 0 | Q85: =N(Q84)+$P85 -> 0
A86: 85 | B86: =IF($T$4=0,IF($I86="","",$I86),IFERROR(IF([2]财务取数接口!$B$85=0,"",[2]财务取数接口!$B$85),"")) | C86: =IF($T$4=0,IF($J86="","",$J86),IFERROR(IF([2]财务取数接口!$C$85=0,"",[2]财务取数接口!$C$85),"")) -> 押金退还 | D86: =IF($T$4=0,IF($K86="","",$K86),IFERROR(IF([2]财务取数接口!$D$85=0,"",[2]财务取数接口!$D$85),"")) | E86: =IF($T$4=0,IF($L86="","",$L86),IFERROR(IF([2]财务取数接口!$E$85=0,"",[2]财务取数接口!$E$85),"")) -> 元 | F86: =IF($T$4=0,IF($M86="","",$M86),IFERROR(IF([2]财务取数接口!$G$85=0,"",[2]财务取数接口!$G$85),"")) | G86: =IF($T$4=0,IF($N86="","",$N86),IFERROR(IF([2]财务取数接口!$H$85=0,"",[2]财务取数接口!$H$85),"")) | H86: =IF($T$4=0,IF($O86="","",$O86),IFERROR(IF([2]财务取数接口!$I$85=0,"",[2]财务取数接口!$I$85),"")) | P86: =IF(AND($C86<>"",$C86<>"项目",OR(N($D86)<>0,N($E86)<>0,N($F86)<>0)),1,0) -> 0 | Q86: =N(Q85)+$P86 -> 0
A87: 86 | B87: =IF($T$4=0,IF($I87="","",$I87),IFERROR(IF([2]财务取数接口!$B$86=0,"",[2]财务取数接口!$B$86),"")) | C87: =IF($T$4=0,IF($J87="","",$J87),IFERROR(IF([2]财务取数接口!$C$86=0,"",[2]财务取数接口!$C$86),"")) -> 押金退还 | D87: =IF($T$4=0,IF($K87="","",$K87),IFERROR(IF([2]财务取数接口!$D$86=0,"",[2]财务取数接口!$D$86),"")) | E87: =IF($T$4=0,IF($L87="","",$L87),IFERROR(IF([2]财务取数接口!$E$86=0,"",[2]财务取数接口!$E$86),"")) -> 元 | F87: =IF($T$4=0,IF($M87="","",$M87),IFERROR(IF([2]财务取数接口!$G$86=0,"",[2]财务取数接口!$G$86),"")) | G87: =IF($T$4=0,IF($N87="","",$N87),IFERROR(IF([2]财务取数接口!$H$86=0,"",[2]财务取数接口!$H$86),"")) | H87: =IF($T$4=0,IF($O87="","",$O87),IFERROR(IF([2]财务取数接口!$I$86=0,"",[2]财务取数接口!$I$86),"")) | P87: =IF(AND($C87<>"",$C87<>"项目",OR(N($D87)<>0,N($E87)<>0,N($F87)<>0)),1,0) -> 0 | Q87: =N(Q86)+$P87 -> 0
A88: 87 | B88: =IF($T$4=0,IF($I88="","",$I88),IFERROR(IF([2]财务取数接口!$B$87=0,"",[2]财务取数接口!$B$87),"")) | C88: =IF($T$4=0,IF($J88="","",$J88),IFERROR(IF([2]财务取数接口!$C$87=0,"",[2]财务取数接口!$C$87),"")) -> 押金退还 | D88: =IF($T$4=0,IF($K88="","",$K88),IFERROR(IF([2]财务取数接口!$D$87=0,"",[2]财务取数接口!$D$87),"")) | E88: =IF($T$4=0,IF($L88="","",$L88),IFERROR(IF([2]财务取数接口!$E$87=0,"",[2]财务取数接口!$E$87),"")) -> 元 | F88: =IF($T$4=0,IF($M88="","",$M88),IFERROR(IF([2]财务取数接口!$G$87=0,"",[2]财务取数接口!$G$87),"")) | G88: =IF($T$4=0,IF($N88="","",$N88),IFERROR(IF([2]财务取数接口!$H$87=0,"",[2]财务取数接口!$H$87),"")) | H88: =IF($T$4=0,IF($O88="","",$O88),IFERROR(IF([2]财务取数接口!$I$87=0,"",[2]财务取数接口!$I$87),"")) | P88: =IF(AND($C88<>"",$C88<>"项目",OR(N($D88)<>0,N($E88)<>0,N($F88)<>0)),1,0) -> 0 | Q88: =N(Q87)+$P88 -> 0
A89: 88 | B89: =IF($T$4=0,IF($I89="","",$I89),IFERROR(IF([2]财务取数接口!$B$88=0,"",[2]财务取数接口!$B$88),"")) | C89: =IF($T$4=0,IF($J89="","",$J89),IFERROR(IF([2]财务取数接口!$C$88=0,"",[2]财务取数接口!$C$88),"")) -> 押金退还 | D89: =IF($T$4=0,IF($K89="","",$K89),IFERROR(IF([2]财务取数接口!$D$88=0,"",[2]财务取数接口!$D$88),"")) | E89: =IF($T$4=0,IF($L89="","",$L89),IFERROR(IF([2]财务取数接口!$E$88=0,"",[2]财务取数接口!$E$88),"")) -> 元 | F89: =IF($T$4=0,IF($M89="","",$M89),IFERROR(IF([2]财务取数接口!$G$88=0,"",[2]财务取数接口!$G$88),"")) | G89: =IF($T$4=0,IF($N89="","",$N89),IFERROR(IF([2]财务取数接口!$H$88=0,"",[2]财务取数接口!$H$88),"")) | H89: =IF($T$4=0,IF($O89="","",$O89),IFERROR(IF([2]财务取数接口!$I$88=0,"",[2]财务取数接口!$I$88),"")) | P89: =IF(AND($C89<>"",$C89<>"项目",OR(N($D89)<>0,N($E89)<>0,N($F89)<>0)),1,0) -> 0 | Q89: =N(Q88)+$P89 -> 0
A90: 89 | B90: =IF($T$4=0,IF($I90="","",$I90),IFERROR(IF([2]财务取数接口!$B$89=0,"",[2]财务取数接口!$B$89),"")) | C90: =IF($T$4=0,IF($J90="","",$J90),IFERROR(IF([2]财务取数接口!$C$89=0,"",[2]财务取数接口!$C$89),"")) -> 押金退还 | D90: =IF($T$4=0,IF($K90="","",$K90),IFERROR(IF([2]财务取数接口!$D$89=0,"",[2]财务取数接口!$D$89),"")) | E90: =IF($T$4=0,IF($L90="","",$L90),IFERROR(IF([2]财务取数接口!$E$89=0,"",[2]财务取数接口!$E$89),"")) -> 元 | F90: =IF($T$4=0,IF($M90="","",$M90),IFERROR(IF([2]财务取数接口!$G$89=0,"",[2]财务取数接口!$G$89),"")) | G90: =IF($T$4=0,IF($N90="","",$N90),IFERROR(IF([2]财务取数接口!$H$89=0,"",[2]财务取数接口!$H$89),"")) | H90: =IF($T$4=0,IF($O90="","",$O90),IFERROR(IF([2]财务取数接口!$I$89=0,"",[2]财务取数接口!$I$89),"")) | P90: =IF(AND($C90<>"",$C90<>"项目",OR(N($D90)<>0,N($E90)<>0,N($F90)<>0)),1,0) -> 0 | Q90: =N(Q89)+$P90 -> 0
A91: 90 | B91: =IF($T$4=0,IF($I91="","",$I91),IFERROR(IF([2]财务取数接口!$B$90=0,"",[2]财务取数接口!$B$90),"")) | C91: =IF($T$4=0,IF($J91="","",$J91),IFERROR(IF([2]财务取数接口!$C$90=0,"",[2]财务取数接口!$C$90),"")) -> 押金退还 | D91: =IF($T$4=0,IF($K91="","",$K91),IFERROR(IF([2]财务取数接口!$D$90=0,"",[2]财务取数接口!$D$90),"")) | E91: =IF($T$4=0,IF($L91="","",$L91),IFERROR(IF([2]财务取数接口!$E$90=0,"",[2]财务取数接口!$E$90),"")) -> 元 | F91: =IF($T$4=0,IF($M91="","",$M91),IFERROR(IF([2]财务取数接口!$G$90=0,"",[2]财务取数接口!$G$90),"")) | G91: =IF($T$4=0,IF($N91="","",$N91),IFERROR(IF([2]财务取数接口!$H$90=0,"",[2]财务取数接口!$H$90),"")) | H91: =IF($T$4=0,IF($O91="","",$O91),IFERROR(IF([2]财务取数接口!$I$90=0,"",[2]财务取数接口!$I$90),"")) | P91: =IF(AND($C91<>"",$C91<>"项目",OR(N($D91)<>0,N($E91)<>0,N($F91)<>0)),1,0) -> 0 | Q91: =N(Q90)+$P91 -> 0
A92: 91 | B92: =IF($T$4=0,IF($I92="","",$I92),IFERROR(IF([2]财务取数接口!$B$91=0,"",[2]财务取数接口!$B$91),"")) | C92: =IF($T$4=0,IF($J92="","",$J92),IFERROR(IF([2]财务取数接口!$C$91=0,"",[2]财务取数接口!$C$91),"")) -> 押金退还 | D92: =IF($T$4=0,IF($K92="","",$K92),IFERROR(IF([2]财务取数接口!$D$91=0,"",[2]财务取数接口!$D$91),"")) | E92: =IF($T$4=0,IF($L92="","",$L92),IFERROR(IF([2]财务取数接口!$E$91=0,"",[2]财务取数接口!$E$91),"")) -> 元 | F92: =IF($T$4=0,IF($M92="","",$M92),IFERROR(IF([2]财务取数接口!$G$91=0,"",[2]财务取数接口!$G$91),"")) | G92: =IF($T$4=0,IF($N92="","",$N92),IFERROR(IF([2]财务取数接口!$H$91=0,"",[2]财务取数接口!$H$91),"")) | H92: =IF($T$4=0,IF($O92="","",$O92),IFERROR(IF([2]财务取数接口!$I$91=0,"",[2]财务取数接口!$I$91),"")) | P92: =IF(AND($C92<>"",$C92<>"项目",OR(N($D92)<>0,N($E92)<>0,N($F92)<>0)),1,0) -> 0 | Q92: =N(Q91)+$P92 -> 0
A93: 92 | B93: =IF($T$4=0,IF($I93="","",$I93),IFERROR(IF([2]财务取数接口!$B$92=0,"",[2]财务取数接口!$B$92),"")) | C93: =IF($T$4=0,IF($J93="","",$J93),IFERROR(IF([2]财务取数接口!$C$92=0,"",[2]财务取数接口!$C$92),"")) -> 押金退还 | D93: =IF($T$4=0,IF($K93="","",$K93),IFERROR(IF([2]财务取数接口!$D$92=0,"",[2]财务取数接口!$D$92),"")) | E93: =IF($T$4=0,IF($L93="","",$L93),IFERROR(IF([2]财务取数接口!$E$92=0,"",[2]财务取数接口!$E$92),"")) -> 元 | F93: =IF($T$4=0,IF($M93="","",$M93),IFERROR(IF([2]财务取数接口!$G$92=0,"",[2]财务取数接口!$G$92),"")) | G93: =IF($T$4=0,IF($N93="","",$N93),IFERROR(IF([2]财务取数接口!$H$92=0,"",[2]财务取数接口!$H$92),"")) | H93: =IF($T$4=0,IF($O93="","",$O93),IFERROR(IF([2]财务取数接口!$I$92=0,"",[2]财务取数接口!$I$92),"")) | P93: =IF(AND($C93<>"",$C93<>"项目",OR(N($D93)<>0,N($E93)<>0,N($F93)<>0)),1,0) -> 0 | Q93: =N(Q92)+$P93 -> 0
A94: 93 | B94: =IF($T$4=0,IF($I94="","",$I94),IFERROR(IF([2]财务取数接口!$B$93=0,"",[2]财务取数接口!$B$93),"")) | C94: =IF($T$4=0,IF($J94="","",$J94),IFERROR(IF([2]财务取数接口!$C$93=0,"",[2]财务取数接口!$C$93),"")) -> 押金退还 | D94: =IF($T$4=0,IF($K94="","",$K94),IFERROR(IF([2]财务取数接口!$D$93=0,"",[2]财务取数接口!$D$93),"")) | E94: =IF($T$4=0,IF($L94="","",$L94),IFERROR(IF([2]财务取数接口!$E$93=0,"",[2]财务取数接口!$E$93),"")) -> 元 | F94: =IF($T$4=0,IF($M94="","",$M94),IFERROR(IF([2]财务取数接口!$G$93=0,"",[2]财务取数接口!$G$93),"")) | G94: =IF($T$4=0,IF($N94="","",$N94),IFERROR(IF([2]财务取数接口!$H$93=0,"",[2]财务取数接口!$H$93),"")) | H94: =IF($T$4=0,IF($O94="","",$O94),IFERROR(IF([2]财务取数接口!$I$93=0,"",[2]财务取数接口!$I$93),"")) | P94: =IF(AND($C94<>"",$C94<>"项目",OR(N($D94)<>0,N($E94)<>0,N($F94)<>0)),1,0) -> 0 | Q94: =N(Q93)+$P94 -> 0
A95: 94 | B95: =IF($T$4=0,IF($I95="","",$I95),IFERROR(IF([2]财务取数接口!$B$94=0,"",[2]财务取数接口!$B$94),"")) | C95: =IF($T$4=0,IF($J95="","",$J95),IFERROR(IF([2]财务取数接口!$C$94=0,"",[2]财务取数接口!$C$94),"")) -> 押金退还 | D95: =IF($T$4=0,IF($K95="","",$K95),IFERROR(IF([2]财务取数接口!$D$94=0,"",[2]财务取数接口!$D$94),"")) | E95: =IF($T$4=0,IF($L95="","",$L95),IFERROR(IF([2]财务取数接口!$E$94=0,"",[2]财务取数接口!$E$94),"")) -> 元 | F95: =IF($T$4=0,IF($M95="","",$M95),IFERROR(IF([2]财务取数接口!$G$94=0,"",[2]财务取数接口!$G$94),"")) | G95: =IF($T$4=0,IF($N95="","",$N95),IFERROR(IF([2]财务取数接口!$H$94=0,"",[2]财务取数接口!$H$94),"")) | H95: =IF($T$4=0,IF($O95="","",$O95),IFERROR(IF([2]财务取数接口!$I$94=0,"",[2]财务取数接口!$I$94),"")) | P95: =IF(AND($C95<>"",$C95<>"项目",OR(N($D95)<>0,N($E95)<>0,N($F95)<>0)),1,0) -> 0 | Q95: =N(Q94)+$P95 -> 0
A96: 95 | B96: =IF($T$4=0,IF($I96="","",$I96),IFERROR(IF([2]财务取数接口!$B$95=0,"",[2]财务取数接口!$B$95),"")) | C96: =IF($T$4=0,IF($J96="","",$J96),IFERROR(IF([2]财务取数接口!$C$95=0,"",[2]财务取数接口!$C$95),"")) -> 押金退还 | D96: =IF($T$4=0,IF($K96="","",$K96),IFERROR(IF([2]财务取数接口!$D$95=0,"",[2]财务取数接口!$D$95),"")) | E96: =IF($T$4=0,IF($L96="","",$L96),IFERROR(IF([2]财务取数接口!$E$95=0,"",[2]财务取数接口!$E$95),"")) -> 元 | F96: =IF($T$4=0,IF($M96="","",$M96),IFERROR(IF([2]财务取数接口!$G$95=0,"",[2]财务取数接口!$G$95),"")) | G96: =IF($T$4=0,IF($N96="","",$N96),IFERROR(IF([2]财务取数接口!$H$95=0,"",[2]财务取数接口!$H$95),"")) | H96: =IF($T$4=0,IF($O96="","",$O96),IFERROR(IF([2]财务取数接口!$I$95=0,"",[2]财务取数接口!$I$95),"")) | P96: =IF(AND($C96<>"",$C96<>"项目",OR(N($D96)<>0,N($E96)<>0,N($F96)<>0)),1,0) -> 0 | Q96: =N(Q95)+$P96 -> 0
A97: 96 | B97: =IF($T$4=0,IF($I97="","",$I97),IFERROR(IF([2]财务取数接口!$B$96=0,"",[2]财务取数接口!$B$96),"")) | C97: =IF($T$4=0,IF($J97="","",$J97),IFERROR(IF([2]财务取数接口!$C$96=0,"",[2]财务取数接口!$C$96),"")) -> 押金退还 | D97: =IF($T$4=0,IF($K97="","",$K97),IFERROR(IF([2]财务取数接口!$D$96=0,"",[2]财务取数接口!$D$96),"")) | E97: =IF($T$4=0,IF($L97="","",$L97),IFERROR(IF([2]财务取数接口!$E$96=0,"",[2]财务取数接口!$E$96),"")) -> 元 | F97: =IF($T$4=0,IF($M97="","",$M97),IFERROR(IF([2]财务取数接口!$G$96=0,"",[2]财务取数接口!$G$96),"")) | G97: =IF($T$4=0,IF($N97="","",$N97),IFERROR(IF([2]财务取数接口!$H$96=0,"",[2]财务取数接口!$H$96),"")) | H97: =IF($T$4=0,IF($O97="","",$O97),IFERROR(IF([2]财务取数接口!$I$96=0,"",[2]财务取数接口!$I$96),"")) | P97: =IF(AND($C97<>"",$C97<>"项目",OR(N($D97)<>0,N($E97)<>0,N($F97)<>0)),1,0) -> 0 | Q97: =N(Q96)+$P97 -> 0
A98: 97 | B98: =IF($T$4=0,IF($I98="","",$I98),IFERROR(IF([2]财务取数接口!$B$97=0,"",[2]财务取数接口!$B$97),"")) | C98: =IF($T$4=0,IF($J98="","",$J98),IFERROR(IF([2]财务取数接口!$C$97=0,"",[2]财务取数接口!$C$97),"")) -> 押金退还 | D98: =IF($T$4=0,IF($K98="","",$K98),IFERROR(IF([2]财务取数接口!$D$97=0,"",[2]财务取数接口!$D$97),"")) | E98: =IF($T$4=0,IF($L98="","",$L98),IFERROR(IF([2]财务取数接口!$E$97=0,"",[2]财务取数接口!$E$97),"")) -> 元 | F98: =IF($T$4=0,IF($M98="","",$M98),IFERROR(IF([2]财务取数接口!$G$97=0,"",[2]财务取数接口!$G$97),"")) | G98: =IF($T$4=0,IF($N98="","",$N98),IFERROR(IF([2]财务取数接口!$H$97=0,"",[2]财务取数接口!$H$97),"")) | H98: =IF($T$4=0,IF($O98="","",$O98),IFERROR(IF([2]财务取数接口!$I$97=0,"",[2]财务取数接口!$I$97),"")) | P98: =IF(AND($C98<>"",$C98<>"项目",OR(N($D98)<>0,N($E98)<>0,N($F98)<>0)),1,0) -> 0 | Q98: =N(Q97)+$P98 -> 0
A99: 98 | B99: =IF($T$4=0,IF($I99="","",$I99),IFERROR(IF([2]财务取数接口!$B$98=0,"",[2]财务取数接口!$B$98),"")) | C99: =IF($T$4=0,IF($J99="","",$J99),IFERROR(IF([2]财务取数接口!$C$98=0,"",[2]财务取数接口!$C$98),"")) -> 押金退还 | D99: =IF($T$4=0,IF($K99="","",$K99),IFERROR(IF([2]财务取数接口!$D$98=0,"",[2]财务取数接口!$D$98),"")) | E99: =IF($T$4=0,IF($L99="","",$L99),IFERROR(IF([2]财务取数接口!$E$98=0,"",[2]财务取数接口!$E$98),"")) -> 元 | F99: =IF($T$4=0,IF($M99="","",$M99),IFERROR(IF([2]财务取数接口!$G$98=0,"",[2]财务取数接口!$G$98),"")) | G99: =IF($T$4=0,IF($N99="","",$N99),IFERROR(IF([2]财务取数接口!$H$98=0,"",[2]财务取数接口!$H$98),"")) | H99: =IF($T$4=0,IF($O99="","",$O99),IFERROR(IF([2]财务取数接口!$I$98=0,"",[2]财务取数接口!$I$98),"")) | P99: =IF(AND($C99<>"",$C99<>"项目",OR(N($D99)<>0,N($E99)<>0,N($F99)<>0)),1,0) -> 0 | Q99: =N(Q98)+$P99 -> 0
A100: 99 | B100: =IF($T$4=0,IF($I100="","",$I100),IFERROR(IF([2]财务取数接口!$B$99=0,"",[2]财务取数接口!$B$99),"")) | C100: =IF($T$4=0,IF($J100="","",$J100),IFERROR(IF([2]财务取数接口!$C$99=0,"",[2]财务取数接口!$C$99),"")) -> 押金退还 | D100: =IF($T$4=0,IF($K100="","",$K100),IFERROR(IF([2]财务取数接口!$D$99=0,"",[2]财务取数接口!$D$99),"")) | E100: =IF($T$4=0,IF($L100="","",$L100),IFERROR(IF([2]财务取数接口!$E$99=0,"",[2]财务取数接口!$E$99),"")) -> 元 | F100: =IF($T$4=0,IF($M100="","",$M100),IFERROR(IF([2]财务取数接口!$G$99=0,"",[2]财务取数接口!$G$99),"")) | G100: =IF($T$4=0,IF($N100="","",$N100),IFERROR(IF([2]财务取数接口!$H$99=0,"",[2]财务取数接口!$H$99),"")) | H100: =IF($T$4=0,IF($O100="","",$O100),IFERROR(IF([2]财务取数接口!$I$99=0,"",[2]财务取数接口!$I$99),"")) | P100: =IF(AND($C100<>"",$C100<>"项目",OR(N($D100)<>0,N($E100)<>0,N($F100)<>0)),1,0) -> 0 | Q100: =N(Q99)+$P100 -> 0
...

Sheet 对接源_01入库吨位
A1: 对 接 源 · 01 入 库 吨 位（跨文件自动取数 · 断链时自动改用应急备份） | U1: 有效行数 | V1: =MAX($S$5:$S$304) -> 22
A2: =IF($V$4=1,"✔ 链接正常，已自动取到 "&$V$1&" 行 ｜ 本表 1:1 对应《01 水果进销存台账》的【入库吨位汇总】第 4～303 行；筐数已按货权属性拆成「周转打冷」与「仓储加工」两列","★★ 链接没接上！当前取数来源："&$V$5&" → 见 V6 修复说明") -> ✔ 链接正常，已自动取到 22 行 ｜ 本表 1:1 对应《01 水果进销存台账》的【入库吨位汇总】第 4～303 行；筐数已按货权属性拆成「周转打冷」与「仓储加工」两列 | U2: 链接探针 | V2: =IFERROR(IF([1]入库吨位汇总!$B$4=0,"未更新",[1]入库吨位汇总!$B$4),"断开") -> 聂新平
A3: 一、实 际 使 用 值（链接正常＝自动取数；断链自动切到右边备份） | J3: 二、应 急 备 份 区（手工粘贴数值） | R3: 状态 | U3: 备份行数 | V3: =COUNTIF($J$5:$J$304,"?*") -> 0
A4: 源行 | B4: 货主/存放人 | C4: 品种 | D4: 周转打冷入库总筐数 | E4: 仓储加工入库总筐数 | F4: 合计总重KG | G4: 合计吨位 | H4: 周转打冷总重KG | I4: 仓储加工总重KG | J4: 备份-货主 | K4: 备份-品种 | L4: 备份-打冷筐数 | M4: 备份-加工筐数 | N4: 备份-总重 | O4: 备份-吨位 | P4: 备份-打冷重 | Q4: 备份-加工重 | R4: 有效 | S4: 累计 | U4: 链接可用 | V4: =IF(OR($V$2="断开",$V$2="未更新"),0,1) -> 1
A5: 4 | B5: =IF($V$4=0,IF($J5="","",$J5),IFERROR(IF([1]入库吨位汇总!$B$4=0,"",[1]入库吨位汇总!$B$4),"")) -> 聂新平 | C5: =IF($V$4=0,IF($K5="","",$K5),IFERROR(IF([1]入库吨位汇总!$C$4=0,"",[1]入库吨位汇总!$C$4),"")) -> 苹果 | D5: =IF($V$4=0,IF($L5="","",$L5),IFERROR(IF([1]入库吨位汇总!$D$4=0,"",[1]入库吨位汇总!$D$4),"")) -> 1729 | E5: =IF($V$4=0,IF($M5="","",$M5),IFERROR(IF([1]入库吨位汇总!$E$4=0,"",[1]入库吨位汇总!$E$4),"")) | F5: =IF($V$4=0,IF($N5="","",$N5),IFERROR(IF([1]入库吨位汇总!$K$4=0,"",[1]入库吨位汇总!$K$4),"")) -> 37692.2 | G5: =IF($V$4=0,IF($O5="","",$O5),IFERROR(IF([1]入库吨位汇总!$L$4=0,"",[1]入库吨位汇总!$L$4),"")) -> 37.692 | H5: =IF($V$4=0,IF($P5="","",$P5),IFERROR(IF([1]入库吨位汇总!$H$4=0,"",[1]入库吨位汇总!$H$4),"")) -> 37692.2 | I5: =IF($V$4=0,IF($Q5="","",$Q5),IFERROR(IF([1]入库吨位汇总!$I$4=0,"",[1]入库吨位汇总!$I$4),"")) | R5: =IF(AND($B5<>"",$C5<>""),1,0) -> 1 | S5: =N(S4)+$R5 -> 1 | U5: 当前取数来源 | V5: =IF($V$4=1,"自动（跨文件链接）",IF($V$3>0,"应急备份","无数据")) -> 自动（跨文件链接）
A6: 5 | B6: =IF($V$4=0,IF($J6="","",$J6),IFERROR(IF([1]入库吨位汇总!$B$5=0,"",[1]入库吨位汇总!$B$5),"")) -> 王照雪 | C6: =IF($V$4=0,IF($K6="","",$K6),IFERROR(IF([1]入库吨位汇总!$C$5=0,"",[1]入库吨位汇总!$C$5),"")) -> 苹果 | D6: =IF($V$4=0,IF($L6="","",$L6),IFERROR(IF([1]入库吨位汇总!$D$5=0,"",[1]入库吨位汇总!$D$5),"")) -> 2385 | E6: =IF($V$4=0,IF($M6="","",$M6),IFERROR(IF([1]入库吨位汇总!$E$5=0,"",[1]入库吨位汇总!$E$5),"")) | F6: =IF($V$4=0,IF($N6="","",$N6),IFERROR(IF([1]入库吨位汇总!$K$5=0,"",[1]入库吨位汇总!$K$5),"")) -> 41829.5 | G6: =IF($V$4=0,IF($O6="","",$O6),IFERROR(IF([1]入库吨位汇总!$L$5=0,"",[1]入库吨位汇总!$L$5),"")) -> 41.83 | H6: =IF($V$4=0,IF($P6="","",$P6),IFERROR(IF([1]入库吨位汇总!$H$5=0,"",[1]入库吨位汇总!$H$5),"")) -> 41829.5 | I6: =IF($V$4=0,IF($Q6="","",$Q6),IFERROR(IF([1]入库吨位汇总!$I$5=0,"",[1]入库吨位汇总!$I$5),"")) | R6: =IF(AND($B6<>"",$C6<>""),1,0) -> 1 | S6: =N(S5)+$R6 -> 2 | U6: 修复说明 | V6: =IF($V$2="断开","✘ 链接已断开。修复：菜单【数据】→【编辑链接】→【更改源】，重新指向《01_水果进销存台账模板.xlsx》",IF($V$2="未更新","★ 链接还没更新。修复：菜单【数据】→【编辑链接】→【立即更新值】","✔ 链接正常。建议每月底把 B5:I304 复制→选择性粘贴【数值】到 J5 作为兜底")) -> ✔ 链接正常。建议每月底把 B5:I304 复制→选择性粘贴【数值】到 J5 作为兜底
A7: 6 | B7: =IF($V$4=0,IF($J7="","",$J7),IFERROR(IF([1]入库吨位汇总!$B$6=0,"",[1]入库吨位汇总!$B$6),"")) -> 伍元虎 | C7: =IF($V$4=0,IF($K7="","",$K7),IFERROR(IF([1]入库吨位汇总!$C$6=0,"",[1]入库吨位汇总!$C$6),"")) -> 苹果 | D7: =IF($V$4=0,IF($L7="","",$L7),IFERROR(IF([1]入库吨位汇总!$D$6=0,"",[1]入库吨位汇总!$D$6),"")) -> 87 | E7: =IF($V$4=0,IF($M7="","",$M7),IFERROR(IF([1]入库吨位汇总!$E$6=0,"",[1]入库吨位汇总!$E$6),"")) | F7: =IF($V$4=0,IF($N7="","",$N7),IFERROR(IF([1]入库吨位汇总!$K$6=0,"",[1]入库吨位汇总!$K$6),"")) -> 1957.5 | G7: =IF($V$4=0,IF($O7="","",$O7),IFERROR(IF([1]入库吨位汇总!$L$6=0,"",[1]入库吨位汇总!$L$6),"")) -> 1.958 | H7: =IF($V$4=0,IF($P7="","",$P7),IFERROR(IF([1]入库吨位汇总!$H$6=0,"",[1]入库吨位汇总!$H$6),"")) -> 1957.5 | I7: =IF($V$4=0,IF($Q7="","",$Q7),IFERROR(IF([1]入库吨位汇总!$I$6=0,"",[1]入库吨位汇总!$I$6),"")) | R7: =IF(AND($B7<>"",$C7<>""),1,0) -> 1 | S7: =N(S6)+$R7 -> 3
A8: 7 | B8: =IF($V$4=0,IF($J8="","",$J8),IFERROR(IF([1]入库吨位汇总!$B$7=0,"",[1]入库吨位汇总!$B$7),"")) -> 王照雪 | C8: =IF($V$4=0,IF($K8="","",$K8),IFERROR(IF([1]入库吨位汇总!$C$7=0,"",[1]入库吨位汇总!$C$7),"")) -> 李子 | D8: =IF($V$4=0,IF($L8="","",$L8),IFERROR(IF([1]入库吨位汇总!$D$7=0,"",[1]入库吨位汇总!$D$7),"")) -> 422 | E8: =IF($V$4=0,IF($M8="","",$M8),IFERROR(IF([1]入库吨位汇总!$E$7=0,"",[1]入库吨位汇总!$E$7),"")) | F8: =IF($V$4=0,IF($N8="","",$N8),IFERROR(IF([1]入库吨位汇总!$K$7=0,"",[1]入库吨位汇总!$K$7),"")) -> 6878.6 | G8: =IF($V$4=0,IF($O8="","",$O8),IFERROR(IF([1]入库吨位汇总!$L$7=0,"",[1]入库吨位汇总!$L$7),"")) -> 6.879 | H8: =IF($V$4=0,IF($P8="","",$P8),IFERROR(IF([1]入库吨位汇总!$H$7=0,"",[1]入库吨位汇总!$H$7),"")) -> 6878.6 | I8: =IF($V$4=0,IF($Q8="","",$Q8),IFERROR(IF([1]入库吨位汇总!$I$7=0,"",[1]入库吨位汇总!$I$7),"")) | R8: =IF(AND($B8<>"",$C8<>""),1,0) -> 1 | S8: =N(S7)+$R8 -> 4
A9: 8 | B9: =IF($V$4=0,IF($J9="","",$J9),IFERROR(IF([1]入库吨位汇总!$B$8=0,"",[1]入库吨位汇总!$B$8),"")) -> 马锦祥 | C9: =IF($V$4=0,IF($K9="","",$K9),IFERROR(IF([1]入库吨位汇总!$C$8=0,"",[1]入库吨位汇总!$C$8),"")) -> 苹果 | D9: =IF($V$4=0,IF($L9="","",$L9),IFERROR(IF([1]入库吨位汇总!$D$8=0,"",[1]入库吨位汇总!$D$8),"")) -> 68 | E9: =IF($V$4=0,IF($M9="","",$M9),IFERROR(IF([1]入库吨位汇总!$E$8=0,"",[1]入库吨位汇总!$E$8),"")) | F9: =IF($V$4=0,IF($N9="","",$N9),IFERROR(IF([1]入库吨位汇总!$K$8=0,"",[1]入库吨位汇总!$K$8),"")) -> 204 | G9: =IF($V$4=0,IF($O9="","",$O9),IFERROR(IF([1]入库吨位汇总!$L$8=0,"",[1]入库吨位汇总!$L$8),"")) -> 0.204 | H9: =IF($V$4=0,IF($P9="","",$P9),IFERROR(IF([1]入库吨位汇总!$H$8=0,"",[1]入库吨位汇总!$H$8),"")) -> 204 | I9: =IF($V$4=0,IF($Q9="","",$Q9),IFERROR(IF([1]入库吨位汇总!$I$8=0,"",[1]入库吨位汇总!$I$8),"")) | R9: =IF(AND($B9<>"",$C9<>""),1,0) -> 1 | S9: =N(S8)+$R9 -> 5
A10: 9 | B10: =IF($V$4=0,IF($J10="","",$J10),IFERROR(IF([1]入库吨位汇总!$B$9=0,"",[1]入库吨位汇总!$B$9),"")) -> 聂新平 | C10: =IF($V$4=0,IF($K10="","",$K10),IFERROR(IF([1]入库吨位汇总!$C$9=0,"",[1]入库吨位汇总!$C$9),"")) -> 西梅 | D10: =IF($V$4=0,IF($L10="","",$L10),IFERROR(IF([1]入库吨位汇总!$D$9=0,"",[1]入库吨位汇总!$D$9),"")) -> 9692 | E10: =IF($V$4=0,IF($M10="","",$M10),IFERROR(IF([1]入库吨位汇总!$E$9=0,"",[1]入库吨位汇总!$E$9),"")) | F10: =IF($V$4=0,IF($N10="","",$N10),IFERROR(IF([1]入库吨位汇总!$K$9=0,"",[1]入库吨位汇总!$K$9),"")) -> 35336 | G10: =IF($V$4=0,IF($O10="","",$O10),IFERROR(IF([1]入库吨位汇总!$L$9=0,"",[1]入库吨位汇总!$L$9),"")) -> 35.336 | H10: =IF($V$4=0,IF($P10="","",$P10),IFERROR(IF([1]入库吨位汇总!$H$9=0,"",[1]入库吨位汇总!$H$9),"")) -> 35336 | I10: =IF($V$4=0,IF($Q10="","",$Q10),IFERROR(IF([1]入库吨位汇总!$I$9=0,"",[1]入库吨位汇总!$I$9),"")) | R10: =IF(AND($B10<>"",$C10<>""),1,0) -> 1 | S10: =N(S9)+$R10 -> 6
A11: 10 | B11: =IF($V$4=0,IF($J11="","",$J11),IFERROR(IF([1]入库吨位汇总!$B$10=0,"",[1]入库吨位汇总!$B$10),"")) -> 马锦祥 | C11: =IF($V$4=0,IF($K11="","",$K11),IFERROR(IF([1]入库吨位汇总!$C$10=0,"",[1]入库吨位汇总!$C$10),"")) -> 香梨 | D11: =IF($V$4=0,IF($L11="","",$L11),IFERROR(IF([1]入库吨位汇总!$D$10=0,"",[1]入库吨位汇总!$D$10),"")) | E11: =IF($V$4=0,IF($M11="","",$M11),IFERROR(IF([1]入库吨位汇总!$E$10=0,"",[1]入库吨位汇总!$E$10),"")) -> 2491 | F11: =IF($V$4=0,IF($N11="","",$N11),IFERROR(IF([1]入库吨位汇总!$K$10=0,"",[1]入库吨位汇总!$K$10),"")) -> 47129.3 | G11: =IF($V$4=0,IF($O11="","",$O11),IFERROR(IF([1]入库吨位汇总!$L$10=0,"",[1]入库吨位汇总!$L$10),"")) -> 47.129 | H11: =IF($V$4=0,IF($P11="","",$P11),IFERROR(IF([1]入库吨位汇总!$H$10=0,"",[1]入库吨位汇总!$H$10),"")) | I11: =IF($V$4=0,IF($Q11="","",$Q11),IFERROR(IF([1]入库吨位汇总!$I$10=0,"",[1]入库吨位汇总!$I$10),"")) -> 47129.3 | R11: =IF(AND($B11<>"",$C11<>""),1,0) -> 1 | S11: =N(S10)+$R11 -> 7
A12: 11 | B12: =IF($V$4=0,IF($J12="","",$J12),IFERROR(IF([1]入库吨位汇总!$B$11=0,"",[1]入库吨位汇总!$B$11),"")) -> 麦麦提 | C12: =IF($V$4=0,IF($K12="","",$K12),IFERROR(IF([1]入库吨位汇总!$C$11=0,"",[1]入库吨位汇总!$C$11),"")) -> 香梨 | D12: =IF($V$4=0,IF($L12="","",$L12),IFERROR(IF([1]入库吨位汇总!$D$11=0,"",[1]入库吨位汇总!$D$11),"")) | E12: =IF($V$4=0,IF($M12="","",$M12),IFERROR(IF([1]入库吨位汇总!$E$11=0,"",[1]入库吨位汇总!$E$11),"")) -> 3790 | F12: =IF($V$4=0,IF($N12="","",$N12),IFERROR(IF([1]入库吨位汇总!$K$11=0,"",[1]入库吨位汇总!$K$11),"")) -> 73453 | G12: =IF($V$4=0,IF($O12="","",$O12),IFERROR(IF([1]入库吨位汇总!$L$11=0,"",[1]入库吨位汇总!$L$11),"")) -> 73.453 | H12: =IF($V$4=0,IF($P12="","",$P12),IFERROR(IF([1]入库吨位汇总!$H$11=0,"",[1]入库吨位汇总!$H$11),"")) | I12: =IF($V$4=0,IF($Q12="","",$Q12),IFERROR(IF([1]入库吨位汇总!$I$11=0,"",[1]入库吨位汇总!$I$11),"")) -> 73453 | R12: =IF(AND($B12<>"",$C12<>""),1,0) -> 1 | S12: =N(S11)+$R12 -> 8
A13: 12 | B13: =IF($V$4=0,IF($J13="","",$J13),IFERROR(IF([1]入库吨位汇总!$B$12=0,"",[1]入库吨位汇总!$B$12),"")) -> 吐尔洪 | C13: =IF($V$4=0,IF($K13="","",$K13),IFERROR(IF([1]入库吨位汇总!$C$12=0,"",[1]入库吨位汇总!$C$12),"")) -> 香梨 | D13: =IF($V$4=0,IF($L13="","",$L13),IFERROR(IF([1]入库吨位汇总!$D$12=0,"",[1]入库吨位汇总!$D$12),"")) | E13: =IF($V$4=0,IF($M13="","",$M13),IFERROR(IF([1]入库吨位汇总!$E$12=0,"",[1]入库吨位汇总!$E$12),"")) -> 1832 | F13: =IF($V$4=0,IF($N13="","",$N13),IFERROR(IF([1]入库吨位汇总!$K$12=0,"",[1]入库吨位汇总!$K$12),"")) -> 36145.6 | G13: =IF($V$4=0,IF($O13="","",$O13),IFERROR(IF([1]入库吨位汇总!$L$12=0,"",[1]入库吨位汇总!$L$12),"")) -> 36.146 | H13: =IF($V$4=0,IF($P13="","",$P13),IFERROR(IF([1]入库吨位汇总!$H$12=0,"",[1]入库吨位汇总!$H$12),"")) | I13: =IF($V$4=0,IF($Q13="","",$Q13),IFERROR(IF([1]入库吨位汇总!$I$12=0,"",[1]入库吨位汇总!$I$12),"")) -> 36145.6 | R13: =IF(AND($B13<>"",$C13<>""),1,0) -> 1 | S13: =N(S12)+$R13 -> 9
A14: 13 | B14: =IF($V$4=0,IF($J14="","",$J14),IFERROR(IF([1]入库吨位汇总!$B$13=0,"",[1]入库吨位汇总!$B$13),"")) -> 热合曼 | C14: =IF($V$4=0,IF($K14="","",$K14),IFERROR(IF([1]入库吨位汇总!$C$13=0,"",[1]入库吨位汇总!$C$13),"")) -> 香梨 | D14: =IF($V$4=0,IF($L14="","",$L14),IFERROR(IF([1]入库吨位汇总!$D$13=0,"",[1]入库吨位汇总!$D$13),"")) | E14: =IF($V$4=0,IF($M14="","",$M14),IFERROR(IF([1]入库吨位汇总!$E$13=0,"",[1]入库吨位汇总!$E$13),"")) -> 1521 | F14: =IF($V$4=0,IF($N14="","",$N14),IFERROR(IF([1]入库吨位汇总!$K$13=0,"",[1]入库吨位汇总!$K$13),"")) -> 29445.3 | G14: =IF($V$4=0,IF($O14="","",$O14),IFERROR(IF([1]入库吨位汇总!$L$13=0,"",[1]入库吨位汇总!$L$13),"")) -> 29.445 | H14: =IF($V$4=0,IF($P14="","",$P14),IFERROR(IF([1]入库吨位汇总!$H$13=0,"",[1]入库吨位汇总!$H$13),"")) | I14: =IF($V$4=0,IF($Q14="","",$Q14),IFERROR(IF([1]入库吨位汇总!$I$13=0,"",[1]入库吨位汇总!$I$13),"")) -> 29445.3 | R14: =IF(AND($B14<>"",$C14<>""),1,0) -> 1 | S14: =N(S13)+$R14 -> 10
A15: 14 | B15: =IF($V$4=0,IF($J15="","",$J15),IFERROR(IF([1]入库吨位汇总!$B$14=0,"",[1]入库吨位汇总!$B$14),"")) -> 贾建国 | C15: =IF($V$4=0,IF($K15="","",$K15),IFERROR(IF([1]入库吨位汇总!$C$14=0,"",[1]入库吨位汇总!$C$14),"")) -> 香梨 | D15: =IF($V$4=0,IF($L15="","",$L15),IFERROR(IF([1]入库吨位汇总!$D$14=0,"",[1]入库吨位汇总!$D$14),"")) | E15: =IF($V$4=0,IF($M15="","",$M15),IFERROR(IF([1]入库吨位汇总!$E$14=0,"",[1]入库吨位汇总!$E$14),"")) -> 1390 | F15: =IF($V$4=0,IF($N15="","",$N15),IFERROR(IF([1]入库吨位汇总!$K$14=0,"",[1]入库吨位汇总!$K$14),"")) -> 28596.6 | G15: =IF($V$4=0,IF($O15="","",$O15),IFERROR(IF([1]入库吨位汇总!$L$14=0,"",[1]入库吨位汇总!$L$14),"")) -> 28.597 | H15: =IF($V$4=0,IF($P15="","",$P15),IFERROR(IF([1]入库吨位汇总!$H$14=0,"",[1]入库吨位汇总!$H$14),"")) | I15: =IF($V$4=0,IF($Q15="","",$Q15),IFERROR(IF([1]入库吨位汇总!$I$14=0,"",[1]入库吨位汇总!$I$14),"")) -> 28596.6 | R15: =IF(AND($B15<>"",$C15<>""),1,0) -> 1 | S15: =N(S14)+$R15 -> 11
A16: 15 | B16: =IF($V$4=0,IF($J16="","",$J16),IFERROR(IF([1]入库吨位汇总!$B$15=0,"",[1]入库吨位汇总!$B$15),"")) -> 王灵云 | C16: =IF($V$4=0,IF($K16="","",$K16),IFERROR(IF([1]入库吨位汇总!$C$15=0,"",[1]入库吨位汇总!$C$15),"")) -> 香梨 | D16: =IF($V$4=0,IF($L16="","",$L16),IFERROR(IF([1]入库吨位汇总!$D$15=0,"",[1]入库吨位汇总!$D$15),"")) -> 4214 | E16: =IF($V$4=0,IF($M16="","",$M16),IFERROR(IF([1]入库吨位汇总!$E$15=0,"",[1]入库吨位汇总!$E$15),"")) | F16: =IF($V$4=0,IF($N16="","",$N16),IFERROR(IF([1]入库吨位汇总!$K$15=0,"",[1]入库吨位汇总!$K$15),"")) -> 79231.2 | G16: =IF($V$4=0,IF($O16="","",$O16),IFERROR(IF([1]入库吨位汇总!$L$15=0,"",[1]入库吨位汇总!$L$15),"")) -> 79.231 | H16: =IF($V$4=0,IF($P16="","",$P16),IFERROR(IF([1]入库吨位汇总!$H$15=0,"",[1]入库吨位汇总!$H$15),"")) -> 79231.2 | I16: =IF($V$4=0,IF($Q16="","",$Q16),IFERROR(IF([1]入库吨位汇总!$I$15=0,"",[1]入库吨位汇总!$I$15),"")) | R16: =IF(AND($B16<>"",$C16<>""),1,0) -> 1 | S16: =N(S15)+$R16 -> 12
A17: 16 | B17: =IF($V$4=0,IF($J17="","",$J17),IFERROR(IF([1]入库吨位汇总!$B$16=0,"",[1]入库吨位汇总!$B$16),"")) -> 杨艳玲 | C17: =IF($V$4=0,IF($K17="","",$K17),IFERROR(IF([1]入库吨位汇总!$C$16=0,"",[1]入库吨位汇总!$C$16),"")) -> 香梨 | D17: =IF($V$4=0,IF($L17="","",$L17),IFERROR(IF([1]入库吨位汇总!$D$16=0,"",[1]入库吨位汇总!$D$16),"")) -> 104 | E17: =IF($V$4=0,IF($M17="","",$M17),IFERROR(IF([1]入库吨位汇总!$E$16=0,"",[1]入库吨位汇总!$E$16),"")) | F17: =IF($V$4=0,IF($N17="","",$N17),IFERROR(IF([1]入库吨位汇总!$K$16=0,"",[1]入库吨位汇总!$K$16),"")) -> 1799.2 | G17: =IF($V$4=0,IF($O17="","",$O17),IFERROR(IF([1]入库吨位汇总!$L$16=0,"",[1]入库吨位汇总!$L$16),"")) -> 1.799 | H17: =IF($V$4=0,IF($P17="","",$P17),IFERROR(IF([1]入库吨位汇总!$H$16=0,"",[1]入库吨位汇总!$H$16),"")) -> 1799.2 | I17: =IF($V$4=0,IF($Q17="","",$Q17),IFERROR(IF([1]入库吨位汇总!$I$16=0,"",[1]入库吨位汇总!$I$16),"")) | R17: =IF(AND($B17<>"",$C17<>""),1,0) -> 1 | S17: =N(S16)+$R17 -> 13
A18: 17 | B18: =IF($V$4=0,IF($J18="","",$J18),IFERROR(IF([1]入库吨位汇总!$B$17=0,"",[1]入库吨位汇总!$B$17),"")) -> 荆建君 | C18: =IF($V$4=0,IF($K18="","",$K18),IFERROR(IF([1]入库吨位汇总!$C$17=0,"",[1]入库吨位汇总!$C$17),"")) -> 香梨 | D18: =IF($V$4=0,IF($L18="","",$L18),IFERROR(IF([1]入库吨位汇总!$D$17=0,"",[1]入库吨位汇总!$D$17),"")) | E18: =IF($V$4=0,IF($M18="","",$M18),IFERROR(IF([1]入库吨位汇总!$E$17=0,"",[1]入库吨位汇总!$E$17),"")) -> 1864 | F18: =IF($V$4=0,IF($N18="","",$N18),IFERROR(IF([1]入库吨位汇总!$K$17=0,"",[1]入库吨位汇总!$K$17),"")) -> 34111.2 | G18: =IF($V$4=0,IF($O18="","",$O18),IFERROR(IF([1]入库吨位汇总!$L$17=0,"",[1]入库吨位汇总!$L$17),"")) -> 34.111 | H18: =IF($V$4=0,IF($P18="","",$P18),IFERROR(IF([1]入库吨位汇总!$H$17=0,"",[1]入库吨位汇总!$H$17),"")) | I18: =IF($V$4=0,IF($Q18="","",$Q18),IFERROR(IF([1]入库吨位汇总!$I$17=0,"",[1]入库吨位汇总!$I$17),"")) -> 34111.2 | R18: =IF(AND($B18<>"",$C18<>""),1,0) -> 1 | S18: =N(S17)+$R18 -> 14
A19: 18 | B19: =IF($V$4=0,IF($J19="","",$J19),IFERROR(IF([1]入库吨位汇总!$B$18=0,"",[1]入库吨位汇总!$B$18),"")) -> 王照雪 | C19: =IF($V$4=0,IF($K19="","",$K19),IFERROR(IF([1]入库吨位汇总!$C$18=0,"",[1]入库吨位汇总!$C$18),"")) -> 香梨 | D19: =IF($V$4=0,IF($L19="","",$L19),IFERROR(IF([1]入库吨位汇总!$D$18=0,"",[1]入库吨位汇总!$D$18),"")) | E19: =IF($V$4=0,IF($M19="","",$M19),IFERROR(IF([1]入库吨位汇总!$E$18=0,"",[1]入库吨位汇总!$E$18),"")) -> 852 | F19: =IF($V$4=0,IF($N19="","",$N19),IFERROR(IF([1]入库吨位汇总!$K$18=0,"",[1]入库吨位汇总!$K$18),"")) -> 16247 | G19: =IF($V$4=0,IF($O19="","",$O19),IFERROR(IF([1]入库吨位汇总!$L$18=0,"",[1]入库吨位汇总!$L$18),"")) -> 16.247 | H19: =IF($V$4=0,IF($P19="","",$P19),IFERROR(IF([1]入库吨位汇总!$H$18=0,"",[1]入库吨位汇总!$H$18),"")) | I19: =IF($V$4=0,IF($Q19="","",$Q19),IFERROR(IF([1]入库吨位汇总!$I$18=0,"",[1]入库吨位汇总!$I$18),"")) -> 16247 | R19: =IF(AND($B19<>"",$C19<>""),1,0) -> 1 | S19: =N(S18)+$R19 -> 15
A20: 19 | B20: =IF($V$4=0,IF($J20="","",$J20),IFERROR(IF([1]入库吨位汇总!$B$19=0,"",[1]入库吨位汇总!$B$19),"")) -> 努尔敦 | C20: =IF($V$4=0,IF($K20="","",$K20),IFERROR(IF([1]入库吨位汇总!$C$19=0,"",[1]入库吨位汇总!$C$19),"")) -> 香梨 | D20: =IF($V$4=0,IF($L20="","",$L20),IFERROR(IF([1]入库吨位汇总!$D$19=0,"",[1]入库吨位汇总!$D$19),"")) | E20: =IF($V$4=0,IF($M20="","",$M20),IFERROR(IF([1]入库吨位汇总!$E$19=0,"",[1]入库吨位汇总!$E$19),"")) -> 3223 | F20: =IF($V$4=0,IF($N20="","",$N20),IFERROR(IF([1]入库吨位汇总!$K$19=0,"",[1]入库吨位汇总!$K$19),"")) -> 62388.9 | G20: =IF($V$4=0,IF($O20="","",$O20),IFERROR(IF([1]入库吨位汇总!$L$19=0,"",[1]入库吨位汇总!$L$19),"")) -> 62.389 | H20: =IF($V$4=0,IF($P20="","",$P20),IFERROR(IF([1]入库吨位汇总!$H$19=0,"",[1]入库吨位汇总!$H$19),"")) | I20: =IF($V$4=0,IF($Q20="","",$Q20),IFERROR(IF([1]入库吨位汇总!$I$19=0,"",[1]入库吨位汇总!$I$19),"")) -> 62388.9 | R20: =IF(AND($B20<>"",$C20<>""),1,0) -> 1 | S20: =N(S19)+$R20 -> 16
A21: 20 | B21: =IF($V$4=0,IF($J21="","",$J21),IFERROR(IF([1]入库吨位汇总!$B$20=0,"",[1]入库吨位汇总!$B$20),"")) -> 王浩 | C21: =IF($V$4=0,IF($K21="","",$K21),IFERROR(IF([1]入库吨位汇总!$C$20=0,"",[1]入库吨位汇总!$C$20),"")) -> 香梨 | D21: =IF($V$4=0,IF($L21="","",$L21),IFERROR(IF([1]入库吨位汇总!$D$20=0,"",[1]入库吨位汇总!$D$20),"")) | E21: =IF($V$4=0,IF($M21="","",$M21),IFERROR(IF([1]入库吨位汇总!$E$20=0,"",[1]入库吨位汇总!$E$20),"")) -> 1184 | F21: =IF($V$4=0,IF($N21="","",$N21),IFERROR(IF([1]入库吨位汇总!$K$20=0,"",[1]入库吨位汇总!$K$20),"")) -> 21667.2 | G21: =IF($V$4=0,IF($O21="","",$O21),IFERROR(IF([1]入库吨位汇总!$L$20=0,"",[1]入库吨位汇总!$L$20),"")) -> 21.667 | H21: =IF($V$4=0,IF($P21="","",$P21),IFERROR(IF([1]入库吨位汇总!$H$20=0,"",[1]入库吨位汇总!$H$20),"")) | I21: =IF($V$4=0,IF($Q21="","",$Q21),IFERROR(IF([1]入库吨位汇总!$I$20=0,"",[1]入库吨位汇总!$I$20),"")) -> 21667.2 | R21: =IF(AND($B21<>"",$C21<>""),1,0) -> 1 | S21: =N(S20)+$R21 -> 17
A22: 21 | B22: =IF($V$4=0,IF($J22="","",$J22),IFERROR(IF([1]入库吨位汇总!$B$21=0,"",[1]入库吨位汇总!$B$21),"")) -> 热合曼+艾则孜 | C22: =IF($V$4=0,IF($K22="","",$K22),IFERROR(IF([1]入库吨位汇总!$C$21=0,"",[1]入库吨位汇总!$C$21),"")) -> 香梨 | D22: =IF($V$4=0,IF($L22="","",$L22),IFERROR(IF([1]入库吨位汇总!$D$21=0,"",[1]入库吨位汇总!$D$21),"")) | E22: =IF($V$4=0,IF($M22="","",$M22),IFERROR(IF([1]入库吨位汇总!$E$21=0,"",[1]入库吨位汇总!$E$21),"")) -> 500 | F22: =IF($V$4=0,IF($N22="","",$N22),IFERROR(IF([1]入库吨位汇总!$K$21=0,"",[1]入库吨位汇总!$K$21),"")) -> 9674 | G22: =IF($V$4=0,IF($O22="","",$O22),IFERROR(IF([1]入库吨位汇总!$L$21=0,"",[1]入库吨位汇总!$L$21),"")) -> 9.674 | H22: =IF($V$4=0,IF($P22="","",$P22),IFERROR(IF([1]入库吨位汇总!$H$21=0,"",[1]入库吨位汇总!$H$21),"")) | I22: =IF($V$4=0,IF($Q22="","",$Q22),IFERROR(IF([1]入库吨位汇总!$I$21=0,"",[1]入库吨位汇总!$I$21),"")) -> 9674 | R22: =IF(AND($B22<>"",$C22<>""),1,0) -> 1 | S22: =N(S21)+$R22 -> 18
A23: 22 | B23: =IF($V$4=0,IF($J23="","",$J23),IFERROR(IF([1]入库吨位汇总!$B$22=0,"",[1]入库吨位汇总!$B$22),"")) -> 李现东 | C23: =IF($V$4=0,IF($K23="","",$K23),IFERROR(IF([1]入库吨位汇总!$C$22=0,"",[1]入库吨位汇总!$C$22),"")) -> 香梨 | D23: =IF($V$4=0,IF($L23="","",$L23),IFERROR(IF([1]入库吨位汇总!$D$22=0,"",[1]入库吨位汇总!$D$22),"")) | E23: =IF($V$4=0,IF($M23="","",$M23),IFERROR(IF([1]入库吨位汇总!$E$22=0,"",[1]入库吨位汇总!$E$22),"")) -> 469 | F23: =IF($V$4=0,IF($N23="","",$N23),IFERROR(IF([1]入库吨位汇总!$K$22=0,"",[1]入库吨位汇总!$K$22),"")) -> 8994.7 | G23: =IF($V$4=0,IF($O23="","",$O23),IFERROR(IF([1]入库吨位汇总!$L$22=0,"",[1]入库吨位汇总!$L$22),"")) -> 8.995 | H23: =IF($V$4=0,IF($P23="","",$P23),IFERROR(IF([1]入库吨位汇总!$H$22=0,"",[1]入库吨位汇总!$H$22),"")) | I23: =IF($V$4=0,IF($Q23="","",$Q23),IFERROR(IF([1]入库吨位汇总!$I$22=0,"",[1]入库吨位汇总!$I$22),"")) -> 8994.7 | R23: =IF(AND($B23<>"",$C23<>""),1,0) -> 1 | S23: =N(S22)+$R23 -> 19
A24: 23 | B24: =IF($V$4=0,IF($J24="","",$J24),IFERROR(IF([1]入库吨位汇总!$B$23=0,"",[1]入库吨位汇总!$B$23),"")) -> 吐尔逊 | C24: =IF($V$4=0,IF($K24="","",$K24),IFERROR(IF([1]入库吨位汇总!$C$23=0,"",[1]入库吨位汇总!$C$23),"")) -> 香梨 | D24: =IF($V$4=0,IF($L24="","",$L24),IFERROR(IF([1]入库吨位汇总!$D$23=0,"",[1]入库吨位汇总!$D$23),"")) | E24: =IF($V$4=0,IF($M24="","",$M24),IFERROR(IF([1]入库吨位汇总!$E$23=0,"",[1]入库吨位汇总!$E$23),"")) -> 200 | F24: =IF($V$4=0,IF($N24="","",$N24),IFERROR(IF([1]入库吨位汇总!$K$23=0,"",[1]入库吨位汇总!$K$23),"")) -> 4200 | G24: =IF($V$4=0,IF($O24="","",$O24),IFERROR(IF([1]入库吨位汇总!$L$23=0,"",[1]入库吨位汇总!$L$23),"")) -> 4.2 | H24: =IF($V$4=0,IF($P24="","",$P24),IFERROR(IF([1]入库吨位汇总!$H$23=0,"",[1]入库吨位汇总!$H$23),"")) | I24: =IF($V$4=0,IF($Q24="","",$Q24),IFERROR(IF([1]入库吨位汇总!$I$23=0,"",[1]入库吨位汇总!$I$23),"")) -> 4200 | R24: =IF(AND($B24<>"",$C24<>""),1,0) -> 1 | S24: =N(S23)+$R24 -> 20
A25: 24 | B25: =IF($V$4=0,IF($J25="","",$J25),IFERROR(IF([1]入库吨位汇总!$B$24=0,"",[1]入库吨位汇总!$B$24),"")) -> 阿布都 | C25: =IF($V$4=0,IF($K25="","",$K25),IFERROR(IF([1]入库吨位汇总!$C$24=0,"",[1]入库吨位汇总!$C$24),"")) -> 香梨 | D25: =IF($V$4=0,IF($L25="","",$L25),IFERROR(IF([1]入库吨位汇总!$D$24=0,"",[1]入库吨位汇总!$D$24),"")) | E25: =IF($V$4=0,IF($M25="","",$M25),IFERROR(IF([1]入库吨位汇总!$E$24=0,"",[1]入库吨位汇总!$E$24),"")) -> 315 | F25: =IF($V$4=0,IF($N25="","",$N25),IFERROR(IF([1]入库吨位汇总!$K$24=0,"",[1]入库吨位汇总!$K$24),"")) -> 5972.5 | G25: =IF($V$4=0,IF($O25="","",$O25),IFERROR(IF([1]入库吨位汇总!$L$24=0,"",[1]入库吨位汇总!$L$24),"")) -> 5.973 | H25: =IF($V$4=0,IF($P25="","",$P25),IFERROR(IF([1]入库吨位汇总!$H$24=0,"",[1]入库吨位汇总!$H$24),"")) | I25: =IF($V$4=0,IF($Q25="","",$Q25),IFERROR(IF([1]入库吨位汇总!$I$24=0,"",[1]入库吨位汇总!$I$24),"")) -> 5972.5 | R25: =IF(AND($B25<>"",$C25<>""),1,0) -> 1 | S25: =N(S24)+$R25 -> 21
A26: 25 | B26: =IF($V$4=0,IF($J26="","",$J26),IFERROR(IF([1]入库吨位汇总!$B$25=0,"",[1]入库吨位汇总!$B$25),"")) -> 艾则孜 | C26: =IF($V$4=0,IF($K26="","",$K26),IFERROR(IF([1]入库吨位汇总!$C$25=0,"",[1]入库吨位汇总!$C$25),"")) -> 香梨 | D26: =IF($V$4=0,IF($L26="","",$L26),IFERROR(IF([1]入库吨位汇总!$D$25=0,"",[1]入库吨位汇总!$D$25),"")) | E26: =IF($V$4=0,IF($M26="","",$M26),IFERROR(IF([1]入库吨位汇总!$E$25=0,"",[1]入库吨位汇总!$E$25),"")) -> 538 | F26: =IF($V$4=0,IF($N26="","",$N26),IFERROR(IF([1]入库吨位汇总!$K$25=0,"",[1]入库吨位汇总!$K$25),"")) -> 10647.4 | G26: =IF($V$4=0,IF($O26="","",$O26),IFERROR(IF([1]入库吨位汇总!$L$25=0,"",[1]入库吨位汇总!$L$25),"")) -> 10.647 | H26: =IF($V$4=0,IF($P26="","",$P26),IFERROR(IF([1]入库吨位汇总!$H$25=0,"",[1]入库吨位汇总!$H$25),"")) | I26: =IF($V$4=0,IF($Q26="","",$Q26),IFERROR(IF([1]入库吨位汇总!$I$25=0,"",[1]入库吨位汇总!$I$25),"")) -> 10647.4 | R26: =IF(AND($B26<>"",$C26<>""),1,0) -> 1 | S26: =N(S25)+$R26 -> 22
A27: 26 | B27: =IF($V$4=0,IF($J27="","",$J27),IFERROR(IF([1]入库吨位汇总!$B$26=0,"",[1]入库吨位汇总!$B$26),"")) | C27: =IF($V$4=0,IF($K27="","",$K27),IFERROR(IF([1]入库吨位汇总!$C$26=0,"",[1]入库吨位汇总!$C$26),"")) | D27: =IF($V$4=0,IF($L27="","",$L27),IFERROR(IF([1]入库吨位汇总!$D$26=0,"",[1]入库吨位汇总!$D$26),"")) | E27: =IF($V$4=0,IF($M27="","",$M27),IFERROR(IF([1]入库吨位汇总!$E$26=0,"",[1]入库吨位汇总!$E$26),"")) | F27: =IF($V$4=0,IF($N27="","",$N27),IFERROR(IF([1]入库吨位汇总!$K$26=0,"",[1]入库吨位汇总!$K$26),"")) | G27: =IF($V$4=0,IF($O27="","",$O27),IFERROR(IF([1]入库吨位汇总!$L$26=0,"",[1]入库吨位汇总!$L$26),"")) | H27: =IF($V$4=0,IF($P27="","",$P27),IFERROR(IF([1]入库吨位汇总!$H$26=0,"",[1]入库吨位汇总!$H$26),"")) | I27: =IF($V$4=0,IF($Q27="","",$Q27),IFERROR(IF([1]入库吨位汇总!$I$26=0,"",[1]入库吨位汇总!$I$26),"")) | R27: =IF(AND($B27<>"",$C27<>""),1,0) -> 0 | S27: =N(S26)+$R27 -> 22
A28: 27 | B28: =IF($V$4=0,IF($J28="","",$J28),IFERROR(IF([1]入库吨位汇总!$B$27=0,"",[1]入库吨位汇总!$B$27),"")) | C28: =IF($V$4=0,IF($K28="","",$K28),IFERROR(IF([1]入库吨位汇总!$C$27=0,"",[1]入库吨位汇总!$C$27),"")) | D28: =IF($V$4=0,IF($L28="","",$L28),IFERROR(IF([1]入库吨位汇总!$D$27=0,"",[1]入库吨位汇总!$D$27),"")) | E28: =IF($V$4=0,IF($M28="","",$M28),IFERROR(IF([1]入库吨位汇总!$E$27=0,"",[1]入库吨位汇总!$E$27),"")) | F28: =IF($V$4=0,IF($N28="","",$N28),IFERROR(IF([1]入库吨位汇总!$K$27=0,"",[1]入库吨位汇总!$K$27),"")) | G28: =IF($V$4=0,IF($O28="","",$O28),IFERROR(IF([1]入库吨位汇总!$L$27=0,"",[1]入库吨位汇总!$L$27),"")) | H28: =IF($V$4=0,IF($P28="","",$P28),IFERROR(IF([1]入库吨位汇总!$H$27=0,"",[1]入库吨位汇总!$H$27),"")) | I28: =IF($V$4=0,IF($Q28="","",$Q28),IFERROR(IF([1]入库吨位汇总!$I$27=0,"",[1]入库吨位汇总!$I$27),"")) | R28: =IF(AND($B28<>"",$C28<>""),1,0) -> 0 | S28: =N(S27)+$R28 -> 22
A29: 28 | B29: =IF($V$4=0,IF($J29="","",$J29),IFERROR(IF([1]入库吨位汇总!$B$28=0,"",[1]入库吨位汇总!$B$28),"")) | C29: =IF($V$4=0,IF($K29="","",$K29),IFERROR(IF([1]入库吨位汇总!$C$28=0,"",[1]入库吨位汇总!$C$28),"")) | D29: =IF($V$4=0,IF($L29="","",$L29),IFERROR(IF([1]入库吨位汇总!$D$28=0,"",[1]入库吨位汇总!$D$28),"")) | E29: =IF($V$4=0,IF($M29="","",$M29),IFERROR(IF([1]入库吨位汇总!$E$28=0,"",[1]入库吨位汇总!$E$28),"")) | F29: =IF($V$4=0,IF($N29="","",$N29),IFERROR(IF([1]入库吨位汇总!$K$28=0,"",[1]入库吨位汇总!$K$28),"")) | G29: =IF($V$4=0,IF($O29="","",$O29),IFERROR(IF([1]入库吨位汇总!$L$28=0,"",[1]入库吨位汇总!$L$28),"")) | H29: =IF($V$4=0,IF($P29="","",$P29),IFERROR(IF([1]入库吨位汇总!$H$28=0,"",[1]入库吨位汇总!$H$28),"")) | I29: =IF($V$4=0,IF($Q29="","",$Q29),IFERROR(IF([1]入库吨位汇总!$I$28=0,"",[1]入库吨位汇总!$I$28),"")) | R29: =IF(AND($B29<>"",$C29<>""),1,0) -> 0 | S29: =N(S28)+$R29 -> 22
A30: 29 | B30: =IF($V$4=0,IF($J30="","",$J30),IFERROR(IF([1]入库吨位汇总!$B$29=0,"",[1]入库吨位汇总!$B$29),"")) | C30: =IF($V$4=0,IF($K30="","",$K30),IFERROR(IF([1]入库吨位汇总!$C$29=0,"",[1]入库吨位汇总!$C$29),"")) | D30: =IF($V$4=0,IF($L30="","",$L30),IFERROR(IF([1]入库吨位汇总!$D$29=0,"",[1]入库吨位汇总!$D$29),"")) | E30: =IF($V$4=0,IF($M30="","",$M30),IFERROR(IF([1]入库吨位汇总!$E$29=0,"",[1]入库吨位汇总!$E$29),"")) | F30: =IF($V$4=0,IF($N30="","",$N30),IFERROR(IF([1]入库吨位汇总!$K$29=0,"",[1]入库吨位汇总!$K$29),"")) | G30: =IF($V$4=0,IF($O30="","",$O30),IFERROR(IF([1]入库吨位汇总!$L$29=0,"",[1]入库吨位汇总!$L$29),"")) | H30: =IF($V$4=0,IF($P30="","",$P30),IFERROR(IF([1]入库吨位汇总!$H$29=0,"",[1]入库吨位汇总!$H$29),"")) | I30: =IF($V$4=0,IF($Q30="","",$Q30),IFERROR(IF([1]入库吨位汇总!$I$29=0,"",[1]入库吨位汇总!$I$29),"")) | R30: =IF(AND($B30<>"",$C30<>""),1,0) -> 0 | S30: =N(S29)+$R30 -> 22
A31: 30 | B31: =IF($V$4=0,IF($J31="","",$J31),IFERROR(IF([1]入库吨位汇总!$B$30=0,"",[1]入库吨位汇总!$B$30),"")) | C31: =IF($V$4=0,IF($K31="","",$K31),IFERROR(IF([1]入库吨位汇总!$C$30=0,"",[1]入库吨位汇总!$C$30),"")) | D31: =IF($V$4=0,IF($L31="","",$L31),IFERROR(IF([1]入库吨位汇总!$D$30=0,"",[1]入库吨位汇总!$D$30),"")) | E31: =IF($V$4=0,IF($M31="","",$M31),IFERROR(IF([1]入库吨位汇总!$E$30=0,"",[1]入库吨位汇总!$E$30),"")) | F31: =IF($V$4=0,IF($N31="","",$N31),IFERROR(IF([1]入库吨位汇总!$K$30=0,"",[1]入库吨位汇总!$K$30),"")) | G31: =IF($V$4=0,IF($O31="","",$O31),IFERROR(IF([1]入库吨位汇总!$L$30=0,"",[1]入库吨位汇总!$L$30),"")) | H31: =IF($V$4=0,IF($P31="","",$P31),IFERROR(IF([1]入库吨位汇总!$H$30=0,"",[1]入库吨位汇总!$H$30),"")) | I31: =IF($V$4=0,IF($Q31="","",$Q31),IFERROR(IF([1]入库吨位汇总!$I$30=0,"",[1]入库吨位汇总!$I$30),"")) | R31: =IF(AND($B31<>"",$C31<>""),1,0) -> 0 | S31: =N(S30)+$R31 -> 22
A32: 31 | B32: =IF($V$4=0,IF($J32="","",$J32),IFERROR(IF([1]入库吨位汇总!$B$31=0,"",[1]入库吨位汇总!$B$31),"")) | C32: =IF($V$4=0,IF($K32="","",$K32),IFERROR(IF([1]入库吨位汇总!$C$31=0,"",[1]入库吨位汇总!$C$31),"")) | D32: =IF($V$4=0,IF($L32="","",$L32),IFERROR(IF([1]入库吨位汇总!$D$31=0,"",[1]入库吨位汇总!$D$31),"")) | E32: =IF($V$4=0,IF($M32="","",$M32),IFERROR(IF([1]入库吨位汇总!$E$31=0,"",[1]入库吨位汇总!$E$31),"")) | F32: =IF($V$4=0,IF($N32="","",$N32),IFERROR(IF([1]入库吨位汇总!$K$31=0,"",[1]入库吨位汇总!$K$31),"")) | G32: =IF($V$4=0,IF($O32="","",$O32),IFERROR(IF([1]入库吨位汇总!$L$31=0,"",[1]入库吨位汇总!$L$31),"")) | H32: =IF($V$4=0,IF($P32="","",$P32),IFERROR(IF([1]入库吨位汇总!$H$31=0,"",[1]入库吨位汇总!$H$31),"")) | I32: =IF($V$4=0,IF($Q32="","",$Q32),IFERROR(IF([1]入库吨位汇总!$I$31=0,"",[1]入库吨位汇总!$I$31),"")) | R32: =IF(AND($B32<>"",$C32<>""),1,0) -> 0 | S32: =N(S31)+$R32 -> 22
A33: 32 | B33: =IF($V$4=0,IF($J33="","",$J33),IFERROR(IF([1]入库吨位汇总!$B$32=0,"",[1]入库吨位汇总!$B$32),"")) | C33: =IF($V$4=0,IF($K33="","",$K33),IFERROR(IF([1]入库吨位汇总!$C$32=0,"",[1]入库吨位汇总!$C$32),"")) | D33: =IF($V$4=0,IF($L33="","",$L33),IFERROR(IF([1]入库吨位汇总!$D$32=0,"",[1]入库吨位汇总!$D$32),"")) | E33: =IF($V$4=0,IF($M33="","",$M33),IFERROR(IF([1]入库吨位汇总!$E$32=0,"",[1]入库吨位汇总!$E$32),"")) | F33: =IF($V$4=0,IF($N33="","",$N33),IFERROR(IF([1]入库吨位汇总!$K$32=0,"",[1]入库吨位汇总!$K$32),"")) | G33: =IF($V$4=0,IF($O33="","",$O33),IFERROR(IF([1]入库吨位汇总!$L$32=0,"",[1]入库吨位汇总!$L$32),"")) | H33: =IF($V$4=0,IF($P33="","",$P33),IFERROR(IF([1]入库吨位汇总!$H$32=0,"",[1]入库吨位汇总!$H$32),"")) | I33: =IF($V$4=0,IF($Q33="","",$Q33),IFERROR(IF([1]入库吨位汇总!$I$32=0,"",[1]入库吨位汇总!$I$32),"")) | R33: =IF(AND($B33<>"",$C33<>""),1,0) -> 0 | S33: =N(S32)+$R33 -> 22
A34: 33 | B34: =IF($V$4=0,IF($J34="","",$J34),IFERROR(IF([1]入库吨位汇总!$B$33=0,"",[1]入库吨位汇总!$B$33),"")) | C34: =IF($V$4=0,IF($K34="","",$K34),IFERROR(IF([1]入库吨位汇总!$C$33=0,"",[1]入库吨位汇总!$C$33),"")) | D34: =IF($V$4=0,IF($L34="","",$L34),IFERROR(IF([1]入库吨位汇总!$D$33=0,"",[1]入库吨位汇总!$D$33),"")) | E34: =IF($V$4=0,IF($M34="","",$M34),IFERROR(IF([1]入库吨位汇总!$E$33=0,"",[1]入库吨位汇总!$E$33),"")) | F34: =IF($V$4=0,IF($N34="","",$N34),IFERROR(IF([1]入库吨位汇总!$K$33=0,"",[1]入库吨位汇总!$K$33),"")) | G34: =IF($V$4=0,IF($O34="","",$O34),IFERROR(IF([1]入库吨位汇总!$L$33=0,"",[1]入库吨位汇总!$L$33),"")) | H34: =IF($V$4=0,IF($P34="","",$P34),IFERROR(IF([1]入库吨位汇总!$H$33=0,"",[1]入库吨位汇总!$H$33),"")) | I34: =IF($V$4=0,IF($Q34="","",$Q34),IFERROR(IF([1]入库吨位汇总!$I$33=0,"",[1]入库吨位汇总!$I$33),"")) | R34: =IF(AND($B34<>"",$C34<>""),1,0) -> 0 | S34: =N(S33)+$R34 -> 22
A35: 34 | B35: =IF($V$4=0,IF($J35="","",$J35),IFERROR(IF([1]入库吨位汇总!$B$34=0,"",[1]入库吨位汇总!$B$34),"")) | C35: =IF($V$4=0,IF($K35="","",$K35),IFERROR(IF([1]入库吨位汇总!$C$34=0,"",[1]入库吨位汇总!$C$34),"")) | D35: =IF($V$4=0,IF($L35="","",$L35),IFERROR(IF([1]入库吨位汇总!$D$34=0,"",[1]入库吨位汇总!$D$34),"")) | E35: =IF($V$4=0,IF($M35="","",$M35),IFERROR(IF([1]入库吨位汇总!$E$34=0,"",[1]入库吨位汇总!$E$34),"")) | F35: =IF($V$4=0,IF($N35="","",$N35),IFERROR(IF([1]入库吨位汇总!$K$34=0,"",[1]入库吨位汇总!$K$34),"")) | G35: =IF($V$4=0,IF($O35="","",$O35),IFERROR(IF([1]入库吨位汇总!$L$34=0,"",[1]入库吨位汇总!$L$34),"")) | H35: =IF($V$4=0,IF($P35="","",$P35),IFERROR(IF([1]入库吨位汇总!$H$34=0,"",[1]入库吨位汇总!$H$34),"")) | I35: =IF($V$4=0,IF($Q35="","",$Q35),IFERROR(IF([1]入库吨位汇总!$I$34=0,"",[1]入库吨位汇总!$I$34),"")) | R35: =IF(AND($B35<>"",$C35<>""),1,0) -> 0 | S35: =N(S34)+$R35 -> 22
A36: 35 | B36: =IF($V$4=0,IF($J36="","",$J36),IFERROR(IF([1]入库吨位汇总!$B$35=0,"",[1]入库吨位汇总!$B$35),"")) | C36: =IF($V$4=0,IF($K36="","",$K36),IFERROR(IF([1]入库吨位汇总!$C$35=0,"",[1]入库吨位汇总!$C$35),"")) | D36: =IF($V$4=0,IF($L36="","",$L36),IFERROR(IF([1]入库吨位汇总!$D$35=0,"",[1]入库吨位汇总!$D$35),"")) | E36: =IF($V$4=0,IF($M36="","",$M36),IFERROR(IF([1]入库吨位汇总!$E$35=0,"",[1]入库吨位汇总!$E$35),"")) | F36: =IF($V$4=0,IF($N36="","",$N36),IFERROR(IF([1]入库吨位汇总!$K$35=0,"",[1]入库吨位汇总!$K$35),"")) | G36: =IF($V$4=0,IF($O36="","",$O36),IFERROR(IF([1]入库吨位汇总!$L$35=0,"",[1]入库吨位汇总!$L$35),"")) | H36: =IF($V$4=0,IF($P36="","",$P36),IFERROR(IF([1]入库吨位汇总!$H$35=0,"",[1]入库吨位汇总!$H$35),"")) | I36: =IF($V$4=0,IF($Q36="","",$Q36),IFERROR(IF([1]入库吨位汇总!$I$35=0,"",[1]入库吨位汇总!$I$35),"")) | R36: =IF(AND($B36<>"",$C36<>""),1,0) -> 0 | S36: =N(S35)+$R36 -> 22
A37: 36 | B37: =IF($V$4=0,IF($J37="","",$J37),IFERROR(IF([1]入库吨位汇总!$B$36=0,"",[1]入库吨位汇总!$B$36),"")) | C37: =IF($V$4=0,IF($K37="","",$K37),IFERROR(IF([1]入库吨位汇总!$C$36=0,"",[1]入库吨位汇总!$C$36),"")) | D37: =IF($V$4=0,IF($L37="","",$L37),IFERROR(IF([1]入库吨位汇总!$D$36=0,"",[1]入库吨位汇总!$D$36),"")) | E37: =IF($V$4=0,IF($M37="","",$M37),IFERROR(IF([1]入库吨位汇总!$E$36=0,"",[1]入库吨位汇总!$E$36),"")) | F37: =IF($V$4=0,IF($N37="","",$N37),IFERROR(IF([1]入库吨位汇总!$K$36=0,"",[1]入库吨位汇总!$K$36),"")) | G37: =IF($V$4=0,IF($O37="","",$O37),IFERROR(IF([1]入库吨位汇总!$L$36=0,"",[1]入库吨位汇总!$L$36),"")) | H37: =IF($V$4=0,IF($P37="","",$P37),IFERROR(IF([1]入库吨位汇总!$H$36=0,"",[1]入库吨位汇总!$H$36),"")) | I37: =IF($V$4=0,IF($Q37="","",$Q37),IFERROR(IF([1]入库吨位汇总!$I$36=0,"",[1]入库吨位汇总!$I$36),"")) | R37: =IF(AND($B37<>"",$C37<>""),1,0) -> 0 | S37: =N(S36)+$R37 -> 22
A38: 37 | B38: =IF($V$4=0,IF($J38="","",$J38),IFERROR(IF([1]入库吨位汇总!$B$37=0,"",[1]入库吨位汇总!$B$37),"")) | C38: =IF($V$4=0,IF($K38="","",$K38),IFERROR(IF([1]入库吨位汇总!$C$37=0,"",[1]入库吨位汇总!$C$37),"")) | D38: =IF($V$4=0,IF($L38="","",$L38),IFERROR(IF([1]入库吨位汇总!$D$37=0,"",[1]入库吨位汇总!$D$37),"")) | E38: =IF($V$4=0,IF($M38="","",$M38),IFERROR(IF([1]入库吨位汇总!$E$37=0,"",[1]入库吨位汇总!$E$37),"")) | F38: =IF($V$4=0,IF($N38="","",$N38),IFERROR(IF([1]入库吨位汇总!$K$37=0,"",[1]入库吨位汇总!$K$37),"")) | G38: =IF($V$4=0,IF($O38="","",$O38),IFERROR(IF([1]入库吨位汇总!$L$37=0,"",[1]入库吨位汇总!$L$37),"")) | H38: =IF($V$4=0,IF($P38="","",$P38),IFERROR(IF([1]入库吨位汇总!$H$37=0,"",[1]入库吨位汇总!$H$37),"")) | I38: =IF($V$4=0,IF($Q38="","",$Q38),IFERROR(IF([1]入库吨位汇总!$I$37=0,"",[1]入库吨位汇总!$I$37),"")) | R38: =IF(AND($B38<>"",$C38<>""),1,0) -> 0 | S38: =N(S37)+$R38 -> 22
A39: 38 | B39: =IF($V$4=0,IF($J39="","",$J39),IFERROR(IF([1]入库吨位汇总!$B$38=0,"",[1]入库吨位汇总!$B$38),"")) | C39: =IF($V$4=0,IF($K39="","",$K39),IFERROR(IF([1]入库吨位汇总!$C$38=0,"",[1]入库吨位汇总!$C$38),"")) | D39: =IF($V$4=0,IF($L39="","",$L39),IFERROR(IF([1]入库吨位汇总!$D$38=0,"",[1]入库吨位汇总!$D$38),"")) | E39: =IF($V$4=0,IF($M39="","",$M39),IFERROR(IF([1]入库吨位汇总!$E$38=0,"",[1]入库吨位汇总!$E$38),"")) | F39: =IF($V$4=0,IF($N39="","",$N39),IFERROR(IF([1]入库吨位汇总!$K$38=0,"",[1]入库吨位汇总!$K$38),"")) | G39: =IF($V$4=0,IF($O39="","",$O39),IFERROR(IF([1]入库吨位汇总!$L$38=0,"",[1]入库吨位汇总!$L$38),"")) | H39: =IF($V$4=0,IF($P39="","",$P39),IFERROR(IF([1]入库吨位汇总!$H$38=0,"",[1]入库吨位汇总!$H$38),"")) | I39: =IF($V$4=0,IF($Q39="","",$Q39),IFERROR(IF([1]入库吨位汇总!$I$38=0,"",[1]入库吨位汇总!$I$38),"")) | R39: =IF(AND($B39<>"",$C39<>""),1,0) -> 0 | S39: =N(S38)+$R39 -> 22
A40: 39 | B40: =IF($V$4=0,IF($J40="","",$J40),IFERROR(IF([1]入库吨位汇总!$B$39=0,"",[1]入库吨位汇总!$B$39),"")) | C40: =IF($V$4=0,IF($K40="","",$K40),IFERROR(IF([1]入库吨位汇总!$C$39=0,"",[1]入库吨位汇总!$C$39),"")) | D40: =IF($V$4=0,IF($L40="","",$L40),IFERROR(IF([1]入库吨位汇总!$D$39=0,"",[1]入库吨位汇总!$D$39),"")) | E40: =IF($V$4=0,IF($M40="","",$M40),IFERROR(IF([1]入库吨位汇总!$E$39=0,"",[1]入库吨位汇总!$E$39),"")) | F40: =IF($V$4=0,IF($N40="","",$N40),IFERROR(IF([1]入库吨位汇总!$K$39=0,"",[1]入库吨位汇总!$K$39),"")) | G40: =IF($V$4=0,IF($O40="","",$O40),IFERROR(IF([1]入库吨位汇总!$L$39=0,"",[1]入库吨位汇总!$L$39),"")) | H40: =IF($V$4=0,IF($P40="","",$P40),IFERROR(IF([1]入库吨位汇总!$H$39=0,"",[1]入库吨位汇总!$H$39),"")) | I40: =IF($V$4=0,IF($Q40="","",$Q40),IFERROR(IF([1]入库吨位汇总!$I$39=0,"",[1]入库吨位汇总!$I$39),"")) | R40: =IF(AND($B40<>"",$C40<>""),1,0) -> 0 | S40: =N(S39)+$R40 -> 22
A41: 40 | B41: =IF($V$4=0,IF($J41="","",$J41),IFERROR(IF([1]入库吨位汇总!$B$40=0,"",[1]入库吨位汇总!$B$40),"")) | C41: =IF($V$4=0,IF($K41="","",$K41),IFERROR(IF([1]入库吨位汇总!$C$40=0,"",[1]入库吨位汇总!$C$40),"")) | D41: =IF($V$4=0,IF($L41="","",$L41),IFERROR(IF([1]入库吨位汇总!$D$40=0,"",[1]入库吨位汇总!$D$40),"")) | E41: =IF($V$4=0,IF($M41="","",$M41),IFERROR(IF([1]入库吨位汇总!$E$40=0,"",[1]入库吨位汇总!$E$40),"")) | F41: =IF($V$4=0,IF($N41="","",$N41),IFERROR(IF([1]入库吨位汇总!$K$40=0,"",[1]入库吨位汇总!$K$40),"")) | G41: =IF($V$4=0,IF($O41="","",$O41),IFERROR(IF([1]入库吨位汇总!$L$40=0,"",[1]入库吨位汇总!$L$40),"")) | H41: =IF($V$4=0,IF($P41="","",$P41),IFERROR(IF([1]入库吨位汇总!$H$40=0,"",[1]入库吨位汇总!$H$40),"")) | I41: =IF($V$4=0,IF($Q41="","",$Q41),IFERROR(IF([1]入库吨位汇总!$I$40=0,"",[1]入库吨位汇总!$I$40),"")) | R41: =IF(AND($B41<>"",$C41<>""),1,0) -> 0 | S41: =N(S40)+$R41 -> 22
A42: 41 | B42: =IF($V$4=0,IF($J42="","",$J42),IFERROR(IF([1]入库吨位汇总!$B$41=0,"",[1]入库吨位汇总!$B$41),"")) | C42: =IF($V$4=0,IF($K42="","",$K42),IFERROR(IF([1]入库吨位汇总!$C$41=0,"",[1]入库吨位汇总!$C$41),"")) | D42: =IF($V$4=0,IF($L42="","",$L42),IFERROR(IF([1]入库吨位汇总!$D$41=0,"",[1]入库吨位汇总!$D$41),"")) | E42: =IF($V$4=0,IF($M42="","",$M42),IFERROR(IF([1]入库吨位汇总!$E$41=0,"",[1]入库吨位汇总!$E$41),"")) | F42: =IF($V$4=0,IF($N42="","",$N42),IFERROR(IF([1]入库吨位汇总!$K$41=0,"",[1]入库吨位汇总!$K$41),"")) | G42: =IF($V$4=0,IF($O42="","",$O42),IFERROR(IF([1]入库吨位汇总!$L$41=0,"",[1]入库吨位汇总!$L$41),"")) | H42: =IF($V$4=0,IF($P42="","",$P42),IFERROR(IF([1]入库吨位汇总!$H$41=0,"",[1]入库吨位汇总!$H$41),"")) | I42: =IF($V$4=0,IF($Q42="","",$Q42),IFERROR(IF([1]入库吨位汇总!$I$41=0,"",[1]入库吨位汇总!$I$41),"")) | R42: =IF(AND($B42<>"",$C42<>""),1,0) -> 0 | S42: =N(S41)+$R42 -> 22
A43: 42 | B43: =IF($V$4=0,IF($J43="","",$J43),IFERROR(IF([1]入库吨位汇总!$B$42=0,"",[1]入库吨位汇总!$B$42),"")) | C43: =IF($V$4=0,IF($K43="","",$K43),IFERROR(IF([1]入库吨位汇总!$C$42=0,"",[1]入库吨位汇总!$C$42),"")) | D43: =IF($V$4=0,IF($L43="","",$L43),IFERROR(IF([1]入库吨位汇总!$D$42=0,"",[1]入库吨位汇总!$D$42),"")) | E43: =IF($V$4=0,IF($M43="","",$M43),IFERROR(IF([1]入库吨位汇总!$E$42=0,"",[1]入库吨位汇总!$E$42),"")) | F43: =IF($V$4=0,IF($N43="","",$N43),IFERROR(IF([1]入库吨位汇总!$K$42=0,"",[1]入库吨位汇总!$K$42),"")) | G43: =IF($V$4=0,IF($O43="","",$O43),IFERROR(IF([1]入库吨位汇总!$L$42=0,"",[1]入库吨位汇总!$L$42),"")) | H43: =IF($V$4=0,IF($P43="","",$P43),IFERROR(IF([1]入库吨位汇总!$H$42=0,"",[1]入库吨位汇总!$H$42),"")) | I43: =IF($V$4=0,IF($Q43="","",$Q43),IFERROR(IF([1]入库吨位汇总!$I$42=0,"",[1]入库吨位汇总!$I$42),"")) | R43: =IF(AND($B43<>"",$C43<>""),1,0) -> 0 | S43: =N(S42)+$R43 -> 22
A44: 43 | B44: =IF($V$4=0,IF($J44="","",$J44),IFERROR(IF([1]入库吨位汇总!$B$43=0,"",[1]入库吨位汇总!$B$43),"")) | C44: =IF($V$4=0,IF($K44="","",$K44),IFERROR(IF([1]入库吨位汇总!$C$43=0,"",[1]入库吨位汇总!$C$43),"")) | D44: =IF($V$4=0,IF($L44="","",$L44),IFERROR(IF([1]入库吨位汇总!$D$43=0,"",[1]入库吨位汇总!$D$43),"")) | E44: =IF($V$4=0,IF($M44="","",$M44),IFERROR(IF([1]入库吨位汇总!$E$43=0,"",[1]入库吨位汇总!$E$43),"")) | F44: =IF($V$4=0,IF($N44="","",$N44),IFERROR(IF([1]入库吨位汇总!$K$43=0,"",[1]入库吨位汇总!$K$43),"")) | G44: =IF($V$4=0,IF($O44="","",$O44),IFERROR(IF([1]入库吨位汇总!$L$43=0,"",[1]入库吨位汇总!$L$43),"")) | H44: =IF($V$4=0,IF($P44="","",$P44),IFERROR(IF([1]入库吨位汇总!$H$43=0,"",[1]入库吨位汇总!$H$43),"")) | I44: =IF($V$4=0,IF($Q44="","",$Q44),IFERROR(IF([1]入库吨位汇总!$I$43=0,"",[1]入库吨位汇总!$I$43),"")) | R44: =IF(AND($B44<>"",$C44<>""),1,0) -> 0 | S44: =N(S43)+$R44 -> 22
A45: 44 | B45: =IF($V$4=0,IF($J45="","",$J45),IFERROR(IF([1]入库吨位汇总!$B$44=0,"",[1]入库吨位汇总!$B$44),"")) | C45: =IF($V$4=0,IF($K45="","",$K45),IFERROR(IF([1]入库吨位汇总!$C$44=0,"",[1]入库吨位汇总!$C$44),"")) | D45: =IF($V$4=0,IF($L45="","",$L45),IFERROR(IF([1]入库吨位汇总!$D$44=0,"",[1]入库吨位汇总!$D$44),"")) | E45: =IF($V$4=0,IF($M45="","",$M45),IFERROR(IF([1]入库吨位汇总!$E$44=0,"",[1]入库吨位汇总!$E$44),"")) | F45: =IF($V$4=0,IF($N45="","",$N45),IFERROR(IF([1]入库吨位汇总!$K$44=0,"",[1]入库吨位汇总!$K$44),"")) | G45: =IF($V$4=0,IF($O45="","",$O45),IFERROR(IF([1]入库吨位汇总!$L$44=0,"",[1]入库吨位汇总!$L$44),"")) | H45: =IF($V$4=0,IF($P45="","",$P45),IFERROR(IF([1]入库吨位汇总!$H$44=0,"",[1]入库吨位汇总!$H$44),"")) | I45: =IF($V$4=0,IF($Q45="","",$Q45),IFERROR(IF([1]入库吨位汇总!$I$44=0,"",[1]入库吨位汇总!$I$44),"")) | R45: =IF(AND($B45<>"",$C45<>""),1,0) -> 0 | S45: =N(S44)+$R45 -> 22
A46: 45 | B46: =IF($V$4=0,IF($J46="","",$J46),IFERROR(IF([1]入库吨位汇总!$B$45=0,"",[1]入库吨位汇总!$B$45),"")) | C46: =IF($V$4=0,IF($K46="","",$K46),IFERROR(IF([1]入库吨位汇总!$C$45=0,"",[1]入库吨位汇总!$C$45),"")) | D46: =IF($V$4=0,IF($L46="","",$L46),IFERROR(IF([1]入库吨位汇总!$D$45=0,"",[1]入库吨位汇总!$D$45),"")) | E46: =IF($V$4=0,IF($M46="","",$M46),IFERROR(IF([1]入库吨位汇总!$E$45=0,"",[1]入库吨位汇总!$E$45),"")) | F46: =IF($V$4=0,IF($N46="","",$N46),IFERROR(IF([1]入库吨位汇总!$K$45=0,"",[1]入库吨位汇总!$K$45),"")) | G46: =IF($V$4=0,IF($O46="","",$O46),IFERROR(IF([1]入库吨位汇总!$L$45=0,"",[1]入库吨位汇总!$L$45),"")) | H46: =IF($V$4=0,IF($P46="","",$P46),IFERROR(IF([1]入库吨位汇总!$H$45=0,"",[1]入库吨位汇总!$H$45),"")) | I46: =IF($V$4=0,IF($Q46="","",$Q46),IFERROR(IF([1]入库吨位汇总!$I$45=0,"",[1]入库吨位汇总!$I$45),"")) | R46: =IF(AND($B46<>"",$C46<>""),1,0) -> 0 | S46: =N(S45)+$R46 -> 22
A47: 46 | B47: =IF($V$4=0,IF($J47="","",$J47),IFERROR(IF([1]入库吨位汇总!$B$46=0,"",[1]入库吨位汇总!$B$46),"")) | C47: =IF($V$4=0,IF($K47="","",$K47),IFERROR(IF([1]入库吨位汇总!$C$46=0,"",[1]入库吨位汇总!$C$46),"")) | D47: =IF($V$4=0,IF($L47="","",$L47),IFERROR(IF([1]入库吨位汇总!$D$46=0,"",[1]入库吨位汇总!$D$46),"")) | E47: =IF($V$4=0,IF($M47="","",$M47),IFERROR(IF([1]入库吨位汇总!$E$46=0,"",[1]入库吨位汇总!$E$46),"")) | F47: =IF($V$4=0,IF($N47="","",$N47),IFERROR(IF([1]入库吨位汇总!$K$46=0,"",[1]入库吨位汇总!$K$46),"")) | G47: =IF($V$4=0,IF($O47="","",$O47),IFERROR(IF([1]入库吨位汇总!$L$46=0,"",[1]入库吨位汇总!$L$46),"")) | H47: =IF($V$4=0,IF($P47="","",$P47),IFERROR(IF([1]入库吨位汇总!$H$46=0,"",[1]入库吨位汇总!$H$46),"")) | I47: =IF($V$4=0,IF($Q47="","",$Q47),IFERROR(IF([1]入库吨位汇总!$I$46=0,"",[1]入库吨位汇总!$I$46),"")) | R47: =IF(AND($B47<>"",$C47<>""),1,0) -> 0 | S47: =N(S46)+$R47 -> 22
A48: 47 | B48: =IF($V$4=0,IF($J48="","",$J48),IFERROR(IF([1]入库吨位汇总!$B$47=0,"",[1]入库吨位汇总!$B$47),"")) | C48: =IF($V$4=0,IF($K48="","",$K48),IFERROR(IF([1]入库吨位汇总!$C$47=0,"",[1]入库吨位汇总!$C$47),"")) | D48: =IF($V$4=0,IF($L48="","",$L48),IFERROR(IF([1]入库吨位汇总!$D$47=0,"",[1]入库吨位汇总!$D$47),"")) | E48: =IF($V$4=0,IF($M48="","",$M48),IFERROR(IF([1]入库吨位汇总!$E$47=0,"",[1]入库吨位汇总!$E$47),"")) | F48: =IF($V$4=0,IF($N48="","",$N48),IFERROR(IF([1]入库吨位汇总!$K$47=0,"",[1]入库吨位汇总!$K$47),"")) | G48: =IF($V$4=0,IF($O48="","",$O48),IFERROR(IF([1]入库吨位汇总!$L$47=0,"",[1]入库吨位汇总!$L$47),"")) | H48: =IF($V$4=0,IF($P48="","",$P48),IFERROR(IF([1]入库吨位汇总!$H$47=0,"",[1]入库吨位汇总!$H$47),"")) | I48: =IF($V$4=0,IF($Q48="","",$Q48),IFERROR(IF([1]入库吨位汇总!$I$47=0,"",[1]入库吨位汇总!$I$47),"")) | R48: =IF(AND($B48<>"",$C48<>""),1,0) -> 0 | S48: =N(S47)+$R48 -> 22
A49: 48 | B49: =IF($V$4=0,IF($J49="","",$J49),IFERROR(IF([1]入库吨位汇总!$B$48=0,"",[1]入库吨位汇总!$B$48),"")) | C49: =IF($V$4=0,IF($K49="","",$K49),IFERROR(IF([1]入库吨位汇总!$C$48=0,"",[1]入库吨位汇总!$C$48),"")) | D49: =IF($V$4=0,IF($L49="","",$L49),IFERROR(IF([1]入库吨位汇总!$D$48=0,"",[1]入库吨位汇总!$D$48),"")) | E49: =IF($V$4=0,IF($M49="","",$M49),IFERROR(IF([1]入库吨位汇总!$E$48=0,"",[1]入库吨位汇总!$E$48),"")) | F49: =IF($V$4=0,IF($N49="","",$N49),IFERROR(IF([1]入库吨位汇总!$K$48=0,"",[1]入库吨位汇总!$K$48),"")) | G49: =IF($V$4=0,IF($O49="","",$O49),IFERROR(IF([1]入库吨位汇总!$L$48=0,"",[1]入库吨位汇总!$L$48),"")) | H49: =IF($V$4=0,IF($P49="","",$P49),IFERROR(IF([1]入库吨位汇总!$H$48=0,"",[1]入库吨位汇总!$H$48),"")) | I49: =IF($V$4=0,IF($Q49="","",$Q49),IFERROR(IF([1]入库吨位汇总!$I$48=0,"",[1]入库吨位汇总!$I$48),"")) | R49: =IF(AND($B49<>"",$C49<>""),1,0) -> 0 | S49: =N(S48)+$R49 -> 22
A50: 49 | B50: =IF($V$4=0,IF($J50="","",$J50),IFERROR(IF([1]入库吨位汇总!$B$49=0,"",[1]入库吨位汇总!$B$49),"")) | C50: =IF($V$4=0,IF($K50="","",$K50),IFERROR(IF([1]入库吨位汇总!$C$49=0,"",[1]入库吨位汇总!$C$49),"")) | D50: =IF($V$4=0,IF($L50="","",$L50),IFERROR(IF([1]入库吨位汇总!$D$49=0,"",[1]入库吨位汇总!$D$49),"")) | E50: =IF($V$4=0,IF($M50="","",$M50),IFERROR(IF([1]入库吨位汇总!$E$49=0,"",[1]入库吨位汇总!$E$49),"")) | F50: =IF($V$4=0,IF($N50="","",$N50),IFERROR(IF([1]入库吨位汇总!$K$49=0,"",[1]入库吨位汇总!$K$49),"")) | G50: =IF($V$4=0,IF($O50="","",$O50),IFERROR(IF([1]入库吨位汇总!$L$49=0,"",[1]入库吨位汇总!$L$49),"")) | H50: =IF($V$4=0,IF($P50="","",$P50),IFERROR(IF([1]入库吨位汇总!$H$49=0,"",[1]入库吨位汇总!$H$49),"")) | I50: =IF($V$4=0,IF($Q50="","",$Q50),IFERROR(IF([1]入库吨位汇总!$I$49=0,"",[1]入库吨位汇总!$I$49),"")) | R50: =IF(AND($B50<>"",$C50<>""),1,0) -> 0 | S50: =N(S49)+$R50 -> 22
A51: 50 | B51: =IF($V$4=0,IF($J51="","",$J51),IFERROR(IF([1]入库吨位汇总!$B$50=0,"",[1]入库吨位汇总!$B$50),"")) | C51: =IF($V$4=0,IF($K51="","",$K51),IFERROR(IF([1]入库吨位汇总!$C$50=0,"",[1]入库吨位汇总!$C$50),"")) | D51: =IF($V$4=0,IF($L51="","",$L51),IFERROR(IF([1]入库吨位汇总!$D$50=0,"",[1]入库吨位汇总!$D$50),"")) | E51: =IF($V$4=0,IF($M51="","",$M51),IFERROR(IF([1]入库吨位汇总!$E$50=0,"",[1]入库吨位汇总!$E$50),"")) | F51: =IF($V$4=0,IF($N51="","",$N51),IFERROR(IF([1]入库吨位汇总!$K$50=0,"",[1]入库吨位汇总!$K$50),"")) | G51: =IF($V$4=0,IF($O51="","",$O51),IFERROR(IF([1]入库吨位汇总!$L$50=0,"",[1]入库吨位汇总!$L$50),"")) | H51: =IF($V$4=0,IF($P51="","",$P51),IFERROR(IF([1]入库吨位汇总!$H$50=0,"",[1]入库吨位汇总!$H$50),"")) | I51: =IF($V$4=0,IF($Q51="","",$Q51),IFERROR(IF([1]入库吨位汇总!$I$50=0,"",[1]入库吨位汇总!$I$50),"")) | R51: =IF(AND($B51<>"",$C51<>""),1,0) -> 0 | S51: =N(S50)+$R51 -> 22
A52: 51 | B52: =IF($V$4=0,IF($J52="","",$J52),IFERROR(IF([1]入库吨位汇总!$B$51=0,"",[1]入库吨位汇总!$B$51),"")) | C52: =IF($V$4=0,IF($K52="","",$K52),IFERROR(IF([1]入库吨位汇总!$C$51=0,"",[1]入库吨位汇总!$C$51),"")) | D52: =IF($V$4=0,IF($L52="","",$L52),IFERROR(IF([1]入库吨位汇总!$D$51=0,"",[1]入库吨位汇总!$D$51),"")) | E52: =IF($V$4=0,IF($M52="","",$M52),IFERROR(IF([1]入库吨位汇总!$E$51=0,"",[1]入库吨位汇总!$E$51),"")) | F52: =IF($V$4=0,IF($N52="","",$N52),IFERROR(IF([1]入库吨位汇总!$K$51=0,"",[1]入库吨位汇总!$K$51),"")) | G52: =IF($V$4=0,IF($O52="","",$O52),IFERROR(IF([1]入库吨位汇总!$L$51=0,"",[1]入库吨位汇总!$L$51),"")) | H52: =IF($V$4=0,IF($P52="","",$P52),IFERROR(IF([1]入库吨位汇总!$H$51=0,"",[1]入库吨位汇总!$H$51),"")) | I52: =IF($V$4=0,IF($Q52="","",$Q52),IFERROR(IF([1]入库吨位汇总!$I$51=0,"",[1]入库吨位汇总!$I$51),"")) | R52: =IF(AND($B52<>"",$C52<>""),1,0) -> 0 | S52: =N(S51)+$R52 -> 22
A53: 52 | B53: =IF($V$4=0,IF($J53="","",$J53),IFERROR(IF([1]入库吨位汇总!$B$52=0,"",[1]入库吨位汇总!$B$52),"")) | C53: =IF($V$4=0,IF($K53="","",$K53),IFERROR(IF([1]入库吨位汇总!$C$52=0,"",[1]入库吨位汇总!$C$52),"")) | D53: =IF($V$4=0,IF($L53="","",$L53),IFERROR(IF([1]入库吨位汇总!$D$52=0,"",[1]入库吨位汇总!$D$52),"")) | E53: =IF($V$4=0,IF($M53="","",$M53),IFERROR(IF([1]入库吨位汇总!$E$52=0,"",[1]入库吨位汇总!$E$52),"")) | F53: =IF($V$4=0,IF($N53="","",$N53),IFERROR(IF([1]入库吨位汇总!$K$52=0,"",[1]入库吨位汇总!$K$52),"")) | G53: =IF($V$4=0,IF($O53="","",$O53),IFERROR(IF([1]入库吨位汇总!$L$52=0,"",[1]入库吨位汇总!$L$52),"")) | H53: =IF($V$4=0,IF($P53="","",$P53),IFERROR(IF([1]入库吨位汇总!$H$52=0,"",[1]入库吨位汇总!$H$52),"")) | I53: =IF($V$4=0,IF($Q53="","",$Q53),IFERROR(IF([1]入库吨位汇总!$I$52=0,"",[1]入库吨位汇总!$I$52),"")) | R53: =IF(AND($B53<>"",$C53<>""),1,0) -> 0 | S53: =N(S52)+$R53 -> 22
A54: 53 | B54: =IF($V$4=0,IF($J54="","",$J54),IFERROR(IF([1]入库吨位汇总!$B$53=0,"",[1]入库吨位汇总!$B$53),"")) | C54: =IF($V$4=0,IF($K54="","",$K54),IFERROR(IF([1]入库吨位汇总!$C$53=0,"",[1]入库吨位汇总!$C$53),"")) | D54: =IF($V$4=0,IF($L54="","",$L54),IFERROR(IF([1]入库吨位汇总!$D$53=0,"",[1]入库吨位汇总!$D$53),"")) | E54: =IF($V$4=0,IF($M54="","",$M54),IFERROR(IF([1]入库吨位汇总!$E$53=0,"",[1]入库吨位汇总!$E$53),"")) | F54: =IF($V$4=0,IF($N54="","",$N54),IFERROR(IF([1]入库吨位汇总!$K$53=0,"",[1]入库吨位汇总!$K$53),"")) | G54: =IF($V$4=0,IF($O54="","",$O54),IFERROR(IF([1]入库吨位汇总!$L$53=0,"",[1]入库吨位汇总!$L$53),"")) | H54: =IF($V$4=0,IF($P54="","",$P54),IFERROR(IF([1]入库吨位汇总!$H$53=0,"",[1]入库吨位汇总!$H$53),"")) | I54: =IF($V$4=0,IF($Q54="","",$Q54),IFERROR(IF([1]入库吨位汇总!$I$53=0,"",[1]入库吨位汇总!$I$53),"")) | R54: =IF(AND($B54<>"",$C54<>""),1,0) -> 0 | S54: =N(S53)+$R54 -> 22
A55: 54 | B55: =IF($V$4=0,IF($J55="","",$J55),IFERROR(IF([1]入库吨位汇总!$B$54=0,"",[1]入库吨位汇总!$B$54),"")) | C55: =IF($V$4=0,IF($K55="","",$K55),IFERROR(IF([1]入库吨位汇总!$C$54=0,"",[1]入库吨位汇总!$C$54),"")) | D55: =IF($V$4=0,IF($L55="","",$L55),IFERROR(IF([1]入库吨位汇总!$D$54=0,"",[1]入库吨位汇总!$D$54),"")) | E55: =IF($V$4=0,IF($M55="","",$M55),IFERROR(IF([1]入库吨位汇总!$E$54=0,"",[1]入库吨位汇总!$E$54),"")) | F55: =IF($V$4=0,IF($N55="","",$N55),IFERROR(IF([1]入库吨位汇总!$K$54=0,"",[1]入库吨位汇总!$K$54),"")) | G55: =IF($V$4=0,IF($O55="","",$O55),IFERROR(IF([1]入库吨位汇总!$L$54=0,"",[1]入库吨位汇总!$L$54),"")) | H55: =IF($V$4=0,IF($P55="","",$P55),IFERROR(IF([1]入库吨位汇总!$H$54=0,"",[1]入库吨位汇总!$H$54),"")) | I55: =IF($V$4=0,IF($Q55="","",$Q55),IFERROR(IF([1]入库吨位汇总!$I$54=0,"",[1]入库吨位汇总!$I$54),"")) | R55: =IF(AND($B55<>"",$C55<>""),1,0) -> 0 | S55: =N(S54)+$R55 -> 22
