Workbook

Sheet 主页
A1: 04 综 合 查 询 对 账 单
A2: 所有对账单集中在这一本；数据全部来自《01》《02》，三个文件必须放同一个文件夹 ｜ 点蓝色表名可跳转
A3: =IF(N(对接源_01水果!$R$1)+N(对接源_02物料!$R$1)=0,"联动状态：★★ 两本业务册的数据都没接进来 —— 请打开对接源表按提示修复链接",IF(N(对接源_01水果!$R$4)*N(对接源_02物料!$R$4)=0,"联动状态：⚠ 有业务册没接上（不是实时数）—— 01水果 "&N(对接源_01水果!$R$1)&" 笔，02物料 "&N(对接源_02物料!$R$1)&" 笔，请尽快修复链接","联动状态：✔ 正常 —— 01水果 "&N(对接源_01水果!$R$1)&" 笔 ＋ 02物料 "&N(对接源_02物料!$R$1)&" 笔已自动接入")) -> 联动状态：✔ 正常 —— 01水果 311 笔 ＋ 02物料 110 笔已自动接入
A5: 一、分类对账单（只填客户和起止日期）
A6: 序号 | B6: 子表名称 | C6: 用途说明 | D6: 属性
A7: 1 | B7: 筐子对账单 | C7: 公司筐：出库／退回（负）／随筐入库（负），含未回库筐子（欠筐） | D7: 录入+自动
A8: 2 | B8: 自备筐对账单 | C8: 客户自备筐的入库、出库明细及汇总 | D8: 录入+自动
A9: 3 | B9: 水果对账单 | C9: 原料入库/出库/结存 ＋ 成品出库，含进出库等级汇总 | D9: 录入+自动
A10: 4 | B10: 公司购买果品对账单 | C10: ★公司（果然鲜）买下客户果品的逐笔明细与应付金额 | D10: 录入+自动
A11: 5 | B11: 物料与筐子销售对账单 | C11: 包装物料销售 ＋ 卖断筐子销售，含已收/未收 | D11: 录入+自动
A13: 二、公用汇总
A14: 序号 | B14: 子表名称 | C14: 用途说明 | D14: 属性
A15: 6 | B15: 筐子库存汇总 | C15: 公司自有各类型筐子的期初、采购、退回、发出、销售与在库结存 | D15: 自动
A16: 7 | B16: 应收应付汇总 | C16: 各往来单位的应收、应付与净往来 | D16: 自动
A18: 三、跨册对接（自动取数，勿手工填）
A19: 序号 | B19: 子表名称 | C19: 用途说明 | D19: 属性
A20: 8 | B20: 对接源_01水果 | C20: 跨文件取《01》对账明细接口（含筐子与采购字段） | D20: 自动
A21: 9 | B21: 对接源_02物料 | C21: 跨文件取《02》对账明细接口 | D21: 自动
A23: 图例：浅绿＝公式自动生成，请勿覆盖 ｜ 浅蓝＝需要手工录入 ｜ 浅黄＝码表/规则，偶尔维护
A25: 本 轮 新 增
A26: 序号 | B26: 子表名称 | C26: 用途说明 | D26: 属性
A27: 1 | B27: =HYPERLINK("#'果然鲜销售对账单'!A1","果然鲜销售对账单") -> 果然鲜销售对账单 | C27: ★按购买方出：卖了什么、多少钱、运费多少、收了多少、还欠多少 | D27: 录入+自动

Sheet 使用说明
A1: 综 合 查 询 对 账 单 使 用 说 明
A2: 本册只用来查询和打印对账单，不录任何数据；数据全部来自《01 水果进销存台账》和《02 物料与周转物台账》
B4: 一、四个文件放在同一个文件夹
B6: 01_水果进销存台账模板.xlsx
B7: 02_物料与周转物台账模板.xlsx
B8: 03_财务账套与报表模板.xlsx
B9: 04_综合查询对账单.xlsx（本文件）
B10: 文件名一个字都不要改。打开本文件时如提示"是否更新链接"，请点【更新】。
B12: 二、怎么查对账单
B14: 打开【综合对账单】，第 3 行三个浅蓝格填一下：往来单位（下拉选）、开始日期、结束日期。
B15: 日期留空＝不限时间。上面自动出八类业务的汇总，下面自动列出每一笔，按业务类别成组排列。
B16: 确认无误直接打印给客户签字即可。
B18: 三、其他两张表
B20: 【筐子库存汇总】：公司每种筐子/托盘还剩多少、客户手上还有多少、公司筐总量是多少。
... B33: 本册按业务台账的收付状态统计，《03》按资金日记账的实际收付统计，以《03》为准。
A35: ★ 本 次 更 新（2026-09）
A36: 1、原「综合对账单」拆成 4 张分类对账单：【筐子对账单】【自备筐对账单】【水果对账单】【物料与筐子销售对账单】；原综合对账单保留，想看全部业务时用它。
A37: 2、四张对账单版式统一：抬头＋客户/起止日期筛选，黄条显示各段总数，右侧小盒显示汇总；只填 B2 客户与 F2/H2 起止日期，其余全自动。
A38: 3、【筐子对账单】只统计公司筐（筐子类型不以「自备」开头）：发出＝原料出库/成品出库带走＋周转筐出库销售；退回＝客户退回的空筐；入库＝随原料入库带回来的筐；未回库筐子（欠筐子数）＝发出−退回−入库（负数表示对方送回来的比我们发出的多）。
A39: 4、【自备筐对账单】＝《01》三张明细里筐子类型以「自备」开头的随货筐数 ＋《02》客户自备加工筐明细，表外备查。
A40: 5、【水果对账单】右侧「入库等级汇总」按下方入库明细自动分等级合计数量与总毛重。
A41: 6、【物料与筐子销售对账单】单价＝金额÷数量自动算，右侧显示物料/筐子销售金额与已收未收。
A43: ★ 本 次 更 新（2026-09 · 第三版）
A44: 1、【筐子对账单】改成周转筐出入库的样式：日期｜票据单号｜筐子类型｜数量｜车牌号，依次显示 出库 → 退回（负数）→ 随筐入库（负数）三段，右侧汇总含「未回库筐子（欠筐）」＝出库＋退回＋随筐入库。
A45: 2、【水果对账单】右侧汇总去掉了「出库总毛重」和「结存毛重」，并在「入库等级汇总」下面新增「出库等级汇总」，按等级自动合计出库数量与总毛重。
A46: 3、四张对账单都只填 B2 客户 与 F2/H2 起止日期，可跨 2026—2027 两年任意区间查询。
A48: ★ 本 次 更 新（2026-09 · 第八版）
... A50: 2、这张单的汇总数会自动进《03 往来对账单》，作为负数抵扣该客户的应收，不用手工加减。

Sheet 筐子对账单
A1: 新疆果然鲜仓储有限公司 | F1: 对账单 | P1: =IF($F$2="",DATE(1900,1,1),$F$2) -> 2
A2: 客 户: | B2: 王照雪 | E2: 开始日期: | G2: 结束日期: | I2: 筐 子 汇 总 | P2: =IF($H$2="",DATE(2999,12,31),$H$2) -> 401768
A3: ★ 只填 B2 客户与起止日期。公司筐口径：出库＝原料出库/成品出库带走＋周转筐领用出库；退回＝客户退回的空筐（显示为负数）；随筐入库＝随原料入库带回来的筐（显示为负数）。未回库筐子（欠筐子数）＝出库 ＋ 退回 ＋ 随筐入库。自备筐请看《自备筐对账单》。 | I3: 出库筐子 | K3: =ROUND(SUMIFS(对接源_01水果!$T$4:$T$1203,对接源_01水果!$C$4:$C$1203,$B$2,对接源_01水果!$B$4:$B$1203,">="&$P$1,对接源_01水果!$B$4:$B$1203,"<="&$P$2,对接源_01水果!$X$4:$X$1203,"公司筐")+SUMIFS(对接源_02物料!$T$4:$T$1203,对接源_02物料!$C$4:$C$1203,$B$2,对接源_02物料!$B$4:$B$1203,">="&$P$1,对接源_02物料!$B$4:$B$1203,"<="&$P$2,对接源_02物料!$X$4:$X$1203,"公司筐"),0) -> 3830
A4: 出库筐子总数 | E4: =ROUND(SUMIFS(对接源_01水果!$T$4:$T$1203,对接源_01水果!$C$4:$C$1203,$B$2,对接源_01水果!$B$4:$B$1203,">="&$P$1,对接源_01水果!$B$4:$B$1203,"<="&$P$2,对接源_01水果!$X$4:$X$1203,"公司筐")+SUMIFS(对接源_02物料!$T$4:$T$1203,对接源_02物料!$C$4:$C$1203,$B$2,对接源_02物料!$B$4:$B$1203,">="&$P$1,对接源_02物料!$B$4:$B$1203,"<="&$P$2,对接源_02物料!$X$4:$X$1203,"公司筐"),0) -> 3830 | I4: 退回筐子(空筐) | K4: =-ROUND(SUMIFS(对接源_01水果!$U$4:$U$1203,对接源_01水果!$C$4:$C$1203,$B$2,对接源_01水果!$B$4:$B$1203,">="&$P$1,对接源_01水果!$B$4:$B$1203,"<="&$P$2,对接源_01水果!$X$4:$X$1203,"公司筐")+SUMIFS(对接源_02物料!$U$4:$U$1203,对接源_02物料!$C$4:$C$1203,$B$2,对接源_02物料!$B$4:$B$1203,">="&$P$1,对接源_02物料!$B$4:$B$1203,"<="&$P$2,对接源_02物料!$X$4:$X$1203,"公司筐"),0) -> -82
A5: 日 期 | B5: 票据单号 | C5: 筐子类型 | D5: 数 量 | E5: 车牌号 | F5: 来源册 | G5: 备 注 | I5: 随筐入库 | K5: =-ROUND(SUMIFS(对接源_01水果!$V$4:$V$1203,对接源_01水果!$C$4:$C$1203,$B$2,对接源_01水果!$B$4:$B$1203,">="&$P$1,对接源_01水果!$B$4:$B$1203,"<="&$P$2,对接源_01水果!$X$4:$X$1203,"公司筐")+SUMIFS(对接源_02物料!$V$4:$V$1203,对接源_02物料!$C$4:$C$1203,$B$2,对接源_02物料!$B$4:$B$1203,">="&$P$1,对接源_02物料!$B$4:$B$1203,"<="&$P$2,对接源_02物料!$X$4:$X$1203,"公司筐"),0) -> -2213
A6: =IF($AE6="","",IF($AE6<=1200,IF(INDEX(对接源_01水果!$B$4:$B$1203,$AE6)=0,"",INDEX(对接源_01水果!$B$4:$B$1203,$AE6)),IF(INDEX(对接源_02物料!$B$4:$B$1203,$AE6-1200)=0,"",INDEX(对接源_02物料!$B$4:$B$1203,$AE6-1200)))) -> 46258 | B6: =IF($AE6="","",IF($AE6<=1200,IF(INDEX(对接源_01水果!$E$4:$E$1203,$AE6)=0,"",INDEX(对接源_01水果!$E$4:$E$1203,$AE6)),IF(INDEX(对接源_02物料!$E$4:$E$1203,$AE6-1200)=0,"",INDEX(对接源_02物料!$E$4:$E$1203,$AE6-1200)))) -> NO:0001032 | C6: =IF($AE6="","",IF($AE6<=1200,IF(INDEX(对接源_01水果!$S$4:$S$1203,$AE6)=0,"",INDEX(对接源_01水果!$S$4:$S$1203,$AE6)),IF(INDEX(对接源_02物料!$S$4:$S$1203,$AE6-1200)=0,"",INDEX(对接源_02物料!$S$4:$S$1203,$AE6-1200)))) -> 公司杂周转筐 | D6: =IF($AE6="","",IF($AE6<=1200,IF(INDEX(对接源_01水果!$T$4:$T$1203,$AE6)=0,"",INDEX(对接源_01水果!$T$4:$T$1203,$AE6)),IF(INDEX(对接源_02物料!$T$4:$T$1203,$AE6-1200)=0,"",INDEX(对接源_02物料!$T$4:$T$1203,$AE6-1200)))) -> 1 | E6: =IF($AE6="","",IF($AE6<=1200,IF(INDEX(对接源_01水果!$W$4:$W$1203,$AE6)=0,"",INDEX(对接源_01水果!$W$4:$W$1203,$AE6)),IF(INDEX(对接源_02物料!$W$4:$W$1203,$AE6-1200)=0,"",INDEX(对接源_02物料!$W$4:$W$1203,$AE6-1200)))) | F6: =IF($AE6="","",IF($AE6<=1200,"01水果册","02物料册")) -> 01水果册 | G6: =IF($AE6="","",IF($AE6<=1200,IF(INDEX(对接源_01水果!$M$4:$M$1203,$AE6)=0,"",INDEX(对接源_01水果!$M$4:$M$1203,$AE6)),IF(INDEX(对接源_02物料!$M$4:$M$1203,$AE6-1200)=0,"",INDEX(对接源_02物料!$M$4:$M$1203,$AE6-1200)))) -> 主播拿走 | I6: 未回库筐子(欠筐) | K6: =ROUND((SUMIFS(对接源_01水果!$T$4:$T$1203,对接源_01水果!$C$4:$C$1203,$B$2,对接源_01水果!$B$4:$B$1203,">="&$P$1,对接源_01水果!$B$4:$B$1203,"<="&$P$2,对接源_01水果!$X$4:$X$1203,"公司筐")+SUMIFS(对接源_02物料!$T$4:$T$1203,对接源_02物料!$C$4:$C$1203,$B$2,对接源_02物料!$B$4:$B$1203,">="&$P$1,对接源_02物料!$B$4:$B$1203,"<="&$P$2,对接源_02物料!$X$4:$X$1203,"公司筐"))-(SUMIFS(对接源_01水果!$U$4:$U$1203,对接源_01水果!$C$4:$C$1203,$B$2,对接源_01水果!$B$4:$B$1203,">="&$P$1,对接源_01水果!$B$4:$B$1203,"<="&$P$2,对接源_01水果!$X$4:$X$1203,"公司筐")+SUMIFS(对接源_02物料!$U$4:$U$1203,对接源_02物料!$C$4:$C$1203,$B$2,对接源_02物料!$B$4:$B$1203,">="&$P$1,对接源_02物料!$B$4:$B$1203,"<="&$P$2,对接源_02物料!$X$4:$X$1203,"公司筐"))-(SUMIFS(对接源_01水果!$V$4:$V$1203,对接源_01水果!$C$4:$C$1203,$B$2,对接源_01水果!$B$4:$B$1203,">="&$P$1,对接源_01水果!$B$4:$B$1203,"<="&$P$2,对接源_01水果!$X$4:$X$1203,"公司筐")+SUMIFS(对接源_02物料!$V$4:$V$1203,对接源_02物料!$C$4:$C$1203,$B$2,对接源_02物料!$B$4:$B$1203,">="&$P$1,对接源_02物料!$B$4:$B$1203,"<="&$P$2,对接源_02物料!$X$4:$X$1203,"公司筐")),0) -> 1535 | AE6: =IFERROR(MATCH(1,_自动清单!$Q$4:$Q$2403,0),"") -> 233
A7: =IF($AE7="","",IF($AE7<=1200,IF(INDEX(对接源_01水果!$B$4:$B$1203,$AE7)=0,"",INDEX(对接源_01水果!$B$4:$B$1203,$AE7)),IF(INDEX(对接源_02物料!$B$4:$B$1203,$AE7-1200)=0,"",INDEX(对接源_02物料!$B$4:$B$1203,$AE7-1200)))) -> 46267 | B7: =IF($AE7="","",IF($AE7<=1200,IF(INDEX(对接源_01水果!$E$4:$E$1203,$AE7)=0,"",INDEX(对接源_01水果!$E$4:$E$1203,$AE7)),IF(INDEX(对接源_02物料!$E$4:$E$1203,$AE7-1200)=0,"",INDEX(对接源_02物料!$E$4:$E$1203,$AE7-1200)))) -> NO:0001063 | C7: =IF($AE7="","",IF($AE7<=1200,IF(INDEX(对接源_01水果!$S$4:$S$1203,$AE7)=0,"",INDEX(对接源_01水果!$S$4:$S$1203,$AE7)),IF(INDEX(对接源_02物料!$S$4:$S$1203,$AE7-1200)=0,"",INDEX(对接源_02物料!$S$4:$S$1203,$AE7-1200)))) -> 公司杂周转筐 | D7: =IF($AE7="","",IF($AE7<=1200,IF(INDEX(对接源_01水果!$T$4:$T$1203,$AE7)=0,"",INDEX(对接源_01水果!$T$4:$T$1203,$AE7)),IF(INDEX(对接源_02物料!$T$4:$T$1203,$AE7-1200)=0,"",INDEX(对接源_02物料!$T$4:$T$1203,$AE7-1200)))) -> 1 | E7: =IF($AE7="","",IF($AE7<=1200,IF(INDEX(对接源_01水果!$W$4:$W$1203,$AE7)=0,"",INDEX(对接源_01水果!$W$4:$W$1203,$AE7)),IF(INDEX(对接源_02物料!$W$4:$W$1203,$AE7-1200)=0,"",INDEX(对接源_02物料!$W$4:$W$1203,$AE7-1200)))) -> 自提 | F7: =IF($AE7="","",IF($AE7<=1200,"01水果册","02物料册")) -> 01水果册 | G7: =IF($AE7="","",IF($AE7<=1200,IF(INDEX(对接源_01水果!$M$4:$M$1203,$AE7)=0,"",INDEX(对接源_01水果!$M$4:$M$1203,$AE7)),IF(INDEX(对接源_02物料!$M$4:$M$1203,$AE7-1200)=0,"",INDEX(对接源_02物料!$M$4:$M$1203,$AE7-1200)))) | AE7: =IFERROR(MATCH(2,_自动清单!$Q$4:$Q$2403,0),"") -> 283
A8: =IF($AE8="","",IF($AE8<=1200,IF(INDEX(对接源_01水果!$B$4:$B$1203,$AE8)=0,"",INDEX(对接源_01水果!$B$4:$B$1203,$AE8)),IF(INDEX(对接源_02物料!$B$4:$B$1203,$AE8-1200)=0,"",INDEX(对接源_02物料!$B$4:$B$1203,$AE8-1200)))) -> 46269 | B8: =IF($AE8="","",IF($AE8<=1200,IF(INDEX(对接源_01水果!$E$4:$E$1203,$AE8)=0,"",INDEX(对接源_01水果!$E$4:$E$1203,$AE8)),IF(INDEX(对接源_02物料!$E$4:$E$1203,$AE8-1200)=0,"",INDEX(对接源_02物料!$E$4:$E$1203,$AE8-1200)))) -> NO:0001083 | C8: =IF($AE8="","",IF($AE8<=1200,IF(INDEX(对接源_01水果!$S$4:$S$1203,$AE8)=0,"",INDEX(对接源_01水果!$S$4:$S$1203,$AE8)),IF(INDEX(对接源_02物料!$S$4:$S$1203,$AE8-1200)=0,"",INDEX(对接源_02物料!$S$4:$S$1203,$AE8-1200)))) -> 公司杂周转筐 | D8: =IF($AE8="","",IF($AE8<=1200,IF(INDEX(对接源_01水果!$T$4:$T$1203,$AE8)=0,"",INDEX(对接源_01水果!$T$4:$T$1203,$AE8)),IF(INDEX(对接源_02物料!$T$4:$T$1203,$AE8-1200)=0,"",INDEX(对接源_02物料!$T$4:$T$1203,$AE8-1200)))) -> 3 | E8: =IF($AE8="","",IF($AE8<=1200,IF(INDEX(对接源_01水果!$W$4:$W$1203,$AE8)=0,"",INDEX(对接源_01水果!$W$4:$W$1203,$AE8)),IF(INDEX(对接源_02物料!$W$4:$W$1203,$AE8-1200)=0,"",INDEX(对接源_02物料!$W$4:$W$1203,$AE8-1200)))) -> 豫N*P269J | F8: =IF($AE8="","",IF($AE8<=1200,"01水果册","02物料册")) -> 01水果册 | G8: =IF($AE8="","",IF($AE8<=1200,IF(INDEX(对接源_01水果!$M$4:$M$1203,$AE8)=0,"",INDEX(对接源_01水果!$M$4:$M$1203,$AE8)),IF(INDEX(对接源_02物料!$M$4:$M$1203,$AE8-1200)=0,"",INDEX(对接源_02物料!$M$4:$M$1203,$AE8-1200)))) | AE8: =IFERROR(MATCH(3,_自动清单!$Q$4:$Q$2403,0),"") -> 290
A9: =IF($AE9="","",IF($AE9<=1200,IF(INDEX(对接源_01水果!$B$4:$B$1203,$AE9)=0,"",INDEX(对接源_01水果!$B$4:$B$1203,$AE9)),IF(INDEX(对接源_02物料!$B$4:$B$1203,$AE9-1200)=0,"",INDEX(对接源_02物料!$B$4:$B$1203,$AE9-1200)))) -> 46245 | B9: =IF($AE9="","",IF($AE9<=1200,IF(INDEX(对接源_01水果!$E$4:$E$1203,$AE9)=0,"",INDEX(对接源_01水果!$E$4:$E$1203,$AE9)),IF(INDEX(对接源_02物料!$E$4:$E$1203,$AE9-1200)=0,"",INDEX(对接源_02物料!$E$4:$E$1203,$AE9-1200)))) -> NO:0001015 | C9: =IF($AE9="","",IF($AE9<=1200,IF(INDEX(对接源_01水果!$S$4:$S$1203,$AE9)=0,"",INDEX(对接源_01水果!$S$4:$S$1203,$AE9)),IF(INDEX(对接源_02物料!$S$4:$S$1203,$AE9-1200)=0,"",INDEX(对接源_02物料!$S$4:$S$1203,$AE9-1200)))) -> 公司杂周转筐 | D9: =IF($AE9="","",IF($AE9<=1200,IF(INDEX(对接源_01水果!$T$4:$T$1203,$AE9)=0,"",INDEX(对接源_01水果!$T$4:$T$1203,$AE9)),IF(INDEX(对接源_02物料!$T$4:$T$1203,$AE9-1200)=0,"",INDEX(对接源_02物料!$T$4:$T$1203,$AE9-1200)))) -> 351 | E9: =IF($AE9="","",IF($AE9<=1200,IF(INDEX(对接源_01水果!$W$4:$W$1203,$AE9)=0,"",INDEX(对接源_01水果!$W$4:$W$1203,$AE9)),IF(INDEX(对接源_02物料!$W$4:$W$1203,$AE9-1200)=0,"",INDEX(对接源_02物料!$W$4:$W$1203,$AE9-1200)))) -> 豫L*88X19 | F9: =IF($AE9="","",IF($AE9<=1200,"01水果册","02物料册")) -> 02物料册 | G9: =IF($AE9="","",IF($AE9<=1200,IF(INDEX(对接源_01水果!$M$4:$M$1203,$AE9)=0,"",INDEX(对接源_01水果!$M$4:$M$1203,$AE9)),IF(INDEX(对接源_02物料!$M$4:$M$1203,$AE9-1200)=0,"",INDEX(对接源_02物料!$M$4:$M$1203,$AE9-1200)))) | AE9: =IFERROR(MATCH(4,_自动清单!$Q$4:$Q$2403,0),"") -> 1238
A10: =IF($AE10="","",IF($AE10<=1200,IF(INDEX(对接源_01水果!$B$4:$B$1203,$AE10)=0,"",INDEX(对接源_01水果!$B$4:$B$1203,$AE10)),IF(INDEX(对接源_02物料!$B$4:$B$1203,$AE10-1200)=0,"",INDEX(对接源_02物料!$B$4:$B$1203,$AE10-1200)))) -> 46255 | B10: =IF($AE10="","",IF($AE10<=1200,IF(INDEX(对接源_01水果!$E$4:$E$1203,$AE10)=0,"",INDEX(对接源_01水果!$E$4:$E$1203,$AE10)),IF(INDEX(对接源_02物料!$E$4:$E$1203,$AE10-1200)=0,"",INDEX(对接源_02物料!$E$4:$E$1203,$AE10-1200)))) -> NO:0001022 | C10: =IF($AE10="","",IF($AE10<=1200,IF(INDEX(对接源_01水果!$S$4:$S$1203,$AE10)=0,"",INDEX(对接源_01水果!$S$4:$S$1203,$AE10)),IF(INDEX(对接源_02物料!$S$4:$S$1203,$AE10-1200)=0,"",INDEX(对接源_02物料!$S$4:$S$1203,$AE10-1200)))) -> 公司杂周转筐 | D10: =IF($AE10="","",IF($AE10<=1200,IF(INDEX(对接源_01水果!$T$4:$T$1203,$AE10)=0,"",INDEX(对接源_01水果!$T$4:$T$1203,$AE10)),IF(INDEX(对接源_02物料!$T$4:$T$1203,$AE10-1200)=0,"",INDEX(对接源_02物料!$T$4:$T$1203,$AE10-1200)))) -> 432 | E10: =IF($AE10="","",IF($AE10<=1200,IF(INDEX(对接源_01水果!$W$4:$W$1203,$AE10)=0,"",INDEX(对接源_01水果!$W$4:$W$1203,$AE10)),IF(INDEX(对接源_02物料!$W$4:$W$1203,$AE10-1200)=0,"",INDEX(对接源_02物料!$W$4:$W$1203,$AE10-1200)))) -> 豫L*88X19 | F10: =IF($AE10="","",IF($AE10<=1200,"01水果册","02物料册")) -> 02物料册 | G10: =IF($AE10="","",IF($AE10<=1200,IF(INDEX(对接源_01水果!$M$4:$M$1203,$AE10)=0,"",INDEX(对接源_01水果!$M$4:$M$1203,$AE10)),IF(INDEX(对接源_02物料!$M$4:$M$1203,$AE10-1200)=0,"",INDEX(对接源_02物料!$M$4:$M$1203,$AE10-1200)))) | AE10: =IFERROR(MATCH(5,_自动清单!$Q$4:$Q$2403,0),"") -> 1239
A11: =IF($AE11="","",IF($AE11<=1200,IF(INDEX(对接源_01水果!$B$4:$B$1203,$AE11)=0,"",INDEX(对接源_01水果!$B$4:$B$1203,$AE11)),IF(INDEX(对接源_02物料!$B$4:$B$1203,$AE11-1200)=0,"",INDEX(对接源_02物料!$B$4:$B$1203,$AE11-1200)))) -> 46258 | B11: =IF($AE11="","",IF($AE11<=1200,IF(INDEX(对接源_01水果!$E$4:$E$1203,$AE11)=0,"",INDEX(对接源_01水果!$E$4:$E$1203,$AE11)),IF(INDEX(对接源_02物料!$E$4:$E$1203,$AE11-1200)=0,"",INDEX(对接源_02物料!$E$4:$E$1203,$AE11-1200)))) -> NO:0001031 | C11: =IF($AE11="","",IF($AE11<=1200,IF(INDEX(对接源_01水果!$S$4:$S$1203,$AE11)=0,"",INDEX(对接源_01水果!$S$4:$S$1203,$AE11)),IF(INDEX(对接源_02物料!$S$4:$S$1203,$AE11-1200)=0,"",INDEX(对接源_02物料!$S$4:$S$1203,$AE11-1200)))) -> 公司杂周转筐 | D11: =IF($AE11="","",IF($AE11<=1200,IF(INDEX(对接源_01水果!$T$4:$T$1203,$AE11)=0,"",INDEX(对接源_01水果!$T$4:$T$1203,$AE11)),IF(INDEX(对接源_02物料!$T$4:$T$1203,$AE11-1200)=0,"",INDEX(对接源_02物料!$T$4:$T$1203,$AE11-1200)))) -> 282 | E11: =IF($AE11="","",IF($AE11<=1200,IF(INDEX(对接源_01水果!$W$4:$W$1203,$AE11)=0,"",INDEX(对接源_01水果!$W$4:$W$1203,$AE11)),IF(INDEX(对接源_02物料!$W$4:$W$1203,$AE11-1200)=0,"",INDEX(对接源_02物料!$W$4:$W$1203,$AE11-1200)))) -> 豫L*88X19 | F11: =IF($AE11="","",IF($AE11<=1200,"01水果册","02物料册")) -> 02物料册 | G11: =IF($AE11="","",IF($AE11<=1200,IF(INDEX(对接源_01水果!$M$4:$M$1203,$AE11)=0,"",INDEX(对接源_01水果!$M$4:$M$1203,$AE11)),IF(INDEX(对接源_02物料!$M$4:$M$1203,$AE11-1200)=0,"",INDEX(对接源_02物料!$M$4:$M$1203,$AE11-1200)))) | AE11: =IFERROR(MATCH(6,_自动清单!$Q$4:$Q$2403,0),"") -> 1240
A12: =IF($AE12="","",IF($AE12<=1200,IF(INDEX(对接源_01水果!$B$4:$B$1203,$AE12)=0,"",INDEX(对接源_01水果!$B$4:$B$1203,$AE12)),IF(INDEX(对接源_02物料!$B$4:$B$1203,$AE12-1200)=0,"",INDEX(对接源_02物料!$B$4:$B$1203,$AE12-1200)))) -> 46260 | B12: =IF($AE12="","",IF($AE12<=1200,IF(INDEX(对接源_01水果!$E$4:$E$1203,$AE12)=0,"",INDEX(对接源_01水果!$E$4:$E$1203,$AE12)),IF(INDEX(对接源_02物料!$E$4:$E$1203,$AE12-1200)=0,"",INDEX(对接源_02物料!$E$4:$E$1203,$AE12-1200)))) -> NO:0001037 | C12: =IF($AE12="","",IF($AE12<=1200,IF(INDEX(对接源_01水果!$S$4:$S$1203,$AE12)=0,"",INDEX(对接源_01水果!$S$4:$S$1203,$AE12)),IF(INDEX(对接源_02物料!$S$4:$S$1203,$AE12-1200)=0,"",INDEX(对接源_02物料!$S$4:$S$1203,$AE12-1200)))) -> 公司杂周转筐 | D12: =IF($AE12="","",IF($AE12<=1200,IF(INDEX(对接源_01水果!$T$4:$T$1203,$AE12)=0,"",INDEX(对接源_01水果!$T$4:$T$1203,$AE12)),IF(INDEX(对接源_02物料!$T$4:$T$1203,$AE12-1200)=0,"",INDEX(对接源_02物料!$T$4:$T$1203,$AE12-1200)))) -> 144 | E12: =IF($AE12="","",IF($AE12<=1200,IF(INDEX(对接源_01水果!$W$4:$W$1203,$AE12)=0,"",INDEX(对接源_01水果!$W$4:$W$1203,$AE12)),IF(INDEX(对接源_02物料!$W$4:$W$1203,$AE12-1200)=0,"",INDEX(对接源_02物料!$W$4:$W$1203,$AE12-1200)))) -> 豫L*88X19 | F12: =IF($AE12="","",IF($AE12<=1200,"01水果册","02物料册")) -> 02物料册 | G12: =IF($AE12="","",IF($AE12<=1200,IF(INDEX(对接源_01水果!$M$4:$M$1203,$AE12)=0,"",INDEX(对接源_01水果!$M$4:$M$1203,$AE12)),IF(INDEX(对接源_02物料!$M$4:$M$1203,$AE12-1200)=0,"",INDEX(对接源_02物料!$M$4:$M$1203,$AE12-1200)))) | AE12: =IFERROR(MATCH(7,_自动清单!$Q$4:$Q$2403,0),"") -> 1241
A13: =IF($AE13="","",IF($AE13<=1200,IF(INDEX(对接源_01水果!$B$4:$B$1203,$AE13)=0,"",INDEX(对接源_01水果!$B$4:$B$1203,$AE13)),IF(INDEX(对接源_02物料!$B$4:$B$1203,$AE13-1200)=0,"",INDEX(对接源_02物料!$B$4:$B$1203,$AE13-1200)))) -> 46274 | B13: =IF($AE13="","",IF($AE13<=1200,IF(INDEX(对接源_01水果!$E$4:$E$1203,$AE13)=0,"",INDEX(对接源_01水果!$E$4:$E$1203,$AE13)),IF(INDEX(对接源_02物料!$E$4:$E$1203,$AE13-1200)=0,"",INDEX(对接源_02物料!$E$4:$E$1203,$AE13-1200)))) -> NO:0001098 | C13: =IF($AE13="","",IF($AE13<=1200,IF(INDEX(对接源_01水果!$S$4:$S$1203,$AE13)=0,"",INDEX(对接源_01水果!$S$4:$S$1203,$AE13)),IF(INDEX(对接源_02物料!$S$4:$S$1203,$AE13-1200)=0,"",INDEX(对接源_02物料!$S$4:$S$1203,$AE13-1200)))) -> 公司一次性筐 | D13: =IF($AE13="","",IF($AE13<=1200,IF(INDEX(对接源_01水果!$T$4:$T$1203,$AE13)=0,"",INDEX(对接源_01水果!$T$4:$T$1203,$AE13)),IF(INDEX(对接源_02物料!$T$4:$T$1203,$AE13-1200)=0,"",INDEX(对接源_02物料!$T$4:$T$1203,$AE13-1200)))) -> 423 | E13: =IF($AE13="","",IF($AE13<=1200,IF(INDEX(对接源_01水果!$W$4:$W$1203,$AE13)=0,"",INDEX(对接源_01水果!$W$4:$W$1203,$AE13)),IF(INDEX(对接源_02物料!$W$4:$W$1203,$AE13-1200)=0,"",INDEX(对接源_02物料!$W$4:$W$1203,$AE13-1200)))) -> 豫L*88X19 | F13: =IF($AE13="","",IF($AE13<=1200,"01水果册","02物料册")) -> 02物料册 | G13: =IF($AE13="","",IF($AE13<=1200,IF(INDEX(对接源_01水果!$M$4:$M$1203,$AE13)=0,"",INDEX(对接源_01水果!$M$4:$M$1203,$AE13)),IF(INDEX(对接源_02物料!$M$4:$M$1203,$AE13-1200)=0,"",INDEX(对接源_02物料!$M$4:$M$1203,$AE13-1200)))) | AE13: =IFERROR(MATCH(8,_自动清单!$Q$4:$Q$2403,0),"") -> 1274
A14: =IF($AE14="","",IF($AE14<=1200,IF(INDEX(对接源_01水果!$B$4:$B$1203,$AE14)=0,"",INDEX(对接源_01水果!$B$4:$B$1203,$AE14)),IF(INDEX(对接源_02物料!$B$4:$B$1203,$AE14-1200)=0,"",INDEX(对接源_02物料!$B$4:$B$1203,$AE14-1200)))) -> 46275 | B14: =IF($AE14="","",IF($AE14<=1200,IF(INDEX(对接源_01水果!$E$4:$E$1203,$AE14)=0,"",INDEX(对接源_01水果!$E$4:$E$1203,$AE14)),IF(INDEX(对接源_02物料!$E$4:$E$1203,$AE14-1200)=0,"",INDEX(对接源_02物料!$E$4:$E$1203,$AE14-1200)))) -> NO:0001107 | C14: =IF($AE14="","",IF($AE14<=1200,IF(INDEX(对接源_01水果!$S$4:$S$1203,$AE14)=0,"",INDEX(对接源_01水果!$S$4:$S$1203,$AE14)),IF(INDEX(对接源_02物料!$S$4:$S$1203,$AE14-1200)=0,"",INDEX(对接源_02物料!$S$4:$S$1203,$AE14-1200)))) -> 公司一次性筐 | D14: =IF($AE14="","",IF($AE14<=1200,IF(INDEX(对接源_01水果!$T$4:$T$1203,$AE14)=0,"",INDEX(对接源_01水果!$T$4:$T$1203,$AE14)),IF(INDEX(对接源_02物料!$T$4:$T$1203,$AE14-1200)=0,"",INDEX(对接源_02物料!$T$4:$T$1203,$AE14-1200)))) -> 423 | E14: =IF($AE14="","",IF($AE14<=1200,IF(INDEX(对接源_01水果!$W$4:$W$1203,$AE14)=0,"",INDEX(对接源_01水果!$W$4:$W$1203,$AE14)),IF(INDEX(对接源_02物料!$W$4:$W$1203,$AE14-1200)=0,"",INDEX(对接源_02物料!$W$4:$W$1203,$AE14-1200)))) -> 豫L*88X19 | F14: =IF($AE14="","",IF($AE14<=1200,"01水果册","02物料册")) -> 02物料册 | G14: =IF($AE14="","",IF($AE14<=1200,IF(INDEX(对接源_01水果!$M$4:$M$1203,$AE14)=0,"",INDEX(对接源_01水果!$M$4:$M$1203,$AE14)),IF(INDEX(对接源_02物料!$M$4:$M$1203,$AE14-1200)=0,"",INDEX(对接源_02物料!$M$4:$M$1203,$AE14-1200)))) | AE14: =IFERROR(MATCH(9,_自动清单!$Q$4:$Q$2403,0),"") -> 1282
A15: =IF($AE15="","",IF($AE15<=1200,IF(INDEX(对接源_01水果!$B$4:$B$1203,$AE15)=0,"",INDEX(对接源_01水果!$B$4:$B$1203,$AE15)),IF(INDEX(对接源_02物料!$B$4:$B$1203,$AE15-1200)=0,"",INDEX(对接源_02物料!$B$4:$B$1203,$AE15-1200)))) -> 46276 | B15: =IF($AE15="","",IF($AE15<=1200,IF(INDEX(对接源_01水果!$E$4:$E$1203,$AE15)=0,"",INDEX(对接源_01水果!$E$4:$E$1203,$AE15)),IF(INDEX(对接源_02物料!$E$4:$E$1203,$AE15-1200)=0,"",INDEX(对接源_02物料!$E$4:$E$1203,$AE15-1200)))) -> NO:0001115 | C15: =IF($AE15="","",IF($AE15<=1200,IF(INDEX(对接源_01水果!$S$4:$S$1203,$AE15)=0,"",INDEX(对接源_01水果!$S$4:$S$1203,$AE15)),IF(INDEX(对接源_02物料!$S$4:$S$1203,$AE15-1200)=0,"",INDEX(对接源_02物料!$S$4:$S$1203,$AE15-1200)))) -> 公司杂周转筐 | D15: =IF($AE15="","",IF($AE15<=1200,IF(INDEX(对接源_01水果!$T$4:$T$1203,$AE15)=0,"",INDEX(对接源_01水果!$T$4:$T$1203,$AE15)),IF(INDEX(对接源_02物料!$T$4:$T$1203,$AE15-1200)=0,"",INDEX(对接源_02物料!$T$4:$T$1203,$AE15-1200)))) -> 213 | E15: =IF($AE15="","",IF($AE15<=1200,IF(INDEX(对接源_01水果!$W$4:$W$1203,$AE15)=0,"",INDEX(对接源_01水果!$W$4:$W$1203,$AE15)),IF(INDEX(对接源_02物料!$W$4:$W$1203,$AE15-1200)=0,"",INDEX(对接源_02物料!$W$4:$W$1203,$AE15-1200)))) -> 豫L*88X19 | F15: =IF($AE15="","",IF($AE15<=1200,"01水果册","02物料册")) -> 02物料册 | G15: =IF($AE15="","",IF($AE15<=1200,IF(INDEX(对接源_01水果!$M$4:$M$1203,$AE15)=0,"",INDEX(对接源_01水果!$M$4:$M$1203,$AE15)),IF(INDEX(对接源_02物料!$M$4:$M$1203,$AE15-1200)=0,"",INDEX(对接源_02物料!$M$4:$M$1203,$AE15-1200)))) | AE15: =IFERROR(MATCH(10,_自动清单!$Q$4:$Q$2403,0),"") -> 1291
A16: =IF($AE16="","",IF($AE16<=1200,IF(INDEX(对接源_01水果!$B$4:$B$1203,$AE16)=0,"",INDEX(对接源_01水果!$B$4:$B$1203,$AE16)),IF(INDEX(对接源_02物料!$B$4:$B$1203,$AE16-1200)=0,"",INDEX(对接源_02物料!$B$4:$B$1203,$AE16-1200)))) -> 46276 | B16: =IF($AE16="","",IF($AE16<=1200,IF(INDEX(对接源_01水果!$E$4:$E$1203,$AE16)=0,"",INDEX(对接源_01水果!$E$4:$E$1203,$AE16)),IF(INDEX(对接源_02物料!$E$4:$E$1203,$AE16-1200)=0,"",INDEX(对接源_02物料!$E$4:$E$1203,$AE16-1200)))) -> NO:0001116 | C16: =IF($AE16="","",IF($AE16<=1200,IF(INDEX(对接源_01水果!$S$4:$S$1203,$AE16)=0,"",INDEX(对接源_01水果!$S$4:$S$1203,$AE16)),IF(INDEX(对接源_02物料!$S$4:$S$1203,$AE16-1200)=0,"",INDEX(对接源_02物料!$S$4:$S$1203,$AE16-1200)))) -> 公司杂周转筐 | D16: =IF($AE16="","",IF($AE16<=1200,IF(INDEX(对接源_01水果!$T$4:$T$1203,$AE16)=0,"",INDEX(对接源_01水果!$T$4:$T$1203,$AE16)),IF(INDEX(对接源_02物料!$T$4:$T$1203,$AE16-1200)=0,"",INDEX(对接源_02物料!$T$4:$T$1203,$AE16-1200)))) -> 423 | E16: =IF($AE16="","",IF($AE16<=1200,IF(INDEX(对接源_01水果!$W$4:$W$1203,$AE16)=0,"",INDEX(对接源_01水果!$W$4:$W$1203,$AE16)),IF(INDEX(对接源_02物料!$W$4:$W$1203,$AE16-1200)=0,"",INDEX(对接源_02物料!$W$4:$W$1203,$AE16-1200)))) -> 豫L*88X19 | F16: =IF($AE16="","",IF($AE16<=1200,"01水果册","02物料册")) -> 02物料册 | G16: =IF($AE16="","",IF($AE16<=1200,IF(INDEX(对接源_01水果!$M$4:$M$1203,$AE16)=0,"",INDEX(对接源_01水果!$M$4:$M$1203,$AE16)),IF(INDEX(对接源_02物料!$M$4:$M$1203,$AE16-1200)=0,"",INDEX(对接源_02物料!$M$4:$M$1203,$AE16-1200)))) | AE16: =IFERROR(MATCH(11,_自动清单!$Q$4:$Q$2403,0),"") -> 1292
A17: =IF($AE17="","",IF($AE17<=1200,IF(INDEX(对接源_01水果!$B$4:$B$1203,$AE17)=0,"",INDEX(对接源_01水果!$B$4:$B$1203,$AE17)),IF(INDEX(对接源_02物料!$B$4:$B$1203,$AE17-1200)=0,"",INDEX(对接源_02物料!$B$4:$B$1203,$AE17-1200)))) -> 46278 | B17: =IF($AE17="","",IF($AE17<=1200,IF(INDEX(对接源_01水果!$E$4:$E$1203,$AE17)=0,"",INDEX(对接源_01水果!$E$4:$E$1203,$AE17)),IF(INDEX(对接源_02物料!$E$4:$E$1203,$AE17-1200)=0,"",INDEX(对接源_02物料!$E$4:$E$1203,$AE17-1200)))) -> NO:0001129 | C17: =IF($AE17="","",IF($AE17<=1200,IF(INDEX(对接源_01水果!$S$4:$S$1203,$AE17)=0,"",INDEX(对接源_01水果!$S$4:$S$1203,$AE17)),IF(INDEX(对接源_02物料!$S$4:$S$1203,$AE17-1200)=0,"",INDEX(对接源_02物料!$S$4:$S$1203,$AE17-1200)))) -> 公司杂周转筐 | D17: =IF($AE17="","",IF($AE17<=1200,IF(INDEX(对接源_01水果!$T$4:$T$1203,$AE17)=0,"",INDEX(对接源_01水果!$T$4:$T$1203,$AE17)),IF(INDEX(对接源_02物料!$T$4:$T$1203,$AE17-1200)=0,"",INDEX(对接源_02物料!$T$4:$T$1203,$AE17-1200)))) -> 423 | E17: =IF($AE17="","",IF($AE17<=1200,IF(INDEX(对接源_01水果!$W$4:$W$1203,$AE17)=0,"",INDEX(对接源_01水果!$W$4:$W$1203,$AE17)),IF(INDEX(对接源_02物料!$W$4:$W$1203,$AE17-1200)=0,"",INDEX(对接源_02物料!$W$4:$W$1203,$AE17-1200)))) -> 豫L*88X19 | F17: =IF($AE17="","",IF($AE17<=1200,"01水果册","02物料册")) -> 02物料册 | G17: =IF($AE17="","",IF($AE17<=1200,IF(INDEX(对接源_01水果!$M$4:$M$1203,$AE17)=0,"",INDEX(对接源_01水果!$M$4:$M$1203,$AE17)),IF(INDEX(对接源_02物料!$M$4:$M$1203,$AE17-1200)=0,"",INDEX(对接源_02物料!$M$4:$M$1203,$AE17-1200)))) | AE17: =IFERROR(MATCH(12,_自动清单!$Q$4:$Q$2403,0),"") -> 1303
A18: =IF($AE18="","",IF($AE18<=1200,IF(INDEX(对接源_01水果!$B$4:$B$1203,$AE18)=0,"",INDEX(对接源_01水果!$B$4:$B$1203,$AE18)),IF(INDEX(对接源_02物料!$B$4:$B$1203,$AE18-1200)=0,"",INDEX(对接源_02物料!$B$4:$B$1203,$AE18-1200)))) -> 46278 | B18: =IF($AE18="","",IF($AE18<=1200,IF(INDEX(对接源_01水果!$E$4:$E$1203,$AE18)=0,"",INDEX(对接源_01水果!$E$4:$E$1203,$AE18)),IF(INDEX(对接源_02物料!$E$4:$E$1203,$AE18-1200)=0,"",INDEX(对接源_02物料!$E$4:$E$1203,$AE18-1200)))) -> NO:0001137 | C18: =IF($AE18="","",IF($AE18<=1200,IF(INDEX(对接源_01水果!$S$4:$S$1203,$AE18)=0,"",INDEX(对接源_01水果!$S$4:$S$1203,$AE18)),IF(INDEX(对接源_02物料!$S$4:$S$1203,$AE18-1200)=0,"",INDEX(对接源_02物料!$S$4:$S$1203,$AE18-1200)))) -> 公司杂周转筐 | D18: =IF($AE18="","",IF($AE18<=1200,IF(INDEX(对接源_01水果!$T$4:$T$1203,$AE18)=0,"",INDEX(对接源_01水果!$T$4:$T$1203,$AE18)),IF(INDEX(对接源_02物料!$T$4:$T$1203,$AE18-1200)=0,"",INDEX(对接源_02物料!$T$4:$T$1203,$AE18-1200)))) -> 711 | E18: =IF($AE18="","",IF($AE18<=1200,IF(INDEX(对接源_01水果!$W$4:$W$1203,$AE18)=0,"",INDEX(对接源_01水果!$W$4:$W$1203,$AE18)),IF(INDEX(对接源_02物料!$W$4:$W$1203,$AE18-1200)=0,"",INDEX(对接源_02物料!$W$4:$W$1203,$AE18-1200)))) -> 新N*53045 | F18: =IF($AE18="","",IF($AE18<=1200,"01水果册","02物料册")) -> 02物料册 | G18: =IF($AE18="","",IF($AE18<=1200,IF(INDEX(对接源_01水果!$M$4:$M$1203,$AE18)=0,"",INDEX(对接源_01水果!$M$4:$M$1203,$AE18)),IF(INDEX(对接源_02物料!$M$4:$M$1203,$AE18-1200)=0,"",INDEX(对接源_02物料!$M$4:$M$1203,$AE18-1200)))) -> 李现东 | AE18: =IFERROR(MATCH(13,_自动清单!$Q$4:$Q$2403,0),"") -> 1308
A19: =IF($AE19="","",IF($AE19<=1200,IF(INDEX(对接源_01水果!$B$4:$B$1203,$AE19)=0,"",INDEX(对接源_01水果!$B$4:$B$1203,$AE19)),IF(INDEX(对接源_02物料!$B$4:$B$1203,$AE19-1200)=0,"",INDEX(对接源_02物料!$B$4:$B$1203,$AE19-1200)))) | B19: =IF($AE19="","",IF($AE19<=1200,IF(INDEX(对接源_01水果!$E$4:$E$1203,$AE19)=0,"",INDEX(对接源_01水果!$E$4:$E$1203,$AE19)),IF(INDEX(对接源_02物料!$E$4:$E$1203,$AE19-1200)=0,"",INDEX(对接源_02物料!$E$4:$E$1203,$AE19-1200)))) | C19: =IF($AE19="","",IF($AE19<=1200,IF(INDEX(对接源_01水果!$S$4:$S$1203,$AE19)=0,"",INDEX(对接源_01水果!$S$4:$S$1203,$AE19)),IF(INDEX(对接源_02物料!$S$4:$S$1203,$AE19-1200)=0,"",INDEX(对接源_02物料!$S$4:$S$1203,$AE19-1200)))) | D19: =IF($AE19="","",IF($AE19<=1200,IF(INDEX(对接源_01水果!$T$4:$T$1203,$AE19)=0,"",INDEX(对接源_01水果!$T$4:$T$1203,$AE19)),IF(INDEX(对接源_02物料!$T$4:$T$1203,$AE19-1200)=0,"",INDEX(对接源_02物料!$T$4:$T$1203,$AE19-1200)))) | E19: =IF($AE19="","",IF($AE19<=1200,IF(INDEX(对接源_01水果!$W$4:$W$1203,$AE19)=0,"",INDEX(对接源_01水果!$W$4:$W$1203,$AE19)),IF(INDEX(对接源_02物料!$W$4:$W$1203,$AE19-1200)=0,"",INDEX(对接源_02物料!$W$4:$W$1203,$AE19-1200)))) | F19: =IF($AE19="","",IF($AE19<=1200,"01水果册","02物料册")) | G19: =IF($AE19="","",IF($AE19<=1200,IF(INDEX(对接源_01水果!$M$4:$M$1203,$AE19)=0,"",INDEX(对接源_01水果!$M$4:$M$1203,$AE19)),IF(INDEX(对接源_02物料!$M$4:$M$1203,$AE19-1200)=0,"",INDEX(对接源_02物料!$M$4:$M$1203,$AE19-1200)))) | AE19: =IFERROR(MATCH(14,_自动清单!$Q$4:$Q$2403,0),"")
A20: =IF($AE20="","",IF($AE20<=1200,IF(INDEX(对接源_01水果!$B$4:$B$1203,$AE20)=0,"",INDEX(对接源_01水果!$B$4:$B$1203,$AE20)),IF(INDEX(对接源_02物料!$B$4:$B$1203,$AE20-1200)=0,"",INDEX(对接源_02物料!$B$4:$B$1203,$AE20-1200)))) | B20: =IF($AE20="","",IF($AE20<=1200,IF(INDEX(对接源_01水果!$E$4:$E$1203,$AE20)=0,"",INDEX(对接源_01水果!$E$4:$E$1203,$AE20)),IF(INDEX(对接源_02物料!$E$4:$E$1203,$AE20-1200)=0,"",INDEX(对接源_02物料!$E$4:$E$1203,$AE20-1200)))) | C20: =IF($AE20="","",IF($AE20<=1200,IF(INDEX(对接源_01水果!$S$4:$S$1203,$AE20)=0,"",INDEX(对接源_01水果!$S$4:$S$1203,$AE20)),IF(INDEX(对接源_02物料!$S$4:$S$1203,$AE20-1200)=0,"",INDEX(对接源_02物料!$S$4:$S$1203,$AE20-1200)))) | D20: =IF($AE20="","",IF($AE20<=1200,IF(INDEX(对接源_01水果!$T$4:$T$1203,$AE20)=0,"",INDEX(对接源_01水果!$T$4:$T$1203,$AE20)),IF(INDEX(对接源_02物料!$T$4:$T$1203,$AE20-1200)=0,"",INDEX(对接源_02物料!$T$4:$T$1203,$AE20-1200)))) | E20: =IF($AE20="","",IF($AE20<=1200,IF(INDEX(对接源_01水果!$W$4:$W$1203,$AE20)=0,"",INDEX(对接源_01水果!$W$4:$W$1203,$AE20)),IF(INDEX(对接源_02物料!$W$4:$W$1203,$AE20-1200)=0,"",INDEX(对接源_02物料!$W$4:$W$1203,$AE20-1200)))) | F20: =IF($AE20="","",IF($AE20<=1200,"01水果册","02物料册")) | G20: =IF($AE20="","",IF($AE20<=1200,IF(INDEX(对接源_01水果!$M$4:$M$1203,$AE20)=0,"",INDEX(对接源_01水果!$M$4:$M$1203,$AE20)),IF(INDEX(对接源_02物料!$M$4:$M$1203,$AE20-1200)=0,"",INDEX(对接源_02物料!$M$4:$M$1203,$AE20-1200)))) | AE20: =IFERROR(MATCH(15,_自动清单!$Q$4:$Q$2403,0),"")
A21: =IF($AE21="","",IF($AE21<=1200,IF(INDEX(对接源_01水果!$B$4:$B$1203,$AE21)=0,"",INDEX(对接源_01水果!$B$4:$B$1203,$AE21)),IF(INDEX(对接源_02物料!$B$4:$B$1203,$AE21-1200)=0,"",INDEX(对接源_02物料!$B$4:$B$1203,$AE21-1200)))) | B21: =IF($AE21="","",IF($AE21<=1200,IF(INDEX(对接源_01水果!$E$4:$E$1203,$AE21)=0,"",INDEX(对接源_01水果!$E$4:$E$1203,$AE21)),IF(INDEX(对接源_02物料!$E$4:$E$1203,$AE21-1200)=0,"",INDEX(对接源_02物料!$E$4:$E$1203,$AE21-1200)))) | C21: =IF($AE21="","",IF($AE21<=1200,IF(INDEX(对接源_01水果!$S$4:$S$1203,$AE21)=0,"",INDEX(对接源_01水果!$S$4:$S$1203,$AE21)),IF(INDEX(对接源_02物料!$S$4:$S$1203,$AE21-1200)=0,"",INDEX(对接源_02物料!$S$4:$S$1203,$AE21-1200)))) | D21: =IF($AE21="","",IF($AE21<=1200,IF(INDEX(对接源_01水果!$T$4:$T$1203,$AE21)=0,"",INDEX(对接源_01水果!$T$4:$T$1203,$AE21)),IF(INDEX(对接源_02物料!$T$4:$T$1203,$AE21-1200)=0,"",INDEX(对接源_02物料!$T$4:$T$1203,$AE21-1200)))) | E21: =IF($AE21="","",IF($AE21<=1200,IF(INDEX(对接源_01水果!$W$4:$W$1203,$AE21)=0,"",INDEX(对接源_01水果!$W$4:$W$1203,$AE21)),IF(INDEX(对接源_02物料!$W$4:$W$1203,$AE21-1200)=0,"",INDEX(对接源_02物料!$W$4:$W$1203,$AE21-1200)))) | F21: =IF($AE21="","",IF($AE21<=1200,"01水果册","02物料册")) | G21: =IF($AE21="","",IF($AE21<=1200,IF(INDEX(对接源_01水果!$M$4:$M$1203,$AE21)=0,"",INDEX(对接源_01水果!$M$4:$M$1203,$AE21)),IF(INDEX(对接源_02物料!$M$4:$M$1203,$AE21-1200)=0,"",INDEX(对接源_02物料!$M$4:$M$1203,$AE21-1200)))) | AE21: =IFERROR(MATCH(16,_自动清单!$Q$4:$Q$2403,0),"")
A22: =IF($AE22="","",IF($AE22<=1200,IF(INDEX(对接源_01水果!$B$4:$B$1203,$AE22)=0,"",INDEX(对接源_01水果!$B$4:$B$1203,$AE22)),IF(INDEX(对接源_02物料!$B$4:$B$1203,$AE22-1200)=0,"",INDEX(对接源_02物料!$B$4:$B$1203,$AE22-1200)))) | B22: =IF($AE22="","",IF($AE22<=1200,IF(INDEX(对接源_01水果!$E$4:$E$1203,$AE22)=0,"",INDEX(对接源_01水果!$E$4:$E$1203,$AE22)),IF(INDEX(对接源_02物料!$E$4:$E$1203,$AE22-1200)=0,"",INDEX(对接源_02物料!$E$4:$E$1203,$AE22-1200)))) | C22: =IF($AE22="","",IF($AE22<=1200,IF(INDEX(对接源_01水果!$S$4:$S$1203,$AE22)=0,"",INDEX(对接源_01水果!$S$4:$S$1203,$AE22)),IF(INDEX(对接源_02物料!$S$4:$S$1203,$AE22-1200)=0,"",INDEX(对接源_02物料!$S$4:$S$1203,$AE22-1200)))) | D22: =IF($AE22="","",IF($AE22<=1200,IF(INDEX(对接源_01水果!$T$4:$T$1203,$AE22)=0,"",INDEX(对接源_01水果!$T$4:$T$1203,$AE22)),IF(INDEX(对接源_02物料!$T$4:$T$1203,$AE22-1200)=0,"",INDEX(对接源_02物料!$T$4:$T$1203,$AE22-1200)))) | E22: =IF($AE22="","",IF($AE22<=1200,IF(INDEX(对接源_01水果!$W$4:$W$1203,$AE22)=0,"",INDEX(对接源_01水果!$W$4:$W$1203,$AE22)),IF(INDEX(对接源_02物料!$W$4:$W$1203,$AE22-1200)=0,"",INDEX(对接源_02物料!$W$4:$W$1203,$AE22-1200)))) | F22: =IF($AE22="","",IF($AE22<=1200,"01水果册","02物料册")) | G22: =IF($AE22="","",IF($AE22<=1200,IF(INDEX(对接源_01水果!$M$4:$M$1203,$AE22)=0,"",INDEX(对接源_01水果!$M$4:$M$1203,$AE22)),IF(INDEX(对接源_02物料!$M$4:$M$1203,$AE22-1200)=0,"",INDEX(对接源_02物料!$M$4:$M$1203,$AE22-1200)))) | AE22: =IFERROR(MATCH(17,_自动清单!$Q$4:$Q$2403,0),"")
A23: =IF($AE23="","",IF($AE23<=1200,IF(INDEX(对接源_01水果!$B$4:$B$1203,$AE23)=0,"",INDEX(对接源_01水果!$B$4:$B$1203,$AE23)),IF(INDEX(对接源_02物料!$B$4:$B$1203,$AE23-1200)=0,"",INDEX(对接源_02物料!$B$4:$B$1203,$AE23-1200)))) | B23: =IF($AE23="","",IF($AE23<=1200,IF(INDEX(对接源_01水果!$E$4:$E$1203,$AE23)=0,"",INDEX(对接源_01水果!$E$4:$E$1203,$AE23)),IF(INDEX(对接源_02物料!$E$4:$E$1203,$AE23-1200)=0,"",INDEX(对接源_02物料!$E$4:$E$1203,$AE23-1200)))) | C23: =IF($AE23="","",IF($AE23<=1200,IF(INDEX(对接源_01水果!$S$4:$S$1203,$AE23)=0,"",INDEX(对接源_01水果!$S$4:$S$1203,$AE23)),IF(INDEX(对接源_02物料!$S$4:$S$1203,$AE23-1200)=0,"",INDEX(对接源_02物料!$S$4:$S$1203,$AE23-1200)))) | D23: =IF($AE23="","",IF($AE23<=1200,IF(INDEX(对接源_01水果!$T$4:$T$1203,$AE23)=0,"",INDEX(对接源_01水果!$T$4:$T$1203,$AE23)),IF(INDEX(对接源_02物料!$T$4:$T$1203,$AE23-1200)=0,"",INDEX(对接源_02物料!$T$4:$T$1203,$AE23-1200)))) | E23: =IF($AE23="","",IF($AE23<=1200,IF(INDEX(对接源_01水果!$W$4:$W$1203,$AE23)=0,"",INDEX(对接源_01水果!$W$4:$W$1203,$AE23)),IF(INDEX(对接源_02物料!$W$4:$W$1203,$AE23-1200)=0,"",INDEX(对接源_02物料!$W$4:$W$1203,$AE23-1200)))) | F23: =IF($AE23="","",IF($AE23<=1200,"01水果册","02物料册")) | G23: =IF($AE23="","",IF($AE23<=1200,IF(INDEX(对接源_01水果!$M$4:$M$1203,$AE23)=0,"",INDEX(对接源_01水果!$M$4:$M$1203,$AE23)),IF(INDEX(对接源_02物料!$M$4:$M$1203,$AE23-1200)=0,"",INDEX(对接源_02物料!$M$4:$M$1203,$AE23-1200)))) | AE23: =IFERROR(MATCH(18,_自动清单!$Q$4:$Q$2403,0),"")
A24: =IF($AE24="","",IF($AE24<=1200,IF(INDEX(对接源_01水果!$B$4:$B$1203,$AE24)=0,"",INDEX(对接源_01水果!$B$4:$B$1203,$AE24)),IF(INDEX(对接源_02物料!$B$4:$B$1203,$AE24-1200)=0,"",INDEX(对接源_02物料!$B$4:$B$1203,$AE24-1200)))) | B24: =IF($AE24="","",IF($AE24<=1200,IF(INDEX(对接源_01水果!$E$4:$E$1203,$AE24)=0,"",INDEX(对接源_01水果!$E$4:$E$1203,$AE24)),IF(INDEX(对接源_02物料!$E$4:$E$1203,$AE24-1200)=0,"",INDEX(对接源_02物料!$E$4:$E$1203,$AE24-1200)))) | C24: =IF($AE24="","",IF($AE24<=1200,IF(INDEX(对接源_01水果!$S$4:$S$1203,$AE24)=0,"",INDEX(对接源_01水果!$S$4:$S$1203,$AE24)),IF(INDEX(对接源_02物料!$S$4:$S$1203,$AE24-1200)=0,"",INDEX(对接源_02物料!$S$4:$S$1203,$AE24-1200)))) | D24: =IF($AE24="","",IF($AE24<=1200,IF(INDEX(对接源_01水果!$T$4:$T$1203,$AE24)=0,"",INDEX(对接源_01水果!$T$4:$T$1203,$AE24)),IF(INDEX(对接源_02物料!$T$4:$T$1203,$AE24-1200)=0,"",INDEX(对接源_02物料!$T$4:$T$1203,$AE24-1200)))) | E24: =IF($AE24="","",IF($AE24<=1200,IF(INDEX(对接源_01水果!$W$4:$W$1203,$AE24)=0,"",INDEX(对接源_01水果!$W$4:$W$1203,$AE24)),IF(INDEX(对接源_02物料!$W$4:$W$1203,$AE24-1200)=0,"",INDEX(对接源_02物料!$W$4:$W$1203,$AE24-1200)))) | F24: =IF($AE24="","",IF($AE24<=1200,"01水果册","02物料册")) | G24: =IF($AE24="","",IF($AE24<=1200,IF(INDEX(对接源_01水果!$M$4:$M$1203,$AE24)=0,"",INDEX(对接源_01水果!$M$4:$M$1203,$AE24)),IF(INDEX(对接源_02物料!$M$4:$M$1203,$AE24-1200)=0,"",INDEX(对接源_02物料!$M$4:$M$1203,$AE24-1200)))) | AE24: =IFERROR(MATCH(19,_自动清单!$Q$4:$Q$2403,0),"")
A25: =IF($AE25="","",IF($AE25<=1200,IF(INDEX(对接源_01水果!$B$4:$B$1203,$AE25)=0,"",INDEX(对接源_01水果!$B$4:$B$1203,$AE25)),IF(INDEX(对接源_02物料!$B$4:$B$1203,$AE25-1200)=0,"",INDEX(对接源_02物料!$B$4:$B$1203,$AE25-1200)))) | B25: =IF($AE25="","",IF($AE25<=1200,IF(INDEX(对接源_01水果!$E$4:$E$1203,$AE25)=0,"",INDEX(对接源_01水果!$E$4:$E$1203,$AE25)),IF(INDEX(对接源_02物料!$E$4:$E$1203,$AE25-1200)=0,"",INDEX(对接源_02物料!$E$4:$E$1203,$AE25-1200)))) | C25: =IF($AE25="","",IF($AE25<=1200,IF(INDEX(对接源_01水果!$S$4:$S$1203,$AE25)=0,"",INDEX(对接源_01水果!$S$4:$S$1203,$AE25)),IF(INDEX(对接源_02物料!$S$4:$S$1203,$AE25-1200)=0,"",INDEX(对接源_02物料!$S$4:$S$1203,$AE25-1200)))) | D25: =IF($AE25="","",IF($AE25<=1200,IF(INDEX(对接源_01水果!$T$4:$T$1203,$AE25)=0,"",INDEX(对接源_01水果!$T$4:$T$1203,$AE25)),IF(INDEX(对接源_02物料!$T$4:$T$1203,$AE25-1200)=0,"",INDEX(对接源_02物料!$T$4:$T$1203,$AE25-1200)))) | E25: =IF($AE25="","",IF($AE25<=1200,IF(INDEX(对接源_01水果!$W$4:$W$1203,$AE25)=0,"",INDEX(对接源_01水果!$W$4:$W$1203,$AE25)),IF(INDEX(对接源_02物料!$W$4:$W$1203,$AE25-1200)=0,"",INDEX(对接源_02物料!$W$4:$W$1203,$AE25-1200)))) | F25: =IF($AE25="","",IF($AE25<=1200,"01水果册","02物料册")) | G25: =IF($AE25="","",IF($AE25<=1200,IF(INDEX(对接源_01水果!$M$4:$M$1203,$AE25)=0,"",INDEX(对接源_01水果!$M$4:$M$1203,$AE25)),IF(INDEX(对接源_02物料!$M$4:$M$1203,$AE25-1200)=0,"",INDEX(对接源_02物料!$M$4:$M$1203,$AE25-1200)))) | AE25: =IFERROR(MATCH(20,_自动清单!$Q$4:$Q$2403,0),"")
A26: =IF($AE26="","",IF($AE26<=1200,IF(INDEX(对接源_01水果!$B$4:$B$1203,$AE26)=0,"",INDEX(对接源_01水果!$B$4:$B$1203,$AE26)),IF(INDEX(对接源_02物料!$B$4:$B$1203,$AE26-1200)=0,"",INDEX(对接源_02物料!$B$4:$B$1203,$AE26-1200)))) | B26: =IF($AE26="","",IF($AE26<=1200,IF(INDEX(对接源_01水果!$E$4:$E$1203,$AE26)=0,"",INDEX(对接源_01水果!$E$4:$E$1203,$AE26)),IF(INDEX(对接源_02物料!$E$4:$E$1203,$AE26-1200)=0,"",INDEX(对接源_02物料!$E$4:$E$1203,$AE26-1200)))) | C26: =IF($AE26="","",IF($AE26<=1200,IF(INDEX(对接源_01水果!$S$4:$S$1203,$AE26)=0,"",INDEX(对接源_01水果!$S$4:$S$1203,$AE26)),IF(INDEX(对接源_02物料!$S$4:$S$1203,$AE26-1200)=0,"",INDEX(对接源_02物料!$S$4:$S$1203,$AE26-1200)))) | D26: =IF($AE26="","",IF($AE26<=1200,IF(INDEX(对接源_01水果!$T$4:$T$1203,$AE26)=0,"",INDEX(对接源_01水果!$T$4:$T$1203,$AE26)),IF(INDEX(对接源_02物料!$T$4:$T$1203,$AE26-1200)=0,"",INDEX(对接源_02物料!$T$4:$T$1203,$AE26-1200)))) | E26: =IF($AE26="","",IF($AE26<=1200,IF(INDEX(对接源_01水果!$W$4:$W$1203,$AE26)=0,"",INDEX(对接源_01水果!$W$4:$W$1203,$AE26)),IF(INDEX(对接源_02物料!$W$4:$W$1203,$AE26-1200)=0,"",INDEX(对接源_02物料!$W$4:$W$1203,$AE26-1200)))) | F26: =IF($AE26="","",IF($AE26<=1200,"01水果册","02物料册")) | G26: =IF($AE26="","",IF($AE26<=1200,IF(INDEX(对接源_01水果!$M$4:$M$1203,$AE26)=0,"",INDEX(对接源_01水果!$M$4:$M$1203,$AE26)),IF(INDEX(对接源_02物料!$M$4:$M$1203,$AE26-1200)=0,"",INDEX(对接源_02物料!$M$4:$M$1203,$AE26-1200)))) | AE26: =IFERROR(MATCH(21,_自动清单!$Q$4:$Q$2403,0),"")
A27: =IF($AE27="","",IF($AE27<=1200,IF(INDEX(对接源_01水果!$B$4:$B$1203,$AE27)=0,"",INDEX(对接源_01水果!$B$4:$B$1203,$AE27)),IF(INDEX(对接源_02物料!$B$4:$B$1203,$AE27-1200)=0,"",INDEX(对接源_02物料!$B$4:$B$1203,$AE27-1200)))) | B27: =IF($AE27="","",IF($AE27<=1200,IF(INDEX(对接源_01水果!$E$4:$E$1203,$AE27)=0,"",INDEX(对接源_01水果!$E$4:$E$1203,$AE27)),IF(INDEX(对接源_02物料!$E$4:$E$1203,$AE27-1200)=0,"",INDEX(对接源_02物料!$E$4:$E$1203,$AE27-1200)))) | C27: =IF($AE27="","",IF($AE27<=1200,IF(INDEX(对接源_01水果!$S$4:$S$1203,$AE27)=0,"",INDEX(对接源_01水果!$S$4:$S$1203,$AE27)),IF(INDEX(对接源_02物料!$S$4:$S$1203,$AE27-1200)=0,"",INDEX(对接源_02物料!$S$4:$S$1203,$AE27-1200)))) | D27: =IF($AE27="","",IF($AE27<=1200,IF(INDEX(对接源_01水果!$T$4:$T$1203,$AE27)=0,"",INDEX(对接源_01水果!$T$4:$T$1203,$AE27)),IF(INDEX(对接源_02物料!$T$4:$T$1203,$AE27-1200)=0,"",INDEX(对接源_02物料!$T$4:$T$1203,$AE27-1200)))) | E27: =IF($AE27="","",IF($AE27<=1200,IF(INDEX(对接源_01水果!$W$4:$W$1203,$AE27)=0,"",INDEX(对接源_01水果!$W$4:$W$1203,$AE27)),IF(INDEX(对接源_02物料!$W$4:$W$1203,$AE27-1200)=0,"",INDEX(对接源_02物料!$W$4:$W$1203,$AE27-1200)))) | F27: =IF($AE27="","",IF($AE27<=1200,"01水果册","02物料册")) | G27: =IF($AE27="","",IF($AE27<=1200,IF(INDEX(对接源_01水果!$M$4:$M$1203,$AE27)=0,"",INDEX(对接源_01水果!$M$4:$M$1203,$AE27)),IF(INDEX(对接源_02物料!$M$4:$M$1203,$AE27-1200)=0,"",INDEX(对接源_02物料!$M$4:$M$1203,$AE27-1200)))) | AE27: =IFERROR(MATCH(22,_自动清单!$Q$4:$Q$2403,0),"")
A28: =IF($AE28="","",IF($AE28<=1200,IF(INDEX(对接源_01水果!$B$4:$B$1203,$AE28)=0,"",INDEX(对接源_01水果!$B$4:$B$1203,$AE28)),IF(INDEX(对接源_02物料!$B$4:$B$1203,$AE28-1200)=0,"",INDEX(对接源_02物料!$B$4:$B$1203,$AE28-1200)))) | B28: =IF($AE28="","",IF($AE28<=1200,IF(INDEX(对接源_01水果!$E$4:$E$1203,$AE28)=0,"",INDEX(对接源_01水果!$E$4:$E$1203,$AE28)),IF(INDEX(对接源_02物料!$E$4:$E$1203,$AE28-1200)=0,"",INDEX(对接源_02物料!$E$4:$E$1203,$AE28-1200)))) | C28: =IF($AE28="","",IF($AE28<=1200,IF(INDEX(对接源_01水果!$S$4:$S$1203,$AE28)=0,"",INDEX(对接源_01水果!$S$4:$S$1203,$AE28)),IF(INDEX(对接源_02物料!$S$4:$S$1203,$AE28-1200)=0,"",INDEX(对接源_02物料!$S$4:$S$1203,$AE28-1200)))) | D28: =IF($AE28="","",IF($AE28<=1200,IF(INDEX(对接源_01水果!$T$4:$T$1203,$AE28)=0,"",INDEX(对接源_01水果!$T$4:$T$1203,$AE28)),IF(INDEX(对接源_02物料!$T$4:$T$1203,$AE28-1200)=0,"",INDEX(对接源_02物料!$T$4:$T$1203,$AE28-1200)))) | E28: =IF($AE28="","",IF($AE28<=1200,IF(INDEX(对接源_01水果!$W$4:$W$1203,$AE28)=0,"",INDEX(对接源_01水果!$W$4:$W$1203,$AE28)),IF(INDEX(对接源_02物料!$W$4:$W$1203,$AE28-1200)=0,"",INDEX(对接源_02物料!$W$4:$W$1203,$AE28-1200)))) | F28: =IF($AE28="","",IF($AE28<=1200,"01水果册","02物料册")) | G28: =IF($AE28="","",IF($AE28<=1200,IF(INDEX(对接源_01水果!$M$4:$M$1203,$AE28)=0,"",INDEX(对接源_01水果!$M$4:$M$1203,$AE28)),IF(INDEX(对接源_02物料!$M$4:$M$1203,$AE28-1200)=0,"",INDEX(对接源_02物料!$M$4:$M$1203,$AE28-1200)))) | AE28: =IFERROR(MATCH(23,_自动清单!$Q$4:$Q$2403,0),"")
A29: =IF($AE29="","",IF($AE29<=1200,IF(INDEX(对接源_01水果!$B$4:$B$1203,$AE29)=0,"",INDEX(对接源_01水果!$B$4:$B$1203,$AE29)),IF(INDEX(对接源_02物料!$B$4:$B$1203,$AE29-1200)=0,"",INDEX(对接源_02物料!$B$4:$B$1203,$AE29-1200)))) | B29: =IF($AE29="","",IF($AE29<=1200,IF(INDEX(对接源_01水果!$E$4:$E$1203,$AE29)=0,"",INDEX(对接源_01水果!$E$4:$E$1203,$AE29)),IF(INDEX(对接源_02物料!$E$4:$E$1203,$AE29-1200)=0,"",INDEX(对接源_02物料!$E$4:$E$1203,$AE29-1200)))) | C29: =IF($AE29="","",IF($AE29<=1200,IF(INDEX(对接源_01水果!$S$4:$S$1203,$AE29)=0,"",INDEX(对接源_01水果!$S$4:$S$1203,$AE29)),IF(INDEX(对接源_02物料!$S$4:$S$1203,$AE29-1200)=0,"",INDEX(对接源_02物料!$S$4:$S$1203,$AE29-1200)))) | D29: =IF($AE29="","",IF($AE29<=1200,IF(INDEX(对接源_01水果!$T$4:$T$1203,$AE29)=0,"",INDEX(对接源_01水果!$T$4:$T$1203,$AE29)),IF(INDEX(对接源_02物料!$T$4:$T$1203,$AE29-1200)=0,"",INDEX(对接源_02物料!$T$4:$T$1203,$AE29-1200)))) | E29: =IF($AE29="","",IF($AE29<=1200,IF(INDEX(对接源_01水果!$W$4:$W$1203,$AE29)=0,"",INDEX(对接源_01水果!$W$4:$W$1203,$AE29)),IF(INDEX(对接源_02物料!$W$4:$W$1203,$AE29-1200)=0,"",INDEX(对接源_02物料!$W$4:$W$1203,$AE29-1200)))) | F29: =IF($AE29="","",IF($AE29<=1200,"01水果册","02物料册")) | G29: =IF($AE29="","",IF($AE29<=1200,IF(INDEX(对接源_01水果!$M$4:$M$1203,$AE29)=0,"",INDEX(对接源_01水果!$M$4:$M$1203,$AE29)),IF(INDEX(对接源_02物料!$M$4:$M$1203,$AE29-1200)=0,"",INDEX(对接源_02物料!$M$4:$M$1203,$AE29-1200)))) | AE29: =IFERROR(MATCH(24,_自动清单!$Q$4:$Q$2403,0),"")
A30: =IF($AE30="","",IF($AE30<=1200,IF(INDEX(对接源_01水果!$B$4:$B$1203,$AE30)=0,"",INDEX(对接源_01水果!$B$4:$B$1203,$AE30)),IF(INDEX(对接源_02物料!$B$4:$B$1203,$AE30-1200)=0,"",INDEX(对接源_02物料!$B$4:$B$1203,$AE30-1200)))) | B30: =IF($AE30="","",IF($AE30<=1200,IF(INDEX(对接源_01水果!$E$4:$E$1203,$AE30)=0,"",INDEX(对接源_01水果!$E$4:$E$1203,$AE30)),IF(INDEX(对接源_02物料!$E$4:$E$1203,$AE30-1200)=0,"",INDEX(对接源_02物料!$E$4:$E$1203,$AE30-1200)))) | C30: =IF($AE30="","",IF($AE30<=1200,IF(INDEX(对接源_01水果!$S$4:$S$1203,$AE30)=0,"",INDEX(对接源_01水果!$S$4:$S$1203,$AE30)),IF(INDEX(对接源_02物料!$S$4:$S$1203,$AE30-1200)=0,"",INDEX(对接源_02物料!$S$4:$S$1203,$AE30-1200)))) | D30: =IF($AE30="","",IF($AE30<=1200,IF(INDEX(对接源_01水果!$T$4:$T$1203,$AE30)=0,"",INDEX(对接源_01水果!$T$4:$T$1203,$AE30)),IF(INDEX(对接源_02物料!$T$4:$T$1203,$AE30-1200)=0,"",INDEX(对接源_02物料!$T$4:$T$1203,$AE30-1200)))) | E30: =IF($AE30="","",IF($AE30<=1200,IF(INDEX(对接源_01水果!$W$4:$W$1203,$AE30)=0,"",INDEX(对接源_01水果!$W$4:$W$1203,$AE30)),IF(INDEX(对接源_02物料!$W$4:$W$1203,$AE30-1200)=0,"",INDEX(对接源_02物料!$W$4:$W$1203,$AE30-1200)))) | F30: =IF($AE30="","",IF($AE30<=1200,"01水果册","02物料册")) | G30: =IF($AE30="","",IF($AE30<=1200,IF(INDEX(对接源_01水果!$M$4:$M$1203,$AE30)=0,"",INDEX(对接源_01水果!$M$4:$M$1203,$AE30)),IF(INDEX(对接源_02物料!$M$4:$M$1203,$AE30-1200)=0,"",INDEX(对接源_02物料!$M$4:$M$1203,$AE30-1200)))) | AE30: =IFERROR(MATCH(25,_自动清单!$Q$4:$Q$2403,0),"")
A31: =IF($AE31="","",IF($AE31<=1200,IF(INDEX(对接源_01水果!$B$4:$B$1203,$AE31)=0,"",INDEX(对接源_01水果!$B$4:$B$1203,$AE31)),IF(INDEX(对接源_02物料!$B$4:$B$1203,$AE31-1200)=0,"",INDEX(对接源_02物料!$B$4:$B$1203,$AE31-1200)))) | B31: =IF($AE31="","",IF($AE31<=1200,IF(INDEX(对接源_01水果!$E$4:$E$1203,$AE31)=0,"",INDEX(对接源_01水果!$E$4:$E$1203,$AE31)),IF(INDEX(对接源_02物料!$E$4:$E$1203,$AE31-1200)=0,"",INDEX(对接源_02物料!$E$4:$E$1203,$AE31-1200)))) | C31: =IF($AE31="","",IF($AE31<=1200,IF(INDEX(对接源_01水果!$S$4:$S$1203,$AE31)=0,"",INDEX(对接源_01水果!$S$4:$S$1203,$AE31)),IF(INDEX(对接源_02物料!$S$4:$S$1203,$AE31-1200)=0,"",INDEX(对接源_02物料!$S$4:$S$1203,$AE31-1200)))) | D31: =IF($AE31="","",IF($AE31<=1200,IF(INDEX(对接源_01水果!$T$4:$T$1203,$AE31)=0,"",INDEX(对接源_01水果!$T$4:$T$1203,$AE31)),IF(INDEX(对接源_02物料!$T$4:$T$1203,$AE31-1200)=0,"",INDEX(对接源_02物料!$T$4:$T$1203,$AE31-1200)))) | E31: =IF($AE31="","",IF($AE31<=1200,IF(INDEX(对接源_01水果!$W$4:$W$1203,$AE31)=0,"",INDEX(对接源_01水果!$W$4:$W$1203,$AE31)),IF(INDEX(对接源_02物料!$W$4:$W$1203,$AE31-1200)=0,"",INDEX(对接源_02物料!$W$4:$W$1203,$AE31-1200)))) | F31: =IF($AE31="","",IF($AE31<=1200,"01水果册","02物料册")) | G31: =IF($AE31="","",IF($AE31<=1200,IF(INDEX(对接源_01水果!$M$4:$M$1203,$AE31)=0,"",INDEX(对接源_01水果!$M$4:$M$1203,$AE31)),IF(INDEX(对接源_02物料!$M$4:$M$1203,$AE31-1200)=0,"",INDEX(对接源_02物料!$M$4:$M$1203,$AE31-1200)))) | AE31: =IFERROR(MATCH(26,_自动清单!$Q$4:$Q$2403,0),"")
A32: =IF($AE32="","",IF($AE32<=1200,IF(INDEX(对接源_01水果!$B$4:$B$1203,$AE32)=0,"",INDEX(对接源_01水果!$B$4:$B$1203,$AE32)),IF(INDEX(对接源_02物料!$B$4:$B$1203,$AE32-1200)=0,"",INDEX(对接源_02物料!$B$4:$B$1203,$AE32-1200)))) | B32: =IF($AE32="","",IF($AE32<=1200,IF(INDEX(对接源_01水果!$E$4:$E$1203,$AE32)=0,"",INDEX(对接源_01水果!$E$4:$E$1203,$AE32)),IF(INDEX(对接源_02物料!$E$4:$E$1203,$AE32-1200)=0,"",INDEX(对接源_02物料!$E$4:$E$1203,$AE32-1200)))) | C32: =IF($AE32="","",IF($AE32<=1200,IF(INDEX(对接源_01水果!$S$4:$S$1203,$AE32)=0,"",INDEX(对接源_01水果!$S$4:$S$1203,$AE32)),IF(INDEX(对接源_02物料!$S$4:$S$1203,$AE32-1200)=0,"",INDEX(对接源_02物料!$S$4:$S$1203,$AE32-1200)))) | D32: =IF($AE32="","",IF($AE32<=1200,IF(INDEX(对接源_01水果!$T$4:$T$1203,$AE32)=0,"",INDEX(对接源_01水果!$T$4:$T$1203,$AE32)),IF(INDEX(对接源_02物料!$T$4:$T$1203,$AE32-1200)=0,"",INDEX(对接源_02物料!$T$4:$T$1203,$AE32-1200)))) | E32: =IF($AE32="","",IF($AE32<=1200,IF(INDEX(对接源_01水果!$W$4:$W$1203,$AE32)=0,"",INDEX(对接源_01水果!$W$4:$W$1203,$AE32)),IF(INDEX(对接源_02物料!$W$4:$W$1203,$AE32-1200)=0,"",INDEX(对接源_02物料!$W$4:$W$1203,$AE32-1200)))) | F32: =IF($AE32="","",IF($AE32<=1200,"01水果册","02物料册")) | G32: =IF($AE32="","",IF($AE32<=1200,IF(INDEX(对接源_01水果!$M$4:$M$1203,$AE32)=0,"",INDEX(对接源_01水果!$M$4:$M$1203,$AE32)),IF(INDEX(对接源_02物料!$M$4:$M$1203,$AE32-1200)=0,"",INDEX(对接源_02物料!$M$4:$M$1203,$AE32-1200)))) | AE32: =IFERROR(MATCH(27,_自动清单!$Q$4:$Q$2403,0),"")
A33: =IF($AE33="","",IF($AE33<=1200,IF(INDEX(对接源_01水果!$B$4:$B$1203,$AE33)=0,"",INDEX(对接源_01水果!$B$4:$B$1203,$AE33)),IF(INDEX(对接源_02物料!$B$4:$B$1203,$AE33-1200)=0,"",INDEX(对接源_02物料!$B$4:$B$1203,$AE33-1200)))) | B33: =IF($AE33="","",IF($AE33<=1200,IF(INDEX(对接源_01水果!$E$4:$E$1203,$AE33)=0,"",INDEX(对接源_01水果!$E$4:$E$1203,$AE33)),IF(INDEX(对接源_02物料!$E$4:$E$1203,$AE33-1200)=0,"",INDEX(对接源_02物料!$E$4:$E$1203,$AE33-1200)))) | C33: =IF($AE33="","",IF($AE33<=1200,IF(INDEX(对接源_01水果!$S$4:$S$1203,$AE33)=0,"",INDEX(对接源_01水果!$S$4:$S$1203,$AE33)),IF(INDEX(对接源_02物料!$S$4:$S$1203,$AE33-1200)=0,"",INDEX(对接源_02物料!$S$4:$S$1203,$AE33-1200)))) | D33: =IF($AE33="","",IF($AE33<=1200,IF(INDEX(对接源_01水果!$T$4:$T$1203,$AE33)=0,"",INDEX(对接源_01水果!$T$4:$T$1203,$AE33)),IF(INDEX(对接源_02物料!$T$4:$T$1203,$AE33-1200)=0,"",INDEX(对接源_02物料!$T$4:$T$1203,$AE33-1200)))) | E33: =IF($AE33="","",IF($AE33<=1200,IF(INDEX(对接源_01水果!$W$4:$W$1203,$AE33)=0,"",INDEX(对接源_01水果!$W$4:$W$1203,$AE33)),IF(INDEX(对接源_02物料!$W$4:$W$1203,$AE33-1200)=0,"",INDEX(对接源_02物料!$W$4:$W$1203,$AE33-1200)))) | F33: =IF($AE33="","",IF($AE33<=1200,"01水果册","02物料册")) | G33: =IF($AE33="","",IF($AE33<=1200,IF(INDEX(对接源_01水果!$M$4:$M$1203,$AE33)=0,"",INDEX(对接源_01水果!$M$4:$M$1203,$AE33)),IF(INDEX(对接源_02物料!$M$4:$M$1203,$AE33-1200)=0,"",INDEX(对接源_02物料!$M$4:$M$1203,$AE33-1200)))) | AE33: =IFERROR(MATCH(28,_自动清单!$Q$4:$Q$2403,0),"")
A34: =IF($AE34="","",IF($AE34<=1200,IF(INDEX(对接源_01水果!$B$4:$B$1203,$AE34)=0,"",INDEX(对接源_01水果!$B$4:$B$1203,$AE34)),IF(INDEX(对接源_02物料!$B$4:$B$1203,$AE34-1200)=0,"",INDEX(对接源_02物料!$B$4:$B$1203,$AE34-1200)))) | B34: =IF($AE34="","",IF($AE34<=1200,IF(INDEX(对接源_01水果!$E$4:$E$1203,$AE34)=0,"",INDEX(对接源_01水果!$E$4:$E$1203,$AE34)),IF(INDEX(对接源_02物料!$E$4:$E$1203,$AE34-1200)=0,"",INDEX(对接源_02物料!$E$4:$E$1203,$AE34-1200)))) | C34: =IF($AE34="","",IF($AE34<=1200,IF(INDEX(对接源_01水果!$S$4:$S$1203,$AE34)=0,"",INDEX(对接源_01水果!$S$4:$S$1203,$AE34)),IF(INDEX(对接源_02物料!$S$4:$S$1203,$AE34-1200)=0,"",INDEX(对接源_02物料!$S$4:$S$1203,$AE34-1200)))) | D34: =IF($AE34="","",IF($AE34<=1200,IF(INDEX(对接源_01水果!$T$4:$T$1203,$AE34)=0,"",INDEX(对接源_01水果!$T$4:$T$1203,$AE34)),IF(INDEX(对接源_02物料!$T$4:$T$1203,$AE34-1200)=0,"",INDEX(对接源_02物料!$T$4:$T$1203,$AE34-1200)))) | E34: =IF($AE34="","",IF($AE34<=1200,IF(INDEX(对接源_01水果!$W$4:$W$1203,$AE34)=0,"",INDEX(对接源_01水果!$W$4:$W$1203,$AE34)),IF(INDEX(对接源_02物料!$W$4:$W$1203,$AE34-1200)=0,"",INDEX(对接源_02物料!$W$4:$W$1203,$AE34-1200)))) | F34: =IF($AE34="","",IF($AE34<=1200,"01水果册","02物料册")) | G34: =IF($AE34="","",IF($AE34<=1200,IF(INDEX(对接源_01水果!$M$4:$M$1203,$AE34)=0,"",INDEX(对接源_01水果!$M$4:$M$1203,$AE34)),IF(INDEX(对接源_02物料!$M$4:$M$1203,$AE34-1200)=0,"",INDEX(对接源_02物料!$M$4:$M$1203,$AE34-1200)))) | AE34: =IFERROR(MATCH(29,_自动清单!$Q$4:$Q$2403,0),"")
A35: =IF($AE35="","",IF($AE35<=1200,IF(INDEX(对接源_01水果!$B$4:$B$1203,$AE35)=0,"",INDEX(对接源_01水果!$B$4:$B$1203,$AE35)),IF(INDEX(对接源_02物料!$B$4:$B$1203,$AE35-1200)=0,"",INDEX(对接源_02物料!$B$4:$B$1203,$AE35-1200)))) | B35: =IF($AE35="","",IF($AE35<=1200,IF(INDEX(对接源_01水果!$E$4:$E$1203,$AE35)=0,"",INDEX(对接源_01水果!$E$4:$E$1203,$AE35)),IF(INDEX(对接源_02物料!$E$4:$E$1203,$AE35-1200)=0,"",INDEX(对接源_02物料!$E$4:$E$1203,$AE35-1200)))) | C35: =IF($AE35="","",IF($AE35<=1200,IF(INDEX(对接源_01水果!$S$4:$S$1203,$AE35)=0,"",INDEX(对接源_01水果!$S$4:$S$1203,$AE35)),IF(INDEX(对接源_02物料!$S$4:$S$1203,$AE35-1200)=0,"",INDEX(对接源_02物料!$S$4:$S$1203,$AE35-1200)))) | D35: =IF($AE35="","",IF($AE35<=1200,IF(INDEX(对接源_01水果!$T$4:$T$1203,$AE35)=0,"",INDEX(对接源_01水果!$T$4:$T$1203,$AE35)),IF(INDEX(对接源_02物料!$T$4:$T$1203,$AE35-1200)=0,"",INDEX(对接源_02物料!$T$4:$T$1203,$AE35-1200)))) | E35: =IF($AE35="","",IF($AE35<=1200,IF(INDEX(对接源_01水果!$W$4:$W$1203,$AE35)=0,"",INDEX(对接源_01水果!$W$4:$W$1203,$AE35)),IF(INDEX(对接源_02物料!$W$4:$W$1203,$AE35-1200)=0,"",INDEX(对接源_02物料!$W$4:$W$1203,$AE35-1200)))) | F35: =IF($AE35="","",IF($AE35<=1200,"01水果册","02物料册")) | G35: =IF($AE35="","",IF($AE35<=1200,IF(INDEX(对接源_01水果!$M$4:$M$1203,$AE35)=0,"",INDEX(对接源_01水果!$M$4:$M$1203,$AE35)),IF(INDEX(对接源_02物料!$M$4:$M$1203,$AE35-1200)=0,"",INDEX(对接源_02物料!$M$4:$M$1203,$AE35-1200)))) | AE35: =IFERROR(MATCH(30,_自动清单!$Q$4:$Q$2403,0),"")
A36: =IF($AE36="","",IF($AE36<=1200,IF(INDEX(对接源_01水果!$B$4:$B$1203,$AE36)=0,"",INDEX(对接源_01水果!$B$4:$B$1203,$AE36)),IF(INDEX(对接源_02物料!$B$4:$B$1203,$AE36-1200)=0,"",INDEX(对接源_02物料!$B$4:$B$1203,$AE36-1200)))) | B36: =IF($AE36="","",IF($AE36<=1200,IF(INDEX(对接源_01水果!$E$4:$E$1203,$AE36)=0,"",INDEX(对接源_01水果!$E$4:$E$1203,$AE36)),IF(INDEX(对接源_02物料!$E$4:$E$1203,$AE36-1200)=0,"",INDEX(对接源_02物料!$E$4:$E$1203,$AE36-1200)))) | C36: =IF($AE36="","",IF($AE36<=1200,IF(INDEX(对接源_01水果!$S$4:$S$1203,$AE36)=0,"",INDEX(对接源_01水果!$S$4:$S$1203,$AE36)),IF(INDEX(对接源_02物料!$S$4:$S$1203,$AE36-1200)=0,"",INDEX(对接源_02物料!$S$4:$S$1203,$AE36-1200)))) | D36: =IF($AE36="","",IF($AE36<=1200,IF(INDEX(对接源_01水果!$T$4:$T$1203,$AE36)=0,"",INDEX(对接源_01水果!$T$4:$T$1203,$AE36)),IF(INDEX(对接源_02物料!$T$4:$T$1203,$AE36-1200)=0,"",INDEX(对接源_02物料!$T$4:$T$1203,$AE36-1200)))) | E36: =IF($AE36="","",IF($AE36<=1200,IF(INDEX(对接源_01水果!$W$4:$W$1203,$AE36)=0,"",INDEX(对接源_01水果!$W$4:$W$1203,$AE36)),IF(INDEX(对接源_02物料!$W$4:$W$1203,$AE36-1200)=0,"",INDEX(对接源_02物料!$W$4:$W$1203,$AE36-1200)))) | F36: =IF($AE36="","",IF($AE36<=1200,"01水果册","02物料册")) | G36: =IF($AE36="","",IF($AE36<=1200,IF(INDEX(对接源_01水果!$M$4:$M$1203,$AE36)=0,"",INDEX(对接源_01水果!$M$4:$M$1203,$AE36)),IF(INDEX(对接源_02物料!$M$4:$M$1203,$AE36-1200)=0,"",INDEX(对接源_02物料!$M$4:$M$1203,$AE36-1200)))) | AE36: =IFERROR(MATCH(31,_自动清单!$Q$4:$Q$2403,0),"")
A37: =IF($AE37="","",IF($AE37<=1200,IF(INDEX(对接源_01水果!$B$4:$B$1203,$AE37)=0,"",INDEX(对接源_01水果!$B$4:$B$1203,$AE37)),IF(INDEX(对接源_02物料!$B$4:$B$1203,$AE37-1200)=0,"",INDEX(对接源_02物料!$B$4:$B$1203,$AE37-1200)))) | B37: =IF($AE37="","",IF($AE37<=1200,IF(INDEX(对接源_01水果!$E$4:$E$1203,$AE37)=0,"",INDEX(对接源_01水果!$E$4:$E$1203,$AE37)),IF(INDEX(对接源_02物料!$E$4:$E$1203,$AE37-1200)=0,"",INDEX(对接源_02物料!$E$4:$E$1203,$AE37-1200)))) | C37: =IF($AE37="","",IF($AE37<=1200,IF(INDEX(对接源_01水果!$S$4:$S$1203,$AE37)=0,"",INDEX(对接源_01水果!$S$4:$S$1203,$AE37)),IF(INDEX(对接源_02物料!$S$4:$S$1203,$AE37-1200)=0,"",INDEX(对接源_02物料!$S$4:$S$1203,$AE37-1200)))) | D37: =IF($AE37="","",IF($AE37<=1200,IF(INDEX(对接源_01水果!$T$4:$T$1203,$AE37)=0,"",INDEX(对接源_01水果!$T$4:$T$1203,$AE37)),IF(INDEX(对接源_02物料!$T$4:$T$1203,$AE37-1200)=0,"",INDEX(对接源_02物料!$T$4:$T$1203,$AE37-1200)))) | E37: =IF($AE37="","",IF($AE37<=1200,IF(INDEX(对接源_01水果!$W$4:$W$1203,$AE37)=0,"",INDEX(对接源_01水果!$W$4:$W$1203,$AE37)),IF(INDEX(对接源_02物料!$W$4:$W$1203,$AE37-1200)=0,"",INDEX(对接源_02物料!$W$4:$W$1203,$AE37-1200)))) | F37: =IF($AE37="","",IF($AE37<=1200,"01水果册","02物料册")) | G37: =IF($AE37="","",IF($AE37<=1200,IF(INDEX(对接源_01水果!$M$4:$M$1203,$AE37)=0,"",INDEX(对接源_01水果!$M$4:$M$1203,$AE37)),IF(INDEX(对接源_02物料!$M$4:$M$1203,$AE37-1200)=0,"",INDEX(对接源_02物料!$M$4:$M$1203,$AE37-1200)))) | AE37: =IFERROR(MATCH(32,_自动清单!$Q$4:$Q$2403,0),"")
A38: =IF($AE38="","",IF($AE38<=1200,IF(INDEX(对接源_01水果!$B$4:$B$1203,$AE38)=0,"",INDEX(对接源_01水果!$B$4:$B$1203,$AE38)),IF(INDEX(对接源_02物料!$B$4:$B$1203,$AE38-1200)=0,"",INDEX(对接源_02物料!$B$4:$B$1203,$AE38-1200)))) | B38: =IF($AE38="","",IF($AE38<=1200,IF(INDEX(对接源_01水果!$E$4:$E$1203,$AE38)=0,"",INDEX(对接源_01水果!$E$4:$E$1203,$AE38)),IF(INDEX(对接源_02物料!$E$4:$E$1203,$AE38-1200)=0,"",INDEX(对接源_02物料!$E$4:$E$1203,$AE38-1200)))) | C38: =IF($AE38="","",IF($AE38<=1200,IF(INDEX(对接源_01水果!$S$4:$S$1203,$AE38)=0,"",INDEX(对接源_01水果!$S$4:$S$1203,$AE38)),IF(INDEX(对接源_02物料!$S$4:$S$1203,$AE38-1200)=0,"",INDEX(对接源_02物料!$S$4:$S$1203,$AE38-1200)))) | D38: =IF($AE38="","",IF($AE38<=1200,IF(INDEX(对接源_01水果!$T$4:$T$1203,$AE38)=0,"",INDEX(对接源_01水果!$T$4:$T$1203,$AE38)),IF(INDEX(对接源_02物料!$T$4:$T$1203,$AE38-1200)=0,"",INDEX(对接源_02物料!$T$4:$T$1203,$AE38-1200)))) | E38: =IF($AE38="","",IF($AE38<=1200,IF(INDEX(对接源_01水果!$W$4:$W$1203,$AE38)=0,"",INDEX(对接源_01水果!$W$4:$W$1203,$AE38)),IF(INDEX(对接源_02物料!$W$4:$W$1203,$AE38-1200)=0,"",INDEX(对接源_02物料!$W$4:$W$1203,$AE38-1200)))) | F38: =IF($AE38="","",IF($AE38<=1200,"01水果册","02物料册")) | G38: =IF($AE38="","",IF($AE38<=1200,IF(INDEX(对接源_01水果!$M$4:$M$1203,$AE38)=0,"",INDEX(对接源_01水果!$M$4:$M$1203,$AE38)),IF(INDEX(对接源_02物料!$M$4:$M$1203,$AE38-1200)=0,"",INDEX(对接源_02物料!$M$4:$M$1203,$AE38-1200)))) | AE38: =IFERROR(MATCH(33,_自动清单!$Q$4:$Q$2403,0),"")
A39: =IF($AE39="","",IF($AE39<=1200,IF(INDEX(对接源_01水果!$B$4:$B$1203,$AE39)=0,"",INDEX(对接源_01水果!$B$4:$B$1203,$AE39)),IF(INDEX(对接源_02物料!$B$4:$B$1203,$AE39-1200)=0,"",INDEX(对接源_02物料!$B$4:$B$1203,$AE39-1200)))) | B39: =IF($AE39="","",IF($AE39<=1200,IF(INDEX(对接源_01水果!$E$4:$E$1203,$AE39)=0,"",INDEX(对接源_01水果!$E$4:$E$1203,$AE39)),IF(INDEX(对接源_02物料!$E$4:$E$1203,$AE39-1200)=0,"",INDEX(对接源_02物料!$E$4:$E$1203,$AE39-1200)))) | C39: =IF($AE39="","",IF($AE39<=1200,IF(INDEX(对接源_01水果!$S$4:$S$1203,$AE39)=0,"",INDEX(对接源_01水果!$S$4:$S$1203,$AE39)),IF(INDEX(对接源_02物料!$S$4:$S$1203,$AE39-1200)=0,"",INDEX(对接源_02物料!$S$4:$S$1203,$AE39-1200)))) | D39: =IF($AE39="","",IF($AE39<=1200,IF(INDEX(对接源_01水果!$T$4:$T$1203,$AE39)=0,"",INDEX(对接源_01水果!$T$4:$T$1203,$AE39)),IF(INDEX(对接源_02物料!$T$4:$T$1203,$AE39-1200)=0,"",INDEX(对接源_02物料!$T$4:$T$1203,$AE39-1200)))) | E39: =IF($AE39="","",IF($AE39<=1200,IF(INDEX(对接源_01水果!$W$4:$W$1203,$AE39)=0,"",INDEX(对接源_01水果!$W$4:$W$1203,$AE39)),IF(INDEX(对接源_02物料!$W$4:$W$1203,$AE39-1200)=0,"",INDEX(对接源_02物料!$W$4:$W$1203,$AE39-1200)))) | F39: =IF($AE39="","",IF($AE39<=1200,"01水果册","02物料册")) | G39: =IF($AE39="","",IF($AE39<=1200,IF(INDEX(对接源_01水果!$M$4:$M$1203,$AE39)=0,"",INDEX(对接源_01水果!$M$4:$M$1203,$AE39)),IF(INDEX(对接源_02物料!$M$4:$M$1203,$AE39-1200)=0,"",INDEX(对接源_02物料!$M$4:$M$1203,$AE39-1200)))) | AE39: =IFERROR(MATCH(34,_自动清单!$Q$4:$Q$2403,0),"")
A40: =IF($AE40="","",IF($AE40<=1200,IF(INDEX(对接源_01水果!$B$4:$B$1203,$AE40)=0,"",INDEX(对接源_01水果!$B$4:$B$1203,$AE40)),IF(INDEX(对接源_02物料!$B$4:$B$1203,$AE40-1200)=0,"",INDEX(对接源_02物料!$B$4:$B$1203,$AE40-1200)))) | B40: =IF($AE40="","",IF($AE40<=1200,IF(INDEX(对接源_01水果!$E$4:$E$1203,$AE40)=0,"",INDEX(对接源_01水果!$E$4:$E$1203,$AE40)),IF(INDEX(对接源_02物料!$E$4:$E$1203,$AE40-1200)=0,"",INDEX(对接源_02物料!$E$4:$E$1203,$AE40-1200)))) | C40: =IF($AE40="","",IF($AE40<=1200,IF(INDEX(对接源_01水果!$S$4:$S$1203,$AE40)=0,"",INDEX(对接源_01水果!$S$4:$S$1203,$AE40)),IF(INDEX(对接源_02物料!$S$4:$S$1203,$AE40-1200)=0,"",INDEX(对接源_02物料!$S$4:$S$1203,$AE40-1200)))) | D40: =IF($AE40="","",IF($AE40<=1200,IF(INDEX(对接源_01水果!$T$4:$T$1203,$AE40)=0,"",INDEX(对接源_01水果!$T$4:$T$1203,$AE40)),IF(INDEX(对接源_02物料!$T$4:$T$1203,$AE40-1200)=0,"",INDEX(对接源_02物料!$T$4:$T$1203,$AE40-1200)))) | E40: =IF($AE40="","",IF($AE40<=1200,IF(INDEX(对接源_01水果!$W$4:$W$1203,$AE40)=0,"",INDEX(对接源_01水果!$W$4:$W$1203,$AE40)),IF(INDEX(对接源_02物料!$W$4:$W$1203,$AE40-1200)=0,"",INDEX(对接源_02物料!$W$4:$W$1203,$AE40-1200)))) | F40: =IF($AE40="","",IF($AE40<=1200,"01水果册","02物料册")) | G40: =IF($AE40="","",IF($AE40<=1200,IF(INDEX(对接源_01水果!$M$4:$M$1203,$AE40)=0,"",INDEX(对接源_01水果!$M$4:$M$1203,$AE40)),IF(INDEX(对接源_02物料!$M$4:$M$1203,$AE40-1200)=0,"",INDEX(对接源_02物料!$M$4:$M$1203,$AE40-1200)))) | AE40: =IFERROR(MATCH(35,_自动清单!$Q$4:$Q$2403,0),"")
A41: =IF($AE41="","",IF($AE41<=1200,IF(INDEX(对接源_01水果!$B$4:$B$1203,$AE41)=0,"",INDEX(对接源_01水果!$B$4:$B$1203,$AE41)),IF(INDEX(对接源_02物料!$B$4:$B$1203,$AE41-1200)=0,"",INDEX(对接源_02物料!$B$4:$B$1203,$AE41-1200)))) | B41: =IF($AE41="","",IF($AE41<=1200,IF(INDEX(对接源_01水果!$E$4:$E$1203,$AE41)=0,"",INDEX(对接源_01水果!$E$4:$E$1203,$AE41)),IF(INDEX(对接源_02物料!$E$4:$E$1203,$AE41-1200)=0,"",INDEX(对接源_02物料!$E$4:$E$1203,$AE41-1200)))) | C41: =IF($AE41="","",IF($AE41<=1200,IF(INDEX(对接源_01水果!$S$4:$S$1203,$AE41)=0,"",INDEX(对接源_01水果!$S$4:$S$1203,$AE41)),IF(INDEX(对接源_02物料!$S$4:$S$1203,$AE41-1200)=0,"",INDEX(对接源_02物料!$S$4:$S$1203,$AE41-1200)))) | D41: =IF($AE41="","",IF($AE41<=1200,IF(INDEX(对接源_01水果!$T$4:$T$1203,$AE41)=0,"",INDEX(对接源_01水果!$T$4:$T$1203,$AE41)),IF(INDEX(对接源_02物料!$T$4:$T$1203,$AE41-1200)=0,"",INDEX(对接源_02物料!$T$4:$T$1203,$AE41-1200)))) | E41: =IF($AE41="","",IF($AE41<=1200,IF(INDEX(对接源_01水果!$W$4:$W$1203,$AE41)=0,"",INDEX(对接源_01水果!$W$4:$W$1203,$AE41)),IF(INDEX(对接源_02物料!$W$4:$W$1203,$AE41-1200)=0,"",INDEX(对接源_02物料!$W$4:$W$1203,$AE41-1200)))) | F41: =IF($AE41="","",IF($AE41<=1200,"01水果册","02物料册")) | G41: =IF($AE41="","",IF($AE41<=1200,IF(INDEX(对接源_01水果!$M$4:$M$1203,$AE41)=0,"",INDEX(对接源_01水果!$M$4:$M$1203,$AE41)),IF(INDEX(对接源_02物料!$M$4:$M$1203,$AE41-1200)=0,"",INDEX(对接源_02物料!$M$4:$M$1203,$AE41-1200)))) | AE41: =IFERROR(MATCH(36,_自动清单!$Q$4:$Q$2403,0),"")
A42: =IF($AE42="","",IF($AE42<=1200,IF(INDEX(对接源_01水果!$B$4:$B$1203,$AE42)=0,"",INDEX(对接源_01水果!$B$4:$B$1203,$AE42)),IF(INDEX(对接源_02物料!$B$4:$B$1203,$AE42-1200)=0,"",INDEX(对接源_02物料!$B$4:$B$1203,$AE42-1200)))) | B42: =IF($AE42="","",IF($AE42<=1200,IF(INDEX(对接源_01水果!$E$4:$E$1203,$AE42)=0,"",INDEX(对接源_01水果!$E$4:$E$1203,$AE42)),IF(INDEX(对接源_02物料!$E$4:$E$1203,$AE42-1200)=0,"",INDEX(对接源_02物料!$E$4:$E$1203,$AE42-1200)))) | C42: =IF($AE42="","",IF($AE42<=1200,IF(INDEX(对接源_01水果!$S$4:$S$1203,$AE42)=0,"",INDEX(对接源_01水果!$S$4:$S$1203,$AE42)),IF(INDEX(对接源_02物料!$S$4:$S$1203,$AE42-1200)=0,"",INDEX(对接源_02物料!$S$4:$S$1203,$AE42-1200)))) | D42: =IF($AE42="","",IF($AE42<=1200,IF(INDEX(对接源_01水果!$T$4:$T$1203,$AE42)=0,"",INDEX(对接源_01水果!$T$4:$T$1203,$AE42)),IF(INDEX(对接源_02物料!$T$4:$T$1203,$AE42-1200)=0,"",INDEX(对接源_02物料!$T$4:$T$1203,$AE42-1200)))) | E42: =IF($AE42="","",IF($AE42<=1200,IF(INDEX(对接源_01水果!$W$4:$W$1203,$AE42)=0,"",INDEX(对接源_01水果!$W$4:$W$1203,$AE42)),IF(INDEX(对接源_02物料!$W$4:$W$1203,$AE42-1200)=0,"",INDEX(对接源_02物料!$W$4:$W$1203,$AE42-1200)))) | F42: =IF($AE42="","",IF($AE42<=1200,"01水果册","02物料册")) | G42: =IF($AE42="","",IF($AE42<=1200,IF(INDEX(对接源_01水果!$M$4:$M$1203,$AE42)=0,"",INDEX(对接源_01水果!$M$4:$M$1203,$AE42)),IF(INDEX(对接源_02物料!$M$4:$M$1203,$AE42-1200)=0,"",INDEX(对接源_02物料!$M$4:$M$1203,$AE42-1200)))) | AE42: =IFERROR(MATCH(37,_自动清单!$Q$4:$Q$2403,0),"")
A43: =IF($AE43="","",IF($AE43<=1200,IF(INDEX(对接源_01水果!$B$4:$B$1203,$AE43)=0,"",INDEX(对接源_01水果!$B$4:$B$1203,$AE43)),IF(INDEX(对接源_02物料!$B$4:$B$1203,$AE43-1200)=0,"",INDEX(对接源_02物料!$B$4:$B$1203,$AE43-1200)))) | B43: =IF($AE43="","",IF($AE43<=1200,IF(INDEX(对接源_01水果!$E$4:$E$1203,$AE43)=0,"",INDEX(对接源_01水果!$E$4:$E$1203,$AE43)),IF(INDEX(对接源_02物料!$E$4:$E$1203,$AE43-1200)=0,"",INDEX(对接源_02物料!$E$4:$E$1203,$AE43-1200)))) | C43: =IF($AE43="","",IF($AE43<=1200,IF(INDEX(对接源_01水果!$S$4:$S$1203,$AE43)=0,"",INDEX(对接源_01水果!$S$4:$S$1203,$AE43)),IF(INDEX(对接源_02物料!$S$4:$S$1203,$AE43-1200)=0,"",INDEX(对接源_02物料!$S$4:$S$1203,$AE43-1200)))) | D43: =IF($AE43="","",IF($AE43<=1200,IF(INDEX(对接源_01水果!$T$4:$T$1203,$AE43)=0,"",INDEX(对接源_01水果!$T$4:$T$1203,$AE43)),IF(INDEX(对接源_02物料!$T$4:$T$1203,$AE43-1200)=0,"",INDEX(对接源_02物料!$T$4:$T$1203,$AE43-1200)))) | E43: =IF($AE43="","",IF($AE43<=1200,IF(INDEX(对接源_01水果!$W$4:$W$1203,$AE43)=0,"",INDEX(对接源_01水果!$W$4:$W$1203,$AE43)),IF(INDEX(对接源_02物料!$W$4:$W$1203,$AE43-1200)=0,"",INDEX(对接源_02物料!$W$4:$W$1203,$AE43-1200)))) | F43: =IF($AE43="","",IF($AE43<=1200,"01水果册","02物料册")) | G43: =IF($AE43="","",IF($AE43<=1200,IF(INDEX(对接源_01水果!$M$4:$M$1203,$AE43)=0,"",INDEX(对接源_01水果!$M$4:$M$1203,$AE43)),IF(INDEX(对接源_02物料!$M$4:$M$1203,$AE43-1200)=0,"",INDEX(对接源_02物料!$M$4:$M$1203,$AE43-1200)))) | AE43: =IFERROR(MATCH(38,_自动清单!$Q$4:$Q$2403,0),"")
A44: =IF($AE44="","",IF($AE44<=1200,IF(INDEX(对接源_01水果!$B$4:$B$1203,$AE44)=0,"",INDEX(对接源_01水果!$B$4:$B$1203,$AE44)),IF(INDEX(对接源_02物料!$B$4:$B$1203,$AE44-1200)=0,"",INDEX(对接源_02物料!$B$4:$B$1203,$AE44-1200)))) | B44: =IF($AE44="","",IF($AE44<=1200,IF(INDEX(对接源_01水果!$E$4:$E$1203,$AE44)=0,"",INDEX(对接源_01水果!$E$4:$E$1203,$AE44)),IF(INDEX(对接源_02物料!$E$4:$E$1203,$AE44-1200)=0,"",INDEX(对接源_02物料!$E$4:$E$1203,$AE44-1200)))) | C44: =IF($AE44="","",IF($AE44<=1200,IF(INDEX(对接源_01水果!$S$4:$S$1203,$AE44)=0,"",INDEX(对接源_01水果!$S$4:$S$1203,$AE44)),IF(INDEX(对接源_02物料!$S$4:$S$1203,$AE44-1200)=0,"",INDEX(对接源_02物料!$S$4:$S$1203,$AE44-1200)))) | D44: =IF($AE44="","",IF($AE44<=1200,IF(INDEX(对接源_01水果!$T$4:$T$1203,$AE44)=0,"",INDEX(对接源_01水果!$T$4:$T$1203,$AE44)),IF(INDEX(对接源_02物料!$T$4:$T$1203,$AE44-1200)=0,"",INDEX(对接源_02物料!$T$4:$T$1203,$AE44-1200)))) | E44: =IF($AE44="","",IF($AE44<=1200,IF(INDEX(对接源_01水果!$W$4:$W$1203,$AE44)=0,"",INDEX(对接源_01水果!$W$4:$W$1203,$AE44)),IF(INDEX(对接源_02物料!$W$4:$W$1203,$AE44-1200)=0,"",INDEX(对接源_02物料!$W$4:$W$1203,$AE44-1200)))) | F44: =IF($AE44="","",IF($AE44<=1200,"01水果册","02物料册")) | G44: =IF($AE44="","",IF($AE44<=1200,IF(INDEX(对接源_01水果!$M$4:$M$1203,$AE44)=0,"",INDEX(对接源_01水果!$M$4:$M$1203,$AE44)),IF(INDEX(对接源_02物料!$M$4:$M$1203,$AE44-1200)=0,"",INDEX(对接源_02物料!$M$4:$M$1203,$AE44-1200)))) | AE44: =IFERROR(MATCH(39,_自动清单!$Q$4:$Q$2403,0),"")
A45: =IF($AE45="","",IF($AE45<=1200,IF(INDEX(对接源_01水果!$B$4:$B$1203,$AE45)=0,"",INDEX(对接源_01水果!$B$4:$B$1203,$AE45)),IF(INDEX(对接源_02物料!$B$4:$B$1203,$AE45-1200)=0,"",INDEX(对接源_02物料!$B$4:$B$1203,$AE45-1200)))) | B45: =IF($AE45="","",IF($AE45<=1200,IF(INDEX(对接源_01水果!$E$4:$E$1203,$AE45)=0,"",INDEX(对接源_01水果!$E$4:$E$1203,$AE45)),IF(INDEX(对接源_02物料!$E$4:$E$1203,$AE45-1200)=0,"",INDEX(对接源_02物料!$E$4:$E$1203,$AE45-1200)))) | C45: =IF($AE45="","",IF($AE45<=1200,IF(INDEX(对接源_01水果!$S$4:$S$1203,$AE45)=0,"",INDEX(对接源_01水果!$S$4:$S$1203,$AE45)),IF(INDEX(对接源_02物料!$S$4:$S$1203,$AE45-1200)=0,"",INDEX(对接源_02物料!$S$4:$S$1203,$AE45-1200)))) | D45: =IF($AE45="","",IF($AE45<=1200,IF(INDEX(对接源_01水果!$T$4:$T$1203,$AE45)=0,"",INDEX(对接源_01水果!$T$4:$T$1203,$AE45)),IF(INDEX(对接源_02物料!$T$4:$T$1203,$AE45-1200)=0,"",INDEX(对接源_02物料!$T$4:$T$1203,$AE45-1200)))) | E45: =IF($AE45="","",IF($AE45<=1200,IF(INDEX(对接源_01水果!$W$4:$W$1203,$AE45)=0,"",INDEX(对接源_01水果!$W$4:$W$1203,$AE45)),IF(INDEX(对接源_02物料!$W$4:$W$1203,$AE45-1200)=0,"",INDEX(对接源_02物料!$W$4:$W$1203,$AE45-1200)))) | F45: =IF($AE45="","",IF($AE45<=1200,"01水果册","02物料册")) | G45: =IF($AE45="","",IF($AE45<=1200,IF(INDEX(对接源_01水果!$M$4:$M$1203,$AE45)=0,"",INDEX(对接源_01水果!$M$4:$M$1203,$AE45)),IF(INDEX(对接源_02物料!$M$4:$M$1203,$AE45-1200)=0,"",INDEX(对接源_02物料!$M$4:$M$1203,$AE45-1200)))) | AE45: =IFERROR(MATCH(40,_自动清单!$Q$4:$Q$2403,0),"")
A46: =IF($AE46="","",IF($AE46<=1200,IF(INDEX(对接源_01水果!$B$4:$B$1203,$AE46)=0,"",INDEX(对接源_01水果!$B$4:$B$1203,$AE46)),IF(INDEX(对接源_02物料!$B$4:$B$1203,$AE46-1200)=0,"",INDEX(对接源_02物料!$B$4:$B$1203,$AE46-1200)))) | B46: =IF($AE46="","",IF($AE46<=1200,IF(INDEX(对接源_01水果!$E$4:$E$1203,$AE46)=0,"",INDEX(对接源_01水果!$E$4:$E$1203,$AE46)),IF(INDEX(对接源_02物料!$E$4:$E$1203,$AE46-1200)=0,"",INDEX(对接源_02物料!$E$4:$E$1203,$AE46-1200)))) | C46: =IF($AE46="","",IF($AE46<=1200,IF(INDEX(对接源_01水果!$S$4:$S$1203,$AE46)=0,"",INDEX(对接源_01水果!$S$4:$S$1203,$AE46)),IF(INDEX(对接源_02物料!$S$4:$S$1203,$AE46-1200)=0,"",INDEX(对接源_02物料!$S$4:$S$1203,$AE46-1200)))) | D46: =IF($AE46="","",IF($AE46<=1200,IF(INDEX(对接源_01水果!$T$4:$T$1203,$AE46)=0,"",INDEX(对接源_01水果!$T$4:$T$1203,$AE46)),IF(INDEX(对接源_02物料!$T$4:$T$1203,$AE46-1200)=0,"",INDEX(对接源_02物料!$T$4:$T$1203,$AE46-1200)))) | E46: =IF($AE46="","",IF($AE46<=1200,IF(INDEX(对接源_01水果!$W$4:$W$1203,$AE46)=0,"",INDEX(对接源_01水果!$W$4:$W$1203,$AE46)),IF(INDEX(对接源_02物料!$W$4:$W$1203,$AE46-1200)=0,"",INDEX(对接源_02物料!$W$4:$W$1203,$AE46-1200)))) | F46: =IF($AE46="","",IF($AE46<=1200,"01水果册","02物料册")) | G46: =IF($AE46="","",IF($AE46<=1200,IF(INDEX(对接源_01水果!$M$4:$M$1203,$AE46)=0,"",INDEX(对接源_01水果!$M$4:$M$1203,$AE46)),IF(INDEX(对接源_02物料!$M$4:$M$1203,$AE46-1200)=0,"",INDEX(对接源_02物料!$M$4:$M$1203,$AE46-1200)))) | AE46: =IFERROR(MATCH(41,_自动清单!$Q$4:$Q$2403,0),"")
A47: =IF($AE47="","",IF($AE47<=1200,IF(INDEX(对接源_01水果!$B$4:$B$1203,$AE47)=0,"",INDEX(对接源_01水果!$B$4:$B$1203,$AE47)),IF(INDEX(对接源_02物料!$B$4:$B$1203,$AE47-1200)=0,"",INDEX(对接源_02物料!$B$4:$B$1203,$AE47-1200)))) | B47: =IF($AE47="","",IF($AE47<=1200,IF(INDEX(对接源_01水果!$E$4:$E$1203,$AE47)=0,"",INDEX(对接源_01水果!$E$4:$E$1203,$AE47)),IF(INDEX(对接源_02物料!$E$4:$E$1203,$AE47-1200)=0,"",INDEX(对接源_02物料!$E$4:$E$1203,$AE47-1200)))) | C47: =IF($AE47="","",IF($AE47<=1200,IF(INDEX(对接源_01水果!$S$4:$S$1203,$AE47)=0,"",INDEX(对接源_01水果!$S$4:$S$1203,$AE47)),IF(INDEX(对接源_02物料!$S$4:$S$1203,$AE47-1200)=0,"",INDEX(对接源_02物料!$S$4:$S$1203,$AE47-1200)))) | D47: =IF($AE47="","",IF($AE47<=1200,IF(INDEX(对接源_01水果!$T$4:$T$1203,$AE47)=0,"",INDEX(对接源_01水果!$T$4:$T$1203,$AE47)),IF(INDEX(对接源_02物料!$T$4:$T$1203,$AE47-1200)=0,"",INDEX(对接源_02物料!$T$4:$T$1203,$AE47-1200)))) | E47: =IF($AE47="","",IF($AE47<=1200,IF(INDEX(对接源_01水果!$W$4:$W$1203,$AE47)=0,"",INDEX(对接源_01水果!$W$4:$W$1203,$AE47)),IF(INDEX(对接源_02物料!$W$4:$W$1203,$AE47-1200)=0,"",INDEX(对接源_02物料!$W$4:$W$1203,$AE47-1200)))) | F47: =IF($AE47="","",IF($AE47<=1200,"01水果册","02物料册")) | G47: =IF($AE47="","",IF($AE47<=1200,IF(INDEX(对接源_01水果!$M$4:$M$1203,$AE47)=0,"",INDEX(对接源_01水果!$M$4:$M$1203,$AE47)),IF(INDEX(对接源_02物料!$M$4:$M$1203,$AE47-1200)=0,"",INDEX(对接源_02物料!$M$4:$M$1203,$AE47-1200)))) | AE47: =IFERROR(MATCH(42,_自动清单!$Q$4:$Q$2403,0),"")
A48: =IF($AE48="","",IF($AE48<=1200,IF(INDEX(对接源_01水果!$B$4:$B$1203,$AE48)=0,"",INDEX(对接源_01水果!$B$4:$B$1203,$AE48)),IF(INDEX(对接源_02物料!$B$4:$B$1203,$AE48-1200)=0,"",INDEX(对接源_02物料!$B$4:$B$1203,$AE48-1200)))) | B48: =IF($AE48="","",IF($AE48<=1200,IF(INDEX(对接源_01水果!$E$4:$E$1203,$AE48)=0,"",INDEX(对接源_01水果!$E$4:$E$1203,$AE48)),IF(INDEX(对接源_02物料!$E$4:$E$1203,$AE48-1200)=0,"",INDEX(对接源_02物料!$E$4:$E$1203,$AE48-1200)))) | C48: =IF($AE48="","",IF($AE48<=1200,IF(INDEX(对接源_01水果!$S$4:$S$1203,$AE48)=0,"",INDEX(对接源_01水果!$S$4:$S$1203,$AE48)),IF(INDEX(对接源_02物料!$S$4:$S$1203,$AE48-1200)=0,"",INDEX(对接源_02物料!$S$4:$S$1203,$AE48-1200)))) | D48: =IF($AE48="","",IF($AE48<=1200,IF(INDEX(对接源_01水果!$T$4:$T$1203,$AE48)=0,"",INDEX(对接源_01水果!$T$4:$T$1203,$AE48)),IF(INDEX(对接源_02物料!$T$4:$T$1203,$AE48-1200)=0,"",INDEX(对接源_02物料!$T$4:$T$1203,$AE48-1200)))) | E48: =IF($AE48="","",IF($AE48<=1200,IF(INDEX(对接源_01水果!$W$4:$W$1203,$AE48)=0,"",INDEX(对接源_01水果!$W$4:$W$1203,$AE48)),IF(INDEX(对接源_02物料!$W$4:$W$1203,$AE48-1200)=0,"",INDEX(对接源_02物料!$W$4:$W$1203,$AE48-1200)))) | F48: =IF($AE48="","",IF($AE48<=1200,"01水果册","02物料册")) | G48: =IF($AE48="","",IF($AE48<=1200,IF(INDEX(对接源_01水果!$M$4:$M$1203,$AE48)=0,"",INDEX(对接源_01水果!$M$4:$M$1203,$AE48)),IF(INDEX(对接源_02物料!$M$4:$M$1203,$AE48-1200)=0,"",INDEX(对接源_02物料!$M$4:$M$1203,$AE48-1200)))) | AE48: =IFERROR(MATCH(43,_自动清单!$Q$4:$Q$2403,0),"")
A49: =IF($AE49="","",IF($AE49<=1200,IF(INDEX(对接源_01水果!$B$4:$B$1203,$AE49)=0,"",INDEX(对接源_01水果!$B$4:$B$1203,$AE49)),IF(INDEX(对接源_02物料!$B$4:$B$1203,$AE49-1200)=0,"",INDEX(对接源_02物料!$B$4:$B$1203,$AE49-1200)))) | B49: =IF($AE49="","",IF($AE49<=1200,IF(INDEX(对接源_01水果!$E$4:$E$1203,$AE49)=0,"",INDEX(对接源_01水果!$E$4:$E$1203,$AE49)),IF(INDEX(对接源_02物料!$E$4:$E$1203,$AE49-1200)=0,"",INDEX(对接源_02物料!$E$4:$E$1203,$AE49-1200)))) | C49: =IF($AE49="","",IF($AE49<=1200,IF(INDEX(对接源_01水果!$S$4:$S$1203,$AE49)=0,"",INDEX(对接源_01水果!$S$4:$S$1203,$AE49)),IF(INDEX(对接源_02物料!$S$4:$S$1203,$AE49-1200)=0,"",INDEX(对接源_02物料!$S$4:$S$1203,$AE49-1200)))) | D49: =IF($AE49="","",IF($AE49<=1200,IF(INDEX(对接源_01水果!$T$4:$T$1203,$AE49)=0,"",INDEX(对接源_01水果!$T$4:$T$1203,$AE49)),IF(INDEX(对接源_02物料!$T$4:$T$1203,$AE49-1200)=0,"",INDEX(对接源_02物料!$T$4:$T$1203,$AE49-1200)))) | E49: =IF($AE49="","",IF($AE49<=1200,IF(INDEX(对接源_01水果!$W$4:$W$1203,$AE49)=0,"",INDEX(对接源_01水果!$W$4:$W$1203,$AE49)),IF(INDEX(对接源_02物料!$W$4:$W$1203,$AE49-1200)=0,"",INDEX(对接源_02物料!$W$4:$W$1203,$AE49-1200)))) | F49: =IF($AE49="","",IF($AE49<=1200,"01水果册","02物料册")) | G49: =IF($AE49="","",IF($AE49<=1200,IF(INDEX(对接源_01水果!$M$4:$M$1203,$AE49)=0,"",INDEX(对接源_01水果!$M$4:$M$1203,$AE49)),IF(INDEX(对接源_02物料!$M$4:$M$1203,$AE49-1200)=0,"",INDEX(对接源_02物料!$M$4:$M$1203,$AE49-1200)))) | AE49: =IFERROR(MATCH(44,_自动清单!$Q$4:$Q$2403,0),"")
A50: =IF($AE50="","",IF($AE50<=1200,IF(INDEX(对接源_01水果!$B$4:$B$1203,$AE50)=0,"",INDEX(对接源_01水果!$B$4:$B$1203,$AE50)),IF(INDEX(对接源_02物料!$B$4:$B$1203,$AE50-1200)=0,"",INDEX(对接源_02物料!$B$4:$B$1203,$AE50-1200)))) | B50: =IF($AE50="","",IF($AE50<=1200,IF(INDEX(对接源_01水果!$E$4:$E$1203,$AE50)=0,"",INDEX(对接源_01水果!$E$4:$E$1203,$AE50)),IF(INDEX(对接源_02物料!$E$4:$E$1203,$AE50-1200)=0,"",INDEX(对接源_02物料!$E$4:$E$1203,$AE50-1200)))) | C50: =IF($AE50="","",IF($AE50<=1200,IF(INDEX(对接源_01水果!$S$4:$S$1203,$AE50)=0,"",INDEX(对接源_01水果!$S$4:$S$1203,$AE50)),IF(INDEX(对接源_02物料!$S$4:$S$1203,$AE50-1200)=0,"",INDEX(对接源_02物料!$S$4:$S$1203,$AE50-1200)))) | D50: =IF($AE50="","",IF($AE50<=1200,IF(INDEX(对接源_01水果!$T$4:$T$1203,$AE50)=0,"",INDEX(对接源_01水果!$T$4:$T$1203,$AE50)),IF(INDEX(对接源_02物料!$T$4:$T$1203,$AE50-1200)=0,"",INDEX(对接源_02物料!$T$4:$T$1203,$AE50-1200)))) | E50: =IF($AE50="","",IF($AE50<=1200,IF(INDEX(对接源_01水果!$W$4:$W$1203,$AE50)=0,"",INDEX(对接源_01水果!$W$4:$W$1203,$AE50)),IF(INDEX(对接源_02物料!$W$4:$W$1203,$AE50-1200)=0,"",INDEX(对接源_02物料!$W$4:$W$1203,$AE50-1200)))) | F50: =IF($AE50="","",IF($AE50<=1200,"01水果册","02物料册")) | G50: =IF($AE50="","",IF($AE50<=1200,IF(INDEX(对接源_01水果!$M$4:$M$1203,$AE50)=0,"",INDEX(对接源_01水果!$M$4:$M$1203,$AE50)),IF(INDEX(对接源_02物料!$M$4:$M$1203,$AE50-1200)=0,"",INDEX(对接源_02物料!$M$4:$M$1203,$AE50-1200)))) | AE50: =IFERROR(MATCH(45,_自动清单!$Q$4:$Q$2403,0),"")
A51: =IF($AE51="","",IF($AE51<=1200,IF(INDEX(对接源_01水果!$B$4:$B$1203,$AE51)=0,"",INDEX(对接源_01水果!$B$4:$B$1203,$AE51)),IF(INDEX(对接源_02物料!$B$4:$B$1203,$AE51-1200)=0,"",INDEX(对接源_02物料!$B$4:$B$1203,$AE51-1200)))) | B51: =IF($AE51="","",IF($AE51<=1200,IF(INDEX(对接源_01水果!$E$4:$E$1203,$AE51)=0,"",INDEX(对接源_01水果!$E$4:$E$1203,$AE51)),IF(INDEX(对接源_02物料!$E$4:$E$1203,$AE51-1200)=0,"",INDEX(对接源_02物料!$E$4:$E$1203,$AE51-1200)))) | C51: =IF($AE51="","",IF($AE51<=1200,IF(INDEX(对接源_01水果!$S$4:$S$1203,$AE51)=0,"",INDEX(对接源_01水果!$S$4:$S$1203,$AE51)),IF(INDEX(对接源_02物料!$S$4:$S$1203,$AE51-1200)=0,"",INDEX(对接源_02物料!$S$4:$S$1203,$AE51-1200)))) | D51: =IF($AE51="","",IF($AE51<=1200,IF(INDEX(对接源_01水果!$T$4:$T$1203,$AE51)=0,"",INDEX(对接源_01水果!$T$4:$T$1203,$AE51)),IF(INDEX(对接源_02物料!$T$4:$T$1203,$AE51-1200)=0,"",INDEX(对接源_02物料!$T$4:$T$1203,$AE51-1200)))) | E51: =IF($AE51="","",IF($AE51<=1200,IF(INDEX(对接源_01水果!$W$4:$W$1203,$AE51)=0,"",INDEX(对接源_01水果!$W$4:$W$1203,$AE51)),IF(INDEX(对接源_02物料!$W$4:$W$1203,$AE51-1200)=0,"",INDEX(对接源_02物料!$W$4:$W$1203,$AE51-1200)))) | F51: =IF($AE51="","",IF($AE51<=1200,"01水果册","02物料册")) | G51: =IF($AE51="","",IF($AE51<=1200,IF(INDEX(对接源_01水果!$M$4:$M$1203,$AE51)=0,"",INDEX(对接源_01水果!$M$4:$M$1203,$AE51)),IF(INDEX(对接源_02物料!$M$4:$M$1203,$AE51-1200)=0,"",INDEX(对接源_02物料!$M$4:$M$1203,$AE51-1200)))) | AE51: =IFERROR(MATCH(46,_自动清单!$Q$4:$Q$2403,0),"")
A52: =IF($AE52="","",IF($AE52<=1200,IF(INDEX(对接源_01水果!$B$4:$B$1203,$AE52)=0,"",INDEX(对接源_01水果!$B$4:$B$1203,$AE52)),IF(INDEX(对接源_02物料!$B$4:$B$1203,$AE52-1200)=0,"",INDEX(对接源_02物料!$B$4:$B$1203,$AE52-1200)))) | B52: =IF($AE52="","",IF($AE52<=1200,IF(INDEX(对接源_01水果!$E$4:$E$1203,$AE52)=0,"",INDEX(对接源_01水果!$E$4:$E$1203,$AE52)),IF(INDEX(对接源_02物料!$E$4:$E$1203,$AE52-1200)=0,"",INDEX(对接源_02物料!$E$4:$E$1203,$AE52-1200)))) | C52: =IF($AE52="","",IF($AE52<=1200,IF(INDEX(对接源_01水果!$S$4:$S$1203,$AE52)=0,"",INDEX(对接源_01水果!$S$4:$S$1203,$AE52)),IF(INDEX(对接源_02物料!$S$4:$S$1203,$AE52-1200)=0,"",INDEX(对接源_02物料!$S$4:$S$1203,$AE52-1200)))) | D52: =IF($AE52="","",IF($AE52<=1200,IF(INDEX(对接源_01水果!$T$4:$T$1203,$AE52)=0,"",INDEX(对接源_01水果!$T$4:$T$1203,$AE52)),IF(INDEX(对接源_02物料!$T$4:$T$1203,$AE52-1200)=0,"",INDEX(对接源_02物料!$T$4:$T$1203,$AE52-1200)))) | E52: =IF($AE52="","",IF($AE52<=1200,IF(INDEX(对接源_01水果!$W$4:$W$1203,$AE52)=0,"",INDEX(对接源_01水果!$W$4:$W$1203,$AE52)),IF(INDEX(对接源_02物料!$W$4:$W$1203,$AE52-1200)=0,"",INDEX(对接源_02物料!$W$4:$W$1203,$AE52-1200)))) | F52: =IF($AE52="","",IF($AE52<=1200,"01水果册","02物料册")) | G52: =IF($AE52="","",IF($AE52<=1200,IF(INDEX(对接源_01水果!$M$4:$M$1203,$AE52)=0,"",INDEX(对接源_01水果!$M$4:$M$1203,$AE52)),IF(INDEX(对接源_02物料!$M$4:$M$1203,$AE52-1200)=0,"",INDEX(对接源_02物料!$M$4:$M$1203,$AE52-1200)))) | AE52: =IFERROR(MATCH(47,_自动清单!$Q$4:$Q$2403,0),"")
A53: =IF($AE53="","",IF($AE53<=1200,IF(INDEX(对接源_01水果!$B$4:$B$1203,$AE53)=0,"",INDEX(对接源_01水果!$B$4:$B$1203,$AE53)),IF(INDEX(对接源_02物料!$B$4:$B$1203,$AE53-1200)=0,"",INDEX(对接源_02物料!$B$4:$B$1203,$AE53-1200)))) | B53: =IF($AE53="","",IF($AE53<=1200,IF(INDEX(对接源_01水果!$E$4:$E$1203,$AE53)=0,"",INDEX(对接源_01水果!$E$4:$E$1203,$AE53)),IF(INDEX(对接源_02物料!$E$4:$E$1203,$AE53-1200)=0,"",INDEX(对接源_02物料!$E$4:$E$1203,$AE53-1200)))) | C53: =IF($AE53="","",IF($AE53<=1200,IF(INDEX(对接源_01水果!$S$4:$S$1203,$AE53)=0,"",INDEX(对接源_01水果!$S$4:$S$1203,$AE53)),IF(INDEX(对接源_02物料!$S$4:$S$1203,$AE53-1200)=0,"",INDEX(对接源_02物料!$S$4:$S$1203,$AE53-1200)))) | D53: =IF($AE53="","",IF($AE53<=1200,IF(INDEX(对接源_01水果!$T$4:$T$1203,$AE53)=0,"",INDEX(对接源_01水果!$T$4:$T$1203,$AE53)),IF(INDEX(对接源_02物料!$T$4:$T$1203,$AE53-1200)=0,"",INDEX(对接源_02物料!$T$4:$T$1203,$AE53-1200)))) | E53: =IF($AE53="","",IF($AE53<=1200,IF(INDEX(对接源_01水果!$W$4:$W$1203,$AE53)=0,"",INDEX(对接源_01水果!$W$4:$W$1203,$AE53)),IF(INDEX(对接源_02物料!$W$4:$W$1203,$AE53-1200)=0,"",INDEX(对接源_02物料!$W$4:$W$1203,$AE53-1200)))) | F53: =IF($AE53="","",IF($AE53<=1200,"01水果册","02物料册")) | G53: =IF($AE53="","",IF($AE53<=1200,IF(INDEX(对接源_01水果!$M$4:$M$1203,$AE53)=0,"",INDEX(对接源_01水果!$M$4:$M$1203,$AE53)),IF(INDEX(对接源_02物料!$M$4:$M$1203,$AE53-1200)=0,"",INDEX(对接源_02物料!$M$4:$M$1203,$AE53-1200)))) | AE53: =IFERROR(MATCH(48,_自动清单!$Q$4:$Q$2403,0),"")
A54: =IF($AE54="","",IF($AE54<=1200,IF(INDEX(对接源_01水果!$B$4:$B$1203,$AE54)=0,"",INDEX(对接源_01水果!$B$4:$B$1203,$AE54)),IF(INDEX(对接源_02物料!$B$4:$B$1203,$AE54-1200)=0,"",INDEX(对接源_02物料!$B$4:$B$1203,$AE54-1200)))) | B54: =IF($AE54="","",IF($AE54<=1200,IF(INDEX(对接源_01水果!$E$4:$E$1203,$AE54)=0,"",INDEX(对接源_01水果!$E$4:$E$1203,$AE54)),IF(INDEX(对接源_02物料!$E$4:$E$1203,$AE54-1200)=0,"",INDEX(对接源_02物料!$E$4:$E$1203,$AE54-1200)))) | C54: =IF($AE54="","",IF($AE54<=1200,IF(INDEX(对接源_01水果!$S$4:$S$1203,$AE54)=0,"",INDEX(对接源_01水果!$S$4:$S$1203,$AE54)),IF(INDEX(对接源_02物料!$S$4:$S$1203,$AE54-1200)=0,"",INDEX(对接源_02物料!$S$4:$S$1203,$AE54-1200)))) | D54: =IF($AE54="","",IF($AE54<=1200,IF(INDEX(对接源_01水果!$T$4:$T$1203,$AE54)=0,"",INDEX(对接源_01水果!$T$4:$T$1203,$AE54)),IF(INDEX(对接源_02物料!$T$4:$T$1203,$AE54-1200)=0,"",INDEX(对接源_02物料!$T$4:$T$1203,$AE54-1200)))) | E54: =IF($AE54="","",IF($AE54<=1200,IF(INDEX(对接源_01水果!$W$4:$W$1203,$AE54)=0,"",INDEX(对接源_01水果!$W$4:$W$1203,$AE54)),IF(INDEX(对接源_02物料!$W$4:$W$1203,$AE54-1200)=0,"",INDEX(对接源_02物料!$W$4:$W$1203,$AE54-1200)))) | F54: =IF($AE54="","",IF($AE54<=1200,"01水果册","02物料册")) | G54: =IF($AE54="","",IF($AE54<=1200,IF(INDEX(对接源_01水果!$M$4:$M$1203,$AE54)=0,"",INDEX(对接源_01水果!$M$4:$M$1203,$AE54)),IF(INDEX(对接源_02物料!$M$4:$M$1203,$AE54-1200)=0,"",INDEX(对接源_02物料!$M$4:$M$1203,$AE54-1200)))) | AE54: =IFERROR(MATCH(49,_自动清单!$Q$4:$Q$2403,0),"")
A55: =IF($AE55="","",IF($AE55<=1200,IF(INDEX(对接源_01水果!$B$4:$B$1203,$AE55)=0,"",INDEX(对接源_01水果!$B$4:$B$1203,$AE55)),IF(INDEX(对接源_02物料!$B$4:$B$1203,$AE55-1200)=0,"",INDEX(对接源_02物料!$B$4:$B$1203,$AE55-1200)))) | B55: =IF($AE55="","",IF($AE55<=1200,IF(INDEX(对接源_01水果!$E$4:$E$1203,$AE55)=0,"",INDEX(对接源_01水果!$E$4:$E$1203,$AE55)),IF(INDEX(对接源_02物料!$E$4:$E$1203,$AE55-1200)=0,"",INDEX(对接源_02物料!$E$4:$E$1203,$AE55-1200)))) | C55: =IF($AE55="","",IF($AE55<=1200,IF(INDEX(对接源_01水果!$S$4:$S$1203,$AE55)=0,"",INDEX(对接源_01水果!$S$4:$S$1203,$AE55)),IF(INDEX(对接源_02物料!$S$4:$S$1203,$AE55-1200)=0,"",INDEX(对接源_02物料!$S$4:$S$1203,$AE55-1200)))) | D55: =IF($AE55="","",IF($AE55<=1200,IF(INDEX(对接源_01水果!$T$4:$T$1203,$AE55)=0,"",INDEX(对接源_01水果!$T$4:$T$1203,$AE55)),IF(INDEX(对接源_02物料!$T$4:$T$1203,$AE55-1200)=0,"",INDEX(对接源_02物料!$T$4:$T$1203,$AE55-1200)))) | E55: =IF($AE55="","",IF($AE55<=1200,IF(INDEX(对接源_01水果!$W$4:$W$1203,$AE55)=0,"",INDEX(对接源_01水果!$W$4:$W$1203,$AE55)),IF(INDEX(对接源_02物料!$W$4:$W$1203,$AE55-1200)=0,"",INDEX(对接源_02物料!$W$4:$W$1203,$AE55-1200)))) | F55: =IF($AE55="","",IF($AE55<=1200,"01水果册","02物料册")) | G55: =IF($AE55="","",IF($AE55<=1200,IF(INDEX(对接源_01水果!$M$4:$M$1203,$AE55)=0,"",INDEX(对接源_01水果!$M$4:$M$1203,$AE55)),IF(INDEX(对接源_02物料!$M$4:$M$1203,$AE55-1200)=0,"",INDEX(对接源_02物料!$M$4:$M$1203,$AE55-1200)))) | AE55: =IFERROR(MATCH(50,_自动清单!$Q$4:$Q$2403,0),"")
A56: =IF($AE56="","",IF($AE56<=1200,IF(INDEX(对接源_01水果!$B$4:$B$1203,$AE56)=0,"",INDEX(对接源_01水果!$B$4:$B$1203,$AE56)),IF(INDEX(对接源_02物料!$B$4:$B$1203,$AE56-1200)=0,"",INDEX(对接源_02物料!$B$4:$B$1203,$AE56-1200)))) | B56: =IF($AE56="","",IF($AE56<=1200,IF(INDEX(对接源_01水果!$E$4:$E$1203,$AE56)=0,"",INDEX(对接源_01水果!$E$4:$E$1203,$AE56)),IF(INDEX(对接源_02物料!$E$4:$E$1203,$AE56-1200)=0,"",INDEX(对接源_02物料!$E$4:$E$1203,$AE56-1200)))) | C56: =IF($AE56="","",IF($AE56<=1200,IF(INDEX(对接源_01水果!$S$4:$S$1203,$AE56)=0,"",INDEX(对接源_01水果!$S$4:$S$1203,$AE56)),IF(INDEX(对接源_02物料!$S$4:$S$1203,$AE56-1200)=0,"",INDEX(对接源_02物料!$S$4:$S$1203,$AE56-1200)))) | D56: =IF($AE56="","",IF($AE56<=1200,IF(INDEX(对接源_01水果!$T$4:$T$1203,$AE56)=0,"",INDEX(对接源_01水果!$T$4:$T$1203,$AE56)),IF(INDEX(对接源_02物料!$T$4:$T$1203,$AE56-1200)=0,"",INDEX(对接源_02物料!$T$4:$T$1203,$AE56-1200)))) | E56: =IF($AE56="","",IF($AE56<=1200,IF(INDEX(对接源_01水果!$W$4:$W$1203,$AE56)=0,"",INDEX(对接源_01水果!$W$4:$W$1203,$AE56)),IF(INDEX(对接源_02物料!$W$4:$W$1203,$AE56-1200)=0,"",INDEX(对接源_02物料!$W$4:$W$1203,$AE56-1200)))) | F56: =IF($AE56="","",IF($AE56<=1200,"01水果册","02物料册")) | G56: =IF($AE56="","",IF($AE56<=1200,IF(INDEX(对接源_01水果!$M$4:$M$1203,$AE56)=0,"",INDEX(对接源_01水果!$M$4:$M$1203,$AE56)),IF(INDEX(对接源_02物料!$M$4:$M$1203,$AE56-1200)=0,"",INDEX(对接源_02物料!$M$4:$M$1203,$AE56-1200)))) | AE56: =IFERROR(MATCH(51,_自动清单!$Q$4:$Q$2403,0),"")
A57: =IF($AE57="","",IF($AE57<=1200,IF(INDEX(对接源_01水果!$B$4:$B$1203,$AE57)=0,"",INDEX(对接源_01水果!$B$4:$B$1203,$AE57)),IF(INDEX(对接源_02物料!$B$4:$B$1203,$AE57-1200)=0,"",INDEX(对接源_02物料!$B$4:$B$1203,$AE57-1200)))) | B57: =IF($AE57="","",IF($AE57<=1200,IF(INDEX(对接源_01水果!$E$4:$E$1203,$AE57)=0,"",INDEX(对接源_01水果!$E$4:$E$1203,$AE57)),IF(INDEX(对接源_02物料!$E$4:$E$1203,$AE57-1200)=0,"",INDEX(对接源_02物料!$E$4:$E$1203,$AE57-1200)))) | C57: =IF($AE57="","",IF($AE57<=1200,IF(INDEX(对接源_01水果!$S$4:$S$1203,$AE57)=0,"",INDEX(对接源_01水果!$S$4:$S$1203,$AE57)),IF(INDEX(对接源_02物料!$S$4:$S$1203,$AE57-1200)=0,"",INDEX(对接源_02物料!$S$4:$S$1203,$AE57-1200)))) | D57: =IF($AE57="","",IF($AE57<=1200,IF(INDEX(对接源_01水果!$T$4:$T$1203,$AE57)=0,"",INDEX(对接源_01水果!$T$4:$T$1203,$AE57)),IF(INDEX(对接源_02物料!$T$4:$T$1203,$AE57-1200)=0,"",INDEX(对接源_02物料!$T$4:$T$1203,$AE57-1200)))) | E57: =IF($AE57="","",IF($AE57<=1200,IF(INDEX(对接源_01水果!$W$4:$W$1203,$AE57)=0,"",INDEX(对接源_01水果!$W$4:$W$1203,$AE57)),IF(INDEX(对接源_02物料!$W$4:$W$1203,$AE57-1200)=0,"",INDEX(对接源_02物料!$W$4:$W$1203,$AE57-1200)))) | F57: =IF($AE57="","",IF($AE57<=1200,"01水果册","02物料册")) | G57: =IF($AE57="","",IF($AE57<=1200,IF(INDEX(对接源_01水果!$M$4:$M$1203,$AE57)=0,"",INDEX(对接源_01水果!$M$4:$M$1203,$AE57)),IF(INDEX(对接源_02物料!$M$4:$M$1203,$AE57-1200)=0,"",INDEX(对接源_02物料!$M$4:$M$1203,$AE57-1200)))) | AE57: =IFERROR(MATCH(52,_自动清单!$Q$4:$Q$2403,0),"")
A58: =IF($AE58="","",IF($AE58<=1200,IF(INDEX(对接源_01水果!$B$4:$B$1203,$AE58)=0,"",INDEX(对接源_01水果!$B$4:$B$1203,$AE58)),IF(INDEX(对接源_02物料!$B$4:$B$1203,$AE58-1200)=0,"",INDEX(对接源_02物料!$B$4:$B$1203,$AE58-1200)))) | B58: =IF($AE58="","",IF($AE58<=1200,IF(INDEX(对接源_01水果!$E$4:$E$1203,$AE58)=0,"",INDEX(对接源_01水果!$E$4:$E$1203,$AE58)),IF(INDEX(对接源_02物料!$E$4:$E$1203,$AE58-1200)=0,"",INDEX(对接源_02物料!$E$4:$E$1203,$AE58-1200)))) | C58: =IF($AE58="","",IF($AE58<=1200,IF(INDEX(对接源_01水果!$S$4:$S$1203,$AE58)=0,"",INDEX(对接源_01水果!$S$4:$S$1203,$AE58)),IF(INDEX(对接源_02物料!$S$4:$S$1203,$AE58-1200)=0,"",INDEX(对接源_02物料!$S$4:$S$1203,$AE58-1200)))) | D58: =IF($AE58="","",IF($AE58<=1200,IF(INDEX(对接源_01水果!$T$4:$T$1203,$AE58)=0,"",INDEX(对接源_01水果!$T$4:$T$1203,$AE58)),IF(INDEX(对接源_02物料!$T$4:$T$1203,$AE58-1200)=0,"",INDEX(对接源_02物料!$T$4:$T$1203,$AE58-1200)))) | E58: =IF($AE58="","",IF($AE58<=1200,IF(INDEX(对接源_01水果!$W$4:$W$1203,$AE58)=0,"",INDEX(对接源_01水果!$W$4:$W$1203,$AE58)),IF(INDEX(对接源_02物料!$W$4:$W$1203,$AE58-1200)=0,"",INDEX(对接源_02物料!$W$4:$W$1203,$AE58-1200)))) | F58: =IF($AE58="","",IF($AE58<=1200,"01水果册","02物料册")) | G58: =IF($AE58="","",IF($AE58<=1200,IF(INDEX(对接源_01水果!$M$4:$M$1203,$AE58)=0,"",INDEX(对接源_01水果!$M$4:$M$1203,$AE58)),IF(INDEX(对接源_02物料!$M$4:$M$1203,$AE58-1200)=0,"",INDEX(对接源_02物料!$M$4:$M$1203,$AE58-1200)))) | AE58: =IFERROR(MATCH(53,_自动清单!$Q$4:$Q$2403,0),"")
A59: =IF($AE59="","",IF($AE59<=1200,IF(INDEX(对接源_01水果!$B$4:$B$1203,$AE59)=0,"",INDEX(对接源_01水果!$B$4:$B$1203,$AE59)),IF(INDEX(对接源_02物料!$B$4:$B$1203,$AE59-1200)=0,"",INDEX(对接源_02物料!$B$4:$B$1203,$AE59-1200)))) | B59: =IF($AE59="","",IF($AE59<=1200,IF(INDEX(对接源_01水果!$E$4:$E$1203,$AE59)=0,"",INDEX(对接源_01水果!$E$4:$E$1203,$AE59)),IF(INDEX(对接源_02物料!$E$4:$E$1203,$AE59-1200)=0,"",INDEX(对接源_02物料!$E$4:$E$1203,$AE59-1200)))) | C59: =IF($AE59="","",IF($AE59<=1200,IF(INDEX(对接源_01水果!$S$4:$S$1203,$AE59)=0,"",INDEX(对接源_01水果!$S$4:$S$1203,$AE59)),IF(INDEX(对接源_02物料!$S$4:$S$1203,$AE59-1200)=0,"",INDEX(对接源_02物料!$S$4:$S$1203,$AE59-1200)))) | D59: =IF($AE59="","",IF($AE59<=1200,IF(INDEX(对接源_01水果!$T$4:$T$1203,$AE59)=0,"",INDEX(对接源_01水果!$T$4:$T$1203,$AE59)),IF(INDEX(对接源_02物料!$T$4:$T$1203,$AE59-1200)=0,"",INDEX(对接源_02物料!$T$4:$T$1203,$AE59-1200)))) | E59: =IF($AE59="","",IF($AE59<=1200,IF(INDEX(对接源_01水果!$W$4:$W$1203,$AE59)=0,"",INDEX(对接源_01水果!$W$4:$W$1203,$AE59)),IF(INDEX(对接源_02物料!$W$4:$W$1203,$AE59-1200)=0,"",INDEX(对接源_02物料!$W$4:$W$1203,$AE59-1200)))) | F59: =IF($AE59="","",IF($AE59<=1200,"01水果册","02物料册")) | G59: =IF($AE59="","",IF($AE59<=1200,IF(INDEX(对接源_01水果!$M$4:$M$1203,$AE59)=0,"",INDEX(对接源_01水果!$M$4:$M$1203,$AE59)),IF(INDEX(对接源_02物料!$M$4:$M$1203,$AE59-1200)=0,"",INDEX(对接源_02物料!$M$4:$M$1203,$AE59-1200)))) | AE59: =IFERROR(MATCH(54,_自动清单!$Q$4:$Q$2403,0),"")
A60: =IF($AE60="","",IF($AE60<=1200,IF(INDEX(对接源_01水果!$B$4:$B$1203,$AE60)=0,"",INDEX(对接源_01水果!$B$4:$B$1203,$AE60)),IF(INDEX(对接源_02物料!$B$4:$B$1203,$AE60-1200)=0,"",INDEX(对接源_02物料!$B$4:$B$1203,$AE60-1200)))) | B60: =IF($AE60="","",IF($AE60<=1200,IF(INDEX(对接源_01水果!$E$4:$E$1203,$AE60)=0,"",INDEX(对接源_01水果!$E$4:$E$1203,$AE60)),IF(INDEX(对接源_02物料!$E$4:$E$1203,$AE60-1200)=0,"",INDEX(对接源_02物料!$E$4:$E$1203,$AE60-1200)))) | C60: =IF($AE60="","",IF($AE60<=1200,IF(INDEX(对接源_01水果!$S$4:$S$1203,$AE60)=0,"",INDEX(对接源_01水果!$S$4:$S$1203,$AE60)),IF(INDEX(对接源_02物料!$S$4:$S$1203,$AE60-1200)=0,"",INDEX(对接源_02物料!$S$4:$S$1203,$AE60-1200)))) | D60: =IF($AE60="","",IF($AE60<=1200,IF(INDEX(对接源_01水果!$T$4:$T$1203,$AE60)=0,"",INDEX(对接源_01水果!$T$4:$T$1203,$AE60)),IF(INDEX(对接源_02物料!$T$4:$T$1203,$AE60-1200)=0,"",INDEX(对接源_02物料!$T$4:$T$1203,$AE60-1200)))) | E60: =IF($AE60="","",IF($AE60<=1200,IF(INDEX(对接源_01水果!$W$4:$W$1203,$AE60)=0,"",INDEX(对接源_01水果!$W$4:$W$1203,$AE60)),IF(INDEX(对接源_02物料!$W$4:$W$1203,$AE60-1200)=0,"",INDEX(对接源_02物料!$W$4:$W$1203,$AE60-1200)))) | F60: =IF($AE60="","",IF($AE60<=1200,"01水果册","02物料册")) | G60: =IF($AE60="","",IF($AE60<=1200,IF(INDEX(对接源_01水果!$M$4:$M$1203,$AE60)=0,"",INDEX(对接源_01水果!$M$4:$M$1203,$AE60)),IF(INDEX(对接源_02物料!$M$4:$M$1203,$AE60-1200)=0,"",INDEX(对接源_02物料!$M$4:$M$1203,$AE60-1200)))) | AE60: =IFERROR(MATCH(55,_自动清单!$Q$4:$Q$2403,0),"")
A61: =IF($AE61="","",IF($AE61<=1200,IF(INDEX(对接源_01水果!$B$4:$B$1203,$AE61)=0,"",INDEX(对接源_01水果!$B$4:$B$1203,$AE61)),IF(INDEX(对接源_02物料!$B$4:$B$1203,$AE61-1200)=0,"",INDEX(对接源_02物料!$B$4:$B$1203,$AE61-1200)))) | B61: =IF($AE61="","",IF($AE61<=1200,IF(INDEX(对接源_01水果!$E$4:$E$1203,$AE61)=0,"",INDEX(对接源_01水果!$E$4:$E$1203,$AE61)),IF(INDEX(对接源_02物料!$E$4:$E$1203,$AE61-1200)=0,"",INDEX(对接源_02物料!$E$4:$E$1203,$AE61-1200)))) | C61: =IF($AE61="","",IF($AE61<=1200,IF(INDEX(对接源_01水果!$S$4:$S$1203,$AE61)=0,"",INDEX(对接源_01水果!$S$4:$S$1203,$AE61)),IF(INDEX(对接源_02物料!$S$4:$S$1203,$AE61-1200)=0,"",INDEX(对接源_02物料!$S$4:$S$1203,$AE61-1200)))) | D61: =IF($AE61="","",IF($AE61<=1200,IF(INDEX(对接源_01水果!$T$4:$T$1203,$AE61)=0,"",INDEX(对接源_01水果!$T$4:$T$1203,$AE61)),IF(INDEX(对接源_02物料!$T$4:$T$1203,$AE61-1200)=0,"",INDEX(对接源_02物料!$T$4:$T$1203,$AE61-1200)))) | E61: =IF($AE61="","",IF($AE61<=1200,IF(INDEX(对接源_01水果!$W$4:$W$1203,$AE61)=0,"",INDEX(对接源_01水果!$W$4:$W$1203,$AE61)),IF(INDEX(对接源_02物料!$W$4:$W$1203,$AE61-1200)=0,"",INDEX(对接源_02物料!$W$4:$W$1203,$AE61-1200)))) | F61: =IF($AE61="","",IF($AE61<=1200,"01水果册","02物料册")) | G61: =IF($AE61="","",IF($AE61<=1200,IF(INDEX(对接源_01水果!$M$4:$M$1203,$AE61)=0,"",INDEX(对接源_01水果!$M$4:$M$1203,$AE61)),IF(INDEX(对接源_02物料!$M$4:$M$1203,$AE61-1200)=0,"",INDEX(对接源_02物料!$M$4:$M$1203,$AE61-1200)))) | AE61: =IFERROR(MATCH(56,_自动清单!$Q$4:$Q$2403,0),"")
A62: =IF($AE62="","",IF($AE62<=1200,IF(INDEX(对接源_01水果!$B$4:$B$1203,$AE62)=0,"",INDEX(对接源_01水果!$B$4:$B$1203,$AE62)),IF(INDEX(对接源_02物料!$B$4:$B$1203,$AE62-1200)=0,"",INDEX(对接源_02物料!$B$4:$B$1203,$AE62-1200)))) | B62: =IF($AE62="","",IF($AE62<=1200,IF(INDEX(对接源_01水果!$E$4:$E$1203,$AE62)=0,"",INDEX(对接源_01水果!$E$4:$E$1203,$AE62)),IF(INDEX(对接源_02物料!$E$4:$E$1203,$AE62-1200)=0,"",INDEX(对接源_02物料!$E$4:$E$1203,$AE62-1200)))) | C62: =IF($AE62="","",IF($AE62<=1200,IF(INDEX(对接源_01水果!$S$4:$S$1203,$AE62)=0,"",INDEX(对接源_01水果!$S$4:$S$1203,$AE62)),IF(INDEX(对接源_02物料!$S$4:$S$1203,$AE62-1200)=0,"",INDEX(对接源_02物料!$S$4:$S$1203,$AE62-1200)))) | D62: =IF($AE62="","",IF($AE62<=1200,IF(INDEX(对接源_01水果!$T$4:$T$1203,$AE62)=0,"",INDEX(对接源_01水果!$T$4:$T$1203,$AE62)),IF(INDEX(对接源_02物料!$T$4:$T$1203,$AE62-1200)=0,"",INDEX(对接源_02物料!$T$4:$T$1203,$AE62-1200)))) | E62: =IF($AE62="","",IF($AE62<=1200,IF(INDEX(对接源_01水果!$W$4:$W$1203,$AE62)=0,"",INDEX(对接源_01水果!$W$4:$W$1203,$AE62)),IF(INDEX(对接源_02物料!$W$4:$W$1203,$AE62-1200)=0,"",INDEX(对接源_02物料!$W$4:$W$1203,$AE62-1200)))) | F62: =IF($AE62="","",IF($AE62<=1200,"01水果册","02物料册")) | G62: =IF($AE62="","",IF($AE62<=1200,IF(INDEX(对接源_01水果!$M$4:$M$1203,$AE62)=0,"",INDEX(对接源_01水果!$M$4:$M$1203,$AE62)),IF(INDEX(对接源_02物料!$M$4:$M$1203,$AE62-1200)=0,"",INDEX(对接源_02物料!$M$4:$M$1203,$AE62-1200)))) | AE62: =IFERROR(MATCH(57,_自动清单!$Q$4:$Q$2403,0),"")
A63: =IF($AE63="","",IF($AE63<=1200,IF(INDEX(对接源_01水果!$B$4:$B$1203,$AE63)=0,"",INDEX(对接源_01水果!$B$4:$B$1203,$AE63)),IF(INDEX(对接源_02物料!$B$4:$B$1203,$AE63-1200)=0,"",INDEX(对接源_02物料!$B$4:$B$1203,$AE63-1200)))) | B63: =IF($AE63="","",IF($AE63<=1200,IF(INDEX(对接源_01水果!$E$4:$E$1203,$AE63)=0,"",INDEX(对接源_01水果!$E$4:$E$1203,$AE63)),IF(INDEX(对接源_02物料!$E$4:$E$1203,$AE63-1200)=0,"",INDEX(对接源_02物料!$E$4:$E$1203,$AE63-1200)))) | C63: =IF($AE63="","",IF($AE63<=1200,IF(INDEX(对接源_01水果!$S$4:$S$1203,$AE63)=0,"",INDEX(对接源_01水果!$S$4:$S$1203,$AE63)),IF(INDEX(对接源_02物料!$S$4:$S$1203,$AE63-1200)=0,"",INDEX(对接源_02物料!$S$4:$S$1203,$AE63-1200)))) | D63: =IF($AE63="","",IF($AE63<=1200,IF(INDEX(对接源_01水果!$T$4:$T$1203,$AE63)=0,"",INDEX(对接源_01水果!$T$4:$T$1203,$AE63)),IF(INDEX(对接源_02物料!$T$4:$T$1203,$AE63-1200)=0,"",INDEX(对接源_02物料!$T$4:$T$1203,$AE63-1200)))) | E63: =IF($AE63="","",IF($AE63<=1200,IF(INDEX(对接源_01水果!$W$4:$W$1203,$AE63)=0,"",INDEX(对接源_01水果!$W$4:$W$1203,$AE63)),IF(INDEX(对接源_02物料!$W$4:$W$1203,$AE63-1200)=0,"",INDEX(对接源_02物料!$W$4:$W$1203,$AE63-1200)))) | F63: =IF($AE63="","",IF($AE63<=1200,"01水果册","02物料册")) | G63: =IF($AE63="","",IF($AE63<=1200,IF(INDEX(对接源_01水果!$M$4:$M$1203,$AE63)=0,"",INDEX(对接源_01水果!$M$4:$M$1203,$AE63)),IF(INDEX(对接源_02物料!$M$4:$M$1203,$AE63-1200)=0,"",INDEX(对接源_02物料!$M$4:$M$1203,$AE63-1200)))) | AE63: =IFERROR(MATCH(58,_自动清单!$Q$4:$Q$2403,0),"")
A64: =IF($AE64="","",IF($AE64<=1200,IF(INDEX(对接源_01水果!$B$4:$B$1203,$AE64)=0,"",INDEX(对接源_01水果!$B$4:$B$1203,$AE64)),IF(INDEX(对接源_02物料!$B$4:$B$1203,$AE64-1200)=0,"",INDEX(对接源_02物料!$B$4:$B$1203,$AE64-1200)))) | B64: =IF($AE64="","",IF($AE64<=1200,IF(INDEX(对接源_01水果!$E$4:$E$1203,$AE64)=0,"",INDEX(对接源_01水果!$E$4:$E$1203,$AE64)),IF(INDEX(对接源_02物料!$E$4:$E$1203,$AE64-1200)=0,"",INDEX(对接源_02物料!$E$4:$E$1203,$AE64-1200)))) | C64: =IF($AE64="","",IF($AE64<=1200,IF(INDEX(对接源_01水果!$S$4:$S$1203,$AE64)=0,"",INDEX(对接源_01水果!$S$4:$S$1203,$AE64)),IF(INDEX(对接源_02物料!$S$4:$S$1203,$AE64-1200)=0,"",INDEX(对接源_02物料!$S$4:$S$1203,$AE64-1200)))) | D64: =IF($AE64="","",IF($AE64<=1200,IF(INDEX(对接源_01水果!$T$4:$T$1203,$AE64)=0,"",INDEX(对接源_01水果!$T$4:$T$1203,$AE64)),IF(INDEX(对接源_02物料!$T$4:$T$1203,$AE64-1200)=0,"",INDEX(对接源_02物料!$T$4:$T$1203,$AE64-1200)))) | E64: =IF($AE64="","",IF($AE64<=1200,IF(INDEX(对接源_01水果!$W$4:$W$1203,$AE64)=0,"",INDEX(对接源_01水果!$W$4:$W$1203,$AE64)),IF(INDEX(对接源_02物料!$W$4:$W$1203,$AE64-1200)=0,"",INDEX(对接源_02物料!$W$4:$W$1203,$AE64-1200)))) | F64: =IF($AE64="","",IF($AE64<=1200,"01水果册","02物料册")) | G64: =IF($AE64="","",IF($AE64<=1200,IF(INDEX(对接源_01水果!$M$4:$M$1203,$AE64)=0,"",INDEX(对接源_01水果!$M$4:$M$1203,$AE64)),IF(INDEX(对接源_02物料!$M$4:$M$1203,$AE64-1200)=0,"",INDEX(对接源_02物料!$M$4:$M$1203,$AE64-1200)))) | AE64: =IFERROR(MATCH(59,_自动清单!$Q$4:$Q$2403,0),"")
A65: =IF($AE65="","",IF($AE65<=1200,IF(INDEX(对接源_01水果!$B$4:$B$1203,$AE65)=0,"",INDEX(对接源_01水果!$B$4:$B$1203,$AE65)),IF(INDEX(对接源_02物料!$B$4:$B$1203,$AE65-1200)=0,"",INDEX(对接源_02物料!$B$4:$B$1203,$AE65-1200)))) | B65: =IF($AE65="","",IF($AE65<=1200,IF(INDEX(对接源_01水果!$E$4:$E$1203,$AE65)=0,"",INDEX(对接源_01水果!$E$4:$E$1203,$AE65)),IF(INDEX(对接源_02物料!$E$4:$E$1203,$AE65-1200)=0,"",INDEX(对接源_02物料!$E$4:$E$1203,$AE65-1200)))) | C65: =IF($AE65="","",IF($AE65<=1200,IF(INDEX(对接源_01水果!$S$4:$S$1203,$AE65)=0,"",INDEX(对接源_01水果!$S$4:$S$1203,$AE65)),IF(INDEX(对接源_02物料!$S$4:$S$1203,$AE65-1200)=0,"",INDEX(对接源_02物料!$S$4:$S$1203,$AE65-1200)))) | D65: =IF($AE65="","",IF($AE65<=1200,IF(INDEX(对接源_01水果!$T$4:$T$1203,$AE65)=0,"",INDEX(对接源_01水果!$T$4:$T$1203,$AE65)),IF(INDEX(对接源_02物料!$T$4:$T$1203,$AE65-1200)=0,"",INDEX(对接源_02物料!$T$4:$T$1203,$AE65-1200)))) | E65: =IF($AE65="","",IF($AE65<=1200,IF(INDEX(对接源_01水果!$W$4:$W$1203,$AE65)=0,"",INDEX(对接源_01水果!$W$4:$W$1203,$AE65)),IF(INDEX(对接源_02物料!$W$4:$W$1203,$AE65-1200)=0,"",INDEX(对接源_02物料!$W$4:$W$1203,$AE65-1200)))) | F65: =IF($AE65="","",IF($AE65<=1200,"01水果册","02物料册")) | G65: =IF($AE65="","",IF($AE65<=1200,IF(INDEX(对接源_01水果!$M$4:$M$1203,$AE65)=0,"",INDEX(对接源_01水果!$M$4:$M$1203,$AE65)),IF(INDEX(对接源_02物料!$M$4:$M$1203,$AE65-1200)=0,"",INDEX(对接源_02物料!$M$4:$M$1203,$AE65-1200)))) | AE65: =IFERROR(MATCH(60,_自动清单!$Q$4:$Q$2403,0),"")
A66: =IF($AE66="","",IF($AE66<=1200,IF(INDEX(对接源_01水果!$B$4:$B$1203,$AE66)=0,"",INDEX(对接源_01水果!$B$4:$B$1203,$AE66)),IF(INDEX(对接源_02物料!$B$4:$B$1203,$AE66-1200)=0,"",INDEX(对接源_02物料!$B$4:$B$1203,$AE66-1200)))) | B66: =IF($AE66="","",IF($AE66<=1200,IF(INDEX(对接源_01水果!$E$4:$E$1203,$AE66)=0,"",INDEX(对接源_01水果!$E$4:$E$1203,$AE66)),IF(INDEX(对接源_02物料!$E$4:$E$1203,$AE66-1200)=0,"",INDEX(对接源_02物料!$E$4:$E$1203,$AE66-1200)))) | C66: =IF($AE66="","",IF($AE66<=1200,IF(INDEX(对接源_01水果!$S$4:$S$1203,$AE66)=0,"",INDEX(对接源_01水果!$S$4:$S$1203,$AE66)),IF(INDEX(对接源_02物料!$S$4:$S$1203,$AE66-1200)=0,"",INDEX(对接源_02物料!$S$4:$S$1203,$AE66-1200)))) | D66: =IF($AE66="","",IF($AE66<=1200,IF(INDEX(对接源_01水果!$T$4:$T$1203,$AE66)=0,"",INDEX(对接源_01水果!$T$4:$T$1203,$AE66)),IF(INDEX(对接源_02物料!$T$4:$T$1203,$AE66-1200)=0,"",INDEX(对接源_02物料!$T$4:$T$1203,$AE66-1200)))) | E66: =IF($AE66="","",IF($AE66<=1200,IF(INDEX(对接源_01水果!$W$4:$W$1203,$AE66)=0,"",INDEX(对接源_01水果!$W$4:$W$1203,$AE66)),IF(INDEX(对接源_02物料!$W$4:$W$1203,$AE66-1200)=0,"",INDEX(对接源_02物料!$W$4:$W$1203,$AE66-1200)))) | F66: =IF($AE66="","",IF($AE66<=1200,"01水果册","02物料册")) | G66: =IF($AE66="","",IF($AE66<=1200,IF(INDEX(对接源_01水果!$M$4:$M$1203,$AE66)=0,"",INDEX(对接源_01水果!$M$4:$M$1203,$AE66)),IF(INDEX(对接源_02物料!$M$4:$M$1203,$AE66-1200)=0,"",INDEX(对接源_02物料!$M$4:$M$1203,$AE66-1200)))) | AE66: =IFERROR(MATCH(61,_自动清单!$Q$4:$Q$2403,0),"")
A67: =IF($AE67="","",IF($AE67<=1200,IF(INDEX(对接源_01水果!$B$4:$B$1203,$AE67)=0,"",INDEX(对接源_01水果!$B$4:$B$1203,$AE67)),IF(INDEX(对接源_02物料!$B$4:$B$1203,$AE67-1200)=0,"",INDEX(对接源_02物料!$B$4:$B$1203,$AE67-1200)))) | B67: =IF($AE67="","",IF($AE67<=1200,IF(INDEX(对接源_01水果!$E$4:$E$1203,$AE67)=0,"",INDEX(对接源_01水果!$E$4:$E$1203,$AE67)),IF(INDEX(对接源_02物料!$E$4:$E$1203,$AE67-1200)=0,"",INDEX(对接源_02物料!$E$4:$E$1203,$AE67-1200)))) | C67: =IF($AE67="","",IF($AE67<=1200,IF(INDEX(对接源_01水果!$S$4:$S$1203,$AE67)=0,"",INDEX(对接源_01水果!$S$4:$S$1203,$AE67)),IF(INDEX(对接源_02物料!$S$4:$S$1203,$AE67-1200)=0,"",INDEX(对接源_02物料!$S$4:$S$1203,$AE67-1200)))) | D67: =IF($AE67="","",IF($AE67<=1200,IF(INDEX(对接源_01水果!$T$4:$T$1203,$AE67)=0,"",INDEX(对接源_01水果!$T$4:$T$1203,$AE67)),IF(INDEX(对接源_02物料!$T$4:$T$1203,$AE67-1200)=0,"",INDEX(对接源_02物料!$T$4:$T$1203,$AE67-1200)))) | E67: =IF($AE67="","",IF($AE67<=1200,IF(INDEX(对接源_01水果!$W$4:$W$1203,$AE67)=0,"",INDEX(对接源_01水果!$W$4:$W$1203,$AE67)),IF(INDEX(对接源_02物料!$W$4:$W$1203,$AE67-1200)=0,"",INDEX(对接源_02物料!$W$4:$W$1203,$AE67-1200)))) | F67: =IF($AE67="","",IF($AE67<=1200,"01水果册","02物料册")) | G67: =IF($AE67="","",IF($AE67<=1200,IF(INDEX(对接源_01水果!$M$4:$M$1203,$AE67)=0,"",INDEX(对接源_01水果!$M$4:$M$1203,$AE67)),IF(INDEX(对接源_02物料!$M$4:$M$1203,$AE67-1200)=0,"",INDEX(对接源_02物料!$M$4:$M$1203,$AE67-1200)))) | AE67: =IFERROR(MATCH(62,_自动清单!$Q$4:$Q$2403,0),"")
A68: =IF($AE68="","",IF($AE68<=1200,IF(INDEX(对接源_01水果!$B$4:$B$1203,$AE68)=0,"",INDEX(对接源_01水果!$B$4:$B$1203,$AE68)),IF(INDEX(对接源_02物料!$B$4:$B$1203,$AE68-1200)=0,"",INDEX(对接源_02物料!$B$4:$B$1203,$AE68-1200)))) | B68: =IF($AE68="","",IF($AE68<=1200,IF(INDEX(对接源_01水果!$E$4:$E$1203,$AE68)=0,"",INDEX(对接源_01水果!$E$4:$E$1203,$AE68)),IF(INDEX(对接源_02物料!$E$4:$E$1203,$AE68-1200)=0,"",INDEX(对接源_02物料!$E$4:$E$1203,$AE68-1200)))) | C68: =IF($AE68="","",IF($AE68<=1200,IF(INDEX(对接源_01水果!$S$4:$S$1203,$AE68)=0,"",INDEX(对接源_01水果!$S$4:$S$1203,$AE68)),IF(INDEX(对接源_02物料!$S$4:$S$1203,$AE68-1200)=0,"",INDEX(对接源_02物料!$S$4:$S$1203,$AE68-1200)))) | D68: =IF($AE68="","",IF($AE68<=1200,IF(INDEX(对接源_01水果!$T$4:$T$1203,$AE68)=0,"",INDEX(对接源_01水果!$T$4:$T$1203,$AE68)),IF(INDEX(对接源_02物料!$T$4:$T$1203,$AE68-1200)=0,"",INDEX(对接源_02物料!$T$4:$T$1203,$AE68-1200)))) | E68: =IF($AE68="","",IF($AE68<=1200,IF(INDEX(对接源_01水果!$W$4:$W$1203,$AE68)=0,"",INDEX(对接源_01水果!$W$4:$W$1203,$AE68)),IF(INDEX(对接源_02物料!$W$4:$W$1203,$AE68-1200)=0,"",INDEX(对接源_02物料!$W$4:$W$1203,$AE68-1200)))) | F68: =IF($AE68="","",IF($AE68<=1200,"01水果册","02物料册")) | G68: =IF($AE68="","",IF($AE68<=1200,IF(INDEX(对接源_01水果!$M$4:$M$1203,$AE68)=0,"",INDEX(对接源_01水果!$M$4:$M$1203,$AE68)),IF(INDEX(对接源_02物料!$M$4:$M$1203,$AE68-1200)=0,"",INDEX(对接源_02物料!$M$4:$M$1203,$AE68-1200)))) | AE68: =IFERROR(MATCH(63,_自动清单!$Q$4:$Q$2403,0),"")
A69: =IF($AE69="","",IF($AE69<=1200,IF(INDEX(对接源_01水果!$B$4:$B$1203,$AE69)=0,"",INDEX(对接源_01水果!$B$4:$B$1203,$AE69)),IF(INDEX(对接源_02物料!$B$4:$B$1203,$AE69-1200)=0,"",INDEX(对接源_02物料!$B$4:$B$1203,$AE69-1200)))) | B69: =IF($AE69="","",IF($AE69<=1200,IF(INDEX(对接源_01水果!$E$4:$E$1203,$AE69)=0,"",INDEX(对接源_01水果!$E$4:$E$1203,$AE69)),IF(INDEX(对接源_02物料!$E$4:$E$1203,$AE69-1200)=0,"",INDEX(对接源_02物料!$E$4:$E$1203,$AE69-1200)))) | C69: =IF($AE69="","",IF($AE69<=1200,IF(INDEX(对接源_01水果!$S$4:$S$1203,$AE69)=0,"",INDEX(对接源_01水果!$S$4:$S$1203,$AE69)),IF(INDEX(对接源_02物料!$S$4:$S$1203,$AE69-1200)=0,"",INDEX(对接源_02物料!$S$4:$S$1203,$AE69-1200)))) | D69: =IF($AE69="","",IF($AE69<=1200,IF(INDEX(对接源_01水果!$T$4:$T$1203,$AE69)=0,"",INDEX(对接源_01水果!$T$4:$T$1203,$AE69)),IF(INDEX(对接源_02物料!$T$4:$T$1203,$AE69-1200)=0,"",INDEX(对接源_02物料!$T$4:$T$1203,$AE69-1200)))) | E69: =IF($AE69="","",IF($AE69<=1200,IF(INDEX(对接源_01水果!$W$4:$W$1203,$AE69)=0,"",INDEX(对接源_01水果!$W$4:$W$1203,$AE69)),IF(INDEX(对接源_02物料!$W$4:$W$1203,$AE69-1200)=0,"",INDEX(对接源_02物料!$W$4:$W$1203,$AE69-1200)))) | F69: =IF($AE69="","",IF($AE69<=1200,"01水果册","02物料册")) | G69: =IF($AE69="","",IF($AE69<=1200,IF(INDEX(对接源_01水果!$M$4:$M$1203,$AE69)=0,"",INDEX(对接源_01水果!$M$4:$M$1203,$AE69)),IF(INDEX(对接源_02物料!$M$4:$M$1203,$AE69-1200)=0,"",INDEX(对接源_02物料!$M$4:$M$1203,$AE69-1200)))) | AE69: =IFERROR(MATCH(64,_自动清单!$Q$4:$Q$2403,0),"")
A70: =IF($AE70="","",IF($AE70<=1200,IF(INDEX(对接源_01水果!$B$4:$B$1203,$AE70)=0,"",INDEX(对接源_01水果!$B$4:$B$1203,$AE70)),IF(INDEX(对接源_02物料!$B$4:$B$1203,$AE70-1200)=0,"",INDEX(对接源_02物料!$B$4:$B$1203,$AE70-1200)))) | B70: =IF($AE70="","",IF($AE70<=1200,IF(INDEX(对接源_01水果!$E$4:$E$1203,$AE70)=0,"",INDEX(对接源_01水果!$E$4:$E$1203,$AE70)),IF(INDEX(对接源_02物料!$E$4:$E$1203,$AE70-1200)=0,"",INDEX(对接源_02物料!$E$4:$E$1203,$AE70-1200)))) | C70: =IF($AE70="","",IF($AE70<=1200,IF(INDEX(对接源_01水果!$S$4:$S$1203,$AE70)=0,"",INDEX(对接源_01水果!$S$4:$S$1203,$AE70)),IF(INDEX(对接源_02物料!$S$4:$S$1203,$AE70-1200)=0,"",INDEX(对接源_02物料!$S$4:$S$1203,$AE70-1200)))) | D70: =IF($AE70="","",IF($AE70<=1200,IF(INDEX(对接源_01水果!$T$4:$T$1203,$AE70)=0,"",INDEX(对接源_01水果!$T$4:$T$1203,$AE70)),IF(INDEX(对接源_02物料!$T$4:$T$1203,$AE70-1200)=0,"",INDEX(对接源_02物料!$T$4:$T$1203,$AE70-1200)))) | E70: =IF($AE70="","",IF($AE70<=1200,IF(INDEX(对接源_01水果!$W$4:$W$1203,$AE70)=0,"",INDEX(对接源_01水果!$W$4:$W$1203,$AE70)),IF(INDEX(对接源_02物料!$W$4:$W$1203,$AE70-1200)=0,"",INDEX(对接源_02物料!$W$4:$W$1203,$AE70-1200)))) | F70: =IF($AE70="","",IF($AE70<=1200,"01水果册","02物料册")) | G70: =IF($AE70="","",IF($AE70<=1200,IF(INDEX(对接源_01水果!$M$4:$M$1203,$AE70)=0,"",INDEX(对接源_01水果!$M$4:$M$1203,$AE70)),IF(INDEX(对接源_02物料!$M$4:$M$1203,$AE70-1200)=0,"",INDEX(对接源_02物料!$M$4:$M$1203,$AE70-1200)))) | AE70: =IFERROR(MATCH(65,_自动清单!$Q$4:$Q$2403,0),"")
A71: =IF($AE71="","",IF($AE71<=1200,IF(INDEX(对接源_01水果!$B$4:$B$1203,$AE71)=0,"",INDEX(对接源_01水果!$B$4:$B$1203,$AE71)),IF(INDEX(对接源_02物料!$B$4:$B$1203,$AE71-1200)=0,"",INDEX(对接源_02物料!$B$4:$B$1203,$AE71-1200)))) | B71: =IF($AE71="","",IF($AE71<=1200,IF(INDEX(对接源_01水果!$E$4:$E$1203,$AE71)=0,"",INDEX(对接源_01水果!$E$4:$E$1203,$AE71)),IF(INDEX(对接源_02物料!$E$4:$E$1203,$AE71-1200)=0,"",INDEX(对接源_02物料!$E$4:$E$1203,$AE71-1200)))) | C71: =IF($AE71="","",IF($AE71<=1200,IF(INDEX(对接源_01水果!$S$4:$S$1203,$AE71)=0,"",INDEX(对接源_01水果!$S$4:$S$1203,$AE71)),IF(INDEX(对接源_02物料!$S$4:$S$1203,$AE71-1200)=0,"",INDEX(对接源_02物料!$S$4:$S$1203,$AE71-1200)))) | D71: =IF($AE71="","",IF($AE71<=1200,IF(INDEX(对接源_01水果!$T$4:$T$1203,$AE71)=0,"",INDEX(对接源_01水果!$T$4:$T$1203,$AE71)),IF(INDEX(对接源_02物料!$T$4:$T$1203,$AE71-1200)=0,"",INDEX(对接源_02物料!$T$4:$T$1203,$AE71-1200)))) | E71: =IF($AE71="","",IF($AE71<=1200,IF(INDEX(对接源_01水果!$W$4:$W$1203,$AE71)=0,"",INDEX(对接源_01水果!$W$4:$W$1203,$AE71)),IF(INDEX(对接源_02物料!$W$4:$W$1203,$AE71-1200)=0,"",INDEX(对接源_02物料!$W$4:$W$1203,$AE71-1200)))) | F71: =IF($AE71="","",IF($AE71<=1200,"01水果册","02物料册")) | G71: =IF($AE71="","",IF($AE71<=1200,IF(INDEX(对接源_01水果!$M$4:$M$1203,$AE71)=0,"",INDEX(对接源_01水果!$M$4:$M$1203,$AE71)),IF(INDEX(对接源_02物料!$M$4:$M$1203,$AE71-1200)=0,"",INDEX(对接源_02物料!$M$4:$M$1203,$AE71-1200)))) | AE71: =IFERROR(MATCH(66,_自动清单!$Q$4:$Q$2403,0),"")
A72: =IF($AE72="","",IF($AE72<=1200,IF(INDEX(对接源_01水果!$B$4:$B$1203,$AE72)=0,"",INDEX(对接源_01水果!$B$4:$B$1203,$AE72)),IF(INDEX(对接源_02物料!$B$4:$B$1203,$AE72-1200)=0,"",INDEX(对接源_02物料!$B$4:$B$1203,$AE72-1200)))) | B72: =IF($AE72="","",IF($AE72<=1200,IF(INDEX(对接源_01水果!$E$4:$E$1203,$AE72)=0,"",INDEX(对接源_01水果!$E$4:$E$1203,$AE72)),IF(INDEX(对接源_02物料!$E$4:$E$1203,$AE72-1200)=0,"",INDEX(对接源_02物料!$E$4:$E$1203,$AE72-1200)))) | C72: =IF($AE72="","",IF($AE72<=1200,IF(INDEX(对接源_01水果!$S$4:$S$1203,$AE72)=0,"",INDEX(对接源_01水果!$S$4:$S$1203,$AE72)),IF(INDEX(对接源_02物料!$S$4:$S$1203,$AE72-1200)=0,"",INDEX(对接源_02物料!$S$4:$S$1203,$AE72-1200)))) | D72: =IF($AE72="","",IF($AE72<=1200,IF(INDEX(对接源_01水果!$T$4:$T$1203,$AE72)=0,"",INDEX(对接源_01水果!$T$4:$T$1203,$AE72)),IF(INDEX(对接源_02物料!$T$4:$T$1203,$AE72-1200)=0,"",INDEX(对接源_02物料!$T$4:$T$1203,$AE72-1200)))) | E72: =IF($AE72="","",IF($AE72<=1200,IF(INDEX(对接源_01水果!$W$4:$W$1203,$AE72)=0,"",INDEX(对接源_01水果!$W$4:$W$1203,$AE72)),IF(INDEX(对接源_02物料!$W$4:$W$1203,$AE72-1200)=0,"",INDEX(对接源_02物料!$W$4:$W$1203,$AE72-1200)))) | F72: =IF($AE72="","",IF($AE72<=1200,"01水果册","02物料册")) | G72: =IF($AE72="","",IF($AE72<=1200,IF(INDEX(对接源_01水果!$M$4:$M$1203,$AE72)=0,"",INDEX(对接源_01水果!$M$4:$M$1203,$AE72)),IF(INDEX(对接源_02物料!$M$4:$M$1203,$AE72-1200)=0,"",INDEX(对接源_02物料!$M$4:$M$1203,$AE72-1200)))) | AE72: =IFERROR(MATCH(67,_自动清单!$Q$4:$Q$2403,0),"")
A73: =IF($AE73="","",IF($AE73<=1200,IF(INDEX(对接源_01水果!$B$4:$B$1203,$AE73)=0,"",INDEX(对接源_01水果!$B$4:$B$1203,$AE73)),IF(INDEX(对接源_02物料!$B$4:$B$1203,$AE73-1200)=0,"",INDEX(对接源_02物料!$B$4:$B$1203,$AE73-1200)))) | B73: =IF($AE73="","",IF($AE73<=1200,IF(INDEX(对接源_01水果!$E$4:$E$1203,$AE73)=0,"",INDEX(对接源_01水果!$E$4:$E$1203,$AE73)),IF(INDEX(对接源_02物料!$E$4:$E$1203,$AE73-1200)=0,"",INDEX(对接源_02物料!$E$4:$E$1203,$AE73-1200)))) | C73: =IF($AE73="","",IF($AE73<=1200,IF(INDEX(对接源_01水果!$S$4:$S$1203,$AE73)=0,"",INDEX(对接源_01水果!$S$4:$S$1203,$AE73)),IF(INDEX(对接源_02物料!$S$4:$S$1203,$AE73-1200)=0,"",INDEX(对接源_02物料!$S$4:$S$1203,$AE73-1200)))) | D73: =IF($AE73="","",IF($AE73<=1200,IF(INDEX(对接源_01水果!$T$4:$T$1203,$AE73)=0,"",INDEX(对接源_01水果!$T$4:$T$1203,$AE73)),IF(INDEX(对接源_02物料!$T$4:$T$1203,$AE73-1200)=0,"",INDEX(对接源_02物料!$T$4:$T$1203,$AE73-1200)))) | E73: =IF($AE73="","",IF($AE73<=1200,IF(INDEX(对接源_01水果!$W$4:$W$1203,$AE73)=0,"",INDEX(对接源_01水果!$W$4:$W$1203,$AE73)),IF(INDEX(对接源_02物料!$W$4:$W$1203,$AE73-1200)=0,"",INDEX(对接源_02物料!$W$4:$W$1203,$AE73-1200)))) | F73: =IF($AE73="","",IF($AE73<=1200,"01水果册","02物料册")) | G73: =IF($AE73="","",IF($AE73<=1200,IF(INDEX(对接源_01水果!$M$4:$M$1203,$AE73)=0,"",INDEX(对接源_01水果!$M$4:$M$1203,$AE73)),IF(INDEX(对接源_02物料!$M$4:$M$1203,$AE73-1200)=0,"",INDEX(对接源_02物料!$M$4:$M$1203,$AE73-1200)))) | AE73: =IFERROR(MATCH(68,_自动清单!$Q$4:$Q$2403,0),"")
A74: =IF($AE74="","",IF($AE74<=1200,IF(INDEX(对接源_01水果!$B$4:$B$1203,$AE74)=0,"",INDEX(对接源_01水果!$B$4:$B$1203,$AE74)),IF(INDEX(对接源_02物料!$B$4:$B$1203,$AE74-1200)=0,"",INDEX(对接源_02物料!$B$4:$B$1203,$AE74-1200)))) | B74: =IF($AE74="","",IF($AE74<=1200,IF(INDEX(对接源_01水果!$E$4:$E$1203,$AE74)=0,"",INDEX(对接源_01水果!$E$4:$E$1203,$AE74)),IF(INDEX(对接源_02物料!$E$4:$E$1203,$AE74-1200)=0,"",INDEX(对接源_02物料!$E$4:$E$1203,$AE74-1200)))) | C74: =IF($AE74="","",IF($AE74<=1200,IF(INDEX(对接源_01水果!$S$4:$S$1203,$AE74)=0,"",INDEX(对接源_01水果!$S$4:$S$1203,$AE74)),IF(INDEX(对接源_02物料!$S$4:$S$1203,$AE74-1200)=0,"",INDEX(对接源_02物料!$S$4:$S$1203,$AE74-1200)))) | D74: =IF($AE74="","",IF($AE74<=1200,IF(INDEX(对接源_01水果!$T$4:$T$1203,$AE74)=0,"",INDEX(对接源_01水果!$T$4:$T$1203,$AE74)),IF(INDEX(对接源_02物料!$T$4:$T$1203,$AE74-1200)=0,"",INDEX(对接源_02物料!$T$4:$T$1203,$AE74-1200)))) | E74: =IF($AE74="","",IF($AE74<=1200,IF(INDEX(对接源_01水果!$W$4:$W$1203,$AE74)=0,"",INDEX(对接源_01水果!$W$4:$W$1203,$AE74)),IF(INDEX(对接源_02物料!$W$4:$W$1203,$AE74-1200)=0,"",INDEX(对接源_02物料!$W$4:$W$1203,$AE74-1200)))) | F74: =IF($AE74="","",IF($AE74<=1200,"01水果册","02物料册")) | G74: =IF($AE74="","",IF($AE74<=1200,IF(INDEX(对接源_01水果!$M$4:$M$1203,$AE74)=0,"",INDEX(对接源_01水果!$M$4:$M$1203,$AE74)),IF(INDEX(对接源_02物料!$M$4:$M$1203,$AE74-1200)=0,"",INDEX(对接源_02物料!$M$4:$M$1203,$AE74-1200)))) | AE74: =IFERROR(MATCH(69,_自动清单!$Q$4:$Q$2403,0),"")
A75: =IF($AE75="","",IF($AE75<=1200,IF(INDEX(对接源_01水果!$B$4:$B$1203,$AE75)=0,"",INDEX(对接源_01水果!$B$4:$B$1203,$AE75)),IF(INDEX(对接源_02物料!$B$4:$B$1203,$AE75-1200)=0,"",INDEX(对接源_02物料!$B$4:$B$1203,$AE75-1200)))) | B75: =IF($AE75="","",IF($AE75<=1200,IF(INDEX(对接源_01水果!$E$4:$E$1203,$AE75)=0,"",INDEX(对接源_01水果!$E$4:$E$1203,$AE75)),IF(INDEX(对接源_02物料!$E$4:$E$1203,$AE75-1200)=0,"",INDEX(对接源_02物料!$E$4:$E$1203,$AE75-1200)))) | C75: =IF($AE75="","",IF($AE75<=1200,IF(INDEX(对接源_01水果!$S$4:$S$1203,$AE75)=0,"",INDEX(对接源_01水果!$S$4:$S$1203,$AE75)),IF(INDEX(对接源_02物料!$S$4:$S$1203,$AE75-1200)=0,"",INDEX(对接源_02物料!$S$4:$S$1203,$AE75-1200)))) | D75: =IF($AE75="","",IF($AE75<=1200,IF(INDEX(对接源_01水果!$T$4:$T$1203,$AE75)=0,"",INDEX(对接源_01水果!$T$4:$T$1203,$AE75)),IF(INDEX(对接源_02物料!$T$4:$T$1203,$AE75-1200)=0,"",INDEX(对接源_02物料!$T$4:$T$1203,$AE75-1200)))) | E75: =IF($AE75="","",IF($AE75<=1200,IF(INDEX(对接源_01水果!$W$4:$W$1203,$AE75)=0,"",INDEX(对接源_01水果!$W$4:$W$1203,$AE75)),IF(INDEX(对接源_02物料!$W$4:$W$1203,$AE75-1200)=0,"",INDEX(对接源_02物料!$W$4:$W$1203,$AE75-1200)))) | F75: =IF($AE75="","",IF($AE75<=1200,"01水果册","02物料册")) | G75: =IF($AE75="","",IF($AE75<=1200,IF(INDEX(对接源_01水果!$M$4:$M$1203,$AE75)=0,"",INDEX(对接源_01水果!$M$4:$M$1203,$AE75)),IF(INDEX(对接源_02物料!$M$4:$M$1203,$AE75-1200)=0,"",INDEX(对接源_02物料!$M$4:$M$1203,$AE75-1200)))) | AE75: =IFERROR(MATCH(70,_自动清单!$Q$4:$Q$2403,0),"")
A76: =IF($AE76="","",IF($AE76<=1200,IF(INDEX(对接源_01水果!$B$4:$B$1203,$AE76)=0,"",INDEX(对接源_01水果!$B$4:$B$1203,$AE76)),IF(INDEX(对接源_02物料!$B$4:$B$1203,$AE76-1200)=0,"",INDEX(对接源_02物料!$B$4:$B$1203,$AE76-1200)))) | B76: =IF($AE76="","",IF($AE76<=1200,IF(INDEX(对接源_01水果!$E$4:$E$1203,$AE76)=0,"",INDEX(对接源_01水果!$E$4:$E$1203,$AE76)),IF(INDEX(对接源_02物料!$E$4:$E$1203,$AE76-1200)=0,"",INDEX(对接源_02物料!$E$4:$E$1203,$AE76-1200)))) | C76: =IF($AE76="","",IF($AE76<=1200,IF(INDEX(对接源_01水果!$S$4:$S$1203,$AE76)=0,"",INDEX(对接源_01水果!$S$4:$S$1203,$AE76)),IF(INDEX(对接源_02物料!$S$4:$S$1203,$AE76-1200)=0,"",INDEX(对接源_02物料!$S$4:$S$1203,$AE76-1200)))) | D76: =IF($AE76="","",IF($AE76<=1200,IF(INDEX(对接源_01水果!$T$4:$T$1203,$AE76)=0,"",INDEX(对接源_01水果!$T$4:$T$1203,$AE76)),IF(INDEX(对接源_02物料!$T$4:$T$1203,$AE76-1200)=0,"",INDEX(对接源_02物料!$T$4:$T$1203,$AE76-1200)))) | E76: =IF($AE76="","",IF($AE76<=1200,IF(INDEX(对接源_01水果!$W$4:$W$1203,$AE76)=0,"",INDEX(对接源_01水果!$W$4:$W$1203,$AE76)),IF(INDEX(对接源_02物料!$W$4:$W$1203,$AE76-1200)=0,"",INDEX(对接源_02物料!$W$4:$W$1203,$AE76-1200)))) | F76: =IF($AE76="","",IF($AE76<=1200,"01水果册","02物料册")) | G76: =IF($AE76="","",IF($AE76<=1200,IF(INDEX(对接源_01水果!$M$4:$M$1203,$AE76)=0,"",INDEX(对接源_01水果!$M$4:$M$1203,$AE76)),IF(INDEX(对接源_02物料!$M$4:$M$1203,$AE76-1200)=0,"",INDEX(对接源_02物料!$M$4:$M$1203,$AE76-1200)))) | AE76: =IFERROR(MATCH(71,_自动清单!$Q$4:$Q$2403,0),"")
A77: =IF($AE77="","",IF($AE77<=1200,IF(INDEX(对接源_01水果!$B$4:$B$1203,$AE77)=0,"",INDEX(对接源_01水果!$B$4:$B$1203,$AE77)),IF(INDEX(对接源_02物料!$B$4:$B$1203,$AE77-1200)=0,"",INDEX(对接源_02物料!$B$4:$B$1203,$AE77-1200)))) | B77: =IF($AE77="","",IF($AE77<=1200,IF(INDEX(对接源_01水果!$E$4:$E$1203,$AE77)=0,"",INDEX(对接源_01水果!$E$4:$E$1203,$AE77)),IF(INDEX(对接源_02物料!$E$4:$E$1203,$AE77-1200)=0,"",INDEX(对接源_02物料!$E$4:$E$1203,$AE77-1200)))) | C77: =IF($AE77="","",IF($AE77<=1200,IF(INDEX(对接源_01水果!$S$4:$S$1203,$AE77)=0,"",INDEX(对接源_01水果!$S$4:$S$1203,$AE77)),IF(INDEX(对接源_02物料!$S$4:$S$1203,$AE77-1200)=0,"",INDEX(对接源_02物料!$S$4:$S$1203,$AE77-1200)))) | D77: =IF($AE77="","",IF($AE77<=1200,IF(INDEX(对接源_01水果!$T$4:$T$1203,$AE77)=0,"",INDEX(对接源_01水果!$T$4:$T$1203,$AE77)),IF(INDEX(对接源_02物料!$T$4:$T$1203,$AE77-1200)=0,"",INDEX(对接源_02物料!$T$4:$T$1203,$AE77-1200)))) | E77: =IF($AE77="","",IF($AE77<=1200,IF(INDEX(对接源_01水果!$W$4:$W$1203,$AE77)=0,"",INDEX(对接源_01水果!$W$4:$W$1203,$AE77)),IF(INDEX(对接源_02物料!$W$4:$W$1203,$AE77-1200)=0,"",INDEX(对接源_02物料!$W$4:$W$1203,$AE77-1200)))) | F77: =IF($AE77="","",IF($AE77<=1200,"01水果册","02物料册")) | G77: =IF($AE77="","",IF($AE77<=1200,IF(INDEX(对接源_01水果!$M$4:$M$1203,$AE77)=0,"",INDEX(对接源_01水果!$M$4:$M$1203,$AE77)),IF(INDEX(对接源_02物料!$M$4:$M$1203,$AE77-1200)=0,"",INDEX(对接源_02物料!$M$4:$M$1203,$AE77-1200)))) | AE77: =IFERROR(MATCH(72,_自动清单!$Q$4:$Q$2403,0),"")
A78: =IF($AE78="","",IF($AE78<=1200,IF(INDEX(对接源_01水果!$B$4:$B$1203,$AE78)=0,"",INDEX(对接源_01水果!$B$4:$B$1203,$AE78)),IF(INDEX(对接源_02物料!$B$4:$B$1203,$AE78-1200)=0,"",INDEX(对接源_02物料!$B$4:$B$1203,$AE78-1200)))) | B78: =IF($AE78="","",IF($AE78<=1200,IF(INDEX(对接源_01水果!$E$4:$E$1203,$AE78)=0,"",INDEX(对接源_01水果!$E$4:$E$1203,$AE78)),IF(INDEX(对接源_02物料!$E$4:$E$1203,$AE78-1200)=0,"",INDEX(对接源_02物料!$E$4:$E$1203,$AE78-1200)))) | C78: =IF($AE78="","",IF($AE78<=1200,IF(INDEX(对接源_01水果!$S$4:$S$1203,$AE78)=0,"",INDEX(对接源_01水果!$S$4:$S$1203,$AE78)),IF(INDEX(对接源_02物料!$S$4:$S$1203,$AE78-1200)=0,"",INDEX(对接源_02物料!$S$4:$S$1203,$AE78-1200)))) | D78: =IF($AE78="","",IF($AE78<=1200,IF(INDEX(对接源_01水果!$T$4:$T$1203,$AE78)=0,"",INDEX(对接源_01水果!$T$4:$T$1203,$AE78)),IF(INDEX(对接源_02物料!$T$4:$T$1203,$AE78-1200)=0,"",INDEX(对接源_02物料!$T$4:$T$1203,$AE78-1200)))) | E78: =IF($AE78="","",IF($AE78<=1200,IF(INDEX(对接源_01水果!$W$4:$W$1203,$AE78)=0,"",INDEX(对接源_01水果!$W$4:$W$1203,$AE78)),IF(INDEX(对接源_02物料!$W$4:$W$1203,$AE78-1200)=0,"",INDEX(对接源_02物料!$W$4:$W$1203,$AE78-1200)))) | F78: =IF($AE78="","",IF($AE78<=1200,"01水果册","02物料册")) | G78: =IF($AE78="","",IF($AE78<=1200,IF(INDEX(对接源_01水果!$M$4:$M$1203,$AE78)=0,"",INDEX(对接源_01水果!$M$4:$M$1203,$AE78)),IF(INDEX(对接源_02物料!$M$4:$M$1203,$AE78-1200)=0,"",INDEX(对接源_02物料!$M$4:$M$1203,$AE78-1200)))) | AE78: =IFERROR(MATCH(73,_自动清单!$Q$4:$Q$2403,0),"")
A79: =IF($AE79="","",IF($AE79<=1200,IF(INDEX(对接源_01水果!$B$4:$B$1203,$AE79)=0,"",INDEX(对接源_01水果!$B$4:$B$1203,$AE79)),IF(INDEX(对接源_02物料!$B$4:$B$1203,$AE79-1200)=0,"",INDEX(对接源_02物料!$B$4:$B$1203,$AE79-1200)))) | B79: =IF($AE79="","",IF($AE79<=1200,IF(INDEX(对接源_01水果!$E$4:$E$1203,$AE79)=0,"",INDEX(对接源_01水果!$E$4:$E$1203,$AE79)),IF(INDEX(对接源_02物料!$E$4:$E$1203,$AE79-1200)=0,"",INDEX(对接源_02物料!$E$4:$E$1203,$AE79-1200)))) | C79: =IF($AE79="","",IF($AE79<=1200,IF(INDEX(对接源_01水果!$S$4:$S$1203,$AE79)=0,"",INDEX(对接源_01水果!$S$4:$S$1203,$AE79)),IF(INDEX(对接源_02物料!$S$4:$S$1203,$AE79-1200)=0,"",INDEX(对接源_02物料!$S$4:$S$1203,$AE79-1200)))) | D79: =IF($AE79="","",IF($AE79<=1200,IF(INDEX(对接源_01水果!$T$4:$T$1203,$AE79)=0,"",INDEX(对接源_01水果!$T$4:$T$1203,$AE79)),IF(INDEX(对接源_02物料!$T$4:$T$1203,$AE79-1200)=0,"",INDEX(对接源_02物料!$T$4:$T$1203,$AE79-1200)))) | E79: =IF($AE79="","",IF($AE79<=1200,IF(INDEX(对接源_01水果!$W$4:$W$1203,$AE79)=0,"",INDEX(对接源_01水果!$W$4:$W$1203,$AE79)),IF(INDEX(对接源_02物料!$W$4:$W$1203,$AE79-1200)=0,"",INDEX(对接源_02物料!$W$4:$W$1203,$AE79-1200)))) | F79: =IF($AE79="","",IF($AE79<=1200,"01水果册","02物料册")) | G79: =IF($AE79="","",IF($AE79<=1200,IF(INDEX(对接源_01水果!$M$4:$M$1203,$AE79)=0,"",INDEX(对接源_01水果!$M$4:$M$1203,$AE79)),IF(INDEX(对接源_02物料!$M$4:$M$1203,$AE79-1200)=0,"",INDEX(对接源_02物料!$M$4:$M$1203,$AE79-1200)))) | AE79: =IFERROR(MATCH(74,_自动清单!$Q$4:$Q$2403,0),"")
A80: =IF($AE80="","",IF($AE80<=1200,IF(INDEX(对接源_01水果!$B$4:$B$1203,$AE80)=0,"",INDEX(对接源_01水果!$B$4:$B$1203,$AE80)),IF(INDEX(对接源_02物料!$B$4:$B$1203,$AE80-1200)=0,"",INDEX(对接源_02物料!$B$4:$B$1203,$AE80-1200)))) | B80: =IF($AE80="","",IF($AE80<=1200,IF(INDEX(对接源_01水果!$E$4:$E$1203,$AE80)=0,"",INDEX(对接源_01水果!$E$4:$E$1203,$AE80)),IF(INDEX(对接源_02物料!$E$4:$E$1203,$AE80-1200)=0,"",INDEX(对接源_02物料!$E$4:$E$1203,$AE80-1200)))) | C80: =IF($AE80="","",IF($AE80<=1200,IF(INDEX(对接源_01水果!$S$4:$S$1203,$AE80)=0,"",INDEX(对接源_01水果!$S$4:$S$1203,$AE80)),IF(INDEX(对接源_02物料!$S$4:$S$1203,$AE80-1200)=0,"",INDEX(对接源_02物料!$S$4:$S$1203,$AE80-1200)))) | D80: =IF($AE80="","",IF($AE80<=1200,IF(INDEX(对接源_01水果!$T$4:$T$1203,$AE80)=0,"",INDEX(对接源_01水果!$T$4:$T$1203,$AE80)),IF(INDEX(对接源_02物料!$T$4:$T$1203,$AE80-1200)=0,"",INDEX(对接源_02物料!$T$4:$T$1203,$AE80-1200)))) | E80: =IF($AE80="","",IF($AE80<=1200,IF(INDEX(对接源_01水果!$W$4:$W$1203,$AE80)=0,"",INDEX(对接源_01水果!$W$4:$W$1203,$AE80)),IF(INDEX(对接源_02物料!$W$4:$W$1203,$AE80-1200)=0,"",INDEX(对接源_02物料!$W$4:$W$1203,$AE80-1200)))) | F80: =IF($AE80="","",IF($AE80<=1200,"01水果册","02物料册")) | G80: =IF($AE80="","",IF($AE80<=1200,IF(INDEX(对接源_01水果!$M$4:$M$1203,$AE80)=0,"",INDEX(对接源_01水果!$M$4:$M$1203,$AE80)),IF(INDEX(对接源_02物料!$M$4:$M$1203,$AE80-1200)=0,"",INDEX(对接源_02物料!$M$4:$M$1203,$AE80-1200)))) | AE80: =IFERROR(MATCH(75,_自动清单!$Q$4:$Q$2403,0),"")
A81: =IF($AE81="","",IF($AE81<=1200,IF(INDEX(对接源_01水果!$B$4:$B$1203,$AE81)=0,"",INDEX(对接源_01水果!$B$4:$B$1203,$AE81)),IF(INDEX(对接源_02物料!$B$4:$B$1203,$AE81-1200)=0,"",INDEX(对接源_02物料!$B$4:$B$1203,$AE81-1200)))) | B81: =IF($AE81="","",IF($AE81<=1200,IF(INDEX(对接源_01水果!$E$4:$E$1203,$AE81)=0,"",INDEX(对接源_01水果!$E$4:$E$1203,$AE81)),IF(INDEX(对接源_02物料!$E$4:$E$1203,$AE81-1200)=0,"",INDEX(对接源_02物料!$E$4:$E$1203,$AE81-1200)))) | C81: =IF($AE81="","",IF($AE81<=1200,IF(INDEX(对接源_01水果!$S$4:$S$1203,$AE81)=0,"",INDEX(对接源_01水果!$S$4:$S$1203,$AE81)),IF(INDEX(对接源_02物料!$S$4:$S$1203,$AE81-1200)=0,"",INDEX(对接源_02物料!$S$4:$S$1203,$AE81-1200)))) | D81: =IF($AE81="","",IF($AE81<=1200,IF(INDEX(对接源_01水果!$T$4:$T$1203,$AE81)=0,"",INDEX(对接源_01水果!$T$4:$T$1203,$AE81)),IF(INDEX(对接源_02物料!$T$4:$T$1203,$AE81-1200)=0,"",INDEX(对接源_02物料!$T$4:$T$1203,$AE81-1200)))) | E81: =IF($AE81="","",IF($AE81<=1200,IF(INDEX(对接源_01水果!$W$4:$W$1203,$AE81)=0,"",INDEX(对接源_01水果!$W$4:$W$1203,$AE81)),IF(INDEX(对接源_02物料!$W$4:$W$1203,$AE81-1200)=0,"",INDEX(对接源_02物料!$W$4:$W$1203,$AE81-1200)))) | F81: =IF($AE81="","",IF($AE81<=1200,"01水果册","02物料册")) | G81: =IF($AE81="","",IF($AE81<=1200,IF(INDEX(对接源_01水果!$M$4:$M$1203,$AE81)=0,"",INDEX(对接源_01水果!$M$4:$M$1203,$AE81)),IF(INDEX(对接源_02物料!$M$4:$M$1203,$AE81-1200)=0,"",INDEX(对接源_02物料!$M$4:$M$1203,$AE81-1200)))) | AE81: =IFERROR(MATCH(76,_自动清单!$Q$4:$Q$2403,0),"")
A82: =IF($AE82="","",IF($AE82<=1200,IF(INDEX(对接源_01水果!$B$4:$B$1203,$AE82)=0,"",INDEX(对接源_01水果!$B$4:$B$1203,$AE82)),IF(INDEX(对接源_02物料!$B$4:$B$1203,$AE82-1200)=0,"",INDEX(对接源_02物料!$B$4:$B$1203,$AE82-1200)))) | B82: =IF($AE82="","",IF($AE82<=1200,IF(INDEX(对接源_01水果!$E$4:$E$1203,$AE82)=0,"",INDEX(对接源_01水果!$E$4:$E$1203,$AE82)),IF(INDEX(对接源_02物料!$E$4:$E$1203,$AE82-1200)=0,"",INDEX(对接源_02物料!$E$4:$E$1203,$AE82-1200)))) | C82: =IF($AE82="","",IF($AE82<=1200,IF(INDEX(对接源_01水果!$S$4:$S$1203,$AE82)=0,"",INDEX(对接源_01水果!$S$4:$S$1203,$AE82)),IF(INDEX(对接源_02物料!$S$4:$S$1203,$AE82-1200)=0,"",INDEX(对接源_02物料!$S$4:$S$1203,$AE82-1200)))) | D82: =IF($AE82="","",IF($AE82<=1200,IF(INDEX(对接源_01水果!$T$4:$T$1203,$AE82)=0,"",INDEX(对接源_01水果!$T$4:$T$1203,$AE82)),IF(INDEX(对接源_02物料!$T$4:$T$1203,$AE82-1200)=0,"",INDEX(对接源_02物料!$T$4:$T$1203,$AE82-1200)))) | E82: =IF($AE82="","",IF($AE82<=1200,IF(INDEX(对接源_01水果!$W$4:$W$1203,$AE82)=0,"",INDEX(对接源_01水果!$W$4:$W$1203,$AE82)),IF(INDEX(对接源_02物料!$W$4:$W$1203,$AE82-1200)=0,"",INDEX(对接源_02物料!$W$4:$W$1203,$AE82-1200)))) | F82: =IF($AE82="","",IF($AE82<=1200,"01水果册","02物料册")) | G82: =IF($AE82="","",IF($AE82<=1200,IF(INDEX(对接源_01水果!$M$4:$M$1203,$AE82)=0,"",INDEX(对接源_01水果!$M$4:$M$1203,$AE82)),IF(INDEX(对接源_02物料!$M$4:$M$1203,$AE82-1200)=0,"",INDEX(对接源_02物料!$M$4:$M$1203,$AE82-1200)))) | AE82: =IFERROR(MATCH(77,_自动清单!$Q$4:$Q$2403,0),"")
A83: =IF($AE83="","",IF($AE83<=1200,IF(INDEX(对接源_01水果!$B$4:$B$1203,$AE83)=0,"",INDEX(对接源_01水果!$B$4:$B$1203,$AE83)),IF(INDEX(对接源_02物料!$B$4:$B$1203,$AE83-1200)=0,"",INDEX(对接源_02物料!$B$4:$B$1203,$AE83-1200)))) | B83: =IF($AE83="","",IF($AE83<=1200,IF(INDEX(对接源_01水果!$E$4:$E$1203,$AE83)=0,"",INDEX(对接源_01水果!$E$4:$E$1203,$AE83)),IF(INDEX(对接源_02物料!$E$4:$E$1203,$AE83-1200)=0,"",INDEX(对接源_02物料!$E$4:$E$1203,$AE83-1200)))) | C83: =IF($AE83="","",IF($AE83<=1200,IF(INDEX(对接源_01水果!$S$4:$S$1203,$AE83)=0,"",INDEX(对接源_01水果!$S$4:$S$1203,$AE83)),IF(INDEX(对接源_02物料!$S$4:$S$1203,$AE83-1200)=0,"",INDEX(对接源_02物料!$S$4:$S$1203,$AE83-1200)))) | D83: =IF($AE83="","",IF($AE83<=1200,IF(INDEX(对接源_01水果!$T$4:$T$1203,$AE83)=0,"",INDEX(对接源_01水果!$T$4:$T$1203,$AE83)),IF(INDEX(对接源_02物料!$T$4:$T$1203,$AE83-1200)=0,"",INDEX(对接源_02物料!$T$4:$T$1203,$AE83-1200)))) | E83: =IF($AE83="","",IF($AE83<=1200,IF(INDEX(对接源_01水果!$W$4:$W$1203,$AE83)=0,"",INDEX(对接源_01水果!$W$4:$W$1203,$AE83)),IF(INDEX(对接源_02物料!$W$4:$W$1203,$AE83-1200)=0,"",INDEX(对接源_02物料!$W$4:$W$1203,$AE83-1200)))) | F83: =IF($AE83="","",IF($AE83<=1200,"01水果册","02物料册")) | G83: =IF($AE83="","",IF($AE83<=1200,IF(INDEX(对接源_01水果!$M$4:$M$1203,$AE83)=0,"",INDEX(对接源_01水果!$M$4:$M$1203,$AE83)),IF(INDEX(对接源_02物料!$M$4:$M$1203,$AE83-1200)=0,"",INDEX(对接源_02物料!$M$4:$M$1203,$AE83-1200)))) | AE83: =IFERROR(MATCH(78,_自动清单!$Q$4:$Q$2403,0),"")
A84: =IF($AE84="","",IF($AE84<=1200,IF(INDEX(对接源_01水果!$B$4:$B$1203,$AE84)=0,"",INDEX(对接源_01水果!$B$4:$B$1203,$AE84)),IF(INDEX(对接源_02物料!$B$4:$B$1203,$AE84-1200)=0,"",INDEX(对接源_02物料!$B$4:$B$1203,$AE84-1200)))) | B84: =IF($AE84="","",IF($AE84<=1200,IF(INDEX(对接源_01水果!$E$4:$E$1203,$AE84)=0,"",INDEX(对接源_01水果!$E$4:$E$1203,$AE84)),IF(INDEX(对接源_02物料!$E$4:$E$1203,$AE84-1200)=0,"",INDEX(对接源_02物料!$E$4:$E$1203,$AE84-1200)))) | C84: =IF($AE84="","",IF($AE84<=1200,IF(INDEX(对接源_01水果!$S$4:$S$1203,$AE84)=0,"",INDEX(对接源_01水果!$S$4:$S$1203,$AE84)),IF(INDEX(对接源_02物料!$S$4:$S$1203,$AE84-1200)=0,"",INDEX(对接源_02物料!$S$4:$S$1203,$AE84-1200)))) | D84: =IF($AE84="","",IF($AE84<=1200,IF(INDEX(对接源_01水果!$T$4:$T$1203,$AE84)=0,"",INDEX(对接源_01水果!$T$4:$T$1203,$AE84)),IF(INDEX(对接源_02物料!$T$4:$T$1203,$AE84-1200)=0,"",INDEX(对接源_02物料!$T$4:$T$1203,$AE84-1200)))) | E84: =IF($AE84="","",IF($AE84<=1200,IF(INDEX(对接源_01水果!$W$4:$W$1203,$AE84)=0,"",INDEX(对接源_01水果!$W$4:$W$1203,$AE84)),IF(INDEX(对接源_02物料!$W$4:$W$1203,$AE84-1200)=0,"",INDEX(对接源_02物料!$W$4:$W$1203,$AE84-1200)))) | F84: =IF($AE84="","",IF($AE84<=1200,"01水果册","02物料册")) | G84: =IF($AE84="","",IF($AE84<=1200,IF(INDEX(对接源_01水果!$M$4:$M$1203,$AE84)=0,"",INDEX(对接源_01水果!$M$4:$M$1203,$AE84)),IF(INDEX(对接源_02物料!$M$4:$M$1203,$AE84-1200)=0,"",INDEX(对接源_02物料!$M$4:$M$1203,$AE84-1200)))) | AE84: =IFERROR(MATCH(79,_自动清单!$Q$4:$Q$2403,0),"")
A85: =IF($AE85="","",IF($AE85<=1200,IF(INDEX(对接源_01水果!$B$4:$B$1203,$AE85)=0,"",INDEX(对接源_01水果!$B$4:$B$1203,$AE85)),IF(INDEX(对接源_02物料!$B$4:$B$1203,$AE85-1200)=0,"",INDEX(对接源_02物料!$B$4:$B$1203,$AE85-1200)))) | B85: =IF($AE85="","",IF($AE85<=1200,IF(INDEX(对接源_01水果!$E$4:$E$1203,$AE85)=0,"",INDEX(对接源_01水果!$E$4:$E$1203,$AE85)),IF(INDEX(对接源_02物料!$E$4:$E$1203,$AE85-1200)=0,"",INDEX(对接源_02物料!$E$4:$E$1203,$AE85-1200)))) | C85: =IF($AE85="","",IF($AE85<=1200,IF(INDEX(对接源_01水果!$S$4:$S$1203,$AE85)=0,"",INDEX(对接源_01水果!$S$4:$S$1203,$AE85)),IF(INDEX(对接源_02物料!$S$4:$S$1203,$AE85-1200)=0,"",INDEX(对接源_02物料!$S$4:$S$1203,$AE85-1200)))) | D85: =IF($AE85="","",IF($AE85<=1200,IF(INDEX(对接源_01水果!$T$4:$T$1203,$AE85)=0,"",INDEX(对接源_01水果!$T$4:$T$1203,$AE85)),IF(INDEX(对接源_02物料!$T$4:$T$1203,$AE85-1200)=0,"",INDEX(对接源_02物料!$T$4:$T$1203,$AE85-1200)))) | E85: =IF($AE85="","",IF($AE85<=1200,IF(INDEX(对接源_01水果!$W$4:$W$1203,$AE85)=0,"",INDEX(对接源_01水果!$W$4:$W$1203,$AE85)),IF(INDEX(对接源_02物料!$W$4:$W$1203,$AE85-1200)=0,"",INDEX(对接源_02物料!$W$4:$W$1203,$AE85-1200)))) | F85: =IF($AE85="","",IF($AE85<=1200,"01水果册","02物料册")) | G85: =IF($AE85="","",IF($AE85<=1200,IF(INDEX(对接源_01水果!$M$4:$M$1203,$AE85)=0,"",INDEX(对接源_01水果!$M$4:$M$1203,$AE85)),IF(INDEX(对接源_02物料!$M$4:$M$1203,$AE85-1200)=0,"",INDEX(对接源_02物料!$M$4:$M$1203,$AE85-1200)))) | AE85: =IFERROR(MATCH(80,_自动清单!$Q$4:$Q$2403,0),"")
A86: =IF($AE86="","",IF($AE86<=1200,IF(INDEX(对接源_01水果!$B$4:$B$1203,$AE86)=0,"",INDEX(对接源_01水果!$B$4:$B$1203,$AE86)),IF(INDEX(对接源_02物料!$B$4:$B$1203,$AE86-1200)=0,"",INDEX(对接源_02物料!$B$4:$B$1203,$AE86-1200)))) | B86: =IF($AE86="","",IF($AE86<=1200,IF(INDEX(对接源_01水果!$E$4:$E$1203,$AE86)=0,"",INDEX(对接源_01水果!$E$4:$E$1203,$AE86)),IF(INDEX(对接源_02物料!$E$4:$E$1203,$AE86-1200)=0,"",INDEX(对接源_02物料!$E$4:$E$1203,$AE86-1200)))) | C86: =IF($AE86="","",IF($AE86<=1200,IF(INDEX(对接源_01水果!$S$4:$S$1203,$AE86)=0,"",INDEX(对接源_01水果!$S$4:$S$1203,$AE86)),IF(INDEX(对接源_02物料!$S$4:$S$1203,$AE86-1200)=0,"",INDEX(对接源_02物料!$S$4:$S$1203,$AE86-1200)))) | D86: =IF($AE86="","",IF($AE86<=1200,IF(INDEX(对接源_01水果!$T$4:$T$1203,$AE86)=0,"",INDEX(对接源_01水果!$T$4:$T$1203,$AE86)),IF(INDEX(对接源_02物料!$T$4:$T$1203,$AE86-1200)=0,"",INDEX(对接源_02物料!$T$4:$T$1203,$AE86-1200)))) | E86: =IF($AE86="","",IF($AE86<=1200,IF(INDEX(对接源_01水果!$W$4:$W$1203,$AE86)=0,"",INDEX(对接源_01水果!$W$4:$W$1203,$AE86)),IF(INDEX(对接源_02物料!$W$4:$W$1203,$AE86-1200)=0,"",INDEX(对接源_02物料!$W$4:$W$1203,$AE86-1200)))) | F86: =IF($AE86="","",IF($AE86<=1200,"01水果册","02物料册")) | G86: =IF($AE86="","",IF($AE86<=1200,IF(INDEX(对接源_01水果!$M$4:$M$1203,$AE86)=0,"",INDEX(对接源_01水果!$M$4:$M$1203,$AE86)),IF(INDEX(对接源_02物料!$M$4:$M$1203,$AE86-1200)=0,"",INDEX(对接源_02物料!$M$4:$M$1203,$AE86-1200)))) | AE86: =IFERROR(MATCH(81,_自动清单!$Q$4:$Q$2403,0),"")
A87: =IF($AE87="","",IF($AE87<=1200,IF(INDEX(对接源_01水果!$B$4:$B$1203,$AE87)=0,"",INDEX(对接源_01水果!$B$4:$B$1203,$AE87)),IF(INDEX(对接源_02物料!$B$4:$B$1203,$AE87-1200)=0,"",INDEX(对接源_02物料!$B$4:$B$1203,$AE87-1200)))) | B87: =IF($AE87="","",IF($AE87<=1200,IF(INDEX(对接源_01水果!$E$4:$E$1203,$AE87)=0,"",INDEX(对接源_01水果!$E$4:$E$1203,$AE87)),IF(INDEX(对接源_02物料!$E$4:$E$1203,$AE87-1200)=0,"",INDEX(对接源_02物料!$E$4:$E$1203,$AE87-1200)))) | C87: =IF($AE87="","",IF($AE87<=1200,IF(INDEX(对接源_01水果!$S$4:$S$1203,$AE87)=0,"",INDEX(对接源_01水果!$S$4:$S$1203,$AE87)),IF(INDEX(对接源_02物料!$S$4:$S$1203,$AE87-1200)=0,"",INDEX(对接源_02物料!$S$4:$S$1203,$AE87-1200)))) | D87: =IF($AE87="","",IF($AE87<=1200,IF(INDEX(对接源_01水果!$T$4:$T$1203,$AE87)=0,"",INDEX(对接源_01水果!$T$4:$T$1203,$AE87)),IF(INDEX(对接源_02物料!$T$4:$T$1203,$AE87-1200)=0,"",INDEX(对接源_02物料!$T$4:$T$1203,$AE87-1200)))) | E87: =IF($AE87="","",IF($AE87<=1200,IF(INDEX(对接源_01水果!$W$4:$W$1203,$AE87)=0,"",INDEX(对接源_01水果!$W$4:$W$1203,$AE87)),IF(INDEX(对接源_02物料!$W$4:$W$1203,$AE87-1200)=0,"",INDEX(对接源_02物料!$W$4:$W$1203,$AE87-1200)))) | F87: =IF($AE87="","",IF($AE87<=1200,"01水果册","02物料册")) | G87: =IF($AE87="","",IF($AE87<=1200,IF(INDEX(对接源_01水果!$M$4:$M$1203,$AE87)=0,"",INDEX(对接源_01水果!$M$4:$M$1203,$AE87)),IF(INDEX(对接源_02物料!$M$4:$M$1203,$AE87-1200)=0,"",INDEX(对接源_02物料!$M$4:$M$1203,$AE87-1200)))) | AE87: =IFERROR(MATCH(82,_自动清单!$Q$4:$Q$2403,0),"")
A88: =IF($AE88="","",IF($AE88<=1200,IF(INDEX(对接源_01水果!$B$4:$B$1203,$AE88)=0,"",INDEX(对接源_01水果!$B$4:$B$1203,$AE88)),IF(INDEX(对接源_02物料!$B$4:$B$1203,$AE88-1200)=0,"",INDEX(对接源_02物料!$B$4:$B$1203,$AE88-1200)))) | B88: =IF($AE88="","",IF($AE88<=1200,IF(INDEX(对接源_01水果!$E$4:$E$1203,$AE88)=0,"",INDEX(对接源_01水果!$E$4:$E$1203,$AE88)),IF(INDEX(对接源_02物料!$E$4:$E$1203,$AE88-1200)=0,"",INDEX(对接源_02物料!$E$4:$E$1203,$AE88-1200)))) | C88: =IF($AE88="","",IF($AE88<=1200,IF(INDEX(对接源_01水果!$S$4:$S$1203,$AE88)=0,"",INDEX(对接源_01水果!$S$4:$S$1203,$AE88)),IF(INDEX(对接源_02物料!$S$4:$S$1203,$AE88-1200)=0,"",INDEX(对接源_02物料!$S$4:$S$1203,$AE88-1200)))) | D88: =IF($AE88="","",IF($AE88<=1200,IF(INDEX(对接源_01水果!$T$4:$T$1203,$AE88)=0,"",INDEX(对接源_01水果!$T$4:$T$1203,$AE88)),IF(INDEX(对接源_02物料!$T$4:$T$1203,$AE88-1200)=0,"",INDEX(对接源_02物料!$T$4:$T$1203,$AE88-1200)))) | E88: =IF($AE88="","",IF($AE88<=1200,IF(INDEX(对接源_01水果!$W$4:$W$1203,$AE88)=0,"",INDEX(对接源_01水果!$W$4:$W$1203,$AE88)),IF(INDEX(对接源_02物料!$W$4:$W$1203,$AE88-1200)=0,"",INDEX(对接源_02物料!$W$4:$W$1203,$AE88-1200)))) | F88: =IF($AE88="","",IF($AE88<=1200,"01水果册","02物料册")) | G88: =IF($AE88="","",IF($AE88<=1200,IF(INDEX(对接源_01水果!$M$4:$M$1203,$AE88)=0,"",INDEX(对接源_01水果!$M$4:$M$1203,$AE88)),IF(INDEX(对接源_02物料!$M$4:$M$1203,$AE88-1200)=0,"",INDEX(对接源_02物料!$M$4:$M$1203,$AE88-1200)))) | AE88: =IFERROR(MATCH(83,_自动清单!$Q$4:$Q$2403,0),"")
A89: =IF($AE89="","",IF($AE89<=1200,IF(INDEX(对接源_01水果!$B$4:$B$1203,$AE89)=0,"",INDEX(对接源_01水果!$B$4:$B$1203,$AE89)),IF(INDEX(对接源_02物料!$B$4:$B$1203,$AE89-1200)=0,"",INDEX(对接源_02物料!$B$4:$B$1203,$AE89-1200)))) | B89: =IF($AE89="","",IF($AE89<=1200,IF(INDEX(对接源_01水果!$E$4:$E$1203,$AE89)=0,"",INDEX(对接源_01水果!$E$4:$E$1203,$AE89)),IF(INDEX(对接源_02物料!$E$4:$E$1203,$AE89-1200)=0,"",INDEX(对接源_02物料!$E$4:$E$1203,$AE89-1200)))) | C89: =IF($AE89="","",IF($AE89<=1200,IF(INDEX(对接源_01水果!$S$4:$S$1203,$AE89)=0,"",INDEX(对接源_01水果!$S$4:$S$1203,$AE89)),IF(INDEX(对接源_02物料!$S$4:$S$1203,$AE89-1200)=0,"",INDEX(对接源_02物料!$S$4:$S$1203,$AE89-1200)))) | D89: =IF($AE89="","",IF($AE89<=1200,IF(INDEX(对接源_01水果!$T$4:$T$1203,$AE89)=0,"",INDEX(对接源_01水果!$T$4:$T$1203,$AE89)),IF(INDEX(对接源_02物料!$T$4:$T$1203,$AE89-1200)=0,"",INDEX(对接源_02物料!$T$4:$T$1203,$AE89-1200)))) | E89: =IF($AE89="","",IF($AE89<=1200,IF(INDEX(对接源_01水果!$W$4:$W$1203,$AE89)=0,"",INDEX(对接源_01水果!$W$4:$W$1203,$AE89)),IF(INDEX(对接源_02物料!$W$4:$W$1203,$AE89-1200)=0,"",INDEX(对接源_02物料!$W$4:$W$1203,$AE89-1200)))) | F89: =IF($AE89="","",IF($AE89<=1200,"01水果册","02物料册")) | G89: =IF($AE89="","",IF($AE89<=1200,IF(INDEX(对接源_01水果!$M$4:$M$1203,$AE89)=0,"",INDEX(对接源_01水果!$M$4:$M$1203,$AE89)),IF(INDEX(对接源_02物料!$M$4:$M$1203,$AE89-1200)=0,"",INDEX(对接源_02物料!$M$4:$M$1203,$AE89-1200)))) | AE89: =IFERROR(MATCH(84,_自动清单!$Q$4:$Q$2403,0),"")
A90: =IF($AE90="","",IF($AE90<=1200,IF(INDEX(对接源_01水果!$B$4:$B$1203,$AE90)=0,"",INDEX(对接源_01水果!$B$4:$B$1203,$AE90)),IF(INDEX(对接源_02物料!$B$4:$B$1203,$AE90-1200)=0,"",INDEX(对接源_02物料!$B$4:$B$1203,$AE90-1200)))) | B90: =IF($AE90="","",IF($AE90<=1200,IF(INDEX(对接源_01水果!$E$4:$E$1203,$AE90)=0,"",INDEX(对接源_01水果!$E$4:$E$1203,$AE90)),IF(INDEX(对接源_02物料!$E$4:$E$1203,$AE90-1200)=0,"",INDEX(对接源_02物料!$E$4:$E$1203,$AE90-1200)))) | C90: =IF($AE90="","",IF($AE90<=1200,IF(INDEX(对接源_01水果!$S$4:$S$1203,$AE90)=0,"",INDEX(对接源_01水果!$S$4:$S$1203,$AE90)),IF(INDEX(对接源_02物料!$S$4:$S$1203,$AE90-1200)=0,"",INDEX(对接源_02物料!$S$4:$S$1203,$AE90-1200)))) | D90: =IF($AE90="","",IF($AE90<=1200,IF(INDEX(对接源_01水果!$T$4:$T$1203,$AE90)=0,"",INDEX(对接源_01水果!$T$4:$T$1203,$AE90)),IF(INDEX(对接源_02物料!$T$4:$T$1203,$AE90-1200)=0,"",INDEX(对接源_02物料!$T$4:$T$1203,$AE90-1200)))) | E90: =IF($AE90="","",IF($AE90<=1200,IF(INDEX(对接源_01水果!$W$4:$W$1203,$AE90)=0,"",INDEX(对接源_01水果!$W$4:$W$1203,$AE90)),IF(INDEX(对接源_02物料!$W$4:$W$1203,$AE90-1200)=0,"",INDEX(对接源_02物料!$W$4:$W$1203,$AE90-1200)))) | F90: =IF($AE90="","",IF($AE90<=1200,"01水果册","02物料册")) | G90: =IF($AE90="","",IF($AE90<=1200,IF(INDEX(对接源_01水果!$M$4:$M$1203,$AE90)=0,"",INDEX(对接源_01水果!$M$4:$M$1203,$AE90)),IF(INDEX(对接源_02物料!$M$4:$M$1203,$AE90-1200)=0,"",INDEX(对接源_02物料!$M$4:$M$1203,$AE90-1200)))) | AE90: =IFERROR(MATCH(85,_自动清单!$Q$4:$Q$2403,0),"")
A91: =IF($AE91="","",IF($AE91<=1200,IF(INDEX(对接源_01水果!$B$4:$B$1203,$AE91)=0,"",INDEX(对接源_01水果!$B$4:$B$1203,$AE91)),IF(INDEX(对接源_02物料!$B$4:$B$1203,$AE91-1200)=0,"",INDEX(对接源_02物料!$B$4:$B$1203,$AE91-1200)))) | B91: =IF($AE91="","",IF($AE91<=1200,IF(INDEX(对接源_01水果!$E$4:$E$1203,$AE91)=0,"",INDEX(对接源_01水果!$E$4:$E$1203,$AE91)),IF(INDEX(对接源_02物料!$E$4:$E$1203,$AE91-1200)=0,"",INDEX(对接源_02物料!$E$4:$E$1203,$AE91-1200)))) | C91: =IF($AE91="","",IF($AE91<=1200,IF(INDEX(对接源_01水果!$S$4:$S$1203,$AE91)=0,"",INDEX(对接源_01水果!$S$4:$S$1203,$AE91)),IF(INDEX(对接源_02物料!$S$4:$S$1203,$AE91-1200)=0,"",INDEX(对接源_02物料!$S$4:$S$1203,$AE91-1200)))) | D91: =IF($AE91="","",IF($AE91<=1200,IF(INDEX(对接源_01水果!$T$4:$T$1203,$AE91)=0,"",INDEX(对接源_01水果!$T$4:$T$1203,$AE91)),IF(INDEX(对接源_02物料!$T$4:$T$1203,$AE91-1200)=0,"",INDEX(对接源_02物料!$T$4:$T$1203,$AE91-1200)))) | E91: =IF($AE91="","",IF($AE91<=1200,IF(INDEX(对接源_01水果!$W$4:$W$1203,$AE91)=0,"",INDEX(对接源_01水果!$W$4:$W$1203,$AE91)),IF(INDEX(对接源_02物料!$W$4:$W$1203,$AE91-1200)=0,"",INDEX(对接源_02物料!$W$4:$W$1203,$AE91-1200)))) | F91: =IF($AE91="","",IF($AE91<=1200,"01水果册","02物料册")) | G91: =IF($AE91="","",IF($AE91<=1200,IF(INDEX(对接源_01水果!$M$4:$M$1203,$AE91)=0,"",INDEX(对接源_01水果!$M$4:$M$1203,$AE91)),IF(INDEX(对接源_02物料!$M$4:$M$1203,$AE91-1200)=0,"",INDEX(对接源_02物料!$M$4:$M$1203,$AE91-1200)))) | AE91: =IFERROR(MATCH(86,_自动清单!$Q$4:$Q$2403,0),"")
A92: =IF($AE92="","",IF($AE92<=1200,IF(INDEX(对接源_01水果!$B$4:$B$1203,$AE92)=0,"",INDEX(对接源_01水果!$B$4:$B$1203,$AE92)),IF(INDEX(对接源_02物料!$B$4:$B$1203,$AE92-1200)=0,"",INDEX(对接源_02物料!$B$4:$B$1203,$AE92-1200)))) | B92: =IF($AE92="","",IF($AE92<=1200,IF(INDEX(对接源_01水果!$E$4:$E$1203,$AE92)=0,"",INDEX(对接源_01水果!$E$4:$E$1203,$AE92)),IF(INDEX(对接源_02物料!$E$4:$E$1203,$AE92-1200)=0,"",INDEX(对接源_02物料!$E$4:$E$1203,$AE92-1200)))) | C92: =IF($AE92="","",IF($AE92<=1200,IF(INDEX(对接源_01水果!$S$4:$S$1203,$AE92)=0,"",INDEX(对接源_01水果!$S$4:$S$1203,$AE92)),IF(INDEX(对接源_02物料!$S$4:$S$1203,$AE92-1200)=0,"",INDEX(对接源_02物料!$S$4:$S$1203,$AE92-1200)))) | D92: =IF($AE92="","",IF($AE92<=1200,IF(INDEX(对接源_01水果!$T$4:$T$1203,$AE92)=0,"",INDEX(对接源_01水果!$T$4:$T$1203,$AE92)),IF(INDEX(对接源_02物料!$T$4:$T$1203,$AE92-1200)=0,"",INDEX(对接源_02物料!$T$4:$T$1203,$AE92-1200)))) | E92: =IF($AE92="","",IF($AE92<=1200,IF(INDEX(对接源_01水果!$W$4:$W$1203,$AE92)=0,"",INDEX(对接源_01水果!$W$4:$W$1203,$AE92)),IF(INDEX(对接源_02物料!$W$4:$W$1203,$AE92-1200)=0,"",INDEX(对接源_02物料!$W$4:$W$1203,$AE92-1200)))) | F92: =IF($AE92="","",IF($AE92<=1200,"01水果册","02物料册")) | G92: =IF($AE92="","",IF($AE92<=1200,IF(INDEX(对接源_01水果!$M$4:$M$1203,$AE92)=0,"",INDEX(对接源_01水果!$M$4:$M$1203,$AE92)),IF(INDEX(对接源_02物料!$M$4:$M$1203,$AE92-1200)=0,"",INDEX(对接源_02物料!$M$4:$M$1203,$AE92-1200)))) | AE92: =IFERROR(MATCH(87,_自动清单!$Q$4:$Q$2403,0),"")
A93: =IF($AE93="","",IF($AE93<=1200,IF(INDEX(对接源_01水果!$B$4:$B$1203,$AE93)=0,"",INDEX(对接源_01水果!$B$4:$B$1203,$AE93)),IF(INDEX(对接源_02物料!$B$4:$B$1203,$AE93-1200)=0,"",INDEX(对接源_02物料!$B$4:$B$1203,$AE93-1200)))) | B93: =IF($AE93="","",IF($AE93<=1200,IF(INDEX(对接源_01水果!$E$4:$E$1203,$AE93)=0,"",INDEX(对接源_01水果!$E$4:$E$1203,$AE93)),IF(INDEX(对接源_02物料!$E$4:$E$1203,$AE93-1200)=0,"",INDEX(对接源_02物料!$E$4:$E$1203,$AE93-1200)))) | C93: =IF($AE93="","",IF($AE93<=1200,IF(INDEX(对接源_01水果!$S$4:$S$1203,$AE93)=0,"",INDEX(对接源_01水果!$S$4:$S$1203,$AE93)),IF(INDEX(对接源_02物料!$S$4:$S$1203,$AE93-1200)=0,"",INDEX(对接源_02物料!$S$4:$S$1203,$AE93-1200)))) | D93: =IF($AE93="","",IF($AE93<=1200,IF(INDEX(对接源_01水果!$T$4:$T$1203,$AE93)=0,"",INDEX(对接源_01水果!$T$4:$T$1203,$AE93)),IF(INDEX(对接源_02物料!$T$4:$T$1203,$AE93-1200)=0,"",INDEX(对接源_02物料!$T$4:$T$1203,$AE93-1200)))) | E93: =IF($AE93="","",IF($AE93<=1200,IF(INDEX(对接源_01水果!$W$4:$W$1203,$AE93)=0,"",INDEX(对接源_01水果!$W$4:$W$1203,$AE93)),IF(INDEX(对接源_02物料!$W$4:$W$1203,$AE93-1200)=0,"",INDEX(对接源_02物料!$W$4:$W$1203,$AE93-1200)))) | F93: =IF($AE93="","",IF($AE93<=1200,"01水果册","02物料册")) | G93: =IF($AE93="","",IF($AE93<=1200,IF(INDEX(对接源_01水果!$M$4:$M$1203,$AE93)=0,"",INDEX(对接源_01水果!$M$4:$M$1203,$AE93)),IF(INDEX(对接源_02物料!$M$4:$M$1203,$AE93-1200)=0,"",INDEX(对接源_02物料!$M$4:$M$1203,$AE93-1200)))) | AE93: =IFERROR(MATCH(88,_自动清单!$Q$4:$Q$2403,0),"")
A94: =IF($AE94="","",IF($AE94<=1200,IF(INDEX(对接源_01水果!$B$4:$B$1203,$AE94)=0,"",INDEX(对接源_01水果!$B$4:$B$1203,$AE94)),IF(INDEX(对接源_02物料!$B$4:$B$1203,$AE94-1200)=0,"",INDEX(对接源_02物料!$B$4:$B$1203,$AE94-1200)))) | B94: =IF($AE94="","",IF($AE94<=1200,IF(INDEX(对接源_01水果!$E$4:$E$1203,$AE94)=0,"",INDEX(对接源_01水果!$E$4:$E$1203,$AE94)),IF(INDEX(对接源_02物料!$E$4:$E$1203,$AE94-1200)=0,"",INDEX(对接源_02物料!$E$4:$E$1203,$AE94-1200)))) | C94: =IF($AE94="","",IF($AE94<=1200,IF(INDEX(对接源_01水果!$S$4:$S$1203,$AE94)=0,"",INDEX(对接源_01水果!$S$4:$S$1203,$AE94)),IF(INDEX(对接源_02物料!$S$4:$S$1203,$AE94-1200)=0,"",INDEX(对接源_02物料!$S$4:$S$1203,$AE94-1200)))) | D94: =IF($AE94="","",IF($AE94<=1200,IF(INDEX(对接源_01水果!$T$4:$T$1203,$AE94)=0,"",INDEX(对接源_01水果!$T$4:$T$1203,$AE94)),IF(INDEX(对接源_02物料!$T$4:$T$1203,$AE94-1200)=0,"",INDEX(对接源_02物料!$T$4:$T$1203,$AE94-1200)))) | E94: =IF($AE94="","",IF($AE94<=1200,IF(INDEX(对接源_01水果!$W$4:$W$1203,$AE94)=0,"",INDEX(对接源_01水果!$W$4:$W$1203,$AE94)),IF(INDEX(对接源_02物料!$W$4:$W$1203,$AE94-1200)=0,"",INDEX(对接源_02物料!$W$4:$W$1203,$AE94-1200)))) | F94: =IF($AE94="","",IF($AE94<=1200,"01水果册","02物料册")) | G94: =IF($AE94="","",IF($AE94<=1200,IF(INDEX(对接源_01水果!$M$4:$M$1203,$AE94)=0,"",INDEX(对接源_01水果!$M$4:$M$1203,$AE94)),IF(INDEX(对接源_02物料!$M$4:$M$1203,$AE94-1200)=0,"",INDEX(对接源_02物料!$M$4:$M$1203,$AE94-1200)))) | AE94: =IFERROR(MATCH(89,_自动清单!$Q$4:$Q$2403,0),"")
A95: =IF($AE95="","",IF($AE95<=1200,IF(INDEX(对接源_01水果!$B$4:$B$1203,$AE95)=0,"",INDEX(对接源_01水果!$B$4:$B$1203,$AE95)),IF(INDEX(对接源_02物料!$B$4:$B$1203,$AE95-1200)=0,"",INDEX(对接源_02物料!$B$4:$B$1203,$AE95-1200)))) | B95: =IF($AE95="","",IF($AE95<=1200,IF(INDEX(对接源_01水果!$E$4:$E$1203,$AE95)=0,"",INDEX(对接源_01水果!$E$4:$E$1203,$AE95)),IF(INDEX(对接源_02物料!$E$4:$E$1203,$AE95-1200)=0,"",INDEX(对接源_02物料!$E$4:$E$1203,$AE95-1200)))) | C95: =IF($AE95="","",IF($AE95<=1200,IF(INDEX(对接源_01水果!$S$4:$S$1203,$AE95)=0,"",INDEX(对接源_01水果!$S$4:$S$1203,$AE95)),IF(INDEX(对接源_02物料!$S$4:$S$1203,$AE95-1200)=0,"",INDEX(对接源_02物料!$S$4:$S$1203,$AE95-1200)))) | D95: =IF($AE95="","",IF($AE95<=1200,IF(INDEX(对接源_01水果!$T$4:$T$1203,$AE95)=0,"",INDEX(对接源_01水果!$T$4:$T$1203,$AE95)),IF(INDEX(对接源_02物料!$T$4:$T$1203,$AE95-1200)=0,"",INDEX(对接源_02物料!$T$4:$T$1203,$AE95-1200)))) | E95: =IF($AE95="","",IF($AE95<=1200,IF(INDEX(对接源_01水果!$W$4:$W$1203,$AE95)=0,"",INDEX(对接源_01水果!$W$4:$W$1203,$AE95)),IF(INDEX(对接源_02物料!$W$4:$W$1203,$AE95-1200)=0,"",INDEX(对接源_02物料!$W$4:$W$1203,$AE95-1200)))) | F95: =IF($AE95="","",IF($AE95<=1200,"01水果册","02物料册")) | G95: =IF($AE95="","",IF($AE95<=1200,IF(INDEX(对接源_01水果!$M$4:$M$1203,$AE95)=0,"",INDEX(对接源_01水果!$M$4:$M$1203,$AE95)),IF(INDEX(对接源_02物料!$M$4:$M$1203,$AE95-1200)=0,"",INDEX(对接源_02物料!$M$4:$M$1203,$AE95-1200)))) | AE95: =IFERROR(MATCH(90,_自动清单!$Q$4:$Q$2403,0),"")
A96: =IF($AE96="","",IF($AE96<=1200,IF(INDEX(对接源_01水果!$B$4:$B$1203,$AE96)=0,"",INDEX(对接源_01水果!$B$4:$B$1203,$AE96)),IF(INDEX(对接源_02物料!$B$4:$B$1203,$AE96-1200)=0,"",INDEX(对接源_02物料!$B$4:$B$1203,$AE96-1200)))) | B96: =IF($AE96="","",IF($AE96<=1200,IF(INDEX(对接源_01水果!$E$4:$E$1203,$AE96)=0,"",INDEX(对接源_01水果!$E$4:$E$1203,$AE96)),IF(INDEX(对接源_02物料!$E$4:$E$1203,$AE96-1200)=0,"",INDEX(对接源_02物料!$E$4:$E$1203,$AE96-1200)))) | C96: =IF($AE96="","",IF($AE96<=1200,IF(INDEX(对接源_01水果!$S$4:$S$1203,$AE96)=0,"",INDEX(对接源_01水果!$S$4:$S$1203,$AE96)),IF(INDEX(对接源_02物料!$S$4:$S$1203,$AE96-1200)=0,"",INDEX(对接源_02物料!$S$4:$S$1203,$AE96-1200)))) | D96: =IF($AE96="","",IF($AE96<=1200,IF(INDEX(对接源_01水果!$T$4:$T$1203,$AE96)=0,"",INDEX(对接源_01水果!$T$4:$T$1203,$AE96)),IF(INDEX(对接源_02物料!$T$4:$T$1203,$AE96-1200)=0,"",INDEX(对接源_02物料!$T$4:$T$1203,$AE96-1200)))) | E96: =IF($AE96="","",IF($AE96<=1200,IF(INDEX(对接源_01水果!$W$4:$W$1203,$AE96)=0,"",INDEX(对接源_01水果!$W$4:$W$1203,$AE96)),IF(INDEX(对接源_02物料!$W$4:$W$1203,$AE96-1200)=0,"",INDEX(对接源_02物料!$W$4:$W$1203,$AE96-1200)))) | F96: =IF($AE96="","",IF($AE96<=1200,"01水果册","02物料册")) | G96: =IF($AE96="","",IF($AE96<=1200,IF(INDEX(对接源_01水果!$M$4:$M$1203,$AE96)=0,"",INDEX(对接源_01水果!$M$4:$M$1203,$AE96)),IF(INDEX(对接源_02物料!$M$4:$M$1203,$AE96-1200)=0,"",INDEX(对接源_02物料!$M$4:$M$1203,$AE96-1200)))) | AE96: =IFERROR(MATCH(91,_自动清单!$Q$4:$Q$2403,0),"")
A97: =IF($AE97="","",IF($AE97<=1200,IF(INDEX(对接源_01水果!$B$4:$B$1203,$AE97)=0,"",INDEX(对接源_01水果!$B$4:$B$1203,$AE97)),IF(INDEX(对接源_02物料!$B$4:$B$1203,$AE97-1200)=0,"",INDEX(对接源_02物料!$B$4:$B$1203,$AE97-1200)))) | B97: =IF($AE97="","",IF($AE97<=1200,IF(INDEX(对接源_01水果!$E$4:$E$1203,$AE97)=0,"",INDEX(对接源_01水果!$E$4:$E$1203,$AE97)),IF(INDEX(对接源_02物料!$E$4:$E$1203,$AE97-1200)=0,"",INDEX(对接源_02物料!$E$4:$E$1203,$AE97-1200)))) | C97: =IF($AE97="","",IF($AE97<=1200,IF(INDEX(对接源_01水果!$S$4:$S$1203,$AE97)=0,"",INDEX(对接源_01水果!$S$4:$S$1203,$AE97)),IF(INDEX(对接源_02物料!$S$4:$S$1203,$AE97-1200)=0,"",INDEX(对接源_02物料!$S$4:$S$1203,$AE97-1200)))) | D97: =IF($AE97="","",IF($AE97<=1200,IF(INDEX(对接源_01水果!$T$4:$T$1203,$AE97)=0,"",INDEX(对接源_01水果!$T$4:$T$1203,$AE97)),IF(INDEX(对接源_02物料!$T$4:$T$1203,$AE97-1200)=0,"",INDEX(对接源_02物料!$T$4:$T$1203,$AE97-1200)))) | E97: =IF($AE97="","",IF($AE97<=1200,IF(INDEX(对接源_01水果!$W$4:$W$1203,$AE97)=0,"",INDEX(对接源_01水果!$W$4:$W$1203,$AE97)),IF(INDEX(对接源_02物料!$W$4:$W$1203,$AE97-1200)=0,"",INDEX(对接源_02物料!$W$4:$W$1203,$AE97-1200)))) | F97: =IF($AE97="","",IF($AE97<=1200,"01水果册","02物料册")) | G97: =IF($AE97="","",IF($AE97<=1200,IF(INDEX(对接源_01水果!$M$4:$M$1203,$AE97)=0,"",INDEX(对接源_01水果!$M$4:$M$1203,$AE97)),IF(INDEX(对接源_02物料!$M$4:$M$1203,$AE97-1200)=0,"",INDEX(对接源_02物料!$M$4:$M$1203,$AE97-1200)))) | AE97: =IFERROR(MATCH(92,_自动清单!$Q$4:$Q$2403,0),"")
A98: =IF($AE98="","",IF($AE98<=1200,IF(INDEX(对接源_01水果!$B$4:$B$1203,$AE98)=0,"",INDEX(对接源_01水果!$B$4:$B$1203,$AE98)),IF(INDEX(对接源_02物料!$B$4:$B$1203,$AE98-1200)=0,"",INDEX(对接源_02物料!$B$4:$B$1203,$AE98-1200)))) | B98: =IF($AE98="","",IF($AE98<=1200,IF(INDEX(对接源_01水果!$E$4:$E$1203,$AE98)=0,"",INDEX(对接源_01水果!$E$4:$E$1203,$AE98)),IF(INDEX(对接源_02物料!$E$4:$E$1203,$AE98-1200)=0,"",INDEX(对接源_02物料!$E$4:$E$1203,$AE98-1200)))) | C98: =IF($AE98="","",IF($AE98<=1200,IF(INDEX(对接源_01水果!$S$4:$S$1203,$AE98)=0,"",INDEX(对接源_01水果!$S$4:$S$1203,$AE98)),IF(INDEX(对接源_02物料!$S$4:$S$1203,$AE98-1200)=0,"",INDEX(对接源_02物料!$S$4:$S$1203,$AE98-1200)))) | D98: =IF($AE98="","",IF($AE98<=1200,IF(INDEX(对接源_01水果!$T$4:$T$1203,$AE98)=0,"",INDEX(对接源_01水果!$T$4:$T$1203,$AE98)),IF(INDEX(对接源_02物料!$T$4:$T$1203,$AE98-1200)=0,"",INDEX(对接源_02物料!$T$4:$T$1203,$AE98-1200)))) | E98: =IF($AE98="","",IF($AE98<=1200,IF(INDEX(对接源_01水果!$W$4:$W$1203,$AE98)=0,"",INDEX(对接源_01水果!$W$4:$W$1203,$AE98)),IF(INDEX(对接源_02物料!$W$4:$W$1203,$AE98-1200)=0,"",INDEX(对接源_02物料!$W$4:$W$1203,$AE98-1200)))) | F98: =IF($AE98="","",IF($AE98<=1200,"01水果册","02物料册")) | G98: =IF($AE98="","",IF($AE98<=1200,IF(INDEX(对接源_01水果!$M$4:$M$1203,$AE98)=0,"",INDEX(对接源_01水果!$M$4:$M$1203,$AE98)),IF(INDEX(对接源_02物料!$M$4:$M$1203,$AE98-1200)=0,"",INDEX(对接源_02物料!$M$4:$M$1203,$AE98-1200)))) | AE98: =IFERROR(MATCH(93,_自动清单!$Q$4:$Q$2403,0),"")
A99: =IF($AE99="","",IF($AE99<=1200,IF(INDEX(对接源_01水果!$B$4:$B$1203,$AE99)=0,"",INDEX(对接源_01水果!$B$4:$B$1203,$AE99)),IF(INDEX(对接源_02物料!$B$4:$B$1203,$AE99-1200)=0,"",INDEX(对接源_02物料!$B$4:$B$1203,$AE99-1200)))) | B99: =IF($AE99="","",IF($AE99<=1200,IF(INDEX(对接源_01水果!$E$4:$E$1203,$AE99)=0,"",INDEX(对接源_01水果!$E$4:$E$1203,$AE99)),IF(INDEX(对接源_02物料!$E$4:$E$1203,$AE99-1200)=0,"",INDEX(对接源_02物料!$E$4:$E$1203,$AE99-1200)))) | C99: =IF($AE99="","",IF($AE99<=1200,IF(INDEX(对接源_01水果!$S$4:$S$1203,$AE99)=0,"",INDEX(对接源_01水果!$S$4:$S$1203,$AE99)),IF(INDEX(对接源_02物料!$S$4:$S$1203,$AE99-1200)=0,"",INDEX(对接源_02物料!$S$4:$S$1203,$AE99-1200)))) | D99: =IF($AE99="","",IF($AE99<=1200,IF(INDEX(对接源_01水果!$T$4:$T$1203,$AE99)=0,"",INDEX(对接源_01水果!$T$4:$T$1203,$AE99)),IF(INDEX(对接源_02物料!$T$4:$T$1203,$AE99-1200)=0,"",INDEX(对接源_02物料!$T$4:$T$1203,$AE99-1200)))) | E99: =IF($AE99="","",IF($AE99<=1200,IF(INDEX(对接源_01水果!$W$4:$W$1203,$AE99)=0,"",INDEX(对接源_01水果!$W$4:$W$1203,$AE99)),IF(INDEX(对接源_02物料!$W$4:$W$1203,$AE99-1200)=0,"",INDEX(对接源_02物料!$W$4:$W$1203,$AE99-1200)))) | F99: =IF($AE99="","",IF($AE99<=1200,"01水果册","02物料册")) | G99: =IF($AE99="","",IF($AE99<=1200,IF(INDEX(对接源_01水果!$M$4:$M$1203,$AE99)=0,"",INDEX(对接源_01水果!$M$4:$M$1203,$AE99)),IF(INDEX(对接源_02物料!$M$4:$M$1203,$AE99-1200)=0,"",INDEX(对接源_02物料!$M$4:$M$1203,$AE99-1200)))) | AE99: =IFERROR(MATCH(94,_自动清单!$Q$4:$Q$2403,0),"")
A100: =IF($AE100="","",IF($AE100<=1200,IF(INDEX(对接源_01水果!$B$4:$B$1203,$AE100)=0,"",INDEX(对接源_01水果!$B$4:$B$1203,$AE100)),IF(INDEX(对接源_02物料!$B$4:$B$1203,$AE100-1200)=0,"",INDEX(对接源_02物料!$B$4:$B$1203,$AE100-1200)))) | B100: =IF($AE100="","",IF($AE100<=1200,IF(INDEX(对接源_01水果!$E$4:$E$1203,$AE100)=0,"",INDEX(对接源_01水果!$E$4:$E$1203,$AE100)),IF(INDEX(对接源_02物料!$E$4:$E$1203,$AE100-1200)=0,"",INDEX(对接源_02物料!$E$4:$E$1203,$AE100-1200)))) | C100: =IF($AE100="","",IF($AE100<=1200,IF(INDEX(对接源_01水果!$S$4:$S$1203,$AE100)=0,"",INDEX(对接源_01水果!$S$4:$S$1203,$AE100)),IF(INDEX(对接源_02物料!$S$4:$S$1203,$AE100-1200)=0,"",INDEX(对接源_02物料!$S$4:$S$1203,$AE100-1200)))) | D100: =IF($AE100="","",IF($AE100<=1200,IF(INDEX(对接源_01水果!$T$4:$T$1203,$AE100)=0,"",INDEX(对接源_01水果!$T$4:$T$1203,$AE100)),IF(INDEX(对接源_02物料!$T$4:$T$1203,$AE100-1200)=0,"",INDEX(对接源_02物料!$T$4:$T$1203,$AE100-1200)))) | E100: =IF($AE100="","",IF($AE100<=1200,IF(INDEX(对接源_01水果!$W$4:$W$1203,$AE100)=0,"",INDEX(对接源_01水果!$W$4:$W$1203,$AE100)),IF(INDEX(对接源_02物料!$W$4:$W$1203,$AE100-1200)=0,"",INDEX(对接源_02物料!$W$4:$W$1203,$AE100-1200)))) | F100: =IF($AE100="","",IF($AE100<=1200,"01水果册","02物料册")) | G100: =IF($AE100="","",IF($AE100<=1200,IF(INDEX(对接源_01水果!$M$4:$M$1203,$AE100)=0,"",INDEX(对接源_01水果!$M$4:$M$1203,$AE100)),IF(INDEX(对接源_02物料!$M$4:$M$1203,$AE100-1200)=0,"",INDEX(对接源_02物料!$M$4:$M$1203,$AE100-1200)))) | AE100: =IFERROR(MATCH(95,_自动清单!$Q$4:$Q$2403,0),"")
...

Sheet 自备筐对账单
A1: 新疆果然鲜仓储有限公司 | H1: 对账单 | P1: =IF($F$2="",DATE(1900,1,1),$F$2) -> 2
A2: 客 户: | B2: 贾建国 | E2: 开始日期: | G2: 结束日期: | K2: 自 备 筐 汇 总 | P2: =IF($H$2="",DATE(2999,12,31),$H$2) -> 401768
A3: ★ 客户自己带来的筐（筐子类型以「自备」开头）＋《02》客户自备加工筐明细。表外备查，不进公司资产。 | K3: 自备筐入库 | M3: =ROUND(SUMIFS(对接源_01水果!$V$4:$V$1203,对接源_01水果!$C$4:$C$1203,$B$2,对接源_01水果!$B$4:$B$1203,">="&$P$1,对接源_01水果!$B$4:$B$1203,"<="&$P$2,对接源_01水果!$X$4:$X$1203,"自备筐")+SUMIFS(对接源_02物料!$V$4:$V$1203,对接源_02物料!$C$4:$C$1203,$B$2,对接源_02物料!$B$4:$B$1203,">="&$P$1,对接源_02物料!$B$4:$B$1203,"<="&$P$2,对接源_02物料!$X$4:$X$1203,"自备筐"),0) -> 1186
A4: 自备筐入库总数 | G4: =ROUND(SUMIFS(对接源_01水果!$V$4:$V$1203,对接源_01水果!$C$4:$C$1203,$B$2,对接源_01水果!$B$4:$B$1203,">="&$P$1,对接源_01水果!$B$4:$B$1203,"<="&$P$2,对接源_01水果!$X$4:$X$1203,"自备筐")+SUMIFS(对接源_02物料!$V$4:$V$1203,对接源_02物料!$C$4:$C$1203,$B$2,对接源_02物料!$B$4:$B$1203,">="&$P$1,对接源_02物料!$B$4:$B$1203,"<="&$P$2,对接源_02物料!$X$4:$X$1203,"自备筐"),0) -> 1186 | K4: 自备筐出库 | M4: =ROUND(SUMIFS(对接源_01水果!$T$4:$T$1203,对接源_01水果!$C$4:$C$1203,$B$2,对接源_01水果!$B$4:$B$1203,">="&$P$1,对接源_01水果!$B$4:$B$1203,"<="&$P$2,对接源_01水果!$X$4:$X$1203,"自备筐")+SUMIFS(对接源_02物料!$T$4:$T$1203,对接源_02物料!$C$4:$C$1203,$B$2,对接源_02物料!$B$4:$B$1203,">="&$P$1,对接源_02物料!$B$4:$B$1203,"<="&$P$2,对接源_02物料!$X$4:$X$1203,"自备筐"),0) -> 0
A5: 日 期 | B5: 筐子类型 | C5: 票据单号 | D5: 入库数量 | E5: 客 户 | F5: 承运人车牌号 | G5: 业务类别 | H5: 来源册 | I5: 备 注 | K5: 剩余在我库 | M5: =ROUND((SUMIFS(对接源_01水果!$V$4:$V$1203,对接源_01水果!$C$4:$C$1203,$B$2,对接源_01水果!$B$4:$B$1203,">="&$P$1,对接源_01水果!$B$4:$B$1203,"<="&$P$2,对接源_01水果!$X$4:$X$1203,"自备筐")+SUMIFS(对接源_02物料!$V$4:$V$1203,对接源_02物料!$C$4:$C$1203,$B$2,对接源_02物料!$B$4:$B$1203,">="&$P$1,对接源_02物料!$B$4:$B$1203,"<="&$P$2,对接源_02物料!$X$4:$X$1203,"自备筐"))-(SUMIFS(对接源_01水果!$T$4:$T$1203,对接源_01水果!$C$4:$C$1203,$B$2,对接源_01水果!$B$4:$B$1203,">="&$P$1,对接源_01水果!$B$4:$B$1203,"<="&$P$2,对接源_01水果!$X$4:$X$1203,"自备筐")+SUMIFS(对接源_02物料!$T$4:$T$1203,对接源_02物料!$C$4:$C$1203,$B$2,对接源_02物料!$B$4:$B$1203,">="&$P$1,对接源_02物料!$B$4:$B$1203,"<="&$P$2,对接源_02物料!$X$4:$X$1203,"自备筐")),0) -> 1186
A6: =IF($AE6="","",IF($AE6<=1200,IF(INDEX(对接源_01水果!$B$4:$B$1203,$AE6)=0,"",INDEX(对接源_01水果!$B$4:$B$1203,$AE6)),IF(INDEX(对接源_02物料!$B$4:$B$1203,$AE6-1200)=0,"",INDEX(对接源_02物料!$B$4:$B$1203,$AE6-1200)))) -> 46273 | B6: =IF($AE6="","",IF($AE6<=1200,IF(INDEX(对接源_01水果!$S$4:$S$1203,$AE6)=0,"",INDEX(对接源_01水果!$S$4:$S$1203,$AE6)),IF(INDEX(对接源_02物料!$S$4:$S$1203,$AE6-1200)=0,"",INDEX(对接源_02物料!$S$4:$S$1203,$AE6-1200)))) -> 自备一次性筐 | C6: =IF($AE6="","",IF($AE6<=1200,IF(INDEX(对接源_01水果!$E$4:$E$1203,$AE6)=0,"",INDEX(对接源_01水果!$E$4:$E$1203,$AE6)),IF(INDEX(对接源_02物料!$E$4:$E$1203,$AE6-1200)=0,"",INDEX(对接源_02物料!$E$4:$E$1203,$AE6-1200)))) -> NO:0000760 | D6: =IF($AE6="","",IF($AE6<=1200,IF(INDEX(对接源_01水果!$V$4:$V$1203,$AE6)=0,"",INDEX(对接源_01水果!$V$4:$V$1203,$AE6)),IF(INDEX(对接源_02物料!$V$4:$V$1203,$AE6-1200)=0,"",INDEX(对接源_02物料!$V$4:$V$1203,$AE6-1200)))) -> 144 | E6: =IF($AE6="","",IF($AE6<=1200,IF(INDEX(对接源_01水果!$C$4:$C$1203,$AE6)=0,"",INDEX(对接源_01水果!$C$4:$C$1203,$AE6)),IF(INDEX(对接源_02物料!$C$4:$C$1203,$AE6-1200)=0,"",INDEX(对接源_02物料!$C$4:$C$1203,$AE6-1200)))) -> 贾建国 | F6: =IF($AE6="","",IF($AE6<=1200,IF(INDEX(对接源_01水果!$W$4:$W$1203,$AE6)=0,"",INDEX(对接源_01水果!$W$4:$W$1203,$AE6)),IF(INDEX(对接源_02物料!$W$4:$W$1203,$AE6-1200)=0,"",INDEX(对接源_02物料!$W$4:$W$1203,$AE6-1200)))) -> 豫Q*H5591 | G6: =IF($AE6="","",IF($AE6<=1200,IF(INDEX(对接源_01水果!$D$4:$D$1203,$AE6)=0,"",INDEX(对接源_01水果!$D$4:$D$1203,$AE6)),IF(INDEX(对接源_02物料!$D$4:$D$1203,$AE6-1200)=0,"",INDEX(对接源_02物料!$D$4:$D$1203,$AE6-1200)))) -> 原料入库 | H6: =IF($AE6="","",IF($AE6<=1200,"01水果册","02物料册")) -> 01水果册 | I6: =IF($AE6="","",IF($AE6<=1200,IF(INDEX(对接源_01水果!$M$4:$M$1203,$AE6)=0,"",INDEX(对接源_01水果!$M$4:$M$1203,$AE6)),IF(INDEX(对接源_02物料!$M$4:$M$1203,$AE6-1200)=0,"",INDEX(对接源_02物料!$M$4:$M$1203,$AE6-1200)))) | AE6: =IFERROR(MATCH(1,_自动清单!$W$4:$W$2403,0),"") -> 154
A7: =IF($AE7="","",IF($AE7<=1200,IF(INDEX(对接源_01水果!$B$4:$B$1203,$AE7)=0,"",INDEX(对接源_01水果!$B$4:$B$1203,$AE7)),IF(INDEX(对接源_02物料!$B$4:$B$1203,$AE7-1200)=0,"",INDEX(对接源_02物料!$B$4:$B$1203,$AE7-1200)))) -> 46273 | B7: =IF($AE7="","",IF($AE7<=1200,IF(INDEX(对接源_01水果!$S$4:$S$1203,$AE7)=0,"",INDEX(对接源_01水果!$S$4:$S$1203,$AE7)),IF(INDEX(对接源_02物料!$S$4:$S$1203,$AE7-1200)=0,"",INDEX(对接源_02物料!$S$4:$S$1203,$AE7-1200)))) -> 自备杂周转筐 | C7: =IF($AE7="","",IF($AE7<=1200,IF(INDEX(对接源_01水果!$E$4:$E$1203,$AE7)=0,"",INDEX(对接源_01水果!$E$4:$E$1203,$AE7)),IF(INDEX(对接源_02物料!$E$4:$E$1203,$AE7-1200)=0,"",INDEX(对接源_02物料!$E$4:$E$1203,$AE7-1200)))) -> NO:0000760 | D7: =IF($AE7="","",IF($AE7<=1200,IF(INDEX(对接源_01水果!$V$4:$V$1203,$AE7)=0,"",INDEX(对接源_01水果!$V$4:$V$1203,$AE7)),IF(INDEX(对接源_02物料!$V$4:$V$1203,$AE7-1200)=0,"",INDEX(对接源_02物料!$V$4:$V$1203,$AE7-1200)))) -> 24 | E7: =IF($AE7="","",IF($AE7<=1200,IF(INDEX(对接源_01水果!$C$4:$C$1203,$AE7)=0,"",INDEX(对接源_01水果!$C$4:$C$1203,$AE7)),IF(INDEX(对接源_02物料!$C$4:$C$1203,$AE7-1200)=0,"",INDEX(对接源_02物料!$C$4:$C$1203,$AE7-1200)))) -> 贾建国 | F7: =IF($AE7="","",IF($AE7<=1200,IF(INDEX(对接源_01水果!$W$4:$W$1203,$AE7)=0,"",INDEX(对接源_01水果!$W$4:$W$1203,$AE7)),IF(INDEX(对接源_02物料!$W$4:$W$1203,$AE7-1200)=0,"",INDEX(对接源_02物料!$W$4:$W$1203,$AE7-1200)))) -> 豫Q*H5591 | G7: =IF($AE7="","",IF($AE7<=1200,IF(INDEX(对接源_01水果!$D$4:$D$1203,$AE7)=0,"",INDEX(对接源_01水果!$D$4:$D$1203,$AE7)),IF(INDEX(对接源_02物料!$D$4:$D$1203,$AE7-1200)=0,"",INDEX(对接源_02物料!$D$4:$D$1203,$AE7-1200)))) -> 原料入库 | H7: =IF($AE7="","",IF($AE7<=1200,"01水果册","02物料册")) -> 01水果册 | I7: =IF($AE7="","",IF($AE7<=1200,IF(INDEX(对接源_01水果!$M$4:$M$1203,$AE7)=0,"",INDEX(对接源_01水果!$M$4:$M$1203,$AE7)),IF(INDEX(对接源_02物料!$M$4:$M$1203,$AE7-1200)=0,"",INDEX(对接源_02物料!$M$4:$M$1203,$AE7-1200)))) | AE7: =IFERROR(MATCH(2,_自动清单!$W$4:$W$2403,0),"") -> 155
A8: =IF($AE8="","",IF($AE8<=1200,IF(INDEX(对接源_01水果!$B$4:$B$1203,$AE8)=0,"",INDEX(对接源_01水果!$B$4:$B$1203,$AE8)),IF(INDEX(对接源_02物料!$B$4:$B$1203,$AE8-1200)=0,"",INDEX(对接源_02物料!$B$4:$B$1203,$AE8-1200)))) -> 46274 | B8: =IF($AE8="","",IF($AE8<=1200,IF(INDEX(对接源_01水果!$S$4:$S$1203,$AE8)=0,"",INDEX(对接源_01水果!$S$4:$S$1203,$AE8)),IF(INDEX(对接源_02物料!$S$4:$S$1203,$AE8-1200)=0,"",INDEX(对接源_02物料!$S$4:$S$1203,$AE8-1200)))) -> 自备杂周转筐 | C8: =IF($AE8="","",IF($AE8<=1200,IF(INDEX(对接源_01水果!$E$4:$E$1203,$AE8)=0,"",INDEX(对接源_01水果!$E$4:$E$1203,$AE8)),IF(INDEX(对接源_02物料!$E$4:$E$1203,$AE8-1200)=0,"",INDEX(对接源_02物料!$E$4:$E$1203,$AE8-1200)))) -> NO:0000767 | D8: =IF($AE8="","",IF($AE8<=1200,IF(INDEX(对接源_01水果!$V$4:$V$1203,$AE8)=0,"",INDEX(对接源_01水果!$V$4:$V$1203,$AE8)),IF(INDEX(对接源_02物料!$V$4:$V$1203,$AE8-1200)=0,"",INDEX(对接源_02物料!$V$4:$V$1203,$AE8-1200)))) -> 170 | E8: =IF($AE8="","",IF($AE8<=1200,IF(INDEX(对接源_01水果!$C$4:$C$1203,$AE8)=0,"",INDEX(对接源_01水果!$C$4:$C$1203,$AE8)),IF(INDEX(对接源_02物料!$C$4:$C$1203,$AE8-1200)=0,"",INDEX(对接源_02物料!$C$4:$C$1203,$AE8-1200)))) -> 贾建国 | F8: =IF($AE8="","",IF($AE8<=1200,IF(INDEX(对接源_01水果!$W$4:$W$1203,$AE8)=0,"",INDEX(对接源_01水果!$W$4:$W$1203,$AE8)),IF(INDEX(对接源_02物料!$W$4:$W$1203,$AE8-1200)=0,"",INDEX(对接源_02物料!$W$4:$W$1203,$AE8-1200)))) -> 豫Q*H5591 | G8: =IF($AE8="","",IF($AE8<=1200,IF(INDEX(对接源_01水果!$D$4:$D$1203,$AE8)=0,"",INDEX(对接源_01水果!$D$4:$D$1203,$AE8)),IF(INDEX(对接源_02物料!$D$4:$D$1203,$AE8-1200)=0,"",INDEX(对接源_02物料!$D$4:$D$1203,$AE8-1200)))) -> 原料入库 | H8: =IF($AE8="","",IF($AE8<=1200,"01水果册","02物料册")) -> 01水果册 | I8: =IF($AE8="","",IF($AE8<=1200,IF(INDEX(对接源_01水果!$M$4:$M$1203,$AE8)=0,"",INDEX(对接源_01水果!$M$4:$M$1203,$AE8)),IF(INDEX(对接源_02物料!$M$4:$M$1203,$AE8-1200)=0,"",INDEX(对接源_02物料!$M$4:$M$1203,$AE8-1200)))) -> 二黄 | AE8: =IFERROR(MATCH(3,_自动清单!$W$4:$W$2403,0),"") -> 162
A9: =IF($AE9="","",IF($AE9<=1200,IF(INDEX(对接源_01水果!$B$4:$B$1203,$AE9)=0,"",INDEX(对接源_01水果!$B$4:$B$1203,$AE9)),IF(INDEX(对接源_02物料!$B$4:$B$1203,$AE9-1200)=0,"",INDEX(对接源_02物料!$B$4:$B$1203,$AE9-1200)))) -> 46274 | B9: =IF($AE9="","",IF($AE9<=1200,IF(INDEX(对接源_01水果!$S$4:$S$1203,$AE9)=0,"",INDEX(对接源_01水果!$S$4:$S$1203,$AE9)),IF(INDEX(对接源_02物料!$S$4:$S$1203,$AE9-1200)=0,"",INDEX(对接源_02物料!$S$4:$S$1203,$AE9-1200)))) -> 自备一次性筐 | C9: =IF($AE9="","",IF($AE9<=1200,IF(INDEX(对接源_01水果!$E$4:$E$1203,$AE9)=0,"",INDEX(对接源_01水果!$E$4:$E$1203,$AE9)),IF(INDEX(对接源_02物料!$E$4:$E$1203,$AE9-1200)=0,"",INDEX(对接源_02物料!$E$4:$E$1203,$AE9-1200)))) -> NO:0000767 | D9: =IF($AE9="","",IF($AE9<=1200,IF(INDEX(对接源_01水果!$V$4:$V$1203,$AE9)=0,"",INDEX(对接源_01水果!$V$4:$V$1203,$AE9)),IF(INDEX(对接源_02物料!$V$4:$V$1203,$AE9-1200)=0,"",INDEX(对接源_02物料!$V$4:$V$1203,$AE9-1200)))) -> 28 | E9: =IF($AE9="","",IF($AE9<=1200,IF(INDEX(对接源_01水果!$C$4:$C$1203,$AE9)=0,"",INDEX(对接源_01水果!$C$4:$C$1203,$AE9)),IF(INDEX(对接源_02物料!$C$4:$C$1203,$AE9-1200)=0,"",INDEX(对接源_02物料!$C$4:$C$1203,$AE9-1200)))) -> 贾建国 | F9: =IF($AE9="","",IF($AE9<=1200,IF(INDEX(对接源_01水果!$W$4:$W$1203,$AE9)=0,"",INDEX(对接源_01水果!$W$4:$W$1203,$AE9)),IF(INDEX(对接源_02物料!$W$4:$W$1203,$AE9-1200)=0,"",INDEX(对接源_02物料!$W$4:$W$1203,$AE9-1200)))) -> 豫Q*H5591 | G9: =IF($AE9="","",IF($AE9<=1200,IF(INDEX(对接源_01水果!$D$4:$D$1203,$AE9)=0,"",INDEX(对接源_01水果!$D$4:$D$1203,$AE9)),IF(INDEX(对接源_02物料!$D$4:$D$1203,$AE9-1200)=0,"",INDEX(对接源_02物料!$D$4:$D$1203,$AE9-1200)))) -> 原料入库 | H9: =IF($AE9="","",IF($AE9<=1200,"01水果册","02物料册")) -> 01水果册 | I9: =IF($AE9="","",IF($AE9<=1200,IF(INDEX(对接源_01水果!$M$4:$M$1203,$AE9)=0,"",INDEX(对接源_01水果!$M$4:$M$1203,$AE9)),IF(INDEX(对接源_02物料!$M$4:$M$1203,$AE9-1200)=0,"",INDEX(对接源_02物料!$M$4:$M$1203,$AE9-1200)))) -> 二黄 | AE9: =IFERROR(MATCH(4,_自动清单!$W$4:$W$2403,0),"") -> 163
A10: =IF($AE10="","",IF($AE10<=1200,IF(INDEX(对接源_01水果!$B$4:$B$1203,$AE10)=0,"",INDEX(对接源_01水果!$B$4:$B$1203,$AE10)),IF(INDEX(对接源_02物料!$B$4:$B$1203,$AE10-1200)=0,"",INDEX(对接源_02物料!$B$4:$B$1203,$AE10-1200)))) -> 46276 | B10: =IF($AE10="","",IF($AE10<=1200,IF(INDEX(对接源_01水果!$S$4:$S$1203,$AE10)=0,"",INDEX(对接源_01水果!$S$4:$S$1203,$AE10)),IF(INDEX(对接源_02物料!$S$4:$S$1203,$AE10-1200)=0,"",INDEX(对接源_02物料!$S$4:$S$1203,$AE10-1200)))) -> 自备一次性筐 | C10: =IF($AE10="","",IF($AE10<=1200,IF(INDEX(对接源_01水果!$E$4:$E$1203,$AE10)=0,"",INDEX(对接源_01水果!$E$4:$E$1203,$AE10)),IF(INDEX(对接源_02物料!$E$4:$E$1203,$AE10-1200)=0,"",INDEX(对接源_02物料!$E$4:$E$1203,$AE10-1200)))) -> NO:0000787 | D10: =IF($AE10="","",IF($AE10<=1200,IF(INDEX(对接源_01水果!$V$4:$V$1203,$AE10)=0,"",INDEX(对接源_01水果!$V$4:$V$1203,$AE10)),IF(INDEX(对接源_02物料!$V$4:$V$1203,$AE10-1200)=0,"",INDEX(对接源_02物料!$V$4:$V$1203,$AE10-1200)))) -> 393 | E10: =IF($AE10="","",IF($AE10<=1200,IF(INDEX(对接源_01水果!$C$4:$C$1203,$AE10)=0,"",INDEX(对接源_01水果!$C$4:$C$1203,$AE10)),IF(INDEX(对接源_02物料!$C$4:$C$1203,$AE10-1200)=0,"",INDEX(对接源_02物料!$C$4:$C$1203,$AE10-1200)))) -> 贾建国 | F10: =IF($AE10="","",IF($AE10<=1200,IF(INDEX(对接源_01水果!$W$4:$W$1203,$AE10)=0,"",INDEX(对接源_01水果!$W$4:$W$1203,$AE10)),IF(INDEX(对接源_02物料!$W$4:$W$1203,$AE10-1200)=0,"",INDEX(对接源_02物料!$W$4:$W$1203,$AE10-1200)))) -> 豫Q*H5591 | G10: =IF($AE10="","",IF($AE10<=1200,IF(INDEX(对接源_01水果!$D$4:$D$1203,$AE10)=0,"",INDEX(对接源_01水果!$D$4:$D$1203,$AE10)),IF(INDEX(对接源_02物料!$D$4:$D$1203,$AE10-1200)=0,"",INDEX(对接源_02物料!$D$4:$D$1203,$AE10-1200)))) -> 原料入库 | H10: =IF($AE10="","",IF($AE10<=1200,"01水果册","02物料册")) -> 01水果册 | I10: =IF($AE10="","",IF($AE10<=1200,IF(INDEX(对接源_01水果!$M$4:$M$1203,$AE10)=0,"",INDEX(对接源_01水果!$M$4:$M$1203,$AE10)),IF(INDEX(对接源_02物料!$M$4:$M$1203,$AE10-1200)=0,"",INDEX(对接源_02物料!$M$4:$M$1203,$AE10-1200)))) | AE10: =IFERROR(MATCH(5,_自动清单!$W$4:$W$2403,0),"") -> 192
A11: =IF($AE11="","",IF($AE11<=1200,IF(INDEX(对接源_01水果!$B$4:$B$1203,$AE11)=0,"",INDEX(对接源_01水果!$B$4:$B$1203,$AE11)),IF(INDEX(对接源_02物料!$B$4:$B$1203,$AE11-1200)=0,"",INDEX(对接源_02物料!$B$4:$B$1203,$AE11-1200)))) -> 46278 | B11: =IF($AE11="","",IF($AE11<=1200,IF(INDEX(对接源_01水果!$S$4:$S$1203,$AE11)=0,"",INDEX(对接源_01水果!$S$4:$S$1203,$AE11)),IF(INDEX(对接源_02物料!$S$4:$S$1203,$AE11-1200)=0,"",INDEX(对接源_02物料!$S$4:$S$1203,$AE11-1200)))) -> 自备杂周转筐 | C11: =IF($AE11="","",IF($AE11<=1200,IF(INDEX(对接源_01水果!$E$4:$E$1203,$AE11)=0,"",INDEX(对接源_01水果!$E$4:$E$1203,$AE11)),IF(INDEX(对接源_02物料!$E$4:$E$1203,$AE11-1200)=0,"",INDEX(对接源_02物料!$E$4:$E$1203,$AE11-1200)))) -> NO:0000797 | D11: =IF($AE11="","",IF($AE11<=1200,IF(INDEX(对接源_01水果!$V$4:$V$1203,$AE11)=0,"",INDEX(对接源_01水果!$V$4:$V$1203,$AE11)),IF(INDEX(对接源_02物料!$V$4:$V$1203,$AE11-1200)=0,"",INDEX(对接源_02物料!$V$4:$V$1203,$AE11-1200)))) -> 160 | E11: =IF($AE11="","",IF($AE11<=1200,IF(INDEX(对接源_01水果!$C$4:$C$1203,$AE11)=0,"",INDEX(对接源_01水果!$C$4:$C$1203,$AE11)),IF(INDEX(对接源_02物料!$C$4:$C$1203,$AE11-1200)=0,"",INDEX(对接源_02物料!$C$4:$C$1203,$AE11-1200)))) -> 贾建国 | F11: =IF($AE11="","",IF($AE11<=1200,IF(INDEX(对接源_01水果!$W$4:$W$1203,$AE11)=0,"",INDEX(对接源_01水果!$W$4:$W$1203,$AE11)),IF(INDEX(对接源_02物料!$W$4:$W$1203,$AE11-1200)=0,"",INDEX(对接源_02物料!$W$4:$W$1203,$AE11-1200)))) -> 豫Q*H5591 | G11: =IF($AE11="","",IF($AE11<=1200,IF(INDEX(对接源_01水果!$D$4:$D$1203,$AE11)=0,"",INDEX(对接源_01水果!$D$4:$D$1203,$AE11)),IF(INDEX(对接源_02物料!$D$4:$D$1203,$AE11-1200)=0,"",INDEX(对接源_02物料!$D$4:$D$1203,$AE11-1200)))) -> 原料入库 | H11: =IF($AE11="","",IF($AE11<=1200,"01水果册","02物料册")) -> 01水果册 | I11: =IF($AE11="","",IF($AE11<=1200,IF(INDEX(对接源_01水果!$M$4:$M$1203,$AE11)=0,"",INDEX(对接源_01水果!$M$4:$M$1203,$AE11)),IF(INDEX(对接源_02物料!$M$4:$M$1203,$AE11-1200)=0,"",INDEX(对接源_02物料!$M$4:$M$1203,$AE11-1200)))) | AE11: =IFERROR(MATCH(6,_自动清单!$W$4:$W$2403,0),"") -> 208
A12: =IF($AE12="","",IF($AE12<=1200,IF(INDEX(对接源_01水果!$B$4:$B$1203,$AE12)=0,"",INDEX(对接源_01水果!$B$4:$B$1203,$AE12)),IF(INDEX(对接源_02物料!$B$4:$B$1203,$AE12-1200)=0,"",INDEX(对接源_02物料!$B$4:$B$1203,$AE12-1200)))) -> 46278 | B12: =IF($AE12="","",IF($AE12<=1200,IF(INDEX(对接源_01水果!$S$4:$S$1203,$AE12)=0,"",INDEX(对接源_01水果!$S$4:$S$1203,$AE12)),IF(INDEX(对接源_02物料!$S$4:$S$1203,$AE12-1200)=0,"",INDEX(对接源_02物料!$S$4:$S$1203,$AE12-1200)))) -> 自备一次性筐 | C12: =IF($AE12="","",IF($AE12<=1200,IF(INDEX(对接源_01水果!$E$4:$E$1203,$AE12)=0,"",INDEX(对接源_01水果!$E$4:$E$1203,$AE12)),IF(INDEX(对接源_02物料!$E$4:$E$1203,$AE12-1200)=0,"",INDEX(对接源_02物料!$E$4:$E$1203,$AE12-1200)))) -> NO:0000797 | D12: =IF($AE12="","",IF($AE12<=1200,IF(INDEX(对接源_01水果!$V$4:$V$1203,$AE12)=0,"",INDEX(对接源_01水果!$V$4:$V$1203,$AE12)),IF(INDEX(对接源_02物料!$V$4:$V$1203,$AE12-1200)=0,"",INDEX(对接源_02物料!$V$4:$V$1203,$AE12-1200)))) -> 267 | E12: =IF($AE12="","",IF($AE12<=1200,IF(INDEX(对接源_01水果!$C$4:$C$1203,$AE12)=0,"",INDEX(对接源_01水果!$C$4:$C$1203,$AE12)),IF(INDEX(对接源_02物料!$C$4:$C$1203,$AE12-1200)=0,"",INDEX(对接源_02物料!$C$4:$C$1203,$AE12-1200)))) -> 贾建国 | F12: =IF($AE12="","",IF($AE12<=1200,IF(INDEX(对接源_01水果!$W$4:$W$1203,$AE12)=0,"",INDEX(对接源_01水果!$W$4:$W$1203,$AE12)),IF(INDEX(对接源_02物料!$W$4:$W$1203,$AE12-1200)=0,"",INDEX(对接源_02物料!$W$4:$W$1203,$AE12-1200)))) -> 豫Q*H5591 | G12: =IF($AE12="","",IF($AE12<=1200,IF(INDEX(对接源_01水果!$D$4:$D$1203,$AE12)=0,"",INDEX(对接源_01水果!$D$4:$D$1203,$AE12)),IF(INDEX(对接源_02物料!$D$4:$D$1203,$AE12-1200)=0,"",INDEX(对接源_02物料!$D$4:$D$1203,$AE12-1200)))) -> 原料入库 | H12: =IF($AE12="","",IF($AE12<=1200,"01水果册","02物料册")) -> 01水果册 | I12: =IF($AE12="","",IF($AE12<=1200,IF(INDEX(对接源_01水果!$M$4:$M$1203,$AE12)=0,"",INDEX(对接源_01水果!$M$4:$M$1203,$AE12)),IF(INDEX(对接源_02物料!$M$4:$M$1203,$AE12-1200)=0,"",INDEX(对接源_02物料!$M$4:$M$1203,$AE12-1200)))) | AE12: =IFERROR(MATCH(7,_自动清单!$W$4:$W$2403,0),"") -> 209
A13: =IF($AE13="","",IF($AE13<=1200,IF(INDEX(对接源_01水果!$B$4:$B$1203,$AE13)=0,"",INDEX(对接源_01水果!$B$4:$B$1203,$AE13)),IF(INDEX(对接源_02物料!$B$4:$B$1203,$AE13-1200)=0,"",INDEX(对接源_02物料!$B$4:$B$1203,$AE13-1200)))) | B13: =IF($AE13="","",IF($AE13<=1200,IF(INDEX(对接源_01水果!$S$4:$S$1203,$AE13)=0,"",INDEX(对接源_01水果!$S$4:$S$1203,$AE13)),IF(INDEX(对接源_02物料!$S$4:$S$1203,$AE13-1200)=0,"",INDEX(对接源_02物料!$S$4:$S$1203,$AE13-1200)))) | C13: =IF($AE13="","",IF($AE13<=1200,IF(INDEX(对接源_01水果!$E$4:$E$1203,$AE13)=0,"",INDEX(对接源_01水果!$E$4:$E$1203,$AE13)),IF(INDEX(对接源_02物料!$E$4:$E$1203,$AE13-1200)=0,"",INDEX(对接源_02物料!$E$4:$E$1203,$AE13-1200)))) | D13: =IF($AE13="","",IF($AE13<=1200,IF(INDEX(对接源_01水果!$V$4:$V$1203,$AE13)=0,"",INDEX(对接源_01水果!$V$4:$V$1203,$AE13)),IF(INDEX(对接源_02物料!$V$4:$V$1203,$AE13-1200)=0,"",INDEX(对接源_02物料!$V$4:$V$1203,$AE13-1200)))) | E13: =IF($AE13="","",IF($AE13<=1200,IF(INDEX(对接源_01水果!$C$4:$C$1203,$AE13)=0,"",INDEX(对接源_01水果!$C$4:$C$1203,$AE13)),IF(INDEX(对接源_02物料!$C$4:$C$1203,$AE13-1200)=0,"",INDEX(对接源_02物料!$C$4:$C$1203,$AE13-1200)))) | F13: =IF($AE13="","",IF($AE13<=1200,IF(INDEX(对接源_01水果!$W$4:$W$1203,$AE13)=0,"",INDEX(对接源_01水果!$W$4:$W$1203,$AE13)),IF(INDEX(对接源_02物料!$W$4:$W$1203,$AE13-1200)=0,"",INDEX(对接源_02物料!$W$4:$W$1203,$AE13-1200)))) | G13: =IF($AE13="","",IF($AE13<=1200,IF(INDEX(对接源_01水果!$D$4:$D$1203,$AE13)=0,"",INDEX(对接源_01水果!$D$4:$D$1203,$AE13)),IF(INDEX(对接源_02物料!$D$4:$D$1203,$AE13-1200)=0,"",INDEX(对接源_02物料!$D$4:$D$1203,$AE13-1200)))) | H13: =IF($AE13="","",IF($AE13<=1200,"01水果册","02物料册")) | I13: =IF($AE13="","",IF($AE13<=1200,IF(INDEX(对接源_01水果!$M$4:$M$1203,$AE13)=0,"",INDEX(对接源_01水果!$M$4:$M$1203,$AE13)),IF(INDEX(对接源_02物料!$M$4:$M$1203,$AE13-1200)=0,"",INDEX(对接源_02物料!$M$4:$M$1203,$AE13-1200)))) | AE13: =IFERROR(MATCH(8,_自动清单!$W$4:$W$2403,0),"")
A14: =IF($AE14="","",IF($AE14<=1200,IF(INDEX(对接源_01水果!$B$4:$B$1203,$AE14)=0,"",INDEX(对接源_01水果!$B$4:$B$1203,$AE14)),IF(INDEX(对接源_02物料!$B$4:$B$1203,$AE14-1200)=0,"",INDEX(对接源_02物料!$B$4:$B$1203,$AE14-1200)))) | B14: =IF($AE14="","",IF($AE14<=1200,IF(INDEX(对接源_01水果!$S$4:$S$1203,$AE14)=0,"",INDEX(对接源_01水果!$S$4:$S$1203,$AE14)),IF(INDEX(对接源_02物料!$S$4:$S$1203,$AE14-1200)=0,"",INDEX(对接源_02物料!$S$4:$S$1203,$AE14-1200)))) | C14: =IF($AE14="","",IF($AE14<=1200,IF(INDEX(对接源_01水果!$E$4:$E$1203,$AE14)=0,"",INDEX(对接源_01水果!$E$4:$E$1203,$AE14)),IF(INDEX(对接源_02物料!$E$4:$E$1203,$AE14-1200)=0,"",INDEX(对接源_02物料!$E$4:$E$1203,$AE14-1200)))) | D14: =IF($AE14="","",IF($AE14<=1200,IF(INDEX(对接源_01水果!$V$4:$V$1203,$AE14)=0,"",INDEX(对接源_01水果!$V$4:$V$1203,$AE14)),IF(INDEX(对接源_02物料!$V$4:$V$1203,$AE14-1200)=0,"",INDEX(对接源_02物料!$V$4:$V$1203,$AE14-1200)))) | E14: =IF($AE14="","",IF($AE14<=1200,IF(INDEX(对接源_01水果!$C$4:$C$1203,$AE14)=0,"",INDEX(对接源_01水果!$C$4:$C$1203,$AE14)),IF(INDEX(对接源_02物料!$C$4:$C$1203,$AE14-1200)=0,"",INDEX(对接源_02物料!$C$4:$C$1203,$AE14-1200)))) | F14: =IF($AE14="","",IF($AE14<=1200,IF(INDEX(对接源_01水果!$W$4:$W$1203,$AE14)=0,"",INDEX(对接源_01水果!$W$4:$W$1203,$AE14)),IF(INDEX(对接源_02物料!$W$4:$W$1203,$AE14-1200)=0,"",INDEX(对接源_02物料!$W$4:$W$1203,$AE14-1200)))) | G14: =IF($AE14="","",IF($AE14<=1200,IF(INDEX(对接源_01水果!$D$4:$D$1203,$AE14)=0,"",INDEX(对接源_01水果!$D$4:$D$1203,$AE14)),IF(INDEX(对接源_02物料!$D$4:$D$1203,$AE14-1200)=0,"",INDEX(对接源_02物料!$D$4:$D$1203,$AE14-1200)))) | H14: =IF($AE14="","",IF($AE14<=1200,"01水果册","02物料册")) | I14: =IF($AE14="","",IF($AE14<=1200,IF(INDEX(对接源_01水果!$M$4:$M$1203,$AE14)=0,"",INDEX(对接源_01水果!$M$4:$M$1203,$AE14)),IF(INDEX(对接源_02物料!$M$4:$M$1203,$AE14-1200)=0,"",INDEX(对接源_02物料!$M$4:$M$1203,$AE14-1200)))) | AE14: =IFERROR(MATCH(9,_自动清单!$W$4:$W$2403,0),"")
A15: =IF($AE15="","",IF($AE15<=1200,IF(INDEX(对接源_01水果!$B$4:$B$1203,$AE15)=0,"",INDEX(对接源_01水果!$B$4:$B$1203,$AE15)),IF(INDEX(对接源_02物料!$B$4:$B$1203,$AE15-1200)=0,"",INDEX(对接源_02物料!$B$4:$B$1203,$AE15-1200)))) | B15: =IF($AE15="","",IF($AE15<=1200,IF(INDEX(对接源_01水果!$S$4:$S$1203,$AE15)=0,"",INDEX(对接源_01水果!$S$4:$S$1203,$AE15)),IF(INDEX(对接源_02物料!$S$4:$S$1203,$AE15-1200)=0,"",INDEX(对接源_02物料!$S$4:$S$1203,$AE15-1200)))) | C15: =IF($AE15="","",IF($AE15<=1200,IF(INDEX(对接源_01水果!$E$4:$E$1203,$AE15)=0,"",INDEX(对接源_01水果!$E$4:$E$1203,$AE15)),IF(INDEX(对接源_02物料!$E$4:$E$1203,$AE15-1200)=0,"",INDEX(对接源_02物料!$E$4:$E$1203,$AE15-1200)))) | D15: =IF($AE15="","",IF($AE15<=1200,IF(INDEX(对接源_01水果!$V$4:$V$1203,$AE15)=0,"",INDEX(对接源_01水果!$V$4:$V$1203,$AE15)),IF(INDEX(对接源_02物料!$V$4:$V$1203,$AE15-1200)=0,"",INDEX(对接源_02物料!$V$4:$V$1203,$AE15-1200)))) | E15: =IF($AE15="","",IF($AE15<=1200,IF(INDEX(对接源_01水果!$C$4:$C$1203,$AE15)=0,"",INDEX(对接源_01水果!$C$4:$C$1203,$AE15)),IF(INDEX(对接源_02物料!$C$4:$C$1203,$AE15-1200)=0,"",INDEX(对接源_02物料!$C$4:$C$1203,$AE15-1200)))) | F15: =IF($AE15="","",IF($AE15<=1200,IF(INDEX(对接源_01水果!$W$4:$W$1203,$AE15)=0,"",INDEX(对接源_01水果!$W$4:$W$1203,$AE15)),IF(INDEX(对接源_02物料!$W$4:$W$1203,$AE15-1200)=0,"",INDEX(对接源_02物料!$W$4:$W$1203,$AE15-1200)))) | G15: =IF($AE15="","",IF($AE15<=1200,IF(INDEX(对接源_01水果!$D$4:$D$1203,$AE15)=0,"",INDEX(对接源_01水果!$D$4:$D$1203,$AE15)),IF(INDEX(对接源_02物料!$D$4:$D$1203,$AE15-1200)=0,"",INDEX(对接源_02物料!$D$4:$D$1203,$AE15-1200)))) | H15: =IF($AE15="","",IF($AE15<=1200,"01水果册","02物料册")) | I15: =IF($AE15="","",IF($AE15<=1200,IF(INDEX(对接源_01水果!$M$4:$M$1203,$AE15)=0,"",INDEX(对接源_01水果!$M$4:$M$1203,$AE15)),IF(INDEX(对接源_02物料!$M$4:$M$1203,$AE15-1200)=0,"",INDEX(对接源_02物料!$M$4:$M$1203,$AE15-1200)))) | AE15: =IFERROR(MATCH(10,_自动清单!$W$4:$W$2403,0),"")
A16: =IF($AE16="","",IF($AE16<=1200,IF(INDEX(对接源_01水果!$B$4:$B$1203,$AE16)=0,"",INDEX(对接源_01水果!$B$4:$B$1203,$AE16)),IF(INDEX(对接源_02物料!$B$4:$B$1203,$AE16-1200)=0,"",INDEX(对接源_02物料!$B$4:$B$1203,$AE16-1200)))) | B16: =IF($AE16="","",IF($AE16<=1200,IF(INDEX(对接源_01水果!$S$4:$S$1203,$AE16)=0,"",INDEX(对接源_01水果!$S$4:$S$1203,$AE16)),IF(INDEX(对接源_02物料!$S$4:$S$1203,$AE16-1200)=0,"",INDEX(对接源_02物料!$S$4:$S$1203,$AE16-1200)))) | C16: =IF($AE16="","",IF($AE16<=1200,IF(INDEX(对接源_01水果!$E$4:$E$1203,$AE16)=0,"",INDEX(对接源_01水果!$E$4:$E$1203,$AE16)),IF(INDEX(对接源_02物料!$E$4:$E$1203,$AE16-1200)=0,"",INDEX(对接源_02物料!$E$4:$E$1203,$AE16-1200)))) | D16: =IF($AE16="","",IF($AE16<=1200,IF(INDEX(对接源_01水果!$V$4:$V$1203,$AE16)=0,"",INDEX(对接源_01水果!$V$4:$V$1203,$AE16)),IF(INDEX(对接源_02物料!$V$4:$V$1203,$AE16-1200)=0,"",INDEX(对接源_02物料!$V$4:$V$1203,$AE16-1200)))) | E16: =IF($AE16="","",IF($AE16<=1200,IF(INDEX(对接源_01水果!$C$4:$C$1203,$AE16)=0,"",INDEX(对接源_01水果!$C$4:$C$1203,$AE16)),IF(INDEX(对接源_02物料!$C$4:$C$1203,$AE16-1200)=0,"",INDEX(对接源_02物料!$C$4:$C$1203,$AE16-1200)))) | F16: =IF($AE16="","",IF($AE16<=1200,IF(INDEX(对接源_01水果!$W$4:$W$1203,$AE16)=0,"",INDEX(对接源_01水果!$W$4:$W$1203,$AE16)),IF(INDEX(对接源_02物料!$W$4:$W$1203,$AE16-1200)=0,"",INDEX(对接源_02物料!$W$4:$W$1203,$AE16-1200)))) | G16: =IF($AE16="","",IF($AE16<=1200,IF(INDEX(对接源_01水果!$D$4:$D$1203,$AE16)=0,"",INDEX(对接源_01水果!$D$4:$D$1203,$AE16)),IF(INDEX(对接源_02物料!$D$4:$D$1203,$AE16-1200)=0,"",INDEX(对接源_02物料!$D$4:$D$1203,$AE16-1200)))) | H16: =IF($AE16="","",IF($AE16<=1200,"01水果册","02物料册")) | I16: =IF($AE16="","",IF($AE16<=1200,IF(INDEX(对接源_01水果!$M$4:$M$1203,$AE16)=0,"",INDEX(对接源_01水果!$M$4:$M$1203,$AE16)),IF(INDEX(对接源_02物料!$M$4:$M$1203,$AE16-1200)=0,"",INDEX(对接源_02物料!$M$4:$M$1203,$AE16-1200)))) | AE16: =IFERROR(MATCH(11,_自动清单!$W$4:$W$2403,0),"")
A17: =IF($AE17="","",IF($AE17<=1200,IF(INDEX(对接源_01水果!$B$4:$B$1203,$AE17)=0,"",INDEX(对接源_01水果!$B$4:$B$1203,$AE17)),IF(INDEX(对接源_02物料!$B$4:$B$1203,$AE17-1200)=0,"",INDEX(对接源_02物料!$B$4:$B$1203,$AE17-1200)))) | B17: =IF($AE17="","",IF($AE17<=1200,IF(INDEX(对接源_01水果!$S$4:$S$1203,$AE17)=0,"",INDEX(对接源_01水果!$S$4:$S$1203,$AE17)),IF(INDEX(对接源_02物料!$S$4:$S$1203,$AE17-1200)=0,"",INDEX(对接源_02物料!$S$4:$S$1203,$AE17-1200)))) | C17: =IF($AE17="","",IF($AE17<=1200,IF(INDEX(对接源_01水果!$E$4:$E$1203,$AE17)=0,"",INDEX(对接源_01水果!$E$4:$E$1203,$AE17)),IF(INDEX(对接源_02物料!$E$4:$E$1203,$AE17-1200)=0,"",INDEX(对接源_02物料!$E$4:$E$1203,$AE17-1200)))) | D17: =IF($AE17="","",IF($AE17<=1200,IF(INDEX(对接源_01水果!$V$4:$V$1203,$AE17)=0,"",INDEX(对接源_01水果!$V$4:$V$1203,$AE17)),IF(INDEX(对接源_02物料!$V$4:$V$1203,$AE17-1200)=0,"",INDEX(对接源_02物料!$V$4:$V$1203,$AE17-1200)))) | E17: =IF($AE17="","",IF($AE17<=1200,IF(INDEX(对接源_01水果!$C$4:$C$1203,$AE17)=0,"",INDEX(对接源_01水果!$C$4:$C$1203,$AE17)),IF(INDEX(对接源_02物料!$C$4:$C$1203,$AE17-1200)=0,"",INDEX(对接源_02物料!$C$4:$C$1203,$AE17-1200)))) | F17: =IF($AE17="","",IF($AE17<=1200,IF(INDEX(对接源_01水果!$W$4:$W$1203,$AE17)=0,"",INDEX(对接源_01水果!$W$4:$W$1203,$AE17)),IF(INDEX(对接源_02物料!$W$4:$W$1203,$AE17-1200)=0,"",INDEX(对接源_02物料!$W$4:$W$1203,$AE17-1200)))) | G17: =IF($AE17="","",IF($AE17<=1200,IF(INDEX(对接源_01水果!$D$4:$D$1203,$AE17)=0,"",INDEX(对接源_01水果!$D$4:$D$1203,$AE17)),IF(INDEX(对接源_02物料!$D$4:$D$1203,$AE17-1200)=0,"",INDEX(对接源_02物料!$D$4:$D$1203,$AE17-1200)))) | H17: =IF($AE17="","",IF($AE17<=1200,"01水果册","02物料册")) | I17: =IF($AE17="","",IF($AE17<=1200,IF(INDEX(对接源_01水果!$M$4:$M$1203,$AE17)=0,"",INDEX(对接源_01水果!$M$4:$M$1203,$AE17)),IF(INDEX(对接源_02物料!$M$4:$M$1203,$AE17-1200)=0,"",INDEX(对接源_02物料!$M$4:$M$1203,$AE17-1200)))) | AE17: =IFERROR(MATCH(12,_自动清单!$W$4:$W$2403,0),"")
A18: =IF($AE18="","",IF($AE18<=1200,IF(INDEX(对接源_01水果!$B$4:$B$1203,$AE18)=0,"",INDEX(对接源_01水果!$B$4:$B$1203,$AE18)),IF(INDEX(对接源_02物料!$B$4:$B$1203,$AE18-1200)=0,"",INDEX(对接源_02物料!$B$4:$B$1203,$AE18-1200)))) | B18: =IF($AE18="","",IF($AE18<=1200,IF(INDEX(对接源_01水果!$S$4:$S$1203,$AE18)=0,"",INDEX(对接源_01水果!$S$4:$S$1203,$AE18)),IF(INDEX(对接源_02物料!$S$4:$S$1203,$AE18-1200)=0,"",INDEX(对接源_02物料!$S$4:$S$1203,$AE18-1200)))) | C18: =IF($AE18="","",IF($AE18<=1200,IF(INDEX(对接源_01水果!$E$4:$E$1203,$AE18)=0,"",INDEX(对接源_01水果!$E$4:$E$1203,$AE18)),IF(INDEX(对接源_02物料!$E$4:$E$1203,$AE18-1200)=0,"",INDEX(对接源_02物料!$E$4:$E$1203,$AE18-1200)))) | D18: =IF($AE18="","",IF($AE18<=1200,IF(INDEX(对接源_01水果!$V$4:$V$1203,$AE18)=0,"",INDEX(对接源_01水果!$V$4:$V$1203,$AE18)),IF(INDEX(对接源_02物料!$V$4:$V$1203,$AE18-1200)=0,"",INDEX(对接源_02物料!$V$4:$V$1203,$AE18-1200)))) | E18: =IF($AE18="","",IF($AE18<=1200,IF(INDEX(对接源_01水果!$C$4:$C$1203,$AE18)=0,"",INDEX(对接源_01水果!$C$4:$C$1203,$AE18)),IF(INDEX(对接源_02物料!$C$4:$C$1203,$AE18-1200)=0,"",INDEX(对接源_02物料!$C$4:$C$1203,$AE18-1200)))) | F18: =IF($AE18="","",IF($AE18<=1200,IF(INDEX(对接源_01水果!$W$4:$W$1203,$AE18)=0,"",INDEX(对接源_01水果!$W$4:$W$1203,$AE18)),IF(INDEX(对接源_02物料!$W$4:$W$1203,$AE18-1200)=0,"",INDEX(对接源_02物料!$W$4:$W$1203,$AE18-1200)))) | G18: =IF($AE18="","",IF($AE18<=1200,IF(INDEX(对接源_01水果!$D$4:$D$1203,$AE18)=0,"",INDEX(对接源_01水果!$D$4:$D$1203,$AE18)),IF(INDEX(对接源_02物料!$D$4:$D$1203,$AE18-1200)=0,"",INDEX(对接源_02物料!$D$4:$D$1203,$AE18-1200)))) | H18: =IF($AE18="","",IF($AE18<=1200,"01水果册","02物料册")) | I18: =IF($AE18="","",IF($AE18<=1200,IF(INDEX(对接源_01水果!$M$4:$M$1203,$AE18)=0,"",INDEX(对接源_01水果!$M$4:$M$1203,$AE18)),IF(INDEX(对接源_02物料!$M$4:$M$1203,$AE18-1200)=0,"",INDEX(对接源_02物料!$M$4:$M$1203,$AE18-1200)))) | AE18: =IFERROR(MATCH(13,_自动清单!$W$4:$W$2403,0),"")
A19: =IF($AE19="","",IF($AE19<=1200,IF(INDEX(对接源_01水果!$B$4:$B$1203,$AE19)=0,"",INDEX(对接源_01水果!$B$4:$B$1203,$AE19)),IF(INDEX(对接源_02物料!$B$4:$B$1203,$AE19-1200)=0,"",INDEX(对接源_02物料!$B$4:$B$1203,$AE19-1200)))) | B19: =IF($AE19="","",IF($AE19<=1200,IF(INDEX(对接源_01水果!$S$4:$S$1203,$AE19)=0,"",INDEX(对接源_01水果!$S$4:$S$1203,$AE19)),IF(INDEX(对接源_02物料!$S$4:$S$1203,$AE19-1200)=0,"",INDEX(对接源_02物料!$S$4:$S$1203,$AE19-1200)))) | C19: =IF($AE19="","",IF($AE19<=1200,IF(INDEX(对接源_01水果!$E$4:$E$1203,$AE19)=0,"",INDEX(对接源_01水果!$E$4:$E$1203,$AE19)),IF(INDEX(对接源_02物料!$E$4:$E$1203,$AE19-1200)=0,"",INDEX(对接源_02物料!$E$4:$E$1203,$AE19-1200)))) | D19: =IF($AE19="","",IF($AE19<=1200,IF(INDEX(对接源_01水果!$V$4:$V$1203,$AE19)=0,"",INDEX(对接源_01水果!$V$4:$V$1203,$AE19)),IF(INDEX(对接源_02物料!$V$4:$V$1203,$AE19-1200)=0,"",INDEX(对接源_02物料!$V$4:$V$1203,$AE19-1200)))) | E19: =IF($AE19="","",IF($AE19<=1200,IF(INDEX(对接源_01水果!$C$4:$C$1203,$AE19)=0,"",INDEX(对接源_01水果!$C$4:$C$1203,$AE19)),IF(INDEX(对接源_02物料!$C$4:$C$1203,$AE19-1200)=0,"",INDEX(对接源_02物料!$C$4:$C$1203,$AE19-1200)))) | F19: =IF($AE19="","",IF($AE19<=1200,IF(INDEX(对接源_01水果!$W$4:$W$1203,$AE19)=0,"",INDEX(对接源_01水果!$W$4:$W$1203,$AE19)),IF(INDEX(对接源_02物料!$W$4:$W$1203,$AE19-1200)=0,"",INDEX(对接源_02物料!$W$4:$W$1203,$AE19-1200)))) | G19: =IF($AE19="","",IF($AE19<=1200,IF(INDEX(对接源_01水果!$D$4:$D$1203,$AE19)=0,"",INDEX(对接源_01水果!$D$4:$D$1203,$AE19)),IF(INDEX(对接源_02物料!$D$4:$D$1203,$AE19-1200)=0,"",INDEX(对接源_02物料!$D$4:$D$1203,$AE19-1200)))) | H19: =IF($AE19="","",IF($AE19<=1200,"01水果册","02物料册")) | I19: =IF($AE19="","",IF($AE19<=1200,IF(INDEX(对接源_01水果!$M$4:$M$1203,$AE19)=0,"",INDEX(对接源_01水果!$M$4:$M$1203,$AE19)),IF(INDEX(对接源_02物料!$M$4:$M$1203,$AE19-1200)=0,"",INDEX(对接源_02物料!$M$4:$M$1203,$AE19-1200)))) | AE19: =IFERROR(MATCH(14,_自动清单!$W$4:$W$2403,0),"")
A20: =IF($AE20="","",IF($AE20<=1200,IF(INDEX(对接源_01水果!$B$4:$B$1203,$AE20)=0,"",INDEX(对接源_01水果!$B$4:$B$1203,$AE20)),IF(INDEX(对接源_02物料!$B$4:$B$1203,$AE20-1200)=0,"",INDEX(对接源_02物料!$B$4:$B$1203,$AE20-1200)))) | B20: =IF($AE20="","",IF($AE20<=1200,IF(INDEX(对接源_01水果!$S$4:$S$1203,$AE20)=0,"",INDEX(对接源_01水果!$S$4:$S$1203,$AE20)),IF(INDEX(对接源_02物料!$S$4:$S$1203,$AE20-1200)=0,"",INDEX(对接源_02物料!$S$4:$S$1203,$AE20-1200)))) | C20: =IF($AE20="","",IF($AE20<=1200,IF(INDEX(对接源_01水果!$E$4:$E$1203,$AE20)=0,"",INDEX(对接源_01水果!$E$4:$E$1203,$AE20)),IF(INDEX(对接源_02物料!$E$4:$E$1203,$AE20-1200)=0,"",INDEX(对接源_02物料!$E$4:$E$1203,$AE20-1200)))) | D20: =IF($AE20="","",IF($AE20<=1200,IF(INDEX(对接源_01水果!$V$4:$V$1203,$AE20)=0,"",INDEX(对接源_01水果!$V$4:$V$1203,$AE20)),IF(INDEX(对接源_02物料!$V$4:$V$1203,$AE20-1200)=0,"",INDEX(对接源_02物料!$V$4:$V$1203,$AE20-1200)))) | E20: =IF($AE20="","",IF($AE20<=1200,IF(INDEX(对接源_01水果!$C$4:$C$1203,$AE20)=0,"",INDEX(对接源_01水果!$C$4:$C$1203,$AE20)),IF(INDEX(对接源_02物料!$C$4:$C$1203,$AE20-1200)=0,"",INDEX(对接源_02物料!$C$4:$C$1203,$AE20-1200)))) | F20: =IF($AE20="","",IF($AE20<=1200,IF(INDEX(对接源_01水果!$W$4:$W$1203,$AE20)=0,"",INDEX(对接源_01水果!$W$4:$W$1203,$AE20)),IF(INDEX(对接源_02物料!$W$4:$W$1203,$AE20-1200)=0,"",INDEX(对接源_02物料!$W$4:$W$1203,$AE20-1200)))) | G20: =IF($AE20="","",IF($AE20<=1200,IF(INDEX(对接源_01水果!$D$4:$D$1203,$AE20)=0,"",INDEX(对接源_01水果!$D$4:$D$1203,$AE20)),IF(INDEX(对接源_02物料!$D$4:$D$1203,$AE20-1200)=0,"",INDEX(对接源_02物料!$D$4:$D$1203,$AE20-1200)))) | H20: =IF($AE20="","",IF($AE20<=1200,"01水果册","02物料册")) | I20: =IF($AE20="","",IF($AE20<=1200,IF(INDEX(对接源_01水果!$M$4:$M$1203,$AE20)=0,"",INDEX(对接源_01水果!$M$4:$M$1203,$AE20)),IF(INDEX(对接源_02物料!$M$4:$M$1203,$AE20-1200)=0,"",INDEX(对接源_02物料!$M$4:$M$1203,$AE20-1200)))) | AE20: =IFERROR(MATCH(15,_自动清单!$W$4:$W$2403,0),"")
A21: =IF($AE21="","",IF($AE21<=1200,IF(INDEX(对接源_01水果!$B$4:$B$1203,$AE21)=0,"",INDEX(对接源_01水果!$B$4:$B$1203,$AE21)),IF(INDEX(对接源_02物料!$B$4:$B$1203,$AE21-1200)=0,"",INDEX(对接源_02物料!$B$4:$B$1203,$AE21-1200)))) | B21: =IF($AE21="","",IF($AE21<=1200,IF(INDEX(对接源_01水果!$S$4:$S$1203,$AE21)=0,"",INDEX(对接源_01水果!$S$4:$S$1203,$AE21)),IF(INDEX(对接源_02物料!$S$4:$S$1203,$AE21-1200)=0,"",INDEX(对接源_02物料!$S$4:$S$1203,$AE21-1200)))) | C21: =IF($AE21="","",IF($AE21<=1200,IF(INDEX(对接源_01水果!$E$4:$E$1203,$AE21)=0,"",INDEX(对接源_01水果!$E$4:$E$1203,$AE21)),IF(INDEX(对接源_02物料!$E$4:$E$1203,$AE21-1200)=0,"",INDEX(对接源_02物料!$E$4:$E$1203,$AE21-1200)))) | D21: =IF($AE21="","",IF($AE21<=1200,IF(INDEX(对接源_01水果!$V$4:$V$1203,$AE21)=0,"",INDEX(对接源_01水果!$V$4:$V$1203,$AE21)),IF(INDEX(对接源_02物料!$V$4:$V$1203,$AE21-1200)=0,"",INDEX(对接源_02物料!$V$4:$V$1203,$AE21-1200)))) | E21: =IF($AE21="","",IF($AE21<=1200,IF(INDEX(对接源_01水果!$C$4:$C$1203,$AE21)=0,"",INDEX(对接源_01水果!$C$4:$C$1203,$AE21)),IF(INDEX(对接源_02物料!$C$4:$C$1203,$AE21-1200)=0,"",INDEX(对接源_02物料!$C$4:$C$1203,$AE21-1200)))) | F21: =IF($AE21="","",IF($AE21<=1200,IF(INDEX(对接源_01水果!$W$4:$W$1203,$AE21)=0,"",INDEX(对接源_01水果!$W$4:$W$1203,$AE21)),IF(INDEX(对接源_02物料!$W$4:$W$1203,$AE21-1200)=0,"",INDEX(对接源_02物料!$W$4:$W$1203,$AE21-1200)))) | G21: =IF($AE21="","",IF($AE21<=1200,IF(INDEX(对接源_01水果!$D$4:$D$1203,$AE21)=0,"",INDEX(对接源_01水果!$D$4:$D$1203,$AE21)),IF(INDEX(对接源_02物料!$D$4:$D$1203,$AE21-1200)=0,"",INDEX(对接源_02物料!$D$4:$D$1203,$AE21-1200)))) | H21: =IF($AE21="","",IF($AE21<=1200,"01水果册","02物料册")) | I21: =IF($AE21="","",IF($AE21<=1200,IF(INDEX(对接源_01水果!$M$4:$M$1203,$AE21)=0,"",INDEX(对接源_01水果!$M$4:$M$1203,$AE21)),IF(INDEX(对接源_02物料!$M$4:$M$1203,$AE21-1200)=0,"",INDEX(对接源_02物料!$M$4:$M$1203,$AE21-1200)))) | AE21: =IFERROR(MATCH(16,_自动清单!$W$4:$W$2403,0),"")
A22: =IF($AE22="","",IF($AE22<=1200,IF(INDEX(对接源_01水果!$B$4:$B$1203,$AE22)=0,"",INDEX(对接源_01水果!$B$4:$B$1203,$AE22)),IF(INDEX(对接源_02物料!$B$4:$B$1203,$AE22-1200)=0,"",INDEX(对接源_02物料!$B$4:$B$1203,$AE22-1200)))) | B22: =IF($AE22="","",IF($AE22<=1200,IF(INDEX(对接源_01水果!$S$4:$S$1203,$AE22)=0,"",INDEX(对接源_01水果!$S$4:$S$1203,$AE22)),IF(INDEX(对接源_02物料!$S$4:$S$1203,$AE22-1200)=0,"",INDEX(对接源_02物料!$S$4:$S$1203,$AE22-1200)))) | C22: =IF($AE22="","",IF($AE22<=1200,IF(INDEX(对接源_01水果!$E$4:$E$1203,$AE22)=0,"",INDEX(对接源_01水果!$E$4:$E$1203,$AE22)),IF(INDEX(对接源_02物料!$E$4:$E$1203,$AE22-1200)=0,"",INDEX(对接源_02物料!$E$4:$E$1203,$AE22-1200)))) | D22: =IF($AE22="","",IF($AE22<=1200,IF(INDEX(对接源_01水果!$V$4:$V$1203,$AE22)=0,"",INDEX(对接源_01水果!$V$4:$V$1203,$AE22)),IF(INDEX(对接源_02物料!$V$4:$V$1203,$AE22-1200)=0,"",INDEX(对接源_02物料!$V$4:$V$1203,$AE22-1200)))) | E22: =IF($AE22="","",IF($AE22<=1200,IF(INDEX(对接源_01水果!$C$4:$C$1203,$AE22)=0,"",INDEX(对接源_01水果!$C$4:$C$1203,$AE22)),IF(INDEX(对接源_02物料!$C$4:$C$1203,$AE22-1200)=0,"",INDEX(对接源_02物料!$C$4:$C$1203,$AE22-1200)))) | F22: =IF($AE22="","",IF($AE22<=1200,IF(INDEX(对接源_01水果!$W$4:$W$1203,$AE22)=0,"",INDEX(对接源_01水果!$W$4:$W$1203,$AE22)),IF(INDEX(对接源_02物料!$W$4:$W$1203,$AE22-1200)=0,"",INDEX(对接源_02物料!$W$4:$W$1203,$AE22-1200)))) | G22: =IF($AE22="","",IF($AE22<=1200,IF(INDEX(对接源_01水果!$D$4:$D$1203,$AE22)=0,"",INDEX(对接源_01水果!$D$4:$D$1203,$AE22)),IF(INDEX(对接源_02物料!$D$4:$D$1203,$AE22-1200)=0,"",INDEX(对接源_02物料!$D$4:$D$1203,$AE22-1200)))) | H22: =IF($AE22="","",IF($AE22<=1200,"01水果册","02物料册")) | I22: =IF($AE22="","",IF($AE22<=1200,IF(INDEX(对接源_01水果!$M$4:$M$1203,$AE22)=0,"",INDEX(对接源_01水果!$M$4:$M$1203,$AE22)),IF(INDEX(对接源_02物料!$M$4:$M$1203,$AE22-1200)=0,"",INDEX(对接源_02物料!$M$4:$M$1203,$AE22-1200)))) | AE22: =IFERROR(MATCH(17,_自动清单!$W$4:$W$2403,0),"")
A23: =IF($AE23="","",IF($AE23<=1200,IF(INDEX(对接源_01水果!$B$4:$B$1203,$AE23)=0,"",INDEX(对接源_01水果!$B$4:$B$1203,$AE23)),IF(INDEX(对接源_02物料!$B$4:$B$1203,$AE23-1200)=0,"",INDEX(对接源_02物料!$B$4:$B$1203,$AE23-1200)))) | B23: =IF($AE23="","",IF($AE23<=1200,IF(INDEX(对接源_01水果!$S$4:$S$1203,$AE23)=0,"",INDEX(对接源_01水果!$S$4:$S$1203,$AE23)),IF(INDEX(对接源_02物料!$S$4:$S$1203,$AE23-1200)=0,"",INDEX(对接源_02物料!$S$4:$S$1203,$AE23-1200)))) | C23: =IF($AE23="","",IF($AE23<=1200,IF(INDEX(对接源_01水果!$E$4:$E$1203,$AE23)=0,"",INDEX(对接源_01水果!$E$4:$E$1203,$AE23)),IF(INDEX(对接源_02物料!$E$4:$E$1203,$AE23-1200)=0,"",INDEX(对接源_02物料!$E$4:$E$1203,$AE23-1200)))) | D23: =IF($AE23="","",IF($AE23<=1200,IF(INDEX(对接源_01水果!$V$4:$V$1203,$AE23)=0,"",INDEX(对接源_01水果!$V$4:$V$1203,$AE23)),IF(INDEX(对接源_02物料!$V$4:$V$1203,$AE23-1200)=0,"",INDEX(对接源_02物料!$V$4:$V$1203,$AE23-1200)))) | E23: =IF($AE23="","",IF($AE23<=1200,IF(INDEX(对接源_01水果!$C$4:$C$1203,$AE23)=0,"",INDEX(对接源_01水果!$C$4:$C$1203,$AE23)),IF(INDEX(对接源_02物料!$C$4:$C$1203,$AE23-1200)=0,"",INDEX(对接源_02物料!$C$4:$C$1203,$AE23-1200)))) | F23: =IF($AE23="","",IF($AE23<=1200,IF(INDEX(对接源_01水果!$W$4:$W$1203,$AE23)=0,"",INDEX(对接源_01水果!$W$4:$W$1203,$AE23)),IF(INDEX(对接源_02物料!$W$4:$W$1203,$AE23-1200)=0,"",INDEX(对接源_02物料!$W$4:$W$1203,$AE23-1200)))) | G23: =IF($AE23="","",IF($AE23<=1200,IF(INDEX(对接源_01水果!$D$4:$D$1203,$AE23)=0,"",INDEX(对接源_01水果!$D$4:$D$1203,$AE23)),IF(INDEX(对接源_02物料!$D$4:$D$1203,$AE23-1200)=0,"",INDEX(对接源_02物料!$D$4:$D$1203,$AE23-1200)))) | H23: =IF($AE23="","",IF($AE23<=1200,"01水果册","02物料册")) | I23: =IF($AE23="","",IF($AE23<=1200,IF(INDEX(对接源_01水果!$M$4:$M$1203,$AE23)=0,"",INDEX(对接源_01水果!$M$4:$M$1203,$AE23)),IF(INDEX(对接源_02物料!$M$4:$M$1203,$AE23-1200)=0,"",INDEX(对接源_02物料!$M$4:$M$1203,$AE23-1200)))) | AE23: =IFERROR(MATCH(18,_自动清单!$W$4:$W$2403,0),"")
A24: =IF($AE24="","",IF($AE24<=1200,IF(INDEX(对接源_01水果!$B$4:$B$1203,$AE24)=0,"",INDEX(对接源_01水果!$B$4:$B$1203,$AE24)),IF(INDEX(对接源_02物料!$B$4:$B$1203,$AE24-1200)=0,"",INDEX(对接源_02物料!$B$4:$B$1203,$AE24-1200)))) | B24: =IF($AE24="","",IF($AE24<=1200,IF(INDEX(对接源_01水果!$S$4:$S$1203,$AE24)=0,"",INDEX(对接源_01水果!$S$4:$S$1203,$AE24)),IF(INDEX(对接源_02物料!$S$4:$S$1203,$AE24-1200)=0,"",INDEX(对接源_02物料!$S$4:$S$1203,$AE24-1200)))) | C24: =IF($AE24="","",IF($AE24<=1200,IF(INDEX(对接源_01水果!$E$4:$E$1203,$AE24)=0,"",INDEX(对接源_01水果!$E$4:$E$1203,$AE24)),IF(INDEX(对接源_02物料!$E$4:$E$1203,$AE24-1200)=0,"",INDEX(对接源_02物料!$E$4:$E$1203,$AE24-1200)))) | D24: =IF($AE24="","",IF($AE24<=1200,IF(INDEX(对接源_01水果!$V$4:$V$1203,$AE24)=0,"",INDEX(对接源_01水果!$V$4:$V$1203,$AE24)),IF(INDEX(对接源_02物料!$V$4:$V$1203,$AE24-1200)=0,"",INDEX(对接源_02物料!$V$4:$V$1203,$AE24-1200)))) | E24: =IF($AE24="","",IF($AE24<=1200,IF(INDEX(对接源_01水果!$C$4:$C$1203,$AE24)=0,"",INDEX(对接源_01水果!$C$4:$C$1203,$AE24)),IF(INDEX(对接源_02物料!$C$4:$C$1203,$AE24-1200)=0,"",INDEX(对接源_02物料!$C$4:$C$1203,$AE24-1200)))) | F24: =IF($AE24="","",IF($AE24<=1200,IF(INDEX(对接源_01水果!$W$4:$W$1203,$AE24)=0,"",INDEX(对接源_01水果!$W$4:$W$1203,$AE24)),IF(INDEX(对接源_02物料!$W$4:$W$1203,$AE24-1200)=0,"",INDEX(对接源_02物料!$W$4:$W$1203,$AE24-1200)))) | G24: =IF($AE24="","",IF($AE24<=1200,IF(INDEX(对接源_01水果!$D$4:$D$1203,$AE24)=0,"",INDEX(对接源_01水果!$D$4:$D$1203,$AE24)),IF(INDEX(对接源_02物料!$D$4:$D$1203,$AE24-1200)=0,"",INDEX(对接源_02物料!$D$4:$D$1203,$AE24-1200)))) | H24: =IF($AE24="","",IF($AE24<=1200,"01水果册","02物料册")) | I24: =IF($AE24="","",IF($AE24<=1200,IF(INDEX(对接源_01水果!$M$4:$M$1203,$AE24)=0,"",INDEX(对接源_01水果!$M$4:$M$1203,$AE24)),IF(INDEX(对接源_02物料!$M$4:$M$1203,$AE24-1200)=0,"",INDEX(对接源_02物料!$M$4:$M$1203,$AE24-1200)))) | AE24: =IFERROR(MATCH(19,_自动清单!$W$4:$W$2403,0),"")
A25: =IF($AE25="","",IF($AE25<=1200,IF(INDEX(对接源_01水果!$B$4:$B$1203,$AE25)=0,"",INDEX(对接源_01水果!$B$4:$B$1203,$AE25)),IF(INDEX(对接源_02物料!$B$4:$B$1203,$AE25-1200)=0,"",INDEX(对接源_02物料!$B$4:$B$1203,$AE25-1200)))) | B25: =IF($AE25="","",IF($AE25<=1200,IF(INDEX(对接源_01水果!$S$4:$S$1203,$AE25)=0,"",INDEX(对接源_01水果!$S$4:$S$1203,$AE25)),IF(INDEX(对接源_02物料!$S$4:$S$1203,$AE25-1200)=0,"",INDEX(对接源_02物料!$S$4:$S$1203,$AE25-1200)))) | C25: =IF($AE25="","",IF($AE25<=1200,IF(INDEX(对接源_01水果!$E$4:$E$1203,$AE25)=0,"",INDEX(对接源_01水果!$E$4:$E$1203,$AE25)),IF(INDEX(对接源_02物料!$E$4:$E$1203,$AE25-1200)=0,"",INDEX(对接源_02物料!$E$4:$E$1203,$AE25-1200)))) | D25: =IF($AE25="","",IF($AE25<=1200,IF(INDEX(对接源_01水果!$V$4:$V$1203,$AE25)=0,"",INDEX(对接源_01水果!$V$4:$V$1203,$AE25)),IF(INDEX(对接源_02物料!$V$4:$V$1203,$AE25-1200)=0,"",INDEX(对接源_02物料!$V$4:$V$1203,$AE25-1200)))) | E25: =IF($AE25="","",IF($AE25<=1200,IF(INDEX(对接源_01水果!$C$4:$C$1203,$AE25)=0,"",INDEX(对接源_01水果!$C$4:$C$1203,$AE25)),IF(INDEX(对接源_02物料!$C$4:$C$1203,$AE25-1200)=0,"",INDEX(对接源_02物料!$C$4:$C$1203,$AE25-1200)))) | F25: =IF($AE25="","",IF($AE25<=1200,IF(INDEX(对接源_01水果!$W$4:$W$1203,$AE25)=0,"",INDEX(对接源_01水果!$W$4:$W$1203,$AE25)),IF(INDEX(对接源_02物料!$W$4:$W$1203,$AE25-1200)=0,"",INDEX(对接源_02物料!$W$4:$W$1203,$AE25-1200)))) | G25: =IF($AE25="","",IF($AE25<=1200,IF(INDEX(对接源_01水果!$D$4:$D$1203,$AE25)=0,"",INDEX(对接源_01水果!$D$4:$D$1203,$AE25)),IF(INDEX(对接源_02物料!$D$4:$D$1203,$AE25-1200)=0,"",INDEX(对接源_02物料!$D$4:$D$1203,$AE25-1200)))) | H25: =IF($AE25="","",IF($AE25<=1200,"01水果册","02物料册")) | I25: =IF($AE25="","",IF($AE25<=1200,IF(INDEX(对接源_01水果!$M$4:$M$1203,$AE25)=0,"",INDEX(对接源_01水果!$M$4:$M$1203,$AE25)),IF(INDEX(对接源_02物料!$M$4:$M$1203,$AE25-1200)=0,"",INDEX(对接源_02物料!$M$4:$M$1203,$AE25-1200)))) | AE25: =IFERROR(MATCH(20,_自动清单!$W$4:$W$2403,0),"")
A26: =IF($AE26="","",IF($AE26<=1200,IF(INDEX(对接源_01水果!$B$4:$B$1203,$AE26)=0,"",INDEX(对接源_01水果!$B$4:$B$1203,$AE26)),IF(INDEX(对接源_02物料!$B$4:$B$1203,$AE26-1200)=0,"",INDEX(对接源_02物料!$B$4:$B$1203,$AE26-1200)))) | B26: =IF($AE26="","",IF($AE26<=1200,IF(INDEX(对接源_01水果!$S$4:$S$1203,$AE26)=0,"",INDEX(对接源_01水果!$S$4:$S$1203,$AE26)),IF(INDEX(对接源_02物料!$S$4:$S$1203,$AE26-1200)=0,"",INDEX(对接源_02物料!$S$4:$S$1203,$AE26-1200)))) | C26: =IF($AE26="","",IF($AE26<=1200,IF(INDEX(对接源_01水果!$E$4:$E$1203,$AE26)=0,"",INDEX(对接源_01水果!$E$4:$E$1203,$AE26)),IF(INDEX(对接源_02物料!$E$4:$E$1203,$AE26-1200)=0,"",INDEX(对接源_02物料!$E$4:$E$1203,$AE26-1200)))) | D26: =IF($AE26="","",IF($AE26<=1200,IF(INDEX(对接源_01水果!$V$4:$V$1203,$AE26)=0,"",INDEX(对接源_01水果!$V$4:$V$1203,$AE26)),IF(INDEX(对接源_02物料!$V$4:$V$1203,$AE26-1200)=0,"",INDEX(对接源_02物料!$V$4:$V$1203,$AE26-1200)))) | E26: =IF($AE26="","",IF($AE26<=1200,IF(INDEX(对接源_01水果!$C$4:$C$1203,$AE26)=0,"",INDEX(对接源_01水果!$C$4:$C$1203,$AE26)),IF(INDEX(对接源_02物料!$C$4:$C$1203,$AE26-1200)=0,"",INDEX(对接源_02物料!$C$4:$C$1203,$AE26-1200)))) | F26: =IF($AE26="","",IF($AE26<=1200,IF(INDEX(对接源_01水果!$W$4:$W$1203,$AE26)=0,"",INDEX(对接源_01水果!$W$4:$W$1203,$AE26)),IF(INDEX(对接源_02物料!$W$4:$W$1203,$AE26-1200)=0,"",INDEX(对接源_02物料!$W$4:$W$1203,$AE26-1200)))) | G26: =IF($AE26="","",IF($AE26<=1200,IF(INDEX(对接源_01水果!$D$4:$D$1203,$AE26)=0,"",INDEX(对接源_01水果!$D$4:$D$1203,$AE26)),IF(INDEX(对接源_02物料!$D$4:$D$1203,$AE26-1200)=0,"",INDEX(对接源_02物料!$D$4:$D$1203,$AE26-1200)))) | H26: =IF($AE26="","",IF($AE26<=1200,"01水果册","02物料册")) | I26: =IF($AE26="","",IF($AE26<=1200,IF(INDEX(对接源_01水果!$M$4:$M$1203,$AE26)=0,"",INDEX(对接源_01水果!$M$4:$M$1203,$AE26)),IF(INDEX(对接源_02物料!$M$4:$M$1203,$AE26-1200)=0,"",INDEX(对接源_02物料!$M$4:$M$1203,$AE26-1200)))) | AE26: =IFERROR(MATCH(21,_自动清单!$W$4:$W$2403,0),"")
A27: =IF($AE27="","",IF($AE27<=1200,IF(INDEX(对接源_01水果!$B$4:$B$1203,$AE27)=0,"",INDEX(对接源_01水果!$B$4:$B$1203,$AE27)),IF(INDEX(对接源_02物料!$B$4:$B$1203,$AE27-1200)=0,"",INDEX(对接源_02物料!$B$4:$B$1203,$AE27-1200)))) | B27: =IF($AE27="","",IF($AE27<=1200,IF(INDEX(对接源_01水果!$S$4:$S$1203,$AE27)=0,"",INDEX(对接源_01水果!$S$4:$S$1203,$AE27)),IF(INDEX(对接源_02物料!$S$4:$S$1203,$AE27-1200)=0,"",INDEX(对接源_02物料!$S$4:$S$1203,$AE27-1200)))) | C27: =IF($AE27="","",IF($AE27<=1200,IF(INDEX(对接源_01水果!$E$4:$E$1203,$AE27)=0,"",INDEX(对接源_01水果!$E$4:$E$1203,$AE27)),IF(INDEX(对接源_02物料!$E$4:$E$1203,$AE27-1200)=0,"",INDEX(对接源_02物料!$E$4:$E$1203,$AE27-1200)))) | D27: =IF($AE27="","",IF($AE27<=1200,IF(INDEX(对接源_01水果!$V$4:$V$1203,$AE27)=0,"",INDEX(对接源_01水果!$V$4:$V$1203,$AE27)),IF(INDEX(对接源_02物料!$V$4:$V$1203,$AE27-1200)=0,"",INDEX(对接源_02物料!$V$4:$V$1203,$AE27-1200)))) | E27: =IF($AE27="","",IF($AE27<=1200,IF(INDEX(对接源_01水果!$C$4:$C$1203,$AE27)=0,"",INDEX(对接源_01水果!$C$4:$C$1203,$AE27)),IF(INDEX(对接源_02物料!$C$4:$C$1203,$AE27-1200)=0,"",INDEX(对接源_02物料!$C$4:$C$1203,$AE27-1200)))) | F27: =IF($AE27="","",IF($AE27<=1200,IF(INDEX(对接源_01水果!$W$4:$W$1203,$AE27)=0,"",INDEX(对接源_01水果!$W$4:$W$1203,$AE27)),IF(INDEX(对接源_02物料!$W$4:$W$1203,$AE27-1200)=0,"",INDEX(对接源_02物料!$W$4:$W$1203,$AE27-1200)))) | G27: =IF($AE27="","",IF($AE27<=1200,IF(INDEX(对接源_01水果!$D$4:$D$1203,$AE27)=0,"",INDEX(对接源_01水果!$D$4:$D$1203,$AE27)),IF(INDEX(对接源_02物料!$D$4:$D$1203,$AE27-1200)=0,"",INDEX(对接源_02物料!$D$4:$D$1203,$AE27-1200)))) | H27: =IF($AE27="","",IF($AE27<=1200,"01水果册","02物料册")) | I27: =IF($AE27="","",IF($AE27<=1200,IF(INDEX(对接源_01水果!$M$4:$M$1203,$AE27)=0,"",INDEX(对接源_01水果!$M$4:$M$1203,$AE27)),IF(INDEX(对接源_02物料!$M$4:$M$1203,$AE27-1200)=0,"",INDEX(对接源_02物料!$M$4:$M$1203,$AE27-1200)))) | AE27: =IFERROR(MATCH(22,_自动清单!$W$4:$W$2403,0),"")
A28: =IF($AE28="","",IF($AE28<=1200,IF(INDEX(对接源_01水果!$B$4:$B$1203,$AE28)=0,"",INDEX(对接源_01水果!$B$4:$B$1203,$AE28)),IF(INDEX(对接源_02物料!$B$4:$B$1203,$AE28-1200)=0,"",INDEX(对接源_02物料!$B$4:$B$1203,$AE28-1200)))) | B28: =IF($AE28="","",IF($AE28<=1200,IF(INDEX(对接源_01水果!$S$4:$S$1203,$AE28)=0,"",INDEX(对接源_01水果!$S$4:$S$1203,$AE28)),IF(INDEX(对接源_02物料!$S$4:$S$1203,$AE28-1200)=0,"",INDEX(对接源_02物料!$S$4:$S$1203,$AE28-1200)))) | C28: =IF($AE28="","",IF($AE28<=1200,IF(INDEX(对接源_01水果!$E$4:$E$1203,$AE28)=0,"",INDEX(对接源_01水果!$E$4:$E$1203,$AE28)),IF(INDEX(对接源_02物料!$E$4:$E$1203,$AE28-1200)=0,"",INDEX(对接源_02物料!$E$4:$E$1203,$AE28-1200)))) | D28: =IF($AE28="","",IF($AE28<=1200,IF(INDEX(对接源_01水果!$V$4:$V$1203,$AE28)=0,"",INDEX(对接源_01水果!$V$4:$V$1203,$AE28)),IF(INDEX(对接源_02物料!$V$4:$V$1203,$AE28-1200)=0,"",INDEX(对接源_02物料!$V$4:$V$1203,$AE28-1200)))) | E28: =IF($AE28="","",IF($AE28<=1200,IF(INDEX(对接源_01水果!$C$4:$C$1203,$AE28)=0,"",INDEX(对接源_01水果!$C$4:$C$1203,$AE28)),IF(INDEX(对接源_02物料!$C$4:$C$1203,$AE28-1200)=0,"",INDEX(对接源_02物料!$C$4:$C$1203,$AE28-1200)))) | F28: =IF($AE28="","",IF($AE28<=1200,IF(INDEX(对接源_01水果!$W$4:$W$1203,$AE28)=0,"",INDEX(对接源_01水果!$W$4:$W$1203,$AE28)),IF(INDEX(对接源_02物料!$W$4:$W$1203,$AE28-1200)=0,"",INDEX(对接源_02物料!$W$4:$W$1203,$AE28-1200)))) | G28: =IF($AE28="","",IF($AE28<=1200,IF(INDEX(对接源_01水果!$D$4:$D$1203,$AE28)=0,"",INDEX(对接源_01水果!$D$4:$D$1203,$AE28)),IF(INDEX(对接源_02物料!$D$4:$D$1203,$AE28-1200)=0,"",INDEX(对接源_02物料!$D$4:$D$1203,$AE28-1200)))) | H28: =IF($AE28="","",IF($AE28<=1200,"01水果册","02物料册")) | I28: =IF($AE28="","",IF($AE28<=1200,IF(INDEX(对接源_01水果!$M$4:$M$1203,$AE28)=0,"",INDEX(对接源_01水果!$M$4:$M$1203,$AE28)),IF(INDEX(对接源_02物料!$M$4:$M$1203,$AE28-1200)=0,"",INDEX(对接源_02物料!$M$4:$M$1203,$AE28-1200)))) | AE28: =IFERROR(MATCH(23,_自动清单!$W$4:$W$2403,0),"")
A29: =IF($AE29="","",IF($AE29<=1200,IF(INDEX(对接源_01水果!$B$4:$B$1203,$AE29)=0,"",INDEX(对接源_01水果!$B$4:$B$1203,$AE29)),IF(INDEX(对接源_02物料!$B$4:$B$1203,$AE29-1200)=0,"",INDEX(对接源_02物料!$B$4:$B$1203,$AE29-1200)))) | B29: =IF($AE29="","",IF($AE29<=1200,IF(INDEX(对接源_01水果!$S$4:$S$1203,$AE29)=0,"",INDEX(对接源_01水果!$S$4:$S$1203,$AE29)),IF(INDEX(对接源_02物料!$S$4:$S$1203,$AE29-1200)=0,"",INDEX(对接源_02物料!$S$4:$S$1203,$AE29-1200)))) | C29: =IF($AE29="","",IF($AE29<=1200,IF(INDEX(对接源_01水果!$E$4:$E$1203,$AE29)=0,"",INDEX(对接源_01水果!$E$4:$E$1203,$AE29)),IF(INDEX(对接源_02物料!$E$4:$E$1203,$AE29-1200)=0,"",INDEX(对接源_02物料!$E$4:$E$1203,$AE29-1200)))) | D29: =IF($AE29="","",IF($AE29<=1200,IF(INDEX(对接源_01水果!$V$4:$V$1203,$AE29)=0,"",INDEX(对接源_01水果!$V$4:$V$1203,$AE29)),IF(INDEX(对接源_02物料!$V$4:$V$1203,$AE29-1200)=0,"",INDEX(对接源_02物料!$V$4:$V$1203,$AE29-1200)))) | E29: =IF($AE29="","",IF($AE29<=1200,IF(INDEX(对接源_01水果!$C$4:$C$1203,$AE29)=0,"",INDEX(对接源_01水果!$C$4:$C$1203,$AE29)),IF(INDEX(对接源_02物料!$C$4:$C$1203,$AE29-1200)=0,"",INDEX(对接源_02物料!$C$4:$C$1203,$AE29-1200)))) | F29: =IF($AE29="","",IF($AE29<=1200,IF(INDEX(对接源_01水果!$W$4:$W$1203,$AE29)=0,"",INDEX(对接源_01水果!$W$4:$W$1203,$AE29)),IF(INDEX(对接源_02物料!$W$4:$W$1203,$AE29-1200)=0,"",INDEX(对接源_02物料!$W$4:$W$1203,$AE29-1200)))) | G29: =IF($AE29="","",IF($AE29<=1200,IF(INDEX(对接源_01水果!$D$4:$D$1203,$AE29)=0,"",INDEX(对接源_01水果!$D$4:$D$1203,$AE29)),IF(INDEX(对接源_02物料!$D$4:$D$1203,$AE29-1200)=0,"",INDEX(对接源_02物料!$D$4:$D$1203,$AE29-1200)))) | H29: =IF($AE29="","",IF($AE29<=1200,"01水果册","02物料册")) | I29: =IF($AE29="","",IF($AE29<=1200,IF(INDEX(对接源_01水果!$M$4:$M$1203,$AE29)=0,"",INDEX(对接源_01水果!$M$4:$M$1203,$AE29)),IF(INDEX(对接源_02物料!$M$4:$M$1203,$AE29-1200)=0,"",INDEX(对接源_02物料!$M$4:$M$1203,$AE29-1200)))) | AE29: =IFERROR(MATCH(24,_自动清单!$W$4:$W$2403,0),"")
A30: =IF($AE30="","",IF($AE30<=1200,IF(INDEX(对接源_01水果!$B$4:$B$1203,$AE30)=0,"",INDEX(对接源_01水果!$B$4:$B$1203,$AE30)),IF(INDEX(对接源_02物料!$B$4:$B$1203,$AE30-1200)=0,"",INDEX(对接源_02物料!$B$4:$B$1203,$AE30-1200)))) | B30: =IF($AE30="","",IF($AE30<=1200,IF(INDEX(对接源_01水果!$S$4:$S$1203,$AE30)=0,"",INDEX(对接源_01水果!$S$4:$S$1203,$AE30)),IF(INDEX(对接源_02物料!$S$4:$S$1203,$AE30-1200)=0,"",INDEX(对接源_02物料!$S$4:$S$1203,$AE30-1200)))) | C30: =IF($AE30="","",IF($AE30<=1200,IF(INDEX(对接源_01水果!$E$4:$E$1203,$AE30)=0,"",INDEX(对接源_01水果!$E$4:$E$1203,$AE30)),IF(INDEX(对接源_02物料!$E$4:$E$1203,$AE30-1200)=0,"",INDEX(对接源_02物料!$E$4:$E$1203,$AE30-1200)))) | D30: =IF($AE30="","",IF($AE30<=1200,IF(INDEX(对接源_01水果!$V$4:$V$1203,$AE30)=0,"",INDEX(对接源_01水果!$V$4:$V$1203,$AE30)),IF(INDEX(对接源_02物料!$V$4:$V$1203,$AE30-1200)=0,"",INDEX(对接源_02物料!$V$4:$V$1203,$AE30-1200)))) | E30: =IF($AE30="","",IF($AE30<=1200,IF(INDEX(对接源_01水果!$C$4:$C$1203,$AE30)=0,"",INDEX(对接源_01水果!$C$4:$C$1203,$AE30)),IF(INDEX(对接源_02物料!$C$4:$C$1203,$AE30-1200)=0,"",INDEX(对接源_02物料!$C$4:$C$1203,$AE30-1200)))) | F30: =IF($AE30="","",IF($AE30<=1200,IF(INDEX(对接源_01水果!$W$4:$W$1203,$AE30)=0,"",INDEX(对接源_01水果!$W$4:$W$1203,$AE30)),IF(INDEX(对接源_02物料!$W$4:$W$1203,$AE30-1200)=0,"",INDEX(对接源_02物料!$W$4:$W$1203,$AE30-1200)))) | G30: =IF($AE30="","",IF($AE30<=1200,IF(INDEX(对接源_01水果!$D$4:$D$1203,$AE30)=0,"",INDEX(对接源_01水果!$D$4:$D$1203,$AE30)),IF(INDEX(对接源_02物料!$D$4:$D$1203,$AE30-1200)=0,"",INDEX(对接源_02物料!$D$4:$D$1203,$AE30-1200)))) | H30: =IF($AE30="","",IF($AE30<=1200,"01水果册","02物料册")) | I30: =IF($AE30="","",IF($AE30<=1200,IF(INDEX(对接源_01水果!$M$4:$M$1203,$AE30)=0,"",INDEX(对接源_01水果!$M$4:$M$1203,$AE30)),IF(INDEX(对接源_02物料!$M$4:$M$1203,$AE30-1200)=0,"",INDEX(对接源_02物料!$M$4:$M$1203,$AE30-1200)))) | AE30: =IFERROR(MATCH(25,_自动清单!$W$4:$W$2403,0),"")
A31: =IF($AE31="","",IF($AE31<=1200,IF(INDEX(对接源_01水果!$B$4:$B$1203,$AE31)=0,"",INDEX(对接源_01水果!$B$4:$B$1203,$AE31)),IF(INDEX(对接源_02物料!$B$4:$B$1203,$AE31-1200)=0,"",INDEX(对接源_02物料!$B$4:$B$1203,$AE31-1200)))) | B31: =IF($AE31="","",IF($AE31<=1200,IF(INDEX(对接源_01水果!$S$4:$S$1203,$AE31)=0,"",INDEX(对接源_01水果!$S$4:$S$1203,$AE31)),IF(INDEX(对接源_02物料!$S$4:$S$1203,$AE31-1200)=0,"",INDEX(对接源_02物料!$S$4:$S$1203,$AE31-1200)))) | C31: =IF($AE31="","",IF($AE31<=1200,IF(INDEX(对接源_01水果!$E$4:$E$1203,$AE31)=0,"",INDEX(对接源_01水果!$E$4:$E$1203,$AE31)),IF(INDEX(对接源_02物料!$E$4:$E$1203,$AE31-1200)=0,"",INDEX(对接源_02物料!$E$4:$E$1203,$AE31-1200)))) | D31: =IF($AE31="","",IF($AE31<=1200,IF(INDEX(对接源_01水果!$V$4:$V$1203,$AE31)=0,"",INDEX(对接源_01水果!$V$4:$V$1203,$AE31)),IF(INDEX(对接源_02物料!$V$4:$V$1203,$AE31-1200)=0,"",INDEX(对接源_02物料!$V$4:$V$1203,$AE31-1200)))) | E31: =IF($AE31="","",IF($AE31<=1200,IF(INDEX(对接源_01水果!$C$4:$C$1203,$AE31)=0,"",INDEX(对接源_01水果!$C$4:$C$1203,$AE31)),IF(INDEX(对接源_02物料!$C$4:$C$1203,$AE31-1200)=0,"",INDEX(对接源_02物料!$C$4:$C$1203,$AE31-1200)))) | F31: =IF($AE31="","",IF($AE31<=1200,IF(INDEX(对接源_01水果!$W$4:$W$1203,$AE31)=0,"",INDEX(对接源_01水果!$W$4:$W$1203,$AE31)),IF(INDEX(对接源_02物料!$W$4:$W$1203,$AE31-1200)=0,"",INDEX(对接源_02物料!$W$4:$W$1203,$AE31-1200)))) | G31: =IF($AE31="","",IF($AE31<=1200,IF(INDEX(对接源_01水果!$D$4:$D$1203,$AE31)=0,"",INDEX(对接源_01水果!$D$4:$D$1203,$AE31)),IF(INDEX(对接源_02物料!$D$4:$D$1203,$AE31-1200)=0,"",INDEX(对接源_02物料!$D$4:$D$1203,$AE31-1200)))) | H31: =IF($AE31="","",IF($AE31<=1200,"01水果册","02物料册")) | I31: =IF($AE31="","",IF($AE31<=1200,IF(INDEX(对接源_01水果!$M$4:$M$1203,$AE31)=0,"",INDEX(对接源_01水果!$M$4:$M$1203,$AE31)),IF(INDEX(对接源_02物料!$M$4:$M$1203,$AE31-1200)=0,"",INDEX(对接源_02物料!$M$4:$M$1203,$AE31-1200)))) | AE31: =IFERROR(MATCH(26,_自动清单!$W$4:$W$2403,0),"")
A32: =IF($AE32="","",IF($AE32<=1200,IF(INDEX(对接源_01水果!$B$4:$B$1203,$AE32)=0,"",INDEX(对接源_01水果!$B$4:$B$1203,$AE32)),IF(INDEX(对接源_02物料!$B$4:$B$1203,$AE32-1200)=0,"",INDEX(对接源_02物料!$B$4:$B$1203,$AE32-1200)))) | B32: =IF($AE32="","",IF($AE32<=1200,IF(INDEX(对接源_01水果!$S$4:$S$1203,$AE32)=0,"",INDEX(对接源_01水果!$S$4:$S$1203,$AE32)),IF(INDEX(对接源_02物料!$S$4:$S$1203,$AE32-1200)=0,"",INDEX(对接源_02物料!$S$4:$S$1203,$AE32-1200)))) | C32: =IF($AE32="","",IF($AE32<=1200,IF(INDEX(对接源_01水果!$E$4:$E$1203,$AE32)=0,"",INDEX(对接源_01水果!$E$4:$E$1203,$AE32)),IF(INDEX(对接源_02物料!$E$4:$E$1203,$AE32-1200)=0,"",INDEX(对接源_02物料!$E$4:$E$1203,$AE32-1200)))) | D32: =IF($AE32="","",IF($AE32<=1200,IF(INDEX(对接源_01水果!$V$4:$V$1203,$AE32)=0,"",INDEX(对接源_01水果!$V$4:$V$1203,$AE32)),IF(INDEX(对接源_02物料!$V$4:$V$1203,$AE32-1200)=0,"",INDEX(对接源_02物料!$V$4:$V$1203,$AE32-1200)))) | E32: =IF($AE32="","",IF($AE32<=1200,IF(INDEX(对接源_01水果!$C$4:$C$1203,$AE32)=0,"",INDEX(对接源_01水果!$C$4:$C$1203,$AE32)),IF(INDEX(对接源_02物料!$C$4:$C$1203,$AE32-1200)=0,"",INDEX(对接源_02物料!$C$4:$C$1203,$AE32-1200)))) | F32: =IF($AE32="","",IF($AE32<=1200,IF(INDEX(对接源_01水果!$W$4:$W$1203,$AE32)=0,"",INDEX(对接源_01水果!$W$4:$W$1203,$AE32)),IF(INDEX(对接源_02物料!$W$4:$W$1203,$AE32-1200)=0,"",INDEX(对接源_02物料!$W$4:$W$1203,$AE32-1200)))) | G32: =IF($AE32="","",IF($AE32<=1200,IF(INDEX(对接源_01水果!$D$4:$D$1203,$AE32)=0,"",INDEX(对接源_01水果!$D$4:$D$1203,$AE32)),IF(INDEX(对接源_02物料!$D$4:$D$1203,$AE32-1200)=0,"",INDEX(对接源_02物料!$D$4:$D$1203,$AE32-1200)))) | H32: =IF($AE32="","",IF($AE32<=1200,"01水果册","02物料册")) | I32: =IF($AE32="","",IF($AE32<=1200,IF(INDEX(对接源_01水果!$M$4:$M$1203,$AE32)=0,"",INDEX(对接源_01水果!$M$4:$M$1203,$AE32)),IF(INDEX(对接源_02物料!$M$4:$M$1203,$AE32-1200)=0,"",INDEX(对接源_02物料!$M$4:$M$1203,$AE32-1200)))) | AE32: =IFERROR(MATCH(27,_自动清单!$W$4:$W$2403,0),"")
A33: =IF($AE33="","",IF($AE33<=1200,IF(INDEX(对接源_01水果!$B$4:$B$1203,$AE33)=0,"",INDEX(对接源_01水果!$B$4:$B$1203,$AE33)),IF(INDEX(对接源_02物料!$B$4:$B$1203,$AE33-1200)=0,"",INDEX(对接源_02物料!$B$4:$B$1203,$AE33-1200)))) | B33: =IF($AE33="","",IF($AE33<=1200,IF(INDEX(对接源_01水果!$S$4:$S$1203,$AE33)=0,"",INDEX(对接源_01水果!$S$4:$S$1203,$AE33)),IF(INDEX(对接源_02物料!$S$4:$S$1203,$AE33-1200)=0,"",INDEX(对接源_02物料!$S$4:$S$1203,$AE33-1200)))) | C33: =IF($AE33="","",IF($AE33<=1200,IF(INDEX(对接源_01水果!$E$4:$E$1203,$AE33)=0,"",INDEX(对接源_01水果!$E$4:$E$1203,$AE33)),IF(INDEX(对接源_02物料!$E$4:$E$1203,$AE33-1200)=0,"",INDEX(对接源_02物料!$E$4:$E$1203,$AE33-1200)))) | D33: =IF($AE33="","",IF($AE33<=1200,IF(INDEX(对接源_01水果!$V$4:$V$1203,$AE33)=0,"",INDEX(对接源_01水果!$V$4:$V$1203,$AE33)),IF(INDEX(对接源_02物料!$V$4:$V$1203,$AE33-1200)=0,"",INDEX(对接源_02物料!$V$4:$V$1203,$AE33-1200)))) | E33: =IF($AE33="","",IF($AE33<=1200,IF(INDEX(对接源_01水果!$C$4:$C$1203,$AE33)=0,"",INDEX(对接源_01水果!$C$4:$C$1203,$AE33)),IF(INDEX(对接源_02物料!$C$4:$C$1203,$AE33-1200)=0,"",INDEX(对接源_02物料!$C$4:$C$1203,$AE33-1200)))) | F33: =IF($AE33="","",IF($AE33<=1200,IF(INDEX(对接源_01水果!$W$4:$W$1203,$AE33)=0,"",INDEX(对接源_01水果!$W$4:$W$1203,$AE33)),IF(INDEX(对接源_02物料!$W$4:$W$1203,$AE33-1200)=0,"",INDEX(对接源_02物料!$W$4:$W$1203,$AE33-1200)))) | G33: =IF($AE33="","",IF($AE33<=1200,IF(INDEX(对接源_01水果!$D$4:$D$1203,$AE33)=0,"",INDEX(对接源_01水果!$D$4:$D$1203,$AE33)),IF(INDEX(对接源_02物料!$D$4:$D$1203,$AE33-1200)=0,"",INDEX(对接源_02物料!$D$4:$D$1203,$AE33-1200)))) | H33: =IF($AE33="","",IF($AE33<=1200,"01水果册","02物料册")) | I33: =IF($AE33="","",IF($AE33<=1200,IF(INDEX(对接源_01水果!$M$4:$M$1203,$AE33)=0,"",INDEX(对接源_01水果!$M$4:$M$1203,$AE33)),IF(INDEX(对接源_02物料!$M$4:$M$1203,$AE33-1200)=0,"",INDEX(对接源_02物料!$M$4:$M$1203,$AE33-1200)))) | AE33: =IFERROR(MATCH(28,_自动清单!$W$4:$W$2403,0),"")
A34: =IF($AE34="","",IF($AE34<=1200,IF(INDEX(对接源_01水果!$B$4:$B$1203,$AE34)=0,"",INDEX(对接源_01水果!$B$4:$B$1203,$AE34)),IF(INDEX(对接源_02物料!$B$4:$B$1203,$AE34-1200)=0,"",INDEX(对接源_02物料!$B$4:$B$1203,$AE34-1200)))) | B34: =IF($AE34="","",IF($AE34<=1200,IF(INDEX(对接源_01水果!$S$4:$S$1203,$AE34)=0,"",INDEX(对接源_01水果!$S$4:$S$1203,$AE34)),IF(INDEX(对接源_02物料!$S$4:$S$1203,$AE34-1200)=0,"",INDEX(对接源_02物料!$S$4:$S$1203,$AE34-1200)))) | C34: =IF($AE34="","",IF($AE34<=1200,IF(INDEX(对接源_01水果!$E$4:$E$1203,$AE34)=0,"",INDEX(对接源_01水果!$E$4:$E$1203,$AE34)),IF(INDEX(对接源_02物料!$E$4:$E$1203,$AE34-1200)=0,"",INDEX(对接源_02物料!$E$4:$E$1203,$AE34-1200)))) | D34: =IF($AE34="","",IF($AE34<=1200,IF(INDEX(对接源_01水果!$V$4:$V$1203,$AE34)=0,"",INDEX(对接源_01水果!$V$4:$V$1203,$AE34)),IF(INDEX(对接源_02物料!$V$4:$V$1203,$AE34-1200)=0,"",INDEX(对接源_02物料!$V$4:$V$1203,$AE34-1200)))) | E34: =IF($AE34="","",IF($AE34<=1200,IF(INDEX(对接源_01水果!$C$4:$C$1203,$AE34)=0,"",INDEX(对接源_01水果!$C$4:$C$1203,$AE34)),IF(INDEX(对接源_02物料!$C$4:$C$1203,$AE34-1200)=0,"",INDEX(对接源_02物料!$C$4:$C$1203,$AE34-1200)))) | F34: =IF($AE34="","",IF($AE34<=1200,IF(INDEX(对接源_01水果!$W$4:$W$1203,$AE34)=0,"",INDEX(对接源_01水果!$W$4:$W$1203,$AE34)),IF(INDEX(对接源_02物料!$W$4:$W$1203,$AE34-1200)=0,"",INDEX(对接源_02物料!$W$4:$W$1203,$AE34-1200)))) | G34: =IF($AE34="","",IF($AE34<=1200,IF(INDEX(对接源_01水果!$D$4:$D$1203,$AE34)=0,"",INDEX(对接源_01水果!$D$4:$D$1203,$AE34)),IF(INDEX(对接源_02物料!$D$4:$D$1203,$AE34-1200)=0,"",INDEX(对接源_02物料!$D$4:$D$1203,$AE34-1200)))) | H34: =IF($AE34="","",IF($AE34<=1200,"01水果册","02物料册")) | I34: =IF($AE34="","",IF($AE34<=1200,IF(INDEX(对接源_01水果!$M$4:$M$1203,$AE34)=0,"",INDEX(对接源_01水果!$M$4:$M$1203,$AE34)),IF(INDEX(对接源_02物料!$M$4:$M$1203,$AE34-1200)=0,"",INDEX(对接源_02物料!$M$4:$M$1203,$AE34-1200)))) | AE34: =IFERROR(MATCH(29,_自动清单!$W$4:$W$2403,0),"")
A35: =IF($AE35="","",IF($AE35<=1200,IF(INDEX(对接源_01水果!$B$4:$B$1203,$AE35)=0,"",INDEX(对接源_01水果!$B$4:$B$1203,$AE35)),IF(INDEX(对接源_02物料!$B$4:$B$1203,$AE35-1200)=0,"",INDEX(对接源_02物料!$B$4:$B$1203,$AE35-1200)))) | B35: =IF($AE35="","",IF($AE35<=1200,IF(INDEX(对接源_01水果!$S$4:$S$1203,$AE35)=0,"",INDEX(对接源_01水果!$S$4:$S$1203,$AE35)),IF(INDEX(对接源_02物料!$S$4:$S$1203,$AE35-1200)=0,"",INDEX(对接源_02物料!$S$4:$S$1203,$AE35-1200)))) | C35: =IF($AE35="","",IF($AE35<=1200,IF(INDEX(对接源_01水果!$E$4:$E$1203,$AE35)=0,"",INDEX(对接源_01水果!$E$4:$E$1203,$AE35)),IF(INDEX(对接源_02物料!$E$4:$E$1203,$AE35-1200)=0,"",INDEX(对接源_02物料!$E$4:$E$1203,$AE35-1200)))) | D35: =IF($AE35="","",IF($AE35<=1200,IF(INDEX(对接源_01水果!$V$4:$V$1203,$AE35)=0,"",INDEX(对接源_01水果!$V$4:$V$1203,$AE35)),IF(INDEX(对接源_02物料!$V$4:$V$1203,$AE35-1200)=0,"",INDEX(对接源_02物料!$V$4:$V$1203,$AE35-1200)))) | E35: =IF($AE35="","",IF($AE35<=1200,IF(INDEX(对接源_01水果!$C$4:$C$1203,$AE35)=0,"",INDEX(对接源_01水果!$C$4:$C$1203,$AE35)),IF(INDEX(对接源_02物料!$C$4:$C$1203,$AE35-1200)=0,"",INDEX(对接源_02物料!$C$4:$C$1203,$AE35-1200)))) | F35: =IF($AE35="","",IF($AE35<=1200,IF(INDEX(对接源_01水果!$W$4:$W$1203,$AE35)=0,"",INDEX(对接源_01水果!$W$4:$W$1203,$AE35)),IF(INDEX(对接源_02物料!$W$4:$W$1203,$AE35-1200)=0,"",INDEX(对接源_02物料!$W$4:$W$1203,$AE35-1200)))) | G35: =IF($AE35="","",IF($AE35<=1200,IF(INDEX(对接源_01水果!$D$4:$D$1203,$AE35)=0,"",INDEX(对接源_01水果!$D$4:$D$1203,$AE35)),IF(INDEX(对接源_02物料!$D$4:$D$1203,$AE35-1200)=0,"",INDEX(对接源_02物料!$D$4:$D$1203,$AE35-1200)))) | H35: =IF($AE35="","",IF($AE35<=1200,"01水果册","02物料册")) | I35: =IF($AE35="","",IF($AE35<=1200,IF(INDEX(对接源_01水果!$M$4:$M$1203,$AE35)=0,"",INDEX(对接源_01水果!$M$4:$M$1203,$AE35)),IF(INDEX(对接源_02物料!$M$4:$M$1203,$AE35-1200)=0,"",INDEX(对接源_02物料!$M$4:$M$1203,$AE35-1200)))) | AE35: =IFERROR(MATCH(30,_自动清单!$W$4:$W$2403,0),"")
A36: =IF($AE36="","",IF($AE36<=1200,IF(INDEX(对接源_01水果!$B$4:$B$1203,$AE36)=0,"",INDEX(对接源_01水果!$B$4:$B$1203,$AE36)),IF(INDEX(对接源_02物料!$B$4:$B$1203,$AE36-1200)=0,"",INDEX(对接源_02物料!$B$4:$B$1203,$AE36-1200)))) | B36: =IF($AE36="","",IF($AE36<=1200,IF(INDEX(对接源_01水果!$S$4:$S$1203,$AE36)=0,"",INDEX(对接源_01水果!$S$4:$S$1203,$AE36)),IF(INDEX(对接源_02物料!$S$4:$S$1203,$AE36-1200)=0,"",INDEX(对接源_02物料!$S$4:$S$1203,$AE36-1200)))) | C36: =IF($AE36="","",IF($AE36<=1200,IF(INDEX(对接源_01水果!$E$4:$E$1203,$AE36)=0,"",INDEX(对接源_01水果!$E$4:$E$1203,$AE36)),IF(INDEX(对接源_02物料!$E$4:$E$1203,$AE36-1200)=0,"",INDEX(对接源_02物料!$E$4:$E$1203,$AE36-1200)))) | D36: =IF($AE36="","",IF($AE36<=1200,IF(INDEX(对接源_01水果!$V$4:$V$1203,$AE36)=0,"",INDEX(对接源_01水果!$V$4:$V$1203,$AE36)),IF(INDEX(对接源_02物料!$V$4:$V$1203,$AE36-1200)=0,"",INDEX(对接源_02物料!$V$4:$V$1203,$AE36-1200)))) | E36: =IF($AE36="","",IF($AE36<=1200,IF(INDEX(对接源_01水果!$C$4:$C$1203,$AE36)=0,"",INDEX(对接源_01水果!$C$4:$C$1203,$AE36)),IF(INDEX(对接源_02物料!$C$4:$C$1203,$AE36-1200)=0,"",INDEX(对接源_02物料!$C$4:$C$1203,$AE36-1200)))) | F36: =IF($AE36="","",IF($AE36<=1200,IF(INDEX(对接源_01水果!$W$4:$W$1203,$AE36)=0,"",INDEX(对接源_01水果!$W$4:$W$1203,$AE36)),IF(INDEX(对接源_02物料!$W$4:$W$1203,$AE36-1200)=0,"",INDEX(对接源_02物料!$W$4:$W$1203,$AE36-1200)))) | G36: =IF($AE36="","",IF($AE36<=1200,IF(INDEX(对接源_01水果!$D$4:$D$1203,$AE36)=0,"",INDEX(对接源_01水果!$D$4:$D$1203,$AE36)),IF(INDEX(对接源_02物料!$D$4:$D$1203,$AE36-1200)=0,"",INDEX(对接源_02物料!$D$4:$D$1203,$AE36-1200)))) | H36: =IF($AE36="","",IF($AE36<=1200,"01水果册","02物料册")) | I36: =IF($AE36="","",IF($AE36<=1200,IF(INDEX(对接源_01水果!$M$4:$M$1203,$AE36)=0,"",INDEX(对接源_01水果!$M$4:$M$1203,$AE36)),IF(INDEX(对接源_02物料!$M$4:$M$1203,$AE36-1200)=0,"",INDEX(对接源_02物料!$M$4:$M$1203,$AE36-1200)))) | AE36: =IFERROR(MATCH(31,_自动清单!$W$4:$W$2403,0),"")
A37: =IF($AE37="","",IF($AE37<=1200,IF(INDEX(对接源_01水果!$B$4:$B$1203,$AE37)=0,"",INDEX(对接源_01水果!$B$4:$B$1203,$AE37)),IF(INDEX(对接源_02物料!$B$4:$B$1203,$AE37-1200)=0,"",INDEX(对接源_02物料!$B$4:$B$1203,$AE37-1200)))) | B37: =IF($AE37="","",IF($AE37<=1200,IF(INDEX(对接源_01水果!$S$4:$S$1203,$AE37)=0,"",INDEX(对接源_01水果!$S$4:$S$1203,$AE37)),IF(INDEX(对接源_02物料!$S$4:$S$1203,$AE37-1200)=0,"",INDEX(对接源_02物料!$S$4:$S$1203,$AE37-1200)))) | C37: =IF($AE37="","",IF($AE37<=1200,IF(INDEX(对接源_01水果!$E$4:$E$1203,$AE37)=0,"",INDEX(对接源_01水果!$E$4:$E$1203,$AE37)),IF(INDEX(对接源_02物料!$E$4:$E$1203,$AE37-1200)=0,"",INDEX(对接源_02物料!$E$4:$E$1203,$AE37-1200)))) | D37: =IF($AE37="","",IF($AE37<=1200,IF(INDEX(对接源_01水果!$V$4:$V$1203,$AE37)=0,"",INDEX(对接源_01水果!$V$4:$V$1203,$AE37)),IF(INDEX(对接源_02物料!$V$4:$V$1203,$AE37-1200)=0,"",INDEX(对接源_02物料!$V$4:$V$1203,$AE37-1200)))) | E37: =IF($AE37="","",IF($AE37<=1200,IF(INDEX(对接源_01水果!$C$4:$C$1203,$AE37)=0,"",INDEX(对接源_01水果!$C$4:$C$1203,$AE37)),IF(INDEX(对接源_02物料!$C$4:$C$1203,$AE37-1200)=0,"",INDEX(对接源_02物料!$C$4:$C$1203,$AE37-1200)))) | F37: =IF($AE37="","",IF($AE37<=1200,IF(INDEX(对接源_01水果!$W$4:$W$1203,$AE37)=0,"",INDEX(对接源_01水果!$W$4:$W$1203,$AE37)),IF(INDEX(对接源_02物料!$W$4:$W$1203,$AE37-1200)=0,"",INDEX(对接源_02物料!$W$4:$W$1203,$AE37-1200)))) | G37: =IF($AE37="","",IF($AE37<=1200,IF(INDEX(对接源_01水果!$D$4:$D$1203,$AE37)=0,"",INDEX(对接源_01水果!$D$4:$D$1203,$AE37)),IF(INDEX(对接源_02物料!$D$4:$D$1203,$AE37-1200)=0,"",INDEX(对接源_02物料!$D$4:$D$1203,$AE37-1200)))) | H37: =IF($AE37="","",IF($AE37<=1200,"01水果册","02物料册")) | I37: =IF($AE37="","",IF($AE37<=1200,IF(INDEX(对接源_01水果!$M$4:$M$1203,$AE37)=0,"",INDEX(对接源_01水果!$M$4:$M$1203,$AE37)),IF(INDEX(对接源_02物料!$M$4:$M$1203,$AE37-1200)=0,"",INDEX(对接源_02物料!$M$4:$M$1203,$AE37-1200)))) | AE37: =IFERROR(MATCH(32,_自动清单!$W$4:$W$2403,0),"")
A38: =IF($AE38="","",IF($AE38<=1200,IF(INDEX(对接源_01水果!$B$4:$B$1203,$AE38)=0,"",INDEX(对接源_01水果!$B$4:$B$1203,$AE38)),IF(INDEX(对接源_02物料!$B$4:$B$1203,$AE38-1200)=0,"",INDEX(对接源_02物料!$B$4:$B$1203,$AE38-1200)))) | B38: =IF($AE38="","",IF($AE38<=1200,IF(INDEX(对接源_01水果!$S$4:$S$1203,$AE38)=0,"",INDEX(对接源_01水果!$S$4:$S$1203,$AE38)),IF(INDEX(对接源_02物料!$S$4:$S$1203,$AE38-1200)=0,"",INDEX(对接源_02物料!$S$4:$S$1203,$AE38-1200)))) | C38: =IF($AE38="","",IF($AE38<=1200,IF(INDEX(对接源_01水果!$E$4:$E$1203,$AE38)=0,"",INDEX(对接源_01水果!$E$4:$E$1203,$AE38)),IF(INDEX(对接源_02物料!$E$4:$E$1203,$AE38-1200)=0,"",INDEX(对接源_02物料!$E$4:$E$1203,$AE38-1200)))) | D38: =IF($AE38="","",IF($AE38<=1200,IF(INDEX(对接源_01水果!$V$4:$V$1203,$AE38)=0,"",INDEX(对接源_01水果!$V$4:$V$1203,$AE38)),IF(INDEX(对接源_02物料!$V$4:$V$1203,$AE38-1200)=0,"",INDEX(对接源_02物料!$V$4:$V$1203,$AE38-1200)))) | E38: =IF($AE38="","",IF($AE38<=1200,IF(INDEX(对接源_01水果!$C$4:$C$1203,$AE38)=0,"",INDEX(对接源_01水果!$C$4:$C$1203,$AE38)),IF(INDEX(对接源_02物料!$C$4:$C$1203,$AE38-1200)=0,"",INDEX(对接源_02物料!$C$4:$C$1203,$AE38-1200)))) | F38: =IF($AE38="","",IF($AE38<=1200,IF(INDEX(对接源_01水果!$W$4:$W$1203,$AE38)=0,"",INDEX(对接源_01水果!$W$4:$W$1203,$AE38)),IF(INDEX(对接源_02物料!$W$4:$W$1203,$AE38-1200)=0,"",INDEX(对接源_02物料!$W$4:$W$1203,$AE38-1200)))) | G38: =IF($AE38="","",IF($AE38<=1200,IF(INDEX(对接源_01水果!$D$4:$D$1203,$AE38)=0,"",INDEX(对接源_01水果!$D$4:$D$1203,$AE38)),IF(INDEX(对接源_02物料!$D$4:$D$1203,$AE38-1200)=0,"",INDEX(对接源_02物料!$D$4:$D$1203,$AE38-1200)))) | H38: =IF($AE38="","",IF($AE38<=1200,"01水果册","02物料册")) | I38: =IF($AE38="","",IF($AE38<=1200,IF(INDEX(对接源_01水果!$M$4:$M$1203,$AE38)=0,"",INDEX(对接源_01水果!$M$4:$M$1203,$AE38)),IF(INDEX(对接源_02物料!$M$4:$M$1203,$AE38-1200)=0,"",INDEX(对接源_02物料!$M$4:$M$1203,$AE38-1200)))) | AE38: =IFERROR(MATCH(33,_自动清单!$W$4:$W$2403,0),"")
A39: =IF($AE39="","",IF($AE39<=1200,IF(INDEX(对接源_01水果!$B$4:$B$1203,$AE39)=0,"",INDEX(对接源_01水果!$B$4:$B$1203,$AE39)),IF(INDEX(对接源_02物料!$B$4:$B$1203,$AE39-1200)=0,"",INDEX(对接源_02物料!$B$4:$B$1203,$AE39-1200)))) | B39: =IF($AE39="","",IF($AE39<=1200,IF(INDEX(对接源_01水果!$S$4:$S$1203,$AE39)=0,"",INDEX(对接源_01水果!$S$4:$S$1203,$AE39)),IF(INDEX(对接源_02物料!$S$4:$S$1203,$AE39-1200)=0,"",INDEX(对接源_02物料!$S$4:$S$1203,$AE39-1200)))) | C39: =IF($AE39="","",IF($AE39<=1200,IF(INDEX(对接源_01水果!$E$4:$E$1203,$AE39)=0,"",INDEX(对接源_01水果!$E$4:$E$1203,$AE39)),IF(INDEX(对接源_02物料!$E$4:$E$1203,$AE39-1200)=0,"",INDEX(对接源_02物料!$E$4:$E$1203,$AE39-1200)))) | D39: =IF($AE39="","",IF($AE39<=1200,IF(INDEX(对接源_01水果!$V$4:$V$1203,$AE39)=0,"",INDEX(对接源_01水果!$V$4:$V$1203,$AE39)),IF(INDEX(对接源_02物料!$V$4:$V$1203,$AE39-1200)=0,"",INDEX(对接源_02物料!$V$4:$V$1203,$AE39-1200)))) | E39: =IF($AE39="","",IF($AE39<=1200,IF(INDEX(对接源_01水果!$C$4:$C$1203,$AE39)=0,"",INDEX(对接源_01水果!$C$4:$C$1203,$AE39)),IF(INDEX(对接源_02物料!$C$4:$C$1203,$AE39-1200)=0,"",INDEX(对接源_02物料!$C$4:$C$1203,$AE39-1200)))) | F39: =IF($AE39="","",IF($AE39<=1200,IF(INDEX(对接源_01水果!$W$4:$W$1203,$AE39)=0,"",INDEX(对接源_01水果!$W$4:$W$1203,$AE39)),IF(INDEX(对接源_02物料!$W$4:$W$1203,$AE39-1200)=0,"",INDEX(对接源_02物料!$W$4:$W$1203,$AE39-1200)))) | G39: =IF($AE39="","",IF($AE39<=1200,IF(INDEX(对接源_01水果!$D$4:$D$1203,$AE39)=0,"",INDEX(对接源_01水果!$D$4:$D$1203,$AE39)),IF(INDEX(对接源_02物料!$D$4:$D$1203,$AE39-1200)=0,"",INDEX(对接源_02物料!$D$4:$D$1203,$AE39-1200)))) | H39: =IF($AE39="","",IF($AE39<=1200,"01水果册","02物料册")) | I39: =IF($AE39="","",IF($AE39<=1200,IF(INDEX(对接源_01水果!$M$4:$M$1203,$AE39)=0,"",INDEX(对接源_01水果!$M$4:$M$1203,$AE39)),IF(INDEX(对接源_02物料!$M$4:$M$1203,$AE39-1200)=0,"",INDEX(对接源_02物料!$M$4:$M$1203,$AE39-1200)))) | AE39: =IFERROR(MATCH(34,_自动清单!$W$4:$W$2403,0),"")
A40: =IF($AE40="","",IF($AE40<=1200,IF(INDEX(对接源_01水果!$B$4:$B$1203,$AE40)=0,"",INDEX(对接源_01水果!$B$4:$B$1203,$AE40)),IF(INDEX(对接源_02物料!$B$4:$B$1203,$AE40-1200)=0,"",INDEX(对接源_02物料!$B$4:$B$1203,$AE40-1200)))) | B40: =IF($AE40="","",IF($AE40<=1200,IF(INDEX(对接源_01水果!$S$4:$S$1203,$AE40)=0,"",INDEX(对接源_01水果!$S$4:$S$1203,$AE40)),IF(INDEX(对接源_02物料!$S$4:$S$1203,$AE40-1200)=0,"",INDEX(对接源_02物料!$S$4:$S$1203,$AE40-1200)))) | C40: =IF($AE40="","",IF($AE40<=1200,IF(INDEX(对接源_01水果!$E$4:$E$1203,$AE40)=0,"",INDEX(对接源_01水果!$E$4:$E$1203,$AE40)),IF(INDEX(对接源_02物料!$E$4:$E$1203,$AE40-1200)=0,"",INDEX(对接源_02物料!$E$4:$E$1203,$AE40-1200)))) | D40: =IF($AE40="","",IF($AE40<=1200,IF(INDEX(对接源_01水果!$V$4:$V$1203,$AE40)=0,"",INDEX(对接源_01水果!$V$4:$V$1203,$AE40)),IF(INDEX(对接源_02物料!$V$4:$V$1203,$AE40-1200)=0,"",INDEX(对接源_02物料!$V$4:$V$1203,$AE40-1200)))) | E40: =IF($AE40="","",IF($AE40<=1200,IF(INDEX(对接源_01水果!$C$4:$C$1203,$AE40)=0,"",INDEX(对接源_01水果!$C$4:$C$1203,$AE40)),IF(INDEX(对接源_02物料!$C$4:$C$1203,$AE40-1200)=0,"",INDEX(对接源_02物料!$C$4:$C$1203,$AE40-1200)))) | F40: =IF($AE40="","",IF($AE40<=1200,IF(INDEX(对接源_01水果!$W$4:$W$1203,$AE40)=0,"",INDEX(对接源_01水果!$W$4:$W$1203,$AE40)),IF(INDEX(对接源_02物料!$W$4:$W$1203,$AE40-1200)=0,"",INDEX(对接源_02物料!$W$4:$W$1203,$AE40-1200)))) | G40: =IF($AE40="","",IF($AE40<=1200,IF(INDEX(对接源_01水果!$D$4:$D$1203,$AE40)=0,"",INDEX(对接源_01水果!$D$4:$D$1203,$AE40)),IF(INDEX(对接源_02物料!$D$4:$D$1203,$AE40-1200)=0,"",INDEX(对接源_02物料!$D$4:$D$1203,$AE40-1200)))) | H40: =IF($AE40="","",IF($AE40<=1200,"01水果册","02物料册")) | I40: =IF($AE40="","",IF($AE40<=1200,IF(INDEX(对接源_01水果!$M$4:$M$1203,$AE40)=0,"",INDEX(对接源_01水果!$M$4:$M$1203,$AE40)),IF(INDEX(对接源_02物料!$M$4:$M$1203,$AE40-1200)=0,"",INDEX(对接源_02物料!$M$4:$M$1203,$AE40-1200)))) | AE40: =IFERROR(MATCH(35,_自动清单!$W$4:$W$2403,0),"")
