Workbook

Sheet 使用说明
A1: 更多财务实操模板，可自行搜索抖音/视频号：老财务的实操笔记
A3: 【老财务实操自用｜初级版财务台账模板】
A4: 作者：老财务的实操笔记
A5: ——————————————————————————
A6: 适用对象：小微企业、个体工商户、小规模纳税人、商贸服务类等
A7: 版本说明
A8: 本套为**通用基础初级版**，满足税务管理、费用报销、收支登记、票据管理等
A9: 可根据行业属性、业务规模、升级定制版。
A11: 模板清单，持续更新
A12: 1、应收账款风险预警表
A13: 2、日常经营情况汇总表
A14: 3、进项台帐自动查重表
... A47: 老财务自用模板｜禁止外传、倒卖、商用

Sheet 基础资料
A1: 账户 | B1: 产品 | C1: 支出类别 | E1: 客户 | G1: 供应商
A2: 现金 | B2: 红曲 | C2: 供应商 | E2: 丁爱妹 | G2: 羊奶供货商
A3: 微信 | B3: 胚脑 | E3: 方建宏 | G3: 乳铁供货商
A4: 支付宝 | B4: 胚优 | C4: 办公费 | E4: 傅荣姣
A5: 杭州 | B5: 乳铁 | C5: 水费 | E5: 郭志伟
A6: 农商 | B6: 羊奶 | C6: 电费 | E6: 过承祁
A7: 备用 | B7: 益生菌 | C7: 伙食费 | E7: 洪宗邦
A8: 备用1 | C8: 工资 | E8: 姜蓉兰
A9: 备用2 | C9: 租赁费 | E9: 姜志鸿
A10: 备用3 | C10: 差旅费 | E10: 李小琴
A11: 备用4 | C11: 业务招待费 | E11: 李晓春
A12: 备用5 | C12: 车辆费用 | E12: 李玉娟
A13: 备用6 | C13: 银行手续费 | E13: 林永来
A14: 备用7 | E14: 陆玉英
A15: 备用8 | E15: 罗理华
E16: 马珍珠
E17: 邵国新
E18: 沈祖模
E19: 唐鑫红
E20: 童炳寿
E21: 王秀娟
E22: 邬香花
E23: 吴亮
E24: 吴旭红
E25: 吴兆香
E26: 谢爱琴
E27: 徐德彪
... E38: 杨建云

Sheet 数据录入
A1: 多帐户收支登记表
F2: 收入总额 | G2: 支出总额 | H2: 账户余额
F3: =SUBTOTAL(109,$F$4:$F$9999) | G3: =SUBTOTAL(109,$G$4:$G$9999) | H3: =SUBTOTAL(109,$H$5:$H$18)+F3-G3
A4: 序号 | B4: 日期 | C4: 公司账户 | D4: 支出类别 | E4: 摘要内容 | F4: 收入 | G4: 支出 | H4: 账户余额 | I4: 产品 | J4: 客户 | K4: 供应商 | L4: 客户生日 | M4: 月份
A5: =IF(B5="","",COUNTA($B$5:B5)) | B5: 46266 | C5: 现金 | E5: 期初余额 | H5: 0 | M5: =IF($B5="","",--TEXT($B5,"yyyymm"))
A6: =IF(B6="","",COUNTA($B$5:B6)) | B6: 46266 | C6: 微信 | E6: 期初余额 | H6: 0 | M6: =IF($B6="","",--TEXT($B6,"yyyymm"))
A7: =IF(B7="","",COUNTA($B$5:B7)) | B7: 46266 | C7: 支付宝 | E7: 期初余额 | H7: 0 | M7: =IF($B7="","",--TEXT($B7,"yyyymm"))
A8: =IF(B8="","",COUNTA($B$5:B8)) | B8: 46266 | C8: 杭州 | E8: 期初余额 | H8: 0 | M8: =IF($B8="","",--TEXT($B8,"yyyymm"))
A9: =IF(B9="","",COUNTA($B$5:B9)) | B9: 46266 | C9: 农商 | E9: 期初余额 | H9: 0 | M9: =IF($B9="","",--TEXT($B9,"yyyymm"))
A10: =IF(B10="","",COUNTA($B$5:B10)) | B10: 46266 | C10: 备用 | E10: 期初余额 | H10: 0 | M10: =IF($B10="","",--TEXT($B10,"yyyymm"))
A11: =IF(B11="","",COUNTA($B$5:B11)) | B11: 46266 | C11: 备用1 | E11: 期初余额 | H11: 0 | M11: =IF($B11="","",--TEXT($B11,"yyyymm"))
A12: =IF(B12="","",COUNTA($B$5:B12)) | B12: 46266 | C12: 备用2 | E12: 期初余额 | H12: 0 | M12: =IF($B12="","",--TEXT($B12,"yyyymm"))
A13: =IF(B13="","",COUNTA($B$5:B13)) | B13: 46266 | C13: 备用3 | E13: 期初余额 | H13: 0 | M13: =IF($B13="","",--TEXT($B13,"yyyymm"))
A14: =IF(B14="","",COUNTA($B$5:B14)) | B14: 46266 | C14: 备用4 | E14: 期初余额 | H14: 0 | M14: =IF($B14="","",--TEXT($B14,"yyyymm"))
A15: =IF(B15="","",COUNTA($B$5:B15)) | B15: 46266 | C15: 备用5 | E15: 期初余额 | H15: 0 | M15: =IF($B15="","",--TEXT($B15,"yyyymm"))
A16: =IF(B16="","",COUNTA($B$5:B16)) | B16: 46266 | C16: 备用6 | E16: 期初余额 | H16: 0 | M16: =IF($B16="","",--TEXT($B16,"yyyymm"))
... A18: =IF(B18="","",COUNTA($B$5:B18)) | B18: 46266 | C18: 备用8 | E18: 期初余额 | H18: 0 | M18: =IF($B18="","",--TEXT($B18,"yyyymm"))
A19: =IF(B19="","",COUNTA($B$5:B19)) | B19: 46266 | C19: 现金 | F19: 2000 | H19: =IFERROR(VLOOKUP($C19,$C$5:$H$18,6,0)+SUMIF($C$19:$C19,$C19,$F$19:$F19)-SUMIF($C$19:$C19,$C19,$G$19:$G19),"") | I19: 红曲 | J19: 丁爱妹 | M19: =IF($B19="","",--TEXT($B19,"yyyymm"))
A20: =IF(B20="","",COUNTA($B$5:B20)) | B20: 46266 | C20: 微信 | D20: 办公费 | G20: 200 | H20: =IFERROR(VLOOKUP($C20,$C$5:$H$18,6,0)+SUMIF($C$19:$C20,$C20,$F$19:$F20)-SUMIF($C$19:$C20,$C20,$G$19:$G20),"") | M20: =IF($B20="","",--TEXT($B20,"yyyymm"))
A21: =IF(B21="","",COUNTA($B$5:B21)) | B21: 46266 | C21: 支付宝 | D21: 电费 | G21: 300 | H21: =IFERROR(VLOOKUP($C21,$C$5:$H$18,6,0)+SUMIF($C$19:$C21,$C21,$F$19:$F21)-SUMIF($C$19:$C21,$C21,$G$19:$G21),"") | M21: =IF($B21="","",--TEXT($B21,"yyyymm"))
A22: =IF(B22="","",COUNTA($B$5:B22)) | B22: 46266 | C22: 杭州 | D22: 差旅费 | G22: 500 | H22: =IFERROR(VLOOKUP($C22,$C$5:$H$18,6,0)+SUMIF($C$19:$C22,$C22,$F$19:$F22)-SUMIF($C$19:$C22,$C22,$G$19:$G22),"") | M22: =IF($B22="","",--TEXT($B22,"yyyymm"))
A23: =IF(B23="","",COUNTA($B$5:B23)) | B23: 46266 | C23: 农商 | F23: 2600 | H23: =IFERROR(VLOOKUP($C23,$C$5:$H$18,6,0)+SUMIF($C$19:$C23,$C23,$F$19:$F23)-SUMIF($C$19:$C23,$C23,$G$19:$G23),"") | M23: =IF($B23="","",--TEXT($B23,"yyyymm"))
A24: =IF(B24="","",COUNTA($B$5:B24)) | B24: 46266 | C24: 备用 | D24: 供应商 | G24: 5000 | H24: =IFERROR(VLOOKUP($C24,$C$5:$H$18,6,0)+SUMIF($C$19:$C24,$C24,$F$19:$F24)-SUMIF($C$19:$C24,$C24,$G$19:$G24),"") | K24: 羊奶供货商 | M24: =IF($B24="","",--TEXT($B24,"yyyymm"))
A25: =IF(B25="","",COUNTA($B$5:B25)) | B25: 46266 | C25: 备用1 | D25: 伙食费 | G25: 200 | H25: =IFERROR(VLOOKUP($C25,$C$5:$H$18,6,0)+SUMIF($C$19:$C25,$C25,$F$19:$F25)-SUMIF($C$19:$C25,$C25,$G$19:$G25),"") | M25: =IF($B25="","",--TEXT($B25,"yyyymm"))
A26: =IF(B26="","",COUNTA($B$5:B26)) | B26: 46266 | C26: 备用2 | D26: 办公费 | G26: 10 | H26: =IFERROR(VLOOKUP($C26,$C$5:$H$18,6,0)+SUMIF($C$19:$C26,$C26,$F$19:$F26)-SUMIF($C$19:$C26,$C26,$G$19:$G26),"") | M26: =IF($B26="","",--TEXT($B26,"yyyymm"))
A27: =IF(B27="","",COUNTA($B$5:B27)) | B27: 46266 | C27: 备用3 | D27: 车辆费用 | G27: 50 | H27: =IFERROR(VLOOKUP($C27,$C$5:$H$18,6,0)+SUMIF($C$19:$C27,$C27,$F$19:$F27)-SUMIF($C$19:$C27,$C27,$G$19:$G27),"") | M27: =IF($B27="","",--TEXT($B27,"yyyymm"))
A28: =IF(B28="","",COUNTA($B$5:B28)) | B28: 46266 | C28: 备用4 | F28: 2100 | H28: =IFERROR(VLOOKUP($C28,$C$5:$H$18,6,0)+SUMIF($C$19:$C28,$C28,$F$19:$F28)-SUMIF($C$19:$C28,$C28,$G$19:$G28),"") | M28: =IF($B28="","",--TEXT($B28,"yyyymm"))
A29: =IF(B29="","",COUNTA($B$5:B29)) | B29: 46266 | C29: 备用5 | D29: 租赁费 | G29: 2000 | H29: =IFERROR(VLOOKUP($C29,$C$5:$H$18,6,0)+SUMIF($C$19:$C29,$C29,$F$19:$F29)-SUMIF($C$19:$C29,$C29,$G$19:$G29),"") | M29: =IF($B29="","",--TEXT($B29,"yyyymm"))
A30: =IF(B30="","",COUNTA($B$5:B30)) | B30: 46266 | C30: 备用6 | D30: 伙食费 | G30: 200 | H30: =IFERROR(VLOOKUP($C30,$C$5:$H$18,6,0)+SUMIF($C$19:$C30,$C30,$F$19:$F30)-SUMIF($C$19:$C30,$C30,$G$19:$G30),"") | M30: =IF($B30="","",--TEXT($B30,"yyyymm"))
A31: =IF(B31="","",COUNTA($B$5:B31)) | B31: 46266 | C31: 备用7 | D31: 差旅费 | G31: 500 | H31: =IFERROR(VLOOKUP($C31,$C$5:$H$18,6,0)+SUMIF($C$19:$C31,$C31,$F$19:$F31)-SUMIF($C$19:$C31,$C31,$G$19:$G31),"") | M31: =IF($B31="","",--TEXT($B31,"yyyymm"))
A32: =IF(B32="","",COUNTA($B$5:B32)) | B32: 46266 | C32: 备用8 | D32: 供应商 | G32: 1000 | H32: =IFERROR(VLOOKUP($C32,$C$5:$H$18,6,0)+SUMIF($C$19:$C32,$C32,$F$19:$F32)-SUMIF($C$19:$C32,$C32,$G$19:$G32),"") | M32: =IF($B32="","",--TEXT($B32,"yyyymm"))
A33: =IF(B33="","",COUNTA($B$5:B33)) | B33: 46266 | C33: 现金 | D33: 业务招待费 | G33: 200 | H33: =IFERROR(VLOOKUP($C33,$C$5:$H$18,6,0)+SUMIF($C$19:$C33,$C33,$F$19:$F33)-SUMIF($C$19:$C33,$C33,$G$19:$G33),"") | M33: =IF($B33="","",--TEXT($B33,"yyyymm"))
A34: =IF(B34="","",COUNTA($B$5:B34)) | B34: 46266 | C34: 微信 | D34: 车辆费用 | G34: 500 | H34: =IFERROR(VLOOKUP($C34,$C$5:$H$18,6,0)+SUMIF($C$19:$C34,$C34,$F$19:$F34)-SUMIF($C$19:$C34,$C34,$G$19:$G34),"") | M34: =IF($B34="","",--TEXT($B34,"yyyymm"))
A35: =IF(B35="","",COUNTA($B$5:B35)) | B35: 46266 | C35: 支付宝 | D35: 伙食费 | G35: 500 | H35: =IFERROR(VLOOKUP($C35,$C$5:$H$18,6,0)+SUMIF($C$19:$C35,$C35,$F$19:$F35)-SUMIF($C$19:$C35,$C35,$G$19:$G35),"") | M35: =IF($B35="","",--TEXT($B35,"yyyymm"))
A36: =IF(B36="","",COUNTA($B$5:B36)) | B36: 46266 | C36: 杭州 | F36: 5000 | H36: =IFERROR(VLOOKUP($C36,$C$5:$H$18,6,0)+SUMIF($C$19:$C36,$C36,$F$19:$F36)-SUMIF($C$19:$C36,$C36,$G$19:$G36),"") | M36: =IF($B36="","",--TEXT($B36,"yyyymm"))
A37: =IF(B37="","",COUNTA($B$5:B37)) | B37: 46266 | C37: 农商 | F37: 500 | H37: =IFERROR(VLOOKUP($C37,$C$5:$H$18,6,0)+SUMIF($C$19:$C37,$C37,$F$19:$F37)-SUMIF($C$19:$C37,$C37,$G$19:$G37),"") | M37: =IF($B37="","",--TEXT($B37,"yyyymm"))
A38: =IF(B38="","",COUNTA($B$5:B38)) | B38: 46266 | C38: 备用 | D38: 电费 | G38: 500 | H38: =IFERROR(VLOOKUP($C38,$C$5:$H$18,6,0)+SUMIF($C$19:$C38,$C38,$F$19:$F38)-SUMIF($C$19:$C38,$C38,$G$19:$G38),"") | M38: =IF($B38="","",--TEXT($B38,"yyyymm"))
A39: =IF(B39="","",COUNTA($B$5:B39)) | B39: 46266 | C39: 备用1 | F39: 10000 | H39: =IFERROR(VLOOKUP($C39,$C$5:$H$18,6,0)+SUMIF($C$19:$C39,$C39,$F$19:$F39)-SUMIF($C$19:$C39,$C39,$G$19:$G39),"") | M39: =IF($B39="","",--TEXT($B39,"yyyymm"))
A40: =IF(B40="","",COUNTA($B$5:B40)) | B40: 46266 | C40: 备用2 | E40: 工行转民生 | F40: 1000 | H40: =IFERROR(VLOOKUP($C40,$C$5:$H$18,6,0)+SUMIF($C$19:$C40,$C40,$F$19:$F40)-SUMIF($C$19:$C40,$C40,$G$19:$G40),"") | M40: =IF($B40="","",--TEXT($B40,"yyyymm"))
A41: =IF(B41="","",COUNTA($B$5:B41)) | B41: 46266 | C41: 备用3 | E41: 工行转民生 | F41: -1000 | H41: =IFERROR(VLOOKUP($C41,$C$5:$H$18,6,0)+SUMIF($C$19:$C41,$C41,$F$19:$F41)-SUMIF($C$19:$C41,$C41,$G$19:$G41),"") | M41: =IF($B41="","",--TEXT($B41,"yyyymm"))
A42: =IF(B42="","",COUNTA($B$5:B42)) | H42: =IFERROR(VLOOKUP($C42,$C$5:$H$18,6,0)+SUMIF($C$19:$C42,$C42,$F$19:$F42)-SUMIF($C$19:$C42,$C42,$G$19:$G42),"") | M42: =IF($B42="","",--TEXT($B42,"yyyymm"))
A43: =IF(B43="","",COUNTA($B$5:B43)) | H43: =IFERROR(VLOOKUP($C43,$C$5:$H$18,6,0)+SUMIF($C$19:$C43,$C43,$F$19:$F43)-SUMIF($C$19:$C43,$C43,$G$19:$G43),"") | M43: =IF($B43="","",--TEXT($B43,"yyyymm"))
A44: =IF(B44="","",COUNTA($B$5:B44)) | H44: =IFERROR(VLOOKUP($C44,$C$5:$H$18,6,0)+SUMIF($C$19:$C44,$C44,$F$19:$F44)-SUMIF($C$19:$C44,$C44,$G$19:$G44),"") | M44: =IF($B44="","",--TEXT($B44,"yyyymm"))
A45: =IF(B45="","",COUNTA($B$5:B45)) | H45: =IFERROR(VLOOKUP($C45,$C$5:$H$18,6,0)+SUMIF($C$19:$C45,$C45,$F$19:$F45)-SUMIF($C$19:$C45,$C45,$G$19:$G45),"") | M45: =IF($B45="","",--TEXT($B45,"yyyymm"))
A46: =IF(B46="","",COUNTA($B$5:B46)) | H46: =IFERROR(VLOOKUP($C46,$C$5:$H$18,6,0)+SUMIF($C$19:$C46,$C46,$F$19:$F46)-SUMIF($C$19:$C46,$C46,$G$19:$G46),"") | M46: =IF($B46="","",--TEXT($B46,"yyyymm"))
A47: =IF(B47="","",COUNTA($B$5:B47)) | H47: =IFERROR(VLOOKUP($C47,$C$5:$H$18,6,0)+SUMIF($C$19:$C47,$C47,$F$19:$F47)-SUMIF($C$19:$C47,$C47,$G$19:$G47),"") | M47: =IF($B47="","",--TEXT($B47,"yyyymm"))
A48: =IF(B48="","",COUNTA($B$5:B48)) | H48: =IFERROR(VLOOKUP($C48,$C$5:$H$18,6,0)+SUMIF($C$19:$C48,$C48,$F$19:$F48)-SUMIF($C$19:$C48,$C48,$G$19:$G48),"") | M48: =IF($B48="","",--TEXT($B48,"yyyymm"))
A49: =IF(B49="","",COUNTA($B$5:B49)) | H49: =IFERROR(VLOOKUP($C49,$C$5:$H$18,6,0)+SUMIF($C$19:$C49,$C49,$F$19:$F49)-SUMIF($C$19:$C49,$C49,$G$19:$G49),"") | M49: =IF($B49="","",--TEXT($B49,"yyyymm"))
A50: =IF(B50="","",COUNTA($B$5:B50)) | H50: =IFERROR(VLOOKUP($C50,$C$5:$H$18,6,0)+SUMIF($C$19:$C50,$C50,$F$19:$F50)-SUMIF($C$19:$C50,$C50,$G$19:$G50),"") | M50: =IF($B50="","",--TEXT($B50,"yyyymm"))
A51: =IF(B51="","",COUNTA($B$5:B51)) | H51: =IFERROR(VLOOKUP($C51,$C$5:$H$18,6,0)+SUMIF($C$19:$C51,$C51,$F$19:$F51)-SUMIF($C$19:$C51,$C51,$G$19:$G51),"") | M51: =IF($B51="","",--TEXT($B51,"yyyymm"))
A52: =IF(B52="","",COUNTA($B$5:B52)) | H52: =IFERROR(VLOOKUP($C52,$C$5:$H$18,6,0)+SUMIF($C$19:$C52,$C52,$F$19:$F52)-SUMIF($C$19:$C52,$C52,$G$19:$G52),"") | M52: =IF($B52="","",--TEXT($B52,"yyyymm"))
A53: =IF(B53="","",COUNTA($B$5:B53)) | H53: =IFERROR(VLOOKUP($C53,$C$5:$H$18,6,0)+SUMIF($C$19:$C53,$C53,$F$19:$F53)-SUMIF($C$19:$C53,$C53,$G$19:$G53),"") | M53: =IF($B53="","",--TEXT($B53,"yyyymm"))
... A4999: =IF(B4999="","",COUNTA($B$5:B4999)) | H4999: =IFERROR(VLOOKUP($C4999,$C$5:$H$18,6,0)+SUMIF($C$19:$C4999,$C4999,$F$19:$F4999)-SUMIF($C$19:$C4999,$C4999,$G$19:$G4999),"") | M4999: =IF($B4999="","",--TEXT($B4999,"yyyymm"))

Sheet 往来款跟进
A2: 填写说明：淡黄色格子是你要填的 —— 日期、客户名称、销售产品、销售金额、销售费用(赠送券)、支付方式、备注，以及右边应付侧的供货商、购货款。 淡灰色格子全部自动算，不要手动改：已收款、尚欠款、未收总计、已付款、尚欠款总计。 「已收款」「已付款」自动从【数据录入】取：在数据录入里按日记流水记账时，把「客户」或「供应商」那一列选上，这里就自动认领。 数据录入里还没记到某个客户的回款之前，这里沿用你原来手工填的数（存在隐藏的 T 列），最右边「核对」列会提示是哪一种。 | L2: 总销售金额 | M2: =ROUND(SUM($F$11:$F$510),2) | N2: 应收账款 | O2: 应收款项 | P2: =ROUND(SUM($F$11:$F$510)-SUM($J$11:$J$510),2) | Q2: 应付账款 | R2: 购货款 | S2: =ROUND(SUM($O$11:$O$510),2)
L3: 购货款 | M3: =ROUND(SUM($O$11:$O$510),2) | O3: 已收款 | P3: =ROUND(SUM($G$11:$G$510),2) | R3: 已付款 | S3: =ROUND(SUM($P$11:$P$510),2)
L4: 销售费用 | M4: =ROUND(SUM($J$11:$J$510),2) | O4: 尚欠款 | P4: =ROUND($P$2-$P$3,2) | R4: 尚欠款 | S4: =ROUND($S$2-$S$3,2)
L5: 毛 利 | M5: =ROUND($M$2-$M$3-$M$4,2) | R5: 应收-应付 | S5: =ROUND($P$4-$S$4,2)
A8: 单位名称：百跃羊奶 | S8: 单位：元
A9: 序号 | B9: 日期 | C9: 客户生日 | D9: 应收账款 | M9: 应付账款 | T9: 已收款 (原手工记录) | U9: 本行应收 | V9: 同客户累计应收 | W9: 该客户回款·数据录入 | X9: 已付款 (原手工记录) | Y9: 同供货商累计购货 | Z9: 该供货商付款·数据录入 | AA9: 核 对
D10: 客户名称 | E10: 销售产品 | F10: 销售金额 | G10: 已收款 | H10: 尚欠款 | I10: 未收总计 | J10: 销售费用 | K10: 支付方式 | L10: 备注 | M10: 日期 | N10: 供货商 | O10: 购货款 | P10: 已付款 | Q10: 尚欠款 | R10: 尚欠款总计 | S10: 备注 | T10: 你原来手工填在「已收款」里的数。 数据录入里还没记这个客户的回款时，左边就用这个数顶着。 | U10: 销售金额 − 销售费用 | V10: 这个客户到本行为止一共该收多少 | W10: 从【数据录入】按客户名汇总的收入 | X10: 同上，应付侧的手工备份 | Y10: 同供货商累计购货 | Z10: 从【数据录入】按供货商汇总的支出 | AA10: 这一行有没有填错、名字对不对得上
A11: =IF(AND($D11="",$N11=""),"",MAX($A$10:A10)+1) | B11: 46269 | C11: 46113 | D11: 沈祖模 | E11: 羊奶 | F11: 3280 | G11: =IF($D11="","",IF(COUNTIF(数据录入!$J$5:$J$4999,$D11)=0,N($T11),ROUND(MIN(MAX(0,N($W11)-(N($V11)-N($U11))),N($U11)),2))) | H11: =IF($D11="","",ROUND(N($F11)-N($G11)-N($J11),2)) | I11: =IF($D11="","",ROUND(SUM($H$11:H11),2)) | J11: 0 | K11: 支付宝 | L11: 货款 | M11: 43971 | N11: 羊奶供货商 | P11: =IF($N11="","",IF(COUNTIF(数据录入!$K$5:$K$4999,$N11)=0,N($X11),ROUND(MIN(MAX(0,N($Z11)-(N($Y11)-N($O11))),N($O11)),2))) | Q11: =IF($N11="","",ROUND(N($O11)-N($P11),2)) | R11: =IF($N11="","",ROUND(SUM($Q$11:Q11),2)) | S11: 采购 | T11: 3280 | U11: =IF($D11="","",ROUND(N($F11)-N($J11),2)) | V11: =IF($D11="","",ROUND(SUMIFS($F$11:F11,$D$11:D11,$D11)-SUMIFS($J$11:J11,$D$11:D11,$D11),2)) | W11: =IF($D11="","",ROUND(SUMIFS(数据录入!$F$5:$F$4999,数据录入!$J$5:$J$4999,$D11),2)) | Y11: =IF($N11="","",ROUND(SUMIFS($O$11:O11,$N$11:N11,$N11),2)) | Z11: =IF($N11="","",ROUND(SUMIFS(数据录入!$G$5:$G$4999,数据录入!$K$5:$K$4999,$N11),2)) | AA11: =IF(AND($D11="",$N11=""),"",IF(AND($D11<>"",COUNTIF(基础资料!$E:$E,$D11)=0),"客户名不在基础资料里",IF(AND($E11<>"",COUNTIF(基础资料!$B:$B,$E11)=0),"产品名不在基础资料里",IF(AND($N11<>"",COUNTIF(基础资料!$G:$G,$N11)=0),"供货商不在基础资料里",IF(AND($C11<>"",ISNUMBER($C11),$C11<10000),"客户生日填得不对（不是日期）",IF(N($J11)>N($F11),"销售费用大于销售金额",IF(AND($D11<>"",COUNTIF(数据录入!$J$5:$J$4999,$D11)=0,N($T11)<>0),"用的还是原手工已收款",IF(AND($D11<>"",COUNTIF(数据录入!$J$5:$J$4999,$D11)>0,ROUND(N($G11)-N($T11),2)<>0,N($T11)<>0),"自动算的已收款和原手工数对不上","√"))))))))
A12: =IF(AND($D12="",$N12=""),"",MAX($A$10:A11)+1) | B12: 46269 | C12: 46113 | D12: 沈祖模 | E12: 乳铁蛋白 | F12: 3980 | G12: =IF($D12="","",IF(COUNTIF(数据录入!$J$5:$J$4999,$D12)=0,N($T12),ROUND(MIN(MAX(0,N($W12)-(N($V12)-N($U12))),N($U12)),2))) | H12: =IF($D12="","",ROUND(N($F12)-N($G12)-N($J12),2)) | I12: =IF($D12="","",ROUND(SUM($H$11:H12),2)) | J12: 0 | K12: 支付宝 | L12: 货款 | N12: 乳铁供货商 | P12: =IF($N12="","",IF(COUNTIF(数据录入!$K$5:$K$4999,$N12)=0,N($X12),ROUND(MIN(MAX(0,N($Z12)-(N($Y12)-N($O12))),N($O12)),2))) | Q12: =IF($N12="","",ROUND(N($O12)-N($P12),2)) | R12: =IF($N12="","",ROUND(SUM($Q$11:Q12),2)) | S12: 采购 | T12: 3980 | U12: =IF($D12="","",ROUND(N($F12)-N($J12),2)) | V12: =IF($D12="","",ROUND(SUMIFS($F$11:F12,$D$11:D12,$D12)-SUMIFS($J$11:J12,$D$11:D12,$D12),2)) | W12: =IF($D12="","",ROUND(SUMIFS(数据录入!$F$5:$F$4999,数据录入!$J$5:$J$4999,$D12),2)) | Y12: =IF($N12="","",ROUND(SUMIFS($O$11:O12,$N$11:N12,$N12),2)) | Z12: =IF($N12="","",ROUND(SUMIFS(数据录入!$G$5:$G$4999,数据录入!$K$5:$K$4999,$N12),2)) | AA12: =IF(AND($D12="",$N12=""),"",IF(AND($D12<>"",COUNTIF(基础资料!$E:$E,$D12)=0),"客户名不在基础资料里",IF(AND($E12<>"",COUNTIF(基础资料!$B:$B,$E12)=0),"产品名不在基础资料里",IF(AND($N12<>"",COUNTIF(基础资料!$G:$G,$N12)=0),"供货商不在基础资料里",IF(AND($C12<>"",ISNUMBER($C12),$C12<10000),"客户生日填得不对（不是日期）",IF(N($J12)>N($F12),"销售费用大于销售金额",IF(AND($D12<>"",COUNTIF(数据录入!$J$5:$J$4999,$D12)=0,N($T12)<>0),"用的还是原手工已收款",IF(AND($D12<>"",COUNTIF(数据录入!$J$5:$J$4999,$D12)>0,ROUND(N($G12)-N($T12),2)<>0,N($T12)<>0),"自动算的已收款和原手工数对不上","√"))))))))
A13: =IF(AND($D13="",$N13=""),"",MAX($A$10:A12)+1) | B13: 46272 | C13: 46300 | D13: 谢爱琴 | E13: 羊奶 | F13: 3280 | G13: =IF($D13="","",IF(COUNTIF(数据录入!$J$5:$J$4999,$D13)=0,N($T13),ROUND(MIN(MAX(0,N($W13)-(N($V13)-N($U13))),N($U13)),2))) | H13: =IF($D13="","",ROUND(N($F13)-N($G13)-N($J13),2)) | I13: =IF($D13="","",ROUND(SUM($H$11:H13),2)) | J13: 300 | K13: 微信 | L13: 货款 | P13: =IF($N13="","",IF(COUNTIF(数据录入!$K$5:$K$4999,$N13)=0,N($X13),ROUND(MIN(MAX(0,N($Z13)-(N($Y13)-N($O13))),N($O13)),2))) | Q13: =IF($N13="","",ROUND(N($O13)-N($P13),2)) | R13: =IF($N13="","",ROUND(SUM($Q$11:Q13),2)) | S13: 采购 | T13: 2980 | U13: =IF($D13="","",ROUND(N($F13)-N($J13),2)) | V13: =IF($D13="","",ROUND(SUMIFS($F$11:F13,$D$11:D13,$D13)-SUMIFS($J$11:J13,$D$11:D13,$D13),2)) | W13: =IF($D13="","",ROUND(SUMIFS(数据录入!$F$5:$F$4999,数据录入!$J$5:$J$4999,$D13),2)) | Y13: =IF($N13="","",ROUND(SUMIFS($O$11:O13,$N$11:N13,$N13),2)) | Z13: =IF($N13="","",ROUND(SUMIFS(数据录入!$G$5:$G$4999,数据录入!$K$5:$K$4999,$N13),2)) | AA13: =IF(AND($D13="",$N13=""),"",IF(AND($D13<>"",COUNTIF(基础资料!$E:$E,$D13)=0),"客户名不在基础资料里",IF(AND($E13<>"",COUNTIF(基础资料!$B:$B,$E13)=0),"产品名不在基础资料里",IF(AND($N13<>"",COUNTIF(基础资料!$G:$G,$N13)=0),"供货商不在基础资料里",IF(AND($C13<>"",ISNUMBER($C13),$C13<10000),"客户生日填得不对（不是日期）",IF(N($J13)>N($F13),"销售费用大于销售金额",IF(AND($D13<>"",COUNTIF(数据录入!$J$5:$J$4999,$D13)=0,N($T13)<>0),"用的还是原手工已收款",IF(AND($D13<>"",COUNTIF(数据录入!$J$5:$J$4999,$D13)>0,ROUND(N($G13)-N($T13),2)<>0,N($T13)<>0),"自动算的已收款和原手工数对不上","√"))))))))
A14: =IF(AND($D14="",$N14=""),"",MAX($A$10:A13)+1) | B14: 46272 | C14: 46300 | D14: 谢爱琴 | E14: 益生菌 | F14: 3280 | G14: =IF($D14="","",IF(COUNTIF(数据录入!$J$5:$J$4999,$D14)=0,N($T14),ROUND(MIN(MAX(0,N($W14)-(N($V14)-N($U14))),N($U14)),2))) | H14: =IF($D14="","",ROUND(N($F14)-N($G14)-N($J14),2)) | I14: =IF($D14="","",ROUND(SUM($H$11:H14),2)) | J14: 300 | K14: 微信 | L14: 货款 | P14: =IF($N14="","",IF(COUNTIF(数据录入!$K$5:$K$4999,$N14)=0,N($X14),ROUND(MIN(MAX(0,N($Z14)-(N($Y14)-N($O14))),N($O14)),2))) | Q14: =IF($N14="","",ROUND(N($O14)-N($P14),2)) | R14: =IF($N14="","",ROUND(SUM($Q$11:Q14),2)) | T14: 2980 | U14: =IF($D14="","",ROUND(N($F14)-N($J14),2)) | V14: =IF($D14="","",ROUND(SUMIFS($F$11:F14,$D$11:D14,$D14)-SUMIFS($J$11:J14,$D$11:D14,$D14),2)) | W14: =IF($D14="","",ROUND(SUMIFS(数据录入!$F$5:$F$4999,数据录入!$J$5:$J$4999,$D14),2)) | Y14: =IF($N14="","",ROUND(SUMIFS($O$11:O14,$N$11:N14,$N14),2)) | Z14: =IF($N14="","",ROUND(SUMIFS(数据录入!$G$5:$G$4999,数据录入!$K$5:$K$4999,$N14),2)) | AA14: =IF(AND($D14="",$N14=""),"",IF(AND($D14<>"",COUNTIF(基础资料!$E:$E,$D14)=0),"客户名不在基础资料里",IF(AND($E14<>"",COUNTIF(基础资料!$B:$B,$E14)=0),"产品名不在基础资料里",IF(AND($N14<>"",COUNTIF(基础资料!$G:$G,$N14)=0),"供货商不在基础资料里",IF(AND($C14<>"",ISNUMBER($C14),$C14<10000),"客户生日填得不对（不是日期）",IF(N($J14)>N($F14),"销售费用大于销售金额",IF(AND($D14<>"",COUNTIF(数据录入!$J$5:$J$4999,$D14)=0,N($T14)<>0),"用的还是原手工已收款",IF(AND($D14<>"",COUNTIF(数据录入!$J$5:$J$4999,$D14)>0,ROUND(N($G14)-N($T14),2)<>0,N($T14)<>0),"自动算的已收款和原手工数对不上","√"))))))))
A15: =IF(AND($D15="",$N15=""),"",MAX($A$10:A14)+1) | B15: 46272 | C15: 46272 | D15: 罗理华 | E15: 羊奶 | F15: 3280 | G15: =IF($D15="","",IF(COUNTIF(数据录入!$J$5:$J$4999,$D15)=0,N($T15),ROUND(MIN(MAX(0,N($W15)-(N($V15)-N($U15))),N($U15)),2))) | H15: =IF($D15="","",ROUND(N($F15)-N($G15)-N($J15),2)) | I15: =IF($D15="","",ROUND(SUM($H$11:H15),2)) | J15: 0 | K15: 支付宝 | L15: 货款 | P15: =IF($N15="","",IF(COUNTIF(数据录入!$K$5:$K$4999,$N15)=0,N($X15),ROUND(MIN(MAX(0,N($Z15)-(N($Y15)-N($O15))),N($O15)),2))) | Q15: =IF($N15="","",ROUND(N($O15)-N($P15),2)) | R15: =IF($N15="","",ROUND(SUM($Q$11:Q15),2)) | T15: 1640 | U15: =IF($D15="","",ROUND(N($F15)-N($J15),2)) | V15: =IF($D15="","",ROUND(SUMIFS($F$11:F15,$D$11:D15,$D15)-SUMIFS($J$11:J15,$D$11:D15,$D15),2)) | W15: =IF($D15="","",ROUND(SUMIFS(数据录入!$F$5:$F$4999,数据录入!$J$5:$J$4999,$D15),2)) | Y15: =IF($N15="","",ROUND(SUMIFS($O$11:O15,$N$11:N15,$N15),2)) | Z15: =IF($N15="","",ROUND(SUMIFS(数据录入!$G$5:$G$4999,数据录入!$K$5:$K$4999,$N15),2)) | AA15: =IF(AND($D15="",$N15=""),"",IF(AND($D15<>"",COUNTIF(基础资料!$E:$E,$D15)=0),"客户名不在基础资料里",IF(AND($E15<>"",COUNTIF(基础资料!$B:$B,$E15)=0),"产品名不在基础资料里",IF(AND($N15<>"",COUNTIF(基础资料!$G:$G,$N15)=0),"供货商不在基础资料里",IF(AND($C15<>"",ISNUMBER($C15),$C15<10000),"客户生日填得不对（不是日期）",IF(N($J15)>N($F15),"销售费用大于销售金额",IF(AND($D15<>"",COUNTIF(数据录入!$J$5:$J$4999,$D15)=0,N($T15)<>0),"用的还是原手工已收款",IF(AND($D15<>"",COUNTIF(数据录入!$J$5:$J$4999,$D15)>0,ROUND(N($G15)-N($T15),2)<>0,N($T15)<>0),"自动算的已收款和原手工数对不上","√"))))))))
A16: =IF(AND($D16="",$N16=""),"",MAX($A$10:A15)+1) | B16: 46274 | C16: 46134 | D16: 马珍珠 | E16: 羊奶 | F16: 3280 | G16: =IF($D16="","",IF(COUNTIF(数据录入!$J$5:$J$4999,$D16)=0,N($T16),ROUND(MIN(MAX(0,N($W16)-(N($V16)-N($U16))),N($U16)),2))) | H16: =IF($D16="","",ROUND(N($F16)-N($G16)-N($J16),2)) | I16: =IF($D16="","",ROUND(SUM($H$11:H16),2)) | J16: 0 | K16: 微信 | L16: 货款 | P16: =IF($N16="","",IF(COUNTIF(数据录入!$K$5:$K$4999,$N16)=0,N($X16),ROUND(MIN(MAX(0,N($Z16)-(N($Y16)-N($O16))),N($O16)),2))) | Q16: =IF($N16="","",ROUND(N($O16)-N($P16),2)) | R16: =IF($N16="","",ROUND(SUM($Q$11:Q16),2)) | T16: 1000 | U16: =IF($D16="","",ROUND(N($F16)-N($J16),2)) | V16: =IF($D16="","",ROUND(SUMIFS($F$11:F16,$D$11:D16,$D16)-SUMIFS($J$11:J16,$D$11:D16,$D16),2)) | W16: =IF($D16="","",ROUND(SUMIFS(数据录入!$F$5:$F$4999,数据录入!$J$5:$J$4999,$D16),2)) | Y16: =IF($N16="","",ROUND(SUMIFS($O$11:O16,$N$11:N16,$N16),2)) | Z16: =IF($N16="","",ROUND(SUMIFS(数据录入!$G$5:$G$4999,数据录入!$K$5:$K$4999,$N16),2)) | AA16: =IF(AND($D16="",$N16=""),"",IF(AND($D16<>"",COUNTIF(基础资料!$E:$E,$D16)=0),"客户名不在基础资料里",IF(AND($E16<>"",COUNTIF(基础资料!$B:$B,$E16)=0),"产品名不在基础资料里",IF(AND($N16<>"",COUNTIF(基础资料!$G:$G,$N16)=0),"供货商不在基础资料里",IF(AND($C16<>"",ISNUMBER($C16),$C16<10000),"客户生日填得不对（不是日期）",IF(N($J16)>N($F16),"销售费用大于销售金额",IF(AND($D16<>"",COUNTIF(数据录入!$J$5:$J$4999,$D16)=0,N($T16)<>0),"用的还是原手工已收款",IF(AND($D16<>"",COUNTIF(数据录入!$J$5:$J$4999,$D16)>0,ROUND(N($G16)-N($T16),2)<>0,N($T16)<>0),"自动算的已收款和原手工数对不上","√"))))))))
A17: =IF(AND($D17="",$N17=""),"",MAX($A$10:A16)+1) | B17: 46277 | C17: 46333 | D17: 徐江英 | E17: 羊奶 | F17: 3280 | G17: =IF($D17="","",IF(COUNTIF(数据录入!$J$5:$J$4999,$D17)=0,N($T17),ROUND(MIN(MAX(0,N($W17)-(N($V17)-N($U17))),N($U17)),2))) | H17: =IF($D17="","",ROUND(N($F17)-N($G17)-N($J17),2)) | I17: =IF($D17="","",ROUND(SUM($H$11:H17),2)) | J17: 0 | K17: 微信 | L17: 货款 | P17: =IF($N17="","",IF(COUNTIF(数据录入!$K$5:$K$4999,$N17)=0,N($X17),ROUND(MIN(MAX(0,N($Z17)-(N($Y17)-N($O17))),N($O17)),2))) | Q17: =IF($N17="","",ROUND(N($O17)-N($P17),2)) | R17: =IF($N17="","",ROUND(SUM($Q$11:Q17),2)) | T17: 3280 | U17: =IF($D17="","",ROUND(N($F17)-N($J17),2)) | V17: =IF($D17="","",ROUND(SUMIFS($F$11:F17,$D$11:D17,$D17)-SUMIFS($J$11:J17,$D$11:D17,$D17),2)) | W17: =IF($D17="","",ROUND(SUMIFS(数据录入!$F$5:$F$4999,数据录入!$J$5:$J$4999,$D17),2)) | Y17: =IF($N17="","",ROUND(SUMIFS($O$11:O17,$N$11:N17,$N17),2)) | Z17: =IF($N17="","",ROUND(SUMIFS(数据录入!$G$5:$G$4999,数据录入!$K$5:$K$4999,$N17),2)) | AA17: =IF(AND($D17="",$N17=""),"",IF(AND($D17<>"",COUNTIF(基础资料!$E:$E,$D17)=0),"客户名不在基础资料里",IF(AND($E17<>"",COUNTIF(基础资料!$B:$B,$E17)=0),"产品名不在基础资料里",IF(AND($N17<>"",COUNTIF(基础资料!$G:$G,$N17)=0),"供货商不在基础资料里",IF(AND($C17<>"",ISNUMBER($C17),$C17<10000),"客户生日填得不对（不是日期）",IF(N($J17)>N($F17),"销售费用大于销售金额",IF(AND($D17<>"",COUNTIF(数据录入!$J$5:$J$4999,$D17)=0,N($T17)<>0),"用的还是原手工已收款",IF(AND($D17<>"",COUNTIF(数据录入!$J$5:$J$4999,$D17)>0,ROUND(N($G17)-N($T17),2)<>0,N($T17)<>0),"自动算的已收款和原手工数对不上","√"))))))))
A18: =IF(AND($D18="",$N18=""),"",MAX($A$10:A17)+1) | C18: 46148 | D18: 邵国新 | G18: =IF($D18="","",IF(COUNTIF(数据录入!$J$5:$J$4999,$D18)=0,N($T18),ROUND(MIN(MAX(0,N($W18)-(N($V18)-N($U18))),N($U18)),2))) | H18: =IF($D18="","",ROUND(N($F18)-N($G18)-N($J18),2)) | I18: =IF($D18="","",ROUND(SUM($H$11:H18),2)) | P18: =IF($N18="","",IF(COUNTIF(数据录入!$K$5:$K$4999,$N18)=0,N($X18),ROUND(MIN(MAX(0,N($Z18)-(N($Y18)-N($O18))),N($O18)),2))) | Q18: =IF($N18="","",ROUND(N($O18)-N($P18),2)) | R18: =IF($N18="","",ROUND(SUM($Q$11:Q18),2)) | U18: =IF($D18="","",ROUND(N($F18)-N($J18),2)) | V18: =IF($D18="","",ROUND(SUMIFS($F$11:F18,$D$11:D18,$D18)-SUMIFS($J$11:J18,$D$11:D18,$D18),2)) | W18: =IF($D18="","",ROUND(SUMIFS(数据录入!$F$5:$F$4999,数据录入!$J$5:$J$4999,$D18),2)) | Y18: =IF($N18="","",ROUND(SUMIFS($O$11:O18,$N$11:N18,$N18),2)) | Z18: =IF($N18="","",ROUND(SUMIFS(数据录入!$G$5:$G$4999,数据录入!$K$5:$K$4999,$N18),2)) | AA18: =IF(AND($D18="",$N18=""),"",IF(AND($D18<>"",COUNTIF(基础资料!$E:$E,$D18)=0),"客户名不在基础资料里",IF(AND($E18<>"",COUNTIF(基础资料!$B:$B,$E18)=0),"产品名不在基础资料里",IF(AND($N18<>"",COUNTIF(基础资料!$G:$G,$N18)=0),"供货商不在基础资料里",IF(AND($C18<>"",ISNUMBER($C18),$C18<10000),"客户生日填得不对（不是日期）",IF(N($J18)>N($F18),"销售费用大于销售金额",IF(AND($D18<>"",COUNTIF(数据录入!$J$5:$J$4999,$D18)=0,N($T18)<>0),"用的还是原手工已收款",IF(AND($D18<>"",COUNTIF(数据录入!$J$5:$J$4999,$D18)>0,ROUND(N($G18)-N($T18),2)<>0,N($T18)<>0),"自动算的已收款和原手工数对不上","√"))))))))
A19: =IF(AND($D19="",$N19=""),"",MAX($A$10:A18)+1) | C19: 46140 | D19: 李晓春 | G19: =IF($D19="","",IF(COUNTIF(数据录入!$J$5:$J$4999,$D19)=0,N($T19),ROUND(MIN(MAX(0,N($W19)-(N($V19)-N($U19))),N($U19)),2))) | H19: =IF($D19="","",ROUND(N($F19)-N($G19)-N($J19),2)) | I19: =IF($D19="","",ROUND(SUM($H$11:H19),2)) | P19: =IF($N19="","",IF(COUNTIF(数据录入!$K$5:$K$4999,$N19)=0,N($X19),ROUND(MIN(MAX(0,N($Z19)-(N($Y19)-N($O19))),N($O19)),2))) | Q19: =IF($N19="","",ROUND(N($O19)-N($P19),2)) | R19: =IF($N19="","",ROUND(SUM($Q$11:Q19),2)) | U19: =IF($D19="","",ROUND(N($F19)-N($J19),2)) | V19: =IF($D19="","",ROUND(SUMIFS($F$11:F19,$D$11:D19,$D19)-SUMIFS($J$11:J19,$D$11:D19,$D19),2)) | W19: =IF($D19="","",ROUND(SUMIFS(数据录入!$F$5:$F$4999,数据录入!$J$5:$J$4999,$D19),2)) | Y19: =IF($N19="","",ROUND(SUMIFS($O$11:O19,$N$11:N19,$N19),2)) | Z19: =IF($N19="","",ROUND(SUMIFS(数据录入!$G$5:$G$4999,数据录入!$K$5:$K$4999,$N19),2)) | AA19: =IF(AND($D19="",$N19=""),"",IF(AND($D19<>"",COUNTIF(基础资料!$E:$E,$D19)=0),"客户名不在基础资料里",IF(AND($E19<>"",COUNTIF(基础资料!$B:$B,$E19)=0),"产品名不在基础资料里",IF(AND($N19<>"",COUNTIF(基础资料!$G:$G,$N19)=0),"供货商不在基础资料里",IF(AND($C19<>"",ISNUMBER($C19),$C19<10000),"客户生日填得不对（不是日期）",IF(N($J19)>N($F19),"销售费用大于销售金额",IF(AND($D19<>"",COUNTIF(数据录入!$J$5:$J$4999,$D19)=0,N($T19)<>0),"用的还是原手工已收款",IF(AND($D19<>"",COUNTIF(数据录入!$J$5:$J$4999,$D19)>0,ROUND(N($G19)-N($T19),2)<>0,N($T19)<>0),"自动算的已收款和原手工数对不上","√"))))))))
A20: =IF(AND($D20="",$N20=""),"",MAX($A$10:A19)+1) | C20: 46154 | D20: 李玉娟 | G20: =IF($D20="","",IF(COUNTIF(数据录入!$J$5:$J$4999,$D20)=0,N($T20),ROUND(MIN(MAX(0,N($W20)-(N($V20)-N($U20))),N($U20)),2))) | H20: =IF($D20="","",ROUND(N($F20)-N($G20)-N($J20),2)) | I20: =IF($D20="","",ROUND(SUM($H$11:H20),2)) | P20: =IF($N20="","",IF(COUNTIF(数据录入!$K$5:$K$4999,$N20)=0,N($X20),ROUND(MIN(MAX(0,N($Z20)-(N($Y20)-N($O20))),N($O20)),2))) | Q20: =IF($N20="","",ROUND(N($O20)-N($P20),2)) | R20: =IF($N20="","",ROUND(SUM($Q$11:Q20),2)) | U20: =IF($D20="","",ROUND(N($F20)-N($J20),2)) | V20: =IF($D20="","",ROUND(SUMIFS($F$11:F20,$D$11:D20,$D20)-SUMIFS($J$11:J20,$D$11:D20,$D20),2)) | W20: =IF($D20="","",ROUND(SUMIFS(数据录入!$F$5:$F$4999,数据录入!$J$5:$J$4999,$D20),2)) | Y20: =IF($N20="","",ROUND(SUMIFS($O$11:O20,$N$11:N20,$N20),2)) | Z20: =IF($N20="","",ROUND(SUMIFS(数据录入!$G$5:$G$4999,数据录入!$K$5:$K$4999,$N20),2)) | AA20: =IF(AND($D20="",$N20=""),"",IF(AND($D20<>"",COUNTIF(基础资料!$E:$E,$D20)=0),"客户名不在基础资料里",IF(AND($E20<>"",COUNTIF(基础资料!$B:$B,$E20)=0),"产品名不在基础资料里",IF(AND($N20<>"",COUNTIF(基础资料!$G:$G,$N20)=0),"供货商不在基础资料里",IF(AND($C20<>"",ISNUMBER($C20),$C20<10000),"客户生日填得不对（不是日期）",IF(N($J20)>N($F20),"销售费用大于销售金额",IF(AND($D20<>"",COUNTIF(数据录入!$J$5:$J$4999,$D20)=0,N($T20)<>0),"用的还是原手工已收款",IF(AND($D20<>"",COUNTIF(数据录入!$J$5:$J$4999,$D20)>0,ROUND(N($G20)-N($T20),2)<>0,N($T20)<>0),"自动算的已收款和原手工数对不上","√"))))))))
A21: =IF(AND($D21="",$N21=""),"",MAX($A$10:A20)+1) | C21: 46174 | D21: 徐德彪 | G21: =IF($D21="","",IF(COUNTIF(数据录入!$J$5:$J$4999,$D21)=0,N($T21),ROUND(MIN(MAX(0,N($W21)-(N($V21)-N($U21))),N($U21)),2))) | H21: =IF($D21="","",ROUND(N($F21)-N($G21)-N($J21),2)) | I21: =IF($D21="","",ROUND(SUM($H$11:H21),2)) | P21: =IF($N21="","",IF(COUNTIF(数据录入!$K$5:$K$4999,$N21)=0,N($X21),ROUND(MIN(MAX(0,N($Z21)-(N($Y21)-N($O21))),N($O21)),2))) | Q21: =IF($N21="","",ROUND(N($O21)-N($P21),2)) | R21: =IF($N21="","",ROUND(SUM($Q$11:Q21),2)) | U21: =IF($D21="","",ROUND(N($F21)-N($J21),2)) | V21: =IF($D21="","",ROUND(SUMIFS($F$11:F21,$D$11:D21,$D21)-SUMIFS($J$11:J21,$D$11:D21,$D21),2)) | W21: =IF($D21="","",ROUND(SUMIFS(数据录入!$F$5:$F$4999,数据录入!$J$5:$J$4999,$D21),2)) | Y21: =IF($N21="","",ROUND(SUMIFS($O$11:O21,$N$11:N21,$N21),2)) | Z21: =IF($N21="","",ROUND(SUMIFS(数据录入!$G$5:$G$4999,数据录入!$K$5:$K$4999,$N21),2)) | AA21: =IF(AND($D21="",$N21=""),"",IF(AND($D21<>"",COUNTIF(基础资料!$E:$E,$D21)=0),"客户名不在基础资料里",IF(AND($E21<>"",COUNTIF(基础资料!$B:$B,$E21)=0),"产品名不在基础资料里",IF(AND($N21<>"",COUNTIF(基础资料!$G:$G,$N21)=0),"供货商不在基础资料里",IF(AND($C21<>"",ISNUMBER($C21),$C21<10000),"客户生日填得不对（不是日期）",IF(N($J21)>N($F21),"销售费用大于销售金额",IF(AND($D21<>"",COUNTIF(数据录入!$J$5:$J$4999,$D21)=0,N($T21)<>0),"用的还是原手工已收款",IF(AND($D21<>"",COUNTIF(数据录入!$J$5:$J$4999,$D21)>0,ROUND(N($G21)-N($T21),2)<>0,N($T21)<>0),"自动算的已收款和原手工数对不上","√"))))))))
A22: =IF(AND($D22="",$N22=""),"",MAX($A$10:A21)+1) | C22: 46188 | D22: 邬香花 方建宏 | G22: =IF($D22="","",IF(COUNTIF(数据录入!$J$5:$J$4999,$D22)=0,N($T22),ROUND(MIN(MAX(0,N($W22)-(N($V22)-N($U22))),N($U22)),2))) | H22: =IF($D22="","",ROUND(N($F22)-N($G22)-N($J22),2)) | I22: =IF($D22="","",ROUND(SUM($H$11:H22),2)) | P22: =IF($N22="","",IF(COUNTIF(数据录入!$K$5:$K$4999,$N22)=0,N($X22),ROUND(MIN(MAX(0,N($Z22)-(N($Y22)-N($O22))),N($O22)),2))) | Q22: =IF($N22="","",ROUND(N($O22)-N($P22),2)) | R22: =IF($N22="","",ROUND(SUM($Q$11:Q22),2)) | U22: =IF($D22="","",ROUND(N($F22)-N($J22),2)) | V22: =IF($D22="","",ROUND(SUMIFS($F$11:F22,$D$11:D22,$D22)-SUMIFS($J$11:J22,$D$11:D22,$D22),2)) | W22: =IF($D22="","",ROUND(SUMIFS(数据录入!$F$5:$F$4999,数据录入!$J$5:$J$4999,$D22),2)) | Y22: =IF($N22="","",ROUND(SUMIFS($O$11:O22,$N$11:N22,$N22),2)) | Z22: =IF($N22="","",ROUND(SUMIFS(数据录入!$G$5:$G$4999,数据录入!$K$5:$K$4999,$N22),2)) | AA22: =IF(AND($D22="",$N22=""),"",IF(AND($D22<>"",COUNTIF(基础资料!$E:$E,$D22)=0),"客户名不在基础资料里",IF(AND($E22<>"",COUNTIF(基础资料!$B:$B,$E22)=0),"产品名不在基础资料里",IF(AND($N22<>"",COUNTIF(基础资料!$G:$G,$N22)=0),"供货商不在基础资料里",IF(AND($C22<>"",ISNUMBER($C22),$C22<10000),"客户生日填得不对（不是日期）",IF(N($J22)>N($F22),"销售费用大于销售金额",IF(AND($D22<>"",COUNTIF(数据录入!$J$5:$J$4999,$D22)=0,N($T22)<>0),"用的还是原手工已收款",IF(AND($D22<>"",COUNTIF(数据录入!$J$5:$J$4999,$D22)>0,ROUND(N($G22)-N($T22),2)<>0,N($T22)<>0),"自动算的已收款和原手工数对不上","√"))))))))
A23: =IF(AND($D23="",$N23=""),"",MAX($A$10:A22)+1) | B23: 46235 | C23: 6月17日 3月4日 | D23: 林永来 杨建云 | G23: =IF($D23="","",IF(COUNTIF(数据录入!$J$5:$J$4999,$D23)=0,N($T23),ROUND(MIN(MAX(0,N($W23)-(N($V23)-N($U23))),N($U23)),2))) | H23: =IF($D23="","",ROUND(N($F23)-N($G23)-N($J23),2)) | I23: =IF($D23="","",ROUND(SUM($H$11:H23),2)) | P23: =IF($N23="","",IF(COUNTIF(数据录入!$K$5:$K$4999,$N23)=0,N($X23),ROUND(MIN(MAX(0,N($Z23)-(N($Y23)-N($O23))),N($O23)),2))) | Q23: =IF($N23="","",ROUND(N($O23)-N($P23),2)) | R23: =IF($N23="","",ROUND(SUM($Q$11:Q23),2)) | U23: =IF($D23="","",ROUND(N($F23)-N($J23),2)) | V23: =IF($D23="","",ROUND(SUMIFS($F$11:F23,$D$11:D23,$D23)-SUMIFS($J$11:J23,$D$11:D23,$D23),2)) | W23: =IF($D23="","",ROUND(SUMIFS(数据录入!$F$5:$F$4999,数据录入!$J$5:$J$4999,$D23),2)) | Y23: =IF($N23="","",ROUND(SUMIFS($O$11:O23,$N$11:N23,$N23),2)) | Z23: =IF($N23="","",ROUND(SUMIFS(数据录入!$G$5:$G$4999,数据录入!$K$5:$K$4999,$N23),2)) | AA23: =IF(AND($D23="",$N23=""),"",IF(AND($D23<>"",COUNTIF(基础资料!$E:$E,$D23)=0),"客户名不在基础资料里",IF(AND($E23<>"",COUNTIF(基础资料!$B:$B,$E23)=0),"产品名不在基础资料里",IF(AND($N23<>"",COUNTIF(基础资料!$G:$G,$N23)=0),"供货商不在基础资料里",IF(AND($C23<>"",ISNUMBER($C23),$C23<10000),"客户生日填得不对（不是日期）",IF(N($J23)>N($F23),"销售费用大于销售金额",IF(AND($D23<>"",COUNTIF(数据录入!$J$5:$J$4999,$D23)=0,N($T23)<>0),"用的还是原手工已收款",IF(AND($D23<>"",COUNTIF(数据录入!$J$5:$J$4999,$D23)>0,ROUND(N($G23)-N($T23),2)<>0,N($T23)<>0),"自动算的已收款和原手工数对不上","√"))))))))
A24: =IF(AND($D24="",$N24=""),"",MAX($A$10:A23)+1) | C24: 46220 | D24: 郭志伟 | G24: =IF($D24="","",IF(COUNTIF(数据录入!$J$5:$J$4999,$D24)=0,N($T24),ROUND(MIN(MAX(0,N($W24)-(N($V24)-N($U24))),N($U24)),2))) | H24: =IF($D24="","",ROUND(N($F24)-N($G24)-N($J24),2)) | I24: =IF($D24="","",ROUND(SUM($H$11:H24),2)) | P24: =IF($N24="","",IF(COUNTIF(数据录入!$K$5:$K$4999,$N24)=0,N($X24),ROUND(MIN(MAX(0,N($Z24)-(N($Y24)-N($O24))),N($O24)),2))) | Q24: =IF($N24="","",ROUND(N($O24)-N($P24),2)) | R24: =IF($N24="","",ROUND(SUM($Q$11:Q24),2)) | U24: =IF($D24="","",ROUND(N($F24)-N($J24),2)) | V24: =IF($D24="","",ROUND(SUMIFS($F$11:F24,$D$11:D24,$D24)-SUMIFS($J$11:J24,$D$11:D24,$D24),2)) | W24: =IF($D24="","",ROUND(SUMIFS(数据录入!$F$5:$F$4999,数据录入!$J$5:$J$4999,$D24),2)) | Y24: =IF($N24="","",ROUND(SUMIFS($O$11:O24,$N$11:N24,$N24),2)) | Z24: =IF($N24="","",ROUND(SUMIFS(数据录入!$G$5:$G$4999,数据录入!$K$5:$K$4999,$N24),2)) | AA24: =IF(AND($D24="",$N24=""),"",IF(AND($D24<>"",COUNTIF(基础资料!$E:$E,$D24)=0),"客户名不在基础资料里",IF(AND($E24<>"",COUNTIF(基础资料!$B:$B,$E24)=0),"产品名不在基础资料里",IF(AND($N24<>"",COUNTIF(基础资料!$G:$G,$N24)=0),"供货商不在基础资料里",IF(AND($C24<>"",ISNUMBER($C24),$C24<10000),"客户生日填得不对（不是日期）",IF(N($J24)>N($F24),"销售费用大于销售金额",IF(AND($D24<>"",COUNTIF(数据录入!$J$5:$J$4999,$D24)=0,N($T24)<>0),"用的还是原手工已收款",IF(AND($D24<>"",COUNTIF(数据录入!$J$5:$J$4999,$D24)>0,ROUND(N($G24)-N($T24),2)<>0,N($T24)<>0),"自动算的已收款和原手工数对不上","√"))))))))
A25: =IF(AND($D25="",$N25=""),"",MAX($A$10:A24)+1) | C25: 46225 | D25: 吴亮 | G25: =IF($D25="","",IF(COUNTIF(数据录入!$J$5:$J$4999,$D25)=0,N($T25),ROUND(MIN(MAX(0,N($W25)-(N($V25)-N($U25))),N($U25)),2))) | H25: =IF($D25="","",ROUND(N($F25)-N($G25)-N($J25),2)) | I25: =IF($D25="","",ROUND(SUM($H$11:H25),2)) | P25: =IF($N25="","",IF(COUNTIF(数据录入!$K$5:$K$4999,$N25)=0,N($X25),ROUND(MIN(MAX(0,N($Z25)-(N($Y25)-N($O25))),N($O25)),2))) | Q25: =IF($N25="","",ROUND(N($O25)-N($P25),2)) | R25: =IF($N25="","",ROUND(SUM($Q$11:Q25),2)) | U25: =IF($D25="","",ROUND(N($F25)-N($J25),2)) | V25: =IF($D25="","",ROUND(SUMIFS($F$11:F25,$D$11:D25,$D25)-SUMIFS($J$11:J25,$D$11:D25,$D25),2)) | W25: =IF($D25="","",ROUND(SUMIFS(数据录入!$F$5:$F$4999,数据录入!$J$5:$J$4999,$D25),2)) | Y25: =IF($N25="","",ROUND(SUMIFS($O$11:O25,$N$11:N25,$N25),2)) | Z25: =IF($N25="","",ROUND(SUMIFS(数据录入!$G$5:$G$4999,数据录入!$K$5:$K$4999,$N25),2)) | AA25: =IF(AND($D25="",$N25=""),"",IF(AND($D25<>"",COUNTIF(基础资料!$E:$E,$D25)=0),"客户名不在基础资料里",IF(AND($E25<>"",COUNTIF(基础资料!$B:$B,$E25)=0),"产品名不在基础资料里",IF(AND($N25<>"",COUNTIF(基础资料!$G:$G,$N25)=0),"供货商不在基础资料里",IF(AND($C25<>"",ISNUMBER($C25),$C25<10000),"客户生日填得不对（不是日期）",IF(N($J25)>N($F25),"销售费用大于销售金额",IF(AND($D25<>"",COUNTIF(数据录入!$J$5:$J$4999,$D25)=0,N($T25)<>0),"用的还是原手工已收款",IF(AND($D25<>"",COUNTIF(数据录入!$J$5:$J$4999,$D25)>0,ROUND(N($G25)-N($T25),2)<>0,N($T25)<>0),"自动算的已收款和原手工数对不上","√"))))))))
A26: =IF(AND($D26="",$N26=""),"",MAX($A$10:A25)+1) | C26: 46232 | D26: 吴兆香 | G26: =IF($D26="","",IF(COUNTIF(数据录入!$J$5:$J$4999,$D26)=0,N($T26),ROUND(MIN(MAX(0,N($W26)-(N($V26)-N($U26))),N($U26)),2))) | H26: =IF($D26="","",ROUND(N($F26)-N($G26)-N($J26),2)) | I26: =IF($D26="","",ROUND(SUM($H$11:H26),2)) | P26: =IF($N26="","",IF(COUNTIF(数据录入!$K$5:$K$4999,$N26)=0,N($X26),ROUND(MIN(MAX(0,N($Z26)-(N($Y26)-N($O26))),N($O26)),2))) | Q26: =IF($N26="","",ROUND(N($O26)-N($P26),2)) | R26: =IF($N26="","",ROUND(SUM($Q$11:Q26),2)) | U26: =IF($D26="","",ROUND(N($F26)-N($J26),2)) | V26: =IF($D26="","",ROUND(SUMIFS($F$11:F26,$D$11:D26,$D26)-SUMIFS($J$11:J26,$D$11:D26,$D26),2)) | W26: =IF($D26="","",ROUND(SUMIFS(数据录入!$F$5:$F$4999,数据录入!$J$5:$J$4999,$D26),2)) | Y26: =IF($N26="","",ROUND(SUMIFS($O$11:O26,$N$11:N26,$N26),2)) | Z26: =IF($N26="","",ROUND(SUMIFS(数据录入!$G$5:$G$4999,数据录入!$K$5:$K$4999,$N26),2)) | AA26: =IF(AND($D26="",$N26=""),"",IF(AND($D26<>"",COUNTIF(基础资料!$E:$E,$D26)=0),"客户名不在基础资料里",IF(AND($E26<>"",COUNTIF(基础资料!$B:$B,$E26)=0),"产品名不在基础资料里",IF(AND($N26<>"",COUNTIF(基础资料!$G:$G,$N26)=0),"供货商不在基础资料里",IF(AND($C26<>"",ISNUMBER($C26),$C26<10000),"客户生日填得不对（不是日期）",IF(N($J26)>N($F26),"销售费用大于销售金额",IF(AND($D26<>"",COUNTIF(数据录入!$J$5:$J$4999,$D26)=0,N($T26)<>0),"用的还是原手工已收款",IF(AND($D26<>"",COUNTIF(数据录入!$J$5:$J$4999,$D26)>0,ROUND(N($G26)-N($T26),2)<>0,N($T26)<>0),"自动算的已收款和原手工数对不上","√"))))))))
A27: =IF(AND($D27="",$N27=""),"",MAX($A$10:A26)+1) | C27: 46242 | D27: 郑玉英 | G27: =IF($D27="","",IF(COUNTIF(数据录入!$J$5:$J$4999,$D27)=0,N($T27),ROUND(MIN(MAX(0,N($W27)-(N($V27)-N($U27))),N($U27)),2))) | H27: =IF($D27="","",ROUND(N($F27)-N($G27)-N($J27),2)) | I27: =IF($D27="","",ROUND(SUM($H$11:H27),2)) | P27: =IF($N27="","",IF(COUNTIF(数据录入!$K$5:$K$4999,$N27)=0,N($X27),ROUND(MIN(MAX(0,N($Z27)-(N($Y27)-N($O27))),N($O27)),2))) | Q27: =IF($N27="","",ROUND(N($O27)-N($P27),2)) | R27: =IF($N27="","",ROUND(SUM($Q$11:Q27),2)) | U27: =IF($D27="","",ROUND(N($F27)-N($J27),2)) | V27: =IF($D27="","",ROUND(SUMIFS($F$11:F27,$D$11:D27,$D27)-SUMIFS($J$11:J27,$D$11:D27,$D27),2)) | W27: =IF($D27="","",ROUND(SUMIFS(数据录入!$F$5:$F$4999,数据录入!$J$5:$J$4999,$D27),2)) | Y27: =IF($N27="","",ROUND(SUMIFS($O$11:O27,$N$11:N27,$N27),2)) | Z27: =IF($N27="","",ROUND(SUMIFS(数据录入!$G$5:$G$4999,数据录入!$K$5:$K$4999,$N27),2)) | AA27: =IF(AND($D27="",$N27=""),"",IF(AND($D27<>"",COUNTIF(基础资料!$E:$E,$D27)=0),"客户名不在基础资料里",IF(AND($E27<>"",COUNTIF(基础资料!$B:$B,$E27)=0),"产品名不在基础资料里",IF(AND($N27<>"",COUNTIF(基础资料!$G:$G,$N27)=0),"供货商不在基础资料里",IF(AND($C27<>"",ISNUMBER($C27),$C27<10000),"客户生日填得不对（不是日期）",IF(N($J27)>N($F27),"销售费用大于销售金额",IF(AND($D27<>"",COUNTIF(数据录入!$J$5:$J$4999,$D27)=0,N($T27)<>0),"用的还是原手工已收款",IF(AND($D27<>"",COUNTIF(数据录入!$J$5:$J$4999,$D27)>0,ROUND(N($G27)-N($T27),2)<>0,N($T27)<>0),"自动算的已收款和原手工数对不上","√"))))))))
A28: =IF(AND($D28="",$N28=""),"",MAX($A$10:A27)+1) | C28: 46274 | D28: 唐鑫红 | G28: =IF($D28="","",IF(COUNTIF(数据录入!$J$5:$J$4999,$D28)=0,N($T28),ROUND(MIN(MAX(0,N($W28)-(N($V28)-N($U28))),N($U28)),2))) | H28: =IF($D28="","",ROUND(N($F28)-N($G28)-N($J28),2)) | I28: =IF($D28="","",ROUND(SUM($H$11:H28),2)) | P28: =IF($N28="","",IF(COUNTIF(数据录入!$K$5:$K$4999,$N28)=0,N($X28),ROUND(MIN(MAX(0,N($Z28)-(N($Y28)-N($O28))),N($O28)),2))) | Q28: =IF($N28="","",ROUND(N($O28)-N($P28),2)) | R28: =IF($N28="","",ROUND(SUM($Q$11:Q28),2)) | U28: =IF($D28="","",ROUND(N($F28)-N($J28),2)) | V28: =IF($D28="","",ROUND(SUMIFS($F$11:F28,$D$11:D28,$D28)-SUMIFS($J$11:J28,$D$11:D28,$D28),2)) | W28: =IF($D28="","",ROUND(SUMIFS(数据录入!$F$5:$F$4999,数据录入!$J$5:$J$4999,$D28),2)) | Y28: =IF($N28="","",ROUND(SUMIFS($O$11:O28,$N$11:N28,$N28),2)) | Z28: =IF($N28="","",ROUND(SUMIFS(数据录入!$G$5:$G$4999,数据录入!$K$5:$K$4999,$N28),2)) | AA28: =IF(AND($D28="",$N28=""),"",IF(AND($D28<>"",COUNTIF(基础资料!$E:$E,$D28)=0),"客户名不在基础资料里",IF(AND($E28<>"",COUNTIF(基础资料!$B:$B,$E28)=0),"产品名不在基础资料里",IF(AND($N28<>"",COUNTIF(基础资料!$G:$G,$N28)=0),"供货商不在基础资料里",IF(AND($C28<>"",ISNUMBER($C28),$C28<10000),"客户生日填得不对（不是日期）",IF(N($J28)>N($F28),"销售费用大于销售金额",IF(AND($D28<>"",COUNTIF(数据录入!$J$5:$J$4999,$D28)=0,N($T28)<>0),"用的还是原手工已收款",IF(AND($D28<>"",COUNTIF(数据录入!$J$5:$J$4999,$D28)>0,ROUND(N($G28)-N($T28),2)<>0,N($T28)<>0),"自动算的已收款和原手工数对不上","√"))))))))
A29: =IF(AND($D29="",$N29=""),"",MAX($A$10:A28)+1) | C29: 46285 | D29: 叶芬 | G29: =IF($D29="","",IF(COUNTIF(数据录入!$J$5:$J$4999,$D29)=0,N($T29),ROUND(MIN(MAX(0,N($W29)-(N($V29)-N($U29))),N($U29)),2))) | H29: =IF($D29="","",ROUND(N($F29)-N($G29)-N($J29),2)) | I29: =IF($D29="","",ROUND(SUM($H$11:H29),2)) | P29: =IF($N29="","",IF(COUNTIF(数据录入!$K$5:$K$4999,$N29)=0,N($X29),ROUND(MIN(MAX(0,N($Z29)-(N($Y29)-N($O29))),N($O29)),2))) | Q29: =IF($N29="","",ROUND(N($O29)-N($P29),2)) | R29: =IF($N29="","",ROUND(SUM($Q$11:Q29),2)) | U29: =IF($D29="","",ROUND(N($F29)-N($J29),2)) | V29: =IF($D29="","",ROUND(SUMIFS($F$11:F29,$D$11:D29,$D29)-SUMIFS($J$11:J29,$D$11:D29,$D29),2)) | W29: =IF($D29="","",ROUND(SUMIFS(数据录入!$F$5:$F$4999,数据录入!$J$5:$J$4999,$D29),2)) | Y29: =IF($N29="","",ROUND(SUMIFS($O$11:O29,$N$11:N29,$N29),2)) | Z29: =IF($N29="","",ROUND(SUMIFS(数据录入!$G$5:$G$4999,数据录入!$K$5:$K$4999,$N29),2)) | AA29: =IF(AND($D29="",$N29=""),"",IF(AND($D29<>"",COUNTIF(基础资料!$E:$E,$D29)=0),"客户名不在基础资料里",IF(AND($E29<>"",COUNTIF(基础资料!$B:$B,$E29)=0),"产品名不在基础资料里",IF(AND($N29<>"",COUNTIF(基础资料!$G:$G,$N29)=0),"供货商不在基础资料里",IF(AND($C29<>"",ISNUMBER($C29),$C29<10000),"客户生日填得不对（不是日期）",IF(N($J29)>N($F29),"销售费用大于销售金额",IF(AND($D29<>"",COUNTIF(数据录入!$J$5:$J$4999,$D29)=0,N($T29)<>0),"用的还是原手工已收款",IF(AND($D29<>"",COUNTIF(数据录入!$J$5:$J$4999,$D29)>0,ROUND(N($G29)-N($T29),2)<>0,N($T29)<>0),"自动算的已收款和原手工数对不上","√"))))))))
A30: =IF(AND($D30="",$N30=""),"",MAX($A$10:A29)+1) | C30: 46288 | D30: 童炳寿 王秀娟 | G30: =IF($D30="","",IF(COUNTIF(数据录入!$J$5:$J$4999,$D30)=0,N($T30),ROUND(MIN(MAX(0,N($W30)-(N($V30)-N($U30))),N($U30)),2))) | H30: =IF($D30="","",ROUND(N($F30)-N($G30)-N($J30),2)) | I30: =IF($D30="","",ROUND(SUM($H$11:H30),2)) | P30: =IF($N30="","",IF(COUNTIF(数据录入!$K$5:$K$4999,$N30)=0,N($X30),ROUND(MIN(MAX(0,N($Z30)-(N($Y30)-N($O30))),N($O30)),2))) | Q30: =IF($N30="","",ROUND(N($O30)-N($P30),2)) | R30: =IF($N30="","",ROUND(SUM($Q$11:Q30),2)) | U30: =IF($D30="","",ROUND(N($F30)-N($J30),2)) | V30: =IF($D30="","",ROUND(SUMIFS($F$11:F30,$D$11:D30,$D30)-SUMIFS($J$11:J30,$D$11:D30,$D30),2)) | W30: =IF($D30="","",ROUND(SUMIFS(数据录入!$F$5:$F$4999,数据录入!$J$5:$J$4999,$D30),2)) | Y30: =IF($N30="","",ROUND(SUMIFS($O$11:O30,$N$11:N30,$N30),2)) | Z30: =IF($N30="","",ROUND(SUMIFS(数据录入!$G$5:$G$4999,数据录入!$K$5:$K$4999,$N30),2)) | AA30: =IF(AND($D30="",$N30=""),"",IF(AND($D30<>"",COUNTIF(基础资料!$E:$E,$D30)=0),"客户名不在基础资料里",IF(AND($E30<>"",COUNTIF(基础资料!$B:$B,$E30)=0),"产品名不在基础资料里",IF(AND($N30<>"",COUNTIF(基础资料!$G:$G,$N30)=0),"供货商不在基础资料里",IF(AND($C30<>"",ISNUMBER($C30),$C30<10000),"客户生日填得不对（不是日期）",IF(N($J30)>N($F30),"销售费用大于销售金额",IF(AND($D30<>"",COUNTIF(数据录入!$J$5:$J$4999,$D30)=0,N($T30)<>0),"用的还是原手工已收款",IF(AND($D30<>"",COUNTIF(数据录入!$J$5:$J$4999,$D30)>0,ROUND(N($G30)-N($T30),2)<>0,N($T30)<>0),"自动算的已收款和原手工数对不上","√"))))))))
A31: =IF(AND($D31="",$N31=""),"",MAX($A$10:A30)+1) | C31: 46299 | D31: 郑爱月 | G31: =IF($D31="","",IF(COUNTIF(数据录入!$J$5:$J$4999,$D31)=0,N($T31),ROUND(MIN(MAX(0,N($W31)-(N($V31)-N($U31))),N($U31)),2))) | H31: =IF($D31="","",ROUND(N($F31)-N($G31)-N($J31),2)) | I31: =IF($D31="","",ROUND(SUM($H$11:H31),2)) | P31: =IF($N31="","",IF(COUNTIF(数据录入!$K$5:$K$4999,$N31)=0,N($X31),ROUND(MIN(MAX(0,N($Z31)-(N($Y31)-N($O31))),N($O31)),2))) | Q31: =IF($N31="","",ROUND(N($O31)-N($P31),2)) | R31: =IF($N31="","",ROUND(SUM($Q$11:Q31),2)) | U31: =IF($D31="","",ROUND(N($F31)-N($J31),2)) | V31: =IF($D31="","",ROUND(SUMIFS($F$11:F31,$D$11:D31,$D31)-SUMIFS($J$11:J31,$D$11:D31,$D31),2)) | W31: =IF($D31="","",ROUND(SUMIFS(数据录入!$F$5:$F$4999,数据录入!$J$5:$J$4999,$D31),2)) | Y31: =IF($N31="","",ROUND(SUMIFS($O$11:O31,$N$11:N31,$N31),2)) | Z31: =IF($N31="","",ROUND(SUMIFS(数据录入!$G$5:$G$4999,数据录入!$K$5:$K$4999,$N31),2)) | AA31: =IF(AND($D31="",$N31=""),"",IF(AND($D31<>"",COUNTIF(基础资料!$E:$E,$D31)=0),"客户名不在基础资料里",IF(AND($E31<>"",COUNTIF(基础资料!$B:$B,$E31)=0),"产品名不在基础资料里",IF(AND($N31<>"",COUNTIF(基础资料!$G:$G,$N31)=0),"供货商不在基础资料里",IF(AND($C31<>"",ISNUMBER($C31),$C31<10000),"客户生日填得不对（不是日期）",IF(N($J31)>N($F31),"销售费用大于销售金额",IF(AND($D31<>"",COUNTIF(数据录入!$J$5:$J$4999,$D31)=0,N($T31)<>0),"用的还是原手工已收款",IF(AND($D31<>"",COUNTIF(数据录入!$J$5:$J$4999,$D31)>0,ROUND(N($G31)-N($T31),2)<>0,N($T31)<>0),"自动算的已收款和原手工数对不上","√"))))))))
A32: =IF(AND($D32="",$N32=""),"",MAX($A$10:A31)+1) | C32: 46309 | D32: 李小琴 | G32: =IF($D32="","",IF(COUNTIF(数据录入!$J$5:$J$4999,$D32)=0,N($T32),ROUND(MIN(MAX(0,N($W32)-(N($V32)-N($U32))),N($U32)),2))) | H32: =IF($D32="","",ROUND(N($F32)-N($G32)-N($J32),2)) | I32: =IF($D32="","",ROUND(SUM($H$11:H32),2)) | P32: =IF($N32="","",IF(COUNTIF(数据录入!$K$5:$K$4999,$N32)=0,N($X32),ROUND(MIN(MAX(0,N($Z32)-(N($Y32)-N($O32))),N($O32)),2))) | Q32: =IF($N32="","",ROUND(N($O32)-N($P32),2)) | R32: =IF($N32="","",ROUND(SUM($Q$11:Q32),2)) | U32: =IF($D32="","",ROUND(N($F32)-N($J32),2)) | V32: =IF($D32="","",ROUND(SUMIFS($F$11:F32,$D$11:D32,$D32)-SUMIFS($J$11:J32,$D$11:D32,$D32),2)) | W32: =IF($D32="","",ROUND(SUMIFS(数据录入!$F$5:$F$4999,数据录入!$J$5:$J$4999,$D32),2)) | Y32: =IF($N32="","",ROUND(SUMIFS($O$11:O32,$N$11:N32,$N32),2)) | Z32: =IF($N32="","",ROUND(SUMIFS(数据录入!$G$5:$G$4999,数据录入!$K$5:$K$4999,$N32),2)) | AA32: =IF(AND($D32="",$N32=""),"",IF(AND($D32<>"",COUNTIF(基础资料!$E:$E,$D32)=0),"客户名不在基础资料里",IF(AND($E32<>"",COUNTIF(基础资料!$B:$B,$E32)=0),"产品名不在基础资料里",IF(AND($N32<>"",COUNTIF(基础资料!$G:$G,$N32)=0),"供货商不在基础资料里",IF(AND($C32<>"",ISNUMBER($C32),$C32<10000),"客户生日填得不对（不是日期）",IF(N($J32)>N($F32),"销售费用大于销售金额",IF(AND($D32<>"",COUNTIF(数据录入!$J$5:$J$4999,$D32)=0,N($T32)<>0),"用的还是原手工已收款",IF(AND($D32<>"",COUNTIF(数据录入!$J$5:$J$4999,$D32)>0,ROUND(N($G32)-N($T32),2)<>0,N($T32)<>0),"自动算的已收款和原手工数对不上","√"))))))))
A33: =IF(AND($D33="",$N33=""),"",MAX($A$10:A32)+1) | C33: 46318 | D33: 郁建红 | G33: =IF($D33="","",IF(COUNTIF(数据录入!$J$5:$J$4999,$D33)=0,N($T33),ROUND(MIN(MAX(0,N($W33)-(N($V33)-N($U33))),N($U33)),2))) | H33: =IF($D33="","",ROUND(N($F33)-N($G33)-N($J33),2)) | I33: =IF($D33="","",ROUND(SUM($H$11:H33),2)) | P33: =IF($N33="","",IF(COUNTIF(数据录入!$K$5:$K$4999,$N33)=0,N($X33),ROUND(MIN(MAX(0,N($Z33)-(N($Y33)-N($O33))),N($O33)),2))) | Q33: =IF($N33="","",ROUND(N($O33)-N($P33),2)) | R33: =IF($N33="","",ROUND(SUM($Q$11:Q33),2)) | U33: =IF($D33="","",ROUND(N($F33)-N($J33),2)) | V33: =IF($D33="","",ROUND(SUMIFS($F$11:F33,$D$11:D33,$D33)-SUMIFS($J$11:J33,$D$11:D33,$D33),2)) | W33: =IF($D33="","",ROUND(SUMIFS(数据录入!$F$5:$F$4999,数据录入!$J$5:$J$4999,$D33),2)) | Y33: =IF($N33="","",ROUND(SUMIFS($O$11:O33,$N$11:N33,$N33),2)) | Z33: =IF($N33="","",ROUND(SUMIFS(数据录入!$G$5:$G$4999,数据录入!$K$5:$K$4999,$N33),2)) | AA33: =IF(AND($D33="",$N33=""),"",IF(AND($D33<>"",COUNTIF(基础资料!$E:$E,$D33)=0),"客户名不在基础资料里",IF(AND($E33<>"",COUNTIF(基础资料!$B:$B,$E33)=0),"产品名不在基础资料里",IF(AND($N33<>"",COUNTIF(基础资料!$G:$G,$N33)=0),"供货商不在基础资料里",IF(AND($C33<>"",ISNUMBER($C33),$C33<10000),"客户生日填得不对（不是日期）",IF(N($J33)>N($F33),"销售费用大于销售金额",IF(AND($D33<>"",COUNTIF(数据录入!$J$5:$J$4999,$D33)=0,N($T33)<>0),"用的还是原手工已收款",IF(AND($D33<>"",COUNTIF(数据录入!$J$5:$J$4999,$D33)>0,ROUND(N($G33)-N($T33),2)<>0,N($T33)<>0),"自动算的已收款和原手工数对不上","√"))))))))
A34: =IF(AND($D34="",$N34=""),"",MAX($A$10:A33)+1) | C34: 10月30日 2月3日 | D34: 姜蓉兰 洪宗邦 | G34: =IF($D34="","",IF(COUNTIF(数据录入!$J$5:$J$4999,$D34)=0,N($T34),ROUND(MIN(MAX(0,N($W34)-(N($V34)-N($U34))),N($U34)),2))) | H34: =IF($D34="","",ROUND(N($F34)-N($G34)-N($J34),2)) | I34: =IF($D34="","",ROUND(SUM($H$11:H34),2)) | P34: =IF($N34="","",IF(COUNTIF(数据录入!$K$5:$K$4999,$N34)=0,N($X34),ROUND(MIN(MAX(0,N($Z34)-(N($Y34)-N($O34))),N($O34)),2))) | Q34: =IF($N34="","",ROUND(N($O34)-N($P34),2)) | R34: =IF($N34="","",ROUND(SUM($Q$11:Q34),2)) | U34: =IF($D34="","",ROUND(N($F34)-N($J34),2)) | V34: =IF($D34="","",ROUND(SUMIFS($F$11:F34,$D$11:D34,$D34)-SUMIFS($J$11:J34,$D$11:D34,$D34),2)) | W34: =IF($D34="","",ROUND(SUMIFS(数据录入!$F$5:$F$4999,数据录入!$J$5:$J$4999,$D34),2)) | Y34: =IF($N34="","",ROUND(SUMIFS($O$11:O34,$N$11:N34,$N34),2)) | Z34: =IF($N34="","",ROUND(SUMIFS(数据录入!$G$5:$G$4999,数据录入!$K$5:$K$4999,$N34),2)) | AA34: =IF(AND($D34="",$N34=""),"",IF(AND($D34<>"",COUNTIF(基础资料!$E:$E,$D34)=0),"客户名不在基础资料里",IF(AND($E34<>"",COUNTIF(基础资料!$B:$B,$E34)=0),"产品名不在基础资料里",IF(AND($N34<>"",COUNTIF(基础资料!$G:$G,$N34)=0),"供货商不在基础资料里",IF(AND($C34<>"",ISNUMBER($C34),$C34<10000),"客户生日填得不对（不是日期）",IF(N($J34)>N($F34),"销售费用大于销售金额",IF(AND($D34<>"",COUNTIF(数据录入!$J$5:$J$4999,$D34)=0,N($T34)<>0),"用的还是原手工已收款",IF(AND($D34<>"",COUNTIF(数据录入!$J$5:$J$4999,$D34)>0,ROUND(N($G34)-N($T34),2)<>0,N($T34)<>0),"自动算的已收款和原手工数对不上","√"))))))))
A35: =IF(AND($D35="",$N35=""),"",MAX($A$10:A34)+1) | C35: 46329 | D35: 过承祁 | G35: =IF($D35="","",IF(COUNTIF(数据录入!$J$5:$J$4999,$D35)=0,N($T35),ROUND(MIN(MAX(0,N($W35)-(N($V35)-N($U35))),N($U35)),2))) | H35: =IF($D35="","",ROUND(N($F35)-N($G35)-N($J35),2)) | I35: =IF($D35="","",ROUND(SUM($H$11:H35),2)) | P35: =IF($N35="","",IF(COUNTIF(数据录入!$K$5:$K$4999,$N35)=0,N($X35),ROUND(MIN(MAX(0,N($Z35)-(N($Y35)-N($O35))),N($O35)),2))) | Q35: =IF($N35="","",ROUND(N($O35)-N($P35),2)) | R35: =IF($N35="","",ROUND(SUM($Q$11:Q35),2)) | U35: =IF($D35="","",ROUND(N($F35)-N($J35),2)) | V35: =IF($D35="","",ROUND(SUMIFS($F$11:F35,$D$11:D35,$D35)-SUMIFS($J$11:J35,$D$11:D35,$D35),2)) | W35: =IF($D35="","",ROUND(SUMIFS(数据录入!$F$5:$F$4999,数据录入!$J$5:$J$4999,$D35),2)) | Y35: =IF($N35="","",ROUND(SUMIFS($O$11:O35,$N$11:N35,$N35),2)) | Z35: =IF($N35="","",ROUND(SUMIFS(数据录入!$G$5:$G$4999,数据录入!$K$5:$K$4999,$N35),2)) | AA35: =IF(AND($D35="",$N35=""),"",IF(AND($D35<>"",COUNTIF(基础资料!$E:$E,$D35)=0),"客户名不在基础资料里",IF(AND($E35<>"",COUNTIF(基础资料!$B:$B,$E35)=0),"产品名不在基础资料里",IF(AND($N35<>"",COUNTIF(基础资料!$G:$G,$N35)=0),"供货商不在基础资料里",IF(AND($C35<>"",ISNUMBER($C35),$C35<10000),"客户生日填得不对（不是日期）",IF(N($J35)>N($F35),"销售费用大于销售金额",IF(AND($D35<>"",COUNTIF(数据录入!$J$5:$J$4999,$D35)=0,N($T35)<>0),"用的还是原手工已收款",IF(AND($D35<>"",COUNTIF(数据录入!$J$5:$J$4999,$D35)>0,ROUND(N($G35)-N($T35),2)<>0,N($T35)<>0),"自动算的已收款和原手工数对不上","√"))))))))
A36: =IF(AND($D36="",$N36=""),"",MAX($A$10:A35)+1) | C36: 46330 | D36: 郑江宏 | G36: =IF($D36="","",IF(COUNTIF(数据录入!$J$5:$J$4999,$D36)=0,N($T36),ROUND(MIN(MAX(0,N($W36)-(N($V36)-N($U36))),N($U36)),2))) | H36: =IF($D36="","",ROUND(N($F36)-N($G36)-N($J36),2)) | I36: =IF($D36="","",ROUND(SUM($H$11:H36),2)) | P36: =IF($N36="","",IF(COUNTIF(数据录入!$K$5:$K$4999,$N36)=0,N($X36),ROUND(MIN(MAX(0,N($Z36)-(N($Y36)-N($O36))),N($O36)),2))) | Q36: =IF($N36="","",ROUND(N($O36)-N($P36),2)) | R36: =IF($N36="","",ROUND(SUM($Q$11:Q36),2)) | U36: =IF($D36="","",ROUND(N($F36)-N($J36),2)) | V36: =IF($D36="","",ROUND(SUMIFS($F$11:F36,$D$11:D36,$D36)-SUMIFS($J$11:J36,$D$11:D36,$D36),2)) | W36: =IF($D36="","",ROUND(SUMIFS(数据录入!$F$5:$F$4999,数据录入!$J$5:$J$4999,$D36),2)) | Y36: =IF($N36="","",ROUND(SUMIFS($O$11:O36,$N$11:N36,$N36),2)) | Z36: =IF($N36="","",ROUND(SUMIFS(数据录入!$G$5:$G$4999,数据录入!$K$5:$K$4999,$N36),2)) | AA36: =IF(AND($D36="",$N36=""),"",IF(AND($D36<>"",COUNTIF(基础资料!$E:$E,$D36)=0),"客户名不在基础资料里",IF(AND($E36<>"",COUNTIF(基础资料!$B:$B,$E36)=0),"产品名不在基础资料里",IF(AND($N36<>"",COUNTIF(基础资料!$G:$G,$N36)=0),"供货商不在基础资料里",IF(AND($C36<>"",ISNUMBER($C36),$C36<10000),"客户生日填得不对（不是日期）",IF(N($J36)>N($F36),"销售费用大于销售金额",IF(AND($D36<>"",COUNTIF(数据录入!$J$5:$J$4999,$D36)=0,N($T36)<>0),"用的还是原手工已收款",IF(AND($D36<>"",COUNTIF(数据录入!$J$5:$J$4999,$D36)>0,ROUND(N($G36)-N($T36),2)<>0,N($T36)<>0),"自动算的已收款和原手工数对不上","√"))))))))
A37: =IF(AND($D37="",$N37=""),"",MAX($A$10:A36)+1) | C37: 46338 | D37: 姜志鸿 | G37: =IF($D37="","",IF(COUNTIF(数据录入!$J$5:$J$4999,$D37)=0,N($T37),ROUND(MIN(MAX(0,N($W37)-(N($V37)-N($U37))),N($U37)),2))) | H37: =IF($D37="","",ROUND(N($F37)-N($G37)-N($J37),2)) | I37: =IF($D37="","",ROUND(SUM($H$11:H37),2)) | P37: =IF($N37="","",IF(COUNTIF(数据录入!$K$5:$K$4999,$N37)=0,N($X37),ROUND(MIN(MAX(0,N($Z37)-(N($Y37)-N($O37))),N($O37)),2))) | Q37: =IF($N37="","",ROUND(N($O37)-N($P37),2)) | R37: =IF($N37="","",ROUND(SUM($Q$11:Q37),2)) | U37: =IF($D37="","",ROUND(N($F37)-N($J37),2)) | V37: =IF($D37="","",ROUND(SUMIFS($F$11:F37,$D$11:D37,$D37)-SUMIFS($J$11:J37,$D$11:D37,$D37),2)) | W37: =IF($D37="","",ROUND(SUMIFS(数据录入!$F$5:$F$4999,数据录入!$J$5:$J$4999,$D37),2)) | Y37: =IF($N37="","",ROUND(SUMIFS($O$11:O37,$N$11:N37,$N37),2)) | Z37: =IF($N37="","",ROUND(SUMIFS(数据录入!$G$5:$G$4999,数据录入!$K$5:$K$4999,$N37),2)) | AA37: =IF(AND($D37="",$N37=""),"",IF(AND($D37<>"",COUNTIF(基础资料!$E:$E,$D37)=0),"客户名不在基础资料里",IF(AND($E37<>"",COUNTIF(基础资料!$B:$B,$E37)=0),"产品名不在基础资料里",IF(AND($N37<>"",COUNTIF(基础资料!$G:$G,$N37)=0),"供货商不在基础资料里",IF(AND($C37<>"",ISNUMBER($C37),$C37<10000),"客户生日填得不对（不是日期）",IF(N($J37)>N($F37),"销售费用大于销售金额",IF(AND($D37<>"",COUNTIF(数据录入!$J$5:$J$4999,$D37)=0,N($T37)<>0),"用的还是原手工已收款",IF(AND($D37<>"",COUNTIF(数据录入!$J$5:$J$4999,$D37)>0,ROUND(N($G37)-N($T37),2)<>0,N($T37)<>0),"自动算的已收款和原手工数对不上","√"))))))))
A38: =IF(AND($D38="",$N38=""),"",MAX($A$10:A37)+1) | C38: 46338 | D38: 吴旭红 | G38: =IF($D38="","",IF(COUNTIF(数据录入!$J$5:$J$4999,$D38)=0,N($T38),ROUND(MIN(MAX(0,N($W38)-(N($V38)-N($U38))),N($U38)),2))) | H38: =IF($D38="","",ROUND(N($F38)-N($G38)-N($J38),2)) | I38: =IF($D38="","",ROUND(SUM($H$11:H38),2)) | P38: =IF($N38="","",IF(COUNTIF(数据录入!$K$5:$K$4999,$N38)=0,N($X38),ROUND(MIN(MAX(0,N($Z38)-(N($Y38)-N($O38))),N($O38)),2))) | Q38: =IF($N38="","",ROUND(N($O38)-N($P38),2)) | R38: =IF($N38="","",ROUND(SUM($Q$11:Q38),2)) | U38: =IF($D38="","",ROUND(N($F38)-N($J38),2)) | V38: =IF($D38="","",ROUND(SUMIFS($F$11:F38,$D$11:D38,$D38)-SUMIFS($J$11:J38,$D$11:D38,$D38),2)) | W38: =IF($D38="","",ROUND(SUMIFS(数据录入!$F$5:$F$4999,数据录入!$J$5:$J$4999,$D38),2)) | Y38: =IF($N38="","",ROUND(SUMIFS($O$11:O38,$N$11:N38,$N38),2)) | Z38: =IF($N38="","",ROUND(SUMIFS(数据录入!$G$5:$G$4999,数据录入!$K$5:$K$4999,$N38),2)) | AA38: =IF(AND($D38="",$N38=""),"",IF(AND($D38<>"",COUNTIF(基础资料!$E:$E,$D38)=0),"客户名不在基础资料里",IF(AND($E38<>"",COUNTIF(基础资料!$B:$B,$E38)=0),"产品名不在基础资料里",IF(AND($N38<>"",COUNTIF(基础资料!$G:$G,$N38)=0),"供货商不在基础资料里",IF(AND($C38<>"",ISNUMBER($C38),$C38<10000),"客户生日填得不对（不是日期）",IF(N($J38)>N($F38),"销售费用大于销售金额",IF(AND($D38<>"",COUNTIF(数据录入!$J$5:$J$4999,$D38)=0,N($T38)<>0),"用的还是原手工已收款",IF(AND($D38<>"",COUNTIF(数据录入!$J$5:$J$4999,$D38)>0,ROUND(N($G38)-N($T38),2)<>0,N($T38)<>0),"自动算的已收款和原手工数对不上","√"))))))))
A39: =IF(AND($D39="",$N39=""),"",MAX($A$10:A38)+1) | C39: 46342 | D39: 丁爱妹 | G39: =IF($D39="","",IF(COUNTIF(数据录入!$J$5:$J$4999,$D39)=0,N($T39),ROUND(MIN(MAX(0,N($W39)-(N($V39)-N($U39))),N($U39)),2))) | H39: =IF($D39="","",ROUND(N($F39)-N($G39)-N($J39),2)) | I39: =IF($D39="","",ROUND(SUM($H$11:H39),2)) | P39: =IF($N39="","",IF(COUNTIF(数据录入!$K$5:$K$4999,$N39)=0,N($X39),ROUND(MIN(MAX(0,N($Z39)-(N($Y39)-N($O39))),N($O39)),2))) | Q39: =IF($N39="","",ROUND(N($O39)-N($P39),2)) | R39: =IF($N39="","",ROUND(SUM($Q$11:Q39),2)) | U39: =IF($D39="","",ROUND(N($F39)-N($J39),2)) | V39: =IF($D39="","",ROUND(SUMIFS($F$11:F39,$D$11:D39,$D39)-SUMIFS($J$11:J39,$D$11:D39,$D39),2)) | W39: =IF($D39="","",ROUND(SUMIFS(数据录入!$F$5:$F$4999,数据录入!$J$5:$J$4999,$D39),2)) | Y39: =IF($N39="","",ROUND(SUMIFS($O$11:O39,$N$11:N39,$N39),2)) | Z39: =IF($N39="","",ROUND(SUMIFS(数据录入!$G$5:$G$4999,数据录入!$K$5:$K$4999,$N39),2)) | AA39: =IF(AND($D39="",$N39=""),"",IF(AND($D39<>"",COUNTIF(基础资料!$E:$E,$D39)=0),"客户名不在基础资料里",IF(AND($E39<>"",COUNTIF(基础资料!$B:$B,$E39)=0),"产品名不在基础资料里",IF(AND($N39<>"",COUNTIF(基础资料!$G:$G,$N39)=0),"供货商不在基础资料里",IF(AND($C39<>"",ISNUMBER($C39),$C39<10000),"客户生日填得不对（不是日期）",IF(N($J39)>N($F39),"销售费用大于销售金额",IF(AND($D39<>"",COUNTIF(数据录入!$J$5:$J$4999,$D39)=0,N($T39)<>0),"用的还是原手工已收款",IF(AND($D39<>"",COUNTIF(数据录入!$J$5:$J$4999,$D39)>0,ROUND(N($G39)-N($T39),2)<>0,N($T39)<>0),"自动算的已收款和原手工数对不上","√"))))))))
A40: =IF(AND($D40="",$N40=""),"",MAX($A$10:A39)+1) | C40: 46351 | D40: 鄢桂香 | G40: =IF($D40="","",IF(COUNTIF(数据录入!$J$5:$J$4999,$D40)=0,N($T40),ROUND(MIN(MAX(0,N($W40)-(N($V40)-N($U40))),N($U40)),2))) | H40: =IF($D40="","",ROUND(N($F40)-N($G40)-N($J40),2)) | I40: =IF($D40="","",ROUND(SUM($H$11:H40),2)) | P40: =IF($N40="","",IF(COUNTIF(数据录入!$K$5:$K$4999,$N40)=0,N($X40),ROUND(MIN(MAX(0,N($Z40)-(N($Y40)-N($O40))),N($O40)),2))) | Q40: =IF($N40="","",ROUND(N($O40)-N($P40),2)) | R40: =IF($N40="","",ROUND(SUM($Q$11:Q40),2)) | U40: =IF($D40="","",ROUND(N($F40)-N($J40),2)) | V40: =IF($D40="","",ROUND(SUMIFS($F$11:F40,$D$11:D40,$D40)-SUMIFS($J$11:J40,$D$11:D40,$D40),2)) | W40: =IF($D40="","",ROUND(SUMIFS(数据录入!$F$5:$F$4999,数据录入!$J$5:$J$4999,$D40),2)) | Y40: =IF($N40="","",ROUND(SUMIFS($O$11:O40,$N$11:N40,$N40),2)) | Z40: =IF($N40="","",ROUND(SUMIFS(数据录入!$G$5:$G$4999,数据录入!$K$5:$K$4999,$N40),2)) | AA40: =IF(AND($D40="",$N40=""),"",IF(AND($D40<>"",COUNTIF(基础资料!$E:$E,$D40)=0),"客户名不在基础资料里",IF(AND($E40<>"",COUNTIF(基础资料!$B:$B,$E40)=0),"产品名不在基础资料里",IF(AND($N40<>"",COUNTIF(基础资料!$G:$G,$N40)=0),"供货商不在基础资料里",IF(AND($C40<>"",ISNUMBER($C40),$C40<10000),"客户生日填得不对（不是日期）",IF(N($J40)>N($F40),"销售费用大于销售金额",IF(AND($D40<>"",COUNTIF(数据录入!$J$5:$J$4999,$D40)=0,N($T40)<>0),"用的还是原手工已收款",IF(AND($D40<>"",COUNTIF(数据录入!$J$5:$J$4999,$D40)>0,ROUND(N($G40)-N($T40),2)<>0,N($T40)<>0),"自动算的已收款和原手工数对不上","√"))))))))
A41: =IF(AND($D41="",$N41=""),"",MAX($A$10:A40)+1) | C41: 46353 | D41: 傅荣姣 | G41: =IF($D41="","",IF(COUNTIF(数据录入!$J$5:$J$4999,$D41)=0,N($T41),ROUND(MIN(MAX(0,N($W41)-(N($V41)-N($U41))),N($U41)),2))) | H41: =IF($D41="","",ROUND(N($F41)-N($G41)-N($J41),2)) | I41: =IF($D41="","",ROUND(SUM($H$11:H41),2)) | P41: =IF($N41="","",IF(COUNTIF(数据录入!$K$5:$K$4999,$N41)=0,N($X41),ROUND(MIN(MAX(0,N($Z41)-(N($Y41)-N($O41))),N($O41)),2))) | Q41: =IF($N41="","",ROUND(N($O41)-N($P41),2)) | R41: =IF($N41="","",ROUND(SUM($Q$11:Q41),2)) | U41: =IF($D41="","",ROUND(N($F41)-N($J41),2)) | V41: =IF($D41="","",ROUND(SUMIFS($F$11:F41,$D$11:D41,$D41)-SUMIFS($J$11:J41,$D$11:D41,$D41),2)) | W41: =IF($D41="","",ROUND(SUMIFS(数据录入!$F$5:$F$4999,数据录入!$J$5:$J$4999,$D41),2)) | Y41: =IF($N41="","",ROUND(SUMIFS($O$11:O41,$N$11:N41,$N41),2)) | Z41: =IF($N41="","",ROUND(SUMIFS(数据录入!$G$5:$G$4999,数据录入!$K$5:$K$4999,$N41),2)) | AA41: =IF(AND($D41="",$N41=""),"",IF(AND($D41<>"",COUNTIF(基础资料!$E:$E,$D41)=0),"客户名不在基础资料里",IF(AND($E41<>"",COUNTIF(基础资料!$B:$B,$E41)=0),"产品名不在基础资料里",IF(AND($N41<>"",COUNTIF(基础资料!$G:$G,$N41)=0),"供货商不在基础资料里",IF(AND($C41<>"",ISNUMBER($C41),$C41<10000),"客户生日填得不对（不是日期）",IF(N($J41)>N($F41),"销售费用大于销售金额",IF(AND($D41<>"",COUNTIF(数据录入!$J$5:$J$4999,$D41)=0,N($T41)<>0),"用的还是原手工已收款",IF(AND($D41<>"",COUNTIF(数据录入!$J$5:$J$4999,$D41)>0,ROUND(N($G41)-N($T41),2)<>0,N($T41)<>0),"自动算的已收款和原手工数对不上","√"))))))))
A42: =IF(AND($D42="",$N42=""),"",MAX($A$10:A41)+1) | C42: 46354 | D42: 陆玉英 | G42: =IF($D42="","",IF(COUNTIF(数据录入!$J$5:$J$4999,$D42)=0,N($T42),ROUND(MIN(MAX(0,N($W42)-(N($V42)-N($U42))),N($U42)),2))) | H42: =IF($D42="","",ROUND(N($F42)-N($G42)-N($J42),2)) | I42: =IF($D42="","",ROUND(SUM($H$11:H42),2)) | P42: =IF($N42="","",IF(COUNTIF(数据录入!$K$5:$K$4999,$N42)=0,N($X42),ROUND(MIN(MAX(0,N($Z42)-(N($Y42)-N($O42))),N($O42)),2))) | Q42: =IF($N42="","",ROUND(N($O42)-N($P42),2)) | R42: =IF($N42="","",ROUND(SUM($Q$11:Q42),2)) | U42: =IF($D42="","",ROUND(N($F42)-N($J42),2)) | V42: =IF($D42="","",ROUND(SUMIFS($F$11:F42,$D$11:D42,$D42)-SUMIFS($J$11:J42,$D$11:D42,$D42),2)) | W42: =IF($D42="","",ROUND(SUMIFS(数据录入!$F$5:$F$4999,数据录入!$J$5:$J$4999,$D42),2)) | Y42: =IF($N42="","",ROUND(SUMIFS($O$11:O42,$N$11:N42,$N42),2)) | Z42: =IF($N42="","",ROUND(SUMIFS(数据录入!$G$5:$G$4999,数据录入!$K$5:$K$4999,$N42),2)) | AA42: =IF(AND($D42="",$N42=""),"",IF(AND($D42<>"",COUNTIF(基础资料!$E:$E,$D42)=0),"客户名不在基础资料里",IF(AND($E42<>"",COUNTIF(基础资料!$B:$B,$E42)=0),"产品名不在基础资料里",IF(AND($N42<>"",COUNTIF(基础资料!$G:$G,$N42)=0),"供货商不在基础资料里",IF(AND($C42<>"",ISNUMBER($C42),$C42<10000),"客户生日填得不对（不是日期）",IF(N($J42)>N($F42),"销售费用大于销售金额",IF(AND($D42<>"",COUNTIF(数据录入!$J$5:$J$4999,$D42)=0,N($T42)<>0),"用的还是原手工已收款",IF(AND($D42<>"",COUNTIF(数据录入!$J$5:$J$4999,$D42)>0,ROUND(N($G42)-N($T42),2)<>0,N($T42)<>0),"自动算的已收款和原手工数对不上","√"))))))))
A43: =IF(AND($D43="",$N43=""),"",MAX($A$10:A42)+1) | C43: 46361 | D43: 祝晓琳 | G43: =IF($D43="","",IF(COUNTIF(数据录入!$J$5:$J$4999,$D43)=0,N($T43),ROUND(MIN(MAX(0,N($W43)-(N($V43)-N($U43))),N($U43)),2))) | H43: =IF($D43="","",ROUND(N($F43)-N($G43)-N($J43),2)) | I43: =IF($D43="","",ROUND(SUM($H$11:H43),2)) | P43: =IF($N43="","",IF(COUNTIF(数据录入!$K$5:$K$4999,$N43)=0,N($X43),ROUND(MIN(MAX(0,N($Z43)-(N($Y43)-N($O43))),N($O43)),2))) | Q43: =IF($N43="","",ROUND(N($O43)-N($P43),2)) | R43: =IF($N43="","",ROUND(SUM($Q$11:Q43),2)) | U43: =IF($D43="","",ROUND(N($F43)-N($J43),2)) | V43: =IF($D43="","",ROUND(SUMIFS($F$11:F43,$D$11:D43,$D43)-SUMIFS($J$11:J43,$D$11:D43,$D43),2)) | W43: =IF($D43="","",ROUND(SUMIFS(数据录入!$F$5:$F$4999,数据录入!$J$5:$J$4999,$D43),2)) | Y43: =IF($N43="","",ROUND(SUMIFS($O$11:O43,$N$11:N43,$N43),2)) | Z43: =IF($N43="","",ROUND(SUMIFS(数据录入!$G$5:$G$4999,数据录入!$K$5:$K$4999,$N43),2)) | AA43: =IF(AND($D43="",$N43=""),"",IF(AND($D43<>"",COUNTIF(基础资料!$E:$E,$D43)=0),"客户名不在基础资料里",IF(AND($E43<>"",COUNTIF(基础资料!$B:$B,$E43)=0),"产品名不在基础资料里",IF(AND($N43<>"",COUNTIF(基础资料!$G:$G,$N43)=0),"供货商不在基础资料里",IF(AND($C43<>"",ISNUMBER($C43),$C43<10000),"客户生日填得不对（不是日期）",IF(N($J43)>N($F43),"销售费用大于销售金额",IF(AND($D43<>"",COUNTIF(数据录入!$J$5:$J$4999,$D43)=0,N($T43)<>0),"用的还是原手工已收款",IF(AND($D43<>"",COUNTIF(数据录入!$J$5:$J$4999,$D43)>0,ROUND(N($G43)-N($T43),2)<>0,N($T43)<>0),"自动算的已收款和原手工数对不上","√"))))))))
A44: =IF(AND($D44="",$N44=""),"",MAX($A$10:A43)+1) | C44: 46362 | D44: 章小英 | G44: =IF($D44="","",IF(COUNTIF(数据录入!$J$5:$J$4999,$D44)=0,N($T44),ROUND(MIN(MAX(0,N($W44)-(N($V44)-N($U44))),N($U44)),2))) | H44: =IF($D44="","",ROUND(N($F44)-N($G44)-N($J44),2)) | I44: =IF($D44="","",ROUND(SUM($H$11:H44),2)) | P44: =IF($N44="","",IF(COUNTIF(数据录入!$K$5:$K$4999,$N44)=0,N($X44),ROUND(MIN(MAX(0,N($Z44)-(N($Y44)-N($O44))),N($O44)),2))) | Q44: =IF($N44="","",ROUND(N($O44)-N($P44),2)) | R44: =IF($N44="","",ROUND(SUM($Q$11:Q44),2)) | U44: =IF($D44="","",ROUND(N($F44)-N($J44),2)) | V44: =IF($D44="","",ROUND(SUMIFS($F$11:F44,$D$11:D44,$D44)-SUMIFS($J$11:J44,$D$11:D44,$D44),2)) | W44: =IF($D44="","",ROUND(SUMIFS(数据录入!$F$5:$F$4999,数据录入!$J$5:$J$4999,$D44),2)) | Y44: =IF($N44="","",ROUND(SUMIFS($O$11:O44,$N$11:N44,$N44),2)) | Z44: =IF($N44="","",ROUND(SUMIFS(数据录入!$G$5:$G$4999,数据录入!$K$5:$K$4999,$N44),2)) | AA44: =IF(AND($D44="",$N44=""),"",IF(AND($D44<>"",COUNTIF(基础资料!$E:$E,$D44)=0),"客户名不在基础资料里",IF(AND($E44<>"",COUNTIF(基础资料!$B:$B,$E44)=0),"产品名不在基础资料里",IF(AND($N44<>"",COUNTIF(基础资料!$G:$G,$N44)=0),"供货商不在基础资料里",IF(AND($C44<>"",ISNUMBER($C44),$C44<10000),"客户生日填得不对（不是日期）",IF(N($J44)>N($F44),"销售费用大于销售金额",IF(AND($D44<>"",COUNTIF(数据录入!$J$5:$J$4999,$D44)=0,N($T44)<>0),"用的还是原手工已收款",IF(AND($D44<>"",COUNTIF(数据录入!$J$5:$J$4999,$D44)>0,ROUND(N($G44)-N($T44),2)<>0,N($T44)<>0),"自动算的已收款和原手工数对不上","√"))))))))
A45: =IF(AND($D45="",$N45=""),"",MAX($A$10:A44)+1) | C45: 10 | D45: 赵庆仙 | G45: =IF($D45="","",IF(COUNTIF(数据录入!$J$5:$J$4999,$D45)=0,N($T45),ROUND(MIN(MAX(0,N($W45)-(N($V45)-N($U45))),N($U45)),2))) | H45: =IF($D45="","",ROUND(N($F45)-N($G45)-N($J45),2)) | I45: =IF($D45="","",ROUND(SUM($H$11:H45),2)) | P45: =IF($N45="","",IF(COUNTIF(数据录入!$K$5:$K$4999,$N45)=0,N($X45),ROUND(MIN(MAX(0,N($Z45)-(N($Y45)-N($O45))),N($O45)),2))) | Q45: =IF($N45="","",ROUND(N($O45)-N($P45),2)) | R45: =IF($N45="","",ROUND(SUM($Q$11:Q45),2)) | U45: =IF($D45="","",ROUND(N($F45)-N($J45),2)) | V45: =IF($D45="","",ROUND(SUMIFS($F$11:F45,$D$11:D45,$D45)-SUMIFS($J$11:J45,$D$11:D45,$D45),2)) | W45: =IF($D45="","",ROUND(SUMIFS(数据录入!$F$5:$F$4999,数据录入!$J$5:$J$4999,$D45),2)) | Y45: =IF($N45="","",ROUND(SUMIFS($O$11:O45,$N$11:N45,$N45),2)) | Z45: =IF($N45="","",ROUND(SUMIFS(数据录入!$G$5:$G$4999,数据录入!$K$5:$K$4999,$N45),2)) | AA45: =IF(AND($D45="",$N45=""),"",IF(AND($D45<>"",COUNTIF(基础资料!$E:$E,$D45)=0),"客户名不在基础资料里",IF(AND($E45<>"",COUNTIF(基础资料!$B:$B,$E45)=0),"产品名不在基础资料里",IF(AND($N45<>"",COUNTIF(基础资料!$G:$G,$N45)=0),"供货商不在基础资料里",IF(AND($C45<>"",ISNUMBER($C45),$C45<10000),"客户生日填得不对（不是日期）",IF(N($J45)>N($F45),"销售费用大于销售金额",IF(AND($D45<>"",COUNTIF(数据录入!$J$5:$J$4999,$D45)=0,N($T45)<>0),"用的还是原手工已收款",IF(AND($D45<>"",COUNTIF(数据录入!$J$5:$J$4999,$D45)>0,ROUND(N($G45)-N($T45),2)<>0,N($T45)<>0),"自动算的已收款和原手工数对不上","√"))))))))
A46: =IF(AND($D46="",$N46=""),"",MAX($A$10:A45)+1) | G46: =IF($D46="","",IF(COUNTIF(数据录入!$J$5:$J$4999,$D46)=0,N($T46),ROUND(MIN(MAX(0,N($W46)-(N($V46)-N($U46))),N($U46)),2))) | H46: =IF($D46="","",ROUND(N($F46)-N($G46)-N($J46),2)) | I46: =IF($D46="","",ROUND(SUM($H$11:H46),2)) | P46: =IF($N46="","",IF(COUNTIF(数据录入!$K$5:$K$4999,$N46)=0,N($X46),ROUND(MIN(MAX(0,N($Z46)-(N($Y46)-N($O46))),N($O46)),2))) | Q46: =IF($N46="","",ROUND(N($O46)-N($P46),2)) | R46: =IF($N46="","",ROUND(SUM($Q$11:Q46),2)) | U46: =IF($D46="","",ROUND(N($F46)-N($J46),2)) | V46: =IF($D46="","",ROUND(SUMIFS($F$11:F46,$D$11:D46,$D46)-SUMIFS($J$11:J46,$D$11:D46,$D46),2)) | W46: =IF($D46="","",ROUND(SUMIFS(数据录入!$F$5:$F$4999,数据录入!$J$5:$J$4999,$D46),2)) | Y46: =IF($N46="","",ROUND(SUMIFS($O$11:O46,$N$11:N46,$N46),2)) | Z46: =IF($N46="","",ROUND(SUMIFS(数据录入!$G$5:$G$4999,数据录入!$K$5:$K$4999,$N46),2)) | AA46: =IF(AND($D46="",$N46=""),"",IF(AND($D46<>"",COUNTIF(基础资料!$E:$E,$D46)=0),"客户名不在基础资料里",IF(AND($E46<>"",COUNTIF(基础资料!$B:$B,$E46)=0),"产品名不在基础资料里",IF(AND($N46<>"",COUNTIF(基础资料!$G:$G,$N46)=0),"供货商不在基础资料里",IF(AND($C46<>"",ISNUMBER($C46),$C46<10000),"客户生日填得不对（不是日期）",IF(N($J46)>N($F46),"销售费用大于销售金额",IF(AND($D46<>"",COUNTIF(数据录入!$J$5:$J$4999,$D46)=0,N($T46)<>0),"用的还是原手工已收款",IF(AND($D46<>"",COUNTIF(数据录入!$J$5:$J$4999,$D46)>0,ROUND(N($G46)-N($T46),2)<>0,N($T46)<>0),"自动算的已收款和原手工数对不上","√"))))))))
A47: =IF(AND($D47="",$N47=""),"",MAX($A$10:A46)+1) | G47: =IF($D47="","",IF(COUNTIF(数据录入!$J$5:$J$4999,$D47)=0,N($T47),ROUND(MIN(MAX(0,N($W47)-(N($V47)-N($U47))),N($U47)),2))) | H47: =IF($D47="","",ROUND(N($F47)-N($G47)-N($J47),2)) | I47: =IF($D47="","",ROUND(SUM($H$11:H47),2)) | P47: =IF($N47="","",IF(COUNTIF(数据录入!$K$5:$K$4999,$N47)=0,N($X47),ROUND(MIN(MAX(0,N($Z47)-(N($Y47)-N($O47))),N($O47)),2))) | Q47: =IF($N47="","",ROUND(N($O47)-N($P47),2)) | R47: =IF($N47="","",ROUND(SUM($Q$11:Q47),2)) | U47: =IF($D47="","",ROUND(N($F47)-N($J47),2)) | V47: =IF($D47="","",ROUND(SUMIFS($F$11:F47,$D$11:D47,$D47)-SUMIFS($J$11:J47,$D$11:D47,$D47),2)) | W47: =IF($D47="","",ROUND(SUMIFS(数据录入!$F$5:$F$4999,数据录入!$J$5:$J$4999,$D47),2)) | Y47: =IF($N47="","",ROUND(SUMIFS($O$11:O47,$N$11:N47,$N47),2)) | Z47: =IF($N47="","",ROUND(SUMIFS(数据录入!$G$5:$G$4999,数据录入!$K$5:$K$4999,$N47),2)) | AA47: =IF(AND($D47="",$N47=""),"",IF(AND($D47<>"",COUNTIF(基础资料!$E:$E,$D47)=0),"客户名不在基础资料里",IF(AND($E47<>"",COUNTIF(基础资料!$B:$B,$E47)=0),"产品名不在基础资料里",IF(AND($N47<>"",COUNTIF(基础资料!$G:$G,$N47)=0),"供货商不在基础资料里",IF(AND($C47<>"",ISNUMBER($C47),$C47<10000),"客户生日填得不对（不是日期）",IF(N($J47)>N($F47),"销售费用大于销售金额",IF(AND($D47<>"",COUNTIF(数据录入!$J$5:$J$4999,$D47)=0,N($T47)<>0),"用的还是原手工已收款",IF(AND($D47<>"",COUNTIF(数据录入!$J$5:$J$4999,$D47)>0,ROUND(N($G47)-N($T47),2)<>0,N($T47)<>0),"自动算的已收款和原手工数对不上","√"))))))))
A48: =IF(AND($D48="",$N48=""),"",MAX($A$10:A47)+1) | G48: =IF($D48="","",IF(COUNTIF(数据录入!$J$5:$J$4999,$D48)=0,N($T48),ROUND(MIN(MAX(0,N($W48)-(N($V48)-N($U48))),N($U48)),2))) | H48: =IF($D48="","",ROUND(N($F48)-N($G48)-N($J48),2)) | I48: =IF($D48="","",ROUND(SUM($H$11:H48),2)) | P48: =IF($N48="","",IF(COUNTIF(数据录入!$K$5:$K$4999,$N48)=0,N($X48),ROUND(MIN(MAX(0,N($Z48)-(N($Y48)-N($O48))),N($O48)),2))) | Q48: =IF($N48="","",ROUND(N($O48)-N($P48),2)) | R48: =IF($N48="","",ROUND(SUM($Q$11:Q48),2)) | U48: =IF($D48="","",ROUND(N($F48)-N($J48),2)) | V48: =IF($D48="","",ROUND(SUMIFS($F$11:F48,$D$11:D48,$D48)-SUMIFS($J$11:J48,$D$11:D48,$D48),2)) | W48: =IF($D48="","",ROUND(SUMIFS(数据录入!$F$5:$F$4999,数据录入!$J$5:$J$4999,$D48),2)) | Y48: =IF($N48="","",ROUND(SUMIFS($O$11:O48,$N$11:N48,$N48),2)) | Z48: =IF($N48="","",ROUND(SUMIFS(数据录入!$G$5:$G$4999,数据录入!$K$5:$K$4999,$N48),2)) | AA48: =IF(AND($D48="",$N48=""),"",IF(AND($D48<>"",COUNTIF(基础资料!$E:$E,$D48)=0),"客户名不在基础资料里",IF(AND($E48<>"",COUNTIF(基础资料!$B:$B,$E48)=0),"产品名不在基础资料里",IF(AND($N48<>"",COUNTIF(基础资料!$G:$G,$N48)=0),"供货商不在基础资料里",IF(AND($C48<>"",ISNUMBER($C48),$C48<10000),"客户生日填得不对（不是日期）",IF(N($J48)>N($F48),"销售费用大于销售金额",IF(AND($D48<>"",COUNTIF(数据录入!$J$5:$J$4999,$D48)=0,N($T48)<>0),"用的还是原手工已收款",IF(AND($D48<>"",COUNTIF(数据录入!$J$5:$J$4999,$D48)>0,ROUND(N($G48)-N($T48),2)<>0,N($T48)<>0),"自动算的已收款和原手工数对不上","√"))))))))
A49: =IF(AND($D49="",$N49=""),"",MAX($A$10:A48)+1) | G49: =IF($D49="","",IF(COUNTIF(数据录入!$J$5:$J$4999,$D49)=0,N($T49),ROUND(MIN(MAX(0,N($W49)-(N($V49)-N($U49))),N($U49)),2))) | H49: =IF($D49="","",ROUND(N($F49)-N($G49)-N($J49),2)) | I49: =IF($D49="","",ROUND(SUM($H$11:H49),2)) | P49: =IF($N49="","",IF(COUNTIF(数据录入!$K$5:$K$4999,$N49)=0,N($X49),ROUND(MIN(MAX(0,N($Z49)-(N($Y49)-N($O49))),N($O49)),2))) | Q49: =IF($N49="","",ROUND(N($O49)-N($P49),2)) | R49: =IF($N49="","",ROUND(SUM($Q$11:Q49),2)) | U49: =IF($D49="","",ROUND(N($F49)-N($J49),2)) | V49: =IF($D49="","",ROUND(SUMIFS($F$11:F49,$D$11:D49,$D49)-SUMIFS($J$11:J49,$D$11:D49,$D49),2)) | W49: =IF($D49="","",ROUND(SUMIFS(数据录入!$F$5:$F$4999,数据录入!$J$5:$J$4999,$D49),2)) | Y49: =IF($N49="","",ROUND(SUMIFS($O$11:O49,$N$11:N49,$N49),2)) | Z49: =IF($N49="","",ROUND(SUMIFS(数据录入!$G$5:$G$4999,数据录入!$K$5:$K$4999,$N49),2)) | AA49: =IF(AND($D49="",$N49=""),"",IF(AND($D49<>"",COUNTIF(基础资料!$E:$E,$D49)=0),"客户名不在基础资料里",IF(AND($E49<>"",COUNTIF(基础资料!$B:$B,$E49)=0),"产品名不在基础资料里",IF(AND($N49<>"",COUNTIF(基础资料!$G:$G,$N49)=0),"供货商不在基础资料里",IF(AND($C49<>"",ISNUMBER($C49),$C49<10000),"客户生日填得不对（不是日期）",IF(N($J49)>N($F49),"销售费用大于销售金额",IF(AND($D49<>"",COUNTIF(数据录入!$J$5:$J$4999,$D49)=0,N($T49)<>0),"用的还是原手工已收款",IF(AND($D49<>"",COUNTIF(数据录入!$J$5:$J$4999,$D49)>0,ROUND(N($G49)-N($T49),2)<>0,N($T49)<>0),"自动算的已收款和原手工数对不上","√"))))))))
A50: =IF(AND($D50="",$N50=""),"",MAX($A$10:A49)+1) | G50: =IF($D50="","",IF(COUNTIF(数据录入!$J$5:$J$4999,$D50)=0,N($T50),ROUND(MIN(MAX(0,N($W50)-(N($V50)-N($U50))),N($U50)),2))) | H50: =IF($D50="","",ROUND(N($F50)-N($G50)-N($J50),2)) | I50: =IF($D50="","",ROUND(SUM($H$11:H50),2)) | P50: =IF($N50="","",IF(COUNTIF(数据录入!$K$5:$K$4999,$N50)=0,N($X50),ROUND(MIN(MAX(0,N($Z50)-(N($Y50)-N($O50))),N($O50)),2))) | Q50: =IF($N50="","",ROUND(N($O50)-N($P50),2)) | R50: =IF($N50="","",ROUND(SUM($Q$11:Q50),2)) | U50: =IF($D50="","",ROUND(N($F50)-N($J50),2)) | V50: =IF($D50="","",ROUND(SUMIFS($F$11:F50,$D$11:D50,$D50)-SUMIFS($J$11:J50,$D$11:D50,$D50),2)) | W50: =IF($D50="","",ROUND(SUMIFS(数据录入!$F$5:$F$4999,数据录入!$J$5:$J$4999,$D50),2)) | Y50: =IF($N50="","",ROUND(SUMIFS($O$11:O50,$N$11:N50,$N50),2)) | Z50: =IF($N50="","",ROUND(SUMIFS(数据录入!$G$5:$G$4999,数据录入!$K$5:$K$4999,$N50),2)) | AA50: =IF(AND($D50="",$N50=""),"",IF(AND($D50<>"",COUNTIF(基础资料!$E:$E,$D50)=0),"客户名不在基础资料里",IF(AND($E50<>"",COUNTIF(基础资料!$B:$B,$E50)=0),"产品名不在基础资料里",IF(AND($N50<>"",COUNTIF(基础资料!$G:$G,$N50)=0),"供货商不在基础资料里",IF(AND($C50<>"",ISNUMBER($C50),$C50<10000),"客户生日填得不对（不是日期）",IF(N($J50)>N($F50),"销售费用大于销售金额",IF(AND($D50<>"",COUNTIF(数据录入!$J$5:$J$4999,$D50)=0,N($T50)<>0),"用的还是原手工已收款",IF(AND($D50<>"",COUNTIF(数据录入!$J$5:$J$4999,$D50)>0,ROUND(N($G50)-N($T50),2)<>0,N($T50)<>0),"自动算的已收款和原手工数对不上","√"))))))))
A51: =IF(AND($D51="",$N51=""),"",MAX($A$10:A50)+1) | G51: =IF($D51="","",IF(COUNTIF(数据录入!$J$5:$J$4999,$D51)=0,N($T51),ROUND(MIN(MAX(0,N($W51)-(N($V51)-N($U51))),N($U51)),2))) | H51: =IF($D51="","",ROUND(N($F51)-N($G51)-N($J51),2)) | I51: =IF($D51="","",ROUND(SUM($H$11:H51),2)) | P51: =IF($N51="","",IF(COUNTIF(数据录入!$K$5:$K$4999,$N51)=0,N($X51),ROUND(MIN(MAX(0,N($Z51)-(N($Y51)-N($O51))),N($O51)),2))) | Q51: =IF($N51="","",ROUND(N($O51)-N($P51),2)) | R51: =IF($N51="","",ROUND(SUM($Q$11:Q51),2)) | U51: =IF($D51="","",ROUND(N($F51)-N($J51),2)) | V51: =IF($D51="","",ROUND(SUMIFS($F$11:F51,$D$11:D51,$D51)-SUMIFS($J$11:J51,$D$11:D51,$D51),2)) | W51: =IF($D51="","",ROUND(SUMIFS(数据录入!$F$5:$F$4999,数据录入!$J$5:$J$4999,$D51),2)) | Y51: =IF($N51="","",ROUND(SUMIFS($O$11:O51,$N$11:N51,$N51),2)) | Z51: =IF($N51="","",ROUND(SUMIFS(数据录入!$G$5:$G$4999,数据录入!$K$5:$K$4999,$N51),2)) | AA51: =IF(AND($D51="",$N51=""),"",IF(AND($D51<>"",COUNTIF(基础资料!$E:$E,$D51)=0),"客户名不在基础资料里",IF(AND($E51<>"",COUNTIF(基础资料!$B:$B,$E51)=0),"产品名不在基础资料里",IF(AND($N51<>"",COUNTIF(基础资料!$G:$G,$N51)=0),"供货商不在基础资料里",IF(AND($C51<>"",ISNUMBER($C51),$C51<10000),"客户生日填得不对（不是日期）",IF(N($J51)>N($F51),"销售费用大于销售金额",IF(AND($D51<>"",COUNTIF(数据录入!$J$5:$J$4999,$D51)=0,N($T51)<>0),"用的还是原手工已收款",IF(AND($D51<>"",COUNTIF(数据录入!$J$5:$J$4999,$D51)>0,ROUND(N($G51)-N($T51),2)<>0,N($T51)<>0),"自动算的已收款和原手工数对不上","√"))))))))
A52: =IF(AND($D52="",$N52=""),"",MAX($A$10:A51)+1) | G52: =IF($D52="","",IF(COUNTIF(数据录入!$J$5:$J$4999,$D52)=0,N($T52),ROUND(MIN(MAX(0,N($W52)-(N($V52)-N($U52))),N($U52)),2))) | H52: =IF($D52="","",ROUND(N($F52)-N($G52)-N($J52),2)) | I52: =IF($D52="","",ROUND(SUM($H$11:H52),2)) | P52: =IF($N52="","",IF(COUNTIF(数据录入!$K$5:$K$4999,$N52)=0,N($X52),ROUND(MIN(MAX(0,N($Z52)-(N($Y52)-N($O52))),N($O52)),2))) | Q52: =IF($N52="","",ROUND(N($O52)-N($P52),2)) | R52: =IF($N52="","",ROUND(SUM($Q$11:Q52),2)) | U52: =IF($D52="","",ROUND(N($F52)-N($J52),2)) | V52: =IF($D52="","",ROUND(SUMIFS($F$11:F52,$D$11:D52,$D52)-SUMIFS($J$11:J52,$D$11:D52,$D52),2)) | W52: =IF($D52="","",ROUND(SUMIFS(数据录入!$F$5:$F$4999,数据录入!$J$5:$J$4999,$D52),2)) | Y52: =IF($N52="","",ROUND(SUMIFS($O$11:O52,$N$11:N52,$N52),2)) | Z52: =IF($N52="","",ROUND(SUMIFS(数据录入!$G$5:$G$4999,数据录入!$K$5:$K$4999,$N52),2)) | AA52: =IF(AND($D52="",$N52=""),"",IF(AND($D52<>"",COUNTIF(基础资料!$E:$E,$D52)=0),"客户名不在基础资料里",IF(AND($E52<>"",COUNTIF(基础资料!$B:$B,$E52)=0),"产品名不在基础资料里",IF(AND($N52<>"",COUNTIF(基础资料!$G:$G,$N52)=0),"供货商不在基础资料里",IF(AND($C52<>"",ISNUMBER($C52),$C52<10000),"客户生日填得不对（不是日期）",IF(N($J52)>N($F52),"销售费用大于销售金额",IF(AND($D52<>"",COUNTIF(数据录入!$J$5:$J$4999,$D52)=0,N($T52)<>0),"用的还是原手工已收款",IF(AND($D52<>"",COUNTIF(数据录入!$J$5:$J$4999,$D52)>0,ROUND(N($G52)-N($T52),2)<>0,N($T52)<>0),"自动算的已收款和原手工数对不上","√"))))))))
A53: =IF(AND($D53="",$N53=""),"",MAX($A$10:A52)+1) | G53: =IF($D53="","",IF(COUNTIF(数据录入!$J$5:$J$4999,$D53)=0,N($T53),ROUND(MIN(MAX(0,N($W53)-(N($V53)-N($U53))),N($U53)),2))) | H53: =IF($D53="","",ROUND(N($F53)-N($G53)-N($J53),2)) | I53: =IF($D53="","",ROUND(SUM($H$11:H53),2)) | P53: =IF($N53="","",IF(COUNTIF(数据录入!$K$5:$K$4999,$N53)=0,N($X53),ROUND(MIN(MAX(0,N($Z53)-(N($Y53)-N($O53))),N($O53)),2))) | Q53: =IF($N53="","",ROUND(N($O53)-N($P53),2)) | R53: =IF($N53="","",ROUND(SUM($Q$11:Q53),2)) | U53: =IF($D53="","",ROUND(N($F53)-N($J53),2)) | V53: =IF($D53="","",ROUND(SUMIFS($F$11:F53,$D$11:D53,$D53)-SUMIFS($J$11:J53,$D$11:D53,$D53),2)) | W53: =IF($D53="","",ROUND(SUMIFS(数据录入!$F$5:$F$4999,数据录入!$J$5:$J$4999,$D53),2)) | Y53: =IF($N53="","",ROUND(SUMIFS($O$11:O53,$N$11:N53,$N53),2)) | Z53: =IF($N53="","",ROUND(SUMIFS(数据录入!$G$5:$G$4999,数据录入!$K$5:$K$4999,$N53),2)) | AA53: =IF(AND($D53="",$N53=""),"",IF(AND($D53<>"",COUNTIF(基础资料!$E:$E,$D53)=0),"客户名不在基础资料里",IF(AND($E53<>"",COUNTIF(基础资料!$B:$B,$E53)=0),"产品名不在基础资料里",IF(AND($N53<>"",COUNTIF(基础资料!$G:$G,$N53)=0),"供货商不在基础资料里",IF(AND($C53<>"",ISNUMBER($C53),$C53<10000),"客户生日填得不对（不是日期）",IF(N($J53)>N($F53),"销售费用大于销售金额",IF(AND($D53<>"",COUNTIF(数据录入!$J$5:$J$4999,$D53)=0,N($T53)<>0),"用的还是原手工已收款",IF(AND($D53<>"",COUNTIF(数据录入!$J$5:$J$4999,$D53)>0,ROUND(N($G53)-N($T53),2)<>0,N($T53)<>0),"自动算的已收款和原手工数对不上","√"))))))))
A54: =IF(AND($D54="",$N54=""),"",MAX($A$10:A53)+1) | G54: =IF($D54="","",IF(COUNTIF(数据录入!$J$5:$J$4999,$D54)=0,N($T54),ROUND(MIN(MAX(0,N($W54)-(N($V54)-N($U54))),N($U54)),2))) | H54: =IF($D54="","",ROUND(N($F54)-N($G54)-N($J54),2)) | I54: =IF($D54="","",ROUND(SUM($H$11:H54),2)) | P54: =IF($N54="","",IF(COUNTIF(数据录入!$K$5:$K$4999,$N54)=0,N($X54),ROUND(MIN(MAX(0,N($Z54)-(N($Y54)-N($O54))),N($O54)),2))) | Q54: =IF($N54="","",ROUND(N($O54)-N($P54),2)) | R54: =IF($N54="","",ROUND(SUM($Q$11:Q54),2)) | U54: =IF($D54="","",ROUND(N($F54)-N($J54),2)) | V54: =IF($D54="","",ROUND(SUMIFS($F$11:F54,$D$11:D54,$D54)-SUMIFS($J$11:J54,$D$11:D54,$D54),2)) | W54: =IF($D54="","",ROUND(SUMIFS(数据录入!$F$5:$F$4999,数据录入!$J$5:$J$4999,$D54),2)) | Y54: =IF($N54="","",ROUND(SUMIFS($O$11:O54,$N$11:N54,$N54),2)) | Z54: =IF($N54="","",ROUND(SUMIFS(数据录入!$G$5:$G$4999,数据录入!$K$5:$K$4999,$N54),2)) | AA54: =IF(AND($D54="",$N54=""),"",IF(AND($D54<>"",COUNTIF(基础资料!$E:$E,$D54)=0),"客户名不在基础资料里",IF(AND($E54<>"",COUNTIF(基础资料!$B:$B,$E54)=0),"产品名不在基础资料里",IF(AND($N54<>"",COUNTIF(基础资料!$G:$G,$N54)=0),"供货商不在基础资料里",IF(AND($C54<>"",ISNUMBER($C54),$C54<10000),"客户生日填得不对（不是日期）",IF(N($J54)>N($F54),"销售费用大于销售金额",IF(AND($D54<>"",COUNTIF(数据录入!$J$5:$J$4999,$D54)=0,N($T54)<>0),"用的还是原手工已收款",IF(AND($D54<>"",COUNTIF(数据录入!$J$5:$J$4999,$D54)>0,ROUND(N($G54)-N($T54),2)<>0,N($T54)<>0),"自动算的已收款和原手工数对不上","√"))))))))
A55: =IF(AND($D55="",$N55=""),"",MAX($A$10:A54)+1) | G55: =IF($D55="","",IF(COUNTIF(数据录入!$J$5:$J$4999,$D55)=0,N($T55),ROUND(MIN(MAX(0,N($W55)-(N($V55)-N($U55))),N($U55)),2))) | H55: =IF($D55="","",ROUND(N($F55)-N($G55)-N($J55),2)) | I55: =IF($D55="","",ROUND(SUM($H$11:H55),2)) | P55: =IF($N55="","",IF(COUNTIF(数据录入!$K$5:$K$4999,$N55)=0,N($X55),ROUND(MIN(MAX(0,N($Z55)-(N($Y55)-N($O55))),N($O55)),2))) | Q55: =IF($N55="","",ROUND(N($O55)-N($P55),2)) | R55: =IF($N55="","",ROUND(SUM($Q$11:Q55),2)) | U55: =IF($D55="","",ROUND(N($F55)-N($J55),2)) | V55: =IF($D55="","",ROUND(SUMIFS($F$11:F55,$D$11:D55,$D55)-SUMIFS($J$11:J55,$D$11:D55,$D55),2)) | W55: =IF($D55="","",ROUND(SUMIFS(数据录入!$F$5:$F$4999,数据录入!$J$5:$J$4999,$D55),2)) | Y55: =IF($N55="","",ROUND(SUMIFS($O$11:O55,$N$11:N55,$N55),2)) | Z55: =IF($N55="","",ROUND(SUMIFS(数据录入!$G$5:$G$4999,数据录入!$K$5:$K$4999,$N55),2)) | AA55: =IF(AND($D55="",$N55=""),"",IF(AND($D55<>"",COUNTIF(基础资料!$E:$E,$D55)=0),"客户名不在基础资料里",IF(AND($E55<>"",COUNTIF(基础资料!$B:$B,$E55)=0),"产品名不在基础资料里",IF(AND($N55<>"",COUNTIF(基础资料!$G:$G,$N55)=0),"供货商不在基础资料里",IF(AND($C55<>"",ISNUMBER($C55),$C55<10000),"客户生日填得不对（不是日期）",IF(N($J55)>N($F55),"销售费用大于销售金额",IF(AND($D55<>"",COUNTIF(数据录入!$J$5:$J$4999,$D55)=0,N($T55)<>0),"用的还是原手工已收款",IF(AND($D55<>"",COUNTIF(数据录入!$J$5:$J$4999,$D55)>0,ROUND(N($G55)-N($T55),2)<>0,N($T55)<>0),"自动算的已收款和原手工数对不上","√"))))))))
A56: =IF(AND($D56="",$N56=""),"",MAX($A$10:A55)+1) | G56: =IF($D56="","",IF(COUNTIF(数据录入!$J$5:$J$4999,$D56)=0,N($T56),ROUND(MIN(MAX(0,N($W56)-(N($V56)-N($U56))),N($U56)),2))) | H56: =IF($D56="","",ROUND(N($F56)-N($G56)-N($J56),2)) | I56: =IF($D56="","",ROUND(SUM($H$11:H56),2)) | P56: =IF($N56="","",IF(COUNTIF(数据录入!$K$5:$K$4999,$N56)=0,N($X56),ROUND(MIN(MAX(0,N($Z56)-(N($Y56)-N($O56))),N($O56)),2))) | Q56: =IF($N56="","",ROUND(N($O56)-N($P56),2)) | R56: =IF($N56="","",ROUND(SUM($Q$11:Q56),2)) | U56: =IF($D56="","",ROUND(N($F56)-N($J56),2)) | V56: =IF($D56="","",ROUND(SUMIFS($F$11:F56,$D$11:D56,$D56)-SUMIFS($J$11:J56,$D$11:D56,$D56),2)) | W56: =IF($D56="","",ROUND(SUMIFS(数据录入!$F$5:$F$4999,数据录入!$J$5:$J$4999,$D56),2)) | Y56: =IF($N56="","",ROUND(SUMIFS($O$11:O56,$N$11:N56,$N56),2)) | Z56: =IF($N56="","",ROUND(SUMIFS(数据录入!$G$5:$G$4999,数据录入!$K$5:$K$4999,$N56),2)) | AA56: =IF(AND($D56="",$N56=""),"",IF(AND($D56<>"",COUNTIF(基础资料!$E:$E,$D56)=0),"客户名不在基础资料里",IF(AND($E56<>"",COUNTIF(基础资料!$B:$B,$E56)=0),"产品名不在基础资料里",IF(AND($N56<>"",COUNTIF(基础资料!$G:$G,$N56)=0),"供货商不在基础资料里",IF(AND($C56<>"",ISNUMBER($C56),$C56<10000),"客户生日填得不对（不是日期）",IF(N($J56)>N($F56),"销售费用大于销售金额",IF(AND($D56<>"",COUNTIF(数据录入!$J$5:$J$4999,$D56)=0,N($T56)<>0),"用的还是原手工已收款",IF(AND($D56<>"",COUNTIF(数据录入!$J$5:$J$4999,$D56)>0,ROUND(N($G56)-N($T56),2)<>0,N($T56)<>0),"自动算的已收款和原手工数对不上","√"))))))))
A57: =IF(AND($D57="",$N57=""),"",MAX($A$10:A56)+1) | G57: =IF($D57="","",IF(COUNTIF(数据录入!$J$5:$J$4999,$D57)=0,N($T57),ROUND(MIN(MAX(0,N($W57)-(N($V57)-N($U57))),N($U57)),2))) | H57: =IF($D57="","",ROUND(N($F57)-N($G57)-N($J57),2)) | I57: =IF($D57="","",ROUND(SUM($H$11:H57),2)) | P57: =IF($N57="","",IF(COUNTIF(数据录入!$K$5:$K$4999,$N57)=0,N($X57),ROUND(MIN(MAX(0,N($Z57)-(N($Y57)-N($O57))),N($O57)),2))) | Q57: =IF($N57="","",ROUND(N($O57)-N($P57),2)) | R57: =IF($N57="","",ROUND(SUM($Q$11:Q57),2)) | U57: =IF($D57="","",ROUND(N($F57)-N($J57),2)) | V57: =IF($D57="","",ROUND(SUMIFS($F$11:F57,$D$11:D57,$D57)-SUMIFS($J$11:J57,$D$11:D57,$D57),2)) | W57: =IF($D57="","",ROUND(SUMIFS(数据录入!$F$5:$F$4999,数据录入!$J$5:$J$4999,$D57),2)) | Y57: =IF($N57="","",ROUND(SUMIFS($O$11:O57,$N$11:N57,$N57),2)) | Z57: =IF($N57="","",ROUND(SUMIFS(数据录入!$G$5:$G$4999,数据录入!$K$5:$K$4999,$N57),2)) | AA57: =IF(AND($D57="",$N57=""),"",IF(AND($D57<>"",COUNTIF(基础资料!$E:$E,$D57)=0),"客户名不在基础资料里",IF(AND($E57<>"",COUNTIF(基础资料!$B:$B,$E57)=0),"产品名不在基础资料里",IF(AND($N57<>"",COUNTIF(基础资料!$G:$G,$N57)=0),"供货商不在基础资料里",IF(AND($C57<>"",ISNUMBER($C57),$C57<10000),"客户生日填得不对（不是日期）",IF(N($J57)>N($F57),"销售费用大于销售金额",IF(AND($D57<>"",COUNTIF(数据录入!$J$5:$J$4999,$D57)=0,N($T57)<>0),"用的还是原手工已收款",IF(AND($D57<>"",COUNTIF(数据录入!$J$5:$J$4999,$D57)>0,ROUND(N($G57)-N($T57),2)<>0,N($T57)<>0),"自动算的已收款和原手工数对不上","√"))))))))
... A510: =IF(AND($D510="",$N510=""),"",MAX($A$10:A509)+1) | G510: =IF($D510="","",IF(COUNTIF(数据录入!$J$5:$J$4999,$D510)=0,N($T510),ROUND(MIN(MAX(0,N($W510)-(N($V510)-N($U510))),N($U510)),2))) | H510: =IF($D510="","",ROUND(N($F510)-N($G510)-N($J510),2)) | I510: =IF($D510="","",ROUND(SUM($H$11:H510),2)) | P510: =IF($N510="","",IF(COUNTIF(数据录入!$K$5:$K$4999,$N510)=0,N($X510),ROUND(MIN(MAX(0,N($Z510)-(N($Y510)-N($O510))),N($O510)),2))) | Q510: =IF($N510="","",ROUND(N($O510)-N($P510),2)) | R510: =IF($N510="","",ROUND(SUM($Q$11:Q510),2)) | U510: =IF($D510="","",ROUND(N($F510)-N($J510),2)) | V510: =IF($D510="","",ROUND(SUMIFS($F$11:F510,$D$11:D510,$D510)-SUMIFS($J$11:J510,$D$11:D510,$D510),2)) | W510: =IF($D510="","",ROUND(SUMIFS(数据录入!$F$5:$F$4999,数据录入!$J$5:$J$4999,$D510),2)) | Y510: =IF($N510="","",ROUND(SUMIFS($O$11:O510,$N$11:N510,$N510),2)) | Z510: =IF($N510="","",ROUND(SUMIFS(数据录入!$G$5:$G$4999,数据录入!$K$5:$K$4999,$N510),2)) | AA510: =IF(AND($D510="",$N510=""),"",IF(AND($D510<>"",COUNTIF(基础资料!$E:$E,$D510)=0),"客户名不在基础资料里",IF(AND($E510<>"",COUNTIF(基础资料!$B:$B,$E510)=0),"产品名不在基础资料里",IF(AND($N510<>"",COUNTIF(基础资料!$G:$G,$N510)=0),"供货商不在基础资料里",IF(AND($C510<>"",ISNUMBER($C510),$C510<10000),"客户生日填得不对（不是日期）",IF(N($J510)>N($F510),"销售费用大于销售金额",IF(AND($D510<>"",COUNTIF(数据录入!$J$5:$J$4999,$D510)=0,N($T510)<>0),"用的还是原手工已收款",IF(AND($D510<>"",COUNTIF(数据录入!$J$5:$J$4999,$D510)>0,ROUND(N($G510)-N($T510),2)<>0,N($T510)<>0),"自动算的已收款和原手工数对不上","√"))))))))

Sheet 客户供应商往来对账
A1: 客户 · 供货商 往来对账表
A2: ★ 全自动，不用填。左半边「该收/该付」来自【往来款跟进】，右半边「实收/实付」来自【数据录入】。 差额 ≠ 0，说明两张表没对上：要么【数据录入】那笔回款没选客户名，要么【往来款跟进】的已收款还是原来的手工数。 客户和供货商名单直接跟着【基础资料】走，你在基础资料里加一个客户，这里自动多一行。
A4: 一、按客户：应收款对账
A5: 序号 | B5: 客户 | C5: 销售金额 | D5: 销售费用 (赠送券) | E5: 应收款 | F5: 已收款 (往来款跟进) | G5: 已收款 (数据录入) | H5: 尚欠款 | I5: 差额 | J5: 提 示
A6: =IF($B6="","",MAX($A$5:A5)+1) | B6: =IF(基础资料!$E2="","",基础资料!$E2) | C6: =IF($B6="","",ROUND(SUMIFS('往来款跟进'!$F$11:$F$510,'往来款跟进'!$D$11:$D$510,$B6),2)) | D6: =IF($B6="","",ROUND(SUMIFS('往来款跟进'!$J$11:$J$510,'往来款跟进'!$D$11:$D$510,$B6),2)) | E6: =IF($B6="","",ROUND(N($C6)-N($D6),2)) | F6: =IF($B6="","",ROUND(SUMIFS('往来款跟进'!$G$11:$G$510,'往来款跟进'!$D$11:$D$510,$B6),2)) | G6: =IF($B6="","",ROUND(SUMIFS(数据录入!$F$5:$F$4999,数据录入!$J$5:$J$4999,$B6),2)) | H6: =IF($B6="","",ROUND(N($E6)-N($F6),2)) | I6: =IF($B6="","",ROUND(N($F6)-N($G6),2)) | J6: =IF($B6="","",IF(AND(N($E6)=0,N($G6)=0),"没有往来",IF(ROUND(N($I6),2)<>0,"差 "&TEXT(N($I6),"0.00")&" 元：【数据录入】里这个客户的回款还没记全，或者没选客户名",IF(N($H6)>0,"还欠 "&TEXT(N($H6),"0.00")&" 元","已结清"))))
A7: =IF($B7="","",MAX($A$5:A6)+1) | B7: =IF(基础资料!$E3="","",基础资料!$E3) | C7: =IF($B7="","",ROUND(SUMIFS('往来款跟进'!$F$11:$F$510,'往来款跟进'!$D$11:$D$510,$B7),2)) | D7: =IF($B7="","",ROUND(SUMIFS('往来款跟进'!$J$11:$J$510,'往来款跟进'!$D$11:$D$510,$B7),2)) | E7: =IF($B7="","",ROUND(N($C7)-N($D7),2)) | F7: =IF($B7="","",ROUND(SUMIFS('往来款跟进'!$G$11:$G$510,'往来款跟进'!$D$11:$D$510,$B7),2)) | G7: =IF($B7="","",ROUND(SUMIFS(数据录入!$F$5:$F$4999,数据录入!$J$5:$J$4999,$B7),2)) | H7: =IF($B7="","",ROUND(N($E7)-N($F7),2)) | I7: =IF($B7="","",ROUND(N($F7)-N($G7),2)) | J7: =IF($B7="","",IF(AND(N($E7)=0,N($G7)=0),"没有往来",IF(ROUND(N($I7),2)<>0,"差 "&TEXT(N($I7),"0.00")&" 元：【数据录入】里这个客户的回款还没记全，或者没选客户名",IF(N($H7)>0,"还欠 "&TEXT(N($H7),"0.00")&" 元","已结清"))))
A8: =IF($B8="","",MAX($A$5:A7)+1) | B8: =IF(基础资料!$E4="","",基础资料!$E4) | C8: =IF($B8="","",ROUND(SUMIFS('往来款跟进'!$F$11:$F$510,'往来款跟进'!$D$11:$D$510,$B8),2)) | D8: =IF($B8="","",ROUND(SUMIFS('往来款跟进'!$J$11:$J$510,'往来款跟进'!$D$11:$D$510,$B8),2)) | E8: =IF($B8="","",ROUND(N($C8)-N($D8),2)) | F8: =IF($B8="","",ROUND(SUMIFS('往来款跟进'!$G$11:$G$510,'往来款跟进'!$D$11:$D$510,$B8),2)) | G8: =IF($B8="","",ROUND(SUMIFS(数据录入!$F$5:$F$4999,数据录入!$J$5:$J$4999,$B8),2)) | H8: =IF($B8="","",ROUND(N($E8)-N($F8),2)) | I8: =IF($B8="","",ROUND(N($F8)-N($G8),2)) | J8: =IF($B8="","",IF(AND(N($E8)=0,N($G8)=0),"没有往来",IF(ROUND(N($I8),2)<>0,"差 "&TEXT(N($I8),"0.00")&" 元：【数据录入】里这个客户的回款还没记全，或者没选客户名",IF(N($H8)>0,"还欠 "&TEXT(N($H8),"0.00")&" 元","已结清"))))
A9: =IF($B9="","",MAX($A$5:A8)+1) | B9: =IF(基础资料!$E5="","",基础资料!$E5) | C9: =IF($B9="","",ROUND(SUMIFS('往来款跟进'!$F$11:$F$510,'往来款跟进'!$D$11:$D$510,$B9),2)) | D9: =IF($B9="","",ROUND(SUMIFS('往来款跟进'!$J$11:$J$510,'往来款跟进'!$D$11:$D$510,$B9),2)) | E9: =IF($B9="","",ROUND(N($C9)-N($D9),2)) | F9: =IF($B9="","",ROUND(SUMIFS('往来款跟进'!$G$11:$G$510,'往来款跟进'!$D$11:$D$510,$B9),2)) | G9: =IF($B9="","",ROUND(SUMIFS(数据录入!$F$5:$F$4999,数据录入!$J$5:$J$4999,$B9),2)) | H9: =IF($B9="","",ROUND(N($E9)-N($F9),2)) | I9: =IF($B9="","",ROUND(N($F9)-N($G9),2)) | J9: =IF($B9="","",IF(AND(N($E9)=0,N($G9)=0),"没有往来",IF(ROUND(N($I9),2)<>0,"差 "&TEXT(N($I9),"0.00")&" 元：【数据录入】里这个客户的回款还没记全，或者没选客户名",IF(N($H9)>0,"还欠 "&TEXT(N($H9),"0.00")&" 元","已结清"))))
A10: =IF($B10="","",MAX($A$5:A9)+1) | B10: =IF(基础资料!$E6="","",基础资料!$E6) | C10: =IF($B10="","",ROUND(SUMIFS('往来款跟进'!$F$11:$F$510,'往来款跟进'!$D$11:$D$510,$B10),2)) | D10: =IF($B10="","",ROUND(SUMIFS('往来款跟进'!$J$11:$J$510,'往来款跟进'!$D$11:$D$510,$B10),2)) | E10: =IF($B10="","",ROUND(N($C10)-N($D10),2)) | F10: =IF($B10="","",ROUND(SUMIFS('往来款跟进'!$G$11:$G$510,'往来款跟进'!$D$11:$D$510,$B10),2)) | G10: =IF($B10="","",ROUND(SUMIFS(数据录入!$F$5:$F$4999,数据录入!$J$5:$J$4999,$B10),2)) | H10: =IF($B10="","",ROUND(N($E10)-N($F10),2)) | I10: =IF($B10="","",ROUND(N($F10)-N($G10),2)) | J10: =IF($B10="","",IF(AND(N($E10)=0,N($G10)=0),"没有往来",IF(ROUND(N($I10),2)<>0,"差 "&TEXT(N($I10),"0.00")&" 元：【数据录入】里这个客户的回款还没记全，或者没选客户名",IF(N($H10)>0,"还欠 "&TEXT(N($H10),"0.00")&" 元","已结清"))))
A11: =IF($B11="","",MAX($A$5:A10)+1) | B11: =IF(基础资料!$E7="","",基础资料!$E7) | C11: =IF($B11="","",ROUND(SUMIFS('往来款跟进'!$F$11:$F$510,'往来款跟进'!$D$11:$D$510,$B11),2)) | D11: =IF($B11="","",ROUND(SUMIFS('往来款跟进'!$J$11:$J$510,'往来款跟进'!$D$11:$D$510,$B11),2)) | E11: =IF($B11="","",ROUND(N($C11)-N($D11),2)) | F11: =IF($B11="","",ROUND(SUMIFS('往来款跟进'!$G$11:$G$510,'往来款跟进'!$D$11:$D$510,$B11),2)) | G11: =IF($B11="","",ROUND(SUMIFS(数据录入!$F$5:$F$4999,数据录入!$J$5:$J$4999,$B11),2)) | H11: =IF($B11="","",ROUND(N($E11)-N($F11),2)) | I11: =IF($B11="","",ROUND(N($F11)-N($G11),2)) | J11: =IF($B11="","",IF(AND(N($E11)=0,N($G11)=0),"没有往来",IF(ROUND(N($I11),2)<>0,"差 "&TEXT(N($I11),"0.00")&" 元：【数据录入】里这个客户的回款还没记全，或者没选客户名",IF(N($H11)>0,"还欠 "&TEXT(N($H11),"0.00")&" 元","已结清"))))
A12: =IF($B12="","",MAX($A$5:A11)+1) | B12: =IF(基础资料!$E8="","",基础资料!$E8) | C12: =IF($B12="","",ROUND(SUMIFS('往来款跟进'!$F$11:$F$510,'往来款跟进'!$D$11:$D$510,$B12),2)) | D12: =IF($B12="","",ROUND(SUMIFS('往来款跟进'!$J$11:$J$510,'往来款跟进'!$D$11:$D$510,$B12),2)) | E12: =IF($B12="","",ROUND(N($C12)-N($D12),2)) | F12: =IF($B12="","",ROUND(SUMIFS('往来款跟进'!$G$11:$G$510,'往来款跟进'!$D$11:$D$510,$B12),2)) | G12: =IF($B12="","",ROUND(SUMIFS(数据录入!$F$5:$F$4999,数据录入!$J$5:$J$4999,$B12),2)) | H12: =IF($B12="","",ROUND(N($E12)-N($F12),2)) | I12: =IF($B12="","",ROUND(N($F12)-N($G12),2)) | J12: =IF($B12="","",IF(AND(N($E12)=0,N($G12)=0),"没有往来",IF(ROUND(N($I12),2)<>0,"差 "&TEXT(N($I12),"0.00")&" 元：【数据录入】里这个客户的回款还没记全，或者没选客户名",IF(N($H12)>0,"还欠 "&TEXT(N($H12),"0.00")&" 元","已结清"))))
A13: =IF($B13="","",MAX($A$5:A12)+1) | B13: =IF(基础资料!$E9="","",基础资料!$E9) | C13: =IF($B13="","",ROUND(SUMIFS('往来款跟进'!$F$11:$F$510,'往来款跟进'!$D$11:$D$510,$B13),2)) | D13: =IF($B13="","",ROUND(SUMIFS('往来款跟进'!$J$11:$J$510,'往来款跟进'!$D$11:$D$510,$B13),2)) | E13: =IF($B13="","",ROUND(N($C13)-N($D13),2)) | F13: =IF($B13="","",ROUND(SUMIFS('往来款跟进'!$G$11:$G$510,'往来款跟进'!$D$11:$D$510,$B13),2)) | G13: =IF($B13="","",ROUND(SUMIFS(数据录入!$F$5:$F$4999,数据录入!$J$5:$J$4999,$B13),2)) | H13: =IF($B13="","",ROUND(N($E13)-N($F13),2)) | I13: =IF($B13="","",ROUND(N($F13)-N($G13),2)) | J13: =IF($B13="","",IF(AND(N($E13)=0,N($G13)=0),"没有往来",IF(ROUND(N($I13),2)<>0,"差 "&TEXT(N($I13),"0.00")&" 元：【数据录入】里这个客户的回款还没记全，或者没选客户名",IF(N($H13)>0,"还欠 "&TEXT(N($H13),"0.00")&" 元","已结清"))))
A14: =IF($B14="","",MAX($A$5:A13)+1) | B14: =IF(基础资料!$E10="","",基础资料!$E10) | C14: =IF($B14="","",ROUND(SUMIFS('往来款跟进'!$F$11:$F$510,'往来款跟进'!$D$11:$D$510,$B14),2)) | D14: =IF($B14="","",ROUND(SUMIFS('往来款跟进'!$J$11:$J$510,'往来款跟进'!$D$11:$D$510,$B14),2)) | E14: =IF($B14="","",ROUND(N($C14)-N($D14),2)) | F14: =IF($B14="","",ROUND(SUMIFS('往来款跟进'!$G$11:$G$510,'往来款跟进'!$D$11:$D$510,$B14),2)) | G14: =IF($B14="","",ROUND(SUMIFS(数据录入!$F$5:$F$4999,数据录入!$J$5:$J$4999,$B14),2)) | H14: =IF($B14="","",ROUND(N($E14)-N($F14),2)) | I14: =IF($B14="","",ROUND(N($F14)-N($G14),2)) | J14: =IF($B14="","",IF(AND(N($E14)=0,N($G14)=0),"没有往来",IF(ROUND(N($I14),2)<>0,"差 "&TEXT(N($I14),"0.00")&" 元：【数据录入】里这个客户的回款还没记全，或者没选客户名",IF(N($H14)>0,"还欠 "&TEXT(N($H14),"0.00")&" 元","已结清"))))
A15: =IF($B15="","",MAX($A$5:A14)+1) | B15: =IF(基础资料!$E11="","",基础资料!$E11) | C15: =IF($B15="","",ROUND(SUMIFS('往来款跟进'!$F$11:$F$510,'往来款跟进'!$D$11:$D$510,$B15),2)) | D15: =IF($B15="","",ROUND(SUMIFS('往来款跟进'!$J$11:$J$510,'往来款跟进'!$D$11:$D$510,$B15),2)) | E15: =IF($B15="","",ROUND(N($C15)-N($D15),2)) | F15: =IF($B15="","",ROUND(SUMIFS('往来款跟进'!$G$11:$G$510,'往来款跟进'!$D$11:$D$510,$B15),2)) | G15: =IF($B15="","",ROUND(SUMIFS(数据录入!$F$5:$F$4999,数据录入!$J$5:$J$4999,$B15),2)) | H15: =IF($B15="","",ROUND(N($E15)-N($F15),2)) | I15: =IF($B15="","",ROUND(N($F15)-N($G15),2)) | J15: =IF($B15="","",IF(AND(N($E15)=0,N($G15)=0),"没有往来",IF(ROUND(N($I15),2)<>0,"差 "&TEXT(N($I15),"0.00")&" 元：【数据录入】里这个客户的回款还没记全，或者没选客户名",IF(N($H15)>0,"还欠 "&TEXT(N($H15),"0.00")&" 元","已结清"))))
A16: =IF($B16="","",MAX($A$5:A15)+1) | B16: =IF(基础资料!$E12="","",基础资料!$E12) | C16: =IF($B16="","",ROUND(SUMIFS('往来款跟进'!$F$11:$F$510,'往来款跟进'!$D$11:$D$510,$B16),2)) | D16: =IF($B16="","",ROUND(SUMIFS('往来款跟进'!$J$11:$J$510,'往来款跟进'!$D$11:$D$510,$B16),2)) | E16: =IF($B16="","",ROUND(N($C16)-N($D16),2)) | F16: =IF($B16="","",ROUND(SUMIFS('往来款跟进'!$G$11:$G$510,'往来款跟进'!$D$11:$D$510,$B16),2)) | G16: =IF($B16="","",ROUND(SUMIFS(数据录入!$F$5:$F$4999,数据录入!$J$5:$J$4999,$B16),2)) | H16: =IF($B16="","",ROUND(N($E16)-N($F16),2)) | I16: =IF($B16="","",ROUND(N($F16)-N($G16),2)) | J16: =IF($B16="","",IF(AND(N($E16)=0,N($G16)=0),"没有往来",IF(ROUND(N($I16),2)<>0,"差 "&TEXT(N($I16),"0.00")&" 元：【数据录入】里这个客户的回款还没记全，或者没选客户名",IF(N($H16)>0,"还欠 "&TEXT(N($H16),"0.00")&" 元","已结清"))))
A17: =IF($B17="","",MAX($A$5:A16)+1) | B17: =IF(基础资料!$E13="","",基础资料!$E13) | C17: =IF($B17="","",ROUND(SUMIFS('往来款跟进'!$F$11:$F$510,'往来款跟进'!$D$11:$D$510,$B17),2)) | D17: =IF($B17="","",ROUND(SUMIFS('往来款跟进'!$J$11:$J$510,'往来款跟进'!$D$11:$D$510,$B17),2)) | E17: =IF($B17="","",ROUND(N($C17)-N($D17),2)) | F17: =IF($B17="","",ROUND(SUMIFS('往来款跟进'!$G$11:$G$510,'往来款跟进'!$D$11:$D$510,$B17),2)) | G17: =IF($B17="","",ROUND(SUMIFS(数据录入!$F$5:$F$4999,数据录入!$J$5:$J$4999,$B17),2)) | H17: =IF($B17="","",ROUND(N($E17)-N($F17),2)) | I17: =IF($B17="","",ROUND(N($F17)-N($G17),2)) | J17: =IF($B17="","",IF(AND(N($E17)=0,N($G17)=0),"没有往来",IF(ROUND(N($I17),2)<>0,"差 "&TEXT(N($I17),"0.00")&" 元：【数据录入】里这个客户的回款还没记全，或者没选客户名",IF(N($H17)>0,"还欠 "&TEXT(N($H17),"0.00")&" 元","已结清"))))
... A65: =IF($B65="","",MAX($A$5:A64)+1) | B65: =IF(基础资料!$E61="","",基础资料!$E61) | C65: =IF($B65="","",ROUND(SUMIFS('往来款跟进'!$F$11:$F$510,'往来款跟进'!$D$11:$D$510,$B65),2)) | D65: =IF($B65="","",ROUND(SUMIFS('往来款跟进'!$J$11:$J$510,'往来款跟进'!$D$11:$D$510,$B65),2)) | E65: =IF($B65="","",ROUND(N($C65)-N($D65),2)) | F65: =IF($B65="","",ROUND(SUMIFS('往来款跟进'!$G$11:$G$510,'往来款跟进'!$D$11:$D$510,$B65),2)) | G65: =IF($B65="","",ROUND(SUMIFS(数据录入!$F$5:$F$4999,数据录入!$J$5:$J$4999,$B65),2)) | H65: =IF($B65="","",ROUND(N($E65)-N($F65),2)) | I65: =IF($B65="","",ROUND(N($F65)-N($G65),2)) | J65: =IF($B65="","",IF(AND(N($E65)=0,N($G65)=0),"没有往来",IF(ROUND(N($I65),2)<>0,"差 "&TEXT(N($I65),"0.00")&" 元：【数据录入】里这个客户的回款还没记全，或者没选客户名",IF(N($H65)>0,"还欠 "&TEXT(N($H65),"0.00")&" 元","已结清"))))
A66: 合 计 | C66: =ROUND(SUM(C6:C65),2) | D66: =ROUND(SUM(D6:D65),2) | E66: =ROUND(SUM(E6:E65),2) | F66: =ROUND(SUM(F6:F65),2) | G66: =ROUND(SUM(G6:G65),2) | H66: =ROUND(SUM(H6:H65),2) | I66: =ROUND(SUM(I6:I65),2)
A68: 二、按供货商：应付款对账
A69: 序号 | B69: 供货商 | C69: 购货款 | E69: 应付款 | F69: 已付款 (往来款跟进) | G69: 已付款 (数据录入) | H69: 尚欠款 | I69: 差额 | J69: 提 示
A70: =IF($B70="","",MAX($A$69:A69)+1) | B70: =IF(基础资料!$G2="","",基础资料!$G2) | C70: =IF($B70="","",ROUND(SUMIFS('往来款跟进'!$O$11:$O$510,'往来款跟进'!$N$11:$N$510,$B70),2)) | E70: =IF($B70="","",N($C70)) | F70: =IF($B70="","",ROUND(SUMIFS('往来款跟进'!$P$11:$P$510,'往来款跟进'!$N$11:$N$510,$B70),2)) | G70: =IF($B70="","",ROUND(SUMIFS(数据录入!$G$5:$G$4999,数据录入!$K$5:$K$4999,$B70),2)) | H70: =IF($B70="","",ROUND(N($E70)-N($F70),2)) | I70: =IF($B70="","",ROUND(N($F70)-N($G70),2)) | J70: =IF($B70="","",IF(AND(N($E70)=0,N($G70)=0),"没有往来",IF(ROUND(N($I70),2)<>0,"差 "&TEXT(N($I70),"0.00")&" 元：【数据录入】里这个供货商的付款还没记全，或者没选供货商名",IF(N($H70)>0,"还欠 "&TEXT(N($H70),"0.00")&" 元","已结清"))))
A71: =IF($B71="","",MAX($A$69:A70)+1) | B71: =IF(基础资料!$G3="","",基础资料!$G3) | C71: =IF($B71="","",ROUND(SUMIFS('往来款跟进'!$O$11:$O$510,'往来款跟进'!$N$11:$N$510,$B71),2)) | E71: =IF($B71="","",N($C71)) | F71: =IF($B71="","",ROUND(SUMIFS('往来款跟进'!$P$11:$P$510,'往来款跟进'!$N$11:$N$510,$B71),2)) | G71: =IF($B71="","",ROUND(SUMIFS(数据录入!$G$5:$G$4999,数据录入!$K$5:$K$4999,$B71),2)) | H71: =IF($B71="","",ROUND(N($E71)-N($F71),2)) | I71: =IF($B71="","",ROUND(N($F71)-N($G71),2)) | J71: =IF($B71="","",IF(AND(N($E71)=0,N($G71)=0),"没有往来",IF(ROUND(N($I71),2)<>0,"差 "&TEXT(N($I71),"0.00")&" 元：【数据录入】里这个供货商的付款还没记全，或者没选供货商名",IF(N($H71)>0,"还欠 "&TEXT(N($H71),"0.00")&" 元","已结清"))))
A72: =IF($B72="","",MAX($A$69:A71)+1) | B72: =IF(基础资料!$G4="","",基础资料!$G4) | C72: =IF($B72="","",ROUND(SUMIFS('往来款跟进'!$O$11:$O$510,'往来款跟进'!$N$11:$N$510,$B72),2)) | E72: =IF($B72="","",N($C72)) | F72: =IF($B72="","",ROUND(SUMIFS('往来款跟进'!$P$11:$P$510,'往来款跟进'!$N$11:$N$510,$B72),2)) | G72: =IF($B72="","",ROUND(SUMIFS(数据录入!$G$5:$G$4999,数据录入!$K$5:$K$4999,$B72),2)) | H72: =IF($B72="","",ROUND(N($E72)-N($F72),2)) | I72: =IF($B72="","",ROUND(N($F72)-N($G72),2)) | J72: =IF($B72="","",IF(AND(N($E72)=0,N($G72)=0),"没有往来",IF(ROUND(N($I72),2)<>0,"差 "&TEXT(N($I72),"0.00")&" 元：【数据录入】里这个供货商的付款还没记全，或者没选供货商名",IF(N($H72)>0,"还欠 "&TEXT(N($H72),"0.00")&" 元","已结清"))))
A73: =IF($B73="","",MAX($A$69:A72)+1) | B73: =IF(基础资料!$G5="","",基础资料!$G5) | C73: =IF($B73="","",ROUND(SUMIFS('往来款跟进'!$O$11:$O$510,'往来款跟进'!$N$11:$N$510,$B73),2)) | E73: =IF($B73="","",N($C73)) | F73: =IF($B73="","",ROUND(SUMIFS('往来款跟进'!$P$11:$P$510,'往来款跟进'!$N$11:$N$510,$B73),2)) | G73: =IF($B73="","",ROUND(SUMIFS(数据录入!$G$5:$G$4999,数据录入!$K$5:$K$4999,$B73),2)) | H73: =IF($B73="","",ROUND(N($E73)-N($F73),2)) | I73: =IF($B73="","",ROUND(N($F73)-N($G73),2)) | J73: =IF($B73="","",IF(AND(N($E73)=0,N($G73)=0),"没有往来",IF(ROUND(N($I73),2)<>0,"差 "&TEXT(N($I73),"0.00")&" 元：【数据录入】里这个供货商的付款还没记全，或者没选供货商名",IF(N($H73)>0,"还欠 "&TEXT(N($H73),"0.00")&" 元","已结清"))))
A74: =IF($B74="","",MAX($A$69:A73)+1) | B74: =IF(基础资料!$G6="","",基础资料!$G6) | C74: =IF($B74="","",ROUND(SUMIFS('往来款跟进'!$O$11:$O$510,'往来款跟进'!$N$11:$N$510,$B74),2)) | E74: =IF($B74="","",N($C74)) | F74: =IF($B74="","",ROUND(SUMIFS('往来款跟进'!$P$11:$P$510,'往来款跟进'!$N$11:$N$510,$B74),2)) | G74: =IF($B74="","",ROUND(SUMIFS(数据录入!$G$5:$G$4999,数据录入!$K$5:$K$4999,$B74),2)) | H74: =IF($B74="","",ROUND(N($E74)-N($F74),2)) | I74: =IF($B74="","",ROUND(N($F74)-N($G74),2)) | J74: =IF($B74="","",IF(AND(N($E74)=0,N($G74)=0),"没有往来",IF(ROUND(N($I74),2)<>0,"差 "&TEXT(N($I74),"0.00")&" 元：【数据录入】里这个供货商的付款还没记全，或者没选供货商名",IF(N($H74)>0,"还欠 "&TEXT(N($H74),"0.00")&" 元","已结清"))))
A75: =IF($B75="","",MAX($A$69:A74)+1) | B75: =IF(基础资料!$G7="","",基础资料!$G7) | C75: =IF($B75="","",ROUND(SUMIFS('往来款跟进'!$O$11:$O$510,'往来款跟进'!$N$11:$N$510,$B75),2)) | E75: =IF($B75="","",N($C75)) | F75: =IF($B75="","",ROUND(SUMIFS('往来款跟进'!$P$11:$P$510,'往来款跟进'!$N$11:$N$510,$B75),2)) | G75: =IF($B75="","",ROUND(SUMIFS(数据录入!$G$5:$G$4999,数据录入!$K$5:$K$4999,$B75),2)) | H75: =IF($B75="","",ROUND(N($E75)-N($F75),2)) | I75: =IF($B75="","",ROUND(N($F75)-N($G75),2)) | J75: =IF($B75="","",IF(AND(N($E75)=0,N($G75)=0),"没有往来",IF(ROUND(N($I75),2)<>0,"差 "&TEXT(N($I75),"0.00")&" 元：【数据录入】里这个供货商的付款还没记全，或者没选供货商名",IF(N($H75)>0,"还欠 "&TEXT(N($H75),"0.00")&" 元","已结清"))))
A76: =IF($B76="","",MAX($A$69:A75)+1) | B76: =IF(基础资料!$G8="","",基础资料!$G8) | C76: =IF($B76="","",ROUND(SUMIFS('往来款跟进'!$O$11:$O$510,'往来款跟进'!$N$11:$N$510,$B76),2)) | E76: =IF($B76="","",N($C76)) | F76: =IF($B76="","",ROUND(SUMIFS('往来款跟进'!$P$11:$P$510,'往来款跟进'!$N$11:$N$510,$B76),2)) | G76: =IF($B76="","",ROUND(SUMIFS(数据录入!$G$5:$G$4999,数据录入!$K$5:$K$4999,$B76),2)) | H76: =IF($B76="","",ROUND(N($E76)-N($F76),2)) | I76: =IF($B76="","",ROUND(N($F76)-N($G76),2)) | J76: =IF($B76="","",IF(AND(N($E76)=0,N($G76)=0),"没有往来",IF(ROUND(N($I76),2)<>0,"差 "&TEXT(N($I76),"0.00")&" 元：【数据录入】里这个供货商的付款还没记全，或者没选供货商名",IF(N($H76)>0,"还欠 "&TEXT(N($H76),"0.00")&" 元","已结清"))))
A77: =IF($B77="","",MAX($A$69:A76)+1) | B77: =IF(基础资料!$G9="","",基础资料!$G9) | C77: =IF($B77="","",ROUND(SUMIFS('往来款跟进'!$O$11:$O$510,'往来款跟进'!$N$11:$N$510,$B77),2)) | E77: =IF($B77="","",N($C77)) | F77: =IF($B77="","",ROUND(SUMIFS('往来款跟进'!$P$11:$P$510,'往来款跟进'!$N$11:$N$510,$B77),2)) | G77: =IF($B77="","",ROUND(SUMIFS(数据录入!$G$5:$G$4999,数据录入!$K$5:$K$4999,$B77),2)) | H77: =IF($B77="","",ROUND(N($E77)-N($F77),2)) | I77: =IF($B77="","",ROUND(N($F77)-N($G77),2)) | J77: =IF($B77="","",IF(AND(N($E77)=0,N($G77)=0),"没有往来",IF(ROUND(N($I77),2)<>0,"差 "&TEXT(N($I77),"0.00")&" 元：【数据录入】里这个供货商的付款还没记全，或者没选供货商名",IF(N($H77)>0,"还欠 "&TEXT(N($H77),"0.00")&" 元","已结清"))))
A78: =IF($B78="","",MAX($A$69:A77)+1) | B78: =IF(基础资料!$G10="","",基础资料!$G10) | C78: =IF($B78="","",ROUND(SUMIFS('往来款跟进'!$O$11:$O$510,'往来款跟进'!$N$11:$N$510,$B78),2)) | E78: =IF($B78="","",N($C78)) | F78: =IF($B78="","",ROUND(SUMIFS('往来款跟进'!$P$11:$P$510,'往来款跟进'!$N$11:$N$510,$B78),2)) | G78: =IF($B78="","",ROUND(SUMIFS(数据录入!$G$5:$G$4999,数据录入!$K$5:$K$4999,$B78),2)) | H78: =IF($B78="","",ROUND(N($E78)-N($F78),2)) | I78: =IF($B78="","",ROUND(N($F78)-N($G78),2)) | J78: =IF($B78="","",IF(AND(N($E78)=0,N($G78)=0),"没有往来",IF(ROUND(N($I78),2)<>0,"差 "&TEXT(N($I78),"0.00")&" 元：【数据录入】里这个供货商的付款还没记全，或者没选供货商名",IF(N($H78)>0,"还欠 "&TEXT(N($H78),"0.00")&" 元","已结清"))))
A79: =IF($B79="","",MAX($A$69:A78)+1) | B79: =IF(基础资料!$G11="","",基础资料!$G11) | C79: =IF($B79="","",ROUND(SUMIFS('往来款跟进'!$O$11:$O$510,'往来款跟进'!$N$11:$N$510,$B79),2)) | E79: =IF($B79="","",N($C79)) | F79: =IF($B79="","",ROUND(SUMIFS('往来款跟进'!$P$11:$P$510,'往来款跟进'!$N$11:$N$510,$B79),2)) | G79: =IF($B79="","",ROUND(SUMIFS(数据录入!$G$5:$G$4999,数据录入!$K$5:$K$4999,$B79),2)) | H79: =IF($B79="","",ROUND(N($E79)-N($F79),2)) | I79: =IF($B79="","",ROUND(N($F79)-N($G79),2)) | J79: =IF($B79="","",IF(AND(N($E79)=0,N($G79)=0),"没有往来",IF(ROUND(N($I79),2)<>0,"差 "&TEXT(N($I79),"0.00")&" 元：【数据录入】里这个供货商的付款还没记全，或者没选供货商名",IF(N($H79)>0,"还欠 "&TEXT(N($H79),"0.00")&" 元","已结清"))))
A80: =IF($B80="","",MAX($A$69:A79)+1) | B80: =IF(基础资料!$G12="","",基础资料!$G12) | C80: =IF($B80="","",ROUND(SUMIFS('往来款跟进'!$O$11:$O$510,'往来款跟进'!$N$11:$N$510,$B80),2)) | E80: =IF($B80="","",N($C80)) | F80: =IF($B80="","",ROUND(SUMIFS('往来款跟进'!$P$11:$P$510,'往来款跟进'!$N$11:$N$510,$B80),2)) | G80: =IF($B80="","",ROUND(SUMIFS(数据录入!$G$5:$G$4999,数据录入!$K$5:$K$4999,$B80),2)) | H80: =IF($B80="","",ROUND(N($E80)-N($F80),2)) | I80: =IF($B80="","",ROUND(N($F80)-N($G80),2)) | J80: =IF($B80="","",IF(AND(N($E80)=0,N($G80)=0),"没有往来",IF(ROUND(N($I80),2)<>0,"差 "&TEXT(N($I80),"0.00")&" 元：【数据录入】里这个供货商的付款还没记全，或者没选供货商名",IF(N($H80)>0,"还欠 "&TEXT(N($H80),"0.00")&" 元","已结清"))))
A81: =IF($B81="","",MAX($A$69:A80)+1) | B81: =IF(基础资料!$G13="","",基础资料!$G13) | C81: =IF($B81="","",ROUND(SUMIFS('往来款跟进'!$O$11:$O$510,'往来款跟进'!$N$11:$N$510,$B81),2)) | E81: =IF($B81="","",N($C81)) | F81: =IF($B81="","",ROUND(SUMIFS('往来款跟进'!$P$11:$P$510,'往来款跟进'!$N$11:$N$510,$B81),2)) | G81: =IF($B81="","",ROUND(SUMIFS(数据录入!$G$5:$G$4999,数据录入!$K$5:$K$4999,$B81),2)) | H81: =IF($B81="","",ROUND(N($E81)-N($F81),2)) | I81: =IF($B81="","",ROUND(N($F81)-N($G81),2)) | J81: =IF($B81="","",IF(AND(N($E81)=0,N($G81)=0),"没有往来",IF(ROUND(N($I81),2)<>0,"差 "&TEXT(N($I81),"0.00")&" 元：【数据录入】里这个供货商的付款还没记全，或者没选供货商名",IF(N($H81)>0,"还欠 "&TEXT(N($H81),"0.00")&" 元","已结清"))))
... A89: =IF($B89="","",MAX($A$69:A88)+1) | B89: =IF(基础资料!$G21="","",基础资料!$G21) | C89: =IF($B89="","",ROUND(SUMIFS('往来款跟进'!$O$11:$O$510,'往来款跟进'!$N$11:$N$510,$B89),2)) | E89: =IF($B89="","",N($C89)) | F89: =IF($B89="","",ROUND(SUMIFS('往来款跟进'!$P$11:$P$510,'往来款跟进'!$N$11:$N$510,$B89),2)) | G89: =IF($B89="","",ROUND(SUMIFS(数据录入!$G$5:$G$4999,数据录入!$K$5:$K$4999,$B89),2)) | H89: =IF($B89="","",ROUND(N($E89)-N($F89),2)) | I89: =IF($B89="","",ROUND(N($F89)-N($G89),2)) | J89: =IF($B89="","",IF(AND(N($E89)=0,N($G89)=0),"没有往来",IF(ROUND(N($I89),2)<>0,"差 "&TEXT(N($I89),"0.00")&" 元：【数据录入】里这个供货商的付款还没记全，或者没选供货商名",IF(N($H89)>0,"还欠 "&TEXT(N($H89),"0.00")&" 元","已结清"))))
A90: 合 计 | C90: =ROUND(SUM(C70:C89),2) | D90: =ROUND(SUM(D70:D89),2) | E90: =ROUND(SUM(E70:E89),2) | F90: =ROUND(SUM(F70:F89),2) | G90: =ROUND(SUM(G70:G89),2) | H90: =ROUND(SUM(H70:H89),2) | I90: =ROUND(SUM(I70:I89),2)
A92: 三、还没挂到人头上的钱（这部分往来款跟进认领不到）
A93: 收进来但没选客户名的钱 | F93: =ROUND(SUMIFS(数据录入!$F$5:$F$4999,数据录入!$J$5:$J$4999,""),2) | J93: 在【数据录入】里把这些行的「客户」列选上，【往来款跟进】的已收款就会自动认领。
A94: 付出去但没选供应商的钱（支出类别已选“供应商”） | F94: =ROUND(SUMIFS(数据录入!$G$5:$G$4999,数据录入!$K$5:$K$4999,"",数据录入!$D$5:$D$4999,"供应商"),2) | J94: 原表第 32 行就是这样：支出类别选了「供应商」，但「供应商」那一列没填，1000 元没人认领。
A95: 【数据录入】收入合计 | F95: =ROUND(SUM(数据录入!$F$5:$F$4999),2) | J95: 供核对：上面第 1 行 ÷ 这一行 ＝ 还没挂人头的比例
A96: 【数据录入】支出合计 | F96: =ROUND(SUM(数据录入!$G$5:$G$4999),2)

Sheet 汇报表
A1: 资金日报统计表（任意连续日期 / 单独一天查询）
A2: 起始日期 | B2: 46266 | D2: 截止日期 | E2: 46295 | G2: 查询天数 | H2: =IF(OR($B$2="",$E$2=""),"",IF($E$2<$B$2,"日期错误",IF($E$2-$B$2+1>31,"超过31天",$E$2-$B$2+1)))
A3: 提示：修改黄色日期即可查询；单独一天时起始日期=截止日期；默认展开31天，超过31天建议按月分段查询。
A4: 公司期初余额 | C4: 期间收款合计 | E4: 期间付款合计 | G4: 期末结余金额
B5: =SUM(B8:B21) | D5: =SUM(BM8:BM21) | F5: =SUM(BN8:BN21) | H5: =SUM(BO8:BO21)
C6: =IF(1<=MIN($H$2,31),$B$2+0,"") | D6: =IF(1<=MIN($H$2,31),$B$2+0,"") | E6: =IF(2<=MIN($H$2,31),$B$2+1,"") | F6: =IF(2<=MIN($H$2,31),$B$2+1,"") | G6: =IF(3<=MIN($H$2,31),$B$2+2,"") | H6: =IF(3<=MIN($H$2,31),$B$2+2,"") | I6: =IF(4<=MIN($H$2,31),$B$2+3,"") | J6: =IF(4<=MIN($H$2,31),$B$2+3,"") | K6: =IF(5<=MIN($H$2,31),$B$2+4,"") | L6: =IF(5<=MIN($H$2,31),$B$2+4,"") | M6: =IF(6<=MIN($H$2,31),$B$2+5,"") | N6: =IF(6<=MIN($H$2,31),$B$2+5,"") | O6: =IF(7<=MIN($H$2,31),$B$2+6,"") | P6: =IF(7<=MIN($H$2,31),$B$2+6,"") | Q6: =IF(8<=MIN($H$2,31),$B$2+7,"") | R6: =IF(8<=MIN($H$2,31),$B$2+7,"") | S6: =IF(9<=MIN($H$2,31),$B$2+8,"") | T6: =IF(9<=MIN($H$2,31),$B$2+8,"") | U6: =IF(10<=MIN($H$2,31),$B$2+9,"") | V6: =IF(10<=MIN($H$2,31),$B$2+9,"") | W6: =IF(11<=MIN($H$2,31),$B$2+10,"") | X6: =IF(11<=MIN($H$2,31),$B$2+10,"") | Y6: =IF(12<=MIN($H$2,31),$B$2+11,"") | Z6: =IF(12<=MIN($H$2,31),$B$2+11,"") | AA6: =IF(13<=MIN($H$2,31),$B$2+12,"") | AB6: =IF(13<=MIN($H$2,31),$B$2+12,"") | AC6: =IF(14<=MIN($H$2,31),$B$2+13,"") | AD6: =IF(14<=MIN($H$2,31),$B$2+13,"") | AE6: =IF(15<=MIN($H$2,31),$B$2+14,"") | AF6: =IF(15<=MIN($H$2,31),$B$2+14,"") | AG6: =IF(16<=MIN($H$2,31),$B$2+15,"") | AH6: =IF(16<=MIN($H$2,31),$B$2+15,"") | AI6: =IF(17<=MIN($H$2,31),$B$2+16,"") | AJ6: =IF(17<=MIN($H$2,31),$B$2+16,"") | AK6: =IF(18<=MIN($H$2,31),$B$2+17,"") | AL6: =IF(18<=MIN($H$2,31),$B$2+17,"") | AM6: =IF(19<=MIN($H$2,31),$B$2+18,"") | AN6: =IF(19<=MIN($H$2,31),$B$2+18,"") | AO6: =IF(20<=MIN($H$2,31),$B$2+19,"") | AP6: =IF(20<=MIN($H$2,31),$B$2+19,"") | AQ6: =IF(21<=MIN($H$2,31),$B$2+20,"") | AR6: =IF(21<=MIN($H$2,31),$B$2+20,"") | AS6: =IF(22<=MIN($H$2,31),$B$2+21,"") | AT6: =IF(22<=MIN($H$2,31),$B$2+21,"") | AU6: =IF(23<=MIN($H$2,31),$B$2+22,"") | AV6: =IF(23<=MIN($H$2,31),$B$2+22,"") | AW6: =IF(24<=MIN($H$2,31),$B$2+23,"") | AX6: =IF(24<=MIN($H$2,31),$B$2+23,"") | AY6: =IF(25<=MIN($H$2,31),$B$2+24,"") | AZ6: =IF(25<=MIN($H$2,31),$B$2+24,"") | BA6: =IF(26<=MIN($H$2,31),$B$2+25,"") | BB6: =IF(26<=MIN($H$2,31),$B$2+25,"") | BC6: =IF(27<=MIN($H$2,31),$B$2+26,"") | BD6: =IF(27<=MIN($H$2,31),$B$2+26,"") | BE6: =IF(28<=MIN($H$2,31),$B$2+27,"") | BF6: =IF(28<=MIN($H$2,31),$B$2+27,"") | BG6: =IF(29<=MIN($H$2,31),$B$2+28,"") | BH6: =IF(29<=MIN($H$2,31),$B$2+28,"") | BI6: =IF(30<=MIN($H$2,31),$B$2+29,"") | BJ6: =IF(30<=MIN($H$2,31),$B$2+29,"") | BK6: =IF(31<=MIN($H$2,31),$B$2+30,"") | BL6: =IF(31<=MIN($H$2,31),$B$2+30,"")
A7: 账户 | B7: 期初余额 | C7: =IF(C$6="","","收款") | D7: =IF(D$6="","","付款") | E7: =IF(E$6="","","收款") | F7: =IF(F$6="","","付款") | G7: =IF(G$6="","","收款") | H7: =IF(H$6="","","付款") | I7: =IF(I$6="","","收款") | J7: =IF(J$6="","","付款") | K7: =IF(K$6="","","收款") | L7: =IF(L$6="","","付款") | M7: =IF(M$6="","","收款") | N7: =IF(N$6="","","付款") | O7: =IF(O$6="","","收款") | P7: =IF(P$6="","","付款") | Q7: =IF(Q$6="","","收款") | R7: =IF(R$6="","","付款") | S7: =IF(S$6="","","收款") | T7: =IF(T$6="","","付款") | U7: =IF(U$6="","","收款") | V7: =IF(V$6="","","付款") | W7: =IF(W$6="","","收款") | X7: =IF(X$6="","","付款") | Y7: =IF(Y$6="","","收款") | Z7: =IF(Z$6="","","付款") | AA7: =IF(AA$6="","","收款") | AB7: =IF(AB$6="","","付款") | AC7: =IF(AC$6="","","收款") | AD7: =IF(AD$6="","","付款") | AE7: =IF(AE$6="","","收款") | AF7: =IF(AF$6="","","付款") | AG7: =IF(AG$6="","","收款") | AH7: =IF(AH$6="","","付款") | AI7: =IF(AI$6="","","收款") | AJ7: =IF(AJ$6="","","付款") | AK7: =IF(AK$6="","","收款") | AL7: =IF(AL$6="","","付款") | AM7: =IF(AM$6="","","收款") | AN7: =IF(AN$6="","","付款") | AO7: =IF(AO$6="","","收款") | AP7: =IF(AP$6="","","付款") | AQ7: =IF(AQ$6="","","收款") | AR7: =IF(AR$6="","","付款") | AS7: =IF(AS$6="","","收款") | AT7: =IF(AT$6="","","付款") | AU7: =IF(AU$6="","","收款") | AV7: =IF(AV$6="","","付款") | AW7: =IF(AW$6="","","收款") | AX7: =IF(AX$6="","","付款") | AY7: =IF(AY$6="","","收款") | AZ7: =IF(AZ$6="","","付款") | BA7: =IF(BA$6="","","收款") | BB7: =IF(BB$6="","","付款") | BC7: =IF(BC$6="","","收款") | BD7: =IF(BD$6="","","付款") | BE7: =IF(BE$6="","","收款") | BF7: =IF(BF$6="","","付款") | BG7: =IF(BG$6="","","收款") | BH7: =IF(BH$6="","","付款") | BI7: =IF(BI$6="","","收款") | BJ7: =IF(BJ$6="","","付款") | BK7: =IF(BK$6="","","收款") | BL7: =IF(BL$6="","","付款") | BM7: 收款合计 | BN7: 付款合计 | BO7: 期末余额
A8: 现金 | B8: =IF(OR($A8="",NOT(ISNUMBER($H$2))),"",SUMIFS(数据录入!$H$5:$H$4999,数据录入!$C$5:$C$4999,$A8,数据录入!$E$5:$E$4999,"期初余额",数据录入!$B$5:$B$4999,"<="&$B$2)+SUMIFS(数据录入!$F$5:$F$4999,数据录入!$C$5:$C$4999,$A8,数据录入!$B$5:$B$4999,"<"&$B$2)-SUMIFS(数据录入!$G$5:$G$4999,数据录入!$C$5:$C$4999,$A8,数据录入!$B$5:$B$4999,"<"&$B$2)) | C8: =IF(OR($A8="",C$6="",NOT(ISNUMBER($H$2))),"",SUMIFS(数据录入!$F$5:$F$4999,数据录入!$C$5:$C$4999,$A8,数据录入!$B$5:$B$4999,C$6)) | D8: =IF(OR($A8="",D$6="",NOT(ISNUMBER($H$2))),"",SUMIFS(数据录入!$G$5:$G$4999,数据录入!$C$5:$C$4999,$A8,数据录入!$B$5:$B$4999,D$6)) | E8: =IF(OR($A8="",E$6="",NOT(ISNUMBER($H$2))),"",SUMIFS(数据录入!$F$5:$F$4999,数据录入!$C$5:$C$4999,$A8,数据录入!$B$5:$B$4999,E$6)) | F8: =IF(OR($A8="",F$6="",NOT(ISNUMBER($H$2))),"",SUMIFS(数据录入!$G$5:$G$4999,数据录入!$C$5:$C$4999,$A8,数据录入!$B$5:$B$4999,F$6)) | G8: =IF(OR($A8="",G$6="",NOT(ISNUMBER($H$2))),"",SUMIFS(数据录入!$F$5:$F$4999,数据录入!$C$5:$C$4999,$A8,数据录入!$B$5:$B$4999,G$6)) | H8: =IF(OR($A8="",H$6="",NOT(ISNUMBER($H$2))),"",SUMIFS(数据录入!$G$5:$G$4999,数据录入!$C$5:$C$4999,$A8,数据录入!$B$5:$B$4999,H$6)) | I8: =IF(OR($A8="",I$6="",NOT(ISNUMBER($H$2))),"",SUMIFS(数据录入!$F$5:$F$4999,数据录入!$C$5:$C$4999,$A8,数据录入!$B$5:$B$4999,I$6)) | J8: =IF(OR($A8="",J$6="",NOT(ISNUMBER($H$2))),"",SUMIFS(数据录入!$G$5:$G$4999,数据录入!$C$5:$C$4999,$A8,数据录入!$B$5:$B$4999,J$6)) | K8: =IF(OR($A8="",K$6="",NOT(ISNUMBER($H$2))),"",SUMIFS(数据录入!$F$5:$F$4999,数据录入!$C$5:$C$4999,$A8,数据录入!$B$5:$B$4999,K$6)) | L8: =IF(OR($A8="",L$6="",NOT(ISNUMBER($H$2))),"",SUMIFS(数据录入!$G$5:$G$4999,数据录入!$C$5:$C$4999,$A8,数据录入!$B$5:$B$4999,L$6)) | M8: =IF(OR($A8="",M$6="",NOT(ISNUMBER($H$2))),"",SUMIFS(数据录入!$F$5:$F$4999,数据录入!$C$5:$C$4999,$A8,数据录入!$B$5:$B$4999,M$6)) | N8: =IF(OR($A8="",N$6="",NOT(ISNUMBER($H$2))),"",SUMIFS(数据录入!$G$5:$G$4999,数据录入!$C$5:$C$4999,$A8,数据录入!$B$5:$B$4999,N$6)) | O8: =IF(OR($A8="",O$6="",NOT(ISNUMBER($H$2))),"",SUMIFS(数据录入!$F$5:$F$4999,数据录入!$C$5:$C$4999,$A8,数据录入!$B$5:$B$4999,O$6)) | P8: =IF(OR($A8="",P$6="",NOT(ISNUMBER($H$2))),"",SUMIFS(数据录入!$G$5:$G$4999,数据录入!$C$5:$C$4999,$A8,数据录入!$B$5:$B$4999,P$6)) | Q8: =IF(OR($A8="",Q$6="",NOT(ISNUMBER($H$2))),"",SUMIFS(数据录入!$F$5:$F$4999,数据录入!$C$5:$C$4999,$A8,数据录入!$B$5:$B$4999,Q$6)) | R8: =IF(OR($A8="",R$6="",NOT(ISNUMBER($H$2))),"",SUMIFS(数据录入!$G$5:$G$4999,数据录入!$C$5:$C$4999,$A8,数据录入!$B$5:$B$4999,R$6)) | S8: =IF(OR($A8="",S$6="",NOT(ISNUMBER($H$2))),"",SUMIFS(数据录入!$F$5:$F$4999,数据录入!$C$5:$C$4999,$A8,数据录入!$B$5:$B$4999,S$6)) | T8: =IF(OR($A8="",T$6="",NOT(ISNUMBER($H$2))),"",SUMIFS(数据录入!$G$5:$G$4999,数据录入!$C$5:$C$4999,$A8,数据录入!$B$5:$B$4999,T$6)) | U8: =IF(OR($A8="",U$6="",NOT(ISNUMBER($H$2))),"",SUMIFS(数据录入!$F$5:$F$4999,数据录入!$C$5:$C$4999,$A8,数据录入!$B$5:$B$4999,U$6)) | V8: =IF(OR($A8="",V$6="",NOT(ISNUMBER($H$2))),"",SUMIFS(数据录入!$G$5:$G$4999,数据录入!$C$5:$C$4999,$A8,数据录入!$B$5:$B$4999,V$6)) | W8: =IF(OR($A8="",W$6="",NOT(ISNUMBER($H$2))),"",SUMIFS(数据录入!$F$5:$F$4999,数据录入!$C$5:$C$4999,$A8,数据录入!$B$5:$B$4999,W$6)) | X8: =IF(OR($A8="",X$6="",NOT(ISNUMBER($H$2))),"",SUMIFS(数据录入!$G$5:$G$4999,数据录入!$C$5:$C$4999,$A8,数据录入!$B$5:$B$4999,X$6)) | Y8: =IF(OR($A8="",Y$6="",NOT(ISNUMBER($H$2))),"",SUMIFS(数据录入!$F$5:$F$4999,数据录入!$C$5:$C$4999,$A8,数据录入!$B$5:$B$4999,Y$6)) | Z8: =IF(OR($A8="",Z$6="",NOT(ISNUMBER($H$2))),"",SUMIFS(数据录入!$G$5:$G$4999,数据录入!$C$5:$C$4999,$A8,数据录入!$B$5:$B$4999,Z$6)) | AA8: =IF(OR($A8="",AA$6="",NOT(ISNUMBER($H$2))),"",SUMIFS(数据录入!$F$5:$F$4999,数据录入!$C$5:$C$4999,$A8,数据录入!$B$5:$B$4999,AA$6)) | AB8: =IF(OR($A8="",AB$6="",NOT(ISNUMBER($H$2))),"",SUMIFS(数据录入!$G$5:$G$4999,数据录入!$C$5:$C$4999,$A8,数据录入!$B$5:$B$4999,AB$6)) | AC8: =IF(OR($A8="",AC$6="",NOT(ISNUMBER($H$2))),"",SUMIFS(数据录入!$F$5:$F$4999,数据录入!$C$5:$C$4999,$A8,数据录入!$B$5:$B$4999,AC$6)) | AD8: =IF(OR($A8="",AD$6="",NOT(ISNUMBER($H$2))),"",SUMIFS(数据录入!$G$5:$G$4999,数据录入!$C$5:$C$4999,$A8,数据录入!$B$5:$B$4999,AD$6)) | AE8: =IF(OR($A8="",AE$6="",NOT(ISNUMBER($H$2))),"",SUMIFS(数据录入!$F$5:$F$4999,数据录入!$C$5:$C$4999,$A8,数据录入!$B$5:$B$4999,AE$6)) | AF8: =IF(OR($A8="",AF$6="",NOT(ISNUMBER($H$2))),"",SUMIFS(数据录入!$G$5:$G$4999,数据录入!$C$5:$C$4999,$A8,数据录入!$B$5:$B$4999,AF$6)) | AG8: =IF(OR($A8="",AG$6="",NOT(ISNUMBER($H$2))),"",SUMIFS(数据录入!$F$5:$F$4999,数据录入!$C$5:$C$4999,$A8,数据录入!$B$5:$B$4999,AG$6)) | AH8: =IF(OR($A8="",AH$6="",NOT(ISNUMBER($H$2))),"",SUMIFS(数据录入!$G$5:$G$4999,数据录入!$C$5:$C$4999,$A8,数据录入!$B$5:$B$4999,AH$6)) | AI8: =IF(OR($A8="",AI$6="",NOT(ISNUMBER($H$2))),"",SUMIFS(数据录入!$F$5:$F$4999,数据录入!$C$5:$C$4999,$A8,数据录入!$B$5:$B$4999,AI$6)) | AJ8: =IF(OR($A8="",AJ$6="",NOT(ISNUMBER($H$2))),"",SUMIFS(数据录入!$G$5:$G$4999,数据录入!$C$5:$C$4999,$A8,数据录入!$B$5:$B$4999,AJ$6)) | AK8: =IF(OR($A8="",AK$6="",NOT(ISNUMBER($H$2))),"",SUMIFS(数据录入!$F$5:$F$4999,数据录入!$C$5:$C$4999,$A8,数据录入!$B$5:$B$4999,AK$6)) | AL8: =IF(OR($A8="",AL$6="",NOT(ISNUMBER($H$2))),"",SUMIFS(数据录入!$G$5:$G$4999,数据录入!$C$5:$C$4999,$A8,数据录入!$B$5:$B$4999,AL$6)) | AM8: =IF(OR($A8="",AM$6="",NOT(ISNUMBER($H$2))),"",SUMIFS(数据录入!$F$5:$F$4999,数据录入!$C$5:$C$4999,$A8,数据录入!$B$5:$B$4999,AM$6)) | AN8: =IF(OR($A8="",AN$6="",NOT(ISNUMBER($H$2))),"",SUMIFS(数据录入!$G$5:$G$4999,数据录入!$C$5:$C$4999,$A8,数据录入!$B$5:$B$4999,AN$6)) | AO8: =IF(OR($A8="",AO$6="",NOT(ISNUMBER($H$2))),"",SUMIFS(数据录入!$F$5:$F$4999,数据录入!$C$5:$C$4999,$A8,数据录入!$B$5:$B$4999,AO$6)) | AP8: =IF(OR($A8="",AP$6="",NOT(ISNUMBER($H$2))),"",SUMIFS(数据录入!$G$5:$G$4999,数据录入!$C$5:$C$4999,$A8,数据录入!$B$5:$B$4999,AP$6)) | AQ8: =IF(OR($A8="",AQ$6="",NOT(ISNUMBER($H$2))),"",SUMIFS(数据录入!$F$5:$F$4999,数据录入!$C$5:$C$4999,$A8,数据录入!$B$5:$B$4999,AQ$6)) | AR8: =IF(OR($A8="",AR$6="",NOT(ISNUMBER($H$2))),"",SUMIFS(数据录入!$G$5:$G$4999,数据录入!$C$5:$C$4999,$A8,数据录入!$B$5:$B$4999,AR$6)) | AS8: =IF(OR($A8="",AS$6="",NOT(ISNUMBER($H$2))),"",SUMIFS(数据录入!$F$5:$F$4999,数据录入!$C$5:$C$4999,$A8,数据录入!$B$5:$B$4999,AS$6)) | AT8: =IF(OR($A8="",AT$6="",NOT(ISNUMBER($H$2))),"",SUMIFS(数据录入!$G$5:$G$4999,数据录入!$C$5:$C$4999,$A8,数据录入!$B$5:$B$4999,AT$6)) | AU8: =IF(OR($A8="",AU$6="",NOT(ISNUMBER($H$2))),"",SUMIFS(数据录入!$F$5:$F$4999,数据录入!$C$5:$C$4999,$A8,数据录入!$B$5:$B$4999,AU$6)) | AV8: =IF(OR($A8="",AV$6="",NOT(ISNUMBER($H$2))),"",SUMIFS(数据录入!$G$5:$G$4999,数据录入!$C$5:$C$4999,$A8,数据录入!$B$5:$B$4999,AV$6)) | AW8: =IF(OR($A8="",AW$6="",NOT(ISNUMBER($H$2))),"",SUMIFS(数据录入!$F$5:$F$4999,数据录入!$C$5:$C$4999,$A8,数据录入!$B$5:$B$4999,AW$6)) | AX8: =IF(OR($A8="",AX$6="",NOT(ISNUMBER($H$2))),"",SUMIFS(数据录入!$G$5:$G$4999,数据录入!$C$5:$C$4999,$A8,数据录入!$B$5:$B$4999,AX$6)) | AY8: =IF(OR($A8="",AY$6="",NOT(ISNUMBER($H$2))),"",SUMIFS(数据录入!$F$5:$F$4999,数据录入!$C$5:$C$4999,$A8,数据录入!$B$5:$B$4999,AY$6)) | AZ8: =IF(OR($A8="",AZ$6="",NOT(ISNUMBER($H$2))),"",SUMIFS(数据录入!$G$5:$G$4999,数据录入!$C$5:$C$4999,$A8,数据录入!$B$5:$B$4999,AZ$6)) | BA8: =IF(OR($A8="",BA$6="",NOT(ISNUMBER($H$2))),"",SUMIFS(数据录入!$F$5:$F$4999,数据录入!$C$5:$C$4999,$A8,数据录入!$B$5:$B$4999,BA$6)) | BB8: =IF(OR($A8="",BB$6="",NOT(ISNUMBER($H$2))),"",SUMIFS(数据录入!$G$5:$G$4999,数据录入!$C$5:$C$4999,$A8,数据录入!$B$5:$B$4999,BB$6)) | BC8: =IF(OR($A8="",BC$6="",NOT(ISNUMBER($H$2))),"",SUMIFS(数据录入!$F$5:$F$4999,数据录入!$C$5:$C$4999,$A8,数据录入!$B$5:$B$4999,BC$6)) | BD8: =IF(OR($A8="",BD$6="",NOT(ISNUMBER($H$2))),"",SUMIFS(数据录入!$G$5:$G$4999,数据录入!$C$5:$C$4999,$A8,数据录入!$B$5:$B$4999,BD$6)) | BE8: =IF(OR($A8="",BE$6="",NOT(ISNUMBER($H$2))),"",SUMIFS(数据录入!$F$5:$F$4999,数据录入!$C$5:$C$4999,$A8,数据录入!$B$5:$B$4999,BE$6)) | BF8: =IF(OR($A8="",BF$6="",NOT(ISNUMBER($H$2))),"",SUMIFS(数据录入!$G$5:$G$4999,数据录入!$C$5:$C$4999,$A8,数据录入!$B$5:$B$4999,BF$6)) | BG8: =IF(OR($A8="",BG$6="",NOT(ISNUMBER($H$2))),"",SUMIFS(数据录入!$F$5:$F$4999,数据录入!$C$5:$C$4999,$A8,数据录入!$B$5:$B$4999,BG$6)) | BH8: =IF(OR($A8="",BH$6="",NOT(ISNUMBER($H$2))),"",SUMIFS(数据录入!$G$5:$G$4999,数据录入!$C$5:$C$4999,$A8,数据录入!$B$5:$B$4999,BH$6)) | BI8: =IF(OR($A8="",BI$6="",NOT(ISNUMBER($H$2))),"",SUMIFS(数据录入!$F$5:$F$4999,数据录入!$C$5:$C$4999,$A8,数据录入!$B$5:$B$4999,BI$6)) | BJ8: =IF(OR($A8="",BJ$6="",NOT(ISNUMBER($H$2))),"",SUMIFS(数据录入!$G$5:$G$4999,数据录入!$C$5:$C$4999,$A8,数据录入!$B$5:$B$4999,BJ$6)) | BK8: =IF(OR($A8="",BK$6="",NOT(ISNUMBER($H$2))),"",SUMIFS(数据录入!$F$5:$F$4999,数据录入!$C$5:$C$4999,$A8,数据录入!$B$5:$B$4999,BK$6)) | BL8: =IF(OR($A8="",BL$6="",NOT(ISNUMBER($H$2))),"",SUMIFS(数据录入!$G$5:$G$4999,数据录入!$C$5:$C$4999,$A8,数据录入!$B$5:$B$4999,BL$6)) | BM8: =IF($A8="","",SUMIF($C$7:$BL$7,"收款",C8:BL8)) | BN8: =IF($A8="","",SUMIF($C$7:$BL$7,"付款",C8:BL8)) | BO8: =IF($A8="","",B8+BM8-BN8)
A9: 微信 | B9: =IF(OR($A9="",NOT(ISNUMBER($H$2))),"",SUMIFS(数据录入!$H$5:$H$4999,数据录入!$C$5:$C$4999,$A9,数据录入!$E$5:$E$4999,"期初余额",数据录入!$B$5:$B$4999,"<="&$B$2)+SUMIFS(数据录入!$F$5:$F$4999,数据录入!$C$5:$C$4999,$A9,数据录入!$B$5:$B$4999,"<"&$B$2)-SUMIFS(数据录入!$G$5:$G$4999,数据录入!$C$5:$C$4999,$A9,数据录入!$B$5:$B$4999,"<"&$B$2)) | C9: =IF(OR($A9="",C$6="",NOT(ISNUMBER($H$2))),"",SUMIFS(数据录入!$F$5:$F$4999,数据录入!$C$5:$C$4999,$A9,数据录入!$B$5:$B$4999,C$6)) | D9: =IF(OR($A9="",D$6="",NOT(ISNUMBER($H$2))),"",SUMIFS(数据录入!$G$5:$G$4999,数据录入!$C$5:$C$4999,$A9,数据录入!$B$5:$B$4999,D$6)) | E9: =IF(OR($A9="",E$6="",NOT(ISNUMBER($H$2))),"",SUMIFS(数据录入!$F$5:$F$4999,数据录入!$C$5:$C$4999,$A9,数据录入!$B$5:$B$4999,E$6)) | F9: =IF(OR($A9="",F$6="",NOT(ISNUMBER($H$2))),"",SUMIFS(数据录入!$G$5:$G$4999,数据录入!$C$5:$C$4999,$A9,数据录入!$B$5:$B$4999,F$6)) | G9: =IF(OR($A9="",G$6="",NOT(ISNUMBER($H$2))),"",SUMIFS(数据录入!$F$5:$F$4999,数据录入!$C$5:$C$4999,$A9,数据录入!$B$5:$B$4999,G$6)) | H9: =IF(OR($A9="",H$6="",NOT(ISNUMBER($H$2))),"",SUMIFS(数据录入!$G$5:$G$4999,数据录入!$C$5:$C$4999,$A9,数据录入!$B$5:$B$4999,H$6)) | I9: =IF(OR($A9="",I$6="",NOT(ISNUMBER($H$2))),"",SUMIFS(数据录入!$F$5:$F$4999,数据录入!$C$5:$C$4999,$A9,数据录入!$B$5:$B$4999,I$6)) | J9: =IF(OR($A9="",J$6="",NOT(ISNUMBER($H$2))),"",SUMIFS(数据录入!$G$5:$G$4999,数据录入!$C$5:$C$4999,$A9,数据录入!$B$5:$B$4999,J$6)) | K9: =IF(OR($A9="",K$6="",NOT(ISNUMBER($H$2))),"",SUMIFS(数据录入!$F$5:$F$4999,数据录入!$C$5:$C$4999,$A9,数据录入!$B$5:$B$4999,K$6)) | L9: =IF(OR($A9="",L$6="",NOT(ISNUMBER($H$2))),"",SUMIFS(数据录入!$G$5:$G$4999,数据录入!$C$5:$C$4999,$A9,数据录入!$B$5:$B$4999,L$6)) | M9: =IF(OR($A9="",M$6="",NOT(ISNUMBER($H$2))),"",SUMIFS(数据录入!$F$5:$F$4999,数据录入!$C$5:$C$4999,$A9,数据录入!$B$5:$B$4999,M$6)) | N9: =IF(OR($A9="",N$6="",NOT(ISNUMBER($H$2))),"",SUMIFS(数据录入!$G$5:$G$4999,数据录入!$C$5:$C$4999,$A9,数据录入!$B$5:$B$4999,N$6)) | O9: =IF(OR($A9="",O$6="",NOT(ISNUMBER($H$2))),"",SUMIFS(数据录入!$F$5:$F$4999,数据录入!$C$5:$C$4999,$A9,数据录入!$B$5:$B$4999,O$6)) | P9: =IF(OR($A9="",P$6="",NOT(ISNUMBER($H$2))),"",SUMIFS(数据录入!$G$5:$G$4999,数据录入!$C$5:$C$4999,$A9,数据录入!$B$5:$B$4999,P$6)) | Q9: =IF(OR($A9="",Q$6="",NOT(ISNUMBER($H$2))),"",SUMIFS(数据录入!$F$5:$F$4999,数据录入!$C$5:$C$4999,$A9,数据录入!$B$5:$B$4999,Q$6)) | R9: =IF(OR($A9="",R$6="",NOT(ISNUMBER($H$2))),"",SUMIFS(数据录入!$G$5:$G$4999,数据录入!$C$5:$C$4999,$A9,数据录入!$B$5:$B$4999,R$6)) | S9: =IF(OR($A9="",S$6="",NOT(ISNUMBER($H$2))),"",SUMIFS(数据录入!$F$5:$F$4999,数据录入!$C$5:$C$4999,$A9,数据录入!$B$5:$B$4999,S$6)) | T9: =IF(OR($A9="",T$6="",NOT(ISNUMBER($H$2))),"",SUMIFS(数据录入!$G$5:$G$4999,数据录入!$C$5:$C$4999,$A9,数据录入!$B$5:$B$4999,T$6)) | U9: =IF(OR($A9="",U$6="",NOT(ISNUMBER($H$2))),"",SUMIFS(数据录入!$F$5:$F$4999,数据录入!$C$5:$C$4999,$A9,数据录入!$B$5:$B$4999,U$6)) | V9: =IF(OR($A9="",V$6="",NOT(ISNUMBER($H$2))),"",SUMIFS(数据录入!$G$5:$G$4999,数据录入!$C$5:$C$4999,$A9,数据录入!$B$5:$B$4999,V$6)) | W9: =IF(OR($A9="",W$6="",NOT(ISNUMBER($H$2))),"",SUMIFS(数据录入!$F$5:$F$4999,数据录入!$C$5:$C$4999,$A9,数据录入!$B$5:$B$4999,W$6)) | X9: =IF(OR($A9="",X$6="",NOT(ISNUMBER($H$2))),"",SUMIFS(数据录入!$G$5:$G$4999,数据录入!$C$5:$C$4999,$A9,数据录入!$B$5:$B$4999,X$6)) | Y9: =IF(OR($A9="",Y$6="",NOT(ISNUMBER($H$2))),"",SUMIFS(数据录入!$F$5:$F$4999,数据录入!$C$5:$C$4999,$A9,数据录入!$B$5:$B$4999,Y$6)) | Z9: =IF(OR($A9="",Z$6="",NOT(ISNUMBER($H$2))),"",SUMIFS(数据录入!$G$5:$G$4999,数据录入!$C$5:$C$4999,$A9,数据录入!$B$5:$B$4999,Z$6)) | AA9: =IF(OR($A9="",AA$6="",NOT(ISNUMBER($H$2))),"",SUMIFS(数据录入!$F$5:$F$4999,数据录入!$C$5:$C$4999,$A9,数据录入!$B$5:$B$4999,AA$6)) | AB9: =IF(OR($A9="",AB$6="",NOT(ISNUMBER($H$2))),"",SUMIFS(数据录入!$G$5:$G$4999,数据录入!$C$5:$C$4999,$A9,数据录入!$B$5:$B$4999,AB$6)) | AC9: =IF(OR($A9="",AC$6="",NOT(ISNUMBER($H$2))),"",SUMIFS(数据录入!$F$5:$F$4999,数据录入!$C$5:$C$4999,$A9,数据录入!$B$5:$B$4999,AC$6)) | AD9: =IF(OR($A9="",AD$6="",NOT(ISNUMBER($H$2))),"",SUMIFS(数据录入!$G$5:$G$4999,数据录入!$C$5:$C$4999,$A9,数据录入!$B$5:$B$4999,AD$6)) | AE9: =IF(OR($A9="",AE$6="",NOT(ISNUMBER($H$2))),"",SUMIFS(数据录入!$F$5:$F$4999,数据录入!$C$5:$C$4999,$A9,数据录入!$B$5:$B$4999,AE$6)) | AF9: =IF(OR($A9="",AF$6="",NOT(ISNUMBER($H$2))),"",SUMIFS(数据录入!$G$5:$G$4999,数据录入!$C$5:$C$4999,$A9,数据录入!$B$5:$B$4999,AF$6)) | AG9: =IF(OR($A9="",AG$6="",NOT(ISNUMBER($H$2))),"",SUMIFS(数据录入!$F$5:$F$4999,数据录入!$C$5:$C$4999,$A9,数据录入!$B$5:$B$4999,AG$6)) | AH9: =IF(OR($A9="",AH$6="",NOT(ISNUMBER($H$2))),"",SUMIFS(数据录入!$G$5:$G$4999,数据录入!$C$5:$C$4999,$A9,数据录入!$B$5:$B$4999,AH$6)) | AI9: =IF(OR($A9="",AI$6="",NOT(ISNUMBER($H$2))),"",SUMIFS(数据录入!$F$5:$F$4999,数据录入!$C$5:$C$4999,$A9,数据录入!$B$5:$B$4999,AI$6)) | AJ9: =IF(OR($A9="",AJ$6="",NOT(ISNUMBER($H$2))),"",SUMIFS(数据录入!$G$5:$G$4999,数据录入!$C$5:$C$4999,$A9,数据录入!$B$5:$B$4999,AJ$6)) | AK9: =IF(OR($A9="",AK$6="",NOT(ISNUMBER($H$2))),"",SUMIFS(数据录入!$F$5:$F$4999,数据录入!$C$5:$C$4999,$A9,数据录入!$B$5:$B$4999,AK$6)) | AL9: =IF(OR($A9="",AL$6="",NOT(ISNUMBER($H$2))),"",SUMIFS(数据录入!$G$5:$G$4999,数据录入!$C$5:$C$4999,$A9,数据录入!$B$5:$B$4999,AL$6)) | AM9: =IF(OR($A9="",AM$6="",NOT(ISNUMBER($H$2))),"",SUMIFS(数据录入!$F$5:$F$4999,数据录入!$C$5:$C$4999,$A9,数据录入!$B$5:$B$4999,AM$6)) | AN9: =IF(OR($A9="",AN$6="",NOT(ISNUMBER($H$2))),"",SUMIFS(数据录入!$G$5:$G$4999,数据录入!$C$5:$C$4999,$A9,数据录入!$B$5:$B$4999,AN$6)) | AO9: =IF(OR($A9="",AO$6="",NOT(ISNUMBER($H$2))),"",SUMIFS(数据录入!$F$5:$F$4999,数据录入!$C$5:$C$4999,$A9,数据录入!$B$5:$B$4999,AO$6)) | AP9: =IF(OR($A9="",AP$6="",NOT(ISNUMBER($H$2))),"",SUMIFS(数据录入!$G$5:$G$4999,数据录入!$C$5:$C$4999,$A9,数据录入!$B$5:$B$4999,AP$6)) | AQ9: =IF(OR($A9="",AQ$6="",NOT(ISNUMBER($H$2))),"",SUMIFS(数据录入!$F$5:$F$4999,数据录入!$C$5:$C$4999,$A9,数据录入!$B$5:$B$4999,AQ$6)) | AR9: =IF(OR($A9="",AR$6="",NOT(ISNUMBER($H$2))),"",SUMIFS(数据录入!$G$5:$G$4999,数据录入!$C$5:$C$4999,$A9,数据录入!$B$5:$B$4999,AR$6)) | AS9: =IF(OR($A9="",AS$6="",NOT(ISNUMBER($H$2))),"",SUMIFS(数据录入!$F$5:$F$4999,数据录入!$C$5:$C$4999,$A9,数据录入!$B$5:$B$4999,AS$6)) | AT9: =IF(OR($A9="",AT$6="",NOT(ISNUMBER($H$2))),"",SUMIFS(数据录入!$G$5:$G$4999,数据录入!$C$5:$C$4999,$A9,数据录入!$B$5:$B$4999,AT$6)) | AU9: =IF(OR($A9="",AU$6="",NOT(ISNUMBER($H$2))),"",SUMIFS(数据录入!$F$5:$F$4999,数据录入!$C$5:$C$4999,$A9,数据录入!$B$5:$B$4999,AU$6)) | AV9: =IF(OR($A9="",AV$6="",NOT(ISNUMBER($H$2))),"",SUMIFS(数据录入!$G$5:$G$4999,数据录入!$C$5:$C$4999,$A9,数据录入!$B$5:$B$4999,AV$6)) | AW9: =IF(OR($A9="",AW$6="",NOT(ISNUMBER($H$2))),"",SUMIFS(数据录入!$F$5:$F$4999,数据录入!$C$5:$C$4999,$A9,数据录入!$B$5:$B$4999,AW$6)) | AX9: =IF(OR($A9="",AX$6="",NOT(ISNUMBER($H$2))),"",SUMIFS(数据录入!$G$5:$G$4999,数据录入!$C$5:$C$4999,$A9,数据录入!$B$5:$B$4999,AX$6)) | AY9: =IF(OR($A9="",AY$6="",NOT(ISNUMBER($H$2))),"",SUMIFS(数据录入!$F$5:$F$4999,数据录入!$C$5:$C$4999,$A9,数据录入!$B$5:$B$4999,AY$6)) | AZ9: =IF(OR($A9="",AZ$6="",NOT(ISNUMBER($H$2))),"",SUMIFS(数据录入!$G$5:$G$4999,数据录入!$C$5:$C$4999,$A9,数据录入!$B$5:$B$4999,AZ$6)) | BA9: =IF(OR($A9="",BA$6="",NOT(ISNUMBER($H$2))),"",SUMIFS(数据录入!$F$5:$F$4999,数据录入!$C$5:$C$4999,$A9,数据录入!$B$5:$B$4999,BA$6)) | BB9: =IF(OR($A9="",BB$6="",NOT(ISNUMBER($H$2))),"",SUMIFS(数据录入!$G$5:$G$4999,数据录入!$C$5:$C$4999,$A9,数据录入!$B$5:$B$4999,BB$6)) | BC9: =IF(OR($A9="",BC$6="",NOT(ISNUMBER($H$2))),"",SUMIFS(数据录入!$F$5:$F$4999,数据录入!$C$5:$C$4999,$A9,数据录入!$B$5:$B$4999,BC$6)) | BD9: =IF(OR($A9="",BD$6="",NOT(ISNUMBER($H$2))),"",SUMIFS(数据录入!$G$5:$G$4999,数据录入!$C$5:$C$4999,$A9,数据录入!$B$5:$B$4999,BD$6)) | BE9: =IF(OR($A9="",BE$6="",NOT(ISNUMBER($H$2))),"",SUMIFS(数据录入!$F$5:$F$4999,数据录入!$C$5:$C$4999,$A9,数据录入!$B$5:$B$4999,BE$6)) | BF9: =IF(OR($A9="",BF$6="",NOT(ISNUMBER($H$2))),"",SUMIFS(数据录入!$G$5:$G$4999,数据录入!$C$5:$C$4999,$A9,数据录入!$B$5:$B$4999,BF$6)) | BG9: =IF(OR($A9="",BG$6="",NOT(ISNUMBER($H$2))),"",SUMIFS(数据录入!$F$5:$F$4999,数据录入!$C$5:$C$4999,$A9,数据录入!$B$5:$B$4999,BG$6)) | BH9: =IF(OR($A9="",BH$6="",NOT(ISNUMBER($H$2))),"",SUMIFS(数据录入!$G$5:$G$4999,数据录入!$C$5:$C$4999,$A9,数据录入!$B$5:$B$4999,BH$6)) | BI9: =IF(OR($A9="",BI$6="",NOT(ISNUMBER($H$2))),"",SUMIFS(数据录入!$F$5:$F$4999,数据录入!$C$5:$C$4999,$A9,数据录入!$B$5:$B$4999,BI$6)) | BJ9: =IF(OR($A9="",BJ$6="",NOT(ISNUMBER($H$2))),"",SUMIFS(数据录入!$G$5:$G$4999,数据录入!$C$5:$C$4999,$A9,数据录入!$B$5:$B$4999,BJ$6)) | BK9: =IF(OR($A9="",BK$6="",NOT(ISNUMBER($H$2))),"",SUMIFS(数据录入!$F$5:$F$4999,数据录入!$C$5:$C$4999,$A9,数据录入!$B$5:$B$4999,BK$6)) | BL9: =IF(OR($A9="",BL$6="",NOT(ISNUMBER($H$2))),"",SUMIFS(数据录入!$G$5:$G$4999,数据录入!$C$5:$C$4999,$A9,数据录入!$B$5:$B$4999,BL$6)) | BM9: =IF($A9="","",SUMIF($C$7:$BL$7,"收款",C9:BL9)) | BN9: =IF($A9="","",SUMIF($C$7:$BL$7,"付款",C9:BL9)) | BO9: =IF($A9="","",B9+BM9-BN9)
A10: 支付宝 | B10: =IF(OR($A10="",NOT(ISNUMBER($H$2))),"",SUMIFS(数据录入!$H$5:$H$4999,数据录入!$C$5:$C$4999,$A10,数据录入!$E$5:$E$4999,"期初余额",数据录入!$B$5:$B$4999,"<="&$B$2)+SUMIFS(数据录入!$F$5:$F$4999,数据录入!$C$5:$C$4999,$A10,数据录入!$B$5:$B$4999,"<"&$B$2)-SUMIFS(数据录入!$G$5:$G$4999,数据录入!$C$5:$C$4999,$A10,数据录入!$B$5:$B$4999,"<"&$B$2)) | C10: =IF(OR($A10="",C$6="",NOT(ISNUMBER($H$2))),"",SUMIFS(数据录入!$F$5:$F$4999,数据录入!$C$5:$C$4999,$A10,数据录入!$B$5:$B$4999,C$6)) | D10: =IF(OR($A10="",D$6="",NOT(ISNUMBER($H$2))),"",SUMIFS(数据录入!$G$5:$G$4999,数据录入!$C$5:$C$4999,$A10,数据录入!$B$5:$B$4999,D$6)) | E10: =IF(OR($A10="",E$6="",NOT(ISNUMBER($H$2))),"",SUMIFS(数据录入!$F$5:$F$4999,数据录入!$C$5:$C$4999,$A10,数据录入!$B$5:$B$4999,E$6)) | F10: =IF(OR($A10="",F$6="",NOT(ISNUMBER($H$2))),"",SUMIFS(数据录入!$G$5:$G$4999,数据录入!$C$5:$C$4999,$A10,数据录入!$B$5:$B$4999,F$6)) | G10: =IF(OR($A10="",G$6="",NOT(ISNUMBER($H$2))),"",SUMIFS(数据录入!$F$5:$F$4999,数据录入!$C$5:$C$4999,$A10,数据录入!$B$5:$B$4999,G$6)) | H10: =IF(OR($A10="",H$6="",NOT(ISNUMBER($H$2))),"",SUMIFS(数据录入!$G$5:$G$4999,数据录入!$C$5:$C$4999,$A10,数据录入!$B$5:$B$4999,H$6)) | I10: =IF(OR($A10="",I$6="",NOT(ISNUMBER($H$2))),"",SUMIFS(数据录入!$F$5:$F$4999,数据录入!$C$5:$C$4999,$A10,数据录入!$B$5:$B$4999,I$6)) | J10: =IF(OR($A10="",J$6="",NOT(ISNUMBER($H$2))),"",SUMIFS(数据录入!$G$5:$G$4999,数据录入!$C$5:$C$4999,$A10,数据录入!$B$5:$B$4999,J$6)) | K10: =IF(OR($A10="",K$6="",NOT(ISNUMBER($H$2))),"",SUMIFS(数据录入!$F$5:$F$4999,数据录入!$C$5:$C$4999,$A10,数据录入!$B$5:$B$4999,K$6)) | L10: =IF(OR($A10="",L$6="",NOT(ISNUMBER($H$2))),"",SUMIFS(数据录入!$G$5:$G$4999,数据录入!$C$5:$C$4999,$A10,数据录入!$B$5:$B$4999,L$6)) | M10: =IF(OR($A10="",M$6="",NOT(ISNUMBER($H$2))),"",SUMIFS(数据录入!$F$5:$F$4999,数据录入!$C$5:$C$4999,$A10,数据录入!$B$5:$B$4999,M$6)) | N10: =IF(OR($A10="",N$6="",NOT(ISNUMBER($H$2))),"",SUMIFS(数据录入!$G$5:$G$4999,数据录入!$C$5:$C$4999,$A10,数据录入!$B$5:$B$4999,N$6)) | O10: =IF(OR($A10="",O$6="",NOT(ISNUMBER($H$2))),"",SUMIFS(数据录入!$F$5:$F$4999,数据录入!$C$5:$C$4999,$A10,数据录入!$B$5:$B$4999,O$6)) | P10: =IF(OR($A10="",P$6="",NOT(ISNUMBER($H$2))),"",SUMIFS(数据录入!$G$5:$G$4999,数据录入!$C$5:$C$4999,$A10,数据录入!$B$5:$B$4999,P$6)) | Q10: =IF(OR($A10="",Q$6="",NOT(ISNUMBER($H$2))),"",SUMIFS(数据录入!$F$5:$F$4999,数据录入!$C$5:$C$4999,$A10,数据录入!$B$5:$B$4999,Q$6)) | R10: =IF(OR($A10="",R$6="",NOT(ISNUMBER($H$2))),"",SUMIFS(数据录入!$G$5:$G$4999,数据录入!$C$5:$C$4999,$A10,数据录入!$B$5:$B$4999,R$6)) | S10: =IF(OR($A10="",S$6="",NOT(ISNUMBER($H$2))),"",SUMIFS(数据录入!$F$5:$F$4999,数据录入!$C$5:$C$4999,$A10,数据录入!$B$5:$B$4999,S$6)) | T10: =IF(OR($A10="",T$6="",NOT(ISNUMBER($H$2))),"",SUMIFS(数据录入!$G$5:$G$4999,数据录入!$C$5:$C$4999,$A10,数据录入!$B$5:$B$4999,T$6)) | U10: =IF(OR($A10="",U$6="",NOT(ISNUMBER($H$2))),"",SUMIFS(数据录入!$F$5:$F$4999,数据录入!$C$5:$C$4999,$A10,数据录入!$B$5:$B$4999,U$6)) | V10: =IF(OR($A10="",V$6="",NOT(ISNUMBER($H$2))),"",SUMIFS(数据录入!$G$5:$G$4999,数据录入!$C$5:$C$4999,$A10,数据录入!$B$5:$B$4999,V$6)) | W10: =IF(OR($A10="",W$6="",NOT(ISNUMBER($H$2))),"",SUMIFS(数据录入!$F$5:$F$4999,数据录入!$C$5:$C$4999,$A10,数据录入!$B$5:$B$4999,W$6)) | X10: =IF(OR($A10="",X$6="",NOT(ISNUMBER($H$2))),"",SUMIFS(数据录入!$G$5:$G$4999,数据录入!$C$5:$C$4999,$A10,数据录入!$B$5:$B$4999,X$6)) | Y10: =IF(OR($A10="",Y$6="",NOT(ISNUMBER($H$2))),"",SUMIFS(数据录入!$F$5:$F$4999,数据录入!$C$5:$C$4999,$A10,数据录入!$B$5:$B$4999,Y$6)) | Z10: =IF(OR($A10="",Z$6="",NOT(ISNUMBER($H$2))),"",SUMIFS(数据录入!$G$5:$G$4999,数据录入!$C$5:$C$4999,$A10,数据录入!$B$5:$B$4999,Z$6)) | AA10: =IF(OR($A10="",AA$6="",NOT(ISNUMBER($H$2))),"",SUMIFS(数据录入!$F$5:$F$4999,数据录入!$C$5:$C$4999,$A10,数据录入!$B$5:$B$4999,AA$6)) | AB10: =IF(OR($A10="",AB$6="",NOT(ISNUMBER($H$2))),"",SUMIFS(数据录入!$G$5:$G$4999,数据录入!$C$5:$C$4999,$A10,数据录入!$B$5:$B$4999,AB$6)) | AC10: =IF(OR($A10="",AC$6="",NOT(ISNUMBER($H$2))),"",SUMIFS(数据录入!$F$5:$F$4999,数据录入!$C$5:$C$4999,$A10,数据录入!$B$5:$B$4999,AC$6)) | AD10: =IF(OR($A10="",AD$6="",NOT(ISNUMBER($H$2))),"",SUMIFS(数据录入!$G$5:$G$4999,数据录入!$C$5:$C$4999,$A10,数据录入!$B$5:$B$4999,AD$6)) | AE10: =IF(OR($A10="",AE$6="",NOT(ISNUMBER($H$2))),"",SUMIFS(数据录入!$F$5:$F$4999,数据录入!$C$5:$C$4999,$A10,数据录入!$B$5:$B$4999,AE$6)) | AF10: =IF(OR($A10="",AF$6="",NOT(ISNUMBER($H$2))),"",SUMIFS(数据录入!$G$5:$G$4999,数据录入!$C$5:$C$4999,$A10,数据录入!$B$5:$B$4999,AF$6)) | AG10: =IF(OR($A10="",AG$6="",NOT(ISNUMBER($H$2))),"",SUMIFS(数据录入!$F$5:$F$4999,数据录入!$C$5:$C$4999,$A10,数据录入!$B$5:$B$4999,AG$6)) | AH10: =IF(OR($A10="",AH$6="",NOT(ISNUMBER($H$2))),"",SUMIFS(数据录入!$G$5:$G$4999,数据录入!$C$5:$C$4999,$A10,数据录入!$B$5:$B$4999,AH$6)) | AI10: =IF(OR($A10="",AI$6="",NOT(ISNUMBER($H$2))),"",SUMIFS(数据录入!$F$5:$F$4999,数据录入!$C$5:$C$4999,$A10,数据录入!$B$5:$B$4999,AI$6)) | AJ10: =IF(OR($A10="",AJ$6="",NOT(ISNUMBER($H$2))),"",SUMIFS(数据录入!$G$5:$G$4999,数据录入!$C$5:$C$4999,$A10,数据录入!$B$5:$B$4999,AJ$6)) | AK10: =IF(OR($A10="",AK$6="",NOT(ISNUMBER($H$2))),"",SUMIFS(数据录入!$F$5:$F$4999,数据录入!$C$5:$C$4999,$A10,数据录入!$B$5:$B$4999,AK$6)) | AL10: =IF(OR($A10="",AL$6="",NOT(ISNUMBER($H$2))),"",SUMIFS(数据录入!$G$5:$G$4999,数据录入!$C$5:$C$4999,$A10,数据录入!$B$5:$B$4999,AL$6)) | AM10: =IF(OR($A10="",AM$6="",NOT(ISNUMBER($H$2))),"",SUMIFS(数据录入!$F$5:$F$4999,数据录入!$C$5:$C$4999,$A10,数据录入!$B$5:$B$4999,AM$6)) | AN10: =IF(OR($A10="",AN$6="",NOT(ISNUMBER($H$2))),"",SUMIFS(数据录入!$G$5:$G$4999,数据录入!$C$5:$C$4999,$A10,数据录入!$B$5:$B$4999,AN$6)) | AO10: =IF(OR($A10="",AO$6="",NOT(ISNUMBER($H$2))),"",SUMIFS(数据录入!$F$5:$F$4999,数据录入!$C$5:$C$4999,$A10,数据录入!$B$5:$B$4999,AO$6)) | AP10: =IF(OR($A10="",AP$6="",NOT(ISNUMBER($H$2))),"",SUMIFS(数据录入!$G$5:$G$4999,数据录入!$C$5:$C$4999,$A10,数据录入!$B$5:$B$4999,AP$6)) | AQ10: =IF(OR($A10="",AQ$6="",NOT(ISNUMBER($H$2))),"",SUMIFS(数据录入!$F$5:$F$4999,数据录入!$C$5:$C$4999,$A10,数据录入!$B$5:$B$4999,AQ$6)) | AR10: =IF(OR($A10="",AR$6="",NOT(ISNUMBER($H$2))),"",SUMIFS(数据录入!$G$5:$G$4999,数据录入!$C$5:$C$4999,$A10,数据录入!$B$5:$B$4999,AR$6)) | AS10: =IF(OR($A10="",AS$6="",NOT(ISNUMBER($H$2))),"",SUMIFS(数据录入!$F$5:$F$4999,数据录入!$C$5:$C$4999,$A10,数据录入!$B$5:$B$4999,AS$6)) | AT10: =IF(OR($A10="",AT$6="",NOT(ISNUMBER($H$2))),"",SUMIFS(数据录入!$G$5:$G$4999,数据录入!$C$5:$C$4999,$A10,数据录入!$B$5:$B$4999,AT$6)) | AU10: =IF(OR($A10="",AU$6="",NOT(ISNUMBER($H$2))),"",SUMIFS(数据录入!$F$5:$F$4999,数据录入!$C$5:$C$4999,$A10,数据录入!$B$5:$B$4999,AU$6)) | AV10: =IF(OR($A10="",AV$6="",NOT(ISNUMBER($H$2))),"",SUMIFS(数据录入!$G$5:$G$4999,数据录入!$C$5:$C$4999,$A10,数据录入!$B$5:$B$4999,AV$6)) | AW10: =IF(OR($A10="",AW$6="",NOT(ISNUMBER($H$2))),"",SUMIFS(数据录入!$F$5:$F$4999,数据录入!$C$5:$C$4999,$A10,数据录入!$B$5:$B$4999,AW$6)) | AX10: =IF(OR($A10="",AX$6="",NOT(ISNUMBER($H$2))),"",SUMIFS(数据录入!$G$5:$G$4999,数据录入!$C$5:$C$4999,$A10,数据录入!$B$5:$B$4999,AX$6)) | AY10: =IF(OR($A10="",AY$6="",NOT(ISNUMBER($H$2))),"",SUMIFS(数据录入!$F$5:$F$4999,数据录入!$C$5:$C$4999,$A10,数据录入!$B$5:$B$4999,AY$6)) | AZ10: =IF(OR($A10="",AZ$6="",NOT(ISNUMBER($H$2))),"",SUMIFS(数据录入!$G$5:$G$4999,数据录入!$C$5:$C$4999,$A10,数据录入!$B$5:$B$4999,AZ$6)) | BA10: =IF(OR($A10="",BA$6="",NOT(ISNUMBER($H$2))),"",SUMIFS(数据录入!$F$5:$F$4999,数据录入!$C$5:$C$4999,$A10,数据录入!$B$5:$B$4999,BA$6)) | BB10: =IF(OR($A10="",BB$6="",NOT(ISNUMBER($H$2))),"",SUMIFS(数据录入!$G$5:$G$4999,数据录入!$C$5:$C$4999,$A10,数据录入!$B$5:$B$4999,BB$6)) | BC10: =IF(OR($A10="",BC$6="",NOT(ISNUMBER($H$2))),"",SUMIFS(数据录入!$F$5:$F$4999,数据录入!$C$5:$C$4999,$A10,数据录入!$B$5:$B$4999,BC$6)) | BD10: =IF(OR($A10="",BD$6="",NOT(ISNUMBER($H$2))),"",SUMIFS(数据录入!$G$5:$G$4999,数据录入!$C$5:$C$4999,$A10,数据录入!$B$5:$B$4999,BD$6)) | BE10: =IF(OR($A10="",BE$6="",NOT(ISNUMBER($H$2))),"",SUMIFS(数据录入!$F$5:$F$4999,数据录入!$C$5:$C$4999,$A10,数据录入!$B$5:$B$4999,BE$6)) | BF10: =IF(OR($A10="",BF$6="",NOT(ISNUMBER($H$2))),"",SUMIFS(数据录入!$G$5:$G$4999,数据录入!$C$5:$C$4999,$A10,数据录入!$B$5:$B$4999,BF$6)) | BG10: =IF(OR($A10="",BG$6="",NOT(ISNUMBER($H$2))),"",SUMIFS(数据录入!$F$5:$F$4999,数据录入!$C$5:$C$4999,$A10,数据录入!$B$5:$B$4999,BG$6)) | BH10: =IF(OR($A10="",BH$6="",NOT(ISNUMBER($H$2))),"",SUMIFS(数据录入!$G$5:$G$4999,数据录入!$C$5:$C$4999,$A10,数据录入!$B$5:$B$4999,BH$6)) | BI10: =IF(OR($A10="",BI$6="",NOT(ISNUMBER($H$2))),"",SUMIFS(数据录入!$F$5:$F$4999,数据录入!$C$5:$C$4999,$A10,数据录入!$B$5:$B$4999,BI$6)) | BJ10: =IF(OR($A10="",BJ$6="",NOT(ISNUMBER($H$2))),"",SUMIFS(数据录入!$G$5:$G$4999,数据录入!$C$5:$C$4999,$A10,数据录入!$B$5:$B$4999,BJ$6)) | BK10: =IF(OR($A10="",BK$6="",NOT(ISNUMBER($H$2))),"",SUMIFS(数据录入!$F$5:$F$4999,数据录入!$C$5:$C$4999,$A10,数据录入!$B$5:$B$4999,BK$6)) | BL10: =IF(OR($A10="",BL$6="",NOT(ISNUMBER($H$2))),"",SUMIFS(数据录入!$G$5:$G$4999,数据录入!$C$5:$C$4999,$A10,数据录入!$B$5:$B$4999,BL$6)) | BM10: =IF($A10="","",SUMIF($C$7:$BL$7,"收款",C10:BL10)) | BN10: =IF($A10="","",SUMIF($C$7:$BL$7,"付款",C10:BL10)) | BO10: =IF($A10="","",B10+BM10-BN10)
A11: 杭州 | B11: =IF(OR($A11="",NOT(ISNUMBER($H$2))),"",SUMIFS(数据录入!$H$5:$H$4999,数据录入!$C$5:$C$4999,$A11,数据录入!$E$5:$E$4999,"期初余额",数据录入!$B$5:$B$4999,"<="&$B$2)+SUMIFS(数据录入!$F$5:$F$4999,数据录入!$C$5:$C$4999,$A11,数据录入!$B$5:$B$4999,"<"&$B$2)-SUMIFS(数据录入!$G$5:$G$4999,数据录入!$C$5:$C$4999,$A11,数据录入!$B$5:$B$4999,"<"&$B$2)) | C11: =IF(OR($A11="",C$6="",NOT(ISNUMBER($H$2))),"",SUMIFS(数据录入!$F$5:$F$4999,数据录入!$C$5:$C$4999,$A11,数据录入!$B$5:$B$4999,C$6)) | D11: =IF(OR($A11="",D$6="",NOT(ISNUMBER($H$2))),"",SUMIFS(数据录入!$G$5:$G$4999,数据录入!$C$5:$C$4999,$A11,数据录入!$B$5:$B$4999,D$6)) | E11: =IF(OR($A11="",E$6="",NOT(ISNUMBER($H$2))),"",SUMIFS(数据录入!$F$5:$F$4999,数据录入!$C$5:$C$4999,$A11,数据录入!$B$5:$B$4999,E$6)) | F11: =IF(OR($A11="",F$6="",NOT(ISNUMBER($H$2))),"",SUMIFS(数据录入!$G$5:$G$4999,数据录入!$C$5:$C$4999,$A11,数据录入!$B$5:$B$4999,F$6)) | G11: =IF(OR($A11="",G$6="",NOT(ISNUMBER($H$2))),"",SUMIFS(数据录入!$F$5:$F$4999,数据录入!$C$5:$C$4999,$A11,数据录入!$B$5:$B$4999,G$6)) | H11: =IF(OR($A11="",H$6="",NOT(ISNUMBER($H$2))),"",SUMIFS(数据录入!$G$5:$G$4999,数据录入!$C$5:$C$4999,$A11,数据录入!$B$5:$B$4999,H$6)) | I11: =IF(OR($A11="",I$6="",NOT(ISNUMBER($H$2))),"",SUMIFS(数据录入!$F$5:$F$4999,数据录入!$C$5:$C$4999,$A11,数据录入!$B$5:$B$4999,I$6)) | J11: =IF(OR($A11="",J$6="",NOT(ISNUMBER($H$2))),"",SUMIFS(数据录入!$G$5:$G$4999,数据录入!$C$5:$C$4999,$A11,数据录入!$B$5:$B$4999,J$6)) | K11: =IF(OR($A11="",K$6="",NOT(ISNUMBER($H$2))),"",SUMIFS(数据录入!$F$5:$F$4999,数据录入!$C$5:$C$4999,$A11,数据录入!$B$5:$B$4999,K$6)) | L11: =IF(OR($A11="",L$6="",NOT(ISNUMBER($H$2))),"",SUMIFS(数据录入!$G$5:$G$4999,数据录入!$C$5:$C$4999,$A11,数据录入!$B$5:$B$4999,L$6)) | M11: =IF(OR($A11="",M$6="",NOT(ISNUMBER($H$2))),"",SUMIFS(数据录入!$F$5:$F$4999,数据录入!$C$5:$C$4999,$A11,数据录入!$B$5:$B$4999,M$6)) | N11: =IF(OR($A11="",N$6="",NOT(ISNUMBER($H$2))),"",SUMIFS(数据录入!$G$5:$G$4999,数据录入!$C$5:$C$4999,$A11,数据录入!$B$5:$B$4999,N$6)) | O11: =IF(OR($A11="",O$6="",NOT(ISNUMBER($H$2))),"",SUMIFS(数据录入!$F$5:$F$4999,数据录入!$C$5:$C$4999,$A11,数据录入!$B$5:$B$4999,O$6)) | P11: =IF(OR($A11="",P$6="",NOT(ISNUMBER($H$2))),"",SUMIFS(数据录入!$G$5:$G$4999,数据录入!$C$5:$C$4999,$A11,数据录入!$B$5:$B$4999,P$6)) | Q11: =IF(OR($A11="",Q$6="",NOT(ISNUMBER($H$2))),"",SUMIFS(数据录入!$F$5:$F$4999,数据录入!$C$5:$C$4999,$A11,数据录入!$B$5:$B$4999,Q$6)) | R11: =IF(OR($A11="",R$6="",NOT(ISNUMBER($H$2))),"",SUMIFS(数据录入!$G$5:$G$4999,数据录入!$C$5:$C$4999,$A11,数据录入!$B$5:$B$4999,R$6)) | S11: =IF(OR($A11="",S$6="",NOT(ISNUMBER($H$2))),"",SUMIFS(数据录入!$F$5:$F$4999,数据录入!$C$5:$C$4999,$A11,数据录入!$B$5:$B$4999,S$6)) | T11: =IF(OR($A11="",T$6="",NOT(ISNUMBER($H$2))),"",SUMIFS(数据录入!$G$5:$G$4999,数据录入!$C$5:$C$4999,$A11,数据录入!$B$5:$B$4999,T$6)) | U11: =IF(OR($A11="",U$6="",NOT(ISNUMBER($H$2))),"",SUMIFS(数据录入!$F$5:$F$4999,数据录入!$C$5:$C$4999,$A11,数据录入!$B$5:$B$4999,U$6)) | V11: =IF(OR($A11="",V$6="",NOT(ISNUMBER($H$2))),"",SUMIFS(数据录入!$G$5:$G$4999,数据录入!$C$5:$C$4999,$A11,数据录入!$B$5:$B$4999,V$6)) | W11: =IF(OR($A11="",W$6="",NOT(ISNUMBER($H$2))),"",SUMIFS(数据录入!$F$5:$F$4999,数据录入!$C$5:$C$4999,$A11,数据录入!$B$5:$B$4999,W$6)) | X11: =IF(OR($A11="",X$6="",NOT(ISNUMBER($H$2))),"",SUMIFS(数据录入!$G$5:$G$4999,数据录入!$C$5:$C$4999,$A11,数据录入!$B$5:$B$4999,X$6)) | Y11: =IF(OR($A11="",Y$6="",NOT(ISNUMBER($H$2))),"",SUMIFS(数据录入!$F$5:$F$4999,数据录入!$C$5:$C$4999,$A11,数据录入!$B$5:$B$4999,Y$6)) | Z11: =IF(OR($A11="",Z$6="",NOT(ISNUMBER($H$2))),"",SUMIFS(数据录入!$G$5:$G$4999,数据录入!$C$5:$C$4999,$A11,数据录入!$B$5:$B$4999,Z$6)) | AA11: =IF(OR($A11="",AA$6="",NOT(ISNUMBER($H$2))),"",SUMIFS(数据录入!$F$5:$F$4999,数据录入!$C$5:$C$4999,$A11,数据录入!$B$5:$B$4999,AA$6)) | AB11: =IF(OR($A11="",AB$6="",NOT(ISNUMBER($H$2))),"",SUMIFS(数据录入!$G$5:$G$4999,数据录入!$C$5:$C$4999,$A11,数据录入!$B$5:$B$4999,AB$6)) | AC11: =IF(OR($A11="",AC$6="",NOT(ISNUMBER($H$2))),"",SUMIFS(数据录入!$F$5:$F$4999,数据录入!$C$5:$C$4999,$A11,数据录入!$B$5:$B$4999,AC$6)) | AD11: =IF(OR($A11="",AD$6="",NOT(ISNUMBER($H$2))),"",SUMIFS(数据录入!$G$5:$G$4999,数据录入!$C$5:$C$4999,$A11,数据录入!$B$5:$B$4999,AD$6)) | AE11: =IF(OR($A11="",AE$6="",NOT(ISNUMBER($H$2))),"",SUMIFS(数据录入!$F$5:$F$4999,数据录入!$C$5:$C$4999,$A11,数据录入!$B$5:$B$4999,AE$6)) | AF11: =IF(OR($A11="",AF$6="",NOT(ISNUMBER($H$2))),"",SUMIFS(数据录入!$G$5:$G$4999,数据录入!$C$5:$C$4999,$A11,数据录入!$B$5:$B$4999,AF$6)) | AG11: =IF(OR($A11="",AG$6="",NOT(ISNUMBER($H$2))),"",SUMIFS(数据录入!$F$5:$F$4999,数据录入!$C$5:$C$4999,$A11,数据录入!$B$5:$B$4999,AG$6)) | AH11: =IF(OR($A11="",AH$6="",NOT(ISNUMBER($H$2))),"",SUMIFS(数据录入!$G$5:$G$4999,数据录入!$C$5:$C$4999,$A11,数据录入!$B$5:$B$4999,AH$6)) | AI11: =IF(OR($A11="",AI$6="",NOT(ISNUMBER($H$2))),"",SUMIFS(数据录入!$F$5:$F$4999,数据录入!$C$5:$C$4999,$A11,数据录入!$B$5:$B$4999,AI$6)) | AJ11: =IF(OR($A11="",AJ$6="",NOT(ISNUMBER($H$2))),"",SUMIFS(数据录入!$G$5:$G$4999,数据录入!$C$5:$C$4999,$A11,数据录入!$B$5:$B$4999,AJ$6)) | AK11: =IF(OR($A11="",AK$6="",NOT(ISNUMBER($H$2))),"",SUMIFS(数据录入!$F$5:$F$4999,数据录入!$C$5:$C$4999,$A11,数据录入!$B$5:$B$4999,AK$6)) | AL11: =IF(OR($A11="",AL$6="",NOT(ISNUMBER($H$2))),"",SUMIFS(数据录入!$G$5:$G$4999,数据录入!$C$5:$C$4999,$A11,数据录入!$B$5:$B$4999,AL$6)) | AM11: =IF(OR($A11="",AM$6="",NOT(ISNUMBER($H$2))),"",SUMIFS(数据录入!$F$5:$F$4999,数据录入!$C$5:$C$4999,$A11,数据录入!$B$5:$B$4999,AM$6)) | AN11: =IF(OR($A11="",AN$6="",NOT(ISNUMBER($H$2))),"",SUMIFS(数据录入!$G$5:$G$4999,数据录入!$C$5:$C$4999,$A11,数据录入!$B$5:$B$4999,AN$6)) | AO11: =IF(OR($A11="",AO$6="",NOT(ISNUMBER($H$2))),"",SUMIFS(数据录入!$F$5:$F$4999,数据录入!$C$5:$C$4999,$A11,数据录入!$B$5:$B$4999,AO$6)) | AP11: =IF(OR($A11="",AP$6="",NOT(ISNUMBER($H$2))),"",SUMIFS(数据录入!$G$5:$G$4999,数据录入!$C$5:$C$4999,$A11,数据录入!$B$5:$B$4999,AP$6)) | AQ11: =IF(OR($A11="",AQ$6="",NOT(ISNUMBER($H$2))),"",SUMIFS(数据录入!$F$5:$F$4999,数据录入!$C$5:$C$4999,$A11,数据录入!$B$5:$B$4999,AQ$6)) | AR11: =IF(OR($A11="",AR$6="",NOT(ISNUMBER($H$2))),"",SUMIFS(数据录入!$G$5:$G$4999,数据录入!$C$5:$C$4999,$A11,数据录入!$B$5:$B$4999,AR$6)) | AS11: =IF(OR($A11="",AS$6="",NOT(ISNUMBER($H$2))),"",SUMIFS(数据录入!$F$5:$F$4999,数据录入!$C$5:$C$4999,$A11,数据录入!$B$5:$B$4999,AS$6)) | AT11: =IF(OR($A11="",AT$6="",NOT(ISNUMBER($H$2))),"",SUMIFS(数据录入!$G$5:$G$4999,数据录入!$C$5:$C$4999,$A11,数据录入!$B$5:$B$4999,AT$6)) | AU11: =IF(OR($A11="",AU$6="",NOT(ISNUMBER($H$2))),"",SUMIFS(数据录入!$F$5:$F$4999,数据录入!$C$5:$C$4999,$A11,数据录入!$B$5:$B$4999,AU$6)) | AV11: =IF(OR($A11="",AV$6="",NOT(ISNUMBER($H$2))),"",SUMIFS(数据录入!$G$5:$G$4999,数据录入!$C$5:$C$4999,$A11,数据录入!$B$5:$B$4999,AV$6)) | AW11: =IF(OR($A11="",AW$6="",NOT(ISNUMBER($H$2))),"",SUMIFS(数据录入!$F$5:$F$4999,数据录入!$C$5:$C$4999,$A11,数据录入!$B$5:$B$4999,AW$6)) | AX11: =IF(OR($A11="",AX$6="",NOT(ISNUMBER($H$2))),"",SUMIFS(数据录入!$G$5:$G$4999,数据录入!$C$5:$C$4999,$A11,数据录入!$B$5:$B$4999,AX$6)) | AY11: =IF(OR($A11="",AY$6="",NOT(ISNUMBER($H$2))),"",SUMIFS(数据录入!$F$5:$F$4999,数据录入!$C$5:$C$4999,$A11,数据录入!$B$5:$B$4999,AY$6)) | AZ11: =IF(OR($A11="",AZ$6="",NOT(ISNUMBER($H$2))),"",SUMIFS(数据录入!$G$5:$G$4999,数据录入!$C$5:$C$4999,$A11,数据录入!$B$5:$B$4999,AZ$6)) | BA11: =IF(OR($A11="",BA$6="",NOT(ISNUMBER($H$2))),"",SUMIFS(数据录入!$F$5:$F$4999,数据录入!$C$5:$C$4999,$A11,数据录入!$B$5:$B$4999,BA$6)) | BB11: =IF(OR($A11="",BB$6="",NOT(ISNUMBER($H$2))),"",SUMIFS(数据录入!$G$5:$G$4999,数据录入!$C$5:$C$4999,$A11,数据录入!$B$5:$B$4999,BB$6)) | BC11: =IF(OR($A11="",BC$6="",NOT(ISNUMBER($H$2))),"",SUMIFS(数据录入!$F$5:$F$4999,数据录入!$C$5:$C$4999,$A11,数据录入!$B$5:$B$4999,BC$6)) | BD11: =IF(OR($A11="",BD$6="",NOT(ISNUMBER($H$2))),"",SUMIFS(数据录入!$G$5:$G$4999,数据录入!$C$5:$C$4999,$A11,数据录入!$B$5:$B$4999,BD$6)) | BE11: =IF(OR($A11="",BE$6="",NOT(ISNUMBER($H$2))),"",SUMIFS(数据录入!$F$5:$F$4999,数据录入!$C$5:$C$4999,$A11,数据录入!$B$5:$B$4999,BE$6)) | BF11: =IF(OR($A11="",BF$6="",NOT(ISNUMBER($H$2))),"",SUMIFS(数据录入!$G$5:$G$4999,数据录入!$C$5:$C$4999,$A11,数据录入!$B$5:$B$4999,BF$6)) | BG11: =IF(OR($A11="",BG$6="",NOT(ISNUMBER($H$2))),"",SUMIFS(数据录入!$F$5:$F$4999,数据录入!$C$5:$C$4999,$A11,数据录入!$B$5:$B$4999,BG$6)) | BH11: =IF(OR($A11="",BH$6="",NOT(ISNUMBER($H$2))),"",SUMIFS(数据录入!$G$5:$G$4999,数据录入!$C$5:$C$4999,$A11,数据录入!$B$5:$B$4999,BH$6)) | BI11: =IF(OR($A11="",BI$6="",NOT(ISNUMBER($H$2))),"",SUMIFS(数据录入!$F$5:$F$4999,数据录入!$C$5:$C$4999,$A11,数据录入!$B$5:$B$4999,BI$6)) | BJ11: =IF(OR($A11="",BJ$6="",NOT(ISNUMBER($H$2))),"",SUMIFS(数据录入!$G$5:$G$4999,数据录入!$C$5:$C$4999,$A11,数据录入!$B$5:$B$4999,BJ$6)) | BK11: =IF(OR($A11="",BK$6="",NOT(ISNUMBER($H$2))),"",SUMIFS(数据录入!$F$5:$F$4999,数据录入!$C$5:$C$4999,$A11,数据录入!$B$5:$B$4999,BK$6)) | BL11: =IF(OR($A11="",BL$6="",NOT(ISNUMBER($H$2))),"",SUMIFS(数据录入!$G$5:$G$4999,数据录入!$C$5:$C$4999,$A11,数据录入!$B$5:$B$4999,BL$6)) | BM11: =IF($A11="","",SUMIF($C$7:$BL$7,"收款",C11:BL11)) | BN11: =IF($A11="","",SUMIF($C$7:$BL$7,"付款",C11:BL11)) | BO11: =IF($A11="","",B11+BM11-BN11)
A12: 农商 | B12: =IF(OR($A12="",NOT(ISNUMBER($H$2))),"",SUMIFS(数据录入!$H$5:$H$4999,数据录入!$C$5:$C$4999,$A12,数据录入!$E$5:$E$4999,"期初余额",数据录入!$B$5:$B$4999,"<="&$B$2)+SUMIFS(数据录入!$F$5:$F$4999,数据录入!$C$5:$C$4999,$A12,数据录入!$B$5:$B$4999,"<"&$B$2)-SUMIFS(数据录入!$G$5:$G$4999,数据录入!$C$5:$C$4999,$A12,数据录入!$B$5:$B$4999,"<"&$B$2)) | C12: =IF(OR($A12="",C$6="",NOT(ISNUMBER($H$2))),"",SUMIFS(数据录入!$F$5:$F$4999,数据录入!$C$5:$C$4999,$A12,数据录入!$B$5:$B$4999,C$6)) | D12: =IF(OR($A12="",D$6="",NOT(ISNUMBER($H$2))),"",SUMIFS(数据录入!$G$5:$G$4999,数据录入!$C$5:$C$4999,$A12,数据录入!$B$5:$B$4999,D$6)) | E12: =IF(OR($A12="",E$6="",NOT(ISNUMBER($H$2))),"",SUMIFS(数据录入!$F$5:$F$4999,数据录入!$C$5:$C$4999,$A12,数据录入!$B$5:$B$4999,E$6)) | F12: =IF(OR($A12="",F$6="",NOT(ISNUMBER($H$2))),"",SUMIFS(数据录入!$G$5:$G$4999,数据录入!$C$5:$C$4999,$A12,数据录入!$B$5:$B$4999,F$6)) | G12: =IF(OR($A12="",G$6="",NOT(ISNUMBER($H$2))),"",SUMIFS(数据录入!$F$5:$F$4999,数据录入!$C$5:$C$4999,$A12,数据录入!$B$5:$B$4999,G$6)) | H12: =IF(OR($A12="",H$6="",NOT(ISNUMBER($H$2))),"",SUMIFS(数据录入!$G$5:$G$4999,数据录入!$C$5:$C$4999,$A12,数据录入!$B$5:$B$4999,H$6)) | I12: =IF(OR($A12="",I$6="",NOT(ISNUMBER($H$2))),"",SUMIFS(数据录入!$F$5:$F$4999,数据录入!$C$5:$C$4999,$A12,数据录入!$B$5:$B$4999,I$6)) | J12: =IF(OR($A12="",J$6="",NOT(ISNUMBER($H$2))),"",SUMIFS(数据录入!$G$5:$G$4999,数据录入!$C$5:$C$4999,$A12,数据录入!$B$5:$B$4999,J$6)) | K12: =IF(OR($A12="",K$6="",NOT(ISNUMBER($H$2))),"",SUMIFS(数据录入!$F$5:$F$4999,数据录入!$C$5:$C$4999,$A12,数据录入!$B$5:$B$4999,K$6)) | L12: =IF(OR($A12="",L$6="",NOT(ISNUMBER($H$2))),"",SUMIFS(数据录入!$G$5:$G$4999,数据录入!$C$5:$C$4999,$A12,数据录入!$B$5:$B$4999,L$6)) | M12: =IF(OR($A12="",M$6="",NOT(ISNUMBER($H$2))),"",SUMIFS(数据录入!$F$5:$F$4999,数据录入!$C$5:$C$4999,$A12,数据录入!$B$5:$B$4999,M$6)) | N12: =IF(OR($A12="",N$6="",NOT(ISNUMBER($H$2))),"",SUMIFS(数据录入!$G$5:$G$4999,数据录入!$C$5:$C$4999,$A12,数据录入!$B$5:$B$4999,N$6)) | O12: =IF(OR($A12="",O$6="",NOT(ISNUMBER($H$2))),"",SUMIFS(数据录入!$F$5:$F$4999,数据录入!$C$5:$C$4999,$A12,数据录入!$B$5:$B$4999,O$6)) | P12: =IF(OR($A12="",P$6="",NOT(ISNUMBER($H$2))),"",SUMIFS(数据录入!$G$5:$G$4999,数据录入!$C$5:$C$4999,$A12,数据录入!$B$5:$B$4999,P$6)) | Q12: =IF(OR($A12="",Q$6="",NOT(ISNUMBER($H$2))),"",SUMIFS(数据录入!$F$5:$F$4999,数据录入!$C$5:$C$4999,$A12,数据录入!$B$5:$B$4999,Q$6)) | R12: =IF(OR($A12="",R$6="",NOT(ISNUMBER($H$2))),"",SUMIFS(数据录入!$G$5:$G$4999,数据录入!$C$5:$C$4999,$A12,数据录入!$B$5:$B$4999,R$6)) | S12: =IF(OR($A12="",S$6="",NOT(ISNUMBER($H$2))),"",SUMIFS(数据录入!$F$5:$F$4999,数据录入!$C$5:$C$4999,$A12,数据录入!$B$5:$B$4999,S$6)) | T12: =IF(OR($A12="",T$6="",NOT(ISNUMBER($H$2))),"",SUMIFS(数据录入!$G$5:$G$4999,数据录入!$C$5:$C$4999,$A12,数据录入!$B$5:$B$4999,T$6)) | U12: =IF(OR($A12="",U$6="",NOT(ISNUMBER($H$2))),"",SUMIFS(数据录入!$F$5:$F$4999,数据录入!$C$5:$C$4999,$A12,数据录入!$B$5:$B$4999,U$6)) | V12: =IF(OR($A12="",V$6="",NOT(ISNUMBER($H$2))),"",SUMIFS(数据录入!$G$5:$G$4999,数据录入!$C$5:$C$4999,$A12,数据录入!$B$5:$B$4999,V$6)) | W12: =IF(OR($A12="",W$6="",NOT(ISNUMBER($H$2))),"",SUMIFS(数据录入!$F$5:$F$4999,数据录入!$C$5:$C$4999,$A12,数据录入!$B$5:$B$4999,W$6)) | X12: =IF(OR($A12="",X$6="",NOT(ISNUMBER($H$2))),"",SUMIFS(数据录入!$G$5:$G$4999,数据录入!$C$5:$C$4999,$A12,数据录入!$B$5:$B$4999,X$6)) | Y12: =IF(OR($A12="",Y$6="",NOT(ISNUMBER($H$2))),"",SUMIFS(数据录入!$F$5:$F$4999,数据录入!$C$5:$C$4999,$A12,数据录入!$B$5:$B$4999,Y$6)) | Z12: =IF(OR($A12="",Z$6="",NOT(ISNUMBER($H$2))),"",SUMIFS(数据录入!$G$5:$G$4999,数据录入!$C$5:$C$4999,$A12,数据录入!$B$5:$B$4999,Z$6)) | AA12: =IF(OR($A12="",AA$6="",NOT(ISNUMBER($H$2))),"",SUMIFS(数据录入!$F$5:$F$4999,数据录入!$C$5:$C$4999,$A12,数据录入!$B$5:$B$4999,AA$6)) | AB12: =IF(OR($A12="",AB$6="",NOT(ISNUMBER($H$2))),"",SUMIFS(数据录入!$G$5:$G$4999,数据录入!$C$5:$C$4999,$A12,数据录入!$B$5:$B$4999,AB$6)) | AC12: =IF(OR($A12="",AC$6="",NOT(ISNUMBER($H$2))),"",SUMIFS(数据录入!$F$5:$F$4999,数据录入!$C$5:$C$4999,$A12,数据录入!$B$5:$B$4999,AC$6)) | AD12: =IF(OR($A12="",AD$6="",NOT(ISNUMBER($H$2))),"",SUMIFS(数据录入!$G$5:$G$4999,数据录入!$C$5:$C$4999,$A12,数据录入!$B$5:$B$4999,AD$6)) | AE12: =IF(OR($A12="",AE$6="",NOT(ISNUMBER($H$2))),"",SUMIFS(数据录入!$F$5:$F$4999,数据录入!$C$5:$C$4999,$A12,数据录入!$B$5:$B$4999,AE$6)) | AF12: =IF(OR($A12="",AF$6="",NOT(ISNUMBER($H$2))),"",SUMIFS(数据录入!$G$5:$G$4999,数据录入!$C$5:$C$4999,$A12,数据录入!$B$5:$B$4999,AF$6)) | AG12: =IF(OR($A12="",AG$6="",NOT(ISNUMBER($H$2))),"",SUMIFS(数据录入!$F$5:$F$4999,数据录入!$C$5:$C$4999,$A12,数据录入!$B$5:$B$4999,AG$6)) | AH12: =IF(OR($A12="",AH$6="",NOT(ISNUMBER($H$2))),"",SUMIFS(数据录入!$G$5:$G$4999,数据录入!$C$5:$C$4999,$A12,数据录入!$B$5:$B$4999,AH$6)) | AI12: =IF(OR($A12="",AI$6="",NOT(ISNUMBER($H$2))),"",SUMIFS(数据录入!$F$5:$F$4999,数据录入!$C$5:$C$4999,$A12,数据录入!$B$5:$B$4999,AI$6)) | AJ12: =IF(OR($A12="",AJ$6="",NOT(ISNUMBER($H$2))),"",SUMIFS(数据录入!$G$5:$G$4999,数据录入!$C$5:$C$4999,$A12,数据录入!$B$5:$B$4999,AJ$6)) | AK12: =IF(OR($A12="",AK$6="",NOT(ISNUMBER($H$2))),"",SUMIFS(数据录入!$F$5:$F$4999,数据录入!$C$5:$C$4999,$A12,数据录入!$B$5:$B$4999,AK$6)) | AL12: =IF(OR($A12="",AL$6="",NOT(ISNUMBER($H$2))),"",SUMIFS(数据录入!$G$5:$G$4999,数据录入!$C$5:$C$4999,$A12,数据录入!$B$5:$B$4999,AL$6)) | AM12: =IF(OR($A12="",AM$6="",NOT(ISNUMBER($H$2))),"",SUMIFS(数据录入!$F$5:$F$4999,数据录入!$C$5:$C$4999,$A12,数据录入!$B$5:$B$4999,AM$6)) | AN12: =IF(OR($A12="",AN$6="",NOT(ISNUMBER($H$2))),"",SUMIFS(数据录入!$G$5:$G$4999,数据录入!$C$5:$C$4999,$A12,数据录入!$B$5:$B$4999,AN$6)) | AO12: =IF(OR($A12="",AO$6="",NOT(ISNUMBER($H$2))),"",SUMIFS(数据录入!$F$5:$F$4999,数据录入!$C$5:$C$4999,$A12,数据录入!$B$5:$B$4999,AO$6)) | AP12: =IF(OR($A12="",AP$6="",NOT(ISNUMBER($H$2))),"",SUMIFS(数据录入!$G$5:$G$4999,数据录入!$C$5:$C$4999,$A12,数据录入!$B$5:$B$4999,AP$6)) | AQ12: =IF(OR($A12="",AQ$6="",NOT(ISNUMBER($H$2))),"",SUMIFS(数据录入!$F$5:$F$4999,数据录入!$C$5:$C$4999,$A12,数据录入!$B$5:$B$4999,AQ$6)) | AR12: =IF(OR($A12="",AR$6="",NOT(ISNUMBER($H$2))),"",SUMIFS(数据录入!$G$5:$G$4999,数据录入!$C$5:$C$4999,$A12,数据录入!$B$5:$B$4999,AR$6)) | AS12: =IF(OR($A12="",AS$6="",NOT(ISNUMBER($H$2))),"",SUMIFS(数据录入!$F$5:$F$4999,数据录入!$C$5:$C$4999,$A12,数据录入!$B$5:$B$4999,AS$6)) | AT12: =IF(OR($A12="",AT$6="",NOT(ISNUMBER($H$2))),"",SUMIFS(数据录入!$G$5:$G$4999,数据录入!$C$5:$C$4999,$A12,数据录入!$B$5:$B$4999,AT$6)) | AU12: =IF(OR($A12="",AU$6="",NOT(ISNUMBER($H$2))),"",SUMIFS(数据录入!$F$5:$F$4999,数据录入!$C$5:$C$4999,$A12,数据录入!$B$5:$B$4999,AU$6)) | AV12: =IF(OR($A12="",AV$6="",NOT(ISNUMBER($H$2))),"",SUMIFS(数据录入!$G$5:$G$4999,数据录入!$C$5:$C$4999,$A12,数据录入!$B$5:$B$4999,AV$6)) | AW12: =IF(OR($A12="",AW$6="",NOT(ISNUMBER($H$2))),"",SUMIFS(数据录入!$F$5:$F$4999,数据录入!$C$5:$C$4999,$A12,数据录入!$B$5:$B$4999,AW$6)) | AX12: =IF(OR($A12="",AX$6="",NOT(ISNUMBER($H$2))),"",SUMIFS(数据录入!$G$5:$G$4999,数据录入!$C$5:$C$4999,$A12,数据录入!$B$5:$B$4999,AX$6)) | AY12: =IF(OR($A12="",AY$6="",NOT(ISNUMBER($H$2))),"",SUMIFS(数据录入!$F$5:$F$4999,数据录入!$C$5:$C$4999,$A12,数据录入!$B$5:$B$4999,AY$6)) | AZ12: =IF(OR($A12="",AZ$6="",NOT(ISNUMBER($H$2))),"",SUMIFS(数据录入!$G$5:$G$4999,数据录入!$C$5:$C$4999,$A12,数据录入!$B$5:$B$4999,AZ$6)) | BA12: =IF(OR($A12="",BA$6="",NOT(ISNUMBER($H$2))),"",SUMIFS(数据录入!$F$5:$F$4999,数据录入!$C$5:$C$4999,$A12,数据录入!$B$5:$B$4999,BA$6)) | BB12: =IF(OR($A12="",BB$6="",NOT(ISNUMBER($H$2))),"",SUMIFS(数据录入!$G$5:$G$4999,数据录入!$C$5:$C$4999,$A12,数据录入!$B$5:$B$4999,BB$6)) | BC12: =IF(OR($A12="",BC$6="",NOT(ISNUMBER($H$2))),"",SUMIFS(数据录入!$F$5:$F$4999,数据录入!$C$5:$C$4999,$A12,数据录入!$B$5:$B$4999,BC$6)) | BD12: =IF(OR($A12="",BD$6="",NOT(ISNUMBER($H$2))),"",SUMIFS(数据录入!$G$5:$G$4999,数据录入!$C$5:$C$4999,$A12,数据录入!$B$5:$B$4999,BD$6)) | BE12: =IF(OR($A12="",BE$6="",NOT(ISNUMBER($H$2))),"",SUMIFS(数据录入!$F$5:$F$4999,数据录入!$C$5:$C$4999,$A12,数据录入!$B$5:$B$4999,BE$6)) | BF12: =IF(OR($A12="",BF$6="",NOT(ISNUMBER($H$2))),"",SUMIFS(数据录入!$G$5:$G$4999,数据录入!$C$5:$C$4999,$A12,数据录入!$B$5:$B$4999,BF$6)) | BG12: =IF(OR($A12="",BG$6="",NOT(ISNUMBER($H$2))),"",SUMIFS(数据录入!$F$5:$F$4999,数据录入!$C$5:$C$4999,$A12,数据录入!$B$5:$B$4999,BG$6)) | BH12: =IF(OR($A12="",BH$6="",NOT(ISNUMBER($H$2))),"",SUMIFS(数据录入!$G$5:$G$4999,数据录入!$C$5:$C$4999,$A12,数据录入!$B$5:$B$4999,BH$6)) | BI12: =IF(OR($A12="",BI$6="",NOT(ISNUMBER($H$2))),"",SUMIFS(数据录入!$F$5:$F$4999,数据录入!$C$5:$C$4999,$A12,数据录入!$B$5:$B$4999,BI$6)) | BJ12: =IF(OR($A12="",BJ$6="",NOT(ISNUMBER($H$2))),"",SUMIFS(数据录入!$G$5:$G$4999,数据录入!$C$5:$C$4999,$A12,数据录入!$B$5:$B$4999,BJ$6)) | BK12: =IF(OR($A12="",BK$6="",NOT(ISNUMBER($H$2))),"",SUMIFS(数据录入!$F$5:$F$4999,数据录入!$C$5:$C$4999,$A12,数据录入!$B$5:$B$4999,BK$6)) | BL12: =IF(OR($A12="",BL$6="",NOT(ISNUMBER($H$2))),"",SUMIFS(数据录入!$G$5:$G$4999,数据录入!$C$5:$C$4999,$A12,数据录入!$B$5:$B$4999,BL$6)) | BM12: =IF($A12="","",SUMIF($C$7:$BL$7,"收款",C12:BL12)) | BN12: =IF($A12="","",SUMIF($C$7:$BL$7,"付款",C12:BL12)) | BO12: =IF($A12="","",B12+BM12-BN12)
A13: 备用 | B13: =IF(OR($A13="",NOT(ISNUMBER($H$2))),"",SUMIFS(数据录入!$H$5:$H$4999,数据录入!$C$5:$C$4999,$A13,数据录入!$E$5:$E$4999,"期初余额",数据录入!$B$5:$B$4999,"<="&$B$2)+SUMIFS(数据录入!$F$5:$F$4999,数据录入!$C$5:$C$4999,$A13,数据录入!$B$5:$B$4999,"<"&$B$2)-SUMIFS(数据录入!$G$5:$G$4999,数据录入!$C$5:$C$4999,$A13,数据录入!$B$5:$B$4999,"<"&$B$2)) | C13: =IF(OR($A13="",C$6="",NOT(ISNUMBER($H$2))),"",SUMIFS(数据录入!$F$5:$F$4999,数据录入!$C$5:$C$4999,$A13,数据录入!$B$5:$B$4999,C$6)) | D13: =IF(OR($A13="",D$6="",NOT(ISNUMBER($H$2))),"",SUMIFS(数据录入!$G$5:$G$4999,数据录入!$C$5:$C$4999,$A13,数据录入!$B$5:$B$4999,D$6)) | E13: =IF(OR($A13="",E$6="",NOT(ISNUMBER($H$2))),"",SUMIFS(数据录入!$F$5:$F$4999,数据录入!$C$5:$C$4999,$A13,数据录入!$B$5:$B$4999,E$6)) | F13: =IF(OR($A13="",F$6="",NOT(ISNUMBER($H$2))),"",SUMIFS(数据录入!$G$5:$G$4999,数据录入!$C$5:$C$4999,$A13,数据录入!$B$5:$B$4999,F$6)) | G13: =IF(OR($A13="",G$6="",NOT(ISNUMBER($H$2))),"",SUMIFS(数据录入!$F$5:$F$4999,数据录入!$C$5:$C$4999,$A13,数据录入!$B$5:$B$4999,G$6)) | H13: =IF(OR($A13="",H$6="",NOT(ISNUMBER($H$2))),"",SUMIFS(数据录入!$G$5:$G$4999,数据录入!$C$5:$C$4999,$A13,数据录入!$B$5:$B$4999,H$6)) | I13: =IF(OR($A13="",I$6="",NOT(ISNUMBER($H$2))),"",SUMIFS(数据录入!$F$5:$F$4999,数据录入!$C$5:$C$4999,$A13,数据录入!$B$5:$B$4999,I$6)) | J13: =IF(OR($A13="",J$6="",NOT(ISNUMBER($H$2))),"",SUMIFS(数据录入!$G$5:$G$4999,数据录入!$C$5:$C$4999,$A13,数据录入!$B$5:$B$4999,J$6)) | K13: =IF(OR($A13="",K$6="",NOT(ISNUMBER($H$2))),"",SUMIFS(数据录入!$F$5:$F$4999,数据录入!$C$5:$C$4999,$A13,数据录入!$B$5:$B$4999,K$6)) | L13: =IF(OR($A13="",L$6="",NOT(ISNUMBER($H$2))),"",SUMIFS(数据录入!$G$5:$G$4999,数据录入!$C$5:$C$4999,$A13,数据录入!$B$5:$B$4999,L$6)) | M13: =IF(OR($A13="",M$6="",NOT(ISNUMBER($H$2))),"",SUMIFS(数据录入!$F$5:$F$4999,数据录入!$C$5:$C$4999,$A13,数据录入!$B$5:$B$4999,M$6)) | N13: =IF(OR($A13="",N$6="",NOT(ISNUMBER($H$2))),"",SUMIFS(数据录入!$G$5:$G$4999,数据录入!$C$5:$C$4999,$A13,数据录入!$B$5:$B$4999,N$6)) | O13: =IF(OR($A13="",O$6="",NOT(ISNUMBER($H$2))),"",SUMIFS(数据录入!$F$5:$F$4999,数据录入!$C$5:$C$4999,$A13,数据录入!$B$5:$B$4999,O$6)) | P13: =IF(OR($A13="",P$6="",NOT(ISNUMBER($H$2))),"",SUMIFS(数据录入!$G$5:$G$4999,数据录入!$C$5:$C$4999,$A13,数据录入!$B$5:$B$4999,P$6)) | Q13: =IF(OR($A13="",Q$6="",NOT(ISNUMBER($H$2))),"",SUMIFS(数据录入!$F$5:$F$4999,数据录入!$C$5:$C$4999,$A13,数据录入!$B$5:$B$4999,Q$6)) | R13: =IF(OR($A13="",R$6="",NOT(ISNUMBER($H$2))),"",SUMIFS(数据录入!$G$5:$G$4999,数据录入!$C$5:$C$4999,$A13,数据录入!$B$5:$B$4999,R$6)) | S13: =IF(OR($A13="",S$6="",NOT(ISNUMBER($H$2))),"",SUMIFS(数据录入!$F$5:$F$4999,数据录入!$C$5:$C$4999,$A13,数据录入!$B$5:$B$4999,S$6)) | T13: =IF(OR($A13="",T$6="",NOT(ISNUMBER($H$2))),"",SUMIFS(数据录入!$G$5:$G$4999,数据录入!$C$5:$C$4999,$A13,数据录入!$B$5:$B$4999,T$6)) | U13: =IF(OR($A13="",U$6="",NOT(ISNUMBER($H$2))),"",SUMIFS(数据录入!$F$5:$F$4999,数据录入!$C$5:$C$4999,$A13,数据录入!$B$5:$B$4999,U$6)) | V13: =IF(OR($A13="",V$6="",NOT(ISNUMBER($H$2))),"",SUMIFS(数据录入!$G$5:$G$4999,数据录入!$C$5:$C$4999,$A13,数据录入!$B$5:$B$4999,V$6)) | W13: =IF(OR($A13="",W$6="",NOT(ISNUMBER($H$2))),"",SUMIFS(数据录入!$F$5:$F$4999,数据录入!$C$5:$C$4999,$A13,数据录入!$B$5:$B$4999,W$6)) | X13: =IF(OR($A13="",X$6="",NOT(ISNUMBER($H$2))),"",SUMIFS(数据录入!$G$5:$G$4999,数据录入!$C$5:$C$4999,$A13,数据录入!$B$5:$B$4999,X$6)) | Y13: =IF(OR($A13="",Y$6="",NOT(ISNUMBER($H$2))),"",SUMIFS(数据录入!$F$5:$F$4999,数据录入!$C$5:$C$4999,$A13,数据录入!$B$5:$B$4999,Y$6)) | Z13: =IF(OR($A13="",Z$6="",NOT(ISNUMBER($H$2))),"",SUMIFS(数据录入!$G$5:$G$4999,数据录入!$C$5:$C$4999,$A13,数据录入!$B$5:$B$4999,Z$6)) | AA13: =IF(OR($A13="",AA$6="",NOT(ISNUMBER($H$2))),"",SUMIFS(数据录入!$F$5:$F$4999,数据录入!$C$5:$C$4999,$A13,数据录入!$B$5:$B$4999,AA$6)) | AB13: =IF(OR($A13="",AB$6="",NOT(ISNUMBER($H$2))),"",SUMIFS(数据录入!$G$5:$G$4999,数据录入!$C$5:$C$4999,$A13,数据录入!$B$5:$B$4999,AB$6)) | AC13: =IF(OR($A13="",AC$6="",NOT(ISNUMBER($H$2))),"",SUMIFS(数据录入!$F$5:$F$4999,数据录入!$C$5:$C$4999,$A13,数据录入!$B$5:$B$4999,AC$6)) | AD13: =IF(OR($A13="",AD$6="",NOT(ISNUMBER($H$2))),"",SUMIFS(数据录入!$G$5:$G$4999,数据录入!$C$5:$C$4999,$A13,数据录入!$B$5:$B$4999,AD$6)) | AE13: =IF(OR($A13="",AE$6="",NOT(ISNUMBER($H$2))),"",SUMIFS(数据录入!$F$5:$F$4999,数据录入!$C$5:$C$4999,$A13,数据录入!$B$5:$B$4999,AE$6)) | AF13: =IF(OR($A13="",AF$6="",NOT(ISNUMBER($H$2))),"",SUMIFS(数据录入!$G$5:$G$4999,数据录入!$C$5:$C$4999,$A13,数据录入!$B$5:$B$4999,AF$6)) | AG13: =IF(OR($A13="",AG$6="",NOT(ISNUMBER($H$2))),"",SUMIFS(数据录入!$F$5:$F$4999,数据录入!$C$5:$C$4999,$A13,数据录入!$B$5:$B$4999,AG$6)) | AH13: =IF(OR($A13="",AH$6="",NOT(ISNUMBER($H$2))),"",SUMIFS(数据录入!$G$5:$G$4999,数据录入!$C$5:$C$4999,$A13,数据录入!$B$5:$B$4999,AH$6)) | AI13: =IF(OR($A13="",AI$6="",NOT(ISNUMBER($H$2))),"",SUMIFS(数据录入!$F$5:$F$4999,数据录入!$C$5:$C$4999,$A13,数据录入!$B$5:$B$4999,AI$6)) | AJ13: =IF(OR($A13="",AJ$6="",NOT(ISNUMBER($H$2))),"",SUMIFS(数据录入!$G$5:$G$4999,数据录入!$C$5:$C$4999,$A13,数据录入!$B$5:$B$4999,AJ$6)) | AK13: =IF(OR($A13="",AK$6="",NOT(ISNUMBER($H$2))),"",SUMIFS(数据录入!$F$5:$F$4999,数据录入!$C$5:$C$4999,$A13,数据录入!$B$5:$B$4999,AK$6)) | AL13: =IF(OR($A13="",AL$6="",NOT(ISNUMBER($H$2))),"",SUMIFS(数据录入!$G$5:$G$4999,数据录入!$C$5:$C$4999,$A13,数据录入!$B$5:$B$4999,AL$6)) | AM13: =IF(OR($A13="",AM$6="",NOT(ISNUMBER($H$2))),"",SUMIFS(数据录入!$F$5:$F$4999,数据录入!$C$5:$C$4999,$A13,数据录入!$B$5:$B$4999,AM$6)) | AN13: =IF(OR($A13="",AN$6="",NOT(ISNUMBER($H$2))),"",SUMIFS(数据录入!$G$5:$G$4999,数据录入!$C$5:$C$4999,$A13,数据录入!$B$5:$B$4999,AN$6)) | AO13: =IF(OR($A13="",AO$6="",NOT(ISNUMBER($H$2))),"",SUMIFS(数据录入!$F$5:$F$4999,数据录入!$C$5:$C$4999,$A13,数据录入!$B$5:$B$4999,AO$6)) | AP13: =IF(OR($A13="",AP$6="",NOT(ISNUMBER($H$2))),"",SUMIFS(数据录入!$G$5:$G$4999,数据录入!$C$5:$C$4999,$A13,数据录入!$B$5:$B$4999,AP$6)) | AQ13: =IF(OR($A13="",AQ$6="",NOT(ISNUMBER($H$2))),"",SUMIFS(数据录入!$F$5:$F$4999,数据录入!$C$5:$C$4999,$A13,数据录入!$B$5:$B$4999,AQ$6)) | AR13: =IF(OR($A13="",AR$6="",NOT(ISNUMBER($H$2))),"",SUMIFS(数据录入!$G$5:$G$4999,数据录入!$C$5:$C$4999,$A13,数据录入!$B$5:$B$4999,AR$6)) | AS13: =IF(OR($A13="",AS$6="",NOT(ISNUMBER($H$2))),"",SUMIFS(数据录入!$F$5:$F$4999,数据录入!$C$5:$C$4999,$A13,数据录入!$B$5:$B$4999,AS$6)) | AT13: =IF(OR($A13="",AT$6="",NOT(ISNUMBER($H$2))),"",SUMIFS(数据录入!$G$5:$G$4999,数据录入!$C$5:$C$4999,$A13,数据录入!$B$5:$B$4999,AT$6)) | AU13: =IF(OR($A13="",AU$6="",NOT(ISNUMBER($H$2))),"",SUMIFS(数据录入!$F$5:$F$4999,数据录入!$C$5:$C$4999,$A13,数据录入!$B$5:$B$4999,AU$6)) | AV13: =IF(OR($A13="",AV$6="",NOT(ISNUMBER($H$2))),"",SUMIFS(数据录入!$G$5:$G$4999,数据录入!$C$5:$C$4999,$A13,数据录入!$B$5:$B$4999,AV$6)) | AW13: =IF(OR($A13="",AW$6="",NOT(ISNUMBER($H$2))),"",SUMIFS(数据录入!$F$5:$F$4999,数据录入!$C$5:$C$4999,$A13,数据录入!$B$5:$B$4999,AW$6)) | AX13: =IF(OR($A13="",AX$6="",NOT(ISNUMBER($H$2))),"",SUMIFS(数据录入!$G$5:$G$4999,数据录入!$C$5:$C$4999,$A13,数据录入!$B$5:$B$4999,AX$6)) | AY13: =IF(OR($A13="",AY$6="",NOT(ISNUMBER($H$2))),"",SUMIFS(数据录入!$F$5:$F$4999,数据录入!$C$5:$C$4999,$A13,数据录入!$B$5:$B$4999,AY$6)) | AZ13: =IF(OR($A13="",AZ$6="",NOT(ISNUMBER($H$2))),"",SUMIFS(数据录入!$G$5:$G$4999,数据录入!$C$5:$C$4999,$A13,数据录入!$B$5:$B$4999,AZ$6)) | BA13: =IF(OR($A13="",BA$6="",NOT(ISNUMBER($H$2))),"",SUMIFS(数据录入!$F$5:$F$4999,数据录入!$C$5:$C$4999,$A13,数据录入!$B$5:$B$4999,BA$6)) | BB13: =IF(OR($A13="",BB$6="",NOT(ISNUMBER($H$2))),"",SUMIFS(数据录入!$G$5:$G$4999,数据录入!$C$5:$C$4999,$A13,数据录入!$B$5:$B$4999,BB$6)) | BC13: =IF(OR($A13="",BC$6="",NOT(ISNUMBER($H$2))),"",SUMIFS(数据录入!$F$5:$F$4999,数据录入!$C$5:$C$4999,$A13,数据录入!$B$5:$B$4999,BC$6)) | BD13: =IF(OR($A13="",BD$6="",NOT(ISNUMBER($H$2))),"",SUMIFS(数据录入!$G$5:$G$4999,数据录入!$C$5:$C$4999,$A13,数据录入!$B$5:$B$4999,BD$6)) | BE13: =IF(OR($A13="",BE$6="",NOT(ISNUMBER($H$2))),"",SUMIFS(数据录入!$F$5:$F$4999,数据录入!$C$5:$C$4999,$A13,数据录入!$B$5:$B$4999,BE$6)) | BF13: =IF(OR($A13="",BF$6="",NOT(ISNUMBER($H$2))),"",SUMIFS(数据录入!$G$5:$G$4999,数据录入!$C$5:$C$4999,$A13,数据录入!$B$5:$B$4999,BF$6)) | BG13: =IF(OR($A13="",BG$6="",NOT(ISNUMBER($H$2))),"",SUMIFS(数据录入!$F$5:$F$4999,数据录入!$C$5:$C$4999,$A13,数据录入!$B$5:$B$4999,BG$6)) | BH13: =IF(OR($A13="",BH$6="",NOT(ISNUMBER($H$2))),"",SUMIFS(数据录入!$G$5:$G$4999,数据录入!$C$5:$C$4999,$A13,数据录入!$B$5:$B$4999,BH$6)) | BI13: =IF(OR($A13="",BI$6="",NOT(ISNUMBER($H$2))),"",SUMIFS(数据录入!$F$5:$F$4999,数据录入!$C$5:$C$4999,$A13,数据录入!$B$5:$B$4999,BI$6)) | BJ13: =IF(OR($A13="",BJ$6="",NOT(ISNUMBER($H$2))),"",SUMIFS(数据录入!$G$5:$G$4999,数据录入!$C$5:$C$4999,$A13,数据录入!$B$5:$B$4999,BJ$6)) | BK13: =IF(OR($A13="",BK$6="",NOT(ISNUMBER($H$2))),"",SUMIFS(数据录入!$F$5:$F$4999,数据录入!$C$5:$C$4999,$A13,数据录入!$B$5:$B$4999,BK$6)) | BL13: =IF(OR($A13="",BL$6="",NOT(ISNUMBER($H$2))),"",SUMIFS(数据录入!$G$5:$G$4999,数据录入!$C$5:$C$4999,$A13,数据录入!$B$5:$B$4999,BL$6)) | BM13: =IF($A13="","",SUMIF($C$7:$BL$7,"收款",C13:BL13)) | BN13: =IF($A13="","",SUMIF($C$7:$BL$7,"付款",C13:BL13)) | BO13: =IF($A13="","",B13+BM13-BN13)
A14: 备用1 | B14: =IF(OR($A14="",NOT(ISNUMBER($H$2))),"",SUMIFS(数据录入!$H$5:$H$4999,数据录入!$C$5:$C$4999,$A14,数据录入!$E$5:$E$4999,"期初余额",数据录入!$B$5:$B$4999,"<="&$B$2)+SUMIFS(数据录入!$F$5:$F$4999,数据录入!$C$5:$C$4999,$A14,数据录入!$B$5:$B$4999,"<"&$B$2)-SUMIFS(数据录入!$G$5:$G$4999,数据录入!$C$5:$C$4999,$A14,数据录入!$B$5:$B$4999,"<"&$B$2)) | C14: =IF(OR($A14="",C$6="",NOT(ISNUMBER($H$2))),"",SUMIFS(数据录入!$F$5:$F$4999,数据录入!$C$5:$C$4999,$A14,数据录入!$B$5:$B$4999,C$6)) | D14: =IF(OR($A14="",D$6="",NOT(ISNUMBER($H$2))),"",SUMIFS(数据录入!$G$5:$G$4999,数据录入!$C$5:$C$4999,$A14,数据录入!$B$5:$B$4999,D$6)) | E14: =IF(OR($A14="",E$6="",NOT(ISNUMBER($H$2))),"",SUMIFS(数据录入!$F$5:$F$4999,数据录入!$C$5:$C$4999,$A14,数据录入!$B$5:$B$4999,E$6)) | F14: =IF(OR($A14="",F$6="",NOT(ISNUMBER($H$2))),"",SUMIFS(数据录入!$G$5:$G$4999,数据录入!$C$5:$C$4999,$A14,数据录入!$B$5:$B$4999,F$6)) | G14: =IF(OR($A14="",G$6="",NOT(ISNUMBER($H$2))),"",SUMIFS(数据录入!$F$5:$F$4999,数据录入!$C$5:$C$4999,$A14,数据录入!$B$5:$B$4999,G$6)) | H14: =IF(OR($A14="",H$6="",NOT(ISNUMBER($H$2))),"",SUMIFS(数据录入!$G$5:$G$4999,数据录入!$C$5:$C$4999,$A14,数据录入!$B$5:$B$4999,H$6)) | I14: =IF(OR($A14="",I$6="",NOT(ISNUMBER($H$2))),"",SUMIFS(数据录入!$F$5:$F$4999,数据录入!$C$5:$C$4999,$A14,数据录入!$B$5:$B$4999,I$6)) | J14: =IF(OR($A14="",J$6="",NOT(ISNUMBER($H$2))),"",SUMIFS(数据录入!$G$5:$G$4999,数据录入!$C$5:$C$4999,$A14,数据录入!$B$5:$B$4999,J$6)) | K14: =IF(OR($A14="",K$6="",NOT(ISNUMBER($H$2))),"",SUMIFS(数据录入!$F$5:$F$4999,数据录入!$C$5:$C$4999,$A14,数据录入!$B$5:$B$4999,K$6)) | L14: =IF(OR($A14="",L$6="",NOT(ISNUMBER($H$2))),"",SUMIFS(数据录入!$G$5:$G$4999,数据录入!$C$5:$C$4999,$A14,数据录入!$B$5:$B$4999,L$6)) | M14: =IF(OR($A14="",M$6="",NOT(ISNUMBER($H$2))),"",SUMIFS(数据录入!$F$5:$F$4999,数据录入!$C$5:$C$4999,$A14,数据录入!$B$5:$B$4999,M$6)) | N14: =IF(OR($A14="",N$6="",NOT(ISNUMBER($H$2))),"",SUMIFS(数据录入!$G$5:$G$4999,数据录入!$C$5:$C$4999,$A14,数据录入!$B$5:$B$4999,N$6)) | O14: =IF(OR($A14="",O$6="",NOT(ISNUMBER($H$2))),"",SUMIFS(数据录入!$F$5:$F$4999,数据录入!$C$5:$C$4999,$A14,数据录入!$B$5:$B$4999,O$6)) | P14: =IF(OR($A14="",P$6="",NOT(ISNUMBER($H$2))),"",SUMIFS(数据录入!$G$5:$G$4999,数据录入!$C$5:$C$4999,$A14,数据录入!$B$5:$B$4999,P$6)) | Q14: =IF(OR($A14="",Q$6="",NOT(ISNUMBER($H$2))),"",SUMIFS(数据录入!$F$5:$F$4999,数据录入!$C$5:$C$4999,$A14,数据录入!$B$5:$B$4999,Q$6)) | R14: =IF(OR($A14="",R$6="",NOT(ISNUMBER($H$2))),"",SUMIFS(数据录入!$G$5:$G$4999,数据录入!$C$5:$C$4999,$A14,数据录入!$B$5:$B$4999,R$6)) | S14: =IF(OR($A14="",S$6="",NOT(ISNUMBER($H$2))),"",SUMIFS(数据录入!$F$5:$F$4999,数据录入!$C$5:$C$4999,$A14,数据录入!$B$5:$B$4999,S$6)) | T14: =IF(OR($A14="",T$6="",NOT(ISNUMBER($H$2))),"",SUMIFS(数据录入!$G$5:$G$4999,数据录入!$C$5:$C$4999,$A14,数据录入!$B$5:$B$4999,T$6)) | U14: =IF(OR($A14="",U$6="",NOT(ISNUMBER($H$2))),"",SUMIFS(数据录入!$F$5:$F$4999,数据录入!$C$5:$C$4999,$A14,数据录入!$B$5:$B$4999,U$6)) | V14: =IF(OR($A14="",V$6="",NOT(ISNUMBER($H$2))),"",SUMIFS(数据录入!$G$5:$G$4999,数据录入!$C$5:$C$4999,$A14,数据录入!$B$5:$B$4999,V$6)) | W14: =IF(OR($A14="",W$6="",NOT(ISNUMBER($H$2))),"",SUMIFS(数据录入!$F$5:$F$4999,数据录入!$C$5:$C$4999,$A14,数据录入!$B$5:$B$4999,W$6)) | X14: =IF(OR($A14="",X$6="",NOT(ISNUMBER($H$2))),"",SUMIFS(数据录入!$G$5:$G$4999,数据录入!$C$5:$C$4999,$A14,数据录入!$B$5:$B$4999,X$6)) | Y14: =IF(OR($A14="",Y$6="",NOT(ISNUMBER($H$2))),"",SUMIFS(数据录入!$F$5:$F$4999,数据录入!$C$5:$C$4999,$A14,数据录入!$B$5:$B$4999,Y$6)) | Z14: =IF(OR($A14="",Z$6="",NOT(ISNUMBER($H$2))),"",SUMIFS(数据录入!$G$5:$G$4999,数据录入!$C$5:$C$4999,$A14,数据录入!$B$5:$B$4999,Z$6)) | AA14: =IF(OR($A14="",AA$6="",NOT(ISNUMBER($H$2))),"",SUMIFS(数据录入!$F$5:$F$4999,数据录入!$C$5:$C$4999,$A14,数据录入!$B$5:$B$4999,AA$6)) | AB14: =IF(OR($A14="",AB$6="",NOT(ISNUMBER($H$2))),"",SUMIFS(数据录入!$G$5:$G$4999,数据录入!$C$5:$C$4999,$A14,数据录入!$B$5:$B$4999,AB$6)) | AC14: =IF(OR($A14="",AC$6="",NOT(ISNUMBER($H$2))),"",SUMIFS(数据录入!$F$5:$F$4999,数据录入!$C$5:$C$4999,$A14,数据录入!$B$5:$B$4999,AC$6)) | AD14: =IF(OR($A14="",AD$6="",NOT(ISNUMBER($H$2))),"",SUMIFS(数据录入!$G$5:$G$4999,数据录入!$C$5:$C$4999,$A14,数据录入!$B$5:$B$4999,AD$6)) | AE14: =IF(OR($A14="",AE$6="",NOT(ISNUMBER($H$2))),"",SUMIFS(数据录入!$F$5:$F$4999,数据录入!$C$5:$C$4999,$A14,数据录入!$B$5:$B$4999,AE$6)) | AF14: =IF(OR($A14="",AF$6="",NOT(ISNUMBER($H$2))),"",SUMIFS(数据录入!$G$5:$G$4999,数据录入!$C$5:$C$4999,$A14,数据录入!$B$5:$B$4999,AF$6)) | AG14: =IF(OR($A14="",AG$6="",NOT(ISNUMBER($H$2))),"",SUMIFS(数据录入!$F$5:$F$4999,数据录入!$C$5:$C$4999,$A14,数据录入!$B$5:$B$4999,AG$6)) | AH14: =IF(OR($A14="",AH$6="",NOT(ISNUMBER($H$2))),"",SUMIFS(数据录入!$G$5:$G$4999,数据录入!$C$5:$C$4999,$A14,数据录入!$B$5:$B$4999,AH$6)) | AI14: =IF(OR($A14="",AI$6="",NOT(ISNUMBER($H$2))),"",SUMIFS(数据录入!$F$5:$F$4999,数据录入!$C$5:$C$4999,$A14,数据录入!$B$5:$B$4999,AI$6)) | AJ14: =IF(OR($A14="",AJ$6="",NOT(ISNUMBER($H$2))),"",SUMIFS(数据录入!$G$5:$G$4999,数据录入!$C$5:$C$4999,$A14,数据录入!$B$5:$B$4999,AJ$6)) | AK14: =IF(OR($A14="",AK$6="",NOT(ISNUMBER($H$2))),"",SUMIFS(数据录入!$F$5:$F$4999,数据录入!$C$5:$C$4999,$A14,数据录入!$B$5:$B$4999,AK$6)) | AL14: =IF(OR($A14="",AL$6="",NOT(ISNUMBER($H$2))),"",SUMIFS(数据录入!$G$5:$G$4999,数据录入!$C$5:$C$4999,$A14,数据录入!$B$5:$B$4999,AL$6)) | AM14: =IF(OR($A14="",AM$6="",NOT(ISNUMBER($H$2))),"",SUMIFS(数据录入!$F$5:$F$4999,数据录入!$C$5:$C$4999,$A14,数据录入!$B$5:$B$4999,AM$6)) | AN14: =IF(OR($A14="",AN$6="",NOT(ISNUMBER($H$2))),"",SUMIFS(数据录入!$G$5:$G$4999,数据录入!$C$5:$C$4999,$A14,数据录入!$B$5:$B$4999,AN$6)) | AO14: =IF(OR($A14="",AO$6="",NOT(ISNUMBER($H$2))),"",SUMIFS(数据录入!$F$5:$F$4999,数据录入!$C$5:$C$4999,$A14,数据录入!$B$5:$B$4999,AO$6)) | AP14: =IF(OR($A14="",AP$6="",NOT(ISNUMBER($H$2))),"",SUMIFS(数据录入!$G$5:$G$4999,数据录入!$C$5:$C$4999,$A14,数据录入!$B$5:$B$4999,AP$6)) | AQ14: =IF(OR($A14="",AQ$6="",NOT(ISNUMBER($H$2))),"",SUMIFS(数据录入!$F$5:$F$4999,数据录入!$C$5:$C$4999,$A14,数据录入!$B$5:$B$4999,AQ$6)) | AR14: =IF(OR($A14="",AR$6="",NOT(ISNUMBER($H$2))),"",SUMIFS(数据录入!$G$5:$G$4999,数据录入!$C$5:$C$4999,$A14,数据录入!$B$5:$B$4999,AR$6)) | AS14: =IF(OR($A14="",AS$6="",NOT(ISNUMBER($H$2))),"",SUMIFS(数据录入!$F$5:$F$4999,数据录入!$C$5:$C$4999,$A14,数据录入!$B$5:$B$4999,AS$6)) | AT14: =IF(OR($A14="",AT$6="",NOT(ISNUMBER($H$2))),"",SUMIFS(数据录入!$G$5:$G$4999,数据录入!$C$5:$C$4999,$A14,数据录入!$B$5:$B$4999,AT$6)) | AU14: =IF(OR($A14="",AU$6="",NOT(ISNUMBER($H$2))),"",SUMIFS(数据录入!$F$5:$F$4999,数据录入!$C$5:$C$4999,$A14,数据录入!$B$5:$B$4999,AU$6)) | AV14: =IF(OR($A14="",AV$6="",NOT(ISNUMBER($H$2))),"",SUMIFS(数据录入!$G$5:$G$4999,数据录入!$C$5:$C$4999,$A14,数据录入!$B$5:$B$4999,AV$6)) | AW14: =IF(OR($A14="",AW$6="",NOT(ISNUMBER($H$2))),"",SUMIFS(数据录入!$F$5:$F$4999,数据录入!$C$5:$C$4999,$A14,数据录入!$B$5:$B$4999,AW$6)) | AX14: =IF(OR($A14="",AX$6="",NOT(ISNUMBER($H$2))),"",SUMIFS(数据录入!$G$5:$G$4999,数据录入!$C$5:$C$4999,$A14,数据录入!$B$5:$B$4999,AX$6)) | AY14: =IF(OR($A14="",AY$6="",NOT(ISNUMBER($H$2))),"",SUMIFS(数据录入!$F$5:$F$4999,数据录入!$C$5:$C$4999,$A14,数据录入!$B$5:$B$4999,AY$6)) | AZ14: =IF(OR($A14="",AZ$6="",NOT(ISNUMBER($H$2))),"",SUMIFS(数据录入!$G$5:$G$4999,数据录入!$C$5:$C$4999,$A14,数据录入!$B$5:$B$4999,AZ$6)) | BA14: =IF(OR($A14="",BA$6="",NOT(ISNUMBER($H$2))),"",SUMIFS(数据录入!$F$5:$F$4999,数据录入!$C$5:$C$4999,$A14,数据录入!$B$5:$B$4999,BA$6)) | BB14: =IF(OR($A14="",BB$6="",NOT(ISNUMBER($H$2))),"",SUMIFS(数据录入!$G$5:$G$4999,数据录入!$C$5:$C$4999,$A14,数据录入!$B$5:$B$4999,BB$6)) | BC14: =IF(OR($A14="",BC$6="",NOT(ISNUMBER($H$2))),"",SUMIFS(数据录入!$F$5:$F$4999,数据录入!$C$5:$C$4999,$A14,数据录入!$B$5:$B$4999,BC$6)) | BD14: =IF(OR($A14="",BD$6="",NOT(ISNUMBER($H$2))),"",SUMIFS(数据录入!$G$5:$G$4999,数据录入!$C$5:$C$4999,$A14,数据录入!$B$5:$B$4999,BD$6)) | BE14: =IF(OR($A14="",BE$6="",NOT(ISNUMBER($H$2))),"",SUMIFS(数据录入!$F$5:$F$4999,数据录入!$C$5:$C$4999,$A14,数据录入!$B$5:$B$4999,BE$6)) | BF14: =IF(OR($A14="",BF$6="",NOT(ISNUMBER($H$2))),"",SUMIFS(数据录入!$G$5:$G$4999,数据录入!$C$5:$C$4999,$A14,数据录入!$B$5:$B$4999,BF$6)) | BG14: =IF(OR($A14="",BG$6="",NOT(ISNUMBER($H$2))),"",SUMIFS(数据录入!$F$5:$F$4999,数据录入!$C$5:$C$4999,$A14,数据录入!$B$5:$B$4999,BG$6)) | BH14: =IF(OR($A14="",BH$6="",NOT(ISNUMBER($H$2))),"",SUMIFS(数据录入!$G$5:$G$4999,数据录入!$C$5:$C$4999,$A14,数据录入!$B$5:$B$4999,BH$6)) | BI14: =IF(OR($A14="",BI$6="",NOT(ISNUMBER($H$2))),"",SUMIFS(数据录入!$F$5:$F$4999,数据录入!$C$5:$C$4999,$A14,数据录入!$B$5:$B$4999,BI$6)) | BJ14: =IF(OR($A14="",BJ$6="",NOT(ISNUMBER($H$2))),"",SUMIFS(数据录入!$G$5:$G$4999,数据录入!$C$5:$C$4999,$A14,数据录入!$B$5:$B$4999,BJ$6)) | BK14: =IF(OR($A14="",BK$6="",NOT(ISNUMBER($H$2))),"",SUMIFS(数据录入!$F$5:$F$4999,数据录入!$C$5:$C$4999,$A14,数据录入!$B$5:$B$4999,BK$6)) | BL14: =IF(OR($A14="",BL$6="",NOT(ISNUMBER($H$2))),"",SUMIFS(数据录入!$G$5:$G$4999,数据录入!$C$5:$C$4999,$A14,数据录入!$B$5:$B$4999,BL$6)) | BM14: =IF($A14="","",SUMIF($C$7:$BL$7,"收款",C14:BL14)) | BN14: =IF($A14="","",SUMIF($C$7:$BL$7,"付款",C14:BL14)) | BO14: =IF($A14="","",B14+BM14-BN14)
A15: 备用2 | B15: =IF(OR($A15="",NOT(ISNUMBER($H$2))),"",SUMIFS(数据录入!$H$5:$H$4999,数据录入!$C$5:$C$4999,$A15,数据录入!$E$5:$E$4999,"期初余额",数据录入!$B$5:$B$4999,"<="&$B$2)+SUMIFS(数据录入!$F$5:$F$4999,数据录入!$C$5:$C$4999,$A15,数据录入!$B$5:$B$4999,"<"&$B$2)-SUMIFS(数据录入!$G$5:$G$4999,数据录入!$C$5:$C$4999,$A15,数据录入!$B$5:$B$4999,"<"&$B$2)) | C15: =IF(OR($A15="",C$6="",NOT(ISNUMBER($H$2))),"",SUMIFS(数据录入!$F$5:$F$4999,数据录入!$C$5:$C$4999,$A15,数据录入!$B$5:$B$4999,C$6)) | D15: =IF(OR($A15="",D$6="",NOT(ISNUMBER($H$2))),"",SUMIFS(数据录入!$G$5:$G$4999,数据录入!$C$5:$C$4999,$A15,数据录入!$B$5:$B$4999,D$6)) | E15: =IF(OR($A15="",E$6="",NOT(ISNUMBER($H$2))),"",SUMIFS(数据录入!$F$5:$F$4999,数据录入!$C$5:$C$4999,$A15,数据录入!$B$5:$B$4999,E$6)) | F15: =IF(OR($A15="",F$6="",NOT(ISNUMBER($H$2))),"",SUMIFS(数据录入!$G$5:$G$4999,数据录入!$C$5:$C$4999,$A15,数据录入!$B$5:$B$4999,F$6)) | G15: =IF(OR($A15="",G$6="",NOT(ISNUMBER($H$2))),"",SUMIFS(数据录入!$F$5:$F$4999,数据录入!$C$5:$C$4999,$A15,数据录入!$B$5:$B$4999,G$6)) | H15: =IF(OR($A15="",H$6="",NOT(ISNUMBER($H$2))),"",SUMIFS(数据录入!$G$5:$G$4999,数据录入!$C$5:$C$4999,$A15,数据录入!$B$5:$B$4999,H$6)) | I15: =IF(OR($A15="",I$6="",NOT(ISNUMBER($H$2))),"",SUMIFS(数据录入!$F$5:$F$4999,数据录入!$C$5:$C$4999,$A15,数据录入!$B$5:$B$4999,I$6)) | J15: =IF(OR($A15="",J$6="",NOT(ISNUMBER($H$2))),"",SUMIFS(数据录入!$G$5:$G$4999,数据录入!$C$5:$C$4999,$A15,数据录入!$B$5:$B$4999,J$6)) | K15: =IF(OR($A15="",K$6="",NOT(ISNUMBER($H$2))),"",SUMIFS(数据录入!$F$5:$F$4999,数据录入!$C$5:$C$4999,$A15,数据录入!$B$5:$B$4999,K$6)) | L15: =IF(OR($A15="",L$6="",NOT(ISNUMBER($H$2))),"",SUMIFS(数据录入!$G$5:$G$4999,数据录入!$C$5:$C$4999,$A15,数据录入!$B$5:$B$4999,L$6)) | M15: =IF(OR($A15="",M$6="",NOT(ISNUMBER($H$2))),"",SUMIFS(数据录入!$F$5:$F$4999,数据录入!$C$5:$C$4999,$A15,数据录入!$B$5:$B$4999,M$6)) | N15: =IF(OR($A15="",N$6="",NOT(ISNUMBER($H$2))),"",SUMIFS(数据录入!$G$5:$G$4999,数据录入!$C$5:$C$4999,$A15,数据录入!$B$5:$B$4999,N$6)) | O15: =IF(OR($A15="",O$6="",NOT(ISNUMBER($H$2))),"",SUMIFS(数据录入!$F$5:$F$4999,数据录入!$C$5:$C$4999,$A15,数据录入!$B$5:$B$4999,O$6)) | P15: =IF(OR($A15="",P$6="",NOT(ISNUMBER($H$2))),"",SUMIFS(数据录入!$G$5:$G$4999,数据录入!$C$5:$C$4999,$A15,数据录入!$B$5:$B$4999,P$6)) | Q15: =IF(OR($A15="",Q$6="",NOT(ISNUMBER($H$2))),"",SUMIFS(数据录入!$F$5:$F$4999,数据录入!$C$5:$C$4999,$A15,数据录入!$B$5:$B$4999,Q$6)) | R15: =IF(OR($A15="",R$6="",NOT(ISNUMBER($H$2))),"",SUMIFS(数据录入!$G$5:$G$4999,数据录入!$C$5:$C$4999,$A15,数据录入!$B$5:$B$4999,R$6)) | S15: =IF(OR($A15="",S$6="",NOT(ISNUMBER($H$2))),"",SUMIFS(数据录入!$F$5:$F$4999,数据录入!$C$5:$C$4999,$A15,数据录入!$B$5:$B$4999,S$6)) | T15: =IF(OR($A15="",T$6="",NOT(ISNUMBER($H$2))),"",SUMIFS(数据录入!$G$5:$G$4999,数据录入!$C$5:$C$4999,$A15,数据录入!$B$5:$B$4999,T$6)) | U15: =IF(OR($A15="",U$6="",NOT(ISNUMBER($H$2))),"",SUMIFS(数据录入!$F$5:$F$4999,数据录入!$C$5:$C$4999,$A15,数据录入!$B$5:$B$4999,U$6)) | V15: =IF(OR($A15="",V$6="",NOT(ISNUMBER($H$2))),"",SUMIFS(数据录入!$G$5:$G$4999,数据录入!$C$5:$C$4999,$A15,数据录入!$B$5:$B$4999,V$6)) | W15: =IF(OR($A15="",W$6="",NOT(ISNUMBER($H$2))),"",SUMIFS(数据录入!$F$5:$F$4999,数据录入!$C$5:$C$4999,$A15,数据录入!$B$5:$B$4999,W$6)) | X15: =IF(OR($A15="",X$6="",NOT(ISNUMBER($H$2))),"",SUMIFS(数据录入!$G$5:$G$4999,数据录入!$C$5:$C$4999,$A15,数据录入!$B$5:$B$4999,X$6)) | Y15: =IF(OR($A15="",Y$6="",NOT(ISNUMBER($H$2))),"",SUMIFS(数据录入!$F$5:$F$4999,数据录入!$C$5:$C$4999,$A15,数据录入!$B$5:$B$4999,Y$6)) | Z15: =IF(OR($A15="",Z$6="",NOT(ISNUMBER($H$2))),"",SUMIFS(数据录入!$G$5:$G$4999,数据录入!$C$5:$C$4999,$A15,数据录入!$B$5:$B$4999,Z$6)) | AA15: =IF(OR($A15="",AA$6="",NOT(ISNUMBER($H$2))),"",SUMIFS(数据录入!$F$5:$F$4999,数据录入!$C$5:$C$4999,$A15,数据录入!$B$5:$B$4999,AA$6)) | AB15: =IF(OR($A15="",AB$6="",NOT(ISNUMBER($H$2))),"",SUMIFS(数据录入!$G$5:$G$4999,数据录入!$C$5:$C$4999,$A15,数据录入!$B$5:$B$4999,AB$6)) | AC15: =IF(OR($A15="",AC$6="",NOT(ISNUMBER($H$2))),"",SUMIFS(数据录入!$F$5:$F$4999,数据录入!$C$5:$C$4999,$A15,数据录入!$B$5:$B$4999,AC$6)) | AD15: =IF(OR($A15="",AD$6="",NOT(ISNUMBER($H$2))),"",SUMIFS(数据录入!$G$5:$G$4999,数据录入!$C$5:$C$4999,$A15,数据录入!$B$5:$B$4999,AD$6)) | AE15: =IF(OR($A15="",AE$6="",NOT(ISNUMBER($H$2))),"",SUMIFS(数据录入!$F$5:$F$4999,数据录入!$C$5:$C$4999,$A15,数据录入!$B$5:$B$4999,AE$6)) | AF15: =IF(OR($A15="",AF$6="",NOT(ISNUMBER($H$2))),"",SUMIFS(数据录入!$G$5:$G$4999,数据录入!$C$5:$C$4999,$A15,数据录入!$B$5:$B$4999,AF$6)) | AG15: =IF(OR($A15="",AG$6="",NOT(ISNUMBER($H$2))),"",SUMIFS(数据录入!$F$5:$F$4999,数据录入!$C$5:$C$4999,$A15,数据录入!$B$5:$B$4999,AG$6)) | AH15: =IF(OR($A15="",AH$6="",NOT(ISNUMBER($H$2))),"",SUMIFS(数据录入!$G$5:$G$4999,数据录入!$C$5:$C$4999,$A15,数据录入!$B$5:$B$4999,AH$6)) | AI15: =IF(OR($A15="",AI$6="",NOT(ISNUMBER($H$2))),"",SUMIFS(数据录入!$F$5:$F$4999,数据录入!$C$5:$C$4999,$A15,数据录入!$B$5:$B$4999,AI$6)) | AJ15: =IF(OR($A15="",AJ$6="",NOT(ISNUMBER($H$2))),"",SUMIFS(数据录入!$G$5:$G$4999,数据录入!$C$5:$C$4999,$A15,数据录入!$B$5:$B$4999,AJ$6)) | AK15: =IF(OR($A15="",AK$6="",NOT(ISNUMBER($H$2))),"",SUMIFS(数据录入!$F$5:$F$4999,数据录入!$C$5:$C$4999,$A15,数据录入!$B$5:$B$4999,AK$6)) | AL15: =IF(OR($A15="",AL$6="",NOT(ISNUMBER($H$2))),"",SUMIFS(数据录入!$G$5:$G$4999,数据录入!$C$5:$C$4999,$A15,数据录入!$B$5:$B$4999,AL$6)) | AM15: =IF(OR($A15="",AM$6="",NOT(ISNUMBER($H$2))),"",SUMIFS(数据录入!$F$5:$F$4999,数据录入!$C$5:$C$4999,$A15,数据录入!$B$5:$B$4999,AM$6)) | AN15: =IF(OR($A15="",AN$6="",NOT(ISNUMBER($H$2))),"",SUMIFS(数据录入!$G$5:$G$4999,数据录入!$C$5:$C$4999,$A15,数据录入!$B$5:$B$4999,AN$6)) | AO15: =IF(OR($A15="",AO$6="",NOT(ISNUMBER($H$2))),"",SUMIFS(数据录入!$F$5:$F$4999,数据录入!$C$5:$C$4999,$A15,数据录入!$B$5:$B$4999,AO$6)) | AP15: =IF(OR($A15="",AP$6="",NOT(ISNUMBER($H$2))),"",SUMIFS(数据录入!$G$5:$G$4999,数据录入!$C$5:$C$4999,$A15,数据录入!$B$5:$B$4999,AP$6)) | AQ15: =IF(OR($A15="",AQ$6="",NOT(ISNUMBER($H$2))),"",SUMIFS(数据录入!$F$5:$F$4999,数据录入!$C$5:$C$4999,$A15,数据录入!$B$5:$B$4999,AQ$6)) | AR15: =IF(OR($A15="",AR$6="",NOT(ISNUMBER($H$2))),"",SUMIFS(数据录入!$G$5:$G$4999,数据录入!$C$5:$C$4999,$A15,数据录入!$B$5:$B$4999,AR$6)) | AS15: =IF(OR($A15="",AS$6="",NOT(ISNUMBER($H$2))),"",SUMIFS(数据录入!$F$5:$F$4999,数据录入!$C$5:$C$4999,$A15,数据录入!$B$5:$B$4999,AS$6)) | AT15: =IF(OR($A15="",AT$6="",NOT(ISNUMBER($H$2))),"",SUMIFS(数据录入!$G$5:$G$4999,数据录入!$C$5:$C$4999,$A15,数据录入!$B$5:$B$4999,AT$6)) | AU15: =IF(OR($A15="",AU$6="",NOT(ISNUMBER($H$2))),"",SUMIFS(数据录入!$F$5:$F$4999,数据录入!$C$5:$C$4999,$A15,数据录入!$B$5:$B$4999,AU$6)) | AV15: =IF(OR($A15="",AV$6="",NOT(ISNUMBER($H$2))),"",SUMIFS(数据录入!$G$5:$G$4999,数据录入!$C$5:$C$4999,$A15,数据录入!$B$5:$B$4999,AV$6)) | AW15: =IF(OR($A15="",AW$6="",NOT(ISNUMBER($H$2))),"",SUMIFS(数据录入!$F$5:$F$4999,数据录入!$C$5:$C$4999,$A15,数据录入!$B$5:$B$4999,AW$6)) | AX15: =IF(OR($A15="",AX$6="",NOT(ISNUMBER($H$2))),"",SUMIFS(数据录入!$G$5:$G$4999,数据录入!$C$5:$C$4999,$A15,数据录入!$B$5:$B$4999,AX$6)) | AY15: =IF(OR($A15="",AY$6="",NOT(ISNUMBER($H$2))),"",SUMIFS(数据录入!$F$5:$F$4999,数据录入!$C$5:$C$4999,$A15,数据录入!$B$5:$B$4999,AY$6)) | AZ15: =IF(OR($A15="",AZ$6="",NOT(ISNUMBER($H$2))),"",SUMIFS(数据录入!$G$5:$G$4999,数据录入!$C$5:$C$4999,$A15,数据录入!$B$5:$B$4999,AZ$6)) | BA15: =IF(OR($A15="",BA$6="",NOT(ISNUMBER($H$2))),"",SUMIFS(数据录入!$F$5:$F$4999,数据录入!$C$5:$C$4999,$A15,数据录入!$B$5:$B$4999,BA$6)) | BB15: =IF(OR($A15="",BB$6="",NOT(ISNUMBER($H$2))),"",SUMIFS(数据录入!$G$5:$G$4999,数据录入!$C$5:$C$4999,$A15,数据录入!$B$5:$B$4999,BB$6)) | BC15: =IF(OR($A15="",BC$6="",NOT(ISNUMBER($H$2))),"",SUMIFS(数据录入!$F$5:$F$4999,数据录入!$C$5:$C$4999,$A15,数据录入!$B$5:$B$4999,BC$6)) | BD15: =IF(OR($A15="",BD$6="",NOT(ISNUMBER($H$2))),"",SUMIFS(数据录入!$G$5:$G$4999,数据录入!$C$5:$C$4999,$A15,数据录入!$B$5:$B$4999,BD$6)) | BE15: =IF(OR($A15="",BE$6="",NOT(ISNUMBER($H$2))),"",SUMIFS(数据录入!$F$5:$F$4999,数据录入!$C$5:$C$4999,$A15,数据录入!$B$5:$B$4999,BE$6)) | BF15: =IF(OR($A15="",BF$6="",NOT(ISNUMBER($H$2))),"",SUMIFS(数据录入!$G$5:$G$4999,数据录入!$C$5:$C$4999,$A15,数据录入!$B$5:$B$4999,BF$6)) | BG15: =IF(OR($A15="",BG$6="",NOT(ISNUMBER($H$2))),"",SUMIFS(数据录入!$F$5:$F$4999,数据录入!$C$5:$C$4999,$A15,数据录入!$B$5:$B$4999,BG$6)) | BH15: =IF(OR($A15="",BH$6="",NOT(ISNUMBER($H$2))),"",SUMIFS(数据录入!$G$5:$G$4999,数据录入!$C$5:$C$4999,$A15,数据录入!$B$5:$B$4999,BH$6)) | BI15: =IF(OR($A15="",BI$6="",NOT(ISNUMBER($H$2))),"",SUMIFS(数据录入!$F$5:$F$4999,数据录入!$C$5:$C$4999,$A15,数据录入!$B$5:$B$4999,BI$6)) | BJ15: =IF(OR($A15="",BJ$6="",NOT(ISNUMBER($H$2))),"",SUMIFS(数据录入!$G$5:$G$4999,数据录入!$C$5:$C$4999,$A15,数据录入!$B$5:$B$4999,BJ$6)) | BK15: =IF(OR($A15="",BK$6="",NOT(ISNUMBER($H$2))),"",SUMIFS(数据录入!$F$5:$F$4999,数据录入!$C$5:$C$4999,$A15,数据录入!$B$5:$B$4999,BK$6)) | BL15: =IF(OR($A15="",BL$6="",NOT(ISNUMBER($H$2))),"",SUMIFS(数据录入!$G$5:$G$4999,数据录入!$C$5:$C$4999,$A15,数据录入!$B$5:$B$4999,BL$6)) | BM15: =IF($A15="","",SUMIF($C$7:$BL$7,"收款",C15:BL15)) | BN15: =IF($A15="","",SUMIF($C$7:$BL$7,"付款",C15:BL15)) | BO15: =IF($A15="","",B15+BM15-BN15)
A16: 备用3 | B16: =IF(OR($A16="",NOT(ISNUMBER($H$2))),"",SUMIFS(数据录入!$H$5:$H$4999,数据录入!$C$5:$C$4999,$A16,数据录入!$E$5:$E$4999,"期初余额",数据录入!$B$5:$B$4999,"<="&$B$2)+SUMIFS(数据录入!$F$5:$F$4999,数据录入!$C$5:$C$4999,$A16,数据录入!$B$5:$B$4999,"<"&$B$2)-SUMIFS(数据录入!$G$5:$G$4999,数据录入!$C$5:$C$4999,$A16,数据录入!$B$5:$B$4999,"<"&$B$2)) | C16: =IF(OR($A16="",C$6="",NOT(ISNUMBER($H$2))),"",SUMIFS(数据录入!$F$5:$F$4999,数据录入!$C$5:$C$4999,$A16,数据录入!$B$5:$B$4999,C$6)) | D16: =IF(OR($A16="",D$6="",NOT(ISNUMBER($H$2))),"",SUMIFS(数据录入!$G$5:$G$4999,数据录入!$C$5:$C$4999,$A16,数据录入!$B$5:$B$4999,D$6)) | E16: =IF(OR($A16="",E$6="",NOT(ISNUMBER($H$2))),"",SUMIFS(数据录入!$F$5:$F$4999,数据录入!$C$5:$C$4999,$A16,数据录入!$B$5:$B$4999,E$6)) | F16: =IF(OR($A16="",F$6="",NOT(ISNUMBER($H$2))),"",SUMIFS(数据录入!$G$5:$G$4999,数据录入!$C$5:$C$4999,$A16,数据录入!$B$5:$B$4999,F$6)) | G16: =IF(OR($A16="",G$6="",NOT(ISNUMBER($H$2))),"",SUMIFS(数据录入!$F$5:$F$4999,数据录入!$C$5:$C$4999,$A16,数据录入!$B$5:$B$4999,G$6)) | H16: =IF(OR($A16="",H$6="",NOT(ISNUMBER($H$2))),"",SUMIFS(数据录入!$G$5:$G$4999,数据录入!$C$5:$C$4999,$A16,数据录入!$B$5:$B$4999,H$6)) | I16: =IF(OR($A16="",I$6="",NOT(ISNUMBER($H$2))),"",SUMIFS(数据录入!$F$5:$F$4999,数据录入!$C$5:$C$4999,$A16,数据录入!$B$5:$B$4999,I$6)) | J16: =IF(OR($A16="",J$6="",NOT(ISNUMBER($H$2))),"",SUMIFS(数据录入!$G$5:$G$4999,数据录入!$C$5:$C$4999,$A16,数据录入!$B$5:$B$4999,J$6)) | K16: =IF(OR($A16="",K$6="",NOT(ISNUMBER($H$2))),"",SUMIFS(数据录入!$F$5:$F$4999,数据录入!$C$5:$C$4999,$A16,数据录入!$B$5:$B$4999,K$6)) | L16: =IF(OR($A16="",L$6="",NOT(ISNUMBER($H$2))),"",SUMIFS(数据录入!$G$5:$G$4999,数据录入!$C$5:$C$4999,$A16,数据录入!$B$5:$B$4999,L$6)) | M16: =IF(OR($A16="",M$6="",NOT(ISNUMBER($H$2))),"",SUMIFS(数据录入!$F$5:$F$4999,数据录入!$C$5:$C$4999,$A16,数据录入!$B$5:$B$4999,M$6)) | N16: =IF(OR($A16="",N$6="",NOT(ISNUMBER($H$2))),"",SUMIFS(数据录入!$G$5:$G$4999,数据录入!$C$5:$C$4999,$A16,数据录入!$B$5:$B$4999,N$6)) | O16: =IF(OR($A16="",O$6="",NOT(ISNUMBER($H$2))),"",SUMIFS(数据录入!$F$5:$F$4999,数据录入!$C$5:$C$4999,$A16,数据录入!$B$5:$B$4999,O$6)) | P16: =IF(OR($A16="",P$6="",NOT(ISNUMBER($H$2))),"",SUMIFS(数据录入!$G$5:$G$4999,数据录入!$C$5:$C$4999,$A16,数据录入!$B$5:$B$4999,P$6)) | Q16: =IF(OR($A16="",Q$6="",NOT(ISNUMBER($H$2))),"",SUMIFS(数据录入!$F$5:$F$4999,数据录入!$C$5:$C$4999,$A16,数据录入!$B$5:$B$4999,Q$6)) | R16: =IF(OR($A16="",R$6="",NOT(ISNUMBER($H$2))),"",SUMIFS(数据录入!$G$5:$G$4999,数据录入!$C$5:$C$4999,$A16,数据录入!$B$5:$B$4999,R$6)) | S16: =IF(OR($A16="",S$6="",NOT(ISNUMBER($H$2))),"",SUMIFS(数据录入!$F$5:$F$4999,数据录入!$C$5:$C$4999,$A16,数据录入!$B$5:$B$4999,S$6)) | T16: =IF(OR($A16="",T$6="",NOT(ISNUMBER($H$2))),"",SUMIFS(数据录入!$G$5:$G$4999,数据录入!$C$5:$C$4999,$A16,数据录入!$B$5:$B$4999,T$6)) | U16: =IF(OR($A16="",U$6="",NOT(ISNUMBER($H$2))),"",SUMIFS(数据录入!$F$5:$F$4999,数据录入!$C$5:$C$4999,$A16,数据录入!$B$5:$B$4999,U$6)) | V16: =IF(OR($A16="",V$6="",NOT(ISNUMBER($H$2))),"",SUMIFS(数据录入!$G$5:$G$4999,数据录入!$C$5:$C$4999,$A16,数据录入!$B$5:$B$4999,V$6)) | W16: =IF(OR($A16="",W$6="",NOT(ISNUMBER($H$2))),"",SUMIFS(数据录入!$F$5:$F$4999,数据录入!$C$5:$C$4999,$A16,数据录入!$B$5:$B$4999,W$6)) | X16: =IF(OR($A16="",X$6="",NOT(ISNUMBER($H$2))),"",SUMIFS(数据录入!$G$5:$G$4999,数据录入!$C$5:$C$4999,$A16,数据录入!$B$5:$B$4999,X$6)) | Y16: =IF(OR($A16="",Y$6="",NOT(ISNUMBER($H$2))),"",SUMIFS(数据录入!$F$5:$F$4999,数据录入!$C$5:$C$4999,$A16,数据录入!$B$5:$B$4999,Y$6)) | Z16: =IF(OR($A16="",Z$6="",NOT(ISNUMBER($H$2))),"",SUMIFS(数据录入!$G$5:$G$4999,数据录入!$C$5:$C$4999,$A16,数据录入!$B$5:$B$4999,Z$6)) | AA16: =IF(OR($A16="",AA$6="",NOT(ISNUMBER($H$2))),"",SUMIFS(数据录入!$F$5:$F$4999,数据录入!$C$5:$C$4999,$A16,数据录入!$B$5:$B$4999,AA$6)) | AB16: =IF(OR($A16="",AB$6="",NOT(ISNUMBER($H$2))),"",SUMIFS(数据录入!$G$5:$G$4999,数据录入!$C$5:$C$4999,$A16,数据录入!$B$5:$B$4999,AB$6)) | AC16: =IF(OR($A16="",AC$6="",NOT(ISNUMBER($H$2))),"",SUMIFS(数据录入!$F$5:$F$4999,数据录入!$C$5:$C$4999,$A16,数据录入!$B$5:$B$4999,AC$6)) | AD16: =IF(OR($A16="",AD$6="",NOT(ISNUMBER($H$2))),"",SUMIFS(数据录入!$G$5:$G$4999,数据录入!$C$5:$C$4999,$A16,数据录入!$B$5:$B$4999,AD$6)) | AE16: =IF(OR($A16="",AE$6="",NOT(ISNUMBER($H$2))),"",SUMIFS(数据录入!$F$5:$F$4999,数据录入!$C$5:$C$4999,$A16,数据录入!$B$5:$B$4999,AE$6)) | AF16: =IF(OR($A16="",AF$6="",NOT(ISNUMBER($H$2))),"",SUMIFS(数据录入!$G$5:$G$4999,数据录入!$C$5:$C$4999,$A16,数据录入!$B$5:$B$4999,AF$6)) | AG16: =IF(OR($A16="",AG$6="",NOT(ISNUMBER($H$2))),"",SUMIFS(数据录入!$F$5:$F$4999,数据录入!$C$5:$C$4999,$A16,数据录入!$B$5:$B$4999,AG$6)) | AH16: =IF(OR($A16="",AH$6="",NOT(ISNUMBER($H$2))),"",SUMIFS(数据录入!$G$5:$G$4999,数据录入!$C$5:$C$4999,$A16,数据录入!$B$5:$B$4999,AH$6)) | AI16: =IF(OR($A16="",AI$6="",NOT(ISNUMBER($H$2))),"",SUMIFS(数据录入!$F$5:$F$4999,数据录入!$C$5:$C$4999,$A16,数据录入!$B$5:$B$4999,AI$6)) | AJ16: =IF(OR($A16="",AJ$6="",NOT(ISNUMBER($H$2))),"",SUMIFS(数据录入!$G$5:$G$4999,数据录入!$C$5:$C$4999,$A16,数据录入!$B$5:$B$4999,AJ$6)) | AK16: =IF(OR($A16="",AK$6="",NOT(ISNUMBER($H$2))),"",SUMIFS(数据录入!$F$5:$F$4999,数据录入!$C$5:$C$4999,$A16,数据录入!$B$5:$B$4999,AK$6)) | AL16: =IF(OR($A16="",AL$6="",NOT(ISNUMBER($H$2))),"",SUMIFS(数据录入!$G$5:$G$4999,数据录入!$C$5:$C$4999,$A16,数据录入!$B$5:$B$4999,AL$6)) | AM16: =IF(OR($A16="",AM$6="",NOT(ISNUMBER($H$2))),"",SUMIFS(数据录入!$F$5:$F$4999,数据录入!$C$5:$C$4999,$A16,数据录入!$B$5:$B$4999,AM$6)) | AN16: =IF(OR($A16="",AN$6="",NOT(ISNUMBER($H$2))),"",SUMIFS(数据录入!$G$5:$G$4999,数据录入!$C$5:$C$4999,$A16,数据录入!$B$5:$B$4999,AN$6)) | AO16: =IF(OR($A16="",AO$6="",NOT(ISNUMBER($H$2))),"",SUMIFS(数据录入!$F$5:$F$4999,数据录入!$C$5:$C$4999,$A16,数据录入!$B$5:$B$4999,AO$6)) | AP16: =IF(OR($A16="",AP$6="",NOT(ISNUMBER($H$2))),"",SUMIFS(数据录入!$G$5:$G$4999,数据录入!$C$5:$C$4999,$A16,数据录入!$B$5:$B$4999,AP$6)) | AQ16: =IF(OR($A16="",AQ$6="",NOT(ISNUMBER($H$2))),"",SUMIFS(数据录入!$F$5:$F$4999,数据录入!$C$5:$C$4999,$A16,数据录入!$B$5:$B$4999,AQ$6)) | AR16: =IF(OR($A16="",AR$6="",NOT(ISNUMBER($H$2))),"",SUMIFS(数据录入!$G$5:$G$4999,数据录入!$C$5:$C$4999,$A16,数据录入!$B$5:$B$4999,AR$6)) | AS16: =IF(OR($A16="",AS$6="",NOT(ISNUMBER($H$2))),"",SUMIFS(数据录入!$F$5:$F$4999,数据录入!$C$5:$C$4999,$A16,数据录入!$B$5:$B$4999,AS$6)) | AT16: =IF(OR($A16="",AT$6="",NOT(ISNUMBER($H$2))),"",SUMIFS(数据录入!$G$5:$G$4999,数据录入!$C$5:$C$4999,$A16,数据录入!$B$5:$B$4999,AT$6)) | AU16: =IF(OR($A16="",AU$6="",NOT(ISNUMBER($H$2))),"",SUMIFS(数据录入!$F$5:$F$4999,数据录入!$C$5:$C$4999,$A16,数据录入!$B$5:$B$4999,AU$6)) | AV16: =IF(OR($A16="",AV$6="",NOT(ISNUMBER($H$2))),"",SUMIFS(数据录入!$G$5:$G$4999,数据录入!$C$5:$C$4999,$A16,数据录入!$B$5:$B$4999,AV$6)) | AW16: =IF(OR($A16="",AW$6="",NOT(ISNUMBER($H$2))),"",SUMIFS(数据录入!$F$5:$F$4999,数据录入!$C$5:$C$4999,$A16,数据录入!$B$5:$B$4999,AW$6)) | AX16: =IF(OR($A16="",AX$6="",NOT(ISNUMBER($H$2))),"",SUMIFS(数据录入!$G$5:$G$4999,数据录入!$C$5:$C$4999,$A16,数据录入!$B$5:$B$4999,AX$6)) | AY16: =IF(OR($A16="",AY$6="",NOT(ISNUMBER($H$2))),"",SUMIFS(数据录入!$F$5:$F$4999,数据录入!$C$5:$C$4999,$A16,数据录入!$B$5:$B$4999,AY$6)) | AZ16: =IF(OR($A16="",AZ$6="",NOT(ISNUMBER($H$2))),"",SUMIFS(数据录入!$G$5:$G$4999,数据录入!$C$5:$C$4999,$A16,数据录入!$B$5:$B$4999,AZ$6)) | BA16: =IF(OR($A16="",BA$6="",NOT(ISNUMBER($H$2))),"",SUMIFS(数据录入!$F$5:$F$4999,数据录入!$C$5:$C$4999,$A16,数据录入!$B$5:$B$4999,BA$6)) | BB16: =IF(OR($A16="",BB$6="",NOT(ISNUMBER($H$2))),"",SUMIFS(数据录入!$G$5:$G$4999,数据录入!$C$5:$C$4999,$A16,数据录入!$B$5:$B$4999,BB$6)) | BC16: =IF(OR($A16="",BC$6="",NOT(ISNUMBER($H$2))),"",SUMIFS(数据录入!$F$5:$F$4999,数据录入!$C$5:$C$4999,$A16,数据录入!$B$5:$B$4999,BC$6)) | BD16: =IF(OR($A16="",BD$6="",NOT(ISNUMBER($H$2))),"",SUMIFS(数据录入!$G$5:$G$4999,数据录入!$C$5:$C$4999,$A16,数据录入!$B$5:$B$4999,BD$6)) | BE16: =IF(OR($A16="",BE$6="",NOT(ISNUMBER($H$2))),"",SUMIFS(数据录入!$F$5:$F$4999,数据录入!$C$5:$C$4999,$A16,数据录入!$B$5:$B$4999,BE$6)) | BF16: =IF(OR($A16="",BF$6="",NOT(ISNUMBER($H$2))),"",SUMIFS(数据录入!$G$5:$G$4999,数据录入!$C$5:$C$4999,$A16,数据录入!$B$5:$B$4999,BF$6)) | BG16: =IF(OR($A16="",BG$6="",NOT(ISNUMBER($H$2))),"",SUMIFS(数据录入!$F$5:$F$4999,数据录入!$C$5:$C$4999,$A16,数据录入!$B$5:$B$4999,BG$6)) | BH16: =IF(OR($A16="",BH$6="",NOT(ISNUMBER($H$2))),"",SUMIFS(数据录入!$G$5:$G$4999,数据录入!$C$5:$C$4999,$A16,数据录入!$B$5:$B$4999,BH$6)) | BI16: =IF(OR($A16="",BI$6="",NOT(ISNUMBER($H$2))),"",SUMIFS(数据录入!$F$5:$F$4999,数据录入!$C$5:$C$4999,$A16,数据录入!$B$5:$B$4999,BI$6)) | BJ16: =IF(OR($A16="",BJ$6="",NOT(ISNUMBER($H$2))),"",SUMIFS(数据录入!$G$5:$G$4999,数据录入!$C$5:$C$4999,$A16,数据录入!$B$5:$B$4999,BJ$6)) | BK16: =IF(OR($A16="",BK$6="",NOT(ISNUMBER($H$2))),"",SUMIFS(数据录入!$F$5:$F$4999,数据录入!$C$5:$C$4999,$A16,数据录入!$B$5:$B$4999,BK$6)) | BL16: =IF(OR($A16="",BL$6="",NOT(ISNUMBER($H$2))),"",SUMIFS(数据录入!$G$5:$G$4999,数据录入!$C$5:$C$4999,$A16,数据录入!$B$5:$B$4999,BL$6)) | BM16: =IF($A16="","",SUMIF($C$7:$BL$7,"收款",C16:BL16)) | BN16: =IF($A16="","",SUMIF($C$7:$BL$7,"付款",C16:BL16)) | BO16: =IF($A16="","",B16+BM16-BN16)
A17: 备用4 | B17: =IF(OR($A17="",NOT(ISNUMBER($H$2))),"",SUMIFS(数据录入!$H$5:$H$4999,数据录入!$C$5:$C$4999,$A17,数据录入!$E$5:$E$4999,"期初余额",数据录入!$B$5:$B$4999,"<="&$B$2)+SUMIFS(数据录入!$F$5:$F$4999,数据录入!$C$5:$C$4999,$A17,数据录入!$B$5:$B$4999,"<"&$B$2)-SUMIFS(数据录入!$G$5:$G$4999,数据录入!$C$5:$C$4999,$A17,数据录入!$B$5:$B$4999,"<"&$B$2)) | C17: =IF(OR($A17="",C$6="",NOT(ISNUMBER($H$2))),"",SUMIFS(数据录入!$F$5:$F$4999,数据录入!$C$5:$C$4999,$A17,数据录入!$B$5:$B$4999,C$6)) | D17: =IF(OR($A17="",D$6="",NOT(ISNUMBER($H$2))),"",SUMIFS(数据录入!$G$5:$G$4999,数据录入!$C$5:$C$4999,$A17,数据录入!$B$5:$B$4999,D$6)) | E17: =IF(OR($A17="",E$6="",NOT(ISNUMBER($H$2))),"",SUMIFS(数据录入!$F$5:$F$4999,数据录入!$C$5:$C$4999,$A17,数据录入!$B$5:$B$4999,E$6)) | F17: =IF(OR($A17="",F$6="",NOT(ISNUMBER($H$2))),"",SUMIFS(数据录入!$G$5:$G$4999,数据录入!$C$5:$C$4999,$A17,数据录入!$B$5:$B$4999,F$6)) | G17: =IF(OR($A17="",G$6="",NOT(ISNUMBER($H$2))),"",SUMIFS(数据录入!$F$5:$F$4999,数据录入!$C$5:$C$4999,$A17,数据录入!$B$5:$B$4999,G$6)) | H17: =IF(OR($A17="",H$6="",NOT(ISNUMBER($H$2))),"",SUMIFS(数据录入!$G$5:$G$4999,数据录入!$C$5:$C$4999,$A17,数据录入!$B$5:$B$4999,H$6)) | I17: =IF(OR($A17="",I$6="",NOT(ISNUMBER($H$2))),"",SUMIFS(数据录入!$F$5:$F$4999,数据录入!$C$5:$C$4999,$A17,数据录入!$B$5:$B$4999,I$6)) | J17: =IF(OR($A17="",J$6="",NOT(ISNUMBER($H$2))),"",SUMIFS(数据录入!$G$5:$G$4999,数据录入!$C$5:$C$4999,$A17,数据录入!$B$5:$B$4999,J$6)) | K17: =IF(OR($A17="",K$6="",NOT(ISNUMBER($H$2))),"",SUMIFS(数据录入!$F$5:$F$4999,数据录入!$C$5:$C$4999,$A17,数据录入!$B$5:$B$4999,K$6)) | L17: =IF(OR($A17="",L$6="",NOT(ISNUMBER($H$2))),"",SUMIFS(数据录入!$G$5:$G$4999,数据录入!$C$5:$C$4999,$A17,数据录入!$B$5:$B$4999,L$6)) | M17: =IF(OR($A17="",M$6="",NOT(ISNUMBER($H$2))),"",SUMIFS(数据录入!$F$5:$F$4999,数据录入!$C$5:$C$4999,$A17,数据录入!$B$5:$B$4999,M$6)) | N17: =IF(OR($A17="",N$6="",NOT(ISNUMBER($H$2))),"",SUMIFS(数据录入!$G$5:$G$4999,数据录入!$C$5:$C$4999,$A17,数据录入!$B$5:$B$4999,N$6)) | O17: =IF(OR($A17="",O$6="",NOT(ISNUMBER($H$2))),"",SUMIFS(数据录入!$F$5:$F$4999,数据录入!$C$5:$C$4999,$A17,数据录入!$B$5:$B$4999,O$6)) | P17: =IF(OR($A17="",P$6="",NOT(ISNUMBER($H$2))),"",SUMIFS(数据录入!$G$5:$G$4999,数据录入!$C$5:$C$4999,$A17,数据录入!$B$5:$B$4999,P$6)) | Q17: =IF(OR($A17="",Q$6="",NOT(ISNUMBER($H$2))),"",SUMIFS(数据录入!$F$5:$F$4999,数据录入!$C$5:$C$4999,$A17,数据录入!$B$5:$B$4999,Q$6)) | R17: =IF(OR($A17="",R$6="",NOT(ISNUMBER($H$2))),"",SUMIFS(数据录入!$G$5:$G$4999,数据录入!$C$5:$C$4999,$A17,数据录入!$B$5:$B$4999,R$6)) | S17: =IF(OR($A17="",S$6="",NOT(ISNUMBER($H$2))),"",SUMIFS(数据录入!$F$5:$F$4999,数据录入!$C$5:$C$4999,$A17,数据录入!$B$5:$B$4999,S$6)) | T17: =IF(OR($A17="",T$6="",NOT(ISNUMBER($H$2))),"",SUMIFS(数据录入!$G$5:$G$4999,数据录入!$C$5:$C$4999,$A17,数据录入!$B$5:$B$4999,T$6)) | U17: =IF(OR($A17="",U$6="",NOT(ISNUMBER($H$2))),"",SUMIFS(数据录入!$F$5:$F$4999,数据录入!$C$5:$C$4999,$A17,数据录入!$B$5:$B$4999,U$6)) | V17: =IF(OR($A17="",V$6="",NOT(ISNUMBER($H$2))),"",SUMIFS(数据录入!$G$5:$G$4999,数据录入!$C$5:$C$4999,$A17,数据录入!$B$5:$B$4999,V$6)) | W17: =IF(OR($A17="",W$6="",NOT(ISNUMBER($H$2))),"",SUMIFS(数据录入!$F$5:$F$4999,数据录入!$C$5:$C$4999,$A17,数据录入!$B$5:$B$4999,W$6)) | X17: =IF(OR($A17="",X$6="",NOT(ISNUMBER($H$2))),"",SUMIFS(数据录入!$G$5:$G$4999,数据录入!$C$5:$C$4999,$A17,数据录入!$B$5:$B$4999,X$6)) | Y17: =IF(OR($A17="",Y$6="",NOT(ISNUMBER($H$2))),"",SUMIFS(数据录入!$F$5:$F$4999,数据录入!$C$5:$C$4999,$A17,数据录入!$B$5:$B$4999,Y$6)) | Z17: =IF(OR($A17="",Z$6="",NOT(ISNUMBER($H$2))),"",SUMIFS(数据录入!$G$5:$G$4999,数据录入!$C$5:$C$4999,$A17,数据录入!$B$5:$B$4999,Z$6)) | AA17: =IF(OR($A17="",AA$6="",NOT(ISNUMBER($H$2))),"",SUMIFS(数据录入!$F$5:$F$4999,数据录入!$C$5:$C$4999,$A17,数据录入!$B$5:$B$4999,AA$6)) | AB17: =IF(OR($A17="",AB$6="",NOT(ISNUMBER($H$2))),"",SUMIFS(数据录入!$G$5:$G$4999,数据录入!$C$5:$C$4999,$A17,数据录入!$B$5:$B$4999,AB$6)) | AC17: =IF(OR($A17="",AC$6="",NOT(ISNUMBER($H$2))),"",SUMIFS(数据录入!$F$5:$F$4999,数据录入!$C$5:$C$4999,$A17,数据录入!$B$5:$B$4999,AC$6)) | AD17: =IF(OR($A17="",AD$6="",NOT(ISNUMBER($H$2))),"",SUMIFS(数据录入!$G$5:$G$4999,数据录入!$C$5:$C$4999,$A17,数据录入!$B$5:$B$4999,AD$6)) | AE17: =IF(OR($A17="",AE$6="",NOT(ISNUMBER($H$2))),"",SUMIFS(数据录入!$F$5:$F$4999,数据录入!$C$5:$C$4999,$A17,数据录入!$B$5:$B$4999,AE$6)) | AF17: =IF(OR($A17="",AF$6="",NOT(ISNUMBER($H$2))),"",SUMIFS(数据录入!$G$5:$G$4999,数据录入!$C$5:$C$4999,$A17,数据录入!$B$5:$B$4999,AF$6)) | AG17: =IF(OR($A17="",AG$6="",NOT(ISNUMBER($H$2))),"",SUMIFS(数据录入!$F$5:$F$4999,数据录入!$C$5:$C$4999,$A17,数据录入!$B$5:$B$4999,AG$6)) | AH17: =IF(OR($A17="",AH$6="",NOT(ISNUMBER($H$2))),"",SUMIFS(数据录入!$G$5:$G$4999,数据录入!$C$5:$C$4999,$A17,数据录入!$B$5:$B$4999,AH$6)) | AI17: =IF(OR($A17="",AI$6="",NOT(ISNUMBER($H$2))),"",SUMIFS(数据录入!$F$5:$F$4999,数据录入!$C$5:$C$4999,$A17,数据录入!$B$5:$B$4999,AI$6)) | AJ17: =IF(OR($A17="",AJ$6="",NOT(ISNUMBER($H$2))),"",SUMIFS(数据录入!$G$5:$G$4999,数据录入!$C$5:$C$4999,$A17,数据录入!$B$5:$B$4999,AJ$6)) | AK17: =IF(OR($A17="",AK$6="",NOT(ISNUMBER($H$2))),"",SUMIFS(数据录入!$F$5:$F$4999,数据录入!$C$5:$C$4999,$A17,数据录入!$B$5:$B$4999,AK$6)) | AL17: =IF(OR($A17="",AL$6="",NOT(ISNUMBER($H$2))),"",SUMIFS(数据录入!$G$5:$G$4999,数据录入!$C$5:$C$4999,$A17,数据录入!$B$5:$B$4999,AL$6)) | AM17: =IF(OR($A17="",AM$6="",NOT(ISNUMBER($H$2))),"",SUMIFS(数据录入!$F$5:$F$4999,数据录入!$C$5:$C$4999,$A17,数据录入!$B$5:$B$4999,AM$6)) | AN17: =IF(OR($A17="",AN$6="",NOT(ISNUMBER($H$2))),"",SUMIFS(数据录入!$G$5:$G$4999,数据录入!$C$5:$C$4999,$A17,数据录入!$B$5:$B$4999,AN$6)) | AO17: =IF(OR($A17="",AO$6="",NOT(ISNUMBER($H$2))),"",SUMIFS(数据录入!$F$5:$F$4999,数据录入!$C$5:$C$4999,$A17,数据录入!$B$5:$B$4999,AO$6)) | AP17: =IF(OR($A17="",AP$6="",NOT(ISNUMBER($H$2))),"",SUMIFS(数据录入!$G$5:$G$4999,数据录入!$C$5:$C$4999,$A17,数据录入!$B$5:$B$4999,AP$6)) | AQ17: =IF(OR($A17="",AQ$6="",NOT(ISNUMBER($H$2))),"",SUMIFS(数据录入!$F$5:$F$4999,数据录入!$C$5:$C$4999,$A17,数据录入!$B$5:$B$4999,AQ$6)) | AR17: =IF(OR($A17="",AR$6="",NOT(ISNUMBER($H$2))),"",SUMIFS(数据录入!$G$5:$G$4999,数据录入!$C$5:$C$4999,$A17,数据录入!$B$5:$B$4999,AR$6)) | AS17: =IF(OR($A17="",AS$6="",NOT(ISNUMBER($H$2))),"",SUMIFS(数据录入!$F$5:$F$4999,数据录入!$C$5:$C$4999,$A17,数据录入!$B$5:$B$4999,AS$6)) | AT17: =IF(OR($A17="",AT$6="",NOT(ISNUMBER($H$2))),"",SUMIFS(数据录入!$G$5:$G$4999,数据录入!$C$5:$C$4999,$A17,数据录入!$B$5:$B$4999,AT$6)) | AU17: =IF(OR($A17="",AU$6="",NOT(ISNUMBER($H$2))),"",SUMIFS(数据录入!$F$5:$F$4999,数据录入!$C$5:$C$4999,$A17,数据录入!$B$5:$B$4999,AU$6)) | AV17: =IF(OR($A17="",AV$6="",NOT(ISNUMBER($H$2))),"",SUMIFS(数据录入!$G$5:$G$4999,数据录入!$C$5:$C$4999,$A17,数据录入!$B$5:$B$4999,AV$6)) | AW17: =IF(OR($A17="",AW$6="",NOT(ISNUMBER($H$2))),"",SUMIFS(数据录入!$F$5:$F$4999,数据录入!$C$5:$C$4999,$A17,数据录入!$B$5:$B$4999,AW$6)) | AX17: =IF(OR($A17="",AX$6="",NOT(ISNUMBER($H$2))),"",SUMIFS(数据录入!$G$5:$G$4999,数据录入!$C$5:$C$4999,$A17,数据录入!$B$5:$B$4999,AX$6)) | AY17: =IF(OR($A17="",AY$6="",NOT(ISNUMBER($H$2))),"",SUMIFS(数据录入!$F$5:$F$4999,数据录入!$C$5:$C$4999,$A17,数据录入!$B$5:$B$4999,AY$6)) | AZ17: =IF(OR($A17="",AZ$6="",NOT(ISNUMBER($H$2))),"",SUMIFS(数据录入!$G$5:$G$4999,数据录入!$C$5:$C$4999,$A17,数据录入!$B$5:$B$4999,AZ$6)) | BA17: =IF(OR($A17="",BA$6="",NOT(ISNUMBER($H$2))),"",SUMIFS(数据录入!$F$5:$F$4999,数据录入!$C$5:$C$4999,$A17,数据录入!$B$5:$B$4999,BA$6)) | BB17: =IF(OR($A17="",BB$6="",NOT(ISNUMBER($H$2))),"",SUMIFS(数据录入!$G$5:$G$4999,数据录入!$C$5:$C$4999,$A17,数据录入!$B$5:$B$4999,BB$6)) | BC17: =IF(OR($A17="",BC$6="",NOT(ISNUMBER($H$2))),"",SUMIFS(数据录入!$F$5:$F$4999,数据录入!$C$5:$C$4999,$A17,数据录入!$B$5:$B$4999,BC$6)) | BD17: =IF(OR($A17="",BD$6="",NOT(ISNUMBER($H$2))),"",SUMIFS(数据录入!$G$5:$G$4999,数据录入!$C$5:$C$4999,$A17,数据录入!$B$5:$B$4999,BD$6)) | BE17: =IF(OR($A17="",BE$6="",NOT(ISNUMBER($H$2))),"",SUMIFS(数据录入!$F$5:$F$4999,数据录入!$C$5:$C$4999,$A17,数据录入!$B$5:$B$4999,BE$6)) | BF17: =IF(OR($A17="",BF$6="",NOT(ISNUMBER($H$2))),"",SUMIFS(数据录入!$G$5:$G$4999,数据录入!$C$5:$C$4999,$A17,数据录入!$B$5:$B$4999,BF$6)) | BG17: =IF(OR($A17="",BG$6="",NOT(ISNUMBER($H$2))),"",SUMIFS(数据录入!$F$5:$F$4999,数据录入!$C$5:$C$4999,$A17,数据录入!$B$5:$B$4999,BG$6)) | BH17: =IF(OR($A17="",BH$6="",NOT(ISNUMBER($H$2))),"",SUMIFS(数据录入!$G$5:$G$4999,数据录入!$C$5:$C$4999,$A17,数据录入!$B$5:$B$4999,BH$6)) | BI17: =IF(OR($A17="",BI$6="",NOT(ISNUMBER($H$2))),"",SUMIFS(数据录入!$F$5:$F$4999,数据录入!$C$5:$C$4999,$A17,数据录入!$B$5:$B$4999,BI$6)) | BJ17: =IF(OR($A17="",BJ$6="",NOT(ISNUMBER($H$2))),"",SUMIFS(数据录入!$G$5:$G$4999,数据录入!$C$5:$C$4999,$A17,数据录入!$B$5:$B$4999,BJ$6)) | BK17: =IF(OR($A17="",BK$6="",NOT(ISNUMBER($H$2))),"",SUMIFS(数据录入!$F$5:$F$4999,数据录入!$C$5:$C$4999,$A17,数据录入!$B$5:$B$4999,BK$6)) | BL17: =IF(OR($A17="",BL$6="",NOT(ISNUMBER($H$2))),"",SUMIFS(数据录入!$G$5:$G$4999,数据录入!$C$5:$C$4999,$A17,数据录入!$B$5:$B$4999,BL$6)) | BM17: =IF($A17="","",SUMIF($C$7:$BL$7,"收款",C17:BL17)) | BN17: =IF($A17="","",SUMIF($C$7:$BL$7,"付款",C17:BL17)) | BO17: =IF($A17="","",B17+BM17-BN17)
A18: 备用5 | B18: =IF(OR($A18="",NOT(ISNUMBER($H$2))),"",SUMIFS(数据录入!$H$5:$H$4999,数据录入!$C$5:$C$4999,$A18,数据录入!$E$5:$E$4999,"期初余额",数据录入!$B$5:$B$4999,"<="&$B$2)+SUMIFS(数据录入!$F$5:$F$4999,数据录入!$C$5:$C$4999,$A18,数据录入!$B$5:$B$4999,"<"&$B$2)-SUMIFS(数据录入!$G$5:$G$4999,数据录入!$C$5:$C$4999,$A18,数据录入!$B$5:$B$4999,"<"&$B$2)) | C18: =IF(OR($A18="",C$6="",NOT(ISNUMBER($H$2))),"",SUMIFS(数据录入!$F$5:$F$4999,数据录入!$C$5:$C$4999,$A18,数据录入!$B$5:$B$4999,C$6)) | D18: =IF(OR($A18="",D$6="",NOT(ISNUMBER($H$2))),"",SUMIFS(数据录入!$G$5:$G$4999,数据录入!$C$5:$C$4999,$A18,数据录入!$B$5:$B$4999,D$6)) | E18: =IF(OR($A18="",E$6="",NOT(ISNUMBER($H$2))),"",SUMIFS(数据录入!$F$5:$F$4999,数据录入!$C$5:$C$4999,$A18,数据录入!$B$5:$B$4999,E$6)) | F18: =IF(OR($A18="",F$6="",NOT(ISNUMBER($H$2))),"",SUMIFS(数据录入!$G$5:$G$4999,数据录入!$C$5:$C$4999,$A18,数据录入!$B$5:$B$4999,F$6)) | G18: =IF(OR($A18="",G$6="",NOT(ISNUMBER($H$2))),"",SUMIFS(数据录入!$F$5:$F$4999,数据录入!$C$5:$C$4999,$A18,数据录入!$B$5:$B$4999,G$6)) | H18: =IF(OR($A18="",H$6="",NOT(ISNUMBER($H$2))),"",SUMIFS(数据录入!$G$5:$G$4999,数据录入!$C$5:$C$4999,$A18,数据录入!$B$5:$B$4999,H$6)) | I18: =IF(OR($A18="",I$6="",NOT(ISNUMBER($H$2))),"",SUMIFS(数据录入!$F$5:$F$4999,数据录入!$C$5:$C$4999,$A18,数据录入!$B$5:$B$4999,I$6)) | J18: =IF(OR($A18="",J$6="",NOT(ISNUMBER($H$2))),"",SUMIFS(数据录入!$G$5:$G$4999,数据录入!$C$5:$C$4999,$A18,数据录入!$B$5:$B$4999,J$6)) | K18: =IF(OR($A18="",K$6="",NOT(ISNUMBER($H$2))),"",SUMIFS(数据录入!$F$5:$F$4999,数据录入!$C$5:$C$4999,$A18,数据录入!$B$5:$B$4999,K$6)) | L18: =IF(OR($A18="",L$6="",NOT(ISNUMBER($H$2))),"",SUMIFS(数据录入!$G$5:$G$4999,数据录入!$C$5:$C$4999,$A18,数据录入!$B$5:$B$4999,L$6)) | M18: =IF(OR($A18="",M$6="",NOT(ISNUMBER($H$2))),"",SUMIFS(数据录入!$F$5:$F$4999,数据录入!$C$5:$C$4999,$A18,数据录入!$B$5:$B$4999,M$6)) | N18: =IF(OR($A18="",N$6="",NOT(ISNUMBER($H$2))),"",SUMIFS(数据录入!$G$5:$G$4999,数据录入!$C$5:$C$4999,$A18,数据录入!$B$5:$B$4999,N$6)) | O18: =IF(OR($A18="",O$6="",NOT(ISNUMBER($H$2))),"",SUMIFS(数据录入!$F$5:$F$4999,数据录入!$C$5:$C$4999,$A18,数据录入!$B$5:$B$4999,O$6)) | P18: =IF(OR($A18="",P$6="",NOT(ISNUMBER($H$2))),"",SUMIFS(数据录入!$G$5:$G$4999,数据录入!$C$5:$C$4999,$A18,数据录入!$B$5:$B$4999,P$6)) | Q18: =IF(OR($A18="",Q$6="",NOT(ISNUMBER($H$2))),"",SUMIFS(数据录入!$F$5:$F$4999,数据录入!$C$5:$C$4999,$A18,数据录入!$B$5:$B$4999,Q$6)) | R18: =IF(OR($A18="",R$6="",NOT(ISNUMBER($H$2))),"",SUMIFS(数据录入!$G$5:$G$4999,数据录入!$C$5:$C$4999,$A18,数据录入!$B$5:$B$4999,R$6)) | S18: =IF(OR($A18="",S$6="",NOT(ISNUMBER($H$2))),"",SUMIFS(数据录入!$F$5:$F$4999,数据录入!$C$5:$C$4999,$A18,数据录入!$B$5:$B$4999,S$6)) | T18: =IF(OR($A18="",T$6="",NOT(ISNUMBER($H$2))),"",SUMIFS(数据录入!$G$5:$G$4999,数据录入!$C$5:$C$4999,$A18,数据录入!$B$5:$B$4999,T$6)) | U18: =IF(OR($A18="",U$6="",NOT(ISNUMBER($H$2))),"",SUMIFS(数据录入!$F$5:$F$4999,数据录入!$C$5:$C$4999,$A18,数据录入!$B$5:$B$4999,U$6)) | V18: =IF(OR($A18="",V$6="",NOT(ISNUMBER($H$2))),"",SUMIFS(数据录入!$G$5:$G$4999,数据录入!$C$5:$C$4999,$A18,数据录入!$B$5:$B$4999,V$6)) | W18: =IF(OR($A18="",W$6="",NOT(ISNUMBER($H$2))),"",SUMIFS(数据录入!$F$5:$F$4999,数据录入!$C$5:$C$4999,$A18,数据录入!$B$5:$B$4999,W$6)) | X18: =IF(OR($A18="",X$6="",NOT(ISNUMBER($H$2))),"",SUMIFS(数据录入!$G$5:$G$4999,数据录入!$C$5:$C$4999,$A18,数据录入!$B$5:$B$4999,X$6)) | Y18: =IF(OR($A18="",Y$6="",NOT(ISNUMBER($H$2))),"",SUMIFS(数据录入!$F$5:$F$4999,数据录入!$C$5:$C$4999,$A18,数据录入!$B$5:$B$4999,Y$6)) | Z18: =IF(OR($A18="",Z$6="",NOT(ISNUMBER($H$2))),"",SUMIFS(数据录入!$G$5:$G$4999,数据录入!$C$5:$C$4999,$A18,数据录入!$B$5:$B$4999,Z$6)) | AA18: =IF(OR($A18="",AA$6="",NOT(ISNUMBER($H$2))),"",SUMIFS(数据录入!$F$5:$F$4999,数据录入!$C$5:$C$4999,$A18,数据录入!$B$5:$B$4999,AA$6)) | AB18: =IF(OR($A18="",AB$6="",NOT(ISNUMBER($H$2))),"",SUMIFS(数据录入!$G$5:$G$4999,数据录入!$C$5:$C$4999,$A18,数据录入!$B$5:$B$4999,AB$6)) | AC18: =IF(OR($A18="",AC$6="",NOT(ISNUMBER($H$2))),"",SUMIFS(数据录入!$F$5:$F$4999,数据录入!$C$5:$C$4999,$A18,数据录入!$B$5:$B$4999,AC$6)) | AD18: =IF(OR($A18="",AD$6="",NOT(ISNUMBER($H$2))),"",SUMIFS(数据录入!$G$5:$G$4999,数据录入!$C$5:$C$4999,$A18,数据录入!$B$5:$B$4999,AD$6)) | AE18: =IF(OR($A18="",AE$6="",NOT(ISNUMBER($H$2))),"",SUMIFS(数据录入!$F$5:$F$4999,数据录入!$C$5:$C$4999,$A18,数据录入!$B$5:$B$4999,AE$6)) | AF18: =IF(OR($A18="",AF$6="",NOT(ISNUMBER($H$2))),"",SUMIFS(数据录入!$G$5:$G$4999,数据录入!$C$5:$C$4999,$A18,数据录入!$B$5:$B$4999,AF$6)) | AG18: =IF(OR($A18="",AG$6="",NOT(ISNUMBER($H$2))),"",SUMIFS(数据录入!$F$5:$F$4999,数据录入!$C$5:$C$4999,$A18,数据录入!$B$5:$B$4999,AG$6)) | AH18: =IF(OR($A18="",AH$6="",NOT(ISNUMBER($H$2))),"",SUMIFS(数据录入!$G$5:$G$4999,数据录入!$C$5:$C$4999,$A18,数据录入!$B$5:$B$4999,AH$6)) | AI18: =IF(OR($A18="",AI$6="",NOT(ISNUMBER($H$2))),"",SUMIFS(数据录入!$F$5:$F$4999,数据录入!$C$5:$C$4999,$A18,数据录入!$B$5:$B$4999,AI$6)) | AJ18: =IF(OR($A18="",AJ$6="",NOT(ISNUMBER($H$2))),"",SUMIFS(数据录入!$G$5:$G$4999,数据录入!$C$5:$C$4999,$A18,数据录入!$B$5:$B$4999,AJ$6)) | AK18: =IF(OR($A18="",AK$6="",NOT(ISNUMBER($H$2))),"",SUMIFS(数据录入!$F$5:$F$4999,数据录入!$C$5:$C$4999,$A18,数据录入!$B$5:$B$4999,AK$6)) | AL18: =IF(OR($A18="",AL$6="",NOT(ISNUMBER($H$2))),"",SUMIFS(数据录入!$G$5:$G$4999,数据录入!$C$5:$C$4999,$A18,数据录入!$B$5:$B$4999,AL$6)) | AM18: =IF(OR($A18="",AM$6="",NOT(ISNUMBER($H$2))),"",SUMIFS(数据录入!$F$5:$F$4999,数据录入!$C$5:$C$4999,$A18,数据录入!$B$5:$B$4999,AM$6)) | AN18: =IF(OR($A18="",AN$6="",NOT(ISNUMBER($H$2))),"",SUMIFS(数据录入!$G$5:$G$4999,数据录入!$C$5:$C$4999,$A18,数据录入!$B$5:$B$4999,AN$6)) | AO18: =IF(OR($A18="",AO$6="",NOT(ISNUMBER($H$2))),"",SUMIFS(数据录入!$F$5:$F$4999,数据录入!$C$5:$C$4999,$A18,数据录入!$B$5:$B$4999,AO$6)) | AP18: =IF(OR($A18="",AP$6="",NOT(ISNUMBER($H$2))),"",SUMIFS(数据录入!$G$5:$G$4999,数据录入!$C$5:$C$4999,$A18,数据录入!$B$5:$B$4999,AP$6)) | AQ18: =IF(OR($A18="",AQ$6="",NOT(ISNUMBER($H$2))),"",SUMIFS(数据录入!$F$5:$F$4999,数据录入!$C$5:$C$4999,$A18,数据录入!$B$5:$B$4999,AQ$6)) | AR18: =IF(OR($A18="",AR$6="",NOT(ISNUMBER($H$2))),"",SUMIFS(数据录入!$G$5:$G$4999,数据录入!$C$5:$C$4999,$A18,数据录入!$B$5:$B$4999,AR$6)) | AS18: =IF(OR($A18="",AS$6="",NOT(ISNUMBER($H$2))),"",SUMIFS(数据录入!$F$5:$F$4999,数据录入!$C$5:$C$4999,$A18,数据录入!$B$5:$B$4999,AS$6)) | AT18: =IF(OR($A18="",AT$6="",NOT(ISNUMBER($H$2))),"",SUMIFS(数据录入!$G$5:$G$4999,数据录入!$C$5:$C$4999,$A18,数据录入!$B$5:$B$4999,AT$6)) | AU18: =IF(OR($A18="",AU$6="",NOT(ISNUMBER($H$2))),"",SUMIFS(数据录入!$F$5:$F$4999,数据录入!$C$5:$C$4999,$A18,数据录入!$B$5:$B$4999,AU$6)) | AV18: =IF(OR($A18="",AV$6="",NOT(ISNUMBER($H$2))),"",SUMIFS(数据录入!$G$5:$G$4999,数据录入!$C$5:$C$4999,$A18,数据录入!$B$5:$B$4999,AV$6)) | AW18: =IF(OR($A18="",AW$6="",NOT(ISNUMBER($H$2))),"",SUMIFS(数据录入!$F$5:$F$4999,数据录入!$C$5:$C$4999,$A18,数据录入!$B$5:$B$4999,AW$6)) | AX18: =IF(OR($A18="",AX$6="",NOT(ISNUMBER($H$2))),"",SUMIFS(数据录入!$G$5:$G$4999,数据录入!$C$5:$C$4999,$A18,数据录入!$B$5:$B$4999,AX$6)) | AY18: =IF(OR($A18="",AY$6="",NOT(ISNUMBER($H$2))),"",SUMIFS(数据录入!$F$5:$F$4999,数据录入!$C$5:$C$4999,$A18,数据录入!$B$5:$B$4999,AY$6)) | AZ18: =IF(OR($A18="",AZ$6="",NOT(ISNUMBER($H$2))),"",SUMIFS(数据录入!$G$5:$G$4999,数据录入!$C$5:$C$4999,$A18,数据录入!$B$5:$B$4999,AZ$6)) | BA18: =IF(OR($A18="",BA$6="",NOT(ISNUMBER($H$2))),"",SUMIFS(数据录入!$F$5:$F$4999,数据录入!$C$5:$C$4999,$A18,数据录入!$B$5:$B$4999,BA$6)) | BB18: =IF(OR($A18="",BB$6="",NOT(ISNUMBER($H$2))),"",SUMIFS(数据录入!$G$5:$G$4999,数据录入!$C$5:$C$4999,$A18,数据录入!$B$5:$B$4999,BB$6)) | BC18: =IF(OR($A18="",BC$6="",NOT(ISNUMBER($H$2))),"",SUMIFS(数据录入!$F$5:$F$4999,数据录入!$C$5:$C$4999,$A18,数据录入!$B$5:$B$4999,BC$6)) | BD18: =IF(OR($A18="",BD$6="",NOT(ISNUMBER($H$2))),"",SUMIFS(数据录入!$G$5:$G$4999,数据录入!$C$5:$C$4999,$A18,数据录入!$B$5:$B$4999,BD$6)) | BE18: =IF(OR($A18="",BE$6="",NOT(ISNUMBER($H$2))),"",SUMIFS(数据录入!$F$5:$F$4999,数据录入!$C$5:$C$4999,$A18,数据录入!$B$5:$B$4999,BE$6)) | BF18: =IF(OR($A18="",BF$6="",NOT(ISNUMBER($H$2))),"",SUMIFS(数据录入!$G$5:$G$4999,数据录入!$C$5:$C$4999,$A18,数据录入!$B$5:$B$4999,BF$6)) | BG18: =IF(OR($A18="",BG$6="",NOT(ISNUMBER($H$2))),"",SUMIFS(数据录入!$F$5:$F$4999,数据录入!$C$5:$C$4999,$A18,数据录入!$B$5:$B$4999,BG$6)) | BH18: =IF(OR($A18="",BH$6="",NOT(ISNUMBER($H$2))),"",SUMIFS(数据录入!$G$5:$G$4999,数据录入!$C$5:$C$4999,$A18,数据录入!$B$5:$B$4999,BH$6)) | BI18: =IF(OR($A18="",BI$6="",NOT(ISNUMBER($H$2))),"",SUMIFS(数据录入!$F$5:$F$4999,数据录入!$C$5:$C$4999,$A18,数据录入!$B$5:$B$4999,BI$6)) | BJ18: =IF(OR($A18="",BJ$6="",NOT(ISNUMBER($H$2))),"",SUMIFS(数据录入!$G$5:$G$4999,数据录入!$C$5:$C$4999,$A18,数据录入!$B$5:$B$4999,BJ$6)) | BK18: =IF(OR($A18="",BK$6="",NOT(ISNUMBER($H$2))),"",SUMIFS(数据录入!$F$5:$F$4999,数据录入!$C$5:$C$4999,$A18,数据录入!$B$5:$B$4999,BK$6)) | BL18: =IF(OR($A18="",BL$6="",NOT(ISNUMBER($H$2))),"",SUMIFS(数据录入!$G$5:$G$4999,数据录入!$C$5:$C$4999,$A18,数据录入!$B$5:$B$4999,BL$6)) | BM18: =IF($A18="","",SUMIF($C$7:$BL$7,"收款",C18:BL18)) | BN18: =IF($A18="","",SUMIF($C$7:$BL$7,"付款",C18:BL18)) | BO18: =IF($A18="","",B18+BM18-BN18)
