Workbook

Sheet 使用说明
A1: 更多财务实操模板，可自行搜索抖音/视频号：老财务的实操笔记
A3: 【老财务实操自用｜初级版财务台账模板】
A4: 作者：老财务的实操笔记
A5: ——————————————————————————
A6: 适用对象：小微企业、个体工商户、小规模纳税人、商贸服务类等
A7: 版本说明
A8: 本套为**通用基础初级版**，满足税务管理、费用报销、收支登记、票据管理等
A9: 可根据行业属性、业务规模、升级定制版。
A11: 模板清单，持续更新
A12: 1、应收账款风险预警表
A13: 2、日常经营情况汇总表
A14: 3、进项台帐自动查重表
... A47: 老财务自用模板｜禁止外传、倒卖、商用

Sheet 基础资料
A1: 账户 | B1: 产品 | C1: 支出类别 | E1: 客户 | G1: 供应商
A2: 现金 | B2: 红曲 | C2: 供应商 | E2: 丁爱妹 | G2: 羊奶供货商
A3: 微信 | B3: 胚脑 | E3: 方建宏 | G3: 乳铁供货商
A4: 支付宝 | B4: 胚优 | C4: 办公费 | E4: 傅荣姣
A5: 杭州 | B5: 乳铁 | C5: 水费 | E5: 郭志伟
A6: 农商 | B6: 羊奶 | C6: 电费 | E6: 过承祁
A7: 备用 | B7: 益生菌 | C7: 伙食费 | E7: 洪宗邦
A8: 备用1 | C8: 工资 | E8: 姜蓉兰
A9: 备用2 | C9: 租赁费 | E9: 姜志鸿
A10: 备用3 | C10: 差旅费 | E10: 李小琴
A11: 备用4 | C11: 业务招待费 | E11: 李晓春
A12: 备用5 | C12: 车辆费用 | E12: 李玉娟
A13: 备用6 | C13: 银行手续费 | E13: 林永来
A14: 备用7 | E14: 陆玉英
A15: 备用8 | E15: 罗理华
E16: 马珍珠
E17: 邵国新
E18: 沈祖模
E19: 唐鑫红
E20: 童炳寿
E21: 王秀娟
E22: 邬香花
E23: 吴亮
E24: 吴旭红
E25: 吴兆香
E26: 谢爱琴
E27: 徐德彪
... E38: 杨建云

Sheet 数据录入
A1: 多帐户收支登记表
F2: 收入总额 | G2: 支出总额 | H2: 账户余额
F3: =SUBTOTAL(109,$F$4:$F$9999) -> 22200 | G3: =SUBTOTAL(109,$G$4:$G$9999) -> 11660 | H3: =SUBTOTAL(109,$H$5:$H$18)+F3-G3 -> 10540
A4: 序号 | B4: 日期 | C4: 公司账户 | D4: 支出类别 | E4: 摘要内容 | F4: 收入 | G4: 支出 | H4: 账户余额 | I4: 产品 | J4: 客户 | K4: 供应商 | L4: 客户生日 | M4: 月份
A5: =IF(B5="","",COUNTA($B$5:B5)) -> 1 | B5: 46266 | C5: 现金 | E5: 期初余额 | H5: 0 | M5: =IF($B5="","",--TEXT($B5,"yyyymm")) -> 202609
A6: =IF(B6="","",COUNTA($B$5:B6)) -> 2 | B6: 46266 | C6: 微信 | E6: 期初余额 | H6: 0 | M6: =IF($B6="","",--TEXT($B6,"yyyymm")) -> 202609
A7: =IF(B7="","",COUNTA($B$5:B7)) -> 3 | B7: 46266 | C7: 支付宝 | E7: 期初余额 | H7: 0 | M7: =IF($B7="","",--TEXT($B7,"yyyymm")) -> 202609
A8: =IF(B8="","",COUNTA($B$5:B8)) -> 4 | B8: 46266 | C8: 杭州 | E8: 期初余额 | H8: 0 | M8: =IF($B8="","",--TEXT($B8,"yyyymm")) -> 202609
A9: =IF(B9="","",COUNTA($B$5:B9)) -> 5 | B9: 46266 | C9: 农商 | E9: 期初余额 | H9: 0 | M9: =IF($B9="","",--TEXT($B9,"yyyymm")) -> 202609
A10: =IF(B10="","",COUNTA($B$5:B10)) -> 6 | B10: 46266 | C10: 备用 | E10: 期初余额 | H10: 0 | M10: =IF($B10="","",--TEXT($B10,"yyyymm")) -> 202609
A11: =IF(B11="","",COUNTA($B$5:B11)) -> 7 | B11: 46266 | C11: 备用1 | E11: 期初余额 | H11: 0 | M11: =IF($B11="","",--TEXT($B11,"yyyymm")) -> 202609
A12: =IF(B12="","",COUNTA($B$5:B12)) -> 8 | B12: 46266 | C12: 备用2 | E12: 期初余额 | H12: 0 | M12: =IF($B12="","",--TEXT($B12,"yyyymm")) -> 202609
A13: =IF(B13="","",COUNTA($B$5:B13)) -> 9 | B13: 46266 | C13: 备用3 | E13: 期初余额 | H13: 0 | M13: =IF($B13="","",--TEXT($B13,"yyyymm")) -> 202609
A14: =IF(B14="","",COUNTA($B$5:B14)) -> 10 | B14: 46266 | C14: 备用4 | E14: 期初余额 | H14: 0 | M14: =IF($B14="","",--TEXT($B14,"yyyymm")) -> 202609
A15: =IF(B15="","",COUNTA($B$5:B15)) -> 11 | B15: 46266 | C15: 备用5 | E15: 期初余额 | H15: 0 | M15: =IF($B15="","",--TEXT($B15,"yyyymm")) -> 202609
A16: =IF(B16="","",COUNTA($B$5:B16)) -> 12 | B16: 46266 | C16: 备用6 | E16: 期初余额 | H16: 0 | M16: =IF($B16="","",--TEXT($B16,"yyyymm")) -> 202609
... A18: =IF(B18="","",COUNTA($B$5:B18)) -> 14 | B18: 46266 | C18: 备用8 | E18: 期初余额 | H18: 0 | M18: =IF($B18="","",--TEXT($B18,"yyyymm")) -> 202609
A19: =IF(B19="","",COUNTA($B$5:B19)) -> 15 | B19: 46266 | C19: 现金 | F19: 2000 | H19: =IFERROR(VLOOKUP($C19,$C$5:$H$18,6,0)+SUMIF($C$19:$C19,$C19,$F$19:$F19)-SUMIF($C$19:$C19,$C19,$G$19:$G19),"") -> 2000 | I19: 红曲 | J19: 丁爱妹 | M19: =IF($B19="","",--TEXT($B19,"yyyymm")) -> 202609
A20: =IF(B20="","",COUNTA($B$5:B20)) -> 16 | B20: 46266 | C20: 微信 | D20: 办公费 | G20: 200 | H20: =IFERROR(VLOOKUP($C20,$C$5:$H$18,6,0)+SUMIF($C$19:$C20,$C20,$F$19:$F20)-SUMIF($C$19:$C20,$C20,$G$19:$G20),"") -> -200 | M20: =IF($B20="","",--TEXT($B20,"yyyymm")) -> 202609
A21: =IF(B21="","",COUNTA($B$5:B21)) -> 17 | B21: 46266 | C21: 支付宝 | D21: 电费 | G21: 300 | H21: =IFERROR(VLOOKUP($C21,$C$5:$H$18,6,0)+SUMIF($C$19:$C21,$C21,$F$19:$F21)-SUMIF($C$19:$C21,$C21,$G$19:$G21),"") -> -300 | M21: =IF($B21="","",--TEXT($B21,"yyyymm")) -> 202609
A22: =IF(B22="","",COUNTA($B$5:B22)) -> 18 | B22: 46266 | C22: 杭州 | D22: 差旅费 | G22: 500 | H22: =IFERROR(VLOOKUP($C22,$C$5:$H$18,6,0)+SUMIF($C$19:$C22,$C22,$F$19:$F22)-SUMIF($C$19:$C22,$C22,$G$19:$G22),"") -> -500 | M22: =IF($B22="","",--TEXT($B22,"yyyymm")) -> 202609
A23: =IF(B23="","",COUNTA($B$5:B23)) -> 19 | B23: 46266 | C23: 农商 | F23: 2600 | H23: =IFERROR(VLOOKUP($C23,$C$5:$H$18,6,0)+SUMIF($C$19:$C23,$C23,$F$19:$F23)-SUMIF($C$19:$C23,$C23,$G$19:$G23),"") -> 2600 | M23: =IF($B23="","",--TEXT($B23,"yyyymm")) -> 202609
A24: =IF(B24="","",COUNTA($B$5:B24)) -> 20 | B24: 46266 | C24: 备用 | D24: 供应商 | G24: 5000 | H24: =IFERROR(VLOOKUP($C24,$C$5:$H$18,6,0)+SUMIF($C$19:$C24,$C24,$F$19:$F24)-SUMIF($C$19:$C24,$C24,$G$19:$G24),"") -> -5000 | K24: 羊奶供货商 | M24: =IF($B24="","",--TEXT($B24,"yyyymm")) -> 202609
A25: =IF(B25="","",COUNTA($B$5:B25)) -> 21 | B25: 46266 | C25: 备用1 | D25: 伙食费 | G25: 200 | H25: =IFERROR(VLOOKUP($C25,$C$5:$H$18,6,0)+SUMIF($C$19:$C25,$C25,$F$19:$F25)-SUMIF($C$19:$C25,$C25,$G$19:$G25),"") -> -200 | M25: =IF($B25="","",--TEXT($B25,"yyyymm")) -> 202609
A26: =IF(B26="","",COUNTA($B$5:B26)) -> 22 | B26: 46266 | C26: 备用2 | D26: 办公费 | G26: 10 | H26: =IFERROR(VLOOKUP($C26,$C$5:$H$18,6,0)+SUMIF($C$19:$C26,$C26,$F$19:$F26)-SUMIF($C$19:$C26,$C26,$G$19:$G26),"") -> -10 | M26: =IF($B26="","",--TEXT($B26,"yyyymm")) -> 202609
A27: =IF(B27="","",COUNTA($B$5:B27)) -> 23 | B27: 46266 | C27: 备用3 | D27: 车辆费用 | G27: 50 | H27: =IFERROR(VLOOKUP($C27,$C$5:$H$18,6,0)+SUMIF($C$19:$C27,$C27,$F$19:$F27)-SUMIF($C$19:$C27,$C27,$G$19:$G27),"") -> -50 | M27: =IF($B27="","",--TEXT($B27,"yyyymm")) -> 202609
A28: =IF(B28="","",COUNTA($B$5:B28)) -> 24 | B28: 46266 | C28: 备用4 | F28: 2100 | H28: =IFERROR(VLOOKUP($C28,$C$5:$H$18,6,0)+SUMIF($C$19:$C28,$C28,$F$19:$F28)-SUMIF($C$19:$C28,$C28,$G$19:$G28),"") -> 2100 | M28: =IF($B28="","",--TEXT($B28,"yyyymm")) -> 202609
A29: =IF(B29="","",COUNTA($B$5:B29)) -> 25 | B29: 46266 | C29: 备用5 | D29: 租赁费 | G29: 2000 | H29: =IFERROR(VLOOKUP($C29,$C$5:$H$18,6,0)+SUMIF($C$19:$C29,$C29,$F$19:$F29)-SUMIF($C$19:$C29,$C29,$G$19:$G29),"") -> -2000 | M29: =IF($B29="","",--TEXT($B29,"yyyymm")) -> 202609
A30: =IF(B30="","",COUNTA($B$5:B30)) -> 26 | B30: 46266 | C30: 备用6 | D30: 伙食费 | G30: 200 | H30: =IFERROR(VLOOKUP($C30,$C$5:$H$18,6,0)+SUMIF($C$19:$C30,$C30,$F$19:$F30)-SUMIF($C$19:$C30,$C30,$G$19:$G30),"") -> -200 | M30: =IF($B30="","",--TEXT($B30,"yyyymm")) -> 202609
A31: =IF(B31="","",COUNTA($B$5:B31)) -> 27 | B31: 46266 | C31: 备用7 | D31: 差旅费 | G31: 500 | H31: =IFERROR(VLOOKUP($C31,$C$5:$H$18,6,0)+SUMIF($C$19:$C31,$C31,$F$19:$F31)-SUMIF($C$19:$C31,$C31,$G$19:$G31),"") -> -500 | M31: =IF($B31="","",--TEXT($B31,"yyyymm")) -> 202609
A32: =IF(B32="","",COUNTA($B$5:B32)) -> 28 | B32: 46266 | C32: 备用8 | D32: 供应商 | G32: 1000 | H32: =IFERROR(VLOOKUP($C32,$C$5:$H$18,6,0)+SUMIF($C$19:$C32,$C32,$F$19:$F32)-SUMIF($C$19:$C32,$C32,$G$19:$G32),"") -> -1000 | M32: =IF($B32="","",--TEXT($B32,"yyyymm")) -> 202609
A33: =IF(B33="","",COUNTA($B$5:B33)) -> 29 | B33: 46266 | C33: 现金 | D33: 业务招待费 | G33: 200 | H33: =IFERROR(VLOOKUP($C33,$C$5:$H$18,6,0)+SUMIF($C$19:$C33,$C33,$F$19:$F33)-SUMIF($C$19:$C33,$C33,$G$19:$G33),"") -> 1800 | M33: =IF($B33="","",--TEXT($B33,"yyyymm")) -> 202609
A34: =IF(B34="","",COUNTA($B$5:B34)) -> 30 | B34: 46266 | C34: 微信 | D34: 车辆费用 | G34: 500 | H34: =IFERROR(VLOOKUP($C34,$C$5:$H$18,6,0)+SUMIF($C$19:$C34,$C34,$F$19:$F34)-SUMIF($C$19:$C34,$C34,$G$19:$G34),"") -> -700 | M34: =IF($B34="","",--TEXT($B34,"yyyymm")) -> 202609
A35: =IF(B35="","",COUNTA($B$5:B35)) -> 31 | B35: 46266 | C35: 支付宝 | D35: 伙食费 | G35: 500 | H35: =IFERROR(VLOOKUP($C35,$C$5:$H$18,6,0)+SUMIF($C$19:$C35,$C35,$F$19:$F35)-SUMIF($C$19:$C35,$C35,$G$19:$G35),"") -> -800 | M35: =IF($B35="","",--TEXT($B35,"yyyymm")) -> 202609
A36: =IF(B36="","",COUNTA($B$5:B36)) -> 32 | B36: 46266 | C36: 杭州 | F36: 5000 | H36: =IFERROR(VLOOKUP($C36,$C$5:$H$18,6,0)+SUMIF($C$19:$C36,$C36,$F$19:$F36)-SUMIF($C$19:$C36,$C36,$G$19:$G36),"") -> 4500 | M36: =IF($B36="","",--TEXT($B36,"yyyymm")) -> 202609
A37: =IF(B37="","",COUNTA($B$5:B37)) -> 33 | B37: 46266 | C37: 农商 | F37: 500 | H37: =IFERROR(VLOOKUP($C37,$C$5:$H$18,6,0)+SUMIF($C$19:$C37,$C37,$F$19:$F37)-SUMIF($C$19:$C37,$C37,$G$19:$G37),"") -> 3100 | M37: =IF($B37="","",--TEXT($B37,"yyyymm")) -> 202609
A38: =IF(B38="","",COUNTA($B$5:B38)) -> 34 | B38: 46266 | C38: 备用 | D38: 电费 | G38: 500 | H38: =IFERROR(VLOOKUP($C38,$C$5:$H$18,6,0)+SUMIF($C$19:$C38,$C38,$F$19:$F38)-SUMIF($C$19:$C38,$C38,$G$19:$G38),"") -> -5500 | M38: =IF($B38="","",--TEXT($B38,"yyyymm")) -> 202609
A39: =IF(B39="","",COUNTA($B$5:B39)) -> 35 | B39: 46266 | C39: 备用1 | F39: 10000 | H39: =IFERROR(VLOOKUP($C39,$C$5:$H$18,6,0)+SUMIF($C$19:$C39,$C39,$F$19:$F39)-SUMIF($C$19:$C39,$C39,$G$19:$G39),"") -> 9800 | M39: =IF($B39="","",--TEXT($B39,"yyyymm")) -> 202609
A40: =IF(B40="","",COUNTA($B$5:B40)) -> 36 | B40: 46266 | C40: 备用2 | E40: 工行转民生 | F40: 1000 | H40: =IFERROR(VLOOKUP($C40,$C$5:$H$18,6,0)+SUMIF($C$19:$C40,$C40,$F$19:$F40)-SUMIF($C$19:$C40,$C40,$G$19:$G40),"") -> 990 | M40: =IF($B40="","",--TEXT($B40,"yyyymm")) -> 202609
A41: =IF(B41="","",COUNTA($B$5:B41)) -> 37 | B41: 46266 | C41: 备用3 | E41: 工行转民生 | F41: -1000 | H41: =IFERROR(VLOOKUP($C41,$C$5:$H$18,6,0)+SUMIF($C$19:$C41,$C41,$F$19:$F41)-SUMIF($C$19:$C41,$C41,$G$19:$G41),"") -> -1050 | M41: =IF($B41="","",--TEXT($B41,"yyyymm")) -> 202609
A42: =IF(B42="","",COUNTA($B$5:B42)) | H42: =IFERROR(VLOOKUP($C42,$C$5:$H$18,6,0)+SUMIF($C$19:$C42,$C42,$F$19:$F42)-SUMIF($C$19:$C42,$C42,$G$19:$G42),"") | M42: =IF($B42="","",--TEXT($B42,"yyyymm"))
A43: =IF(B43="","",COUNTA($B$5:B43)) | H43: =IFERROR(VLOOKUP($C43,$C$5:$H$18,6,0)+SUMIF($C$19:$C43,$C43,$F$19:$F43)-SUMIF($C$19:$C43,$C43,$G$19:$G43),"") | M43: =IF($B43="","",--TEXT($B43,"yyyymm"))
A44: =IF(B44="","",COUNTA($B$5:B44)) | H44: =IFERROR(VLOOKUP($C44,$C$5:$H$18,6,0)+SUMIF($C$19:$C44,$C44,$F$19:$F44)-SUMIF($C$19:$C44,$C44,$G$19:$G44),"") | M44: =IF($B44="","",--TEXT($B44,"yyyymm"))
A45: =IF(B45="","",COUNTA($B$5:B45)) | H45: =IFERROR(VLOOKUP($C45,$C$5:$H$18,6,0)+SUMIF($C$19:$C45,$C45,$F$19:$F45)-SUMIF($C$19:$C45,$C45,$G$19:$G45),"") | M45: =IF($B45="","",--TEXT($B45,"yyyymm"))
A46: =IF(B46="","",COUNTA($B$5:B46)) | H46: =IFERROR(VLOOKUP($C46,$C$5:$H$18,6,0)+SUMIF($C$19:$C46,$C46,$F$19:$F46)-SUMIF($C$19:$C46,$C46,$G$19:$G46),"") | M46: =IF($B46="","",--TEXT($B46,"yyyymm"))
A47: =IF(B47="","",COUNTA($B$5:B47)) | H47: =IFERROR(VLOOKUP($C47,$C$5:$H$18,6,0)+SUMIF($C$19:$C47,$C47,$F$19:$F47)-SUMIF($C$19:$C47,$C47,$G$19:$G47),"") | M47: =IF($B47="","",--TEXT($B47,"yyyymm"))
A48: =IF(B48="","",COUNTA($B$5:B48)) | H48: =IFERROR(VLOOKUP($C48,$C$5:$H$18,6,0)+SUMIF($C$19:$C48,$C48,$F$19:$F48)-SUMIF($C$19:$C48,$C48,$G$19:$G48),"") | M48: =IF($B48="","",--TEXT($B48,"yyyymm"))
A49: =IF(B49="","",COUNTA($B$5:B49)) | H49: =IFERROR(VLOOKUP($C49,$C$5:$H$18,6,0)+SUMIF($C$19:$C49,$C49,$F$19:$F49)-SUMIF($C$19:$C49,$C49,$G$19:$G49),"") | M49: =IF($B49="","",--TEXT($B49,"yyyymm"))
A50: =IF(B50="","",COUNTA($B$5:B50)) | H50: =IFERROR(VLOOKUP($C50,$C$5:$H$18,6,0)+SUMIF($C$19:$C50,$C50,$F$19:$F50)-SUMIF($C$19:$C50,$C50,$G$19:$G50),"") | M50: =IF($B50="","",--TEXT($B50,"yyyymm"))
A51: =IF(B51="","",COUNTA($B$5:B51)) | H51: =IFERROR(VLOOKUP($C51,$C$5:$H$18,6,0)+SUMIF($C$19:$C51,$C51,$F$19:$F51)-SUMIF($C$19:$C51,$C51,$G$19:$G51),"") | M51: =IF($B51="","",--TEXT($B51,"yyyymm"))
A52: =IF(B52="","",COUNTA($B$5:B52)) | H52: =IFERROR(VLOOKUP($C52,$C$5:$H$18,6,0)+SUMIF($C$19:$C52,$C52,$F$19:$F52)-SUMIF($C$19:$C52,$C52,$G$19:$G52),"") | M52: =IF($B52="","",--TEXT($B52,"yyyymm"))
A53: =IF(B53="","",COUNTA($B$5:B53)) | H53: =IFERROR(VLOOKUP($C53,$C$5:$H$18,6,0)+SUMIF($C$19:$C53,$C53,$F$19:$F53)-SUMIF($C$19:$C53,$C53,$G$19:$G53),"") | M53: =IF($B53="","",--TEXT($B53,"yyyymm"))
... A100: =IF(B100="","",COUNTA($B$5:B100)) | H100: =IFERROR(VLOOKUP($C100,$C$5:$H$18,6,0)+SUMIF($C$19:$C100,$C100,$F$19:$F100)-SUMIF($C$19:$C100,$C100,$G$19:$G100),"") | M100: =IF($B100="","",--TEXT($B100,"yyyymm"))
A101: =IF(B101="","",COUNTA($B$5:B101)) | M101: =IF($B101="","",--TEXT($B101,"yyyymm"))
A102: =IF(B102="","",COUNTA($B$5:B102)) | M102: =IF($B102="","",--TEXT($B102,"yyyymm"))
A103: =IF(B103="","",COUNTA($B$5:B103)) | M103: =IF($B103="","",--TEXT($B103,"yyyymm"))
A104: =IF(B104="","",COUNTA($B$5:B104)) | M104: =IF($B104="","",--TEXT($B104,"yyyymm"))
A105: =IF(B105="","",COUNTA($B$5:B105)) | M105: =IF($B105="","",--TEXT($B105,"yyyymm"))
A106: =IF(B106="","",COUNTA($B$5:B106)) | M106: =IF($B106="","",--TEXT($B106,"yyyymm"))
A107: =IF(B107="","",COUNTA($B$5:B107)) | M107: =IF($B107="","",--TEXT($B107,"yyyymm"))
A108: =IF(B108="","",COUNTA($B$5:B108)) | M108: =IF($B108="","",--TEXT($B108,"yyyymm"))
A109: =IF(B109="","",COUNTA($B$5:B109)) | M109: =IF($B109="","",--TEXT($B109,"yyyymm"))
A110: =IF(B110="","",COUNTA($B$5:B110)) | M110: =IF($B110="","",--TEXT($B110,"yyyymm"))
A111: =IF(B111="","",COUNTA($B$5:B111)) | M111: =IF($B111="","",--TEXT($B111,"yyyymm"))
A112: =IF(B112="","",COUNTA($B$5:B112)) | M112: =IF($B112="","",--TEXT($B112,"yyyymm"))
... A249: =IF(B249="","",COUNTA($B$5:B249)) | M249: =IF($B249="","",--TEXT($B249,"yyyymm"))
M250: =IF($B250="","",--TEXT($B250,"yyyymm"))
M251: =IF($B251="","",--TEXT($B251,"yyyymm"))
M252: =IF($B252="","",--TEXT($B252,"yyyymm"))
M253: =IF($B253="","",--TEXT($B253,"yyyymm"))
M254: =IF($B254="","",--TEXT($B254,"yyyymm"))
M255: =IF($B255="","",--TEXT($B255,"yyyymm"))
M256: =IF($B256="","",--TEXT($B256,"yyyymm"))
M257: =IF($B257="","",--TEXT($B257,"yyyymm"))
M258: =IF($B258="","",--TEXT($B258,"yyyymm"))
M259: =IF($B259="","",--TEXT($B259,"yyyymm"))
M260: =IF($B260="","",--TEXT($B260,"yyyymm"))
M261: =IF($B261="","",--TEXT($B261,"yyyymm"))
... M4999: =IF($B4999="","",--TEXT($B4999,"yyyymm"))

Sheet 往来款跟进
L2: 总销售金额 | M2: =SUMIF(F11:F2001,">0") -> 23660 | N2: 应收账款 | O2: 应收款项 | P2: =SUM(F11:F2000)-SUM(J11:J2000) -> 23060 | Q2: 应付账款 | R2: 供货商 | S2: 供货商2
L3: 购货款 | M3: =SUMIF(O11:O2001,">0") -> 0 | O3: 已收款 | P3: =SUM(G11:G2000) -> 19140 | R3: 购货款 | S3: =SUMIFS(O11:O1000,N11:N1000,S2) -> 0
L4: 销售费用 | M4: =SUM(J11:J1001) -> 600 | O4: 未收总计 | P4: =SUM(H11:H2000) -> 3920 | R4: 已付款 | S4: =SUMIFS(P11:P1000,N11:N1000,S2) -> 0
L5: 利润 | M5: =M2-M3-M4 -> 23060 | R5: 尚欠款 | S5: =S3-S4 -> 0
A8: 单位名称：百跃羊奶 | S8: 单位：元
A9: 序号 | B9: 日期 | C9: 客户生日 | D9: 应收账款 | M9: 应付账款
D10: 客户名称 | E10: 销售产品 | F10: 销售金额 | G10: 已收款 | H10: 尚欠款 | I10: 未收总计 | J10: 销售费用 | K10: 支付方式 | L10: 备注 | M10: 日期 | N10: 供货商 | O10: 购货款 | P10: 已付款 | Q10: 尚欠款 | R10: 尚欠款总计 | S10: 备注
A11: {=ROW(2:500)} -> 2 | B11: 46269 | C11: 46113 | D11: 沈祖模 | E11: 羊奶 | F11: 3280 | G11: 3280 | H11: =F11-G11 -> 0 | I11: =F11-G11 -> 0 | J11: 0 | K11: 支付宝 | L11: 货款 | M11: 43971 | N11: 羊奶供货商 | Q11: =O11-P11 -> 0 | R11: =Q11 -> 0 | S11: 采购
A12: 3 | B12: 46269 | C12: 46113 | D12: 沈祖模 | E12: 乳铁蛋白 | F12: 3980 | G12: 3980 | H12: =F12-G12 -> 0 | I12: =I11+H12 -> 0 | J12: 0 | K12: 支付宝 | L12: 货款 | N12: 乳铁供货商 | Q12: =O12-P12 -> 0 | R12: =R11+O12-P12 -> 0 | S12: 采购
A13: 4 | B13: 46272 | C13: 46300 | D13: 谢爱琴 | E13: 羊奶 | F13: 3280 | G13: 2980 | H13: 0 | I13: =I12+H13 -> 0 | J13: 300 | K13: 微信 | L13: 货款 | Q13: =O13-P13 -> 0 | R13: =R12+O13-P13 -> 0 | S13: 采购
A14: 5 | B14: 46272 | C14: 46300 | D14: 谢爱琴 | E14: 益生菌 | F14: 3280 | G14: 2980 | H14: 0 | I14: =I13+H14 -> 0 | J14: 300 | K14: 微信 | L14: 货款 | Q14: =O14-P14 -> 0 | R14: =R13+O14-P14 -> 0
A15: 6 | B15: 46272 | C15: 46272 | D15: 罗理华 | E15: 羊奶 | F15: 3280 | G15: 1640 | H15: 1640 | I15: =I14+H15 -> 1640 | J15: 0 | K15: 支付宝 | L15: 货款 | Q15: =O15-P15 -> 0 | R15: =R14+O15-P15 -> 0
A16: 7 | B16: 46274 | C16: 46134 | D16: 马珍珠 | E16: 羊奶 | F16: 3280 | G16: 1000 | H16: 2280 | I16: =I15+H16 -> 3920 | J16: 0 | K16: 微信 | L16: 货款 | Q16: =O16-P16 -> 0 | R16: =R15+O16-P16 -> 0
A17: 8 | B17: 46277 | C17: 46333 | D17: 徐江英 | E17: 羊奶 | F17: 3280 | G17: 3280 | H17: 0 | I17: =I16+H17 -> 3920 | J17: 0 | K17: 微信 | L17: 货款 | Q17: =O17-P17 -> 0 | R17: =R16+O17-P17 -> 0
A18: 9 | C18: 46148 | D18: 邵国新 | I18: =I17+H18 -> 3920 | Q18: =O18-P18 -> 0 | R18: =R17+O18-P18 -> 0
A19: 10 | C19: 46140 | D19: 李晓春 | I19: =I18+H19 -> 3920 | R19: =R18+O19-P19 -> 0
A20: 11 | C20: 46154 | D20: 李玉娟 | I20: =I19+H20 -> 3920 | Q20: =O20-P20 -> 0 | R20: =R19+O20-P20 -> 0
A21: 12 | C21: 46174 | D21: 徐德彪 | I21: =I20+H21 -> 3920 | Q21: =O21-P21 -> 0 | R21: =R20+O21-P21 -> 0
A22: 13 | C22: 46188 | D22: 邬香花 方建宏 | I22: =I21+H22 -> 3920 | Q22: =O22-P22 -> 0 | R22: =R21+O22-P22 -> 0
A23: 14 | B23: 46235 | C23: 6月17日 3月4日 | D23: 林永来 杨建云 | I23: =I22+H23 -> 3920 | Q23: =O23-P23 -> 0 | R23: =R22+O23-P23 -> 0
A24: 15 | C24: 46220 | D24: 郭志伟 | I24: =I23+H24 -> 3920 | Q24: =O24-P24 -> 0 | R24: =R23+O24-P24 -> 0
A25: 16 | C25: 46225 | D25: 吴亮 | I25: =I24+H25 -> 3920 | Q25: =O25-P25 -> 0 | R25: =R24+O25-P25 -> 0
A26: 17 | C26: 46232 | D26: 吴兆香 | I26: =I25+H26 -> 3920 | Q26: =O26-P26 -> 0 | R26: =R25+O26-P26 -> 0
A27: 18 | C27: 46242 | D27: 郑玉英 | I27: =I26+H27 -> 3920 | Q27: =O27-P27 -> 0 | R27: =R26+O27-P27 -> 0
A28: 19 | C28: 46274 | D28: 唐鑫红 | I28: =I27+H28 -> 3920 | Q28: =O28-P28 -> 0 | R28: =R27+O28-P28 -> 0
A29: 20 | C29: 46285 | D29: 叶芬 | I29: =I28+H29 -> 3920 | Q29: =O29-P29 -> 0 | R29: =R28+O29-P29 -> 0
A30: 21 | C30: 46288 | D30: 童炳寿 王秀娟 | I30: =I29+H30 -> 3920 | Q30: =O30-P30 -> 0 | R30: =R29+O30-P30 -> 0
A31: 22 | C31: 46299 | D31: 郑爱月 | I31: =I30+H31 -> 3920 | Q31: =O31-P31 -> 0 | R31: =R30+O31-P31 -> 0
A32: 23 | C32: 46309 | D32: 李小琴 | I32: =I31+H32 -> 3920 | Q32: =O32-P32 -> 0 | R32: =R31+O32-P32 -> 0
A33: 24 | C33: 46318 | D33: 郁建红 | I33: =I32+H33 -> 3920 | Q33: =O33-P33 -> 0 | R33: =R32+O33-P33 -> 0
A34: 25 | C34: 10月30日 2月3日 | D34: 姜蓉兰 洪宗邦 | I34: =I33+H34 -> 3920 | Q34: =O34-P34 -> 0 | R34: =R33+O34-P34 -> 0
A35: 26 | C35: 46329 | D35: 过承祁 | I35: =I34+H35 -> 3920 | Q35: =O35-P35 -> 0 | R35: =R34+O35-P35 -> 0
A36: 27 | C36: 46330 | D36: 郑江宏 | I36: =I35+H36 -> 3920 | Q36: =O36-P36 -> 0 | R36: =R35+O36-P36 -> 0
A37: 28 | C37: 46338 | D37: 姜志鸿 | I37: =I36+H37 -> 3920 | Q37: =O37-P37 -> 0 | R37: =R36+O37-P37 -> 0
A38: 29 | C38: 46338 | D38: 吴旭红 | I38: =I37+H38 -> 3920 | Q38: =O38-P38 -> 0 | R38: =R37+O38-P38 -> 0
A39: 30 | C39: 46342 | D39: 丁爱妹 | I39: =I38+H39 -> 3920 | Q39: =O39-P39 -> 0 | R39: =R38+O39-P39 -> 0
A40: 31 | C40: 46351 | D40: 鄢桂香 | I40: =I39+H40 -> 3920 | Q40: =O40-P40 -> 0 | R40: =R39+O40-P40 -> 0
A41: 32 | C41: 46353 | D41: 傅荣姣 | I41: =I40+H41 -> 3920 | Q41: =O41-P41 -> 0 | R41: =R40+O41-P41 -> 0
A42: 33 | C42: 46354 | D42: 陆玉英 | I42: =I41+H42 -> 3920 | Q42: =O42-P42 -> 0 | R42: =R41+O42-P42 -> 0
A43: 34 | C43: 46361 | D43: 祝晓琳 | I43: =I42+H43 -> 3920 | Q43: =O43-P43 -> 0 | R43: =R42+O43-P43 -> 0
A44: 35 | C44: 46362 | D44: 章小英 | I44: =I43+H44 -> 3920 | Q44: =O44-P44 -> 0 | R44: =R43+O44-P44 -> 0
A45: 36 | C45: 10 | D45: 赵庆仙 | I45: =I44+H45 -> 3920 | Q45: =O45-P45 -> 0 | R45: =R44+O45-P45 -> 0
A46: 37 | I46: =I45+H46 -> 3920 | Q46: =O46-P46 -> 0 | R46: =R45+O46-P46 -> 0
A47: 38 | Q47: =O47-P47 -> 0 | R47: =R46+O47-P47 -> 0
A48: 39 | H48: =F48-G48 -> 0 | I48: =I47+H48 -> 0 | Q48: =O48-P48 -> 0 | R48: =R47+O48-P48 -> 0
A49: 40 | H49: =F49-G49 -> 0 | I49: =I48+H49 -> 0 | Q49: =O49-P49 -> 0 | R49: =R48+O49-P49 -> 0
A50: 41 | H50: =F50-G50 -> 0 | I50: =I49+H50 -> 0 | Q50: =O50-P50 -> 0 | R50: =R49+O50-P50 -> 0
A51: 42 | H51: =F51-G51 -> 0 | I51: =I50+H51 -> 0 | Q51: =O51-P51 -> 0 | R51: =R50+O51-P51 -> 0
A52: 43 | H52: =F52-G52 -> 0 | I52: =I51+H52 -> 0 | Q52: =O52-P52 -> 0 | R52: =R51+O52-P52 -> 0
A53: 44 | H53: =F53-G53 -> 0 | I53: =I52+H53 -> 0 | Q53: =O53-P53 -> 0 | R53: =R52+O53-P53 -> 0
A54: 45 | H54: =F54-G54 -> 0 | I54: =I53+H54 -> 0 | Q54: =O54-P54 -> 0 | R54: =R53+O54-P54 -> 0
A55: 46 | H55: =F55-G55 -> 0 | I55: =I54+H55 -> 0 | Q55: =O55-P55 -> 0 | R55: =R54+O55-P55 -> 0
A56: 47 | H56: =F56-G56 -> 0 | I56: =I55+H56 -> 0 | Q56: =O56-P56 -> 0 | R56: =R55+O56-P56 -> 0
A57: 48 | H57: =F57-G57 -> 0 | I57: =I56+H57 -> 0 | Q57: =O57-P57 -> 0 | R57: =R56+O57-P57 -> 0
A58: 49 | H58: =F58-G58 -> 0 | I58: =I57+H58 -> 0 | Q58: =O58-P58 -> 0 | R58: =R57+O58-P58 -> 0
A59: 50 | H59: =F59-G59 -> 0 | I59: =I58+H59 -> 0 | Q59: =O59-P59 -> 0 | R59: =R58+O59-P59 -> 0
... A501: 492 | H501: =F501-G501 -> 0 | I501: =I500+H501 -> 0 | Q501: =O501-P501 -> 0 | R501: =R500+O501-P501 -> 0
A502: 493
A503: 494
A504: 495
A505: 496
A506: 497
A507: 498
A508: 499
A509: 500

Sheet 汇报表
A1: 资金日报统计表（任意连续日期 / 单独一天查询）
A2: 起始日期 | B2: 46266 | D2: 截止日期 | E2: 46295 | G2: 查询天数 | H2: =IF(OR($B$2="",$E$2=""),"",IF($E$2<$B$2,"日期错误",IF($E$2-$B$2+1>31,"超过31天",$E$2-$B$2+1))) -> 30
A3: 提示：修改黄色日期即可查询；单独一天时起始日期=截止日期；默认展开31天，超过31天建议按月分段查询。
A4: 公司期初余额 | C4: 期间收款合计 | E4: 期间付款合计 | G4: 期末结余金额
B5: =SUM(B8:B21) -> 0 | D5: =SUM(BM8:BM21) -> 22200 | F5: =SUM(BN8:BN21) -> 11660 | H5: =SUM(BO8:BO21) -> 10540
C6: =IF(1<=MIN($H$2,31),$B$2+0,"") -> 46266 | D6: =IF(1<=MIN($H$2,31),$B$2+0,"") -> 46266 | E6: =IF(2<=MIN($H$2,31),$B$2+1,"") -> 46267 | F6: =IF(2<=MIN($H$2,31),$B$2+1,"") -> 46267 | G6: =IF(3<=MIN($H$2,31),$B$2+2,"") -> 46268 | H6: =IF(3<=MIN($H$2,31),$B$2+2,"") -> 46268 | I6: =IF(4<=MIN($H$2,31),$B$2+3,"") -> 46269 | J6: =IF(4<=MIN($H$2,31),$B$2+3,"") -> 46269 | K6: =IF(5<=MIN($H$2,31),$B$2+4,"") -> 46270 | L6: =IF(5<=MIN($H$2,31),$B$2+4,"") -> 46270 | M6: =IF(6<=MIN($H$2,31),$B$2+5,"") -> 46271 | N6: =IF(6<=MIN($H$2,31),$B$2+5,"") -> 46271 | O6: =IF(7<=MIN($H$2,31),$B$2+6,"") -> 46272 | P6: =IF(7<=MIN($H$2,31),$B$2+6,"") -> 46272 | Q6: =IF(8<=MIN($H$2,31),$B$2+7,"") -> 46273 | R6: =IF(8<=MIN($H$2,31),$B$2+7,"") -> 46273 | S6: =IF(9<=MIN($H$2,31),$B$2+8,"") -> 46274 | T6: =IF(9<=MIN($H$2,31),$B$2+8,"") -> 46274 | U6: =IF(10<=MIN($H$2,31),$B$2+9,"") -> 46275 | V6: =IF(10<=MIN($H$2,31),$B$2+9,"") -> 46275 | W6: =IF(11<=MIN($H$2,31),$B$2+10,"") -> 46276 | X6: =IF(11<=MIN($H$2,31),$B$2+10,"") -> 46276 | Y6: =IF(12<=MIN($H$2,31),$B$2+11,"") -> 46277 | Z6: =IF(12<=MIN($H$2,31),$B$2+11,"") -> 46277 | AA6: =IF(13<=MIN($H$2,31),$B$2+12,"") -> 46278 | AB6: =IF(13<=MIN($H$2,31),$B$2+12,"") -> 46278 | AC6: =IF(14<=MIN($H$2,31),$B$2+13,"") -> 46279 | AD6: =IF(14<=MIN($H$2,31),$B$2+13,"") -> 46279 | AE6: =IF(15<=MIN($H$2,31),$B$2+14,"") -> 46280 | AF6: =IF(15<=MIN($H$2,31),$B$2+14,"") -> 46280 | AG6: =IF(16<=MIN($H$2,31),$B$2+15,"") -> 46281 | AH6: =IF(16<=MIN($H$2,31),$B$2+15,"") -> 46281 | AI6: =IF(17<=MIN($H$2,31),$B$2+16,"") -> 46282 | AJ6: =IF(17<=MIN($H$2,31),$B$2+16,"") -> 46282 | AK6: =IF(18<=MIN($H$2,31),$B$2+17,"") -> 46283 | AL6: =IF(18<=MIN($H$2,31),$B$2+17,"") -> 46283 | AM6: =IF(19<=MIN($H$2,31),$B$2+18,"") -> 46284 | AN6: =IF(19<=MIN($H$2,31),$B$2+18,"") -> 46284 | AO6: =IF(20<=MIN($H$2,31),$B$2+19,"") -> 46285 | AP6: =IF(20<=MIN($H$2,31),$B$2+19,"") -> 46285 | AQ6: =IF(21<=MIN($H$2,31),$B$2+20,"") -> 46286 | AR6: =IF(21<=MIN($H$2,31),$B$2+20,"") -> 46286 | AS6: =IF(22<=MIN($H$2,31),$B$2+21,"") -> 46287 | AT6: =IF(22<=MIN($H$2,31),$B$2+21,"") -> 46287 | AU6: =IF(23<=MIN($H$2,31),$B$2+22,"") -> 46288 | AV6: =IF(23<=MIN($H$2,31),$B$2+22,"") -> 46288 | AW6: =IF(24<=MIN($H$2,31),$B$2+23,"") -> 46289 | AX6: =IF(24<=MIN($H$2,31),$B$2+23,"") -> 46289 | AY6: =IF(25<=MIN($H$2,31),$B$2+24,"") -> 46290 | AZ6: =IF(25<=MIN($H$2,31),$B$2+24,"") -> 46290 | BA6: =IF(26<=MIN($H$2,31),$B$2+25,"") -> 46291 | BB6: =IF(26<=MIN($H$2,31),$B$2+25,"") -> 46291 | BC6: =IF(27<=MIN($H$2,31),$B$2+26,"") -> 46292 | BD6: =IF(27<=MIN($H$2,31),$B$2+26,"") -> 46292 | BE6: =IF(28<=MIN($H$2,31),$B$2+27,"") -> 46293 | BF6: =IF(28<=MIN($H$2,31),$B$2+27,"") -> 46293 | BG6: =IF(29<=MIN($H$2,31),$B$2+28,"") -> 46294 | BH6: =IF(29<=MIN($H$2,31),$B$2+28,"") -> 46294 | BI6: =IF(30<=MIN($H$2,31),$B$2+29,"") -> 46295 | BJ6: =IF(30<=MIN($H$2,31),$B$2+29,"") -> 46295 | BK6: =IF(31<=MIN($H$2,31),$B$2+30,"") | BL6: =IF(31<=MIN($H$2,31),$B$2+30,"")
A7: 账户 | B7: 期初余额 | C7: =IF(C$6="","","收款") -> 收款 | D7: =IF(D$6="","","付款") -> 付款 | E7: =IF(E$6="","","收款") -> 收款 | F7: =IF(F$6="","","付款") -> 付款 | G7: =IF(G$6="","","收款") -> 收款 | H7: =IF(H$6="","","付款") -> 付款 | I7: =IF(I$6="","","收款") -> 收款 | J7: =IF(J$6="","","付款") -> 付款 | K7: =IF(K$6="","","收款") -> 收款 | L7: =IF(L$6="","","付款") -> 付款 | M7: =IF(M$6="","","收款") -> 收款 | N7: =IF(N$6="","","付款") -> 付款 | O7: =IF(O$6="","","收款") -> 收款 | P7: =IF(P$6="","","付款") -> 付款 | Q7: =IF(Q$6="","","收款") -> 收款 | R7: =IF(R$6="","","付款") -> 付款 | S7: =IF(S$6="","","收款") -> 收款 | T7: =IF(T$6="","","付款") -> 付款 | U7: =IF(U$6="","","收款") -> 收款 | V7: =IF(V$6="","","付款") -> 付款 | W7: =IF(W$6="","","收款") -> 收款 | X7: =IF(X$6="","","付款") -> 付款 | Y7: =IF(Y$6="","","收款") -> 收款 | Z7: =IF(Z$6="","","付款") -> 付款 | AA7: =IF(AA$6="","","收款") -> 收款 | AB7: =IF(AB$6="","","付款") -> 付款 | AC7: =IF(AC$6="","","收款") -> 收款 | AD7: =IF(AD$6="","","付款") -> 付款 | AE7: =IF(AE$6="","","收款") -> 收款 | AF7: =IF(AF$6="","","付款") -> 付款 | AG7: =IF(AG$6="","","收款") -> 收款 | AH7: =IF(AH$6="","","付款") -> 付款 | AI7: =IF(AI$6="","","收款") -> 收款 | AJ7: =IF(AJ$6="","","付款") -> 付款 | AK7: =IF(AK$6="","","收款") -> 收款 | AL7: =IF(AL$6="","","付款") -> 付款 | AM7: =IF(AM$6="","","收款") -> 收款 | AN7: =IF(AN$6="","","付款") -> 付款 | AO7: =IF(AO$6="","","收款") -> 收款 | AP7: =IF(AP$6="","","付款") -> 付款 | AQ7: =IF(AQ$6="","","收款") -> 收款 | AR7: =IF(AR$6="","","付款") -> 付款 | AS7: =IF(AS$6="","","收款") -> 收款 | AT7: =IF(AT$6="","","付款") -> 付款 | AU7: =IF(AU$6="","","收款") -> 收款 | AV7: =IF(AV$6="","","付款") -> 付款 | AW7: =IF(AW$6="","","收款") -> 收款 | AX7: =IF(AX$6="","","付款") -> 付款 | AY7: =IF(AY$6="","","收款") -> 收款 | AZ7: =IF(AZ$6="","","付款") -> 付款 | BA7: =IF(BA$6="","","收款") -> 收款 | BB7: =IF(BB$6="","","付款") -> 付款 | BC7: =IF(BC$6="","","收款") -> 收款 | BD7: =IF(BD$6="","","付款") -> 付款 | BE7: =IF(BE$6="","","收款") -> 收款 | BF7: =IF(BF$6="","","付款") -> 付款 | BG7: =IF(BG$6="","","收款") -> 收款 | BH7: =IF(BH$6="","","付款") -> 付款 | BI7: =IF(BI$6="","","收款") -> 收款 | BJ7: =IF(BJ$6="","","付款") -> 付款 | BK7: =IF(BK$6="","","收款") | BL7: =IF(BL$6="","","付款") | BM7: 收款合计 | BN7: 付款合计 | BO7: 期末余额
A8: 现金 | B8: =IF(OR($A8="",NOT(ISNUMBER($H$2))),"",SUMIFS(数据录入!$H$5:$H$4999,数据录入!$C$5:$C$4999,$A8,数据录入!$E$5:$E$4999,"期初余额",数据录入!$B$5:$B$4999,"<="&$B$2)+SUMIFS(数据录入!$F$5:$F$4999,数据录入!$C$5:$C$4999,$A8,数据录入!$B$5:$B$4999,"<"&$B$2)-SUMIFS(数据录入!$G$5:$G$4999,数据录入!$C$5:$C$4999,$A8,数据录入!$B$5:$B$4999,"<"&$B$2)) -> 0 | C8: =IF(OR($A8="",C$6="",NOT(ISNUMBER($H$2))),"",SUMIFS(数据录入!$F$5:$F$4999,数据录入!$C$5:$C$4999,$A8,数据录入!$B$5:$B$4999,C$6)) -> 2000 | D8: =IF(OR($A8="",D$6="",NOT(ISNUMBER($H$2))),"",SUMIFS(数据录入!$G$5:$G$4999,数据录入!$C$5:$C$4999,$A8,数据录入!$B$5:$B$4999,D$6)) -> 200 | E8: =IF(OR($A8="",E$6="",NOT(ISNUMBER($H$2))),"",SUMIFS(数据录入!$F$5:$F$4999,数据录入!$C$5:$C$4999,$A8,数据录入!$B$5:$B$4999,E$6)) -> 0 | F8: =IF(OR($A8="",F$6="",NOT(ISNUMBER($H$2))),"",SUMIFS(数据录入!$G$5:$G$4999,数据录入!$C$5:$C$4999,$A8,数据录入!$B$5:$B$4999,F$6)) -> 0 | G8: =IF(OR($A8="",G$6="",NOT(ISNUMBER($H$2))),"",SUMIFS(数据录入!$F$5:$F$4999,数据录入!$C$5:$C$4999,$A8,数据录入!$B$5:$B$4999,G$6)) -> 0 | H8: =IF(OR($A8="",H$6="",NOT(ISNUMBER($H$2))),"",SUMIFS(数据录入!$G$5:$G$4999,数据录入!$C$5:$C$4999,$A8,数据录入!$B$5:$B$4999,H$6)) -> 0 | I8: =IF(OR($A8="",I$6="",NOT(ISNUMBER($H$2))),"",SUMIFS(数据录入!$F$5:$F$4999,数据录入!$C$5:$C$4999,$A8,数据录入!$B$5:$B$4999,I$6)) -> 0 | J8: =IF(OR($A8="",J$6="",NOT(ISNUMBER($H$2))),"",SUMIFS(数据录入!$G$5:$G$4999,数据录入!$C$5:$C$4999,$A8,数据录入!$B$5:$B$4999,J$6)) -> 0 | K8: =IF(OR($A8="",K$6="",NOT(ISNUMBER($H$2))),"",SUMIFS(数据录入!$F$5:$F$4999,数据录入!$C$5:$C$4999,$A8,数据录入!$B$5:$B$4999,K$6)) -> 0 | L8: =IF(OR($A8="",L$6="",NOT(ISNUMBER($H$2))),"",SUMIFS(数据录入!$G$5:$G$4999,数据录入!$C$5:$C$4999,$A8,数据录入!$B$5:$B$4999,L$6)) -> 0 | M8: =IF(OR($A8="",M$6="",NOT(ISNUMBER($H$2))),"",SUMIFS(数据录入!$F$5:$F$4999,数据录入!$C$5:$C$4999,$A8,数据录入!$B$5:$B$4999,M$6)) -> 0 | N8: =IF(OR($A8="",N$6="",NOT(ISNUMBER($H$2))),"",SUMIFS(数据录入!$G$5:$G$4999,数据录入!$C$5:$C$4999,$A8,数据录入!$B$5:$B$4999,N$6)) -> 0 | O8: =IF(OR($A8="",O$6="",NOT(ISNUMBER($H$2))),"",SUMIFS(数据录入!$F$5:$F$4999,数据录入!$C$5:$C$4999,$A8,数据录入!$B$5:$B$4999,O$6)) -> 0 | P8: =IF(OR($A8="",P$6="",NOT(ISNUMBER($H$2))),"",SUMIFS(数据录入!$G$5:$G$4999,数据录入!$C$5:$C$4999,$A8,数据录入!$B$5:$B$4999,P$6)) -> 0 | Q8: =IF(OR($A8="",Q$6="",NOT(ISNUMBER($H$2))),"",SUMIFS(数据录入!$F$5:$F$4999,数据录入!$C$5:$C$4999,$A8,数据录入!$B$5:$B$4999,Q$6)) -> 0 | R8: =IF(OR($A8="",R$6="",NOT(ISNUMBER($H$2))),"",SUMIFS(数据录入!$G$5:$G$4999,数据录入!$C$5:$C$4999,$A8,数据录入!$B$5:$B$4999,R$6)) -> 0 | S8: =IF(OR($A8="",S$6="",NOT(ISNUMBER($H$2))),"",SUMIFS(数据录入!$F$5:$F$4999,数据录入!$C$5:$C$4999,$A8,数据录入!$B$5:$B$4999,S$6)) -> 0 | T8: =IF(OR($A8="",T$6="",NOT(ISNUMBER($H$2))),"",SUMIFS(数据录入!$G$5:$G$4999,数据录入!$C$5:$C$4999,$A8,数据录入!$B$5:$B$4999,T$6)) -> 0 | U8: =IF(OR($A8="",U$6="",NOT(ISNUMBER($H$2))),"",SUMIFS(数据录入!$F$5:$F$4999,数据录入!$C$5:$C$4999,$A8,数据录入!$B$5:$B$4999,U$6)) -> 0 | V8: =IF(OR($A8="",V$6="",NOT(ISNUMBER($H$2))),"",SUMIFS(数据录入!$G$5:$G$4999,数据录入!$C$5:$C$4999,$A8,数据录入!$B$5:$B$4999,V$6)) -> 0 | W8: =IF(OR($A8="",W$6="",NOT(ISNUMBER($H$2))),"",SUMIFS(数据录入!$F$5:$F$4999,数据录入!$C$5:$C$4999,$A8,数据录入!$B$5:$B$4999,W$6)) -> 0 | X8: =IF(OR($A8="",X$6="",NOT(ISNUMBER($H$2))),"",SUMIFS(数据录入!$G$5:$G$4999,数据录入!$C$5:$C$4999,$A8,数据录入!$B$5:$B$4999,X$6)) -> 0 | Y8: =IF(OR($A8="",Y$6="",NOT(ISNUMBER($H$2))),"",SUMIFS(数据录入!$F$5:$F$4999,数据录入!$C$5:$C$4999,$A8,数据录入!$B$5:$B$4999,Y$6)) -> 0 | Z8: =IF(OR($A8="",Z$6="",NOT(ISNUMBER($H$2))),"",SUMIFS(数据录入!$G$5:$G$4999,数据录入!$C$5:$C$4999,$A8,数据录入!$B$5:$B$4999,Z$6)) -> 0 | AA8: =IF(OR($A8="",AA$6="",NOT(ISNUMBER($H$2))),"",SUMIFS(数据录入!$F$5:$F$4999,数据录入!$C$5:$C$4999,$A8,数据录入!$B$5:$B$4999,AA$6)) -> 0 | AB8: =IF(OR($A8="",AB$6="",NOT(ISNUMBER($H$2))),"",SUMIFS(数据录入!$G$5:$G$4999,数据录入!$C$5:$C$4999,$A8,数据录入!$B$5:$B$4999,AB$6)) -> 0 | AC8: =IF(OR($A8="",AC$6="",NOT(ISNUMBER($H$2))),"",SUMIFS(数据录入!$F$5:$F$4999,数据录入!$C$5:$C$4999,$A8,数据录入!$B$5:$B$4999,AC$6)) -> 0 | AD8: =IF(OR($A8="",AD$6="",NOT(ISNUMBER($H$2))),"",SUMIFS(数据录入!$G$5:$G$4999,数据录入!$C$5:$C$4999,$A8,数据录入!$B$5:$B$4999,AD$6)) -> 0 | AE8: =IF(OR($A8="",AE$6="",NOT(ISNUMBER($H$2))),"",SUMIFS(数据录入!$F$5:$F$4999,数据录入!$C$5:$C$4999,$A8,数据录入!$B$5:$B$4999,AE$6)) -> 0 | AF8: =IF(OR($A8="",AF$6="",NOT(ISNUMBER($H$2))),"",SUMIFS(数据录入!$G$5:$G$4999,数据录入!$C$5:$C$4999,$A8,数据录入!$B$5:$B$4999,AF$6)) -> 0 | AG8: =IF(OR($A8="",AG$6="",NOT(ISNUMBER($H$2))),"",SUMIFS(数据录入!$F$5:$F$4999,数据录入!$C$5:$C$4999,$A8,数据录入!$B$5:$B$4999,AG$6)) -> 0 | AH8: =IF(OR($A8="",AH$6="",NOT(ISNUMBER($H$2))),"",SUMIFS(数据录入!$G$5:$G$4999,数据录入!$C$5:$C$4999,$A8,数据录入!$B$5:$B$4999,AH$6)) -> 0 | AI8: =IF(OR($A8="",AI$6="",NOT(ISNUMBER($H$2))),"",SUMIFS(数据录入!$F$5:$F$4999,数据录入!$C$5:$C$4999,$A8,数据录入!$B$5:$B$4999,AI$6)) -> 0 | AJ8: =IF(OR($A8="",AJ$6="",NOT(ISNUMBER($H$2))),"",SUMIFS(数据录入!$G$5:$G$4999,数据录入!$C$5:$C$4999,$A8,数据录入!$B$5:$B$4999,AJ$6)) -> 0 | AK8: =IF(OR($A8="",AK$6="",NOT(ISNUMBER($H$2))),"",SUMIFS(数据录入!$F$5:$F$4999,数据录入!$C$5:$C$4999,$A8,数据录入!$B$5:$B$4999,AK$6)) -> 0 | AL8: =IF(OR($A8="",AL$6="",NOT(ISNUMBER($H$2))),"",SUMIFS(数据录入!$G$5:$G$4999,数据录入!$C$5:$C$4999,$A8,数据录入!$B$5:$B$4999,AL$6)) -> 0 | AM8: =IF(OR($A8="",AM$6="",NOT(ISNUMBER($H$2))),"",SUMIFS(数据录入!$F$5:$F$4999,数据录入!$C$5:$C$4999,$A8,数据录入!$B$5:$B$4999,AM$6)) -> 0 | AN8: =IF(OR($A8="",AN$6="",NOT(ISNUMBER($H$2))),"",SUMIFS(数据录入!$G$5:$G$4999,数据录入!$C$5:$C$4999,$A8,数据录入!$B$5:$B$4999,AN$6)) -> 0 | AO8: =IF(OR($A8="",AO$6="",NOT(ISNUMBER($H$2))),"",SUMIFS(数据录入!$F$5:$F$4999,数据录入!$C$5:$C$4999,$A8,数据录入!$B$5:$B$4999,AO$6)) -> 0 | AP8: =IF(OR($A8="",AP$6="",NOT(ISNUMBER($H$2))),"",SUMIFS(数据录入!$G$5:$G$4999,数据录入!$C$5:$C$4999,$A8,数据录入!$B$5:$B$4999,AP$6)) -> 0 | AQ8: =IF(OR($A8="",AQ$6="",NOT(ISNUMBER($H$2))),"",SUMIFS(数据录入!$F$5:$F$4999,数据录入!$C$5:$C$4999,$A8,数据录入!$B$5:$B$4999,AQ$6)) -> 0 | AR8: =IF(OR($A8="",AR$6="",NOT(ISNUMBER($H$2))),"",SUMIFS(数据录入!$G$5:$G$4999,数据录入!$C$5:$C$4999,$A8,数据录入!$B$5:$B$4999,AR$6)) -> 0 | AS8: =IF(OR($A8="",AS$6="",NOT(ISNUMBER($H$2))),"",SUMIFS(数据录入!$F$5:$F$4999,数据录入!$C$5:$C$4999,$A8,数据录入!$B$5:$B$4999,AS$6)) -> 0 | AT8: =IF(OR($A8="",AT$6="",NOT(ISNUMBER($H$2))),"",SUMIFS(数据录入!$G$5:$G$4999,数据录入!$C$5:$C$4999,$A8,数据录入!$B$5:$B$4999,AT$6)) -> 0 | AU8: =IF(OR($A8="",AU$6="",NOT(ISNUMBER($H$2))),"",SUMIFS(数据录入!$F$5:$F$4999,数据录入!$C$5:$C$4999,$A8,数据录入!$B$5:$B$4999,AU$6)) -> 0 | AV8: =IF(OR($A8="",AV$6="",NOT(ISNUMBER($H$2))),"",SUMIFS(数据录入!$G$5:$G$4999,数据录入!$C$5:$C$4999,$A8,数据录入!$B$5:$B$4999,AV$6)) -> 0 | AW8: =IF(OR($A8="",AW$6="",NOT(ISNUMBER($H$2))),"",SUMIFS(数据录入!$F$5:$F$4999,数据录入!$C$5:$C$4999,$A8,数据录入!$B$5:$B$4999,AW$6)) -> 0 | AX8: =IF(OR($A8="",AX$6="",NOT(ISNUMBER($H$2))),"",SUMIFS(数据录入!$G$5:$G$4999,数据录入!$C$5:$C$4999,$A8,数据录入!$B$5:$B$4999,AX$6)) -> 0 | AY8: =IF(OR($A8="",AY$6="",NOT(ISNUMBER($H$2))),"",SUMIFS(数据录入!$F$5:$F$4999,数据录入!$C$5:$C$4999,$A8,数据录入!$B$5:$B$4999,AY$6)) -> 0 | AZ8: =IF(OR($A8="",AZ$6="",NOT(ISNUMBER($H$2))),"",SUMIFS(数据录入!$G$5:$G$4999,数据录入!$C$5:$C$4999,$A8,数据录入!$B$5:$B$4999,AZ$6)) -> 0 | BA8: =IF(OR($A8="",BA$6="",NOT(ISNUMBER($H$2))),"",SUMIFS(数据录入!$F$5:$F$4999,数据录入!$C$5:$C$4999,$A8,数据录入!$B$5:$B$4999,BA$6)) -> 0 | BB8: =IF(OR($A8="",BB$6="",NOT(ISNUMBER($H$2))),"",SUMIFS(数据录入!$G$5:$G$4999,数据录入!$C$5:$C$4999,$A8,数据录入!$B$5:$B$4999,BB$6)) -> 0 | BC8: =IF(OR($A8="",BC$6="",NOT(ISNUMBER($H$2))),"",SUMIFS(数据录入!$F$5:$F$4999,数据录入!$C$5:$C$4999,$A8,数据录入!$B$5:$B$4999,BC$6)) -> 0 | BD8: =IF(OR($A8="",BD$6="",NOT(ISNUMBER($H$2))),"",SUMIFS(数据录入!$G$5:$G$4999,数据录入!$C$5:$C$4999,$A8,数据录入!$B$5:$B$4999,BD$6)) -> 0 | BE8: =IF(OR($A8="",BE$6="",NOT(ISNUMBER($H$2))),"",SUMIFS(数据录入!$F$5:$F$4999,数据录入!$C$5:$C$4999,$A8,数据录入!$B$5:$B$4999,BE$6)) -> 0 | BF8: =IF(OR($A8="",BF$6="",NOT(ISNUMBER($H$2))),"",SUMIFS(数据录入!$G$5:$G$4999,数据录入!$C$5:$C$4999,$A8,数据录入!$B$5:$B$4999,BF$6)) -> 0 | BG8: =IF(OR($A8="",BG$6="",NOT(ISNUMBER($H$2))),"",SUMIFS(数据录入!$F$5:$F$4999,数据录入!$C$5:$C$4999,$A8,数据录入!$B$5:$B$4999,BG$6)) -> 0 | BH8: =IF(OR($A8="",BH$6="",NOT(ISNUMBER($H$2))),"",SUMIFS(数据录入!$G$5:$G$4999,数据录入!$C$5:$C$4999,$A8,数据录入!$B$5:$B$4999,BH$6)) -> 0 | BI8: =IF(OR($A8="",BI$6="",NOT(ISNUMBER($H$2))),"",SUMIFS(数据录入!$F$5:$F$4999,数据录入!$C$5:$C$4999,$A8,数据录入!$B$5:$B$4999,BI$6)) -> 0 | BJ8: =IF(OR($A8="",BJ$6="",NOT(ISNUMBER($H$2))),"",SUMIFS(数据录入!$G$5:$G$4999,数据录入!$C$5:$C$4999,$A8,数据录入!$B$5:$B$4999,BJ$6)) -> 0 | BK8: =IF(OR($A8="",BK$6="",NOT(ISNUMBER($H$2))),"",SUMIFS(数据录入!$F$5:$F$4999,数据录入!$C$5:$C$4999,$A8,数据录入!$B$5:$B$4999,BK$6)) | BL8: =IF(OR($A8="",BL$6="",NOT(ISNUMBER($H$2))),"",SUMIFS(数据录入!$G$5:$G$4999,数据录入!$C$5:$C$4999,$A8,数据录入!$B$5:$B$4999,BL$6)) | BM8: =IF($A8="","",SUMIF($C$7:$BL$7,"收款",C8:BL8)) -> 2000 | BN8: =IF($A8="","",SUMIF($C$7:$BL$7,"付款",C8:BL8)) -> 200 | BO8: =IF($A8="","",B8+BM8-BN8) -> 1800
A9: 微信 | B9: =IF(OR($A9="",NOT(ISNUMBER($H$2))),"",SUMIFS(数据录入!$H$5:$H$4999,数据录入!$C$5:$C$4999,$A9,数据录入!$E$5:$E$4999,"期初余额",数据录入!$B$5:$B$4999,"<="&$B$2)+SUMIFS(数据录入!$F$5:$F$4999,数据录入!$C$5:$C$4999,$A9,数据录入!$B$5:$B$4999,"<"&$B$2)-SUMIFS(数据录入!$G$5:$G$4999,数据录入!$C$5:$C$4999,$A9,数据录入!$B$5:$B$4999,"<"&$B$2)) -> 0 | C9: =IF(OR($A9="",C$6="",NOT(ISNUMBER($H$2))),"",SUMIFS(数据录入!$F$5:$F$4999,数据录入!$C$5:$C$4999,$A9,数据录入!$B$5:$B$4999,C$6)) -> 0 | D9: =IF(OR($A9="",D$6="",NOT(ISNUMBER($H$2))),"",SUMIFS(数据录入!$G$5:$G$4999,数据录入!$C$5:$C$4999,$A9,数据录入!$B$5:$B$4999,D$6)) -> 700 | E9: =IF(OR($A9="",E$6="",NOT(ISNUMBER($H$2))),"",SUMIFS(数据录入!$F$5:$F$4999,数据录入!$C$5:$C$4999,$A9,数据录入!$B$5:$B$4999,E$6)) -> 0 | F9: =IF(OR($A9="",F$6="",NOT(ISNUMBER($H$2))),"",SUMIFS(数据录入!$G$5:$G$4999,数据录入!$C$5:$C$4999,$A9,数据录入!$B$5:$B$4999,F$6)) -> 0 | G9: =IF(OR($A9="",G$6="",NOT(ISNUMBER($H$2))),"",SUMIFS(数据录入!$F$5:$F$4999,数据录入!$C$5:$C$4999,$A9,数据录入!$B$5:$B$4999,G$6)) -> 0 | H9: =IF(OR($A9="",H$6="",NOT(ISNUMBER($H$2))),"",SUMIFS(数据录入!$G$5:$G$4999,数据录入!$C$5:$C$4999,$A9,数据录入!$B$5:$B$4999,H$6)) -> 0 | I9: =IF(OR($A9="",I$6="",NOT(ISNUMBER($H$2))),"",SUMIFS(数据录入!$F$5:$F$4999,数据录入!$C$5:$C$4999,$A9,数据录入!$B$5:$B$4999,I$6)) -> 0 | J9: =IF(OR($A9="",J$6="",NOT(ISNUMBER($H$2))),"",SUMIFS(数据录入!$G$5:$G$4999,数据录入!$C$5:$C$4999,$A9,数据录入!$B$5:$B$4999,J$6)) -> 0 | K9: =IF(OR($A9="",K$6="",NOT(ISNUMBER($H$2))),"",SUMIFS(数据录入!$F$5:$F$4999,数据录入!$C$5:$C$4999,$A9,数据录入!$B$5:$B$4999,K$6)) -> 0 | L9: =IF(OR($A9="",L$6="",NOT(ISNUMBER($H$2))),"",SUMIFS(数据录入!$G$5:$G$4999,数据录入!$C$5:$C$4999,$A9,数据录入!$B$5:$B$4999,L$6)) -> 0 | M9: =IF(OR($A9="",M$6="",NOT(ISNUMBER($H$2))),"",SUMIFS(数据录入!$F$5:$F$4999,数据录入!$C$5:$C$4999,$A9,数据录入!$B$5:$B$4999,M$6)) -> 0 | N9: =IF(OR($A9="",N$6="",NOT(ISNUMBER($H$2))),"",SUMIFS(数据录入!$G$5:$G$4999,数据录入!$C$5:$C$4999,$A9,数据录入!$B$5:$B$4999,N$6)) -> 0 | O9: =IF(OR($A9="",O$6="",NOT(ISNUMBER($H$2))),"",SUMIFS(数据录入!$F$5:$F$4999,数据录入!$C$5:$C$4999,$A9,数据录入!$B$5:$B$4999,O$6)) -> 0 | P9: =IF(OR($A9="",P$6="",NOT(ISNUMBER($H$2))),"",SUMIFS(数据录入!$G$5:$G$4999,数据录入!$C$5:$C$4999,$A9,数据录入!$B$5:$B$4999,P$6)) -> 0 | Q9: =IF(OR($A9="",Q$6="",NOT(ISNUMBER($H$2))),"",SUMIFS(数据录入!$F$5:$F$4999,数据录入!$C$5:$C$4999,$A9,数据录入!$B$5:$B$4999,Q$6)) -> 0 | R9: =IF(OR($A9="",R$6="",NOT(ISNUMBER($H$2))),"",SUMIFS(数据录入!$G$5:$G$4999,数据录入!$C$5:$C$4999,$A9,数据录入!$B$5:$B$4999,R$6)) -> 0 | S9: =IF(OR($A9="",S$6="",NOT(ISNUMBER($H$2))),"",SUMIFS(数据录入!$F$5:$F$4999,数据录入!$C$5:$C$4999,$A9,数据录入!$B$5:$B$4999,S$6)) -> 0 | T9: =IF(OR($A9="",T$6="",NOT(ISNUMBER($H$2))),"",SUMIFS(数据录入!$G$5:$G$4999,数据录入!$C$5:$C$4999,$A9,数据录入!$B$5:$B$4999,T$6)) -> 0 | U9: =IF(OR($A9="",U$6="",NOT(ISNUMBER($H$2))),"",SUMIFS(数据录入!$F$5:$F$4999,数据录入!$C$5:$C$4999,$A9,数据录入!$B$5:$B$4999,U$6)) -> 0 | V9: =IF(OR($A9="",V$6="",NOT(ISNUMBER($H$2))),"",SUMIFS(数据录入!$G$5:$G$4999,数据录入!$C$5:$C$4999,$A9,数据录入!$B$5:$B$4999,V$6)) -> 0 | W9: =IF(OR($A9="",W$6="",NOT(ISNUMBER($H$2))),"",SUMIFS(数据录入!$F$5:$F$4999,数据录入!$C$5:$C$4999,$A9,数据录入!$B$5:$B$4999,W$6)) -> 0 | X9: =IF(OR($A9="",X$6="",NOT(ISNUMBER($H$2))),"",SUMIFS(数据录入!$G$5:$G$4999,数据录入!$C$5:$C$4999,$A9,数据录入!$B$5:$B$4999,X$6)) -> 0 | Y9: =IF(OR($A9="",Y$6="",NOT(ISNUMBER($H$2))),"",SUMIFS(数据录入!$F$5:$F$4999,数据录入!$C$5:$C$4999,$A9,数据录入!$B$5:$B$4999,Y$6)) -> 0 | Z9: =IF(OR($A9="",Z$6="",NOT(ISNUMBER($H$2))),"",SUMIFS(数据录入!$G$5:$G$4999,数据录入!$C$5:$C$4999,$A9,数据录入!$B$5:$B$4999,Z$6)) -> 0 | AA9: =IF(OR($A9="",AA$6="",NOT(ISNUMBER($H$2))),"",SUMIFS(数据录入!$F$5:$F$4999,数据录入!$C$5:$C$4999,$A9,数据录入!$B$5:$B$4999,AA$6)) -> 0 | AB9: =IF(OR($A9="",AB$6="",NOT(ISNUMBER($H$2))),"",SUMIFS(数据录入!$G$5:$G$4999,数据录入!$C$5:$C$4999,$A9,数据录入!$B$5:$B$4999,AB$6)) -> 0 | AC9: =IF(OR($A9="",AC$6="",NOT(ISNUMBER($H$2))),"",SUMIFS(数据录入!$F$5:$F$4999,数据录入!$C$5:$C$4999,$A9,数据录入!$B$5:$B$4999,AC$6)) -> 0 | AD9: =IF(OR($A9="",AD$6="",NOT(ISNUMBER($H$2))),"",SUMIFS(数据录入!$G$5:$G$4999,数据录入!$C$5:$C$4999,$A9,数据录入!$B$5:$B$4999,AD$6)) -> 0 | AE9: =IF(OR($A9="",AE$6="",NOT(ISNUMBER($H$2))),"",SUMIFS(数据录入!$F$5:$F$4999,数据录入!$C$5:$C$4999,$A9,数据录入!$B$5:$B$4999,AE$6)) -> 0 | AF9: =IF(OR($A9="",AF$6="",NOT(ISNUMBER($H$2))),"",SUMIFS(数据录入!$G$5:$G$4999,数据录入!$C$5:$C$4999,$A9,数据录入!$B$5:$B$4999,AF$6)) -> 0 | AG9: =IF(OR($A9="",AG$6="",NOT(ISNUMBER($H$2))),"",SUMIFS(数据录入!$F$5:$F$4999,数据录入!$C$5:$C$4999,$A9,数据录入!$B$5:$B$4999,AG$6)) -> 0 | AH9: =IF(OR($A9="",AH$6="",NOT(ISNUMBER($H$2))),"",SUMIFS(数据录入!$G$5:$G$4999,数据录入!$C$5:$C$4999,$A9,数据录入!$B$5:$B$4999,AH$6)) -> 0 | AI9: =IF(OR($A9="",AI$6="",NOT(ISNUMBER($H$2))),"",SUMIFS(数据录入!$F$5:$F$4999,数据录入!$C$5:$C$4999,$A9,数据录入!$B$5:$B$4999,AI$6)) -> 0 | AJ9: =IF(OR($A9="",AJ$6="",NOT(ISNUMBER($H$2))),"",SUMIFS(数据录入!$G$5:$G$4999,数据录入!$C$5:$C$4999,$A9,数据录入!$B$5:$B$4999,AJ$6)) -> 0 | AK9: =IF(OR($A9="",AK$6="",NOT(ISNUMBER($H$2))),"",SUMIFS(数据录入!$F$5:$F$4999,数据录入!$C$5:$C$4999,$A9,数据录入!$B$5:$B$4999,AK$6)) -> 0 | AL9: =IF(OR($A9="",AL$6="",NOT(ISNUMBER($H$2))),"",SUMIFS(数据录入!$G$5:$G$4999,数据录入!$C$5:$C$4999,$A9,数据录入!$B$5:$B$4999,AL$6)) -> 0 | AM9: =IF(OR($A9="",AM$6="",NOT(ISNUMBER($H$2))),"",SUMIFS(数据录入!$F$5:$F$4999,数据录入!$C$5:$C$4999,$A9,数据录入!$B$5:$B$4999,AM$6)) -> 0 | AN9: =IF(OR($A9="",AN$6="",NOT(ISNUMBER($H$2))),"",SUMIFS(数据录入!$G$5:$G$4999,数据录入!$C$5:$C$4999,$A9,数据录入!$B$5:$B$4999,AN$6)) -> 0 | AO9: =IF(OR($A9="",AO$6="",NOT(ISNUMBER($H$2))),"",SUMIFS(数据录入!$F$5:$F$4999,数据录入!$C$5:$C$4999,$A9,数据录入!$B$5:$B$4999,AO$6)) -> 0 | AP9: =IF(OR($A9="",AP$6="",NOT(ISNUMBER($H$2))),"",SUMIFS(数据录入!$G$5:$G$4999,数据录入!$C$5:$C$4999,$A9,数据录入!$B$5:$B$4999,AP$6)) -> 0 | AQ9: =IF(OR($A9="",AQ$6="",NOT(ISNUMBER($H$2))),"",SUMIFS(数据录入!$F$5:$F$4999,数据录入!$C$5:$C$4999,$A9,数据录入!$B$5:$B$4999,AQ$6)) -> 0 | AR9: =IF(OR($A9="",AR$6="",NOT(ISNUMBER($H$2))),"",SUMIFS(数据录入!$G$5:$G$4999,数据录入!$C$5:$C$4999,$A9,数据录入!$B$5:$B$4999,AR$6)) -> 0 | AS9: =IF(OR($A9="",AS$6="",NOT(ISNUMBER($H$2))),"",SUMIFS(数据录入!$F$5:$F$4999,数据录入!$C$5:$C$4999,$A9,数据录入!$B$5:$B$4999,AS$6)) -> 0 | AT9: =IF(OR($A9="",AT$6="",NOT(ISNUMBER($H$2))),"",SUMIFS(数据录入!$G$5:$G$4999,数据录入!$C$5:$C$4999,$A9,数据录入!$B$5:$B$4999,AT$6)) -> 0 | AU9: =IF(OR($A9="",AU$6="",NOT(ISNUMBER($H$2))),"",SUMIFS(数据录入!$F$5:$F$4999,数据录入!$C$5:$C$4999,$A9,数据录入!$B$5:$B$4999,AU$6)) -> 0 | AV9: =IF(OR($A9="",AV$6="",NOT(ISNUMBER($H$2))),"",SUMIFS(数据录入!$G$5:$G$4999,数据录入!$C$5:$C$4999,$A9,数据录入!$B$5:$B$4999,AV$6)) -> 0 | AW9: =IF(OR($A9="",AW$6="",NOT(ISNUMBER($H$2))),"",SUMIFS(数据录入!$F$5:$F$4999,数据录入!$C$5:$C$4999,$A9,数据录入!$B$5:$B$4999,AW$6)) -> 0 | AX9: =IF(OR($A9="",AX$6="",NOT(ISNUMBER($H$2))),"",SUMIFS(数据录入!$G$5:$G$4999,数据录入!$C$5:$C$4999,$A9,数据录入!$B$5:$B$4999,AX$6)) -> 0 | AY9: =IF(OR($A9="",AY$6="",NOT(ISNUMBER($H$2))),"",SUMIFS(数据录入!$F$5:$F$4999,数据录入!$C$5:$C$4999,$A9,数据录入!$B$5:$B$4999,AY$6)) -> 0 | AZ9: =IF(OR($A9="",AZ$6="",NOT(ISNUMBER($H$2))),"",SUMIFS(数据录入!$G$5:$G$4999,数据录入!$C$5:$C$4999,$A9,数据录入!$B$5:$B$4999,AZ$6)) -> 0 | BA9: =IF(OR($A9="",BA$6="",NOT(ISNUMBER($H$2))),"",SUMIFS(数据录入!$F$5:$F$4999,数据录入!$C$5:$C$4999,$A9,数据录入!$B$5:$B$4999,BA$6)) -> 0 | BB9: =IF(OR($A9="",BB$6="",NOT(ISNUMBER($H$2))),"",SUMIFS(数据录入!$G$5:$G$4999,数据录入!$C$5:$C$4999,$A9,数据录入!$B$5:$B$4999,BB$6)) -> 0 | BC9: =IF(OR($A9="",BC$6="",NOT(ISNUMBER($H$2))),"",SUMIFS(数据录入!$F$5:$F$4999,数据录入!$C$5:$C$4999,$A9,数据录入!$B$5:$B$4999,BC$6)) -> 0 | BD9: =IF(OR($A9="",BD$6="",NOT(ISNUMBER($H$2))),"",SUMIFS(数据录入!$G$5:$G$4999,数据录入!$C$5:$C$4999,$A9,数据录入!$B$5:$B$4999,BD$6)) -> 0 | BE9: =IF(OR($A9="",BE$6="",NOT(ISNUMBER($H$2))),"",SUMIFS(数据录入!$F$5:$F$4999,数据录入!$C$5:$C$4999,$A9,数据录入!$B$5:$B$4999,BE$6)) -> 0 | BF9: =IF(OR($A9="",BF$6="",NOT(ISNUMBER($H$2))),"",SUMIFS(数据录入!$G$5:$G$4999,数据录入!$C$5:$C$4999,$A9,数据录入!$B$5:$B$4999,BF$6)) -> 0 | BG9: =IF(OR($A9="",BG$6="",NOT(ISNUMBER($H$2))),"",SUMIFS(数据录入!$F$5:$F$4999,数据录入!$C$5:$C$4999,$A9,数据录入!$B$5:$B$4999,BG$6)) -> 0 | BH9: =IF(OR($A9="",BH$6="",NOT(ISNUMBER($H$2))),"",SUMIFS(数据录入!$G$5:$G$4999,数据录入!$C$5:$C$4999,$A9,数据录入!$B$5:$B$4999,BH$6)) -> 0 | BI9: =IF(OR($A9="",BI$6="",NOT(ISNUMBER($H$2))),"",SUMIFS(数据录入!$F$5:$F$4999,数据录入!$C$5:$C$4999,$A9,数据录入!$B$5:$B$4999,BI$6)) -> 0 | BJ9: =IF(OR($A9="",BJ$6="",NOT(ISNUMBER($H$2))),"",SUMIFS(数据录入!$G$5:$G$4999,数据录入!$C$5:$C$4999,$A9,数据录入!$B$5:$B$4999,BJ$6)) -> 0 | BK9: =IF(OR($A9="",BK$6="",NOT(ISNUMBER($H$2))),"",SUMIFS(数据录入!$F$5:$F$4999,数据录入!$C$5:$C$4999,$A9,数据录入!$B$5:$B$4999,BK$6)) | BL9: =IF(OR($A9="",BL$6="",NOT(ISNUMBER($H$2))),"",SUMIFS(数据录入!$G$5:$G$4999,数据录入!$C$5:$C$4999,$A9,数据录入!$B$5:$B$4999,BL$6)) | BM9: =IF($A9="","",SUMIF($C$7:$BL$7,"收款",C9:BL9)) -> 0 | BN9: =IF($A9="","",SUMIF($C$7:$BL$7,"付款",C9:BL9)) -> 700 | BO9: =IF($A9="","",B9+BM9-BN9) -> -700
A10: 支付宝 | B10: =IF(OR($A10="",NOT(ISNUMBER($H$2))),"",SUMIFS(数据录入!$H$5:$H$4999,数据录入!$C$5:$C$4999,$A10,数据录入!$E$5:$E$4999,"期初余额",数据录入!$B$5:$B$4999,"<="&$B$2)+SUMIFS(数据录入!$F$5:$F$4999,数据录入!$C$5:$C$4999,$A10,数据录入!$B$5:$B$4999,"<"&$B$2)-SUMIFS(数据录入!$G$5:$G$4999,数据录入!$C$5:$C$4999,$A10,数据录入!$B$5:$B$4999,"<"&$B$2)) -> 0 | C10: =IF(OR($A10="",C$6="",NOT(ISNUMBER($H$2))),"",SUMIFS(数据录入!$F$5:$F$4999,数据录入!$C$5:$C$4999,$A10,数据录入!$B$5:$B$4999,C$6)) -> 0 | D10: =IF(OR($A10="",D$6="",NOT(ISNUMBER($H$2))),"",SUMIFS(数据录入!$G$5:$G$4999,数据录入!$C$5:$C$4999,$A10,数据录入!$B$5:$B$4999,D$6)) -> 800 | E10: =IF(OR($A10="",E$6="",NOT(ISNUMBER($H$2))),"",SUMIFS(数据录入!$F$5:$F$4999,数据录入!$C$5:$C$4999,$A10,数据录入!$B$5:$B$4999,E$6)) -> 0 | F10: =IF(OR($A10="",F$6="",NOT(ISNUMBER($H$2))),"",SUMIFS(数据录入!$G$5:$G$4999,数据录入!$C$5:$C$4999,$A10,数据录入!$B$5:$B$4999,F$6)) -> 0 | G10: =IF(OR($A10="",G$6="",NOT(ISNUMBER($H$2))),"",SUMIFS(数据录入!$F$5:$F$4999,数据录入!$C$5:$C$4999,$A10,数据录入!$B$5:$B$4999,G$6)) -> 0 | H10: =IF(OR($A10="",H$6="",NOT(ISNUMBER($H$2))),"",SUMIFS(数据录入!$G$5:$G$4999,数据录入!$C$5:$C$4999,$A10,数据录入!$B$5:$B$4999,H$6)) -> 0 | I10: =IF(OR($A10="",I$6="",NOT(ISNUMBER($H$2))),"",SUMIFS(数据录入!$F$5:$F$4999,数据录入!$C$5:$C$4999,$A10,数据录入!$B$5:$B$4999,I$6)) -> 0 | J10: =IF(OR($A10="",J$6="",NOT(ISNUMBER($H$2))),"",SUMIFS(数据录入!$G$5:$G$4999,数据录入!$C$5:$C$4999,$A10,数据录入!$B$5:$B$4999,J$6)) -> 0 | K10: =IF(OR($A10="",K$6="",NOT(ISNUMBER($H$2))),"",SUMIFS(数据录入!$F$5:$F$4999,数据录入!$C$5:$C$4999,$A10,数据录入!$B$5:$B$4999,K$6)) -> 0 | L10: =IF(OR($A10="",L$6="",NOT(ISNUMBER($H$2))),"",SUMIFS(数据录入!$G$5:$G$4999,数据录入!$C$5:$C$4999,$A10,数据录入!$B$5:$B$4999,L$6)) -> 0 | M10: =IF(OR($A10="",M$6="",NOT(ISNUMBER($H$2))),"",SUMIFS(数据录入!$F$5:$F$4999,数据录入!$C$5:$C$4999,$A10,数据录入!$B$5:$B$4999,M$6)) -> 0 | N10: =IF(OR($A10="",N$6="",NOT(ISNUMBER($H$2))),"",SUMIFS(数据录入!$G$5:$G$4999,数据录入!$C$5:$C$4999,$A10,数据录入!$B$5:$B$4999,N$6)) -> 0 | O10: =IF(OR($A10="",O$6="",NOT(ISNUMBER($H$2))),"",SUMIFS(数据录入!$F$5:$F$4999,数据录入!$C$5:$C$4999,$A10,数据录入!$B$5:$B$4999,O$6)) -> 0 | P10: =IF(OR($A10="",P$6="",NOT(ISNUMBER($H$2))),"",SUMIFS(数据录入!$G$5:$G$4999,数据录入!$C$5:$C$4999,$A10,数据录入!$B$5:$B$4999,P$6)) -> 0 | Q10: =IF(OR($A10="",Q$6="",NOT(ISNUMBER($H$2))),"",SUMIFS(数据录入!$F$5:$F$4999,数据录入!$C$5:$C$4999,$A10,数据录入!$B$5:$B$4999,Q$6)) -> 0 | R10: =IF(OR($A10="",R$6="",NOT(ISNUMBER($H$2))),"",SUMIFS(数据录入!$G$5:$G$4999,数据录入!$C$5:$C$4999,$A10,数据录入!$B$5:$B$4999,R$6)) -> 0 | S10: =IF(OR($A10="",S$6="",NOT(ISNUMBER($H$2))),"",SUMIFS(数据录入!$F$5:$F$4999,数据录入!$C$5:$C$4999,$A10,数据录入!$B$5:$B$4999,S$6)) -> 0 | T10: =IF(OR($A10="",T$6="",NOT(ISNUMBER($H$2))),"",SUMIFS(数据录入!$G$5:$G$4999,数据录入!$C$5:$C$4999,$A10,数据录入!$B$5:$B$4999,T$6)) -> 0 | U10: =IF(OR($A10="",U$6="",NOT(ISNUMBER($H$2))),"",SUMIFS(数据录入!$F$5:$F$4999,数据录入!$C$5:$C$4999,$A10,数据录入!$B$5:$B$4999,U$6)) -> 0 | V10: =IF(OR($A10="",V$6="",NOT(ISNUMBER($H$2))),"",SUMIFS(数据录入!$G$5:$G$4999,数据录入!$C$5:$C$4999,$A10,数据录入!$B$5:$B$4999,V$6)) -> 0 | W10: =IF(OR($A10="",W$6="",NOT(ISNUMBER($H$2))),"",SUMIFS(数据录入!$F$5:$F$4999,数据录入!$C$5:$C$4999,$A10,数据录入!$B$5:$B$4999,W$6)) -> 0 | X10: =IF(OR($A10="",X$6="",NOT(ISNUMBER($H$2))),"",SUMIFS(数据录入!$G$5:$G$4999,数据录入!$C$5:$C$4999,$A10,数据录入!$B$5:$B$4999,X$6)) -> 0 | Y10: =IF(OR($A10="",Y$6="",NOT(ISNUMBER($H$2))),"",SUMIFS(数据录入!$F$5:$F$4999,数据录入!$C$5:$C$4999,$A10,数据录入!$B$5:$B$4999,Y$6)) -> 0 | Z10: =IF(OR($A10="",Z$6="",NOT(ISNUMBER($H$2))),"",SUMIFS(数据录入!$G$5:$G$4999,数据录入!$C$5:$C$4999,$A10,数据录入!$B$5:$B$4999,Z$6)) -> 0 | AA10: =IF(OR($A10="",AA$6="",NOT(ISNUMBER($H$2))),"",SUMIFS(数据录入!$F$5:$F$4999,数据录入!$C$5:$C$4999,$A10,数据录入!$B$5:$B$4999,AA$6)) -> 0 | AB10: =IF(OR($A10="",AB$6="",NOT(ISNUMBER($H$2))),"",SUMIFS(数据录入!$G$5:$G$4999,数据录入!$C$5:$C$4999,$A10,数据录入!$B$5:$B$4999,AB$6)) -> 0 | AC10: =IF(OR($A10="",AC$6="",NOT(ISNUMBER($H$2))),"",SUMIFS(数据录入!$F$5:$F$4999,数据录入!$C$5:$C$4999,$A10,数据录入!$B$5:$B$4999,AC$6)) -> 0 | AD10: =IF(OR($A10="",AD$6="",NOT(ISNUMBER($H$2))),"",SUMIFS(数据录入!$G$5:$G$4999,数据录入!$C$5:$C$4999,$A10,数据录入!$B$5:$B$4999,AD$6)) -> 0 | AE10: =IF(OR($A10="",AE$6="",NOT(ISNUMBER($H$2))),"",SUMIFS(数据录入!$F$5:$F$4999,数据录入!$C$5:$C$4999,$A10,数据录入!$B$5:$B$4999,AE$6)) -> 0 | AF10: =IF(OR($A10="",AF$6="",NOT(ISNUMBER($H$2))),"",SUMIFS(数据录入!$G$5:$G$4999,数据录入!$C$5:$C$4999,$A10,数据录入!$B$5:$B$4999,AF$6)) -> 0 | AG10: =IF(OR($A10="",AG$6="",NOT(ISNUMBER($H$2))),"",SUMIFS(数据录入!$F$5:$F$4999,数据录入!$C$5:$C$4999,$A10,数据录入!$B$5:$B$4999,AG$6)) -> 0 | AH10: =IF(OR($A10="",AH$6="",NOT(ISNUMBER($H$2))),"",SUMIFS(数据录入!$G$5:$G$4999,数据录入!$C$5:$C$4999,$A10,数据录入!$B$5:$B$4999,AH$6)) -> 0 | AI10: =IF(OR($A10="",AI$6="",NOT(ISNUMBER($H$2))),"",SUMIFS(数据录入!$F$5:$F$4999,数据录入!$C$5:$C$4999,$A10,数据录入!$B$5:$B$4999,AI$6)) -> 0 | AJ10: =IF(OR($A10="",AJ$6="",NOT(ISNUMBER($H$2))),"",SUMIFS(数据录入!$G$5:$G$4999,数据录入!$C$5:$C$4999,$A10,数据录入!$B$5:$B$4999,AJ$6)) -> 0 | AK10: =IF(OR($A10="",AK$6="",NOT(ISNUMBER($H$2))),"",SUMIFS(数据录入!$F$5:$F$4999,数据录入!$C$5:$C$4999,$A10,数据录入!$B$5:$B$4999,AK$6)) -> 0 | AL10: =IF(OR($A10="",AL$6="",NOT(ISNUMBER($H$2))),"",SUMIFS(数据录入!$G$5:$G$4999,数据录入!$C$5:$C$4999,$A10,数据录入!$B$5:$B$4999,AL$6)) -> 0 | AM10: =IF(OR($A10="",AM$6="",NOT(ISNUMBER($H$2))),"",SUMIFS(数据录入!$F$5:$F$4999,数据录入!$C$5:$C$4999,$A10,数据录入!$B$5:$B$4999,AM$6)) -> 0 | AN10: =IF(OR($A10="",AN$6="",NOT(ISNUMBER($H$2))),"",SUMIFS(数据录入!$G$5:$G$4999,数据录入!$C$5:$C$4999,$A10,数据录入!$B$5:$B$4999,AN$6)) -> 0 | AO10: =IF(OR($A10="",AO$6="",NOT(ISNUMBER($H$2))),"",SUMIFS(数据录入!$F$5:$F$4999,数据录入!$C$5:$C$4999,$A10,数据录入!$B$5:$B$4999,AO$6)) -> 0 | AP10: =IF(OR($A10="",AP$6="",NOT(ISNUMBER($H$2))),"",SUMIFS(数据录入!$G$5:$G$4999,数据录入!$C$5:$C$4999,$A10,数据录入!$B$5:$B$4999,AP$6)) -> 0 | AQ10: =IF(OR($A10="",AQ$6="",NOT(ISNUMBER($H$2))),"",SUMIFS(数据录入!$F$5:$F$4999,数据录入!$C$5:$C$4999,$A10,数据录入!$B$5:$B$4999,AQ$6)) -> 0 | AR10: =IF(OR($A10="",AR$6="",NOT(ISNUMBER($H$2))),"",SUMIFS(数据录入!$G$5:$G$4999,数据录入!$C$5:$C$4999,$A10,数据录入!$B$5:$B$4999,AR$6)) -> 0 | AS10: =IF(OR($A10="",AS$6="",NOT(ISNUMBER($H$2))),"",SUMIFS(数据录入!$F$5:$F$4999,数据录入!$C$5:$C$4999,$A10,数据录入!$B$5:$B$4999,AS$6)) -> 0 | AT10: =IF(OR($A10="",AT$6="",NOT(ISNUMBER($H$2))),"",SUMIFS(数据录入!$G$5:$G$4999,数据录入!$C$5:$C$4999,$A10,数据录入!$B$5:$B$4999,AT$6)) -> 0 | AU10: =IF(OR($A10="",AU$6="",NOT(ISNUMBER($H$2))),"",SUMIFS(数据录入!$F$5:$F$4999,数据录入!$C$5:$C$4999,$A10,数据录入!$B$5:$B$4999,AU$6)) -> 0 | AV10: =IF(OR($A10="",AV$6="",NOT(ISNUMBER($H$2))),"",SUMIFS(数据录入!$G$5:$G$4999,数据录入!$C$5:$C$4999,$A10,数据录入!$B$5:$B$4999,AV$6)) -> 0 | AW10: =IF(OR($A10="",AW$6="",NOT(ISNUMBER($H$2))),"",SUMIFS(数据录入!$F$5:$F$4999,数据录入!$C$5:$C$4999,$A10,数据录入!$B$5:$B$4999,AW$6)) -> 0 | AX10: =IF(OR($A10="",AX$6="",NOT(ISNUMBER($H$2))),"",SUMIFS(数据录入!$G$5:$G$4999,数据录入!$C$5:$C$4999,$A10,数据录入!$B$5:$B$4999,AX$6)) -> 0 | AY10: =IF(OR($A10="",AY$6="",NOT(ISNUMBER($H$2))),"",SUMIFS(数据录入!$F$5:$F$4999,数据录入!$C$5:$C$4999,$A10,数据录入!$B$5:$B$4999,AY$6)) -> 0 | AZ10: =IF(OR($A10="",AZ$6="",NOT(ISNUMBER($H$2))),"",SUMIFS(数据录入!$G$5:$G$4999,数据录入!$C$5:$C$4999,$A10,数据录入!$B$5:$B$4999,AZ$6)) -> 0 | BA10: =IF(OR($A10="",BA$6="",NOT(ISNUMBER($H$2))),"",SUMIFS(数据录入!$F$5:$F$4999,数据录入!$C$5:$C$4999,$A10,数据录入!$B$5:$B$4999,BA$6)) -> 0 | BB10: =IF(OR($A10="",BB$6="",NOT(ISNUMBER($H$2))),"",SUMIFS(数据录入!$G$5:$G$4999,数据录入!$C$5:$C$4999,$A10,数据录入!$B$5:$B$4999,BB$6)) -> 0 | BC10: =IF(OR($A10="",BC$6="",NOT(ISNUMBER($H$2))),"",SUMIFS(数据录入!$F$5:$F$4999,数据录入!$C$5:$C$4999,$A10,数据录入!$B$5:$B$4999,BC$6)) -> 0 | BD10: =IF(OR($A10="",BD$6="",NOT(ISNUMBER($H$2))),"",SUMIFS(数据录入!$G$5:$G$4999,数据录入!$C$5:$C$4999,$A10,数据录入!$B$5:$B$4999,BD$6)) -> 0 | BE10: =IF(OR($A10="",BE$6="",NOT(ISNUMBER($H$2))),"",SUMIFS(数据录入!$F$5:$F$4999,数据录入!$C$5:$C$4999,$A10,数据录入!$B$5:$B$4999,BE$6)) -> 0 | BF10: =IF(OR($A10="",BF$6="",NOT(ISNUMBER($H$2))),"",SUMIFS(数据录入!$G$5:$G$4999,数据录入!$C$5:$C$4999,$A10,数据录入!$B$5:$B$4999,BF$6)) -> 0 | BG10: =IF(OR($A10="",BG$6="",NOT(ISNUMBER($H$2))),"",SUMIFS(数据录入!$F$5:$F$4999,数据录入!$C$5:$C$4999,$A10,数据录入!$B$5:$B$4999,BG$6)) -> 0 | BH10: =IF(OR($A10="",BH$6="",NOT(ISNUMBER($H$2))),"",SUMIFS(数据录入!$G$5:$G$4999,数据录入!$C$5:$C$4999,$A10,数据录入!$B$5:$B$4999,BH$6)) -> 0 | BI10: =IF(OR($A10="",BI$6="",NOT(ISNUMBER($H$2))),"",SUMIFS(数据录入!$F$5:$F$4999,数据录入!$C$5:$C$4999,$A10,数据录入!$B$5:$B$4999,BI$6)) -> 0 | BJ10: =IF(OR($A10="",BJ$6="",NOT(ISNUMBER($H$2))),"",SUMIFS(数据录入!$G$5:$G$4999,数据录入!$C$5:$C$4999,$A10,数据录入!$B$5:$B$4999,BJ$6)) -> 0 | BK10: =IF(OR($A10="",BK$6="",NOT(ISNUMBER($H$2))),"",SUMIFS(数据录入!$F$5:$F$4999,数据录入!$C$5:$C$4999,$A10,数据录入!$B$5:$B$4999,BK$6)) | BL10: =IF(OR($A10="",BL$6="",NOT(ISNUMBER($H$2))),"",SUMIFS(数据录入!$G$5:$G$4999,数据录入!$C$5:$C$4999,$A10,数据录入!$B$5:$B$4999,BL$6)) | BM10: =IF($A10="","",SUMIF($C$7:$BL$7,"收款",C10:BL10)) -> 0 | BN10: =IF($A10="","",SUMIF($C$7:$BL$7,"付款",C10:BL10)) -> 800 | BO10: =IF($A10="","",B10+BM10-BN10) -> -800
A11: 杭州 | B11: =IF(OR($A11="",NOT(ISNUMBER($H$2))),"",SUMIFS(数据录入!$H$5:$H$4999,数据录入!$C$5:$C$4999,$A11,数据录入!$E$5:$E$4999,"期初余额",数据录入!$B$5:$B$4999,"<="&$B$2)+SUMIFS(数据录入!$F$5:$F$4999,数据录入!$C$5:$C$4999,$A11,数据录入!$B$5:$B$4999,"<"&$B$2)-SUMIFS(数据录入!$G$5:$G$4999,数据录入!$C$5:$C$4999,$A11,数据录入!$B$5:$B$4999,"<"&$B$2)) -> 0 | C11: =IF(OR($A11="",C$6="",NOT(ISNUMBER($H$2))),"",SUMIFS(数据录入!$F$5:$F$4999,数据录入!$C$5:$C$4999,$A11,数据录入!$B$5:$B$4999,C$6)) -> 5000 | D11: =IF(OR($A11="",D$6="",NOT(ISNUMBER($H$2))),"",SUMIFS(数据录入!$G$5:$G$4999,数据录入!$C$5:$C$4999,$A11,数据录入!$B$5:$B$4999,D$6)) -> 500 | E11: =IF(OR($A11="",E$6="",NOT(ISNUMBER($H$2))),"",SUMIFS(数据录入!$F$5:$F$4999,数据录入!$C$5:$C$4999,$A11,数据录入!$B$5:$B$4999,E$6)) -> 0 | F11: =IF(OR($A11="",F$6="",NOT(ISNUMBER($H$2))),"",SUMIFS(数据录入!$G$5:$G$4999,数据录入!$C$5:$C$4999,$A11,数据录入!$B$5:$B$4999,F$6)) -> 0 | G11: =IF(OR($A11="",G$6="",NOT(ISNUMBER($H$2))),"",SUMIFS(数据录入!$F$5:$F$4999,数据录入!$C$5:$C$4999,$A11,数据录入!$B$5:$B$4999,G$6)) -> 0 | H11: =IF(OR($A11="",H$6="",NOT(ISNUMBER($H$2))),"",SUMIFS(数据录入!$G$5:$G$4999,数据录入!$C$5:$C$4999,$A11,数据录入!$B$5:$B$4999,H$6)) -> 0 | I11: =IF(OR($A11="",I$6="",NOT(ISNUMBER($H$2))),"",SUMIFS(数据录入!$F$5:$F$4999,数据录入!$C$5:$C$4999,$A11,数据录入!$B$5:$B$4999,I$6)) -> 0 | J11: =IF(OR($A11="",J$6="",NOT(ISNUMBER($H$2))),"",SUMIFS(数据录入!$G$5:$G$4999,数据录入!$C$5:$C$4999,$A11,数据录入!$B$5:$B$4999,J$6)) -> 0 | K11: =IF(OR($A11="",K$6="",NOT(ISNUMBER($H$2))),"",SUMIFS(数据录入!$F$5:$F$4999,数据录入!$C$5:$C$4999,$A11,数据录入!$B$5:$B$4999,K$6)) -> 0 | L11: =IF(OR($A11="",L$6="",NOT(ISNUMBER($H$2))),"",SUMIFS(数据录入!$G$5:$G$4999,数据录入!$C$5:$C$4999,$A11,数据录入!$B$5:$B$4999,L$6)) -> 0 | M11: =IF(OR($A11="",M$6="",NOT(ISNUMBER($H$2))),"",SUMIFS(数据录入!$F$5:$F$4999,数据录入!$C$5:$C$4999,$A11,数据录入!$B$5:$B$4999,M$6)) -> 0 | N11: =IF(OR($A11="",N$6="",NOT(ISNUMBER($H$2))),"",SUMIFS(数据录入!$G$5:$G$4999,数据录入!$C$5:$C$4999,$A11,数据录入!$B$5:$B$4999,N$6)) -> 0 | O11: =IF(OR($A11="",O$6="",NOT(ISNUMBER($H$2))),"",SUMIFS(数据录入!$F$5:$F$4999,数据录入!$C$5:$C$4999,$A11,数据录入!$B$5:$B$4999,O$6)) -> 0 | P11: =IF(OR($A11="",P$6="",NOT(ISNUMBER($H$2))),"",SUMIFS(数据录入!$G$5:$G$4999,数据录入!$C$5:$C$4999,$A11,数据录入!$B$5:$B$4999,P$6)) -> 0 | Q11: =IF(OR($A11="",Q$6="",NOT(ISNUMBER($H$2))),"",SUMIFS(数据录入!$F$5:$F$4999,数据录入!$C$5:$C$4999,$A11,数据录入!$B$5:$B$4999,Q$6)) -> 0 | R11: =IF(OR($A11="",R$6="",NOT(ISNUMBER($H$2))),"",SUMIFS(数据录入!$G$5:$G$4999,数据录入!$C$5:$C$4999,$A11,数据录入!$B$5:$B$4999,R$6)) -> 0 | S11: =IF(OR($A11="",S$6="",NOT(ISNUMBER($H$2))),"",SUMIFS(数据录入!$F$5:$F$4999,数据录入!$C$5:$C$4999,$A11,数据录入!$B$5:$B$4999,S$6)) -> 0 | T11: =IF(OR($A11="",T$6="",NOT(ISNUMBER($H$2))),"",SUMIFS(数据录入!$G$5:$G$4999,数据录入!$C$5:$C$4999,$A11,数据录入!$B$5:$B$4999,T$6)) -> 0 | U11: =IF(OR($A11="",U$6="",NOT(ISNUMBER($H$2))),"",SUMIFS(数据录入!$F$5:$F$4999,数据录入!$C$5:$C$4999,$A11,数据录入!$B$5:$B$4999,U$6)) -> 0 | V11: =IF(OR($A11="",V$6="",NOT(ISNUMBER($H$2))),"",SUMIFS(数据录入!$G$5:$G$4999,数据录入!$C$5:$C$4999,$A11,数据录入!$B$5:$B$4999,V$6)) -> 0 | W11: =IF(OR($A11="",W$6="",NOT(ISNUMBER($H$2))),"",SUMIFS(数据录入!$F$5:$F$4999,数据录入!$C$5:$C$4999,$A11,数据录入!$B$5:$B$4999,W$6)) -> 0 | X11: =IF(OR($A11="",X$6="",NOT(ISNUMBER($H$2))),"",SUMIFS(数据录入!$G$5:$G$4999,数据录入!$C$5:$C$4999,$A11,数据录入!$B$5:$B$4999,X$6)) -> 0 | Y11: =IF(OR($A11="",Y$6="",NOT(ISNUMBER($H$2))),"",SUMIFS(数据录入!$F$5:$F$4999,数据录入!$C$5:$C$4999,$A11,数据录入!$B$5:$B$4999,Y$6)) -> 0 | Z11: =IF(OR($A11="",Z$6="",NOT(ISNUMBER($H$2))),"",SUMIFS(数据录入!$G$5:$G$4999,数据录入!$C$5:$C$4999,$A11,数据录入!$B$5:$B$4999,Z$6)) -> 0 | AA11: =IF(OR($A11="",AA$6="",NOT(ISNUMBER($H$2))),"",SUMIFS(数据录入!$F$5:$F$4999,数据录入!$C$5:$C$4999,$A11,数据录入!$B$5:$B$4999,AA$6)) -> 0 | AB11: =IF(OR($A11="",AB$6="",NOT(ISNUMBER($H$2))),"",SUMIFS(数据录入!$G$5:$G$4999,数据录入!$C$5:$C$4999,$A11,数据录入!$B$5:$B$4999,AB$6)) -> 0 | AC11: =IF(OR($A11="",AC$6="",NOT(ISNUMBER($H$2))),"",SUMIFS(数据录入!$F$5:$F$4999,数据录入!$C$5:$C$4999,$A11,数据录入!$B$5:$B$4999,AC$6)) -> 0 | AD11: =IF(OR($A11="",AD$6="",NOT(ISNUMBER($H$2))),"",SUMIFS(数据录入!$G$5:$G$4999,数据录入!$C$5:$C$4999,$A11,数据录入!$B$5:$B$4999,AD$6)) -> 0 | AE11: =IF(OR($A11="",AE$6="",NOT(ISNUMBER($H$2))),"",SUMIFS(数据录入!$F$5:$F$4999,数据录入!$C$5:$C$4999,$A11,数据录入!$B$5:$B$4999,AE$6)) -> 0 | AF11: =IF(OR($A11="",AF$6="",NOT(ISNUMBER($H$2))),"",SUMIFS(数据录入!$G$5:$G$4999,数据录入!$C$5:$C$4999,$A11,数据录入!$B$5:$B$4999,AF$6)) -> 0 | AG11: =IF(OR($A11="",AG$6="",NOT(ISNUMBER($H$2))),"",SUMIFS(数据录入!$F$5:$F$4999,数据录入!$C$5:$C$4999,$A11,数据录入!$B$5:$B$4999,AG$6)) -> 0 | AH11: =IF(OR($A11="",AH$6="",NOT(ISNUMBER($H$2))),"",SUMIFS(数据录入!$G$5:$G$4999,数据录入!$C$5:$C$4999,$A11,数据录入!$B$5:$B$4999,AH$6)) -> 0 | AI11: =IF(OR($A11="",AI$6="",NOT(ISNUMBER($H$2))),"",SUMIFS(数据录入!$F$5:$F$4999,数据录入!$C$5:$C$4999,$A11,数据录入!$B$5:$B$4999,AI$6)) -> 0 | AJ11: =IF(OR($A11="",AJ$6="",NOT(ISNUMBER($H$2))),"",SUMIFS(数据录入!$G$5:$G$4999,数据录入!$C$5:$C$4999,$A11,数据录入!$B$5:$B$4999,AJ$6)) -> 0 | AK11: =IF(OR($A11="",AK$6="",NOT(ISNUMBER($H$2))),"",SUMIFS(数据录入!$F$5:$F$4999,数据录入!$C$5:$C$4999,$A11,数据录入!$B$5:$B$4999,AK$6)) -> 0 | AL11: =IF(OR($A11="",AL$6="",NOT(ISNUMBER($H$2))),"",SUMIFS(数据录入!$G$5:$G$4999,数据录入!$C$5:$C$4999,$A11,数据录入!$B$5:$B$4999,AL$6)) -> 0 | AM11: =IF(OR($A11="",AM$6="",NOT(ISNUMBER($H$2))),"",SUMIFS(数据录入!$F$5:$F$4999,数据录入!$C$5:$C$4999,$A11,数据录入!$B$5:$B$4999,AM$6)) -> 0 | AN11: =IF(OR($A11="",AN$6="",NOT(ISNUMBER($H$2))),"",SUMIFS(数据录入!$G$5:$G$4999,数据录入!$C$5:$C$4999,$A11,数据录入!$B$5:$B$4999,AN$6)) -> 0 | AO11: =IF(OR($A11="",AO$6="",NOT(ISNUMBER($H$2))),"",SUMIFS(数据录入!$F$5:$F$4999,数据录入!$C$5:$C$4999,$A11,数据录入!$B$5:$B$4999,AO$6)) -> 0 | AP11: =IF(OR($A11="",AP$6="",NOT(ISNUMBER($H$2))),"",SUMIFS(数据录入!$G$5:$G$4999,数据录入!$C$5:$C$4999,$A11,数据录入!$B$5:$B$4999,AP$6)) -> 0 | AQ11: =IF(OR($A11="",AQ$6="",NOT(ISNUMBER($H$2))),"",SUMIFS(数据录入!$F$5:$F$4999,数据录入!$C$5:$C$4999,$A11,数据录入!$B$5:$B$4999,AQ$6)) -> 0 | AR11: =IF(OR($A11="",AR$6="",NOT(ISNUMBER($H$2))),"",SUMIFS(数据录入!$G$5:$G$4999,数据录入!$C$5:$C$4999,$A11,数据录入!$B$5:$B$4999,AR$6)) -> 0 | AS11: =IF(OR($A11="",AS$6="",NOT(ISNUMBER($H$2))),"",SUMIFS(数据录入!$F$5:$F$4999,数据录入!$C$5:$C$4999,$A11,数据录入!$B$5:$B$4999,AS$6)) -> 0 | AT11: =IF(OR($A11="",AT$6="",NOT(ISNUMBER($H$2))),"",SUMIFS(数据录入!$G$5:$G$4999,数据录入!$C$5:$C$4999,$A11,数据录入!$B$5:$B$4999,AT$6)) -> 0 | AU11: =IF(OR($A11="",AU$6="",NOT(ISNUMBER($H$2))),"",SUMIFS(数据录入!$F$5:$F$4999,数据录入!$C$5:$C$4999,$A11,数据录入!$B$5:$B$4999,AU$6)) -> 0 | AV11: =IF(OR($A11="",AV$6="",NOT(ISNUMBER($H$2))),"",SUMIFS(数据录入!$G$5:$G$4999,数据录入!$C$5:$C$4999,$A11,数据录入!$B$5:$B$4999,AV$6)) -> 0 | AW11: =IF(OR($A11="",AW$6="",NOT(ISNUMBER($H$2))),"",SUMIFS(数据录入!$F$5:$F$4999,数据录入!$C$5:$C$4999,$A11,数据录入!$B$5:$B$4999,AW$6)) -> 0 | AX11: =IF(OR($A11="",AX$6="",NOT(ISNUMBER($H$2))),"",SUMIFS(数据录入!$G$5:$G$4999,数据录入!$C$5:$C$4999,$A11,数据录入!$B$5:$B$4999,AX$6)) -> 0 | AY11: =IF(OR($A11="",AY$6="",NOT(ISNUMBER($H$2))),"",SUMIFS(数据录入!$F$5:$F$4999,数据录入!$C$5:$C$4999,$A11,数据录入!$B$5:$B$4999,AY$6)) -> 0 | AZ11: =IF(OR($A11="",AZ$6="",NOT(ISNUMBER($H$2))),"",SUMIFS(数据录入!$G$5:$G$4999,数据录入!$C$5:$C$4999,$A11,数据录入!$B$5:$B$4999,AZ$6)) -> 0 | BA11: =IF(OR($A11="",BA$6="",NOT(ISNUMBER($H$2))),"",SUMIFS(数据录入!$F$5:$F$4999,数据录入!$C$5:$C$4999,$A11,数据录入!$B$5:$B$4999,BA$6)) -> 0 | BB11: =IF(OR($A11="",BB$6="",NOT(ISNUMBER($H$2))),"",SUMIFS(数据录入!$G$5:$G$4999,数据录入!$C$5:$C$4999,$A11,数据录入!$B$5:$B$4999,BB$6)) -> 0 | BC11: =IF(OR($A11="",BC$6="",NOT(ISNUMBER($H$2))),"",SUMIFS(数据录入!$F$5:$F$4999,数据录入!$C$5:$C$4999,$A11,数据录入!$B$5:$B$4999,BC$6)) -> 0 | BD11: =IF(OR($A11="",BD$6="",NOT(ISNUMBER($H$2))),"",SUMIFS(数据录入!$G$5:$G$4999,数据录入!$C$5:$C$4999,$A11,数据录入!$B$5:$B$4999,BD$6)) -> 0 | BE11: =IF(OR($A11="",BE$6="",NOT(ISNUMBER($H$2))),"",SUMIFS(数据录入!$F$5:$F$4999,数据录入!$C$5:$C$4999,$A11,数据录入!$B$5:$B$4999,BE$6)) -> 0 | BF11: =IF(OR($A11="",BF$6="",NOT(ISNUMBER($H$2))),"",SUMIFS(数据录入!$G$5:$G$4999,数据录入!$C$5:$C$4999,$A11,数据录入!$B$5:$B$4999,BF$6)) -> 0 | BG11: =IF(OR($A11="",BG$6="",NOT(ISNUMBER($H$2))),"",SUMIFS(数据录入!$F$5:$F$4999,数据录入!$C$5:$C$4999,$A11,数据录入!$B$5:$B$4999,BG$6)) -> 0 | BH11: =IF(OR($A11="",BH$6="",NOT(ISNUMBER($H$2))),"",SUMIFS(数据录入!$G$5:$G$4999,数据录入!$C$5:$C$4999,$A11,数据录入!$B$5:$B$4999,BH$6)) -> 0 | BI11: =IF(OR($A11="",BI$6="",NOT(ISNUMBER($H$2))),"",SUMIFS(数据录入!$F$5:$F$4999,数据录入!$C$5:$C$4999,$A11,数据录入!$B$5:$B$4999,BI$6)) -> 0 | BJ11: =IF(OR($A11="",BJ$6="",NOT(ISNUMBER($H$2))),"",SUMIFS(数据录入!$G$5:$G$4999,数据录入!$C$5:$C$4999,$A11,数据录入!$B$5:$B$4999,BJ$6)) -> 0 | BK11: =IF(OR($A11="",BK$6="",NOT(ISNUMBER($H$2))),"",SUMIFS(数据录入!$F$5:$F$4999,数据录入!$C$5:$C$4999,$A11,数据录入!$B$5:$B$4999,BK$6)) | BL11: =IF(OR($A11="",BL$6="",NOT(ISNUMBER($H$2))),"",SUMIFS(数据录入!$G$5:$G$4999,数据录入!$C$5:$C$4999,$A11,数据录入!$B$5:$B$4999,BL$6)) | BM11: =IF($A11="","",SUMIF($C$7:$BL$7,"收款",C11:BL11)) -> 5000 | BN11: =IF($A11="","",SUMIF($C$7:$BL$7,"付款",C11:BL11)) -> 500 | BO11: =IF($A11="","",B11+BM11-BN11) -> 4500
A12: 农商 | B12: =IF(OR($A12="",NOT(ISNUMBER($H$2))),"",SUMIFS(数据录入!$H$5:$H$4999,数据录入!$C$5:$C$4999,$A12,数据录入!$E$5:$E$4999,"期初余额",数据录入!$B$5:$B$4999,"<="&$B$2)+SUMIFS(数据录入!$F$5:$F$4999,数据录入!$C$5:$C$4999,$A12,数据录入!$B$5:$B$4999,"<"&$B$2)-SUMIFS(数据录入!$G$5:$G$4999,数据录入!$C$5:$C$4999,$A12,数据录入!$B$5:$B$4999,"<"&$B$2)) -> 0 | C12: =IF(OR($A12="",C$6="",NOT(ISNUMBER($H$2))),"",SUMIFS(数据录入!$F$5:$F$4999,数据录入!$C$5:$C$4999,$A12,数据录入!$B$5:$B$4999,C$6)) -> 3100 | D12: =IF(OR($A12="",D$6="",NOT(ISNUMBER($H$2))),"",SUMIFS(数据录入!$G$5:$G$4999,数据录入!$C$5:$C$4999,$A12,数据录入!$B$5:$B$4999,D$6)) -> 0 | E12: =IF(OR($A12="",E$6="",NOT(ISNUMBER($H$2))),"",SUMIFS(数据录入!$F$5:$F$4999,数据录入!$C$5:$C$4999,$A12,数据录入!$B$5:$B$4999,E$6)) -> 0 | F12: =IF(OR($A12="",F$6="",NOT(ISNUMBER($H$2))),"",SUMIFS(数据录入!$G$5:$G$4999,数据录入!$C$5:$C$4999,$A12,数据录入!$B$5:$B$4999,F$6)) -> 0 | G12: =IF(OR($A12="",G$6="",NOT(ISNUMBER($H$2))),"",SUMIFS(数据录入!$F$5:$F$4999,数据录入!$C$5:$C$4999,$A12,数据录入!$B$5:$B$4999,G$6)) -> 0 | H12: =IF(OR($A12="",H$6="",NOT(ISNUMBER($H$2))),"",SUMIFS(数据录入!$G$5:$G$4999,数据录入!$C$5:$C$4999,$A12,数据录入!$B$5:$B$4999,H$6)) -> 0 | I12: =IF(OR($A12="",I$6="",NOT(ISNUMBER($H$2))),"",SUMIFS(数据录入!$F$5:$F$4999,数据录入!$C$5:$C$4999,$A12,数据录入!$B$5:$B$4999,I$6)) -> 0 | J12: =IF(OR($A12="",J$6="",NOT(ISNUMBER($H$2))),"",SUMIFS(数据录入!$G$5:$G$4999,数据录入!$C$5:$C$4999,$A12,数据录入!$B$5:$B$4999,J$6)) -> 0 | K12: =IF(OR($A12="",K$6="",NOT(ISNUMBER($H$2))),"",SUMIFS(数据录入!$F$5:$F$4999,数据录入!$C$5:$C$4999,$A12,数据录入!$B$5:$B$4999,K$6)) -> 0 | L12: =IF(OR($A12="",L$6="",NOT(ISNUMBER($H$2))),"",SUMIFS(数据录入!$G$5:$G$4999,数据录入!$C$5:$C$4999,$A12,数据录入!$B$5:$B$4999,L$6)) -> 0 | M12: =IF(OR($A12="",M$6="",NOT(ISNUMBER($H$2))),"",SUMIFS(数据录入!$F$5:$F$4999,数据录入!$C$5:$C$4999,$A12,数据录入!$B$5:$B$4999,M$6)) -> 0 | N12: =IF(OR($A12="",N$6="",NOT(ISNUMBER($H$2))),"",SUMIFS(数据录入!$G$5:$G$4999,数据录入!$C$5:$C$4999,$A12,数据录入!$B$5:$B$4999,N$6)) -> 0 | O12: =IF(OR($A12="",O$6="",NOT(ISNUMBER($H$2))),"",SUMIFS(数据录入!$F$5:$F$4999,数据录入!$C$5:$C$4999,$A12,数据录入!$B$5:$B$4999,O$6)) -> 0 | P12: =IF(OR($A12="",P$6="",NOT(ISNUMBER($H$2))),"",SUMIFS(数据录入!$G$5:$G$4999,数据录入!$C$5:$C$4999,$A12,数据录入!$B$5:$B$4999,P$6)) -> 0 | Q12: =IF(OR($A12="",Q$6="",NOT(ISNUMBER($H$2))),"",SUMIFS(数据录入!$F$5:$F$4999,数据录入!$C$5:$C$4999,$A12,数据录入!$B$5:$B$4999,Q$6)) -> 0 | R12: =IF(OR($A12="",R$6="",NOT(ISNUMBER($H$2))),"",SUMIFS(数据录入!$G$5:$G$4999,数据录入!$C$5:$C$4999,$A12,数据录入!$B$5:$B$4999,R$6)) -> 0 | S12: =IF(OR($A12="",S$6="",NOT(ISNUMBER($H$2))),"",SUMIFS(数据录入!$F$5:$F$4999,数据录入!$C$5:$C$4999,$A12,数据录入!$B$5:$B$4999,S$6)) -> 0 | T12: =IF(OR($A12="",T$6="",NOT(ISNUMBER($H$2))),"",SUMIFS(数据录入!$G$5:$G$4999,数据录入!$C$5:$C$4999,$A12,数据录入!$B$5:$B$4999,T$6)) -> 0 | U12: =IF(OR($A12="",U$6="",NOT(ISNUMBER($H$2))),"",SUMIFS(数据录入!$F$5:$F$4999,数据录入!$C$5:$C$4999,$A12,数据录入!$B$5:$B$4999,U$6)) -> 0 | V12: =IF(OR($A12="",V$6="",NOT(ISNUMBER($H$2))),"",SUMIFS(数据录入!$G$5:$G$4999,数据录入!$C$5:$C$4999,$A12,数据录入!$B$5:$B$4999,V$6)) -> 0 | W12: =IF(OR($A12="",W$6="",NOT(ISNUMBER($H$2))),"",SUMIFS(数据录入!$F$5:$F$4999,数据录入!$C$5:$C$4999,$A12,数据录入!$B$5:$B$4999,W$6)) -> 0 | X12: =IF(OR($A12="",X$6="",NOT(ISNUMBER($H$2))),"",SUMIFS(数据录入!$G$5:$G$4999,数据录入!$C$5:$C$4999,$A12,数据录入!$B$5:$B$4999,X$6)) -> 0 | Y12: =IF(OR($A12="",Y$6="",NOT(ISNUMBER($H$2))),"",SUMIFS(数据录入!$F$5:$F$4999,数据录入!$C$5:$C$4999,$A12,数据录入!$B$5:$B$4999,Y$6)) -> 0 | Z12: =IF(OR($A12="",Z$6="",NOT(ISNUMBER($H$2))),"",SUMIFS(数据录入!$G$5:$G$4999,数据录入!$C$5:$C$4999,$A12,数据录入!$B$5:$B$4999,Z$6)) -> 0 | AA12: =IF(OR($A12="",AA$6="",NOT(ISNUMBER($H$2))),"",SUMIFS(数据录入!$F$5:$F$4999,数据录入!$C$5:$C$4999,$A12,数据录入!$B$5:$B$4999,AA$6)) -> 0 | AB12: =IF(OR($A12="",AB$6="",NOT(ISNUMBER($H$2))),"",SUMIFS(数据录入!$G$5:$G$4999,数据录入!$C$5:$C$4999,$A12,数据录入!$B$5:$B$4999,AB$6)) -> 0 | AC12: =IF(OR($A12="",AC$6="",NOT(ISNUMBER($H$2))),"",SUMIFS(数据录入!$F$5:$F$4999,数据录入!$C$5:$C$4999,$A12,数据录入!$B$5:$B$4999,AC$6)) -> 0 | AD12: =IF(OR($A12="",AD$6="",NOT(ISNUMBER($H$2))),"",SUMIFS(数据录入!$G$5:$G$4999,数据录入!$C$5:$C$4999,$A12,数据录入!$B$5:$B$4999,AD$6)) -> 0 | AE12: =IF(OR($A12="",AE$6="",NOT(ISNUMBER($H$2))),"",SUMIFS(数据录入!$F$5:$F$4999,数据录入!$C$5:$C$4999,$A12,数据录入!$B$5:$B$4999,AE$6)) -> 0 | AF12: =IF(OR($A12="",AF$6="",NOT(ISNUMBER($H$2))),"",SUMIFS(数据录入!$G$5:$G$4999,数据录入!$C$5:$C$4999,$A12,数据录入!$B$5:$B$4999,AF$6)) -> 0 | AG12: =IF(OR($A12="",AG$6="",NOT(ISNUMBER($H$2))),"",SUMIFS(数据录入!$F$5:$F$4999,数据录入!$C$5:$C$4999,$A12,数据录入!$B$5:$B$4999,AG$6)) -> 0 | AH12: =IF(OR($A12="",AH$6="",NOT(ISNUMBER($H$2))),"",SUMIFS(数据录入!$G$5:$G$4999,数据录入!$C$5:$C$4999,$A12,数据录入!$B$5:$B$4999,AH$6)) -> 0 | AI12: =IF(OR($A12="",AI$6="",NOT(ISNUMBER($H$2))),"",SUMIFS(数据录入!$F$5:$F$4999,数据录入!$C$5:$C$4999,$A12,数据录入!$B$5:$B$4999,AI$6)) -> 0 | AJ12: =IF(OR($A12="",AJ$6="",NOT(ISNUMBER($H$2))),"",SUMIFS(数据录入!$G$5:$G$4999,数据录入!$C$5:$C$4999,$A12,数据录入!$B$5:$B$4999,AJ$6)) -> 0 | AK12: =IF(OR($A12="",AK$6="",NOT(ISNUMBER($H$2))),"",SUMIFS(数据录入!$F$5:$F$4999,数据录入!$C$5:$C$4999,$A12,数据录入!$B$5:$B$4999,AK$6)) -> 0 | AL12: =IF(OR($A12="",AL$6="",NOT(ISNUMBER($H$2))),"",SUMIFS(数据录入!$G$5:$G$4999,数据录入!$C$5:$C$4999,$A12,数据录入!$B$5:$B$4999,AL$6)) -> 0 | AM12: =IF(OR($A12="",AM$6="",NOT(ISNUMBER($H$2))),"",SUMIFS(数据录入!$F$5:$F$4999,数据录入!$C$5:$C$4999,$A12,数据录入!$B$5:$B$4999,AM$6)) -> 0 | AN12: =IF(OR($A12="",AN$6="",NOT(ISNUMBER($H$2))),"",SUMIFS(数据录入!$G$5:$G$4999,数据录入!$C$5:$C$4999,$A12,数据录入!$B$5:$B$4999,AN$6)) -> 0 | AO12: =IF(OR($A12="",AO$6="",NOT(ISNUMBER($H$2))),"",SUMIFS(数据录入!$F$5:$F$4999,数据录入!$C$5:$C$4999,$A12,数据录入!$B$5:$B$4999,AO$6)) -> 0 | AP12: =IF(OR($A12="",AP$6="",NOT(ISNUMBER($H$2))),"",SUMIFS(数据录入!$G$5:$G$4999,数据录入!$C$5:$C$4999,$A12,数据录入!$B$5:$B$4999,AP$6)) -> 0 | AQ12: =IF(OR($A12="",AQ$6="",NOT(ISNUMBER($H$2))),"",SUMIFS(数据录入!$F$5:$F$4999,数据录入!$C$5:$C$4999,$A12,数据录入!$B$5:$B$4999,AQ$6)) -> 0 | AR12: =IF(OR($A12="",AR$6="",NOT(ISNUMBER($H$2))),"",SUMIFS(数据录入!$G$5:$G$4999,数据录入!$C$5:$C$4999,$A12,数据录入!$B$5:$B$4999,AR$6)) -> 0 | AS12: =IF(OR($A12="",AS$6="",NOT(ISNUMBER($H$2))),"",SUMIFS(数据录入!$F$5:$F$4999,数据录入!$C$5:$C$4999,$A12,数据录入!$B$5:$B$4999,AS$6)) -> 0 | AT12: =IF(OR($A12="",AT$6="",NOT(ISNUMBER($H$2))),"",SUMIFS(数据录入!$G$5:$G$4999,数据录入!$C$5:$C$4999,$A12,数据录入!$B$5:$B$4999,AT$6)) -> 0 | AU12: =IF(OR($A12="",AU$6="",NOT(ISNUMBER($H$2))),"",SUMIFS(数据录入!$F$5:$F$4999,数据录入!$C$5:$C$4999,$A12,数据录入!$B$5:$B$4999,AU$6)) -> 0 | AV12: =IF(OR($A12="",AV$6="",NOT(ISNUMBER($H$2))),"",SUMIFS(数据录入!$G$5:$G$4999,数据录入!$C$5:$C$4999,$A12,数据录入!$B$5:$B$4999,AV$6)) -> 0 | AW12: =IF(OR($A12="",AW$6="",NOT(ISNUMBER($H$2))),"",SUMIFS(数据录入!$F$5:$F$4999,数据录入!$C$5:$C$4999,$A12,数据录入!$B$5:$B$4999,AW$6)) -> 0 | AX12: =IF(OR($A12="",AX$6="",NOT(ISNUMBER($H$2))),"",SUMIFS(数据录入!$G$5:$G$4999,数据录入!$C$5:$C$4999,$A12,数据录入!$B$5:$B$4999,AX$6)) -> 0 | AY12: =IF(OR($A12="",AY$6="",NOT(ISNUMBER($H$2))),"",SUMIFS(数据录入!$F$5:$F$4999,数据录入!$C$5:$C$4999,$A12,数据录入!$B$5:$B$4999,AY$6)) -> 0 | AZ12: =IF(OR($A12="",AZ$6="",NOT(ISNUMBER($H$2))),"",SUMIFS(数据录入!$G$5:$G$4999,数据录入!$C$5:$C$4999,$A12,数据录入!$B$5:$B$4999,AZ$6)) -> 0 | BA12: =IF(OR($A12="",BA$6="",NOT(ISNUMBER($H$2))),"",SUMIFS(数据录入!$F$5:$F$4999,数据录入!$C$5:$C$4999,$A12,数据录入!$B$5:$B$4999,BA$6)) -> 0 | BB12: =IF(OR($A12="",BB$6="",NOT(ISNUMBER($H$2))),"",SUMIFS(数据录入!$G$5:$G$4999,数据录入!$C$5:$C$4999,$A12,数据录入!$B$5:$B$4999,BB$6)) -> 0 | BC12: =IF(OR($A12="",BC$6="",NOT(ISNUMBER($H$2))),"",SUMIFS(数据录入!$F$5:$F$4999,数据录入!$C$5:$C$4999,$A12,数据录入!$B$5:$B$4999,BC$6)) -> 0 | BD12: =IF(OR($A12="",BD$6="",NOT(ISNUMBER($H$2))),"",SUMIFS(数据录入!$G$5:$G$4999,数据录入!$C$5:$C$4999,$A12,数据录入!$B$5:$B$4999,BD$6)) -> 0 | BE12: =IF(OR($A12="",BE$6="",NOT(ISNUMBER($H$2))),"",SUMIFS(数据录入!$F$5:$F$4999,数据录入!$C$5:$C$4999,$A12,数据录入!$B$5:$B$4999,BE$6)) -> 0 | BF12: =IF(OR($A12="",BF$6="",NOT(ISNUMBER($H$2))),"",SUMIFS(数据录入!$G$5:$G$4999,数据录入!$C$5:$C$4999,$A12,数据录入!$B$5:$B$4999,BF$6)) -> 0 | BG12: =IF(OR($A12="",BG$6="",NOT(ISNUMBER($H$2))),"",SUMIFS(数据录入!$F$5:$F$4999,数据录入!$C$5:$C$4999,$A12,数据录入!$B$5:$B$4999,BG$6)) -> 0 | BH12: =IF(OR($A12="",BH$6="",NOT(ISNUMBER($H$2))),"",SUMIFS(数据录入!$G$5:$G$4999,数据录入!$C$5:$C$4999,$A12,数据录入!$B$5:$B$4999,BH$6)) -> 0 | BI12: =IF(OR($A12="",BI$6="",NOT(ISNUMBER($H$2))),"",SUMIFS(数据录入!$F$5:$F$4999,数据录入!$C$5:$C$4999,$A12,数据录入!$B$5:$B$4999,BI$6)) -> 0 | BJ12: =IF(OR($A12="",BJ$6="",NOT(ISNUMBER($H$2))),"",SUMIFS(数据录入!$G$5:$G$4999,数据录入!$C$5:$C$4999,$A12,数据录入!$B$5:$B$4999,BJ$6)) -> 0 | BK12: =IF(OR($A12="",BK$6="",NOT(ISNUMBER($H$2))),"",SUMIFS(数据录入!$F$5:$F$4999,数据录入!$C$5:$C$4999,$A12,数据录入!$B$5:$B$4999,BK$6)) | BL12: =IF(OR($A12="",BL$6="",NOT(ISNUMBER($H$2))),"",SUMIFS(数据录入!$G$5:$G$4999,数据录入!$C$5:$C$4999,$A12,数据录入!$B$5:$B$4999,BL$6)) | BM12: =IF($A12="","",SUMIF($C$7:$BL$7,"收款",C12:BL12)) -> 3100 | BN12: =IF($A12="","",SUMIF($C$7:$BL$7,"付款",C12:BL12)) -> 0 | BO12: =IF($A12="","",B12+BM12-BN12) -> 3100
A13: 备用 | B13: =IF(OR($A13="",NOT(ISNUMBER($H$2))),"",SUMIFS(数据录入!$H$5:$H$4999,数据录入!$C$5:$C$4999,$A13,数据录入!$E$5:$E$4999,"期初余额",数据录入!$B$5:$B$4999,"<="&$B$2)+SUMIFS(数据录入!$F$5:$F$4999,数据录入!$C$5:$C$4999,$A13,数据录入!$B$5:$B$4999,"<"&$B$2)-SUMIFS(数据录入!$G$5:$G$4999,数据录入!$C$5:$C$4999,$A13,数据录入!$B$5:$B$4999,"<"&$B$2)) -> 0 | C13: =IF(OR($A13="",C$6="",NOT(ISNUMBER($H$2))),"",SUMIFS(数据录入!$F$5:$F$4999,数据录入!$C$5:$C$4999,$A13,数据录入!$B$5:$B$4999,C$6)) -> 0 | D13: =IF(OR($A13="",D$6="",NOT(ISNUMBER($H$2))),"",SUMIFS(数据录入!$G$5:$G$4999,数据录入!$C$5:$C$4999,$A13,数据录入!$B$5:$B$4999,D$6)) -> 5500 | E13: =IF(OR($A13="",E$6="",NOT(ISNUMBER($H$2))),"",SUMIFS(数据录入!$F$5:$F$4999,数据录入!$C$5:$C$4999,$A13,数据录入!$B$5:$B$4999,E$6)) -> 0 | F13: =IF(OR($A13="",F$6="",NOT(ISNUMBER($H$2))),"",SUMIFS(数据录入!$G$5:$G$4999,数据录入!$C$5:$C$4999,$A13,数据录入!$B$5:$B$4999,F$6)) -> 0 | G13: =IF(OR($A13="",G$6="",NOT(ISNUMBER($H$2))),"",SUMIFS(数据录入!$F$5:$F$4999,数据录入!$C$5:$C$4999,$A13,数据录入!$B$5:$B$4999,G$6)) -> 0 | H13: =IF(OR($A13="",H$6="",NOT(ISNUMBER($H$2))),"",SUMIFS(数据录入!$G$5:$G$4999,数据录入!$C$5:$C$4999,$A13,数据录入!$B$5:$B$4999,H$6)) -> 0 | I13: =IF(OR($A13="",I$6="",NOT(ISNUMBER($H$2))),"",SUMIFS(数据录入!$F$5:$F$4999,数据录入!$C$5:$C$4999,$A13,数据录入!$B$5:$B$4999,I$6)) -> 0 | J13: =IF(OR($A13="",J$6="",NOT(ISNUMBER($H$2))),"",SUMIFS(数据录入!$G$5:$G$4999,数据录入!$C$5:$C$4999,$A13,数据录入!$B$5:$B$4999,J$6)) -> 0 | K13: =IF(OR($A13="",K$6="",NOT(ISNUMBER($H$2))),"",SUMIFS(数据录入!$F$5:$F$4999,数据录入!$C$5:$C$4999,$A13,数据录入!$B$5:$B$4999,K$6)) -> 0 | L13: =IF(OR($A13="",L$6="",NOT(ISNUMBER($H$2))),"",SUMIFS(数据录入!$G$5:$G$4999,数据录入!$C$5:$C$4999,$A13,数据录入!$B$5:$B$4999,L$6)) -> 0 | M13: =IF(OR($A13="",M$6="",NOT(ISNUMBER($H$2))),"",SUMIFS(数据录入!$F$5:$F$4999,数据录入!$C$5:$C$4999,$A13,数据录入!$B$5:$B$4999,M$6)) -> 0 | N13: =IF(OR($A13="",N$6="",NOT(ISNUMBER($H$2))),"",SUMIFS(数据录入!$G$5:$G$4999,数据录入!$C$5:$C$4999,$A13,数据录入!$B$5:$B$4999,N$6)) -> 0 | O13: =IF(OR($A13="",O$6="",NOT(ISNUMBER($H$2))),"",SUMIFS(数据录入!$F$5:$F$4999,数据录入!$C$5:$C$4999,$A13,数据录入!$B$5:$B$4999,O$6)) -> 0 | P13: =IF(OR($A13="",P$6="",NOT(ISNUMBER($H$2))),"",SUMIFS(数据录入!$G$5:$G$4999,数据录入!$C$5:$C$4999,$A13,数据录入!$B$5:$B$4999,P$6)) -> 0 | Q13: =IF(OR($A13="",Q$6="",NOT(ISNUMBER($H$2))),"",SUMIFS(数据录入!$F$5:$F$4999,数据录入!$C$5:$C$4999,$A13,数据录入!$B$5:$B$4999,Q$6)) -> 0 | R13: =IF(OR($A13="",R$6="",NOT(ISNUMBER($H$2))),"",SUMIFS(数据录入!$G$5:$G$4999,数据录入!$C$5:$C$4999,$A13,数据录入!$B$5:$B$4999,R$6)) -> 0 | S13: =IF(OR($A13="",S$6="",NOT(ISNUMBER($H$2))),"",SUMIFS(数据录入!$F$5:$F$4999,数据录入!$C$5:$C$4999,$A13,数据录入!$B$5:$B$4999,S$6)) -> 0 | T13: =IF(OR($A13="",T$6="",NOT(ISNUMBER($H$2))),"",SUMIFS(数据录入!$G$5:$G$4999,数据录入!$C$5:$C$4999,$A13,数据录入!$B$5:$B$4999,T$6)) -> 0 | U13: =IF(OR($A13="",U$6="",NOT(ISNUMBER($H$2))),"",SUMIFS(数据录入!$F$5:$F$4999,数据录入!$C$5:$C$4999,$A13,数据录入!$B$5:$B$4999,U$6)) -> 0 | V13: =IF(OR($A13="",V$6="",NOT(ISNUMBER($H$2))),"",SUMIFS(数据录入!$G$5:$G$4999,数据录入!$C$5:$C$4999,$A13,数据录入!$B$5:$B$4999,V$6)) -> 0 | W13: =IF(OR($A13="",W$6="",NOT(ISNUMBER($H$2))),"",SUMIFS(数据录入!$F$5:$F$4999,数据录入!$C$5:$C$4999,$A13,数据录入!$B$5:$B$4999,W$6)) -> 0 | X13: =IF(OR($A13="",X$6="",NOT(ISNUMBER($H$2))),"",SUMIFS(数据录入!$G$5:$G$4999,数据录入!$C$5:$C$4999,$A13,数据录入!$B$5:$B$4999,X$6)) -> 0 | Y13: =IF(OR($A13="",Y$6="",NOT(ISNUMBER($H$2))),"",SUMIFS(数据录入!$F$5:$F$4999,数据录入!$C$5:$C$4999,$A13,数据录入!$B$5:$B$4999,Y$6)) -> 0 | Z13: =IF(OR($A13="",Z$6="",NOT(ISNUMBER($H$2))),"",SUMIFS(数据录入!$G$5:$G$4999,数据录入!$C$5:$C$4999,$A13,数据录入!$B$5:$B$4999,Z$6)) -> 0 | AA13: =IF(OR($A13="",AA$6="",NOT(ISNUMBER($H$2))),"",SUMIFS(数据录入!$F$5:$F$4999,数据录入!$C$5:$C$4999,$A13,数据录入!$B$5:$B$4999,AA$6)) -> 0 | AB13: =IF(OR($A13="",AB$6="",NOT(ISNUMBER($H$2))),"",SUMIFS(数据录入!$G$5:$G$4999,数据录入!$C$5:$C$4999,$A13,数据录入!$B$5:$B$4999,AB$6)) -> 0 | AC13: =IF(OR($A13="",AC$6="",NOT(ISNUMBER($H$2))),"",SUMIFS(数据录入!$F$5:$F$4999,数据录入!$C$5:$C$4999,$A13,数据录入!$B$5:$B$4999,AC$6)) -> 0 | AD13: =IF(OR($A13="",AD$6="",NOT(ISNUMBER($H$2))),"",SUMIFS(数据录入!$G$5:$G$4999,数据录入!$C$5:$C$4999,$A13,数据录入!$B$5:$B$4999,AD$6)) -> 0 | AE13: =IF(OR($A13="",AE$6="",NOT(ISNUMBER($H$2))),"",SUMIFS(数据录入!$F$5:$F$4999,数据录入!$C$5:$C$4999,$A13,数据录入!$B$5:$B$4999,AE$6)) -> 0 | AF13: =IF(OR($A13="",AF$6="",NOT(ISNUMBER($H$2))),"",SUMIFS(数据录入!$G$5:$G$4999,数据录入!$C$5:$C$4999,$A13,数据录入!$B$5:$B$4999,AF$6)) -> 0 | AG13: =IF(OR($A13="",AG$6="",NOT(ISNUMBER($H$2))),"",SUMIFS(数据录入!$F$5:$F$4999,数据录入!$C$5:$C$4999,$A13,数据录入!$B$5:$B$4999,AG$6)) -> 0 | AH13: =IF(OR($A13="",AH$6="",NOT(ISNUMBER($H$2))),"",SUMIFS(数据录入!$G$5:$G$4999,数据录入!$C$5:$C$4999,$A13,数据录入!$B$5:$B$4999,AH$6)) -> 0 | AI13: =IF(OR($A13="",AI$6="",NOT(ISNUMBER($H$2))),"",SUMIFS(数据录入!$F$5:$F$4999,数据录入!$C$5:$C$4999,$A13,数据录入!$B$5:$B$4999,AI$6)) -> 0 | AJ13: =IF(OR($A13="",AJ$6="",NOT(ISNUMBER($H$2))),"",SUMIFS(数据录入!$G$5:$G$4999,数据录入!$C$5:$C$4999,$A13,数据录入!$B$5:$B$4999,AJ$6)) -> 0 | AK13: =IF(OR($A13="",AK$6="",NOT(ISNUMBER($H$2))),"",SUMIFS(数据录入!$F$5:$F$4999,数据录入!$C$5:$C$4999,$A13,数据录入!$B$5:$B$4999,AK$6)) -> 0 | AL13: =IF(OR($A13="",AL$6="",NOT(ISNUMBER($H$2))),"",SUMIFS(数据录入!$G$5:$G$4999,数据录入!$C$5:$C$4999,$A13,数据录入!$B$5:$B$4999,AL$6)) -> 0 | AM13: =IF(OR($A13="",AM$6="",NOT(ISNUMBER($H$2))),"",SUMIFS(数据录入!$F$5:$F$4999,数据录入!$C$5:$C$4999,$A13,数据录入!$B$5:$B$4999,AM$6)) -> 0 | AN13: =IF(OR($A13="",AN$6="",NOT(ISNUMBER($H$2))),"",SUMIFS(数据录入!$G$5:$G$4999,数据录入!$C$5:$C$4999,$A13,数据录入!$B$5:$B$4999,AN$6)) -> 0 | AO13: =IF(OR($A13="",AO$6="",NOT(ISNUMBER($H$2))),"",SUMIFS(数据录入!$F$5:$F$4999,数据录入!$C$5:$C$4999,$A13,数据录入!$B$5:$B$4999,AO$6)) -> 0 | AP13: =IF(OR($A13="",AP$6="",NOT(ISNUMBER($H$2))),"",SUMIFS(数据录入!$G$5:$G$4999,数据录入!$C$5:$C$4999,$A13,数据录入!$B$5:$B$4999,AP$6)) -> 0 | AQ13: =IF(OR($A13="",AQ$6="",NOT(ISNUMBER($H$2))),"",SUMIFS(数据录入!$F$5:$F$4999,数据录入!$C$5:$C$4999,$A13,数据录入!$B$5:$B$4999,AQ$6)) -> 0 | AR13: =IF(OR($A13="",AR$6="",NOT(ISNUMBER($H$2))),"",SUMIFS(数据录入!$G$5:$G$4999,数据录入!$C$5:$C$4999,$A13,数据录入!$B$5:$B$4999,AR$6)) -> 0 | AS13: =IF(OR($A13="",AS$6="",NOT(ISNUMBER($H$2))),"",SUMIFS(数据录入!$F$5:$F$4999,数据录入!$C$5:$C$4999,$A13,数据录入!$B$5:$B$4999,AS$6)) -> 0 | AT13: =IF(OR($A13="",AT$6="",NOT(ISNUMBER($H$2))),"",SUMIFS(数据录入!$G$5:$G$4999,数据录入!$C$5:$C$4999,$A13,数据录入!$B$5:$B$4999,AT$6)) -> 0 | AU13: =IF(OR($A13="",AU$6="",NOT(ISNUMBER($H$2))),"",SUMIFS(数据录入!$F$5:$F$4999,数据录入!$C$5:$C$4999,$A13,数据录入!$B$5:$B$4999,AU$6)) -> 0 | AV13: =IF(OR($A13="",AV$6="",NOT(ISNUMBER($H$2))),"",SUMIFS(数据录入!$G$5:$G$4999,数据录入!$C$5:$C$4999,$A13,数据录入!$B$5:$B$4999,AV$6)) -> 0 | AW13: =IF(OR($A13="",AW$6="",NOT(ISNUMBER($H$2))),"",SUMIFS(数据录入!$F$5:$F$4999,数据录入!$C$5:$C$4999,$A13,数据录入!$B$5:$B$4999,AW$6)) -> 0 | AX13: =IF(OR($A13="",AX$6="",NOT(ISNUMBER($H$2))),"",SUMIFS(数据录入!$G$5:$G$4999,数据录入!$C$5:$C$4999,$A13,数据录入!$B$5:$B$4999,AX$6)) -> 0 | AY13: =IF(OR($A13="",AY$6="",NOT(ISNUMBER($H$2))),"",SUMIFS(数据录入!$F$5:$F$4999,数据录入!$C$5:$C$4999,$A13,数据录入!$B$5:$B$4999,AY$6)) -> 0 | AZ13: =IF(OR($A13="",AZ$6="",NOT(ISNUMBER($H$2))),"",SUMIFS(数据录入!$G$5:$G$4999,数据录入!$C$5:$C$4999,$A13,数据录入!$B$5:$B$4999,AZ$6)) -> 0 | BA13: =IF(OR($A13="",BA$6="",NOT(ISNUMBER($H$2))),"",SUMIFS(数据录入!$F$5:$F$4999,数据录入!$C$5:$C$4999,$A13,数据录入!$B$5:$B$4999,BA$6)) -> 0 | BB13: =IF(OR($A13="",BB$6="",NOT(ISNUMBER($H$2))),"",SUMIFS(数据录入!$G$5:$G$4999,数据录入!$C$5:$C$4999,$A13,数据录入!$B$5:$B$4999,BB$6)) -> 0 | BC13: =IF(OR($A13="",BC$6="",NOT(ISNUMBER($H$2))),"",SUMIFS(数据录入!$F$5:$F$4999,数据录入!$C$5:$C$4999,$A13,数据录入!$B$5:$B$4999,BC$6)) -> 0 | BD13: =IF(OR($A13="",BD$6="",NOT(ISNUMBER($H$2))),"",SUMIFS(数据录入!$G$5:$G$4999,数据录入!$C$5:$C$4999,$A13,数据录入!$B$5:$B$4999,BD$6)) -> 0 | BE13: =IF(OR($A13="",BE$6="",NOT(ISNUMBER($H$2))),"",SUMIFS(数据录入!$F$5:$F$4999,数据录入!$C$5:$C$4999,$A13,数据录入!$B$5:$B$4999,BE$6)) -> 0 | BF13: =IF(OR($A13="",BF$6="",NOT(ISNUMBER($H$2))),"",SUMIFS(数据录入!$G$5:$G$4999,数据录入!$C$5:$C$4999,$A13,数据录入!$B$5:$B$4999,BF$6)) -> 0 | BG13: =IF(OR($A13="",BG$6="",NOT(ISNUMBER($H$2))),"",SUMIFS(数据录入!$F$5:$F$4999,数据录入!$C$5:$C$4999,$A13,数据录入!$B$5:$B$4999,BG$6)) -> 0 | BH13: =IF(OR($A13="",BH$6="",NOT(ISNUMBER($H$2))),"",SUMIFS(数据录入!$G$5:$G$4999,数据录入!$C$5:$C$4999,$A13,数据录入!$B$5:$B$4999,BH$6)) -> 0 | BI13: =IF(OR($A13="",BI$6="",NOT(ISNUMBER($H$2))),"",SUMIFS(数据录入!$F$5:$F$4999,数据录入!$C$5:$C$4999,$A13,数据录入!$B$5:$B$4999,BI$6)) -> 0 | BJ13: =IF(OR($A13="",BJ$6="",NOT(ISNUMBER($H$2))),"",SUMIFS(数据录入!$G$5:$G$4999,数据录入!$C$5:$C$4999,$A13,数据录入!$B$5:$B$4999,BJ$6)) -> 0 | BK13: =IF(OR($A13="",BK$6="",NOT(ISNUMBER($H$2))),"",SUMIFS(数据录入!$F$5:$F$4999,数据录入!$C$5:$C$4999,$A13,数据录入!$B$5:$B$4999,BK$6)) | BL13: =IF(OR($A13="",BL$6="",NOT(ISNUMBER($H$2))),"",SUMIFS(数据录入!$G$5:$G$4999,数据录入!$C$5:$C$4999,$A13,数据录入!$B$5:$B$4999,BL$6)) | BM13: =IF($A13="","",SUMIF($C$7:$BL$7,"收款",C13:BL13)) -> 0 | BN13: =IF($A13="","",SUMIF($C$7:$BL$7,"付款",C13:BL13)) -> 5500 | BO13: =IF($A13="","",B13+BM13-BN13) -> -5500
A14: 备用1 | B14: =IF(OR($A14="",NOT(ISNUMBER($H$2))),"",SUMIFS(数据录入!$H$5:$H$4999,数据录入!$C$5:$C$4999,$A14,数据录入!$E$5:$E$4999,"期初余额",数据录入!$B$5:$B$4999,"<="&$B$2)+SUMIFS(数据录入!$F$5:$F$4999,数据录入!$C$5:$C$4999,$A14,数据录入!$B$5:$B$4999,"<"&$B$2)-SUMIFS(数据录入!$G$5:$G$4999,数据录入!$C$5:$C$4999,$A14,数据录入!$B$5:$B$4999,"<"&$B$2)) -> 0 | C14: =IF(OR($A14="",C$6="",NOT(ISNUMBER($H$2))),"",SUMIFS(数据录入!$F$5:$F$4999,数据录入!$C$5:$C$4999,$A14,数据录入!$B$5:$B$4999,C$6)) -> 10000 | D14: =IF(OR($A14="",D$6="",NOT(ISNUMBER($H$2))),"",SUMIFS(数据录入!$G$5:$G$4999,数据录入!$C$5:$C$4999,$A14,数据录入!$B$5:$B$4999,D$6)) -> 200 | E14: =IF(OR($A14="",E$6="",NOT(ISNUMBER($H$2))),"",SUMIFS(数据录入!$F$5:$F$4999,数据录入!$C$5:$C$4999,$A14,数据录入!$B$5:$B$4999,E$6)) -> 0 | F14: =IF(OR($A14="",F$6="",NOT(ISNUMBER($H$2))),"",SUMIFS(数据录入!$G$5:$G$4999,数据录入!$C$5:$C$4999,$A14,数据录入!$B$5:$B$4999,F$6)) -> 0 | G14: =IF(OR($A14="",G$6="",NOT(ISNUMBER($H$2))),"",SUMIFS(数据录入!$F$5:$F$4999,数据录入!$C$5:$C$4999,$A14,数据录入!$B$5:$B$4999,G$6)) -> 0 | H14: =IF(OR($A14="",H$6="",NOT(ISNUMBER($H$2))),"",SUMIFS(数据录入!$G$5:$G$4999,数据录入!$C$5:$C$4999,$A14,数据录入!$B$5:$B$4999,H$6)) -> 0 | I14: =IF(OR($A14="",I$6="",NOT(ISNUMBER($H$2))),"",SUMIFS(数据录入!$F$5:$F$4999,数据录入!$C$5:$C$4999,$A14,数据录入!$B$5:$B$4999,I$6)) -> 0 | J14: =IF(OR($A14="",J$6="",NOT(ISNUMBER($H$2))),"",SUMIFS(数据录入!$G$5:$G$4999,数据录入!$C$5:$C$4999,$A14,数据录入!$B$5:$B$4999,J$6)) -> 0 | K14: =IF(OR($A14="",K$6="",NOT(ISNUMBER($H$2))),"",SUMIFS(数据录入!$F$5:$F$4999,数据录入!$C$5:$C$4999,$A14,数据录入!$B$5:$B$4999,K$6)) -> 0 | L14: =IF(OR($A14="",L$6="",NOT(ISNUMBER($H$2))),"",SUMIFS(数据录入!$G$5:$G$4999,数据录入!$C$5:$C$4999,$A14,数据录入!$B$5:$B$4999,L$6)) -> 0 | M14: =IF(OR($A14="",M$6="",NOT(ISNUMBER($H$2))),"",SUMIFS(数据录入!$F$5:$F$4999,数据录入!$C$5:$C$4999,$A14,数据录入!$B$5:$B$4999,M$6)) -> 0 | N14: =IF(OR($A14="",N$6="",NOT(ISNUMBER($H$2))),"",SUMIFS(数据录入!$G$5:$G$4999,数据录入!$C$5:$C$4999,$A14,数据录入!$B$5:$B$4999,N$6)) -> 0 | O14: =IF(OR($A14="",O$6="",NOT(ISNUMBER($H$2))),"",SUMIFS(数据录入!$F$5:$F$4999,数据录入!$C$5:$C$4999,$A14,数据录入!$B$5:$B$4999,O$6)) -> 0 | P14: =IF(OR($A14="",P$6="",NOT(ISNUMBER($H$2))),"",SUMIFS(数据录入!$G$5:$G$4999,数据录入!$C$5:$C$4999,$A14,数据录入!$B$5:$B$4999,P$6)) -> 0 | Q14: =IF(OR($A14="",Q$6="",NOT(ISNUMBER($H$2))),"",SUMIFS(数据录入!$F$5:$F$4999,数据录入!$C$5:$C$4999,$A14,数据录入!$B$5:$B$4999,Q$6)) -> 0 | R14: =IF(OR($A14="",R$6="",NOT(ISNUMBER($H$2))),"",SUMIFS(数据录入!$G$5:$G$4999,数据录入!$C$5:$C$4999,$A14,数据录入!$B$5:$B$4999,R$6)) -> 0 | S14: =IF(OR($A14="",S$6="",NOT(ISNUMBER($H$2))),"",SUMIFS(数据录入!$F$5:$F$4999,数据录入!$C$5:$C$4999,$A14,数据录入!$B$5:$B$4999,S$6)) -> 0 | T14: =IF(OR($A14="",T$6="",NOT(ISNUMBER($H$2))),"",SUMIFS(数据录入!$G$5:$G$4999,数据录入!$C$5:$C$4999,$A14,数据录入!$B$5:$B$4999,T$6)) -> 0 | U14: =IF(OR($A14="",U$6="",NOT(ISNUMBER($H$2))),"",SUMIFS(数据录入!$F$5:$F$4999,数据录入!$C$5:$C$4999,$A14,数据录入!$B$5:$B$4999,U$6)) -> 0 | V14: =IF(OR($A14="",V$6="",NOT(ISNUMBER($H$2))),"",SUMIFS(数据录入!$G$5:$G$4999,数据录入!$C$5:$C$4999,$A14,数据录入!$B$5:$B$4999,V$6)) -> 0 | W14: =IF(OR($A14="",W$6="",NOT(ISNUMBER($H$2))),"",SUMIFS(数据录入!$F$5:$F$4999,数据录入!$C$5:$C$4999,$A14,数据录入!$B$5:$B$4999,W$6)) -> 0 | X14: =IF(OR($A14="",X$6="",NOT(ISNUMBER($H$2))),"",SUMIFS(数据录入!$G$5:$G$4999,数据录入!$C$5:$C$4999,$A14,数据录入!$B$5:$B$4999,X$6)) -> 0 | Y14: =IF(OR($A14="",Y$6="",NOT(ISNUMBER($H$2))),"",SUMIFS(数据录入!$F$5:$F$4999,数据录入!$C$5:$C$4999,$A14,数据录入!$B$5:$B$4999,Y$6)) -> 0 | Z14: =IF(OR($A14="",Z$6="",NOT(ISNUMBER($H$2))),"",SUMIFS(数据录入!$G$5:$G$4999,数据录入!$C$5:$C$4999,$A14,数据录入!$B$5:$B$4999,Z$6)) -> 0 | AA14: =IF(OR($A14="",AA$6="",NOT(ISNUMBER($H$2))),"",SUMIFS(数据录入!$F$5:$F$4999,数据录入!$C$5:$C$4999,$A14,数据录入!$B$5:$B$4999,AA$6)) -> 0 | AB14: =IF(OR($A14="",AB$6="",NOT(ISNUMBER($H$2))),"",SUMIFS(数据录入!$G$5:$G$4999,数据录入!$C$5:$C$4999,$A14,数据录入!$B$5:$B$4999,AB$6)) -> 0 | AC14: =IF(OR($A14="",AC$6="",NOT(ISNUMBER($H$2))),"",SUMIFS(数据录入!$F$5:$F$4999,数据录入!$C$5:$C$4999,$A14,数据录入!$B$5:$B$4999,AC$6)) -> 0 | AD14: =IF(OR($A14="",AD$6="",NOT(ISNUMBER($H$2))),"",SUMIFS(数据录入!$G$5:$G$4999,数据录入!$C$5:$C$4999,$A14,数据录入!$B$5:$B$4999,AD$6)) -> 0 | AE14: =IF(OR($A14="",AE$6="",NOT(ISNUMBER($H$2))),"",SUMIFS(数据录入!$F$5:$F$4999,数据录入!$C$5:$C$4999,$A14,数据录入!$B$5:$B$4999,AE$6)) -> 0 | AF14: =IF(OR($A14="",AF$6="",NOT(ISNUMBER($H$2))),"",SUMIFS(数据录入!$G$5:$G$4999,数据录入!$C$5:$C$4999,$A14,数据录入!$B$5:$B$4999,AF$6)) -> 0 | AG14: =IF(OR($A14="",AG$6="",NOT(ISNUMBER($H$2))),"",SUMIFS(数据录入!$F$5:$F$4999,数据录入!$C$5:$C$4999,$A14,数据录入!$B$5:$B$4999,AG$6)) -> 0 | AH14: =IF(OR($A14="",AH$6="",NOT(ISNUMBER($H$2))),"",SUMIFS(数据录入!$G$5:$G$4999,数据录入!$C$5:$C$4999,$A14,数据录入!$B$5:$B$4999,AH$6)) -> 0 | AI14: =IF(OR($A14="",AI$6="",NOT(ISNUMBER($H$2))),"",SUMIFS(数据录入!$F$5:$F$4999,数据录入!$C$5:$C$4999,$A14,数据录入!$B$5:$B$4999,AI$6)) -> 0 | AJ14: =IF(OR($A14="",AJ$6="",NOT(ISNUMBER($H$2))),"",SUMIFS(数据录入!$G$5:$G$4999,数据录入!$C$5:$C$4999,$A14,数据录入!$B$5:$B$4999,AJ$6)) -> 0 | AK14: =IF(OR($A14="",AK$6="",NOT(ISNUMBER($H$2))),"",SUMIFS(数据录入!$F$5:$F$4999,数据录入!$C$5:$C$4999,$A14,数据录入!$B$5:$B$4999,AK$6)) -> 0 | AL14: =IF(OR($A14="",AL$6="",NOT(ISNUMBER($H$2))),"",SUMIFS(数据录入!$G$5:$G$4999,数据录入!$C$5:$C$4999,$A14,数据录入!$B$5:$B$4999,AL$6)) -> 0 | AM14: =IF(OR($A14="",AM$6="",NOT(ISNUMBER($H$2))),"",SUMIFS(数据录入!$F$5:$F$4999,数据录入!$C$5:$C$4999,$A14,数据录入!$B$5:$B$4999,AM$6)) -> 0 | AN14: =IF(OR($A14="",AN$6="",NOT(ISNUMBER($H$2))),"",SUMIFS(数据录入!$G$5:$G$4999,数据录入!$C$5:$C$4999,$A14,数据录入!$B$5:$B$4999,AN$6)) -> 0 | AO14: =IF(OR($A14="",AO$6="",NOT(ISNUMBER($H$2))),"",SUMIFS(数据录入!$F$5:$F$4999,数据录入!$C$5:$C$4999,$A14,数据录入!$B$5:$B$4999,AO$6)) -> 0 | AP14: =IF(OR($A14="",AP$6="",NOT(ISNUMBER($H$2))),"",SUMIFS(数据录入!$G$5:$G$4999,数据录入!$C$5:$C$4999,$A14,数据录入!$B$5:$B$4999,AP$6)) -> 0 | AQ14: =IF(OR($A14="",AQ$6="",NOT(ISNUMBER($H$2))),"",SUMIFS(数据录入!$F$5:$F$4999,数据录入!$C$5:$C$4999,$A14,数据录入!$B$5:$B$4999,AQ$6)) -> 0 | AR14: =IF(OR($A14="",AR$6="",NOT(ISNUMBER($H$2))),"",SUMIFS(数据录入!$G$5:$G$4999,数据录入!$C$5:$C$4999,$A14,数据录入!$B$5:$B$4999,AR$6)) -> 0 | AS14: =IF(OR($A14="",AS$6="",NOT(ISNUMBER($H$2))),"",SUMIFS(数据录入!$F$5:$F$4999,数据录入!$C$5:$C$4999,$A14,数据录入!$B$5:$B$4999,AS$6)) -> 0 | AT14: =IF(OR($A14="",AT$6="",NOT(ISNUMBER($H$2))),"",SUMIFS(数据录入!$G$5:$G$4999,数据录入!$C$5:$C$4999,$A14,数据录入!$B$5:$B$4999,AT$6)) -> 0 | AU14: =IF(OR($A14="",AU$6="",NOT(ISNUMBER($H$2))),"",SUMIFS(数据录入!$F$5:$F$4999,数据录入!$C$5:$C$4999,$A14,数据录入!$B$5:$B$4999,AU$6)) -> 0 | AV14: =IF(OR($A14="",AV$6="",NOT(ISNUMBER($H$2))),"",SUMIFS(数据录入!$G$5:$G$4999,数据录入!$C$5:$C$4999,$A14,数据录入!$B$5:$B$4999,AV$6)) -> 0 | AW14: =IF(OR($A14="",AW$6="",NOT(ISNUMBER($H$2))),"",SUMIFS(数据录入!$F$5:$F$4999,数据录入!$C$5:$C$4999,$A14,数据录入!$B$5:$B$4999,AW$6)) -> 0 | AX14: =IF(OR($A14="",AX$6="",NOT(ISNUMBER($H$2))),"",SUMIFS(数据录入!$G$5:$G$4999,数据录入!$C$5:$C$4999,$A14,数据录入!$B$5:$B$4999,AX$6)) -> 0 | AY14: =IF(OR($A14="",AY$6="",NOT(ISNUMBER($H$2))),"",SUMIFS(数据录入!$F$5:$F$4999,数据录入!$C$5:$C$4999,$A14,数据录入!$B$5:$B$4999,AY$6)) -> 0 | AZ14: =IF(OR($A14="",AZ$6="",NOT(ISNUMBER($H$2))),"",SUMIFS(数据录入!$G$5:$G$4999,数据录入!$C$5:$C$4999,$A14,数据录入!$B$5:$B$4999,AZ$6)) -> 0 | BA14: =IF(OR($A14="",BA$6="",NOT(ISNUMBER($H$2))),"",SUMIFS(数据录入!$F$5:$F$4999,数据录入!$C$5:$C$4999,$A14,数据录入!$B$5:$B$4999,BA$6)) -> 0 | BB14: =IF(OR($A14="",BB$6="",NOT(ISNUMBER($H$2))),"",SUMIFS(数据录入!$G$5:$G$4999,数据录入!$C$5:$C$4999,$A14,数据录入!$B$5:$B$4999,BB$6)) -> 0 | BC14: =IF(OR($A14="",BC$6="",NOT(ISNUMBER($H$2))),"",SUMIFS(数据录入!$F$5:$F$4999,数据录入!$C$5:$C$4999,$A14,数据录入!$B$5:$B$4999,BC$6)) -> 0 | BD14: =IF(OR($A14="",BD$6="",NOT(ISNUMBER($H$2))),"",SUMIFS(数据录入!$G$5:$G$4999,数据录入!$C$5:$C$4999,$A14,数据录入!$B$5:$B$4999,BD$6)) -> 0 | BE14: =IF(OR($A14="",BE$6="",NOT(ISNUMBER($H$2))),"",SUMIFS(数据录入!$F$5:$F$4999,数据录入!$C$5:$C$4999,$A14,数据录入!$B$5:$B$4999,BE$6)) -> 0 | BF14: =IF(OR($A14="",BF$6="",NOT(ISNUMBER($H$2))),"",SUMIFS(数据录入!$G$5:$G$4999,数据录入!$C$5:$C$4999,$A14,数据录入!$B$5:$B$4999,BF$6)) -> 0 | BG14: =IF(OR($A14="",BG$6="",NOT(ISNUMBER($H$2))),"",SUMIFS(数据录入!$F$5:$F$4999,数据录入!$C$5:$C$4999,$A14,数据录入!$B$5:$B$4999,BG$6)) -> 0 | BH14: =IF(OR($A14="",BH$6="",NOT(ISNUMBER($H$2))),"",SUMIFS(数据录入!$G$5:$G$4999,数据录入!$C$5:$C$4999,$A14,数据录入!$B$5:$B$4999,BH$6)) -> 0 | BI14: =IF(OR($A14="",BI$6="",NOT(ISNUMBER($H$2))),"",SUMIFS(数据录入!$F$5:$F$4999,数据录入!$C$5:$C$4999,$A14,数据录入!$B$5:$B$4999,BI$6)) -> 0 | BJ14: =IF(OR($A14="",BJ$6="",NOT(ISNUMBER($H$2))),"",SUMIFS(数据录入!$G$5:$G$4999,数据录入!$C$5:$C$4999,$A14,数据录入!$B$5:$B$4999,BJ$6)) -> 0 | BK14: =IF(OR($A14="",BK$6="",NOT(ISNUMBER($H$2))),"",SUMIFS(数据录入!$F$5:$F$4999,数据录入!$C$5:$C$4999,$A14,数据录入!$B$5:$B$4999,BK$6)) | BL14: =IF(OR($A14="",BL$6="",NOT(ISNUMBER($H$2))),"",SUMIFS(数据录入!$G$5:$G$4999,数据录入!$C$5:$C$4999,$A14,数据录入!$B$5:$B$4999,BL$6)) | BM14: =IF($A14="","",SUMIF($C$7:$BL$7,"收款",C14:BL14)) -> 10000 | BN14: =IF($A14="","",SUMIF($C$7:$BL$7,"付款",C14:BL14)) -> 200 | BO14: =IF($A14="","",B14+BM14-BN14) -> 9800
A15: 备用2 | B15: =IF(OR($A15="",NOT(ISNUMBER($H$2))),"",SUMIFS(数据录入!$H$5:$H$4999,数据录入!$C$5:$C$4999,$A15,数据录入!$E$5:$E$4999,"期初余额",数据录入!$B$5:$B$4999,"<="&$B$2)+SUMIFS(数据录入!$F$5:$F$4999,数据录入!$C$5:$C$4999,$A15,数据录入!$B$5:$B$4999,"<"&$B$2)-SUMIFS(数据录入!$G$5:$G$4999,数据录入!$C$5:$C$4999,$A15,数据录入!$B$5:$B$4999,"<"&$B$2)) -> 0 | C15: =IF(OR($A15="",C$6="",NOT(ISNUMBER($H$2))),"",SUMIFS(数据录入!$F$5:$F$4999,数据录入!$C$5:$C$4999,$A15,数据录入!$B$5:$B$4999,C$6)) -> 1000 | D15: =IF(OR($A15="",D$6="",NOT(ISNUMBER($H$2))),"",SUMIFS(数据录入!$G$5:$G$4999,数据录入!$C$5:$C$4999,$A15,数据录入!$B$5:$B$4999,D$6)) -> 10 | E15: =IF(OR($A15="",E$6="",NOT(ISNUMBER($H$2))),"",SUMIFS(数据录入!$F$5:$F$4999,数据录入!$C$5:$C$4999,$A15,数据录入!$B$5:$B$4999,E$6)) -> 0 | F15: =IF(OR($A15="",F$6="",NOT(ISNUMBER($H$2))),"",SUMIFS(数据录入!$G$5:$G$4999,数据录入!$C$5:$C$4999,$A15,数据录入!$B$5:$B$4999,F$6)) -> 0 | G15: =IF(OR($A15="",G$6="",NOT(ISNUMBER($H$2))),"",SUMIFS(数据录入!$F$5:$F$4999,数据录入!$C$5:$C$4999,$A15,数据录入!$B$5:$B$4999,G$6)) -> 0 | H15: =IF(OR($A15="",H$6="",NOT(ISNUMBER($H$2))),"",SUMIFS(数据录入!$G$5:$G$4999,数据录入!$C$5:$C$4999,$A15,数据录入!$B$5:$B$4999,H$6)) -> 0 | I15: =IF(OR($A15="",I$6="",NOT(ISNUMBER($H$2))),"",SUMIFS(数据录入!$F$5:$F$4999,数据录入!$C$5:$C$4999,$A15,数据录入!$B$5:$B$4999,I$6)) -> 0 | J15: =IF(OR($A15="",J$6="",NOT(ISNUMBER($H$2))),"",SUMIFS(数据录入!$G$5:$G$4999,数据录入!$C$5:$C$4999,$A15,数据录入!$B$5:$B$4999,J$6)) -> 0 | K15: =IF(OR($A15="",K$6="",NOT(ISNUMBER($H$2))),"",SUMIFS(数据录入!$F$5:$F$4999,数据录入!$C$5:$C$4999,$A15,数据录入!$B$5:$B$4999,K$6)) -> 0 | L15: =IF(OR($A15="",L$6="",NOT(ISNUMBER($H$2))),"",SUMIFS(数据录入!$G$5:$G$4999,数据录入!$C$5:$C$4999,$A15,数据录入!$B$5:$B$4999,L$6)) -> 0 | M15: =IF(OR($A15="",M$6="",NOT(ISNUMBER($H$2))),"",SUMIFS(数据录入!$F$5:$F$4999,数据录入!$C$5:$C$4999,$A15,数据录入!$B$5:$B$4999,M$6)) -> 0 | N15: =IF(OR($A15="",N$6="",NOT(ISNUMBER($H$2))),"",SUMIFS(数据录入!$G$5:$G$4999,数据录入!$C$5:$C$4999,$A15,数据录入!$B$5:$B$4999,N$6)) -> 0 | O15: =IF(OR($A15="",O$6="",NOT(ISNUMBER($H$2))),"",SUMIFS(数据录入!$F$5:$F$4999,数据录入!$C$5:$C$4999,$A15,数据录入!$B$5:$B$4999,O$6)) -> 0 | P15: =IF(OR($A15="",P$6="",NOT(ISNUMBER($H$2))),"",SUMIFS(数据录入!$G$5:$G$4999,数据录入!$C$5:$C$4999,$A15,数据录入!$B$5:$B$4999,P$6)) -> 0 | Q15: =IF(OR($A15="",Q$6="",NOT(ISNUMBER($H$2))),"",SUMIFS(数据录入!$F$5:$F$4999,数据录入!$C$5:$C$4999,$A15,数据录入!$B$5:$B$4999,Q$6)) -> 0 | R15: =IF(OR($A15="",R$6="",NOT(ISNUMBER($H$2))),"",SUMIFS(数据录入!$G$5:$G$4999,数据录入!$C$5:$C$4999,$A15,数据录入!$B$5:$B$4999,R$6)) -> 0 | S15: =IF(OR($A15="",S$6="",NOT(ISNUMBER($H$2))),"",SUMIFS(数据录入!$F$5:$F$4999,数据录入!$C$5:$C$4999,$A15,数据录入!$B$5:$B$4999,S$6)) -> 0 | T15: =IF(OR($A15="",T$6="",NOT(ISNUMBER($H$2))),"",SUMIFS(数据录入!$G$5:$G$4999,数据录入!$C$5:$C$4999,$A15,数据录入!$B$5:$B$4999,T$6)) -> 0 | U15: =IF(OR($A15="",U$6="",NOT(ISNUMBER($H$2))),"",SUMIFS(数据录入!$F$5:$F$4999,数据录入!$C$5:$C$4999,$A15,数据录入!$B$5:$B$4999,U$6)) -> 0 | V15: =IF(OR($A15="",V$6="",NOT(ISNUMBER($H$2))),"",SUMIFS(数据录入!$G$5:$G$4999,数据录入!$C$5:$C$4999,$A15,数据录入!$B$5:$B$4999,V$6)) -> 0 | W15: =IF(OR($A15="",W$6="",NOT(ISNUMBER($H$2))),"",SUMIFS(数据录入!$F$5:$F$4999,数据录入!$C$5:$C$4999,$A15,数据录入!$B$5:$B$4999,W$6)) -> 0 | X15: =IF(OR($A15="",X$6="",NOT(ISNUMBER($H$2))),"",SUMIFS(数据录入!$G$5:$G$4999,数据录入!$C$5:$C$4999,$A15,数据录入!$B$5:$B$4999,X$6)) -> 0 | Y15: =IF(OR($A15="",Y$6="",NOT(ISNUMBER($H$2))),"",SUMIFS(数据录入!$F$5:$F$4999,数据录入!$C$5:$C$4999,$A15,数据录入!$B$5:$B$4999,Y$6)) -> 0 | Z15: =IF(OR($A15="",Z$6="",NOT(ISNUMBER($H$2))),"",SUMIFS(数据录入!$G$5:$G$4999,数据录入!$C$5:$C$4999,$A15,数据录入!$B$5:$B$4999,Z$6)) -> 0 | AA15: =IF(OR($A15="",AA$6="",NOT(ISNUMBER($H$2))),"",SUMIFS(数据录入!$F$5:$F$4999,数据录入!$C$5:$C$4999,$A15,数据录入!$B$5:$B$4999,AA$6)) -> 0 | AB15: =IF(OR($A15="",AB$6="",NOT(ISNUMBER($H$2))),"",SUMIFS(数据录入!$G$5:$G$4999,数据录入!$C$5:$C$4999,$A15,数据录入!$B$5:$B$4999,AB$6)) -> 0 | AC15: =IF(OR($A15="",AC$6="",NOT(ISNUMBER($H$2))),"",SUMIFS(数据录入!$F$5:$F$4999,数据录入!$C$5:$C$4999,$A15,数据录入!$B$5:$B$4999,AC$6)) -> 0 | AD15: =IF(OR($A15="",AD$6="",NOT(ISNUMBER($H$2))),"",SUMIFS(数据录入!$G$5:$G$4999,数据录入!$C$5:$C$4999,$A15,数据录入!$B$5:$B$4999,AD$6)) -> 0 | AE15: =IF(OR($A15="",AE$6="",NOT(ISNUMBER($H$2))),"",SUMIFS(数据录入!$F$5:$F$4999,数据录入!$C$5:$C$4999,$A15,数据录入!$B$5:$B$4999,AE$6)) -> 0 | AF15: =IF(OR($A15="",AF$6="",NOT(ISNUMBER($H$2))),"",SUMIFS(数据录入!$G$5:$G$4999,数据录入!$C$5:$C$4999,$A15,数据录入!$B$5:$B$4999,AF$6)) -> 0 | AG15: =IF(OR($A15="",AG$6="",NOT(ISNUMBER($H$2))),"",SUMIFS(数据录入!$F$5:$F$4999,数据录入!$C$5:$C$4999,$A15,数据录入!$B$5:$B$4999,AG$6)) -> 0 | AH15: =IF(OR($A15="",AH$6="",NOT(ISNUMBER($H$2))),"",SUMIFS(数据录入!$G$5:$G$4999,数据录入!$C$5:$C$4999,$A15,数据录入!$B$5:$B$4999,AH$6)) -> 0 | AI15: =IF(OR($A15="",AI$6="",NOT(ISNUMBER($H$2))),"",SUMIFS(数据录入!$F$5:$F$4999,数据录入!$C$5:$C$4999,$A15,数据录入!$B$5:$B$4999,AI$6)) -> 0 | AJ15: =IF(OR($A15="",AJ$6="",NOT(ISNUMBER($H$2))),"",SUMIFS(数据录入!$G$5:$G$4999,数据录入!$C$5:$C$4999,$A15,数据录入!$B$5:$B$4999,AJ$6)) -> 0 | AK15: =IF(OR($A15="",AK$6="",NOT(ISNUMBER($H$2))),"",SUMIFS(数据录入!$F$5:$F$4999,数据录入!$C$5:$C$4999,$A15,数据录入!$B$5:$B$4999,AK$6)) -> 0 | AL15: =IF(OR($A15="",AL$6="",NOT(ISNUMBER($H$2))),"",SUMIFS(数据录入!$G$5:$G$4999,数据录入!$C$5:$C$4999,$A15,数据录入!$B$5:$B$4999,AL$6)) -> 0 | AM15: =IF(OR($A15="",AM$6="",NOT(ISNUMBER($H$2))),"",SUMIFS(数据录入!$F$5:$F$4999,数据录入!$C$5:$C$4999,$A15,数据录入!$B$5:$B$4999,AM$6)) -> 0 | AN15: =IF(OR($A15="",AN$6="",NOT(ISNUMBER($H$2))),"",SUMIFS(数据录入!$G$5:$G$4999,数据录入!$C$5:$C$4999,$A15,数据录入!$B$5:$B$4999,AN$6)) -> 0 | AO15: =IF(OR($A15="",AO$6="",NOT(ISNUMBER($H$2))),"",SUMIFS(数据录入!$F$5:$F$4999,数据录入!$C$5:$C$4999,$A15,数据录入!$B$5:$B$4999,AO$6)) -> 0 | AP15: =IF(OR($A15="",AP$6="",NOT(ISNUMBER($H$2))),"",SUMIFS(数据录入!$G$5:$G$4999,数据录入!$C$5:$C$4999,$A15,数据录入!$B$5:$B$4999,AP$6)) -> 0 | AQ15: =IF(OR($A15="",AQ$6="",NOT(ISNUMBER($H$2))),"",SUMIFS(数据录入!$F$5:$F$4999,数据录入!$C$5:$C$4999,$A15,数据录入!$B$5:$B$4999,AQ$6)) -> 0 | AR15: =IF(OR($A15="",AR$6="",NOT(ISNUMBER($H$2))),"",SUMIFS(数据录入!$G$5:$G$4999,数据录入!$C$5:$C$4999,$A15,数据录入!$B$5:$B$4999,AR$6)) -> 0 | AS15: =IF(OR($A15="",AS$6="",NOT(ISNUMBER($H$2))),"",SUMIFS(数据录入!$F$5:$F$4999,数据录入!$C$5:$C$4999,$A15,数据录入!$B$5:$B$4999,AS$6)) -> 0 | AT15: =IF(OR($A15="",AT$6="",NOT(ISNUMBER($H$2))),"",SUMIFS(数据录入!$G$5:$G$4999,数据录入!$C$5:$C$4999,$A15,数据录入!$B$5:$B$4999,AT$6)) -> 0 | AU15: =IF(OR($A15="",AU$6="",NOT(ISNUMBER($H$2))),"",SUMIFS(数据录入!$F$5:$F$4999,数据录入!$C$5:$C$4999,$A15,数据录入!$B$5:$B$4999,AU$6)) -> 0 | AV15: =IF(OR($A15="",AV$6="",NOT(ISNUMBER($H$2))),"",SUMIFS(数据录入!$G$5:$G$4999,数据录入!$C$5:$C$4999,$A15,数据录入!$B$5:$B$4999,AV$6)) -> 0 | AW15: =IF(OR($A15="",AW$6="",NOT(ISNUMBER($H$2))),"",SUMIFS(数据录入!$F$5:$F$4999,数据录入!$C$5:$C$4999,$A15,数据录入!$B$5:$B$4999,AW$6)) -> 0 | AX15: =IF(OR($A15="",AX$6="",NOT(ISNUMBER($H$2))),"",SUMIFS(数据录入!$G$5:$G$4999,数据录入!$C$5:$C$4999,$A15,数据录入!$B$5:$B$4999,AX$6)) -> 0 | AY15: =IF(OR($A15="",AY$6="",NOT(ISNUMBER($H$2))),"",SUMIFS(数据录入!$F$5:$F$4999,数据录入!$C$5:$C$4999,$A15,数据录入!$B$5:$B$4999,AY$6)) -> 0 | AZ15: =IF(OR($A15="",AZ$6="",NOT(ISNUMBER($H$2))),"",SUMIFS(数据录入!$G$5:$G$4999,数据录入!$C$5:$C$4999,$A15,数据录入!$B$5:$B$4999,AZ$6)) -> 0 | BA15: =IF(OR($A15="",BA$6="",NOT(ISNUMBER($H$2))),"",SUMIFS(数据录入!$F$5:$F$4999,数据录入!$C$5:$C$4999,$A15,数据录入!$B$5:$B$4999,BA$6)) -> 0 | BB15: =IF(OR($A15="",BB$6="",NOT(ISNUMBER($H$2))),"",SUMIFS(数据录入!$G$5:$G$4999,数据录入!$C$5:$C$4999,$A15,数据录入!$B$5:$B$4999,BB$6)) -> 0 | BC15: =IF(OR($A15="",BC$6="",NOT(ISNUMBER($H$2))),"",SUMIFS(数据录入!$F$5:$F$4999,数据录入!$C$5:$C$4999,$A15,数据录入!$B$5:$B$4999,BC$6)) -> 0 | BD15: =IF(OR($A15="",BD$6="",NOT(ISNUMBER($H$2))),"",SUMIFS(数据录入!$G$5:$G$4999,数据录入!$C$5:$C$4999,$A15,数据录入!$B$5:$B$4999,BD$6)) -> 0 | BE15: =IF(OR($A15="",BE$6="",NOT(ISNUMBER($H$2))),"",SUMIFS(数据录入!$F$5:$F$4999,数据录入!$C$5:$C$4999,$A15,数据录入!$B$5:$B$4999,BE$6)) -> 0 | BF15: =IF(OR($A15="",BF$6="",NOT(ISNUMBER($H$2))),"",SUMIFS(数据录入!$G$5:$G$4999,数据录入!$C$5:$C$4999,$A15,数据录入!$B$5:$B$4999,BF$6)) -> 0 | BG15: =IF(OR($A15="",BG$6="",NOT(ISNUMBER($H$2))),"",SUMIFS(数据录入!$F$5:$F$4999,数据录入!$C$5:$C$4999,$A15,数据录入!$B$5:$B$4999,BG$6)) -> 0 | BH15: =IF(OR($A15="",BH$6="",NOT(ISNUMBER($H$2))),"",SUMIFS(数据录入!$G$5:$G$4999,数据录入!$C$5:$C$4999,$A15,数据录入!$B$5:$B$4999,BH$6)) -> 0 | BI15: =IF(OR($A15="",BI$6="",NOT(ISNUMBER($H$2))),"",SUMIFS(数据录入!$F$5:$F$4999,数据录入!$C$5:$C$4999,$A15,数据录入!$B$5:$B$4999,BI$6)) -> 0 | BJ15: =IF(OR($A15="",BJ$6="",NOT(ISNUMBER($H$2))),"",SUMIFS(数据录入!$G$5:$G$4999,数据录入!$C$5:$C$4999,$A15,数据录入!$B$5:$B$4999,BJ$6)) -> 0 | BK15: =IF(OR($A15="",BK$6="",NOT(ISNUMBER($H$2))),"",SUMIFS(数据录入!$F$5:$F$4999,数据录入!$C$5:$C$4999,$A15,数据录入!$B$5:$B$4999,BK$6)) | BL15: =IF(OR($A15="",BL$6="",NOT(ISNUMBER($H$2))),"",SUMIFS(数据录入!$G$5:$G$4999,数据录入!$C$5:$C$4999,$A15,数据录入!$B$5:$B$4999,BL$6)) | BM15: =IF($A15="","",SUMIF($C$7:$BL$7,"收款",C15:BL15)) -> 1000 | BN15: =IF($A15="","",SUMIF($C$7:$BL$7,"付款",C15:BL15)) -> 10 | BO15: =IF($A15="","",B15+BM15-BN15) -> 990
A16: 备用3 | B16: =IF(OR($A16="",NOT(ISNUMBER($H$2))),"",SUMIFS(数据录入!$H$5:$H$4999,数据录入!$C$5:$C$4999,$A16,数据录入!$E$5:$E$4999,"期初余额",数据录入!$B$5:$B$4999,"<="&$B$2)+SUMIFS(数据录入!$F$5:$F$4999,数据录入!$C$5:$C$4999,$A16,数据录入!$B$5:$B$4999,"<"&$B$2)-SUMIFS(数据录入!$G$5:$G$4999,数据录入!$C$5:$C$4999,$A16,数据录入!$B$5:$B$4999,"<"&$B$2)) -> 0 | C16: =IF(OR($A16="",C$6="",NOT(ISNUMBER($H$2))),"",SUMIFS(数据录入!$F$5:$F$4999,数据录入!$C$5:$C$4999,$A16,数据录入!$B$5:$B$4999,C$6)) -> -1000 | D16: =IF(OR($A16="",D$6="",NOT(ISNUMBER($H$2))),"",SUMIFS(数据录入!$G$5:$G$4999,数据录入!$C$5:$C$4999,$A16,数据录入!$B$5:$B$4999,D$6)) -> 50 | E16: =IF(OR($A16="",E$6="",NOT(ISNUMBER($H$2))),"",SUMIFS(数据录入!$F$5:$F$4999,数据录入!$C$5:$C$4999,$A16,数据录入!$B$5:$B$4999,E$6)) -> 0 | F16: =IF(OR($A16="",F$6="",NOT(ISNUMBER($H$2))),"",SUMIFS(数据录入!$G$5:$G$4999,数据录入!$C$5:$C$4999,$A16,数据录入!$B$5:$B$4999,F$6)) -> 0 | G16: =IF(OR($A16="",G$6="",NOT(ISNUMBER($H$2))),"",SUMIFS(数据录入!$F$5:$F$4999,数据录入!$C$5:$C$4999,$A16,数据录入!$B$5:$B$4999,G$6)) -> 0 | H16: =IF(OR($A16="",H$6="",NOT(ISNUMBER($H$2))),"",SUMIFS(数据录入!$G$5:$G$4999,数据录入!$C$5:$C$4999,$A16,数据录入!$B$5:$B$4999,H$6)) -> 0 | I16: =IF(OR($A16="",I$6="",NOT(ISNUMBER($H$2))),"",SUMIFS(数据录入!$F$5:$F$4999,数据录入!$C$5:$C$4999,$A16,数据录入!$B$5:$B$4999,I$6)) -> 0 | J16: =IF(OR($A16="",J$6="",NOT(ISNUMBER($H$2))),"",SUMIFS(数据录入!$G$5:$G$4999,数据录入!$C$5:$C$4999,$A16,数据录入!$B$5:$B$4999,J$6)) -> 0 | K16: =IF(OR($A16="",K$6="",NOT(ISNUMBER($H$2))),"",SUMIFS(数据录入!$F$5:$F$4999,数据录入!$C$5:$C$4999,$A16,数据录入!$B$5:$B$4999,K$6)) -> 0 | L16: =IF(OR($A16="",L$6="",NOT(ISNUMBER($H$2))),"",SUMIFS(数据录入!$G$5:$G$4999,数据录入!$C$5:$C$4999,$A16,数据录入!$B$5:$B$4999,L$6)) -> 0 | M16: =IF(OR($A16="",M$6="",NOT(ISNUMBER($H$2))),"",SUMIFS(数据录入!$F$5:$F$4999,数据录入!$C$5:$C$4999,$A16,数据录入!$B$5:$B$4999,M$6)) -> 0 | N16: =IF(OR($A16="",N$6="",NOT(ISNUMBER($H$2))),"",SUMIFS(数据录入!$G$5:$G$4999,数据录入!$C$5:$C$4999,$A16,数据录入!$B$5:$B$4999,N$6)) -> 0 | O16: =IF(OR($A16="",O$6="",NOT(ISNUMBER($H$2))),"",SUMIFS(数据录入!$F$5:$F$4999,数据录入!$C$5:$C$4999,$A16,数据录入!$B$5:$B$4999,O$6)) -> 0 | P16: =IF(OR($A16="",P$6="",NOT(ISNUMBER($H$2))),"",SUMIFS(数据录入!$G$5:$G$4999,数据录入!$C$5:$C$4999,$A16,数据录入!$B$5:$B$4999,P$6)) -> 0 | Q16: =IF(OR($A16="",Q$6="",NOT(ISNUMBER($H$2))),"",SUMIFS(数据录入!$F$5:$F$4999,数据录入!$C$5:$C$4999,$A16,数据录入!$B$5:$B$4999,Q$6)) -> 0 | R16: =IF(OR($A16="",R$6="",NOT(ISNUMBER($H$2))),"",SUMIFS(数据录入!$G$5:$G$4999,数据录入!$C$5:$C$4999,$A16,数据录入!$B$5:$B$4999,R$6)) -> 0 | S16: =IF(OR($A16="",S$6="",NOT(ISNUMBER($H$2))),"",SUMIFS(数据录入!$F$5:$F$4999,数据录入!$C$5:$C$4999,$A16,数据录入!$B$5:$B$4999,S$6)) -> 0 | T16: =IF(OR($A16="",T$6="",NOT(ISNUMBER($H$2))),"",SUMIFS(数据录入!$G$5:$G$4999,数据录入!$C$5:$C$4999,$A16,数据录入!$B$5:$B$4999,T$6)) -> 0 | U16: =IF(OR($A16="",U$6="",NOT(ISNUMBER($H$2))),"",SUMIFS(数据录入!$F$5:$F$4999,数据录入!$C$5:$C$4999,$A16,数据录入!$B$5:$B$4999,U$6)) -> 0 | V16: =IF(OR($A16="",V$6="",NOT(ISNUMBER($H$2))),"",SUMIFS(数据录入!$G$5:$G$4999,数据录入!$C$5:$C$4999,$A16,数据录入!$B$5:$B$4999,V$6)) -> 0 | W16: =IF(OR($A16="",W$6="",NOT(ISNUMBER($H$2))),"",SUMIFS(数据录入!$F$5:$F$4999,数据录入!$C$5:$C$4999,$A16,数据录入!$B$5:$B$4999,W$6)) -> 0 | X16: =IF(OR($A16="",X$6="",NOT(ISNUMBER($H$2))),"",SUMIFS(数据录入!$G$5:$G$4999,数据录入!$C$5:$C$4999,$A16,数据录入!$B$5:$B$4999,X$6)) -> 0 | Y16: =IF(OR($A16="",Y$6="",NOT(ISNUMBER($H$2))),"",SUMIFS(数据录入!$F$5:$F$4999,数据录入!$C$5:$C$4999,$A16,数据录入!$B$5:$B$4999,Y$6)) -> 0 | Z16: =IF(OR($A16="",Z$6="",NOT(ISNUMBER($H$2))),"",SUMIFS(数据录入!$G$5:$G$4999,数据录入!$C$5:$C$4999,$A16,数据录入!$B$5:$B$4999,Z$6)) -> 0 | AA16: =IF(OR($A16="",AA$6="",NOT(ISNUMBER($H$2))),"",SUMIFS(数据录入!$F$5:$F$4999,数据录入!$C$5:$C$4999,$A16,数据录入!$B$5:$B$4999,AA$6)) -> 0 | AB16: =IF(OR($A16="",AB$6="",NOT(ISNUMBER($H$2))),"",SUMIFS(数据录入!$G$5:$G$4999,数据录入!$C$5:$C$4999,$A16,数据录入!$B$5:$B$4999,AB$6)) -> 0 | AC16: =IF(OR($A16="",AC$6="",NOT(ISNUMBER($H$2))),"",SUMIFS(数据录入!$F$5:$F$4999,数据录入!$C$5:$C$4999,$A16,数据录入!$B$5:$B$4999,AC$6)) -> 0 | AD16: =IF(OR($A16="",AD$6="",NOT(ISNUMBER($H$2))),"",SUMIFS(数据录入!$G$5:$G$4999,数据录入!$C$5:$C$4999,$A16,数据录入!$B$5:$B$4999,AD$6)) -> 0 | AE16: =IF(OR($A16="",AE$6="",NOT(ISNUMBER($H$2))),"",SUMIFS(数据录入!$F$5:$F$4999,数据录入!$C$5:$C$4999,$A16,数据录入!$B$5:$B$4999,AE$6)) -> 0 | AF16: =IF(OR($A16="",AF$6="",NOT(ISNUMBER($H$2))),"",SUMIFS(数据录入!$G$5:$G$4999,数据录入!$C$5:$C$4999,$A16,数据录入!$B$5:$B$4999,AF$6)) -> 0 | AG16: =IF(OR($A16="",AG$6="",NOT(ISNUMBER($H$2))),"",SUMIFS(数据录入!$F$5:$F$4999,数据录入!$C$5:$C$4999,$A16,数据录入!$B$5:$B$4999,AG$6)) -> 0 | AH16: =IF(OR($A16="",AH$6="",NOT(ISNUMBER($H$2))),"",SUMIFS(数据录入!$G$5:$G$4999,数据录入!$C$5:$C$4999,$A16,数据录入!$B$5:$B$4999,AH$6)) -> 0 | AI16: =IF(OR($A16="",AI$6="",NOT(ISNUMBER($H$2))),"",SUMIFS(数据录入!$F$5:$F$4999,数据录入!$C$5:$C$4999,$A16,数据录入!$B$5:$B$4999,AI$6)) -> 0 | AJ16: =IF(OR($A16="",AJ$6="",NOT(ISNUMBER($H$2))),"",SUMIFS(数据录入!$G$5:$G$4999,数据录入!$C$5:$C$4999,$A16,数据录入!$B$5:$B$4999,AJ$6)) -> 0 | AK16: =IF(OR($A16="",AK$6="",NOT(ISNUMBER($H$2))),"",SUMIFS(数据录入!$F$5:$F$4999,数据录入!$C$5:$C$4999,$A16,数据录入!$B$5:$B$4999,AK$6)) -> 0 | AL16: =IF(OR($A16="",AL$6="",NOT(ISNUMBER($H$2))),"",SUMIFS(数据录入!$G$5:$G$4999,数据录入!$C$5:$C$4999,$A16,数据录入!$B$5:$B$4999,AL$6)) -> 0 | AM16: =IF(OR($A16="",AM$6="",NOT(ISNUMBER($H$2))),"",SUMIFS(数据录入!$F$5:$F$4999,数据录入!$C$5:$C$4999,$A16,数据录入!$B$5:$B$4999,AM$6)) -> 0 | AN16: =IF(OR($A16="",AN$6="",NOT(ISNUMBER($H$2))),"",SUMIFS(数据录入!$G$5:$G$4999,数据录入!$C$5:$C$4999,$A16,数据录入!$B$5:$B$4999,AN$6)) -> 0 | AO16: =IF(OR($A16="",AO$6="",NOT(ISNUMBER($H$2))),"",SUMIFS(数据录入!$F$5:$F$4999,数据录入!$C$5:$C$4999,$A16,数据录入!$B$5:$B$4999,AO$6)) -> 0 | AP16: =IF(OR($A16="",AP$6="",NOT(ISNUMBER($H$2))),"",SUMIFS(数据录入!$G$5:$G$4999,数据录入!$C$5:$C$4999,$A16,数据录入!$B$5:$B$4999,AP$6)) -> 0 | AQ16: =IF(OR($A16="",AQ$6="",NOT(ISNUMBER($H$2))),"",SUMIFS(数据录入!$F$5:$F$4999,数据录入!$C$5:$C$4999,$A16,数据录入!$B$5:$B$4999,AQ$6)) -> 0 | AR16: =IF(OR($A16="",AR$6="",NOT(ISNUMBER($H$2))),"",SUMIFS(数据录入!$G$5:$G$4999,数据录入!$C$5:$C$4999,$A16,数据录入!$B$5:$B$4999,AR$6)) -> 0 | AS16: =IF(OR($A16="",AS$6="",NOT(ISNUMBER($H$2))),"",SUMIFS(数据录入!$F$5:$F$4999,数据录入!$C$5:$C$4999,$A16,数据录入!$B$5:$B$4999,AS$6)) -> 0 | AT16: =IF(OR($A16="",AT$6="",NOT(ISNUMBER($H$2))),"",SUMIFS(数据录入!$G$5:$G$4999,数据录入!$C$5:$C$4999,$A16,数据录入!$B$5:$B$4999,AT$6)) -> 0 | AU16: =IF(OR($A16="",AU$6="",NOT(ISNUMBER($H$2))),"",SUMIFS(数据录入!$F$5:$F$4999,数据录入!$C$5:$C$4999,$A16,数据录入!$B$5:$B$4999,AU$6)) -> 0 | AV16: =IF(OR($A16="",AV$6="",NOT(ISNUMBER($H$2))),"",SUMIFS(数据录入!$G$5:$G$4999,数据录入!$C$5:$C$4999,$A16,数据录入!$B$5:$B$4999,AV$6)) -> 0 | AW16: =IF(OR($A16="",AW$6="",NOT(ISNUMBER($H$2))),"",SUMIFS(数据录入!$F$5:$F$4999,数据录入!$C$5:$C$4999,$A16,数据录入!$B$5:$B$4999,AW$6)) -> 0 | AX16: =IF(OR($A16="",AX$6="",NOT(ISNUMBER($H$2))),"",SUMIFS(数据录入!$G$5:$G$4999,数据录入!$C$5:$C$4999,$A16,数据录入!$B$5:$B$4999,AX$6)) -> 0 | AY16: =IF(OR($A16="",AY$6="",NOT(ISNUMBER($H$2))),"",SUMIFS(数据录入!$F$5:$F$4999,数据录入!$C$5:$C$4999,$A16,数据录入!$B$5:$B$4999,AY$6)) -> 0 | AZ16: =IF(OR($A16="",AZ$6="",NOT(ISNUMBER($H$2))),"",SUMIFS(数据录入!$G$5:$G$4999,数据录入!$C$5:$C$4999,$A16,数据录入!$B$5:$B$4999,AZ$6)) -> 0 | BA16: =IF(OR($A16="",BA$6="",NOT(ISNUMBER($H$2))),"",SUMIFS(数据录入!$F$5:$F$4999,数据录入!$C$5:$C$4999,$A16,数据录入!$B$5:$B$4999,BA$6)) -> 0 | BB16: =IF(OR($A16="",BB$6="",NOT(ISNUMBER($H$2))),"",SUMIFS(数据录入!$G$5:$G$4999,数据录入!$C$5:$C$4999,$A16,数据录入!$B$5:$B$4999,BB$6)) -> 0 | BC16: =IF(OR($A16="",BC$6="",NOT(ISNUMBER($H$2))),"",SUMIFS(数据录入!$F$5:$F$4999,数据录入!$C$5:$C$4999,$A16,数据录入!$B$5:$B$4999,BC$6)) -> 0 | BD16: =IF(OR($A16="",BD$6="",NOT(ISNUMBER($H$2))),"",SUMIFS(数据录入!$G$5:$G$4999,数据录入!$C$5:$C$4999,$A16,数据录入!$B$5:$B$4999,BD$6)) -> 0 | BE16: =IF(OR($A16="",BE$6="",NOT(ISNUMBER($H$2))),"",SUMIFS(数据录入!$F$5:$F$4999,数据录入!$C$5:$C$4999,$A16,数据录入!$B$5:$B$4999,BE$6)) -> 0 | BF16: =IF(OR($A16="",BF$6="",NOT(ISNUMBER($H$2))),"",SUMIFS(数据录入!$G$5:$G$4999,数据录入!$C$5:$C$4999,$A16,数据录入!$B$5:$B$4999,BF$6)) -> 0 | BG16: =IF(OR($A16="",BG$6="",NOT(ISNUMBER($H$2))),"",SUMIFS(数据录入!$F$5:$F$4999,数据录入!$C$5:$C$4999,$A16,数据录入!$B$5:$B$4999,BG$6)) -> 0 | BH16: =IF(OR($A16="",BH$6="",NOT(ISNUMBER($H$2))),"",SUMIFS(数据录入!$G$5:$G$4999,数据录入!$C$5:$C$4999,$A16,数据录入!$B$5:$B$4999,BH$6)) -> 0 | BI16: =IF(OR($A16="",BI$6="",NOT(ISNUMBER($H$2))),"",SUMIFS(数据录入!$F$5:$F$4999,数据录入!$C$5:$C$4999,$A16,数据录入!$B$5:$B$4999,BI$6)) -> 0 | BJ16: =IF(OR($A16="",BJ$6="",NOT(ISNUMBER($H$2))),"",SUMIFS(数据录入!$G$5:$G$4999,数据录入!$C$5:$C$4999,$A16,数据录入!$B$5:$B$4999,BJ$6)) -> 0 | BK16: =IF(OR($A16="",BK$6="",NOT(ISNUMBER($H$2))),"",SUMIFS(数据录入!$F$5:$F$4999,数据录入!$C$5:$C$4999,$A16,数据录入!$B$5:$B$4999,BK$6)) | BL16: =IF(OR($A16="",BL$6="",NOT(ISNUMBER($H$2))),"",SUMIFS(数据录入!$G$5:$G$4999,数据录入!$C$5:$C$4999,$A16,数据录入!$B$5:$B$4999,BL$6)) | BM16: =IF($A16="","",SUMIF($C$7:$BL$7,"收款",C16:BL16)) -> -1000 | BN16: =IF($A16="","",SUMIF($C$7:$BL$7,"付款",C16:BL16)) -> 50 | BO16: =IF($A16="","",B16+BM16-BN16) -> -1050
A17: 备用4 | B17: =IF(OR($A17="",NOT(ISNUMBER($H$2))),"",SUMIFS(数据录入!$H$5:$H$4999,数据录入!$C$5:$C$4999,$A17,数据录入!$E$5:$E$4999,"期初余额",数据录入!$B$5:$B$4999,"<="&$B$2)+SUMIFS(数据录入!$F$5:$F$4999,数据录入!$C$5:$C$4999,$A17,数据录入!$B$5:$B$4999,"<"&$B$2)-SUMIFS(数据录入!$G$5:$G$4999,数据录入!$C$5:$C$4999,$A17,数据录入!$B$5:$B$4999,"<"&$B$2)) -> 0 | C17: =IF(OR($A17="",C$6="",NOT(ISNUMBER($H$2))),"",SUMIFS(数据录入!$F$5:$F$4999,数据录入!$C$5:$C$4999,$A17,数据录入!$B$5:$B$4999,C$6)) -> 2100 | D17: =IF(OR($A17="",D$6="",NOT(ISNUMBER($H$2))),"",SUMIFS(数据录入!$G$5:$G$4999,数据录入!$C$5:$C$4999,$A17,数据录入!$B$5:$B$4999,D$6)) -> 0 | E17: =IF(OR($A17="",E$6="",NOT(ISNUMBER($H$2))),"",SUMIFS(数据录入!$F$5:$F$4999,数据录入!$C$5:$C$4999,$A17,数据录入!$B$5:$B$4999,E$6)) -> 0 | F17: =IF(OR($A17="",F$6="",NOT(ISNUMBER($H$2))),"",SUMIFS(数据录入!$G$5:$G$4999,数据录入!$C$5:$C$4999,$A17,数据录入!$B$5:$B$4999,F$6)) -> 0 | G17: =IF(OR($A17="",G$6="",NOT(ISNUMBER($H$2))),"",SUMIFS(数据录入!$F$5:$F$4999,数据录入!$C$5:$C$4999,$A17,数据录入!$B$5:$B$4999,G$6)) -> 0 | H17: =IF(OR($A17="",H$6="",NOT(ISNUMBER($H$2))),"",SUMIFS(数据录入!$G$5:$G$4999,数据录入!$C$5:$C$4999,$A17,数据录入!$B$5:$B$4999,H$6)) -> 0 | I17: =IF(OR($A17="",I$6="",NOT(ISNUMBER($H$2))),"",SUMIFS(数据录入!$F$5:$F$4999,数据录入!$C$5:$C$4999,$A17,数据录入!$B$5:$B$4999,I$6)) -> 0 | J17: =IF(OR($A17="",J$6="",NOT(ISNUMBER($H$2))),"",SUMIFS(数据录入!$G$5:$G$4999,数据录入!$C$5:$C$4999,$A17,数据录入!$B$5:$B$4999,J$6)) -> 0 | K17: =IF(OR($A17="",K$6="",NOT(ISNUMBER($H$2))),"",SUMIFS(数据录入!$F$5:$F$4999,数据录入!$C$5:$C$4999,$A17,数据录入!$B$5:$B$4999,K$6)) -> 0 | L17: =IF(OR($A17="",L$6="",NOT(ISNUMBER($H$2))),"",SUMIFS(数据录入!$G$5:$G$4999,数据录入!$C$5:$C$4999,$A17,数据录入!$B$5:$B$4999,L$6)) -> 0 | M17: =IF(OR($A17="",M$6="",NOT(ISNUMBER($H$2))),"",SUMIFS(数据录入!$F$5:$F$4999,数据录入!$C$5:$C$4999,$A17,数据录入!$B$5:$B$4999,M$6)) -> 0 | N17: =IF(OR($A17="",N$6="",NOT(ISNUMBER($H$2))),"",SUMIFS(数据录入!$G$5:$G$4999,数据录入!$C$5:$C$4999,$A17,数据录入!$B$5:$B$4999,N$6)) -> 0 | O17: =IF(OR($A17="",O$6="",NOT(ISNUMBER($H$2))),"",SUMIFS(数据录入!$F$5:$F$4999,数据录入!$C$5:$C$4999,$A17,数据录入!$B$5:$B$4999,O$6)) -> 0 | P17: =IF(OR($A17="",P$6="",NOT(ISNUMBER($H$2))),"",SUMIFS(数据录入!$G$5:$G$4999,数据录入!$C$5:$C$4999,$A17,数据录入!$B$5:$B$4999,P$6)) -> 0 | Q17: =IF(OR($A17="",Q$6="",NOT(ISNUMBER($H$2))),"",SUMIFS(数据录入!$F$5:$F$4999,数据录入!$C$5:$C$4999,$A17,数据录入!$B$5:$B$4999,Q$6)) -> 0 | R17: =IF(OR($A17="",R$6="",NOT(ISNUMBER($H$2))),"",SUMIFS(数据录入!$G$5:$G$4999,数据录入!$C$5:$C$4999,$A17,数据录入!$B$5:$B$4999,R$6)) -> 0 | S17: =IF(OR($A17="",S$6="",NOT(ISNUMBER($H$2))),"",SUMIFS(数据录入!$F$5:$F$4999,数据录入!$C$5:$C$4999,$A17,数据录入!$B$5:$B$4999,S$6)) -> 0 | T17: =IF(OR($A17="",T$6="",NOT(ISNUMBER($H$2))),"",SUMIFS(数据录入!$G$5:$G$4999,数据录入!$C$5:$C$4999,$A17,数据录入!$B$5:$B$4999,T$6)) -> 0 | U17: =IF(OR($A17="",U$6="",NOT(ISNUMBER($H$2))),"",SUMIFS(数据录入!$F$5:$F$4999,数据录入!$C$5:$C$4999,$A17,数据录入!$B$5:$B$4999,U$6)) -> 0 | V17: =IF(OR($A17="",V$6="",NOT(ISNUMBER($H$2))),"",SUMIFS(数据录入!$G$5:$G$4999,数据录入!$C$5:$C$4999,$A17,数据录入!$B$5:$B$4999,V$6)) -> 0 | W17: =IF(OR($A17="",W$6="",NOT(ISNUMBER($H$2))),"",SUMIFS(数据录入!$F$5:$F$4999,数据录入!$C$5:$C$4999,$A17,数据录入!$B$5:$B$4999,W$6)) -> 0 | X17: =IF(OR($A17="",X$6="",NOT(ISNUMBER($H$2))),"",SUMIFS(数据录入!$G$5:$G$4999,数据录入!$C$5:$C$4999,$A17,数据录入!$B$5:$B$4999,X$6)) -> 0 | Y17: =IF(OR($A17="",Y$6="",NOT(ISNUMBER($H$2))),"",SUMIFS(数据录入!$F$5:$F$4999,数据录入!$C$5:$C$4999,$A17,数据录入!$B$5:$B$4999,Y$6)) -> 0 | Z17: =IF(OR($A17="",Z$6="",NOT(ISNUMBER($H$2))),"",SUMIFS(数据录入!$G$5:$G$4999,数据录入!$C$5:$C$4999,$A17,数据录入!$B$5:$B$4999,Z$6)) -> 0 | AA17: =IF(OR($A17="",AA$6="",NOT(ISNUMBER($H$2))),"",SUMIFS(数据录入!$F$5:$F$4999,数据录入!$C$5:$C$4999,$A17,数据录入!$B$5:$B$4999,AA$6)) -> 0 | AB17: =IF(OR($A17="",AB$6="",NOT(ISNUMBER($H$2))),"",SUMIFS(数据录入!$G$5:$G$4999,数据录入!$C$5:$C$4999,$A17,数据录入!$B$5:$B$4999,AB$6)) -> 0 | AC17: =IF(OR($A17="",AC$6="",NOT(ISNUMBER($H$2))),"",SUMIFS(数据录入!$F$5:$F$4999,数据录入!$C$5:$C$4999,$A17,数据录入!$B$5:$B$4999,AC$6)) -> 0 | AD17: =IF(OR($A17="",AD$6="",NOT(ISNUMBER($H$2))),"",SUMIFS(数据录入!$G$5:$G$4999,数据录入!$C$5:$C$4999,$A17,数据录入!$B$5:$B$4999,AD$6)) -> 0 | AE17: =IF(OR($A17="",AE$6="",NOT(ISNUMBER($H$2))),"",SUMIFS(数据录入!$F$5:$F$4999,数据录入!$C$5:$C$4999,$A17,数据录入!$B$5:$B$4999,AE$6)) -> 0 | AF17: =IF(OR($A17="",AF$6="",NOT(ISNUMBER($H$2))),"",SUMIFS(数据录入!$G$5:$G$4999,数据录入!$C$5:$C$4999,$A17,数据录入!$B$5:$B$4999,AF$6)) -> 0 | AG17: =IF(OR($A17="",AG$6="",NOT(ISNUMBER($H$2))),"",SUMIFS(数据录入!$F$5:$F$4999,数据录入!$C$5:$C$4999,$A17,数据录入!$B$5:$B$4999,AG$6)) -> 0 | AH17: =IF(OR($A17="",AH$6="",NOT(ISNUMBER($H$2))),"",SUMIFS(数据录入!$G$5:$G$4999,数据录入!$C$5:$C$4999,$A17,数据录入!$B$5:$B$4999,AH$6)) -> 0 | AI17: =IF(OR($A17="",AI$6="",NOT(ISNUMBER($H$2))),"",SUMIFS(数据录入!$F$5:$F$4999,数据录入!$C$5:$C$4999,$A17,数据录入!$B$5:$B$4999,AI$6)) -> 0 | AJ17: =IF(OR($A17="",AJ$6="",NOT(ISNUMBER($H$2))),"",SUMIFS(数据录入!$G$5:$G$4999,数据录入!$C$5:$C$4999,$A17,数据录入!$B$5:$B$4999,AJ$6)) -> 0 | AK17: =IF(OR($A17="",AK$6="",NOT(ISNUMBER($H$2))),"",SUMIFS(数据录入!$F$5:$F$4999,数据录入!$C$5:$C$4999,$A17,数据录入!$B$5:$B$4999,AK$6)) -> 0 | AL17: =IF(OR($A17="",AL$6="",NOT(ISNUMBER($H$2))),"",SUMIFS(数据录入!$G$5:$G$4999,数据录入!$C$5:$C$4999,$A17,数据录入!$B$5:$B$4999,AL$6)) -> 0 | AM17: =IF(OR($A17="",AM$6="",NOT(ISNUMBER($H$2))),"",SUMIFS(数据录入!$F$5:$F$4999,数据录入!$C$5:$C$4999,$A17,数据录入!$B$5:$B$4999,AM$6)) -> 0 | AN17: =IF(OR($A17="",AN$6="",NOT(ISNUMBER($H$2))),"",SUMIFS(数据录入!$G$5:$G$4999,数据录入!$C$5:$C$4999,$A17,数据录入!$B$5:$B$4999,AN$6)) -> 0 | AO17: =IF(OR($A17="",AO$6="",NOT(ISNUMBER($H$2))),"",SUMIFS(数据录入!$F$5:$F$4999,数据录入!$C$5:$C$4999,$A17,数据录入!$B$5:$B$4999,AO$6)) -> 0 | AP17: =IF(OR($A17="",AP$6="",NOT(ISNUMBER($H$2))),"",SUMIFS(数据录入!$G$5:$G$4999,数据录入!$C$5:$C$4999,$A17,数据录入!$B$5:$B$4999,AP$6)) -> 0 | AQ17: =IF(OR($A17="",AQ$6="",NOT(ISNUMBER($H$2))),"",SUMIFS(数据录入!$F$5:$F$4999,数据录入!$C$5:$C$4999,$A17,数据录入!$B$5:$B$4999,AQ$6)) -> 0 | AR17: =IF(OR($A17="",AR$6="",NOT(ISNUMBER($H$2))),"",SUMIFS(数据录入!$G$5:$G$4999,数据录入!$C$5:$C$4999,$A17,数据录入!$B$5:$B$4999,AR$6)) -> 0 | AS17: =IF(OR($A17="",AS$6="",NOT(ISNUMBER($H$2))),"",SUMIFS(数据录入!$F$5:$F$4999,数据录入!$C$5:$C$4999,$A17,数据录入!$B$5:$B$4999,AS$6)) -> 0 | AT17: =IF(OR($A17="",AT$6="",NOT(ISNUMBER($H$2))),"",SUMIFS(数据录入!$G$5:$G$4999,数据录入!$C$5:$C$4999,$A17,数据录入!$B$5:$B$4999,AT$6)) -> 0 | AU17: =IF(OR($A17="",AU$6="",NOT(ISNUMBER($H$2))),"",SUMIFS(数据录入!$F$5:$F$4999,数据录入!$C$5:$C$4999,$A17,数据录入!$B$5:$B$4999,AU$6)) -> 0 | AV17: =IF(OR($A17="",AV$6="",NOT(ISNUMBER($H$2))),"",SUMIFS(数据录入!$G$5:$G$4999,数据录入!$C$5:$C$4999,$A17,数据录入!$B$5:$B$4999,AV$6)) -> 0 | AW17: =IF(OR($A17="",AW$6="",NOT(ISNUMBER($H$2))),"",SUMIFS(数据录入!$F$5:$F$4999,数据录入!$C$5:$C$4999,$A17,数据录入!$B$5:$B$4999,AW$6)) -> 0 | AX17: =IF(OR($A17="",AX$6="",NOT(ISNUMBER($H$2))),"",SUMIFS(数据录入!$G$5:$G$4999,数据录入!$C$5:$C$4999,$A17,数据录入!$B$5:$B$4999,AX$6)) -> 0 | AY17: =IF(OR($A17="",AY$6="",NOT(ISNUMBER($H$2))),"",SUMIFS(数据录入!$F$5:$F$4999,数据录入!$C$5:$C$4999,$A17,数据录入!$B$5:$B$4999,AY$6)) -> 0 | AZ17: =IF(OR($A17="",AZ$6="",NOT(ISNUMBER($H$2))),"",SUMIFS(数据录入!$G$5:$G$4999,数据录入!$C$5:$C$4999,$A17,数据录入!$B$5:$B$4999,AZ$6)) -> 0 | BA17: =IF(OR($A17="",BA$6="",NOT(ISNUMBER($H$2))),"",SUMIFS(数据录入!$F$5:$F$4999,数据录入!$C$5:$C$4999,$A17,数据录入!$B$5:$B$4999,BA$6)) -> 0 | BB17: =IF(OR($A17="",BB$6="",NOT(ISNUMBER($H$2))),"",SUMIFS(数据录入!$G$5:$G$4999,数据录入!$C$5:$C$4999,$A17,数据录入!$B$5:$B$4999,BB$6)) -> 0 | BC17: =IF(OR($A17="",BC$6="",NOT(ISNUMBER($H$2))),"",SUMIFS(数据录入!$F$5:$F$4999,数据录入!$C$5:$C$4999,$A17,数据录入!$B$5:$B$4999,BC$6)) -> 0 | BD17: =IF(OR($A17="",BD$6="",NOT(ISNUMBER($H$2))),"",SUMIFS(数据录入!$G$5:$G$4999,数据录入!$C$5:$C$4999,$A17,数据录入!$B$5:$B$4999,BD$6)) -> 0 | BE17: =IF(OR($A17="",BE$6="",NOT(ISNUMBER($H$2))),"",SUMIFS(数据录入!$F$5:$F$4999,数据录入!$C$5:$C$4999,$A17,数据录入!$B$5:$B$4999,BE$6)) -> 0 | BF17: =IF(OR($A17="",BF$6="",NOT(ISNUMBER($H$2))),"",SUMIFS(数据录入!$G$5:$G$4999,数据录入!$C$5:$C$4999,$A17,数据录入!$B$5:$B$4999,BF$6)) -> 0 | BG17: =IF(OR($A17="",BG$6="",NOT(ISNUMBER($H$2))),"",SUMIFS(数据录入!$F$5:$F$4999,数据录入!$C$5:$C$4999,$A17,数据录入!$B$5:$B$4999,BG$6)) -> 0 | BH17: =IF(OR($A17="",BH$6="",NOT(ISNUMBER($H$2))),"",SUMIFS(数据录入!$G$5:$G$4999,数据录入!$C$5:$C$4999,$A17,数据录入!$B$5:$B$4999,BH$6)) -> 0 | BI17: =IF(OR($A17="",BI$6="",NOT(ISNUMBER($H$2))),"",SUMIFS(数据录入!$F$5:$F$4999,数据录入!$C$5:$C$4999,$A17,数据录入!$B$5:$B$4999,BI$6)) -> 0 | BJ17: =IF(OR($A17="",BJ$6="",NOT(ISNUMBER($H$2))),"",SUMIFS(数据录入!$G$5:$G$4999,数据录入!$C$5:$C$4999,$A17,数据录入!$B$5:$B$4999,BJ$6)) -> 0 | BK17: =IF(OR($A17="",BK$6="",NOT(ISNUMBER($H$2))),"",SUMIFS(数据录入!$F$5:$F$4999,数据录入!$C$5:$C$4999,$A17,数据录入!$B$5:$B$4999,BK$6)) | BL17: =IF(OR($A17="",BL$6="",NOT(ISNUMBER($H$2))),"",SUMIFS(数据录入!$G$5:$G$4999,数据录入!$C$5:$C$4999,$A17,数据录入!$B$5:$B$4999,BL$6)) | BM17: =IF($A17="","",SUMIF($C$7:$BL$7,"收款",C17:BL17)) -> 2100 | BN17: =IF($A17="","",SUMIF($C$7:$BL$7,"付款",C17:BL17)) -> 0 | BO17: =IF($A17="","",B17+BM17-BN17) -> 2100
A18: 备用5 | B18: =IF(OR($A18="",NOT(ISNUMBER($H$2))),"",SUMIFS(数据录入!$H$5:$H$4999,数据录入!$C$5:$C$4999,$A18,数据录入!$E$5:$E$4999,"期初余额",数据录入!$B$5:$B$4999,"<="&$B$2)+SUMIFS(数据录入!$F$5:$F$4999,数据录入!$C$5:$C$4999,$A18,数据录入!$B$5:$B$4999,"<"&$B$2)-SUMIFS(数据录入!$G$5:$G$4999,数据录入!$C$5:$C$4999,$A18,数据录入!$B$5:$B$4999,"<"&$B$2)) -> 0 | C18: =IF(OR($A18="",C$6="",NOT(ISNUMBER($H$2))),"",SUMIFS(数据录入!$F$5:$F$4999,数据录入!$C$5:$C$4999,$A18,数据录入!$B$5:$B$4999,C$6)) -> 0 | D18: =IF(OR($A18="",D$6="",NOT(ISNUMBER($H$2))),"",SUMIFS(数据录入!$G$5:$G$4999,数据录入!$C$5:$C$4999,$A18,数据录入!$B$5:$B$4999,D$6)) -> 2000 | E18: =IF(OR($A18="",E$6="",NOT(ISNUMBER($H$2))),"",SUMIFS(数据录入!$F$5:$F$4999,数据录入!$C$5:$C$4999,$A18,数据录入!$B$5:$B$4999,E$6)) -> 0 | F18: =IF(OR($A18="",F$6="",NOT(ISNUMBER($H$2))),"",SUMIFS(数据录入!$G$5:$G$4999,数据录入!$C$5:$C$4999,$A18,数据录入!$B$5:$B$4999,F$6)) -> 0 | G18: =IF(OR($A18="",G$6="",NOT(ISNUMBER($H$2))),"",SUMIFS(数据录入!$F$5:$F$4999,数据录入!$C$5:$C$4999,$A18,数据录入!$B$5:$B$4999,G$6)) -> 0 | H18: =IF(OR($A18="",H$6="",NOT(ISNUMBER($H$2))),"",SUMIFS(数据录入!$G$5:$G$4999,数据录入!$C$5:$C$4999,$A18,数据录入!$B$5:$B$4999,H$6)) -> 0 | I18: =IF(OR($A18="",I$6="",NOT(ISNUMBER($H$2))),"",SUMIFS(数据录入!$F$5:$F$4999,数据录入!$C$5:$C$4999,$A18,数据录入!$B$5:$B$4999,I$6)) -> 0 | J18: =IF(OR($A18="",J$6="",NOT(ISNUMBER($H$2))),"",SUMIFS(数据录入!$G$5:$G$4999,数据录入!$C$5:$C$4999,$A18,数据录入!$B$5:$B$4999,J$6)) -> 0 | K18: =IF(OR($A18="",K$6="",NOT(ISNUMBER($H$2))),"",SUMIFS(数据录入!$F$5:$F$4999,数据录入!$C$5:$C$4999,$A18,数据录入!$B$5:$B$4999,K$6)) -> 0 | L18: =IF(OR($A18="",L$6="",NOT(ISNUMBER($H$2))),"",SUMIFS(数据录入!$G$5:$G$4999,数据录入!$C$5:$C$4999,$A18,数据录入!$B$5:$B$4999,L$6)) -> 0 | M18: =IF(OR($A18="",M$6="",NOT(ISNUMBER($H$2))),"",SUMIFS(数据录入!$F$5:$F$4999,数据录入!$C$5:$C$4999,$A18,数据录入!$B$5:$B$4999,M$6)) -> 0 | N18: =IF(OR($A18="",N$6="",NOT(ISNUMBER($H$2))),"",SUMIFS(数据录入!$G$5:$G$4999,数据录入!$C$5:$C$4999,$A18,数据录入!$B$5:$B$4999,N$6)) -> 0 | O18: =IF(OR($A18="",O$6="",NOT(ISNUMBER($H$2))),"",SUMIFS(数据录入!$F$5:$F$4999,数据录入!$C$5:$C$4999,$A18,数据录入!$B$5:$B$4999,O$6)) -> 0 | P18: =IF(OR($A18="",P$6="",NOT(ISNUMBER($H$2))),"",SUMIFS(数据录入!$G$5:$G$4999,数据录入!$C$5:$C$4999,$A18,数据录入!$B$5:$B$4999,P$6)) -> 0 | Q18: =IF(OR($A18="",Q$6="",NOT(ISNUMBER($H$2))),"",SUMIFS(数据录入!$F$5:$F$4999,数据录入!$C$5:$C$4999,$A18,数据录入!$B$5:$B$4999,Q$6)) -> 0 | R18: =IF(OR($A18="",R$6="",NOT(ISNUMBER($H$2))),"",SUMIFS(数据录入!$G$5:$G$4999,数据录入!$C$5:$C$4999,$A18,数据录入!$B$5:$B$4999,R$6)) -> 0 | S18: =IF(OR($A18="",S$6="",NOT(ISNUMBER($H$2))),"",SUMIFS(数据录入!$F$5:$F$4999,数据录入!$C$5:$C$4999,$A18,数据录入!$B$5:$B$4999,S$6)) -> 0 | T18: =IF(OR($A18="",T$6="",NOT(ISNUMBER($H$2))),"",SUMIFS(数据录入!$G$5:$G$4999,数据录入!$C$5:$C$4999,$A18,数据录入!$B$5:$B$4999,T$6)) -> 0 | U18: =IF(OR($A18="",U$6="",NOT(ISNUMBER($H$2))),"",SUMIFS(数据录入!$F$5:$F$4999,数据录入!$C$5:$C$4999,$A18,数据录入!$B$5:$B$4999,U$6)) -> 0 | V18: =IF(OR($A18="",V$6="",NOT(ISNUMBER($H$2))),"",SUMIFS(数据录入!$G$5:$G$4999,数据录入!$C$5:$C$4999,$A18,数据录入!$B$5:$B$4999,V$6)) -> 0 | W18: =IF(OR($A18="",W$6="",NOT(ISNUMBER($H$2))),"",SUMIFS(数据录入!$F$5:$F$4999,数据录入!$C$5:$C$4999,$A18,数据录入!$B$5:$B$4999,W$6)) -> 0 | X18: =IF(OR($A18="",X$6="",NOT(ISNUMBER($H$2))),"",SUMIFS(数据录入!$G$5:$G$4999,数据录入!$C$5:$C$4999,$A18,数据录入!$B$5:$B$4999,X$6)) -> 0 | Y18: =IF(OR($A18="",Y$6="",NOT(ISNUMBER($H$2))),"",SUMIFS(数据录入!$F$5:$F$4999,数据录入!$C$5:$C$4999,$A18,数据录入!$B$5:$B$4999,Y$6)) -> 0 | Z18: =IF(OR($A18="",Z$6="",NOT(ISNUMBER($H$2))),"",SUMIFS(数据录入!$G$5:$G$4999,数据录入!$C$5:$C$4999,$A18,数据录入!$B$5:$B$4999,Z$6)) -> 0 | AA18: =IF(OR($A18="",AA$6="",NOT(ISNUMBER($H$2))),"",SUMIFS(数据录入!$F$5:$F$4999,数据录入!$C$5:$C$4999,$A18,数据录入!$B$5:$B$4999,AA$6)) -> 0 | AB18: =IF(OR($A18="",AB$6="",NOT(ISNUMBER($H$2))),"",SUMIFS(数据录入!$G$5:$G$4999,数据录入!$C$5:$C$4999,$A18,数据录入!$B$5:$B$4999,AB$6)) -> 0 | AC18: =IF(OR($A18="",AC$6="",NOT(ISNUMBER($H$2))),"",SUMIFS(数据录入!$F$5:$F$4999,数据录入!$C$5:$C$4999,$A18,数据录入!$B$5:$B$4999,AC$6)) -> 0 | AD18: =IF(OR($A18="",AD$6="",NOT(ISNUMBER($H$2))),"",SUMIFS(数据录入!$G$5:$G$4999,数据录入!$C$5:$C$4999,$A18,数据录入!$B$5:$B$4999,AD$6)) -> 0 | AE18: =IF(OR($A18="",AE$6="",NOT(ISNUMBER($H$2))),"",SUMIFS(数据录入!$F$5:$F$4999,数据录入!$C$5:$C$4999,$A18,数据录入!$B$5:$B$4999,AE$6)) -> 0 | AF18: =IF(OR($A18="",AF$6="",NOT(ISNUMBER($H$2))),"",SUMIFS(数据录入!$G$5:$G$4999,数据录入!$C$5:$C$4999,$A18,数据录入!$B$5:$B$4999,AF$6)) -> 0 | AG18: =IF(OR($A18="",AG$6="",NOT(ISNUMBER($H$2))),"",SUMIFS(数据录入!$F$5:$F$4999,数据录入!$C$5:$C$4999,$A18,数据录入!$B$5:$B$4999,AG$6)) -> 0 | AH18: =IF(OR($A18="",AH$6="",NOT(ISNUMBER($H$2))),"",SUMIFS(数据录入!$G$5:$G$4999,数据录入!$C$5:$C$4999,$A18,数据录入!$B$5:$B$4999,AH$6)) -> 0 | AI18: =IF(OR($A18="",AI$6="",NOT(ISNUMBER($H$2))),"",SUMIFS(数据录入!$F$5:$F$4999,数据录入!$C$5:$C$4999,$A18,数据录入!$B$5:$B$4999,AI$6)) -> 0 | AJ18: =IF(OR($A18="",AJ$6="",NOT(ISNUMBER($H$2))),"",SUMIFS(数据录入!$G$5:$G$4999,数据录入!$C$5:$C$4999,$A18,数据录入!$B$5:$B$4999,AJ$6)) -> 0 | AK18: =IF(OR($A18="",AK$6="",NOT(ISNUMBER($H$2))),"",SUMIFS(数据录入!$F$5:$F$4999,数据录入!$C$5:$C$4999,$A18,数据录入!$B$5:$B$4999,AK$6)) -> 0 | AL18: =IF(OR($A18="",AL$6="",NOT(ISNUMBER($H$2))),"",SUMIFS(数据录入!$G$5:$G$4999,数据录入!$C$5:$C$4999,$A18,数据录入!$B$5:$B$4999,AL$6)) -> 0 | AM18: =IF(OR($A18="",AM$6="",NOT(ISNUMBER($H$2))),"",SUMIFS(数据录入!$F$5:$F$4999,数据录入!$C$5:$C$4999,$A18,数据录入!$B$5:$B$4999,AM$6)) -> 0 | AN18: =IF(OR($A18="",AN$6="",NOT(ISNUMBER($H$2))),"",SUMIFS(数据录入!$G$5:$G$4999,数据录入!$C$5:$C$4999,$A18,数据录入!$B$5:$B$4999,AN$6)) -> 0 | AO18: =IF(OR($A18="",AO$6="",NOT(ISNUMBER($H$2))),"",SUMIFS(数据录入!$F$5:$F$4999,数据录入!$C$5:$C$4999,$A18,数据录入!$B$5:$B$4999,AO$6)) -> 0 | AP18: =IF(OR($A18="",AP$6="",NOT(ISNUMBER($H$2))),"",SUMIFS(数据录入!$G$5:$G$4999,数据录入!$C$5:$C$4999,$A18,数据录入!$B$5:$B$4999,AP$6)) -> 0 | AQ18: =IF(OR($A18="",AQ$6="",NOT(ISNUMBER($H$2))),"",SUMIFS(数据录入!$F$5:$F$4999,数据录入!$C$5:$C$4999,$A18,数据录入!$B$5:$B$4999,AQ$6)) -> 0 | AR18: =IF(OR($A18="",AR$6="",NOT(ISNUMBER($H$2))),"",SUMIFS(数据录入!$G$5:$G$4999,数据录入!$C$5:$C$4999,$A18,数据录入!$B$5:$B$4999,AR$6)) -> 0 | AS18: =IF(OR($A18="",AS$6="",NOT(ISNUMBER($H$2))),"",SUMIFS(数据录入!$F$5:$F$4999,数据录入!$C$5:$C$4999,$A18,数据录入!$B$5:$B$4999,AS$6)) -> 0 | AT18: =IF(OR($A18="",AT$6="",NOT(ISNUMBER($H$2))),"",SUMIFS(数据录入!$G$5:$G$4999,数据录入!$C$5:$C$4999,$A18,数据录入!$B$5:$B$4999,AT$6)) -> 0 | AU18: =IF(OR($A18="",AU$6="",NOT(ISNUMBER($H$2))),"",SUMIFS(数据录入!$F$5:$F$4999,数据录入!$C$5:$C$4999,$A18,数据录入!$B$5:$B$4999,AU$6)) -> 0 | AV18: =IF(OR($A18="",AV$6="",NOT(ISNUMBER($H$2))),"",SUMIFS(数据录入!$G$5:$G$4999,数据录入!$C$5:$C$4999,$A18,数据录入!$B$5:$B$4999,AV$6)) -> 0 | AW18: =IF(OR($A18="",AW$6="",NOT(ISNUMBER($H$2))),"",SUMIFS(数据录入!$F$5:$F$4999,数据录入!$C$5:$C$4999,$A18,数据录入!$B$5:$B$4999,AW$6)) -> 0 | AX18: =IF(OR($A18="",AX$6="",NOT(ISNUMBER($H$2))),"",SUMIFS(数据录入!$G$5:$G$4999,数据录入!$C$5:$C$4999,$A18,数据录入!$B$5:$B$4999,AX$6)) -> 0 | AY18: =IF(OR($A18="",AY$6="",NOT(ISNUMBER($H$2))),"",SUMIFS(数据录入!$F$5:$F$4999,数据录入!$C$5:$C$4999,$A18,数据录入!$B$5:$B$4999,AY$6)) -> 0 | AZ18: =IF(OR($A18="",AZ$6="",NOT(ISNUMBER($H$2))),"",SUMIFS(数据录入!$G$5:$G$4999,数据录入!$C$5:$C$4999,$A18,数据录入!$B$5:$B$4999,AZ$6)) -> 0 | BA18: =IF(OR($A18="",BA$6="",NOT(ISNUMBER($H$2))),"",SUMIFS(数据录入!$F$5:$F$4999,数据录入!$C$5:$C$4999,$A18,数据录入!$B$5:$B$4999,BA$6)) -> 0 | BB18: =IF(OR($A18="",BB$6="",NOT(ISNUMBER($H$2))),"",SUMIFS(数据录入!$G$5:$G$4999,数据录入!$C$5:$C$4999,$A18,数据录入!$B$5:$B$4999,BB$6)) -> 0 | BC18: =IF(OR($A18="",BC$6="",NOT(ISNUMBER($H$2))),"",SUMIFS(数据录入!$F$5:$F$4999,数据录入!$C$5:$C$4999,$A18,数据录入!$B$5:$B$4999,BC$6)) -> 0 | BD18: =IF(OR($A18="",BD$6="",NOT(ISNUMBER($H$2))),"",SUMIFS(数据录入!$G$5:$G$4999,数据录入!$C$5:$C$4999,$A18,数据录入!$B$5:$B$4999,BD$6)) -> 0 | BE18: =IF(OR($A18="",BE$6="",NOT(ISNUMBER($H$2))),"",SUMIFS(数据录入!$F$5:$F$4999,数据录入!$C$5:$C$4999,$A18,数据录入!$B$5:$B$4999,BE$6)) -> 0 | BF18: =IF(OR($A18="",BF$6="",NOT(ISNUMBER($H$2))),"",SUMIFS(数据录入!$G$5:$G$4999,数据录入!$C$5:$C$4999,$A18,数据录入!$B$5:$B$4999,BF$6)) -> 0 | BG18: =IF(OR($A18="",BG$6="",NOT(ISNUMBER($H$2))),"",SUMIFS(数据录入!$F$5:$F$4999,数据录入!$C$5:$C$4999,$A18,数据录入!$B$5:$B$4999,BG$6)) -> 0 | BH18: =IF(OR($A18="",BH$6="",NOT(ISNUMBER($H$2))),"",SUMIFS(数据录入!$G$5:$G$4999,数据录入!$C$5:$C$4999,$A18,数据录入!$B$5:$B$4999,BH$6)) -> 0 | BI18: =IF(OR($A18="",BI$6="",NOT(ISNUMBER($H$2))),"",SUMIFS(数据录入!$F$5:$F$4999,数据录入!$C$5:$C$4999,$A18,数据录入!$B$5:$B$4999,BI$6)) -> 0 | BJ18: =IF(OR($A18="",BJ$6="",NOT(ISNUMBER($H$2))),"",SUMIFS(数据录入!$G$5:$G$4999,数据录入!$C$5:$C$4999,$A18,数据录入!$B$5:$B$4999,BJ$6)) -> 0 | BK18: =IF(OR($A18="",BK$6="",NOT(ISNUMBER($H$2))),"",SUMIFS(数据录入!$F$5:$F$4999,数据录入!$C$5:$C$4999,$A18,数据录入!$B$5:$B$4999,BK$6)) | BL18: =IF(OR($A18="",BL$6="",NOT(ISNUMBER($H$2))),"",SUMIFS(数据录入!$G$5:$G$4999,数据录入!$C$5:$C$4999,$A18,数据录入!$B$5:$B$4999,BL$6)) | BM18: =IF($A18="","",SUMIF($C$7:$BL$7,"收款",C18:BL18)) -> 0 | BN18: =IF($A18="","",SUMIF($C$7:$BL$7,"付款",C18:BL18)) -> 2000 | BO18: =IF($A18="","",B18+BM18-BN18) -> -2000
A19: 备用6 | B19: =IF(OR($A19="",NOT(ISNUMBER($H$2))),"",SUMIFS(数据录入!$H$5:$H$4999,数据录入!$C$5:$C$4999,$A19,数据录入!$E$5:$E$4999,"期初余额",数据录入!$B$5:$B$4999,"<="&$B$2)+SUMIFS(数据录入!$F$5:$F$4999,数据录入!$C$5:$C$4999,$A19,数据录入!$B$5:$B$4999,"<"&$B$2)-SUMIFS(数据录入!$G$5:$G$4999,数据录入!$C$5:$C$4999,$A19,数据录入!$B$5:$B$4999,"<"&$B$2)) -> 0 | C19: =IF(OR($A19="",C$6="",NOT(ISNUMBER($H$2))),"",SUMIFS(数据录入!$F$5:$F$4999,数据录入!$C$5:$C$4999,$A19,数据录入!$B$5:$B$4999,C$6)) -> 0 | D19: =IF(OR($A19="",D$6="",NOT(ISNUMBER($H$2))),"",SUMIFS(数据录入!$G$5:$G$4999,数据录入!$C$5:$C$4999,$A19,数据录入!$B$5:$B$4999,D$6)) -> 200 | E19: =IF(OR($A19="",E$6="",NOT(ISNUMBER($H$2))),"",SUMIFS(数据录入!$F$5:$F$4999,数据录入!$C$5:$C$4999,$A19,数据录入!$B$5:$B$4999,E$6)) -> 0 | F19: =IF(OR($A19="",F$6="",NOT(ISNUMBER($H$2))),"",SUMIFS(数据录入!$G$5:$G$4999,数据录入!$C$5:$C$4999,$A19,数据录入!$B$5:$B$4999,F$6)) -> 0 | G19: =IF(OR($A19="",G$6="",NOT(ISNUMBER($H$2))),"",SUMIFS(数据录入!$F$5:$F$4999,数据录入!$C$5:$C$4999,$A19,数据录入!$B$5:$B$4999,G$6)) -> 0 | H19: =IF(OR($A19="",H$6="",NOT(ISNUMBER($H$2))),"",SUMIFS(数据录入!$G$5:$G$4999,数据录入!$C$5:$C$4999,$A19,数据录入!$B$5:$B$4999,H$6)) -> 0 | I19: =IF(OR($A19="",I$6="",NOT(ISNUMBER($H$2))),"",SUMIFS(数据录入!$F$5:$F$4999,数据录入!$C$5:$C$4999,$A19,数据录入!$B$5:$B$4999,I$6)) -> 0 | J19: =IF(OR($A19="",J$6="",NOT(ISNUMBER($H$2))),"",SUMIFS(数据录入!$G$5:$G$4999,数据录入!$C$5:$C$4999,$A19,数据录入!$B$5:$B$4999,J$6)) -> 0 | K19: =IF(OR($A19="",K$6="",NOT(ISNUMBER($H$2))),"",SUMIFS(数据录入!$F$5:$F$4999,数据录入!$C$5:$C$4999,$A19,数据录入!$B$5:$B$4999,K$6)) -> 0 | L19: =IF(OR($A19="",L$6="",NOT(ISNUMBER($H$2))),"",SUMIFS(数据录入!$G$5:$G$4999,数据录入!$C$5:$C$4999,$A19,数据录入!$B$5:$B$4999,L$6)) -> 0 | M19: =IF(OR($A19="",M$6="",NOT(ISNUMBER($H$2))),"",SUMIFS(数据录入!$F$5:$F$4999,数据录入!$C$5:$C$4999,$A19,数据录入!$B$5:$B$4999,M$6)) -> 0 | N19: =IF(OR($A19="",N$6="",NOT(ISNUMBER($H$2))),"",SUMIFS(数据录入!$G$5:$G$4999,数据录入!$C$5:$C$4999,$A19,数据录入!$B$5:$B$4999,N$6)) -> 0 | O19: =IF(OR($A19="",O$6="",NOT(ISNUMBER($H$2))),"",SUMIFS(数据录入!$F$5:$F$4999,数据录入!$C$5:$C$4999,$A19,数据录入!$B$5:$B$4999,O$6)) -> 0 | P19: =IF(OR($A19="",P$6="",NOT(ISNUMBER($H$2))),"",SUMIFS(数据录入!$G$5:$G$4999,数据录入!$C$5:$C$4999,$A19,数据录入!$B$5:$B$4999,P$6)) -> 0 | Q19: =IF(OR($A19="",Q$6="",NOT(ISNUMBER($H$2))),"",SUMIFS(数据录入!$F$5:$F$4999,数据录入!$C$5:$C$4999,$A19,数据录入!$B$5:$B$4999,Q$6)) -> 0 | R19: =IF(OR($A19="",R$6="",NOT(ISNUMBER($H$2))),"",SUMIFS(数据录入!$G$5:$G$4999,数据录入!$C$5:$C$4999,$A19,数据录入!$B$5:$B$4999,R$6)) -> 0 | S19: =IF(OR($A19="",S$6="",NOT(ISNUMBER($H$2))),"",SUMIFS(数据录入!$F$5:$F$4999,数据录入!$C$5:$C$4999,$A19,数据录入!$B$5:$B$4999,S$6)) -> 0 | T19: =IF(OR($A19="",T$6="",NOT(ISNUMBER($H$2))),"",SUMIFS(数据录入!$G$5:$G$4999,数据录入!$C$5:$C$4999,$A19,数据录入!$B$5:$B$4999,T$6)) -> 0 | U19: =IF(OR($A19="",U$6="",NOT(ISNUMBER($H$2))),"",SUMIFS(数据录入!$F$5:$F$4999,数据录入!$C$5:$C$4999,$A19,数据录入!$B$5:$B$4999,U$6)) -> 0 | V19: =IF(OR($A19="",V$6="",NOT(ISNUMBER($H$2))),"",SUMIFS(数据录入!$G$5:$G$4999,数据录入!$C$5:$C$4999,$A19,数据录入!$B$5:$B$4999,V$6)) -> 0 | W19: =IF(OR($A19="",W$6="",NOT(ISNUMBER($H$2))),"",SUMIFS(数据录入!$F$5:$F$4999,数据录入!$C$5:$C$4999,$A19,数据录入!$B$5:$B$4999,W$6)) -> 0 | X19: =IF(OR($A19="",X$6="",NOT(ISNUMBER($H$2))),"",SUMIFS(数据录入!$G$5:$G$4999,数据录入!$C$5:$C$4999,$A19,数据录入!$B$5:$B$4999,X$6)) -> 0 | Y19: =IF(OR($A19="",Y$6="",NOT(ISNUMBER($H$2))),"",SUMIFS(数据录入!$F$5:$F$4999,数据录入!$C$5:$C$4999,$A19,数据录入!$B$5:$B$4999,Y$6)) -> 0 | Z19: =IF(OR($A19="",Z$6="",NOT(ISNUMBER($H$2))),"",SUMIFS(数据录入!$G$5:$G$4999,数据录入!$C$5:$C$4999,$A19,数据录入!$B$5:$B$4999,Z$6)) -> 0 | AA19: =IF(OR($A19="",AA$6="",NOT(ISNUMBER($H$2))),"",SUMIFS(数据录入!$F$5:$F$4999,数据录入!$C$5:$C$4999,$A19,数据录入!$B$5:$B$4999,AA$6)) -> 0 | AB19: =IF(OR($A19="",AB$6="",NOT(ISNUMBER($H$2))),"",SUMIFS(数据录入!$G$5:$G$4999,数据录入!$C$5:$C$4999,$A19,数据录入!$B$5:$B$4999,AB$6)) -> 0 | AC19: =IF(OR($A19="",AC$6="",NOT(ISNUMBER($H$2))),"",SUMIFS(数据录入!$F$5:$F$4999,数据录入!$C$5:$C$4999,$A19,数据录入!$B$5:$B$4999,AC$6)) -> 0 | AD19: =IF(OR($A19="",AD$6="",NOT(ISNUMBER($H$2))),"",SUMIFS(数据录入!$G$5:$G$4999,数据录入!$C$5:$C$4999,$A19,数据录入!$B$5:$B$4999,AD$6)) -> 0 | AE19: =IF(OR($A19="",AE$6="",NOT(ISNUMBER($H$2))),"",SUMIFS(数据录入!$F$5:$F$4999,数据录入!$C$5:$C$4999,$A19,数据录入!$B$5:$B$4999,AE$6)) -> 0 | AF19: =IF(OR($A19="",AF$6="",NOT(ISNUMBER($H$2))),"",SUMIFS(数据录入!$G$5:$G$4999,数据录入!$C$5:$C$4999,$A19,数据录入!$B$5:$B$4999,AF$6)) -> 0 | AG19: =IF(OR($A19="",AG$6="",NOT(ISNUMBER($H$2))),"",SUMIFS(数据录入!$F$5:$F$4999,数据录入!$C$5:$C$4999,$A19,数据录入!$B$5:$B$4999,AG$6)) -> 0 | AH19: =IF(OR($A19="",AH$6="",NOT(ISNUMBER($H$2))),"",SUMIFS(数据录入!$G$5:$G$4999,数据录入!$C$5:$C$4999,$A19,数据录入!$B$5:$B$4999,AH$6)) -> 0 | AI19: =IF(OR($A19="",AI$6="",NOT(ISNUMBER($H$2))),"",SUMIFS(数据录入!$F$5:$F$4999,数据录入!$C$5:$C$4999,$A19,数据录入!$B$5:$B$4999,AI$6)) -> 0 | AJ19: =IF(OR($A19="",AJ$6="",NOT(ISNUMBER($H$2))),"",SUMIFS(数据录入!$G$5:$G$4999,数据录入!$C$5:$C$4999,$A19,数据录入!$B$5:$B$4999,AJ$6)) -> 0 | AK19: =IF(OR($A19="",AK$6="",NOT(ISNUMBER($H$2))),"",SUMIFS(数据录入!$F$5:$F$4999,数据录入!$C$5:$C$4999,$A19,数据录入!$B$5:$B$4999,AK$6)) -> 0 | AL19: =IF(OR($A19="",AL$6="",NOT(ISNUMBER($H$2))),"",SUMIFS(数据录入!$G$5:$G$4999,数据录入!$C$5:$C$4999,$A19,数据录入!$B$5:$B$4999,AL$6)) -> 0 | AM19: =IF(OR($A19="",AM$6="",NOT(ISNUMBER($H$2))),"",SUMIFS(数据录入!$F$5:$F$4999,数据录入!$C$5:$C$4999,$A19,数据录入!$B$5:$B$4999,AM$6)) -> 0 | AN19: =IF(OR($A19="",AN$6="",NOT(ISNUMBER($H$2))),"",SUMIFS(数据录入!$G$5:$G$4999,数据录入!$C$5:$C$4999,$A19,数据录入!$B$5:$B$4999,AN$6)) -> 0 | AO19: =IF(OR($A19="",AO$6="",NOT(ISNUMBER($H$2))),"",SUMIFS(数据录入!$F$5:$F$4999,数据录入!$C$5:$C$4999,$A19,数据录入!$B$5:$B$4999,AO$6)) -> 0 | AP19: =IF(OR($A19="",AP$6="",NOT(ISNUMBER($H$2))),"",SUMIFS(数据录入!$G$5:$G$4999,数据录入!$C$5:$C$4999,$A19,数据录入!$B$5:$B$4999,AP$6)) -> 0 | AQ19: =IF(OR($A19="",AQ$6="",NOT(ISNUMBER($H$2))),"",SUMIFS(数据录入!$F$5:$F$4999,数据录入!$C$5:$C$4999,$A19,数据录入!$B$5:$B$4999,AQ$6)) -> 0 | AR19: =IF(OR($A19="",AR$6="",NOT(ISNUMBER($H$2))),"",SUMIFS(数据录入!$G$5:$G$4999,数据录入!$C$5:$C$4999,$A19,数据录入!$B$5:$B$4999,AR$6)) -> 0 | AS19: =IF(OR($A19="",AS$6="",NOT(ISNUMBER($H$2))),"",SUMIFS(数据录入!$F$5:$F$4999,数据录入!$C$5:$C$4999,$A19,数据录入!$B$5:$B$4999,AS$6)) -> 0 | AT19: =IF(OR($A19="",AT$6="",NOT(ISNUMBER($H$2))),"",SUMIFS(数据录入!$G$5:$G$4999,数据录入!$C$5:$C$4999,$A19,数据录入!$B$5:$B$4999,AT$6)) -> 0 | AU19: =IF(OR($A19="",AU$6="",NOT(ISNUMBER($H$2))),"",SUMIFS(数据录入!$F$5:$F$4999,数据录入!$C$5:$C$4999,$A19,数据录入!$B$5:$B$4999,AU$6)) -> 0 | AV19: =IF(OR($A19="",AV$6="",NOT(ISNUMBER($H$2))),"",SUMIFS(数据录入!$G$5:$G$4999,数据录入!$C$5:$C$4999,$A19,数据录入!$B$5:$B$4999,AV$6)) -> 0 | AW19: =IF(OR($A19="",AW$6="",NOT(ISNUMBER($H$2))),"",SUMIFS(数据录入!$F$5:$F$4999,数据录入!$C$5:$C$4999,$A19,数据录入!$B$5:$B$4999,AW$6)) -> 0 | AX19: =IF(OR($A19="",AX$6="",NOT(ISNUMBER($H$2))),"",SUMIFS(数据录入!$G$5:$G$4999,数据录入!$C$5:$C$4999,$A19,数据录入!$B$5:$B$4999,AX$6)) -> 0 | AY19: =IF(OR($A19="",AY$6="",NOT(ISNUMBER($H$2))),"",SUMIFS(数据录入!$F$5:$F$4999,数据录入!$C$5:$C$4999,$A19,数据录入!$B$5:$B$4999,AY$6)) -> 0 | AZ19: =IF(OR($A19="",AZ$6="",NOT(ISNUMBER($H$2))),"",SUMIFS(数据录入!$G$5:$G$4999,数据录入!$C$5:$C$4999,$A19,数据录入!$B$5:$B$4999,AZ$6)) -> 0 | BA19: =IF(OR($A19="",BA$6="",NOT(ISNUMBER($H$2))),"",SUMIFS(数据录入!$F$5:$F$4999,数据录入!$C$5:$C$4999,$A19,数据录入!$B$5:$B$4999,BA$6)) -> 0 | BB19: =IF(OR($A19="",BB$6="",NOT(ISNUMBER($H$2))),"",SUMIFS(数据录入!$G$5:$G$4999,数据录入!$C$5:$C$4999,$A19,数据录入!$B$5:$B$4999,BB$6)) -> 0 | BC19: =IF(OR($A19="",BC$6="",NOT(ISNUMBER($H$2))),"",SUMIFS(数据录入!$F$5:$F$4999,数据录入!$C$5:$C$4999,$A19,数据录入!$B$5:$B$4999,BC$6)) -> 0 | BD19: =IF(OR($A19="",BD$6="",NOT(ISNUMBER($H$2))),"",SUMIFS(数据录入!$G$5:$G$4999,数据录入!$C$5:$C$4999,$A19,数据录入!$B$5:$B$4999,BD$6)) -> 0 | BE19: =IF(OR($A19="",BE$6="",NOT(ISNUMBER($H$2))),"",SUMIFS(数据录入!$F$5:$F$4999,数据录入!$C$5:$C$4999,$A19,数据录入!$B$5:$B$4999,BE$6)) -> 0 | BF19: =IF(OR($A19="",BF$6="",NOT(ISNUMBER($H$2))),"",SUMIFS(数据录入!$G$5:$G$4999,数据录入!$C$5:$C$4999,$A19,数据录入!$B$5:$B$4999,BF$6)) -> 0 | BG19: =IF(OR($A19="",BG$6="",NOT(ISNUMBER($H$2))),"",SUMIFS(数据录入!$F$5:$F$4999,数据录入!$C$5:$C$4999,$A19,数据录入!$B$5:$B$4999,BG$6)) -> 0 | BH19: =IF(OR($A19="",BH$6="",NOT(ISNUMBER($H$2))),"",SUMIFS(数据录入!$G$5:$G$4999,数据录入!$C$5:$C$4999,$A19,数据录入!$B$5:$B$4999,BH$6)) -> 0 | BI19: =IF(OR($A19="",BI$6="",NOT(ISNUMBER($H$2))),"",SUMIFS(数据录入!$F$5:$F$4999,数据录入!$C$5:$C$4999,$A19,数据录入!$B$5:$B$4999,BI$6)) -> 0 | BJ19: =IF(OR($A19="",BJ$6="",NOT(ISNUMBER($H$2))),"",SUMIFS(数据录入!$G$5:$G$4999,数据录入!$C$5:$C$4999,$A19,数据录入!$B$5:$B$4999,BJ$6)) -> 0 | BK19: =IF(OR($A19="",BK$6="",NOT(ISNUMBER($H$2))),"",SUMIFS(数据录入!$F$5:$F$4999,数据录入!$C$5:$C$4999,$A19,数据录入!$B$5:$B$4999,BK$6)) | BL19: =IF(OR($A19="",BL$6="",NOT(ISNUMBER($H$2))),"",SUMIFS(数据录入!$G$5:$G$4999,数据录入!$C$5:$C$4999,$A19,数据录入!$B$5:$B$4999,BL$6)) | BM19: =IF($A19="","",SUMIF($C$7:$BL$7,"收款",C19:BL19)) -> 0 | BN19: =IF($A19="","",SUMIF($C$7:$BL$7,"付款",C19:BL19)) -> 200 | BO19: =IF($A19="","",B19+BM19-BN19) -> -200
... A21: 备用8 | B21: =IF(OR($A21="",NOT(ISNUMBER($H$2))),"",SUMIFS(数据录入!$H$5:$H$4999,数据录入!$C$5:$C$4999,$A21,数据录入!$E$5:$E$4999,"期初余额",数据录入!$B$5:$B$4999,"<="&$B$2)+SUMIFS(数据录入!$F$5:$F$4999,数据录入!$C$5:$C$4999,$A21,数据录入!$B$5:$B$4999,"<"&$B$2)-SUMIFS(数据录入!$G$5:$G$4999,数据录入!$C$5:$C$4999,$A21,数据录入!$B$5:$B$4999,"<"&$B$2)) -> 0 | C21: =IF(OR($A21="",C$6="",NOT(ISNUMBER($H$2))),"",SUMIFS(数据录入!$F$5:$F$4999,数据录入!$C$5:$C$4999,$A21,数据录入!$B$5:$B$4999,C$6)) -> 0 | D21: =IF(OR($A21="",D$6="",NOT(ISNUMBER($H$2))),"",SUMIFS(数据录入!$G$5:$G$4999,数据录入!$C$5:$C$4999,$A21,数据录入!$B$5:$B$4999,D$6)) -> 1000 | E21: =IF(OR($A21="",E$6="",NOT(ISNUMBER($H$2))),"",SUMIFS(数据录入!$F$5:$F$4999,数据录入!$C$5:$C$4999,$A21,数据录入!$B$5:$B$4999,E$6)) -> 0 | F21: =IF(OR($A21="",F$6="",NOT(ISNUMBER($H$2))),"",SUMIFS(数据录入!$G$5:$G$4999,数据录入!$C$5:$C$4999,$A21,数据录入!$B$5:$B$4999,F$6)) -> 0 | G21: =IF(OR($A21="",G$6="",NOT(ISNUMBER($H$2))),"",SUMIFS(数据录入!$F$5:$F$4999,数据录入!$C$5:$C$4999,$A21,数据录入!$B$5:$B$4999,G$6)) -> 0 | H21: =IF(OR($A21="",H$6="",NOT(ISNUMBER($H$2))),"",SUMIFS(数据录入!$G$5:$G$4999,数据录入!$C$5:$C$4999,$A21,数据录入!$B$5:$B$4999,H$6)) -> 0 | I21: =IF(OR($A21="",I$6="",NOT(ISNUMBER($H$2))),"",SUMIFS(数据录入!$F$5:$F$4999,数据录入!$C$5:$C$4999,$A21,数据录入!$B$5:$B$4999,I$6)) -> 0 | J21: =IF(OR($A21="",J$6="",NOT(ISNUMBER($H$2))),"",SUMIFS(数据录入!$G$5:$G$4999,数据录入!$C$5:$C$4999,$A21,数据录入!$B$5:$B$4999,J$6)) -> 0 | K21: =IF(OR($A21="",K$6="",NOT(ISNUMBER($H$2))),"",SUMIFS(数据录入!$F$5:$F$4999,数据录入!$C$5:$C$4999,$A21,数据录入!$B$5:$B$4999,K$6)) -> 0 | L21: =IF(OR($A21="",L$6="",NOT(ISNUMBER($H$2))),"",SUMIFS(数据录入!$G$5:$G$4999,数据录入!$C$5:$C$4999,$A21,数据录入!$B$5:$B$4999,L$6)) -> 0 | M21: =IF(OR($A21="",M$6="",NOT(ISNUMBER($H$2))),"",SUMIFS(数据录入!$F$5:$F$4999,数据录入!$C$5:$C$4999,$A21,数据录入!$B$5:$B$4999,M$6)) -> 0 | N21: =IF(OR($A21="",N$6="",NOT(ISNUMBER($H$2))),"",SUMIFS(数据录入!$G$5:$G$4999,数据录入!$C$5:$C$4999,$A21,数据录入!$B$5:$B$4999,N$6)) -> 0 | O21: =IF(OR($A21="",O$6="",NOT(ISNUMBER($H$2))),"",SUMIFS(数据录入!$F$5:$F$4999,数据录入!$C$5:$C$4999,$A21,数据录入!$B$5:$B$4999,O$6)) -> 0 | P21: =IF(OR($A21="",P$6="",NOT(ISNUMBER($H$2))),"",SUMIFS(数据录入!$G$5:$G$4999,数据录入!$C$5:$C$4999,$A21,数据录入!$B$5:$B$4999,P$6)) -> 0 | Q21: =IF(OR($A21="",Q$6="",NOT(ISNUMBER($H$2))),"",SUMIFS(数据录入!$F$5:$F$4999,数据录入!$C$5:$C$4999,$A21,数据录入!$B$5:$B$4999,Q$6)) -> 0 | R21: =IF(OR($A21="",R$6="",NOT(ISNUMBER($H$2))),"",SUMIFS(数据录入!$G$5:$G$4999,数据录入!$C$5:$C$4999,$A21,数据录入!$B$5:$B$4999,R$6)) -> 0 | S21: =IF(OR($A21="",S$6="",NOT(ISNUMBER($H$2))),"",SUMIFS(数据录入!$F$5:$F$4999,数据录入!$C$5:$C$4999,$A21,数据录入!$B$5:$B$4999,S$6)) -> 0 | T21: =IF(OR($A21="",T$6="",NOT(ISNUMBER($H$2))),"",SUMIFS(数据录入!$G$5:$G$4999,数据录入!$C$5:$C$4999,$A21,数据录入!$B$5:$B$4999,T$6)) -> 0 | U21: =IF(OR($A21="",U$6="",NOT(ISNUMBER($H$2))),"",SUMIFS(数据录入!$F$5:$F$4999,数据录入!$C$5:$C$4999,$A21,数据录入!$B$5:$B$4999,U$6)) -> 0 | V21: =IF(OR($A21="",V$6="",NOT(ISNUMBER($H$2))),"",SUMIFS(数据录入!$G$5:$G$4999,数据录入!$C$5:$C$4999,$A21,数据录入!$B$5:$B$4999,V$6)) -> 0 | W21: =IF(OR($A21="",W$6="",NOT(ISNUMBER($H$2))),"",SUMIFS(数据录入!$F$5:$F$4999,数据录入!$C$5:$C$4999,$A21,数据录入!$B$5:$B$4999,W$6)) -> 0 | X21: =IF(OR($A21="",X$6="",NOT(ISNUMBER($H$2))),"",SUMIFS(数据录入!$G$5:$G$4999,数据录入!$C$5:$C$4999,$A21,数据录入!$B$5:$B$4999,X$6)) -> 0 | Y21: =IF(OR($A21="",Y$6="",NOT(ISNUMBER($H$2))),"",SUMIFS(数据录入!$F$5:$F$4999,数据录入!$C$5:$C$4999,$A21,数据录入!$B$5:$B$4999,Y$6)) -> 0 | Z21: =IF(OR($A21="",Z$6="",NOT(ISNUMBER($H$2))),"",SUMIFS(数据录入!$G$5:$G$4999,数据录入!$C$5:$C$4999,$A21,数据录入!$B$5:$B$4999,Z$6)) -> 0 | AA21: =IF(OR($A21="",AA$6="",NOT(ISNUMBER($H$2))),"",SUMIFS(数据录入!$F$5:$F$4999,数据录入!$C$5:$C$4999,$A21,数据录入!$B$5:$B$4999,AA$6)) -> 0 | AB21: =IF(OR($A21="",AB$6="",NOT(ISNUMBER($H$2))),"",SUMIFS(数据录入!$G$5:$G$4999,数据录入!$C$5:$C$4999,$A21,数据录入!$B$5:$B$4999,AB$6)) -> 0 | AC21: =IF(OR($A21="",AC$6="",NOT(ISNUMBER($H$2))),"",SUMIFS(数据录入!$F$5:$F$4999,数据录入!$C$5:$C$4999,$A21,数据录入!$B$5:$B$4999,AC$6)) -> 0 | AD21: =IF(OR($A21="",AD$6="",NOT(ISNUMBER($H$2))),"",SUMIFS(数据录入!$G$5:$G$4999,数据录入!$C$5:$C$4999,$A21,数据录入!$B$5:$B$4999,AD$6)) -> 0 | AE21: =IF(OR($A21="",AE$6="",NOT(ISNUMBER($H$2))),"",SUMIFS(数据录入!$F$5:$F$4999,数据录入!$C$5:$C$4999,$A21,数据录入!$B$5:$B$4999,AE$6)) -> 0 | AF21: =IF(OR($A21="",AF$6="",NOT(ISNUMBER($H$2))),"",SUMIFS(数据录入!$G$5:$G$4999,数据录入!$C$5:$C$4999,$A21,数据录入!$B$5:$B$4999,AF$6)) -> 0 | AG21: =IF(OR($A21="",AG$6="",NOT(ISNUMBER($H$2))),"",SUMIFS(数据录入!$F$5:$F$4999,数据录入!$C$5:$C$4999,$A21,数据录入!$B$5:$B$4999,AG$6)) -> 0 | AH21: =IF(OR($A21="",AH$6="",NOT(ISNUMBER($H$2))),"",SUMIFS(数据录入!$G$5:$G$4999,数据录入!$C$5:$C$4999,$A21,数据录入!$B$5:$B$4999,AH$6)) -> 0 | AI21: =IF(OR($A21="",AI$6="",NOT(ISNUMBER($H$2))),"",SUMIFS(数据录入!$F$5:$F$4999,数据录入!$C$5:$C$4999,$A21,数据录入!$B$5:$B$4999,AI$6)) -> 0 | AJ21: =IF(OR($A21="",AJ$6="",NOT(ISNUMBER($H$2))),"",SUMIFS(数据录入!$G$5:$G$4999,数据录入!$C$5:$C$4999,$A21,数据录入!$B$5:$B$4999,AJ$6)) -> 0 | AK21: =IF(OR($A21="",AK$6="",NOT(ISNUMBER($H$2))),"",SUMIFS(数据录入!$F$5:$F$4999,数据录入!$C$5:$C$4999,$A21,数据录入!$B$5:$B$4999,AK$6)) -> 0 | AL21: =IF(OR($A21="",AL$6="",NOT(ISNUMBER($H$2))),"",SUMIFS(数据录入!$G$5:$G$4999,数据录入!$C$5:$C$4999,$A21,数据录入!$B$5:$B$4999,AL$6)) -> 0 | AM21: =IF(OR($A21="",AM$6="",NOT(ISNUMBER($H$2))),"",SUMIFS(数据录入!$F$5:$F$4999,数据录入!$C$5:$C$4999,$A21,数据录入!$B$5:$B$4999,AM$6)) -> 0 | AN21: =IF(OR($A21="",AN$6="",NOT(ISNUMBER($H$2))),"",SUMIFS(数据录入!$G$5:$G$4999,数据录入!$C$5:$C$4999,$A21,数据录入!$B$5:$B$4999,AN$6)) -> 0 | AO21: =IF(OR($A21="",AO$6="",NOT(ISNUMBER($H$2))),"",SUMIFS(数据录入!$F$5:$F$4999,数据录入!$C$5:$C$4999,$A21,数据录入!$B$5:$B$4999,AO$6)) -> 0 | AP21: =IF(OR($A21="",AP$6="",NOT(ISNUMBER($H$2))),"",SUMIFS(数据录入!$G$5:$G$4999,数据录入!$C$5:$C$4999,$A21,数据录入!$B$5:$B$4999,AP$6)) -> 0 | AQ21: =IF(OR($A21="",AQ$6="",NOT(ISNUMBER($H$2))),"",SUMIFS(数据录入!$F$5:$F$4999,数据录入!$C$5:$C$4999,$A21,数据录入!$B$5:$B$4999,AQ$6)) -> 0 | AR21: =IF(OR($A21="",AR$6="",NOT(ISNUMBER($H$2))),"",SUMIFS(数据录入!$G$5:$G$4999,数据录入!$C$5:$C$4999,$A21,数据录入!$B$5:$B$4999,AR$6)) -> 0 | AS21: =IF(OR($A21="",AS$6="",NOT(ISNUMBER($H$2))),"",SUMIFS(数据录入!$F$5:$F$4999,数据录入!$C$5:$C$4999,$A21,数据录入!$B$5:$B$4999,AS$6)) -> 0 | AT21: =IF(OR($A21="",AT$6="",NOT(ISNUMBER($H$2))),"",SUMIFS(数据录入!$G$5:$G$4999,数据录入!$C$5:$C$4999,$A21,数据录入!$B$5:$B$4999,AT$6)) -> 0 | AU21: =IF(OR($A21="",AU$6="",NOT(ISNUMBER($H$2))),"",SUMIFS(数据录入!$F$5:$F$4999,数据录入!$C$5:$C$4999,$A21,数据录入!$B$5:$B$4999,AU$6)) -> 0 | AV21: =IF(OR($A21="",AV$6="",NOT(ISNUMBER($H$2))),"",SUMIFS(数据录入!$G$5:$G$4999,数据录入!$C$5:$C$4999,$A21,数据录入!$B$5:$B$4999,AV$6)) -> 0 | AW21: =IF(OR($A21="",AW$6="",NOT(ISNUMBER($H$2))),"",SUMIFS(数据录入!$F$5:$F$4999,数据录入!$C$5:$C$4999,$A21,数据录入!$B$5:$B$4999,AW$6)) -> 0 | AX21: =IF(OR($A21="",AX$6="",NOT(ISNUMBER($H$2))),"",SUMIFS(数据录入!$G$5:$G$4999,数据录入!$C$5:$C$4999,$A21,数据录入!$B$5:$B$4999,AX$6)) -> 0 | AY21: =IF(OR($A21="",AY$6="",NOT(ISNUMBER($H$2))),"",SUMIFS(数据录入!$F$5:$F$4999,数据录入!$C$5:$C$4999,$A21,数据录入!$B$5:$B$4999,AY$6)) -> 0 | AZ21: =IF(OR($A21="",AZ$6="",NOT(ISNUMBER($H$2))),"",SUMIFS(数据录入!$G$5:$G$4999,数据录入!$C$5:$C$4999,$A21,数据录入!$B$5:$B$4999,AZ$6)) -> 0 | BA21: =IF(OR($A21="",BA$6="",NOT(ISNUMBER($H$2))),"",SUMIFS(数据录入!$F$5:$F$4999,数据录入!$C$5:$C$4999,$A21,数据录入!$B$5:$B$4999,BA$6)) -> 0 | BB21: =IF(OR($A21="",BB$6="",NOT(ISNUMBER($H$2))),"",SUMIFS(数据录入!$G$5:$G$4999,数据录入!$C$5:$C$4999,$A21,数据录入!$B$5:$B$4999,BB$6)) -> 0 | BC21: =IF(OR($A21="",BC$6="",NOT(ISNUMBER($H$2))),"",SUMIFS(数据录入!$F$5:$F$4999,数据录入!$C$5:$C$4999,$A21,数据录入!$B$5:$B$4999,BC$6)) -> 0 | BD21: =IF(OR($A21="",BD$6="",NOT(ISNUMBER($H$2))),"",SUMIFS(数据录入!$G$5:$G$4999,数据录入!$C$5:$C$4999,$A21,数据录入!$B$5:$B$4999,BD$6)) -> 0 | BE21: =IF(OR($A21="",BE$6="",NOT(ISNUMBER($H$2))),"",SUMIFS(数据录入!$F$5:$F$4999,数据录入!$C$5:$C$4999,$A21,数据录入!$B$5:$B$4999,BE$6)) -> 0 | BF21: =IF(OR($A21="",BF$6="",NOT(ISNUMBER($H$2))),"",SUMIFS(数据录入!$G$5:$G$4999,数据录入!$C$5:$C$4999,$A21,数据录入!$B$5:$B$4999,BF$6)) -> 0 | BG21: =IF(OR($A21="",BG$6="",NOT(ISNUMBER($H$2))),"",SUMIFS(数据录入!$F$5:$F$4999,数据录入!$C$5:$C$4999,$A21,数据录入!$B$5:$B$4999,BG$6)) -> 0 | BH21: =IF(OR($A21="",BH$6="",NOT(ISNUMBER($H$2))),"",SUMIFS(数据录入!$G$5:$G$4999,数据录入!$C$5:$C$4999,$A21,数据录入!$B$5:$B$4999,BH$6)) -> 0 | BI21: =IF(OR($A21="",BI$6="",NOT(ISNUMBER($H$2))),"",SUMIFS(数据录入!$F$5:$F$4999,数据录入!$C$5:$C$4999,$A21,数据录入!$B$5:$B$4999,BI$6)) -> 0 | BJ21: =IF(OR($A21="",BJ$6="",NOT(ISNUMBER($H$2))),"",SUMIFS(数据录入!$G$5:$G$4999,数据录入!$C$5:$C$4999,$A21,数据录入!$B$5:$B$4999,BJ$6)) -> 0 | BK21: =IF(OR($A21="",BK$6="",NOT(ISNUMBER($H$2))),"",SUMIFS(数据录入!$F$5:$F$4999,数据录入!$C$5:$C$4999,$A21,数据录入!$B$5:$B$4999,BK$6)) | BL21: =IF(OR($A21="",BL$6="",NOT(ISNUMBER($H$2))),"",SUMIFS(数据录入!$G$5:$G$4999,数据录入!$C$5:$C$4999,$A21,数据录入!$B$5:$B$4999,BL$6)) | BM21: =IF($A21="","",SUMIF($C$7:$BL$7,"收款",C21:BL21)) -> 0 | BN21: =IF($A21="","",SUMIF($C$7:$BL$7,"付款",C21:BL21)) -> 1000 | BO21: =IF($A21="","",B21+BM21-BN21) -> -1000
A22: 合计 | B22: =SUM(B8:B21) -> 0 | C22: =SUM(C8:C21) -> 22200 | D22: =SUM(D8:D21) -> 11660 | E22: =SUM(E8:E21) -> 0 | F22: =SUM(F8:F21) -> 0 | G22: =SUM(G8:G21) -> 0 | H22: =SUM(H8:H21) -> 0 | I22: =SUM(I8:I21) -> 0 | ... BO22: =SUM(BO8:BO21) -> 10540
A24: 货币资金日报表 | H24: 多帐户资金汇总表（月度汇总）
B25: 日期： | C25: 46279 | F25: 单位：元 | I25: 月份： | K25: 46266
A26: 序号 | B26: 账户 | C26: 昨日余额 | D26: 本日收入 | E26: 本日支出 | F26: 本日余额 | H26: 序号 | I26: 账号名称 | J26: 期初余额 | K26: 本月收入 | L26: 本月支出 | M26: 结余 | P26: 本列不要删除
A27: 1 | B27: 现金 | C27: =IF($B27="","",SUMIFS(数据录入!$H$5:$H$4999,数据录入!$C$5:$C$4999,$B27,数据录入!$E$5:$E$4999,"期初余额",数据录入!$B$5:$B$4999,"<="&$C$25)+SUMIFS(数据录入!$F$5:$F$4999,数据录入!$C$5:$C$4999,$B27,数据录入!$B$5:$B$4999,"<"&$C$25)-SUMIFS(数据录入!$G$5:$G$4999,数据录入!$C$5:$C$4999,$B27,数据录入!$B$5:$B$4999,"<"&$C$25)) -> 1800 | D27: =IF($B27="","",SUMIFS(数据录入!$F$5:$F$4999,数据录入!$C$5:$C$4999,$B27,数据录入!$B$5:$B$4999,$C$25)) -> 0 | E27: =IF($B27="","",SUMIFS(数据录入!$G$5:$G$4999,数据录入!$C$5:$C$4999,$B27,数据录入!$B$5:$B$4999,$C$25)) -> 0 | F27: =IF($B27="","",C27+D27-E27) -> 1800 | H27: 1 | I27: 现金 | J27: =IF($I27="","",SUMIFS(数据录入!$H$5:$H$4999,数据录入!$C$5:$C$4999,$I27,数据录入!$E$5:$E$4999,"期初余额",数据录入!$B$5:$B$4999,"<="&DATE(YEAR($K$25),MONTH($K$25),1))+SUMIFS(数据录入!$F$5:$F$4999,数据录入!$C$5:$C$4999,$I27,数据录入!$B$5:$B$4999,"<"&DATE(YEAR($K$25),MONTH($K$25),1))-SUMIFS(数据录入!$G$5:$G$4999,数据录入!$C$5:$C$4999,$I27,数据录入!$B$5:$B$4999,"<"&DATE(YEAR($K$25),MONTH($K$25),1))) -> 0 | K27: =IF($I27="","",SUMIFS(数据录入!$F$5:$F$4999,数据录入!$C$5:$C$4999,$I27,数据录入!$B$5:$B$4999,">="&DATE(YEAR($K$25),MONTH($K$25),1),数据录入!$B$5:$B$4999,"<="&DATE(YEAR($K$25),MONTH($K$25)+1,0))) -> 2000 | L27: =IF($I27="","",SUMIFS(数据录入!$G$5:$G$4999,数据录入!$C$5:$C$4999,$I27,数据录入!$B$5:$B$4999,">="&DATE(YEAR($K$25),MONTH($K$25),1),数据录入!$B$5:$B$4999,"<="&DATE(YEAR($K$25),MONTH($K$25)+1,0))) -> 200 | M27: =IF($I27="","",J27+K27-L27) -> 1800 | P27: 月份筛选列
A28: 2 | B28: 微信 | C28: =IF($B28="","",SUMIFS(数据录入!$H$5:$H$4999,数据录入!$C$5:$C$4999,$B28,数据录入!$E$5:$E$4999,"期初余额",数据录入!$B$5:$B$4999,"<="&$C$25)+SUMIFS(数据录入!$F$5:$F$4999,数据录入!$C$5:$C$4999,$B28,数据录入!$B$5:$B$4999,"<"&$C$25)-SUMIFS(数据录入!$G$5:$G$4999,数据录入!$C$5:$C$4999,$B28,数据录入!$B$5:$B$4999,"<"&$C$25)) -> -700 | D28: =IF($B28="","",SUMIFS(数据录入!$F$5:$F$4999,数据录入!$C$5:$C$4999,$B28,数据录入!$B$5:$B$4999,$C$25)) -> 0 | E28: =IF($B28="","",SUMIFS(数据录入!$G$5:$G$4999,数据录入!$C$5:$C$4999,$B28,数据录入!$B$5:$B$4999,$C$25)) -> 0 | F28: =IF($B28="","",C28+D28-E28) -> -700 | H28: 2 | I28: 微信 | J28: =IF($I28="","",SUMIFS(数据录入!$H$5:$H$4999,数据录入!$C$5:$C$4999,$I28,数据录入!$E$5:$E$4999,"期初余额",数据录入!$B$5:$B$4999,"<="&DATE(YEAR($K$25),MONTH($K$25),1))+SUMIFS(数据录入!$F$5:$F$4999,数据录入!$C$5:$C$4999,$I28,数据录入!$B$5:$B$4999,"<"&DATE(YEAR($K$25),MONTH($K$25),1))-SUMIFS(数据录入!$G$5:$G$4999,数据录入!$C$5:$C$4999,$I28,数据录入!$B$5:$B$4999,"<"&DATE(YEAR($K$25),MONTH($K$25),1))) -> 0 | K28: =IF($I28="","",SUMIFS(数据录入!$F$5:$F$4999,数据录入!$C$5:$C$4999,$I28,数据录入!$B$5:$B$4999,">="&DATE(YEAR($K$25),MONTH($K$25),1),数据录入!$B$5:$B$4999,"<="&DATE(YEAR($K$25),MONTH($K$25)+1,0))) -> 0 | L28: =IF($I28="","",SUMIFS(数据录入!$G$5:$G$4999,数据录入!$C$5:$C$4999,$I28,数据录入!$B$5:$B$4999,">="&DATE(YEAR($K$25),MONTH($K$25),1),数据录入!$B$5:$B$4999,"<="&DATE(YEAR($K$25),MONTH($K$25)+1,0))) -> 700 | M28: =IF($I28="","",J28+K28-L28) -> -700 | P28: 46023
A29: 3 | B29: 支付宝 | C29: =IF($B29="","",SUMIFS(数据录入!$H$5:$H$4999,数据录入!$C$5:$C$4999,$B29,数据录入!$E$5:$E$4999,"期初余额",数据录入!$B$5:$B$4999,"<="&$C$25)+SUMIFS(数据录入!$F$5:$F$4999,数据录入!$C$5:$C$4999,$B29,数据录入!$B$5:$B$4999,"<"&$C$25)-SUMIFS(数据录入!$G$5:$G$4999,数据录入!$C$5:$C$4999,$B29,数据录入!$B$5:$B$4999,"<"&$C$25)) -> -800 | D29: =IF($B29="","",SUMIFS(数据录入!$F$5:$F$4999,数据录入!$C$5:$C$4999,$B29,数据录入!$B$5:$B$4999,$C$25)) -> 0 | E29: =IF($B29="","",SUMIFS(数据录入!$G$5:$G$4999,数据录入!$C$5:$C$4999,$B29,数据录入!$B$5:$B$4999,$C$25)) -> 0 | F29: =IF($B29="","",C29+D29-E29) -> -800 | H29: 3 | I29: 支付宝 | J29: =IF($I29="","",SUMIFS(数据录入!$H$5:$H$4999,数据录入!$C$5:$C$4999,$I29,数据录入!$E$5:$E$4999,"期初余额",数据录入!$B$5:$B$4999,"<="&DATE(YEAR($K$25),MONTH($K$25),1))+SUMIFS(数据录入!$F$5:$F$4999,数据录入!$C$5:$C$4999,$I29,数据录入!$B$5:$B$4999,"<"&DATE(YEAR($K$25),MONTH($K$25),1))-SUMIFS(数据录入!$G$5:$G$4999,数据录入!$C$5:$C$4999,$I29,数据录入!$B$5:$B$4999,"<"&DATE(YEAR($K$25),MONTH($K$25),1))) -> 0 | K29: =IF($I29="","",SUMIFS(数据录入!$F$5:$F$4999,数据录入!$C$5:$C$4999,$I29,数据录入!$B$5:$B$4999,">="&DATE(YEAR($K$25),MONTH($K$25),1),数据录入!$B$5:$B$4999,"<="&DATE(YEAR($K$25),MONTH($K$25)+1,0))) -> 0 | L29: =IF($I29="","",SUMIFS(数据录入!$G$5:$G$4999,数据录入!$C$5:$C$4999,$I29,数据录入!$B$5:$B$4999,">="&DATE(YEAR($K$25),MONTH($K$25),1),数据录入!$B$5:$B$4999,"<="&DATE(YEAR($K$25),MONTH($K$25)+1,0))) -> 800 | M29: =IF($I29="","",J29+K29-L29) -> -800 | P29: 46054
A30: 4 | B30: 杭州 | C30: =IF($B30="","",SUMIFS(数据录入!$H$5:$H$4999,数据录入!$C$5:$C$4999,$B30,数据录入!$E$5:$E$4999,"期初余额",数据录入!$B$5:$B$4999,"<="&$C$25)+SUMIFS(数据录入!$F$5:$F$4999,数据录入!$C$5:$C$4999,$B30,数据录入!$B$5:$B$4999,"<"&$C$25)-SUMIFS(数据录入!$G$5:$G$4999,数据录入!$C$5:$C$4999,$B30,数据录入!$B$5:$B$4999,"<"&$C$25)) -> 4500 | D30: =IF($B30="","",SUMIFS(数据录入!$F$5:$F$4999,数据录入!$C$5:$C$4999,$B30,数据录入!$B$5:$B$4999,$C$25)) -> 0 | E30: =IF($B30="","",SUMIFS(数据录入!$G$5:$G$4999,数据录入!$C$5:$C$4999,$B30,数据录入!$B$5:$B$4999,$C$25)) -> 0 | F30: =IF($B30="","",C30+D30-E30) -> 4500 | H30: 4 | I30: 杭州 | J30: =IF($I30="","",SUMIFS(数据录入!$H$5:$H$4999,数据录入!$C$5:$C$4999,$I30,数据录入!$E$5:$E$4999,"期初余额",数据录入!$B$5:$B$4999,"<="&DATE(YEAR($K$25),MONTH($K$25),1))+SUMIFS(数据录入!$F$5:$F$4999,数据录入!$C$5:$C$4999,$I30,数据录入!$B$5:$B$4999,"<"&DATE(YEAR($K$25),MONTH($K$25),1))-SUMIFS(数据录入!$G$5:$G$4999,数据录入!$C$5:$C$4999,$I30,数据录入!$B$5:$B$4999,"<"&DATE(YEAR($K$25),MONTH($K$25),1))) -> 0 | K30: =IF($I30="","",SUMIFS(数据录入!$F$5:$F$4999,数据录入!$C$5:$C$4999,$I30,数据录入!$B$5:$B$4999,">="&DATE(YEAR($K$25),MONTH($K$25),1),数据录入!$B$5:$B$4999,"<="&DATE(YEAR($K$25),MONTH($K$25)+1,0))) -> 5000 | L30: =IF($I30="","",SUMIFS(数据录入!$G$5:$G$4999,数据录入!$C$5:$C$4999,$I30,数据录入!$B$5:$B$4999,">="&DATE(YEAR($K$25),MONTH($K$25),1),数据录入!$B$5:$B$4999,"<="&DATE(YEAR($K$25),MONTH($K$25)+1,0))) -> 500 | M30: =IF($I30="","",J30+K30-L30) -> 4500 | P30: 46082
A31: 5 | B31: 农商 | C31: =IF($B31="","",SUMIFS(数据录入!$H$5:$H$4999,数据录入!$C$5:$C$4999,$B31,数据录入!$E$5:$E$4999,"期初余额",数据录入!$B$5:$B$4999,"<="&$C$25)+SUMIFS(数据录入!$F$5:$F$4999,数据录入!$C$5:$C$4999,$B31,数据录入!$B$5:$B$4999,"<"&$C$25)-SUMIFS(数据录入!$G$5:$G$4999,数据录入!$C$5:$C$4999,$B31,数据录入!$B$5:$B$4999,"<"&$C$25)) -> 3100 | D31: =IF($B31="","",SUMIFS(数据录入!$F$5:$F$4999,数据录入!$C$5:$C$4999,$B31,数据录入!$B$5:$B$4999,$C$25)) -> 0 | E31: =IF($B31="","",SUMIFS(数据录入!$G$5:$G$4999,数据录入!$C$5:$C$4999,$B31,数据录入!$B$5:$B$4999,$C$25)) -> 0 | F31: =IF($B31="","",C31+D31-E31) -> 3100 | H31: 5 | I31: 农商 | J31: =IF($I31="","",SUMIFS(数据录入!$H$5:$H$4999,数据录入!$C$5:$C$4999,$I31,数据录入!$E$5:$E$4999,"期初余额",数据录入!$B$5:$B$4999,"<="&DATE(YEAR($K$25),MONTH($K$25),1))+SUMIFS(数据录入!$F$5:$F$4999,数据录入!$C$5:$C$4999,$I31,数据录入!$B$5:$B$4999,"<"&DATE(YEAR($K$25),MONTH($K$25),1))-SUMIFS(数据录入!$G$5:$G$4999,数据录入!$C$5:$C$4999,$I31,数据录入!$B$5:$B$4999,"<"&DATE(YEAR($K$25),MONTH($K$25),1))) -> 0 | K31: =IF($I31="","",SUMIFS(数据录入!$F$5:$F$4999,数据录入!$C$5:$C$4999,$I31,数据录入!$B$5:$B$4999,">="&DATE(YEAR($K$25),MONTH($K$25),1),数据录入!$B$5:$B$4999,"<="&DATE(YEAR($K$25),MONTH($K$25)+1,0))) -> 3100 | L31: =IF($I31="","",SUMIFS(数据录入!$G$5:$G$4999,数据录入!$C$5:$C$4999,$I31,数据录入!$B$5:$B$4999,">="&DATE(YEAR($K$25),MONTH($K$25),1),数据录入!$B$5:$B$4999,"<="&DATE(YEAR($K$25),MONTH($K$25)+1,0))) -> 0 | M31: =IF($I31="","",J31+K31-L31) -> 3100 | P31: 46113
A32: 6 | B32: 备用 | C32: =IF($B32="","",SUMIFS(数据录入!$H$5:$H$4999,数据录入!$C$5:$C$4999,$B32,数据录入!$E$5:$E$4999,"期初余额",数据录入!$B$5:$B$4999,"<="&$C$25)+SUMIFS(数据录入!$F$5:$F$4999,数据录入!$C$5:$C$4999,$B32,数据录入!$B$5:$B$4999,"<"&$C$25)-SUMIFS(数据录入!$G$5:$G$4999,数据录入!$C$5:$C$4999,$B32,数据录入!$B$5:$B$4999,"<"&$C$25)) -> -5500 | D32: =IF($B32="","",SUMIFS(数据录入!$F$5:$F$4999,数据录入!$C$5:$C$4999,$B32,数据录入!$B$5:$B$4999,$C$25)) -> 0 | E32: =IF($B32="","",SUMIFS(数据录入!$G$5:$G$4999,数据录入!$C$5:$C$4999,$B32,数据录入!$B$5:$B$4999,$C$25)) -> 0 | F32: =IF($B32="","",C32+D32-E32) -> -5500 | H32: 6 | I32: 备用 | J32: =IF($I32="","",SUMIFS(数据录入!$H$5:$H$4999,数据录入!$C$5:$C$4999,$I32,数据录入!$E$5:$E$4999,"期初余额",数据录入!$B$5:$B$4999,"<="&DATE(YEAR($K$25),MONTH($K$25),1))+SUMIFS(数据录入!$F$5:$F$4999,数据录入!$C$5:$C$4999,$I32,数据录入!$B$5:$B$4999,"<"&DATE(YEAR($K$25),MONTH($K$25),1))-SUMIFS(数据录入!$G$5:$G$4999,数据录入!$C$5:$C$4999,$I32,数据录入!$B$5:$B$4999,"<"&DATE(YEAR($K$25),MONTH($K$25),1))) -> 0 | K32: =IF($I32="","",SUMIFS(数据录入!$F$5:$F$4999,数据录入!$C$5:$C$4999,$I32,数据录入!$B$5:$B$4999,">="&DATE(YEAR($K$25),MONTH($K$25),1),数据录入!$B$5:$B$4999,"<="&DATE(YEAR($K$25),MONTH($K$25)+1,0))) -> 0 | L32: =IF($I32="","",SUMIFS(数据录入!$G$5:$G$4999,数据录入!$C$5:$C$4999,$I32,数据录入!$B$5:$B$4999,">="&DATE(YEAR($K$25),MONTH($K$25),1),数据录入!$B$5:$B$4999,"<="&DATE(YEAR($K$25),MONTH($K$25)+1,0))) -> 5500 | M32: =IF($I32="","",J32+K32-L32) -> -5500 | P32: 46143
A33: 7 | B33: 备用1 | C33: =IF($B33="","",SUMIFS(数据录入!$H$5:$H$4999,数据录入!$C$5:$C$4999,$B33,数据录入!$E$5:$E$4999,"期初余额",数据录入!$B$5:$B$4999,"<="&$C$25)+SUMIFS(数据录入!$F$5:$F$4999,数据录入!$C$5:$C$4999,$B33,数据录入!$B$5:$B$4999,"<"&$C$25)-SUMIFS(数据录入!$G$5:$G$4999,数据录入!$C$5:$C$4999,$B33,数据录入!$B$5:$B$4999,"<"&$C$25)) -> 9800 | D33: =IF($B33="","",SUMIFS(数据录入!$F$5:$F$4999,数据录入!$C$5:$C$4999,$B33,数据录入!$B$5:$B$4999,$C$25)) -> 0 | E33: =IF($B33="","",SUMIFS(数据录入!$G$5:$G$4999,数据录入!$C$5:$C$4999,$B33,数据录入!$B$5:$B$4999,$C$25)) -> 0 | F33: =IF($B33="","",C33+D33-E33) -> 9800 | H33: 7 | I33: 备用1 | J33: =IF($I33="","",SUMIFS(数据录入!$H$5:$H$4999,数据录入!$C$5:$C$4999,$I33,数据录入!$E$5:$E$4999,"期初余额",数据录入!$B$5:$B$4999,"<="&DATE(YEAR($K$25),MONTH($K$25),1))+SUMIFS(数据录入!$F$5:$F$4999,数据录入!$C$5:$C$4999,$I33,数据录入!$B$5:$B$4999,"<"&DATE(YEAR($K$25),MONTH($K$25),1))-SUMIFS(数据录入!$G$5:$G$4999,数据录入!$C$5:$C$4999,$I33,数据录入!$B$5:$B$4999,"<"&DATE(YEAR($K$25),MONTH($K$25),1))) -> 0 | K33: =IF($I33="","",SUMIFS(数据录入!$F$5:$F$4999,数据录入!$C$5:$C$4999,$I33,数据录入!$B$5:$B$4999,">="&DATE(YEAR($K$25),MONTH($K$25),1),数据录入!$B$5:$B$4999,"<="&DATE(YEAR($K$25),MONTH($K$25)+1,0))) -> 10000 | L33: =IF($I33="","",SUMIFS(数据录入!$G$5:$G$4999,数据录入!$C$5:$C$4999,$I33,数据录入!$B$5:$B$4999,">="&DATE(YEAR($K$25),MONTH($K$25),1),数据录入!$B$5:$B$4999,"<="&DATE(YEAR($K$25),MONTH($K$25)+1,0))) -> 200 | M33: =IF($I33="","",J33+K33-L33) -> 9800 | P33: 46174
A34: 8 | B34: 备用2 | C34: =IF($B34="","",SUMIFS(数据录入!$H$5:$H$4999,数据录入!$C$5:$C$4999,$B34,数据录入!$E$5:$E$4999,"期初余额",数据录入!$B$5:$B$4999,"<="&$C$25)+SUMIFS(数据录入!$F$5:$F$4999,数据录入!$C$5:$C$4999,$B34,数据录入!$B$5:$B$4999,"<"&$C$25)-SUMIFS(数据录入!$G$5:$G$4999,数据录入!$C$5:$C$4999,$B34,数据录入!$B$5:$B$4999,"<"&$C$25)) -> 990 | D34: =IF($B34="","",SUMIFS(数据录入!$F$5:$F$4999,数据录入!$C$5:$C$4999,$B34,数据录入!$B$5:$B$4999,$C$25)) -> 0 | E34: =IF($B34="","",SUMIFS(数据录入!$G$5:$G$4999,数据录入!$C$5:$C$4999,$B34,数据录入!$B$5:$B$4999,$C$25)) -> 0 | F34: =IF($B34="","",C34+D34-E34) -> 990 | H34: 8 | I34: 备用2 | J34: =IF($I34="","",SUMIFS(数据录入!$H$5:$H$4999,数据录入!$C$5:$C$4999,$I34,数据录入!$E$5:$E$4999,"期初余额",数据录入!$B$5:$B$4999,"<="&DATE(YEAR($K$25),MONTH($K$25),1))+SUMIFS(数据录入!$F$5:$F$4999,数据录入!$C$5:$C$4999,$I34,数据录入!$B$5:$B$4999,"<"&DATE(YEAR($K$25),MONTH($K$25),1))-SUMIFS(数据录入!$G$5:$G$4999,数据录入!$C$5:$C$4999,$I34,数据录入!$B$5:$B$4999,"<"&DATE(YEAR($K$25),MONTH($K$25),1))) -> 0 | K34: =IF($I34="","",SUMIFS(数据录入!$F$5:$F$4999,数据录入!$C$5:$C$4999,$I34,数据录入!$B$5:$B$4999,">="&DATE(YEAR($K$25),MONTH($K$25),1),数据录入!$B$5:$B$4999,"<="&DATE(YEAR($K$25),MONTH($K$25)+1,0))) -> 1000 | L34: =IF($I34="","",SUMIFS(数据录入!$G$5:$G$4999,数据录入!$C$5:$C$4999,$I34,数据录入!$B$5:$B$4999,">="&DATE(YEAR($K$25),MONTH($K$25),1),数据录入!$B$5:$B$4999,"<="&DATE(YEAR($K$25),MONTH($K$25)+1,0))) -> 10 | M34: =IF($I34="","",J34+K34-L34) -> 990 | P34: 46204
A35: 9 | B35: 备用3 | C35: =IF($B35="","",SUMIFS(数据录入!$H$5:$H$4999,数据录入!$C$5:$C$4999,$B35,数据录入!$E$5:$E$4999,"期初余额",数据录入!$B$5:$B$4999,"<="&$C$25)+SUMIFS(数据录入!$F$5:$F$4999,数据录入!$C$5:$C$4999,$B35,数据录入!$B$5:$B$4999,"<"&$C$25)-SUMIFS(数据录入!$G$5:$G$4999,数据录入!$C$5:$C$4999,$B35,数据录入!$B$5:$B$4999,"<"&$C$25)) -> -1050 | D35: =IF($B35="","",SUMIFS(数据录入!$F$5:$F$4999,数据录入!$C$5:$C$4999,$B35,数据录入!$B$5:$B$4999,$C$25)) -> 0 | E35: =IF($B35="","",SUMIFS(数据录入!$G$5:$G$4999,数据录入!$C$5:$C$4999,$B35,数据录入!$B$5:$B$4999,$C$25)) -> 0 | F35: =IF($B35="","",C35+D35-E35) -> -1050 | H35: 9 | I35: 备用3 | J35: =IF($I35="","",SUMIFS(数据录入!$H$5:$H$4999,数据录入!$C$5:$C$4999,$I35,数据录入!$E$5:$E$4999,"期初余额",数据录入!$B$5:$B$4999,"<="&DATE(YEAR($K$25),MONTH($K$25),1))+SUMIFS(数据录入!$F$5:$F$4999,数据录入!$C$5:$C$4999,$I35,数据录入!$B$5:$B$4999,"<"&DATE(YEAR($K$25),MONTH($K$25),1))-SUMIFS(数据录入!$G$5:$G$4999,数据录入!$C$5:$C$4999,$I35,数据录入!$B$5:$B$4999,"<"&DATE(YEAR($K$25),MONTH($K$25),1))) -> 0 | K35: =IF($I35="","",SUMIFS(数据录入!$F$5:$F$4999,数据录入!$C$5:$C$4999,$I35,数据录入!$B$5:$B$4999,">="&DATE(YEAR($K$25),MONTH($K$25),1),数据录入!$B$5:$B$4999,"<="&DATE(YEAR($K$25),MONTH($K$25)+1,0))) -> -1000 | L35: =IF($I35="","",SUMIFS(数据录入!$G$5:$G$4999,数据录入!$C$5:$C$4999,$I35,数据录入!$B$5:$B$4999,">="&DATE(YEAR($K$25),MONTH($K$25),1),数据录入!$B$5:$B$4999,"<="&DATE(YEAR($K$25),MONTH($K$25)+1,0))) -> 50 | M35: =IF($I35="","",J35+K35-L35) -> -1050 | P35: 46235
A36: 10 | B36: 备用4 | C36: =IF($B36="","",SUMIFS(数据录入!$H$5:$H$4999,数据录入!$C$5:$C$4999,$B36,数据录入!$E$5:$E$4999,"期初余额",数据录入!$B$5:$B$4999,"<="&$C$25)+SUMIFS(数据录入!$F$5:$F$4999,数据录入!$C$5:$C$4999,$B36,数据录入!$B$5:$B$4999,"<"&$C$25)-SUMIFS(数据录入!$G$5:$G$4999,数据录入!$C$5:$C$4999,$B36,数据录入!$B$5:$B$4999,"<"&$C$25)) -> 2100 | D36: =IF($B36="","",SUMIFS(数据录入!$F$5:$F$4999,数据录入!$C$5:$C$4999,$B36,数据录入!$B$5:$B$4999,$C$25)) -> 0 | E36: =IF($B36="","",SUMIFS(数据录入!$G$5:$G$4999,数据录入!$C$5:$C$4999,$B36,数据录入!$B$5:$B$4999,$C$25)) -> 0 | F36: =IF($B36="","",C36+D36-E36) -> 2100 | H36: 10 | I36: 备用4 | J36: =IF($I36="","",SUMIFS(数据录入!$H$5:$H$4999,数据录入!$C$5:$C$4999,$I36,数据录入!$E$5:$E$4999,"期初余额",数据录入!$B$5:$B$4999,"<="&DATE(YEAR($K$25),MONTH($K$25),1))+SUMIFS(数据录入!$F$5:$F$4999,数据录入!$C$5:$C$4999,$I36,数据录入!$B$5:$B$4999,"<"&DATE(YEAR($K$25),MONTH($K$25),1))-SUMIFS(数据录入!$G$5:$G$4999,数据录入!$C$5:$C$4999,$I36,数据录入!$B$5:$B$4999,"<"&DATE(YEAR($K$25),MONTH($K$25),1))) -> 0 | K36: =IF($I36="","",SUMIFS(数据录入!$F$5:$F$4999,数据录入!$C$5:$C$4999,$I36,数据录入!$B$5:$B$4999,">="&DATE(YEAR($K$25),MONTH($K$25),1),数据录入!$B$5:$B$4999,"<="&DATE(YEAR($K$25),MONTH($K$25)+1,0))) -> 2100 | L36: =IF($I36="","",SUMIFS(数据录入!$G$5:$G$4999,数据录入!$C$5:$C$4999,$I36,数据录入!$B$5:$B$4999,">="&DATE(YEAR($K$25),MONTH($K$25),1),数据录入!$B$5:$B$4999,"<="&DATE(YEAR($K$25),MONTH($K$25)+1,0))) -> 0 | M36: =IF($I36="","",J36+K36-L36) -> 2100 | P36: 46266
A37: 11 | B37: 备用5 | C37: =IF($B37="","",SUMIFS(数据录入!$H$5:$H$4999,数据录入!$C$5:$C$4999,$B37,数据录入!$E$5:$E$4999,"期初余额",数据录入!$B$5:$B$4999,"<="&$C$25)+SUMIFS(数据录入!$F$5:$F$4999,数据录入!$C$5:$C$4999,$B37,数据录入!$B$5:$B$4999,"<"&$C$25)-SUMIFS(数据录入!$G$5:$G$4999,数据录入!$C$5:$C$4999,$B37,数据录入!$B$5:$B$4999,"<"&$C$25)) -> -2000 | D37: =IF($B37="","",SUMIFS(数据录入!$F$5:$F$4999,数据录入!$C$5:$C$4999,$B37,数据录入!$B$5:$B$4999,$C$25)) -> 0 | E37: =IF($B37="","",SUMIFS(数据录入!$G$5:$G$4999,数据录入!$C$5:$C$4999,$B37,数据录入!$B$5:$B$4999,$C$25)) -> 0 | F37: =IF($B37="","",C37+D37-E37) -> -2000 | H37: 11 | I37: 备用5 | J37: =IF($I37="","",SUMIFS(数据录入!$H$5:$H$4999,数据录入!$C$5:$C$4999,$I37,数据录入!$E$5:$E$4999,"期初余额",数据录入!$B$5:$B$4999,"<="&DATE(YEAR($K$25),MONTH($K$25),1))+SUMIFS(数据录入!$F$5:$F$4999,数据录入!$C$5:$C$4999,$I37,数据录入!$B$5:$B$4999,"<"&DATE(YEAR($K$25),MONTH($K$25),1))-SUMIFS(数据录入!$G$5:$G$4999,数据录入!$C$5:$C$4999,$I37,数据录入!$B$5:$B$4999,"<"&DATE(YEAR($K$25),MONTH($K$25),1))) -> 0 | K37: =IF($I37="","",SUMIFS(数据录入!$F$5:$F$4999,数据录入!$C$5:$C$4999,$I37,数据录入!$B$5:$B$4999,">="&DATE(YEAR($K$25),MONTH($K$25),1),数据录入!$B$5:$B$4999,"<="&DATE(YEAR($K$25),MONTH($K$25)+1,0))) -> 0 | L37: =IF($I37="","",SUMIFS(数据录入!$G$5:$G$4999,数据录入!$C$5:$C$4999,$I37,数据录入!$B$5:$B$4999,">="&DATE(YEAR($K$25),MONTH($K$25),1),数据录入!$B$5:$B$4999,"<="&DATE(YEAR($K$25),MONTH($K$25)+1,0))) -> 2000 | M37: =IF($I37="","",J37+K37-L37) -> -2000 | P37: 46296
A38: 12 | B38: 备用6 | C38: =IF($B38="","",SUMIFS(数据录入!$H$5:$H$4999,数据录入!$C$5:$C$4999,$B38,数据录入!$E$5:$E$4999,"期初余额",数据录入!$B$5:$B$4999,"<="&$C$25)+SUMIFS(数据录入!$F$5:$F$4999,数据录入!$C$5:$C$4999,$B38,数据录入!$B$5:$B$4999,"<"&$C$25)-SUMIFS(数据录入!$G$5:$G$4999,数据录入!$C$5:$C$4999,$B38,数据录入!$B$5:$B$4999,"<"&$C$25)) -> -200 | D38: =IF($B38="","",SUMIFS(数据录入!$F$5:$F$4999,数据录入!$C$5:$C$4999,$B38,数据录入!$B$5:$B$4999,$C$25)) -> 0 | E38: =IF($B38="","",SUMIFS(数据录入!$G$5:$G$4999,数据录入!$C$5:$C$4999,$B38,数据录入!$B$5:$B$4999,$C$25)) -> 0 | F38: =IF($B38="","",C38+D38-E38) -> -200 | H38: 12 | I38: 备用6 | J38: =IF($I38="","",SUMIFS(数据录入!$H$5:$H$4999,数据录入!$C$5:$C$4999,$I38,数据录入!$E$5:$E$4999,"期初余额",数据录入!$B$5:$B$4999,"<="&DATE(YEAR($K$25),MONTH($K$25),1))+SUMIFS(数据录入!$F$5:$F$4999,数据录入!$C$5:$C$4999,$I38,数据录入!$B$5:$B$4999,"<"&DATE(YEAR($K$25),MONTH($K$25),1))-SUMIFS(数据录入!$G$5:$G$4999,数据录入!$C$5:$C$4999,$I38,数据录入!$B$5:$B$4999,"<"&DATE(YEAR($K$25),MONTH($K$25),1))) -> 0 | K38: =IF($I38="","",SUMIFS(数据录入!$F$5:$F$4999,数据录入!$C$5:$C$4999,$I38,数据录入!$B$5:$B$4999,">="&DATE(YEAR($K$25),MONTH($K$25),1),数据录入!$B$5:$B$4999,"<="&DATE(YEAR($K$25),MONTH($K$25)+1,0))) -> 0 | L38: =IF($I38="","",SUMIFS(数据录入!$G$5:$G$4999,数据录入!$C$5:$C$4999,$I38,数据录入!$B$5:$B$4999,">="&DATE(YEAR($K$25),MONTH($K$25),1),数据录入!$B$5:$B$4999,"<="&DATE(YEAR($K$25),MONTH($K$25)+1,0))) -> 200 | M38: =IF($I38="","",J38+K38-L38) -> -200 | P38: 46327
A39: 13 | B39: 备用7 | C39: =IF($B39="","",SUMIFS(数据录入!$H$5:$H$4999,数据录入!$C$5:$C$4999,$B39,数据录入!$E$5:$E$4999,"期初余额",数据录入!$B$5:$B$4999,"<="&$C$25)+SUMIFS(数据录入!$F$5:$F$4999,数据录入!$C$5:$C$4999,$B39,数据录入!$B$5:$B$4999,"<"&$C$25)-SUMIFS(数据录入!$G$5:$G$4999,数据录入!$C$5:$C$4999,$B39,数据录入!$B$5:$B$4999,"<"&$C$25)) -> -500 | D39: =IF($B39="","",SUMIFS(数据录入!$F$5:$F$4999,数据录入!$C$5:$C$4999,$B39,数据录入!$B$5:$B$4999,$C$25)) -> 0 | E39: =IF($B39="","",SUMIFS(数据录入!$G$5:$G$4999,数据录入!$C$5:$C$4999,$B39,数据录入!$B$5:$B$4999,$C$25)) -> 0 | F39: =IF($B39="","",C39+D39-E39) -> -500 | H39: 13 | I39: 备用7 | J39: =IF($I39="","",SUMIFS(数据录入!$H$5:$H$4999,数据录入!$C$5:$C$4999,$I39,数据录入!$E$5:$E$4999,"期初余额",数据录入!$B$5:$B$4999,"<="&DATE(YEAR($K$25),MONTH($K$25),1))+SUMIFS(数据录入!$F$5:$F$4999,数据录入!$C$5:$C$4999,$I39,数据录入!$B$5:$B$4999,"<"&DATE(YEAR($K$25),MONTH($K$25),1))-SUMIFS(数据录入!$G$5:$G$4999,数据录入!$C$5:$C$4999,$I39,数据录入!$B$5:$B$4999,"<"&DATE(YEAR($K$25),MONTH($K$25),1))) -> 0 | K39: =IF($I39="","",SUMIFS(数据录入!$F$5:$F$4999,数据录入!$C$5:$C$4999,$I39,数据录入!$B$5:$B$4999,">="&DATE(YEAR($K$25),MONTH($K$25),1),数据录入!$B$5:$B$4999,"<="&DATE(YEAR($K$25),MONTH($K$25)+1,0))) -> 0 | L39: =IF($I39="","",SUMIFS(数据录入!$G$5:$G$4999,数据录入!$C$5:$C$4999,$I39,数据录入!$B$5:$B$4999,">="&DATE(YEAR($K$25),MONTH($K$25),1),数据录入!$B$5:$B$4999,"<="&DATE(YEAR($K$25),MONTH($K$25)+1,0))) -> 500 | M39: =IF($I39="","",J39+K39-L39) -> -500 | P39: 46357
A40: 14 | B40: 备用8 | C40: =IF($B40="","",SUMIFS(数据录入!$H$5:$H$4999,数据录入!$C$5:$C$4999,$B40,数据录入!$E$5:$E$4999,"期初余额",数据录入!$B$5:$B$4999,"<="&$C$25)+SUMIFS(数据录入!$F$5:$F$4999,数据录入!$C$5:$C$4999,$B40,数据录入!$B$5:$B$4999,"<"&$C$25)-SUMIFS(数据录入!$G$5:$G$4999,数据录入!$C$5:$C$4999,$B40,数据录入!$B$5:$B$4999,"<"&$C$25)) -> -1000 | D40: =IF($B40="","",SUMIFS(数据录入!$F$5:$F$4999,数据录入!$C$5:$C$4999,$B40,数据录入!$B$5:$B$4999,$C$25)) -> 0 | E40: =IF($B40="","",SUMIFS(数据录入!$G$5:$G$4999,数据录入!$C$5:$C$4999,$B40,数据录入!$B$5:$B$4999,$C$25)) -> 0 | F40: =IF($B40="","",C40+D40-E40) -> -1000 | H40: 14 | I40: 备用8 | J40: =IF($I40="","",SUMIFS(数据录入!$H$5:$H$4999,数据录入!$C$5:$C$4999,$I40,数据录入!$E$5:$E$4999,"期初余额",数据录入!$B$5:$B$4999,"<="&DATE(YEAR($K$25),MONTH($K$25),1))+SUMIFS(数据录入!$F$5:$F$4999,数据录入!$C$5:$C$4999,$I40,数据录入!$B$5:$B$4999,"<"&DATE(YEAR($K$25),MONTH($K$25),1))-SUMIFS(数据录入!$G$5:$G$4999,数据录入!$C$5:$C$4999,$I40,数据录入!$B$5:$B$4999,"<"&DATE(YEAR($K$25),MONTH($K$25),1))) -> 0 | K40: =IF($I40="","",SUMIFS(数据录入!$F$5:$F$4999,数据录入!$C$5:$C$4999,$I40,数据录入!$B$5:$B$4999,">="&DATE(YEAR($K$25),MONTH($K$25),1),数据录入!$B$5:$B$4999,"<="&DATE(YEAR($K$25),MONTH($K$25)+1,0))) -> 0 | L40: =IF($I40="","",SUMIFS(数据录入!$G$5:$G$4999,数据录入!$C$5:$C$4999,$I40,数据录入!$B$5:$B$4999,">="&DATE(YEAR($K$25),MONTH($K$25),1),数据录入!$B$5:$B$4999,"<="&DATE(YEAR($K$25),MONTH($K$25)+1,0))) -> 1000 | M40: =IF($I40="","",J40+K40-L40) -> -1000
A41: 合计 | C41: =SUM(C27:C40) -> 10540 | D41: =SUM(D27:D40) -> 0 | E41: =SUM(E27:E40) -> 0 | F41: =SUM(F27:F40) -> 10540 | I41: 合计 | J41: =SUM(J27:J40) -> 0 | K41: =SUM(K27:K40) -> 22200 | L41: =SUM(L27:L40) -> 11660 | M41: =SUM(M27:M40) -> 10540

Sheet 任意时间段收支报表
B1: 任意时间段收支盈亏查询 | J1: 说明：修改黄色日期即可查询；支持单日或任意连续日期
B2: 开始日期 | C2: 46174 | D2: 收入总额 | E2: =IF(OR($C$2="",$C$3=""),"",SUMIFS([1]数据录入!$J$4:$J$9999,[1]数据录入!$B$4:$B$9999,">="&$C$2,[1]数据录入!$B$4:$B$9999,"<="&$C$3)) -> #VALUE! | F2: =SUM(C5:C39) -> 0 | G2: 盈亏 | H2: =IF(OR(F2="",F3=""),"",F2-F3) -> 0
B3: 结束日期 | C3: 46203 | D3: 支出总额 | E3: =IF(OR($C$2="",$C$3=""),"",SUMIFS([1]数据录入!$K$4:$K$9999,[1]数据录入!$B$4:$B$9999,">="&$C$2,[1]数据录入!$B$4:$B$9999,"<="&$C$3)) -> #VALUE! | F3: =SUM(G5:G39) -> 0
B4: 资金收入 | C4: 金额 | D4: 收入占比 | E4: 序号 | F4: 资金支出 | G4: 金额 | H4: 支出占比
B5: 丁爱妹 | C5: =IF($B5="","",SUMIFS(数据录入!$F$4:$F$9999,数据录入!$J$4:$J$9999,$B5,数据录入!$B$4:$B$9999,">="&$C$2,数据录入!$B$4:$B$9999,"<="&$C$3)) -> 0 | D5: =IF(OR($B5="",$F$2=0),"",C5/$F$2) | E5: 1 | F5: 供应商 | G5: =IF($F5="","",SUMIFS(数据录入!$G$4:$G$9999,数据录入!$D$4:$D$9999,$F5,数据录入!$B$4:$B$9999,">="&$C$2,数据录入!$B$4:$B$9999,"<="&$C$3)) -> 0 | H5: =IF(OR($F5="",$F$3=0),"",G5/$F$3)
B6: 方建宏 | C6: =IF($B6="","",SUMIFS(数据录入!$F$4:$F$9999,数据录入!$J$4:$J$9999,$B6,数据录入!$B$4:$B$9999,">="&$C$2,数据录入!$B$4:$B$9999,"<="&$C$3)) -> 0 | D6: =IF(OR($B6="",$F$2=0),"",C6/$F$2) | E6: 2 | G6: =IF($F6="","",SUMIFS(数据录入!$G$4:$G$9999,数据录入!$D$4:$D$9999,$F6,数据录入!$B$4:$B$9999,">="&$C$2,数据录入!$B$4:$B$9999,"<="&$C$3)) | H6: =IF(OR($F6="",$F$3=0),"",G6/$F$3)
B7: 傅荣姣 | C7: =IF($B7="","",SUMIFS(数据录入!$F$4:$F$9999,数据录入!$J$4:$J$9999,$B7,数据录入!$B$4:$B$9999,">="&$C$2,数据录入!$B$4:$B$9999,"<="&$C$3)) -> 0 | D7: =IF(OR($B7="",$F$2=0),"",C7/$F$2) | E7: 3 | F7: 办公费 | G7: =IF($F7="","",SUMIFS(数据录入!$G$4:$G$9999,数据录入!$D$4:$D$9999,$F7,数据录入!$B$4:$B$9999,">="&$C$2,数据录入!$B$4:$B$9999,"<="&$C$3)) -> 0 | H7: =IF(OR($F7="",$F$3=0),"",G7/$F$3)
B8: 郭志伟 | C8: =IF($B8="","",SUMIFS(数据录入!$F$4:$F$9999,数据录入!$J$4:$J$9999,$B8,数据录入!$B$4:$B$9999,">="&$C$2,数据录入!$B$4:$B$9999,"<="&$C$3)) -> 0 | D8: =IF(OR($B8="",$F$2=0),"",C8/$F$2) | E8: 4 | F8: 水费 | G8: =IF($F8="","",SUMIFS(数据录入!$G$4:$G$9999,数据录入!$D$4:$D$9999,$F8,数据录入!$B$4:$B$9999,">="&$C$2,数据录入!$B$4:$B$9999,"<="&$C$3)) -> 0 | H8: =IF(OR($F8="",$F$3=0),"",G8/$F$3)
B9: 过承祁 | C9: =IF($B9="","",SUMIFS(数据录入!$F$4:$F$9999,数据录入!$J$4:$J$9999,$B9,数据录入!$B$4:$B$9999,">="&$C$2,数据录入!$B$4:$B$9999,"<="&$C$3)) -> 0 | D9: =IF(OR($B9="",$F$2=0),"",C9/$F$2) | E9: 5 | F9: 电费 | G9: =IF($F9="","",SUMIFS(数据录入!$G$4:$G$9999,数据录入!$D$4:$D$9999,$F9,数据录入!$B$4:$B$9999,">="&$C$2,数据录入!$B$4:$B$9999,"<="&$C$3)) -> 0 | H9: =IF(OR($F9="",$F$3=0),"",G9/$F$3)
B10: 洪宗邦 | C10: =IF($B10="","",SUMIFS(数据录入!$F$4:$F$9999,数据录入!$J$4:$J$9999,$B10,数据录入!$B$4:$B$9999,">="&$C$2,数据录入!$B$4:$B$9999,"<="&$C$3)) -> 0 | D10: =IF(OR($B10="",$F$2=0),"",C10/$F$2) | E10: 6 | F10: 伙食费 | G10: =IF($F10="","",SUMIFS(数据录入!$G$4:$G$9999,数据录入!$D$4:$D$9999,$F10,数据录入!$B$4:$B$9999,">="&$C$2,数据录入!$B$4:$B$9999,"<="&$C$3)) -> 0 | H10: =IF(OR($F10="",$F$3=0),"",G10/$F$3)
B11: 姜蓉兰 | C11: =IF($B11="","",SUMIFS(数据录入!$F$4:$F$9999,数据录入!$J$4:$J$9999,$B11,数据录入!$B$4:$B$9999,">="&$C$2,数据录入!$B$4:$B$9999,"<="&$C$3)) -> 0 | D11: =IF(OR($B11="",$F$2=0),"",C11/$F$2) | E11: 7 | F11: 工资 | G11: =IF($F11="","",SUMIFS(数据录入!$G$4:$G$9999,数据录入!$D$4:$D$9999,$F11,数据录入!$B$4:$B$9999,">="&$C$2,数据录入!$B$4:$B$9999,"<="&$C$3)) -> 0 | H11: =IF(OR($F11="",$F$3=0),"",G11/$F$3)
B12: 姜志鸿 | C12: =IF($B12="","",SUMIFS(数据录入!$F$4:$F$9999,数据录入!$J$4:$J$9999,$B12,数据录入!$B$4:$B$9999,">="&$C$2,数据录入!$B$4:$B$9999,"<="&$C$3)) -> 0 | D12: =IF(OR($B12="",$F$2=0),"",C12/$F$2) | E12: 8 | F12: 租赁费 | G12: =IF($F12="","",SUMIFS(数据录入!$G$4:$G$9999,数据录入!$D$4:$D$9999,$F12,数据录入!$B$4:$B$9999,">="&$C$2,数据录入!$B$4:$B$9999,"<="&$C$3)) -> 0 | H12: =IF(OR($F12="",$F$3=0),"",G12/$F$3)
B13: 李小琴 | C13: =IF($B13="","",SUMIFS(数据录入!$F$4:$F$9999,数据录入!$J$4:$J$9999,$B13,数据录入!$B$4:$B$9999,">="&$C$2,数据录入!$B$4:$B$9999,"<="&$C$3)) -> 0 | D13: =IF(OR($B13="",$F$2=0),"",C13/$F$2) | E13: 9 | F13: 差旅费 | G13: =IF($F13="","",SUMIFS(数据录入!$G$4:$G$9999,数据录入!$D$4:$D$9999,$F13,数据录入!$B$4:$B$9999,">="&$C$2,数据录入!$B$4:$B$9999,"<="&$C$3)) -> 0 | H13: =IF(OR($F13="",$F$3=0),"",G13/$F$3)
B14: 李晓春 | C14: =IF($B14="","",SUMIFS(数据录入!$F$4:$F$9999,数据录入!$J$4:$J$9999,$B14,数据录入!$B$4:$B$9999,">="&$C$2,数据录入!$B$4:$B$9999,"<="&$C$3)) -> 0 | D14: =IF(OR($B14="",$F$2=0),"",C14/$F$2) | E14: 10 | F14: 业务招待费 | G14: =IF($F14="","",SUMIFS(数据录入!$G$4:$G$9999,数据录入!$D$4:$D$9999,$F14,数据录入!$B$4:$B$9999,">="&$C$2,数据录入!$B$4:$B$9999,"<="&$C$3)) -> 0 | H14: =IF(OR($F14="",$F$3=0),"",G14/$F$3)
B15: 李玉娟 | C15: =IF($B15="","",SUMIFS(数据录入!$F$4:$F$9999,数据录入!$J$4:$J$9999,$B15,数据录入!$B$4:$B$9999,">="&$C$2,数据录入!$B$4:$B$9999,"<="&$C$3)) -> 0 | D15: =IF(OR($B15="",$F$2=0),"",C15/$F$2) | E15: 11 | F15: 车辆费用 | G15: =IF($F15="","",SUMIFS(数据录入!$G$4:$G$9999,数据录入!$D$4:$D$9999,$F15,数据录入!$B$4:$B$9999,">="&$C$2,数据录入!$B$4:$B$9999,"<="&$C$3)) -> 0 | H15: =IF(OR($F15="",$F$3=0),"",G15/$F$3)
B16: 林永来 | C16: =IF($B16="","",SUMIFS(数据录入!$F$4:$F$9999,数据录入!$J$4:$J$9999,$B16,数据录入!$B$4:$B$9999,">="&$C$2,数据录入!$B$4:$B$9999,"<="&$C$3)) -> 0 | D16: =IF(OR($B16="",$F$2=0),"",C16/$F$2) | E16: 12 | F16: 银行手续费 | G16: =IF($F16="","",SUMIFS(数据录入!$G$4:$G$9999,数据录入!$D$4:$D$9999,$F16,数据录入!$B$4:$B$9999,">="&$C$2,数据录入!$B$4:$B$9999,"<="&$C$3)) -> 0 | H16: =IF(OR($F16="",$F$3=0),"",G16/$F$3)
B17: 陆玉英 | C17: =IF($B17="","",SUMIFS(数据录入!$F$4:$F$9999,数据录入!$J$4:$J$9999,$B17,数据录入!$B$4:$B$9999,">="&$C$2,数据录入!$B$4:$B$9999,"<="&$C$3)) -> 0 | D17: =IF(OR($B17="",$F$2=0),"",C17/$F$2) | E17: 13 | G17: =IF($F17="","",SUMIFS(数据录入!$G$4:$G$9999,数据录入!$D$4:$D$9999,$F17,数据录入!$B$4:$B$9999,">="&$C$2,数据录入!$B$4:$B$9999,"<="&$C$3)) | H17: =IF(OR($F17="",$F$3=0),"",G17/$F$3)
B18: 罗理华 | C18: =IF($B18="","",SUMIFS(数据录入!$F$4:$F$9999,数据录入!$J$4:$J$9999,$B18,数据录入!$B$4:$B$9999,">="&$C$2,数据录入!$B$4:$B$9999,"<="&$C$3)) -> 0 | D18: =IF(OR($B18="",$F$2=0),"",C18/$F$2) | G18: =IF($F18="","",SUMIFS(数据录入!$G$4:$G$9999,数据录入!$D$4:$D$9999,$F18,数据录入!$B$4:$B$9999,">="&$C$2,数据录入!$B$4:$B$9999,"<="&$C$3)) | H18: =IF(OR($F18="",$F$3=0),"",G18/$F$3)
B19: 马珍珠 | C19: =IF($B19="","",SUMIFS(数据录入!$F$4:$F$9999,数据录入!$J$4:$J$9999,$B19,数据录入!$B$4:$B$9999,">="&$C$2,数据录入!$B$4:$B$9999,"<="&$C$3)) -> 0 | D19: =IF(OR($B19="",$F$2=0),"",C19/$F$2) | G19: =IF($F19="","",SUMIFS(数据录入!$G$4:$G$9999,数据录入!$D$4:$D$9999,$F19,数据录入!$B$4:$B$9999,">="&$C$2,数据录入!$B$4:$B$9999,"<="&$C$3)) | H19: =IF(OR($F19="",$F$3=0),"",G19/$F$3)
B20: 邵国新 | C20: =IF($B20="","",SUMIFS(数据录入!$F$4:$F$9999,数据录入!$J$4:$J$9999,$B20,数据录入!$B$4:$B$9999,">="&$C$2,数据录入!$B$4:$B$9999,"<="&$C$3)) -> 0 | D20: =IF(OR($B20="",$F$2=0),"",C20/$F$2) | G20: =IF($F20="","",SUMIFS(数据录入!$G$4:$G$9999,数据录入!$D$4:$D$9999,$F20,数据录入!$B$4:$B$9999,">="&$C$2,数据录入!$B$4:$B$9999,"<="&$C$3)) | H20: =IF(OR($F20="",$F$3=0),"",G20/$F$3)
B21: 沈祖模 | C21: =IF($B21="","",SUMIFS(数据录入!$F$4:$F$9999,数据录入!$J$4:$J$9999,$B21,数据录入!$B$4:$B$9999,">="&$C$2,数据录入!$B$4:$B$9999,"<="&$C$3)) -> 0 | D21: =IF(OR($B21="",$F$2=0),"",C21/$F$2) | G21: =IF($F21="","",SUMIFS(数据录入!$G$4:$G$9999,数据录入!$D$4:$D$9999,$F21,数据录入!$B$4:$B$9999,">="&$C$2,数据录入!$B$4:$B$9999,"<="&$C$3)) | H21: =IF(OR($F21="",$F$3=0),"",G21/$F$3)
B22: 唐鑫红 | C22: =IF($B22="","",SUMIFS(数据录入!$F$4:$F$9999,数据录入!$J$4:$J$9999,$B22,数据录入!$B$4:$B$9999,">="&$C$2,数据录入!$B$4:$B$9999,"<="&$C$3)) -> 0 | D22: =IF(OR($B22="",$F$2=0),"",C22/$F$2) | G22: =IF($F22="","",SUMIFS(数据录入!$G$4:$G$9999,数据录入!$D$4:$D$9999,$F22,数据录入!$B$4:$B$9999,">="&$C$2,数据录入!$B$4:$B$9999,"<="&$C$3)) | H22: =IF(OR($F22="",$F$3=0),"",G22/$F$3)
B23: 童炳寿 | C23: =IF($B23="","",SUMIFS(数据录入!$F$4:$F$9999,数据录入!$J$4:$J$9999,$B23,数据录入!$B$4:$B$9999,">="&$C$2,数据录入!$B$4:$B$9999,"<="&$C$3)) -> 0 | D23: =IF(OR($B23="",$F$2=0),"",C23/$F$2) | G23: =IF($F23="","",SUMIFS(数据录入!$G$4:$G$9999,数据录入!$D$4:$D$9999,$F23,数据录入!$B$4:$B$9999,">="&$C$2,数据录入!$B$4:$B$9999,"<="&$C$3)) | H23: =IF(OR($F23="",$F$3=0),"",G23/$F$3)
B24: 王秀娟 | C24: =IF($B24="","",SUMIFS(数据录入!$F$4:$F$9999,数据录入!$J$4:$J$9999,$B24,数据录入!$B$4:$B$9999,">="&$C$2,数据录入!$B$4:$B$9999,"<="&$C$3)) -> 0 | D24: =IF(OR($B24="",$F$2=0),"",C24/$F$2) | G24: =IF($F24="","",SUMIFS(数据录入!$G$4:$G$9999,数据录入!$D$4:$D$9999,$F24,数据录入!$B$4:$B$9999,">="&$C$2,数据录入!$B$4:$B$9999,"<="&$C$3)) | H24: =IF(OR($F24="",$F$3=0),"",G24/$F$3)
B25: 邬香花 | C25: =IF($B25="","",SUMIFS(数据录入!$F$4:$F$9999,数据录入!$J$4:$J$9999,$B25,数据录入!$B$4:$B$9999,">="&$C$2,数据录入!$B$4:$B$9999,"<="&$C$3)) -> 0 | D25: =IF(OR($B25="",$F$2=0),"",C25/$F$2) | G25: =IF($F25="","",SUMIFS(数据录入!$G$4:$G$9999,数据录入!$D$4:$D$9999,$F25,数据录入!$B$4:$B$9999,">="&$C$2,数据录入!$B$4:$B$9999,"<="&$C$3)) | H25: =IF(OR($F25="",$F$3=0),"",G25/$F$3)
B26: 吴亮 | C26: =IF($B26="","",SUMIFS(数据录入!$F$4:$F$9999,数据录入!$J$4:$J$9999,$B26,数据录入!$B$4:$B$9999,">="&$C$2,数据录入!$B$4:$B$9999,"<="&$C$3)) -> 0 | D26: =IF(OR($B26="",$F$2=0),"",C26/$F$2) | G26: =IF($F26="","",SUMIFS(数据录入!$G$4:$G$9999,数据录入!$D$4:$D$9999,$F26,数据录入!$B$4:$B$9999,">="&$C$2,数据录入!$B$4:$B$9999,"<="&$C$3)) | H26: =IF(OR($F26="",$F$3=0),"",G26/$F$3)
B27: 吴旭红 | C27: =IF($B27="","",SUMIFS(数据录入!$F$4:$F$9999,数据录入!$J$4:$J$9999,$B27,数据录入!$B$4:$B$9999,">="&$C$2,数据录入!$B$4:$B$9999,"<="&$C$3)) -> 0 | D27: =IF(OR($B27="",$F$2=0),"",C27/$F$2) | G27: =IF($F27="","",SUMIFS(数据录入!$G$4:$G$9999,数据录入!$D$4:$D$9999,$F27,数据录入!$B$4:$B$9999,">="&$C$2,数据录入!$B$4:$B$9999,"<="&$C$3)) | H27: =IF(OR($F27="",$F$3=0),"",G27/$F$3)
B28: 吴兆香 | C28: =IF($B28="","",SUMIFS(数据录入!$F$4:$F$9999,数据录入!$J$4:$J$9999,$B28,数据录入!$B$4:$B$9999,">="&$C$2,数据录入!$B$4:$B$9999,"<="&$C$3)) -> 0 | D28: =IF(OR($B28="",$F$2=0),"",C28/$F$2) | G28: =IF($F28="","",SUMIFS(数据录入!$G$4:$G$9999,数据录入!$D$4:$D$9999,$F28,数据录入!$B$4:$B$9999,">="&$C$2,数据录入!$B$4:$B$9999,"<="&$C$3)) | H28: =IF(OR($F28="",$F$3=0),"",G28/$F$3)
B29: 谢爱琴 | C29: =IF($B29="","",SUMIFS(数据录入!$F$4:$F$9999,数据录入!$J$4:$J$9999,$B29,数据录入!$B$4:$B$9999,">="&$C$2,数据录入!$B$4:$B$9999,"<="&$C$3)) -> 0 | D29: =IF(OR($B29="",$F$2=0),"",C29/$F$2) | G29: =IF($F29="","",SUMIFS(数据录入!$G$4:$G$9999,数据录入!$D$4:$D$9999,$F29,数据录入!$B$4:$B$9999,">="&$C$2,数据录入!$B$4:$B$9999,"<="&$C$3)) | H29: =IF(OR($F29="",$F$3=0),"",G29/$F$3)
... B39: 郑玉英 | C39: =IF($B39="","",SUMIFS(数据录入!$F$4:$F$9999,数据录入!$J$4:$J$9999,$B39,数据录入!$B$4:$B$9999,">="&$C$2,数据录入!$B$4:$B$9999,"<="&$C$3)) -> 0 | D39: =IF(OR($B39="",$F$2=0),"",C39/$F$2) | G39: =IF($F39="","",SUMIFS(数据录入!$G$4:$G$9999,数据录入!$D$4:$D$9999,$F39,数据录入!$B$4:$B$9999,">="&$C$2,数据录入!$B$4:$B$9999,"<="&$C$3)) | H39: =IF(OR($F39="",$F$3=0),"",G39/$F$3)
B40: 祝晓琳
B41: 杨建云

Sheet 客户供应商汇总
A1: 收支报表
B3: 收支盈亏 | C3: =C4-C55 -> 0 | D3: =D4-D55 -> 0 | E3: =E4-E55 -> 0 | F3: =F4-F55 -> 0 | G3: =G4-G55 -> 0 | H3: =H4-H55 -> 0 | I3: =I4-I55 -> 0 | J3: =J4-J55 -> 0 | ... O3: =O4-O55 -> -3000
B4: 收入总额 | C4: =SUM(C6:C52) -> 0 | D4: =SUM(D6:D52) -> 0 | E4: =SUM(E6:E52) -> 0 | F4: =SUM(F6:F52) -> 0 | G4: =SUM(G6:G52) -> 0 | H4: =SUM(H6:H52) -> 0 | I4: =SUM(I6:I52) -> 0 | J4: =SUM(J6:J52) -> 0 | ... N4: =SUM(N6:N52) -> 0 | O4: =SUM(C4:N4) -> 2000
A5: 序 | B5: 客户 | C5: 202601 | D5: 202602 | E5: 202603 | F5: 202604 | G5: 202605 | H5: 202606 | I5: 202607 | J5: 202608 | K5: 202609 | L5: 202610 | M5: 202611 | N5: 202612 | O5: 合计 | P5: 总收入占比
A6: 1 | B6: 丁爱妹 | C6: =IF($B6="","",SUMIFS(数据录入!$F$5:$F$4999,数据录入!$J$5:$J$4999,$B6,数据录入!$M$5:$M$4999,C$5)) -> 0 | D6: =IF($B6="","",SUMIFS(数据录入!$F$5:$F$4999,数据录入!$J$5:$J$4999,$B6,数据录入!$M$5:$M$4999,D$5)) -> 0 | E6: =IF($B6="","",SUMIFS(数据录入!$F$5:$F$4999,数据录入!$J$5:$J$4999,$B6,数据录入!$M$5:$M$4999,E$5)) -> 0 | F6: =IF($B6="","",SUMIFS(数据录入!$F$5:$F$4999,数据录入!$J$5:$J$4999,$B6,数据录入!$M$5:$M$4999,F$5)) -> 0 | G6: =IF($B6="","",SUMIFS(数据录入!$F$5:$F$4999,数据录入!$J$5:$J$4999,$B6,数据录入!$M$5:$M$4999,G$5)) -> 0 | H6: =IF($B6="","",SUMIFS(数据录入!$F$5:$F$4999,数据录入!$J$5:$J$4999,$B6,数据录入!$M$5:$M$4999,H$5)) -> 0 | I6: =IF($B6="","",SUMIFS(数据录入!$F$5:$F$4999,数据录入!$J$5:$J$4999,$B6,数据录入!$M$5:$M$4999,I$5)) -> 0 | J6: =IF($B6="","",SUMIFS(数据录入!$F$5:$F$4999,数据录入!$J$5:$J$4999,$B6,数据录入!$M$5:$M$4999,J$5)) -> 0 | ... N6: =IF($B6="","",SUMIFS(数据录入!$F$5:$F$4999,数据录入!$J$5:$J$4999,$B6,数据录入!$M$5:$M$4999,N$5)) -> 0 | O6: =SUM(C6:N6) -> 2000 | P6: =IF($O$55=0,"",O6/$O$4) -> 1
A7: 2 | B7: 方建宏 | C7: =IF($B7="","",SUMIFS(数据录入!$F$5:$F$4999,数据录入!$J$5:$J$4999,$B7,数据录入!$M$5:$M$4999,C$5)) -> 0 | D7: =IF($B7="","",SUMIFS(数据录入!$F$5:$F$4999,数据录入!$J$5:$J$4999,$B7,数据录入!$M$5:$M$4999,D$5)) -> 0 | E7: =IF($B7="","",SUMIFS(数据录入!$F$5:$F$4999,数据录入!$J$5:$J$4999,$B7,数据录入!$M$5:$M$4999,E$5)) -> 0 | F7: =IF($B7="","",SUMIFS(数据录入!$F$5:$F$4999,数据录入!$J$5:$J$4999,$B7,数据录入!$M$5:$M$4999,F$5)) -> 0 | G7: =IF($B7="","",SUMIFS(数据录入!$F$5:$F$4999,数据录入!$J$5:$J$4999,$B7,数据录入!$M$5:$M$4999,G$5)) -> 0 | H7: =IF($B7="","",SUMIFS(数据录入!$F$5:$F$4999,数据录入!$J$5:$J$4999,$B7,数据录入!$M$5:$M$4999,H$5)) -> 0 | I7: =IF($B7="","",SUMIFS(数据录入!$F$5:$F$4999,数据录入!$J$5:$J$4999,$B7,数据录入!$M$5:$M$4999,I$5)) -> 0 | J7: =IF($B7="","",SUMIFS(数据录入!$F$5:$F$4999,数据录入!$J$5:$J$4999,$B7,数据录入!$M$5:$M$4999,J$5)) -> 0 | ... N7: =IF($B7="","",SUMIFS(数据录入!$F$5:$F$4999,数据录入!$J$5:$J$4999,$B7,数据录入!$M$5:$M$4999,N$5)) -> 0 | O7: =SUM(C7:N7) -> 0 | P7: =IF($O$55=0,"",O7/$O$4) -> 0
A8: 3 | B8: 傅荣姣 | C8: =IF($B8="","",SUMIFS(数据录入!$F$5:$F$4999,数据录入!$J$5:$J$4999,$B8,数据录入!$M$5:$M$4999,C$5)) -> 0 | D8: =IF($B8="","",SUMIFS(数据录入!$F$5:$F$4999,数据录入!$J$5:$J$4999,$B8,数据录入!$M$5:$M$4999,D$5)) -> 0 | E8: =IF($B8="","",SUMIFS(数据录入!$F$5:$F$4999,数据录入!$J$5:$J$4999,$B8,数据录入!$M$5:$M$4999,E$5)) -> 0 | F8: =IF($B8="","",SUMIFS(数据录入!$F$5:$F$4999,数据录入!$J$5:$J$4999,$B8,数据录入!$M$5:$M$4999,F$5)) -> 0 | G8: =IF($B8="","",SUMIFS(数据录入!$F$5:$F$4999,数据录入!$J$5:$J$4999,$B8,数据录入!$M$5:$M$4999,G$5)) -> 0 | H8: =IF($B8="","",SUMIFS(数据录入!$F$5:$F$4999,数据录入!$J$5:$J$4999,$B8,数据录入!$M$5:$M$4999,H$5)) -> 0 | I8: =IF($B8="","",SUMIFS(数据录入!$F$5:$F$4999,数据录入!$J$5:$J$4999,$B8,数据录入!$M$5:$M$4999,I$5)) -> 0 | J8: =IF($B8="","",SUMIFS(数据录入!$F$5:$F$4999,数据录入!$J$5:$J$4999,$B8,数据录入!$M$5:$M$4999,J$5)) -> 0 | ... N8: =IF($B8="","",SUMIFS(数据录入!$F$5:$F$4999,数据录入!$J$5:$J$4999,$B8,数据录入!$M$5:$M$4999,N$5)) -> 0 | O8: =SUM(C8:N8) -> 0 | P8: =IF($O$55=0,"",O8/$O$4) -> 0
A9: 4 | B9: 郭志伟 | C9: =IF($B9="","",SUMIFS(数据录入!$F$5:$F$4999,数据录入!$J$5:$J$4999,$B9,数据录入!$M$5:$M$4999,C$5)) -> 0 | D9: =IF($B9="","",SUMIFS(数据录入!$F$5:$F$4999,数据录入!$J$5:$J$4999,$B9,数据录入!$M$5:$M$4999,D$5)) -> 0 | E9: =IF($B9="","",SUMIFS(数据录入!$F$5:$F$4999,数据录入!$J$5:$J$4999,$B9,数据录入!$M$5:$M$4999,E$5)) -> 0 | F9: =IF($B9="","",SUMIFS(数据录入!$F$5:$F$4999,数据录入!$J$5:$J$4999,$B9,数据录入!$M$5:$M$4999,F$5)) -> 0 | G9: =IF($B9="","",SUMIFS(数据录入!$F$5:$F$4999,数据录入!$J$5:$J$4999,$B9,数据录入!$M$5:$M$4999,G$5)) -> 0 | H9: =IF($B9="","",SUMIFS(数据录入!$F$5:$F$4999,数据录入!$J$5:$J$4999,$B9,数据录入!$M$5:$M$4999,H$5)) -> 0 | I9: =IF($B9="","",SUMIFS(数据录入!$F$5:$F$4999,数据录入!$J$5:$J$4999,$B9,数据录入!$M$5:$M$4999,I$5)) -> 0 | J9: =IF($B9="","",SUMIFS(数据录入!$F$5:$F$4999,数据录入!$J$5:$J$4999,$B9,数据录入!$M$5:$M$4999,J$5)) -> 0 | ... N9: =IF($B9="","",SUMIFS(数据录入!$F$5:$F$4999,数据录入!$J$5:$J$4999,$B9,数据录入!$M$5:$M$4999,N$5)) -> 0 | O9: =SUM(C9:N9) -> 0 | P9: =IF($O$55=0,"",O9/$O$4) -> 0
A10: 5 | B10: 过承祁 | C10: =IF($B10="","",SUMIFS(数据录入!$F$5:$F$4999,数据录入!$J$5:$J$4999,$B10,数据录入!$M$5:$M$4999,C$5)) -> 0 | D10: =IF($B10="","",SUMIFS(数据录入!$F$5:$F$4999,数据录入!$J$5:$J$4999,$B10,数据录入!$M$5:$M$4999,D$5)) -> 0 | E10: =IF($B10="","",SUMIFS(数据录入!$F$5:$F$4999,数据录入!$J$5:$J$4999,$B10,数据录入!$M$5:$M$4999,E$5)) -> 0 | F10: =IF($B10="","",SUMIFS(数据录入!$F$5:$F$4999,数据录入!$J$5:$J$4999,$B10,数据录入!$M$5:$M$4999,F$5)) -> 0 | G10: =IF($B10="","",SUMIFS(数据录入!$F$5:$F$4999,数据录入!$J$5:$J$4999,$B10,数据录入!$M$5:$M$4999,G$5)) -> 0 | H10: =IF($B10="","",SUMIFS(数据录入!$F$5:$F$4999,数据录入!$J$5:$J$4999,$B10,数据录入!$M$5:$M$4999,H$5)) -> 0 | I10: =IF($B10="","",SUMIFS(数据录入!$F$5:$F$4999,数据录入!$J$5:$J$4999,$B10,数据录入!$M$5:$M$4999,I$5)) -> 0 | J10: =IF($B10="","",SUMIFS(数据录入!$F$5:$F$4999,数据录入!$J$5:$J$4999,$B10,数据录入!$M$5:$M$4999,J$5)) -> 0 | ... N10: =IF($B10="","",SUMIFS(数据录入!$F$5:$F$4999,数据录入!$J$5:$J$4999,$B10,数据录入!$M$5:$M$4999,N$5)) -> 0 | O10: =SUM(C10:N10) -> 0 | P10: =IF($O$55=0,"",O10/$O$4) -> 0
A11: 6 | B11: 洪宗邦 | C11: =IF($B11="","",SUMIFS(数据录入!$F$5:$F$4999,数据录入!$J$5:$J$4999,$B11,数据录入!$M$5:$M$4999,C$5)) -> 0 | D11: =IF($B11="","",SUMIFS(数据录入!$F$5:$F$4999,数据录入!$J$5:$J$4999,$B11,数据录入!$M$5:$M$4999,D$5)) -> 0 | E11: =IF($B11="","",SUMIFS(数据录入!$F$5:$F$4999,数据录入!$J$5:$J$4999,$B11,数据录入!$M$5:$M$4999,E$5)) -> 0 | F11: =IF($B11="","",SUMIFS(数据录入!$F$5:$F$4999,数据录入!$J$5:$J$4999,$B11,数据录入!$M$5:$M$4999,F$5)) -> 0 | G11: =IF($B11="","",SUMIFS(数据录入!$F$5:$F$4999,数据录入!$J$5:$J$4999,$B11,数据录入!$M$5:$M$4999,G$5)) -> 0 | H11: =IF($B11="","",SUMIFS(数据录入!$F$5:$F$4999,数据录入!$J$5:$J$4999,$B11,数据录入!$M$5:$M$4999,H$5)) -> 0 | I11: =IF($B11="","",SUMIFS(数据录入!$F$5:$F$4999,数据录入!$J$5:$J$4999,$B11,数据录入!$M$5:$M$4999,I$5)) -> 0 | J11: =IF($B11="","",SUMIFS(数据录入!$F$5:$F$4999,数据录入!$J$5:$J$4999,$B11,数据录入!$M$5:$M$4999,J$5)) -> 0 | ... N11: =IF($B11="","",SUMIFS(数据录入!$F$5:$F$4999,数据录入!$J$5:$J$4999,$B11,数据录入!$M$5:$M$4999,N$5)) -> 0 | O11: =SUM(C11:N11) -> 0 | P11: =IF($O$55=0,"",O11/$O$4) -> 0
A12: 7 | B12: 姜蓉兰 | C12: =IF($B12="","",SUMIFS(数据录入!$F$5:$F$4999,数据录入!$J$5:$J$4999,$B12,数据录入!$M$5:$M$4999,C$5)) -> 0 | D12: =IF($B12="","",SUMIFS(数据录入!$F$5:$F$4999,数据录入!$J$5:$J$4999,$B12,数据录入!$M$5:$M$4999,D$5)) -> 0 | E12: =IF($B12="","",SUMIFS(数据录入!$F$5:$F$4999,数据录入!$J$5:$J$4999,$B12,数据录入!$M$5:$M$4999,E$5)) -> 0 | F12: =IF($B12="","",SUMIFS(数据录入!$F$5:$F$4999,数据录入!$J$5:$J$4999,$B12,数据录入!$M$5:$M$4999,F$5)) -> 0 | G12: =IF($B12="","",SUMIFS(数据录入!$F$5:$F$4999,数据录入!$J$5:$J$4999,$B12,数据录入!$M$5:$M$4999,G$5)) -> 0 | H12: =IF($B12="","",SUMIFS(数据录入!$F$5:$F$4999,数据录入!$J$5:$J$4999,$B12,数据录入!$M$5:$M$4999,H$5)) -> 0 | I12: =IF($B12="","",SUMIFS(数据录入!$F$5:$F$4999,数据录入!$J$5:$J$4999,$B12,数据录入!$M$5:$M$4999,I$5)) -> 0 | J12: =IF($B12="","",SUMIFS(数据录入!$F$5:$F$4999,数据录入!$J$5:$J$4999,$B12,数据录入!$M$5:$M$4999,J$5)) -> 0 | ... N12: =IF($B12="","",SUMIFS(数据录入!$F$5:$F$4999,数据录入!$J$5:$J$4999,$B12,数据录入!$M$5:$M$4999,N$5)) -> 0 | O12: =SUM(C12:N12) -> 0 | P12: =IF($O$55=0,"",O12/$O$4) -> 0
A13: 8 | B13: 姜志鸿 | C13: =IF($B13="","",SUMIFS(数据录入!$F$5:$F$4999,数据录入!$J$5:$J$4999,$B13,数据录入!$M$5:$M$4999,C$5)) -> 0 | D13: =IF($B13="","",SUMIFS(数据录入!$F$5:$F$4999,数据录入!$J$5:$J$4999,$B13,数据录入!$M$5:$M$4999,D$5)) -> 0 | E13: =IF($B13="","",SUMIFS(数据录入!$F$5:$F$4999,数据录入!$J$5:$J$4999,$B13,数据录入!$M$5:$M$4999,E$5)) -> 0 | F13: =IF($B13="","",SUMIFS(数据录入!$F$5:$F$4999,数据录入!$J$5:$J$4999,$B13,数据录入!$M$5:$M$4999,F$5)) -> 0 | G13: =IF($B13="","",SUMIFS(数据录入!$F$5:$F$4999,数据录入!$J$5:$J$4999,$B13,数据录入!$M$5:$M$4999,G$5)) -> 0 | H13: =IF($B13="","",SUMIFS(数据录入!$F$5:$F$4999,数据录入!$J$5:$J$4999,$B13,数据录入!$M$5:$M$4999,H$5)) -> 0 | I13: =IF($B13="","",SUMIFS(数据录入!$F$5:$F$4999,数据录入!$J$5:$J$4999,$B13,数据录入!$M$5:$M$4999,I$5)) -> 0 | J13: =IF($B13="","",SUMIFS(数据录入!$F$5:$F$4999,数据录入!$J$5:$J$4999,$B13,数据录入!$M$5:$M$4999,J$5)) -> 0 | ... N13: =IF($B13="","",SUMIFS(数据录入!$F$5:$F$4999,数据录入!$J$5:$J$4999,$B13,数据录入!$M$5:$M$4999,N$5)) -> 0 | O13: =SUM(C13:N13) -> 0 | P13: =IF($O$55=0,"",O13/$O$4) -> 0
A14: 9 | B14: 李小琴 | C14: =IF($B14="","",SUMIFS(数据录入!$F$5:$F$4999,数据录入!$J$5:$J$4999,$B14,数据录入!$M$5:$M$4999,C$5)) -> 0 | D14: =IF($B14="","",SUMIFS(数据录入!$F$5:$F$4999,数据录入!$J$5:$J$4999,$B14,数据录入!$M$5:$M$4999,D$5)) -> 0 | E14: =IF($B14="","",SUMIFS(数据录入!$F$5:$F$4999,数据录入!$J$5:$J$4999,$B14,数据录入!$M$5:$M$4999,E$5)) -> 0 | F14: =IF($B14="","",SUMIFS(数据录入!$F$5:$F$4999,数据录入!$J$5:$J$4999,$B14,数据录入!$M$5:$M$4999,F$5)) -> 0 | G14: =IF($B14="","",SUMIFS(数据录入!$F$5:$F$4999,数据录入!$J$5:$J$4999,$B14,数据录入!$M$5:$M$4999,G$5)) -> 0 | H14: =IF($B14="","",SUMIFS(数据录入!$F$5:$F$4999,数据录入!$J$5:$J$4999,$B14,数据录入!$M$5:$M$4999,H$5)) -> 0 | I14: =IF($B14="","",SUMIFS(数据录入!$F$5:$F$4999,数据录入!$J$5:$J$4999,$B14,数据录入!$M$5:$M$4999,I$5)) -> 0 | J14: =IF($B14="","",SUMIFS(数据录入!$F$5:$F$4999,数据录入!$J$5:$J$4999,$B14,数据录入!$M$5:$M$4999,J$5)) -> 0 | ... N14: =IF($B14="","",SUMIFS(数据录入!$F$5:$F$4999,数据录入!$J$5:$J$4999,$B14,数据录入!$M$5:$M$4999,N$5)) -> 0 | O14: =SUM(C14:N14) -> 0 | P14: =IF($O$55=0,"",O14/$O$4) -> 0
A15: 10 | B15: 李晓春 | C15: =IF($B15="","",SUMIFS(数据录入!$F$5:$F$4999,数据录入!$J$5:$J$4999,$B15,数据录入!$M$5:$M$4999,C$5)) -> 0 | D15: =IF($B15="","",SUMIFS(数据录入!$F$5:$F$4999,数据录入!$J$5:$J$4999,$B15,数据录入!$M$5:$M$4999,D$5)) -> 0 | E15: =IF($B15="","",SUMIFS(数据录入!$F$5:$F$4999,数据录入!$J$5:$J$4999,$B15,数据录入!$M$5:$M$4999,E$5)) -> 0 | F15: =IF($B15="","",SUMIFS(数据录入!$F$5:$F$4999,数据录入!$J$5:$J$4999,$B15,数据录入!$M$5:$M$4999,F$5)) -> 0 | G15: =IF($B15="","",SUMIFS(数据录入!$F$5:$F$4999,数据录入!$J$5:$J$4999,$B15,数据录入!$M$5:$M$4999,G$5)) -> 0 | H15: =IF($B15="","",SUMIFS(数据录入!$F$5:$F$4999,数据录入!$J$5:$J$4999,$B15,数据录入!$M$5:$M$4999,H$5)) -> 0 | I15: =IF($B15="","",SUMIFS(数据录入!$F$5:$F$4999,数据录入!$J$5:$J$4999,$B15,数据录入!$M$5:$M$4999,I$5)) -> 0 | J15: =IF($B15="","",SUMIFS(数据录入!$F$5:$F$4999,数据录入!$J$5:$J$4999,$B15,数据录入!$M$5:$M$4999,J$5)) -> 0 | ... N15: =IF($B15="","",SUMIFS(数据录入!$F$5:$F$4999,数据录入!$J$5:$J$4999,$B15,数据录入!$M$5:$M$4999,N$5)) -> 0 | O15: =SUM(C15:N15) -> 0 | P15: =IF($O$55=0,"",O15/$O$4) -> 0
A16: 11 | B16: 李玉娟 | C16: =IF($B16="","",SUMIFS(数据录入!$F$5:$F$4999,数据录入!$J$5:$J$4999,$B16,数据录入!$M$5:$M$4999,C$5)) -> 0 | D16: =IF($B16="","",SUMIFS(数据录入!$F$5:$F$4999,数据录入!$J$5:$J$4999,$B16,数据录入!$M$5:$M$4999,D$5)) -> 0 | E16: =IF($B16="","",SUMIFS(数据录入!$F$5:$F$4999,数据录入!$J$5:$J$4999,$B16,数据录入!$M$5:$M$4999,E$5)) -> 0 | F16: =IF($B16="","",SUMIFS(数据录入!$F$5:$F$4999,数据录入!$J$5:$J$4999,$B16,数据录入!$M$5:$M$4999,F$5)) -> 0 | G16: =IF($B16="","",SUMIFS(数据录入!$F$5:$F$4999,数据录入!$J$5:$J$4999,$B16,数据录入!$M$5:$M$4999,G$5)) -> 0 | H16: =IF($B16="","",SUMIFS(数据录入!$F$5:$F$4999,数据录入!$J$5:$J$4999,$B16,数据录入!$M$5:$M$4999,H$5)) -> 0 | I16: =IF($B16="","",SUMIFS(数据录入!$F$5:$F$4999,数据录入!$J$5:$J$4999,$B16,数据录入!$M$5:$M$4999,I$5)) -> 0 | J16: =IF($B16="","",SUMIFS(数据录入!$F$5:$F$4999,数据录入!$J$5:$J$4999,$B16,数据录入!$M$5:$M$4999,J$5)) -> 0 | ... N16: =IF($B16="","",SUMIFS(数据录入!$F$5:$F$4999,数据录入!$J$5:$J$4999,$B16,数据录入!$M$5:$M$4999,N$5)) -> 0 | O16: =SUM(C16:N16) -> 0 | P16: =IF($O$55=0,"",O16/$O$4) -> 0
A17: 12 | B17: 林永来 | C17: =IF($B17="","",SUMIFS(数据录入!$F$5:$F$4999,数据录入!$J$5:$J$4999,$B17,数据录入!$M$5:$M$4999,C$5)) -> 0 | D17: =IF($B17="","",SUMIFS(数据录入!$F$5:$F$4999,数据录入!$J$5:$J$4999,$B17,数据录入!$M$5:$M$4999,D$5)) -> 0 | E17: =IF($B17="","",SUMIFS(数据录入!$F$5:$F$4999,数据录入!$J$5:$J$4999,$B17,数据录入!$M$5:$M$4999,E$5)) -> 0 | F17: =IF($B17="","",SUMIFS(数据录入!$F$5:$F$4999,数据录入!$J$5:$J$4999,$B17,数据录入!$M$5:$M$4999,F$5)) -> 0 | G17: =IF($B17="","",SUMIFS(数据录入!$F$5:$F$4999,数据录入!$J$5:$J$4999,$B17,数据录入!$M$5:$M$4999,G$5)) -> 0 | H17: =IF($B17="","",SUMIFS(数据录入!$F$5:$F$4999,数据录入!$J$5:$J$4999,$B17,数据录入!$M$5:$M$4999,H$5)) -> 0 | I17: =IF($B17="","",SUMIFS(数据录入!$F$5:$F$4999,数据录入!$J$5:$J$4999,$B17,数据录入!$M$5:$M$4999,I$5)) -> 0 | J17: =IF($B17="","",SUMIFS(数据录入!$F$5:$F$4999,数据录入!$J$5:$J$4999,$B17,数据录入!$M$5:$M$4999,J$5)) -> 0 | ... N17: =IF($B17="","",SUMIFS(数据录入!$F$5:$F$4999,数据录入!$J$5:$J$4999,$B17,数据录入!$M$5:$M$4999,N$5)) -> 0 | O17: =SUM(C17:N17) -> 0 | P17: =IF($O$55=0,"",O17/$O$4) -> 0
... A42: 37 | B42: 杨建云 | C42: =IF($B42="","",SUMIFS(数据录入!$F$5:$F$4999,数据录入!$J$5:$J$4999,$B42,数据录入!$M$5:$M$4999,C$5)) -> 0 | D42: =IF($B42="","",SUMIFS(数据录入!$F$5:$F$4999,数据录入!$J$5:$J$4999,$B42,数据录入!$M$5:$M$4999,D$5)) -> 0 | E42: =IF($B42="","",SUMIFS(数据录入!$F$5:$F$4999,数据录入!$J$5:$J$4999,$B42,数据录入!$M$5:$M$4999,E$5)) -> 0 | F42: =IF($B42="","",SUMIFS(数据录入!$F$5:$F$4999,数据录入!$J$5:$J$4999,$B42,数据录入!$M$5:$M$4999,F$5)) -> 0 | G42: =IF($B42="","",SUMIFS(数据录入!$F$5:$F$4999,数据录入!$J$5:$J$4999,$B42,数据录入!$M$5:$M$4999,G$5)) -> 0 | H42: =IF($B42="","",SUMIFS(数据录入!$F$5:$F$4999,数据录入!$J$5:$J$4999,$B42,数据录入!$M$5:$M$4999,H$5)) -> 0 | I42: =IF($B42="","",SUMIFS(数据录入!$F$5:$F$4999,数据录入!$J$5:$J$4999,$B42,数据录入!$M$5:$M$4999,I$5)) -> 0 | J42: =IF($B42="","",SUMIFS(数据录入!$F$5:$F$4999,数据录入!$J$5:$J$4999,$B42,数据录入!$M$5:$M$4999,J$5)) -> 0 | ... N42: =IF($B42="","",SUMIFS(数据录入!$F$5:$F$4999,数据录入!$J$5:$J$4999,$B42,数据录入!$M$5:$M$4999,N$5)) -> 0 | O42: =SUM(C42:N42) -> 0 | P42: =IF($O$55=0,"",O42/$O$4) -> 0
A43: 38 | C43: =IF($B43="","",SUMIFS(数据录入!$F$5:$F$4999,数据录入!$J$5:$J$4999,$B43,数据录入!$M$5:$M$4999,C$5)) | D43: =IF($B43="","",SUMIFS(数据录入!$F$5:$F$4999,数据录入!$J$5:$J$4999,$B43,数据录入!$M$5:$M$4999,D$5)) | E43: =IF($B43="","",SUMIFS(数据录入!$F$5:$F$4999,数据录入!$J$5:$J$4999,$B43,数据录入!$M$5:$M$4999,E$5)) | F43: =IF($B43="","",SUMIFS(数据录入!$F$5:$F$4999,数据录入!$J$5:$J$4999,$B43,数据录入!$M$5:$M$4999,F$5)) | G43: =IF($B43="","",SUMIFS(数据录入!$F$5:$F$4999,数据录入!$J$5:$J$4999,$B43,数据录入!$M$5:$M$4999,G$5)) | H43: =IF($B43="","",SUMIFS(数据录入!$F$5:$F$4999,数据录入!$J$5:$J$4999,$B43,数据录入!$M$5:$M$4999,H$5)) | I43: =IF($B43="","",SUMIFS(数据录入!$F$5:$F$4999,数据录入!$J$5:$J$4999,$B43,数据录入!$M$5:$M$4999,I$5)) | J43: =IF($B43="","",SUMIFS(数据录入!$F$5:$F$4999,数据录入!$J$5:$J$4999,$B43,数据录入!$M$5:$M$4999,J$5)) | ... N43: =IF($B43="","",SUMIFS(数据录入!$F$5:$F$4999,数据录入!$J$5:$J$4999,$B43,数据录入!$M$5:$M$4999,N$5)) | O43: =SUM(C43:N43) -> 0 | P43: =IF($O$55=0,"",O43/$O$4) -> 0
A44: 39 | C44: =IF($B44="","",SUMIFS(数据录入!$F$5:$F$4999,数据录入!$J$5:$J$4999,$B44,数据录入!$M$5:$M$4999,C$5)) | D44: =IF($B44="","",SUMIFS(数据录入!$F$5:$F$4999,数据录入!$J$5:$J$4999,$B44,数据录入!$M$5:$M$4999,D$5)) | E44: =IF($B44="","",SUMIFS(数据录入!$F$5:$F$4999,数据录入!$J$5:$J$4999,$B44,数据录入!$M$5:$M$4999,E$5)) | F44: =IF($B44="","",SUMIFS(数据录入!$F$5:$F$4999,数据录入!$J$5:$J$4999,$B44,数据录入!$M$5:$M$4999,F$5)) | G44: =IF($B44="","",SUMIFS(数据录入!$F$5:$F$4999,数据录入!$J$5:$J$4999,$B44,数据录入!$M$5:$M$4999,G$5)) | H44: =IF($B44="","",SUMIFS(数据录入!$F$5:$F$4999,数据录入!$J$5:$J$4999,$B44,数据录入!$M$5:$M$4999,H$5)) | I44: =IF($B44="","",SUMIFS(数据录入!$F$5:$F$4999,数据录入!$J$5:$J$4999,$B44,数据录入!$M$5:$M$4999,I$5)) | J44: =IF($B44="","",SUMIFS(数据录入!$F$5:$F$4999,数据录入!$J$5:$J$4999,$B44,数据录入!$M$5:$M$4999,J$5)) | ... N44: =IF($B44="","",SUMIFS(数据录入!$F$5:$F$4999,数据录入!$J$5:$J$4999,$B44,数据录入!$M$5:$M$4999,N$5)) | O44: =SUM(C44:N44) -> 0 | P44: =IF($O$55=0,"",O44/$O$4) -> 0
A45: 40 | C45: =IF($B45="","",SUMIFS(数据录入!$F$5:$F$4999,数据录入!$J$5:$J$4999,$B45,数据录入!$M$5:$M$4999,C$5)) | D45: =IF($B45="","",SUMIFS(数据录入!$F$5:$F$4999,数据录入!$J$5:$J$4999,$B45,数据录入!$M$5:$M$4999,D$5)) | E45: =IF($B45="","",SUMIFS(数据录入!$F$5:$F$4999,数据录入!$J$5:$J$4999,$B45,数据录入!$M$5:$M$4999,E$5)) | F45: =IF($B45="","",SUMIFS(数据录入!$F$5:$F$4999,数据录入!$J$5:$J$4999,$B45,数据录入!$M$5:$M$4999,F$5)) | G45: =IF($B45="","",SUMIFS(数据录入!$F$5:$F$4999,数据录入!$J$5:$J$4999,$B45,数据录入!$M$5:$M$4999,G$5)) | H45: =IF($B45="","",SUMIFS(数据录入!$F$5:$F$4999,数据录入!$J$5:$J$4999,$B45,数据录入!$M$5:$M$4999,H$5)) | I45: =IF($B45="","",SUMIFS(数据录入!$F$5:$F$4999,数据录入!$J$5:$J$4999,$B45,数据录入!$M$5:$M$4999,I$5)) | J45: =IF($B45="","",SUMIFS(数据录入!$F$5:$F$4999,数据录入!$J$5:$J$4999,$B45,数据录入!$M$5:$M$4999,J$5)) | ... N45: =IF($B45="","",SUMIFS(数据录入!$F$5:$F$4999,数据录入!$J$5:$J$4999,$B45,数据录入!$M$5:$M$4999,N$5)) | O45: =SUM(C45:N45) -> 0 | P45: =IF($O$55=0,"",O45/$O$4) -> 0
A46: 41 | C46: =IF($B46="","",SUMIFS(数据录入!$F$5:$F$4999,数据录入!$J$5:$J$4999,$B46,数据录入!$M$5:$M$4999,C$5)) | D46: =IF($B46="","",SUMIFS(数据录入!$F$5:$F$4999,数据录入!$J$5:$J$4999,$B46,数据录入!$M$5:$M$4999,D$5)) | E46: =IF($B46="","",SUMIFS(数据录入!$F$5:$F$4999,数据录入!$J$5:$J$4999,$B46,数据录入!$M$5:$M$4999,E$5)) | F46: =IF($B46="","",SUMIFS(数据录入!$F$5:$F$4999,数据录入!$J$5:$J$4999,$B46,数据录入!$M$5:$M$4999,F$5)) | G46: =IF($B46="","",SUMIFS(数据录入!$F$5:$F$4999,数据录入!$J$5:$J$4999,$B46,数据录入!$M$5:$M$4999,G$5)) | H46: =IF($B46="","",SUMIFS(数据录入!$F$5:$F$4999,数据录入!$J$5:$J$4999,$B46,数据录入!$M$5:$M$4999,H$5)) | I46: =IF($B46="","",SUMIFS(数据录入!$F$5:$F$4999,数据录入!$J$5:$J$4999,$B46,数据录入!$M$5:$M$4999,I$5)) | J46: =IF($B46="","",SUMIFS(数据录入!$F$5:$F$4999,数据录入!$J$5:$J$4999,$B46,数据录入!$M$5:$M$4999,J$5)) | ... N46: =IF($B46="","",SUMIFS(数据录入!$F$5:$F$4999,数据录入!$J$5:$J$4999,$B46,数据录入!$M$5:$M$4999,N$5)) | O46: =SUM(C46:N46) -> 0 | P46: =IF($O$55=0,"",O46/$O$4) -> 0
A47: 42 | C47: =IF($B47="","",SUMIFS(数据录入!$F$5:$F$4999,数据录入!$J$5:$J$4999,$B47,数据录入!$M$5:$M$4999,C$5)) | D47: =IF($B47="","",SUMIFS(数据录入!$F$5:$F$4999,数据录入!$J$5:$J$4999,$B47,数据录入!$M$5:$M$4999,D$5)) | E47: =IF($B47="","",SUMIFS(数据录入!$F$5:$F$4999,数据录入!$J$5:$J$4999,$B47,数据录入!$M$5:$M$4999,E$5)) | F47: =IF($B47="","",SUMIFS(数据录入!$F$5:$F$4999,数据录入!$J$5:$J$4999,$B47,数据录入!$M$5:$M$4999,F$5)) | G47: =IF($B47="","",SUMIFS(数据录入!$F$5:$F$4999,数据录入!$J$5:$J$4999,$B47,数据录入!$M$5:$M$4999,G$5)) | H47: =IF($B47="","",SUMIFS(数据录入!$F$5:$F$4999,数据录入!$J$5:$J$4999,$B47,数据录入!$M$5:$M$4999,H$5)) | I47: =IF($B47="","",SUMIFS(数据录入!$F$5:$F$4999,数据录入!$J$5:$J$4999,$B47,数据录入!$M$5:$M$4999,I$5)) | J47: =IF($B47="","",SUMIFS(数据录入!$F$5:$F$4999,数据录入!$J$5:$J$4999,$B47,数据录入!$M$5:$M$4999,J$5)) | ... N47: =IF($B47="","",SUMIFS(数据录入!$F$5:$F$4999,数据录入!$J$5:$J$4999,$B47,数据录入!$M$5:$M$4999,N$5)) | O47: =SUM(C47:N47) -> 0 | P47: =IF($O$55=0,"",O47/$O$4) -> 0
A48: 43 | C48: =IF($B48="","",SUMIFS(数据录入!$F$5:$F$4999,数据录入!$J$5:$J$4999,$B48,数据录入!$M$5:$M$4999,C$5)) | D48: =IF($B48="","",SUMIFS(数据录入!$F$5:$F$4999,数据录入!$J$5:$J$4999,$B48,数据录入!$M$5:$M$4999,D$5)) | E48: =IF($B48="","",SUMIFS(数据录入!$F$5:$F$4999,数据录入!$J$5:$J$4999,$B48,数据录入!$M$5:$M$4999,E$5)) | F48: =IF($B48="","",SUMIFS(数据录入!$F$5:$F$4999,数据录入!$J$5:$J$4999,$B48,数据录入!$M$5:$M$4999,F$5)) | G48: =IF($B48="","",SUMIFS(数据录入!$F$5:$F$4999,数据录入!$J$5:$J$4999,$B48,数据录入!$M$5:$M$4999,G$5)) | H48: =IF($B48="","",SUMIFS(数据录入!$F$5:$F$4999,数据录入!$J$5:$J$4999,$B48,数据录入!$M$5:$M$4999,H$5)) | I48: =IF($B48="","",SUMIFS(数据录入!$F$5:$F$4999,数据录入!$J$5:$J$4999,$B48,数据录入!$M$5:$M$4999,I$5)) | J48: =IF($B48="","",SUMIFS(数据录入!$F$5:$F$4999,数据录入!$J$5:$J$4999,$B48,数据录入!$M$5:$M$4999,J$5)) | ... N48: =IF($B48="","",SUMIFS(数据录入!$F$5:$F$4999,数据录入!$J$5:$J$4999,$B48,数据录入!$M$5:$M$4999,N$5)) | O48: =SUM(C48:N48) -> 0 | P48: =IF($O$55=0,"",O48/$O$4) -> 0
A49: 44 | C49: =IF($B49="","",SUMIFS(数据录入!$F$5:$F$4999,数据录入!$J$5:$J$4999,$B49,数据录入!$M$5:$M$4999,C$5)) | D49: =IF($B49="","",SUMIFS(数据录入!$F$5:$F$4999,数据录入!$J$5:$J$4999,$B49,数据录入!$M$5:$M$4999,D$5)) | E49: =IF($B49="","",SUMIFS(数据录入!$F$5:$F$4999,数据录入!$J$5:$J$4999,$B49,数据录入!$M$5:$M$4999,E$5)) | F49: =IF($B49="","",SUMIFS(数据录入!$F$5:$F$4999,数据录入!$J$5:$J$4999,$B49,数据录入!$M$5:$M$4999,F$5)) | G49: =IF($B49="","",SUMIFS(数据录入!$F$5:$F$4999,数据录入!$J$5:$J$4999,$B49,数据录入!$M$5:$M$4999,G$5)) | H49: =IF($B49="","",SUMIFS(数据录入!$F$5:$F$4999,数据录入!$J$5:$J$4999,$B49,数据录入!$M$5:$M$4999,H$5)) | I49: =IF($B49="","",SUMIFS(数据录入!$F$5:$F$4999,数据录入!$J$5:$J$4999,$B49,数据录入!$M$5:$M$4999,I$5)) | J49: =IF($B49="","",SUMIFS(数据录入!$F$5:$F$4999,数据录入!$J$5:$J$4999,$B49,数据录入!$M$5:$M$4999,J$5)) | ... N49: =IF($B49="","",SUMIFS(数据录入!$F$5:$F$4999,数据录入!$J$5:$J$4999,$B49,数据录入!$M$5:$M$4999,N$5)) | O49: =SUM(C49:N49) -> 0 | P49: =IF($O$55=0,"",O49/$O$4) -> 0
A50: 45 | C50: =IF($B50="","",SUMIFS(数据录入!$F$5:$F$4999,数据录入!$J$5:$J$4999,$B50,数据录入!$M$5:$M$4999,C$5)) | D50: =IF($B50="","",SUMIFS(数据录入!$F$5:$F$4999,数据录入!$J$5:$J$4999,$B50,数据录入!$M$5:$M$4999,D$5)) | E50: =IF($B50="","",SUMIFS(数据录入!$F$5:$F$4999,数据录入!$J$5:$J$4999,$B50,数据录入!$M$5:$M$4999,E$5)) | F50: =IF($B50="","",SUMIFS(数据录入!$F$5:$F$4999,数据录入!$J$5:$J$4999,$B50,数据录入!$M$5:$M$4999,F$5)) | G50: =IF($B50="","",SUMIFS(数据录入!$F$5:$F$4999,数据录入!$J$5:$J$4999,$B50,数据录入!$M$5:$M$4999,G$5)) | H50: =IF($B50="","",SUMIFS(数据录入!$F$5:$F$4999,数据录入!$J$5:$J$4999,$B50,数据录入!$M$5:$M$4999,H$5)) | I50: =IF($B50="","",SUMIFS(数据录入!$F$5:$F$4999,数据录入!$J$5:$J$4999,$B50,数据录入!$M$5:$M$4999,I$5)) | J50: =IF($B50="","",SUMIFS(数据录入!$F$5:$F$4999,数据录入!$J$5:$J$4999,$B50,数据录入!$M$5:$M$4999,J$5)) | ... N50: =IF($B50="","",SUMIFS(数据录入!$F$5:$F$4999,数据录入!$J$5:$J$4999,$B50,数据录入!$M$5:$M$4999,N$5)) | O50: =SUM(C50:N50) -> 0 | P50: =IF($O$55=0,"",O50/$O$4) -> 0
A51: 46 | C51: =IF($B51="","",SUMIFS(数据录入!$F$5:$F$4999,数据录入!$J$5:$J$4999,$B51,数据录入!$M$5:$M$4999,C$5)) | D51: =IF($B51="","",SUMIFS(数据录入!$F$5:$F$4999,数据录入!$J$5:$J$4999,$B51,数据录入!$M$5:$M$4999,D$5)) | E51: =IF($B51="","",SUMIFS(数据录入!$F$5:$F$4999,数据录入!$J$5:$J$4999,$B51,数据录入!$M$5:$M$4999,E$5)) | F51: =IF($B51="","",SUMIFS(数据录入!$F$5:$F$4999,数据录入!$J$5:$J$4999,$B51,数据录入!$M$5:$M$4999,F$5)) | G51: =IF($B51="","",SUMIFS(数据录入!$F$5:$F$4999,数据录入!$J$5:$J$4999,$B51,数据录入!$M$5:$M$4999,G$5)) | H51: =IF($B51="","",SUMIFS(数据录入!$F$5:$F$4999,数据录入!$J$5:$J$4999,$B51,数据录入!$M$5:$M$4999,H$5)) | I51: =IF($B51="","",SUMIFS(数据录入!$F$5:$F$4999,数据录入!$J$5:$J$4999,$B51,数据录入!$M$5:$M$4999,I$5)) | J51: =IF($B51="","",SUMIFS(数据录入!$F$5:$F$4999,数据录入!$J$5:$J$4999,$B51,数据录入!$M$5:$M$4999,J$5)) | ... N51: =IF($B51="","",SUMIFS(数据录入!$F$5:$F$4999,数据录入!$J$5:$J$4999,$B51,数据录入!$M$5:$M$4999,N$5)) | O51: =SUM(C51:N51) -> 0 | P51: =IF($O$55=0,"",O51/$O$4) -> 0
A52: 47 | C52: =IF($B52="","",SUMIFS(数据录入!$F$5:$F$4999,数据录入!$J$5:$J$4999,$B52,数据录入!$M$5:$M$4999,C$5)) | D52: =IF($B52="","",SUMIFS(数据录入!$F$5:$F$4999,数据录入!$J$5:$J$4999,$B52,数据录入!$M$5:$M$4999,D$5)) | E52: =IF($B52="","",SUMIFS(数据录入!$F$5:$F$4999,数据录入!$J$5:$J$4999,$B52,数据录入!$M$5:$M$4999,E$5)) | F52: =IF($B52="","",SUMIFS(数据录入!$F$5:$F$4999,数据录入!$J$5:$J$4999,$B52,数据录入!$M$5:$M$4999,F$5)) | G52: =IF($B52="","",SUMIFS(数据录入!$F$5:$F$4999,数据录入!$J$5:$J$4999,$B52,数据录入!$M$5:$M$4999,G$5)) | H52: =IF($B52="","",SUMIFS(数据录入!$F$5:$F$4999,数据录入!$J$5:$J$4999,$B52,数据录入!$M$5:$M$4999,H$5)) | I52: =IF($B52="","",SUMIFS(数据录入!$F$5:$F$4999,数据录入!$J$5:$J$4999,$B52,数据录入!$M$5:$M$4999,I$5)) | J52: =IF($B52="","",SUMIFS(数据录入!$F$5:$F$4999,数据录入!$J$5:$J$4999,$B52,数据录入!$M$5:$M$4999,J$5)) | ... N52: =IF($B52="","",SUMIFS(数据录入!$F$5:$F$4999,数据录入!$J$5:$J$4999,$B52,数据录入!$M$5:$M$4999,N$5)) | O52: =SUM(C52:N52) -> 0 | P52: =IF($O$55=0,"",O52/$O$4) -> 0
B55: 支出总额 | C55: =SUM(C57:C66) -> 0 | D55: =SUM(D57:D66) -> 0 | E55: =SUM(E57:E66) -> 0 | F55: =SUM(F57:F66) -> 0 | G55: =SUM(G57:G66) -> 0 | H55: =SUM(H57:H66) -> 0 | I55: =SUM(I57:I66) -> 0 | J55: =SUM(J57:J66) -> 0 | ... N55: =SUM(N57:N66) -> 0 | O55: =SUM(C55:N55) -> 5000 | P55: =IF($O$55=0,"",1) -> 1
A56: 序 | B56: 供应商 | C56: 202601 | D56: 202602 | E56: 202603 | F56: 202604 | G56: 202605 | H56: 202606 | I56: 202607 | J56: 202608 | K56: 202609 | L56: 202610 | M56: 202611 | N56: 202612 | O56: 合计 | P56: 总支出占比
A57: 1 | B57: 羊奶供货商 | C57: =IF($B57="","",SUMIFS(数据录入!$G$5:$G$4999,数据录入!$K$5:$K$4999,$B57,数据录入!$M$5:$M$4999,C$56)) -> 0 | D57: =IF($B57="","",SUMIFS(数据录入!$G$5:$G$4999,数据录入!$K$5:$K$4999,$B57,数据录入!$M$5:$M$4999,D$56)) -> 0 | E57: =IF($B57="","",SUMIFS(数据录入!$G$5:$G$4999,数据录入!$K$5:$K$4999,$B57,数据录入!$M$5:$M$4999,E$56)) -> 0 | F57: =IF($B57="","",SUMIFS(数据录入!$G$5:$G$4999,数据录入!$K$5:$K$4999,$B57,数据录入!$M$5:$M$4999,F$56)) -> 0 | G57: =IF($B57="","",SUMIFS(数据录入!$G$5:$G$4999,数据录入!$K$5:$K$4999,$B57,数据录入!$M$5:$M$4999,G$56)) -> 0 | H57: =IF($B57="","",SUMIFS(数据录入!$G$5:$G$4999,数据录入!$K$5:$K$4999,$B57,数据录入!$M$5:$M$4999,H$56)) -> 0 | I57: =IF($B57="","",SUMIFS(数据录入!$G$5:$G$4999,数据录入!$K$5:$K$4999,$B57,数据录入!$M$5:$M$4999,I$56)) -> 0 | J57: =IF($B57="","",SUMIFS(数据录入!$G$5:$G$4999,数据录入!$K$5:$K$4999,$B57,数据录入!$M$5:$M$4999,J$56)) -> 0 | ... N57: =IF($B57="","",SUMIFS(数据录入!$G$5:$G$4999,数据录入!$K$5:$K$4999,$B57,数据录入!$M$5:$M$4999,N$56)) -> 0 | O57: =SUM(C57:N57) -> 5000 | P57: =IF($O$55=0,"",O57/$O$55) -> 1
A58: 2 | B58: 乳铁供货商 | C58: =IF($B58="","",SUMIFS(数据录入!$G$5:$G$4999,数据录入!$K$5:$K$4999,$B58,数据录入!$M$5:$M$4999,C$56)) -> 0 | D58: =IF($B58="","",SUMIFS(数据录入!$G$5:$G$4999,数据录入!$K$5:$K$4999,$B58,数据录入!$M$5:$M$4999,D$56)) -> 0 | E58: =IF($B58="","",SUMIFS(数据录入!$G$5:$G$4999,数据录入!$K$5:$K$4999,$B58,数据录入!$M$5:$M$4999,E$56)) -> 0 | F58: =IF($B58="","",SUMIFS(数据录入!$G$5:$G$4999,数据录入!$K$5:$K$4999,$B58,数据录入!$M$5:$M$4999,F$56)) -> 0 | G58: =IF($B58="","",SUMIFS(数据录入!$G$5:$G$4999,数据录入!$K$5:$K$4999,$B58,数据录入!$M$5:$M$4999,G$56)) -> 0 | H58: =IF($B58="","",SUMIFS(数据录入!$G$5:$G$4999,数据录入!$K$5:$K$4999,$B58,数据录入!$M$5:$M$4999,H$56)) -> 0 | I58: =IF($B58="","",SUMIFS(数据录入!$G$5:$G$4999,数据录入!$K$5:$K$4999,$B58,数据录入!$M$5:$M$4999,I$56)) -> 0 | J58: =IF($B58="","",SUMIFS(数据录入!$G$5:$G$4999,数据录入!$K$5:$K$4999,$B58,数据录入!$M$5:$M$4999,J$56)) -> 0 | ... N58: =IF($B58="","",SUMIFS(数据录入!$G$5:$G$4999,数据录入!$K$5:$K$4999,$B58,数据录入!$M$5:$M$4999,N$56)) -> 0 | O58: =SUM(C58:N58) -> 0 | P58: =IF($O$55=0,"",O58/$O$55) -> 0
A59: 3 | C59: =IF($B59="","",SUMIFS(数据录入!$G$5:$G$4999,数据录入!$K$5:$K$4999,$B59,数据录入!$M$5:$M$4999,C$56)) | D59: =IF($B59="","",SUMIFS(数据录入!$G$5:$G$4999,数据录入!$K$5:$K$4999,$B59,数据录入!$M$5:$M$4999,D$56)) | E59: =IF($B59="","",SUMIFS(数据录入!$G$5:$G$4999,数据录入!$K$5:$K$4999,$B59,数据录入!$M$5:$M$4999,E$56)) | F59: =IF($B59="","",SUMIFS(数据录入!$G$5:$G$4999,数据录入!$K$5:$K$4999,$B59,数据录入!$M$5:$M$4999,F$56)) | G59: =IF($B59="","",SUMIFS(数据录入!$G$5:$G$4999,数据录入!$K$5:$K$4999,$B59,数据录入!$M$5:$M$4999,G$56)) | H59: =IF($B59="","",SUMIFS(数据录入!$G$5:$G$4999,数据录入!$K$5:$K$4999,$B59,数据录入!$M$5:$M$4999,H$56)) | I59: =IF($B59="","",SUMIFS(数据录入!$G$5:$G$4999,数据录入!$K$5:$K$4999,$B59,数据录入!$M$5:$M$4999,I$56)) | J59: =IF($B59="","",SUMIFS(数据录入!$G$5:$G$4999,数据录入!$K$5:$K$4999,$B59,数据录入!$M$5:$M$4999,J$56)) | ... N59: =IF($B59="","",SUMIFS(数据录入!$G$5:$G$4999,数据录入!$K$5:$K$4999,$B59,数据录入!$M$5:$M$4999,N$56)) | O59: =SUM(C59:N59) -> 0 | P59: =IF($O$55=0,"",O59/$O$55) -> 0
A60: 4 | C60: =IF($B60="","",SUMIFS(数据录入!$G$5:$G$4999,数据录入!$K$5:$K$4999,$B60,数据录入!$M$5:$M$4999,C$56)) | D60: =IF($B60="","",SUMIFS(数据录入!$G$5:$G$4999,数据录入!$K$5:$K$4999,$B60,数据录入!$M$5:$M$4999,D$56)) | E60: =IF($B60="","",SUMIFS(数据录入!$G$5:$G$4999,数据录入!$K$5:$K$4999,$B60,数据录入!$M$5:$M$4999,E$56)) | F60: =IF($B60="","",SUMIFS(数据录入!$G$5:$G$4999,数据录入!$K$5:$K$4999,$B60,数据录入!$M$5:$M$4999,F$56)) | G60: =IF($B60="","",SUMIFS(数据录入!$G$5:$G$4999,数据录入!$K$5:$K$4999,$B60,数据录入!$M$5:$M$4999,G$56)) | H60: =IF($B60="","",SUMIFS(数据录入!$G$5:$G$4999,数据录入!$K$5:$K$4999,$B60,数据录入!$M$5:$M$4999,H$56)) | I60: =IF($B60="","",SUMIFS(数据录入!$G$5:$G$4999,数据录入!$K$5:$K$4999,$B60,数据录入!$M$5:$M$4999,I$56)) | J60: =IF($B60="","",SUMIFS(数据录入!$G$5:$G$4999,数据录入!$K$5:$K$4999,$B60,数据录入!$M$5:$M$4999,J$56)) | ... N60: =IF($B60="","",SUMIFS(数据录入!$G$5:$G$4999,数据录入!$K$5:$K$4999,$B60,数据录入!$M$5:$M$4999,N$56)) | O60: =SUM(C60:N60) -> 0 | P60: =IF($O$55=0,"",O60/$O$55) -> 0
A61: 5 | C61: =IF($B61="","",SUMIFS(数据录入!$G$5:$G$4999,数据录入!$K$5:$K$4999,$B61,数据录入!$M$5:$M$4999,C$56)) | D61: =IF($B61="","",SUMIFS(数据录入!$G$5:$G$4999,数据录入!$K$5:$K$4999,$B61,数据录入!$M$5:$M$4999,D$56)) | E61: =IF($B61="","",SUMIFS(数据录入!$G$5:$G$4999,数据录入!$K$5:$K$4999,$B61,数据录入!$M$5:$M$4999,E$56)) | F61: =IF($B61="","",SUMIFS(数据录入!$G$5:$G$4999,数据录入!$K$5:$K$4999,$B61,数据录入!$M$5:$M$4999,F$56)) | G61: =IF($B61="","",SUMIFS(数据录入!$G$5:$G$4999,数据录入!$K$5:$K$4999,$B61,数据录入!$M$5:$M$4999,G$56)) | H61: =IF($B61="","",SUMIFS(数据录入!$G$5:$G$4999,数据录入!$K$5:$K$4999,$B61,数据录入!$M$5:$M$4999,H$56)) | I61: =IF($B61="","",SUMIFS(数据录入!$G$5:$G$4999,数据录入!$K$5:$K$4999,$B61,数据录入!$M$5:$M$4999,I$56)) | J61: =IF($B61="","",SUMIFS(数据录入!$G$5:$G$4999,数据录入!$K$5:$K$4999,$B61,数据录入!$M$5:$M$4999,J$56)) | ... N61: =IF($B61="","",SUMIFS(数据录入!$G$5:$G$4999,数据录入!$K$5:$K$4999,$B61,数据录入!$M$5:$M$4999,N$56)) | O61: =SUM(C61:N61) -> 0 | P61: =IF($O$55=0,"",O61/$O$55) -> 0
A62: 6 | C62: =IF($B62="","",SUMIFS(数据录入!$G$5:$G$4999,数据录入!$K$5:$K$4999,$B62,数据录入!$M$5:$M$4999,C$56)) | D62: =IF($B62="","",SUMIFS(数据录入!$G$5:$G$4999,数据录入!$K$5:$K$4999,$B62,数据录入!$M$5:$M$4999,D$56)) | E62: =IF($B62="","",SUMIFS(数据录入!$G$5:$G$4999,数据录入!$K$5:$K$4999,$B62,数据录入!$M$5:$M$4999,E$56)) | F62: =IF($B62="","",SUMIFS(数据录入!$G$5:$G$4999,数据录入!$K$5:$K$4999,$B62,数据录入!$M$5:$M$4999,F$56)) | G62: =IF($B62="","",SUMIFS(数据录入!$G$5:$G$4999,数据录入!$K$5:$K$4999,$B62,数据录入!$M$5:$M$4999,G$56)) | H62: =IF($B62="","",SUMIFS(数据录入!$G$5:$G$4999,数据录入!$K$5:$K$4999,$B62,数据录入!$M$5:$M$4999,H$56)) | I62: =IF($B62="","",SUMIFS(数据录入!$G$5:$G$4999,数据录入!$K$5:$K$4999,$B62,数据录入!$M$5:$M$4999,I$56)) | J62: =IF($B62="","",SUMIFS(数据录入!$G$5:$G$4999,数据录入!$K$5:$K$4999,$B62,数据录入!$M$5:$M$4999,J$56)) | ... N62: =IF($B62="","",SUMIFS(数据录入!$G$5:$G$4999,数据录入!$K$5:$K$4999,$B62,数据录入!$M$5:$M$4999,N$56)) | O62: =SUM(C62:N62) -> 0 | P62: =IF($O$55=0,"",O62/$O$55) -> 0
A63: 7 | C63: =IF($B63="","",SUMIFS(数据录入!$G$5:$G$4999,数据录入!$K$5:$K$4999,$B63,数据录入!$M$5:$M$4999,C$56)) | D63: =IF($B63="","",SUMIFS(数据录入!$G$5:$G$4999,数据录入!$K$5:$K$4999,$B63,数据录入!$M$5:$M$4999,D$56)) | E63: =IF($B63="","",SUMIFS(数据录入!$G$5:$G$4999,数据录入!$K$5:$K$4999,$B63,数据录入!$M$5:$M$4999,E$56)) | F63: =IF($B63="","",SUMIFS(数据录入!$G$5:$G$4999,数据录入!$K$5:$K$4999,$B63,数据录入!$M$5:$M$4999,F$56)) | G63: =IF($B63="","",SUMIFS(数据录入!$G$5:$G$4999,数据录入!$K$5:$K$4999,$B63,数据录入!$M$5:$M$4999,G$56)) | H63: =IF($B63="","",SUMIFS(数据录入!$G$5:$G$4999,数据录入!$K$5:$K$4999,$B63,数据录入!$M$5:$M$4999,H$56)) | I63: =IF($B63="","",SUMIFS(数据录入!$G$5:$G$4999,数据录入!$K$5:$K$4999,$B63,数据录入!$M$5:$M$4999,I$56)) | J63: =IF($B63="","",SUMIFS(数据录入!$G$5:$G$4999,数据录入!$K$5:$K$4999,$B63,数据录入!$M$5:$M$4999,J$56)) | ... N63: =IF($B63="","",SUMIFS(数据录入!$G$5:$G$4999,数据录入!$K$5:$K$4999,$B63,数据录入!$M$5:$M$4999,N$56)) | O63: =SUM(C63:N63) -> 0 | P63: =IF($O$55=0,"",O63/$O$55) -> 0
A64: 8 | C64: =IF($B64="","",SUMIFS(数据录入!$G$5:$G$4999,数据录入!$K$5:$K$4999,$B64,数据录入!$M$5:$M$4999,C$56)) | D64: =IF($B64="","",SUMIFS(数据录入!$G$5:$G$4999,数据录入!$K$5:$K$4999,$B64,数据录入!$M$5:$M$4999,D$56)) | E64: =IF($B64="","",SUMIFS(数据录入!$G$5:$G$4999,数据录入!$K$5:$K$4999,$B64,数据录入!$M$5:$M$4999,E$56)) | F64: =IF($B64="","",SUMIFS(数据录入!$G$5:$G$4999,数据录入!$K$5:$K$4999,$B64,数据录入!$M$5:$M$4999,F$56)) | G64: =IF($B64="","",SUMIFS(数据录入!$G$5:$G$4999,数据录入!$K$5:$K$4999,$B64,数据录入!$M$5:$M$4999,G$56)) | H64: =IF($B64="","",SUMIFS(数据录入!$G$5:$G$4999,数据录入!$K$5:$K$4999,$B64,数据录入!$M$5:$M$4999,H$56)) | I64: =IF($B64="","",SUMIFS(数据录入!$G$5:$G$4999,数据录入!$K$5:$K$4999,$B64,数据录入!$M$5:$M$4999,I$56)) | J64: =IF($B64="","",SUMIFS(数据录入!$G$5:$G$4999,数据录入!$K$5:$K$4999,$B64,数据录入!$M$5:$M$4999,J$56)) | ... N64: =IF($B64="","",SUMIFS(数据录入!$G$5:$G$4999,数据录入!$K$5:$K$4999,$B64,数据录入!$M$5:$M$4999,N$56)) | O64: =SUM(C64:N64) -> 0 | P64: =IF($O$55=0,"",O64/$O$55) -> 0
A65: 9 | C65: =IF($B65="","",SUMIFS(数据录入!$G$5:$G$4999,数据录入!$K$5:$K$4999,$B65,数据录入!$M$5:$M$4999,C$56)) | D65: =IF($B65="","",SUMIFS(数据录入!$G$5:$G$4999,数据录入!$K$5:$K$4999,$B65,数据录入!$M$5:$M$4999,D$56)) | E65: =IF($B65="","",SUMIFS(数据录入!$G$5:$G$4999,数据录入!$K$5:$K$4999,$B65,数据录入!$M$5:$M$4999,E$56)) | F65: =IF($B65="","",SUMIFS(数据录入!$G$5:$G$4999,数据录入!$K$5:$K$4999,$B65,数据录入!$M$5:$M$4999,F$56)) | G65: =IF($B65="","",SUMIFS(数据录入!$G$5:$G$4999,数据录入!$K$5:$K$4999,$B65,数据录入!$M$5:$M$4999,G$56)) | H65: =IF($B65="","",SUMIFS(数据录入!$G$5:$G$4999,数据录入!$K$5:$K$4999,$B65,数据录入!$M$5:$M$4999,H$56)) | I65: =IF($B65="","",SUMIFS(数据录入!$G$5:$G$4999,数据录入!$K$5:$K$4999,$B65,数据录入!$M$5:$M$4999,I$56)) | J65: =IF($B65="","",SUMIFS(数据录入!$G$5:$G$4999,数据录入!$K$5:$K$4999,$B65,数据录入!$M$5:$M$4999,J$56)) | ... N65: =IF($B65="","",SUMIFS(数据录入!$G$5:$G$4999,数据录入!$K$5:$K$4999,$B65,数据录入!$M$5:$M$4999,N$56)) | O65: =SUM(C65:N65) -> 0 | P65: =IF($O$55=0,"",O65/$O$55) -> 0
