Workbook

Sheet 首页
A1: 内帐财务管理系统 · 稳定重构版
A2: 日常只录：资金流水 + 销售录入 + 采购录入；其他报表自动生成。
A4: 查询月份 | B4: 46174
A5: 本月销售额 | D5: 客户回款 | G5: 本月毛利 | J5: 本月净利润
A6: =SUMIFS(销售录入!$I$4:$I$203,销售录入!$B$4:$B$203,TEXT($B$4,"yyyy-mm")) -> 26080 | D6: =SUMIFS(资金流水!$J$4:$J$203,资金流水!$D$4:$D$203,"客户回款",资金流水!$B$4:$B$203,TEXT($B$4,"yyyy-mm")) -> 20000 | G6: =库存收发存!M3 -> 13040 | J6: =利润表!C27 -> -8360
A9: 当前资金 | D9: 应收余额 | G9: 逾期应收 | J9: 应付余额
A10: =账户余额!H55 -> 848600 | D10: =应收跟进!F3 -> 164080 | G10: =应收跟进!L3 -> 138000 | J10: =应付跟进!F3 -> 220300
A13: 未来30天应付 | D13: 库存金额 | G13: 资金安全余量 | J13: 勾稽状态
A14: =应付跟进!G3 -> 16500 | D14: =库存收发存!J3 -> 107260 | G14: =账户余额!H55-应付跟进!G3 -> 832100 | J14: =财务勾稽核查!E15 -> 全部正常，可月结
A18: 日常入口：资金流水 ｜ 销售录入 ｜ 采购录入 月末检查：财务勾稽核查 ｜ 利润表 ｜ 资产负债表

Sheet 基础资料
A1: 基础资料（统一维护）
A2: 各模块横向并列维护；新增资料直接在对应模块下方继续录入。
A3: 资金账户 | F3: 部门 | J3: 员工 | O3: 商品档案 | X3: 客户档案 | AD3: 供应商档案 | AJ3: 资金流水分类 | AO3: 会计科目及报表映射
A4: 账户名称 | B4: 账户类型 | C4: 资金科目 | D4: 状态 | F4: 部门名称 | G4: 状态 | H4: 备注 | J4: 员工姓名 | K4: 部门 | L4: 岗位 | M4: 状态 | O4: 商品编号 | P4: 商品名称 | Q4: 规格型号 | R4: 单位 | S4: 状态 | T4: 参考成本 | U4: 参考售价 | V4: 备注 | W4: 库存显示 | X4: 客户编号 | Y4: 客户名称 | Z4: 业务员 | AA4: 账期(天) | AB4: 状态 | AD4: 供应商编号 | AE4: 供应商名称 | AF4: 采购员 | AG4: 账期(天) | AH4: 状态 | AJ4: 收支类型 | AK4: 收支科目 | AL4: 建议借方科目 | AM4: 建议贷方科目 | AO4: 科目编码 | AP4: 科目名称 | AQ4: 科目类别 | AR4: 余额方向 | AS4: 启用状态 | AT4: 资产负债表项目 | AU4: 利润表项目 | AV4: 现金流性质 | AW4: 辅助核算
A5: 现金 | B5: 现金类 | C5: 1001 | D5: 正常 | F5: 销售部 | G5: 正常 | J5: 张伟 | K5: 销售部 | L5: 销售 | M5: 正常 | O5: P001 | P5: A配件 | Q5: A-01 | R5: 个 | S5: 正常 | T5: 100 | U5: 200 | W5: =IF(P5="","",IF(SUMIFS(期初数据!$S$5:$S$14,期初数据!$P$5:$P$14,P5)+SUMIFS(采购录入!$G$4:$G$203,采购录入!$D$4:$D$203,P5,采购录入!$A$4:$A$203,"<="&EOMONTH(首页!$B$4,0))-SUMIFS(销售录入!$G$4:$G$203,销售录入!$D$4:$D$203,P5,销售录入!$A$4:$A$203,"<="&EOMONTH(首页!$B$4,0))<>0,"显示",IF(COUNTIFS(采购录入!$D$4:$D$203,P5,采购录入!$B$4:$B$203,TEXT(首页!$B$4,"yyyy-mm"))+COUNTIFS(销售录入!$D$4:$D$203,P5,销售录入!$B$4:$B$203,TEXT(首页!$B$4,"yyyy-mm"))>0,"显示",""))) -> 显示 | X5: C001 | Y5: 客户A | Z5: 张伟 | AA5: 30 | AB5: 正常 | AD5: S001 | AE5: 供应商A | AF5: 王强 | AG5: 30 | AH5: 正常 | AJ5: 收入 | AK5: 客户回款 | AL5: 1002 | AM5: 1122 | AO5: 1001 | AP5: 库存现金 | AQ5: 资产 | AR5: 借 | AS5: 启用 | AT5: 货币资金 | AV5: 非现金/资产负债 | AW5: 无
A6: 工商银行 | B6: 银行类 | C6: 1002 | D6: 正常 | F6: 财务部 | G6: 正常 | J6: 李娜 | K6: 销售部 | L6: 销售 | M6: 正常 | O6: P002 | P6: B配件 | Q6: B-02 | R6: 个 | S6: 正常 | T6: 125 | U6: 250 | W6: =IF(P6="","",IF(SUMIFS(期初数据!$S$5:$S$14,期初数据!$P$5:$P$14,P6)+SUMIFS(采购录入!$G$4:$G$203,采购录入!$D$4:$D$203,P6,采购录入!$A$4:$A$203,"<="&EOMONTH(首页!$B$4,0))-SUMIFS(销售录入!$G$4:$G$203,销售录入!$D$4:$D$203,P6,销售录入!$A$4:$A$203,"<="&EOMONTH(首页!$B$4,0))<>0,"显示",IF(COUNTIFS(采购录入!$D$4:$D$203,P6,采购录入!$B$4:$B$203,TEXT(首页!$B$4,"yyyy-mm"))+COUNTIFS(销售录入!$D$4:$D$203,P6,销售录入!$B$4:$B$203,TEXT(首页!$B$4,"yyyy-mm"))>0,"显示",""))) -> 显示 | X6: C002 | Y6: 客户B | Z6: 李娜 | AA6: 30 | AB6: 正常 | AD6: S002 | AE6: 供应商B | AF6: 王强 | AG6: 30 | AH6: 正常 | AJ6: 收入 | AK6: 服务收入 | AL6: 1002 | AM6: 6051 | AO6: 1002 | AP6: 银行存款 | AQ6: 资产 | AR6: 借 | AS6: 启用 | AT6: 货币资金 | AV6: 非现金/资产负债 | AW6: 无
A7: 农业银行 | B7: 银行类 | C7: 1002 | D7: 正常 | F7: 行政部 | G7: 正常 | J7: 王强 | K7: 采购部 | L7: 采购 | M7: 正常 | O7: P003 | P7: C配件 | Q7: C-03 | R7: 个 | S7: 正常 | T7: 50 | U7: 100 | W7: =IF(P7="","",IF(SUMIFS(期初数据!$S$5:$S$14,期初数据!$P$5:$P$14,P7)+SUMIFS(采购录入!$G$4:$G$203,采购录入!$D$4:$D$203,P7,采购录入!$A$4:$A$203,"<="&EOMONTH(首页!$B$4,0))-SUMIFS(销售录入!$G$4:$G$203,销售录入!$D$4:$D$203,P7,销售录入!$A$4:$A$203,"<="&EOMONTH(首页!$B$4,0))<>0,"显示",IF(COUNTIFS(采购录入!$D$4:$D$203,P7,采购录入!$B$4:$B$203,TEXT(首页!$B$4,"yyyy-mm"))+COUNTIFS(销售录入!$D$4:$D$203,P7,销售录入!$B$4:$B$203,TEXT(首页!$B$4,"yyyy-mm"))>0,"显示",""))) -> 显示 | X7: C003 | Y7: 客户C | Z7: 张伟 | AA7: 45 | AB7: 正常 | AD7: S003 | AE7: 供应商C | AF7: 王强 | AG7: 45 | AH7: 正常 | AJ7: 收入 | AK7: 其他业务收入 | AL7: 1002 | AM7: 6051 | AO7: 1012 | AP7: 其他货币资金 | AQ7: 资产 | AR7: 借 | AS7: 启用 | AT7: 货币资金 | AV7: 非现金/资产负债 | AW7: 无
A8: 建设银行 | B8: 银行类 | C8: 1002 | D8: 正常 | F8: 采购部 | G8: 正常 | J8: 陈敏 | K8: 行政部 | L8: 行政 | M8: 正常 | O8: P004 | P8: D配件 | Q8: D-04 | R8: 个 | S8: 正常 | T8: 200 | U8: 400 | W8: =IF(P8="","",IF(SUMIFS(期初数据!$S$5:$S$14,期初数据!$P$5:$P$14,P8)+SUMIFS(采购录入!$G$4:$G$203,采购录入!$D$4:$D$203,P8,采购录入!$A$4:$A$203,"<="&EOMONTH(首页!$B$4,0))-SUMIFS(销售录入!$G$4:$G$203,销售录入!$D$4:$D$203,P8,销售录入!$A$4:$A$203,"<="&EOMONTH(首页!$B$4,0))<>0,"显示",IF(COUNTIFS(采购录入!$D$4:$D$203,P8,采购录入!$B$4:$B$203,TEXT(首页!$B$4,"yyyy-mm"))+COUNTIFS(销售录入!$D$4:$D$203,P8,销售录入!$B$4:$B$203,TEXT(首页!$B$4,"yyyy-mm"))>0,"显示",""))) -> 显示 | X8: C004 | Y8: 客户D | Z8: 李娜 | AA8: 30 | AB8: 正常 | AD8: S004 | AE8: 供应商D | AF8: 王强 | AG8: 30 | AH8: 正常 | AJ8: 收入 | AK8: 利息收入 | AL8: 1002 | AM8: 6051 | AO8: 1101 | AP8: 交易性金融资产 | AQ8: 资产 | AR8: 借 | AS8: 启用 | AT8: 交易性金融资产 | AV8: 非现金/资产负债 | AW8: 无
A9: 招商银行 | B9: 银行类 | C9: 1002 | D9: 正常 | F9: 生产一部 | G9: 正常 | J9: 赵静 | K9: 财务部 | L9: 财务 | M9: 正常 | O9: P005 | P9: E配件 | Q9: E-05 | R9: 个 | S9: 正常 | T9: 25 | U9: 50 | W9: =IF(P9="","",IF(SUMIFS(期初数据!$S$5:$S$14,期初数据!$P$5:$P$14,P9)+SUMIFS(采购录入!$G$4:$G$203,采购录入!$D$4:$D$203,P9,采购录入!$A$4:$A$203,"<="&EOMONTH(首页!$B$4,0))-SUMIFS(销售录入!$G$4:$G$203,销售录入!$D$4:$D$203,P9,销售录入!$A$4:$A$203,"<="&EOMONTH(首页!$B$4,0))<>0,"显示",IF(COUNTIFS(采购录入!$D$4:$D$203,P9,采购录入!$B$4:$B$203,TEXT(首页!$B$4,"yyyy-mm"))+COUNTIFS(销售录入!$D$4:$D$203,P9,销售录入!$B$4:$B$203,TEXT(首页!$B$4,"yyyy-mm"))>0,"显示",""))) -> 显示 | X9: C005 | Y9: 客户E | Z9: 张伟 | AA9: 60 | AB9: 正常 | AD9: S005 | AE9: 供应商E | AF9: 王强 | AG9: 60 | AH9: 正常 | AJ9: 收入 | AK9: 租赁收入 | AL9: 1002 | AM9: 6051 | AO9: 1121 | AP9: 应收票据 | AQ9: 资产 | AR9: 借 | AS9: 启用 | AT9: 应收票据 | AV9: 非现金/资产负债 | AW9: 无
A10: 中国银行 | B10: 银行类 | C10: 1002 | D10: 正常 | F10: 生产二部 | G10: 正常 | J10: 刘洋 | K10: 仓储部 | L10: 仓储 | M10: 正常 | O10: P006 | P10: F配件 | Q10: F-06 | R10: 个 | S10: 正常 | T10: 80 | U10: 160 | W10: =IF(P10="","",IF(SUMIFS(期初数据!$S$5:$S$14,期初数据!$P$5:$P$14,P10)+SUMIFS(采购录入!$G$4:$G$203,采购录入!$D$4:$D$203,P10,采购录入!$A$4:$A$203,"<="&EOMONTH(首页!$B$4,0))-SUMIFS(销售录入!$G$4:$G$203,销售录入!$D$4:$D$203,P10,销售录入!$A$4:$A$203,"<="&EOMONTH(首页!$B$4,0))<>0,"显示",IF(COUNTIFS(采购录入!$D$4:$D$203,P10,采购录入!$B$4:$B$203,TEXT(首页!$B$4,"yyyy-mm"))+COUNTIFS(销售录入!$D$4:$D$203,P10,销售录入!$B$4:$B$203,TEXT(首页!$B$4,"yyyy-mm"))>0,"显示",""))) -> 显示 | X10: C006 | Y10: 客户F | Z10: 李娜 | AA10: 30 | AB10: 正常 | AD10: S006 | AE10: 供应商F | AF10: 王强 | AG10: 30 | AH10: 正常 | AJ10: 收入 | AK10: 废料收入 | AL10: 1002 | AM10: 6051 | AO10: 1122 | AP10: 应收账款 | AQ10: 资产 | AR10: 借 | AS10: 启用 | AT10: 应收账款 | AV10: 非现金/资产负债 | AW10: 客户
A11: 微信 | B11: 电子账户 | C11: 1002 | D11: 正常 | F11: 仓储部 | G11: 正常 | J11: 周磊 | K11: 生产一部 | L11: 生产 | M11: 正常 | O11: P007 | P11: G配件 | Q11: G-07 | R11: 个 | S11: 正常 | T11: 75 | U11: 150 | W11: =IF(P11="","",IF(SUMIFS(期初数据!$S$5:$S$14,期初数据!$P$5:$P$14,P11)+SUMIFS(采购录入!$G$4:$G$203,采购录入!$D$4:$D$203,P11,采购录入!$A$4:$A$203,"<="&EOMONTH(首页!$B$4,0))-SUMIFS(销售录入!$G$4:$G$203,销售录入!$D$4:$D$203,P11,销售录入!$A$4:$A$203,"<="&EOMONTH(首页!$B$4,0))<>0,"显示",IF(COUNTIFS(采购录入!$D$4:$D$203,P11,采购录入!$B$4:$B$203,TEXT(首页!$B$4,"yyyy-mm"))+COUNTIFS(销售录入!$D$4:$D$203,P11,销售录入!$B$4:$B$203,TEXT(首页!$B$4,"yyyy-mm"))>0,"显示",""))) -> 显示 | X11: C007 | Y11: 客户G | Z11: 张伟 | AA11: 45 | AB11: 正常 | AD11: S007 | AE11: 供应商G | AF11: 王强 | AG11: 45 | AH11: 正常 | AJ11: 收入 | AK11: 补贴收入 | AL11: 1002 | AM11: 6051 | AO11: 1123 | AP11: 预付账款 | AQ11: 资产 | AR11: 借 | AS11: 启用 | AT11: 预付款项 | AV11: 非现金/资产负债 | AW11: 供应商
A12: 支付宝 | B12: 电子账户 | C12: 1002 | D12: 正常 | F12: 电商部 | G12: 正常 | J12: 孙悦 | K12: 电商部 | L12: 电商 | M12: 正常 | O12: P008 | P12: H配件 | Q12: H-08 | R12: 个 | S12: 正常 | T12: 150 | U12: 300 | W12: =IF(P12="","",IF(SUMIFS(期初数据!$S$5:$S$14,期初数据!$P$5:$P$14,P12)+SUMIFS(采购录入!$G$4:$G$203,采购录入!$D$4:$D$203,P12,采购录入!$A$4:$A$203,"<="&EOMONTH(首页!$B$4,0))-SUMIFS(销售录入!$G$4:$G$203,销售录入!$D$4:$D$203,P12,销售录入!$A$4:$A$203,"<="&EOMONTH(首页!$B$4,0))<>0,"显示",IF(COUNTIFS(采购录入!$D$4:$D$203,P12,采购录入!$B$4:$B$203,TEXT(首页!$B$4,"yyyy-mm"))+COUNTIFS(销售录入!$D$4:$D$203,P12,销售录入!$B$4:$B$203,TEXT(首页!$B$4,"yyyy-mm"))>0,"显示",""))) -> 显示 | X12: C008 | Y12: 客户H | Z12: 李娜 | AA12: 30 | AB12: 正常 | AD12: S008 | AE12: 供应商H | AF12: 王强 | AG12: 30 | AH12: 正常 | AJ12: 收入 | AK12: 返点收入 | AL12: 1002 | AM12: 6051 | AO12: 1131 | AP12: 应收股利 | AQ12: 资产 | AR12: 借 | AS12: 启用 | AT12: 应收股利 | AV12: 非现金/资产负债 | AW12: 无
A13: 备用金 | B13: 现金类 | C13: 1001 | D13: 正常 | F13: 售后部 | G13: 正常 | J13: 吴刚 | K13: 售后部 | L13: 售后 | M13: 正常 | O13: P009 | P13: I配件 | Q13: I-09 | R13: 个 | S13: 正常 | T13: 30 | U13: 60 | W13: =IF(P13="","",IF(SUMIFS(期初数据!$S$5:$S$14,期初数据!$P$5:$P$14,P13)+SUMIFS(采购录入!$G$4:$G$203,采购录入!$D$4:$D$203,P13,采购录入!$A$4:$A$203,"<="&EOMONTH(首页!$B$4,0))-SUMIFS(销售录入!$G$4:$G$203,销售录入!$D$4:$D$203,P13,销售录入!$A$4:$A$203,"<="&EOMONTH(首页!$B$4,0))<>0,"显示",IF(COUNTIFS(采购录入!$D$4:$D$203,P13,采购录入!$B$4:$B$203,TEXT(首页!$B$4,"yyyy-mm"))+COUNTIFS(销售录入!$D$4:$D$203,P13,销售录入!$B$4:$B$203,TEXT(首页!$B$4,"yyyy-mm"))>0,"显示",""))) -> 显示 | X13: C009 | Y13: 客户I | Z13: 张伟 | AA13: 30 | AB13: 正常 | AD13: S009 | AE13: 供应商I | AF13: 王强 | AG13: 30 | AH13: 正常 | AJ13: 收入 | AK13: 手续费返还 | AL13: 1002 | AM13: 6051 | AO13: 1132 | AP13: 应收利息 | AQ13: 资产 | AR13: 借 | AS13: 启用 | AT13: 应收利息 | AV13: 非现金/资产负债 | AW13: 无
A14: 其他账户 | B14: 银行类 | C14: 1002 | D14: 正常 | F14: 管理层 | G14: 正常 | J14: 郑欣 | K14: 管理层 | L14: 管理 | M14: 正常 | O14: P010 | P14: J配件 | Q14: J-10 | R14: 个 | S14: 正常 | T14: 60 | U14: 120 | W14: =IF(P14="","",IF(SUMIFS(期初数据!$S$5:$S$14,期初数据!$P$5:$P$14,P14)+SUMIFS(采购录入!$G$4:$G$203,采购录入!$D$4:$D$203,P14,采购录入!$A$4:$A$203,"<="&EOMONTH(首页!$B$4,0))-SUMIFS(销售录入!$G$4:$G$203,销售录入!$D$4:$D$203,P14,销售录入!$A$4:$A$203,"<="&EOMONTH(首页!$B$4,0))<>0,"显示",IF(COUNTIFS(采购录入!$D$4:$D$203,P14,采购录入!$B$4:$B$203,TEXT(首页!$B$4,"yyyy-mm"))+COUNTIFS(销售录入!$D$4:$D$203,P14,销售录入!$B$4:$B$203,TEXT(首页!$B$4,"yyyy-mm"))>0,"显示",""))) -> 显示 | X14: C010 | Y14: 客户J | Z14: 李娜 | AA14: 60 | AB14: 正常 | AD14: S010 | AE14: 供应商J | AF14: 王强 | AG14: 60 | AH14: 正常 | AJ14: 收入 | AK14: 其他收入 | AL14: 1002 | AM14: 6051 | AO14: 1221 | AP14: 其他应收款 | AQ14: 资产 | AR14: 借 | AS14: 启用 | AT14: 其他应收款 | AV14: 非现金/资产负债 | AW14: 员工/其他
W15: =IF(P15="","",IF(SUMIFS(期初数据!$S$5:$S$14,期初数据!$P$5:$P$14,P15)+SUMIFS(采购录入!$G$4:$G$203,采购录入!$D$4:$D$203,P15,采购录入!$A$4:$A$203,"<="&EOMONTH(首页!$B$4,0))-SUMIFS(销售录入!$G$4:$G$203,销售录入!$D$4:$D$203,P15,销售录入!$A$4:$A$203,"<="&EOMONTH(首页!$B$4,0))<>0,"显示",IF(COUNTIFS(采购录入!$D$4:$D$203,P15,采购录入!$B$4:$B$203,TEXT(首页!$B$4,"yyyy-mm"))+COUNTIFS(销售录入!$D$4:$D$203,P15,销售录入!$B$4:$B$203,TEXT(首页!$B$4,"yyyy-mm"))>0,"显示",""))) | AJ15: 支出 | AK15: 供应商付款 | AL15: 2202 | AM15: 1002 | AO15: 1231 | AP15: 坏账准备 | AQ15: 资产 | AR15: 贷 | AS15: 启用 | AT15: 应收账款 | AV15: 非现金/资产负债 | AW15: 无
W16: =IF(P16="","",IF(SUMIFS(期初数据!$S$5:$S$14,期初数据!$P$5:$P$14,P16)+SUMIFS(采购录入!$G$4:$G$203,采购录入!$D$4:$D$203,P16,采购录入!$A$4:$A$203,"<="&EOMONTH(首页!$B$4,0))-SUMIFS(销售录入!$G$4:$G$203,销售录入!$D$4:$D$203,P16,销售录入!$A$4:$A$203,"<="&EOMONTH(首页!$B$4,0))<>0,"显示",IF(COUNTIFS(采购录入!$D$4:$D$203,P16,采购录入!$B$4:$B$203,TEXT(首页!$B$4,"yyyy-mm"))+COUNTIFS(销售录入!$D$4:$D$203,P16,销售录入!$B$4:$B$203,TEXT(首页!$B$4,"yyyy-mm"))>0,"显示",""))) | AJ16: 支出 | AK16: 办公费 | AL16: 6602 | AM16: 1002 | AO16: 1401 | AP16: 材料采购 | AQ16: 资产 | AR16: 借 | AS16: 启用 | AT16: 存货 | AV16: 非现金/资产负债 | AW16: 无
W17: =IF(P17="","",IF(SUMIFS(期初数据!$S$5:$S$14,期初数据!$P$5:$P$14,P17)+SUMIFS(采购录入!$G$4:$G$203,采购录入!$D$4:$D$203,P17,采购录入!$A$4:$A$203,"<="&EOMONTH(首页!$B$4,0))-SUMIFS(销售录入!$G$4:$G$203,销售录入!$D$4:$D$203,P17,销售录入!$A$4:$A$203,"<="&EOMONTH(首页!$B$4,0))<>0,"显示",IF(COUNTIFS(采购录入!$D$4:$D$203,P17,采购录入!$B$4:$B$203,TEXT(首页!$B$4,"yyyy-mm"))+COUNTIFS(销售录入!$D$4:$D$203,P17,销售录入!$B$4:$B$203,TEXT(首页!$B$4,"yyyy-mm"))>0,"显示",""))) | AJ17: 支出 | AK17: 房租 | AL17: 6602 | AM17: 1002 | AO17: 1402 | AP17: 在途物资 | AQ17: 资产 | AR17: 借 | AS17: 启用 | AT17: 存货 | AV17: 非现金/资产负债 | AW17: 无
W18: =IF(P18="","",IF(SUMIFS(期初数据!$S$5:$S$14,期初数据!$P$5:$P$14,P18)+SUMIFS(采购录入!$G$4:$G$203,采购录入!$D$4:$D$203,P18,采购录入!$A$4:$A$203,"<="&EOMONTH(首页!$B$4,0))-SUMIFS(销售录入!$G$4:$G$203,销售录入!$D$4:$D$203,P18,销售录入!$A$4:$A$203,"<="&EOMONTH(首页!$B$4,0))<>0,"显示",IF(COUNTIFS(采购录入!$D$4:$D$203,P18,采购录入!$B$4:$B$203,TEXT(首页!$B$4,"yyyy-mm"))+COUNTIFS(销售录入!$D$4:$D$203,P18,销售录入!$B$4:$B$203,TEXT(首页!$B$4,"yyyy-mm"))>0,"显示",""))) | AJ18: 支出 | AK18: 水电费 | AL18: 6602 | AM18: 1002 | AO18: 1403 | AP18: 原材料 | AQ18: 资产 | AR18: 借 | AS18: 启用 | AT18: 存货 | AV18: 非现金/资产负债 | AW18: 无
W19: =IF(P19="","",IF(SUMIFS(期初数据!$S$5:$S$14,期初数据!$P$5:$P$14,P19)+SUMIFS(采购录入!$G$4:$G$203,采购录入!$D$4:$D$203,P19,采购录入!$A$4:$A$203,"<="&EOMONTH(首页!$B$4,0))-SUMIFS(销售录入!$G$4:$G$203,销售录入!$D$4:$D$203,P19,销售录入!$A$4:$A$203,"<="&EOMONTH(首页!$B$4,0))<>0,"显示",IF(COUNTIFS(采购录入!$D$4:$D$203,P19,采购录入!$B$4:$B$203,TEXT(首页!$B$4,"yyyy-mm"))+COUNTIFS(销售录入!$D$4:$D$203,P19,销售录入!$B$4:$B$203,TEXT(首页!$B$4,"yyyy-mm"))>0,"显示",""))) | AJ19: 支出 | AK19: 维修费 | AL19: 6602 | AM19: 1002 | AO19: 1404 | AP19: 材料成本差异 | AQ19: 资产 | AR19: 借 | AS19: 启用 | AT19: 存货 | AV19: 非现金/资产负债 | AW19: 无
W20: =IF(P20="","",IF(SUMIFS(期初数据!$S$5:$S$14,期初数据!$P$5:$P$14,P20)+SUMIFS(采购录入!$G$4:$G$203,采购录入!$D$4:$D$203,P20,采购录入!$A$4:$A$203,"<="&EOMONTH(首页!$B$4,0))-SUMIFS(销售录入!$G$4:$G$203,销售录入!$D$4:$D$203,P20,销售录入!$A$4:$A$203,"<="&EOMONTH(首页!$B$4,0))<>0,"显示",IF(COUNTIFS(采购录入!$D$4:$D$203,P20,采购录入!$B$4:$B$203,TEXT(首页!$B$4,"yyyy-mm"))+COUNTIFS(销售录入!$D$4:$D$203,P20,销售录入!$B$4:$B$203,TEXT(首页!$B$4,"yyyy-mm"))>0,"显示",""))) | AJ20: 支出 | AK20: 工资 | AL20: 6602 | AM20: 1002 | AO20: 1405 | AP20: 库存商品 | AQ20: 资产 | AR20: 借 | AS20: 启用 | AT20: 存货 | AV20: 非现金/资产负债 | AW20: 无
W21: =IF(P21="","",IF(SUMIFS(期初数据!$S$5:$S$14,期初数据!$P$5:$P$14,P21)+SUMIFS(采购录入!$G$4:$G$203,采购录入!$D$4:$D$203,P21,采购录入!$A$4:$A$203,"<="&EOMONTH(首页!$B$4,0))-SUMIFS(销售录入!$G$4:$G$203,销售录入!$D$4:$D$203,P21,销售录入!$A$4:$A$203,"<="&EOMONTH(首页!$B$4,0))<>0,"显示",IF(COUNTIFS(采购录入!$D$4:$D$203,P21,采购录入!$B$4:$B$203,TEXT(首页!$B$4,"yyyy-mm"))+COUNTIFS(销售录入!$D$4:$D$203,P21,销售录入!$B$4:$B$203,TEXT(首页!$B$4,"yyyy-mm"))>0,"显示",""))) | AJ21: 支出 | AK21: 差旅费 | AL21: 6602 | AM21: 1002 | AO21: 1406 | AP21: 发出商品 | AQ21: 资产 | AR21: 借 | AS21: 启用 | AT21: 存货 | AV21: 非现金/资产负债 | AW21: 无
W22: =IF(P22="","",IF(SUMIFS(期初数据!$S$5:$S$14,期初数据!$P$5:$P$14,P22)+SUMIFS(采购录入!$G$4:$G$203,采购录入!$D$4:$D$203,P22,采购录入!$A$4:$A$203,"<="&EOMONTH(首页!$B$4,0))-SUMIFS(销售录入!$G$4:$G$203,销售录入!$D$4:$D$203,P22,销售录入!$A$4:$A$203,"<="&EOMONTH(首页!$B$4,0))<>0,"显示",IF(COUNTIFS(采购录入!$D$4:$D$203,P22,采购录入!$B$4:$B$203,TEXT(首页!$B$4,"yyyy-mm"))+COUNTIFS(销售录入!$D$4:$D$203,P22,销售录入!$B$4:$B$203,TEXT(首页!$B$4,"yyyy-mm"))>0,"显示",""))) | AJ22: 支出 | AK22: 其他费用 | AL22: 6602 | AM22: 1002 | AO22: 1407 | AP22: 商品进销差价 | AQ22: 资产 | AR22: 贷 | AS22: 启用 | AT22: 存货 | AV22: 非现金/资产负债 | AW22: 无
W23: =IF(P23="","",IF(SUMIFS(期初数据!$S$5:$S$14,期初数据!$P$5:$P$14,P23)+SUMIFS(采购录入!$G$4:$G$203,采购录入!$D$4:$D$203,P23,采购录入!$A$4:$A$203,"<="&EOMONTH(首页!$B$4,0))-SUMIFS(销售录入!$G$4:$G$203,销售录入!$D$4:$D$203,P23,销售录入!$A$4:$A$203,"<="&EOMONTH(首页!$B$4,0))<>0,"显示",IF(COUNTIFS(采购录入!$D$4:$D$203,P23,采购录入!$B$4:$B$203,TEXT(首页!$B$4,"yyyy-mm"))+COUNTIFS(销售录入!$D$4:$D$203,P23,销售录入!$B$4:$B$203,TEXT(首页!$B$4,"yyyy-mm"))>0,"显示",""))) | AJ23: 支出 | AK23: 广告费 | AL23: 6601 | AM23: 1002 | AO23: 1408 | AP23: 委托加工物资 | AQ23: 资产 | AR23: 借 | AS23: 启用 | AT23: 存货 | AV23: 非现金/资产负债 | AW23: 无
W24: =IF(P24="","",IF(SUMIFS(期初数据!$S$5:$S$14,期初数据!$P$5:$P$14,P24)+SUMIFS(采购录入!$G$4:$G$203,采购录入!$D$4:$D$203,P24,采购录入!$A$4:$A$203,"<="&EOMONTH(首页!$B$4,0))-SUMIFS(销售录入!$G$4:$G$203,销售录入!$D$4:$D$203,P24,销售录入!$A$4:$A$203,"<="&EOMONTH(首页!$B$4,0))<>0,"显示",IF(COUNTIFS(采购录入!$D$4:$D$203,P24,采购录入!$B$4:$B$203,TEXT(首页!$B$4,"yyyy-mm"))+COUNTIFS(销售录入!$D$4:$D$203,P24,销售录入!$B$4:$B$203,TEXT(首页!$B$4,"yyyy-mm"))>0,"显示",""))) | AJ24: 支出 | AK24: 物流费 | AL24: 6601 | AM24: 1002 | AO24: 1411 | AP24: 周转材料 | AQ24: 资产 | AR24: 借 | AS24: 启用 | AT24: 存货 | AV24: 非现金/资产负债 | AW24: 无
W25: =IF(P25="","",IF(SUMIFS(期初数据!$S$5:$S$14,期初数据!$P$5:$P$14,P25)+SUMIFS(采购录入!$G$4:$G$203,采购录入!$D$4:$D$203,P25,采购录入!$A$4:$A$203,"<="&EOMONTH(首页!$B$4,0))-SUMIFS(销售录入!$G$4:$G$203,销售录入!$D$4:$D$203,P25,销售录入!$A$4:$A$203,"<="&EOMONTH(首页!$B$4,0))<>0,"显示",IF(COUNTIFS(采购录入!$D$4:$D$203,P25,采购录入!$B$4:$B$203,TEXT(首页!$B$4,"yyyy-mm"))+COUNTIFS(销售录入!$D$4:$D$203,P25,销售录入!$B$4:$B$203,TEXT(首页!$B$4,"yyyy-mm"))>0,"显示",""))) | AJ25: 支出 | AK25: 财务手续费 | AL25: 6603 | AM25: 1002 | AO25: 1471 | AP25: 存货跌价准备 | AQ25: 资产 | AR25: 贷 | AS25: 启用 | AT25: 存货 | AV25: 非现金/资产负债 | AW25: 无
W26: =IF(P26="","",IF(SUMIFS(期初数据!$S$5:$S$14,期初数据!$P$5:$P$14,P26)+SUMIFS(采购录入!$G$4:$G$203,采购录入!$D$4:$D$203,P26,采购录入!$A$4:$A$203,"<="&EOMONTH(首页!$B$4,0))-SUMIFS(销售录入!$G$4:$G$203,销售录入!$D$4:$D$203,P26,销售录入!$A$4:$A$203,"<="&EOMONTH(首页!$B$4,0))<>0,"显示",IF(COUNTIFS(采购录入!$D$4:$D$203,P26,采购录入!$B$4:$B$203,TEXT(首页!$B$4,"yyyy-mm"))+COUNTIFS(销售录入!$D$4:$D$203,P26,销售录入!$B$4:$B$203,TEXT(首页!$B$4,"yyyy-mm"))>0,"显示",""))) | AJ26: 转账 | AK26: 账户转账 | AL26: 1002 | AM26: 1002 | AO26: 1501 | AP26: 债权投资 | AQ26: 资产 | AR26: 借 | AS26: 启用 | AT26: 债权投资 | AV26: 投资活动 | AW26: 无
W27: =IF(P27="","",IF(SUMIFS(期初数据!$S$5:$S$14,期初数据!$P$5:$P$14,P27)+SUMIFS(采购录入!$G$4:$G$203,采购录入!$D$4:$D$203,P27,采购录入!$A$4:$A$203,"<="&EOMONTH(首页!$B$4,0))-SUMIFS(销售录入!$G$4:$G$203,销售录入!$D$4:$D$203,P27,销售录入!$A$4:$A$203,"<="&EOMONTH(首页!$B$4,0))<>0,"显示",IF(COUNTIFS(采购录入!$D$4:$D$203,P27,采购录入!$B$4:$B$203,TEXT(首页!$B$4,"yyyy-mm"))+COUNTIFS(销售录入!$D$4:$D$203,P27,销售录入!$B$4:$B$203,TEXT(首页!$B$4,"yyyy-mm"))>0,"显示",""))) | AO27: 1511 | AP27: 长期股权投资 | AQ27: 资产 | AR27: 借 | AS27: 启用 | AT27: 长期股权投资 | AV27: 投资活动 | AW27: 无
W28: =IF(P28="","",IF(SUMIFS(期初数据!$S$5:$S$14,期初数据!$P$5:$P$14,P28)+SUMIFS(采购录入!$G$4:$G$203,采购录入!$D$4:$D$203,P28,采购录入!$A$4:$A$203,"<="&EOMONTH(首页!$B$4,0))-SUMIFS(销售录入!$G$4:$G$203,销售录入!$D$4:$D$203,P28,销售录入!$A$4:$A$203,"<="&EOMONTH(首页!$B$4,0))<>0,"显示",IF(COUNTIFS(采购录入!$D$4:$D$203,P28,采购录入!$B$4:$B$203,TEXT(首页!$B$4,"yyyy-mm"))+COUNTIFS(销售录入!$D$4:$D$203,P28,销售录入!$B$4:$B$203,TEXT(首页!$B$4,"yyyy-mm"))>0,"显示",""))) | AO28: 1521 | AP28: 投资性房地产 | AQ28: 资产 | AR28: 借 | AS28: 启用 | AT28: 投资性房地产 | AV28: 非现金/资产负债 | AW28: 无
W29: =IF(P29="","",IF(SUMIFS(期初数据!$S$5:$S$14,期初数据!$P$5:$P$14,P29)+SUMIFS(采购录入!$G$4:$G$203,采购录入!$D$4:$D$203,P29,采购录入!$A$4:$A$203,"<="&EOMONTH(首页!$B$4,0))-SUMIFS(销售录入!$G$4:$G$203,销售录入!$D$4:$D$203,P29,销售录入!$A$4:$A$203,"<="&EOMONTH(首页!$B$4,0))<>0,"显示",IF(COUNTIFS(采购录入!$D$4:$D$203,P29,采购录入!$B$4:$B$203,TEXT(首页!$B$4,"yyyy-mm"))+COUNTIFS(销售录入!$D$4:$D$203,P29,销售录入!$B$4:$B$203,TEXT(首页!$B$4,"yyyy-mm"))>0,"显示",""))) | AO29: 1601 | AP29: 固定资产 | AQ29: 资产 | AR29: 借 | AS29: 启用 | AT29: 固定资产 | AV29: 投资活动 | AW29: 无
W30: =IF(P30="","",IF(SUMIFS(期初数据!$S$5:$S$14,期初数据!$P$5:$P$14,P30)+SUMIFS(采购录入!$G$4:$G$203,采购录入!$D$4:$D$203,P30,采购录入!$A$4:$A$203,"<="&EOMONTH(首页!$B$4,0))-SUMIFS(销售录入!$G$4:$G$203,销售录入!$D$4:$D$203,P30,销售录入!$A$4:$A$203,"<="&EOMONTH(首页!$B$4,0))<>0,"显示",IF(COUNTIFS(采购录入!$D$4:$D$203,P30,采购录入!$B$4:$B$203,TEXT(首页!$B$4,"yyyy-mm"))+COUNTIFS(销售录入!$D$4:$D$203,P30,销售录入!$B$4:$B$203,TEXT(首页!$B$4,"yyyy-mm"))>0,"显示",""))) | AO30: 1602 | AP30: 累计折旧 | AQ30: 资产 | AR30: 贷 | AS30: 启用 | AT30: 固定资产 | AV30: 非现金/资产负债 | AW30: 无
W31: =IF(P31="","",IF(SUMIFS(期初数据!$S$5:$S$14,期初数据!$P$5:$P$14,P31)+SUMIFS(采购录入!$G$4:$G$203,采购录入!$D$4:$D$203,P31,采购录入!$A$4:$A$203,"<="&EOMONTH(首页!$B$4,0))-SUMIFS(销售录入!$G$4:$G$203,销售录入!$D$4:$D$203,P31,销售录入!$A$4:$A$203,"<="&EOMONTH(首页!$B$4,0))<>0,"显示",IF(COUNTIFS(采购录入!$D$4:$D$203,P31,采购录入!$B$4:$B$203,TEXT(首页!$B$4,"yyyy-mm"))+COUNTIFS(销售录入!$D$4:$D$203,P31,销售录入!$B$4:$B$203,TEXT(首页!$B$4,"yyyy-mm"))>0,"显示",""))) | AO31: 1604 | AP31: 在建工程 | AQ31: 资产 | AR31: 借 | AS31: 启用 | AT31: 在建工程 | AV31: 投资活动 | AW31: 无
W32: =IF(P32="","",IF(SUMIFS(期初数据!$S$5:$S$14,期初数据!$P$5:$P$14,P32)+SUMIFS(采购录入!$G$4:$G$203,采购录入!$D$4:$D$203,P32,采购录入!$A$4:$A$203,"<="&EOMONTH(首页!$B$4,0))-SUMIFS(销售录入!$G$4:$G$203,销售录入!$D$4:$D$203,P32,销售录入!$A$4:$A$203,"<="&EOMONTH(首页!$B$4,0))<>0,"显示",IF(COUNTIFS(采购录入!$D$4:$D$203,P32,采购录入!$B$4:$B$203,TEXT(首页!$B$4,"yyyy-mm"))+COUNTIFS(销售录入!$D$4:$D$203,P32,销售录入!$B$4:$B$203,TEXT(首页!$B$4,"yyyy-mm"))>0,"显示",""))) | AO32: 1605 | AP32: 工程物资 | AQ32: 资产 | AR32: 借 | AS32: 启用 | AT32: 在建工程 | AV32: 非现金/资产负债 | AW32: 无
W33: =IF(P33="","",IF(SUMIFS(期初数据!$S$5:$S$14,期初数据!$P$5:$P$14,P33)+SUMIFS(采购录入!$G$4:$G$203,采购录入!$D$4:$D$203,P33,采购录入!$A$4:$A$203,"<="&EOMONTH(首页!$B$4,0))-SUMIFS(销售录入!$G$4:$G$203,销售录入!$D$4:$D$203,P33,销售录入!$A$4:$A$203,"<="&EOMONTH(首页!$B$4,0))<>0,"显示",IF(COUNTIFS(采购录入!$D$4:$D$203,P33,采购录入!$B$4:$B$203,TEXT(首页!$B$4,"yyyy-mm"))+COUNTIFS(销售录入!$D$4:$D$203,P33,销售录入!$B$4:$B$203,TEXT(首页!$B$4,"yyyy-mm"))>0,"显示",""))) | AO33: 1606 | AP33: 固定资产清理 | AQ33: 资产 | AR33: 借 | AS33: 启用 | AT33: 固定资产 | AV33: 非现金/资产负债 | AW33: 无
W34: =IF(P34="","",IF(SUMIFS(期初数据!$S$5:$S$14,期初数据!$P$5:$P$14,P34)+SUMIFS(采购录入!$G$4:$G$203,采购录入!$D$4:$D$203,P34,采购录入!$A$4:$A$203,"<="&EOMONTH(首页!$B$4,0))-SUMIFS(销售录入!$G$4:$G$203,销售录入!$D$4:$D$203,P34,销售录入!$A$4:$A$203,"<="&EOMONTH(首页!$B$4,0))<>0,"显示",IF(COUNTIFS(采购录入!$D$4:$D$203,P34,采购录入!$B$4:$B$203,TEXT(首页!$B$4,"yyyy-mm"))+COUNTIFS(销售录入!$D$4:$D$203,P34,销售录入!$B$4:$B$203,TEXT(首页!$B$4,"yyyy-mm"))>0,"显示",""))) | AO34: 1701 | AP34: 无形资产 | AQ34: 资产 | AR34: 借 | AS34: 启用 | AT34: 无形资产 | AV34: 投资活动 | AW34: 无
W35: =IF(P35="","",IF(SUMIFS(期初数据!$S$5:$S$14,期初数据!$P$5:$P$14,P35)+SUMIFS(采购录入!$G$4:$G$203,采购录入!$D$4:$D$203,P35,采购录入!$A$4:$A$203,"<="&EOMONTH(首页!$B$4,0))-SUMIFS(销售录入!$G$4:$G$203,销售录入!$D$4:$D$203,P35,销售录入!$A$4:$A$203,"<="&EOMONTH(首页!$B$4,0))<>0,"显示",IF(COUNTIFS(采购录入!$D$4:$D$203,P35,采购录入!$B$4:$B$203,TEXT(首页!$B$4,"yyyy-mm"))+COUNTIFS(销售录入!$D$4:$D$203,P35,销售录入!$B$4:$B$203,TEXT(首页!$B$4,"yyyy-mm"))>0,"显示",""))) | AO35: 1702 | AP35: 累计摊销 | AQ35: 资产 | AR35: 贷 | AS35: 启用 | AT35: 无形资产 | AV35: 非现金/资产负债 | AW35: 无
W36: =IF(P36="","",IF(SUMIFS(期初数据!$S$5:$S$14,期初数据!$P$5:$P$14,P36)+SUMIFS(采购录入!$G$4:$G$203,采购录入!$D$4:$D$203,P36,采购录入!$A$4:$A$203,"<="&EOMONTH(首页!$B$4,0))-SUMIFS(销售录入!$G$4:$G$203,销售录入!$D$4:$D$203,P36,销售录入!$A$4:$A$203,"<="&EOMONTH(首页!$B$4,0))<>0,"显示",IF(COUNTIFS(采购录入!$D$4:$D$203,P36,采购录入!$B$4:$B$203,TEXT(首页!$B$4,"yyyy-mm"))+COUNTIFS(销售录入!$D$4:$D$203,P36,销售录入!$B$4:$B$203,TEXT(首页!$B$4,"yyyy-mm"))>0,"显示",""))) | AO36: 1801 | AP36: 长期待摊费用 | AQ36: 资产 | AR36: 借 | AS36: 启用 | AT36: 长期待摊费用 | AV36: 非现金/资产负债 | AW36: 无
W37: =IF(P37="","",IF(SUMIFS(期初数据!$S$5:$S$14,期初数据!$P$5:$P$14,P37)+SUMIFS(采购录入!$G$4:$G$203,采购录入!$D$4:$D$203,P37,采购录入!$A$4:$A$203,"<="&EOMONTH(首页!$B$4,0))-SUMIFS(销售录入!$G$4:$G$203,销售录入!$D$4:$D$203,P37,销售录入!$A$4:$A$203,"<="&EOMONTH(首页!$B$4,0))<>0,"显示",IF(COUNTIFS(采购录入!$D$4:$D$203,P37,采购录入!$B$4:$B$203,TEXT(首页!$B$4,"yyyy-mm"))+COUNTIFS(销售录入!$D$4:$D$203,P37,销售录入!$B$4:$B$203,TEXT(首页!$B$4,"yyyy-mm"))>0,"显示",""))) | AO37: 1811 | AP37: 递延所得税资产 | AQ37: 资产 | AR37: 借 | AS37: 启用 | AT37: 递延所得税资产 | AV37: 非现金/资产负债 | AW37: 无
W38: =IF(P38="","",IF(SUMIFS(期初数据!$S$5:$S$14,期初数据!$P$5:$P$14,P38)+SUMIFS(采购录入!$G$4:$G$203,采购录入!$D$4:$D$203,P38,采购录入!$A$4:$A$203,"<="&EOMONTH(首页!$B$4,0))-SUMIFS(销售录入!$G$4:$G$203,销售录入!$D$4:$D$203,P38,销售录入!$A$4:$A$203,"<="&EOMONTH(首页!$B$4,0))<>0,"显示",IF(COUNTIFS(采购录入!$D$4:$D$203,P38,采购录入!$B$4:$B$203,TEXT(首页!$B$4,"yyyy-mm"))+COUNTIFS(销售录入!$D$4:$D$203,P38,销售录入!$B$4:$B$203,TEXT(首页!$B$4,"yyyy-mm"))>0,"显示",""))) | AO38: 1901 | AP38: 待处理财产损溢 | AQ38: 资产 | AR38: 借 | AS38: 启用 | AT38: 其他流动资产 | AV38: 非现金/资产负债 | AW38: 无
... W60: =IF(P60="","",IF(SUMIFS(期初数据!$S$5:$S$14,期初数据!$P$5:$P$14,P60)+SUMIFS(采购录入!$G$4:$G$203,采购录入!$D$4:$D$203,P60,采购录入!$A$4:$A$203,"<="&EOMONTH(首页!$B$4,0))-SUMIFS(销售录入!$G$4:$G$203,销售录入!$D$4:$D$203,P60,销售录入!$A$4:$A$203,"<="&EOMONTH(首页!$B$4,0))<>0,"显示",IF(COUNTIFS(采购录入!$D$4:$D$203,P60,采购录入!$B$4:$B$203,TEXT(首页!$B$4,"yyyy-mm"))+COUNTIFS(销售录入!$D$4:$D$203,P60,销售录入!$B$4:$B$203,TEXT(首页!$B$4,"yyyy-mm"))>0,"显示",""))) | AO60: 4101 | AP60: 盈余公积 | AQ60: 权益 | AR60: 贷 | AS60: 启用 | AT60: 盈余公积 | AV60: 非现金/资产负债 | AW60: 无
W61: =IF(P61="","",IF(SUMIFS(期初数据!$S$5:$S$14,期初数据!$P$5:$P$14,P61)+SUMIFS(采购录入!$G$4:$G$203,采购录入!$D$4:$D$203,P61,采购录入!$A$4:$A$203,"<="&EOMONTH(首页!$B$4,0))-SUMIFS(销售录入!$G$4:$G$203,销售录入!$D$4:$D$203,P61,销售录入!$A$4:$A$203,"<="&EOMONTH(首页!$B$4,0))<>0,"显示",IF(COUNTIFS(采购录入!$D$4:$D$203,P61,采购录入!$B$4:$B$203,TEXT(首页!$B$4,"yyyy-mm"))+COUNTIFS(销售录入!$D$4:$D$203,P61,销售录入!$B$4:$B$203,TEXT(首页!$B$4,"yyyy-mm"))>0,"显示",""))) | AO61: 4103 | AP61: 本年利润 | AQ61: 权益 | AR61: 贷 | AS61: 启用 | AV61: 非现金/资产负债 | AW61: 无
W62: =IF(P62="","",IF(SUMIFS(期初数据!$S$5:$S$14,期初数据!$P$5:$P$14,P62)+SUMIFS(采购录入!$G$4:$G$203,采购录入!$D$4:$D$203,P62,采购录入!$A$4:$A$203,"<="&EOMONTH(首页!$B$4,0))-SUMIFS(销售录入!$G$4:$G$203,销售录入!$D$4:$D$203,P62,销售录入!$A$4:$A$203,"<="&EOMONTH(首页!$B$4,0))<>0,"显示",IF(COUNTIFS(采购录入!$D$4:$D$203,P62,采购录入!$B$4:$B$203,TEXT(首页!$B$4,"yyyy-mm"))+COUNTIFS(销售录入!$D$4:$D$203,P62,销售录入!$B$4:$B$203,TEXT(首页!$B$4,"yyyy-mm"))>0,"显示",""))) | AO62: 4104 | AP62: 利润分配 | AQ62: 权益 | AR62: 贷 | AS62: 启用 | AT62: 未分配利润 | AV62: 非现金/资产负债 | AW62: 无
W63: =IF(P63="","",IF(SUMIFS(期初数据!$S$5:$S$14,期初数据!$P$5:$P$14,P63)+SUMIFS(采购录入!$G$4:$G$203,采购录入!$D$4:$D$203,P63,采购录入!$A$4:$A$203,"<="&EOMONTH(首页!$B$4,0))-SUMIFS(销售录入!$G$4:$G$203,销售录入!$D$4:$D$203,P63,销售录入!$A$4:$A$203,"<="&EOMONTH(首页!$B$4,0))<>0,"显示",IF(COUNTIFS(采购录入!$D$4:$D$203,P63,采购录入!$B$4:$B$203,TEXT(首页!$B$4,"yyyy-mm"))+COUNTIFS(销售录入!$D$4:$D$203,P63,销售录入!$B$4:$B$203,TEXT(首页!$B$4,"yyyy-mm"))>0,"显示",""))) | AO63: 5001 | AP63: 生产成本 | AQ63: 成本 | AR63: 借 | AS63: 启用 | AT63: 存货 | AV63: 非现金/资产负债 | AW63: 无
W64: =IF(P64="","",IF(SUMIFS(期初数据!$S$5:$S$14,期初数据!$P$5:$P$14,P64)+SUMIFS(采购录入!$G$4:$G$203,采购录入!$D$4:$D$203,P64,采购录入!$A$4:$A$203,"<="&EOMONTH(首页!$B$4,0))-SUMIFS(销售录入!$G$4:$G$203,销售录入!$D$4:$D$203,P64,销售录入!$A$4:$A$203,"<="&EOMONTH(首页!$B$4,0))<>0,"显示",IF(COUNTIFS(采购录入!$D$4:$D$203,P64,采购录入!$B$4:$B$203,TEXT(首页!$B$4,"yyyy-mm"))+COUNTIFS(销售录入!$D$4:$D$203,P64,销售录入!$B$4:$B$203,TEXT(首页!$B$4,"yyyy-mm"))>0,"显示",""))) | AO64: 5101 | AP64: 制造费用 | AQ64: 成本 | AR64: 借 | AS64: 启用 | AT64: 存货 | AV64: 非现金/资产负债 | AW64: 无
W65: =IF(P65="","",IF(SUMIFS(期初数据!$S$5:$S$14,期初数据!$P$5:$P$14,P65)+SUMIFS(采购录入!$G$4:$G$203,采购录入!$D$4:$D$203,P65,采购录入!$A$4:$A$203,"<="&EOMONTH(首页!$B$4,0))-SUMIFS(销售录入!$G$4:$G$203,销售录入!$D$4:$D$203,P65,销售录入!$A$4:$A$203,"<="&EOMONTH(首页!$B$4,0))<>0,"显示",IF(COUNTIFS(采购录入!$D$4:$D$203,P65,采购录入!$B$4:$B$203,TEXT(首页!$B$4,"yyyy-mm"))+COUNTIFS(销售录入!$D$4:$D$203,P65,销售录入!$B$4:$B$203,TEXT(首页!$B$4,"yyyy-mm"))>0,"显示",""))) | AO65: 5201 | AP65: 劳务成本 | AQ65: 成本 | AR65: 借 | AS65: 启用 | AV65: 非现金/资产负债 | AW65: 无
W66: =IF(P66="","",IF(SUMIFS(期初数据!$S$5:$S$14,期初数据!$P$5:$P$14,P66)+SUMIFS(采购录入!$G$4:$G$203,采购录入!$D$4:$D$203,P66,采购录入!$A$4:$A$203,"<="&EOMONTH(首页!$B$4,0))-SUMIFS(销售录入!$G$4:$G$203,销售录入!$D$4:$D$203,P66,销售录入!$A$4:$A$203,"<="&EOMONTH(首页!$B$4,0))<>0,"显示",IF(COUNTIFS(采购录入!$D$4:$D$203,P66,采购录入!$B$4:$B$203,TEXT(首页!$B$4,"yyyy-mm"))+COUNTIFS(销售录入!$D$4:$D$203,P66,销售录入!$B$4:$B$203,TEXT(首页!$B$4,"yyyy-mm"))>0,"显示",""))) | AO66: 5301 | AP66: 研发支出 | AQ66: 成本 | AR66: 借 | AS66: 启用 | AT66: 开发支出 | AV66: 非现金/资产负债 | AW66: 无
W67: =IF(P67="","",IF(SUMIFS(期初数据!$S$5:$S$14,期初数据!$P$5:$P$14,P67)+SUMIFS(采购录入!$G$4:$G$203,采购录入!$D$4:$D$203,P67,采购录入!$A$4:$A$203,"<="&EOMONTH(首页!$B$4,0))-SUMIFS(销售录入!$G$4:$G$203,销售录入!$D$4:$D$203,P67,销售录入!$A$4:$A$203,"<="&EOMONTH(首页!$B$4,0))<>0,"显示",IF(COUNTIFS(采购录入!$D$4:$D$203,P67,采购录入!$B$4:$B$203,TEXT(首页!$B$4,"yyyy-mm"))+COUNTIFS(销售录入!$D$4:$D$203,P67,销售录入!$B$4:$B$203,TEXT(首页!$B$4,"yyyy-mm"))>0,"显示",""))) | AO67: 6001 | AP67: 主营业务收入 | AQ67: 收入 | AR67: 贷 | AS67: 启用 | AU67: 主营业务收入 | AV67: 经营活动流入 | AW67: 客户/部门
W68: =IF(P68="","",IF(SUMIFS(期初数据!$S$5:$S$14,期初数据!$P$5:$P$14,P68)+SUMIFS(采购录入!$G$4:$G$203,采购录入!$D$4:$D$203,P68,采购录入!$A$4:$A$203,"<="&EOMONTH(首页!$B$4,0))-SUMIFS(销售录入!$G$4:$G$203,销售录入!$D$4:$D$203,P68,销售录入!$A$4:$A$203,"<="&EOMONTH(首页!$B$4,0))<>0,"显示",IF(COUNTIFS(采购录入!$D$4:$D$203,P68,采购录入!$B$4:$B$203,TEXT(首页!$B$4,"yyyy-mm"))+COUNTIFS(销售录入!$D$4:$D$203,P68,销售录入!$B$4:$B$203,TEXT(首页!$B$4,"yyyy-mm"))>0,"显示",""))) | AO68: 6051 | AP68: 其他业务收入 | AQ68: 收入 | AR68: 贷 | AS68: 启用 | AU68: 其他业务收入 | AV68: 经营活动流入 | AW68: 客户/部门
W69: =IF(P69="","",IF(SUMIFS(期初数据!$S$5:$S$14,期初数据!$P$5:$P$14,P69)+SUMIFS(采购录入!$G$4:$G$203,采购录入!$D$4:$D$203,P69,采购录入!$A$4:$A$203,"<="&EOMONTH(首页!$B$4,0))-SUMIFS(销售录入!$G$4:$G$203,销售录入!$D$4:$D$203,P69,销售录入!$A$4:$A$203,"<="&EOMONTH(首页!$B$4,0))<>0,"显示",IF(COUNTIFS(采购录入!$D$4:$D$203,P69,采购录入!$B$4:$B$203,TEXT(首页!$B$4,"yyyy-mm"))+COUNTIFS(销售录入!$D$4:$D$203,P69,销售录入!$B$4:$B$203,TEXT(首页!$B$4,"yyyy-mm"))>0,"显示",""))) | AO69: 6101 | AP69: 公允价值变动损益 | AQ69: 收入 | AR69: 贷 | AS69: 启用 | AU69: 公允价值变动收益 | AV69: 非现金/资产负债 | AW69: 无
W70: =IF(P70="","",IF(SUMIFS(期初数据!$S$5:$S$14,期初数据!$P$5:$P$14,P70)+SUMIFS(采购录入!$G$4:$G$203,采购录入!$D$4:$D$203,P70,采购录入!$A$4:$A$203,"<="&EOMONTH(首页!$B$4,0))-SUMIFS(销售录入!$G$4:$G$203,销售录入!$D$4:$D$203,P70,销售录入!$A$4:$A$203,"<="&EOMONTH(首页!$B$4,0))<>0,"显示",IF(COUNTIFS(采购录入!$D$4:$D$203,P70,采购录入!$B$4:$B$203,TEXT(首页!$B$4,"yyyy-mm"))+COUNTIFS(销售录入!$D$4:$D$203,P70,销售录入!$B$4:$B$203,TEXT(首页!$B$4,"yyyy-mm"))>0,"显示",""))) | AO70: 6111 | AP70: 投资收益 | AQ70: 收入 | AR70: 贷 | AS70: 启用 | AU70: 投资收益 | AV70: 非现金/资产负债 | AW70: 无
W71: =IF(P71="","",IF(SUMIFS(期初数据!$S$5:$S$14,期初数据!$P$5:$P$14,P71)+SUMIFS(采购录入!$G$4:$G$203,采购录入!$D$4:$D$203,P71,采购录入!$A$4:$A$203,"<="&EOMONTH(首页!$B$4,0))-SUMIFS(销售录入!$G$4:$G$203,销售录入!$D$4:$D$203,P71,销售录入!$A$4:$A$203,"<="&EOMONTH(首页!$B$4,0))<>0,"显示",IF(COUNTIFS(采购录入!$D$4:$D$203,P71,采购录入!$B$4:$B$203,TEXT(首页!$B$4,"yyyy-mm"))+COUNTIFS(销售录入!$D$4:$D$203,P71,销售录入!$B$4:$B$203,TEXT(首页!$B$4,"yyyy-mm"))>0,"显示",""))) | AO71: 6115 | AP71: 资产处置收益 | AQ71: 收入 | AR71: 贷 | AS71: 启用 | AU71: 资产处置收益 | AV71: 非现金/资产负债 | AW71: 无
W72: =IF(P72="","",IF(SUMIFS(期初数据!$S$5:$S$14,期初数据!$P$5:$P$14,P72)+SUMIFS(采购录入!$G$4:$G$203,采购录入!$D$4:$D$203,P72,采购录入!$A$4:$A$203,"<="&EOMONTH(首页!$B$4,0))-SUMIFS(销售录入!$G$4:$G$203,销售录入!$D$4:$D$203,P72,销售录入!$A$4:$A$203,"<="&EOMONTH(首页!$B$4,0))<>0,"显示",IF(COUNTIFS(采购录入!$D$4:$D$203,P72,采购录入!$B$4:$B$203,TEXT(首页!$B$4,"yyyy-mm"))+COUNTIFS(销售录入!$D$4:$D$203,P72,销售录入!$B$4:$B$203,TEXT(首页!$B$4,"yyyy-mm"))>0,"显示",""))) | AO72: 6117 | AP72: 其他收益 | AQ72: 收入 | AR72: 贷 | AS72: 启用 | AU72: 其他收益 | AV72: 非现金/资产负债 | AW72: 无
W73: =IF(P73="","",IF(SUMIFS(期初数据!$S$5:$S$14,期初数据!$P$5:$P$14,P73)+SUMIFS(采购录入!$G$4:$G$203,采购录入!$D$4:$D$203,P73,采购录入!$A$4:$A$203,"<="&EOMONTH(首页!$B$4,0))-SUMIFS(销售录入!$G$4:$G$203,销售录入!$D$4:$D$203,P73,销售录入!$A$4:$A$203,"<="&EOMONTH(首页!$B$4,0))<>0,"显示",IF(COUNTIFS(采购录入!$D$4:$D$203,P73,采购录入!$B$4:$B$203,TEXT(首页!$B$4,"yyyy-mm"))+COUNTIFS(销售录入!$D$4:$D$203,P73,销售录入!$B$4:$B$203,TEXT(首页!$B$4,"yyyy-mm"))>0,"显示",""))) | AO73: 6301 | AP73: 营业外收入 | AQ73: 收入 | AR73: 贷 | AS73: 启用 | AU73: 营业外收入 | AV73: 经营活动流入 | AW73: 无
W74: =IF(P74="","",IF(SUMIFS(期初数据!$S$5:$S$14,期初数据!$P$5:$P$14,P74)+SUMIFS(采购录入!$G$4:$G$203,采购录入!$D$4:$D$203,P74,采购录入!$A$4:$A$203,"<="&EOMONTH(首页!$B$4,0))-SUMIFS(销售录入!$G$4:$G$203,销售录入!$D$4:$D$203,P74,销售录入!$A$4:$A$203,"<="&EOMONTH(首页!$B$4,0))<>0,"显示",IF(COUNTIFS(采购录入!$D$4:$D$203,P74,采购录入!$B$4:$B$203,TEXT(首页!$B$4,"yyyy-mm"))+COUNTIFS(销售录入!$D$4:$D$203,P74,销售录入!$B$4:$B$203,TEXT(首页!$B$4,"yyyy-mm"))>0,"显示",""))) | AO74: 6401 | AP74: 主营业务成本 | AQ74: 费用 | AR74: 借 | AS74: 启用 | AU74: 主营业务成本 | AV74: 经营活动流出 | AW74: 商品/部门
W75: =IF(P75="","",IF(SUMIFS(期初数据!$S$5:$S$14,期初数据!$P$5:$P$14,P75)+SUMIFS(采购录入!$G$4:$G$203,采购录入!$D$4:$D$203,P75,采购录入!$A$4:$A$203,"<="&EOMONTH(首页!$B$4,0))-SUMIFS(销售录入!$G$4:$G$203,销售录入!$D$4:$D$203,P75,销售录入!$A$4:$A$203,"<="&EOMONTH(首页!$B$4,0))<>0,"显示",IF(COUNTIFS(采购录入!$D$4:$D$203,P75,采购录入!$B$4:$B$203,TEXT(首页!$B$4,"yyyy-mm"))+COUNTIFS(销售录入!$D$4:$D$203,P75,销售录入!$B$4:$B$203,TEXT(首页!$B$4,"yyyy-mm"))>0,"显示",""))) | AO75: 6402 | AP75: 其他业务成本 | AQ75: 费用 | AR75: 借 | AS75: 启用 | AU75: 其他业务成本 | AV75: 经营活动流出 | AW75: 无
W76: =IF(P76="","",IF(SUMIFS(期初数据!$S$5:$S$14,期初数据!$P$5:$P$14,P76)+SUMIFS(采购录入!$G$4:$G$203,采购录入!$D$4:$D$203,P76,采购录入!$A$4:$A$203,"<="&EOMONTH(首页!$B$4,0))-SUMIFS(销售录入!$G$4:$G$203,销售录入!$D$4:$D$203,P76,销售录入!$A$4:$A$203,"<="&EOMONTH(首页!$B$4,0))<>0,"显示",IF(COUNTIFS(采购录入!$D$4:$D$203,P76,采购录入!$B$4:$B$203,TEXT(首页!$B$4,"yyyy-mm"))+COUNTIFS(销售录入!$D$4:$D$203,P76,销售录入!$B$4:$B$203,TEXT(首页!$B$4,"yyyy-mm"))>0,"显示",""))) | AO76: 6403 | AP76: 税金及附加 | AQ76: 费用 | AR76: 借 | AS76: 启用 | AU76: 税金及附加 | AV76: 经营活动流出 | AW76: 无
W77: =IF(P77="","",IF(SUMIFS(期初数据!$S$5:$S$14,期初数据!$P$5:$P$14,P77)+SUMIFS(采购录入!$G$4:$G$203,采购录入!$D$4:$D$203,P77,采购录入!$A$4:$A$203,"<="&EOMONTH(首页!$B$4,0))-SUMIFS(销售录入!$G$4:$G$203,销售录入!$D$4:$D$203,P77,销售录入!$A$4:$A$203,"<="&EOMONTH(首页!$B$4,0))<>0,"显示",IF(COUNTIFS(采购录入!$D$4:$D$203,P77,采购录入!$B$4:$B$203,TEXT(首页!$B$4,"yyyy-mm"))+COUNTIFS(销售录入!$D$4:$D$203,P77,销售录入!$B$4:$B$203,TEXT(首页!$B$4,"yyyy-mm"))>0,"显示",""))) | AO77: 6601 | AP77: 销售费用 | AQ77: 费用 | AR77: 借 | AS77: 启用 | AU77: 销售费用 | AV77: 经营活动流出 | AW77: 部门/员工
W78: =IF(P78="","",IF(SUMIFS(期初数据!$S$5:$S$14,期初数据!$P$5:$P$14,P78)+SUMIFS(采购录入!$G$4:$G$203,采购录入!$D$4:$D$203,P78,采购录入!$A$4:$A$203,"<="&EOMONTH(首页!$B$4,0))-SUMIFS(销售录入!$G$4:$G$203,销售录入!$D$4:$D$203,P78,销售录入!$A$4:$A$203,"<="&EOMONTH(首页!$B$4,0))<>0,"显示",IF(COUNTIFS(采购录入!$D$4:$D$203,P78,采购录入!$B$4:$B$203,TEXT(首页!$B$4,"yyyy-mm"))+COUNTIFS(销售录入!$D$4:$D$203,P78,销售录入!$B$4:$B$203,TEXT(首页!$B$4,"yyyy-mm"))>0,"显示",""))) | AO78: 6602 | AP78: 管理费用 | AQ78: 费用 | AR78: 借 | AS78: 启用 | AU78: 管理费用 | AV78: 经营活动流出 | AW78: 部门/员工
... W84: =IF(P84="","",IF(SUMIFS(期初数据!$S$5:$S$14,期初数据!$P$5:$P$14,P84)+SUMIFS(采购录入!$G$4:$G$203,采购录入!$D$4:$D$203,P84,采购录入!$A$4:$A$203,"<="&EOMONTH(首页!$B$4,0))-SUMIFS(销售录入!$G$4:$G$203,销售录入!$D$4:$D$203,P84,销售录入!$A$4:$A$203,"<="&EOMONTH(首页!$B$4,0))<>0,"显示",IF(COUNTIFS(采购录入!$D$4:$D$203,P84,采购录入!$B$4:$B$203,TEXT(首页!$B$4,"yyyy-mm"))+COUNTIFS(销售录入!$D$4:$D$203,P84,销售录入!$B$4:$B$203,TEXT(首页!$B$4,"yyyy-mm"))>0,"显示",""))) | AO84: 6801 | AP84: 所得税费用 | AQ84: 费用 | AR84: 借 | AS84: 启用 | AU84: 所得税费用 | AV84: 经营活动流出 | AW84: 无
W85: =IF(P85="","",IF(SUMIFS(期初数据!$S$5:$S$14,期初数据!$P$5:$P$14,P85)+SUMIFS(采购录入!$G$4:$G$203,采购录入!$D$4:$D$203,P85,采购录入!$A$4:$A$203,"<="&EOMONTH(首页!$B$4,0))-SUMIFS(销售录入!$G$4:$G$203,销售录入!$D$4:$D$203,P85,销售录入!$A$4:$A$203,"<="&EOMONTH(首页!$B$4,0))<>0,"显示",IF(COUNTIFS(采购录入!$D$4:$D$203,P85,采购录入!$B$4:$B$203,TEXT(首页!$B$4,"yyyy-mm"))+COUNTIFS(销售录入!$D$4:$D$203,P85,销售录入!$B$4:$B$203,TEXT(首页!$B$4,"yyyy-mm"))>0,"显示","")))
W86: =IF(P86="","",IF(SUMIFS(期初数据!$S$5:$S$14,期初数据!$P$5:$P$14,P86)+SUMIFS(采购录入!$G$4:$G$203,采购录入!$D$4:$D$203,P86,采购录入!$A$4:$A$203,"<="&EOMONTH(首页!$B$4,0))-SUMIFS(销售录入!$G$4:$G$203,销售录入!$D$4:$D$203,P86,销售录入!$A$4:$A$203,"<="&EOMONTH(首页!$B$4,0))<>0,"显示",IF(COUNTIFS(采购录入!$D$4:$D$203,P86,采购录入!$B$4:$B$203,TEXT(首页!$B$4,"yyyy-mm"))+COUNTIFS(销售录入!$D$4:$D$203,P86,销售录入!$B$4:$B$203,TEXT(首页!$B$4,"yyyy-mm"))>0,"显示","")))
W87: =IF(P87="","",IF(SUMIFS(期初数据!$S$5:$S$14,期初数据!$P$5:$P$14,P87)+SUMIFS(采购录入!$G$4:$G$203,采购录入!$D$4:$D$203,P87,采购录入!$A$4:$A$203,"<="&EOMONTH(首页!$B$4,0))-SUMIFS(销售录入!$G$4:$G$203,销售录入!$D$4:$D$203,P87,销售录入!$A$4:$A$203,"<="&EOMONTH(首页!$B$4,0))<>0,"显示",IF(COUNTIFS(采购录入!$D$4:$D$203,P87,采购录入!$B$4:$B$203,TEXT(首页!$B$4,"yyyy-mm"))+COUNTIFS(销售录入!$D$4:$D$203,P87,销售录入!$B$4:$B$203,TEXT(首页!$B$4,"yyyy-mm"))>0,"显示","")))
W88: =IF(P88="","",IF(SUMIFS(期初数据!$S$5:$S$14,期初数据!$P$5:$P$14,P88)+SUMIFS(采购录入!$G$4:$G$203,采购录入!$D$4:$D$203,P88,采购录入!$A$4:$A$203,"<="&EOMONTH(首页!$B$4,0))-SUMIFS(销售录入!$G$4:$G$203,销售录入!$D$4:$D$203,P88,销售录入!$A$4:$A$203,"<="&EOMONTH(首页!$B$4,0))<>0,"显示",IF(COUNTIFS(采购录入!$D$4:$D$203,P88,采购录入!$B$4:$B$203,TEXT(首页!$B$4,"yyyy-mm"))+COUNTIFS(销售录入!$D$4:$D$203,P88,销售录入!$B$4:$B$203,TEXT(首页!$B$4,"yyyy-mm"))>0,"显示","")))
W89: =IF(P89="","",IF(SUMIFS(期初数据!$S$5:$S$14,期初数据!$P$5:$P$14,P89)+SUMIFS(采购录入!$G$4:$G$203,采购录入!$D$4:$D$203,P89,采购录入!$A$4:$A$203,"<="&EOMONTH(首页!$B$4,0))-SUMIFS(销售录入!$G$4:$G$203,销售录入!$D$4:$D$203,P89,销售录入!$A$4:$A$203,"<="&EOMONTH(首页!$B$4,0))<>0,"显示",IF(COUNTIFS(采购录入!$D$4:$D$203,P89,采购录入!$B$4:$B$203,TEXT(首页!$B$4,"yyyy-mm"))+COUNTIFS(销售录入!$D$4:$D$203,P89,销售录入!$B$4:$B$203,TEXT(首页!$B$4,"yyyy-mm"))>0,"显示","")))
W90: =IF(P90="","",IF(SUMIFS(期初数据!$S$5:$S$14,期初数据!$P$5:$P$14,P90)+SUMIFS(采购录入!$G$4:$G$203,采购录入!$D$4:$D$203,P90,采购录入!$A$4:$A$203,"<="&EOMONTH(首页!$B$4,0))-SUMIFS(销售录入!$G$4:$G$203,销售录入!$D$4:$D$203,P90,销售录入!$A$4:$A$203,"<="&EOMONTH(首页!$B$4,0))<>0,"显示",IF(COUNTIFS(采购录入!$D$4:$D$203,P90,采购录入!$B$4:$B$203,TEXT(首页!$B$4,"yyyy-mm"))+COUNTIFS(销售录入!$D$4:$D$203,P90,销售录入!$B$4:$B$203,TEXT(首页!$B$4,"yyyy-mm"))>0,"显示","")))
W91: =IF(P91="","",IF(SUMIFS(期初数据!$S$5:$S$14,期初数据!$P$5:$P$14,P91)+SUMIFS(采购录入!$G$4:$G$203,采购录入!$D$4:$D$203,P91,采购录入!$A$4:$A$203,"<="&EOMONTH(首页!$B$4,0))-SUMIFS(销售录入!$G$4:$G$203,销售录入!$D$4:$D$203,P91,销售录入!$A$4:$A$203,"<="&EOMONTH(首页!$B$4,0))<>0,"显示",IF(COUNTIFS(采购录入!$D$4:$D$203,P91,采购录入!$B$4:$B$203,TEXT(首页!$B$4,"yyyy-mm"))+COUNTIFS(销售录入!$D$4:$D$203,P91,销售录入!$B$4:$B$203,TEXT(首页!$B$4,"yyyy-mm"))>0,"显示","")))
W92: =IF(P92="","",IF(SUMIFS(期初数据!$S$5:$S$14,期初数据!$P$5:$P$14,P92)+SUMIFS(采购录入!$G$4:$G$203,采购录入!$D$4:$D$203,P92,采购录入!$A$4:$A$203,"<="&EOMONTH(首页!$B$4,0))-SUMIFS(销售录入!$G$4:$G$203,销售录入!$D$4:$D$203,P92,销售录入!$A$4:$A$203,"<="&EOMONTH(首页!$B$4,0))<>0,"显示",IF(COUNTIFS(采购录入!$D$4:$D$203,P92,采购录入!$B$4:$B$203,TEXT(首页!$B$4,"yyyy-mm"))+COUNTIFS(销售录入!$D$4:$D$203,P92,销售录入!$B$4:$B$203,TEXT(首页!$B$4,"yyyy-mm"))>0,"显示","")))
W93: =IF(P93="","",IF(SUMIFS(期初数据!$S$5:$S$14,期初数据!$P$5:$P$14,P93)+SUMIFS(采购录入!$G$4:$G$203,采购录入!$D$4:$D$203,P93,采购录入!$A$4:$A$203,"<="&EOMONTH(首页!$B$4,0))-SUMIFS(销售录入!$G$4:$G$203,销售录入!$D$4:$D$203,P93,销售录入!$A$4:$A$203,"<="&EOMONTH(首页!$B$4,0))<>0,"显示",IF(COUNTIFS(采购录入!$D$4:$D$203,P93,采购录入!$B$4:$B$203,TEXT(首页!$B$4,"yyyy-mm"))+COUNTIFS(销售录入!$D$4:$D$203,P93,销售录入!$B$4:$B$203,TEXT(首页!$B$4,"yyyy-mm"))>0,"显示","")))
W94: =IF(P94="","",IF(SUMIFS(期初数据!$S$5:$S$14,期初数据!$P$5:$P$14,P94)+SUMIFS(采购录入!$G$4:$G$203,采购录入!$D$4:$D$203,P94,采购录入!$A$4:$A$203,"<="&EOMONTH(首页!$B$4,0))-SUMIFS(销售录入!$G$4:$G$203,销售录入!$D$4:$D$203,P94,销售录入!$A$4:$A$203,"<="&EOMONTH(首页!$B$4,0))<>0,"显示",IF(COUNTIFS(采购录入!$D$4:$D$203,P94,采购录入!$B$4:$B$203,TEXT(首页!$B$4,"yyyy-mm"))+COUNTIFS(销售录入!$D$4:$D$203,P94,销售录入!$B$4:$B$203,TEXT(首页!$B$4,"yyyy-mm"))>0,"显示","")))
W95: =IF(P95="","",IF(SUMIFS(期初数据!$S$5:$S$14,期初数据!$P$5:$P$14,P95)+SUMIFS(采购录入!$G$4:$G$203,采购录入!$D$4:$D$203,P95,采购录入!$A$4:$A$203,"<="&EOMONTH(首页!$B$4,0))-SUMIFS(销售录入!$G$4:$G$203,销售录入!$D$4:$D$203,P95,销售录入!$A$4:$A$203,"<="&EOMONTH(首页!$B$4,0))<>0,"显示",IF(COUNTIFS(采购录入!$D$4:$D$203,P95,采购录入!$B$4:$B$203,TEXT(首页!$B$4,"yyyy-mm"))+COUNTIFS(销售录入!$D$4:$D$203,P95,销售录入!$B$4:$B$203,TEXT(首页!$B$4,"yyyy-mm"))>0,"显示","")))
W96: =IF(P96="","",IF(SUMIFS(期初数据!$S$5:$S$14,期初数据!$P$5:$P$14,P96)+SUMIFS(采购录入!$G$4:$G$203,采购录入!$D$4:$D$203,P96,采购录入!$A$4:$A$203,"<="&EOMONTH(首页!$B$4,0))-SUMIFS(销售录入!$G$4:$G$203,销售录入!$D$4:$D$203,P96,销售录入!$A$4:$A$203,"<="&EOMONTH(首页!$B$4,0))<>0,"显示",IF(COUNTIFS(采购录入!$D$4:$D$203,P96,采购录入!$B$4:$B$203,TEXT(首页!$B$4,"yyyy-mm"))+COUNTIFS(销售录入!$D$4:$D$203,P96,销售录入!$B$4:$B$203,TEXT(首页!$B$4,"yyyy-mm"))>0,"显示","")))
... W204: =IF(P204="","",IF(SUMIFS(期初数据!$S$5:$S$14,期初数据!$P$5:$P$14,P204)+SUMIFS(采购录入!$G$4:$G$203,采购录入!$D$4:$D$203,P204,采购录入!$A$4:$A$203,"<="&EOMONTH(首页!$B$4,0))-SUMIFS(销售录入!$G$4:$G$203,销售录入!$D$4:$D$203,P204,销售录入!$A$4:$A$203,"<="&EOMONTH(首页!$B$4,0))<>0,"显示",IF(COUNTIFS(采购录入!$D$4:$D$203,P204,采购录入!$B$4:$B$203,TEXT(首页!$B$4,"yyyy-mm"))+COUNTIFS(销售录入!$D$4:$D$203,P204,销售录入!$B$4:$B$203,TEXT(首页!$B$4,"yyyy-mm"))>0,"显示","")))

Sheet 期初数据
A1: 期初数据（年初只录一次）
A3: 资金期初 | F3: 应收期初 | K3: 应付期初 | P3: 库存期初 | X3: 会计科目期初
A4: 账户 | B4: 类型 | C4: 期初余额 | D4: 备注 | F4: 客户 | G4: 原业务日期 | H4: 期初应收 | I4: 备注 | K4: 供应商 | L4: 原业务日期 | M4: 期初应付 | N4: 备注 | P4: 商品 | Q4: 规格 | R4: 单位 | S4: 期初数量 | T4: 期初单位成本 | U4: 期初金额 | V4: 备注 | X4: 科目编码 | Y4: 科目名称 | Z4: 科目类别 | AA4: 方向 | AB4: 期初借方 | AC4: 期初贷方 | AD4: 备注
A5: 现金 | B5: 现金类 | C5: 50000 | D5: 演示 | F5: 客户A | G5: 46023 | H5: 15000 | I5: 演示 | K5: 供应商A | L5: 46023 | M5: 25000 | N5: 演示 | P5: A配件 | Q5: A-01 | R5: 个 | S5: 100 | T5: 100 | U5: 10000 | V5: 演示 | X5: 1001 | Y5: 库存现金 | Z5: 资产 | AA5: 借 | AB5: 55000 | AC5: 0 | AD5: 演示
A6: 工商银行 | B6: 银行类 | C6: 300000 | D6: 演示 | F6: 客户B | G6: 46023 | H6: 12000 | I6: 演示 | K6: 供应商B | L6: 46023 | M6: 22000 | N6: 演示 | P6: B配件 | Q6: B-02 | R6: 个 | S6: 80 | T6: 125 | U6: 10000 | V6: 演示 | X6: 1002 | Y6: 银行存款 | Z6: 资产 | AA6: 借 | AB6: 805000 | AC6: 0 | AD6: 演示
A7: 农业银行 | B7: 银行类 | C7: 200000 | D7: 演示 | F7: 客户C | G7: 46023 | H7: 18000 | I7: 演示 | K7: 供应商C | L7: 46023 | M7: 18000 | N7: 演示 | P7: C配件 | Q7: C-03 | R7: 个 | S7: 200 | T7: 50 | U7: 10000 | V7: 演示 | X7: 1012 | Y7: 其他货币资金 | Z7: 资产 | AA7: 借 | AB7: 0 | AC7: 0
A8: 建设银行 | B8: 银行类 | C8: 120000 | D8: 演示 | F8: 客户D | G8: 46023 | H8: 8000 | I8: 演示 | K8: 供应商D | L8: 46023 | M8: 30000 | N8: 演示 | P8: D配件 | Q8: D-04 | R8: 个 | S8: 50 | T8: 200 | U8: 10000 | V8: 演示 | X8: 1101 | Y8: 交易性金融资产 | Z8: 资产 | AA8: 借 | AB8: 0 | AC8: 0
A9: 招商银行 | B9: 银行类 | C9: 80000 | D9: 演示 | F9: 客户E | G9: 46023 | H9: 25000 | I9: 演示 | K9: 供应商E | L9: 46023 | M9: 15000 | N9: 演示 | P9: E配件 | Q9: E-05 | R9: 个 | S9: 400 | T9: 25 | U9: 10000 | V9: 演示 | X9: 1121 | Y9: 应收票据 | Z9: 资产 | AA9: 借 | AB9: 0 | AC9: 0
A10: 中国银行 | B10: 银行类 | C10: 60000 | D10: 演示 | F10: 客户F | G10: 46023 | H10: 16000 | I10: 演示 | K10: 供应商F | L10: 46023 | M10: 24000 | N10: 演示 | P10: F配件 | Q10: F-06 | R10: 个 | S10: 100 | T10: 80 | U10: 8000 | V10: 演示 | X10: 1122 | Y10: 应收账款 | Z10: 资产 | AA10: 借 | AB10: 158000 | AC10: 0 | AD10: 演示
A11: 微信 | B11: 电子账户 | C11: 20000 | D11: 演示 | F11: 客户G | G11: 46023 | H11: 14000 | I11: 演示 | K11: 供应商G | L11: 46023 | M11: 20000 | N11: 演示 | P11: G配件 | Q11: G-07 | R11: 个 | S11: 120 | T11: 75 | U11: 9000 | V11: 演示 | X11: 1123 | Y11: 预付账款 | Z11: 资产 | AA11: 借 | AB11: 0 | AC11: 0
A12: 支付宝 | B12: 电子账户 | C12: 15000 | D12: 演示 | F12: 客户H | G12: 46023 | H12: 20000 | I12: 演示 | K12: 供应商H | L12: 46023 | M12: 16000 | N12: 演示 | P12: H配件 | Q12: H-08 | R12: 个 | S12: 60 | T12: 150 | U12: 9000 | V12: 演示 | X12: 1131 | Y12: 应收股利 | Z12: 资产 | AA12: 借 | AB12: 0 | AC12: 0
A13: 备用金 | B13: 现金类 | C13: 5000 | D13: 演示 | F13: 客户I | G13: 46023 | H13: 10000 | I13: 演示 | K13: 供应商I | L13: 46023 | M13: 18000 | N13: 演示 | P13: I配件 | Q13: I-09 | R13: 个 | S13: 300 | T13: 30 | U13: 9000 | V13: 演示 | X13: 1132 | Y13: 应收利息 | Z13: 资产 | AA13: 借 | AB13: 0 | AC13: 0
A14: 其他账户 | B14: 银行类 | C14: 10000 | D14: 演示 | F14: 客户J | G14: 46023 | H14: 20000 | I14: 演示 | K14: 供应商J | L14: 46023 | M14: 22000 | N14: 演示 | P14: J配件 | Q14: J-10 | R14: 个 | S14: 250 | T14: 60 | U14: 15000 | V14: 演示 | X14: 1221 | Y14: 其他应收款 | Z14: 资产 | AA14: 借 | AB14: 0 | AC14: 0
X15: 1231 | Y15: 坏账准备 | Z15: 资产 | AA15: 贷 | AB15: 0 | AC15: 0
X16: 1401 | Y16: 材料采购 | Z16: 资产 | AA16: 借 | AB16: 0 | AC16: 0
X17: 1402 | Y17: 在途物资 | Z17: 资产 | AA17: 借 | AB17: 0 | AC17: 0
X18: 1403 | Y18: 原材料 | Z18: 资产 | AA18: 借 | AB18: 0 | AC18: 0
X19: 1404 | Y19: 材料成本差异 | Z19: 资产 | AA19: 借 | AB19: 0 | AC19: 0
X20: 1405 | Y20: 库存商品 | Z20: 资产 | AA20: 借 | AB20: 100000 | AC20: 0 | AD20: 演示
X21: 1406 | Y21: 发出商品 | Z21: 资产 | AA21: 借 | AB21: 0 | AC21: 0
X22: 1407 | Y22: 商品进销差价 | Z22: 资产 | AA22: 贷 | AB22: 0 | AC22: 0
X23: 1408 | Y23: 委托加工物资 | Z23: 资产 | AA23: 借 | AB23: 0 | AC23: 0
X24: 1411 | Y24: 周转材料 | Z24: 资产 | AA24: 借 | AB24: 0 | AC24: 0
X25: 1471 | Y25: 存货跌价准备 | Z25: 资产 | AA25: 贷 | AB25: 0 | AC25: 0
X26: 1501 | Y26: 债权投资 | Z26: 资产 | AA26: 借 | AB26: 0 | AC26: 0
X27: 1511 | Y27: 长期股权投资 | Z27: 资产 | AA27: 借 | AB27: 0 | AC27: 0
X28: 1521 | Y28: 投资性房地产 | Z28: 资产 | AA28: 借 | AB28: 0 | AC28: 0
X29: 1601 | Y29: 固定资产 | Z29: 资产 | AA29: 借 | AB29: 600000 | AC29: 0 | AD29: 演示
X30: 1602 | Y30: 累计折旧 | Z30: 资产 | AA30: 贷 | AB30: 0 | AC30: 0
X31: 1604 | Y31: 在建工程 | Z31: 资产 | AA31: 借 | AB31: 0 | AC31: 0
X32: 1605 | Y32: 工程物资 | Z32: 资产 | AA32: 借 | AB32: 0 | AC32: 0
X33: 1606 | Y33: 固定资产清理 | Z33: 资产 | AA33: 借 | AB33: 0 | AC33: 0
X34: 1701 | Y34: 无形资产 | Z34: 资产 | AA34: 借 | AB34: 0 | AC34: 0
X35: 1702 | Y35: 累计摊销 | Z35: 资产 | AA35: 贷 | AB35: 0 | AC35: 0
X36: 1801 | Y36: 长期待摊费用 | Z36: 资产 | AA36: 借 | AB36: 0 | AC36: 0
X37: 1811 | Y37: 递延所得税资产 | Z37: 资产 | AA37: 借 | AB37: 0 | AC37: 0
X38: 1901 | Y38: 待处理财产损溢 | Z38: 资产 | AA38: 借 | AB38: 0 | AC38: 0
X39: 1905 | Y39: 其他流动资产 | Z39: 资产 | AA39: 借 | AB39: 0 | AC39: 0
X40: 1906 | Y40: 其他非流动资产 | Z40: 资产 | AA40: 借 | AB40: 0 | AC40: 0
X41: 2001 | Y41: 短期借款 | Z41: 负债 | AA41: 贷 | AB41: 0 | AC41: 300000 | AD41: 演示
X42: 2201 | Y42: 应付票据 | Z42: 负债 | AA42: 贷 | AB42: 0 | AC42: 0
X43: 2202 | Y43: 应付账款 | Z43: 负债 | AA43: 贷 | AB43: 0 | AC43: 210000 | AD43: 演示
X44: 2203 | Y44: 预收账款 | Z44: 负债 | AA44: 贷 | AB44: 0 | AC44: 0
X45: 2206 | Y45: 合同负债 | Z45: 负债 | AA45: 贷 | AB45: 0 | AC45: 0
X46: 2211 | Y46: 应付职工薪酬 | Z46: 负债 | AA46: 贷 | AB46: 0 | AC46: 30000 | AD46: 演示
X47: 2221 | Y47: 应交税费 | Z47: 负债 | AA47: 贷 | AB47: 0 | AC47: 0
X48: 2231 | Y48: 应付利息 | Z48: 负债 | AA48: 贷 | AB48: 0 | AC48: 0
X49: 2232 | Y49: 应付股利 | Z49: 负债 | AA49: 贷 | AB49: 0 | AC49: 0
X50: 2241 | Y50: 其他应付款 | Z50: 负债 | AA50: 贷 | AB50: 0 | AC50: 0
X51: 2301 | Y51: 一年内到期的非流动负债 | Z51: 负债 | AA51: 贷 | AB51: 0 | AC51: 0
X52: 2401 | Y52: 递延收益 | Z52: 负债 | AA52: 贷 | AB52: 0 | AC52: 0
X53: 2491 | Y53: 其他流动负债 | Z53: 负债 | AA53: 贷 | AB53: 0 | AC53: 0
X54: 2501 | Y54: 长期借款 | Z54: 负债 | AA54: 贷 | AB54: 0 | AC54: 0
X55: 2701 | Y55: 长期应付款 | Z55: 负债 | AA55: 贷 | AB55: 0 | AC55: 0
X56: 2901 | Y56: 递延所得税负债 | Z56: 负债 | AA56: 贷 | AB56: 0 | AC56: 0
X57: 2902 | Y57: 其他非流动负债 | Z57: 负债 | AA57: 贷 | AB57: 0 | AC57: 0
X58: 4001 | Y58: 实收资本 | Z58: 权益 | AA58: 贷 | AB58: 0 | AC58: 1000000 | AD58: 演示
X59: 4002 | Y59: 资本公积 | Z59: 权益 | AA59: 贷 | AB59: 0 | AC59: 0
X60: 4101 | Y60: 盈余公积 | Z60: 权益 | AA60: 贷 | AB60: 0 | AC60: 0
X61: 4103 | Y61: 本年利润 | Z61: 权益 | AA61: 贷 | AB61: 0 | AC61: 0
X62: 4104 | Y62: 利润分配 | Z62: 权益 | AA62: 贷 | AB62: 0 | AC62: 178000 | AD62: 演示
X63: 5001 | Y63: 生产成本 | Z63: 成本 | AA63: 借 | AB63: 0 | AC63: 0
X64: 5101 | Y64: 制造费用 | Z64: 成本 | AA64: 借 | AB64: 0 | AC64: 0
X65: 5201 | Y65: 劳务成本 | Z65: 成本 | AA65: 借 | AB65: 0 | AC65: 0
X66: 5301 | Y66: 研发支出 | Z66: 成本 | AA66: 借 | AB66: 0 | AC66: 0
X67: 6001 | Y67: 主营业务收入 | Z67: 收入 | AA67: 贷 | AB67: 0 | AC67: 0
X68: 6051 | Y68: 其他业务收入 | Z68: 收入 | AA68: 贷 | AB68: 0 | AC68: 0
X69: 6101 | Y69: 公允价值变动损益 | Z69: 收入 | AA69: 贷 | AB69: 0 | AC69: 0
X70: 6111 | Y70: 投资收益 | Z70: 收入 | AA70: 贷 | AB70: 0 | AC70: 0
X71: 6115 | Y71: 资产处置收益 | Z71: 收入 | AA71: 贷 | AB71: 0 | AC71: 0
X72: 6117 | Y72: 其他收益 | Z72: 收入 | AA72: 贷 | AB72: 0 | AC72: 0
X73: 6301 | Y73: 营业外收入 | Z73: 收入 | AA73: 贷 | AB73: 0 | AC73: 0
X74: 6401 | Y74: 主营业务成本 | Z74: 费用 | AA74: 借 | AB74: 0 | AC74: 0
... X84: 6801 | Y84: 所得税费用 | Z84: 费用 | AA84: 借 | AB84: 0 | AC84: 0

Sheet 资金流水
A1: 资金流水（唯一实际收付款录入口）
A2: 所有实际到账、付款、费用、工资、账户转账只在这里登记；销售、采购不要重复登记收入/成本。
A3: 日期 | B3: 月份 | C3: 收支类型 | D3: 收支科目 | E3: 账户 | F3: 往来单位/转入账户 | G3: 部门 | H3: 员工 | I3: 摘要 | J3: 收入金额 | K3: 支出金额 | L3: 账户余额 | M3: 资金科目 | N3: 转入资金科目 | O3: 借方科目 | P3: 贷方科目 | Q3: 发生金额 | R3: 月结检查
A4: 46175 | B4: =IF(A4="","",TEXT(A4,"yyyy-mm")) -> 2026-06 | C4: =IF(D4="","",IFERROR(INDEX(基础资料!$AJ$5:$AJ$204,MATCH(D4,基础资料!$AK$5:$AK$204,0)),"")) -> 收入 | D4: 客户回款 | E4: 工商银行 | F4: 客户A | G4: 销售部 | H4: 张伟 | I4: 收到客户A货款 | J4: 12000 | K4: 0 | L4: =IF(OR(A4="",E4=""),"",SUMIFS(期初数据!$C$5:$C$14,期初数据!$A$5:$A$14,E4)+SUMIFS($J$4:J4,$E$4:E4,E4)-SUMIFS($K$4:K4,$E$4:E4,E4)+SUMIFS($K$4:K4,$F$4:F4,E4,$D$4:D4,"账户转账")) -> 312000 | M4: =IF(E4="","",IFERROR(VLOOKUP(E4,基础资料!$A$5:$C$204,3,FALSE),"")) -> 1002 | N4: =IF(D4="账户转账",IFERROR(VLOOKUP(F4,基础资料!$A$5:$C$204,3,FALSE),""),"") | O4: =IF(D4="","",IF(D4="账户转账",N4,IFERROR(IF(VLOOKUP(D4,基础资料!$AK$5:$AM$204,2,FALSE)="1002",M4,VLOOKUP(D4,基础资料!$AK$5:$AM$204,2,FALSE)),""))) -> 1002 | P4: =IF(D4="","",IF(D4="账户转账",M4,IFERROR(IF(VLOOKUP(D4,基础资料!$AK$5:$AM$204,3,FALSE)="1002",M4,VLOOKUP(D4,基础资料!$AK$5:$AM$204,3,FALSE)),""))) -> 1122 | Q4: =IF(A4="","",N(J4)+N(K4)) -> 12000 | R4: =IF(A4="","","可录入") -> 可录入
A5: 46176 | B5: =IF(A5="","",TEXT(A5,"yyyy-mm")) -> 2026-06 | C5: =IF(D5="","",IFERROR(INDEX(基础资料!$AJ$5:$AJ$204,MATCH(D5,基础资料!$AK$5:$AK$204,0)),"")) -> 支出 | D5: 供应商付款 | E5: 工商银行 | F5: 供应商A | G5: 采购部 | H5: 王强 | I5: 支付供应商A货款 | J5: 0 | K5: 10000 | L5: =IF(OR(A5="",E5=""),"",SUMIFS(期初数据!$C$5:$C$14,期初数据!$A$5:$A$14,E5)+SUMIFS($J$4:J5,$E$4:E5,E5)-SUMIFS($K$4:K5,$E$4:E5,E5)+SUMIFS($K$4:K5,$F$4:F5,E5,$D$4:D5,"账户转账")) -> 302000 | M5: =IF(E5="","",IFERROR(VLOOKUP(E5,基础资料!$A$5:$C$204,3,FALSE),"")) -> 1002 | N5: =IF(D5="账户转账",IFERROR(VLOOKUP(F5,基础资料!$A$5:$C$204,3,FALSE),""),"") | O5: =IF(D5="","",IF(D5="账户转账",N5,IFERROR(IF(VLOOKUP(D5,基础资料!$AK$5:$AM$204,2,FALSE)="1002",M5,VLOOKUP(D5,基础资料!$AK$5:$AM$204,2,FALSE)),""))) -> 2202 | P5: =IF(D5="","",IF(D5="账户转账",M5,IFERROR(IF(VLOOKUP(D5,基础资料!$AK$5:$AM$204,3,FALSE)="1002",M5,VLOOKUP(D5,基础资料!$AK$5:$AM$204,3,FALSE)),""))) -> 1002 | Q5: =IF(A5="","",N(J5)+N(K5)) -> 10000 | R5: =IF(A5="","","可录入") -> 可录入
A6: 46178 | B6: =IF(A6="","",TEXT(A6,"yyyy-mm")) -> 2026-06 | C6: =IF(D6="","",IFERROR(INDEX(基础资料!$AJ$5:$AJ$204,MATCH(D6,基础资料!$AK$5:$AK$204,0)),"")) -> 支出 | D6: 办公费 | E6: 微信 | G6: 行政部 | H6: 陈敏 | I6: 购买办公用品 | J6: 0 | K6: 800 | L6: =IF(OR(A6="",E6=""),"",SUMIFS(期初数据!$C$5:$C$14,期初数据!$A$5:$A$14,E6)+SUMIFS($J$4:J6,$E$4:E6,E6)-SUMIFS($K$4:K6,$E$4:E6,E6)+SUMIFS($K$4:K6,$F$4:F6,E6,$D$4:D6,"账户转账")) -> 19200 | M6: =IF(E6="","",IFERROR(VLOOKUP(E6,基础资料!$A$5:$C$204,3,FALSE),"")) -> 1002 | N6: =IF(D6="账户转账",IFERROR(VLOOKUP(F6,基础资料!$A$5:$C$204,3,FALSE),""),"") | O6: =IF(D6="","",IF(D6="账户转账",N6,IFERROR(IF(VLOOKUP(D6,基础资料!$AK$5:$AM$204,2,FALSE)="1002",M6,VLOOKUP(D6,基础资料!$AK$5:$AM$204,2,FALSE)),""))) -> 6602 | P6: =IF(D6="","",IF(D6="账户转账",M6,IFERROR(IF(VLOOKUP(D6,基础资料!$AK$5:$AM$204,3,FALSE)="1002",M6,VLOOKUP(D6,基础资料!$AK$5:$AM$204,3,FALSE)),""))) -> 1002 | Q6: =IF(A6="","",N(J6)+N(K6)) -> 800 | R6: =IF(A6="","","可录入") -> 可录入
A7: 46181 | B7: =IF(A7="","",TEXT(A7,"yyyy-mm")) -> 2026-06 | C7: =IF(D7="","",IFERROR(INDEX(基础资料!$AJ$5:$AJ$204,MATCH(D7,基础资料!$AK$5:$AK$204,0)),"")) -> 支出 | D7: 房租 | E7: 农业银行 | G7: 行政部 | H7: 陈敏 | I7: 支付6月房租 | J7: 0 | K7: 5000 | L7: =IF(OR(A7="",E7=""),"",SUMIFS(期初数据!$C$5:$C$14,期初数据!$A$5:$A$14,E7)+SUMIFS($J$4:J7,$E$4:E7,E7)-SUMIFS($K$4:K7,$E$4:E7,E7)+SUMIFS($K$4:K7,$F$4:F7,E7,$D$4:D7,"账户转账")) -> 195000 | M7: =IF(E7="","",IFERROR(VLOOKUP(E7,基础资料!$A$5:$C$204,3,FALSE),"")) -> 1002 | N7: =IF(D7="账户转账",IFERROR(VLOOKUP(F7,基础资料!$A$5:$C$204,3,FALSE),""),"") | O7: =IF(D7="","",IF(D7="账户转账",N7,IFERROR(IF(VLOOKUP(D7,基础资料!$AK$5:$AM$204,2,FALSE)="1002",M7,VLOOKUP(D7,基础资料!$AK$5:$AM$204,2,FALSE)),""))) -> 6602 | P7: =IF(D7="","",IF(D7="账户转账",M7,IFERROR(IF(VLOOKUP(D7,基础资料!$AK$5:$AM$204,3,FALSE)="1002",M7,VLOOKUP(D7,基础资料!$AK$5:$AM$204,3,FALSE)),""))) -> 1002 | Q7: =IF(A7="","",N(J7)+N(K7)) -> 5000 | R7: =IF(A7="","","可录入") -> 可录入
A8: 46183 | B8: =IF(A8="","",TEXT(A8,"yyyy-mm")) -> 2026-06 | C8: =IF(D8="","",IFERROR(INDEX(基础资料!$AJ$5:$AJ$204,MATCH(D8,基础资料!$AK$5:$AK$204,0)),"")) -> 支出 | D8: 水电费 | E8: 工商银行 | G8: 行政部 | H8: 陈敏 | I8: 支付水电费 | J8: 0 | K8: 1800 | L8: =IF(OR(A8="",E8=""),"",SUMIFS(期初数据!$C$5:$C$14,期初数据!$A$5:$A$14,E8)+SUMIFS($J$4:J8,$E$4:E8,E8)-SUMIFS($K$4:K8,$E$4:E8,E8)+SUMIFS($K$4:K8,$F$4:F8,E8,$D$4:D8,"账户转账")) -> 300200 | M8: =IF(E8="","",IFERROR(VLOOKUP(E8,基础资料!$A$5:$C$204,3,FALSE),"")) -> 1002 | N8: =IF(D8="账户转账",IFERROR(VLOOKUP(F8,基础资料!$A$5:$C$204,3,FALSE),""),"") | O8: =IF(D8="","",IF(D8="账户转账",N8,IFERROR(IF(VLOOKUP(D8,基础资料!$AK$5:$AM$204,2,FALSE)="1002",M8,VLOOKUP(D8,基础资料!$AK$5:$AM$204,2,FALSE)),""))) -> 6602 | P8: =IF(D8="","",IF(D8="账户转账",M8,IFERROR(IF(VLOOKUP(D8,基础资料!$AK$5:$AM$204,3,FALSE)="1002",M8,VLOOKUP(D8,基础资料!$AK$5:$AM$204,3,FALSE)),""))) -> 1002 | Q8: =IF(A8="","",N(J8)+N(K8)) -> 1800 | R8: =IF(A8="","","可录入") -> 可录入
A9: 46185 | B9: =IF(A9="","",TEXT(A9,"yyyy-mm")) -> 2026-06 | C9: =IF(D9="","",IFERROR(INDEX(基础资料!$AJ$5:$AJ$204,MATCH(D9,基础资料!$AK$5:$AK$204,0)),"")) -> 支出 | D9: 广告费 | E9: 支付宝 | G9: 电商部 | H9: 孙悦 | I9: 广告投放 | J9: 0 | K9: 2000 | L9: =IF(OR(A9="",E9=""),"",SUMIFS(期初数据!$C$5:$C$14,期初数据!$A$5:$A$14,E9)+SUMIFS($J$4:J9,$E$4:E9,E9)-SUMIFS($K$4:K9,$E$4:E9,E9)+SUMIFS($K$4:K9,$F$4:F9,E9,$D$4:D9,"账户转账")) -> 13000 | M9: =IF(E9="","",IFERROR(VLOOKUP(E9,基础资料!$A$5:$C$204,3,FALSE),"")) -> 1002 | N9: =IF(D9="账户转账",IFERROR(VLOOKUP(F9,基础资料!$A$5:$C$204,3,FALSE),""),"") | O9: =IF(D9="","",IF(D9="账户转账",N9,IFERROR(IF(VLOOKUP(D9,基础资料!$AK$5:$AM$204,2,FALSE)="1002",M9,VLOOKUP(D9,基础资料!$AK$5:$AM$204,2,FALSE)),""))) -> 6601 | P9: =IF(D9="","",IF(D9="账户转账",M9,IFERROR(IF(VLOOKUP(D9,基础资料!$AK$5:$AM$204,3,FALSE)="1002",M9,VLOOKUP(D9,基础资料!$AK$5:$AM$204,3,FALSE)),""))) -> 1002 | Q9: =IF(A9="","",N(J9)+N(K9)) -> 2000 | R9: =IF(A9="","","可录入") -> 可录入
A10: 46188 | B10: =IF(A10="","",TEXT(A10,"yyyy-mm")) -> 2026-06 | C10: =IF(D10="","",IFERROR(INDEX(基础资料!$AJ$5:$AJ$204,MATCH(D10,基础资料!$AK$5:$AK$204,0)),"")) -> 支出 | D10: 工资 | E10: 工商银行 | G10: 财务部 | H10: 赵静 | I10: 支付工资 | J10: 0 | K10: 15000 | L10: =IF(OR(A10="",E10=""),"",SUMIFS(期初数据!$C$5:$C$14,期初数据!$A$5:$A$14,E10)+SUMIFS($J$4:J10,$E$4:E10,E10)-SUMIFS($K$4:K10,$E$4:E10,E10)+SUMIFS($K$4:K10,$F$4:F10,E10,$D$4:D10,"账户转账")) -> 285200 | M10: =IF(E10="","",IFERROR(VLOOKUP(E10,基础资料!$A$5:$C$204,3,FALSE),"")) -> 1002 | N10: =IF(D10="账户转账",IFERROR(VLOOKUP(F10,基础资料!$A$5:$C$204,3,FALSE),""),"") | O10: =IF(D10="","",IF(D10="账户转账",N10,IFERROR(IF(VLOOKUP(D10,基础资料!$AK$5:$AM$204,2,FALSE)="1002",M10,VLOOKUP(D10,基础资料!$AK$5:$AM$204,2,FALSE)),""))) -> 6602 | P10: =IF(D10="","",IF(D10="账户转账",M10,IFERROR(IF(VLOOKUP(D10,基础资料!$AK$5:$AM$204,3,FALSE)="1002",M10,VLOOKUP(D10,基础资料!$AK$5:$AM$204,3,FALSE)),""))) -> 1002 | Q10: =IF(A10="","",N(J10)+N(K10)) -> 15000 | R10: =IF(A10="","","可录入") -> 可录入
A11: 46191 | B11: =IF(A11="","",TEXT(A11,"yyyy-mm")) -> 2026-06 | C11: =IF(D11="","",IFERROR(INDEX(基础资料!$AJ$5:$AJ$204,MATCH(D11,基础资料!$AK$5:$AK$204,0)),"")) -> 收入 | D11: 服务收入 | E11: 中国银行 | G11: 管理层 | H11: 郑欣 | I11: 服务收入 | J11: 3200 | K11: 0 | L11: =IF(OR(A11="",E11=""),"",SUMIFS(期初数据!$C$5:$C$14,期初数据!$A$5:$A$14,E11)+SUMIFS($J$4:J11,$E$4:E11,E11)-SUMIFS($K$4:K11,$E$4:E11,E11)+SUMIFS($K$4:K11,$F$4:F11,E11,$D$4:D11,"账户转账")) -> 63200 | M11: =IF(E11="","",IFERROR(VLOOKUP(E11,基础资料!$A$5:$C$204,3,FALSE),"")) -> 1002 | N11: =IF(D11="账户转账",IFERROR(VLOOKUP(F11,基础资料!$A$5:$C$204,3,FALSE),""),"") | O11: =IF(D11="","",IF(D11="账户转账",N11,IFERROR(IF(VLOOKUP(D11,基础资料!$AK$5:$AM$204,2,FALSE)="1002",M11,VLOOKUP(D11,基础资料!$AK$5:$AM$204,2,FALSE)),""))) -> 1002 | P11: =IF(D11="","",IF(D11="账户转账",M11,IFERROR(IF(VLOOKUP(D11,基础资料!$AK$5:$AM$204,3,FALSE)="1002",M11,VLOOKUP(D11,基础资料!$AK$5:$AM$204,3,FALSE)),""))) -> 6051 | Q11: =IF(A11="","",N(J11)+N(K11)) -> 3200 | R11: =IF(A11="","","可录入") -> 可录入
A12: 46193 | B12: =IF(A12="","",TEXT(A12,"yyyy-mm")) -> 2026-06 | C12: =IF(D12="","",IFERROR(INDEX(基础资料!$AJ$5:$AJ$204,MATCH(D12,基础资料!$AK$5:$AK$204,0)),"")) -> 转账 | D12: 账户转账 | E12: 工商银行 | F12: 建设银行 | G12: 财务部 | H12: 赵静 | I12: 账户转账 | J12: 0 | K12: 20000 | L12: =IF(OR(A12="",E12=""),"",SUMIFS(期初数据!$C$5:$C$14,期初数据!$A$5:$A$14,E12)+SUMIFS($J$4:J12,$E$4:E12,E12)-SUMIFS($K$4:K12,$E$4:E12,E12)+SUMIFS($K$4:K12,$F$4:F12,E12,$D$4:D12,"账户转账")) -> 265200 | M12: =IF(E12="","",IFERROR(VLOOKUP(E12,基础资料!$A$5:$C$204,3,FALSE),"")) -> 1002 | N12: =IF(D12="账户转账",IFERROR(VLOOKUP(F12,基础资料!$A$5:$C$204,3,FALSE),""),"") -> 1002 | O12: =IF(D12="","",IF(D12="账户转账",N12,IFERROR(IF(VLOOKUP(D12,基础资料!$AK$5:$AM$204,2,FALSE)="1002",M12,VLOOKUP(D12,基础资料!$AK$5:$AM$204,2,FALSE)),""))) -> 1002 | P12: =IF(D12="","",IF(D12="账户转账",M12,IFERROR(IF(VLOOKUP(D12,基础资料!$AK$5:$AM$204,3,FALSE)="1002",M12,VLOOKUP(D12,基础资料!$AK$5:$AM$204,3,FALSE)),""))) -> 1002 | Q12: =IF(A12="","",N(J12)+N(K12)) -> 20000 | R12: =IF(A12="","","可录入") -> 可录入
A13: 46198 | B13: =IF(A13="","",TEXT(A13,"yyyy-mm")) -> 2026-06 | C13: =IF(D13="","",IFERROR(INDEX(基础资料!$AJ$5:$AJ$204,MATCH(D13,基础资料!$AK$5:$AK$204,0)),"")) -> 收入 | D13: 客户回款 | E13: 建设银行 | F13: 客户B | G13: 销售部 | H13: 李娜 | I13: 收到客户B货款 | J13: 8000 | K13: 0 | L13: =IF(OR(A13="",E13=""),"",SUMIFS(期初数据!$C$5:$C$14,期初数据!$A$5:$A$14,E13)+SUMIFS($J$4:J13,$E$4:E13,E13)-SUMIFS($K$4:K13,$E$4:E13,E13)+SUMIFS($K$4:K13,$F$4:F13,E13,$D$4:D13,"账户转账")) -> 148000 | M13: =IF(E13="","",IFERROR(VLOOKUP(E13,基础资料!$A$5:$C$204,3,FALSE),"")) -> 1002 | N13: =IF(D13="账户转账",IFERROR(VLOOKUP(F13,基础资料!$A$5:$C$204,3,FALSE),""),"") | O13: =IF(D13="","",IF(D13="账户转账",N13,IFERROR(IF(VLOOKUP(D13,基础资料!$AK$5:$AM$204,2,FALSE)="1002",M13,VLOOKUP(D13,基础资料!$AK$5:$AM$204,2,FALSE)),""))) -> 1002 | P13: =IF(D13="","",IF(D13="账户转账",M13,IFERROR(IF(VLOOKUP(D13,基础资料!$AK$5:$AM$204,3,FALSE)="1002",M13,VLOOKUP(D13,基础资料!$AK$5:$AM$204,3,FALSE)),""))) -> 1122 | Q13: =IF(A13="","",N(J13)+N(K13)) -> 8000 | R13: =IF(A13="","","可录入") -> 可录入
B14: =IF(A14="","",TEXT(A14,"yyyy-mm")) | C14: =IF(D14="","",IFERROR(INDEX(基础资料!$AJ$5:$AJ$204,MATCH(D14,基础资料!$AK$5:$AK$204,0)),"")) | L14: =IF(OR(A14="",E14=""),"",SUMIFS(期初数据!$C$5:$C$14,期初数据!$A$5:$A$14,E14)+SUMIFS($J$4:J14,$E$4:E14,E14)-SUMIFS($K$4:K14,$E$4:E14,E14)+SUMIFS($K$4:K14,$F$4:F14,E14,$D$4:D14,"账户转账")) | M14: =IF(E14="","",IFERROR(VLOOKUP(E14,基础资料!$A$5:$C$204,3,FALSE),"")) | N14: =IF(D14="账户转账",IFERROR(VLOOKUP(F14,基础资料!$A$5:$C$204,3,FALSE),""),"") | O14: =IF(D14="","",IF(D14="账户转账",N14,IFERROR(IF(VLOOKUP(D14,基础资料!$AK$5:$AM$204,2,FALSE)="1002",M14,VLOOKUP(D14,基础资料!$AK$5:$AM$204,2,FALSE)),""))) | P14: =IF(D14="","",IF(D14="账户转账",M14,IFERROR(IF(VLOOKUP(D14,基础资料!$AK$5:$AM$204,3,FALSE)="1002",M14,VLOOKUP(D14,基础资料!$AK$5:$AM$204,3,FALSE)),""))) | Q14: =IF(A14="","",N(J14)+N(K14)) | R14: =IF(A14="","","可录入")
B15: =IF(A15="","",TEXT(A15,"yyyy-mm")) | C15: =IF(D15="","",IFERROR(INDEX(基础资料!$AJ$5:$AJ$204,MATCH(D15,基础资料!$AK$5:$AK$204,0)),"")) | L15: =IF(OR(A15="",E15=""),"",SUMIFS(期初数据!$C$5:$C$14,期初数据!$A$5:$A$14,E15)+SUMIFS($J$4:J15,$E$4:E15,E15)-SUMIFS($K$4:K15,$E$4:E15,E15)+SUMIFS($K$4:K15,$F$4:F15,E15,$D$4:D15,"账户转账")) | M15: =IF(E15="","",IFERROR(VLOOKUP(E15,基础资料!$A$5:$C$204,3,FALSE),"")) | N15: =IF(D15="账户转账",IFERROR(VLOOKUP(F15,基础资料!$A$5:$C$204,3,FALSE),""),"") | O15: =IF(D15="","",IF(D15="账户转账",N15,IFERROR(IF(VLOOKUP(D15,基础资料!$AK$5:$AM$204,2,FALSE)="1002",M15,VLOOKUP(D15,基础资料!$AK$5:$AM$204,2,FALSE)),""))) | P15: =IF(D15="","",IF(D15="账户转账",M15,IFERROR(IF(VLOOKUP(D15,基础资料!$AK$5:$AM$204,3,FALSE)="1002",M15,VLOOKUP(D15,基础资料!$AK$5:$AM$204,3,FALSE)),""))) | Q15: =IF(A15="","",N(J15)+N(K15)) | R15: =IF(A15="","","可录入")
B16: =IF(A16="","",TEXT(A16,"yyyy-mm")) | C16: =IF(D16="","",IFERROR(INDEX(基础资料!$AJ$5:$AJ$204,MATCH(D16,基础资料!$AK$5:$AK$204,0)),"")) | L16: =IF(OR(A16="",E16=""),"",SUMIFS(期初数据!$C$5:$C$14,期初数据!$A$5:$A$14,E16)+SUMIFS($J$4:J16,$E$4:E16,E16)-SUMIFS($K$4:K16,$E$4:E16,E16)+SUMIFS($K$4:K16,$F$4:F16,E16,$D$4:D16,"账户转账")) | M16: =IF(E16="","",IFERROR(VLOOKUP(E16,基础资料!$A$5:$C$204,3,FALSE),"")) | N16: =IF(D16="账户转账",IFERROR(VLOOKUP(F16,基础资料!$A$5:$C$204,3,FALSE),""),"") | O16: =IF(D16="","",IF(D16="账户转账",N16,IFERROR(IF(VLOOKUP(D16,基础资料!$AK$5:$AM$204,2,FALSE)="1002",M16,VLOOKUP(D16,基础资料!$AK$5:$AM$204,2,FALSE)),""))) | P16: =IF(D16="","",IF(D16="账户转账",M16,IFERROR(IF(VLOOKUP(D16,基础资料!$AK$5:$AM$204,3,FALSE)="1002",M16,VLOOKUP(D16,基础资料!$AK$5:$AM$204,3,FALSE)),""))) | Q16: =IF(A16="","",N(J16)+N(K16)) | R16: =IF(A16="","","可录入")
B17: =IF(A17="","",TEXT(A17,"yyyy-mm")) | C17: =IF(D17="","",IFERROR(INDEX(基础资料!$AJ$5:$AJ$204,MATCH(D17,基础资料!$AK$5:$AK$204,0)),"")) | L17: =IF(OR(A17="",E17=""),"",SUMIFS(期初数据!$C$5:$C$14,期初数据!$A$5:$A$14,E17)+SUMIFS($J$4:J17,$E$4:E17,E17)-SUMIFS($K$4:K17,$E$4:E17,E17)+SUMIFS($K$4:K17,$F$4:F17,E17,$D$4:D17,"账户转账")) | M17: =IF(E17="","",IFERROR(VLOOKUP(E17,基础资料!$A$5:$C$204,3,FALSE),"")) | N17: =IF(D17="账户转账",IFERROR(VLOOKUP(F17,基础资料!$A$5:$C$204,3,FALSE),""),"") | O17: =IF(D17="","",IF(D17="账户转账",N17,IFERROR(IF(VLOOKUP(D17,基础资料!$AK$5:$AM$204,2,FALSE)="1002",M17,VLOOKUP(D17,基础资料!$AK$5:$AM$204,2,FALSE)),""))) | P17: =IF(D17="","",IF(D17="账户转账",M17,IFERROR(IF(VLOOKUP(D17,基础资料!$AK$5:$AM$204,3,FALSE)="1002",M17,VLOOKUP(D17,基础资料!$AK$5:$AM$204,3,FALSE)),""))) | Q17: =IF(A17="","",N(J17)+N(K17)) | R17: =IF(A17="","","可录入")
B18: =IF(A18="","",TEXT(A18,"yyyy-mm")) | C18: =IF(D18="","",IFERROR(INDEX(基础资料!$AJ$5:$AJ$204,MATCH(D18,基础资料!$AK$5:$AK$204,0)),"")) | L18: =IF(OR(A18="",E18=""),"",SUMIFS(期初数据!$C$5:$C$14,期初数据!$A$5:$A$14,E18)+SUMIFS($J$4:J18,$E$4:E18,E18)-SUMIFS($K$4:K18,$E$4:E18,E18)+SUMIFS($K$4:K18,$F$4:F18,E18,$D$4:D18,"账户转账")) | M18: =IF(E18="","",IFERROR(VLOOKUP(E18,基础资料!$A$5:$C$204,3,FALSE),"")) | N18: =IF(D18="账户转账",IFERROR(VLOOKUP(F18,基础资料!$A$5:$C$204,3,FALSE),""),"") | O18: =IF(D18="","",IF(D18="账户转账",N18,IFERROR(IF(VLOOKUP(D18,基础资料!$AK$5:$AM$204,2,FALSE)="1002",M18,VLOOKUP(D18,基础资料!$AK$5:$AM$204,2,FALSE)),""))) | P18: =IF(D18="","",IF(D18="账户转账",M18,IFERROR(IF(VLOOKUP(D18,基础资料!$AK$5:$AM$204,3,FALSE)="1002",M18,VLOOKUP(D18,基础资料!$AK$5:$AM$204,3,FALSE)),""))) | Q18: =IF(A18="","",N(J18)+N(K18)) | R18: =IF(A18="","","可录入")
B19: =IF(A19="","",TEXT(A19,"yyyy-mm")) | C19: =IF(D19="","",IFERROR(INDEX(基础资料!$AJ$5:$AJ$204,MATCH(D19,基础资料!$AK$5:$AK$204,0)),"")) | L19: =IF(OR(A19="",E19=""),"",SUMIFS(期初数据!$C$5:$C$14,期初数据!$A$5:$A$14,E19)+SUMIFS($J$4:J19,$E$4:E19,E19)-SUMIFS($K$4:K19,$E$4:E19,E19)+SUMIFS($K$4:K19,$F$4:F19,E19,$D$4:D19,"账户转账")) | M19: =IF(E19="","",IFERROR(VLOOKUP(E19,基础资料!$A$5:$C$204,3,FALSE),"")) | N19: =IF(D19="账户转账",IFERROR(VLOOKUP(F19,基础资料!$A$5:$C$204,3,FALSE),""),"") | O19: =IF(D19="","",IF(D19="账户转账",N19,IFERROR(IF(VLOOKUP(D19,基础资料!$AK$5:$AM$204,2,FALSE)="1002",M19,VLOOKUP(D19,基础资料!$AK$5:$AM$204,2,FALSE)),""))) | P19: =IF(D19="","",IF(D19="账户转账",M19,IFERROR(IF(VLOOKUP(D19,基础资料!$AK$5:$AM$204,3,FALSE)="1002",M19,VLOOKUP(D19,基础资料!$AK$5:$AM$204,3,FALSE)),""))) | Q19: =IF(A19="","",N(J19)+N(K19)) | R19: =IF(A19="","","可录入")
B20: =IF(A20="","",TEXT(A20,"yyyy-mm")) | C20: =IF(D20="","",IFERROR(INDEX(基础资料!$AJ$5:$AJ$204,MATCH(D20,基础资料!$AK$5:$AK$204,0)),"")) | L20: =IF(OR(A20="",E20=""),"",SUMIFS(期初数据!$C$5:$C$14,期初数据!$A$5:$A$14,E20)+SUMIFS($J$4:J20,$E$4:E20,E20)-SUMIFS($K$4:K20,$E$4:E20,E20)+SUMIFS($K$4:K20,$F$4:F20,E20,$D$4:D20,"账户转账")) | M20: =IF(E20="","",IFERROR(VLOOKUP(E20,基础资料!$A$5:$C$204,3,FALSE),"")) | N20: =IF(D20="账户转账",IFERROR(VLOOKUP(F20,基础资料!$A$5:$C$204,3,FALSE),""),"") | O20: =IF(D20="","",IF(D20="账户转账",N20,IFERROR(IF(VLOOKUP(D20,基础资料!$AK$5:$AM$204,2,FALSE)="1002",M20,VLOOKUP(D20,基础资料!$AK$5:$AM$204,2,FALSE)),""))) | P20: =IF(D20="","",IF(D20="账户转账",M20,IFERROR(IF(VLOOKUP(D20,基础资料!$AK$5:$AM$204,3,FALSE)="1002",M20,VLOOKUP(D20,基础资料!$AK$5:$AM$204,3,FALSE)),""))) | Q20: =IF(A20="","",N(J20)+N(K20)) | R20: =IF(A20="","","可录入")
B21: =IF(A21="","",TEXT(A21,"yyyy-mm")) | C21: =IF(D21="","",IFERROR(INDEX(基础资料!$AJ$5:$AJ$204,MATCH(D21,基础资料!$AK$5:$AK$204,0)),"")) | L21: =IF(OR(A21="",E21=""),"",SUMIFS(期初数据!$C$5:$C$14,期初数据!$A$5:$A$14,E21)+SUMIFS($J$4:J21,$E$4:E21,E21)-SUMIFS($K$4:K21,$E$4:E21,E21)+SUMIFS($K$4:K21,$F$4:F21,E21,$D$4:D21,"账户转账")) | M21: =IF(E21="","",IFERROR(VLOOKUP(E21,基础资料!$A$5:$C$204,3,FALSE),"")) | N21: =IF(D21="账户转账",IFERROR(VLOOKUP(F21,基础资料!$A$5:$C$204,3,FALSE),""),"") | O21: =IF(D21="","",IF(D21="账户转账",N21,IFERROR(IF(VLOOKUP(D21,基础资料!$AK$5:$AM$204,2,FALSE)="1002",M21,VLOOKUP(D21,基础资料!$AK$5:$AM$204,2,FALSE)),""))) | P21: =IF(D21="","",IF(D21="账户转账",M21,IFERROR(IF(VLOOKUP(D21,基础资料!$AK$5:$AM$204,3,FALSE)="1002",M21,VLOOKUP(D21,基础资料!$AK$5:$AM$204,3,FALSE)),""))) | Q21: =IF(A21="","",N(J21)+N(K21)) | R21: =IF(A21="","","可录入")
B22: =IF(A22="","",TEXT(A22,"yyyy-mm")) | C22: =IF(D22="","",IFERROR(INDEX(基础资料!$AJ$5:$AJ$204,MATCH(D22,基础资料!$AK$5:$AK$204,0)),"")) | L22: =IF(OR(A22="",E22=""),"",SUMIFS(期初数据!$C$5:$C$14,期初数据!$A$5:$A$14,E22)+SUMIFS($J$4:J22,$E$4:E22,E22)-SUMIFS($K$4:K22,$E$4:E22,E22)+SUMIFS($K$4:K22,$F$4:F22,E22,$D$4:D22,"账户转账")) | M22: =IF(E22="","",IFERROR(VLOOKUP(E22,基础资料!$A$5:$C$204,3,FALSE),"")) | N22: =IF(D22="账户转账",IFERROR(VLOOKUP(F22,基础资料!$A$5:$C$204,3,FALSE),""),"") | O22: =IF(D22="","",IF(D22="账户转账",N22,IFERROR(IF(VLOOKUP(D22,基础资料!$AK$5:$AM$204,2,FALSE)="1002",M22,VLOOKUP(D22,基础资料!$AK$5:$AM$204,2,FALSE)),""))) | P22: =IF(D22="","",IF(D22="账户转账",M22,IFERROR(IF(VLOOKUP(D22,基础资料!$AK$5:$AM$204,3,FALSE)="1002",M22,VLOOKUP(D22,基础资料!$AK$5:$AM$204,3,FALSE)),""))) | Q22: =IF(A22="","",N(J22)+N(K22)) | R22: =IF(A22="","","可录入")
B23: =IF(A23="","",TEXT(A23,"yyyy-mm")) | C23: =IF(D23="","",IFERROR(INDEX(基础资料!$AJ$5:$AJ$204,MATCH(D23,基础资料!$AK$5:$AK$204,0)),"")) | L23: =IF(OR(A23="",E23=""),"",SUMIFS(期初数据!$C$5:$C$14,期初数据!$A$5:$A$14,E23)+SUMIFS($J$4:J23,$E$4:E23,E23)-SUMIFS($K$4:K23,$E$4:E23,E23)+SUMIFS($K$4:K23,$F$4:F23,E23,$D$4:D23,"账户转账")) | M23: =IF(E23="","",IFERROR(VLOOKUP(E23,基础资料!$A$5:$C$204,3,FALSE),"")) | N23: =IF(D23="账户转账",IFERROR(VLOOKUP(F23,基础资料!$A$5:$C$204,3,FALSE),""),"") | O23: =IF(D23="","",IF(D23="账户转账",N23,IFERROR(IF(VLOOKUP(D23,基础资料!$AK$5:$AM$204,2,FALSE)="1002",M23,VLOOKUP(D23,基础资料!$AK$5:$AM$204,2,FALSE)),""))) | P23: =IF(D23="","",IF(D23="账户转账",M23,IFERROR(IF(VLOOKUP(D23,基础资料!$AK$5:$AM$204,3,FALSE)="1002",M23,VLOOKUP(D23,基础资料!$AK$5:$AM$204,3,FALSE)),""))) | Q23: =IF(A23="","",N(J23)+N(K23)) | R23: =IF(A23="","","可录入")
B24: =IF(A24="","",TEXT(A24,"yyyy-mm")) | C24: =IF(D24="","",IFERROR(INDEX(基础资料!$AJ$5:$AJ$204,MATCH(D24,基础资料!$AK$5:$AK$204,0)),"")) | L24: =IF(OR(A24="",E24=""),"",SUMIFS(期初数据!$C$5:$C$14,期初数据!$A$5:$A$14,E24)+SUMIFS($J$4:J24,$E$4:E24,E24)-SUMIFS($K$4:K24,$E$4:E24,E24)+SUMIFS($K$4:K24,$F$4:F24,E24,$D$4:D24,"账户转账")) | M24: =IF(E24="","",IFERROR(VLOOKUP(E24,基础资料!$A$5:$C$204,3,FALSE),"")) | N24: =IF(D24="账户转账",IFERROR(VLOOKUP(F24,基础资料!$A$5:$C$204,3,FALSE),""),"") | O24: =IF(D24="","",IF(D24="账户转账",N24,IFERROR(IF(VLOOKUP(D24,基础资料!$AK$5:$AM$204,2,FALSE)="1002",M24,VLOOKUP(D24,基础资料!$AK$5:$AM$204,2,FALSE)),""))) | P24: =IF(D24="","",IF(D24="账户转账",M24,IFERROR(IF(VLOOKUP(D24,基础资料!$AK$5:$AM$204,3,FALSE)="1002",M24,VLOOKUP(D24,基础资料!$AK$5:$AM$204,3,FALSE)),""))) | Q24: =IF(A24="","",N(J24)+N(K24)) | R24: =IF(A24="","","可录入")
B25: =IF(A25="","",TEXT(A25,"yyyy-mm")) | C25: =IF(D25="","",IFERROR(INDEX(基础资料!$AJ$5:$AJ$204,MATCH(D25,基础资料!$AK$5:$AK$204,0)),"")) | L25: =IF(OR(A25="",E25=""),"",SUMIFS(期初数据!$C$5:$C$14,期初数据!$A$5:$A$14,E25)+SUMIFS($J$4:J25,$E$4:E25,E25)-SUMIFS($K$4:K25,$E$4:E25,E25)+SUMIFS($K$4:K25,$F$4:F25,E25,$D$4:D25,"账户转账")) | M25: =IF(E25="","",IFERROR(VLOOKUP(E25,基础资料!$A$5:$C$204,3,FALSE),"")) | N25: =IF(D25="账户转账",IFERROR(VLOOKUP(F25,基础资料!$A$5:$C$204,3,FALSE),""),"") | O25: =IF(D25="","",IF(D25="账户转账",N25,IFERROR(IF(VLOOKUP(D25,基础资料!$AK$5:$AM$204,2,FALSE)="1002",M25,VLOOKUP(D25,基础资料!$AK$5:$AM$204,2,FALSE)),""))) | P25: =IF(D25="","",IF(D25="账户转账",M25,IFERROR(IF(VLOOKUP(D25,基础资料!$AK$5:$AM$204,3,FALSE)="1002",M25,VLOOKUP(D25,基础资料!$AK$5:$AM$204,3,FALSE)),""))) | Q25: =IF(A25="","",N(J25)+N(K25)) | R25: =IF(A25="","","可录入")
... B203: =IF(A203="","",TEXT(A203,"yyyy-mm")) | C203: =IF(D203="","",IFERROR(INDEX(基础资料!$AJ$5:$AJ$204,MATCH(D203,基础资料!$AK$5:$AK$204,0)),"")) | L203: =IF(OR(A203="",E203=""),"",SUMIFS(期初数据!$C$5:$C$14,期初数据!$A$5:$A$14,E203)+SUMIFS($J$4:J203,$E$4:E203,E203)-SUMIFS($K$4:K203,$E$4:E203,E203)+SUMIFS($K$4:K203,$F$4:F203,E203,$D$4:D203,"账户转账")) | M203: =IF(E203="","",IFERROR(VLOOKUP(E203,基础资料!$A$5:$C$204,3,FALSE),"")) | N203: =IF(D203="账户转账",IFERROR(VLOOKUP(F203,基础资料!$A$5:$C$204,3,FALSE),""),"") | O203: =IF(D203="","",IF(D203="账户转账",N203,IFERROR(IF(VLOOKUP(D203,基础资料!$AK$5:$AM$204,2,FALSE)="1002",M203,VLOOKUP(D203,基础资料!$AK$5:$AM$204,2,FALSE)),""))) | P203: =IF(D203="","",IF(D203="账户转账",M203,IFERROR(IF(VLOOKUP(D203,基础资料!$AK$5:$AM$204,3,FALSE)="1002",M203,VLOOKUP(D203,基础资料!$AK$5:$AM$204,3,FALSE)),""))) | Q203: =IF(A203="","",N(J203)+N(K203)) | R203: =IF(A203="","","可录入")

Sheet 销售录入
A1: 销售录入（销售业务唯一入口）
A2: 客户销售只在这里登记；回款只在资金流水登记。销售单价每笔手工填写。
A3: 日期 | B3: 月份 | C3: 客户 | D3: 商品 | E3: 规格 | F3: 单位 | G3: 数量 | H3: 销售单价（手工） | I3: 销售金额 | J3: 成本单价 | K3: 销售成本 | L3: 到期日 | M3: 部门 | N3: 业务员 | O3: 备注 | P3: 月结检查 | Q3: 毛利金额
A4: 46174 | B4: =IF(A4="","",TEXT(A4,"yyyy-mm")) -> 2026-06 | C4: 客户A | D4: A配件 | E4: =IF(D4="","",IFERROR(VLOOKUP(D4,基础资料!$P$5:$R$204,2,FALSE),"")) -> A-01 | F4: =IF(D4="","",IFERROR(VLOOKUP(D4,基础资料!$P$5:$R$204,3,FALSE),"")) -> 个 | G4: 20 | H4: 200 | I4: =IF(OR(G4="",H4=""),"",G4*H4) -> 4000 | J4: =IF(D4="","",IFERROR(VLOOKUP(D4,基础资料!$P$5:$T$204,5,FALSE),0)) -> 100 | K4: =IF(OR(G4="",J4=""),"",G4*J4) -> 2000 | L4: =IF(OR(A4="",C4=""),"",A4+IFERROR(VLOOKUP(C4,基础资料!$Y$5:$AA$204,3,FALSE),0)) -> 46204 | M4: 销售部 | N4: 张伟 | O4: 演示销售 | P4: =IF(A4="","","可录入") -> 可录入 | Q4: =IF(I4="","",I4-K4) -> 2000
A5: 46176 | B5: =IF(A5="","",TEXT(A5,"yyyy-mm")) -> 2026-06 | C5: 客户B | D5: B配件 | E5: =IF(D5="","",IFERROR(VLOOKUP(D5,基础资料!$P$5:$R$204,2,FALSE),"")) -> B-02 | F5: =IF(D5="","",IFERROR(VLOOKUP(D5,基础资料!$P$5:$R$204,3,FALSE),"")) -> 个 | G5: 15 | H5: 250 | I5: =IF(OR(G5="",H5=""),"",G5*H5) -> 3750 | J5: =IF(D5="","",IFERROR(VLOOKUP(D5,基础资料!$P$5:$T$204,5,FALSE),0)) -> 125 | K5: =IF(OR(G5="",J5=""),"",G5*J5) -> 1875 | L5: =IF(OR(A5="",C5=""),"",A5+IFERROR(VLOOKUP(C5,基础资料!$Y$5:$AA$204,3,FALSE),0)) -> 46206 | M5: 销售部 | N5: 李娜 | O5: 演示销售 | P5: =IF(A5="","","可录入") -> 可录入 | Q5: =IF(I5="","",I5-K5) -> 1875
A6: 46178 | B6: =IF(A6="","",TEXT(A6,"yyyy-mm")) -> 2026-06 | C6: 客户C | D6: C配件 | E6: =IF(D6="","",IFERROR(VLOOKUP(D6,基础资料!$P$5:$R$204,2,FALSE),"")) -> C-03 | F6: =IF(D6="","",IFERROR(VLOOKUP(D6,基础资料!$P$5:$R$204,3,FALSE),"")) -> 个 | G6: 30 | H6: 100 | I6: =IF(OR(G6="",H6=""),"",G6*H6) -> 3000 | J6: =IF(D6="","",IFERROR(VLOOKUP(D6,基础资料!$P$5:$T$204,5,FALSE),0)) -> 50 | K6: =IF(OR(G6="",J6=""),"",G6*J6) -> 1500 | L6: =IF(OR(A6="",C6=""),"",A6+IFERROR(VLOOKUP(C6,基础资料!$Y$5:$AA$204,3,FALSE),0)) -> 46223 | M6: 销售部 | N6: 张伟 | O6: 演示销售 | P6: =IF(A6="","","可录入") -> 可录入 | Q6: =IF(I6="","",I6-K6) -> 1500
A7: 46180 | B7: =IF(A7="","",TEXT(A7,"yyyy-mm")) -> 2026-06 | C7: 客户D | D7: D配件 | E7: =IF(D7="","",IFERROR(VLOOKUP(D7,基础资料!$P$5:$R$204,2,FALSE),"")) -> D-04 | F7: =IF(D7="","",IFERROR(VLOOKUP(D7,基础资料!$P$5:$R$204,3,FALSE),"")) -> 个 | G7: 8 | H7: 400 | I7: =IF(OR(G7="",H7=""),"",G7*H7) -> 3200 | J7: =IF(D7="","",IFERROR(VLOOKUP(D7,基础资料!$P$5:$T$204,5,FALSE),0)) -> 200 | K7: =IF(OR(G7="",J7=""),"",G7*J7) -> 1600 | L7: =IF(OR(A7="",C7=""),"",A7+IFERROR(VLOOKUP(C7,基础资料!$Y$5:$AA$204,3,FALSE),0)) -> 46210 | M7: 销售部 | N7: 李娜 | O7: 演示销售 | P7: =IF(A7="","","可录入") -> 可录入 | Q7: =IF(I7="","",I7-K7) -> 1600
A8: 46182 | B8: =IF(A8="","",TEXT(A8,"yyyy-mm")) -> 2026-06 | C8: 客户E | D8: E配件 | E8: =IF(D8="","",IFERROR(VLOOKUP(D8,基础资料!$P$5:$R$204,2,FALSE),"")) -> E-05 | F8: =IF(D8="","",IFERROR(VLOOKUP(D8,基础资料!$P$5:$R$204,3,FALSE),"")) -> 个 | G8: 50 | H8: 50 | I8: =IF(OR(G8="",H8=""),"",G8*H8) -> 2500 | J8: =IF(D8="","",IFERROR(VLOOKUP(D8,基础资料!$P$5:$T$204,5,FALSE),0)) -> 25 | K8: =IF(OR(G8="",J8=""),"",G8*J8) -> 1250 | L8: =IF(OR(A8="",C8=""),"",A8+IFERROR(VLOOKUP(C8,基础资料!$Y$5:$AA$204,3,FALSE),0)) -> 46242 | M8: 电商部 | N8: 孙悦 | O8: 演示销售 | P8: =IF(A8="","","可录入") -> 可录入 | Q8: =IF(I8="","",I8-K8) -> 1250
A9: 46184 | B9: =IF(A9="","",TEXT(A9,"yyyy-mm")) -> 2026-06 | C9: 客户F | D9: F配件 | E9: =IF(D9="","",IFERROR(VLOOKUP(D9,基础资料!$P$5:$R$204,2,FALSE),"")) -> F-06 | F9: =IF(D9="","",IFERROR(VLOOKUP(D9,基础资料!$P$5:$R$204,3,FALSE),"")) -> 个 | G9: 12 | H9: 160 | I9: =IF(OR(G9="",H9=""),"",G9*H9) -> 1920 | J9: =IF(D9="","",IFERROR(VLOOKUP(D9,基础资料!$P$5:$T$204,5,FALSE),0)) -> 80 | K9: =IF(OR(G9="",J9=""),"",G9*J9) -> 960 | L9: =IF(OR(A9="",C9=""),"",A9+IFERROR(VLOOKUP(C9,基础资料!$Y$5:$AA$204,3,FALSE),0)) -> 46214 | M9: 销售部 | N9: 李娜 | O9: 演示销售 | P9: =IF(A9="","","可录入") -> 可录入 | Q9: =IF(I9="","",I9-K9) -> 960
A10: 46186 | B10: =IF(A10="","",TEXT(A10,"yyyy-mm")) -> 2026-06 | C10: 客户G | D10: G配件 | E10: =IF(D10="","",IFERROR(VLOOKUP(D10,基础资料!$P$5:$R$204,2,FALSE),"")) -> G-07 | F10: =IF(D10="","",IFERROR(VLOOKUP(D10,基础资料!$P$5:$R$204,3,FALSE),"")) -> 个 | G10: 15 | H10: 150 | I10: =IF(OR(G10="",H10=""),"",G10*H10) -> 2250 | J10: =IF(D10="","",IFERROR(VLOOKUP(D10,基础资料!$P$5:$T$204,5,FALSE),0)) -> 75 | K10: =IF(OR(G10="",J10=""),"",G10*J10) -> 1125 | L10: =IF(OR(A10="",C10=""),"",A10+IFERROR(VLOOKUP(C10,基础资料!$Y$5:$AA$204,3,FALSE),0)) -> 46231 | M10: 销售部 | N10: 张伟 | O10: 演示销售 | P10: =IF(A10="","","可录入") -> 可录入 | Q10: =IF(I10="","",I10-K10) -> 1125
A11: 46188 | B11: =IF(A11="","",TEXT(A11,"yyyy-mm")) -> 2026-06 | C11: 客户H | D11: H配件 | E11: =IF(D11="","",IFERROR(VLOOKUP(D11,基础资料!$P$5:$R$204,2,FALSE),"")) -> H-08 | F11: =IF(D11="","",IFERROR(VLOOKUP(D11,基础资料!$P$5:$R$204,3,FALSE),"")) -> 个 | G11: 6 | H11: 300 | I11: =IF(OR(G11="",H11=""),"",G11*H11) -> 1800 | J11: =IF(D11="","",IFERROR(VLOOKUP(D11,基础资料!$P$5:$T$204,5,FALSE),0)) -> 150 | K11: =IF(OR(G11="",J11=""),"",G11*J11) -> 900 | L11: =IF(OR(A11="",C11=""),"",A11+IFERROR(VLOOKUP(C11,基础资料!$Y$5:$AA$204,3,FALSE),0)) -> 46218 | M11: 销售部 | N11: 李娜 | O11: 演示销售 | P11: =IF(A11="","","可录入") -> 可录入 | Q11: =IF(I11="","",I11-K11) -> 900
A12: 46190 | B12: =IF(A12="","",TEXT(A12,"yyyy-mm")) -> 2026-06 | C12: 客户I | D12: I配件 | E12: =IF(D12="","",IFERROR(VLOOKUP(D12,基础资料!$P$5:$R$204,2,FALSE),"")) -> I-09 | F12: =IF(D12="","",IFERROR(VLOOKUP(D12,基础资料!$P$5:$R$204,3,FALSE),"")) -> 个 | G12: 25 | H12: 60 | I12: =IF(OR(G12="",H12=""),"",G12*H12) -> 1500 | J12: =IF(D12="","",IFERROR(VLOOKUP(D12,基础资料!$P$5:$T$204,5,FALSE),0)) -> 30 | K12: =IF(OR(G12="",J12=""),"",G12*J12) -> 750 | L12: =IF(OR(A12="",C12=""),"",A12+IFERROR(VLOOKUP(C12,基础资料!$Y$5:$AA$204,3,FALSE),0)) -> 46220 | M12: 销售部 | N12: 张伟 | O12: 演示销售 | P12: =IF(A12="","","可录入") -> 可录入 | Q12: =IF(I12="","",I12-K12) -> 750
A13: 46192 | B13: =IF(A13="","",TEXT(A13,"yyyy-mm")) -> 2026-06 | C13: 客户J | D13: J配件 | E13: =IF(D13="","",IFERROR(VLOOKUP(D13,基础资料!$P$5:$R$204,2,FALSE),"")) -> J-10 | F13: =IF(D13="","",IFERROR(VLOOKUP(D13,基础资料!$P$5:$R$204,3,FALSE),"")) -> 个 | G13: 18 | H13: 120 | I13: =IF(OR(G13="",H13=""),"",G13*H13) -> 2160 | J13: =IF(D13="","",IFERROR(VLOOKUP(D13,基础资料!$P$5:$T$204,5,FALSE),0)) -> 60 | K13: =IF(OR(G13="",J13=""),"",G13*J13) -> 1080 | L13: =IF(OR(A13="",C13=""),"",A13+IFERROR(VLOOKUP(C13,基础资料!$Y$5:$AA$204,3,FALSE),0)) -> 46252 | M13: 销售部 | N13: 李娜 | O13: 演示销售 | P13: =IF(A13="","","可录入") -> 可录入 | Q13: =IF(I13="","",I13-K13) -> 1080
B14: =IF(A14="","",TEXT(A14,"yyyy-mm")) | E14: =IF(D14="","",IFERROR(VLOOKUP(D14,基础资料!$P$5:$R$204,2,FALSE),"")) | F14: =IF(D14="","",IFERROR(VLOOKUP(D14,基础资料!$P$5:$R$204,3,FALSE),"")) | I14: =IF(OR(G14="",H14=""),"",G14*H14) | J14: =IF(D14="","",IFERROR(VLOOKUP(D14,基础资料!$P$5:$T$204,5,FALSE),0)) | K14: =IF(OR(G14="",J14=""),"",G14*J14) | L14: =IF(OR(A14="",C14=""),"",A14+IFERROR(VLOOKUP(C14,基础资料!$Y$5:$AA$204,3,FALSE),0)) | P14: =IF(A14="","","可录入") | Q14: =IF(I14="","",I14-K14)
B15: =IF(A15="","",TEXT(A15,"yyyy-mm")) | E15: =IF(D15="","",IFERROR(VLOOKUP(D15,基础资料!$P$5:$R$204,2,FALSE),"")) | F15: =IF(D15="","",IFERROR(VLOOKUP(D15,基础资料!$P$5:$R$204,3,FALSE),"")) | I15: =IF(OR(G15="",H15=""),"",G15*H15) | J15: =IF(D15="","",IFERROR(VLOOKUP(D15,基础资料!$P$5:$T$204,5,FALSE),0)) | K15: =IF(OR(G15="",J15=""),"",G15*J15) | L15: =IF(OR(A15="",C15=""),"",A15+IFERROR(VLOOKUP(C15,基础资料!$Y$5:$AA$204,3,FALSE),0)) | P15: =IF(A15="","","可录入") | Q15: =IF(I15="","",I15-K15)
B16: =IF(A16="","",TEXT(A16,"yyyy-mm")) | E16: =IF(D16="","",IFERROR(VLOOKUP(D16,基础资料!$P$5:$R$204,2,FALSE),"")) | F16: =IF(D16="","",IFERROR(VLOOKUP(D16,基础资料!$P$5:$R$204,3,FALSE),"")) | I16: =IF(OR(G16="",H16=""),"",G16*H16) | J16: =IF(D16="","",IFERROR(VLOOKUP(D16,基础资料!$P$5:$T$204,5,FALSE),0)) | K16: =IF(OR(G16="",J16=""),"",G16*J16) | L16: =IF(OR(A16="",C16=""),"",A16+IFERROR(VLOOKUP(C16,基础资料!$Y$5:$AA$204,3,FALSE),0)) | P16: =IF(A16="","","可录入") | Q16: =IF(I16="","",I16-K16)
B17: =IF(A17="","",TEXT(A17,"yyyy-mm")) | E17: =IF(D17="","",IFERROR(VLOOKUP(D17,基础资料!$P$5:$R$204,2,FALSE),"")) | F17: =IF(D17="","",IFERROR(VLOOKUP(D17,基础资料!$P$5:$R$204,3,FALSE),"")) | I17: =IF(OR(G17="",H17=""),"",G17*H17) | J17: =IF(D17="","",IFERROR(VLOOKUP(D17,基础资料!$P$5:$T$204,5,FALSE),0)) | K17: =IF(OR(G17="",J17=""),"",G17*J17) | L17: =IF(OR(A17="",C17=""),"",A17+IFERROR(VLOOKUP(C17,基础资料!$Y$5:$AA$204,3,FALSE),0)) | P17: =IF(A17="","","可录入") | Q17: =IF(I17="","",I17-K17)
B18: =IF(A18="","",TEXT(A18,"yyyy-mm")) | E18: =IF(D18="","",IFERROR(VLOOKUP(D18,基础资料!$P$5:$R$204,2,FALSE),"")) | F18: =IF(D18="","",IFERROR(VLOOKUP(D18,基础资料!$P$5:$R$204,3,FALSE),"")) | I18: =IF(OR(G18="",H18=""),"",G18*H18) | J18: =IF(D18="","",IFERROR(VLOOKUP(D18,基础资料!$P$5:$T$204,5,FALSE),0)) | K18: =IF(OR(G18="",J18=""),"",G18*J18) | L18: =IF(OR(A18="",C18=""),"",A18+IFERROR(VLOOKUP(C18,基础资料!$Y$5:$AA$204,3,FALSE),0)) | P18: =IF(A18="","","可录入") | Q18: =IF(I18="","",I18-K18)
B19: =IF(A19="","",TEXT(A19,"yyyy-mm")) | E19: =IF(D19="","",IFERROR(VLOOKUP(D19,基础资料!$P$5:$R$204,2,FALSE),"")) | F19: =IF(D19="","",IFERROR(VLOOKUP(D19,基础资料!$P$5:$R$204,3,FALSE),"")) | I19: =IF(OR(G19="",H19=""),"",G19*H19) | J19: =IF(D19="","",IFERROR(VLOOKUP(D19,基础资料!$P$5:$T$204,5,FALSE),0)) | K19: =IF(OR(G19="",J19=""),"",G19*J19) | L19: =IF(OR(A19="",C19=""),"",A19+IFERROR(VLOOKUP(C19,基础资料!$Y$5:$AA$204,3,FALSE),0)) | P19: =IF(A19="","","可录入") | Q19: =IF(I19="","",I19-K19)
B20: =IF(A20="","",TEXT(A20,"yyyy-mm")) | E20: =IF(D20="","",IFERROR(VLOOKUP(D20,基础资料!$P$5:$R$204,2,FALSE),"")) | F20: =IF(D20="","",IFERROR(VLOOKUP(D20,基础资料!$P$5:$R$204,3,FALSE),"")) | I20: =IF(OR(G20="",H20=""),"",G20*H20) | J20: =IF(D20="","",IFERROR(VLOOKUP(D20,基础资料!$P$5:$T$204,5,FALSE),0)) | K20: =IF(OR(G20="",J20=""),"",G20*J20) | L20: =IF(OR(A20="",C20=""),"",A20+IFERROR(VLOOKUP(C20,基础资料!$Y$5:$AA$204,3,FALSE),0)) | P20: =IF(A20="","","可录入") | Q20: =IF(I20="","",I20-K20)
B21: =IF(A21="","",TEXT(A21,"yyyy-mm")) | E21: =IF(D21="","",IFERROR(VLOOKUP(D21,基础资料!$P$5:$R$204,2,FALSE),"")) | F21: =IF(D21="","",IFERROR(VLOOKUP(D21,基础资料!$P$5:$R$204,3,FALSE),"")) | I21: =IF(OR(G21="",H21=""),"",G21*H21) | J21: =IF(D21="","",IFERROR(VLOOKUP(D21,基础资料!$P$5:$T$204,5,FALSE),0)) | K21: =IF(OR(G21="",J21=""),"",G21*J21) | L21: =IF(OR(A21="",C21=""),"",A21+IFERROR(VLOOKUP(C21,基础资料!$Y$5:$AA$204,3,FALSE),0)) | P21: =IF(A21="","","可录入") | Q21: =IF(I21="","",I21-K21)
B22: =IF(A22="","",TEXT(A22,"yyyy-mm")) | E22: =IF(D22="","",IFERROR(VLOOKUP(D22,基础资料!$P$5:$R$204,2,FALSE),"")) | F22: =IF(D22="","",IFERROR(VLOOKUP(D22,基础资料!$P$5:$R$204,3,FALSE),"")) | I22: =IF(OR(G22="",H22=""),"",G22*H22) | J22: =IF(D22="","",IFERROR(VLOOKUP(D22,基础资料!$P$5:$T$204,5,FALSE),0)) | K22: =IF(OR(G22="",J22=""),"",G22*J22) | L22: =IF(OR(A22="",C22=""),"",A22+IFERROR(VLOOKUP(C22,基础资料!$Y$5:$AA$204,3,FALSE),0)) | P22: =IF(A22="","","可录入") | Q22: =IF(I22="","",I22-K22)
B23: =IF(A23="","",TEXT(A23,"yyyy-mm")) | E23: =IF(D23="","",IFERROR(VLOOKUP(D23,基础资料!$P$5:$R$204,2,FALSE),"")) | F23: =IF(D23="","",IFERROR(VLOOKUP(D23,基础资料!$P$5:$R$204,3,FALSE),"")) | I23: =IF(OR(G23="",H23=""),"",G23*H23) | J23: =IF(D23="","",IFERROR(VLOOKUP(D23,基础资料!$P$5:$T$204,5,FALSE),0)) | K23: =IF(OR(G23="",J23=""),"",G23*J23) | L23: =IF(OR(A23="",C23=""),"",A23+IFERROR(VLOOKUP(C23,基础资料!$Y$5:$AA$204,3,FALSE),0)) | P23: =IF(A23="","","可录入") | Q23: =IF(I23="","",I23-K23)
B24: =IF(A24="","",TEXT(A24,"yyyy-mm")) | E24: =IF(D24="","",IFERROR(VLOOKUP(D24,基础资料!$P$5:$R$204,2,FALSE),"")) | F24: =IF(D24="","",IFERROR(VLOOKUP(D24,基础资料!$P$5:$R$204,3,FALSE),"")) | I24: =IF(OR(G24="",H24=""),"",G24*H24) | J24: =IF(D24="","",IFERROR(VLOOKUP(D24,基础资料!$P$5:$T$204,5,FALSE),0)) | K24: =IF(OR(G24="",J24=""),"",G24*J24) | L24: =IF(OR(A24="",C24=""),"",A24+IFERROR(VLOOKUP(C24,基础资料!$Y$5:$AA$204,3,FALSE),0)) | P24: =IF(A24="","","可录入") | Q24: =IF(I24="","",I24-K24)
B25: =IF(A25="","",TEXT(A25,"yyyy-mm")) | E25: =IF(D25="","",IFERROR(VLOOKUP(D25,基础资料!$P$5:$R$204,2,FALSE),"")) | F25: =IF(D25="","",IFERROR(VLOOKUP(D25,基础资料!$P$5:$R$204,3,FALSE),"")) | I25: =IF(OR(G25="",H25=""),"",G25*H25) | J25: =IF(D25="","",IFERROR(VLOOKUP(D25,基础资料!$P$5:$T$204,5,FALSE),0)) | K25: =IF(OR(G25="",J25=""),"",G25*J25) | L25: =IF(OR(A25="",C25=""),"",A25+IFERROR(VLOOKUP(C25,基础资料!$Y$5:$AA$204,3,FALSE),0)) | P25: =IF(A25="","","可录入") | Q25: =IF(I25="","",I25-K25)
... B203: =IF(A203="","",TEXT(A203,"yyyy-mm")) | E203: =IF(D203="","",IFERROR(VLOOKUP(D203,基础资料!$P$5:$R$204,2,FALSE),"")) | F203: =IF(D203="","",IFERROR(VLOOKUP(D203,基础资料!$P$5:$R$204,3,FALSE),"")) | I203: =IF(OR(G203="",H203=""),"",G203*H203) | J203: =IF(D203="","",IFERROR(VLOOKUP(D203,基础资料!$P$5:$T$204,5,FALSE),0)) | K203: =IF(OR(G203="",J203=""),"",G203*J203) | L203: =IF(OR(A203="",C203=""),"",A203+IFERROR(VLOOKUP(C203,基础资料!$Y$5:$AA$204,3,FALSE),0)) | P203: =IF(A203="","","可录入") | Q203: =IF(I203="","",I203-K203)

Sheet 采购录入
A1: 采购录入（采购业务唯一入口）
A2: 采购只在这里登记；供应商付款只在资金流水登记。采购单价每笔手工填写。
A3: 日期 | B3: 月份 | C3: 供应商 | D3: 商品 | E3: 规格 | F3: 单位 | G3: 数量 | H3: 采购单价（手工） | I3: 采购金额 | J3: 到期日 | K3: 部门 | L3: 采购员 | M3: 备注 | N3: 月结检查
A4: 46174 | B4: =IF(A4="","",TEXT(A4,"yyyy-mm")) -> 2026-06 | C4: 供应商A | D4: A配件 | E4: =IF(D4="","",IFERROR(VLOOKUP(D4,基础资料!$P$5:$R$204,2,FALSE),"")) -> A-01 | F4: =IF(D4="","",IFERROR(VLOOKUP(D4,基础资料!$P$5:$R$204,3,FALSE),"")) -> 个 | G4: 30 | H4: 100 | I4: =IF(OR(G4="",H4=""),"",G4*H4) -> 3000 | J4: =IF(OR(A4="",C4=""),"",A4+IFERROR(VLOOKUP(C4,基础资料!$AE$5:$AG$204,3,FALSE),0)) -> 46204 | K4: 采购部 | L4: 王强 | M4: 演示采购 | N4: =IF(A4="","","可录入") -> 可录入
A5: 46176 | B5: =IF(A5="","",TEXT(A5,"yyyy-mm")) -> 2026-06 | C5: 供应商B | D5: B配件 | E5: =IF(D5="","",IFERROR(VLOOKUP(D5,基础资料!$P$5:$R$204,2,FALSE),"")) -> B-02 | F5: =IF(D5="","",IFERROR(VLOOKUP(D5,基础资料!$P$5:$R$204,3,FALSE),"")) -> 个 | G5: 20 | H5: 125 | I5: =IF(OR(G5="",H5=""),"",G5*H5) -> 2500 | J5: =IF(OR(A5="",C5=""),"",A5+IFERROR(VLOOKUP(C5,基础资料!$AE$5:$AG$204,3,FALSE),0)) -> 46206 | K5: 采购部 | L5: 王强 | M5: 演示采购 | N5: =IF(A5="","","可录入") -> 可录入
A6: 46178 | B6: =IF(A6="","",TEXT(A6,"yyyy-mm")) -> 2026-06 | C6: 供应商C | D6: C配件 | E6: =IF(D6="","",IFERROR(VLOOKUP(D6,基础资料!$P$5:$R$204,2,FALSE),"")) -> C-03 | F6: =IF(D6="","",IFERROR(VLOOKUP(D6,基础资料!$P$5:$R$204,3,FALSE),"")) -> 个 | G6: 50 | H6: 50 | I6: =IF(OR(G6="",H6=""),"",G6*H6) -> 2500 | J6: =IF(OR(A6="",C6=""),"",A6+IFERROR(VLOOKUP(C6,基础资料!$AE$5:$AG$204,3,FALSE),0)) -> 46223 | K6: 采购部 | L6: 王强 | M6: 演示采购 | N6: =IF(A6="","","可录入") -> 可录入
A7: 46180 | B7: =IF(A7="","",TEXT(A7,"yyyy-mm")) -> 2026-06 | C7: 供应商D | D7: D配件 | E7: =IF(D7="","",IFERROR(VLOOKUP(D7,基础资料!$P$5:$R$204,2,FALSE),"")) -> D-04 | F7: =IF(D7="","",IFERROR(VLOOKUP(D7,基础资料!$P$5:$R$204,3,FALSE),"")) -> 个 | G7: 10 | H7: 200 | I7: =IF(OR(G7="",H7=""),"",G7*H7) -> 2000 | J7: =IF(OR(A7="",C7=""),"",A7+IFERROR(VLOOKUP(C7,基础资料!$AE$5:$AG$204,3,FALSE),0)) -> 46210 | K7: 采购部 | L7: 王强 | M7: 演示采购 | N7: =IF(A7="","","可录入") -> 可录入
A8: 46182 | B8: =IF(A8="","",TEXT(A8,"yyyy-mm")) -> 2026-06 | C8: 供应商E | D8: E配件 | E8: =IF(D8="","",IFERROR(VLOOKUP(D8,基础资料!$P$5:$R$204,2,FALSE),"")) -> E-05 | F8: =IF(D8="","",IFERROR(VLOOKUP(D8,基础资料!$P$5:$R$204,3,FALSE),"")) -> 个 | G8: 80 | H8: 25 | I8: =IF(OR(G8="",H8=""),"",G8*H8) -> 2000 | J8: =IF(OR(A8="",C8=""),"",A8+IFERROR(VLOOKUP(C8,基础资料!$AE$5:$AG$204,3,FALSE),0)) -> 46242 | K8: 采购部 | L8: 王强 | M8: 演示采购 | N8: =IF(A8="","","可录入") -> 可录入
A9: 46184 | B9: =IF(A9="","",TEXT(A9,"yyyy-mm")) -> 2026-06 | C9: 供应商F | D9: F配件 | E9: =IF(D9="","",IFERROR(VLOOKUP(D9,基础资料!$P$5:$R$204,2,FALSE),"")) -> F-06 | F9: =IF(D9="","",IFERROR(VLOOKUP(D9,基础资料!$P$5:$R$204,3,FALSE),"")) -> 个 | G9: 25 | H9: 80 | I9: =IF(OR(G9="",H9=""),"",G9*H9) -> 2000 | J9: =IF(OR(A9="",C9=""),"",A9+IFERROR(VLOOKUP(C9,基础资料!$AE$5:$AG$204,3,FALSE),0)) -> 46214 | K9: 采购部 | L9: 王强 | M9: 演示采购 | N9: =IF(A9="","","可录入") -> 可录入
A10: 46186 | B10: =IF(A10="","",TEXT(A10,"yyyy-mm")) -> 2026-06 | C10: 供应商G | D10: G配件 | E10: =IF(D10="","",IFERROR(VLOOKUP(D10,基础资料!$P$5:$R$204,2,FALSE),"")) -> G-07 | F10: =IF(D10="","",IFERROR(VLOOKUP(D10,基础资料!$P$5:$R$204,3,FALSE),"")) -> 个 | G10: 20 | H10: 75 | I10: =IF(OR(G10="",H10=""),"",G10*H10) -> 1500 | J10: =IF(OR(A10="",C10=""),"",A10+IFERROR(VLOOKUP(C10,基础资料!$AE$5:$AG$204,3,FALSE),0)) -> 46231 | K10: 采购部 | L10: 王强 | M10: 演示采购 | N10: =IF(A10="","","可录入") -> 可录入
A11: 46188 | B11: =IF(A11="","",TEXT(A11,"yyyy-mm")) -> 2026-06 | C11: 供应商H | D11: H配件 | E11: =IF(D11="","",IFERROR(VLOOKUP(D11,基础资料!$P$5:$R$204,2,FALSE),"")) -> H-08 | F11: =IF(D11="","",IFERROR(VLOOKUP(D11,基础资料!$P$5:$R$204,3,FALSE),"")) -> 个 | G11: 12 | H11: 150 | I11: =IF(OR(G11="",H11=""),"",G11*H11) -> 1800 | J11: =IF(OR(A11="",C11=""),"",A11+IFERROR(VLOOKUP(C11,基础资料!$AE$5:$AG$204,3,FALSE),0)) -> 46218 | K11: 采购部 | L11: 王强 | M11: 演示采购 | N11: =IF(A11="","","可录入") -> 可录入
A12: 46190 | B12: =IF(A12="","",TEXT(A12,"yyyy-mm")) -> 2026-06 | C12: 供应商I | D12: I配件 | E12: =IF(D12="","",IFERROR(VLOOKUP(D12,基础资料!$P$5:$R$204,2,FALSE),"")) -> I-09 | F12: =IF(D12="","",IFERROR(VLOOKUP(D12,基础资料!$P$5:$R$204,3,FALSE),"")) -> 个 | G12: 40 | H12: 30 | I12: =IF(OR(G12="",H12=""),"",G12*H12) -> 1200 | J12: =IF(OR(A12="",C12=""),"",A12+IFERROR(VLOOKUP(C12,基础资料!$AE$5:$AG$204,3,FALSE),0)) -> 46220 | K12: 采购部 | L12: 王强 | M12: 演示采购 | N12: =IF(A12="","","可录入") -> 可录入
A13: 46192 | B13: =IF(A13="","",TEXT(A13,"yyyy-mm")) -> 2026-06 | C13: 供应商J | D13: J配件 | E13: =IF(D13="","",IFERROR(VLOOKUP(D13,基础资料!$P$5:$R$204,2,FALSE),"")) -> J-10 | F13: =IF(D13="","",IFERROR(VLOOKUP(D13,基础资料!$P$5:$R$204,3,FALSE),"")) -> 个 | G13: 30 | H13: 60 | I13: =IF(OR(G13="",H13=""),"",G13*H13) -> 1800 | J13: =IF(OR(A13="",C13=""),"",A13+IFERROR(VLOOKUP(C13,基础资料!$AE$5:$AG$204,3,FALSE),0)) -> 46252 | K13: 采购部 | L13: 王强 | M13: 演示采购 | N13: =IF(A13="","","可录入") -> 可录入
B14: =IF(A14="","",TEXT(A14,"yyyy-mm")) | E14: =IF(D14="","",IFERROR(VLOOKUP(D14,基础资料!$P$5:$R$204,2,FALSE),"")) | F14: =IF(D14="","",IFERROR(VLOOKUP(D14,基础资料!$P$5:$R$204,3,FALSE),"")) | I14: =IF(OR(G14="",H14=""),"",G14*H14) | J14: =IF(OR(A14="",C14=""),"",A14+IFERROR(VLOOKUP(C14,基础资料!$AE$5:$AG$204,3,FALSE),0)) | N14: =IF(A14="","","可录入")
B15: =IF(A15="","",TEXT(A15,"yyyy-mm")) | E15: =IF(D15="","",IFERROR(VLOOKUP(D15,基础资料!$P$5:$R$204,2,FALSE),"")) | F15: =IF(D15="","",IFERROR(VLOOKUP(D15,基础资料!$P$5:$R$204,3,FALSE),"")) | I15: =IF(OR(G15="",H15=""),"",G15*H15) | J15: =IF(OR(A15="",C15=""),"",A15+IFERROR(VLOOKUP(C15,基础资料!$AE$5:$AG$204,3,FALSE),0)) | N15: =IF(A15="","","可录入")
B16: =IF(A16="","",TEXT(A16,"yyyy-mm")) | E16: =IF(D16="","",IFERROR(VLOOKUP(D16,基础资料!$P$5:$R$204,2,FALSE),"")) | F16: =IF(D16="","",IFERROR(VLOOKUP(D16,基础资料!$P$5:$R$204,3,FALSE),"")) | I16: =IF(OR(G16="",H16=""),"",G16*H16) | J16: =IF(OR(A16="",C16=""),"",A16+IFERROR(VLOOKUP(C16,基础资料!$AE$5:$AG$204,3,FALSE),0)) | N16: =IF(A16="","","可录入")
B17: =IF(A17="","",TEXT(A17,"yyyy-mm")) | E17: =IF(D17="","",IFERROR(VLOOKUP(D17,基础资料!$P$5:$R$204,2,FALSE),"")) | F17: =IF(D17="","",IFERROR(VLOOKUP(D17,基础资料!$P$5:$R$204,3,FALSE),"")) | I17: =IF(OR(G17="",H17=""),"",G17*H17) | J17: =IF(OR(A17="",C17=""),"",A17+IFERROR(VLOOKUP(C17,基础资料!$AE$5:$AG$204,3,FALSE),0)) | N17: =IF(A17="","","可录入")
B18: =IF(A18="","",TEXT(A18,"yyyy-mm")) | E18: =IF(D18="","",IFERROR(VLOOKUP(D18,基础资料!$P$5:$R$204,2,FALSE),"")) | F18: =IF(D18="","",IFERROR(VLOOKUP(D18,基础资料!$P$5:$R$204,3,FALSE),"")) | I18: =IF(OR(G18="",H18=""),"",G18*H18) | J18: =IF(OR(A18="",C18=""),"",A18+IFERROR(VLOOKUP(C18,基础资料!$AE$5:$AG$204,3,FALSE),0)) | N18: =IF(A18="","","可录入")
B19: =IF(A19="","",TEXT(A19,"yyyy-mm")) | E19: =IF(D19="","",IFERROR(VLOOKUP(D19,基础资料!$P$5:$R$204,2,FALSE),"")) | F19: =IF(D19="","",IFERROR(VLOOKUP(D19,基础资料!$P$5:$R$204,3,FALSE),"")) | I19: =IF(OR(G19="",H19=""),"",G19*H19) | J19: =IF(OR(A19="",C19=""),"",A19+IFERROR(VLOOKUP(C19,基础资料!$AE$5:$AG$204,3,FALSE),0)) | N19: =IF(A19="","","可录入")
B20: =IF(A20="","",TEXT(A20,"yyyy-mm")) | E20: =IF(D20="","",IFERROR(VLOOKUP(D20,基础资料!$P$5:$R$204,2,FALSE),"")) | F20: =IF(D20="","",IFERROR(VLOOKUP(D20,基础资料!$P$5:$R$204,3,FALSE),"")) | I20: =IF(OR(G20="",H20=""),"",G20*H20) | J20: =IF(OR(A20="",C20=""),"",A20+IFERROR(VLOOKUP(C20,基础资料!$AE$5:$AG$204,3,FALSE),0)) | N20: =IF(A20="","","可录入")
B21: =IF(A21="","",TEXT(A21,"yyyy-mm")) | E21: =IF(D21="","",IFERROR(VLOOKUP(D21,基础资料!$P$5:$R$204,2,FALSE),"")) | F21: =IF(D21="","",IFERROR(VLOOKUP(D21,基础资料!$P$5:$R$204,3,FALSE),"")) | I21: =IF(OR(G21="",H21=""),"",G21*H21) | J21: =IF(OR(A21="",C21=""),"",A21+IFERROR(VLOOKUP(C21,基础资料!$AE$5:$AG$204,3,FALSE),0)) | N21: =IF(A21="","","可录入")
B22: =IF(A22="","",TEXT(A22,"yyyy-mm")) | E22: =IF(D22="","",IFERROR(VLOOKUP(D22,基础资料!$P$5:$R$204,2,FALSE),"")) | F22: =IF(D22="","",IFERROR(VLOOKUP(D22,基础资料!$P$5:$R$204,3,FALSE),"")) | I22: =IF(OR(G22="",H22=""),"",G22*H22) | J22: =IF(OR(A22="",C22=""),"",A22+IFERROR(VLOOKUP(C22,基础资料!$AE$5:$AG$204,3,FALSE),0)) | N22: =IF(A22="","","可录入")
B23: =IF(A23="","",TEXT(A23,"yyyy-mm")) | E23: =IF(D23="","",IFERROR(VLOOKUP(D23,基础资料!$P$5:$R$204,2,FALSE),"")) | F23: =IF(D23="","",IFERROR(VLOOKUP(D23,基础资料!$P$5:$R$204,3,FALSE),"")) | I23: =IF(OR(G23="",H23=""),"",G23*H23) | J23: =IF(OR(A23="",C23=""),"",A23+IFERROR(VLOOKUP(C23,基础资料!$AE$5:$AG$204,3,FALSE),0)) | N23: =IF(A23="","","可录入")
B24: =IF(A24="","",TEXT(A24,"yyyy-mm")) | E24: =IF(D24="","",IFERROR(VLOOKUP(D24,基础资料!$P$5:$R$204,2,FALSE),"")) | F24: =IF(D24="","",IFERROR(VLOOKUP(D24,基础资料!$P$5:$R$204,3,FALSE),"")) | I24: =IF(OR(G24="",H24=""),"",G24*H24) | J24: =IF(OR(A24="",C24=""),"",A24+IFERROR(VLOOKUP(C24,基础资料!$AE$5:$AG$204,3,FALSE),0)) | N24: =IF(A24="","","可录入")
B25: =IF(A25="","",TEXT(A25,"yyyy-mm")) | E25: =IF(D25="","",IFERROR(VLOOKUP(D25,基础资料!$P$5:$R$204,2,FALSE),"")) | F25: =IF(D25="","",IFERROR(VLOOKUP(D25,基础资料!$P$5:$R$204,3,FALSE),"")) | I25: =IF(OR(G25="",H25=""),"",G25*H25) | J25: =IF(OR(A25="",C25=""),"",A25+IFERROR(VLOOKUP(C25,基础资料!$AE$5:$AG$204,3,FALSE),0)) | N25: =IF(A25="","","可录入")
... B203: =IF(A203="","",TEXT(A203,"yyyy-mm")) | E203: =IF(D203="","",IFERROR(VLOOKUP(D203,基础资料!$P$5:$R$204,2,FALSE),"")) | F203: =IF(D203="","",IFERROR(VLOOKUP(D203,基础资料!$P$5:$R$204,3,FALSE),"")) | I203: =IF(OR(G203="",H203=""),"",G203*H203) | J203: =IF(OR(A203="",C203=""),"",A203+IFERROR(VLOOKUP(C203,基础资料!$AE$5:$AG$204,3,FALSE),0)) | N203: =IF(A203="","","可录入")

Sheet 库存收发存
A1: 库存收发存 + 成本/异常预警
A2: 查询月份 | B2: =首页!$B$4 -> 46174 | D2: 只显示月末有库存或本月有购销发生的商品；合计固定在第3行。
A3: 合计 | D3: =SUM(D5:D104) -> 1660 | E3: =SUM(E5:E104) -> 317 | F3: =SUM(F5:F104) -> 20300 | G3: =SUM(G5:G104) -> 199 | H3: =SUM(H5:H104) -> 13040 | I3: =SUM(I5:I104) -> 1778 | J3: =SUM(J5:J104) -> 107260 | K3: =IFERROR(J3/I3,0) -> 60.326209 | L3: =SUM(L5:L104) -> 26080 | M3: =SUM(M5:M104) -> 13040 | O3: =IFERROR(M3/L3,0) -> 0.5
A4: 商品 | B4: 规格 | C4: 单位 | D4: 月初数量 | E4: 本月采购数量 | F4: 本月采购金额 | G4: 本月销售数量 | H4: 本月销售成本 | I4: 月末数量 | J4: 月末金额 | K4: 月末单位成本 | L4: 本月销售额 | M4: 本月毛利 | N4: 采购均价偏差 | O4: 毛利率 | P4: 库存状态 | Q4: 综合预警
A5: {=_xlfn._xlws.FILTER(基础资料!$P$5:$P$204,基础资料!$W$5:$W$204="显示","")} -> A配件 | B5: =IF(A5="","",IFERROR(VLOOKUP(A5,基础资料!$P$5:$R$204,2,FALSE),"")) -> A-01 | C5: =IF(A5="","",IFERROR(VLOOKUP(A5,基础资料!$P$5:$R$204,3,FALSE),"")) -> 个 | D5: =IF(A5="","",SUMIFS(期初数据!$S$5:$S$14,期初数据!$P$5:$P$14,A5)+SUMIFS(采购录入!$G$4:$G$203,采购录入!$D$4:$D$203,A5,采购录入!$A$4:$A$203,"<"&EOMONTH($B$2,-1)+1)-SUMIFS(销售录入!$G$4:$G$203,销售录入!$D$4:$D$203,A5,销售录入!$A$4:$A$203,"<"&EOMONTH($B$2,-1)+1)) -> 100 | E5: =IF(A5="","",SUMIFS(采购录入!$G$4:$G$203,采购录入!$D$4:$D$203,A5,采购录入!$B$4:$B$203,TEXT($B$2,"yyyy-mm"))) -> 30 | F5: =IF(A5="","",SUMIFS(采购录入!$I$4:$I$203,采购录入!$D$4:$D$203,A5,采购录入!$B$4:$B$203,TEXT($B$2,"yyyy-mm"))) -> 3000 | G5: =IF(A5="","",SUMIFS(销售录入!$G$4:$G$203,销售录入!$D$4:$D$203,A5,销售录入!$B$4:$B$203,TEXT($B$2,"yyyy-mm"))) -> 20 | H5: =IF(A5="","",SUMIFS(销售录入!$K$4:$K$203,销售录入!$D$4:$D$203,A5,销售录入!$B$4:$B$203,TEXT($B$2,"yyyy-mm"))) -> 2000 | I5: =IF(A5="","",D5+E5-G5) -> 110 | J5: =IF(A5="","",SUMIFS(期初数据!$U$5:$U$14,期初数据!$P$5:$P$14,A5)+SUMIFS(采购录入!$I$4:$I$203,采购录入!$D$4:$D$203,A5,采购录入!$A$4:$A$203,"<="&EOMONTH($B$2,0))-SUMIFS(销售录入!$K$4:$K$203,销售录入!$D$4:$D$203,A5,销售录入!$A$4:$A$203,"<="&EOMONTH($B$2,0))) -> 11000 | K5: =IF(A5="","",IFERROR(J5/I5,0)) -> 100 | L5: =IF(A5="","",SUMIFS(销售录入!$I$4:$I$203,销售录入!$D$4:$D$203,A5,销售录入!$B$4:$B$203,TEXT($B$2,"yyyy-mm"))) -> 4000 | M5: =IF(A5="","",L5-H5) -> 2000 | N5: =IF(A5="","",IFERROR(IF(E5=0,0,(F5/E5)/VLOOKUP(A5,基础资料!$P$5:$T$204,5,FALSE)-1),0)) -> 0 | O5: =IF(A5="","",IFERROR(M5/L5,0)) -> 0.5 | P5: =IF(A5="","",IF(I5<0,"负库存",IF(I5=0,"零库存","正常"))) -> 正常 | Q5: =IF(A5="","",IF(P5="负库存","高风险",IF(AND(L5>0,O5<0.1),"低毛利",IF(ABS(N5)>0.2,"采购价异常","正常")))) -> 正常
A6: B配件 | B6: =IF(A6="","",IFERROR(VLOOKUP(A6,基础资料!$P$5:$R$204,2,FALSE),"")) -> B-02 | C6: =IF(A6="","",IFERROR(VLOOKUP(A6,基础资料!$P$5:$R$204,3,FALSE),"")) -> 个 | D6: =IF(A6="","",SUMIFS(期初数据!$S$5:$S$14,期初数据!$P$5:$P$14,A6)+SUMIFS(采购录入!$G$4:$G$203,采购录入!$D$4:$D$203,A6,采购录入!$A$4:$A$203,"<"&EOMONTH($B$2,-1)+1)-SUMIFS(销售录入!$G$4:$G$203,销售录入!$D$4:$D$203,A6,销售录入!$A$4:$A$203,"<"&EOMONTH($B$2,-1)+1)) -> 80 | E6: =IF(A6="","",SUMIFS(采购录入!$G$4:$G$203,采购录入!$D$4:$D$203,A6,采购录入!$B$4:$B$203,TEXT($B$2,"yyyy-mm"))) -> 20 | F6: =IF(A6="","",SUMIFS(采购录入!$I$4:$I$203,采购录入!$D$4:$D$203,A6,采购录入!$B$4:$B$203,TEXT($B$2,"yyyy-mm"))) -> 2500 | G6: =IF(A6="","",SUMIFS(销售录入!$G$4:$G$203,销售录入!$D$4:$D$203,A6,销售录入!$B$4:$B$203,TEXT($B$2,"yyyy-mm"))) -> 15 | H6: =IF(A6="","",SUMIFS(销售录入!$K$4:$K$203,销售录入!$D$4:$D$203,A6,销售录入!$B$4:$B$203,TEXT($B$2,"yyyy-mm"))) -> 1875 | I6: =IF(A6="","",D6+E6-G6) -> 85 | J6: =IF(A6="","",SUMIFS(期初数据!$U$5:$U$14,期初数据!$P$5:$P$14,A6)+SUMIFS(采购录入!$I$4:$I$203,采购录入!$D$4:$D$203,A6,采购录入!$A$4:$A$203,"<="&EOMONTH($B$2,0))-SUMIFS(销售录入!$K$4:$K$203,销售录入!$D$4:$D$203,A6,销售录入!$A$4:$A$203,"<="&EOMONTH($B$2,0))) -> 10625 | K6: =IF(A6="","",IFERROR(J6/I6,0)) -> 125 | L6: =IF(A6="","",SUMIFS(销售录入!$I$4:$I$203,销售录入!$D$4:$D$203,A6,销售录入!$B$4:$B$203,TEXT($B$2,"yyyy-mm"))) -> 3750 | M6: =IF(A6="","",L6-H6) -> 1875 | N6: =IF(A6="","",IFERROR(IF(E6=0,0,(F6/E6)/VLOOKUP(A6,基础资料!$P$5:$T$204,5,FALSE)-1),0)) -> 0 | O6: =IF(A6="","",IFERROR(M6/L6,0)) -> 0.5 | P6: =IF(A6="","",IF(I6<0,"负库存",IF(I6=0,"零库存","正常"))) -> 正常 | Q6: =IF(A6="","",IF(P6="负库存","高风险",IF(AND(L6>0,O6<0.1),"低毛利",IF(ABS(N6)>0.2,"采购价异常","正常")))) -> 正常
A7: C配件 | B7: =IF(A7="","",IFERROR(VLOOKUP(A7,基础资料!$P$5:$R$204,2,FALSE),"")) -> C-03 | C7: =IF(A7="","",IFERROR(VLOOKUP(A7,基础资料!$P$5:$R$204,3,FALSE),"")) -> 个 | D7: =IF(A7="","",SUMIFS(期初数据!$S$5:$S$14,期初数据!$P$5:$P$14,A7)+SUMIFS(采购录入!$G$4:$G$203,采购录入!$D$4:$D$203,A7,采购录入!$A$4:$A$203,"<"&EOMONTH($B$2,-1)+1)-SUMIFS(销售录入!$G$4:$G$203,销售录入!$D$4:$D$203,A7,销售录入!$A$4:$A$203,"<"&EOMONTH($B$2,-1)+1)) -> 200 | E7: =IF(A7="","",SUMIFS(采购录入!$G$4:$G$203,采购录入!$D$4:$D$203,A7,采购录入!$B$4:$B$203,TEXT($B$2,"yyyy-mm"))) -> 50 | F7: =IF(A7="","",SUMIFS(采购录入!$I$4:$I$203,采购录入!$D$4:$D$203,A7,采购录入!$B$4:$B$203,TEXT($B$2,"yyyy-mm"))) -> 2500 | G7: =IF(A7="","",SUMIFS(销售录入!$G$4:$G$203,销售录入!$D$4:$D$203,A7,销售录入!$B$4:$B$203,TEXT($B$2,"yyyy-mm"))) -> 30 | H7: =IF(A7="","",SUMIFS(销售录入!$K$4:$K$203,销售录入!$D$4:$D$203,A7,销售录入!$B$4:$B$203,TEXT($B$2,"yyyy-mm"))) -> 1500 | I7: =IF(A7="","",D7+E7-G7) -> 220 | J7: =IF(A7="","",SUMIFS(期初数据!$U$5:$U$14,期初数据!$P$5:$P$14,A7)+SUMIFS(采购录入!$I$4:$I$203,采购录入!$D$4:$D$203,A7,采购录入!$A$4:$A$203,"<="&EOMONTH($B$2,0))-SUMIFS(销售录入!$K$4:$K$203,销售录入!$D$4:$D$203,A7,销售录入!$A$4:$A$203,"<="&EOMONTH($B$2,0))) -> 11000 | K7: =IF(A7="","",IFERROR(J7/I7,0)) -> 50 | L7: =IF(A7="","",SUMIFS(销售录入!$I$4:$I$203,销售录入!$D$4:$D$203,A7,销售录入!$B$4:$B$203,TEXT($B$2,"yyyy-mm"))) -> 3000 | M7: =IF(A7="","",L7-H7) -> 1500 | N7: =IF(A7="","",IFERROR(IF(E7=0,0,(F7/E7)/VLOOKUP(A7,基础资料!$P$5:$T$204,5,FALSE)-1),0)) -> 0 | O7: =IF(A7="","",IFERROR(M7/L7,0)) -> 0.5 | P7: =IF(A7="","",IF(I7<0,"负库存",IF(I7=0,"零库存","正常"))) -> 正常 | Q7: =IF(A7="","",IF(P7="负库存","高风险",IF(AND(L7>0,O7<0.1),"低毛利",IF(ABS(N7)>0.2,"采购价异常","正常")))) -> 正常
A8: D配件 | B8: =IF(A8="","",IFERROR(VLOOKUP(A8,基础资料!$P$5:$R$204,2,FALSE),"")) -> D-04 | C8: =IF(A8="","",IFERROR(VLOOKUP(A8,基础资料!$P$5:$R$204,3,FALSE),"")) -> 个 | D8: =IF(A8="","",SUMIFS(期初数据!$S$5:$S$14,期初数据!$P$5:$P$14,A8)+SUMIFS(采购录入!$G$4:$G$203,采购录入!$D$4:$D$203,A8,采购录入!$A$4:$A$203,"<"&EOMONTH($B$2,-1)+1)-SUMIFS(销售录入!$G$4:$G$203,销售录入!$D$4:$D$203,A8,销售录入!$A$4:$A$203,"<"&EOMONTH($B$2,-1)+1)) -> 50 | E8: =IF(A8="","",SUMIFS(采购录入!$G$4:$G$203,采购录入!$D$4:$D$203,A8,采购录入!$B$4:$B$203,TEXT($B$2,"yyyy-mm"))) -> 10 | F8: =IF(A8="","",SUMIFS(采购录入!$I$4:$I$203,采购录入!$D$4:$D$203,A8,采购录入!$B$4:$B$203,TEXT($B$2,"yyyy-mm"))) -> 2000 | G8: =IF(A8="","",SUMIFS(销售录入!$G$4:$G$203,销售录入!$D$4:$D$203,A8,销售录入!$B$4:$B$203,TEXT($B$2,"yyyy-mm"))) -> 8 | H8: =IF(A8="","",SUMIFS(销售录入!$K$4:$K$203,销售录入!$D$4:$D$203,A8,销售录入!$B$4:$B$203,TEXT($B$2,"yyyy-mm"))) -> 1600 | I8: =IF(A8="","",D8+E8-G8) -> 52 | J8: =IF(A8="","",SUMIFS(期初数据!$U$5:$U$14,期初数据!$P$5:$P$14,A8)+SUMIFS(采购录入!$I$4:$I$203,采购录入!$D$4:$D$203,A8,采购录入!$A$4:$A$203,"<="&EOMONTH($B$2,0))-SUMIFS(销售录入!$K$4:$K$203,销售录入!$D$4:$D$203,A8,销售录入!$A$4:$A$203,"<="&EOMONTH($B$2,0))) -> 10400 | K8: =IF(A8="","",IFERROR(J8/I8,0)) -> 200 | L8: =IF(A8="","",SUMIFS(销售录入!$I$4:$I$203,销售录入!$D$4:$D$203,A8,销售录入!$B$4:$B$203,TEXT($B$2,"yyyy-mm"))) -> 3200 | M8: =IF(A8="","",L8-H8) -> 1600 | N8: =IF(A8="","",IFERROR(IF(E8=0,0,(F8/E8)/VLOOKUP(A8,基础资料!$P$5:$T$204,5,FALSE)-1),0)) -> 0 | O8: =IF(A8="","",IFERROR(M8/L8,0)) -> 0.5 | P8: =IF(A8="","",IF(I8<0,"负库存",IF(I8=0,"零库存","正常"))) -> 正常 | Q8: =IF(A8="","",IF(P8="负库存","高风险",IF(AND(L8>0,O8<0.1),"低毛利",IF(ABS(N8)>0.2,"采购价异常","正常")))) -> 正常
A9: E配件 | B9: =IF(A9="","",IFERROR(VLOOKUP(A9,基础资料!$P$5:$R$204,2,FALSE),"")) -> E-05 | C9: =IF(A9="","",IFERROR(VLOOKUP(A9,基础资料!$P$5:$R$204,3,FALSE),"")) -> 个 | D9: =IF(A9="","",SUMIFS(期初数据!$S$5:$S$14,期初数据!$P$5:$P$14,A9)+SUMIFS(采购录入!$G$4:$G$203,采购录入!$D$4:$D$203,A9,采购录入!$A$4:$A$203,"<"&EOMONTH($B$2,-1)+1)-SUMIFS(销售录入!$G$4:$G$203,销售录入!$D$4:$D$203,A9,销售录入!$A$4:$A$203,"<"&EOMONTH($B$2,-1)+1)) -> 400 | E9: =IF(A9="","",SUMIFS(采购录入!$G$4:$G$203,采购录入!$D$4:$D$203,A9,采购录入!$B$4:$B$203,TEXT($B$2,"yyyy-mm"))) -> 80 | F9: =IF(A9="","",SUMIFS(采购录入!$I$4:$I$203,采购录入!$D$4:$D$203,A9,采购录入!$B$4:$B$203,TEXT($B$2,"yyyy-mm"))) -> 2000 | G9: =IF(A9="","",SUMIFS(销售录入!$G$4:$G$203,销售录入!$D$4:$D$203,A9,销售录入!$B$4:$B$203,TEXT($B$2,"yyyy-mm"))) -> 50 | H9: =IF(A9="","",SUMIFS(销售录入!$K$4:$K$203,销售录入!$D$4:$D$203,A9,销售录入!$B$4:$B$203,TEXT($B$2,"yyyy-mm"))) -> 1250 | I9: =IF(A9="","",D9+E9-G9) -> 430 | J9: =IF(A9="","",SUMIFS(期初数据!$U$5:$U$14,期初数据!$P$5:$P$14,A9)+SUMIFS(采购录入!$I$4:$I$203,采购录入!$D$4:$D$203,A9,采购录入!$A$4:$A$203,"<="&EOMONTH($B$2,0))-SUMIFS(销售录入!$K$4:$K$203,销售录入!$D$4:$D$203,A9,销售录入!$A$4:$A$203,"<="&EOMONTH($B$2,0))) -> 10750 | K9: =IF(A9="","",IFERROR(J9/I9,0)) -> 25 | L9: =IF(A9="","",SUMIFS(销售录入!$I$4:$I$203,销售录入!$D$4:$D$203,A9,销售录入!$B$4:$B$203,TEXT($B$2,"yyyy-mm"))) -> 2500 | M9: =IF(A9="","",L9-H9) -> 1250 | N9: =IF(A9="","",IFERROR(IF(E9=0,0,(F9/E9)/VLOOKUP(A9,基础资料!$P$5:$T$204,5,FALSE)-1),0)) -> 0 | O9: =IF(A9="","",IFERROR(M9/L9,0)) -> 0.5 | P9: =IF(A9="","",IF(I9<0,"负库存",IF(I9=0,"零库存","正常"))) -> 正常 | Q9: =IF(A9="","",IF(P9="负库存","高风险",IF(AND(L9>0,O9<0.1),"低毛利",IF(ABS(N9)>0.2,"采购价异常","正常")))) -> 正常
A10: F配件 | B10: =IF(A10="","",IFERROR(VLOOKUP(A10,基础资料!$P$5:$R$204,2,FALSE),"")) -> F-06 | C10: =IF(A10="","",IFERROR(VLOOKUP(A10,基础资料!$P$5:$R$204,3,FALSE),"")) -> 个 | D10: =IF(A10="","",SUMIFS(期初数据!$S$5:$S$14,期初数据!$P$5:$P$14,A10)+SUMIFS(采购录入!$G$4:$G$203,采购录入!$D$4:$D$203,A10,采购录入!$A$4:$A$203,"<"&EOMONTH($B$2,-1)+1)-SUMIFS(销售录入!$G$4:$G$203,销售录入!$D$4:$D$203,A10,销售录入!$A$4:$A$203,"<"&EOMONTH($B$2,-1)+1)) -> 100 | E10: =IF(A10="","",SUMIFS(采购录入!$G$4:$G$203,采购录入!$D$4:$D$203,A10,采购录入!$B$4:$B$203,TEXT($B$2,"yyyy-mm"))) -> 25 | F10: =IF(A10="","",SUMIFS(采购录入!$I$4:$I$203,采购录入!$D$4:$D$203,A10,采购录入!$B$4:$B$203,TEXT($B$2,"yyyy-mm"))) -> 2000 | G10: =IF(A10="","",SUMIFS(销售录入!$G$4:$G$203,销售录入!$D$4:$D$203,A10,销售录入!$B$4:$B$203,TEXT($B$2,"yyyy-mm"))) -> 12 | H10: =IF(A10="","",SUMIFS(销售录入!$K$4:$K$203,销售录入!$D$4:$D$203,A10,销售录入!$B$4:$B$203,TEXT($B$2,"yyyy-mm"))) -> 960 | I10: =IF(A10="","",D10+E10-G10) -> 113 | J10: =IF(A10="","",SUMIFS(期初数据!$U$5:$U$14,期初数据!$P$5:$P$14,A10)+SUMIFS(采购录入!$I$4:$I$203,采购录入!$D$4:$D$203,A10,采购录入!$A$4:$A$203,"<="&EOMONTH($B$2,0))-SUMIFS(销售录入!$K$4:$K$203,销售录入!$D$4:$D$203,A10,销售录入!$A$4:$A$203,"<="&EOMONTH($B$2,0))) -> 9040 | K10: =IF(A10="","",IFERROR(J10/I10,0)) -> 80 | L10: =IF(A10="","",SUMIFS(销售录入!$I$4:$I$203,销售录入!$D$4:$D$203,A10,销售录入!$B$4:$B$203,TEXT($B$2,"yyyy-mm"))) -> 1920 | M10: =IF(A10="","",L10-H10) -> 960 | N10: =IF(A10="","",IFERROR(IF(E10=0,0,(F10/E10)/VLOOKUP(A10,基础资料!$P$5:$T$204,5,FALSE)-1),0)) -> 0 | O10: =IF(A10="","",IFERROR(M10/L10,0)) -> 0.5 | P10: =IF(A10="","",IF(I10<0,"负库存",IF(I10=0,"零库存","正常"))) -> 正常 | Q10: =IF(A10="","",IF(P10="负库存","高风险",IF(AND(L10>0,O10<0.1),"低毛利",IF(ABS(N10)>0.2,"采购价异常","正常")))) -> 正常
A11: G配件 | B11: =IF(A11="","",IFERROR(VLOOKUP(A11,基础资料!$P$5:$R$204,2,FALSE),"")) -> G-07 | C11: =IF(A11="","",IFERROR(VLOOKUP(A11,基础资料!$P$5:$R$204,3,FALSE),"")) -> 个 | D11: =IF(A11="","",SUMIFS(期初数据!$S$5:$S$14,期初数据!$P$5:$P$14,A11)+SUMIFS(采购录入!$G$4:$G$203,采购录入!$D$4:$D$203,A11,采购录入!$A$4:$A$203,"<"&EOMONTH($B$2,-1)+1)-SUMIFS(销售录入!$G$4:$G$203,销售录入!$D$4:$D$203,A11,销售录入!$A$4:$A$203,"<"&EOMONTH($B$2,-1)+1)) -> 120 | E11: =IF(A11="","",SUMIFS(采购录入!$G$4:$G$203,采购录入!$D$4:$D$203,A11,采购录入!$B$4:$B$203,TEXT($B$2,"yyyy-mm"))) -> 20 | F11: =IF(A11="","",SUMIFS(采购录入!$I$4:$I$203,采购录入!$D$4:$D$203,A11,采购录入!$B$4:$B$203,TEXT($B$2,"yyyy-mm"))) -> 1500 | G11: =IF(A11="","",SUMIFS(销售录入!$G$4:$G$203,销售录入!$D$4:$D$203,A11,销售录入!$B$4:$B$203,TEXT($B$2,"yyyy-mm"))) -> 15 | H11: =IF(A11="","",SUMIFS(销售录入!$K$4:$K$203,销售录入!$D$4:$D$203,A11,销售录入!$B$4:$B$203,TEXT($B$2,"yyyy-mm"))) -> 1125 | I11: =IF(A11="","",D11+E11-G11) -> 125 | J11: =IF(A11="","",SUMIFS(期初数据!$U$5:$U$14,期初数据!$P$5:$P$14,A11)+SUMIFS(采购录入!$I$4:$I$203,采购录入!$D$4:$D$203,A11,采购录入!$A$4:$A$203,"<="&EOMONTH($B$2,0))-SUMIFS(销售录入!$K$4:$K$203,销售录入!$D$4:$D$203,A11,销售录入!$A$4:$A$203,"<="&EOMONTH($B$2,0))) -> 9375 | K11: =IF(A11="","",IFERROR(J11/I11,0)) -> 75 | L11: =IF(A11="","",SUMIFS(销售录入!$I$4:$I$203,销售录入!$D$4:$D$203,A11,销售录入!$B$4:$B$203,TEXT($B$2,"yyyy-mm"))) -> 2250 | M11: =IF(A11="","",L11-H11) -> 1125 | N11: =IF(A11="","",IFERROR(IF(E11=0,0,(F11/E11)/VLOOKUP(A11,基础资料!$P$5:$T$204,5,FALSE)-1),0)) -> 0 | O11: =IF(A11="","",IFERROR(M11/L11,0)) -> 0.5 | P11: =IF(A11="","",IF(I11<0,"负库存",IF(I11=0,"零库存","正常"))) -> 正常 | Q11: =IF(A11="","",IF(P11="负库存","高风险",IF(AND(L11>0,O11<0.1),"低毛利",IF(ABS(N11)>0.2,"采购价异常","正常")))) -> 正常
A12: H配件 | B12: =IF(A12="","",IFERROR(VLOOKUP(A12,基础资料!$P$5:$R$204,2,FALSE),"")) -> H-08 | C12: =IF(A12="","",IFERROR(VLOOKUP(A12,基础资料!$P$5:$R$204,3,FALSE),"")) -> 个 | D12: =IF(A12="","",SUMIFS(期初数据!$S$5:$S$14,期初数据!$P$5:$P$14,A12)+SUMIFS(采购录入!$G$4:$G$203,采购录入!$D$4:$D$203,A12,采购录入!$A$4:$A$203,"<"&EOMONTH($B$2,-1)+1)-SUMIFS(销售录入!$G$4:$G$203,销售录入!$D$4:$D$203,A12,销售录入!$A$4:$A$203,"<"&EOMONTH($B$2,-1)+1)) -> 60 | E12: =IF(A12="","",SUMIFS(采购录入!$G$4:$G$203,采购录入!$D$4:$D$203,A12,采购录入!$B$4:$B$203,TEXT($B$2,"yyyy-mm"))) -> 12 | F12: =IF(A12="","",SUMIFS(采购录入!$I$4:$I$203,采购录入!$D$4:$D$203,A12,采购录入!$B$4:$B$203,TEXT($B$2,"yyyy-mm"))) -> 1800 | G12: =IF(A12="","",SUMIFS(销售录入!$G$4:$G$203,销售录入!$D$4:$D$203,A12,销售录入!$B$4:$B$203,TEXT($B$2,"yyyy-mm"))) -> 6 | H12: =IF(A12="","",SUMIFS(销售录入!$K$4:$K$203,销售录入!$D$4:$D$203,A12,销售录入!$B$4:$B$203,TEXT($B$2,"yyyy-mm"))) -> 900 | I12: =IF(A12="","",D12+E12-G12) -> 66 | J12: =IF(A12="","",SUMIFS(期初数据!$U$5:$U$14,期初数据!$P$5:$P$14,A12)+SUMIFS(采购录入!$I$4:$I$203,采购录入!$D$4:$D$203,A12,采购录入!$A$4:$A$203,"<="&EOMONTH($B$2,0))-SUMIFS(销售录入!$K$4:$K$203,销售录入!$D$4:$D$203,A12,销售录入!$A$4:$A$203,"<="&EOMONTH($B$2,0))) -> 9900 | K12: =IF(A12="","",IFERROR(J12/I12,0)) -> 150 | L12: =IF(A12="","",SUMIFS(销售录入!$I$4:$I$203,销售录入!$D$4:$D$203,A12,销售录入!$B$4:$B$203,TEXT($B$2,"yyyy-mm"))) -> 1800 | M12: =IF(A12="","",L12-H12) -> 900 | N12: =IF(A12="","",IFERROR(IF(E12=0,0,(F12/E12)/VLOOKUP(A12,基础资料!$P$5:$T$204,5,FALSE)-1),0)) -> 0 | O12: =IF(A12="","",IFERROR(M12/L12,0)) -> 0.5 | P12: =IF(A12="","",IF(I12<0,"负库存",IF(I12=0,"零库存","正常"))) -> 正常 | Q12: =IF(A12="","",IF(P12="负库存","高风险",IF(AND(L12>0,O12<0.1),"低毛利",IF(ABS(N12)>0.2,"采购价异常","正常")))) -> 正常
A13: I配件 | B13: =IF(A13="","",IFERROR(VLOOKUP(A13,基础资料!$P$5:$R$204,2,FALSE),"")) -> I-09 | C13: =IF(A13="","",IFERROR(VLOOKUP(A13,基础资料!$P$5:$R$204,3,FALSE),"")) -> 个 | D13: =IF(A13="","",SUMIFS(期初数据!$S$5:$S$14,期初数据!$P$5:$P$14,A13)+SUMIFS(采购录入!$G$4:$G$203,采购录入!$D$4:$D$203,A13,采购录入!$A$4:$A$203,"<"&EOMONTH($B$2,-1)+1)-SUMIFS(销售录入!$G$4:$G$203,销售录入!$D$4:$D$203,A13,销售录入!$A$4:$A$203,"<"&EOMONTH($B$2,-1)+1)) -> 300 | E13: =IF(A13="","",SUMIFS(采购录入!$G$4:$G$203,采购录入!$D$4:$D$203,A13,采购录入!$B$4:$B$203,TEXT($B$2,"yyyy-mm"))) -> 40 | F13: =IF(A13="","",SUMIFS(采购录入!$I$4:$I$203,采购录入!$D$4:$D$203,A13,采购录入!$B$4:$B$203,TEXT($B$2,"yyyy-mm"))) -> 1200 | G13: =IF(A13="","",SUMIFS(销售录入!$G$4:$G$203,销售录入!$D$4:$D$203,A13,销售录入!$B$4:$B$203,TEXT($B$2,"yyyy-mm"))) -> 25 | H13: =IF(A13="","",SUMIFS(销售录入!$K$4:$K$203,销售录入!$D$4:$D$203,A13,销售录入!$B$4:$B$203,TEXT($B$2,"yyyy-mm"))) -> 750 | I13: =IF(A13="","",D13+E13-G13) -> 315 | J13: =IF(A13="","",SUMIFS(期初数据!$U$5:$U$14,期初数据!$P$5:$P$14,A13)+SUMIFS(采购录入!$I$4:$I$203,采购录入!$D$4:$D$203,A13,采购录入!$A$4:$A$203,"<="&EOMONTH($B$2,0))-SUMIFS(销售录入!$K$4:$K$203,销售录入!$D$4:$D$203,A13,销售录入!$A$4:$A$203,"<="&EOMONTH($B$2,0))) -> 9450 | K13: =IF(A13="","",IFERROR(J13/I13,0)) -> 30 | L13: =IF(A13="","",SUMIFS(销售录入!$I$4:$I$203,销售录入!$D$4:$D$203,A13,销售录入!$B$4:$B$203,TEXT($B$2,"yyyy-mm"))) -> 1500 | M13: =IF(A13="","",L13-H13) -> 750 | N13: =IF(A13="","",IFERROR(IF(E13=0,0,(F13/E13)/VLOOKUP(A13,基础资料!$P$5:$T$204,5,FALSE)-1),0)) -> 0 | O13: =IF(A13="","",IFERROR(M13/L13,0)) -> 0.5 | P13: =IF(A13="","",IF(I13<0,"负库存",IF(I13=0,"零库存","正常"))) -> 正常 | Q13: =IF(A13="","",IF(P13="负库存","高风险",IF(AND(L13>0,O13<0.1),"低毛利",IF(ABS(N13)>0.2,"采购价异常","正常")))) -> 正常
A14: J配件 | B14: =IF(A14="","",IFERROR(VLOOKUP(A14,基础资料!$P$5:$R$204,2,FALSE),"")) -> J-10 | C14: =IF(A14="","",IFERROR(VLOOKUP(A14,基础资料!$P$5:$R$204,3,FALSE),"")) -> 个 | D14: =IF(A14="","",SUMIFS(期初数据!$S$5:$S$14,期初数据!$P$5:$P$14,A14)+SUMIFS(采购录入!$G$4:$G$203,采购录入!$D$4:$D$203,A14,采购录入!$A$4:$A$203,"<"&EOMONTH($B$2,-1)+1)-SUMIFS(销售录入!$G$4:$G$203,销售录入!$D$4:$D$203,A14,销售录入!$A$4:$A$203,"<"&EOMONTH($B$2,-1)+1)) -> 250 | E14: =IF(A14="","",SUMIFS(采购录入!$G$4:$G$203,采购录入!$D$4:$D$203,A14,采购录入!$B$4:$B$203,TEXT($B$2,"yyyy-mm"))) -> 30 | F14: =IF(A14="","",SUMIFS(采购录入!$I$4:$I$203,采购录入!$D$4:$D$203,A14,采购录入!$B$4:$B$203,TEXT($B$2,"yyyy-mm"))) -> 1800 | G14: =IF(A14="","",SUMIFS(销售录入!$G$4:$G$203,销售录入!$D$4:$D$203,A14,销售录入!$B$4:$B$203,TEXT($B$2,"yyyy-mm"))) -> 18 | H14: =IF(A14="","",SUMIFS(销售录入!$K$4:$K$203,销售录入!$D$4:$D$203,A14,销售录入!$B$4:$B$203,TEXT($B$2,"yyyy-mm"))) -> 1080 | I14: =IF(A14="","",D14+E14-G14) -> 262 | J14: =IF(A14="","",SUMIFS(期初数据!$U$5:$U$14,期初数据!$P$5:$P$14,A14)+SUMIFS(采购录入!$I$4:$I$203,采购录入!$D$4:$D$203,A14,采购录入!$A$4:$A$203,"<="&EOMONTH($B$2,0))-SUMIFS(销售录入!$K$4:$K$203,销售录入!$D$4:$D$203,A14,销售录入!$A$4:$A$203,"<="&EOMONTH($B$2,0))) -> 15720 | K14: =IF(A14="","",IFERROR(J14/I14,0)) -> 60 | L14: =IF(A14="","",SUMIFS(销售录入!$I$4:$I$203,销售录入!$D$4:$D$203,A14,销售录入!$B$4:$B$203,TEXT($B$2,"yyyy-mm"))) -> 2160 | M14: =IF(A14="","",L14-H14) -> 1080 | N14: =IF(A14="","",IFERROR(IF(E14=0,0,(F14/E14)/VLOOKUP(A14,基础资料!$P$5:$T$204,5,FALSE)-1),0)) -> 0 | O14: =IF(A14="","",IFERROR(M14/L14,0)) -> 0.5 | P14: =IF(A14="","",IF(I14<0,"负库存",IF(I14=0,"零库存","正常"))) -> 正常 | Q14: =IF(A14="","",IF(P14="负库存","高风险",IF(AND(L14>0,O14<0.1),"低毛利",IF(ABS(N14)>0.2,"采购价异常","正常")))) -> 正常
B15: =IF(A15="","",IFERROR(VLOOKUP(A15,基础资料!$P$5:$R$104,2,FALSE),"")) | C15: =IF(A15="","",IFERROR(VLOOKUP(A15,基础资料!$P$5:$R$104,3,FALSE),"")) | D15: =IF(A15="","",SUMIFS(期初数据!$S$5:$S$14,期初数据!$P$5:$P$14,A15)+SUMIFS(采购录入!$G$4:$G$103,采购录入!$D$4:$D$103,A15,采购录入!$A$4:$A$103,"<"&EOMONTH($B$2,-1)+1)-SUMIFS(销售录入!$G$4:$G$103,销售录入!$D$4:$D$103,A15,销售录入!$A$4:$A$103,"<"&EOMONTH($B$2,-1)+1)) | E15: =IF(A15="","",SUMIFS(采购录入!$G$4:$G$103,采购录入!$D$4:$D$103,A15,采购录入!$B$4:$B$103,TEXT($B$2,"yyyy-mm"))) | F15: =IF(A15="","",SUMIFS(采购录入!$I$4:$I$103,采购录入!$D$4:$D$103,A15,采购录入!$B$4:$B$103,TEXT($B$2,"yyyy-mm"))) | G15: =IF(A15="","",SUMIFS(销售录入!$G$4:$G$103,销售录入!$D$4:$D$103,A15,销售录入!$B$4:$B$103,TEXT($B$2,"yyyy-mm"))) | H15: =IF(A15="","",SUMIFS(销售录入!$K$4:$K$103,销售录入!$D$4:$D$103,A15,销售录入!$B$4:$B$103,TEXT($B$2,"yyyy-mm"))) | I15: =IF(A15="","",D15+E15-G15) | J15: =IF(A15="","",SUMIFS(期初数据!$U$5:$U$14,期初数据!$P$5:$P$14,A15)+SUMIFS(采购录入!$I$4:$I$103,采购录入!$D$4:$D$103,A15,采购录入!$A$4:$A$103,"<="&EOMONTH($B$2,0))-SUMIFS(销售录入!$K$4:$K$103,销售录入!$D$4:$D$103,A15,销售录入!$A$4:$A$103,"<="&EOMONTH($B$2,0))) | K15: =IF(A15="","",IFERROR(J15/I15,0)) | L15: =IF(A15="","",SUMIFS(销售录入!$I$4:$I$103,销售录入!$D$4:$D$103,A15,销售录入!$B$4:$B$103,TEXT($B$2,"yyyy-mm"))) | M15: =IF(A15="","",L15-H15) | N15: =IF(A15="","",IFERROR(IF(E15=0,0,(F15/E15)/VLOOKUP(A15,基础资料!$P$5:$T$104,5,FALSE)-1),0)) | O15: =IF(A15="","",IFERROR(M15/L15,0)) | P15: =IF(A15="","",IF(I15<0,"负库存",IF(I15=0,"零库存","正常"))) | Q15: =IF(A15="","",IF(P15="负库存","高风险",IF(AND(L15>0,O15<0.1),"低毛利",IF(ABS(N15)>0.2,"采购价异常","正常"))))
B16: =IF(A16="","",IFERROR(VLOOKUP(A16,基础资料!$P$5:$R$104,2,FALSE),"")) | C16: =IF(A16="","",IFERROR(VLOOKUP(A16,基础资料!$P$5:$R$104,3,FALSE),"")) | D16: =IF(A16="","",SUMIFS(期初数据!$S$5:$S$14,期初数据!$P$5:$P$14,A16)+SUMIFS(采购录入!$G$4:$G$103,采购录入!$D$4:$D$103,A16,采购录入!$A$4:$A$103,"<"&EOMONTH($B$2,-1)+1)-SUMIFS(销售录入!$G$4:$G$103,销售录入!$D$4:$D$103,A16,销售录入!$A$4:$A$103,"<"&EOMONTH($B$2,-1)+1)) | E16: =IF(A16="","",SUMIFS(采购录入!$G$4:$G$103,采购录入!$D$4:$D$103,A16,采购录入!$B$4:$B$103,TEXT($B$2,"yyyy-mm"))) | F16: =IF(A16="","",SUMIFS(采购录入!$I$4:$I$103,采购录入!$D$4:$D$103,A16,采购录入!$B$4:$B$103,TEXT($B$2,"yyyy-mm"))) | G16: =IF(A16="","",SUMIFS(销售录入!$G$4:$G$103,销售录入!$D$4:$D$103,A16,销售录入!$B$4:$B$103,TEXT($B$2,"yyyy-mm"))) | H16: =IF(A16="","",SUMIFS(销售录入!$K$4:$K$103,销售录入!$D$4:$D$103,A16,销售录入!$B$4:$B$103,TEXT($B$2,"yyyy-mm"))) | I16: =IF(A16="","",D16+E16-G16) | J16: =IF(A16="","",SUMIFS(期初数据!$U$5:$U$14,期初数据!$P$5:$P$14,A16)+SUMIFS(采购录入!$I$4:$I$103,采购录入!$D$4:$D$103,A16,采购录入!$A$4:$A$103,"<="&EOMONTH($B$2,0))-SUMIFS(销售录入!$K$4:$K$103,销售录入!$D$4:$D$103,A16,销售录入!$A$4:$A$103,"<="&EOMONTH($B$2,0))) | K16: =IF(A16="","",IFERROR(J16/I16,0)) | L16: =IF(A16="","",SUMIFS(销售录入!$I$4:$I$103,销售录入!$D$4:$D$103,A16,销售录入!$B$4:$B$103,TEXT($B$2,"yyyy-mm"))) | M16: =IF(A16="","",L16-H16) | N16: =IF(A16="","",IFERROR(IF(E16=0,0,(F16/E16)/VLOOKUP(A16,基础资料!$P$5:$T$104,5,FALSE)-1),0)) | O16: =IF(A16="","",IFERROR(M16/L16,0)) | P16: =IF(A16="","",IF(I16<0,"负库存",IF(I16=0,"零库存","正常"))) | Q16: =IF(A16="","",IF(P16="负库存","高风险",IF(AND(L16>0,O16<0.1),"低毛利",IF(ABS(N16)>0.2,"采购价异常","正常"))))
B17: =IF(A17="","",IFERROR(VLOOKUP(A17,基础资料!$P$5:$R$104,2,FALSE),"")) | C17: =IF(A17="","",IFERROR(VLOOKUP(A17,基础资料!$P$5:$R$104,3,FALSE),"")) | D17: =IF(A17="","",SUMIFS(期初数据!$S$5:$S$14,期初数据!$P$5:$P$14,A17)+SUMIFS(采购录入!$G$4:$G$103,采购录入!$D$4:$D$103,A17,采购录入!$A$4:$A$103,"<"&EOMONTH($B$2,-1)+1)-SUMIFS(销售录入!$G$4:$G$103,销售录入!$D$4:$D$103,A17,销售录入!$A$4:$A$103,"<"&EOMONTH($B$2,-1)+1)) | E17: =IF(A17="","",SUMIFS(采购录入!$G$4:$G$103,采购录入!$D$4:$D$103,A17,采购录入!$B$4:$B$103,TEXT($B$2,"yyyy-mm"))) | F17: =IF(A17="","",SUMIFS(采购录入!$I$4:$I$103,采购录入!$D$4:$D$103,A17,采购录入!$B$4:$B$103,TEXT($B$2,"yyyy-mm"))) | G17: =IF(A17="","",SUMIFS(销售录入!$G$4:$G$103,销售录入!$D$4:$D$103,A17,销售录入!$B$4:$B$103,TEXT($B$2,"yyyy-mm"))) | H17: =IF(A17="","",SUMIFS(销售录入!$K$4:$K$103,销售录入!$D$4:$D$103,A17,销售录入!$B$4:$B$103,TEXT($B$2,"yyyy-mm"))) | I17: =IF(A17="","",D17+E17-G17) | J17: =IF(A17="","",SUMIFS(期初数据!$U$5:$U$14,期初数据!$P$5:$P$14,A17)+SUMIFS(采购录入!$I$4:$I$103,采购录入!$D$4:$D$103,A17,采购录入!$A$4:$A$103,"<="&EOMONTH($B$2,0))-SUMIFS(销售录入!$K$4:$K$103,销售录入!$D$4:$D$103,A17,销售录入!$A$4:$A$103,"<="&EOMONTH($B$2,0))) | K17: =IF(A17="","",IFERROR(J17/I17,0)) | L17: =IF(A17="","",SUMIFS(销售录入!$I$4:$I$103,销售录入!$D$4:$D$103,A17,销售录入!$B$4:$B$103,TEXT($B$2,"yyyy-mm"))) | M17: =IF(A17="","",L17-H17) | N17: =IF(A17="","",IFERROR(IF(E17=0,0,(F17/E17)/VLOOKUP(A17,基础资料!$P$5:$T$104,5,FALSE)-1),0)) | O17: =IF(A17="","",IFERROR(M17/L17,0)) | P17: =IF(A17="","",IF(I17<0,"负库存",IF(I17=0,"零库存","正常"))) | Q17: =IF(A17="","",IF(P17="负库存","高风险",IF(AND(L17>0,O17<0.1),"低毛利",IF(ABS(N17)>0.2,"采购价异常","正常"))))
B18: =IF(A18="","",IFERROR(VLOOKUP(A18,基础资料!$P$5:$R$104,2,FALSE),"")) | C18: =IF(A18="","",IFERROR(VLOOKUP(A18,基础资料!$P$5:$R$104,3,FALSE),"")) | D18: =IF(A18="","",SUMIFS(期初数据!$S$5:$S$14,期初数据!$P$5:$P$14,A18)+SUMIFS(采购录入!$G$4:$G$103,采购录入!$D$4:$D$103,A18,采购录入!$A$4:$A$103,"<"&EOMONTH($B$2,-1)+1)-SUMIFS(销售录入!$G$4:$G$103,销售录入!$D$4:$D$103,A18,销售录入!$A$4:$A$103,"<"&EOMONTH($B$2,-1)+1)) | E18: =IF(A18="","",SUMIFS(采购录入!$G$4:$G$103,采购录入!$D$4:$D$103,A18,采购录入!$B$4:$B$103,TEXT($B$2,"yyyy-mm"))) | F18: =IF(A18="","",SUMIFS(采购录入!$I$4:$I$103,采购录入!$D$4:$D$103,A18,采购录入!$B$4:$B$103,TEXT($B$2,"yyyy-mm"))) | G18: =IF(A18="","",SUMIFS(销售录入!$G$4:$G$103,销售录入!$D$4:$D$103,A18,销售录入!$B$4:$B$103,TEXT($B$2,"yyyy-mm"))) | H18: =IF(A18="","",SUMIFS(销售录入!$K$4:$K$103,销售录入!$D$4:$D$103,A18,销售录入!$B$4:$B$103,TEXT($B$2,"yyyy-mm"))) | I18: =IF(A18="","",D18+E18-G18) | J18: =IF(A18="","",SUMIFS(期初数据!$U$5:$U$14,期初数据!$P$5:$P$14,A18)+SUMIFS(采购录入!$I$4:$I$103,采购录入!$D$4:$D$103,A18,采购录入!$A$4:$A$103,"<="&EOMONTH($B$2,0))-SUMIFS(销售录入!$K$4:$K$103,销售录入!$D$4:$D$103,A18,销售录入!$A$4:$A$103,"<="&EOMONTH($B$2,0))) | K18: =IF(A18="","",IFERROR(J18/I18,0)) | L18: =IF(A18="","",SUMIFS(销售录入!$I$4:$I$103,销售录入!$D$4:$D$103,A18,销售录入!$B$4:$B$103,TEXT($B$2,"yyyy-mm"))) | M18: =IF(A18="","",L18-H18) | N18: =IF(A18="","",IFERROR(IF(E18=0,0,(F18/E18)/VLOOKUP(A18,基础资料!$P$5:$T$104,5,FALSE)-1),0)) | O18: =IF(A18="","",IFERROR(M18/L18,0)) | P18: =IF(A18="","",IF(I18<0,"负库存",IF(I18=0,"零库存","正常"))) | Q18: =IF(A18="","",IF(P18="负库存","高风险",IF(AND(L18>0,O18<0.1),"低毛利",IF(ABS(N18)>0.2,"采购价异常","正常"))))
B19: =IF(A19="","",IFERROR(VLOOKUP(A19,基础资料!$P$5:$R$104,2,FALSE),"")) | C19: =IF(A19="","",IFERROR(VLOOKUP(A19,基础资料!$P$5:$R$104,3,FALSE),"")) | D19: =IF(A19="","",SUMIFS(期初数据!$S$5:$S$14,期初数据!$P$5:$P$14,A19)+SUMIFS(采购录入!$G$4:$G$103,采购录入!$D$4:$D$103,A19,采购录入!$A$4:$A$103,"<"&EOMONTH($B$2,-1)+1)-SUMIFS(销售录入!$G$4:$G$103,销售录入!$D$4:$D$103,A19,销售录入!$A$4:$A$103,"<"&EOMONTH($B$2,-1)+1)) | E19: =IF(A19="","",SUMIFS(采购录入!$G$4:$G$103,采购录入!$D$4:$D$103,A19,采购录入!$B$4:$B$103,TEXT($B$2,"yyyy-mm"))) | F19: =IF(A19="","",SUMIFS(采购录入!$I$4:$I$103,采购录入!$D$4:$D$103,A19,采购录入!$B$4:$B$103,TEXT($B$2,"yyyy-mm"))) | G19: =IF(A19="","",SUMIFS(销售录入!$G$4:$G$103,销售录入!$D$4:$D$103,A19,销售录入!$B$4:$B$103,TEXT($B$2,"yyyy-mm"))) | H19: =IF(A19="","",SUMIFS(销售录入!$K$4:$K$103,销售录入!$D$4:$D$103,A19,销售录入!$B$4:$B$103,TEXT($B$2,"yyyy-mm"))) | I19: =IF(A19="","",D19+E19-G19) | J19: =IF(A19="","",SUMIFS(期初数据!$U$5:$U$14,期初数据!$P$5:$P$14,A19)+SUMIFS(采购录入!$I$4:$I$103,采购录入!$D$4:$D$103,A19,采购录入!$A$4:$A$103,"<="&EOMONTH($B$2,0))-SUMIFS(销售录入!$K$4:$K$103,销售录入!$D$4:$D$103,A19,销售录入!$A$4:$A$103,"<="&EOMONTH($B$2,0))) | K19: =IF(A19="","",IFERROR(J19/I19,0)) | L19: =IF(A19="","",SUMIFS(销售录入!$I$4:$I$103,销售录入!$D$4:$D$103,A19,销售录入!$B$4:$B$103,TEXT($B$2,"yyyy-mm"))) | M19: =IF(A19="","",L19-H19) | N19: =IF(A19="","",IFERROR(IF(E19=0,0,(F19/E19)/VLOOKUP(A19,基础资料!$P$5:$T$104,5,FALSE)-1),0)) | O19: =IF(A19="","",IFERROR(M19/L19,0)) | P19: =IF(A19="","",IF(I19<0,"负库存",IF(I19=0,"零库存","正常"))) | Q19: =IF(A19="","",IF(P19="负库存","高风险",IF(AND(L19>0,O19<0.1),"低毛利",IF(ABS(N19)>0.2,"采购价异常","正常"))))
B20: =IF(A20="","",IFERROR(VLOOKUP(A20,基础资料!$P$5:$R$104,2,FALSE),"")) | C20: =IF(A20="","",IFERROR(VLOOKUP(A20,基础资料!$P$5:$R$104,3,FALSE),"")) | D20: =IF(A20="","",SUMIFS(期初数据!$S$5:$S$14,期初数据!$P$5:$P$14,A20)+SUMIFS(采购录入!$G$4:$G$103,采购录入!$D$4:$D$103,A20,采购录入!$A$4:$A$103,"<"&EOMONTH($B$2,-1)+1)-SUMIFS(销售录入!$G$4:$G$103,销售录入!$D$4:$D$103,A20,销售录入!$A$4:$A$103,"<"&EOMONTH($B$2,-1)+1)) | E20: =IF(A20="","",SUMIFS(采购录入!$G$4:$G$103,采购录入!$D$4:$D$103,A20,采购录入!$B$4:$B$103,TEXT($B$2,"yyyy-mm"))) | F20: =IF(A20="","",SUMIFS(采购录入!$I$4:$I$103,采购录入!$D$4:$D$103,A20,采购录入!$B$4:$B$103,TEXT($B$2,"yyyy-mm"))) | G20: =IF(A20="","",SUMIFS(销售录入!$G$4:$G$103,销售录入!$D$4:$D$103,A20,销售录入!$B$4:$B$103,TEXT($B$2,"yyyy-mm"))) | H20: =IF(A20="","",SUMIFS(销售录入!$K$4:$K$103,销售录入!$D$4:$D$103,A20,销售录入!$B$4:$B$103,TEXT($B$2,"yyyy-mm"))) | I20: =IF(A20="","",D20+E20-G20) | J20: =IF(A20="","",SUMIFS(期初数据!$U$5:$U$14,期初数据!$P$5:$P$14,A20)+SUMIFS(采购录入!$I$4:$I$103,采购录入!$D$4:$D$103,A20,采购录入!$A$4:$A$103,"<="&EOMONTH($B$2,0))-SUMIFS(销售录入!$K$4:$K$103,销售录入!$D$4:$D$103,A20,销售录入!$A$4:$A$103,"<="&EOMONTH($B$2,0))) | K20: =IF(A20="","",IFERROR(J20/I20,0)) | L20: =IF(A20="","",SUMIFS(销售录入!$I$4:$I$103,销售录入!$D$4:$D$103,A20,销售录入!$B$4:$B$103,TEXT($B$2,"yyyy-mm"))) | M20: =IF(A20="","",L20-H20) | N20: =IF(A20="","",IFERROR(IF(E20=0,0,(F20/E20)/VLOOKUP(A20,基础资料!$P$5:$T$104,5,FALSE)-1),0)) | O20: =IF(A20="","",IFERROR(M20/L20,0)) | P20: =IF(A20="","",IF(I20<0,"负库存",IF(I20=0,"零库存","正常"))) | Q20: =IF(A20="","",IF(P20="负库存","高风险",IF(AND(L20>0,O20<0.1),"低毛利",IF(ABS(N20)>0.2,"采购价异常","正常"))))
B21: =IF(A21="","",IFERROR(VLOOKUP(A21,基础资料!$P$5:$R$104,2,FALSE),"")) | C21: =IF(A21="","",IFERROR(VLOOKUP(A21,基础资料!$P$5:$R$104,3,FALSE),"")) | D21: =IF(A21="","",SUMIFS(期初数据!$S$5:$S$14,期初数据!$P$5:$P$14,A21)+SUMIFS(采购录入!$G$4:$G$103,采购录入!$D$4:$D$103,A21,采购录入!$A$4:$A$103,"<"&EOMONTH($B$2,-1)+1)-SUMIFS(销售录入!$G$4:$G$103,销售录入!$D$4:$D$103,A21,销售录入!$A$4:$A$103,"<"&EOMONTH($B$2,-1)+1)) | E21: =IF(A21="","",SUMIFS(采购录入!$G$4:$G$103,采购录入!$D$4:$D$103,A21,采购录入!$B$4:$B$103,TEXT($B$2,"yyyy-mm"))) | F21: =IF(A21="","",SUMIFS(采购录入!$I$4:$I$103,采购录入!$D$4:$D$103,A21,采购录入!$B$4:$B$103,TEXT($B$2,"yyyy-mm"))) | G21: =IF(A21="","",SUMIFS(销售录入!$G$4:$G$103,销售录入!$D$4:$D$103,A21,销售录入!$B$4:$B$103,TEXT($B$2,"yyyy-mm"))) | H21: =IF(A21="","",SUMIFS(销售录入!$K$4:$K$103,销售录入!$D$4:$D$103,A21,销售录入!$B$4:$B$103,TEXT($B$2,"yyyy-mm"))) | I21: =IF(A21="","",D21+E21-G21) | J21: =IF(A21="","",SUMIFS(期初数据!$U$5:$U$14,期初数据!$P$5:$P$14,A21)+SUMIFS(采购录入!$I$4:$I$103,采购录入!$D$4:$D$103,A21,采购录入!$A$4:$A$103,"<="&EOMONTH($B$2,0))-SUMIFS(销售录入!$K$4:$K$103,销售录入!$D$4:$D$103,A21,销售录入!$A$4:$A$103,"<="&EOMONTH($B$2,0))) | K21: =IF(A21="","",IFERROR(J21/I21,0)) | L21: =IF(A21="","",SUMIFS(销售录入!$I$4:$I$103,销售录入!$D$4:$D$103,A21,销售录入!$B$4:$B$103,TEXT($B$2,"yyyy-mm"))) | M21: =IF(A21="","",L21-H21) | N21: =IF(A21="","",IFERROR(IF(E21=0,0,(F21/E21)/VLOOKUP(A21,基础资料!$P$5:$T$104,5,FALSE)-1),0)) | O21: =IF(A21="","",IFERROR(M21/L21,0)) | P21: =IF(A21="","",IF(I21<0,"负库存",IF(I21=0,"零库存","正常"))) | Q21: =IF(A21="","",IF(P21="负库存","高风险",IF(AND(L21>0,O21<0.1),"低毛利",IF(ABS(N21)>0.2,"采购价异常","正常"))))
B22: =IF(A22="","",IFERROR(VLOOKUP(A22,基础资料!$P$5:$R$104,2,FALSE),"")) | C22: =IF(A22="","",IFERROR(VLOOKUP(A22,基础资料!$P$5:$R$104,3,FALSE),"")) | D22: =IF(A22="","",SUMIFS(期初数据!$S$5:$S$14,期初数据!$P$5:$P$14,A22)+SUMIFS(采购录入!$G$4:$G$103,采购录入!$D$4:$D$103,A22,采购录入!$A$4:$A$103,"<"&EOMONTH($B$2,-1)+1)-SUMIFS(销售录入!$G$4:$G$103,销售录入!$D$4:$D$103,A22,销售录入!$A$4:$A$103,"<"&EOMONTH($B$2,-1)+1)) | E22: =IF(A22="","",SUMIFS(采购录入!$G$4:$G$103,采购录入!$D$4:$D$103,A22,采购录入!$B$4:$B$103,TEXT($B$2,"yyyy-mm"))) | F22: =IF(A22="","",SUMIFS(采购录入!$I$4:$I$103,采购录入!$D$4:$D$103,A22,采购录入!$B$4:$B$103,TEXT($B$2,"yyyy-mm"))) | G22: =IF(A22="","",SUMIFS(销售录入!$G$4:$G$103,销售录入!$D$4:$D$103,A22,销售录入!$B$4:$B$103,TEXT($B$2,"yyyy-mm"))) | H22: =IF(A22="","",SUMIFS(销售录入!$K$4:$K$103,销售录入!$D$4:$D$103,A22,销售录入!$B$4:$B$103,TEXT($B$2,"yyyy-mm"))) | I22: =IF(A22="","",D22+E22-G22) | J22: =IF(A22="","",SUMIFS(期初数据!$U$5:$U$14,期初数据!$P$5:$P$14,A22)+SUMIFS(采购录入!$I$4:$I$103,采购录入!$D$4:$D$103,A22,采购录入!$A$4:$A$103,"<="&EOMONTH($B$2,0))-SUMIFS(销售录入!$K$4:$K$103,销售录入!$D$4:$D$103,A22,销售录入!$A$4:$A$103,"<="&EOMONTH($B$2,0))) | K22: =IF(A22="","",IFERROR(J22/I22,0)) | L22: =IF(A22="","",SUMIFS(销售录入!$I$4:$I$103,销售录入!$D$4:$D$103,A22,销售录入!$B$4:$B$103,TEXT($B$2,"yyyy-mm"))) | M22: =IF(A22="","",L22-H22) | N22: =IF(A22="","",IFERROR(IF(E22=0,0,(F22/E22)/VLOOKUP(A22,基础资料!$P$5:$T$104,5,FALSE)-1),0)) | O22: =IF(A22="","",IFERROR(M22/L22,0)) | P22: =IF(A22="","",IF(I22<0,"负库存",IF(I22=0,"零库存","正常"))) | Q22: =IF(A22="","",IF(P22="负库存","高风险",IF(AND(L22>0,O22<0.1),"低毛利",IF(ABS(N22)>0.2,"采购价异常","正常"))))
B23: =IF(A23="","",IFERROR(VLOOKUP(A23,基础资料!$P$5:$R$104,2,FALSE),"")) | C23: =IF(A23="","",IFERROR(VLOOKUP(A23,基础资料!$P$5:$R$104,3,FALSE),"")) | D23: =IF(A23="","",SUMIFS(期初数据!$S$5:$S$14,期初数据!$P$5:$P$14,A23)+SUMIFS(采购录入!$G$4:$G$103,采购录入!$D$4:$D$103,A23,采购录入!$A$4:$A$103,"<"&EOMONTH($B$2,-1)+1)-SUMIFS(销售录入!$G$4:$G$103,销售录入!$D$4:$D$103,A23,销售录入!$A$4:$A$103,"<"&EOMONTH($B$2,-1)+1)) | E23: =IF(A23="","",SUMIFS(采购录入!$G$4:$G$103,采购录入!$D$4:$D$103,A23,采购录入!$B$4:$B$103,TEXT($B$2,"yyyy-mm"))) | F23: =IF(A23="","",SUMIFS(采购录入!$I$4:$I$103,采购录入!$D$4:$D$103,A23,采购录入!$B$4:$B$103,TEXT($B$2,"yyyy-mm"))) | G23: =IF(A23="","",SUMIFS(销售录入!$G$4:$G$103,销售录入!$D$4:$D$103,A23,销售录入!$B$4:$B$103,TEXT($B$2,"yyyy-mm"))) | H23: =IF(A23="","",SUMIFS(销售录入!$K$4:$K$103,销售录入!$D$4:$D$103,A23,销售录入!$B$4:$B$103,TEXT($B$2,"yyyy-mm"))) | I23: =IF(A23="","",D23+E23-G23) | J23: =IF(A23="","",SUMIFS(期初数据!$U$5:$U$14,期初数据!$P$5:$P$14,A23)+SUMIFS(采购录入!$I$4:$I$103,采购录入!$D$4:$D$103,A23,采购录入!$A$4:$A$103,"<="&EOMONTH($B$2,0))-SUMIFS(销售录入!$K$4:$K$103,销售录入!$D$4:$D$103,A23,销售录入!$A$4:$A$103,"<="&EOMONTH($B$2,0))) | K23: =IF(A23="","",IFERROR(J23/I23,0)) | L23: =IF(A23="","",SUMIFS(销售录入!$I$4:$I$103,销售录入!$D$4:$D$103,A23,销售录入!$B$4:$B$103,TEXT($B$2,"yyyy-mm"))) | M23: =IF(A23="","",L23-H23) | N23: =IF(A23="","",IFERROR(IF(E23=0,0,(F23/E23)/VLOOKUP(A23,基础资料!$P$5:$T$104,5,FALSE)-1),0)) | O23: =IF(A23="","",IFERROR(M23/L23,0)) | P23: =IF(A23="","",IF(I23<0,"负库存",IF(I23=0,"零库存","正常"))) | Q23: =IF(A23="","",IF(P23="负库存","高风险",IF(AND(L23>0,O23<0.1),"低毛利",IF(ABS(N23)>0.2,"采购价异常","正常"))))
B24: =IF(A24="","",IFERROR(VLOOKUP(A24,基础资料!$P$5:$R$104,2,FALSE),"")) | C24: =IF(A24="","",IFERROR(VLOOKUP(A24,基础资料!$P$5:$R$104,3,FALSE),"")) | D24: =IF(A24="","",SUMIFS(期初数据!$S$5:$S$14,期初数据!$P$5:$P$14,A24)+SUMIFS(采购录入!$G$4:$G$103,采购录入!$D$4:$D$103,A24,采购录入!$A$4:$A$103,"<"&EOMONTH($B$2,-1)+1)-SUMIFS(销售录入!$G$4:$G$103,销售录入!$D$4:$D$103,A24,销售录入!$A$4:$A$103,"<"&EOMONTH($B$2,-1)+1)) | E24: =IF(A24="","",SUMIFS(采购录入!$G$4:$G$103,采购录入!$D$4:$D$103,A24,采购录入!$B$4:$B$103,TEXT($B$2,"yyyy-mm"))) | F24: =IF(A24="","",SUMIFS(采购录入!$I$4:$I$103,采购录入!$D$4:$D$103,A24,采购录入!$B$4:$B$103,TEXT($B$2,"yyyy-mm"))) | G24: =IF(A24="","",SUMIFS(销售录入!$G$4:$G$103,销售录入!$D$4:$D$103,A24,销售录入!$B$4:$B$103,TEXT($B$2,"yyyy-mm"))) | H24: =IF(A24="","",SUMIFS(销售录入!$K$4:$K$103,销售录入!$D$4:$D$103,A24,销售录入!$B$4:$B$103,TEXT($B$2,"yyyy-mm"))) | I24: =IF(A24="","",D24+E24-G24) | J24: =IF(A24="","",SUMIFS(期初数据!$U$5:$U$14,期初数据!$P$5:$P$14,A24)+SUMIFS(采购录入!$I$4:$I$103,采购录入!$D$4:$D$103,A24,采购录入!$A$4:$A$103,"<="&EOMONTH($B$2,0))-SUMIFS(销售录入!$K$4:$K$103,销售录入!$D$4:$D$103,A24,销售录入!$A$4:$A$103,"<="&EOMONTH($B$2,0))) | K24: =IF(A24="","",IFERROR(J24/I24,0)) | L24: =IF(A24="","",SUMIFS(销售录入!$I$4:$I$103,销售录入!$D$4:$D$103,A24,销售录入!$B$4:$B$103,TEXT($B$2,"yyyy-mm"))) | M24: =IF(A24="","",L24-H24) | N24: =IF(A24="","",IFERROR(IF(E24=0,0,(F24/E24)/VLOOKUP(A24,基础资料!$P$5:$T$104,5,FALSE)-1),0)) | O24: =IF(A24="","",IFERROR(M24/L24,0)) | P24: =IF(A24="","",IF(I24<0,"负库存",IF(I24=0,"零库存","正常"))) | Q24: =IF(A24="","",IF(P24="负库存","高风险",IF(AND(L24>0,O24<0.1),"低毛利",IF(ABS(N24)>0.2,"采购价异常","正常"))))
B25: =IF(A25="","",IFERROR(VLOOKUP(A25,基础资料!$P$5:$R$104,2,FALSE),"")) | C25: =IF(A25="","",IFERROR(VLOOKUP(A25,基础资料!$P$5:$R$104,3,FALSE),"")) | D25: =IF(A25="","",SUMIFS(期初数据!$S$5:$S$14,期初数据!$P$5:$P$14,A25)+SUMIFS(采购录入!$G$4:$G$103,采购录入!$D$4:$D$103,A25,采购录入!$A$4:$A$103,"<"&EOMONTH($B$2,-1)+1)-SUMIFS(销售录入!$G$4:$G$103,销售录入!$D$4:$D$103,A25,销售录入!$A$4:$A$103,"<"&EOMONTH($B$2,-1)+1)) | E25: =IF(A25="","",SUMIFS(采购录入!$G$4:$G$103,采购录入!$D$4:$D$103,A25,采购录入!$B$4:$B$103,TEXT($B$2,"yyyy-mm"))) | F25: =IF(A25="","",SUMIFS(采购录入!$I$4:$I$103,采购录入!$D$4:$D$103,A25,采购录入!$B$4:$B$103,TEXT($B$2,"yyyy-mm"))) | G25: =IF(A25="","",SUMIFS(销售录入!$G$4:$G$103,销售录入!$D$4:$D$103,A25,销售录入!$B$4:$B$103,TEXT($B$2,"yyyy-mm"))) | H25: =IF(A25="","",SUMIFS(销售录入!$K$4:$K$103,销售录入!$D$4:$D$103,A25,销售录入!$B$4:$B$103,TEXT($B$2,"yyyy-mm"))) | I25: =IF(A25="","",D25+E25-G25) | J25: =IF(A25="","",SUMIFS(期初数据!$U$5:$U$14,期初数据!$P$5:$P$14,A25)+SUMIFS(采购录入!$I$4:$I$103,采购录入!$D$4:$D$103,A25,采购录入!$A$4:$A$103,"<="&EOMONTH($B$2,0))-SUMIFS(销售录入!$K$4:$K$103,销售录入!$D$4:$D$103,A25,销售录入!$A$4:$A$103,"<="&EOMONTH($B$2,0))) | K25: =IF(A25="","",IFERROR(J25/I25,0)) | L25: =IF(A25="","",SUMIFS(销售录入!$I$4:$I$103,销售录入!$D$4:$D$103,A25,销售录入!$B$4:$B$103,TEXT($B$2,"yyyy-mm"))) | M25: =IF(A25="","",L25-H25) | N25: =IF(A25="","",IFERROR(IF(E25=0,0,(F25/E25)/VLOOKUP(A25,基础资料!$P$5:$T$104,5,FALSE)-1),0)) | O25: =IF(A25="","",IFERROR(M25/L25,0)) | P25: =IF(A25="","",IF(I25<0,"负库存",IF(I25=0,"零库存","正常"))) | Q25: =IF(A25="","",IF(P25="负库存","高风险",IF(AND(L25>0,O25<0.1),"低毛利",IF(ABS(N25)>0.2,"采购价异常","正常"))))
B26: =IF(A26="","",IFERROR(VLOOKUP(A26,基础资料!$P$5:$R$104,2,FALSE),"")) | C26: =IF(A26="","",IFERROR(VLOOKUP(A26,基础资料!$P$5:$R$104,3,FALSE),"")) | D26: =IF(A26="","",SUMIFS(期初数据!$S$5:$S$14,期初数据!$P$5:$P$14,A26)+SUMIFS(采购录入!$G$4:$G$103,采购录入!$D$4:$D$103,A26,采购录入!$A$4:$A$103,"<"&EOMONTH($B$2,-1)+1)-SUMIFS(销售录入!$G$4:$G$103,销售录入!$D$4:$D$103,A26,销售录入!$A$4:$A$103,"<"&EOMONTH($B$2,-1)+1)) | E26: =IF(A26="","",SUMIFS(采购录入!$G$4:$G$103,采购录入!$D$4:$D$103,A26,采购录入!$B$4:$B$103,TEXT($B$2,"yyyy-mm"))) | F26: =IF(A26="","",SUMIFS(采购录入!$I$4:$I$103,采购录入!$D$4:$D$103,A26,采购录入!$B$4:$B$103,TEXT($B$2,"yyyy-mm"))) | G26: =IF(A26="","",SUMIFS(销售录入!$G$4:$G$103,销售录入!$D$4:$D$103,A26,销售录入!$B$4:$B$103,TEXT($B$2,"yyyy-mm"))) | H26: =IF(A26="","",SUMIFS(销售录入!$K$4:$K$103,销售录入!$D$4:$D$103,A26,销售录入!$B$4:$B$103,TEXT($B$2,"yyyy-mm"))) | I26: =IF(A26="","",D26+E26-G26) | J26: =IF(A26="","",SUMIFS(期初数据!$U$5:$U$14,期初数据!$P$5:$P$14,A26)+SUMIFS(采购录入!$I$4:$I$103,采购录入!$D$4:$D$103,A26,采购录入!$A$4:$A$103,"<="&EOMONTH($B$2,0))-SUMIFS(销售录入!$K$4:$K$103,销售录入!$D$4:$D$103,A26,销售录入!$A$4:$A$103,"<="&EOMONTH($B$2,0))) | K26: =IF(A26="","",IFERROR(J26/I26,0)) | L26: =IF(A26="","",SUMIFS(销售录入!$I$4:$I$103,销售录入!$D$4:$D$103,A26,销售录入!$B$4:$B$103,TEXT($B$2,"yyyy-mm"))) | M26: =IF(A26="","",L26-H26) | N26: =IF(A26="","",IFERROR(IF(E26=0,0,(F26/E26)/VLOOKUP(A26,基础资料!$P$5:$T$104,5,FALSE)-1),0)) | O26: =IF(A26="","",IFERROR(M26/L26,0)) | P26: =IF(A26="","",IF(I26<0,"负库存",IF(I26=0,"零库存","正常"))) | Q26: =IF(A26="","",IF(P26="负库存","高风险",IF(AND(L26>0,O26<0.1),"低毛利",IF(ABS(N26)>0.2,"采购价异常","正常"))))
... B104: =IF(A104="","",IFERROR(VLOOKUP(A104,基础资料!$P$5:$R$104,2,FALSE),"")) | C104: =IF(A104="","",IFERROR(VLOOKUP(A104,基础资料!$P$5:$R$104,3,FALSE),"")) | D104: =IF(A104="","",SUMIFS(期初数据!$S$5:$S$14,期初数据!$P$5:$P$14,A104)+SUMIFS(采购录入!$G$4:$G$103,采购录入!$D$4:$D$103,A104,采购录入!$A$4:$A$103,"<"&EOMONTH($B$2,-1)+1)-SUMIFS(销售录入!$G$4:$G$103,销售录入!$D$4:$D$103,A104,销售录入!$A$4:$A$103,"<"&EOMONTH($B$2,-1)+1)) | E104: =IF(A104="","",SUMIFS(采购录入!$G$4:$G$103,采购录入!$D$4:$D$103,A104,采购录入!$B$4:$B$103,TEXT($B$2,"yyyy-mm"))) | F104: =IF(A104="","",SUMIFS(采购录入!$I$4:$I$103,采购录入!$D$4:$D$103,A104,采购录入!$B$4:$B$103,TEXT($B$2,"yyyy-mm"))) | G104: =IF(A104="","",SUMIFS(销售录入!$G$4:$G$103,销售录入!$D$4:$D$103,A104,销售录入!$B$4:$B$103,TEXT($B$2,"yyyy-mm"))) | H104: =IF(A104="","",SUMIFS(销售录入!$K$4:$K$103,销售录入!$D$4:$D$103,A104,销售录入!$B$4:$B$103,TEXT($B$2,"yyyy-mm"))) | I104: =IF(A104="","",D104+E104-G104) | J104: =IF(A104="","",SUMIFS(期初数据!$U$5:$U$14,期初数据!$P$5:$P$14,A104)+SUMIFS(采购录入!$I$4:$I$103,采购录入!$D$4:$D$103,A104,采购录入!$A$4:$A$103,"<="&EOMONTH($B$2,0))-SUMIFS(销售录入!$K$4:$K$103,销售录入!$D$4:$D$103,A104,销售录入!$A$4:$A$103,"<="&EOMONTH($B$2,0))) | K104: =IF(A104="","",IFERROR(J104/I104,0)) | L104: =IF(A104="","",SUMIFS(销售录入!$I$4:$I$103,销售录入!$D$4:$D$103,A104,销售录入!$B$4:$B$103,TEXT($B$2,"yyyy-mm"))) | M104: =IF(A104="","",L104-H104) | N104: =IF(A104="","",IFERROR(IF(E104=0,0,(F104/E104)/VLOOKUP(A104,基础资料!$P$5:$T$104,5,FALSE)-1),0)) | O104: =IF(A104="","",IFERROR(M104/L104,0)) | P104: =IF(A104="","",IF(I104<0,"负库存",IF(I104=0,"零库存","正常"))) | Q104: =IF(A104="","",IF(P104="负库存","高风险",IF(AND(L104>0,O104<0.1),"低毛利",IF(ABS(N104)>0.2,"采购价异常","正常"))))

Sheet 应收跟进
A1: 应收跟进 · 账期/账龄/催收管理
A2: 查询月份 | B2: =首页!$B$4 -> 46174 | D2: 截止日 | E2: =EOMONTH(B2,0) -> 46203
A3: 合计 | C3: =SUM(C5:C54) -> 158000 | D3: =SUM(D5:D54) -> 26080 | E3: =SUM(E5:E54) -> 20000 | F3: =SUM(F5:F54) -> 164080 | G3: =SUM(G5:G54) -> 26080 | H3: =SUM(H5:H54) -> 0 | I3: =SUM(I5:I54) -> 0 | J3: =SUM(J5:J54) -> 0 | ... L3: =SUM(L5:L54) -> 138000
A4: 客户 | B4: 账期(天) | C4: 月初应收 | D4: 本月销售 | E4: 本月回款 | F4: 月末应收 | G4: 未到期 | H4: 逾期1-30天 | I4: 逾期31-60天 | J4: 逾期61-90天 | K4: 逾期90天以上 | L4: 逾期合计 | M4: 最长逾期区间 | N4: 风险等级 | O4: 业务员 | P4: 跟进状态 | Q4: 下次跟进日 | R4: 催收备注
A5: =IF(基础资料!Y5="","",基础资料!Y5) -> 客户A | B5: =IF(A5="","",IFERROR(VLOOKUP(A5,基础资料!$Y$5:$AA$204,3,FALSE),0)) -> 30 | C5: =IF(A5="","",SUMIFS(期初数据!$H$5:$H$14,期初数据!$F$5:$F$14,A5)+SUMIFS(销售录入!$I$4:$I$203,销售录入!$C$4:$C$203,A5,销售录入!$A$4:$A$203,"<"&EOMONTH($B$2,-1)+1)-SUMIFS(资金流水!$J$4:$J$203,资金流水!$F$4:$F$203,A5,资金流水!$D$4:$D$203,"客户回款",资金流水!$A$4:$A$203,"<"&EOMONTH($B$2,-1)+1)) -> 15000 | D5: =IF(A5="","",SUMIFS(销售录入!$I$4:$I$203,销售录入!$C$4:$C$203,A5,销售录入!$B$4:$B$203,TEXT($B$2,"yyyy-mm"))) -> 4000 | E5: =IF(A5="","",SUMIFS(资金流水!$J$4:$J$203,资金流水!$F$4:$F$203,A5,资金流水!$D$4:$D$203,"客户回款",资金流水!$B$4:$B$203,TEXT($B$2,"yyyy-mm"))) -> 12000 | F5: =IF(A5="","",SUMIFS(应收明细账龄!$L$4:$L$213,应收明细账龄!$C$4:$C$213,A5)) -> 7000 | G5: =IF(A5="","",SUMIFS(应收明细账龄!$L$4:$L$213,应收明细账龄!$C$4:$C$213,A5,应收明细账龄!$N$4:$N$213,"未到期")) -> 4000 | H5: =IF(A5="","",SUMIFS(应收明细账龄!$L$4:$L$213,应收明细账龄!$C$4:$C$213,A5,应收明细账龄!$N$4:$N$213,"逾期1-30天")) -> 0 | I5: =IF(A5="","",SUMIFS(应收明细账龄!$L$4:$L$213,应收明细账龄!$C$4:$C$213,A5,应收明细账龄!$N$4:$N$213,"逾期31-60天")) -> 0 | J5: =IF(A5="","",SUMIFS(应收明细账龄!$L$4:$L$213,应收明细账龄!$C$4:$C$213,A5,应收明细账龄!$N$4:$N$213,"逾期61-90天")) -> 0 | K5: =IF(A5="","",SUMIFS(应收明细账龄!$L$4:$L$213,应收明细账龄!$C$4:$C$213,A5,应收明细账龄!$N$4:$N$213,"逾期90天以上")) -> 3000 | L5: =IF(A5="","",SUM(H5:K5)) -> 3000 | M5: =IF(A5="","",IF(K5>0,"90天以上",IF(J5>0,"61-90天",IF(I5>0,"31-60天",IF(H5>0,"1-30天",IF(G5>0,"未到期","已收清")))))) -> 90天以上 | N5: =IF(A5="","",IF(K5>0,"高风险",IF(J5+I5>0,"重点关注",IF(H5>0,"到期提醒",IF(F5>0,"正常","已收清"))))) -> 高风险 | O5: =IF(A5="","",IFERROR(VLOOKUP(A5,基础资料!$Y$5:$Z$204,2,FALSE),"")) -> 张伟 | P5: 已联系 | Q5: 46206 | R5: 已沟通，等待付款
A6: =IF(基础资料!Y6="","",基础资料!Y6) -> 客户B | B6: =IF(A6="","",IFERROR(VLOOKUP(A6,基础资料!$Y$5:$AA$204,3,FALSE),0)) -> 30 | C6: =IF(A6="","",SUMIFS(期初数据!$H$5:$H$14,期初数据!$F$5:$F$14,A6)+SUMIFS(销售录入!$I$4:$I$203,销售录入!$C$4:$C$203,A6,销售录入!$A$4:$A$203,"<"&EOMONTH($B$2,-1)+1)-SUMIFS(资金流水!$J$4:$J$203,资金流水!$F$4:$F$203,A6,资金流水!$D$4:$D$203,"客户回款",资金流水!$A$4:$A$203,"<"&EOMONTH($B$2,-1)+1)) -> 12000 | D6: =IF(A6="","",SUMIFS(销售录入!$I$4:$I$203,销售录入!$C$4:$C$203,A6,销售录入!$B$4:$B$203,TEXT($B$2,"yyyy-mm"))) -> 3750 | E6: =IF(A6="","",SUMIFS(资金流水!$J$4:$J$203,资金流水!$F$4:$F$203,A6,资金流水!$D$4:$D$203,"客户回款",资金流水!$B$4:$B$203,TEXT($B$2,"yyyy-mm"))) -> 8000 | F6: =IF(A6="","",SUMIFS(应收明细账龄!$L$4:$L$213,应收明细账龄!$C$4:$C$213,A6)) -> 7750 | G6: =IF(A6="","",SUMIFS(应收明细账龄!$L$4:$L$213,应收明细账龄!$C$4:$C$213,A6,应收明细账龄!$N$4:$N$213,"未到期")) -> 3750 | H6: =IF(A6="","",SUMIFS(应收明细账龄!$L$4:$L$213,应收明细账龄!$C$4:$C$213,A6,应收明细账龄!$N$4:$N$213,"逾期1-30天")) -> 0 | I6: =IF(A6="","",SUMIFS(应收明细账龄!$L$4:$L$213,应收明细账龄!$C$4:$C$213,A6,应收明细账龄!$N$4:$N$213,"逾期31-60天")) -> 0 | J6: =IF(A6="","",SUMIFS(应收明细账龄!$L$4:$L$213,应收明细账龄!$C$4:$C$213,A6,应收明细账龄!$N$4:$N$213,"逾期61-90天")) -> 0 | K6: =IF(A6="","",SUMIFS(应收明细账龄!$L$4:$L$213,应收明细账龄!$C$4:$C$213,A6,应收明细账龄!$N$4:$N$213,"逾期90天以上")) -> 4000 | L6: =IF(A6="","",SUM(H6:K6)) -> 4000 | M6: =IF(A6="","",IF(K6>0,"90天以上",IF(J6>0,"61-90天",IF(I6>0,"31-60天",IF(H6>0,"1-30天",IF(G6>0,"未到期","已收清")))))) -> 90天以上 | N6: =IF(A6="","",IF(K6>0,"高风险",IF(J6+I6>0,"重点关注",IF(H6>0,"到期提醒",IF(F6>0,"正常","已收清"))))) -> 高风险 | O6: =IF(A6="","",IFERROR(VLOOKUP(A6,基础资料!$Y$5:$Z$204,2,FALSE),"")) -> 李娜 | P6: 承诺付款 | Q6: 46207 | R6: 客户承诺本周支付
A7: =IF(基础资料!Y7="","",基础资料!Y7) -> 客户C | B7: =IF(A7="","",IFERROR(VLOOKUP(A7,基础资料!$Y$5:$AA$204,3,FALSE),0)) -> 45 | C7: =IF(A7="","",SUMIFS(期初数据!$H$5:$H$14,期初数据!$F$5:$F$14,A7)+SUMIFS(销售录入!$I$4:$I$203,销售录入!$C$4:$C$203,A7,销售录入!$A$4:$A$203,"<"&EOMONTH($B$2,-1)+1)-SUMIFS(资金流水!$J$4:$J$203,资金流水!$F$4:$F$203,A7,资金流水!$D$4:$D$203,"客户回款",资金流水!$A$4:$A$203,"<"&EOMONTH($B$2,-1)+1)) -> 18000 | D7: =IF(A7="","",SUMIFS(销售录入!$I$4:$I$203,销售录入!$C$4:$C$203,A7,销售录入!$B$4:$B$203,TEXT($B$2,"yyyy-mm"))) -> 3000 | E7: =IF(A7="","",SUMIFS(资金流水!$J$4:$J$203,资金流水!$F$4:$F$203,A7,资金流水!$D$4:$D$203,"客户回款",资金流水!$B$4:$B$203,TEXT($B$2,"yyyy-mm"))) -> 0 | F7: =IF(A7="","",SUMIFS(应收明细账龄!$L$4:$L$213,应收明细账龄!$C$4:$C$213,A7)) -> 21000 | G7: =IF(A7="","",SUMIFS(应收明细账龄!$L$4:$L$213,应收明细账龄!$C$4:$C$213,A7,应收明细账龄!$N$4:$N$213,"未到期")) -> 3000 | H7: =IF(A7="","",SUMIFS(应收明细账龄!$L$4:$L$213,应收明细账龄!$C$4:$C$213,A7,应收明细账龄!$N$4:$N$213,"逾期1-30天")) -> 0 | I7: =IF(A7="","",SUMIFS(应收明细账龄!$L$4:$L$213,应收明细账龄!$C$4:$C$213,A7,应收明细账龄!$N$4:$N$213,"逾期31-60天")) -> 0 | J7: =IF(A7="","",SUMIFS(应收明细账龄!$L$4:$L$213,应收明细账龄!$C$4:$C$213,A7,应收明细账龄!$N$4:$N$213,"逾期61-90天")) -> 0 | K7: =IF(A7="","",SUMIFS(应收明细账龄!$L$4:$L$213,应收明细账龄!$C$4:$C$213,A7,应收明细账龄!$N$4:$N$213,"逾期90天以上")) -> 18000 | L7: =IF(A7="","",SUM(H7:K7)) -> 18000 | M7: =IF(A7="","",IF(K7>0,"90天以上",IF(J7>0,"61-90天",IF(I7>0,"31-60天",IF(H7>0,"1-30天",IF(G7>0,"未到期","已收清")))))) -> 90天以上 | N7: =IF(A7="","",IF(K7>0,"高风险",IF(J7+I7>0,"重点关注",IF(H7>0,"到期提醒",IF(F7>0,"正常","已收清"))))) -> 高风险 | O7: =IF(A7="","",IFERROR(VLOOKUP(A7,基础资料!$Y$5:$Z$204,2,FALSE),"")) -> 张伟 | P7: 重点催收 | Q7: 46208 | R7: 历史欠款较久，重点跟进
A8: =IF(基础资料!Y8="","",基础资料!Y8) -> 客户D | B8: =IF(A8="","",IFERROR(VLOOKUP(A8,基础资料!$Y$5:$AA$204,3,FALSE),0)) -> 30 | C8: =IF(A8="","",SUMIFS(期初数据!$H$5:$H$14,期初数据!$F$5:$F$14,A8)+SUMIFS(销售录入!$I$4:$I$203,销售录入!$C$4:$C$203,A8,销售录入!$A$4:$A$203,"<"&EOMONTH($B$2,-1)+1)-SUMIFS(资金流水!$J$4:$J$203,资金流水!$F$4:$F$203,A8,资金流水!$D$4:$D$203,"客户回款",资金流水!$A$4:$A$203,"<"&EOMONTH($B$2,-1)+1)) -> 8000 | D8: =IF(A8="","",SUMIFS(销售录入!$I$4:$I$203,销售录入!$C$4:$C$203,A8,销售录入!$B$4:$B$203,TEXT($B$2,"yyyy-mm"))) -> 3200 | E8: =IF(A8="","",SUMIFS(资金流水!$J$4:$J$203,资金流水!$F$4:$F$203,A8,资金流水!$D$4:$D$203,"客户回款",资金流水!$B$4:$B$203,TEXT($B$2,"yyyy-mm"))) -> 0 | F8: =IF(A8="","",SUMIFS(应收明细账龄!$L$4:$L$213,应收明细账龄!$C$4:$C$213,A8)) -> 11200 | G8: =IF(A8="","",SUMIFS(应收明细账龄!$L$4:$L$213,应收明细账龄!$C$4:$C$213,A8,应收明细账龄!$N$4:$N$213,"未到期")) -> 3200 | H8: =IF(A8="","",SUMIFS(应收明细账龄!$L$4:$L$213,应收明细账龄!$C$4:$C$213,A8,应收明细账龄!$N$4:$N$213,"逾期1-30天")) -> 0 | I8: =IF(A8="","",SUMIFS(应收明细账龄!$L$4:$L$213,应收明细账龄!$C$4:$C$213,A8,应收明细账龄!$N$4:$N$213,"逾期31-60天")) -> 0 | J8: =IF(A8="","",SUMIFS(应收明细账龄!$L$4:$L$213,应收明细账龄!$C$4:$C$213,A8,应收明细账龄!$N$4:$N$213,"逾期61-90天")) -> 0 | K8: =IF(A8="","",SUMIFS(应收明细账龄!$L$4:$L$213,应收明细账龄!$C$4:$C$213,A8,应收明细账龄!$N$4:$N$213,"逾期90天以上")) -> 8000 | L8: =IF(A8="","",SUM(H8:K8)) -> 8000 | M8: =IF(A8="","",IF(K8>0,"90天以上",IF(J8>0,"61-90天",IF(I8>0,"31-60天",IF(H8>0,"1-30天",IF(G8>0,"未到期","已收清")))))) -> 90天以上 | N8: =IF(A8="","",IF(K8>0,"高风险",IF(J8+I8>0,"重点关注",IF(H8>0,"到期提醒",IF(F8>0,"正常","已收清"))))) -> 高风险 | O8: =IF(A8="","",IFERROR(VLOOKUP(A8,基础资料!$Y$5:$Z$204,2,FALSE),"")) -> 李娜 | P8: 未跟进 | Q8: 46209 | R8: 待首次联系
A9: =IF(基础资料!Y9="","",基础资料!Y9) -> 客户E | B9: =IF(A9="","",IFERROR(VLOOKUP(A9,基础资料!$Y$5:$AA$204,3,FALSE),0)) -> 60 | C9: =IF(A9="","",SUMIFS(期初数据!$H$5:$H$14,期初数据!$F$5:$F$14,A9)+SUMIFS(销售录入!$I$4:$I$203,销售录入!$C$4:$C$203,A9,销售录入!$A$4:$A$203,"<"&EOMONTH($B$2,-1)+1)-SUMIFS(资金流水!$J$4:$J$203,资金流水!$F$4:$F$203,A9,资金流水!$D$4:$D$203,"客户回款",资金流水!$A$4:$A$203,"<"&EOMONTH($B$2,-1)+1)) -> 25000 | D9: =IF(A9="","",SUMIFS(销售录入!$I$4:$I$203,销售录入!$C$4:$C$203,A9,销售录入!$B$4:$B$203,TEXT($B$2,"yyyy-mm"))) -> 2500 | E9: =IF(A9="","",SUMIFS(资金流水!$J$4:$J$203,资金流水!$F$4:$F$203,A9,资金流水!$D$4:$D$203,"客户回款",资金流水!$B$4:$B$203,TEXT($B$2,"yyyy-mm"))) -> 0 | F9: =IF(A9="","",SUMIFS(应收明细账龄!$L$4:$L$213,应收明细账龄!$C$4:$C$213,A9)) -> 27500 | G9: =IF(A9="","",SUMIFS(应收明细账龄!$L$4:$L$213,应收明细账龄!$C$4:$C$213,A9,应收明细账龄!$N$4:$N$213,"未到期")) -> 2500 | H9: =IF(A9="","",SUMIFS(应收明细账龄!$L$4:$L$213,应收明细账龄!$C$4:$C$213,A9,应收明细账龄!$N$4:$N$213,"逾期1-30天")) -> 0 | I9: =IF(A9="","",SUMIFS(应收明细账龄!$L$4:$L$213,应收明细账龄!$C$4:$C$213,A9,应收明细账龄!$N$4:$N$213,"逾期31-60天")) -> 0 | J9: =IF(A9="","",SUMIFS(应收明细账龄!$L$4:$L$213,应收明细账龄!$C$4:$C$213,A9,应收明细账龄!$N$4:$N$213,"逾期61-90天")) -> 0 | K9: =IF(A9="","",SUMIFS(应收明细账龄!$L$4:$L$213,应收明细账龄!$C$4:$C$213,A9,应收明细账龄!$N$4:$N$213,"逾期90天以上")) -> 25000 | L9: =IF(A9="","",SUM(H9:K9)) -> 25000 | M9: =IF(A9="","",IF(K9>0,"90天以上",IF(J9>0,"61-90天",IF(I9>0,"31-60天",IF(H9>0,"1-30天",IF(G9>0,"未到期","已收清")))))) -> 90天以上 | N9: =IF(A9="","",IF(K9>0,"高风险",IF(J9+I9>0,"重点关注",IF(H9>0,"到期提醒",IF(F9>0,"正常","已收清"))))) -> 高风险 | O9: =IF(A9="","",IFERROR(VLOOKUP(A9,基础资料!$Y$5:$Z$204,2,FALSE),"")) -> 张伟 | P9: 已联系 | Q9: 46210 | R9: 正常催收
A10: =IF(基础资料!Y10="","",基础资料!Y10) -> 客户F | B10: =IF(A10="","",IFERROR(VLOOKUP(A10,基础资料!$Y$5:$AA$204,3,FALSE),0)) -> 30 | C10: =IF(A10="","",SUMIFS(期初数据!$H$5:$H$14,期初数据!$F$5:$F$14,A10)+SUMIFS(销售录入!$I$4:$I$203,销售录入!$C$4:$C$203,A10,销售录入!$A$4:$A$203,"<"&EOMONTH($B$2,-1)+1)-SUMIFS(资金流水!$J$4:$J$203,资金流水!$F$4:$F$203,A10,资金流水!$D$4:$D$203,"客户回款",资金流水!$A$4:$A$203,"<"&EOMONTH($B$2,-1)+1)) -> 16000 | D10: =IF(A10="","",SUMIFS(销售录入!$I$4:$I$203,销售录入!$C$4:$C$203,A10,销售录入!$B$4:$B$203,TEXT($B$2,"yyyy-mm"))) -> 1920 | E10: =IF(A10="","",SUMIFS(资金流水!$J$4:$J$203,资金流水!$F$4:$F$203,A10,资金流水!$D$4:$D$203,"客户回款",资金流水!$B$4:$B$203,TEXT($B$2,"yyyy-mm"))) -> 0 | F10: =IF(A10="","",SUMIFS(应收明细账龄!$L$4:$L$213,应收明细账龄!$C$4:$C$213,A10)) -> 17920 | G10: =IF(A10="","",SUMIFS(应收明细账龄!$L$4:$L$213,应收明细账龄!$C$4:$C$213,A10,应收明细账龄!$N$4:$N$213,"未到期")) -> 1920 | H10: =IF(A10="","",SUMIFS(应收明细账龄!$L$4:$L$213,应收明细账龄!$C$4:$C$213,A10,应收明细账龄!$N$4:$N$213,"逾期1-30天")) -> 0 | I10: =IF(A10="","",SUMIFS(应收明细账龄!$L$4:$L$213,应收明细账龄!$C$4:$C$213,A10,应收明细账龄!$N$4:$N$213,"逾期31-60天")) -> 0 | J10: =IF(A10="","",SUMIFS(应收明细账龄!$L$4:$L$213,应收明细账龄!$C$4:$C$213,A10,应收明细账龄!$N$4:$N$213,"逾期61-90天")) -> 0 | K10: =IF(A10="","",SUMIFS(应收明细账龄!$L$4:$L$213,应收明细账龄!$C$4:$C$213,A10,应收明细账龄!$N$4:$N$213,"逾期90天以上")) -> 16000 | L10: =IF(A10="","",SUM(H10:K10)) -> 16000 | M10: =IF(A10="","",IF(K10>0,"90天以上",IF(J10>0,"61-90天",IF(I10>0,"31-60天",IF(H10>0,"1-30天",IF(G10>0,"未到期","已收清")))))) -> 90天以上 | N10: =IF(A10="","",IF(K10>0,"高风险",IF(J10+I10>0,"重点关注",IF(H10>0,"到期提醒",IF(F10>0,"正常","已收清"))))) -> 高风险 | O10: =IF(A10="","",IFERROR(VLOOKUP(A10,基础资料!$Y$5:$Z$204,2,FALSE),"")) -> 李娜 | P10: 未跟进 | Q10: 46211 | R10: 待联系
A11: =IF(基础资料!Y11="","",基础资料!Y11) -> 客户G | B11: =IF(A11="","",IFERROR(VLOOKUP(A11,基础资料!$Y$5:$AA$204,3,FALSE),0)) -> 45 | C11: =IF(A11="","",SUMIFS(期初数据!$H$5:$H$14,期初数据!$F$5:$F$14,A11)+SUMIFS(销售录入!$I$4:$I$203,销售录入!$C$4:$C$203,A11,销售录入!$A$4:$A$203,"<"&EOMONTH($B$2,-1)+1)-SUMIFS(资金流水!$J$4:$J$203,资金流水!$F$4:$F$203,A11,资金流水!$D$4:$D$203,"客户回款",资金流水!$A$4:$A$203,"<"&EOMONTH($B$2,-1)+1)) -> 14000 | D11: =IF(A11="","",SUMIFS(销售录入!$I$4:$I$203,销售录入!$C$4:$C$203,A11,销售录入!$B$4:$B$203,TEXT($B$2,"yyyy-mm"))) -> 2250 | E11: =IF(A11="","",SUMIFS(资金流水!$J$4:$J$203,资金流水!$F$4:$F$203,A11,资金流水!$D$4:$D$203,"客户回款",资金流水!$B$4:$B$203,TEXT($B$2,"yyyy-mm"))) -> 0 | F11: =IF(A11="","",SUMIFS(应收明细账龄!$L$4:$L$213,应收明细账龄!$C$4:$C$213,A11)) -> 16250 | G11: =IF(A11="","",SUMIFS(应收明细账龄!$L$4:$L$213,应收明细账龄!$C$4:$C$213,A11,应收明细账龄!$N$4:$N$213,"未到期")) -> 2250 | H11: =IF(A11="","",SUMIFS(应收明细账龄!$L$4:$L$213,应收明细账龄!$C$4:$C$213,A11,应收明细账龄!$N$4:$N$213,"逾期1-30天")) -> 0 | I11: =IF(A11="","",SUMIFS(应收明细账龄!$L$4:$L$213,应收明细账龄!$C$4:$C$213,A11,应收明细账龄!$N$4:$N$213,"逾期31-60天")) -> 0 | J11: =IF(A11="","",SUMIFS(应收明细账龄!$L$4:$L$213,应收明细账龄!$C$4:$C$213,A11,应收明细账龄!$N$4:$N$213,"逾期61-90天")) -> 0 | K11: =IF(A11="","",SUMIFS(应收明细账龄!$L$4:$L$213,应收明细账龄!$C$4:$C$213,A11,应收明细账龄!$N$4:$N$213,"逾期90天以上")) -> 14000 | L11: =IF(A11="","",SUM(H11:K11)) -> 14000 | M11: =IF(A11="","",IF(K11>0,"90天以上",IF(J11>0,"61-90天",IF(I11>0,"31-60天",IF(H11>0,"1-30天",IF(G11>0,"未到期","已收清")))))) -> 90天以上 | N11: =IF(A11="","",IF(K11>0,"高风险",IF(J11+I11>0,"重点关注",IF(H11>0,"到期提醒",IF(F11>0,"正常","已收清"))))) -> 高风险 | O11: =IF(A11="","",IFERROR(VLOOKUP(A11,基础资料!$Y$5:$Z$204,2,FALSE),"")) -> 张伟 | P11: 承诺付款 | Q11: 46212 | R11: 已确认付款计划
A12: =IF(基础资料!Y12="","",基础资料!Y12) -> 客户H | B12: =IF(A12="","",IFERROR(VLOOKUP(A12,基础资料!$Y$5:$AA$204,3,FALSE),0)) -> 30 | C12: =IF(A12="","",SUMIFS(期初数据!$H$5:$H$14,期初数据!$F$5:$F$14,A12)+SUMIFS(销售录入!$I$4:$I$203,销售录入!$C$4:$C$203,A12,销售录入!$A$4:$A$203,"<"&EOMONTH($B$2,-1)+1)-SUMIFS(资金流水!$J$4:$J$203,资金流水!$F$4:$F$203,A12,资金流水!$D$4:$D$203,"客户回款",资金流水!$A$4:$A$203,"<"&EOMONTH($B$2,-1)+1)) -> 20000 | D12: =IF(A12="","",SUMIFS(销售录入!$I$4:$I$203,销售录入!$C$4:$C$203,A12,销售录入!$B$4:$B$203,TEXT($B$2,"yyyy-mm"))) -> 1800 | E12: =IF(A12="","",SUMIFS(资金流水!$J$4:$J$203,资金流水!$F$4:$F$203,A12,资金流水!$D$4:$D$203,"客户回款",资金流水!$B$4:$B$203,TEXT($B$2,"yyyy-mm"))) -> 0 | F12: =IF(A12="","",SUMIFS(应收明细账龄!$L$4:$L$213,应收明细账龄!$C$4:$C$213,A12)) -> 21800 | G12: =IF(A12="","",SUMIFS(应收明细账龄!$L$4:$L$213,应收明细账龄!$C$4:$C$213,A12,应收明细账龄!$N$4:$N$213,"未到期")) -> 1800 | H12: =IF(A12="","",SUMIFS(应收明细账龄!$L$4:$L$213,应收明细账龄!$C$4:$C$213,A12,应收明细账龄!$N$4:$N$213,"逾期1-30天")) -> 0 | I12: =IF(A12="","",SUMIFS(应收明细账龄!$L$4:$L$213,应收明细账龄!$C$4:$C$213,A12,应收明细账龄!$N$4:$N$213,"逾期31-60天")) -> 0 | J12: =IF(A12="","",SUMIFS(应收明细账龄!$L$4:$L$213,应收明细账龄!$C$4:$C$213,A12,应收明细账龄!$N$4:$N$213,"逾期61-90天")) -> 0 | K12: =IF(A12="","",SUMIFS(应收明细账龄!$L$4:$L$213,应收明细账龄!$C$4:$C$213,A12,应收明细账龄!$N$4:$N$213,"逾期90天以上")) -> 20000 | L12: =IF(A12="","",SUM(H12:K12)) -> 20000 | M12: =IF(A12="","",IF(K12>0,"90天以上",IF(J12>0,"61-90天",IF(I12>0,"31-60天",IF(H12>0,"1-30天",IF(G12>0,"未到期","已收清")))))) -> 90天以上 | N12: =IF(A12="","",IF(K12>0,"高风险",IF(J12+I12>0,"重点关注",IF(H12>0,"到期提醒",IF(F12>0,"正常","已收清"))))) -> 高风险 | O12: =IF(A12="","",IFERROR(VLOOKUP(A12,基础资料!$Y$5:$Z$204,2,FALSE),"")) -> 李娜 | P12: 已联系 | Q12: 46213 | R12: 按账期跟进
A13: =IF(基础资料!Y13="","",基础资料!Y13) -> 客户I | B13: =IF(A13="","",IFERROR(VLOOKUP(A13,基础资料!$Y$5:$AA$204,3,FALSE),0)) -> 30 | C13: =IF(A13="","",SUMIFS(期初数据!$H$5:$H$14,期初数据!$F$5:$F$14,A13)+SUMIFS(销售录入!$I$4:$I$203,销售录入!$C$4:$C$203,A13,销售录入!$A$4:$A$203,"<"&EOMONTH($B$2,-1)+1)-SUMIFS(资金流水!$J$4:$J$203,资金流水!$F$4:$F$203,A13,资金流水!$D$4:$D$203,"客户回款",资金流水!$A$4:$A$203,"<"&EOMONTH($B$2,-1)+1)) -> 10000 | D13: =IF(A13="","",SUMIFS(销售录入!$I$4:$I$203,销售录入!$C$4:$C$203,A13,销售录入!$B$4:$B$203,TEXT($B$2,"yyyy-mm"))) -> 1500 | E13: =IF(A13="","",SUMIFS(资金流水!$J$4:$J$203,资金流水!$F$4:$F$203,A13,资金流水!$D$4:$D$203,"客户回款",资金流水!$B$4:$B$203,TEXT($B$2,"yyyy-mm"))) -> 0 | F13: =IF(A13="","",SUMIFS(应收明细账龄!$L$4:$L$213,应收明细账龄!$C$4:$C$213,A13)) -> 11500 | G13: =IF(A13="","",SUMIFS(应收明细账龄!$L$4:$L$213,应收明细账龄!$C$4:$C$213,A13,应收明细账龄!$N$4:$N$213,"未到期")) -> 1500 | H13: =IF(A13="","",SUMIFS(应收明细账龄!$L$4:$L$213,应收明细账龄!$C$4:$C$213,A13,应收明细账龄!$N$4:$N$213,"逾期1-30天")) -> 0 | I13: =IF(A13="","",SUMIFS(应收明细账龄!$L$4:$L$213,应收明细账龄!$C$4:$C$213,A13,应收明细账龄!$N$4:$N$213,"逾期31-60天")) -> 0 | J13: =IF(A13="","",SUMIFS(应收明细账龄!$L$4:$L$213,应收明细账龄!$C$4:$C$213,A13,应收明细账龄!$N$4:$N$213,"逾期61-90天")) -> 0 | K13: =IF(A13="","",SUMIFS(应收明细账龄!$L$4:$L$213,应收明细账龄!$C$4:$C$213,A13,应收明细账龄!$N$4:$N$213,"逾期90天以上")) -> 10000 | L13: =IF(A13="","",SUM(H13:K13)) -> 10000 | M13: =IF(A13="","",IF(K13>0,"90天以上",IF(J13>0,"61-90天",IF(I13>0,"31-60天",IF(H13>0,"1-30天",IF(G13>0,"未到期","已收清")))))) -> 90天以上 | N13: =IF(A13="","",IF(K13>0,"高风险",IF(J13+I13>0,"重点关注",IF(H13>0,"到期提醒",IF(F13>0,"正常","已收清"))))) -> 高风险 | O13: =IF(A13="","",IFERROR(VLOOKUP(A13,基础资料!$Y$5:$Z$204,2,FALSE),"")) -> 张伟 | P13: 未跟进 | Q13: 46214 | R13: 待确认付款时间
A14: =IF(基础资料!Y14="","",基础资料!Y14) -> 客户J | B14: =IF(A14="","",IFERROR(VLOOKUP(A14,基础资料!$Y$5:$AA$204,3,FALSE),0)) -> 60 | C14: =IF(A14="","",SUMIFS(期初数据!$H$5:$H$14,期初数据!$F$5:$F$14,A14)+SUMIFS(销售录入!$I$4:$I$203,销售录入!$C$4:$C$203,A14,销售录入!$A$4:$A$203,"<"&EOMONTH($B$2,-1)+1)-SUMIFS(资金流水!$J$4:$J$203,资金流水!$F$4:$F$203,A14,资金流水!$D$4:$D$203,"客户回款",资金流水!$A$4:$A$203,"<"&EOMONTH($B$2,-1)+1)) -> 20000 | D14: =IF(A14="","",SUMIFS(销售录入!$I$4:$I$203,销售录入!$C$4:$C$203,A14,销售录入!$B$4:$B$203,TEXT($B$2,"yyyy-mm"))) -> 2160 | E14: =IF(A14="","",SUMIFS(资金流水!$J$4:$J$203,资金流水!$F$4:$F$203,A14,资金流水!$D$4:$D$203,"客户回款",资金流水!$B$4:$B$203,TEXT($B$2,"yyyy-mm"))) -> 0 | F14: =IF(A14="","",SUMIFS(应收明细账龄!$L$4:$L$213,应收明细账龄!$C$4:$C$213,A14)) -> 22160 | G14: =IF(A14="","",SUMIFS(应收明细账龄!$L$4:$L$213,应收明细账龄!$C$4:$C$213,A14,应收明细账龄!$N$4:$N$213,"未到期")) -> 2160 | H14: =IF(A14="","",SUMIFS(应收明细账龄!$L$4:$L$213,应收明细账龄!$C$4:$C$213,A14,应收明细账龄!$N$4:$N$213,"逾期1-30天")) -> 0 | I14: =IF(A14="","",SUMIFS(应收明细账龄!$L$4:$L$213,应收明细账龄!$C$4:$C$213,A14,应收明细账龄!$N$4:$N$213,"逾期31-60天")) -> 0 | J14: =IF(A14="","",SUMIFS(应收明细账龄!$L$4:$L$213,应收明细账龄!$C$4:$C$213,A14,应收明细账龄!$N$4:$N$213,"逾期61-90天")) -> 0 | K14: =IF(A14="","",SUMIFS(应收明细账龄!$L$4:$L$213,应收明细账龄!$C$4:$C$213,A14,应收明细账龄!$N$4:$N$213,"逾期90天以上")) -> 20000 | L14: =IF(A14="","",SUM(H14:K14)) -> 20000 | M14: =IF(A14="","",IF(K14>0,"90天以上",IF(J14>0,"61-90天",IF(I14>0,"31-60天",IF(H14>0,"1-30天",IF(G14>0,"未到期","已收清")))))) -> 90天以上 | N14: =IF(A14="","",IF(K14>0,"高风险",IF(J14+I14>0,"重点关注",IF(H14>0,"到期提醒",IF(F14>0,"正常","已收清"))))) -> 高风险 | O14: =IF(A14="","",IFERROR(VLOOKUP(A14,基础资料!$Y$5:$Z$204,2,FALSE),"")) -> 李娜 | P14: 重点催收 | Q14: 46215 | R14: 重点催收
A15: =IF(基础资料!Y15="","",基础资料!Y15) | B15: =IF(A15="","",IFERROR(VLOOKUP(A15,基础资料!$Y$5:$AA$204,3,FALSE),0)) | C15: =IF(A15="","",SUMIFS(期初数据!$H$5:$H$14,期初数据!$F$5:$F$14,A15)+SUMIFS(销售录入!$I$4:$I$203,销售录入!$C$4:$C$203,A15,销售录入!$A$4:$A$203,"<"&EOMONTH($B$2,-1)+1)-SUMIFS(资金流水!$J$4:$J$203,资金流水!$F$4:$F$203,A15,资金流水!$D$4:$D$203,"客户回款",资金流水!$A$4:$A$203,"<"&EOMONTH($B$2,-1)+1)) | D15: =IF(A15="","",SUMIFS(销售录入!$I$4:$I$203,销售录入!$C$4:$C$203,A15,销售录入!$B$4:$B$203,TEXT($B$2,"yyyy-mm"))) | E15: =IF(A15="","",SUMIFS(资金流水!$J$4:$J$203,资金流水!$F$4:$F$203,A15,资金流水!$D$4:$D$203,"客户回款",资金流水!$B$4:$B$203,TEXT($B$2,"yyyy-mm"))) | F15: =IF(A15="","",SUMIFS(应收明细账龄!$L$4:$L$213,应收明细账龄!$C$4:$C$213,A15)) | G15: =IF(A15="","",SUMIFS(应收明细账龄!$L$4:$L$213,应收明细账龄!$C$4:$C$213,A15,应收明细账龄!$N$4:$N$213,"未到期")) | H15: =IF(A15="","",SUMIFS(应收明细账龄!$L$4:$L$213,应收明细账龄!$C$4:$C$213,A15,应收明细账龄!$N$4:$N$213,"逾期1-30天")) | I15: =IF(A15="","",SUMIFS(应收明细账龄!$L$4:$L$213,应收明细账龄!$C$4:$C$213,A15,应收明细账龄!$N$4:$N$213,"逾期31-60天")) | J15: =IF(A15="","",SUMIFS(应收明细账龄!$L$4:$L$213,应收明细账龄!$C$4:$C$213,A15,应收明细账龄!$N$4:$N$213,"逾期61-90天")) | K15: =IF(A15="","",SUMIFS(应收明细账龄!$L$4:$L$213,应收明细账龄!$C$4:$C$213,A15,应收明细账龄!$N$4:$N$213,"逾期90天以上")) | L15: =IF(A15="","",SUM(H15:K15)) | M15: =IF(A15="","",IF(K15>0,"90天以上",IF(J15>0,"61-90天",IF(I15>0,"31-60天",IF(H15>0,"1-30天",IF(G15>0,"未到期","已收清")))))) | N15: =IF(A15="","",IF(K15>0,"高风险",IF(J15+I15>0,"重点关注",IF(H15>0,"到期提醒",IF(F15>0,"正常","已收清"))))) | O15: =IF(A15="","",IFERROR(VLOOKUP(A15,基础资料!$Y$5:$Z$204,2,FALSE),""))
A16: =IF(基础资料!Y16="","",基础资料!Y16) | B16: =IF(A16="","",IFERROR(VLOOKUP(A16,基础资料!$Y$5:$AA$204,3,FALSE),0)) | C16: =IF(A16="","",SUMIFS(期初数据!$H$5:$H$14,期初数据!$F$5:$F$14,A16)+SUMIFS(销售录入!$I$4:$I$203,销售录入!$C$4:$C$203,A16,销售录入!$A$4:$A$203,"<"&EOMONTH($B$2,-1)+1)-SUMIFS(资金流水!$J$4:$J$203,资金流水!$F$4:$F$203,A16,资金流水!$D$4:$D$203,"客户回款",资金流水!$A$4:$A$203,"<"&EOMONTH($B$2,-1)+1)) | D16: =IF(A16="","",SUMIFS(销售录入!$I$4:$I$203,销售录入!$C$4:$C$203,A16,销售录入!$B$4:$B$203,TEXT($B$2,"yyyy-mm"))) | E16: =IF(A16="","",SUMIFS(资金流水!$J$4:$J$203,资金流水!$F$4:$F$203,A16,资金流水!$D$4:$D$203,"客户回款",资金流水!$B$4:$B$203,TEXT($B$2,"yyyy-mm"))) | F16: =IF(A16="","",SUMIFS(应收明细账龄!$L$4:$L$213,应收明细账龄!$C$4:$C$213,A16)) | G16: =IF(A16="","",SUMIFS(应收明细账龄!$L$4:$L$213,应收明细账龄!$C$4:$C$213,A16,应收明细账龄!$N$4:$N$213,"未到期")) | H16: =IF(A16="","",SUMIFS(应收明细账龄!$L$4:$L$213,应收明细账龄!$C$4:$C$213,A16,应收明细账龄!$N$4:$N$213,"逾期1-30天")) | I16: =IF(A16="","",SUMIFS(应收明细账龄!$L$4:$L$213,应收明细账龄!$C$4:$C$213,A16,应收明细账龄!$N$4:$N$213,"逾期31-60天")) | J16: =IF(A16="","",SUMIFS(应收明细账龄!$L$4:$L$213,应收明细账龄!$C$4:$C$213,A16,应收明细账龄!$N$4:$N$213,"逾期61-90天")) | K16: =IF(A16="","",SUMIFS(应收明细账龄!$L$4:$L$213,应收明细账龄!$C$4:$C$213,A16,应收明细账龄!$N$4:$N$213,"逾期90天以上")) | L16: =IF(A16="","",SUM(H16:K16)) | M16: =IF(A16="","",IF(K16>0,"90天以上",IF(J16>0,"61-90天",IF(I16>0,"31-60天",IF(H16>0,"1-30天",IF(G16>0,"未到期","已收清")))))) | N16: =IF(A16="","",IF(K16>0,"高风险",IF(J16+I16>0,"重点关注",IF(H16>0,"到期提醒",IF(F16>0,"正常","已收清"))))) | O16: =IF(A16="","",IFERROR(VLOOKUP(A16,基础资料!$Y$5:$Z$204,2,FALSE),""))
A17: =IF(基础资料!Y17="","",基础资料!Y17) | B17: =IF(A17="","",IFERROR(VLOOKUP(A17,基础资料!$Y$5:$AA$204,3,FALSE),0)) | C17: =IF(A17="","",SUMIFS(期初数据!$H$5:$H$14,期初数据!$F$5:$F$14,A17)+SUMIFS(销售录入!$I$4:$I$203,销售录入!$C$4:$C$203,A17,销售录入!$A$4:$A$203,"<"&EOMONTH($B$2,-1)+1)-SUMIFS(资金流水!$J$4:$J$203,资金流水!$F$4:$F$203,A17,资金流水!$D$4:$D$203,"客户回款",资金流水!$A$4:$A$203,"<"&EOMONTH($B$2,-1)+1)) | D17: =IF(A17="","",SUMIFS(销售录入!$I$4:$I$203,销售录入!$C$4:$C$203,A17,销售录入!$B$4:$B$203,TEXT($B$2,"yyyy-mm"))) | E17: =IF(A17="","",SUMIFS(资金流水!$J$4:$J$203,资金流水!$F$4:$F$203,A17,资金流水!$D$4:$D$203,"客户回款",资金流水!$B$4:$B$203,TEXT($B$2,"yyyy-mm"))) | F17: =IF(A17="","",SUMIFS(应收明细账龄!$L$4:$L$213,应收明细账龄!$C$4:$C$213,A17)) | G17: =IF(A17="","",SUMIFS(应收明细账龄!$L$4:$L$213,应收明细账龄!$C$4:$C$213,A17,应收明细账龄!$N$4:$N$213,"未到期")) | H17: =IF(A17="","",SUMIFS(应收明细账龄!$L$4:$L$213,应收明细账龄!$C$4:$C$213,A17,应收明细账龄!$N$4:$N$213,"逾期1-30天")) | I17: =IF(A17="","",SUMIFS(应收明细账龄!$L$4:$L$213,应收明细账龄!$C$4:$C$213,A17,应收明细账龄!$N$4:$N$213,"逾期31-60天")) | J17: =IF(A17="","",SUMIFS(应收明细账龄!$L$4:$L$213,应收明细账龄!$C$4:$C$213,A17,应收明细账龄!$N$4:$N$213,"逾期61-90天")) | K17: =IF(A17="","",SUMIFS(应收明细账龄!$L$4:$L$213,应收明细账龄!$C$4:$C$213,A17,应收明细账龄!$N$4:$N$213,"逾期90天以上")) | L17: =IF(A17="","",SUM(H17:K17)) | M17: =IF(A17="","",IF(K17>0,"90天以上",IF(J17>0,"61-90天",IF(I17>0,"31-60天",IF(H17>0,"1-30天",IF(G17>0,"未到期","已收清")))))) | N17: =IF(A17="","",IF(K17>0,"高风险",IF(J17+I17>0,"重点关注",IF(H17>0,"到期提醒",IF(F17>0,"正常","已收清"))))) | O17: =IF(A17="","",IFERROR(VLOOKUP(A17,基础资料!$Y$5:$Z$204,2,FALSE),""))
A18: =IF(基础资料!Y18="","",基础资料!Y18) | B18: =IF(A18="","",IFERROR(VLOOKUP(A18,基础资料!$Y$5:$AA$204,3,FALSE),0)) | C18: =IF(A18="","",SUMIFS(期初数据!$H$5:$H$14,期初数据!$F$5:$F$14,A18)+SUMIFS(销售录入!$I$4:$I$203,销售录入!$C$4:$C$203,A18,销售录入!$A$4:$A$203,"<"&EOMONTH($B$2,-1)+1)-SUMIFS(资金流水!$J$4:$J$203,资金流水!$F$4:$F$203,A18,资金流水!$D$4:$D$203,"客户回款",资金流水!$A$4:$A$203,"<"&EOMONTH($B$2,-1)+1)) | D18: =IF(A18="","",SUMIFS(销售录入!$I$4:$I$203,销售录入!$C$4:$C$203,A18,销售录入!$B$4:$B$203,TEXT($B$2,"yyyy-mm"))) | E18: =IF(A18="","",SUMIFS(资金流水!$J$4:$J$203,资金流水!$F$4:$F$203,A18,资金流水!$D$4:$D$203,"客户回款",资金流水!$B$4:$B$203,TEXT($B$2,"yyyy-mm"))) | F18: =IF(A18="","",SUMIFS(应收明细账龄!$L$4:$L$213,应收明细账龄!$C$4:$C$213,A18)) | G18: =IF(A18="","",SUMIFS(应收明细账龄!$L$4:$L$213,应收明细账龄!$C$4:$C$213,A18,应收明细账龄!$N$4:$N$213,"未到期")) | H18: =IF(A18="","",SUMIFS(应收明细账龄!$L$4:$L$213,应收明细账龄!$C$4:$C$213,A18,应收明细账龄!$N$4:$N$213,"逾期1-30天")) | I18: =IF(A18="","",SUMIFS(应收明细账龄!$L$4:$L$213,应收明细账龄!$C$4:$C$213,A18,应收明细账龄!$N$4:$N$213,"逾期31-60天")) | J18: =IF(A18="","",SUMIFS(应收明细账龄!$L$4:$L$213,应收明细账龄!$C$4:$C$213,A18,应收明细账龄!$N$4:$N$213,"逾期61-90天")) | K18: =IF(A18="","",SUMIFS(应收明细账龄!$L$4:$L$213,应收明细账龄!$C$4:$C$213,A18,应收明细账龄!$N$4:$N$213,"逾期90天以上")) | L18: =IF(A18="","",SUM(H18:K18)) | M18: =IF(A18="","",IF(K18>0,"90天以上",IF(J18>0,"61-90天",IF(I18>0,"31-60天",IF(H18>0,"1-30天",IF(G18>0,"未到期","已收清")))))) | N18: =IF(A18="","",IF(K18>0,"高风险",IF(J18+I18>0,"重点关注",IF(H18>0,"到期提醒",IF(F18>0,"正常","已收清"))))) | O18: =IF(A18="","",IFERROR(VLOOKUP(A18,基础资料!$Y$5:$Z$204,2,FALSE),""))
A19: =IF(基础资料!Y19="","",基础资料!Y19) | B19: =IF(A19="","",IFERROR(VLOOKUP(A19,基础资料!$Y$5:$AA$204,3,FALSE),0)) | C19: =IF(A19="","",SUMIFS(期初数据!$H$5:$H$14,期初数据!$F$5:$F$14,A19)+SUMIFS(销售录入!$I$4:$I$203,销售录入!$C$4:$C$203,A19,销售录入!$A$4:$A$203,"<"&EOMONTH($B$2,-1)+1)-SUMIFS(资金流水!$J$4:$J$203,资金流水!$F$4:$F$203,A19,资金流水!$D$4:$D$203,"客户回款",资金流水!$A$4:$A$203,"<"&EOMONTH($B$2,-1)+1)) | D19: =IF(A19="","",SUMIFS(销售录入!$I$4:$I$203,销售录入!$C$4:$C$203,A19,销售录入!$B$4:$B$203,TEXT($B$2,"yyyy-mm"))) | E19: =IF(A19="","",SUMIFS(资金流水!$J$4:$J$203,资金流水!$F$4:$F$203,A19,资金流水!$D$4:$D$203,"客户回款",资金流水!$B$4:$B$203,TEXT($B$2,"yyyy-mm"))) | F19: =IF(A19="","",SUMIFS(应收明细账龄!$L$4:$L$213,应收明细账龄!$C$4:$C$213,A19)) | G19: =IF(A19="","",SUMIFS(应收明细账龄!$L$4:$L$213,应收明细账龄!$C$4:$C$213,A19,应收明细账龄!$N$4:$N$213,"未到期")) | H19: =IF(A19="","",SUMIFS(应收明细账龄!$L$4:$L$213,应收明细账龄!$C$4:$C$213,A19,应收明细账龄!$N$4:$N$213,"逾期1-30天")) | I19: =IF(A19="","",SUMIFS(应收明细账龄!$L$4:$L$213,应收明细账龄!$C$4:$C$213,A19,应收明细账龄!$N$4:$N$213,"逾期31-60天")) | J19: =IF(A19="","",SUMIFS(应收明细账龄!$L$4:$L$213,应收明细账龄!$C$4:$C$213,A19,应收明细账龄!$N$4:$N$213,"逾期61-90天")) | K19: =IF(A19="","",SUMIFS(应收明细账龄!$L$4:$L$213,应收明细账龄!$C$4:$C$213,A19,应收明细账龄!$N$4:$N$213,"逾期90天以上")) | L19: =IF(A19="","",SUM(H19:K19)) | M19: =IF(A19="","",IF(K19>0,"90天以上",IF(J19>0,"61-90天",IF(I19>0,"31-60天",IF(H19>0,"1-30天",IF(G19>0,"未到期","已收清")))))) | N19: =IF(A19="","",IF(K19>0,"高风险",IF(J19+I19>0,"重点关注",IF(H19>0,"到期提醒",IF(F19>0,"正常","已收清"))))) | O19: =IF(A19="","",IFERROR(VLOOKUP(A19,基础资料!$Y$5:$Z$204,2,FALSE),""))
A20: =IF(基础资料!Y20="","",基础资料!Y20) | B20: =IF(A20="","",IFERROR(VLOOKUP(A20,基础资料!$Y$5:$AA$204,3,FALSE),0)) | C20: =IF(A20="","",SUMIFS(期初数据!$H$5:$H$14,期初数据!$F$5:$F$14,A20)+SUMIFS(销售录入!$I$4:$I$203,销售录入!$C$4:$C$203,A20,销售录入!$A$4:$A$203,"<"&EOMONTH($B$2,-1)+1)-SUMIFS(资金流水!$J$4:$J$203,资金流水!$F$4:$F$203,A20,资金流水!$D$4:$D$203,"客户回款",资金流水!$A$4:$A$203,"<"&EOMONTH($B$2,-1)+1)) | D20: =IF(A20="","",SUMIFS(销售录入!$I$4:$I$203,销售录入!$C$4:$C$203,A20,销售录入!$B$4:$B$203,TEXT($B$2,"yyyy-mm"))) | E20: =IF(A20="","",SUMIFS(资金流水!$J$4:$J$203,资金流水!$F$4:$F$203,A20,资金流水!$D$4:$D$203,"客户回款",资金流水!$B$4:$B$203,TEXT($B$2,"yyyy-mm"))) | F20: =IF(A20="","",SUMIFS(应收明细账龄!$L$4:$L$213,应收明细账龄!$C$4:$C$213,A20)) | G20: =IF(A20="","",SUMIFS(应收明细账龄!$L$4:$L$213,应收明细账龄!$C$4:$C$213,A20,应收明细账龄!$N$4:$N$213,"未到期")) | H20: =IF(A20="","",SUMIFS(应收明细账龄!$L$4:$L$213,应收明细账龄!$C$4:$C$213,A20,应收明细账龄!$N$4:$N$213,"逾期1-30天")) | I20: =IF(A20="","",SUMIFS(应收明细账龄!$L$4:$L$213,应收明细账龄!$C$4:$C$213,A20,应收明细账龄!$N$4:$N$213,"逾期31-60天")) | J20: =IF(A20="","",SUMIFS(应收明细账龄!$L$4:$L$213,应收明细账龄!$C$4:$C$213,A20,应收明细账龄!$N$4:$N$213,"逾期61-90天")) | K20: =IF(A20="","",SUMIFS(应收明细账龄!$L$4:$L$213,应收明细账龄!$C$4:$C$213,A20,应收明细账龄!$N$4:$N$213,"逾期90天以上")) | L20: =IF(A20="","",SUM(H20:K20)) | M20: =IF(A20="","",IF(K20>0,"90天以上",IF(J20>0,"61-90天",IF(I20>0,"31-60天",IF(H20>0,"1-30天",IF(G20>0,"未到期","已收清")))))) | N20: =IF(A20="","",IF(K20>0,"高风险",IF(J20+I20>0,"重点关注",IF(H20>0,"到期提醒",IF(F20>0,"正常","已收清"))))) | O20: =IF(A20="","",IFERROR(VLOOKUP(A20,基础资料!$Y$5:$Z$204,2,FALSE),""))
A21: =IF(基础资料!Y21="","",基础资料!Y21) | B21: =IF(A21="","",IFERROR(VLOOKUP(A21,基础资料!$Y$5:$AA$204,3,FALSE),0)) | C21: =IF(A21="","",SUMIFS(期初数据!$H$5:$H$14,期初数据!$F$5:$F$14,A21)+SUMIFS(销售录入!$I$4:$I$203,销售录入!$C$4:$C$203,A21,销售录入!$A$4:$A$203,"<"&EOMONTH($B$2,-1)+1)-SUMIFS(资金流水!$J$4:$J$203,资金流水!$F$4:$F$203,A21,资金流水!$D$4:$D$203,"客户回款",资金流水!$A$4:$A$203,"<"&EOMONTH($B$2,-1)+1)) | D21: =IF(A21="","",SUMIFS(销售录入!$I$4:$I$203,销售录入!$C$4:$C$203,A21,销售录入!$B$4:$B$203,TEXT($B$2,"yyyy-mm"))) | E21: =IF(A21="","",SUMIFS(资金流水!$J$4:$J$203,资金流水!$F$4:$F$203,A21,资金流水!$D$4:$D$203,"客户回款",资金流水!$B$4:$B$203,TEXT($B$2,"yyyy-mm"))) | F21: =IF(A21="","",SUMIFS(应收明细账龄!$L$4:$L$213,应收明细账龄!$C$4:$C$213,A21)) | G21: =IF(A21="","",SUMIFS(应收明细账龄!$L$4:$L$213,应收明细账龄!$C$4:$C$213,A21,应收明细账龄!$N$4:$N$213,"未到期")) | H21: =IF(A21="","",SUMIFS(应收明细账龄!$L$4:$L$213,应收明细账龄!$C$4:$C$213,A21,应收明细账龄!$N$4:$N$213,"逾期1-30天")) | I21: =IF(A21="","",SUMIFS(应收明细账龄!$L$4:$L$213,应收明细账龄!$C$4:$C$213,A21,应收明细账龄!$N$4:$N$213,"逾期31-60天")) | J21: =IF(A21="","",SUMIFS(应收明细账龄!$L$4:$L$213,应收明细账龄!$C$4:$C$213,A21,应收明细账龄!$N$4:$N$213,"逾期61-90天")) | K21: =IF(A21="","",SUMIFS(应收明细账龄!$L$4:$L$213,应收明细账龄!$C$4:$C$213,A21,应收明细账龄!$N$4:$N$213,"逾期90天以上")) | L21: =IF(A21="","",SUM(H21:K21)) | M21: =IF(A21="","",IF(K21>0,"90天以上",IF(J21>0,"61-90天",IF(I21>0,"31-60天",IF(H21>0,"1-30天",IF(G21>0,"未到期","已收清")))))) | N21: =IF(A21="","",IF(K21>0,"高风险",IF(J21+I21>0,"重点关注",IF(H21>0,"到期提醒",IF(F21>0,"正常","已收清"))))) | O21: =IF(A21="","",IFERROR(VLOOKUP(A21,基础资料!$Y$5:$Z$204,2,FALSE),""))
A22: =IF(基础资料!Y22="","",基础资料!Y22) | B22: =IF(A22="","",IFERROR(VLOOKUP(A22,基础资料!$Y$5:$AA$204,3,FALSE),0)) | C22: =IF(A22="","",SUMIFS(期初数据!$H$5:$H$14,期初数据!$F$5:$F$14,A22)+SUMIFS(销售录入!$I$4:$I$203,销售录入!$C$4:$C$203,A22,销售录入!$A$4:$A$203,"<"&EOMONTH($B$2,-1)+1)-SUMIFS(资金流水!$J$4:$J$203,资金流水!$F$4:$F$203,A22,资金流水!$D$4:$D$203,"客户回款",资金流水!$A$4:$A$203,"<"&EOMONTH($B$2,-1)+1)) | D22: =IF(A22="","",SUMIFS(销售录入!$I$4:$I$203,销售录入!$C$4:$C$203,A22,销售录入!$B$4:$B$203,TEXT($B$2,"yyyy-mm"))) | E22: =IF(A22="","",SUMIFS(资金流水!$J$4:$J$203,资金流水!$F$4:$F$203,A22,资金流水!$D$4:$D$203,"客户回款",资金流水!$B$4:$B$203,TEXT($B$2,"yyyy-mm"))) | F22: =IF(A22="","",SUMIFS(应收明细账龄!$L$4:$L$213,应收明细账龄!$C$4:$C$213,A22)) | G22: =IF(A22="","",SUMIFS(应收明细账龄!$L$4:$L$213,应收明细账龄!$C$4:$C$213,A22,应收明细账龄!$N$4:$N$213,"未到期")) | H22: =IF(A22="","",SUMIFS(应收明细账龄!$L$4:$L$213,应收明细账龄!$C$4:$C$213,A22,应收明细账龄!$N$4:$N$213,"逾期1-30天")) | I22: =IF(A22="","",SUMIFS(应收明细账龄!$L$4:$L$213,应收明细账龄!$C$4:$C$213,A22,应收明细账龄!$N$4:$N$213,"逾期31-60天")) | J22: =IF(A22="","",SUMIFS(应收明细账龄!$L$4:$L$213,应收明细账龄!$C$4:$C$213,A22,应收明细账龄!$N$4:$N$213,"逾期61-90天")) | K22: =IF(A22="","",SUMIFS(应收明细账龄!$L$4:$L$213,应收明细账龄!$C$4:$C$213,A22,应收明细账龄!$N$4:$N$213,"逾期90天以上")) | L22: =IF(A22="","",SUM(H22:K22)) | M22: =IF(A22="","",IF(K22>0,"90天以上",IF(J22>0,"61-90天",IF(I22>0,"31-60天",IF(H22>0,"1-30天",IF(G22>0,"未到期","已收清")))))) | N22: =IF(A22="","",IF(K22>0,"高风险",IF(J22+I22>0,"重点关注",IF(H22>0,"到期提醒",IF(F22>0,"正常","已收清"))))) | O22: =IF(A22="","",IFERROR(VLOOKUP(A22,基础资料!$Y$5:$Z$204,2,FALSE),""))
A23: =IF(基础资料!Y23="","",基础资料!Y23) | B23: =IF(A23="","",IFERROR(VLOOKUP(A23,基础资料!$Y$5:$AA$204,3,FALSE),0)) | C23: =IF(A23="","",SUMIFS(期初数据!$H$5:$H$14,期初数据!$F$5:$F$14,A23)+SUMIFS(销售录入!$I$4:$I$203,销售录入!$C$4:$C$203,A23,销售录入!$A$4:$A$203,"<"&EOMONTH($B$2,-1)+1)-SUMIFS(资金流水!$J$4:$J$203,资金流水!$F$4:$F$203,A23,资金流水!$D$4:$D$203,"客户回款",资金流水!$A$4:$A$203,"<"&EOMONTH($B$2,-1)+1)) | D23: =IF(A23="","",SUMIFS(销售录入!$I$4:$I$203,销售录入!$C$4:$C$203,A23,销售录入!$B$4:$B$203,TEXT($B$2,"yyyy-mm"))) | E23: =IF(A23="","",SUMIFS(资金流水!$J$4:$J$203,资金流水!$F$4:$F$203,A23,资金流水!$D$4:$D$203,"客户回款",资金流水!$B$4:$B$203,TEXT($B$2,"yyyy-mm"))) | F23: =IF(A23="","",SUMIFS(应收明细账龄!$L$4:$L$213,应收明细账龄!$C$4:$C$213,A23)) | G23: =IF(A23="","",SUMIFS(应收明细账龄!$L$4:$L$213,应收明细账龄!$C$4:$C$213,A23,应收明细账龄!$N$4:$N$213,"未到期")) | H23: =IF(A23="","",SUMIFS(应收明细账龄!$L$4:$L$213,应收明细账龄!$C$4:$C$213,A23,应收明细账龄!$N$4:$N$213,"逾期1-30天")) | I23: =IF(A23="","",SUMIFS(应收明细账龄!$L$4:$L$213,应收明细账龄!$C$4:$C$213,A23,应收明细账龄!$N$4:$N$213,"逾期31-60天")) | J23: =IF(A23="","",SUMIFS(应收明细账龄!$L$4:$L$213,应收明细账龄!$C$4:$C$213,A23,应收明细账龄!$N$4:$N$213,"逾期61-90天")) | K23: =IF(A23="","",SUMIFS(应收明细账龄!$L$4:$L$213,应收明细账龄!$C$4:$C$213,A23,应收明细账龄!$N$4:$N$213,"逾期90天以上")) | L23: =IF(A23="","",SUM(H23:K23)) | M23: =IF(A23="","",IF(K23>0,"90天以上",IF(J23>0,"61-90天",IF(I23>0,"31-60天",IF(H23>0,"1-30天",IF(G23>0,"未到期","已收清")))))) | N23: =IF(A23="","",IF(K23>0,"高风险",IF(J23+I23>0,"重点关注",IF(H23>0,"到期提醒",IF(F23>0,"正常","已收清"))))) | O23: =IF(A23="","",IFERROR(VLOOKUP(A23,基础资料!$Y$5:$Z$204,2,FALSE),""))
A24: =IF(基础资料!Y24="","",基础资料!Y24) | B24: =IF(A24="","",IFERROR(VLOOKUP(A24,基础资料!$Y$5:$AA$204,3,FALSE),0)) | C24: =IF(A24="","",SUMIFS(期初数据!$H$5:$H$14,期初数据!$F$5:$F$14,A24)+SUMIFS(销售录入!$I$4:$I$203,销售录入!$C$4:$C$203,A24,销售录入!$A$4:$A$203,"<"&EOMONTH($B$2,-1)+1)-SUMIFS(资金流水!$J$4:$J$203,资金流水!$F$4:$F$203,A24,资金流水!$D$4:$D$203,"客户回款",资金流水!$A$4:$A$203,"<"&EOMONTH($B$2,-1)+1)) | D24: =IF(A24="","",SUMIFS(销售录入!$I$4:$I$203,销售录入!$C$4:$C$203,A24,销售录入!$B$4:$B$203,TEXT($B$2,"yyyy-mm"))) | E24: =IF(A24="","",SUMIFS(资金流水!$J$4:$J$203,资金流水!$F$4:$F$203,A24,资金流水!$D$4:$D$203,"客户回款",资金流水!$B$4:$B$203,TEXT($B$2,"yyyy-mm"))) | F24: =IF(A24="","",SUMIFS(应收明细账龄!$L$4:$L$213,应收明细账龄!$C$4:$C$213,A24)) | G24: =IF(A24="","",SUMIFS(应收明细账龄!$L$4:$L$213,应收明细账龄!$C$4:$C$213,A24,应收明细账龄!$N$4:$N$213,"未到期")) | H24: =IF(A24="","",SUMIFS(应收明细账龄!$L$4:$L$213,应收明细账龄!$C$4:$C$213,A24,应收明细账龄!$N$4:$N$213,"逾期1-30天")) | I24: =IF(A24="","",SUMIFS(应收明细账龄!$L$4:$L$213,应收明细账龄!$C$4:$C$213,A24,应收明细账龄!$N$4:$N$213,"逾期31-60天")) | J24: =IF(A24="","",SUMIFS(应收明细账龄!$L$4:$L$213,应收明细账龄!$C$4:$C$213,A24,应收明细账龄!$N$4:$N$213,"逾期61-90天")) | K24: =IF(A24="","",SUMIFS(应收明细账龄!$L$4:$L$213,应收明细账龄!$C$4:$C$213,A24,应收明细账龄!$N$4:$N$213,"逾期90天以上")) | L24: =IF(A24="","",SUM(H24:K24)) | M24: =IF(A24="","",IF(K24>0,"90天以上",IF(J24>0,"61-90天",IF(I24>0,"31-60天",IF(H24>0,"1-30天",IF(G24>0,"未到期","已收清")))))) | N24: =IF(A24="","",IF(K24>0,"高风险",IF(J24+I24>0,"重点关注",IF(H24>0,"到期提醒",IF(F24>0,"正常","已收清"))))) | O24: =IF(A24="","",IFERROR(VLOOKUP(A24,基础资料!$Y$5:$Z$204,2,FALSE),""))
A25: =IF(基础资料!Y25="","",基础资料!Y25) | B25: =IF(A25="","",IFERROR(VLOOKUP(A25,基础资料!$Y$5:$AA$204,3,FALSE),0)) | C25: =IF(A25="","",SUMIFS(期初数据!$H$5:$H$14,期初数据!$F$5:$F$14,A25)+SUMIFS(销售录入!$I$4:$I$203,销售录入!$C$4:$C$203,A25,销售录入!$A$4:$A$203,"<"&EOMONTH($B$2,-1)+1)-SUMIFS(资金流水!$J$4:$J$203,资金流水!$F$4:$F$203,A25,资金流水!$D$4:$D$203,"客户回款",资金流水!$A$4:$A$203,"<"&EOMONTH($B$2,-1)+1)) | D25: =IF(A25="","",SUMIFS(销售录入!$I$4:$I$203,销售录入!$C$4:$C$203,A25,销售录入!$B$4:$B$203,TEXT($B$2,"yyyy-mm"))) | E25: =IF(A25="","",SUMIFS(资金流水!$J$4:$J$203,资金流水!$F$4:$F$203,A25,资金流水!$D$4:$D$203,"客户回款",资金流水!$B$4:$B$203,TEXT($B$2,"yyyy-mm"))) | F25: =IF(A25="","",SUMIFS(应收明细账龄!$L$4:$L$213,应收明细账龄!$C$4:$C$213,A25)) | G25: =IF(A25="","",SUMIFS(应收明细账龄!$L$4:$L$213,应收明细账龄!$C$4:$C$213,A25,应收明细账龄!$N$4:$N$213,"未到期")) | H25: =IF(A25="","",SUMIFS(应收明细账龄!$L$4:$L$213,应收明细账龄!$C$4:$C$213,A25,应收明细账龄!$N$4:$N$213,"逾期1-30天")) | I25: =IF(A25="","",SUMIFS(应收明细账龄!$L$4:$L$213,应收明细账龄!$C$4:$C$213,A25,应收明细账龄!$N$4:$N$213,"逾期31-60天")) | J25: =IF(A25="","",SUMIFS(应收明细账龄!$L$4:$L$213,应收明细账龄!$C$4:$C$213,A25,应收明细账龄!$N$4:$N$213,"逾期61-90天")) | K25: =IF(A25="","",SUMIFS(应收明细账龄!$L$4:$L$213,应收明细账龄!$C$4:$C$213,A25,应收明细账龄!$N$4:$N$213,"逾期90天以上")) | L25: =IF(A25="","",SUM(H25:K25)) | M25: =IF(A25="","",IF(K25>0,"90天以上",IF(J25>0,"61-90天",IF(I25>0,"31-60天",IF(H25>0,"1-30天",IF(G25>0,"未到期","已收清")))))) | N25: =IF(A25="","",IF(K25>0,"高风险",IF(J25+I25>0,"重点关注",IF(H25>0,"到期提醒",IF(F25>0,"正常","已收清"))))) | O25: =IF(A25="","",IFERROR(VLOOKUP(A25,基础资料!$Y$5:$Z$204,2,FALSE),""))
A26: =IF(基础资料!Y26="","",基础资料!Y26) | B26: =IF(A26="","",IFERROR(VLOOKUP(A26,基础资料!$Y$5:$AA$204,3,FALSE),0)) | C26: =IF(A26="","",SUMIFS(期初数据!$H$5:$H$14,期初数据!$F$5:$F$14,A26)+SUMIFS(销售录入!$I$4:$I$203,销售录入!$C$4:$C$203,A26,销售录入!$A$4:$A$203,"<"&EOMONTH($B$2,-1)+1)-SUMIFS(资金流水!$J$4:$J$203,资金流水!$F$4:$F$203,A26,资金流水!$D$4:$D$203,"客户回款",资金流水!$A$4:$A$203,"<"&EOMONTH($B$2,-1)+1)) | D26: =IF(A26="","",SUMIFS(销售录入!$I$4:$I$203,销售录入!$C$4:$C$203,A26,销售录入!$B$4:$B$203,TEXT($B$2,"yyyy-mm"))) | E26: =IF(A26="","",SUMIFS(资金流水!$J$4:$J$203,资金流水!$F$4:$F$203,A26,资金流水!$D$4:$D$203,"客户回款",资金流水!$B$4:$B$203,TEXT($B$2,"yyyy-mm"))) | F26: =IF(A26="","",SUMIFS(应收明细账龄!$L$4:$L$213,应收明细账龄!$C$4:$C$213,A26)) | G26: =IF(A26="","",SUMIFS(应收明细账龄!$L$4:$L$213,应收明细账龄!$C$4:$C$213,A26,应收明细账龄!$N$4:$N$213,"未到期")) | H26: =IF(A26="","",SUMIFS(应收明细账龄!$L$4:$L$213,应收明细账龄!$C$4:$C$213,A26,应收明细账龄!$N$4:$N$213,"逾期1-30天")) | I26: =IF(A26="","",SUMIFS(应收明细账龄!$L$4:$L$213,应收明细账龄!$C$4:$C$213,A26,应收明细账龄!$N$4:$N$213,"逾期31-60天")) | J26: =IF(A26="","",SUMIFS(应收明细账龄!$L$4:$L$213,应收明细账龄!$C$4:$C$213,A26,应收明细账龄!$N$4:$N$213,"逾期61-90天")) | K26: =IF(A26="","",SUMIFS(应收明细账龄!$L$4:$L$213,应收明细账龄!$C$4:$C$213,A26,应收明细账龄!$N$4:$N$213,"逾期90天以上")) | L26: =IF(A26="","",SUM(H26:K26)) | M26: =IF(A26="","",IF(K26>0,"90天以上",IF(J26>0,"61-90天",IF(I26>0,"31-60天",IF(H26>0,"1-30天",IF(G26>0,"未到期","已收清")))))) | N26: =IF(A26="","",IF(K26>0,"高风险",IF(J26+I26>0,"重点关注",IF(H26>0,"到期提醒",IF(F26>0,"正常","已收清"))))) | O26: =IF(A26="","",IFERROR(VLOOKUP(A26,基础资料!$Y$5:$Z$204,2,FALSE),""))
... A54: =IF(基础资料!Y54="","",基础资料!Y54) | B54: =IF(A54="","",IFERROR(VLOOKUP(A54,基础资料!$Y$5:$AA$204,3,FALSE),0)) | C54: =IF(A54="","",SUMIFS(期初数据!$H$5:$H$14,期初数据!$F$5:$F$14,A54)+SUMIFS(销售录入!$I$4:$I$203,销售录入!$C$4:$C$203,A54,销售录入!$A$4:$A$203,"<"&EOMONTH($B$2,-1)+1)-SUMIFS(资金流水!$J$4:$J$203,资金流水!$F$4:$F$203,A54,资金流水!$D$4:$D$203,"客户回款",资金流水!$A$4:$A$203,"<"&EOMONTH($B$2,-1)+1)) | D54: =IF(A54="","",SUMIFS(销售录入!$I$4:$I$203,销售录入!$C$4:$C$203,A54,销售录入!$B$4:$B$203,TEXT($B$2,"yyyy-mm"))) | E54: =IF(A54="","",SUMIFS(资金流水!$J$4:$J$203,资金流水!$F$4:$F$203,A54,资金流水!$D$4:$D$203,"客户回款",资金流水!$B$4:$B$203,TEXT($B$2,"yyyy-mm"))) | F54: =IF(A54="","",SUMIFS(应收明细账龄!$L$4:$L$213,应收明细账龄!$C$4:$C$213,A54)) | G54: =IF(A54="","",SUMIFS(应收明细账龄!$L$4:$L$213,应收明细账龄!$C$4:$C$213,A54,应收明细账龄!$N$4:$N$213,"未到期")) | H54: =IF(A54="","",SUMIFS(应收明细账龄!$L$4:$L$213,应收明细账龄!$C$4:$C$213,A54,应收明细账龄!$N$4:$N$213,"逾期1-30天")) | I54: =IF(A54="","",SUMIFS(应收明细账龄!$L$4:$L$213,应收明细账龄!$C$4:$C$213,A54,应收明细账龄!$N$4:$N$213,"逾期31-60天")) | J54: =IF(A54="","",SUMIFS(应收明细账龄!$L$4:$L$213,应收明细账龄!$C$4:$C$213,A54,应收明细账龄!$N$4:$N$213,"逾期61-90天")) | K54: =IF(A54="","",SUMIFS(应收明细账龄!$L$4:$L$213,应收明细账龄!$C$4:$C$213,A54,应收明细账龄!$N$4:$N$213,"逾期90天以上")) | L54: =IF(A54="","",SUM(H54:K54)) | M54: =IF(A54="","",IF(K54>0,"90天以上",IF(J54>0,"61-90天",IF(I54>0,"31-60天",IF(H54>0,"1-30天",IF(G54>0,"未到期","已收清")))))) | N54: =IF(A54="","",IF(K54>0,"高风险",IF(J54+I54>0,"重点关注",IF(H54>0,"到期提醒",IF(F54>0,"正常","已收清"))))) | O54: =IF(A54="","",IFERROR(VLOOKUP(A54,基础资料!$Y$5:$Z$204,2,FALSE),""))

Sheet 应收明细账龄
A1: 应收明细账龄（FIFO自动核销 + 可人工指定核销）
A2: 默认按最早应收优先核销；人工指定核销仅在特殊情况下填写。
A3: 来源 | B3: 业务日期 | C3: 客户 | D3: 摘要/商品 | E3: 原应收 | F3: 到期日 | G3: 客户累计回款 | H3: 前序应收累计 | I3: 人工指定核销 | J3: FIFO自动核销 | K3: 本笔已核销 | L3: 剩余应收 | M3: 逾期天数 | N3: 账龄区间 | O3: 风险等级 | P3: 业务员 | Q3: 备注
A4: ="期初" -> 期初 | B4: =期初数据!G5 -> 46023 | C4: =期初数据!F5 -> 客户A | D4: ="期初应收" -> 期初应收 | E4: =期初数据!H5 -> 15000 | F4: =IF(B4="","",B4+IFERROR(VLOOKUP(C4,基础资料!$Y$5:$AA$204,3,FALSE),0)) -> 46053 | G4: =IF(C4="","",SUMIFS(资金流水!$J$4:$J$203,资金流水!$F$4:$F$203,C4,资金流水!$D$4:$D$203,"客户回款",资金流水!$A$4:$A$203,"<="&应收跟进!$E$2)) -> 12000 | H4: =0 -> 0 | J4: =IF(C4="","",MIN(MAX(0,E4-N(I4)),MAX(0,G4-SUMIFS($I$4:$I$213,$C$4:$C$213,C4)))) -> 12000 | K4: =IF(C4="","",MIN(E4,N(I4)+J4)) -> 12000 | L4: =IF(C4="","",MAX(0,E4-K4)) -> 3000 | M4: =IF(C4="","",IF(OR(L4<=0,F4=""),0,MAX(0,应收跟进!$E$2-F4))) -> 150 | N4: =IF(C4="","",IF(L4<=0,"已结清",IF(F4>应收跟进!$E$2,"未到期",IF(M4<=30,"逾期1-30天",IF(M4<=60,"逾期31-60天",IF(M4<=90,"逾期61-90天","逾期90天以上")))))) -> 逾期90天以上 | O4: =IF(C4="","",IF(L4<=0,"已结清",IF(M4>90,"高风险",IF(M4>30,"重点关注",IF(M4>0,"到期提醒","正常"))))) -> 高风险 | P4: =IFERROR(VLOOKUP(C4,基础资料!$Y$5:$Z$204,2,FALSE),"") -> 张伟 | Q4: ="期初应收" -> 期初应收
A5: ="期初" -> 期初 | B5: =期初数据!G6 -> 46023 | C5: =期初数据!F6 -> 客户B | D5: ="期初应收" -> 期初应收 | E5: =期初数据!H6 -> 12000 | F5: =IF(B5="","",B5+IFERROR(VLOOKUP(C5,基础资料!$Y$5:$AA$204,3,FALSE),0)) -> 46053 | G5: =IF(C5="","",SUMIFS(资金流水!$J$4:$J$203,资金流水!$F$4:$F$203,C5,资金流水!$D$4:$D$203,"客户回款",资金流水!$A$4:$A$203,"<="&应收跟进!$E$2)) -> 8000 | H5: =IF(C5="","",SUMIFS($E$4:E4,$C$4:C4,C5)) -> 0 | J5: =IF(C5="","",MIN(MAX(0,E5-N(I5)),MAX(0,G5-SUMIFS($I$4:$I$213,$C$4:$C$213,C5)-(SUMIFS($E$4:E4,$C$4:C4,C5)-SUMIFS($I$4:I4,$C$4:C4,C5))))) -> 8000 | K5: =IF(C5="","",MIN(E5,N(I5)+J5)) -> 8000 | L5: =IF(C5="","",MAX(0,E5-K5)) -> 4000 | M5: =IF(C5="","",IF(OR(L5<=0,F5=""),0,MAX(0,应收跟进!$E$2-F5))) -> 150 | N5: =IF(C5="","",IF(L5<=0,"已结清",IF(F5>应收跟进!$E$2,"未到期",IF(M5<=30,"逾期1-30天",IF(M5<=60,"逾期31-60天",IF(M5<=90,"逾期61-90天","逾期90天以上")))))) -> 逾期90天以上 | O5: =IF(C5="","",IF(L5<=0,"已结清",IF(M5>90,"高风险",IF(M5>30,"重点关注",IF(M5>0,"到期提醒","正常"))))) -> 高风险 | P5: =IFERROR(VLOOKUP(C5,基础资料!$Y$5:$Z$204,2,FALSE),"") -> 李娜 | Q5: ="期初应收" -> 期初应收
A6: ="期初" -> 期初 | B6: =期初数据!G7 -> 46023 | C6: =期初数据!F7 -> 客户C | D6: ="期初应收" -> 期初应收 | E6: =期初数据!H7 -> 18000 | F6: =IF(B6="","",B6+IFERROR(VLOOKUP(C6,基础资料!$Y$5:$AA$204,3,FALSE),0)) -> 46068 | G6: =IF(C6="","",SUMIFS(资金流水!$J$4:$J$203,资金流水!$F$4:$F$203,C6,资金流水!$D$4:$D$203,"客户回款",资金流水!$A$4:$A$203,"<="&应收跟进!$E$2)) -> 0 | H6: =IF(C6="","",SUMIFS($E$4:E5,$C$4:C5,C6)) -> 0 | J6: =IF(C6="","",MIN(MAX(0,E6-N(I6)),MAX(0,G6-SUMIFS($I$4:$I$213,$C$4:$C$213,C6)-(SUMIFS($E$4:E5,$C$4:C5,C6)-SUMIFS($I$4:I5,$C$4:C5,C6))))) -> 0 | K6: =IF(C6="","",MIN(E6,N(I6)+J6)) -> 0 | L6: =IF(C6="","",MAX(0,E6-K6)) -> 18000 | M6: =IF(C6="","",IF(OR(L6<=0,F6=""),0,MAX(0,应收跟进!$E$2-F6))) -> 135 | N6: =IF(C6="","",IF(L6<=0,"已结清",IF(F6>应收跟进!$E$2,"未到期",IF(M6<=30,"逾期1-30天",IF(M6<=60,"逾期31-60天",IF(M6<=90,"逾期61-90天","逾期90天以上")))))) -> 逾期90天以上 | O6: =IF(C6="","",IF(L6<=0,"已结清",IF(M6>90,"高风险",IF(M6>30,"重点关注",IF(M6>0,"到期提醒","正常"))))) -> 高风险 | P6: =IFERROR(VLOOKUP(C6,基础资料!$Y$5:$Z$204,2,FALSE),"") -> 张伟 | Q6: ="期初应收" -> 期初应收
A7: ="期初" -> 期初 | B7: =期初数据!G8 -> 46023 | C7: =期初数据!F8 -> 客户D | D7: ="期初应收" -> 期初应收 | E7: =期初数据!H8 -> 8000 | F7: =IF(B7="","",B7+IFERROR(VLOOKUP(C7,基础资料!$Y$5:$AA$204,3,FALSE),0)) -> 46053 | G7: =IF(C7="","",SUMIFS(资金流水!$J$4:$J$203,资金流水!$F$4:$F$203,C7,资金流水!$D$4:$D$203,"客户回款",资金流水!$A$4:$A$203,"<="&应收跟进!$E$2)) -> 0 | H7: =IF(C7="","",SUMIFS($E$4:E6,$C$4:C6,C7)) -> 0 | J7: =IF(C7="","",MIN(MAX(0,E7-N(I7)),MAX(0,G7-SUMIFS($I$4:$I$213,$C$4:$C$213,C7)-(SUMIFS($E$4:E6,$C$4:C6,C7)-SUMIFS($I$4:I6,$C$4:C6,C7))))) -> 0 | K7: =IF(C7="","",MIN(E7,N(I7)+J7)) -> 0 | L7: =IF(C7="","",MAX(0,E7-K7)) -> 8000 | M7: =IF(C7="","",IF(OR(L7<=0,F7=""),0,MAX(0,应收跟进!$E$2-F7))) -> 150 | N7: =IF(C7="","",IF(L7<=0,"已结清",IF(F7>应收跟进!$E$2,"未到期",IF(M7<=30,"逾期1-30天",IF(M7<=60,"逾期31-60天",IF(M7<=90,"逾期61-90天","逾期90天以上")))))) -> 逾期90天以上 | O7: =IF(C7="","",IF(L7<=0,"已结清",IF(M7>90,"高风险",IF(M7>30,"重点关注",IF(M7>0,"到期提醒","正常"))))) -> 高风险 | P7: =IFERROR(VLOOKUP(C7,基础资料!$Y$5:$Z$204,2,FALSE),"") -> 李娜 | Q7: ="期初应收" -> 期初应收
A8: ="期初" -> 期初 | B8: =期初数据!G9 -> 46023 | C8: =期初数据!F9 -> 客户E | D8: ="期初应收" -> 期初应收 | E8: =期初数据!H9 -> 25000 | F8: =IF(B8="","",B8+IFERROR(VLOOKUP(C8,基础资料!$Y$5:$AA$204,3,FALSE),0)) -> 46083 | G8: =IF(C8="","",SUMIFS(资金流水!$J$4:$J$203,资金流水!$F$4:$F$203,C8,资金流水!$D$4:$D$203,"客户回款",资金流水!$A$4:$A$203,"<="&应收跟进!$E$2)) -> 0 | H8: =IF(C8="","",SUMIFS($E$4:E7,$C$4:C7,C8)) -> 0 | J8: =IF(C8="","",MIN(MAX(0,E8-N(I8)),MAX(0,G8-SUMIFS($I$4:$I$213,$C$4:$C$213,C8)-(SUMIFS($E$4:E7,$C$4:C7,C8)-SUMIFS($I$4:I7,$C$4:C7,C8))))) -> 0 | K8: =IF(C8="","",MIN(E8,N(I8)+J8)) -> 0 | L8: =IF(C8="","",MAX(0,E8-K8)) -> 25000 | M8: =IF(C8="","",IF(OR(L8<=0,F8=""),0,MAX(0,应收跟进!$E$2-F8))) -> 120 | N8: =IF(C8="","",IF(L8<=0,"已结清",IF(F8>应收跟进!$E$2,"未到期",IF(M8<=30,"逾期1-30天",IF(M8<=60,"逾期31-60天",IF(M8<=90,"逾期61-90天","逾期90天以上")))))) -> 逾期90天以上 | O8: =IF(C8="","",IF(L8<=0,"已结清",IF(M8>90,"高风险",IF(M8>30,"重点关注",IF(M8>0,"到期提醒","正常"))))) -> 高风险 | P8: =IFERROR(VLOOKUP(C8,基础资料!$Y$5:$Z$204,2,FALSE),"") -> 张伟 | Q8: ="期初应收" -> 期初应收
A9: ="期初" -> 期初 | B9: =期初数据!G10 -> 46023 | C9: =期初数据!F10 -> 客户F | D9: ="期初应收" -> 期初应收 | E9: =期初数据!H10 -> 16000 | F9: =IF(B9="","",B9+IFERROR(VLOOKUP(C9,基础资料!$Y$5:$AA$204,3,FALSE),0)) -> 46053 | G9: =IF(C9="","",SUMIFS(资金流水!$J$4:$J$203,资金流水!$F$4:$F$203,C9,资金流水!$D$4:$D$203,"客户回款",资金流水!$A$4:$A$203,"<="&应收跟进!$E$2)) -> 0 | H9: =IF(C9="","",SUMIFS($E$4:E8,$C$4:C8,C9)) -> 0 | J9: =IF(C9="","",MIN(MAX(0,E9-N(I9)),MAX(0,G9-SUMIFS($I$4:$I$213,$C$4:$C$213,C9)-(SUMIFS($E$4:E8,$C$4:C8,C9)-SUMIFS($I$4:I8,$C$4:C8,C9))))) -> 0 | K9: =IF(C9="","",MIN(E9,N(I9)+J9)) -> 0 | L9: =IF(C9="","",MAX(0,E9-K9)) -> 16000 | M9: =IF(C9="","",IF(OR(L9<=0,F9=""),0,MAX(0,应收跟进!$E$2-F9))) -> 150 | N9: =IF(C9="","",IF(L9<=0,"已结清",IF(F9>应收跟进!$E$2,"未到期",IF(M9<=30,"逾期1-30天",IF(M9<=60,"逾期31-60天",IF(M9<=90,"逾期61-90天","逾期90天以上")))))) -> 逾期90天以上 | O9: =IF(C9="","",IF(L9<=0,"已结清",IF(M9>90,"高风险",IF(M9>30,"重点关注",IF(M9>0,"到期提醒","正常"))))) -> 高风险 | P9: =IFERROR(VLOOKUP(C9,基础资料!$Y$5:$Z$204,2,FALSE),"") -> 李娜 | Q9: ="期初应收" -> 期初应收
A10: ="期初" -> 期初 | B10: =期初数据!G11 -> 46023 | C10: =期初数据!F11 -> 客户G | D10: ="期初应收" -> 期初应收 | E10: =期初数据!H11 -> 14000 | F10: =IF(B10="","",B10+IFERROR(VLOOKUP(C10,基础资料!$Y$5:$AA$204,3,FALSE),0)) -> 46068 | G10: =IF(C10="","",SUMIFS(资金流水!$J$4:$J$203,资金流水!$F$4:$F$203,C10,资金流水!$D$4:$D$203,"客户回款",资金流水!$A$4:$A$203,"<="&应收跟进!$E$2)) -> 0 | H10: =IF(C10="","",SUMIFS($E$4:E9,$C$4:C9,C10)) -> 0 | J10: =IF(C10="","",MIN(MAX(0,E10-N(I10)),MAX(0,G10-SUMIFS($I$4:$I$213,$C$4:$C$213,C10)-(SUMIFS($E$4:E9,$C$4:C9,C10)-SUMIFS($I$4:I9,$C$4:C9,C10))))) -> 0 | K10: =IF(C10="","",MIN(E10,N(I10)+J10)) -> 0 | L10: =IF(C10="","",MAX(0,E10-K10)) -> 14000 | M10: =IF(C10="","",IF(OR(L10<=0,F10=""),0,MAX(0,应收跟进!$E$2-F10))) -> 135 | N10: =IF(C10="","",IF(L10<=0,"已结清",IF(F10>应收跟进!$E$2,"未到期",IF(M10<=30,"逾期1-30天",IF(M10<=60,"逾期31-60天",IF(M10<=90,"逾期61-90天","逾期90天以上")))))) -> 逾期90天以上 | O10: =IF(C10="","",IF(L10<=0,"已结清",IF(M10>90,"高风险",IF(M10>30,"重点关注",IF(M10>0,"到期提醒","正常"))))) -> 高风险 | P10: =IFERROR(VLOOKUP(C10,基础资料!$Y$5:$Z$204,2,FALSE),"") -> 张伟 | Q10: ="期初应收" -> 期初应收
A11: ="期初" -> 期初 | B11: =期初数据!G12 -> 46023 | C11: =期初数据!F12 -> 客户H | D11: ="期初应收" -> 期初应收 | E11: =期初数据!H12 -> 20000 | F11: =IF(B11="","",B11+IFERROR(VLOOKUP(C11,基础资料!$Y$5:$AA$204,3,FALSE),0)) -> 46053 | G11: =IF(C11="","",SUMIFS(资金流水!$J$4:$J$203,资金流水!$F$4:$F$203,C11,资金流水!$D$4:$D$203,"客户回款",资金流水!$A$4:$A$203,"<="&应收跟进!$E$2)) -> 0 | H11: =IF(C11="","",SUMIFS($E$4:E10,$C$4:C10,C11)) -> 0 | J11: =IF(C11="","",MIN(MAX(0,E11-N(I11)),MAX(0,G11-SUMIFS($I$4:$I$213,$C$4:$C$213,C11)-(SUMIFS($E$4:E10,$C$4:C10,C11)-SUMIFS($I$4:I10,$C$4:C10,C11))))) -> 0 | K11: =IF(C11="","",MIN(E11,N(I11)+J11)) -> 0 | L11: =IF(C11="","",MAX(0,E11-K11)) -> 20000 | M11: =IF(C11="","",IF(OR(L11<=0,F11=""),0,MAX(0,应收跟进!$E$2-F11))) -> 150 | N11: =IF(C11="","",IF(L11<=0,"已结清",IF(F11>应收跟进!$E$2,"未到期",IF(M11<=30,"逾期1-30天",IF(M11<=60,"逾期31-60天",IF(M11<=90,"逾期61-90天","逾期90天以上")))))) -> 逾期90天以上 | O11: =IF(C11="","",IF(L11<=0,"已结清",IF(M11>90,"高风险",IF(M11>30,"重点关注",IF(M11>0,"到期提醒","正常"))))) -> 高风险 | P11: =IFERROR(VLOOKUP(C11,基础资料!$Y$5:$Z$204,2,FALSE),"") -> 李娜 | Q11: ="期初应收" -> 期初应收
A12: ="期初" -> 期初 | B12: =期初数据!G13 -> 46023 | C12: =期初数据!F13 -> 客户I | D12: ="期初应收" -> 期初应收 | E12: =期初数据!H13 -> 10000 | F12: =IF(B12="","",B12+IFERROR(VLOOKUP(C12,基础资料!$Y$5:$AA$204,3,FALSE),0)) -> 46053 | G12: =IF(C12="","",SUMIFS(资金流水!$J$4:$J$203,资金流水!$F$4:$F$203,C12,资金流水!$D$4:$D$203,"客户回款",资金流水!$A$4:$A$203,"<="&应收跟进!$E$2)) -> 0 | H12: =IF(C12="","",SUMIFS($E$4:E11,$C$4:C11,C12)) -> 0 | J12: =IF(C12="","",MIN(MAX(0,E12-N(I12)),MAX(0,G12-SUMIFS($I$4:$I$213,$C$4:$C$213,C12)-(SUMIFS($E$4:E11,$C$4:C11,C12)-SUMIFS($I$4:I11,$C$4:C11,C12))))) -> 0 | K12: =IF(C12="","",MIN(E12,N(I12)+J12)) -> 0 | L12: =IF(C12="","",MAX(0,E12-K12)) -> 10000 | M12: =IF(C12="","",IF(OR(L12<=0,F12=""),0,MAX(0,应收跟进!$E$2-F12))) -> 150 | N12: =IF(C12="","",IF(L12<=0,"已结清",IF(F12>应收跟进!$E$2,"未到期",IF(M12<=30,"逾期1-30天",IF(M12<=60,"逾期31-60天",IF(M12<=90,"逾期61-90天","逾期90天以上")))))) -> 逾期90天以上 | O12: =IF(C12="","",IF(L12<=0,"已结清",IF(M12>90,"高风险",IF(M12>30,"重点关注",IF(M12>0,"到期提醒","正常"))))) -> 高风险 | P12: =IFERROR(VLOOKUP(C12,基础资料!$Y$5:$Z$204,2,FALSE),"") -> 张伟 | Q12: ="期初应收" -> 期初应收
A13: ="期初" -> 期初 | B13: =期初数据!G14 -> 46023 | C13: =期初数据!F14 -> 客户J | D13: ="期初应收" -> 期初应收 | E13: =期初数据!H14 -> 20000 | F13: =IF(B13="","",B13+IFERROR(VLOOKUP(C13,基础资料!$Y$5:$AA$204,3,FALSE),0)) -> 46083 | G13: =IF(C13="","",SUMIFS(资金流水!$J$4:$J$203,资金流水!$F$4:$F$203,C13,资金流水!$D$4:$D$203,"客户回款",资金流水!$A$4:$A$203,"<="&应收跟进!$E$2)) -> 0 | H13: =IF(C13="","",SUMIFS($E$4:E12,$C$4:C12,C13)) -> 0 | J13: =IF(C13="","",MIN(MAX(0,E13-N(I13)),MAX(0,G13-SUMIFS($I$4:$I$213,$C$4:$C$213,C13)-(SUMIFS($E$4:E12,$C$4:C12,C13)-SUMIFS($I$4:I12,$C$4:C12,C13))))) -> 0 | K13: =IF(C13="","",MIN(E13,N(I13)+J13)) -> 0 | L13: =IF(C13="","",MAX(0,E13-K13)) -> 20000 | M13: =IF(C13="","",IF(OR(L13<=0,F13=""),0,MAX(0,应收跟进!$E$2-F13))) -> 120 | N13: =IF(C13="","",IF(L13<=0,"已结清",IF(F13>应收跟进!$E$2,"未到期",IF(M13<=30,"逾期1-30天",IF(M13<=60,"逾期31-60天",IF(M13<=90,"逾期61-90天","逾期90天以上")))))) -> 逾期90天以上 | O13: =IF(C13="","",IF(L13<=0,"已结清",IF(M13>90,"高风险",IF(M13>30,"重点关注",IF(M13>0,"到期提醒","正常"))))) -> 高风险 | P13: =IFERROR(VLOOKUP(C13,基础资料!$Y$5:$Z$204,2,FALSE),"") -> 李娜 | Q13: ="期初应收" -> 期初应收
A14: =IF(销售录入!A4="","","销售") -> 销售 | B14: =IF(销售录入!A4="","",销售录入!A4) -> 46174 | C14: =IF(销售录入!A4="","",销售录入!C4) -> 客户A | D14: =IF(销售录入!A4="","",销售录入!D4) -> A配件 | E14: =IF(销售录入!A4="","",销售录入!I4) -> 4000 | F14: =IF(销售录入!A4="","",销售录入!L4) -> 46204 | G14: =IF(C14="","",SUMIFS(资金流水!$J$4:$J$203,资金流水!$F$4:$F$203,C14,资金流水!$D$4:$D$203,"客户回款",资金流水!$A$4:$A$203,"<="&应收跟进!$E$2)) -> 12000 | H14: =IF(C14="","",SUMIFS($E$4:E13,$C$4:C13,C14)) -> 15000 | J14: =IF(C14="","",MIN(MAX(0,E14-N(I14)),MAX(0,G14-SUMIFS($I$4:$I$213,$C$4:$C$213,C14)-(SUMIFS($E$4:E13,$C$4:C13,C14)-SUMIFS($I$4:I13,$C$4:C13,C14))))) -> 0 | K14: =IF(C14="","",MIN(E14,N(I14)+J14)) -> 0 | L14: =IF(C14="","",MAX(0,E14-K14)) -> 4000 | M14: =IF(C14="","",IF(OR(L14<=0,F14=""),0,MAX(0,应收跟进!$E$2-F14))) -> 0 | N14: =IF(C14="","",IF(L14<=0,"已结清",IF(F14>应收跟进!$E$2,"未到期",IF(M14<=30,"逾期1-30天",IF(M14<=60,"逾期31-60天",IF(M14<=90,"逾期61-90天","逾期90天以上")))))) -> 未到期 | O14: =IF(C14="","",IF(L14<=0,"已结清",IF(M14>90,"高风险",IF(M14>30,"重点关注",IF(M14>0,"到期提醒","正常"))))) -> 正常 | P14: =IF(销售录入!A4="","",销售录入!N4) -> 张伟 | Q14: =IF(销售录入!A4="","",销售录入!O4) -> 演示销售
A15: =IF(销售录入!A5="","","销售") -> 销售 | B15: =IF(销售录入!A5="","",销售录入!A5) -> 46176 | C15: =IF(销售录入!A5="","",销售录入!C5) -> 客户B | D15: =IF(销售录入!A5="","",销售录入!D5) -> B配件 | E15: =IF(销售录入!A5="","",销售录入!I5) -> 3750 | F15: =IF(销售录入!A5="","",销售录入!L5) -> 46206 | G15: =IF(C15="","",SUMIFS(资金流水!$J$4:$J$203,资金流水!$F$4:$F$203,C15,资金流水!$D$4:$D$203,"客户回款",资金流水!$A$4:$A$203,"<="&应收跟进!$E$2)) -> 8000 | H15: =IF(C15="","",SUMIFS($E$4:E14,$C$4:C14,C15)) -> 12000 | J15: =IF(C15="","",MIN(MAX(0,E15-N(I15)),MAX(0,G15-SUMIFS($I$4:$I$213,$C$4:$C$213,C15)-(SUMIFS($E$4:E14,$C$4:C14,C15)-SUMIFS($I$4:I14,$C$4:C14,C15))))) -> 0 | K15: =IF(C15="","",MIN(E15,N(I15)+J15)) -> 0 | L15: =IF(C15="","",MAX(0,E15-K15)) -> 3750 | M15: =IF(C15="","",IF(OR(L15<=0,F15=""),0,MAX(0,应收跟进!$E$2-F15))) -> 0 | N15: =IF(C15="","",IF(L15<=0,"已结清",IF(F15>应收跟进!$E$2,"未到期",IF(M15<=30,"逾期1-30天",IF(M15<=60,"逾期31-60天",IF(M15<=90,"逾期61-90天","逾期90天以上")))))) -> 未到期 | O15: =IF(C15="","",IF(L15<=0,"已结清",IF(M15>90,"高风险",IF(M15>30,"重点关注",IF(M15>0,"到期提醒","正常"))))) -> 正常 | P15: =IF(销售录入!A5="","",销售录入!N5) -> 李娜 | Q15: =IF(销售录入!A5="","",销售录入!O5) -> 演示销售
A16: =IF(销售录入!A6="","","销售") -> 销售 | B16: =IF(销售录入!A6="","",销售录入!A6) -> 46178 | C16: =IF(销售录入!A6="","",销售录入!C6) -> 客户C | D16: =IF(销售录入!A6="","",销售录入!D6) -> C配件 | E16: =IF(销售录入!A6="","",销售录入!I6) -> 3000 | F16: =IF(销售录入!A6="","",销售录入!L6) -> 46223 | G16: =IF(C16="","",SUMIFS(资金流水!$J$4:$J$203,资金流水!$F$4:$F$203,C16,资金流水!$D$4:$D$203,"客户回款",资金流水!$A$4:$A$203,"<="&应收跟进!$E$2)) -> 0 | H16: =IF(C16="","",SUMIFS($E$4:E15,$C$4:C15,C16)) -> 18000 | J16: =IF(C16="","",MIN(MAX(0,E16-N(I16)),MAX(0,G16-SUMIFS($I$4:$I$213,$C$4:$C$213,C16)-(SUMIFS($E$4:E15,$C$4:C15,C16)-SUMIFS($I$4:I15,$C$4:C15,C16))))) -> 0 | K16: =IF(C16="","",MIN(E16,N(I16)+J16)) -> 0 | L16: =IF(C16="","",MAX(0,E16-K16)) -> 3000 | M16: =IF(C16="","",IF(OR(L16<=0,F16=""),0,MAX(0,应收跟进!$E$2-F16))) -> 0 | N16: =IF(C16="","",IF(L16<=0,"已结清",IF(F16>应收跟进!$E$2,"未到期",IF(M16<=30,"逾期1-30天",IF(M16<=60,"逾期31-60天",IF(M16<=90,"逾期61-90天","逾期90天以上")))))) -> 未到期 | O16: =IF(C16="","",IF(L16<=0,"已结清",IF(M16>90,"高风险",IF(M16>30,"重点关注",IF(M16>0,"到期提醒","正常"))))) -> 正常 | P16: =IF(销售录入!A6="","",销售录入!N6) -> 张伟 | Q16: =IF(销售录入!A6="","",销售录入!O6) -> 演示销售
A17: =IF(销售录入!A7="","","销售") -> 销售 | B17: =IF(销售录入!A7="","",销售录入!A7) -> 46180 | C17: =IF(销售录入!A7="","",销售录入!C7) -> 客户D | D17: =IF(销售录入!A7="","",销售录入!D7) -> D配件 | E17: =IF(销售录入!A7="","",销售录入!I7) -> 3200 | F17: =IF(销售录入!A7="","",销售录入!L7) -> 46210 | G17: =IF(C17="","",SUMIFS(资金流水!$J$4:$J$203,资金流水!$F$4:$F$203,C17,资金流水!$D$4:$D$203,"客户回款",资金流水!$A$4:$A$203,"<="&应收跟进!$E$2)) -> 0 | H17: =IF(C17="","",SUMIFS($E$4:E16,$C$4:C16,C17)) -> 8000 | J17: =IF(C17="","",MIN(MAX(0,E17-N(I17)),MAX(0,G17-SUMIFS($I$4:$I$213,$C$4:$C$213,C17)-(SUMIFS($E$4:E16,$C$4:C16,C17)-SUMIFS($I$4:I16,$C$4:C16,C17))))) -> 0 | K17: =IF(C17="","",MIN(E17,N(I17)+J17)) -> 0 | L17: =IF(C17="","",MAX(0,E17-K17)) -> 3200 | M17: =IF(C17="","",IF(OR(L17<=0,F17=""),0,MAX(0,应收跟进!$E$2-F17))) -> 0 | N17: =IF(C17="","",IF(L17<=0,"已结清",IF(F17>应收跟进!$E$2,"未到期",IF(M17<=30,"逾期1-30天",IF(M17<=60,"逾期31-60天",IF(M17<=90,"逾期61-90天","逾期90天以上")))))) -> 未到期 | O17: =IF(C17="","",IF(L17<=0,"已结清",IF(M17>90,"高风险",IF(M17>30,"重点关注",IF(M17>0,"到期提醒","正常"))))) -> 正常 | P17: =IF(销售录入!A7="","",销售录入!N7) -> 李娜 | Q17: =IF(销售录入!A7="","",销售录入!O7) -> 演示销售
A18: =IF(销售录入!A8="","","销售") -> 销售 | B18: =IF(销售录入!A8="","",销售录入!A8) -> 46182 | C18: =IF(销售录入!A8="","",销售录入!C8) -> 客户E | D18: =IF(销售录入!A8="","",销售录入!D8) -> E配件 | E18: =IF(销售录入!A8="","",销售录入!I8) -> 2500 | F18: =IF(销售录入!A8="","",销售录入!L8) -> 46242 | G18: =IF(C18="","",SUMIFS(资金流水!$J$4:$J$203,资金流水!$F$4:$F$203,C18,资金流水!$D$4:$D$203,"客户回款",资金流水!$A$4:$A$203,"<="&应收跟进!$E$2)) -> 0 | H18: =IF(C18="","",SUMIFS($E$4:E17,$C$4:C17,C18)) -> 25000 | J18: =IF(C18="","",MIN(MAX(0,E18-N(I18)),MAX(0,G18-SUMIFS($I$4:$I$213,$C$4:$C$213,C18)-(SUMIFS($E$4:E17,$C$4:C17,C18)-SUMIFS($I$4:I17,$C$4:C17,C18))))) -> 0 | K18: =IF(C18="","",MIN(E18,N(I18)+J18)) -> 0 | L18: =IF(C18="","",MAX(0,E18-K18)) -> 2500 | M18: =IF(C18="","",IF(OR(L18<=0,F18=""),0,MAX(0,应收跟进!$E$2-F18))) -> 0 | N18: =IF(C18="","",IF(L18<=0,"已结清",IF(F18>应收跟进!$E$2,"未到期",IF(M18<=30,"逾期1-30天",IF(M18<=60,"逾期31-60天",IF(M18<=90,"逾期61-90天","逾期90天以上")))))) -> 未到期 | O18: =IF(C18="","",IF(L18<=0,"已结清",IF(M18>90,"高风险",IF(M18>30,"重点关注",IF(M18>0,"到期提醒","正常"))))) -> 正常 | P18: =IF(销售录入!A8="","",销售录入!N8) -> 孙悦 | Q18: =IF(销售录入!A8="","",销售录入!O8) -> 演示销售
A19: =IF(销售录入!A9="","","销售") -> 销售 | B19: =IF(销售录入!A9="","",销售录入!A9) -> 46184 | C19: =IF(销售录入!A9="","",销售录入!C9) -> 客户F | D19: =IF(销售录入!A9="","",销售录入!D9) -> F配件 | E19: =IF(销售录入!A9="","",销售录入!I9) -> 1920 | F19: =IF(销售录入!A9="","",销售录入!L9) -> 46214 | G19: =IF(C19="","",SUMIFS(资金流水!$J$4:$J$203,资金流水!$F$4:$F$203,C19,资金流水!$D$4:$D$203,"客户回款",资金流水!$A$4:$A$203,"<="&应收跟进!$E$2)) -> 0 | H19: =IF(C19="","",SUMIFS($E$4:E18,$C$4:C18,C19)) -> 16000 | J19: =IF(C19="","",MIN(MAX(0,E19-N(I19)),MAX(0,G19-SUMIFS($I$4:$I$213,$C$4:$C$213,C19)-(SUMIFS($E$4:E18,$C$4:C18,C19)-SUMIFS($I$4:I18,$C$4:C18,C19))))) -> 0 | K19: =IF(C19="","",MIN(E19,N(I19)+J19)) -> 0 | L19: =IF(C19="","",MAX(0,E19-K19)) -> 1920 | M19: =IF(C19="","",IF(OR(L19<=0,F19=""),0,MAX(0,应收跟进!$E$2-F19))) -> 0 | N19: =IF(C19="","",IF(L19<=0,"已结清",IF(F19>应收跟进!$E$2,"未到期",IF(M19<=30,"逾期1-30天",IF(M19<=60,"逾期31-60天",IF(M19<=90,"逾期61-90天","逾期90天以上")))))) -> 未到期 | O19: =IF(C19="","",IF(L19<=0,"已结清",IF(M19>90,"高风险",IF(M19>30,"重点关注",IF(M19>0,"到期提醒","正常"))))) -> 正常 | P19: =IF(销售录入!A9="","",销售录入!N9) -> 李娜 | Q19: =IF(销售录入!A9="","",销售录入!O9) -> 演示销售
A20: =IF(销售录入!A10="","","销售") -> 销售 | B20: =IF(销售录入!A10="","",销售录入!A10) -> 46186 | C20: =IF(销售录入!A10="","",销售录入!C10) -> 客户G | D20: =IF(销售录入!A10="","",销售录入!D10) -> G配件 | E20: =IF(销售录入!A10="","",销售录入!I10) -> 2250 | F20: =IF(销售录入!A10="","",销售录入!L10) -> 46231 | G20: =IF(C20="","",SUMIFS(资金流水!$J$4:$J$203,资金流水!$F$4:$F$203,C20,资金流水!$D$4:$D$203,"客户回款",资金流水!$A$4:$A$203,"<="&应收跟进!$E$2)) -> 0 | H20: =IF(C20="","",SUMIFS($E$4:E19,$C$4:C19,C20)) -> 14000 | J20: =IF(C20="","",MIN(MAX(0,E20-N(I20)),MAX(0,G20-SUMIFS($I$4:$I$213,$C$4:$C$213,C20)-(SUMIFS($E$4:E19,$C$4:C19,C20)-SUMIFS($I$4:I19,$C$4:C19,C20))))) -> 0 | K20: =IF(C20="","",MIN(E20,N(I20)+J20)) -> 0 | L20: =IF(C20="","",MAX(0,E20-K20)) -> 2250 | M20: =IF(C20="","",IF(OR(L20<=0,F20=""),0,MAX(0,应收跟进!$E$2-F20))) -> 0 | N20: =IF(C20="","",IF(L20<=0,"已结清",IF(F20>应收跟进!$E$2,"未到期",IF(M20<=30,"逾期1-30天",IF(M20<=60,"逾期31-60天",IF(M20<=90,"逾期61-90天","逾期90天以上")))))) -> 未到期 | O20: =IF(C20="","",IF(L20<=0,"已结清",IF(M20>90,"高风险",IF(M20>30,"重点关注",IF(M20>0,"到期提醒","正常"))))) -> 正常 | P20: =IF(销售录入!A10="","",销售录入!N10) -> 张伟 | Q20: =IF(销售录入!A10="","",销售录入!O10) -> 演示销售
A21: =IF(销售录入!A11="","","销售") -> 销售 | B21: =IF(销售录入!A11="","",销售录入!A11) -> 46188 | C21: =IF(销售录入!A11="","",销售录入!C11) -> 客户H | D21: =IF(销售录入!A11="","",销售录入!D11) -> H配件 | E21: =IF(销售录入!A11="","",销售录入!I11) -> 1800 | F21: =IF(销售录入!A11="","",销售录入!L11) -> 46218 | G21: =IF(C21="","",SUMIFS(资金流水!$J$4:$J$203,资金流水!$F$4:$F$203,C21,资金流水!$D$4:$D$203,"客户回款",资金流水!$A$4:$A$203,"<="&应收跟进!$E$2)) -> 0 | H21: =IF(C21="","",SUMIFS($E$4:E20,$C$4:C20,C21)) -> 20000 | J21: =IF(C21="","",MIN(MAX(0,E21-N(I21)),MAX(0,G21-SUMIFS($I$4:$I$213,$C$4:$C$213,C21)-(SUMIFS($E$4:E20,$C$4:C20,C21)-SUMIFS($I$4:I20,$C$4:C20,C21))))) -> 0 | K21: =IF(C21="","",MIN(E21,N(I21)+J21)) -> 0 | L21: =IF(C21="","",MAX(0,E21-K21)) -> 1800 | M21: =IF(C21="","",IF(OR(L21<=0,F21=""),0,MAX(0,应收跟进!$E$2-F21))) -> 0 | N21: =IF(C21="","",IF(L21<=0,"已结清",IF(F21>应收跟进!$E$2,"未到期",IF(M21<=30,"逾期1-30天",IF(M21<=60,"逾期31-60天",IF(M21<=90,"逾期61-90天","逾期90天以上")))))) -> 未到期 | O21: =IF(C21="","",IF(L21<=0,"已结清",IF(M21>90,"高风险",IF(M21>30,"重点关注",IF(M21>0,"到期提醒","正常"))))) -> 正常 | P21: =IF(销售录入!A11="","",销售录入!N11) -> 李娜 | Q21: =IF(销售录入!A11="","",销售录入!O11) -> 演示销售
A22: =IF(销售录入!A12="","","销售") -> 销售 | B22: =IF(销售录入!A12="","",销售录入!A12) -> 46190 | C22: =IF(销售录入!A12="","",销售录入!C12) -> 客户I | D22: =IF(销售录入!A12="","",销售录入!D12) -> I配件 | E22: =IF(销售录入!A12="","",销售录入!I12) -> 1500 | F22: =IF(销售录入!A12="","",销售录入!L12) -> 46220 | G22: =IF(C22="","",SUMIFS(资金流水!$J$4:$J$203,资金流水!$F$4:$F$203,C22,资金流水!$D$4:$D$203,"客户回款",资金流水!$A$4:$A$203,"<="&应收跟进!$E$2)) -> 0 | H22: =IF(C22="","",SUMIFS($E$4:E21,$C$4:C21,C22)) -> 10000 | J22: =IF(C22="","",MIN(MAX(0,E22-N(I22)),MAX(0,G22-SUMIFS($I$4:$I$213,$C$4:$C$213,C22)-(SUMIFS($E$4:E21,$C$4:C21,C22)-SUMIFS($I$4:I21,$C$4:C21,C22))))) -> 0 | K22: =IF(C22="","",MIN(E22,N(I22)+J22)) -> 0 | L22: =IF(C22="","",MAX(0,E22-K22)) -> 1500 | M22: =IF(C22="","",IF(OR(L22<=0,F22=""),0,MAX(0,应收跟进!$E$2-F22))) -> 0 | N22: =IF(C22="","",IF(L22<=0,"已结清",IF(F22>应收跟进!$E$2,"未到期",IF(M22<=30,"逾期1-30天",IF(M22<=60,"逾期31-60天",IF(M22<=90,"逾期61-90天","逾期90天以上")))))) -> 未到期 | O22: =IF(C22="","",IF(L22<=0,"已结清",IF(M22>90,"高风险",IF(M22>30,"重点关注",IF(M22>0,"到期提醒","正常"))))) -> 正常 | P22: =IF(销售录入!A12="","",销售录入!N12) -> 张伟 | Q22: =IF(销售录入!A12="","",销售录入!O12) -> 演示销售
A23: =IF(销售录入!A13="","","销售") -> 销售 | B23: =IF(销售录入!A13="","",销售录入!A13) -> 46192 | C23: =IF(销售录入!A13="","",销售录入!C13) -> 客户J | D23: =IF(销售录入!A13="","",销售录入!D13) -> J配件 | E23: =IF(销售录入!A13="","",销售录入!I13) -> 2160 | F23: =IF(销售录入!A13="","",销售录入!L13) -> 46252 | G23: =IF(C23="","",SUMIFS(资金流水!$J$4:$J$203,资金流水!$F$4:$F$203,C23,资金流水!$D$4:$D$203,"客户回款",资金流水!$A$4:$A$203,"<="&应收跟进!$E$2)) -> 0 | H23: =IF(C23="","",SUMIFS($E$4:E22,$C$4:C22,C23)) -> 20000 | J23: =IF(C23="","",MIN(MAX(0,E23-N(I23)),MAX(0,G23-SUMIFS($I$4:$I$213,$C$4:$C$213,C23)-(SUMIFS($E$4:E22,$C$4:C22,C23)-SUMIFS($I$4:I22,$C$4:C22,C23))))) -> 0 | K23: =IF(C23="","",MIN(E23,N(I23)+J23)) -> 0 | L23: =IF(C23="","",MAX(0,E23-K23)) -> 2160 | M23: =IF(C23="","",IF(OR(L23<=0,F23=""),0,MAX(0,应收跟进!$E$2-F23))) -> 0 | N23: =IF(C23="","",IF(L23<=0,"已结清",IF(F23>应收跟进!$E$2,"未到期",IF(M23<=30,"逾期1-30天",IF(M23<=60,"逾期31-60天",IF(M23<=90,"逾期61-90天","逾期90天以上")))))) -> 未到期 | O23: =IF(C23="","",IF(L23<=0,"已结清",IF(M23>90,"高风险",IF(M23>30,"重点关注",IF(M23>0,"到期提醒","正常"))))) -> 正常 | P23: =IF(销售录入!A13="","",销售录入!N13) -> 李娜 | Q23: =IF(销售录入!A13="","",销售录入!O13) -> 演示销售
A24: =IF(销售录入!A14="","","销售") | B24: =IF(销售录入!A14="","",销售录入!A14) | C24: =IF(销售录入!A14="","",销售录入!C14) | D24: =IF(销售录入!A14="","",销售录入!D14) | E24: =IF(销售录入!A14="","",销售录入!I14) | F24: =IF(销售录入!A14="","",销售录入!L14) | G24: =IF(C24="","",SUMIFS(资金流水!$J$4:$J$203,资金流水!$F$4:$F$203,C24,资金流水!$D$4:$D$203,"客户回款",资金流水!$A$4:$A$203,"<="&应收跟进!$E$2)) | H24: =IF(C24="","",SUMIFS($E$4:E23,$C$4:C23,C24)) | J24: =IF(C24="","",MIN(MAX(0,E24-N(I24)),MAX(0,G24-SUMIFS($I$4:$I$213,$C$4:$C$213,C24)-(SUMIFS($E$4:E23,$C$4:C23,C24)-SUMIFS($I$4:I23,$C$4:C23,C24))))) | K24: =IF(C24="","",MIN(E24,N(I24)+J24)) | L24: =IF(C24="","",MAX(0,E24-K24)) | M24: =IF(C24="","",IF(OR(L24<=0,F24=""),0,MAX(0,应收跟进!$E$2-F24))) | N24: =IF(C24="","",IF(L24<=0,"已结清",IF(F24>应收跟进!$E$2,"未到期",IF(M24<=30,"逾期1-30天",IF(M24<=60,"逾期31-60天",IF(M24<=90,"逾期61-90天","逾期90天以上")))))) | O24: =IF(C24="","",IF(L24<=0,"已结清",IF(M24>90,"高风险",IF(M24>30,"重点关注",IF(M24>0,"到期提醒","正常"))))) | P24: =IF(销售录入!A14="","",销售录入!N14) | Q24: =IF(销售录入!A14="","",销售录入!O14)
A25: =IF(销售录入!A15="","","销售") | B25: =IF(销售录入!A15="","",销售录入!A15) | C25: =IF(销售录入!A15="","",销售录入!C15) | D25: =IF(销售录入!A15="","",销售录入!D15) | E25: =IF(销售录入!A15="","",销售录入!I15) | F25: =IF(销售录入!A15="","",销售录入!L15) | G25: =IF(C25="","",SUMIFS(资金流水!$J$4:$J$203,资金流水!$F$4:$F$203,C25,资金流水!$D$4:$D$203,"客户回款",资金流水!$A$4:$A$203,"<="&应收跟进!$E$2)) | H25: =IF(C25="","",SUMIFS($E$4:E24,$C$4:C24,C25)) | J25: =IF(C25="","",MIN(MAX(0,E25-N(I25)),MAX(0,G25-SUMIFS($I$4:$I$213,$C$4:$C$213,C25)-(SUMIFS($E$4:E24,$C$4:C24,C25)-SUMIFS($I$4:I24,$C$4:C24,C25))))) | K25: =IF(C25="","",MIN(E25,N(I25)+J25)) | L25: =IF(C25="","",MAX(0,E25-K25)) | M25: =IF(C25="","",IF(OR(L25<=0,F25=""),0,MAX(0,应收跟进!$E$2-F25))) | N25: =IF(C25="","",IF(L25<=0,"已结清",IF(F25>应收跟进!$E$2,"未到期",IF(M25<=30,"逾期1-30天",IF(M25<=60,"逾期31-60天",IF(M25<=90,"逾期61-90天","逾期90天以上")))))) | O25: =IF(C25="","",IF(L25<=0,"已结清",IF(M25>90,"高风险",IF(M25>30,"重点关注",IF(M25>0,"到期提醒","正常"))))) | P25: =IF(销售录入!A15="","",销售录入!N15) | Q25: =IF(销售录入!A15="","",销售录入!O15)
... A113: =IF(销售录入!A103="","","销售") | B113: =IF(销售录入!A103="","",销售录入!A103) | C113: =IF(销售录入!A103="","",销售录入!C103) | D113: =IF(销售录入!A103="","",销售录入!D103) | E113: =IF(销售录入!A103="","",销售录入!I103) | F113: =IF(销售录入!A103="","",销售录入!L103) | G113: =IF(C113="","",SUMIFS(资金流水!$J$4:$J$203,资金流水!$F$4:$F$203,C113,资金流水!$D$4:$D$203,"客户回款",资金流水!$A$4:$A$203,"<="&应收跟进!$E$2)) | H113: =IF(C113="","",SUMIFS($E$4:E112,$C$4:C112,C113)) | J113: =IF(C113="","",MIN(MAX(0,E113-N(I113)),MAX(0,G113-SUMIFS($I$4:$I$213,$C$4:$C$213,C113)-(SUMIFS($E$4:E112,$C$4:C112,C113)-SUMIFS($I$4:I112,$C$4:C112,C113))))) | K113: =IF(C113="","",MIN(E113,N(I113)+J113)) | L113: =IF(C113="","",MAX(0,E113-K113)) | M113: =IF(C113="","",IF(OR(L113<=0,F113=""),0,MAX(0,应收跟进!$E$2-F113))) | N113: =IF(C113="","",IF(L113<=0,"已结清",IF(F113>应收跟进!$E$2,"未到期",IF(M113<=30,"逾期1-30天",IF(M113<=60,"逾期31-60天",IF(M113<=90,"逾期61-90天","逾期90天以上")))))) | O113: =IF(C113="","",IF(L113<=0,"已结清",IF(M113>90,"高风险",IF(M113>30,"重点关注",IF(M113>0,"到期提醒","正常"))))) | P113: =IF(销售录入!A103="","",销售录入!N103) | Q113: =IF(销售录入!A103="","",销售录入!O103)
A114: =IF(销售录入!A104="","","销售") | B114: =IF(销售录入!A104="","",销售录入!A104) | C114: =IF(销售录入!A104="","",销售录入!C104) | D114: =IF(销售录入!A104="","",销售录入!D104) | E114: =IF(销售录入!A104="","",销售录入!I104) | F114: =IF(销售录入!A104="","",销售录入!L104) | G114: =IF(C114="","",SUMIFS(资金流水!$J$4:$J$203,资金流水!$F$4:$F$203,C114,资金流水!$D$4:$D$203,"客户回款",资金流水!$A$4:$A$203,"<="&应收跟进!$E$2)) | H114: =IF(C114="","",SUMIFS($E$4:E113,$C$4:C113,C114)) | J114: =IF(C114="","",MIN(MAX(0,E114-N(I114)),MAX(0,G114-SUMIFS($I$4:$I$213,$C$4:$C$213,C114)-(SUMIFS($E$4:E113,$C$4:C113,C114)-SUMIFS($I$4:I113,$C$4:C113,C114))))) | M114: =IF(C114="","",IF(OR(L114<=0,F114=""),0,MAX(0,应收跟进!$E$2-F114))) | N114: =IF(C114="","",IF(L114<=0,"已结清",IF(F114>应收跟进!$E$2,"未到期",IF(M114<=30,"逾期1-30天",IF(M114<=60,"逾期31-60天",IF(M114<=90,"逾期61-90天","逾期90天以上")))))) | P114: =IF(销售录入!A104="","",销售录入!N104) | Q114: =IF(销售录入!A104="","",销售录入!O104)
A115: =IF(销售录入!A105="","","销售") | B115: =IF(销售录入!A105="","",销售录入!A105) | C115: =IF(销售录入!A105="","",销售录入!C105) | D115: =IF(销售录入!A105="","",销售录入!D105) | E115: =IF(销售录入!A105="","",销售录入!I105) | F115: =IF(销售录入!A105="","",销售录入!L105) | G115: =IF(C115="","",SUMIFS(资金流水!$J$4:$J$203,资金流水!$F$4:$F$203,C115,资金流水!$D$4:$D$203,"客户回款",资金流水!$A$4:$A$203,"<="&应收跟进!$E$2)) | H115: =IF(C115="","",SUMIFS($E$4:E114,$C$4:C114,C115)) | J115: =IF(C115="","",MIN(MAX(0,E115-N(I115)),MAX(0,G115-SUMIFS($I$4:$I$213,$C$4:$C$213,C115)-(SUMIFS($E$4:E114,$C$4:C114,C115)-SUMIFS($I$4:I114,$C$4:C114,C115))))) | M115: =IF(C115="","",IF(OR(L115<=0,F115=""),0,MAX(0,应收跟进!$E$2-F115))) | N115: =IF(C115="","",IF(L115<=0,"已结清",IF(F115>应收跟进!$E$2,"未到期",IF(M115<=30,"逾期1-30天",IF(M115<=60,"逾期31-60天",IF(M115<=90,"逾期61-90天","逾期90天以上")))))) | P115: =IF(销售录入!A105="","",销售录入!N105) | Q115: =IF(销售录入!A105="","",销售录入!O105)
A116: =IF(销售录入!A106="","","销售") | B116: =IF(销售录入!A106="","",销售录入!A106) | C116: =IF(销售录入!A106="","",销售录入!C106) | D116: =IF(销售录入!A106="","",销售录入!D106) | E116: =IF(销售录入!A106="","",销售录入!I106) | F116: =IF(销售录入!A106="","",销售录入!L106) | G116: =IF(C116="","",SUMIFS(资金流水!$J$4:$J$203,资金流水!$F$4:$F$203,C116,资金流水!$D$4:$D$203,"客户回款",资金流水!$A$4:$A$203,"<="&应收跟进!$E$2)) | H116: =IF(C116="","",SUMIFS($E$4:E115,$C$4:C115,C116)) | J116: =IF(C116="","",MIN(MAX(0,E116-N(I116)),MAX(0,G116-SUMIFS($I$4:$I$213,$C$4:$C$213,C116)-(SUMIFS($E$4:E115,$C$4:C115,C116)-SUMIFS($I$4:I115,$C$4:C115,C116))))) | M116: =IF(C116="","",IF(OR(L116<=0,F116=""),0,MAX(0,应收跟进!$E$2-F116))) | N116: =IF(C116="","",IF(L116<=0,"已结清",IF(F116>应收跟进!$E$2,"未到期",IF(M116<=30,"逾期1-30天",IF(M116<=60,"逾期31-60天",IF(M116<=90,"逾期61-90天","逾期90天以上")))))) | P116: =IF(销售录入!A106="","",销售录入!N106) | Q116: =IF(销售录入!A106="","",销售录入!O106)
A117: =IF(销售录入!A107="","","销售") | B117: =IF(销售录入!A107="","",销售录入!A107) | C117: =IF(销售录入!A107="","",销售录入!C107) | D117: =IF(销售录入!A107="","",销售录入!D107) | E117: =IF(销售录入!A107="","",销售录入!I107) | F117: =IF(销售录入!A107="","",销售录入!L107) | G117: =IF(C117="","",SUMIFS(资金流水!$J$4:$J$203,资金流水!$F$4:$F$203,C117,资金流水!$D$4:$D$203,"客户回款",资金流水!$A$4:$A$203,"<="&应收跟进!$E$2)) | H117: =IF(C117="","",SUMIFS($E$4:E116,$C$4:C116,C117)) | J117: =IF(C117="","",MIN(MAX(0,E117-N(I117)),MAX(0,G117-SUMIFS($I$4:$I$213,$C$4:$C$213,C117)-(SUMIFS($E$4:E116,$C$4:C116,C117)-SUMIFS($I$4:I116,$C$4:C116,C117))))) | M117: =IF(C117="","",IF(OR(L117<=0,F117=""),0,MAX(0,应收跟进!$E$2-F117))) | N117: =IF(C117="","",IF(L117<=0,"已结清",IF(F117>应收跟进!$E$2,"未到期",IF(M117<=30,"逾期1-30天",IF(M117<=60,"逾期31-60天",IF(M117<=90,"逾期61-90天","逾期90天以上")))))) | P117: =IF(销售录入!A107="","",销售录入!N107) | Q117: =IF(销售录入!A107="","",销售录入!O107)
A118: =IF(销售录入!A108="","","销售") | B118: =IF(销售录入!A108="","",销售录入!A108) | C118: =IF(销售录入!A108="","",销售录入!C108) | D118: =IF(销售录入!A108="","",销售录入!D108) | E118: =IF(销售录入!A108="","",销售录入!I108) | F118: =IF(销售录入!A108="","",销售录入!L108) | G118: =IF(C118="","",SUMIFS(资金流水!$J$4:$J$203,资金流水!$F$4:$F$203,C118,资金流水!$D$4:$D$203,"客户回款",资金流水!$A$4:$A$203,"<="&应收跟进!$E$2)) | H118: =IF(C118="","",SUMIFS($E$4:E117,$C$4:C117,C118)) | J118: =IF(C118="","",MIN(MAX(0,E118-N(I118)),MAX(0,G118-SUMIFS($I$4:$I$213,$C$4:$C$213,C118)-(SUMIFS($E$4:E117,$C$4:C117,C118)-SUMIFS($I$4:I117,$C$4:C117,C118))))) | M118: =IF(C118="","",IF(OR(L118<=0,F118=""),0,MAX(0,应收跟进!$E$2-F118))) | N118: =IF(C118="","",IF(L118<=0,"已结清",IF(F118>应收跟进!$E$2,"未到期",IF(M118<=30,"逾期1-30天",IF(M118<=60,"逾期31-60天",IF(M118<=90,"逾期61-90天","逾期90天以上")))))) | P118: =IF(销售录入!A108="","",销售录入!N108) | Q118: =IF(销售录入!A108="","",销售录入!O108)
A119: =IF(销售录入!A109="","","销售") | B119: =IF(销售录入!A109="","",销售录入!A109) | C119: =IF(销售录入!A109="","",销售录入!C109) | D119: =IF(销售录入!A109="","",销售录入!D109) | E119: =IF(销售录入!A109="","",销售录入!I109) | F119: =IF(销售录入!A109="","",销售录入!L109) | G119: =IF(C119="","",SUMIFS(资金流水!$J$4:$J$203,资金流水!$F$4:$F$203,C119,资金流水!$D$4:$D$203,"客户回款",资金流水!$A$4:$A$203,"<="&应收跟进!$E$2)) | H119: =IF(C119="","",SUMIFS($E$4:E118,$C$4:C118,C119)) | J119: =IF(C119="","",MIN(MAX(0,E119-N(I119)),MAX(0,G119-SUMIFS($I$4:$I$213,$C$4:$C$213,C119)-(SUMIFS($E$4:E118,$C$4:C118,C119)-SUMIFS($I$4:I118,$C$4:C118,C119))))) | M119: =IF(C119="","",IF(OR(L119<=0,F119=""),0,MAX(0,应收跟进!$E$2-F119))) | N119: =IF(C119="","",IF(L119<=0,"已结清",IF(F119>应收跟进!$E$2,"未到期",IF(M119<=30,"逾期1-30天",IF(M119<=60,"逾期31-60天",IF(M119<=90,"逾期61-90天","逾期90天以上")))))) | P119: =IF(销售录入!A109="","",销售录入!N109) | Q119: =IF(销售录入!A109="","",销售录入!O109)
A120: =IF(销售录入!A110="","","销售") | B120: =IF(销售录入!A110="","",销售录入!A110) | C120: =IF(销售录入!A110="","",销售录入!C110) | D120: =IF(销售录入!A110="","",销售录入!D110) | E120: =IF(销售录入!A110="","",销售录入!I110) | F120: =IF(销售录入!A110="","",销售录入!L110) | G120: =IF(C120="","",SUMIFS(资金流水!$J$4:$J$203,资金流水!$F$4:$F$203,C120,资金流水!$D$4:$D$203,"客户回款",资金流水!$A$4:$A$203,"<="&应收跟进!$E$2)) | H120: =IF(C120="","",SUMIFS($E$4:E119,$C$4:C119,C120)) | J120: =IF(C120="","",MIN(MAX(0,E120-N(I120)),MAX(0,G120-SUMIFS($I$4:$I$213,$C$4:$C$213,C120)-(SUMIFS($E$4:E119,$C$4:C119,C120)-SUMIFS($I$4:I119,$C$4:C119,C120))))) | M120: =IF(C120="","",IF(OR(L120<=0,F120=""),0,MAX(0,应收跟进!$E$2-F120))) | N120: =IF(C120="","",IF(L120<=0,"已结清",IF(F120>应收跟进!$E$2,"未到期",IF(M120<=30,"逾期1-30天",IF(M120<=60,"逾期31-60天",IF(M120<=90,"逾期61-90天","逾期90天以上")))))) | P120: =IF(销售录入!A110="","",销售录入!N110) | Q120: =IF(销售录入!A110="","",销售录入!O110)
A121: =IF(销售录入!A111="","","销售") | B121: =IF(销售录入!A111="","",销售录入!A111) | C121: =IF(销售录入!A111="","",销售录入!C111) | D121: =IF(销售录入!A111="","",销售录入!D111) | E121: =IF(销售录入!A111="","",销售录入!I111) | F121: =IF(销售录入!A111="","",销售录入!L111) | G121: =IF(C121="","",SUMIFS(资金流水!$J$4:$J$203,资金流水!$F$4:$F$203,C121,资金流水!$D$4:$D$203,"客户回款",资金流水!$A$4:$A$203,"<="&应收跟进!$E$2)) | H121: =IF(C121="","",SUMIFS($E$4:E120,$C$4:C120,C121)) | J121: =IF(C121="","",MIN(MAX(0,E121-N(I121)),MAX(0,G121-SUMIFS($I$4:$I$213,$C$4:$C$213,C121)-(SUMIFS($E$4:E120,$C$4:C120,C121)-SUMIFS($I$4:I120,$C$4:C120,C121))))) | M121: =IF(C121="","",IF(OR(L121<=0,F121=""),0,MAX(0,应收跟进!$E$2-F121))) | N121: =IF(C121="","",IF(L121<=0,"已结清",IF(F121>应收跟进!$E$2,"未到期",IF(M121<=30,"逾期1-30天",IF(M121<=60,"逾期31-60天",IF(M121<=90,"逾期61-90天","逾期90天以上")))))) | P121: =IF(销售录入!A111="","",销售录入!N111) | Q121: =IF(销售录入!A111="","",销售录入!O111)
A122: =IF(销售录入!A112="","","销售") | B122: =IF(销售录入!A112="","",销售录入!A112) | C122: =IF(销售录入!A112="","",销售录入!C112) | D122: =IF(销售录入!A112="","",销售录入!D112) | E122: =IF(销售录入!A112="","",销售录入!I112) | F122: =IF(销售录入!A112="","",销售录入!L112) | G122: =IF(C122="","",SUMIFS(资金流水!$J$4:$J$203,资金流水!$F$4:$F$203,C122,资金流水!$D$4:$D$203,"客户回款",资金流水!$A$4:$A$203,"<="&应收跟进!$E$2)) | H122: =IF(C122="","",SUMIFS($E$4:E121,$C$4:C121,C122)) | J122: =IF(C122="","",MIN(MAX(0,E122-N(I122)),MAX(0,G122-SUMIFS($I$4:$I$213,$C$4:$C$213,C122)-(SUMIFS($E$4:E121,$C$4:C121,C122)-SUMIFS($I$4:I121,$C$4:C121,C122))))) | M122: =IF(C122="","",IF(OR(L122<=0,F122=""),0,MAX(0,应收跟进!$E$2-F122))) | N122: =IF(C122="","",IF(L122<=0,"已结清",IF(F122>应收跟进!$E$2,"未到期",IF(M122<=30,"逾期1-30天",IF(M122<=60,"逾期31-60天",IF(M122<=90,"逾期61-90天","逾期90天以上")))))) | P122: =IF(销售录入!A112="","",销售录入!N112) | Q122: =IF(销售录入!A112="","",销售录入!O112)
A123: =IF(销售录入!A113="","","销售") | B123: =IF(销售录入!A113="","",销售录入!A113) | C123: =IF(销售录入!A113="","",销售录入!C113) | D123: =IF(销售录入!A113="","",销售录入!D113) | E123: =IF(销售录入!A113="","",销售录入!I113) | F123: =IF(销售录入!A113="","",销售录入!L113) | G123: =IF(C123="","",SUMIFS(资金流水!$J$4:$J$203,资金流水!$F$4:$F$203,C123,资金流水!$D$4:$D$203,"客户回款",资金流水!$A$4:$A$203,"<="&应收跟进!$E$2)) | H123: =IF(C123="","",SUMIFS($E$4:E122,$C$4:C122,C123)) | J123: =IF(C123="","",MIN(MAX(0,E123-N(I123)),MAX(0,G123-SUMIFS($I$4:$I$213,$C$4:$C$213,C123)-(SUMIFS($E$4:E122,$C$4:C122,C123)-SUMIFS($I$4:I122,$C$4:C122,C123))))) | M123: =IF(C123="","",IF(OR(L123<=0,F123=""),0,MAX(0,应收跟进!$E$2-F123))) | N123: =IF(C123="","",IF(L123<=0,"已结清",IF(F123>应收跟进!$E$2,"未到期",IF(M123<=30,"逾期1-30天",IF(M123<=60,"逾期31-60天",IF(M123<=90,"逾期61-90天","逾期90天以上")))))) | P123: =IF(销售录入!A113="","",销售录入!N113) | Q123: =IF(销售录入!A113="","",销售录入!O113)
A124: =IF(销售录入!A114="","","销售") | B124: =IF(销售录入!A114="","",销售录入!A114) | C124: =IF(销售录入!A114="","",销售录入!C114) | D124: =IF(销售录入!A114="","",销售录入!D114) | E124: =IF(销售录入!A114="","",销售录入!I114) | F124: =IF(销售录入!A114="","",销售录入!L114) | G124: =IF(C124="","",SUMIFS(资金流水!$J$4:$J$203,资金流水!$F$4:$F$203,C124,资金流水!$D$4:$D$203,"客户回款",资金流水!$A$4:$A$203,"<="&应收跟进!$E$2)) | H124: =IF(C124="","",SUMIFS($E$4:E123,$C$4:C123,C124)) | J124: =IF(C124="","",MIN(MAX(0,E124-N(I124)),MAX(0,G124-SUMIFS($I$4:$I$213,$C$4:$C$213,C124)-(SUMIFS($E$4:E123,$C$4:C123,C124)-SUMIFS($I$4:I123,$C$4:C123,C124))))) | M124: =IF(C124="","",IF(OR(L124<=0,F124=""),0,MAX(0,应收跟进!$E$2-F124))) | N124: =IF(C124="","",IF(L124<=0,"已结清",IF(F124>应收跟进!$E$2,"未到期",IF(M124<=30,"逾期1-30天",IF(M124<=60,"逾期31-60天",IF(M124<=90,"逾期61-90天","逾期90天以上")))))) | P124: =IF(销售录入!A114="","",销售录入!N114) | Q124: =IF(销售录入!A114="","",销售录入!O114)
A125: =IF(销售录入!A115="","","销售") | B125: =IF(销售录入!A115="","",销售录入!A115) | C125: =IF(销售录入!A115="","",销售录入!C115) | D125: =IF(销售录入!A115="","",销售录入!D115) | E125: =IF(销售录入!A115="","",销售录入!I115) | F125: =IF(销售录入!A115="","",销售录入!L115) | G125: =IF(C125="","",SUMIFS(资金流水!$J$4:$J$203,资金流水!$F$4:$F$203,C125,资金流水!$D$4:$D$203,"客户回款",资金流水!$A$4:$A$203,"<="&应收跟进!$E$2)) | H125: =IF(C125="","",SUMIFS($E$4:E124,$C$4:C124,C125)) | J125: =IF(C125="","",MIN(MAX(0,E125-N(I125)),MAX(0,G125-SUMIFS($I$4:$I$213,$C$4:$C$213,C125)-(SUMIFS($E$4:E124,$C$4:C124,C125)-SUMIFS($I$4:I124,$C$4:C124,C125))))) | M125: =IF(C125="","",IF(OR(L125<=0,F125=""),0,MAX(0,应收跟进!$E$2-F125))) | N125: =IF(C125="","",IF(L125<=0,"已结清",IF(F125>应收跟进!$E$2,"未到期",IF(M125<=30,"逾期1-30天",IF(M125<=60,"逾期31-60天",IF(M125<=90,"逾期61-90天","逾期90天以上")))))) | P125: =IF(销售录入!A115="","",销售录入!N115) | Q125: =IF(销售录入!A115="","",销售录入!O115)
... A213: =IF(销售录入!A203="","","销售") | B213: =IF(销售录入!A203="","",销售录入!A203) | C213: =IF(销售录入!A203="","",销售录入!C203) | D213: =IF(销售录入!A203="","",销售录入!D203) | E213: =IF(销售录入!A203="","",销售录入!I203) | F213: =IF(销售录入!A203="","",销售录入!L203) | G213: =IF(C213="","",SUMIFS(资金流水!$J$4:$J$203,资金流水!$F$4:$F$203,C213,资金流水!$D$4:$D$203,"客户回款",资金流水!$A$4:$A$203,"<="&应收跟进!$E$2)) | H213: =IF(C213="","",SUMIFS($E$4:E212,$C$4:C212,C213)) | J213: =IF(C213="","",MIN(MAX(0,E213-N(I213)),MAX(0,G213-SUMIFS($I$4:$I$213,$C$4:$C$213,C213)-(SUMIFS($E$4:E212,$C$4:C212,C213)-SUMIFS($I$4:I212,$C$4:C212,C213))))) | M213: =IF(C213="","",IF(OR(L213<=0,F213=""),0,MAX(0,应收跟进!$E$2-F213))) | N213: =IF(C213="","",IF(L213<=0,"已结清",IF(F213>应收跟进!$E$2,"未到期",IF(M213<=30,"逾期1-30天",IF(M213<=60,"逾期31-60天",IF(M213<=90,"逾期61-90天","逾期90天以上")))))) | P213: =IF(销售录入!A203="","",销售录入!N203) | Q213: =IF(销售录入!A203="","",销售录入!O203)

Sheet 应付跟进
A1: 应付跟进 · 账期/付款计划分析
A2: 查询月份 | B2: =首页!$B$4 -> 46174
A3: 合计 | C3: =SUM(C5:C54) -> 210000 | D3: =SUM(D5:D54) -> 20300 | E3: =SUM(E5:E54) -> 10000 | F3: =SUM(F5:F54) -> 220300 | G3: =SUM(G5:G54) -> 16500 | H3: =SUM(H5:H54) -> 0 | I3: =SUM(I5:I54) -> 0 | J3: =SUM(J5:J54) -> 0 | ... L3: =SUM(L5:L54) -> 200000
A4: 供应商 | B4: 账期(天) | C4: 月初应付 | D4: 本月采购 | E4: 本月付款 | F4: 月末应付 | G4: 未来30天到期 | H4: 逾期1-30天 | I4: 逾期31-60天 | J4: 逾期61-90天 | K4: 逾期90天以上 | L4: 逾期合计 | M4: 付款优先级 | N4: 采购员
A5: =IF(基础资料!AE5="","",基础资料!AE5) -> 供应商A | B5: =IF(A5="","",IFERROR(VLOOKUP(A5,基础资料!$AE$5:$AG$204,3,FALSE),0)) -> 30 | C5: =IF(A5="","",SUMIFS(期初数据!$M$5:$M$14,期初数据!$K$5:$K$14,A5)+SUMIFS(采购录入!$I$4:$I$203,采购录入!$C$4:$C$203,A5,采购录入!$A$4:$A$203,"<"&EOMONTH($B$2,-1)+1)-SUMIFS(资金流水!$K$4:$K$203,资金流水!$F$4:$F$203,A5,资金流水!$D$4:$D$203,"供应商付款",资金流水!$A$4:$A$203,"<"&EOMONTH($B$2,-1)+1)) -> 25000 | D5: =IF(A5="","",SUMIFS(采购录入!$I$4:$I$203,采购录入!$C$4:$C$203,A5,采购录入!$B$4:$B$203,TEXT($B$2,"yyyy-mm"))) -> 3000 | E5: =IF(A5="","",SUMIFS(资金流水!$K$4:$K$203,资金流水!$F$4:$F$203,A5,资金流水!$D$4:$D$203,"供应商付款",资金流水!$B$4:$B$203,TEXT($B$2,"yyyy-mm"))) -> 10000 | F5: =IF(A5="","",SUMIFS(应付明细账龄!$K$4:$K$213,应付明细账龄!$C$4:$C$213,A5)) -> 18000 | G5: =IF(A5="","",SUMIFS(应付明细账龄!$K$4:$K$213,应付明细账龄!$C$4:$C$213,A5,应付明细账龄!$M$4:$M$213,"未来30天到期")) -> 3000 | H5: =IF(A5="","",SUMIFS(应付明细账龄!$K$4:$K$213,应付明细账龄!$C$4:$C$213,A5,应付明细账龄!$M$4:$M$213,"逾期1-30天")) -> 0 | I5: =IF(A5="","",SUMIFS(应付明细账龄!$K$4:$K$213,应付明细账龄!$C$4:$C$213,A5,应付明细账龄!$M$4:$M$213,"逾期31-60天")) -> 0 | J5: =IF(A5="","",SUMIFS(应付明细账龄!$K$4:$K$213,应付明细账龄!$C$4:$C$213,A5,应付明细账龄!$M$4:$M$213,"逾期61-90天")) -> 0 | K5: =IF(A5="","",SUMIFS(应付明细账龄!$K$4:$K$213,应付明细账龄!$C$4:$C$213,A5,应付明细账龄!$M$4:$M$213,"逾期90天以上")) -> 15000 | L5: =IF(A5="","",SUM(H5:K5)) -> 15000 | M5: =IF(A5="","",IF(K5>0,"紧急",IF(L5>0,"高",IF(G5>0,"中","低")))) -> 紧急 | N5: =IF(A5="","",IFERROR(VLOOKUP(A5,基础资料!$AE$5:$AF$204,2,FALSE),"")) -> 王强
A6: =IF(基础资料!AE6="","",基础资料!AE6) -> 供应商B | B6: =IF(A6="","",IFERROR(VLOOKUP(A6,基础资料!$AE$5:$AG$204,3,FALSE),0)) -> 30 | C6: =IF(A6="","",SUMIFS(期初数据!$M$5:$M$14,期初数据!$K$5:$K$14,A6)+SUMIFS(采购录入!$I$4:$I$203,采购录入!$C$4:$C$203,A6,采购录入!$A$4:$A$203,"<"&EOMONTH($B$2,-1)+1)-SUMIFS(资金流水!$K$4:$K$203,资金流水!$F$4:$F$203,A6,资金流水!$D$4:$D$203,"供应商付款",资金流水!$A$4:$A$203,"<"&EOMONTH($B$2,-1)+1)) -> 22000 | D6: =IF(A6="","",SUMIFS(采购录入!$I$4:$I$203,采购录入!$C$4:$C$203,A6,采购录入!$B$4:$B$203,TEXT($B$2,"yyyy-mm"))) -> 2500 | E6: =IF(A6="","",SUMIFS(资金流水!$K$4:$K$203,资金流水!$F$4:$F$203,A6,资金流水!$D$4:$D$203,"供应商付款",资金流水!$B$4:$B$203,TEXT($B$2,"yyyy-mm"))) -> 0 | F6: =IF(A6="","",SUMIFS(应付明细账龄!$K$4:$K$213,应付明细账龄!$C$4:$C$213,A6)) -> 24500 | G6: =IF(A6="","",SUMIFS(应付明细账龄!$K$4:$K$213,应付明细账龄!$C$4:$C$213,A6,应付明细账龄!$M$4:$M$213,"未来30天到期")) -> 2500 | H6: =IF(A6="","",SUMIFS(应付明细账龄!$K$4:$K$213,应付明细账龄!$C$4:$C$213,A6,应付明细账龄!$M$4:$M$213,"逾期1-30天")) -> 0 | I6: =IF(A6="","",SUMIFS(应付明细账龄!$K$4:$K$213,应付明细账龄!$C$4:$C$213,A6,应付明细账龄!$M$4:$M$213,"逾期31-60天")) -> 0 | J6: =IF(A6="","",SUMIFS(应付明细账龄!$K$4:$K$213,应付明细账龄!$C$4:$C$213,A6,应付明细账龄!$M$4:$M$213,"逾期61-90天")) -> 0 | K6: =IF(A6="","",SUMIFS(应付明细账龄!$K$4:$K$213,应付明细账龄!$C$4:$C$213,A6,应付明细账龄!$M$4:$M$213,"逾期90天以上")) -> 22000 | L6: =IF(A6="","",SUM(H6:K6)) -> 22000 | M6: =IF(A6="","",IF(K6>0,"紧急",IF(L6>0,"高",IF(G6>0,"中","低")))) -> 紧急 | N6: =IF(A6="","",IFERROR(VLOOKUP(A6,基础资料!$AE$5:$AF$204,2,FALSE),"")) -> 王强
