Workbook
Name 账户表: 基础资料!$B$5:$B$34
Name 账户类型表: 基础资料!$C$5:$C$34
Name 账户期初: 基础资料!$D$5:$D$34
Name 账户启用: 基础资料!$E$5:$E$34
Name 类别表: 基础资料!$H$5:$H$44
Name 类别属性: 基础资料!$I$5:$I$44
Name 客户表: 基础资料!$K$5:$K$204
Name 供应商表: 基础资料!$M$5:$M$204
Name 项目表: 基础资料!$O$5:$O$54
Name 流水日期: 数据录入!$B$5:$B$5004
Name 流水账户: 数据录入!$C$5:$C$5004
Name 流水类别: 数据录入!$D$5:$D$5004
Name 流水收入: 数据录入!$F$5:$F$5004
Name 流水支出: 数据录入!$G$5:$G$5004
Name 流水月份: 数据录入!$K$5:$K$5004
Name 流水属性: 数据录入!$L$5:$L$5004
Name 流水对方: 数据录入!$M$5:$M$5004
Name 流水客户: 数据录入!$I$5:$I$5004
Name 流水供应商: 数据录入!$J$5:$J$5004
Name 流水项目: 数据录入!$N$5:$N$5004
Name 流水核对: 数据录入!$P$5:$P$5004
Name 日报期末合计: 汇报表!$BO$38
Name 月报收入合计: 月度汇报表!$B$17
Name 月报支出合计: 月度汇报表!$C$17
Name 分类收入合计: 收支分类报表!$O$5
Name 分类支出合计: 收支分类报表!$O$6
Name 分类转账净额: 收支分类报表!$O$7
Name 报表收入总额: 收支报表!$O$4
Name 报表支出总额: 收支报表!$O$48

Sheet 使用说明
A1: 资金日报表 · 混合录入版 ｜ 使用说明（单币种：人民币）
A3: 一、两步就能用起来
A4: 第 1 步 | B4: 【基础资料】 | C4: 把账户档案改成你们真实的账户：账户名称、类型、期初余额。收支类别、客户、供应商、项目也在这一页维护。
A5: 第 2 步 | B5: 【数据录入】 | C5: 每天在这一张录。选账户 → 余额自动结；收入和支出分两列，只填一个。其余所有表全自动。
A7: 二、这次跟原来那份比，改了什么
A8: 改动 | B8: 为什么 | C8: 影响
A9: 加了「内部转账」 | B9: 账户互转原来两头都算进收支 | C9: 【基础资料】收支类别多了一列「属性」：收入 / 支出 / 内部转账。账户之间调头寸选「内部转账」，它就不会被算进收入合计和支出合计 —— 原来把 5 万从工行转到现金，收入 +5 万、支出 +5 万，两头一起虚增。
A10: 收入也有类别了 | B10: 原表只有「支出业务类别」 | C10: 原来收入一侧一个类别都没有，只能按客户分析。现在收入、支出、内部转账统一用一张「收支类别」清单。【收支报表】的收入区「仍然按客户」归集，跟原来一样，没动。
A11: 期初余额挪了个地方 | B11: 原来放在【数据录入】第 5~18 行 | C11: 挪到【基础资料】账户档案的「期初余额」列。原来的写法有个坑：【汇报表】取期初用的是「期初余额行的日期 <= 查询起始日」，一旦查询起始日早于期初行的日期（比如期初记的是 6 月 1 日，你查 5 月），期初余额直接取不到，整列变成 0。
A12: 账户清单自动长 | B12: 原来写死在【汇报表】三个地方 | C12: 【汇报表】那三块的账户列（原 A8:A21 / B27:B40 / I27:I40）现在都是公式，在【基础资料】加一个账户，三块同时多一行。以前要手工改三处，漏一处就少一个账户。
A13: 收支报表加了空行 + 未列示 | B13: 原来收入区只有 13 行，且合计范围正好卡死 | C13: 原表 C4=SUM(C6:C18) 正好等于 13 个客户，加第 14 个客户「不会进合计」。现在每一块留 40 行，合计范围把整块都算进去；最后再加一行「未列示」自动补差 —— 所以合计永远等于总额，漏列谁都不会少数。
A14: 新增两张汇总表 | B14: 按你说的参照外汇资金台账 | C14: 【月度汇报表】：按月的收入 / 支出 / 净流入 / 「内部转入」 / 「内部转出」 / 月末资金总额，下半张是指定月份的各账户明细。【收支分类报表】：收支类别 × 12 个月，顶上四行是「收入合计 / 支出合计 / 内部转账净额 / 经营净额」。
A15: 新增【核对表】 | B15: 原来没有自检 | C15: 勾稽 6 项必须全是 0；待办 12 项是数据没填齐。录完看一眼这张就够了。
A17: 三、账户之间调头寸怎么录
A18: 录两行 | B18: 转出一行、转入一行 | C18: 转出账户记一笔「支出」，转入账户记一笔「收入」，两行的「收/支类别」都选「内部转账」。
A19: 写上对方 | B19: 「对方账户」列 | C19: 转出那行写转入账户名，转入那行写转出账户名。核对列会盯着你有没有写。
A20: 报表里怎么显示 | B20: 单列，不进合计 | C20: 【月度汇报表】和【汇报表】③ 各有「内部转入 / 内部转出」两列；【收支分类报表】单列一行「内部转账净额」。收入合计、支出合计里都不含它。
A21: 净额应该是 0 | B21: 不是 0 = 漏了一头 | C21: 同一笔转账两头金额相等，净额自然是 0。【核对表】第 10、11 项专门盯这个。
A23: 四、三块老界面都还在
A24: 表名 | B24: 哪一块 | C24: 说明
A25: 汇报表 ① | B25: 资金日报统计表 | C25: 改上面两个日期，最多 31 天，每天两列「收款 / 付款」。这一块是「账户口径」：内部划转也算进收款付款，因为账户余额确实动了。
A26: 汇报表 ② | B26: 货币资金日报表 | C26: 指定某一天，各账户的昨日余额 / 本日收入 / 本日支出 / 本日余额。也是账户口径。
A27: 汇报表 ③ | B27: 多帐户资金汇总表 | C27: 按月，这一块是「经营口径」：本月收入 / 本月支出不含内部划转，内部转入 / 内部转出另开两列。
A28: 收支报表 | B28: 12 个月 | C28: 收入按客户、支出按收支类别，上下两块分开列 —— 跟原来一样。
A29: 任意时间段收支报表 | B29: 任意起止日期 | C29: 左右两栏收支分列 —— 跟原来一样。
A30: 账户子表 | B30: 每个账户一张（现在 14 张） | C30: 自动从【数据录入】拆，不用填。B2 是拆分依据。
A32: 五、加东西怎么加
A33: 加一个账户 | B33: 两步 | C33: ① 【基础资料】账户档案接着写一行（记得填期初余额）；② 右键复制任意一张账户子表，改表名，把 B2 改成新账户名。【汇报表】三块会自动多出这一行。核对表第 6 项盯着你有没有漏第 ② 步。
A34: 加一个收支类别 | B34: 一步 | C34: 【基础资料】收支类别接着写，「属性一定要填」（收入 / 支出 / 内部转账）。【收支分类报表】自动多一行。
A35: 加客户 / 供应商 / 项目 | B35: 一步 | C35: 【基础资料】对应清单接着写。【收支报表】和【任意时间段收支报表】的清单是手填的，记得把新客户也补到那两张表的空行里（不补也不会少数，会落到「未列示」那一行）。
A36: 行不够了 | B36: 告诉我 | C36: 流水预留 5000 行、账户 30 个、收支类别 40 个、客户和供应商各 200 个、子表每张 600 行。核对表第 17 项显示用了多少。
A38: 六、颜色和符号
A39: 淡黄色格子 | B39: 要你填 | C39: 这是人工输入区。
A40: 灰色格子 | B40: 公式自动算 | C40: 别手动改，改了就把公式顶掉了。
A41: ※ 红字 | B41: 是错，必须改 | C41: 账户不在档案、收支同时填、金额填了负数、类别不在清单……
A42: △ 琥珀字 | B42: 待补的数据 | C42: 内部转账没写对方账户、余额成负数……不影响公式，补齐了数才准。
A44: 七、示例数据
A45: · 【数据录入】第 5 ~ 29 行是示例（原表那 23 笔 + 2 笔内部转账），正式用之前整段选中删掉即可，所有报表自动归零。
A46: · 账户、客户、供应商、支出类别全部按原表搬过来，一个不少；收入类别和内部转账类别是这次新加的。
A47: · 期初余额也按原表那 14 个账户的数搬过来了（现金 5000、微信 6000、工行 7000 …… 备用4 18000）。

Sheet 基础资料
A1: 基础资料 · 账户、收支类别、客户、供应商都在这里维护
A2: 淡黄色格子是要你填的，灰色是公式算的。账户名称必须唯一。「收支类别」比原表多一列「属性」：收入 / 支出 / 内部转账 —— 属性填「内部转账」的，不计入收入合计和支出合计，账户之间调头寸就靠它。
A3: 一、账户档案 —— 加一个账户：这里接着写一行，再复制一张账户子表改 B2 | H3: 二、收支类别（属性 = 内部转账的不计入收支合计） | K3: 三、客户 | M3: 四、供应商 | O3: 五、项目 / 部门
A4: 序号 | B4: 账户名称 ★（唯一） | C4: 账户类型 | D4: 期初余额 | E4: 启用日期 | F4: 核对 | H4: 收/支类别 ★ | I4: 属性 ★ | K4: 客户 | M4: 供应商 | O4: 项目 / 部门
A5: =IF($B5="","",COUNTA($B$5:$B5)) | B5: 现金 | C5: 现金 | D5: 5000 | E5: 46174 | F5: =IF($B5="","",IF(COUNTIF($B$5:$B$34,$B5)>1,"※账户名称重复了，后面按名字取数会串",IF($D5="","※期初余额没填（没有就填 0）",IF(AND($E5<>"",COUNTIFS(流水账户,$B5,流水日期,"<"&$E5)>0),"※有流水的日期早于启用日期，期初余额会重复计算","")))) | H5: 销售回款 | I5: 收入 | K5: 客户1 | M5: 供应商1 | O5: 主营业务
A6: =IF($B6="","",COUNTA($B$5:$B6)) | B6: 微信 | C6: 微信 | D6: 6000 | E6: 46174 | F6: =IF($B6="","",IF(COUNTIF($B$5:$B$34,$B6)>1,"※账户名称重复了，后面按名字取数会串",IF($D6="","※期初余额没填（没有就填 0）",IF(AND($E6<>"",COUNTIFS(流水账户,$B6,流水日期,"<"&$E6)>0),"※有流水的日期早于启用日期，期初余额会重复计算","")))) | H6: 其他业务收入 | I6: 收入 | K6: 客户2 | M6: 供应商2 | O6: 其他业务
A7: =IF($B7="","",COUNTA($B$5:$B7)) | B7: 工行 | C7: 银行 | D7: 7000 | E7: 46174 | F7: =IF($B7="","",IF(COUNTIF($B$5:$B$34,$B7)>1,"※账户名称重复了，后面按名字取数会串",IF($D7="","※期初余额没填（没有就填 0）",IF(AND($E7<>"",COUNTIFS(流水账户,$B7,流水日期,"<"&$E7)>0),"※有流水的日期早于启用日期，期初余额会重复计算","")))) | H7: 投资款 | I7: 收入 | K7: 客户3 | M7: 供应商3 | O7: 行政
A8: =IF($B8="","",COUNTA($B$5:$B8)) | B8: 民生 | C8: 银行 | D8: 8000 | E8: 46174 | F8: =IF($B8="","",IF(COUNTIF($B$5:$B$34,$B8)>1,"※账户名称重复了，后面按名字取数会串",IF($D8="","※期初余额没填（没有就填 0）",IF(AND($E8<>"",COUNTIFS(流水账户,$B8,流水日期,"<"&$E8)>0),"※有流水的日期早于启用日期，期初余额会重复计算","")))) | H8: 借款 | I8: 收入 | K8: 客户4 | M8: 供应商4 | O8: 融资
A9: =IF($B9="","",COUNTA($B$5:$B9)) | B9: 建行 | C9: 银行 | D9: 9000 | E9: 46174 | F9: =IF($B9="","",IF(COUNTIF($B$5:$B$34,$B9)>1,"※账户名称重复了，后面按名字取数会串",IF($D9="","※期初余额没填（没有就填 0）",IF(AND($E9<>"",COUNTIFS(流水账户,$B9,流水日期,"<"&$E9)>0),"※有流水的日期早于启用日期，期初余额会重复计算","")))) | H9: 利息收入 | I9: 收入 | K9: 客户5 | M9: 供应商5 | O9: 内部调拨
A10: =IF($B10="","",COUNTA($B$5:$B10)) | B10: 农行 | C10: 银行 | D10: 10000 | E10: 46174 | F10: =IF($B10="","",IF(COUNTIF($B$5:$B$34,$B10)>1,"※账户名称重复了，后面按名字取数会串",IF($D10="","※期初余额没填（没有就填 0）",IF(AND($E10<>"",COUNTIFS(流水账户,$B10,流水日期,"<"&$E10)>0),"※有流水的日期早于启用日期，期初余额会重复计算","")))) | H10: 退款收回 | I10: 收入 | K10: 客户6 | M10: 供应商6
A11: =IF($B11="","",COUNTA($B$5:$B11)) | B11: 中行 | C11: 银行 | D11: 11000 | E11: 46174 | F11: =IF($B11="","",IF(COUNTIF($B$5:$B$34,$B11)>1,"※账户名称重复了，后面按名字取数会串",IF($D11="","※期初余额没填（没有就填 0）",IF(AND($E11<>"",COUNTIFS(流水账户,$B11,流水日期,"<"&$E11)>0),"※有流水的日期早于启用日期，期初余额会重复计算","")))) | H11: 政府补助 | I11: 收入 | K11: 客户7 | M11: 供应商7
A12: =IF($B12="","",COUNTA($B$5:$B12)) | B12: 支付宝 | C12: 第三方 | D12: 12000 | E12: 46174 | F12: =IF($B12="","",IF(COUNTIF($B$5:$B$34,$B12)>1,"※账户名称重复了，后面按名字取数会串",IF($D12="","※期初余额没填（没有就填 0）",IF(AND($E12<>"",COUNTIFS(流水账户,$B12,流水日期,"<"&$E12)>0),"※有流水的日期早于启用日期，期初余额会重复计算","")))) | H12: 供应商 | I12: 支出 | K12: 客户8 | M12: 供应商8
A13: =IF($B13="","",COUNTA($B$5:$B13)) | B13: 农商行 | C13: 银行 | D13: 13000 | E13: 46174 | F13: =IF($B13="","",IF(COUNTIF($B$5:$B$34,$B13)>1,"※账户名称重复了，后面按名字取数会串",IF($D13="","※期初余额没填（没有就填 0）",IF(AND($E13<>"",COUNTIFS(流水账户,$B13,流水日期,"<"&$E13)>0),"※有流水的日期早于启用日期，期初余额会重复计算","")))) | H13: 办公费 | I13: 支出 | K13: 客户9 | M13: 供应商9
A14: =IF($B14="","",COUNTA($B$5:$B14)) | B14: 备用 | C14: 备用 | D14: 14000 | E14: 46174 | F14: =IF($B14="","",IF(COUNTIF($B$5:$B$34,$B14)>1,"※账户名称重复了，后面按名字取数会串",IF($D14="","※期初余额没填（没有就填 0）",IF(AND($E14<>"",COUNTIFS(流水账户,$B14,流水日期,"<"&$E14)>0),"※有流水的日期早于启用日期，期初余额会重复计算","")))) | H14: 水费 | I14: 支出 | K14: 客户10 | M14: 供应商10
A15: =IF($B15="","",COUNTA($B$5:$B15)) | B15: 备用1 | C15: 备用 | D15: 15000 | E15: 46174 | F15: =IF($B15="","",IF(COUNTIF($B$5:$B$34,$B15)>1,"※账户名称重复了，后面按名字取数会串",IF($D15="","※期初余额没填（没有就填 0）",IF(AND($E15<>"",COUNTIFS(流水账户,$B15,流水日期,"<"&$E15)>0),"※有流水的日期早于启用日期，期初余额会重复计算","")))) | H15: 电费 | I15: 支出 | K15: 客户11 | M15: 供应商11
A16: =IF($B16="","",COUNTA($B$5:$B16)) | B16: 备用2 | C16: 备用 | D16: 16000 | E16: 46174 | F16: =IF($B16="","",IF(COUNTIF($B$5:$B$34,$B16)>1,"※账户名称重复了，后面按名字取数会串",IF($D16="","※期初余额没填（没有就填 0）",IF(AND($E16<>"",COUNTIFS(流水账户,$B16,流水日期,"<"&$E16)>0),"※有流水的日期早于启用日期，期初余额会重复计算","")))) | H16: 伙食费 | I16: 支出 | K16: 客户12 | M16: 供应商12
A17: =IF($B17="","",COUNTA($B$5:$B17)) | B17: 备用3 | C17: 备用 | D17: 17000 | E17: 46174 | F17: =IF($B17="","",IF(COUNTIF($B$5:$B$34,$B17)>1,"※账户名称重复了，后面按名字取数会串",IF($D17="","※期初余额没填（没有就填 0）",IF(AND($E17<>"",COUNTIFS(流水账户,$B17,流水日期,"<"&$E17)>0),"※有流水的日期早于启用日期，期初余额会重复计算","")))) | H17: 工资 | I17: 支出 | K17: 客户13 | M17: 供应商13
A18: =IF($B18="","",COUNTA($B$5:$B18)) | B18: 备用4 | C18: 备用 | D18: 18000 | E18: 46174 | F18: =IF($B18="","",IF(COUNTIF($B$5:$B$34,$B18)>1,"※账户名称重复了，后面按名字取数会串",IF($D18="","※期初余额没填（没有就填 0）",IF(AND($E18<>"",COUNTIFS(流水账户,$B18,流水日期,"<"&$E18)>0),"※有流水的日期早于启用日期，期初余额会重复计算","")))) | H18: 租赁费 | I18: 支出
A19: =IF($B19="","",COUNTA($B$5:$B19)) | F19: =IF($B19="","",IF(COUNTIF($B$5:$B$34,$B19)>1,"※账户名称重复了，后面按名字取数会串",IF($D19="","※期初余额没填（没有就填 0）",IF(AND($E19<>"",COUNTIFS(流水账户,$B19,流水日期,"<"&$E19)>0),"※有流水的日期早于启用日期，期初余额会重复计算","")))) | H19: 差旅费 | I19: 支出
A20: =IF($B20="","",COUNTA($B$5:$B20)) | F20: =IF($B20="","",IF(COUNTIF($B$5:$B$34,$B20)>1,"※账户名称重复了，后面按名字取数会串",IF($D20="","※期初余额没填（没有就填 0）",IF(AND($E20<>"",COUNTIFS(流水账户,$B20,流水日期,"<"&$E20)>0),"※有流水的日期早于启用日期，期初余额会重复计算","")))) | H20: 业务招待费 | I20: 支出
A21: =IF($B21="","",COUNTA($B$5:$B21)) | F21: =IF($B21="","",IF(COUNTIF($B$5:$B$34,$B21)>1,"※账户名称重复了，后面按名字取数会串",IF($D21="","※期初余额没填（没有就填 0）",IF(AND($E21<>"",COUNTIFS(流水账户,$B21,流水日期,"<"&$E21)>0),"※有流水的日期早于启用日期，期初余额会重复计算","")))) | H21: 车辆费用 | I21: 支出
A22: =IF($B22="","",COUNTA($B$5:$B22)) | F22: =IF($B22="","",IF(COUNTIF($B$5:$B$34,$B22)>1,"※账户名称重复了，后面按名字取数会串",IF($D22="","※期初余额没填（没有就填 0）",IF(AND($E22<>"",COUNTIFS(流水账户,$B22,流水日期,"<"&$E22)>0),"※有流水的日期早于启用日期，期初余额会重复计算","")))) | H22: 银行手续费 | I22: 支出
A23: =IF($B23="","",COUNTA($B$5:$B23)) | F23: =IF($B23="","",IF(COUNTIF($B$5:$B$34,$B23)>1,"※账户名称重复了，后面按名字取数会串",IF($D23="","※期初余额没填（没有就填 0）",IF(AND($E23<>"",COUNTIFS(流水账户,$B23,流水日期,"<"&$E23)>0),"※有流水的日期早于启用日期，期初余额会重复计算","")))) | H23: 税费 | I23: 支出
A24: =IF($B24="","",COUNTA($B$5:$B24)) | F24: =IF($B24="","",IF(COUNTIF($B$5:$B$34,$B24)>1,"※账户名称重复了，后面按名字取数会串",IF($D24="","※期初余额没填（没有就填 0）",IF(AND($E24<>"",COUNTIFS(流水账户,$B24,流水日期,"<"&$E24)>0),"※有流水的日期早于启用日期，期初余额会重复计算","")))) | H24: 还款 | I24: 支出
A25: =IF($B25="","",COUNTA($B$5:$B25)) | F25: =IF($B25="","",IF(COUNTIF($B$5:$B$34,$B25)>1,"※账户名称重复了，后面按名字取数会串",IF($D25="","※期初余额没填（没有就填 0）",IF(AND($E25<>"",COUNTIFS(流水账户,$B25,流水日期,"<"&$E25)>0),"※有流水的日期早于启用日期，期初余额会重复计算","")))) | H25: 资产购买 | I25: 支出
A26: =IF($B26="","",COUNTA($B$5:$B26)) | F26: =IF($B26="","",IF(COUNTIF($B$5:$B$34,$B26)>1,"※账户名称重复了，后面按名字取数会串",IF($D26="","※期初余额没填（没有就填 0）",IF(AND($E26<>"",COUNTIFS(流水账户,$B26,流水日期,"<"&$E26)>0),"※有流水的日期早于启用日期，期初余额会重复计算","")))) | H26: 利息支出 | I26: 支出
A27: =IF($B27="","",COUNTA($B$5:$B27)) | F27: =IF($B27="","",IF(COUNTIF($B$5:$B$34,$B27)>1,"※账户名称重复了，后面按名字取数会串",IF($D27="","※期初余额没填（没有就填 0）",IF(AND($E27<>"",COUNTIFS(流水账户,$B27,流水日期,"<"&$E27)>0),"※有流水的日期早于启用日期，期初余额会重复计算","")))) | H27: 内部转账 | I27: 内部转账
A28: =IF($B28="","",COUNTA($B$5:$B28)) | F28: =IF($B28="","",IF(COUNTIF($B$5:$B$34,$B28)>1,"※账户名称重复了，后面按名字取数会串",IF($D28="","※期初余额没填（没有就填 0）",IF(AND($E28<>"",COUNTIFS(流水账户,$B28,流水日期,"<"&$E28)>0),"※有流水的日期早于启用日期，期初余额会重复计算","")))) | H28: 备用金调拨 | I28: 内部转账
A29: =IF($B29="","",COUNTA($B$5:$B29)) | F29: =IF($B29="","",IF(COUNTIF($B$5:$B$34,$B29)>1,"※账户名称重复了，后面按名字取数会串",IF($D29="","※期初余额没填（没有就填 0）",IF(AND($E29<>"",COUNTIFS(流水账户,$B29,流水日期,"<"&$E29)>0),"※有流水的日期早于启用日期，期初余额会重复计算",""))))
A30: =IF($B30="","",COUNTA($B$5:$B30)) | F30: =IF($B30="","",IF(COUNTIF($B$5:$B$34,$B30)>1,"※账户名称重复了，后面按名字取数会串",IF($D30="","※期初余额没填（没有就填 0）",IF(AND($E30<>"",COUNTIFS(流水账户,$B30,流水日期,"<"&$E30)>0),"※有流水的日期早于启用日期，期初余额会重复计算",""))))
A31: =IF($B31="","",COUNTA($B$5:$B31)) | F31: =IF($B31="","",IF(COUNTIF($B$5:$B$34,$B31)>1,"※账户名称重复了，后面按名字取数会串",IF($D31="","※期初余额没填（没有就填 0）",IF(AND($E31<>"",COUNTIFS(流水账户,$B31,流水日期,"<"&$E31)>0),"※有流水的日期早于启用日期，期初余额会重复计算",""))))
A32: =IF($B32="","",COUNTA($B$5:$B32)) | F32: =IF($B32="","",IF(COUNTIF($B$5:$B$34,$B32)>1,"※账户名称重复了，后面按名字取数会串",IF($D32="","※期初余额没填（没有就填 0）",IF(AND($E32<>"",COUNTIFS(流水账户,$B32,流水日期,"<"&$E32)>0),"※有流水的日期早于启用日期，期初余额会重复计算",""))))
A33: =IF($B33="","",COUNTA($B$5:$B33)) | F33: =IF($B33="","",IF(COUNTIF($B$5:$B$34,$B33)>1,"※账户名称重复了，后面按名字取数会串",IF($D33="","※期初余额没填（没有就填 0）",IF(AND($E33<>"",COUNTIFS(流水账户,$B33,流水日期,"<"&$E33)>0),"※有流水的日期早于启用日期，期初余额会重复计算",""))))
A34: =IF($B34="","",COUNTA($B$5:$B34)) | F34: =IF($B34="","",IF(COUNTIF($B$5:$B$34,$B34)>1,"※账户名称重复了，后面按名字取数会串",IF($D34="","※期初余额没填（没有就填 0）",IF(AND($E34<>"",COUNTIFS(流水账户,$B34,流水日期,"<"&$E34)>0),"※有流水的日期早于启用日期，期初余额会重复计算",""))))

Sheet 数据录入
A1: 数据录入 · 全套表只有这一张要填
A2: 选账户 → 余额自动结；收入和支出分两列，只填一个。账户之间调头寸：转出账户记一笔支出、转入账户记一笔收入，类别都选「内部转账」，在「对方账户」写上另一头 —— 这样它就不会被算进收入和支出合计。期初余额挪到【基础资料】了，这里只放真实流水。最后一列「核对」会自己挑毛病。
A3: 收入总额 | B3: =ROUND(SUMIFS(流水收入,流水属性,"<>内部转账"),2) | C3: 支出总额 | D3: =ROUND(SUMIFS(流水支出,流水属性,"<>内部转账"),2) | E3: 经营净额 | F3: =ROUND($B$3-$D$3,2) | G3: 内部转账净额 | H3: =ROUND(SUMIFS(流水收入,流水属性,"内部转账")-SUMIFS(流水支出,流水属性,"内部转账"),2) | I3: 资金总额 | J3: =ROUND(SUM(账户期初)+SUM(流水收入)-SUM(流水支出),2) | K3: 已用行数 | L3: =COUNTA($C$5:$C$5004)&" / 5000" | M3: 收入总额、支出总额都不含内部转账；内部转账净额应该是 0，不为 0 就是有一头没录
A4: 序号 | B4: 日期 ★ | C4: 公司账户 ★ | D4: 收/支类别 ★ | E4: 摘要内容 | F4: 收入 | G4: 支出 | H4: 账户余额 | I4: 客户 | J4: 供应商 | K4: 月份 | L4: 类别属性 | M4: 对方账户 (内部转账填) | N4: 项目/部门 | O4: 备注 | P4: 核对
A5: =IF($C5="","",COUNTA($C$5:$C5)) | B5: 46175 | C5: 现金 | D5: 销售回款 | F5: 2000 | H5: =IF($C5="","",ROUND(SUMIF(账户表,$C5,账户期初)+SUMIFS($F$5:F5,$C$5:C5,$C5)-SUMIFS($G$5:G5,$C$5:C5,$C5),2)) | I5: 客户1 | K5: =IF($B5="","",--TEXT($B5,"yyyymm")) | L5: =IF($D5="","",IFERROR(INDEX(类别属性,MATCH($D5,类别表,0)),"")) | N5: 主营业务 | P5: =IF($C5="","",IF(ISNA(MATCH($C5,账户表,0)),"※这个账户不在【基础资料】的账户档案里",IF($B5="","※没填日期，这一笔不会进任何月份的报表",IF(AND($F5<>"",$G5<>""),"※收入和支出不能同时填",IF(AND(N($F5)=0,N($G5)=0),"※收入和支出都没填",IF(OR(N($F5)<0,N($G5)<0),"※金额不能填负数，方向反了就换一列填",IF($D5="","※没填收支类别，分类报表会漏掉这一笔",IF(ISNA(MATCH($D5,类别表,0)),"※收支类别不在【基础资料】的清单里",IF(AND($L5="内部转账",$M5=""),"△内部转账要在「对方账户」写上另一头",IF(AND($L5="内部转账",$M5=$C5),"※对方账户跟本账户是同一个",IF(AND($L5<>"内部转账",$M5<>""),"△填了对方账户，但类别不是内部转账",IF($H5<0,"△这一笔之后该账户余额成负数了，核一下",""))))))))))))
A6: =IF($C6="","",COUNTA($C$5:$C6)) | B6: 46176 | C6: 微信 | D6: 办公费 | G6: 200 | H6: =IF($C6="","",ROUND(SUMIF(账户表,$C6,账户期初)+SUMIFS($F$5:F6,$C$5:C6,$C6)-SUMIFS($G$5:G6,$C$5:C6,$C6),2)) | K6: =IF($B6="","",--TEXT($B6,"yyyymm")) | L6: =IF($D6="","",IFERROR(INDEX(类别属性,MATCH($D6,类别表,0)),"")) | N6: 行政 | P6: =IF($C6="","",IF(ISNA(MATCH($C6,账户表,0)),"※这个账户不在【基础资料】的账户档案里",IF($B6="","※没填日期，这一笔不会进任何月份的报表",IF(AND($F6<>"",$G6<>""),"※收入和支出不能同时填",IF(AND(N($F6)=0,N($G6)=0),"※收入和支出都没填",IF(OR(N($F6)<0,N($G6)<0),"※金额不能填负数，方向反了就换一列填",IF($D6="","※没填收支类别，分类报表会漏掉这一笔",IF(ISNA(MATCH($D6,类别表,0)),"※收支类别不在【基础资料】的清单里",IF(AND($L6="内部转账",$M6=""),"△内部转账要在「对方账户」写上另一头",IF(AND($L6="内部转账",$M6=$C6),"※对方账户跟本账户是同一个",IF(AND($L6<>"内部转账",$M6<>""),"△填了对方账户，但类别不是内部转账",IF($H6<0,"△这一笔之后该账户余额成负数了，核一下",""))))))))))))
A7: =IF($C7="","",COUNTA($C$5:$C7)) | B7: 46178 | C7: 工行 | D7: 电费 | G7: 300 | H7: =IF($C7="","",ROUND(SUMIF(账户表,$C7,账户期初)+SUMIFS($F$5:F7,$C$5:C7,$C7)-SUMIFS($G$5:G7,$C$5:C7,$C7),2)) | K7: =IF($B7="","",--TEXT($B7,"yyyymm")) | L7: =IF($D7="","",IFERROR(INDEX(类别属性,MATCH($D7,类别表,0)),"")) | N7: 行政 | P7: =IF($C7="","",IF(ISNA(MATCH($C7,账户表,0)),"※这个账户不在【基础资料】的账户档案里",IF($B7="","※没填日期，这一笔不会进任何月份的报表",IF(AND($F7<>"",$G7<>""),"※收入和支出不能同时填",IF(AND(N($F7)=0,N($G7)=0),"※收入和支出都没填",IF(OR(N($F7)<0,N($G7)<0),"※金额不能填负数，方向反了就换一列填",IF($D7="","※没填收支类别，分类报表会漏掉这一笔",IF(ISNA(MATCH($D7,类别表,0)),"※收支类别不在【基础资料】的清单里",IF(AND($L7="内部转账",$M7=""),"△内部转账要在「对方账户」写上另一头",IF(AND($L7="内部转账",$M7=$C7),"※对方账户跟本账户是同一个",IF(AND($L7<>"内部转账",$M7<>""),"△填了对方账户，但类别不是内部转账",IF($H7<0,"△这一笔之后该账户余额成负数了，核一下",""))))))))))))
A8: =IF($C8="","",COUNTA($C$5:$C8)) | B8: 46179 | C8: 民生 | D8: 差旅费 | G8: 500 | H8: =IF($C8="","",ROUND(SUMIF(账户表,$C8,账户期初)+SUMIFS($F$5:F8,$C$5:C8,$C8)-SUMIFS($G$5:G8,$C$5:C8,$C8),2)) | K8: =IF($B8="","",--TEXT($B8,"yyyymm")) | L8: =IF($D8="","",IFERROR(INDEX(类别属性,MATCH($D8,类别表,0)),"")) | N8: 行政 | P8: =IF($C8="","",IF(ISNA(MATCH($C8,账户表,0)),"※这个账户不在【基础资料】的账户档案里",IF($B8="","※没填日期，这一笔不会进任何月份的报表",IF(AND($F8<>"",$G8<>""),"※收入和支出不能同时填",IF(AND(N($F8)=0,N($G8)=0),"※收入和支出都没填",IF(OR(N($F8)<0,N($G8)<0),"※金额不能填负数，方向反了就换一列填",IF($D8="","※没填收支类别，分类报表会漏掉这一笔",IF(ISNA(MATCH($D8,类别表,0)),"※收支类别不在【基础资料】的清单里",IF(AND($L8="内部转账",$M8=""),"△内部转账要在「对方账户」写上另一头",IF(AND($L8="内部转账",$M8=$C8),"※对方账户跟本账户是同一个",IF(AND($L8<>"内部转账",$M8<>""),"△填了对方账户，但类别不是内部转账",IF($H8<0,"△这一笔之后该账户余额成负数了，核一下",""))))))))))))
A9: =IF($C9="","",COUNTA($C$5:$C9)) | B9: 46183 | C9: 建行 | D9: 销售回款 | F9: 2600 | H9: =IF($C9="","",ROUND(SUMIF(账户表,$C9,账户期初)+SUMIFS($F$5:F9,$C$5:C9,$C9)-SUMIFS($G$5:G9,$C$5:C9,$C9),2)) | I9: 客户2 | K9: =IF($B9="","",--TEXT($B9,"yyyymm")) | L9: =IF($D9="","",IFERROR(INDEX(类别属性,MATCH($D9,类别表,0)),"")) | N9: 主营业务 | P9: =IF($C9="","",IF(ISNA(MATCH($C9,账户表,0)),"※这个账户不在【基础资料】的账户档案里",IF($B9="","※没填日期，这一笔不会进任何月份的报表",IF(AND($F9<>"",$G9<>""),"※收入和支出不能同时填",IF(AND(N($F9)=0,N($G9)=0),"※收入和支出都没填",IF(OR(N($F9)<0,N($G9)<0),"※金额不能填负数，方向反了就换一列填",IF($D9="","※没填收支类别，分类报表会漏掉这一笔",IF(ISNA(MATCH($D9,类别表,0)),"※收支类别不在【基础资料】的清单里",IF(AND($L9="内部转账",$M9=""),"△内部转账要在「对方账户」写上另一头",IF(AND($L9="内部转账",$M9=$C9),"※对方账户跟本账户是同一个",IF(AND($L9<>"内部转账",$M9<>""),"△填了对方账户，但类别不是内部转账",IF($H9<0,"△这一笔之后该账户余额成负数了，核一下",""))))))))))))
A10: =IF($C10="","",COUNTA($C$5:$C10)) | B10: 46185 | C10: 农行 | D10: 供应商 | G10: 5000 | H10: =IF($C10="","",ROUND(SUMIF(账户表,$C10,账户期初)+SUMIFS($F$5:F10,$C$5:C10,$C10)-SUMIFS($G$5:G10,$C$5:C10,$C10),2)) | J10: 供应商1 | K10: =IF($B10="","",--TEXT($B10,"yyyymm")) | L10: =IF($D10="","",IFERROR(INDEX(类别属性,MATCH($D10,类别表,0)),"")) | N10: 主营业务 | P10: =IF($C10="","",IF(ISNA(MATCH($C10,账户表,0)),"※这个账户不在【基础资料】的账户档案里",IF($B10="","※没填日期，这一笔不会进任何月份的报表",IF(AND($F10<>"",$G10<>""),"※收入和支出不能同时填",IF(AND(N($F10)=0,N($G10)=0),"※收入和支出都没填",IF(OR(N($F10)<0,N($G10)<0),"※金额不能填负数，方向反了就换一列填",IF($D10="","※没填收支类别，分类报表会漏掉这一笔",IF(ISNA(MATCH($D10,类别表,0)),"※收支类别不在【基础资料】的清单里",IF(AND($L10="内部转账",$M10=""),"△内部转账要在「对方账户」写上另一头",IF(AND($L10="内部转账",$M10=$C10),"※对方账户跟本账户是同一个",IF(AND($L10<>"内部转账",$M10<>""),"△填了对方账户，但类别不是内部转账",IF($H10<0,"△这一笔之后该账户余额成负数了，核一下",""))))))))))))
A11: =IF($C11="","",COUNTA($C$5:$C11)) | B11: 46193 | C11: 中行 | D11: 伙食费 | G11: 200 | H11: =IF($C11="","",ROUND(SUMIF(账户表,$C11,账户期初)+SUMIFS($F$5:F11,$C$5:C11,$C11)-SUMIFS($G$5:G11,$C$5:C11,$C11),2)) | K11: =IF($B11="","",--TEXT($B11,"yyyymm")) | L11: =IF($D11="","",IFERROR(INDEX(类别属性,MATCH($D11,类别表,0)),"")) | N11: 行政 | P11: =IF($C11="","",IF(ISNA(MATCH($C11,账户表,0)),"※这个账户不在【基础资料】的账户档案里",IF($B11="","※没填日期，这一笔不会进任何月份的报表",IF(AND($F11<>"",$G11<>""),"※收入和支出不能同时填",IF(AND(N($F11)=0,N($G11)=0),"※收入和支出都没填",IF(OR(N($F11)<0,N($G11)<0),"※金额不能填负数，方向反了就换一列填",IF($D11="","※没填收支类别，分类报表会漏掉这一笔",IF(ISNA(MATCH($D11,类别表,0)),"※收支类别不在【基础资料】的清单里",IF(AND($L11="内部转账",$M11=""),"△内部转账要在「对方账户」写上另一头",IF(AND($L11="内部转账",$M11=$C11),"※对方账户跟本账户是同一个",IF(AND($L11<>"内部转账",$M11<>""),"△填了对方账户，但类别不是内部转账",IF($H11<0,"△这一笔之后该账户余额成负数了，核一下",""))))))))))))
A12: =IF($C12="","",COUNTA($C$5:$C12)) | B12: 46196 | C12: 支付宝 | D12: 办公费 | G12: 10 | H12: =IF($C12="","",ROUND(SUMIF(账户表,$C12,账户期初)+SUMIFS($F$5:F12,$C$5:C12,$C12)-SUMIFS($G$5:G12,$C$5:C12,$C12),2)) | K12: =IF($B12="","",--TEXT($B12,"yyyymm")) | L12: =IF($D12="","",IFERROR(INDEX(类别属性,MATCH($D12,类别表,0)),"")) | N12: 行政 | P12: =IF($C12="","",IF(ISNA(MATCH($C12,账户表,0)),"※这个账户不在【基础资料】的账户档案里",IF($B12="","※没填日期，这一笔不会进任何月份的报表",IF(AND($F12<>"",$G12<>""),"※收入和支出不能同时填",IF(AND(N($F12)=0,N($G12)=0),"※收入和支出都没填",IF(OR(N($F12)<0,N($G12)<0),"※金额不能填负数，方向反了就换一列填",IF($D12="","※没填收支类别，分类报表会漏掉这一笔",IF(ISNA(MATCH($D12,类别表,0)),"※收支类别不在【基础资料】的清单里",IF(AND($L12="内部转账",$M12=""),"△内部转账要在「对方账户」写上另一头",IF(AND($L12="内部转账",$M12=$C12),"※对方账户跟本账户是同一个",IF(AND($L12<>"内部转账",$M12<>""),"△填了对方账户，但类别不是内部转账",IF($H12<0,"△这一笔之后该账户余额成负数了，核一下",""))))))))))))
A13: =IF($C13="","",COUNTA($C$5:$C13)) | B13: 46197 | C13: 农商行 | D13: 车辆费用 | G13: 50 | H13: =IF($C13="","",ROUND(SUMIF(账户表,$C13,账户期初)+SUMIFS($F$5:F13,$C$5:C13,$C13)-SUMIFS($G$5:G13,$C$5:C13,$C13),2)) | K13: =IF($B13="","",--TEXT($B13,"yyyymm")) | L13: =IF($D13="","",IFERROR(INDEX(类别属性,MATCH($D13,类别表,0)),"")) | N13: 行政 | P13: =IF($C13="","",IF(ISNA(MATCH($C13,账户表,0)),"※这个账户不在【基础资料】的账户档案里",IF($B13="","※没填日期，这一笔不会进任何月份的报表",IF(AND($F13<>"",$G13<>""),"※收入和支出不能同时填",IF(AND(N($F13)=0,N($G13)=0),"※收入和支出都没填",IF(OR(N($F13)<0,N($G13)<0),"※金额不能填负数，方向反了就换一列填",IF($D13="","※没填收支类别，分类报表会漏掉这一笔",IF(ISNA(MATCH($D13,类别表,0)),"※收支类别不在【基础资料】的清单里",IF(AND($L13="内部转账",$M13=""),"△内部转账要在「对方账户」写上另一头",IF(AND($L13="内部转账",$M13=$C13),"※对方账户跟本账户是同一个",IF(AND($L13<>"内部转账",$M13<>""),"△填了对方账户，但类别不是内部转账",IF($H13<0,"△这一笔之后该账户余额成负数了，核一下",""))))))))))))
A14: =IF($C14="","",COUNTA($C$5:$C14)) | B14: 46198 | C14: 备用 | D14: 销售回款 | F14: 2100 | H14: =IF($C14="","",ROUND(SUMIF(账户表,$C14,账户期初)+SUMIFS($F$5:F14,$C$5:C14,$C14)-SUMIFS($G$5:G14,$C$5:C14,$C14),2)) | I14: 客户3 | K14: =IF($B14="","",--TEXT($B14,"yyyymm")) | L14: =IF($D14="","",IFERROR(INDEX(类别属性,MATCH($D14,类别表,0)),"")) | N14: 主营业务 | P14: =IF($C14="","",IF(ISNA(MATCH($C14,账户表,0)),"※这个账户不在【基础资料】的账户档案里",IF($B14="","※没填日期，这一笔不会进任何月份的报表",IF(AND($F14<>"",$G14<>""),"※收入和支出不能同时填",IF(AND(N($F14)=0,N($G14)=0),"※收入和支出都没填",IF(OR(N($F14)<0,N($G14)<0),"※金额不能填负数，方向反了就换一列填",IF($D14="","※没填收支类别，分类报表会漏掉这一笔",IF(ISNA(MATCH($D14,类别表,0)),"※收支类别不在【基础资料】的清单里",IF(AND($L14="内部转账",$M14=""),"△内部转账要在「对方账户」写上另一头",IF(AND($L14="内部转账",$M14=$C14),"※对方账户跟本账户是同一个",IF(AND($L14<>"内部转账",$M14<>""),"△填了对方账户，但类别不是内部转账",IF($H14<0,"△这一笔之后该账户余额成负数了，核一下",""))))))))))))
A15: =IF($C15="","",COUNTA($C$5:$C15)) | B15: 46198 | C15: 备用1 | D15: 租赁费 | G15: 2000 | H15: =IF($C15="","",ROUND(SUMIF(账户表,$C15,账户期初)+SUMIFS($F$5:F15,$C$5:C15,$C15)-SUMIFS($G$5:G15,$C$5:C15,$C15),2)) | K15: =IF($B15="","",--TEXT($B15,"yyyymm")) | L15: =IF($D15="","",IFERROR(INDEX(类别属性,MATCH($D15,类别表,0)),"")) | N15: 行政 | P15: =IF($C15="","",IF(ISNA(MATCH($C15,账户表,0)),"※这个账户不在【基础资料】的账户档案里",IF($B15="","※没填日期，这一笔不会进任何月份的报表",IF(AND($F15<>"",$G15<>""),"※收入和支出不能同时填",IF(AND(N($F15)=0,N($G15)=0),"※收入和支出都没填",IF(OR(N($F15)<0,N($G15)<0),"※金额不能填负数，方向反了就换一列填",IF($D15="","※没填收支类别，分类报表会漏掉这一笔",IF(ISNA(MATCH($D15,类别表,0)),"※收支类别不在【基础资料】的清单里",IF(AND($L15="内部转账",$M15=""),"△内部转账要在「对方账户」写上另一头",IF(AND($L15="内部转账",$M15=$C15),"※对方账户跟本账户是同一个",IF(AND($L15<>"内部转账",$M15<>""),"△填了对方账户，但类别不是内部转账",IF($H15<0,"△这一笔之后该账户余额成负数了，核一下",""))))))))))))
A16: =IF($C16="","",COUNTA($C$5:$C16)) | B16: 46198 | C16: 现金 | D16: 业务招待费 | G16: 200 | H16: =IF($C16="","",ROUND(SUMIF(账户表,$C16,账户期初)+SUMIFS($F$5:F16,$C$5:C16,$C16)-SUMIFS($G$5:G16,$C$5:C16,$C16),2)) | K16: =IF($B16="","",--TEXT($B16,"yyyymm")) | L16: =IF($D16="","",IFERROR(INDEX(类别属性,MATCH($D16,类别表,0)),"")) | N16: 行政 | P16: =IF($C16="","",IF(ISNA(MATCH($C16,账户表,0)),"※这个账户不在【基础资料】的账户档案里",IF($B16="","※没填日期，这一笔不会进任何月份的报表",IF(AND($F16<>"",$G16<>""),"※收入和支出不能同时填",IF(AND(N($F16)=0,N($G16)=0),"※收入和支出都没填",IF(OR(N($F16)<0,N($G16)<0),"※金额不能填负数，方向反了就换一列填",IF($D16="","※没填收支类别，分类报表会漏掉这一笔",IF(ISNA(MATCH($D16,类别表,0)),"※收支类别不在【基础资料】的清单里",IF(AND($L16="内部转账",$M16=""),"△内部转账要在「对方账户」写上另一头",IF(AND($L16="内部转账",$M16=$C16),"※对方账户跟本账户是同一个",IF(AND($L16<>"内部转账",$M16<>""),"△填了对方账户，但类别不是内部转账",IF($H16<0,"△这一笔之后该账户余额成负数了，核一下",""))))))))))))
A17: =IF($C17="","",COUNTA($C$5:$C17)) | B17: 46199 | C17: 备用2 | D17: 销售回款 | F17: 3000 | H17: =IF($C17="","",ROUND(SUMIF(账户表,$C17,账户期初)+SUMIFS($F$5:F17,$C$5:C17,$C17)-SUMIFS($G$5:G17,$C$5:C17,$C17),2)) | I17: 客户4 | K17: =IF($B17="","",--TEXT($B17,"yyyymm")) | L17: =IF($D17="","",IFERROR(INDEX(类别属性,MATCH($D17,类别表,0)),"")) | N17: 主营业务 | P17: =IF($C17="","",IF(ISNA(MATCH($C17,账户表,0)),"※这个账户不在【基础资料】的账户档案里",IF($B17="","※没填日期，这一笔不会进任何月份的报表",IF(AND($F17<>"",$G17<>""),"※收入和支出不能同时填",IF(AND(N($F17)=0,N($G17)=0),"※收入和支出都没填",IF(OR(N($F17)<0,N($G17)<0),"※金额不能填负数，方向反了就换一列填",IF($D17="","※没填收支类别，分类报表会漏掉这一笔",IF(ISNA(MATCH($D17,类别表,0)),"※收支类别不在【基础资料】的清单里",IF(AND($L17="内部转账",$M17=""),"△内部转账要在「对方账户」写上另一头",IF(AND($L17="内部转账",$M17=$C17),"※对方账户跟本账户是同一个",IF(AND($L17<>"内部转账",$M17<>""),"△填了对方账户，但类别不是内部转账",IF($H17<0,"△这一笔之后该账户余额成负数了，核一下",""))))))))))))
A18: =IF($C18="","",COUNTA($C$5:$C18)) | B18: 46199 | C18: 备用3 | D18: 工资 | G18: 8000 | H18: =IF($C18="","",ROUND(SUMIF(账户表,$C18,账户期初)+SUMIFS($F$5:F18,$C$5:C18,$C18)-SUMIFS($G$5:G18,$C$5:C18,$C18),2)) | K18: =IF($B18="","",--TEXT($B18,"yyyymm")) | L18: =IF($D18="","",IFERROR(INDEX(类别属性,MATCH($D18,类别表,0)),"")) | N18: 行政 | P18: =IF($C18="","",IF(ISNA(MATCH($C18,账户表,0)),"※这个账户不在【基础资料】的账户档案里",IF($B18="","※没填日期，这一笔不会进任何月份的报表",IF(AND($F18<>"",$G18<>""),"※收入和支出不能同时填",IF(AND(N($F18)=0,N($G18)=0),"※收入和支出都没填",IF(OR(N($F18)<0,N($G18)<0),"※金额不能填负数，方向反了就换一列填",IF($D18="","※没填收支类别，分类报表会漏掉这一笔",IF(ISNA(MATCH($D18,类别表,0)),"※收支类别不在【基础资料】的清单里",IF(AND($L18="内部转账",$M18=""),"△内部转账要在「对方账户」写上另一头",IF(AND($L18="内部转账",$M18=$C18),"※对方账户跟本账户是同一个",IF(AND($L18<>"内部转账",$M18<>""),"△填了对方账户，但类别不是内部转账",IF($H18<0,"△这一笔之后该账户余额成负数了，核一下",""))))))))))))
A19: =IF($C19="","",COUNTA($C$5:$C19)) | B19: 46200 | C19: 备用4 | D19: 销售回款 | F19: 1500 | H19: =IF($C19="","",ROUND(SUMIF(账户表,$C19,账户期初)+SUMIFS($F$5:F19,$C$5:C19,$C19)-SUMIFS($G$5:G19,$C$5:C19,$C19),2)) | I19: 客户5 | K19: =IF($B19="","",--TEXT($B19,"yyyymm")) | L19: =IF($D19="","",IFERROR(INDEX(类别属性,MATCH($D19,类别表,0)),"")) | N19: 主营业务 | P19: =IF($C19="","",IF(ISNA(MATCH($C19,账户表,0)),"※这个账户不在【基础资料】的账户档案里",IF($B19="","※没填日期，这一笔不会进任何月份的报表",IF(AND($F19<>"",$G19<>""),"※收入和支出不能同时填",IF(AND(N($F19)=0,N($G19)=0),"※收入和支出都没填",IF(OR(N($F19)<0,N($G19)<0),"※金额不能填负数，方向反了就换一列填",IF($D19="","※没填收支类别，分类报表会漏掉这一笔",IF(ISNA(MATCH($D19,类别表,0)),"※收支类别不在【基础资料】的清单里",IF(AND($L19="内部转账",$M19=""),"△内部转账要在「对方账户」写上另一头",IF(AND($L19="内部转账",$M19=$C19),"※对方账户跟本账户是同一个",IF(AND($L19<>"内部转账",$M19<>""),"△填了对方账户，但类别不是内部转账",IF($H19<0,"△这一笔之后该账户余额成负数了，核一下",""))))))))))))
A20: =IF($C20="","",COUNTA($C$5:$C20)) | B20: 46201 | C20: 工行 | D20: 供应商 | G20: 3000 | H20: =IF($C20="","",ROUND(SUMIF(账户表,$C20,账户期初)+SUMIFS($F$5:F20,$C$5:C20,$C20)-SUMIFS($G$5:G20,$C$5:C20,$C20),2)) | J20: 供应商2 | K20: =IF($B20="","",--TEXT($B20,"yyyymm")) | L20: =IF($D20="","",IFERROR(INDEX(类别属性,MATCH($D20,类别表,0)),"")) | N20: 主营业务 | P20: =IF($C20="","",IF(ISNA(MATCH($C20,账户表,0)),"※这个账户不在【基础资料】的账户档案里",IF($B20="","※没填日期，这一笔不会进任何月份的报表",IF(AND($F20<>"",$G20<>""),"※收入和支出不能同时填",IF(AND(N($F20)=0,N($G20)=0),"※收入和支出都没填",IF(OR(N($F20)<0,N($G20)<0),"※金额不能填负数，方向反了就换一列填",IF($D20="","※没填收支类别，分类报表会漏掉这一笔",IF(ISNA(MATCH($D20,类别表,0)),"※收支类别不在【基础资料】的清单里",IF(AND($L20="内部转账",$M20=""),"△内部转账要在「对方账户」写上另一头",IF(AND($L20="内部转账",$M20=$C20),"※对方账户跟本账户是同一个",IF(AND($L20<>"内部转账",$M20<>""),"△填了对方账户，但类别不是内部转账",IF($H20<0,"△这一笔之后该账户余额成负数了，核一下",""))))))))))))
A21: =IF($C21="","",COUNTA($C$5:$C21)) | B21: 46201 | C21: 微信 | D21: 销售回款 | F21: 800 | H21: =IF($C21="","",ROUND(SUMIF(账户表,$C21,账户期初)+SUMIFS($F$5:F21,$C$5:C21,$C21)-SUMIFS($G$5:G21,$C$5:C21,$C21),2)) | I21: 客户6 | K21: =IF($B21="","",--TEXT($B21,"yyyymm")) | L21: =IF($D21="","",IFERROR(INDEX(类别属性,MATCH($D21,类别表,0)),"")) | N21: 主营业务 | P21: =IF($C21="","",IF(ISNA(MATCH($C21,账户表,0)),"※这个账户不在【基础资料】的账户档案里",IF($B21="","※没填日期，这一笔不会进任何月份的报表",IF(AND($F21<>"",$G21<>""),"※收入和支出不能同时填",IF(AND(N($F21)=0,N($G21)=0),"※收入和支出都没填",IF(OR(N($F21)<0,N($G21)<0),"※金额不能填负数，方向反了就换一列填",IF($D21="","※没填收支类别，分类报表会漏掉这一笔",IF(ISNA(MATCH($D21,类别表,0)),"※收支类别不在【基础资料】的清单里",IF(AND($L21="内部转账",$M21=""),"△内部转账要在「对方账户」写上另一头",IF(AND($L21="内部转账",$M21=$C21),"※对方账户跟本账户是同一个",IF(AND($L21<>"内部转账",$M21<>""),"△填了对方账户，但类别不是内部转账",IF($H21<0,"△这一笔之后该账户余额成负数了，核一下",""))))))))))))
A22: =IF($C22="","",COUNTA($C$5:$C22)) | B22: 46202 | C22: 民生 | D22: 水费 | G22: 120 | H22: =IF($C22="","",ROUND(SUMIF(账户表,$C22,账户期初)+SUMIFS($F$5:F22,$C$5:C22,$C22)-SUMIFS($G$5:G22,$C$5:C22,$C22),2)) | K22: =IF($B22="","",--TEXT($B22,"yyyymm")) | L22: =IF($D22="","",IFERROR(INDEX(类别属性,MATCH($D22,类别表,0)),"")) | N22: 行政 | P22: =IF($C22="","",IF(ISNA(MATCH($C22,账户表,0)),"※这个账户不在【基础资料】的账户档案里",IF($B22="","※没填日期，这一笔不会进任何月份的报表",IF(AND($F22<>"",$G22<>""),"※收入和支出不能同时填",IF(AND(N($F22)=0,N($G22)=0),"※收入和支出都没填",IF(OR(N($F22)<0,N($G22)<0),"※金额不能填负数，方向反了就换一列填",IF($D22="","※没填收支类别，分类报表会漏掉这一笔",IF(ISNA(MATCH($D22,类别表,0)),"※收支类别不在【基础资料】的清单里",IF(AND($L22="内部转账",$M22=""),"△内部转账要在「对方账户」写上另一头",IF(AND($L22="内部转账",$M22=$C22),"※对方账户跟本账户是同一个",IF(AND($L22<>"内部转账",$M22<>""),"△填了对方账户，但类别不是内部转账",IF($H22<0,"△这一笔之后该账户余额成负数了，核一下",""))))))))))))
A23: =IF($C23="","",COUNTA($C$5:$C23)) | B23: 46202 | C23: 建行 | D23: 银行手续费 | G23: 30 | H23: =IF($C23="","",ROUND(SUMIF(账户表,$C23,账户期初)+SUMIFS($F$5:F23,$C$5:C23,$C23)-SUMIFS($G$5:G23,$C$5:C23,$C23),2)) | K23: =IF($B23="","",--TEXT($B23,"yyyymm")) | L23: =IF($D23="","",IFERROR(INDEX(类别属性,MATCH($D23,类别表,0)),"")) | N23: 行政 | P23: =IF($C23="","",IF(ISNA(MATCH($C23,账户表,0)),"※这个账户不在【基础资料】的账户档案里",IF($B23="","※没填日期，这一笔不会进任何月份的报表",IF(AND($F23<>"",$G23<>""),"※收入和支出不能同时填",IF(AND(N($F23)=0,N($G23)=0),"※收入和支出都没填",IF(OR(N($F23)<0,N($G23)<0),"※金额不能填负数，方向反了就换一列填",IF($D23="","※没填收支类别，分类报表会漏掉这一笔",IF(ISNA(MATCH($D23,类别表,0)),"※收支类别不在【基础资料】的清单里",IF(AND($L23="内部转账",$M23=""),"△内部转账要在「对方账户」写上另一头",IF(AND($L23="内部转账",$M23=$C23),"※对方账户跟本账户是同一个",IF(AND($L23<>"内部转账",$M23<>""),"△填了对方账户，但类别不是内部转账",IF($H23<0,"△这一笔之后该账户余额成负数了，核一下",""))))))))))))
A24: =IF($C24="","",COUNTA($C$5:$C24)) | B24: 46203 | C24: 农行 | D24: 销售回款 | F24: 4200 | H24: =IF($C24="","",ROUND(SUMIF(账户表,$C24,账户期初)+SUMIFS($F$5:F24,$C$5:C24,$C24)-SUMIFS($G$5:G24,$C$5:C24,$C24),2)) | I24: 客户7 | K24: =IF($B24="","",--TEXT($B24,"yyyymm")) | L24: =IF($D24="","",IFERROR(INDEX(类别属性,MATCH($D24,类别表,0)),"")) | N24: 主营业务 | P24: =IF($C24="","",IF(ISNA(MATCH($C24,账户表,0)),"※这个账户不在【基础资料】的账户档案里",IF($B24="","※没填日期，这一笔不会进任何月份的报表",IF(AND($F24<>"",$G24<>""),"※收入和支出不能同时填",IF(AND(N($F24)=0,N($G24)=0),"※收入和支出都没填",IF(OR(N($F24)<0,N($G24)<0),"※金额不能填负数，方向反了就换一列填",IF($D24="","※没填收支类别，分类报表会漏掉这一笔",IF(ISNA(MATCH($D24,类别表,0)),"※收支类别不在【基础资料】的清单里",IF(AND($L24="内部转账",$M24=""),"△内部转账要在「对方账户」写上另一头",IF(AND($L24="内部转账",$M24=$C24),"※对方账户跟本账户是同一个",IF(AND($L24<>"内部转账",$M24<>""),"△填了对方账户，但类别不是内部转账",IF($H24<0,"△这一笔之后该账户余额成负数了，核一下",""))))))))))))
A25: =IF($C25="","",COUNTA($C$5:$C25)) | B25: 46203 | C25: 中行 | D25: 供应商 | G25: 2500 | H25: =IF($C25="","",ROUND(SUMIF(账户表,$C25,账户期初)+SUMIFS($F$5:F25,$C$5:C25,$C25)-SUMIFS($G$5:G25,$C$5:C25,$C25),2)) | J25: 供应商3 | K25: =IF($B25="","",--TEXT($B25,"yyyymm")) | L25: =IF($D25="","",IFERROR(INDEX(类别属性,MATCH($D25,类别表,0)),"")) | N25: 主营业务 | P25: =IF($C25="","",IF(ISNA(MATCH($C25,账户表,0)),"※这个账户不在【基础资料】的账户档案里",IF($B25="","※没填日期，这一笔不会进任何月份的报表",IF(AND($F25<>"",$G25<>""),"※收入和支出不能同时填",IF(AND(N($F25)=0,N($G25)=0),"※收入和支出都没填",IF(OR(N($F25)<0,N($G25)<0),"※金额不能填负数，方向反了就换一列填",IF($D25="","※没填收支类别，分类报表会漏掉这一笔",IF(ISNA(MATCH($D25,类别表,0)),"※收支类别不在【基础资料】的清单里",IF(AND($L25="内部转账",$M25=""),"△内部转账要在「对方账户」写上另一头",IF(AND($L25="内部转账",$M25=$C25),"※对方账户跟本账户是同一个",IF(AND($L25<>"内部转账",$M25<>""),"△填了对方账户，但类别不是内部转账",IF($H25<0,"△这一笔之后该账户余额成负数了，核一下",""))))))))))))
A26: =IF($C26="","",COUNTA($C$5:$C26)) | B26: 46203 | C26: 支付宝 | D26: 销售回款 | F26: 600 | H26: =IF($C26="","",ROUND(SUMIF(账户表,$C26,账户期初)+SUMIFS($F$5:F26,$C$5:C26,$C26)-SUMIFS($G$5:G26,$C$5:C26,$C26),2)) | I26: 客户8 | K26: =IF($B26="","",--TEXT($B26,"yyyymm")) | L26: =IF($D26="","",IFERROR(INDEX(类别属性,MATCH($D26,类别表,0)),"")) | N26: 主营业务 | P26: =IF($C26="","",IF(ISNA(MATCH($C26,账户表,0)),"※这个账户不在【基础资料】的账户档案里",IF($B26="","※没填日期，这一笔不会进任何月份的报表",IF(AND($F26<>"",$G26<>""),"※收入和支出不能同时填",IF(AND(N($F26)=0,N($G26)=0),"※收入和支出都没填",IF(OR(N($F26)<0,N($G26)<0),"※金额不能填负数，方向反了就换一列填",IF($D26="","※没填收支类别，分类报表会漏掉这一笔",IF(ISNA(MATCH($D26,类别表,0)),"※收支类别不在【基础资料】的清单里",IF(AND($L26="内部转账",$M26=""),"△内部转账要在「对方账户」写上另一头",IF(AND($L26="内部转账",$M26=$C26),"※对方账户跟本账户是同一个",IF(AND($L26<>"内部转账",$M26<>""),"△填了对方账户，但类别不是内部转账",IF($H26<0,"△这一笔之后该账户余额成负数了，核一下",""))))))))))))
A27: =IF($C27="","",COUNTA($C$5:$C27)) | B27: 46203 | C27: 农商行 | D27: 办公费 | G27: 80 | H27: =IF($C27="","",ROUND(SUMIF(账户表,$C27,账户期初)+SUMIFS($F$5:F27,$C$5:C27,$C27)-SUMIFS($G$5:G27,$C$5:C27,$C27),2)) | K27: =IF($B27="","",--TEXT($B27,"yyyymm")) | L27: =IF($D27="","",IFERROR(INDEX(类别属性,MATCH($D27,类别表,0)),"")) | N27: 行政 | P27: =IF($C27="","",IF(ISNA(MATCH($C27,账户表,0)),"※这个账户不在【基础资料】的账户档案里",IF($B27="","※没填日期，这一笔不会进任何月份的报表",IF(AND($F27<>"",$G27<>""),"※收入和支出不能同时填",IF(AND(N($F27)=0,N($G27)=0),"※收入和支出都没填",IF(OR(N($F27)<0,N($G27)<0),"※金额不能填负数，方向反了就换一列填",IF($D27="","※没填收支类别，分类报表会漏掉这一笔",IF(ISNA(MATCH($D27,类别表,0)),"※收支类别不在【基础资料】的清单里",IF(AND($L27="内部转账",$M27=""),"△内部转账要在「对方账户」写上另一头",IF(AND($L27="内部转账",$M27=$C27),"※对方账户跟本账户是同一个",IF(AND($L27<>"内部转账",$M27<>""),"△填了对方账户，但类别不是内部转账",IF($H27<0,"△这一笔之后该账户余额成负数了，核一下",""))))))))))))
A28: =IF($C28="","",COUNTA($C$5:$C28)) | B28: 46203 | C28: 工行 | D28: 内部转账 | E28: 工行转现金备用 | G28: 2000 | H28: =IF($C28="","",ROUND(SUMIF(账户表,$C28,账户期初)+SUMIFS($F$5:F28,$C$5:C28,$C28)-SUMIFS($G$5:G28,$C$5:C28,$C28),2)) | K28: =IF($B28="","",--TEXT($B28,"yyyymm")) | L28: =IF($D28="","",IFERROR(INDEX(类别属性,MATCH($D28,类别表,0)),"")) | M28: 现金 | N28: 内部调拨 | P28: =IF($C28="","",IF(ISNA(MATCH($C28,账户表,0)),"※这个账户不在【基础资料】的账户档案里",IF($B28="","※没填日期，这一笔不会进任何月份的报表",IF(AND($F28<>"",$G28<>""),"※收入和支出不能同时填",IF(AND(N($F28)=0,N($G28)=0),"※收入和支出都没填",IF(OR(N($F28)<0,N($G28)<0),"※金额不能填负数，方向反了就换一列填",IF($D28="","※没填收支类别，分类报表会漏掉这一笔",IF(ISNA(MATCH($D28,类别表,0)),"※收支类别不在【基础资料】的清单里",IF(AND($L28="内部转账",$M28=""),"△内部转账要在「对方账户」写上另一头",IF(AND($L28="内部转账",$M28=$C28),"※对方账户跟本账户是同一个",IF(AND($L28<>"内部转账",$M28<>""),"△填了对方账户，但类别不是内部转账",IF($H28<0,"△这一笔之后该账户余额成负数了，核一下",""))))))))))))
A29: =IF($C29="","",COUNTA($C$5:$C29)) | B29: 46203 | C29: 现金 | D29: 内部转账 | E29: 收到工行转入 | F29: 2000 | H29: =IF($C29="","",ROUND(SUMIF(账户表,$C29,账户期初)+SUMIFS($F$5:F29,$C$5:C29,$C29)-SUMIFS($G$5:G29,$C$5:C29,$C29),2)) | K29: =IF($B29="","",--TEXT($B29,"yyyymm")) | L29: =IF($D29="","",IFERROR(INDEX(类别属性,MATCH($D29,类别表,0)),"")) | M29: 工行 | N29: 内部调拨 | P29: =IF($C29="","",IF(ISNA(MATCH($C29,账户表,0)),"※这个账户不在【基础资料】的账户档案里",IF($B29="","※没填日期，这一笔不会进任何月份的报表",IF(AND($F29<>"",$G29<>""),"※收入和支出不能同时填",IF(AND(N($F29)=0,N($G29)=0),"※收入和支出都没填",IF(OR(N($F29)<0,N($G29)<0),"※金额不能填负数，方向反了就换一列填",IF($D29="","※没填收支类别，分类报表会漏掉这一笔",IF(ISNA(MATCH($D29,类别表,0)),"※收支类别不在【基础资料】的清单里",IF(AND($L29="内部转账",$M29=""),"△内部转账要在「对方账户」写上另一头",IF(AND($L29="内部转账",$M29=$C29),"※对方账户跟本账户是同一个",IF(AND($L29<>"内部转账",$M29<>""),"△填了对方账户，但类别不是内部转账",IF($H29<0,"△这一笔之后该账户余额成负数了，核一下",""))))))))))))
A30: =IF($C30="","",COUNTA($C$5:$C30)) | H30: =IF($C30="","",ROUND(SUMIF(账户表,$C30,账户期初)+SUMIFS($F$5:F30,$C$5:C30,$C30)-SUMIFS($G$5:G30,$C$5:C30,$C30),2)) | K30: =IF($B30="","",--TEXT($B30,"yyyymm")) | L30: =IF($D30="","",IFERROR(INDEX(类别属性,MATCH($D30,类别表,0)),"")) | P30: =IF($C30="","",IF(ISNA(MATCH($C30,账户表,0)),"※这个账户不在【基础资料】的账户档案里",IF($B30="","※没填日期，这一笔不会进任何月份的报表",IF(AND($F30<>"",$G30<>""),"※收入和支出不能同时填",IF(AND(N($F30)=0,N($G30)=0),"※收入和支出都没填",IF(OR(N($F30)<0,N($G30)<0),"※金额不能填负数，方向反了就换一列填",IF($D30="","※没填收支类别，分类报表会漏掉这一笔",IF(ISNA(MATCH($D30,类别表,0)),"※收支类别不在【基础资料】的清单里",IF(AND($L30="内部转账",$M30=""),"△内部转账要在「对方账户」写上另一头",IF(AND($L30="内部转账",$M30=$C30),"※对方账户跟本账户是同一个",IF(AND($L30<>"内部转账",$M30<>""),"△填了对方账户，但类别不是内部转账",IF($H30<0,"△这一笔之后该账户余额成负数了，核一下",""))))))))))))
A31: =IF($C31="","",COUNTA($C$5:$C31)) | H31: =IF($C31="","",ROUND(SUMIF(账户表,$C31,账户期初)+SUMIFS($F$5:F31,$C$5:C31,$C31)-SUMIFS($G$5:G31,$C$5:C31,$C31),2)) | K31: =IF($B31="","",--TEXT($B31,"yyyymm")) | L31: =IF($D31="","",IFERROR(INDEX(类别属性,MATCH($D31,类别表,0)),"")) | P31: =IF($C31="","",IF(ISNA(MATCH($C31,账户表,0)),"※这个账户不在【基础资料】的账户档案里",IF($B31="","※没填日期，这一笔不会进任何月份的报表",IF(AND($F31<>"",$G31<>""),"※收入和支出不能同时填",IF(AND(N($F31)=0,N($G31)=0),"※收入和支出都没填",IF(OR(N($F31)<0,N($G31)<0),"※金额不能填负数，方向反了就换一列填",IF($D31="","※没填收支类别，分类报表会漏掉这一笔",IF(ISNA(MATCH($D31,类别表,0)),"※收支类别不在【基础资料】的清单里",IF(AND($L31="内部转账",$M31=""),"△内部转账要在「对方账户」写上另一头",IF(AND($L31="内部转账",$M31=$C31),"※对方账户跟本账户是同一个",IF(AND($L31<>"内部转账",$M31<>""),"△填了对方账户，但类别不是内部转账",IF($H31<0,"△这一笔之后该账户余额成负数了，核一下",""))))))))))))
A32: =IF($C32="","",COUNTA($C$5:$C32)) | H32: =IF($C32="","",ROUND(SUMIF(账户表,$C32,账户期初)+SUMIFS($F$5:F32,$C$5:C32,$C32)-SUMIFS($G$5:G32,$C$5:C32,$C32),2)) | K32: =IF($B32="","",--TEXT($B32,"yyyymm")) | L32: =IF($D32="","",IFERROR(INDEX(类别属性,MATCH($D32,类别表,0)),"")) | P32: =IF($C32="","",IF(ISNA(MATCH($C32,账户表,0)),"※这个账户不在【基础资料】的账户档案里",IF($B32="","※没填日期，这一笔不会进任何月份的报表",IF(AND($F32<>"",$G32<>""),"※收入和支出不能同时填",IF(AND(N($F32)=0,N($G32)=0),"※收入和支出都没填",IF(OR(N($F32)<0,N($G32)<0),"※金额不能填负数，方向反了就换一列填",IF($D32="","※没填收支类别，分类报表会漏掉这一笔",IF(ISNA(MATCH($D32,类别表,0)),"※收支类别不在【基础资料】的清单里",IF(AND($L32="内部转账",$M32=""),"△内部转账要在「对方账户」写上另一头",IF(AND($L32="内部转账",$M32=$C32),"※对方账户跟本账户是同一个",IF(AND($L32<>"内部转账",$M32<>""),"△填了对方账户，但类别不是内部转账",IF($H32<0,"△这一笔之后该账户余额成负数了，核一下",""))))))))))))
A33: =IF($C33="","",COUNTA($C$5:$C33)) | H33: =IF($C33="","",ROUND(SUMIF(账户表,$C33,账户期初)+SUMIFS($F$5:F33,$C$5:C33,$C33)-SUMIFS($G$5:G33,$C$5:C33,$C33),2)) | K33: =IF($B33="","",--TEXT($B33,"yyyymm")) | L33: =IF($D33="","",IFERROR(INDEX(类别属性,MATCH($D33,类别表,0)),"")) | P33: =IF($C33="","",IF(ISNA(MATCH($C33,账户表,0)),"※这个账户不在【基础资料】的账户档案里",IF($B33="","※没填日期，这一笔不会进任何月份的报表",IF(AND($F33<>"",$G33<>""),"※收入和支出不能同时填",IF(AND(N($F33)=0,N($G33)=0),"※收入和支出都没填",IF(OR(N($F33)<0,N($G33)<0),"※金额不能填负数，方向反了就换一列填",IF($D33="","※没填收支类别，分类报表会漏掉这一笔",IF(ISNA(MATCH($D33,类别表,0)),"※收支类别不在【基础资料】的清单里",IF(AND($L33="内部转账",$M33=""),"△内部转账要在「对方账户」写上另一头",IF(AND($L33="内部转账",$M33=$C33),"※对方账户跟本账户是同一个",IF(AND($L33<>"内部转账",$M33<>""),"△填了对方账户，但类别不是内部转账",IF($H33<0,"△这一笔之后该账户余额成负数了，核一下",""))))))))))))
A34: =IF($C34="","",COUNTA($C$5:$C34)) | H34: =IF($C34="","",ROUND(SUMIF(账户表,$C34,账户期初)+SUMIFS($F$5:F34,$C$5:C34,$C34)-SUMIFS($G$5:G34,$C$5:C34,$C34),2)) | K34: =IF($B34="","",--TEXT($B34,"yyyymm")) | L34: =IF($D34="","",IFERROR(INDEX(类别属性,MATCH($D34,类别表,0)),"")) | P34: =IF($C34="","",IF(ISNA(MATCH($C34,账户表,0)),"※这个账户不在【基础资料】的账户档案里",IF($B34="","※没填日期，这一笔不会进任何月份的报表",IF(AND($F34<>"",$G34<>""),"※收入和支出不能同时填",IF(AND(N($F34)=0,N($G34)=0),"※收入和支出都没填",IF(OR(N($F34)<0,N($G34)<0),"※金额不能填负数，方向反了就换一列填",IF($D34="","※没填收支类别，分类报表会漏掉这一笔",IF(ISNA(MATCH($D34,类别表,0)),"※收支类别不在【基础资料】的清单里",IF(AND($L34="内部转账",$M34=""),"△内部转账要在「对方账户」写上另一头",IF(AND($L34="内部转账",$M34=$C34),"※对方账户跟本账户是同一个",IF(AND($L34<>"内部转账",$M34<>""),"△填了对方账户，但类别不是内部转账",IF($H34<0,"△这一笔之后该账户余额成负数了，核一下",""))))))))))))
A35: =IF($C35="","",COUNTA($C$5:$C35)) | H35: =IF($C35="","",ROUND(SUMIF(账户表,$C35,账户期初)+SUMIFS($F$5:F35,$C$5:C35,$C35)-SUMIFS($G$5:G35,$C$5:C35,$C35),2)) | K35: =IF($B35="","",--TEXT($B35,"yyyymm")) | L35: =IF($D35="","",IFERROR(INDEX(类别属性,MATCH($D35,类别表,0)),"")) | P35: =IF($C35="","",IF(ISNA(MATCH($C35,账户表,0)),"※这个账户不在【基础资料】的账户档案里",IF($B35="","※没填日期，这一笔不会进任何月份的报表",IF(AND($F35<>"",$G35<>""),"※收入和支出不能同时填",IF(AND(N($F35)=0,N($G35)=0),"※收入和支出都没填",IF(OR(N($F35)<0,N($G35)<0),"※金额不能填负数，方向反了就换一列填",IF($D35="","※没填收支类别，分类报表会漏掉这一笔",IF(ISNA(MATCH($D35,类别表,0)),"※收支类别不在【基础资料】的清单里",IF(AND($L35="内部转账",$M35=""),"△内部转账要在「对方账户」写上另一头",IF(AND($L35="内部转账",$M35=$C35),"※对方账户跟本账户是同一个",IF(AND($L35<>"内部转账",$M35<>""),"△填了对方账户，但类别不是内部转账",IF($H35<0,"△这一笔之后该账户余额成负数了，核一下",""))))))))))))
A36: =IF($C36="","",COUNTA($C$5:$C36)) | H36: =IF($C36="","",ROUND(SUMIF(账户表,$C36,账户期初)+SUMIFS($F$5:F36,$C$5:C36,$C36)-SUMIFS($G$5:G36,$C$5:C36,$C36),2)) | K36: =IF($B36="","",--TEXT($B36,"yyyymm")) | L36: =IF($D36="","",IFERROR(INDEX(类别属性,MATCH($D36,类别表,0)),"")) | P36: =IF($C36="","",IF(ISNA(MATCH($C36,账户表,0)),"※这个账户不在【基础资料】的账户档案里",IF($B36="","※没填日期，这一笔不会进任何月份的报表",IF(AND($F36<>"",$G36<>""),"※收入和支出不能同时填",IF(AND(N($F36)=0,N($G36)=0),"※收入和支出都没填",IF(OR(N($F36)<0,N($G36)<0),"※金额不能填负数，方向反了就换一列填",IF($D36="","※没填收支类别，分类报表会漏掉这一笔",IF(ISNA(MATCH($D36,类别表,0)),"※收支类别不在【基础资料】的清单里",IF(AND($L36="内部转账",$M36=""),"△内部转账要在「对方账户」写上另一头",IF(AND($L36="内部转账",$M36=$C36),"※对方账户跟本账户是同一个",IF(AND($L36<>"内部转账",$M36<>""),"△填了对方账户，但类别不是内部转账",IF($H36<0,"△这一笔之后该账户余额成负数了，核一下",""))))))))))))
A37: =IF($C37="","",COUNTA($C$5:$C37)) | H37: =IF($C37="","",ROUND(SUMIF(账户表,$C37,账户期初)+SUMIFS($F$5:F37,$C$5:C37,$C37)-SUMIFS($G$5:G37,$C$5:C37,$C37),2)) | K37: =IF($B37="","",--TEXT($B37,"yyyymm")) | L37: =IF($D37="","",IFERROR(INDEX(类别属性,MATCH($D37,类别表,0)),"")) | P37: =IF($C37="","",IF(ISNA(MATCH($C37,账户表,0)),"※这个账户不在【基础资料】的账户档案里",IF($B37="","※没填日期，这一笔不会进任何月份的报表",IF(AND($F37<>"",$G37<>""),"※收入和支出不能同时填",IF(AND(N($F37)=0,N($G37)=0),"※收入和支出都没填",IF(OR(N($F37)<0,N($G37)<0),"※金额不能填负数，方向反了就换一列填",IF($D37="","※没填收支类别，分类报表会漏掉这一笔",IF(ISNA(MATCH($D37,类别表,0)),"※收支类别不在【基础资料】的清单里",IF(AND($L37="内部转账",$M37=""),"△内部转账要在「对方账户」写上另一头",IF(AND($L37="内部转账",$M37=$C37),"※对方账户跟本账户是同一个",IF(AND($L37<>"内部转账",$M37<>""),"△填了对方账户，但类别不是内部转账",IF($H37<0,"△这一笔之后该账户余额成负数了，核一下",""))))))))))))
A38: =IF($C38="","",COUNTA($C$5:$C38)) | H38: =IF($C38="","",ROUND(SUMIF(账户表,$C38,账户期初)+SUMIFS($F$5:F38,$C$5:C38,$C38)-SUMIFS($G$5:G38,$C$5:C38,$C38),2)) | K38: =IF($B38="","",--TEXT($B38,"yyyymm")) | L38: =IF($D38="","",IFERROR(INDEX(类别属性,MATCH($D38,类别表,0)),"")) | P38: =IF($C38="","",IF(ISNA(MATCH($C38,账户表,0)),"※这个账户不在【基础资料】的账户档案里",IF($B38="","※没填日期，这一笔不会进任何月份的报表",IF(AND($F38<>"",$G38<>""),"※收入和支出不能同时填",IF(AND(N($F38)=0,N($G38)=0),"※收入和支出都没填",IF(OR(N($F38)<0,N($G38)<0),"※金额不能填负数，方向反了就换一列填",IF($D38="","※没填收支类别，分类报表会漏掉这一笔",IF(ISNA(MATCH($D38,类别表,0)),"※收支类别不在【基础资料】的清单里",IF(AND($L38="内部转账",$M38=""),"△内部转账要在「对方账户」写上另一头",IF(AND($L38="内部转账",$M38=$C38),"※对方账户跟本账户是同一个",IF(AND($L38<>"内部转账",$M38<>""),"△填了对方账户，但类别不是内部转账",IF($H38<0,"△这一笔之后该账户余额成负数了，核一下",""))))))))))))
A39: =IF($C39="","",COUNTA($C$5:$C39)) | H39: =IF($C39="","",ROUND(SUMIF(账户表,$C39,账户期初)+SUMIFS($F$5:F39,$C$5:C39,$C39)-SUMIFS($G$5:G39,$C$5:C39,$C39),2)) | K39: =IF($B39="","",--TEXT($B39,"yyyymm")) | L39: =IF($D39="","",IFERROR(INDEX(类别属性,MATCH($D39,类别表,0)),"")) | P39: =IF($C39="","",IF(ISNA(MATCH($C39,账户表,0)),"※这个账户不在【基础资料】的账户档案里",IF($B39="","※没填日期，这一笔不会进任何月份的报表",IF(AND($F39<>"",$G39<>""),"※收入和支出不能同时填",IF(AND(N($F39)=0,N($G39)=0),"※收入和支出都没填",IF(OR(N($F39)<0,N($G39)<0),"※金额不能填负数，方向反了就换一列填",IF($D39="","※没填收支类别，分类报表会漏掉这一笔",IF(ISNA(MATCH($D39,类别表,0)),"※收支类别不在【基础资料】的清单里",IF(AND($L39="内部转账",$M39=""),"△内部转账要在「对方账户」写上另一头",IF(AND($L39="内部转账",$M39=$C39),"※对方账户跟本账户是同一个",IF(AND($L39<>"内部转账",$M39<>""),"△填了对方账户，但类别不是内部转账",IF($H39<0,"△这一笔之后该账户余额成负数了，核一下",""))))))))))))
A40: =IF($C40="","",COUNTA($C$5:$C40)) | H40: =IF($C40="","",ROUND(SUMIF(账户表,$C40,账户期初)+SUMIFS($F$5:F40,$C$5:C40,$C40)-SUMIFS($G$5:G40,$C$5:C40,$C40),2)) | K40: =IF($B40="","",--TEXT($B40,"yyyymm")) | L40: =IF($D40="","",IFERROR(INDEX(类别属性,MATCH($D40,类别表,0)),"")) | P40: =IF($C40="","",IF(ISNA(MATCH($C40,账户表,0)),"※这个账户不在【基础资料】的账户档案里",IF($B40="","※没填日期，这一笔不会进任何月份的报表",IF(AND($F40<>"",$G40<>""),"※收入和支出不能同时填",IF(AND(N($F40)=0,N($G40)=0),"※收入和支出都没填",IF(OR(N($F40)<0,N($G40)<0),"※金额不能填负数，方向反了就换一列填",IF($D40="","※没填收支类别，分类报表会漏掉这一笔",IF(ISNA(MATCH($D40,类别表,0)),"※收支类别不在【基础资料】的清单里",IF(AND($L40="内部转账",$M40=""),"△内部转账要在「对方账户」写上另一头",IF(AND($L40="内部转账",$M40=$C40),"※对方账户跟本账户是同一个",IF(AND($L40<>"内部转账",$M40<>""),"△填了对方账户，但类别不是内部转账",IF($H40<0,"△这一笔之后该账户余额成负数了，核一下",""))))))))))))
A41: =IF($C41="","",COUNTA($C$5:$C41)) | H41: =IF($C41="","",ROUND(SUMIF(账户表,$C41,账户期初)+SUMIFS($F$5:F41,$C$5:C41,$C41)-SUMIFS($G$5:G41,$C$5:C41,$C41),2)) | K41: =IF($B41="","",--TEXT($B41,"yyyymm")) | L41: =IF($D41="","",IFERROR(INDEX(类别属性,MATCH($D41,类别表,0)),"")) | P41: =IF($C41="","",IF(ISNA(MATCH($C41,账户表,0)),"※这个账户不在【基础资料】的账户档案里",IF($B41="","※没填日期，这一笔不会进任何月份的报表",IF(AND($F41<>"",$G41<>""),"※收入和支出不能同时填",IF(AND(N($F41)=0,N($G41)=0),"※收入和支出都没填",IF(OR(N($F41)<0,N($G41)<0),"※金额不能填负数，方向反了就换一列填",IF($D41="","※没填收支类别，分类报表会漏掉这一笔",IF(ISNA(MATCH($D41,类别表,0)),"※收支类别不在【基础资料】的清单里",IF(AND($L41="内部转账",$M41=""),"△内部转账要在「对方账户」写上另一头",IF(AND($L41="内部转账",$M41=$C41),"※对方账户跟本账户是同一个",IF(AND($L41<>"内部转账",$M41<>""),"△填了对方账户，但类别不是内部转账",IF($H41<0,"△这一笔之后该账户余额成负数了，核一下",""))))))))))))
... A5004: =IF($C5004="","",COUNTA($C$5:$C5004)) | H5004: =IF($C5004="","",ROUND(SUMIF(账户表,$C5004,账户期初)+SUMIFS($F$5:F5004,$C$5:C5004,$C5004)-SUMIFS($G$5:G5004,$C$5:C5004,$C5004),2)) | K5004: =IF($B5004="","",--TEXT($B5004,"yyyymm")) | L5004: =IF($D5004="","",IFERROR(INDEX(类别属性,MATCH($D5004,类别表,0)),"")) | P5004: =IF($C5004="","",IF(ISNA(MATCH($C5004,账户表,0)),"※这个账户不在【基础资料】的账户档案里",IF($B5004="","※没填日期，这一笔不会进任何月份的报表",IF(AND($F5004<>"",$G5004<>""),"※收入和支出不能同时填",IF(AND(N($F5004)=0,N($G5004)=0),"※收入和支出都没填",IF(OR(N($F5004)<0,N($G5004)<0),"※金额不能填负数，方向反了就换一列填",IF($D5004="","※没填收支类别，分类报表会漏掉这一笔",IF(ISNA(MATCH($D5004,类别表,0)),"※收支类别不在【基础资料】的清单里",IF(AND($L5004="内部转账",$M5004=""),"△内部转账要在「对方账户」写上另一头",IF(AND($L5004="内部转账",$M5004=$C5004),"※对方账户跟本账户是同一个",IF(AND($L5004<>"内部转账",$M5004<>""),"△填了对方账户，但类别不是内部转账",IF($H5004<0,"△这一笔之后该账户余额成负数了，核一下",""))))))))))))

Sheet 汇报表
A1: 汇报表 · 三块老界面原样保留（账户清单改成自动长，加账户不用再改三处）
A2: ① 资金日报统计表：改上面两个日期就行，最多 31 天。这一块是「账户口径」 ——收款/付款按钱进出账户算，内部划转也算在里面（因为账户余额确实动了）。② 货币资金日报表：指定某一天。③ 多帐户资金汇总表：按月，这一块是「经营口径」，内部转入/转出单独两列，不混进本月收入和本月支出。
A3: 起始日期 | B3: 46174 | D3: 截止日期 | E3: 46203 | G3: 查询天数 | H3: =IF(OR($B$3="",$E$3=""),"",IF($E$3<$B$3,"※截止早于起始",IF($E$3-$B$3+1>31,"※超过 31 天，请分段查",$E$3-$B$3+1)))
A4: 公司期初余额 | C4: 期间收款合计 | E4: 期间付款合计 | G4: 期末结余金额
B5: =ROUND(SUM(B8:B37),2) | D5: =ROUND(SUM(BM8:BM37),2) | F5: =ROUND(SUM(BN8:BN37),2) | H5: =ROUND(SUM(BO8:BO37),2)
A6: ① 资金日报统计表（账户口径，含内部划转） | C6: =IF(NOT(ISNUMBER($H$3)),"",IF(1<=MIN($H$3,31),$B$3+0,"")) | D6: =IF(NOT(ISNUMBER($H$3)),"",IF(1<=MIN($H$3,31),$B$3+0,"")) | E6: =IF(NOT(ISNUMBER($H$3)),"",IF(2<=MIN($H$3,31),$B$3+1,"")) | F6: =IF(NOT(ISNUMBER($H$3)),"",IF(2<=MIN($H$3,31),$B$3+1,"")) | G6: =IF(NOT(ISNUMBER($H$3)),"",IF(3<=MIN($H$3,31),$B$3+2,"")) | H6: =IF(NOT(ISNUMBER($H$3)),"",IF(3<=MIN($H$3,31),$B$3+2,"")) | I6: =IF(NOT(ISNUMBER($H$3)),"",IF(4<=MIN($H$3,31),$B$3+3,"")) | J6: =IF(NOT(ISNUMBER($H$3)),"",IF(4<=MIN($H$3,31),$B$3+3,"")) | K6: =IF(NOT(ISNUMBER($H$3)),"",IF(5<=MIN($H$3,31),$B$3+4,"")) | L6: =IF(NOT(ISNUMBER($H$3)),"",IF(5<=MIN($H$3,31),$B$3+4,"")) | M6: =IF(NOT(ISNUMBER($H$3)),"",IF(6<=MIN($H$3,31),$B$3+5,"")) | N6: =IF(NOT(ISNUMBER($H$3)),"",IF(6<=MIN($H$3,31),$B$3+5,"")) | O6: =IF(NOT(ISNUMBER($H$3)),"",IF(7<=MIN($H$3,31),$B$3+6,"")) | P6: =IF(NOT(ISNUMBER($H$3)),"",IF(7<=MIN($H$3,31),$B$3+6,"")) | Q6: =IF(NOT(ISNUMBER($H$3)),"",IF(8<=MIN($H$3,31),$B$3+7,"")) | R6: =IF(NOT(ISNUMBER($H$3)),"",IF(8<=MIN($H$3,31),$B$3+7,"")) | S6: =IF(NOT(ISNUMBER($H$3)),"",IF(9<=MIN($H$3,31),$B$3+8,"")) | T6: =IF(NOT(ISNUMBER($H$3)),"",IF(9<=MIN($H$3,31),$B$3+8,"")) | U6: =IF(NOT(ISNUMBER($H$3)),"",IF(10<=MIN($H$3,31),$B$3+9,"")) | V6: =IF(NOT(ISNUMBER($H$3)),"",IF(10<=MIN($H$3,31),$B$3+9,"")) | W6: =IF(NOT(ISNUMBER($H$3)),"",IF(11<=MIN($H$3,31),$B$3+10,"")) | X6: =IF(NOT(ISNUMBER($H$3)),"",IF(11<=MIN($H$3,31),$B$3+10,"")) | Y6: =IF(NOT(ISNUMBER($H$3)),"",IF(12<=MIN($H$3,31),$B$3+11,"")) | Z6: =IF(NOT(ISNUMBER($H$3)),"",IF(12<=MIN($H$3,31),$B$3+11,"")) | AA6: =IF(NOT(ISNUMBER($H$3)),"",IF(13<=MIN($H$3,31),$B$3+12,"")) | AB6: =IF(NOT(ISNUMBER($H$3)),"",IF(13<=MIN($H$3,31),$B$3+12,"")) | AC6: =IF(NOT(ISNUMBER($H$3)),"",IF(14<=MIN($H$3,31),$B$3+13,"")) | AD6: =IF(NOT(ISNUMBER($H$3)),"",IF(14<=MIN($H$3,31),$B$3+13,"")) | AE6: =IF(NOT(ISNUMBER($H$3)),"",IF(15<=MIN($H$3,31),$B$3+14,"")) | AF6: =IF(NOT(ISNUMBER($H$3)),"",IF(15<=MIN($H$3,31),$B$3+14,"")) | AG6: =IF(NOT(ISNUMBER($H$3)),"",IF(16<=MIN($H$3,31),$B$3+15,"")) | AH6: =IF(NOT(ISNUMBER($H$3)),"",IF(16<=MIN($H$3,31),$B$3+15,"")) | AI6: =IF(NOT(ISNUMBER($H$3)),"",IF(17<=MIN($H$3,31),$B$3+16,"")) | AJ6: =IF(NOT(ISNUMBER($H$3)),"",IF(17<=MIN($H$3,31),$B$3+16,"")) | AK6: =IF(NOT(ISNUMBER($H$3)),"",IF(18<=MIN($H$3,31),$B$3+17,"")) | AL6: =IF(NOT(ISNUMBER($H$3)),"",IF(18<=MIN($H$3,31),$B$3+17,"")) | AM6: =IF(NOT(ISNUMBER($H$3)),"",IF(19<=MIN($H$3,31),$B$3+18,"")) | AN6: =IF(NOT(ISNUMBER($H$3)),"",IF(19<=MIN($H$3,31),$B$3+18,"")) | AO6: =IF(NOT(ISNUMBER($H$3)),"",IF(20<=MIN($H$3,31),$B$3+19,"")) | AP6: =IF(NOT(ISNUMBER($H$3)),"",IF(20<=MIN($H$3,31),$B$3+19,"")) | AQ6: =IF(NOT(ISNUMBER($H$3)),"",IF(21<=MIN($H$3,31),$B$3+20,"")) | AR6: =IF(NOT(ISNUMBER($H$3)),"",IF(21<=MIN($H$3,31),$B$3+20,"")) | AS6: =IF(NOT(ISNUMBER($H$3)),"",IF(22<=MIN($H$3,31),$B$3+21,"")) | AT6: =IF(NOT(ISNUMBER($H$3)),"",IF(22<=MIN($H$3,31),$B$3+21,"")) | AU6: =IF(NOT(ISNUMBER($H$3)),"",IF(23<=MIN($H$3,31),$B$3+22,"")) | AV6: =IF(NOT(ISNUMBER($H$3)),"",IF(23<=MIN($H$3,31),$B$3+22,"")) | AW6: =IF(NOT(ISNUMBER($H$3)),"",IF(24<=MIN($H$3,31),$B$3+23,"")) | AX6: =IF(NOT(ISNUMBER($H$3)),"",IF(24<=MIN($H$3,31),$B$3+23,"")) | AY6: =IF(NOT(ISNUMBER($H$3)),"",IF(25<=MIN($H$3,31),$B$3+24,"")) | AZ6: =IF(NOT(ISNUMBER($H$3)),"",IF(25<=MIN($H$3,31),$B$3+24,"")) | BA6: =IF(NOT(ISNUMBER($H$3)),"",IF(26<=MIN($H$3,31),$B$3+25,"")) | BB6: =IF(NOT(ISNUMBER($H$3)),"",IF(26<=MIN($H$3,31),$B$3+25,"")) | BC6: =IF(NOT(ISNUMBER($H$3)),"",IF(27<=MIN($H$3,31),$B$3+26,"")) | BD6: =IF(NOT(ISNUMBER($H$3)),"",IF(27<=MIN($H$3,31),$B$3+26,"")) | BE6: =IF(NOT(ISNUMBER($H$3)),"",IF(28<=MIN($H$3,31),$B$3+27,"")) | BF6: =IF(NOT(ISNUMBER($H$3)),"",IF(28<=MIN($H$3,31),$B$3+27,"")) | BG6: =IF(NOT(ISNUMBER($H$3)),"",IF(29<=MIN($H$3,31),$B$3+28,"")) | BH6: =IF(NOT(ISNUMBER($H$3)),"",IF(29<=MIN($H$3,31),$B$3+28,"")) | BI6: =IF(NOT(ISNUMBER($H$3)),"",IF(30<=MIN($H$3,31),$B$3+29,"")) | BJ6: =IF(NOT(ISNUMBER($H$3)),"",IF(30<=MIN($H$3,31),$B$3+29,"")) | BK6: =IF(NOT(ISNUMBER($H$3)),"",IF(31<=MIN($H$3,31),$B$3+30,"")) | BL6: =IF(NOT(ISNUMBER($H$3)),"",IF(31<=MIN($H$3,31),$B$3+30,""))
A7: 账户 | B7: 期初余额 | C7: =IF(C$6="","","收款") | D7: =IF(D$6="","","付款") | E7: =IF(E$6="","","收款") | F7: =IF(F$6="","","付款") | G7: =IF(G$6="","","收款") | H7: =IF(H$6="","","付款") | I7: =IF(I$6="","","收款") | J7: =IF(J$6="","","付款") | K7: =IF(K$6="","","收款") | L7: =IF(L$6="","","付款") | M7: =IF(M$6="","","收款") | N7: =IF(N$6="","","付款") | O7: =IF(O$6="","","收款") | P7: =IF(P$6="","","付款") | Q7: =IF(Q$6="","","收款") | R7: =IF(R$6="","","付款") | S7: =IF(S$6="","","收款") | T7: =IF(T$6="","","付款") | U7: =IF(U$6="","","收款") | V7: =IF(V$6="","","付款") | W7: =IF(W$6="","","收款") | X7: =IF(X$6="","","付款") | Y7: =IF(Y$6="","","收款") | Z7: =IF(Z$6="","","付款") | AA7: =IF(AA$6="","","收款") | AB7: =IF(AB$6="","","付款") | AC7: =IF(AC$6="","","收款") | AD7: =IF(AD$6="","","付款") | AE7: =IF(AE$6="","","收款") | AF7: =IF(AF$6="","","付款") | AG7: =IF(AG$6="","","收款") | AH7: =IF(AH$6="","","付款") | AI7: =IF(AI$6="","","收款") | AJ7: =IF(AJ$6="","","付款") | AK7: =IF(AK$6="","","收款") | AL7: =IF(AL$6="","","付款") | AM7: =IF(AM$6="","","收款") | AN7: =IF(AN$6="","","付款") | AO7: =IF(AO$6="","","收款") | AP7: =IF(AP$6="","","付款") | AQ7: =IF(AQ$6="","","收款") | AR7: =IF(AR$6="","","付款") | AS7: =IF(AS$6="","","收款") | AT7: =IF(AT$6="","","付款") | AU7: =IF(AU$6="","","收款") | AV7: =IF(AV$6="","","付款") | AW7: =IF(AW$6="","","收款") | AX7: =IF(AX$6="","","付款") | AY7: =IF(AY$6="","","收款") | AZ7: =IF(AZ$6="","","付款") | BA7: =IF(BA$6="","","收款") | BB7: =IF(BB$6="","","付款") | BC7: =IF(BC$6="","","收款") | BD7: =IF(BD$6="","","付款") | BE7: =IF(BE$6="","","收款") | BF7: =IF(BF$6="","","付款") | BG7: =IF(BG$6="","","收款") | BH7: =IF(BH$6="","","付款") | BI7: =IF(BI$6="","","收款") | BJ7: =IF(BJ$6="","","付款") | BK7: =IF(BK$6="","","收款") | BL7: =IF(BL$6="","","付款") | BM7: 期间收款 | BN7: 期间付款 | BO7: 期末余额
A8: =IF(基础资料!$B$5="","",基础资料!$B$5) | B8: =IF(OR($A8="",NOT(ISNUMBER($H$3))),"",ROUND(SUMIF(账户表,$A8,账户期初)+SUMIFS(流水收入,流水账户,$A8,流水日期,"<"&$B$3)-SUMIFS(流水支出,流水账户,$A8,流水日期,"<"&$B$3),2)) | C8: =IF(OR($A8="",C$6=""),"",ROUND(SUMIFS(流水收入,流水账户,$A8,流水日期,C$6),2)) | D8: =IF(OR($A8="",D$6=""),"",ROUND(SUMIFS(流水支出,流水账户,$A8,流水日期,D$6),2)) | E8: =IF(OR($A8="",E$6=""),"",ROUND(SUMIFS(流水收入,流水账户,$A8,流水日期,E$6),2)) | F8: =IF(OR($A8="",F$6=""),"",ROUND(SUMIFS(流水支出,流水账户,$A8,流水日期,F$6),2)) | G8: =IF(OR($A8="",G$6=""),"",ROUND(SUMIFS(流水收入,流水账户,$A8,流水日期,G$6),2)) | H8: =IF(OR($A8="",H$6=""),"",ROUND(SUMIFS(流水支出,流水账户,$A8,流水日期,H$6),2)) | I8: =IF(OR($A8="",I$6=""),"",ROUND(SUMIFS(流水收入,流水账户,$A8,流水日期,I$6),2)) | J8: =IF(OR($A8="",J$6=""),"",ROUND(SUMIFS(流水支出,流水账户,$A8,流水日期,J$6),2)) | K8: =IF(OR($A8="",K$6=""),"",ROUND(SUMIFS(流水收入,流水账户,$A8,流水日期,K$6),2)) | L8: =IF(OR($A8="",L$6=""),"",ROUND(SUMIFS(流水支出,流水账户,$A8,流水日期,L$6),2)) | M8: =IF(OR($A8="",M$6=""),"",ROUND(SUMIFS(流水收入,流水账户,$A8,流水日期,M$6),2)) | N8: =IF(OR($A8="",N$6=""),"",ROUND(SUMIFS(流水支出,流水账户,$A8,流水日期,N$6),2)) | O8: =IF(OR($A8="",O$6=""),"",ROUND(SUMIFS(流水收入,流水账户,$A8,流水日期,O$6),2)) | P8: =IF(OR($A8="",P$6=""),"",ROUND(SUMIFS(流水支出,流水账户,$A8,流水日期,P$6),2)) | Q8: =IF(OR($A8="",Q$6=""),"",ROUND(SUMIFS(流水收入,流水账户,$A8,流水日期,Q$6),2)) | R8: =IF(OR($A8="",R$6=""),"",ROUND(SUMIFS(流水支出,流水账户,$A8,流水日期,R$6),2)) | S8: =IF(OR($A8="",S$6=""),"",ROUND(SUMIFS(流水收入,流水账户,$A8,流水日期,S$6),2)) | T8: =IF(OR($A8="",T$6=""),"",ROUND(SUMIFS(流水支出,流水账户,$A8,流水日期,T$6),2)) | U8: =IF(OR($A8="",U$6=""),"",ROUND(SUMIFS(流水收入,流水账户,$A8,流水日期,U$6),2)) | V8: =IF(OR($A8="",V$6=""),"",ROUND(SUMIFS(流水支出,流水账户,$A8,流水日期,V$6),2)) | W8: =IF(OR($A8="",W$6=""),"",ROUND(SUMIFS(流水收入,流水账户,$A8,流水日期,W$6),2)) | X8: =IF(OR($A8="",X$6=""),"",ROUND(SUMIFS(流水支出,流水账户,$A8,流水日期,X$6),2)) | Y8: =IF(OR($A8="",Y$6=""),"",ROUND(SUMIFS(流水收入,流水账户,$A8,流水日期,Y$6),2)) | Z8: =IF(OR($A8="",Z$6=""),"",ROUND(SUMIFS(流水支出,流水账户,$A8,流水日期,Z$6),2)) | AA8: =IF(OR($A8="",AA$6=""),"",ROUND(SUMIFS(流水收入,流水账户,$A8,流水日期,AA$6),2)) | AB8: =IF(OR($A8="",AB$6=""),"",ROUND(SUMIFS(流水支出,流水账户,$A8,流水日期,AB$6),2)) | AC8: =IF(OR($A8="",AC$6=""),"",ROUND(SUMIFS(流水收入,流水账户,$A8,流水日期,AC$6),2)) | AD8: =IF(OR($A8="",AD$6=""),"",ROUND(SUMIFS(流水支出,流水账户,$A8,流水日期,AD$6),2)) | AE8: =IF(OR($A8="",AE$6=""),"",ROUND(SUMIFS(流水收入,流水账户,$A8,流水日期,AE$6),2)) | AF8: =IF(OR($A8="",AF$6=""),"",ROUND(SUMIFS(流水支出,流水账户,$A8,流水日期,AF$6),2)) | AG8: =IF(OR($A8="",AG$6=""),"",ROUND(SUMIFS(流水收入,流水账户,$A8,流水日期,AG$6),2)) | AH8: =IF(OR($A8="",AH$6=""),"",ROUND(SUMIFS(流水支出,流水账户,$A8,流水日期,AH$6),2)) | AI8: =IF(OR($A8="",AI$6=""),"",ROUND(SUMIFS(流水收入,流水账户,$A8,流水日期,AI$6),2)) | AJ8: =IF(OR($A8="",AJ$6=""),"",ROUND(SUMIFS(流水支出,流水账户,$A8,流水日期,AJ$6),2)) | AK8: =IF(OR($A8="",AK$6=""),"",ROUND(SUMIFS(流水收入,流水账户,$A8,流水日期,AK$6),2)) | AL8: =IF(OR($A8="",AL$6=""),"",ROUND(SUMIFS(流水支出,流水账户,$A8,流水日期,AL$6),2)) | AM8: =IF(OR($A8="",AM$6=""),"",ROUND(SUMIFS(流水收入,流水账户,$A8,流水日期,AM$6),2)) | AN8: =IF(OR($A8="",AN$6=""),"",ROUND(SUMIFS(流水支出,流水账户,$A8,流水日期,AN$6),2)) | AO8: =IF(OR($A8="",AO$6=""),"",ROUND(SUMIFS(流水收入,流水账户,$A8,流水日期,AO$6),2)) | AP8: =IF(OR($A8="",AP$6=""),"",ROUND(SUMIFS(流水支出,流水账户,$A8,流水日期,AP$6),2)) | AQ8: =IF(OR($A8="",AQ$6=""),"",ROUND(SUMIFS(流水收入,流水账户,$A8,流水日期,AQ$6),2)) | AR8: =IF(OR($A8="",AR$6=""),"",ROUND(SUMIFS(流水支出,流水账户,$A8,流水日期,AR$6),2)) | AS8: =IF(OR($A8="",AS$6=""),"",ROUND(SUMIFS(流水收入,流水账户,$A8,流水日期,AS$6),2)) | AT8: =IF(OR($A8="",AT$6=""),"",ROUND(SUMIFS(流水支出,流水账户,$A8,流水日期,AT$6),2)) | AU8: =IF(OR($A8="",AU$6=""),"",ROUND(SUMIFS(流水收入,流水账户,$A8,流水日期,AU$6),2)) | AV8: =IF(OR($A8="",AV$6=""),"",ROUND(SUMIFS(流水支出,流水账户,$A8,流水日期,AV$6),2)) | AW8: =IF(OR($A8="",AW$6=""),"",ROUND(SUMIFS(流水收入,流水账户,$A8,流水日期,AW$6),2)) | AX8: =IF(OR($A8="",AX$6=""),"",ROUND(SUMIFS(流水支出,流水账户,$A8,流水日期,AX$6),2)) | AY8: =IF(OR($A8="",AY$6=""),"",ROUND(SUMIFS(流水收入,流水账户,$A8,流水日期,AY$6),2)) | AZ8: =IF(OR($A8="",AZ$6=""),"",ROUND(SUMIFS(流水支出,流水账户,$A8,流水日期,AZ$6),2)) | BA8: =IF(OR($A8="",BA$6=""),"",ROUND(SUMIFS(流水收入,流水账户,$A8,流水日期,BA$6),2)) | BB8: =IF(OR($A8="",BB$6=""),"",ROUND(SUMIFS(流水支出,流水账户,$A8,流水日期,BB$6),2)) | BC8: =IF(OR($A8="",BC$6=""),"",ROUND(SUMIFS(流水收入,流水账户,$A8,流水日期,BC$6),2)) | BD8: =IF(OR($A8="",BD$6=""),"",ROUND(SUMIFS(流水支出,流水账户,$A8,流水日期,BD$6),2)) | BE8: =IF(OR($A8="",BE$6=""),"",ROUND(SUMIFS(流水收入,流水账户,$A8,流水日期,BE$6),2)) | BF8: =IF(OR($A8="",BF$6=""),"",ROUND(SUMIFS(流水支出,流水账户,$A8,流水日期,BF$6),2)) | BG8: =IF(OR($A8="",BG$6=""),"",ROUND(SUMIFS(流水收入,流水账户,$A8,流水日期,BG$6),2)) | BH8: =IF(OR($A8="",BH$6=""),"",ROUND(SUMIFS(流水支出,流水账户,$A8,流水日期,BH$6),2)) | BI8: =IF(OR($A8="",BI$6=""),"",ROUND(SUMIFS(流水收入,流水账户,$A8,流水日期,BI$6),2)) | BJ8: =IF(OR($A8="",BJ$6=""),"",ROUND(SUMIFS(流水支出,流水账户,$A8,流水日期,BJ$6),2)) | BK8: =IF(OR($A8="",BK$6=""),"",ROUND(SUMIFS(流水收入,流水账户,$A8,流水日期,BK$6),2)) | BL8: =IF(OR($A8="",BL$6=""),"",ROUND(SUMIFS(流水支出,流水账户,$A8,流水日期,BL$6),2)) | BM8: =IF($A8="","",ROUND(SUMIF($C$7:$BL$7,"收款",C8:BL8),2)) | BN8: =IF($A8="","",ROUND(SUMIF($C$7:$BL$7,"付款",C8:BL8),2)) | BO8: =IF($A8="","",ROUND(N($B8)+N(BM8)-N(BN8),2))
A9: =IF(基础资料!$B$6="","",基础资料!$B$6) | B9: =IF(OR($A9="",NOT(ISNUMBER($H$3))),"",ROUND(SUMIF(账户表,$A9,账户期初)+SUMIFS(流水收入,流水账户,$A9,流水日期,"<"&$B$3)-SUMIFS(流水支出,流水账户,$A9,流水日期,"<"&$B$3),2)) | C9: =IF(OR($A9="",C$6=""),"",ROUND(SUMIFS(流水收入,流水账户,$A9,流水日期,C$6),2)) | D9: =IF(OR($A9="",D$6=""),"",ROUND(SUMIFS(流水支出,流水账户,$A9,流水日期,D$6),2)) | E9: =IF(OR($A9="",E$6=""),"",ROUND(SUMIFS(流水收入,流水账户,$A9,流水日期,E$6),2)) | F9: =IF(OR($A9="",F$6=""),"",ROUND(SUMIFS(流水支出,流水账户,$A9,流水日期,F$6),2)) | G9: =IF(OR($A9="",G$6=""),"",ROUND(SUMIFS(流水收入,流水账户,$A9,流水日期,G$6),2)) | H9: =IF(OR($A9="",H$6=""),"",ROUND(SUMIFS(流水支出,流水账户,$A9,流水日期,H$6),2)) | I9: =IF(OR($A9="",I$6=""),"",ROUND(SUMIFS(流水收入,流水账户,$A9,流水日期,I$6),2)) | J9: =IF(OR($A9="",J$6=""),"",ROUND(SUMIFS(流水支出,流水账户,$A9,流水日期,J$6),2)) | K9: =IF(OR($A9="",K$6=""),"",ROUND(SUMIFS(流水收入,流水账户,$A9,流水日期,K$6),2)) | L9: =IF(OR($A9="",L$6=""),"",ROUND(SUMIFS(流水支出,流水账户,$A9,流水日期,L$6),2)) | M9: =IF(OR($A9="",M$6=""),"",ROUND(SUMIFS(流水收入,流水账户,$A9,流水日期,M$6),2)) | N9: =IF(OR($A9="",N$6=""),"",ROUND(SUMIFS(流水支出,流水账户,$A9,流水日期,N$6),2)) | O9: =IF(OR($A9="",O$6=""),"",ROUND(SUMIFS(流水收入,流水账户,$A9,流水日期,O$6),2)) | P9: =IF(OR($A9="",P$6=""),"",ROUND(SUMIFS(流水支出,流水账户,$A9,流水日期,P$6),2)) | Q9: =IF(OR($A9="",Q$6=""),"",ROUND(SUMIFS(流水收入,流水账户,$A9,流水日期,Q$6),2)) | R9: =IF(OR($A9="",R$6=""),"",ROUND(SUMIFS(流水支出,流水账户,$A9,流水日期,R$6),2)) | S9: =IF(OR($A9="",S$6=""),"",ROUND(SUMIFS(流水收入,流水账户,$A9,流水日期,S$6),2)) | T9: =IF(OR($A9="",T$6=""),"",ROUND(SUMIFS(流水支出,流水账户,$A9,流水日期,T$6),2)) | U9: =IF(OR($A9="",U$6=""),"",ROUND(SUMIFS(流水收入,流水账户,$A9,流水日期,U$6),2)) | V9: =IF(OR($A9="",V$6=""),"",ROUND(SUMIFS(流水支出,流水账户,$A9,流水日期,V$6),2)) | W9: =IF(OR($A9="",W$6=""),"",ROUND(SUMIFS(流水收入,流水账户,$A9,流水日期,W$6),2)) | X9: =IF(OR($A9="",X$6=""),"",ROUND(SUMIFS(流水支出,流水账户,$A9,流水日期,X$6),2)) | Y9: =IF(OR($A9="",Y$6=""),"",ROUND(SUMIFS(流水收入,流水账户,$A9,流水日期,Y$6),2)) | Z9: =IF(OR($A9="",Z$6=""),"",ROUND(SUMIFS(流水支出,流水账户,$A9,流水日期,Z$6),2)) | AA9: =IF(OR($A9="",AA$6=""),"",ROUND(SUMIFS(流水收入,流水账户,$A9,流水日期,AA$6),2)) | AB9: =IF(OR($A9="",AB$6=""),"",ROUND(SUMIFS(流水支出,流水账户,$A9,流水日期,AB$6),2)) | AC9: =IF(OR($A9="",AC$6=""),"",ROUND(SUMIFS(流水收入,流水账户,$A9,流水日期,AC$6),2)) | AD9: =IF(OR($A9="",AD$6=""),"",ROUND(SUMIFS(流水支出,流水账户,$A9,流水日期,AD$6),2)) | AE9: =IF(OR($A9="",AE$6=""),"",ROUND(SUMIFS(流水收入,流水账户,$A9,流水日期,AE$6),2)) | AF9: =IF(OR($A9="",AF$6=""),"",ROUND(SUMIFS(流水支出,流水账户,$A9,流水日期,AF$6),2)) | AG9: =IF(OR($A9="",AG$6=""),"",ROUND(SUMIFS(流水收入,流水账户,$A9,流水日期,AG$6),2)) | AH9: =IF(OR($A9="",AH$6=""),"",ROUND(SUMIFS(流水支出,流水账户,$A9,流水日期,AH$6),2)) | AI9: =IF(OR($A9="",AI$6=""),"",ROUND(SUMIFS(流水收入,流水账户,$A9,流水日期,AI$6),2)) | AJ9: =IF(OR($A9="",AJ$6=""),"",ROUND(SUMIFS(流水支出,流水账户,$A9,流水日期,AJ$6),2)) | AK9: =IF(OR($A9="",AK$6=""),"",ROUND(SUMIFS(流水收入,流水账户,$A9,流水日期,AK$6),2)) | AL9: =IF(OR($A9="",AL$6=""),"",ROUND(SUMIFS(流水支出,流水账户,$A9,流水日期,AL$6),2)) | AM9: =IF(OR($A9="",AM$6=""),"",ROUND(SUMIFS(流水收入,流水账户,$A9,流水日期,AM$6),2)) | AN9: =IF(OR($A9="",AN$6=""),"",ROUND(SUMIFS(流水支出,流水账户,$A9,流水日期,AN$6),2)) | AO9: =IF(OR($A9="",AO$6=""),"",ROUND(SUMIFS(流水收入,流水账户,$A9,流水日期,AO$6),2)) | AP9: =IF(OR($A9="",AP$6=""),"",ROUND(SUMIFS(流水支出,流水账户,$A9,流水日期,AP$6),2)) | AQ9: =IF(OR($A9="",AQ$6=""),"",ROUND(SUMIFS(流水收入,流水账户,$A9,流水日期,AQ$6),2)) | AR9: =IF(OR($A9="",AR$6=""),"",ROUND(SUMIFS(流水支出,流水账户,$A9,流水日期,AR$6),2)) | AS9: =IF(OR($A9="",AS$6=""),"",ROUND(SUMIFS(流水收入,流水账户,$A9,流水日期,AS$6),2)) | AT9: =IF(OR($A9="",AT$6=""),"",ROUND(SUMIFS(流水支出,流水账户,$A9,流水日期,AT$6),2)) | AU9: =IF(OR($A9="",AU$6=""),"",ROUND(SUMIFS(流水收入,流水账户,$A9,流水日期,AU$6),2)) | AV9: =IF(OR($A9="",AV$6=""),"",ROUND(SUMIFS(流水支出,流水账户,$A9,流水日期,AV$6),2)) | AW9: =IF(OR($A9="",AW$6=""),"",ROUND(SUMIFS(流水收入,流水账户,$A9,流水日期,AW$6),2)) | AX9: =IF(OR($A9="",AX$6=""),"",ROUND(SUMIFS(流水支出,流水账户,$A9,流水日期,AX$6),2)) | AY9: =IF(OR($A9="",AY$6=""),"",ROUND(SUMIFS(流水收入,流水账户,$A9,流水日期,AY$6),2)) | AZ9: =IF(OR($A9="",AZ$6=""),"",ROUND(SUMIFS(流水支出,流水账户,$A9,流水日期,AZ$6),2)) | BA9: =IF(OR($A9="",BA$6=""),"",ROUND(SUMIFS(流水收入,流水账户,$A9,流水日期,BA$6),2)) | BB9: =IF(OR($A9="",BB$6=""),"",ROUND(SUMIFS(流水支出,流水账户,$A9,流水日期,BB$6),2)) | BC9: =IF(OR($A9="",BC$6=""),"",ROUND(SUMIFS(流水收入,流水账户,$A9,流水日期,BC$6),2)) | BD9: =IF(OR($A9="",BD$6=""),"",ROUND(SUMIFS(流水支出,流水账户,$A9,流水日期,BD$6),2)) | BE9: =IF(OR($A9="",BE$6=""),"",ROUND(SUMIFS(流水收入,流水账户,$A9,流水日期,BE$6),2)) | BF9: =IF(OR($A9="",BF$6=""),"",ROUND(SUMIFS(流水支出,流水账户,$A9,流水日期,BF$6),2)) | BG9: =IF(OR($A9="",BG$6=""),"",ROUND(SUMIFS(流水收入,流水账户,$A9,流水日期,BG$6),2)) | BH9: =IF(OR($A9="",BH$6=""),"",ROUND(SUMIFS(流水支出,流水账户,$A9,流水日期,BH$6),2)) | BI9: =IF(OR($A9="",BI$6=""),"",ROUND(SUMIFS(流水收入,流水账户,$A9,流水日期,BI$6),2)) | BJ9: =IF(OR($A9="",BJ$6=""),"",ROUND(SUMIFS(流水支出,流水账户,$A9,流水日期,BJ$6),2)) | BK9: =IF(OR($A9="",BK$6=""),"",ROUND(SUMIFS(流水收入,流水账户,$A9,流水日期,BK$6),2)) | BL9: =IF(OR($A9="",BL$6=""),"",ROUND(SUMIFS(流水支出,流水账户,$A9,流水日期,BL$6),2)) | BM9: =IF($A9="","",ROUND(SUMIF($C$7:$BL$7,"收款",C9:BL9),2)) | BN9: =IF($A9="","",ROUND(SUMIF($C$7:$BL$7,"付款",C9:BL9),2)) | BO9: =IF($A9="","",ROUND(N($B9)+N(BM9)-N(BN9),2))
A10: =IF(基础资料!$B$7="","",基础资料!$B$7) | B10: =IF(OR($A10="",NOT(ISNUMBER($H$3))),"",ROUND(SUMIF(账户表,$A10,账户期初)+SUMIFS(流水收入,流水账户,$A10,流水日期,"<"&$B$3)-SUMIFS(流水支出,流水账户,$A10,流水日期,"<"&$B$3),2)) | C10: =IF(OR($A10="",C$6=""),"",ROUND(SUMIFS(流水收入,流水账户,$A10,流水日期,C$6),2)) | D10: =IF(OR($A10="",D$6=""),"",ROUND(SUMIFS(流水支出,流水账户,$A10,流水日期,D$6),2)) | E10: =IF(OR($A10="",E$6=""),"",ROUND(SUMIFS(流水收入,流水账户,$A10,流水日期,E$6),2)) | F10: =IF(OR($A10="",F$6=""),"",ROUND(SUMIFS(流水支出,流水账户,$A10,流水日期,F$6),2)) | G10: =IF(OR($A10="",G$6=""),"",ROUND(SUMIFS(流水收入,流水账户,$A10,流水日期,G$6),2)) | H10: =IF(OR($A10="",H$6=""),"",ROUND(SUMIFS(流水支出,流水账户,$A10,流水日期,H$6),2)) | I10: =IF(OR($A10="",I$6=""),"",ROUND(SUMIFS(流水收入,流水账户,$A10,流水日期,I$6),2)) | J10: =IF(OR($A10="",J$6=""),"",ROUND(SUMIFS(流水支出,流水账户,$A10,流水日期,J$6),2)) | K10: =IF(OR($A10="",K$6=""),"",ROUND(SUMIFS(流水收入,流水账户,$A10,流水日期,K$6),2)) | L10: =IF(OR($A10="",L$6=""),"",ROUND(SUMIFS(流水支出,流水账户,$A10,流水日期,L$6),2)) | M10: =IF(OR($A10="",M$6=""),"",ROUND(SUMIFS(流水收入,流水账户,$A10,流水日期,M$6),2)) | N10: =IF(OR($A10="",N$6=""),"",ROUND(SUMIFS(流水支出,流水账户,$A10,流水日期,N$6),2)) | O10: =IF(OR($A10="",O$6=""),"",ROUND(SUMIFS(流水收入,流水账户,$A10,流水日期,O$6),2)) | P10: =IF(OR($A10="",P$6=""),"",ROUND(SUMIFS(流水支出,流水账户,$A10,流水日期,P$6),2)) | Q10: =IF(OR($A10="",Q$6=""),"",ROUND(SUMIFS(流水收入,流水账户,$A10,流水日期,Q$6),2)) | R10: =IF(OR($A10="",R$6=""),"",ROUND(SUMIFS(流水支出,流水账户,$A10,流水日期,R$6),2)) | S10: =IF(OR($A10="",S$6=""),"",ROUND(SUMIFS(流水收入,流水账户,$A10,流水日期,S$6),2)) | T10: =IF(OR($A10="",T$6=""),"",ROUND(SUMIFS(流水支出,流水账户,$A10,流水日期,T$6),2)) | U10: =IF(OR($A10="",U$6=""),"",ROUND(SUMIFS(流水收入,流水账户,$A10,流水日期,U$6),2)) | V10: =IF(OR($A10="",V$6=""),"",ROUND(SUMIFS(流水支出,流水账户,$A10,流水日期,V$6),2)) | W10: =IF(OR($A10="",W$6=""),"",ROUND(SUMIFS(流水收入,流水账户,$A10,流水日期,W$6),2)) | X10: =IF(OR($A10="",X$6=""),"",ROUND(SUMIFS(流水支出,流水账户,$A10,流水日期,X$6),2)) | Y10: =IF(OR($A10="",Y$6=""),"",ROUND(SUMIFS(流水收入,流水账户,$A10,流水日期,Y$6),2)) | Z10: =IF(OR($A10="",Z$6=""),"",ROUND(SUMIFS(流水支出,流水账户,$A10,流水日期,Z$6),2)) | AA10: =IF(OR($A10="",AA$6=""),"",ROUND(SUMIFS(流水收入,流水账户,$A10,流水日期,AA$6),2)) | AB10: =IF(OR($A10="",AB$6=""),"",ROUND(SUMIFS(流水支出,流水账户,$A10,流水日期,AB$6),2)) | AC10: =IF(OR($A10="",AC$6=""),"",ROUND(SUMIFS(流水收入,流水账户,$A10,流水日期,AC$6),2)) | AD10: =IF(OR($A10="",AD$6=""),"",ROUND(SUMIFS(流水支出,流水账户,$A10,流水日期,AD$6),2)) | AE10: =IF(OR($A10="",AE$6=""),"",ROUND(SUMIFS(流水收入,流水账户,$A10,流水日期,AE$6),2)) | AF10: =IF(OR($A10="",AF$6=""),"",ROUND(SUMIFS(流水支出,流水账户,$A10,流水日期,AF$6),2)) | AG10: =IF(OR($A10="",AG$6=""),"",ROUND(SUMIFS(流水收入,流水账户,$A10,流水日期,AG$6),2)) | AH10: =IF(OR($A10="",AH$6=""),"",ROUND(SUMIFS(流水支出,流水账户,$A10,流水日期,AH$6),2)) | AI10: =IF(OR($A10="",AI$6=""),"",ROUND(SUMIFS(流水收入,流水账户,$A10,流水日期,AI$6),2)) | AJ10: =IF(OR($A10="",AJ$6=""),"",ROUND(SUMIFS(流水支出,流水账户,$A10,流水日期,AJ$6),2)) | AK10: =IF(OR($A10="",AK$6=""),"",ROUND(SUMIFS(流水收入,流水账户,$A10,流水日期,AK$6),2)) | AL10: =IF(OR($A10="",AL$6=""),"",ROUND(SUMIFS(流水支出,流水账户,$A10,流水日期,AL$6),2)) | AM10: =IF(OR($A10="",AM$6=""),"",ROUND(SUMIFS(流水收入,流水账户,$A10,流水日期,AM$6),2)) | AN10: =IF(OR($A10="",AN$6=""),"",ROUND(SUMIFS(流水支出,流水账户,$A10,流水日期,AN$6),2)) | AO10: =IF(OR($A10="",AO$6=""),"",ROUND(SUMIFS(流水收入,流水账户,$A10,流水日期,AO$6),2)) | AP10: =IF(OR($A10="",AP$6=""),"",ROUND(SUMIFS(流水支出,流水账户,$A10,流水日期,AP$6),2)) | AQ10: =IF(OR($A10="",AQ$6=""),"",ROUND(SUMIFS(流水收入,流水账户,$A10,流水日期,AQ$6),2)) | AR10: =IF(OR($A10="",AR$6=""),"",ROUND(SUMIFS(流水支出,流水账户,$A10,流水日期,AR$6),2)) | AS10: =IF(OR($A10="",AS$6=""),"",ROUND(SUMIFS(流水收入,流水账户,$A10,流水日期,AS$6),2)) | AT10: =IF(OR($A10="",AT$6=""),"",ROUND(SUMIFS(流水支出,流水账户,$A10,流水日期,AT$6),2)) | AU10: =IF(OR($A10="",AU$6=""),"",ROUND(SUMIFS(流水收入,流水账户,$A10,流水日期,AU$6),2)) | AV10: =IF(OR($A10="",AV$6=""),"",ROUND(SUMIFS(流水支出,流水账户,$A10,流水日期,AV$6),2)) | AW10: =IF(OR($A10="",AW$6=""),"",ROUND(SUMIFS(流水收入,流水账户,$A10,流水日期,AW$6),2)) | AX10: =IF(OR($A10="",AX$6=""),"",ROUND(SUMIFS(流水支出,流水账户,$A10,流水日期,AX$6),2)) | AY10: =IF(OR($A10="",AY$6=""),"",ROUND(SUMIFS(流水收入,流水账户,$A10,流水日期,AY$6),2)) | AZ10: =IF(OR($A10="",AZ$6=""),"",ROUND(SUMIFS(流水支出,流水账户,$A10,流水日期,AZ$6),2)) | BA10: =IF(OR($A10="",BA$6=""),"",ROUND(SUMIFS(流水收入,流水账户,$A10,流水日期,BA$6),2)) | BB10: =IF(OR($A10="",BB$6=""),"",ROUND(SUMIFS(流水支出,流水账户,$A10,流水日期,BB$6),2)) | BC10: =IF(OR($A10="",BC$6=""),"",ROUND(SUMIFS(流水收入,流水账户,$A10,流水日期,BC$6),2)) | BD10: =IF(OR($A10="",BD$6=""),"",ROUND(SUMIFS(流水支出,流水账户,$A10,流水日期,BD$6),2)) | BE10: =IF(OR($A10="",BE$6=""),"",ROUND(SUMIFS(流水收入,流水账户,$A10,流水日期,BE$6),2)) | BF10: =IF(OR($A10="",BF$6=""),"",ROUND(SUMIFS(流水支出,流水账户,$A10,流水日期,BF$6),2)) | BG10: =IF(OR($A10="",BG$6=""),"",ROUND(SUMIFS(流水收入,流水账户,$A10,流水日期,BG$6),2)) | BH10: =IF(OR($A10="",BH$6=""),"",ROUND(SUMIFS(流水支出,流水账户,$A10,流水日期,BH$6),2)) | BI10: =IF(OR($A10="",BI$6=""),"",ROUND(SUMIFS(流水收入,流水账户,$A10,流水日期,BI$6),2)) | BJ10: =IF(OR($A10="",BJ$6=""),"",ROUND(SUMIFS(流水支出,流水账户,$A10,流水日期,BJ$6),2)) | BK10: =IF(OR($A10="",BK$6=""),"",ROUND(SUMIFS(流水收入,流水账户,$A10,流水日期,BK$6),2)) | BL10: =IF(OR($A10="",BL$6=""),"",ROUND(SUMIFS(流水支出,流水账户,$A10,流水日期,BL$6),2)) | BM10: =IF($A10="","",ROUND(SUMIF($C$7:$BL$7,"收款",C10:BL10),2)) | BN10: =IF($A10="","",ROUND(SUMIF($C$7:$BL$7,"付款",C10:BL10),2)) | BO10: =IF($A10="","",ROUND(N($B10)+N(BM10)-N(BN10),2))
A11: =IF(基础资料!$B$8="","",基础资料!$B$8) | B11: =IF(OR($A11="",NOT(ISNUMBER($H$3))),"",ROUND(SUMIF(账户表,$A11,账户期初)+SUMIFS(流水收入,流水账户,$A11,流水日期,"<"&$B$3)-SUMIFS(流水支出,流水账户,$A11,流水日期,"<"&$B$3),2)) | C11: =IF(OR($A11="",C$6=""),"",ROUND(SUMIFS(流水收入,流水账户,$A11,流水日期,C$6),2)) | D11: =IF(OR($A11="",D$6=""),"",ROUND(SUMIFS(流水支出,流水账户,$A11,流水日期,D$6),2)) | E11: =IF(OR($A11="",E$6=""),"",ROUND(SUMIFS(流水收入,流水账户,$A11,流水日期,E$6),2)) | F11: =IF(OR($A11="",F$6=""),"",ROUND(SUMIFS(流水支出,流水账户,$A11,流水日期,F$6),2)) | G11: =IF(OR($A11="",G$6=""),"",ROUND(SUMIFS(流水收入,流水账户,$A11,流水日期,G$6),2)) | H11: =IF(OR($A11="",H$6=""),"",ROUND(SUMIFS(流水支出,流水账户,$A11,流水日期,H$6),2)) | I11: =IF(OR($A11="",I$6=""),"",ROUND(SUMIFS(流水收入,流水账户,$A11,流水日期,I$6),2)) | J11: =IF(OR($A11="",J$6=""),"",ROUND(SUMIFS(流水支出,流水账户,$A11,流水日期,J$6),2)) | K11: =IF(OR($A11="",K$6=""),"",ROUND(SUMIFS(流水收入,流水账户,$A11,流水日期,K$6),2)) | L11: =IF(OR($A11="",L$6=""),"",ROUND(SUMIFS(流水支出,流水账户,$A11,流水日期,L$6),2)) | M11: =IF(OR($A11="",M$6=""),"",ROUND(SUMIFS(流水收入,流水账户,$A11,流水日期,M$6),2)) | N11: =IF(OR($A11="",N$6=""),"",ROUND(SUMIFS(流水支出,流水账户,$A11,流水日期,N$6),2)) | O11: =IF(OR($A11="",O$6=""),"",ROUND(SUMIFS(流水收入,流水账户,$A11,流水日期,O$6),2)) | P11: =IF(OR($A11="",P$6=""),"",ROUND(SUMIFS(流水支出,流水账户,$A11,流水日期,P$6),2)) | Q11: =IF(OR($A11="",Q$6=""),"",ROUND(SUMIFS(流水收入,流水账户,$A11,流水日期,Q$6),2)) | R11: =IF(OR($A11="",R$6=""),"",ROUND(SUMIFS(流水支出,流水账户,$A11,流水日期,R$6),2)) | S11: =IF(OR($A11="",S$6=""),"",ROUND(SUMIFS(流水收入,流水账户,$A11,流水日期,S$6),2)) | T11: =IF(OR($A11="",T$6=""),"",ROUND(SUMIFS(流水支出,流水账户,$A11,流水日期,T$6),2)) | U11: =IF(OR($A11="",U$6=""),"",ROUND(SUMIFS(流水收入,流水账户,$A11,流水日期,U$6),2)) | V11: =IF(OR($A11="",V$6=""),"",ROUND(SUMIFS(流水支出,流水账户,$A11,流水日期,V$6),2)) | W11: =IF(OR($A11="",W$6=""),"",ROUND(SUMIFS(流水收入,流水账户,$A11,流水日期,W$6),2)) | X11: =IF(OR($A11="",X$6=""),"",ROUND(SUMIFS(流水支出,流水账户,$A11,流水日期,X$6),2)) | Y11: =IF(OR($A11="",Y$6=""),"",ROUND(SUMIFS(流水收入,流水账户,$A11,流水日期,Y$6),2)) | Z11: =IF(OR($A11="",Z$6=""),"",ROUND(SUMIFS(流水支出,流水账户,$A11,流水日期,Z$6),2)) | AA11: =IF(OR($A11="",AA$6=""),"",ROUND(SUMIFS(流水收入,流水账户,$A11,流水日期,AA$6),2)) | AB11: =IF(OR($A11="",AB$6=""),"",ROUND(SUMIFS(流水支出,流水账户,$A11,流水日期,AB$6),2)) | AC11: =IF(OR($A11="",AC$6=""),"",ROUND(SUMIFS(流水收入,流水账户,$A11,流水日期,AC$6),2)) | AD11: =IF(OR($A11="",AD$6=""),"",ROUND(SUMIFS(流水支出,流水账户,$A11,流水日期,AD$6),2)) | AE11: =IF(OR($A11="",AE$6=""),"",ROUND(SUMIFS(流水收入,流水账户,$A11,流水日期,AE$6),2)) | AF11: =IF(OR($A11="",AF$6=""),"",ROUND(SUMIFS(流水支出,流水账户,$A11,流水日期,AF$6),2)) | AG11: =IF(OR($A11="",AG$6=""),"",ROUND(SUMIFS(流水收入,流水账户,$A11,流水日期,AG$6),2)) | AH11: =IF(OR($A11="",AH$6=""),"",ROUND(SUMIFS(流水支出,流水账户,$A11,流水日期,AH$6),2)) | AI11: =IF(OR($A11="",AI$6=""),"",ROUND(SUMIFS(流水收入,流水账户,$A11,流水日期,AI$6),2)) | AJ11: =IF(OR($A11="",AJ$6=""),"",ROUND(SUMIFS(流水支出,流水账户,$A11,流水日期,AJ$6),2)) | AK11: =IF(OR($A11="",AK$6=""),"",ROUND(SUMIFS(流水收入,流水账户,$A11,流水日期,AK$6),2)) | AL11: =IF(OR($A11="",AL$6=""),"",ROUND(SUMIFS(流水支出,流水账户,$A11,流水日期,AL$6),2)) | AM11: =IF(OR($A11="",AM$6=""),"",ROUND(SUMIFS(流水收入,流水账户,$A11,流水日期,AM$6),2)) | AN11: =IF(OR($A11="",AN$6=""),"",ROUND(SUMIFS(流水支出,流水账户,$A11,流水日期,AN$6),2)) | AO11: =IF(OR($A11="",AO$6=""),"",ROUND(SUMIFS(流水收入,流水账户,$A11,流水日期,AO$6),2)) | AP11: =IF(OR($A11="",AP$6=""),"",ROUND(SUMIFS(流水支出,流水账户,$A11,流水日期,AP$6),2)) | AQ11: =IF(OR($A11="",AQ$6=""),"",ROUND(SUMIFS(流水收入,流水账户,$A11,流水日期,AQ$6),2)) | AR11: =IF(OR($A11="",AR$6=""),"",ROUND(SUMIFS(流水支出,流水账户,$A11,流水日期,AR$6),2)) | AS11: =IF(OR($A11="",AS$6=""),"",ROUND(SUMIFS(流水收入,流水账户,$A11,流水日期,AS$6),2)) | AT11: =IF(OR($A11="",AT$6=""),"",ROUND(SUMIFS(流水支出,流水账户,$A11,流水日期,AT$6),2)) | AU11: =IF(OR($A11="",AU$6=""),"",ROUND(SUMIFS(流水收入,流水账户,$A11,流水日期,AU$6),2)) | AV11: =IF(OR($A11="",AV$6=""),"",ROUND(SUMIFS(流水支出,流水账户,$A11,流水日期,AV$6),2)) | AW11: =IF(OR($A11="",AW$6=""),"",ROUND(SUMIFS(流水收入,流水账户,$A11,流水日期,AW$6),2)) | AX11: =IF(OR($A11="",AX$6=""),"",ROUND(SUMIFS(流水支出,流水账户,$A11,流水日期,AX$6),2)) | AY11: =IF(OR($A11="",AY$6=""),"",ROUND(SUMIFS(流水收入,流水账户,$A11,流水日期,AY$6),2)) | AZ11: =IF(OR($A11="",AZ$6=""),"",ROUND(SUMIFS(流水支出,流水账户,$A11,流水日期,AZ$6),2)) | BA11: =IF(OR($A11="",BA$6=""),"",ROUND(SUMIFS(流水收入,流水账户,$A11,流水日期,BA$6),2)) | BB11: =IF(OR($A11="",BB$6=""),"",ROUND(SUMIFS(流水支出,流水账户,$A11,流水日期,BB$6),2)) | BC11: =IF(OR($A11="",BC$6=""),"",ROUND(SUMIFS(流水收入,流水账户,$A11,流水日期,BC$6),2)) | BD11: =IF(OR($A11="",BD$6=""),"",ROUND(SUMIFS(流水支出,流水账户,$A11,流水日期,BD$6),2)) | BE11: =IF(OR($A11="",BE$6=""),"",ROUND(SUMIFS(流水收入,流水账户,$A11,流水日期,BE$6),2)) | BF11: =IF(OR($A11="",BF$6=""),"",ROUND(SUMIFS(流水支出,流水账户,$A11,流水日期,BF$6),2)) | BG11: =IF(OR($A11="",BG$6=""),"",ROUND(SUMIFS(流水收入,流水账户,$A11,流水日期,BG$6),2)) | BH11: =IF(OR($A11="",BH$6=""),"",ROUND(SUMIFS(流水支出,流水账户,$A11,流水日期,BH$6),2)) | BI11: =IF(OR($A11="",BI$6=""),"",ROUND(SUMIFS(流水收入,流水账户,$A11,流水日期,BI$6),2)) | BJ11: =IF(OR($A11="",BJ$6=""),"",ROUND(SUMIFS(流水支出,流水账户,$A11,流水日期,BJ$6),2)) | BK11: =IF(OR($A11="",BK$6=""),"",ROUND(SUMIFS(流水收入,流水账户,$A11,流水日期,BK$6),2)) | BL11: =IF(OR($A11="",BL$6=""),"",ROUND(SUMIFS(流水支出,流水账户,$A11,流水日期,BL$6),2)) | BM11: =IF($A11="","",ROUND(SUMIF($C$7:$BL$7,"收款",C11:BL11),2)) | BN11: =IF($A11="","",ROUND(SUMIF($C$7:$BL$7,"付款",C11:BL11),2)) | BO11: =IF($A11="","",ROUND(N($B11)+N(BM11)-N(BN11),2))
A12: =IF(基础资料!$B$9="","",基础资料!$B$9) | B12: =IF(OR($A12="",NOT(ISNUMBER($H$3))),"",ROUND(SUMIF(账户表,$A12,账户期初)+SUMIFS(流水收入,流水账户,$A12,流水日期,"<"&$B$3)-SUMIFS(流水支出,流水账户,$A12,流水日期,"<"&$B$3),2)) | C12: =IF(OR($A12="",C$6=""),"",ROUND(SUMIFS(流水收入,流水账户,$A12,流水日期,C$6),2)) | D12: =IF(OR($A12="",D$6=""),"",ROUND(SUMIFS(流水支出,流水账户,$A12,流水日期,D$6),2)) | E12: =IF(OR($A12="",E$6=""),"",ROUND(SUMIFS(流水收入,流水账户,$A12,流水日期,E$6),2)) | F12: =IF(OR($A12="",F$6=""),"",ROUND(SUMIFS(流水支出,流水账户,$A12,流水日期,F$6),2)) | G12: =IF(OR($A12="",G$6=""),"",ROUND(SUMIFS(流水收入,流水账户,$A12,流水日期,G$6),2)) | H12: =IF(OR($A12="",H$6=""),"",ROUND(SUMIFS(流水支出,流水账户,$A12,流水日期,H$6),2)) | I12: =IF(OR($A12="",I$6=""),"",ROUND(SUMIFS(流水收入,流水账户,$A12,流水日期,I$6),2)) | J12: =IF(OR($A12="",J$6=""),"",ROUND(SUMIFS(流水支出,流水账户,$A12,流水日期,J$6),2)) | K12: =IF(OR($A12="",K$6=""),"",ROUND(SUMIFS(流水收入,流水账户,$A12,流水日期,K$6),2)) | L12: =IF(OR($A12="",L$6=""),"",ROUND(SUMIFS(流水支出,流水账户,$A12,流水日期,L$6),2)) | M12: =IF(OR($A12="",M$6=""),"",ROUND(SUMIFS(流水收入,流水账户,$A12,流水日期,M$6),2)) | N12: =IF(OR($A12="",N$6=""),"",ROUND(SUMIFS(流水支出,流水账户,$A12,流水日期,N$6),2)) | O12: =IF(OR($A12="",O$6=""),"",ROUND(SUMIFS(流水收入,流水账户,$A12,流水日期,O$6),2)) | P12: =IF(OR($A12="",P$6=""),"",ROUND(SUMIFS(流水支出,流水账户,$A12,流水日期,P$6),2)) | Q12: =IF(OR($A12="",Q$6=""),"",ROUND(SUMIFS(流水收入,流水账户,$A12,流水日期,Q$6),2)) | R12: =IF(OR($A12="",R$6=""),"",ROUND(SUMIFS(流水支出,流水账户,$A12,流水日期,R$6),2)) | S12: =IF(OR($A12="",S$6=""),"",ROUND(SUMIFS(流水收入,流水账户,$A12,流水日期,S$6),2)) | T12: =IF(OR($A12="",T$6=""),"",ROUND(SUMIFS(流水支出,流水账户,$A12,流水日期,T$6),2)) | U12: =IF(OR($A12="",U$6=""),"",ROUND(SUMIFS(流水收入,流水账户,$A12,流水日期,U$6),2)) | V12: =IF(OR($A12="",V$6=""),"",ROUND(SUMIFS(流水支出,流水账户,$A12,流水日期,V$6),2)) | W12: =IF(OR($A12="",W$6=""),"",ROUND(SUMIFS(流水收入,流水账户,$A12,流水日期,W$6),2)) | X12: =IF(OR($A12="",X$6=""),"",ROUND(SUMIFS(流水支出,流水账户,$A12,流水日期,X$6),2)) | Y12: =IF(OR($A12="",Y$6=""),"",ROUND(SUMIFS(流水收入,流水账户,$A12,流水日期,Y$6),2)) | Z12: =IF(OR($A12="",Z$6=""),"",ROUND(SUMIFS(流水支出,流水账户,$A12,流水日期,Z$6),2)) | AA12: =IF(OR($A12="",AA$6=""),"",ROUND(SUMIFS(流水收入,流水账户,$A12,流水日期,AA$6),2)) | AB12: =IF(OR($A12="",AB$6=""),"",ROUND(SUMIFS(流水支出,流水账户,$A12,流水日期,AB$6),2)) | AC12: =IF(OR($A12="",AC$6=""),"",ROUND(SUMIFS(流水收入,流水账户,$A12,流水日期,AC$6),2)) | AD12: =IF(OR($A12="",AD$6=""),"",ROUND(SUMIFS(流水支出,流水账户,$A12,流水日期,AD$6),2)) | AE12: =IF(OR($A12="",AE$6=""),"",ROUND(SUMIFS(流水收入,流水账户,$A12,流水日期,AE$6),2)) | AF12: =IF(OR($A12="",AF$6=""),"",ROUND(SUMIFS(流水支出,流水账户,$A12,流水日期,AF$6),2)) | AG12: =IF(OR($A12="",AG$6=""),"",ROUND(SUMIFS(流水收入,流水账户,$A12,流水日期,AG$6),2)) | AH12: =IF(OR($A12="",AH$6=""),"",ROUND(SUMIFS(流水支出,流水账户,$A12,流水日期,AH$6),2)) | AI12: =IF(OR($A12="",AI$6=""),"",ROUND(SUMIFS(流水收入,流水账户,$A12,流水日期,AI$6),2)) | AJ12: =IF(OR($A12="",AJ$6=""),"",ROUND(SUMIFS(流水支出,流水账户,$A12,流水日期,AJ$6),2)) | AK12: =IF(OR($A12="",AK$6=""),"",ROUND(SUMIFS(流水收入,流水账户,$A12,流水日期,AK$6),2)) | AL12: =IF(OR($A12="",AL$6=""),"",ROUND(SUMIFS(流水支出,流水账户,$A12,流水日期,AL$6),2)) | AM12: =IF(OR($A12="",AM$6=""),"",ROUND(SUMIFS(流水收入,流水账户,$A12,流水日期,AM$6),2)) | AN12: =IF(OR($A12="",AN$6=""),"",ROUND(SUMIFS(流水支出,流水账户,$A12,流水日期,AN$6),2)) | AO12: =IF(OR($A12="",AO$6=""),"",ROUND(SUMIFS(流水收入,流水账户,$A12,流水日期,AO$6),2)) | AP12: =IF(OR($A12="",AP$6=""),"",ROUND(SUMIFS(流水支出,流水账户,$A12,流水日期,AP$6),2)) | AQ12: =IF(OR($A12="",AQ$6=""),"",ROUND(SUMIFS(流水收入,流水账户,$A12,流水日期,AQ$6),2)) | AR12: =IF(OR($A12="",AR$6=""),"",ROUND(SUMIFS(流水支出,流水账户,$A12,流水日期,AR$6),2)) | AS12: =IF(OR($A12="",AS$6=""),"",ROUND(SUMIFS(流水收入,流水账户,$A12,流水日期,AS$6),2)) | AT12: =IF(OR($A12="",AT$6=""),"",ROUND(SUMIFS(流水支出,流水账户,$A12,流水日期,AT$6),2)) | AU12: =IF(OR($A12="",AU$6=""),"",ROUND(SUMIFS(流水收入,流水账户,$A12,流水日期,AU$6),2)) | AV12: =IF(OR($A12="",AV$6=""),"",ROUND(SUMIFS(流水支出,流水账户,$A12,流水日期,AV$6),2)) | AW12: =IF(OR($A12="",AW$6=""),"",ROUND(SUMIFS(流水收入,流水账户,$A12,流水日期,AW$6),2)) | AX12: =IF(OR($A12="",AX$6=""),"",ROUND(SUMIFS(流水支出,流水账户,$A12,流水日期,AX$6),2)) | AY12: =IF(OR($A12="",AY$6=""),"",ROUND(SUMIFS(流水收入,流水账户,$A12,流水日期,AY$6),2)) | AZ12: =IF(OR($A12="",AZ$6=""),"",ROUND(SUMIFS(流水支出,流水账户,$A12,流水日期,AZ$6),2)) | BA12: =IF(OR($A12="",BA$6=""),"",ROUND(SUMIFS(流水收入,流水账户,$A12,流水日期,BA$6),2)) | BB12: =IF(OR($A12="",BB$6=""),"",ROUND(SUMIFS(流水支出,流水账户,$A12,流水日期,BB$6),2)) | BC12: =IF(OR($A12="",BC$6=""),"",ROUND(SUMIFS(流水收入,流水账户,$A12,流水日期,BC$6),2)) | BD12: =IF(OR($A12="",BD$6=""),"",ROUND(SUMIFS(流水支出,流水账户,$A12,流水日期,BD$6),2)) | BE12: =IF(OR($A12="",BE$6=""),"",ROUND(SUMIFS(流水收入,流水账户,$A12,流水日期,BE$6),2)) | BF12: =IF(OR($A12="",BF$6=""),"",ROUND(SUMIFS(流水支出,流水账户,$A12,流水日期,BF$6),2)) | BG12: =IF(OR($A12="",BG$6=""),"",ROUND(SUMIFS(流水收入,流水账户,$A12,流水日期,BG$6),2)) | BH12: =IF(OR($A12="",BH$6=""),"",ROUND(SUMIFS(流水支出,流水账户,$A12,流水日期,BH$6),2)) | BI12: =IF(OR($A12="",BI$6=""),"",ROUND(SUMIFS(流水收入,流水账户,$A12,流水日期,BI$6),2)) | BJ12: =IF(OR($A12="",BJ$6=""),"",ROUND(SUMIFS(流水支出,流水账户,$A12,流水日期,BJ$6),2)) | BK12: =IF(OR($A12="",BK$6=""),"",ROUND(SUMIFS(流水收入,流水账户,$A12,流水日期,BK$6),2)) | BL12: =IF(OR($A12="",BL$6=""),"",ROUND(SUMIFS(流水支出,流水账户,$A12,流水日期,BL$6),2)) | BM12: =IF($A12="","",ROUND(SUMIF($C$7:$BL$7,"收款",C12:BL12),2)) | BN12: =IF($A12="","",ROUND(SUMIF($C$7:$BL$7,"付款",C12:BL12),2)) | BO12: =IF($A12="","",ROUND(N($B12)+N(BM12)-N(BN12),2))
A13: =IF(基础资料!$B$10="","",基础资料!$B$10) | B13: =IF(OR($A13="",NOT(ISNUMBER($H$3))),"",ROUND(SUMIF(账户表,$A13,账户期初)+SUMIFS(流水收入,流水账户,$A13,流水日期,"<"&$B$3)-SUMIFS(流水支出,流水账户,$A13,流水日期,"<"&$B$3),2)) | C13: =IF(OR($A13="",C$6=""),"",ROUND(SUMIFS(流水收入,流水账户,$A13,流水日期,C$6),2)) | D13: =IF(OR($A13="",D$6=""),"",ROUND(SUMIFS(流水支出,流水账户,$A13,流水日期,D$6),2)) | E13: =IF(OR($A13="",E$6=""),"",ROUND(SUMIFS(流水收入,流水账户,$A13,流水日期,E$6),2)) | F13: =IF(OR($A13="",F$6=""),"",ROUND(SUMIFS(流水支出,流水账户,$A13,流水日期,F$6),2)) | G13: =IF(OR($A13="",G$6=""),"",ROUND(SUMIFS(流水收入,流水账户,$A13,流水日期,G$6),2)) | H13: =IF(OR($A13="",H$6=""),"",ROUND(SUMIFS(流水支出,流水账户,$A13,流水日期,H$6),2)) | I13: =IF(OR($A13="",I$6=""),"",ROUND(SUMIFS(流水收入,流水账户,$A13,流水日期,I$6),2)) | J13: =IF(OR($A13="",J$6=""),"",ROUND(SUMIFS(流水支出,流水账户,$A13,流水日期,J$6),2)) | K13: =IF(OR($A13="",K$6=""),"",ROUND(SUMIFS(流水收入,流水账户,$A13,流水日期,K$6),2)) | L13: =IF(OR($A13="",L$6=""),"",ROUND(SUMIFS(流水支出,流水账户,$A13,流水日期,L$6),2)) | M13: =IF(OR($A13="",M$6=""),"",ROUND(SUMIFS(流水收入,流水账户,$A13,流水日期,M$6),2)) | N13: =IF(OR($A13="",N$6=""),"",ROUND(SUMIFS(流水支出,流水账户,$A13,流水日期,N$6),2)) | O13: =IF(OR($A13="",O$6=""),"",ROUND(SUMIFS(流水收入,流水账户,$A13,流水日期,O$6),2)) | P13: =IF(OR($A13="",P$6=""),"",ROUND(SUMIFS(流水支出,流水账户,$A13,流水日期,P$6),2)) | Q13: =IF(OR($A13="",Q$6=""),"",ROUND(SUMIFS(流水收入,流水账户,$A13,流水日期,Q$6),2)) | R13: =IF(OR($A13="",R$6=""),"",ROUND(SUMIFS(流水支出,流水账户,$A13,流水日期,R$6),2)) | S13: =IF(OR($A13="",S$6=""),"",ROUND(SUMIFS(流水收入,流水账户,$A13,流水日期,S$6),2)) | T13: =IF(OR($A13="",T$6=""),"",ROUND(SUMIFS(流水支出,流水账户,$A13,流水日期,T$6),2)) | U13: =IF(OR($A13="",U$6=""),"",ROUND(SUMIFS(流水收入,流水账户,$A13,流水日期,U$6),2)) | V13: =IF(OR($A13="",V$6=""),"",ROUND(SUMIFS(流水支出,流水账户,$A13,流水日期,V$6),2)) | W13: =IF(OR($A13="",W$6=""),"",ROUND(SUMIFS(流水收入,流水账户,$A13,流水日期,W$6),2)) | X13: =IF(OR($A13="",X$6=""),"",ROUND(SUMIFS(流水支出,流水账户,$A13,流水日期,X$6),2)) | Y13: =IF(OR($A13="",Y$6=""),"",ROUND(SUMIFS(流水收入,流水账户,$A13,流水日期,Y$6),2)) | Z13: =IF(OR($A13="",Z$6=""),"",ROUND(SUMIFS(流水支出,流水账户,$A13,流水日期,Z$6),2)) | AA13: =IF(OR($A13="",AA$6=""),"",ROUND(SUMIFS(流水收入,流水账户,$A13,流水日期,AA$6),2)) | AB13: =IF(OR($A13="",AB$6=""),"",ROUND(SUMIFS(流水支出,流水账户,$A13,流水日期,AB$6),2)) | AC13: =IF(OR($A13="",AC$6=""),"",ROUND(SUMIFS(流水收入,流水账户,$A13,流水日期,AC$6),2)) | AD13: =IF(OR($A13="",AD$6=""),"",ROUND(SUMIFS(流水支出,流水账户,$A13,流水日期,AD$6),2)) | AE13: =IF(OR($A13="",AE$6=""),"",ROUND(SUMIFS(流水收入,流水账户,$A13,流水日期,AE$6),2)) | AF13: =IF(OR($A13="",AF$6=""),"",ROUND(SUMIFS(流水支出,流水账户,$A13,流水日期,AF$6),2)) | AG13: =IF(OR($A13="",AG$6=""),"",ROUND(SUMIFS(流水收入,流水账户,$A13,流水日期,AG$6),2)) | AH13: =IF(OR($A13="",AH$6=""),"",ROUND(SUMIFS(流水支出,流水账户,$A13,流水日期,AH$6),2)) | AI13: =IF(OR($A13="",AI$6=""),"",ROUND(SUMIFS(流水收入,流水账户,$A13,流水日期,AI$6),2)) | AJ13: =IF(OR($A13="",AJ$6=""),"",ROUND(SUMIFS(流水支出,流水账户,$A13,流水日期,AJ$6),2)) | AK13: =IF(OR($A13="",AK$6=""),"",ROUND(SUMIFS(流水收入,流水账户,$A13,流水日期,AK$6),2)) | AL13: =IF(OR($A13="",AL$6=""),"",ROUND(SUMIFS(流水支出,流水账户,$A13,流水日期,AL$6),2)) | AM13: =IF(OR($A13="",AM$6=""),"",ROUND(SUMIFS(流水收入,流水账户,$A13,流水日期,AM$6),2)) | AN13: =IF(OR($A13="",AN$6=""),"",ROUND(SUMIFS(流水支出,流水账户,$A13,流水日期,AN$6),2)) | AO13: =IF(OR($A13="",AO$6=""),"",ROUND(SUMIFS(流水收入,流水账户,$A13,流水日期,AO$6),2)) | AP13: =IF(OR($A13="",AP$6=""),"",ROUND(SUMIFS(流水支出,流水账户,$A13,流水日期,AP$6),2)) | AQ13: =IF(OR($A13="",AQ$6=""),"",ROUND(SUMIFS(流水收入,流水账户,$A13,流水日期,AQ$6),2)) | AR13: =IF(OR($A13="",AR$6=""),"",ROUND(SUMIFS(流水支出,流水账户,$A13,流水日期,AR$6),2)) | AS13: =IF(OR($A13="",AS$6=""),"",ROUND(SUMIFS(流水收入,流水账户,$A13,流水日期,AS$6),2)) | AT13: =IF(OR($A13="",AT$6=""),"",ROUND(SUMIFS(流水支出,流水账户,$A13,流水日期,AT$6),2)) | AU13: =IF(OR($A13="",AU$6=""),"",ROUND(SUMIFS(流水收入,流水账户,$A13,流水日期,AU$6),2)) | AV13: =IF(OR($A13="",AV$6=""),"",ROUND(SUMIFS(流水支出,流水账户,$A13,流水日期,AV$6),2)) | AW13: =IF(OR($A13="",AW$6=""),"",ROUND(SUMIFS(流水收入,流水账户,$A13,流水日期,AW$6),2)) | AX13: =IF(OR($A13="",AX$6=""),"",ROUND(SUMIFS(流水支出,流水账户,$A13,流水日期,AX$6),2)) | AY13: =IF(OR($A13="",AY$6=""),"",ROUND(SUMIFS(流水收入,流水账户,$A13,流水日期,AY$6),2)) | AZ13: =IF(OR($A13="",AZ$6=""),"",ROUND(SUMIFS(流水支出,流水账户,$A13,流水日期,AZ$6),2)) | BA13: =IF(OR($A13="",BA$6=""),"",ROUND(SUMIFS(流水收入,流水账户,$A13,流水日期,BA$6),2)) | BB13: =IF(OR($A13="",BB$6=""),"",ROUND(SUMIFS(流水支出,流水账户,$A13,流水日期,BB$6),2)) | BC13: =IF(OR($A13="",BC$6=""),"",ROUND(SUMIFS(流水收入,流水账户,$A13,流水日期,BC$6),2)) | BD13: =IF(OR($A13="",BD$6=""),"",ROUND(SUMIFS(流水支出,流水账户,$A13,流水日期,BD$6),2)) | BE13: =IF(OR($A13="",BE$6=""),"",ROUND(SUMIFS(流水收入,流水账户,$A13,流水日期,BE$6),2)) | BF13: =IF(OR($A13="",BF$6=""),"",ROUND(SUMIFS(流水支出,流水账户,$A13,流水日期,BF$6),2)) | BG13: =IF(OR($A13="",BG$6=""),"",ROUND(SUMIFS(流水收入,流水账户,$A13,流水日期,BG$6),2)) | BH13: =IF(OR($A13="",BH$6=""),"",ROUND(SUMIFS(流水支出,流水账户,$A13,流水日期,BH$6),2)) | BI13: =IF(OR($A13="",BI$6=""),"",ROUND(SUMIFS(流水收入,流水账户,$A13,流水日期,BI$6),2)) | BJ13: =IF(OR($A13="",BJ$6=""),"",ROUND(SUMIFS(流水支出,流水账户,$A13,流水日期,BJ$6),2)) | BK13: =IF(OR($A13="",BK$6=""),"",ROUND(SUMIFS(流水收入,流水账户,$A13,流水日期,BK$6),2)) | BL13: =IF(OR($A13="",BL$6=""),"",ROUND(SUMIFS(流水支出,流水账户,$A13,流水日期,BL$6),2)) | BM13: =IF($A13="","",ROUND(SUMIF($C$7:$BL$7,"收款",C13:BL13),2)) | BN13: =IF($A13="","",ROUND(SUMIF($C$7:$BL$7,"付款",C13:BL13),2)) | BO13: =IF($A13="","",ROUND(N($B13)+N(BM13)-N(BN13),2))
A14: =IF(基础资料!$B$11="","",基础资料!$B$11) | B14: =IF(OR($A14="",NOT(ISNUMBER($H$3))),"",ROUND(SUMIF(账户表,$A14,账户期初)+SUMIFS(流水收入,流水账户,$A14,流水日期,"<"&$B$3)-SUMIFS(流水支出,流水账户,$A14,流水日期,"<"&$B$3),2)) | C14: =IF(OR($A14="",C$6=""),"",ROUND(SUMIFS(流水收入,流水账户,$A14,流水日期,C$6),2)) | D14: =IF(OR($A14="",D$6=""),"",ROUND(SUMIFS(流水支出,流水账户,$A14,流水日期,D$6),2)) | E14: =IF(OR($A14="",E$6=""),"",ROUND(SUMIFS(流水收入,流水账户,$A14,流水日期,E$6),2)) | F14: =IF(OR($A14="",F$6=""),"",ROUND(SUMIFS(流水支出,流水账户,$A14,流水日期,F$6),2)) | G14: =IF(OR($A14="",G$6=""),"",ROUND(SUMIFS(流水收入,流水账户,$A14,流水日期,G$6),2)) | H14: =IF(OR($A14="",H$6=""),"",ROUND(SUMIFS(流水支出,流水账户,$A14,流水日期,H$6),2)) | I14: =IF(OR($A14="",I$6=""),"",ROUND(SUMIFS(流水收入,流水账户,$A14,流水日期,I$6),2)) | J14: =IF(OR($A14="",J$6=""),"",ROUND(SUMIFS(流水支出,流水账户,$A14,流水日期,J$6),2)) | K14: =IF(OR($A14="",K$6=""),"",ROUND(SUMIFS(流水收入,流水账户,$A14,流水日期,K$6),2)) | L14: =IF(OR($A14="",L$6=""),"",ROUND(SUMIFS(流水支出,流水账户,$A14,流水日期,L$6),2)) | M14: =IF(OR($A14="",M$6=""),"",ROUND(SUMIFS(流水收入,流水账户,$A14,流水日期,M$6),2)) | N14: =IF(OR($A14="",N$6=""),"",ROUND(SUMIFS(流水支出,流水账户,$A14,流水日期,N$6),2)) | O14: =IF(OR($A14="",O$6=""),"",ROUND(SUMIFS(流水收入,流水账户,$A14,流水日期,O$6),2)) | P14: =IF(OR($A14="",P$6=""),"",ROUND(SUMIFS(流水支出,流水账户,$A14,流水日期,P$6),2)) | Q14: =IF(OR($A14="",Q$6=""),"",ROUND(SUMIFS(流水收入,流水账户,$A14,流水日期,Q$6),2)) | R14: =IF(OR($A14="",R$6=""),"",ROUND(SUMIFS(流水支出,流水账户,$A14,流水日期,R$6),2)) | S14: =IF(OR($A14="",S$6=""),"",ROUND(SUMIFS(流水收入,流水账户,$A14,流水日期,S$6),2)) | T14: =IF(OR($A14="",T$6=""),"",ROUND(SUMIFS(流水支出,流水账户,$A14,流水日期,T$6),2)) | U14: =IF(OR($A14="",U$6=""),"",ROUND(SUMIFS(流水收入,流水账户,$A14,流水日期,U$6),2)) | V14: =IF(OR($A14="",V$6=""),"",ROUND(SUMIFS(流水支出,流水账户,$A14,流水日期,V$6),2)) | W14: =IF(OR($A14="",W$6=""),"",ROUND(SUMIFS(流水收入,流水账户,$A14,流水日期,W$6),2)) | X14: =IF(OR($A14="",X$6=""),"",ROUND(SUMIFS(流水支出,流水账户,$A14,流水日期,X$6),2)) | Y14: =IF(OR($A14="",Y$6=""),"",ROUND(SUMIFS(流水收入,流水账户,$A14,流水日期,Y$6),2)) | Z14: =IF(OR($A14="",Z$6=""),"",ROUND(SUMIFS(流水支出,流水账户,$A14,流水日期,Z$6),2)) | AA14: =IF(OR($A14="",AA$6=""),"",ROUND(SUMIFS(流水收入,流水账户,$A14,流水日期,AA$6),2)) | AB14: =IF(OR($A14="",AB$6=""),"",ROUND(SUMIFS(流水支出,流水账户,$A14,流水日期,AB$6),2)) | AC14: =IF(OR($A14="",AC$6=""),"",ROUND(SUMIFS(流水收入,流水账户,$A14,流水日期,AC$6),2)) | AD14: =IF(OR($A14="",AD$6=""),"",ROUND(SUMIFS(流水支出,流水账户,$A14,流水日期,AD$6),2)) | AE14: =IF(OR($A14="",AE$6=""),"",ROUND(SUMIFS(流水收入,流水账户,$A14,流水日期,AE$6),2)) | AF14: =IF(OR($A14="",AF$6=""),"",ROUND(SUMIFS(流水支出,流水账户,$A14,流水日期,AF$6),2)) | AG14: =IF(OR($A14="",AG$6=""),"",ROUND(SUMIFS(流水收入,流水账户,$A14,流水日期,AG$6),2)) | AH14: =IF(OR($A14="",AH$6=""),"",ROUND(SUMIFS(流水支出,流水账户,$A14,流水日期,AH$6),2)) | AI14: =IF(OR($A14="",AI$6=""),"",ROUND(SUMIFS(流水收入,流水账户,$A14,流水日期,AI$6),2)) | AJ14: =IF(OR($A14="",AJ$6=""),"",ROUND(SUMIFS(流水支出,流水账户,$A14,流水日期,AJ$6),2)) | AK14: =IF(OR($A14="",AK$6=""),"",ROUND(SUMIFS(流水收入,流水账户,$A14,流水日期,AK$6),2)) | AL14: =IF(OR($A14="",AL$6=""),"",ROUND(SUMIFS(流水支出,流水账户,$A14,流水日期,AL$6),2)) | AM14: =IF(OR($A14="",AM$6=""),"",ROUND(SUMIFS(流水收入,流水账户,$A14,流水日期,AM$6),2)) | AN14: =IF(OR($A14="",AN$6=""),"",ROUND(SUMIFS(流水支出,流水账户,$A14,流水日期,AN$6),2)) | AO14: =IF(OR($A14="",AO$6=""),"",ROUND(SUMIFS(流水收入,流水账户,$A14,流水日期,AO$6),2)) | AP14: =IF(OR($A14="",AP$6=""),"",ROUND(SUMIFS(流水支出,流水账户,$A14,流水日期,AP$6),2)) | AQ14: =IF(OR($A14="",AQ$6=""),"",ROUND(SUMIFS(流水收入,流水账户,$A14,流水日期,AQ$6),2)) | AR14: =IF(OR($A14="",AR$6=""),"",ROUND(SUMIFS(流水支出,流水账户,$A14,流水日期,AR$6),2)) | AS14: =IF(OR($A14="",AS$6=""),"",ROUND(SUMIFS(流水收入,流水账户,$A14,流水日期,AS$6),2)) | AT14: =IF(OR($A14="",AT$6=""),"",ROUND(SUMIFS(流水支出,流水账户,$A14,流水日期,AT$6),2)) | AU14: =IF(OR($A14="",AU$6=""),"",ROUND(SUMIFS(流水收入,流水账户,$A14,流水日期,AU$6),2)) | AV14: =IF(OR($A14="",AV$6=""),"",ROUND(SUMIFS(流水支出,流水账户,$A14,流水日期,AV$6),2)) | AW14: =IF(OR($A14="",AW$6=""),"",ROUND(SUMIFS(流水收入,流水账户,$A14,流水日期,AW$6),2)) | AX14: =IF(OR($A14="",AX$6=""),"",ROUND(SUMIFS(流水支出,流水账户,$A14,流水日期,AX$6),2)) | AY14: =IF(OR($A14="",AY$6=""),"",ROUND(SUMIFS(流水收入,流水账户,$A14,流水日期,AY$6),2)) | AZ14: =IF(OR($A14="",AZ$6=""),"",ROUND(SUMIFS(流水支出,流水账户,$A14,流水日期,AZ$6),2)) | BA14: =IF(OR($A14="",BA$6=""),"",ROUND(SUMIFS(流水收入,流水账户,$A14,流水日期,BA$6),2)) | BB14: =IF(OR($A14="",BB$6=""),"",ROUND(SUMIFS(流水支出,流水账户,$A14,流水日期,BB$6),2)) | BC14: =IF(OR($A14="",BC$6=""),"",ROUND(SUMIFS(流水收入,流水账户,$A14,流水日期,BC$6),2)) | BD14: =IF(OR($A14="",BD$6=""),"",ROUND(SUMIFS(流水支出,流水账户,$A14,流水日期,BD$6),2)) | BE14: =IF(OR($A14="",BE$6=""),"",ROUND(SUMIFS(流水收入,流水账户,$A14,流水日期,BE$6),2)) | BF14: =IF(OR($A14="",BF$6=""),"",ROUND(SUMIFS(流水支出,流水账户,$A14,流水日期,BF$6),2)) | BG14: =IF(OR($A14="",BG$6=""),"",ROUND(SUMIFS(流水收入,流水账户,$A14,流水日期,BG$6),2)) | BH14: =IF(OR($A14="",BH$6=""),"",ROUND(SUMIFS(流水支出,流水账户,$A14,流水日期,BH$6),2)) | BI14: =IF(OR($A14="",BI$6=""),"",ROUND(SUMIFS(流水收入,流水账户,$A14,流水日期,BI$6),2)) | BJ14: =IF(OR($A14="",BJ$6=""),"",ROUND(SUMIFS(流水支出,流水账户,$A14,流水日期,BJ$6),2)) | BK14: =IF(OR($A14="",BK$6=""),"",ROUND(SUMIFS(流水收入,流水账户,$A14,流水日期,BK$6),2)) | BL14: =IF(OR($A14="",BL$6=""),"",ROUND(SUMIFS(流水支出,流水账户,$A14,流水日期,BL$6),2)) | BM14: =IF($A14="","",ROUND(SUMIF($C$7:$BL$7,"收款",C14:BL14),2)) | BN14: =IF($A14="","",ROUND(SUMIF($C$7:$BL$7,"付款",C14:BL14),2)) | BO14: =IF($A14="","",ROUND(N($B14)+N(BM14)-N(BN14),2))
A15: =IF(基础资料!$B$12="","",基础资料!$B$12) | B15: =IF(OR($A15="",NOT(ISNUMBER($H$3))),"",ROUND(SUMIF(账户表,$A15,账户期初)+SUMIFS(流水收入,流水账户,$A15,流水日期,"<"&$B$3)-SUMIFS(流水支出,流水账户,$A15,流水日期,"<"&$B$3),2)) | C15: =IF(OR($A15="",C$6=""),"",ROUND(SUMIFS(流水收入,流水账户,$A15,流水日期,C$6),2)) | D15: =IF(OR($A15="",D$6=""),"",ROUND(SUMIFS(流水支出,流水账户,$A15,流水日期,D$6),2)) | E15: =IF(OR($A15="",E$6=""),"",ROUND(SUMIFS(流水收入,流水账户,$A15,流水日期,E$6),2)) | F15: =IF(OR($A15="",F$6=""),"",ROUND(SUMIFS(流水支出,流水账户,$A15,流水日期,F$6),2)) | G15: =IF(OR($A15="",G$6=""),"",ROUND(SUMIFS(流水收入,流水账户,$A15,流水日期,G$6),2)) | H15: =IF(OR($A15="",H$6=""),"",ROUND(SUMIFS(流水支出,流水账户,$A15,流水日期,H$6),2)) | I15: =IF(OR($A15="",I$6=""),"",ROUND(SUMIFS(流水收入,流水账户,$A15,流水日期,I$6),2)) | J15: =IF(OR($A15="",J$6=""),"",ROUND(SUMIFS(流水支出,流水账户,$A15,流水日期,J$6),2)) | K15: =IF(OR($A15="",K$6=""),"",ROUND(SUMIFS(流水收入,流水账户,$A15,流水日期,K$6),2)) | L15: =IF(OR($A15="",L$6=""),"",ROUND(SUMIFS(流水支出,流水账户,$A15,流水日期,L$6),2)) | M15: =IF(OR($A15="",M$6=""),"",ROUND(SUMIFS(流水收入,流水账户,$A15,流水日期,M$6),2)) | N15: =IF(OR($A15="",N$6=""),"",ROUND(SUMIFS(流水支出,流水账户,$A15,流水日期,N$6),2)) | O15: =IF(OR($A15="",O$6=""),"",ROUND(SUMIFS(流水收入,流水账户,$A15,流水日期,O$6),2)) | P15: =IF(OR($A15="",P$6=""),"",ROUND(SUMIFS(流水支出,流水账户,$A15,流水日期,P$6),2)) | Q15: =IF(OR($A15="",Q$6=""),"",ROUND(SUMIFS(流水收入,流水账户,$A15,流水日期,Q$6),2)) | R15: =IF(OR($A15="",R$6=""),"",ROUND(SUMIFS(流水支出,流水账户,$A15,流水日期,R$6),2)) | S15: =IF(OR($A15="",S$6=""),"",ROUND(SUMIFS(流水收入,流水账户,$A15,流水日期,S$6),2)) | T15: =IF(OR($A15="",T$6=""),"",ROUND(SUMIFS(流水支出,流水账户,$A15,流水日期,T$6),2)) | U15: =IF(OR($A15="",U$6=""),"",ROUND(SUMIFS(流水收入,流水账户,$A15,流水日期,U$6),2)) | V15: =IF(OR($A15="",V$6=""),"",ROUND(SUMIFS(流水支出,流水账户,$A15,流水日期,V$6),2)) | W15: =IF(OR($A15="",W$6=""),"",ROUND(SUMIFS(流水收入,流水账户,$A15,流水日期,W$6),2)) | X15: =IF(OR($A15="",X$6=""),"",ROUND(SUMIFS(流水支出,流水账户,$A15,流水日期,X$6),2)) | Y15: =IF(OR($A15="",Y$6=""),"",ROUND(SUMIFS(流水收入,流水账户,$A15,流水日期,Y$6),2)) | Z15: =IF(OR($A15="",Z$6=""),"",ROUND(SUMIFS(流水支出,流水账户,$A15,流水日期,Z$6),2)) | AA15: =IF(OR($A15="",AA$6=""),"",ROUND(SUMIFS(流水收入,流水账户,$A15,流水日期,AA$6),2)) | AB15: =IF(OR($A15="",AB$6=""),"",ROUND(SUMIFS(流水支出,流水账户,$A15,流水日期,AB$6),2)) | AC15: =IF(OR($A15="",AC$6=""),"",ROUND(SUMIFS(流水收入,流水账户,$A15,流水日期,AC$6),2)) | AD15: =IF(OR($A15="",AD$6=""),"",ROUND(SUMIFS(流水支出,流水账户,$A15,流水日期,AD$6),2)) | AE15: =IF(OR($A15="",AE$6=""),"",ROUND(SUMIFS(流水收入,流水账户,$A15,流水日期,AE$6),2)) | AF15: =IF(OR($A15="",AF$6=""),"",ROUND(SUMIFS(流水支出,流水账户,$A15,流水日期,AF$6),2)) | AG15: =IF(OR($A15="",AG$6=""),"",ROUND(SUMIFS(流水收入,流水账户,$A15,流水日期,AG$6),2)) | AH15: =IF(OR($A15="",AH$6=""),"",ROUND(SUMIFS(流水支出,流水账户,$A15,流水日期,AH$6),2)) | AI15: =IF(OR($A15="",AI$6=""),"",ROUND(SUMIFS(流水收入,流水账户,$A15,流水日期,AI$6),2)) | AJ15: =IF(OR($A15="",AJ$6=""),"",ROUND(SUMIFS(流水支出,流水账户,$A15,流水日期,AJ$6),2)) | AK15: =IF(OR($A15="",AK$6=""),"",ROUND(SUMIFS(流水收入,流水账户,$A15,流水日期,AK$6),2)) | AL15: =IF(OR($A15="",AL$6=""),"",ROUND(SUMIFS(流水支出,流水账户,$A15,流水日期,AL$6),2)) | AM15: =IF(OR($A15="",AM$6=""),"",ROUND(SUMIFS(流水收入,流水账户,$A15,流水日期,AM$6),2)) | AN15: =IF(OR($A15="",AN$6=""),"",ROUND(SUMIFS(流水支出,流水账户,$A15,流水日期,AN$6),2)) | AO15: =IF(OR($A15="",AO$6=""),"",ROUND(SUMIFS(流水收入,流水账户,$A15,流水日期,AO$6),2)) | AP15: =IF(OR($A15="",AP$6=""),"",ROUND(SUMIFS(流水支出,流水账户,$A15,流水日期,AP$6),2)) | AQ15: =IF(OR($A15="",AQ$6=""),"",ROUND(SUMIFS(流水收入,流水账户,$A15,流水日期,AQ$6),2)) | AR15: =IF(OR($A15="",AR$6=""),"",ROUND(SUMIFS(流水支出,流水账户,$A15,流水日期,AR$6),2)) | AS15: =IF(OR($A15="",AS$6=""),"",ROUND(SUMIFS(流水收入,流水账户,$A15,流水日期,AS$6),2)) | AT15: =IF(OR($A15="",AT$6=""),"",ROUND(SUMIFS(流水支出,流水账户,$A15,流水日期,AT$6),2)) | AU15: =IF(OR($A15="",AU$6=""),"",ROUND(SUMIFS(流水收入,流水账户,$A15,流水日期,AU$6),2)) | AV15: =IF(OR($A15="",AV$6=""),"",ROUND(SUMIFS(流水支出,流水账户,$A15,流水日期,AV$6),2)) | AW15: =IF(OR($A15="",AW$6=""),"",ROUND(SUMIFS(流水收入,流水账户,$A15,流水日期,AW$6),2)) | AX15: =IF(OR($A15="",AX$6=""),"",ROUND(SUMIFS(流水支出,流水账户,$A15,流水日期,AX$6),2)) | AY15: =IF(OR($A15="",AY$6=""),"",ROUND(SUMIFS(流水收入,流水账户,$A15,流水日期,AY$6),2)) | AZ15: =IF(OR($A15="",AZ$6=""),"",ROUND(SUMIFS(流水支出,流水账户,$A15,流水日期,AZ$6),2)) | BA15: =IF(OR($A15="",BA$6=""),"",ROUND(SUMIFS(流水收入,流水账户,$A15,流水日期,BA$6),2)) | BB15: =IF(OR($A15="",BB$6=""),"",ROUND(SUMIFS(流水支出,流水账户,$A15,流水日期,BB$6),2)) | BC15: =IF(OR($A15="",BC$6=""),"",ROUND(SUMIFS(流水收入,流水账户,$A15,流水日期,BC$6),2)) | BD15: =IF(OR($A15="",BD$6=""),"",ROUND(SUMIFS(流水支出,流水账户,$A15,流水日期,BD$6),2)) | BE15: =IF(OR($A15="",BE$6=""),"",ROUND(SUMIFS(流水收入,流水账户,$A15,流水日期,BE$6),2)) | BF15: =IF(OR($A15="",BF$6=""),"",ROUND(SUMIFS(流水支出,流水账户,$A15,流水日期,BF$6),2)) | BG15: =IF(OR($A15="",BG$6=""),"",ROUND(SUMIFS(流水收入,流水账户,$A15,流水日期,BG$6),2)) | BH15: =IF(OR($A15="",BH$6=""),"",ROUND(SUMIFS(流水支出,流水账户,$A15,流水日期,BH$6),2)) | BI15: =IF(OR($A15="",BI$6=""),"",ROUND(SUMIFS(流水收入,流水账户,$A15,流水日期,BI$6),2)) | BJ15: =IF(OR($A15="",BJ$6=""),"",ROUND(SUMIFS(流水支出,流水账户,$A15,流水日期,BJ$6),2)) | BK15: =IF(OR($A15="",BK$6=""),"",ROUND(SUMIFS(流水收入,流水账户,$A15,流水日期,BK$6),2)) | BL15: =IF(OR($A15="",BL$6=""),"",ROUND(SUMIFS(流水支出,流水账户,$A15,流水日期,BL$6),2)) | BM15: =IF($A15="","",ROUND(SUMIF($C$7:$BL$7,"收款",C15:BL15),2)) | BN15: =IF($A15="","",ROUND(SUMIF($C$7:$BL$7,"付款",C15:BL15),2)) | BO15: =IF($A15="","",ROUND(N($B15)+N(BM15)-N(BN15),2))
A16: =IF(基础资料!$B$13="","",基础资料!$B$13) | B16: =IF(OR($A16="",NOT(ISNUMBER($H$3))),"",ROUND(SUMIF(账户表,$A16,账户期初)+SUMIFS(流水收入,流水账户,$A16,流水日期,"<"&$B$3)-SUMIFS(流水支出,流水账户,$A16,流水日期,"<"&$B$3),2)) | C16: =IF(OR($A16="",C$6=""),"",ROUND(SUMIFS(流水收入,流水账户,$A16,流水日期,C$6),2)) | D16: =IF(OR($A16="",D$6=""),"",ROUND(SUMIFS(流水支出,流水账户,$A16,流水日期,D$6),2)) | E16: =IF(OR($A16="",E$6=""),"",ROUND(SUMIFS(流水收入,流水账户,$A16,流水日期,E$6),2)) | F16: =IF(OR($A16="",F$6=""),"",ROUND(SUMIFS(流水支出,流水账户,$A16,流水日期,F$6),2)) | G16: =IF(OR($A16="",G$6=""),"",ROUND(SUMIFS(流水收入,流水账户,$A16,流水日期,G$6),2)) | H16: =IF(OR($A16="",H$6=""),"",ROUND(SUMIFS(流水支出,流水账户,$A16,流水日期,H$6),2)) | I16: =IF(OR($A16="",I$6=""),"",ROUND(SUMIFS(流水收入,流水账户,$A16,流水日期,I$6),2)) | J16: =IF(OR($A16="",J$6=""),"",ROUND(SUMIFS(流水支出,流水账户,$A16,流水日期,J$6),2)) | K16: =IF(OR($A16="",K$6=""),"",ROUND(SUMIFS(流水收入,流水账户,$A16,流水日期,K$6),2)) | L16: =IF(OR($A16="",L$6=""),"",ROUND(SUMIFS(流水支出,流水账户,$A16,流水日期,L$6),2)) | M16: =IF(OR($A16="",M$6=""),"",ROUND(SUMIFS(流水收入,流水账户,$A16,流水日期,M$6),2)) | N16: =IF(OR($A16="",N$6=""),"",ROUND(SUMIFS(流水支出,流水账户,$A16,流水日期,N$6),2)) | O16: =IF(OR($A16="",O$6=""),"",ROUND(SUMIFS(流水收入,流水账户,$A16,流水日期,O$6),2)) | P16: =IF(OR($A16="",P$6=""),"",ROUND(SUMIFS(流水支出,流水账户,$A16,流水日期,P$6),2)) | Q16: =IF(OR($A16="",Q$6=""),"",ROUND(SUMIFS(流水收入,流水账户,$A16,流水日期,Q$6),2)) | R16: =IF(OR($A16="",R$6=""),"",ROUND(SUMIFS(流水支出,流水账户,$A16,流水日期,R$6),2)) | S16: =IF(OR($A16="",S$6=""),"",ROUND(SUMIFS(流水收入,流水账户,$A16,流水日期,S$6),2)) | T16: =IF(OR($A16="",T$6=""),"",ROUND(SUMIFS(流水支出,流水账户,$A16,流水日期,T$6),2)) | U16: =IF(OR($A16="",U$6=""),"",ROUND(SUMIFS(流水收入,流水账户,$A16,流水日期,U$6),2)) | V16: =IF(OR($A16="",V$6=""),"",ROUND(SUMIFS(流水支出,流水账户,$A16,流水日期,V$6),2)) | W16: =IF(OR($A16="",W$6=""),"",ROUND(SUMIFS(流水收入,流水账户,$A16,流水日期,W$6),2)) | X16: =IF(OR($A16="",X$6=""),"",ROUND(SUMIFS(流水支出,流水账户,$A16,流水日期,X$6),2)) | Y16: =IF(OR($A16="",Y$6=""),"",ROUND(SUMIFS(流水收入,流水账户,$A16,流水日期,Y$6),2)) | Z16: =IF(OR($A16="",Z$6=""),"",ROUND(SUMIFS(流水支出,流水账户,$A16,流水日期,Z$6),2)) | AA16: =IF(OR($A16="",AA$6=""),"",ROUND(SUMIFS(流水收入,流水账户,$A16,流水日期,AA$6),2)) | AB16: =IF(OR($A16="",AB$6=""),"",ROUND(SUMIFS(流水支出,流水账户,$A16,流水日期,AB$6),2)) | AC16: =IF(OR($A16="",AC$6=""),"",ROUND(SUMIFS(流水收入,流水账户,$A16,流水日期,AC$6),2)) | AD16: =IF(OR($A16="",AD$6=""),"",ROUND(SUMIFS(流水支出,流水账户,$A16,流水日期,AD$6),2)) | AE16: =IF(OR($A16="",AE$6=""),"",ROUND(SUMIFS(流水收入,流水账户,$A16,流水日期,AE$6),2)) | AF16: =IF(OR($A16="",AF$6=""),"",ROUND(SUMIFS(流水支出,流水账户,$A16,流水日期,AF$6),2)) | AG16: =IF(OR($A16="",AG$6=""),"",ROUND(SUMIFS(流水收入,流水账户,$A16,流水日期,AG$6),2)) | AH16: =IF(OR($A16="",AH$6=""),"",ROUND(SUMIFS(流水支出,流水账户,$A16,流水日期,AH$6),2)) | AI16: =IF(OR($A16="",AI$6=""),"",ROUND(SUMIFS(流水收入,流水账户,$A16,流水日期,AI$6),2)) | AJ16: =IF(OR($A16="",AJ$6=""),"",ROUND(SUMIFS(流水支出,流水账户,$A16,流水日期,AJ$6),2)) | AK16: =IF(OR($A16="",AK$6=""),"",ROUND(SUMIFS(流水收入,流水账户,$A16,流水日期,AK$6),2)) | AL16: =IF(OR($A16="",AL$6=""),"",ROUND(SUMIFS(流水支出,流水账户,$A16,流水日期,AL$6),2)) | AM16: =IF(OR($A16="",AM$6=""),"",ROUND(SUMIFS(流水收入,流水账户,$A16,流水日期,AM$6),2)) | AN16: =IF(OR($A16="",AN$6=""),"",ROUND(SUMIFS(流水支出,流水账户,$A16,流水日期,AN$6),2)) | AO16: =IF(OR($A16="",AO$6=""),"",ROUND(SUMIFS(流水收入,流水账户,$A16,流水日期,AO$6),2)) | AP16: =IF(OR($A16="",AP$6=""),"",ROUND(SUMIFS(流水支出,流水账户,$A16,流水日期,AP$6),2)) | AQ16: =IF(OR($A16="",AQ$6=""),"",ROUND(SUMIFS(流水收入,流水账户,$A16,流水日期,AQ$6),2)) | AR16: =IF(OR($A16="",AR$6=""),"",ROUND(SUMIFS(流水支出,流水账户,$A16,流水日期,AR$6),2)) | AS16: =IF(OR($A16="",AS$6=""),"",ROUND(SUMIFS(流水收入,流水账户,$A16,流水日期,AS$6),2)) | AT16: =IF(OR($A16="",AT$6=""),"",ROUND(SUMIFS(流水支出,流水账户,$A16,流水日期,AT$6),2)) | AU16: =IF(OR($A16="",AU$6=""),"",ROUND(SUMIFS(流水收入,流水账户,$A16,流水日期,AU$6),2)) | AV16: =IF(OR($A16="",AV$6=""),"",ROUND(SUMIFS(流水支出,流水账户,$A16,流水日期,AV$6),2)) | AW16: =IF(OR($A16="",AW$6=""),"",ROUND(SUMIFS(流水收入,流水账户,$A16,流水日期,AW$6),2)) | AX16: =IF(OR($A16="",AX$6=""),"",ROUND(SUMIFS(流水支出,流水账户,$A16,流水日期,AX$6),2)) | AY16: =IF(OR($A16="",AY$6=""),"",ROUND(SUMIFS(流水收入,流水账户,$A16,流水日期,AY$6),2)) | AZ16: =IF(OR($A16="",AZ$6=""),"",ROUND(SUMIFS(流水支出,流水账户,$A16,流水日期,AZ$6),2)) | BA16: =IF(OR($A16="",BA$6=""),"",ROUND(SUMIFS(流水收入,流水账户,$A16,流水日期,BA$6),2)) | BB16: =IF(OR($A16="",BB$6=""),"",ROUND(SUMIFS(流水支出,流水账户,$A16,流水日期,BB$6),2)) | BC16: =IF(OR($A16="",BC$6=""),"",ROUND(SUMIFS(流水收入,流水账户,$A16,流水日期,BC$6),2)) | BD16: =IF(OR($A16="",BD$6=""),"",ROUND(SUMIFS(流水支出,流水账户,$A16,流水日期,BD$6),2)) | BE16: =IF(OR($A16="",BE$6=""),"",ROUND(SUMIFS(流水收入,流水账户,$A16,流水日期,BE$6),2)) | BF16: =IF(OR($A16="",BF$6=""),"",ROUND(SUMIFS(流水支出,流水账户,$A16,流水日期,BF$6),2)) | BG16: =IF(OR($A16="",BG$6=""),"",ROUND(SUMIFS(流水收入,流水账户,$A16,流水日期,BG$6),2)) | BH16: =IF(OR($A16="",BH$6=""),"",ROUND(SUMIFS(流水支出,流水账户,$A16,流水日期,BH$6),2)) | BI16: =IF(OR($A16="",BI$6=""),"",ROUND(SUMIFS(流水收入,流水账户,$A16,流水日期,BI$6),2)) | BJ16: =IF(OR($A16="",BJ$6=""),"",ROUND(SUMIFS(流水支出,流水账户,$A16,流水日期,BJ$6),2)) | BK16: =IF(OR($A16="",BK$6=""),"",ROUND(SUMIFS(流水收入,流水账户,$A16,流水日期,BK$6),2)) | BL16: =IF(OR($A16="",BL$6=""),"",ROUND(SUMIFS(流水支出,流水账户,$A16,流水日期,BL$6),2)) | BM16: =IF($A16="","",ROUND(SUMIF($C$7:$BL$7,"收款",C16:BL16),2)) | BN16: =IF($A16="","",ROUND(SUMIF($C$7:$BL$7,"付款",C16:BL16),2)) | BO16: =IF($A16="","",ROUND(N($B16)+N(BM16)-N(BN16),2))
A17: =IF(基础资料!$B$14="","",基础资料!$B$14) | B17: =IF(OR($A17="",NOT(ISNUMBER($H$3))),"",ROUND(SUMIF(账户表,$A17,账户期初)+SUMIFS(流水收入,流水账户,$A17,流水日期,"<"&$B$3)-SUMIFS(流水支出,流水账户,$A17,流水日期,"<"&$B$3),2)) | C17: =IF(OR($A17="",C$6=""),"",ROUND(SUMIFS(流水收入,流水账户,$A17,流水日期,C$6),2)) | D17: =IF(OR($A17="",D$6=""),"",ROUND(SUMIFS(流水支出,流水账户,$A17,流水日期,D$6),2)) | E17: =IF(OR($A17="",E$6=""),"",ROUND(SUMIFS(流水收入,流水账户,$A17,流水日期,E$6),2)) | F17: =IF(OR($A17="",F$6=""),"",ROUND(SUMIFS(流水支出,流水账户,$A17,流水日期,F$6),2)) | G17: =IF(OR($A17="",G$6=""),"",ROUND(SUMIFS(流水收入,流水账户,$A17,流水日期,G$6),2)) | H17: =IF(OR($A17="",H$6=""),"",ROUND(SUMIFS(流水支出,流水账户,$A17,流水日期,H$6),2)) | I17: =IF(OR($A17="",I$6=""),"",ROUND(SUMIFS(流水收入,流水账户,$A17,流水日期,I$6),2)) | J17: =IF(OR($A17="",J$6=""),"",ROUND(SUMIFS(流水支出,流水账户,$A17,流水日期,J$6),2)) | K17: =IF(OR($A17="",K$6=""),"",ROUND(SUMIFS(流水收入,流水账户,$A17,流水日期,K$6),2)) | L17: =IF(OR($A17="",L$6=""),"",ROUND(SUMIFS(流水支出,流水账户,$A17,流水日期,L$6),2)) | M17: =IF(OR($A17="",M$6=""),"",ROUND(SUMIFS(流水收入,流水账户,$A17,流水日期,M$6),2)) | N17: =IF(OR($A17="",N$6=""),"",ROUND(SUMIFS(流水支出,流水账户,$A17,流水日期,N$6),2)) | O17: =IF(OR($A17="",O$6=""),"",ROUND(SUMIFS(流水收入,流水账户,$A17,流水日期,O$6),2)) | P17: =IF(OR($A17="",P$6=""),"",ROUND(SUMIFS(流水支出,流水账户,$A17,流水日期,P$6),2)) | Q17: =IF(OR($A17="",Q$6=""),"",ROUND(SUMIFS(流水收入,流水账户,$A17,流水日期,Q$6),2)) | R17: =IF(OR($A17="",R$6=""),"",ROUND(SUMIFS(流水支出,流水账户,$A17,流水日期,R$6),2)) | S17: =IF(OR($A17="",S$6=""),"",ROUND(SUMIFS(流水收入,流水账户,$A17,流水日期,S$6),2)) | T17: =IF(OR($A17="",T$6=""),"",ROUND(SUMIFS(流水支出,流水账户,$A17,流水日期,T$6),2)) | U17: =IF(OR($A17="",U$6=""),"",ROUND(SUMIFS(流水收入,流水账户,$A17,流水日期,U$6),2)) | V17: =IF(OR($A17="",V$6=""),"",ROUND(SUMIFS(流水支出,流水账户,$A17,流水日期,V$6),2)) | W17: =IF(OR($A17="",W$6=""),"",ROUND(SUMIFS(流水收入,流水账户,$A17,流水日期,W$6),2)) | X17: =IF(OR($A17="",X$6=""),"",ROUND(SUMIFS(流水支出,流水账户,$A17,流水日期,X$6),2)) | Y17: =IF(OR($A17="",Y$6=""),"",ROUND(SUMIFS(流水收入,流水账户,$A17,流水日期,Y$6),2)) | Z17: =IF(OR($A17="",Z$6=""),"",ROUND(SUMIFS(流水支出,流水账户,$A17,流水日期,Z$6),2)) | AA17: =IF(OR($A17="",AA$6=""),"",ROUND(SUMIFS(流水收入,流水账户,$A17,流水日期,AA$6),2)) | AB17: =IF(OR($A17="",AB$6=""),"",ROUND(SUMIFS(流水支出,流水账户,$A17,流水日期,AB$6),2)) | AC17: =IF(OR($A17="",AC$6=""),"",ROUND(SUMIFS(流水收入,流水账户,$A17,流水日期,AC$6),2)) | AD17: =IF(OR($A17="",AD$6=""),"",ROUND(SUMIFS(流水支出,流水账户,$A17,流水日期,AD$6),2)) | AE17: =IF(OR($A17="",AE$6=""),"",ROUND(SUMIFS(流水收入,流水账户,$A17,流水日期,AE$6),2)) | AF17: =IF(OR($A17="",AF$6=""),"",ROUND(SUMIFS(流水支出,流水账户,$A17,流水日期,AF$6),2)) | AG17: =IF(OR($A17="",AG$6=""),"",ROUND(SUMIFS(流水收入,流水账户,$A17,流水日期,AG$6),2)) | AH17: =IF(OR($A17="",AH$6=""),"",ROUND(SUMIFS(流水支出,流水账户,$A17,流水日期,AH$6),2)) | AI17: =IF(OR($A17="",AI$6=""),"",ROUND(SUMIFS(流水收入,流水账户,$A17,流水日期,AI$6),2)) | AJ17: =IF(OR($A17="",AJ$6=""),"",ROUND(SUMIFS(流水支出,流水账户,$A17,流水日期,AJ$6),2)) | AK17: =IF(OR($A17="",AK$6=""),"",ROUND(SUMIFS(流水收入,流水账户,$A17,流水日期,AK$6),2)) | AL17: =IF(OR($A17="",AL$6=""),"",ROUND(SUMIFS(流水支出,流水账户,$A17,流水日期,AL$6),2)) | AM17: =IF(OR($A17="",AM$6=""),"",ROUND(SUMIFS(流水收入,流水账户,$A17,流水日期,AM$6),2)) | AN17: =IF(OR($A17="",AN$6=""),"",ROUND(SUMIFS(流水支出,流水账户,$A17,流水日期,AN$6),2)) | AO17: =IF(OR($A17="",AO$6=""),"",ROUND(SUMIFS(流水收入,流水账户,$A17,流水日期,AO$6),2)) | AP17: =IF(OR($A17="",AP$6=""),"",ROUND(SUMIFS(流水支出,流水账户,$A17,流水日期,AP$6),2)) | AQ17: =IF(OR($A17="",AQ$6=""),"",ROUND(SUMIFS(流水收入,流水账户,$A17,流水日期,AQ$6),2)) | AR17: =IF(OR($A17="",AR$6=""),"",ROUND(SUMIFS(流水支出,流水账户,$A17,流水日期,AR$6),2)) | AS17: =IF(OR($A17="",AS$6=""),"",ROUND(SUMIFS(流水收入,流水账户,$A17,流水日期,AS$6),2)) | AT17: =IF(OR($A17="",AT$6=""),"",ROUND(SUMIFS(流水支出,流水账户,$A17,流水日期,AT$6),2)) | AU17: =IF(OR($A17="",AU$6=""),"",ROUND(SUMIFS(流水收入,流水账户,$A17,流水日期,AU$6),2)) | AV17: =IF(OR($A17="",AV$6=""),"",ROUND(SUMIFS(流水支出,流水账户,$A17,流水日期,AV$6),2)) | AW17: =IF(OR($A17="",AW$6=""),"",ROUND(SUMIFS(流水收入,流水账户,$A17,流水日期,AW$6),2)) | AX17: =IF(OR($A17="",AX$6=""),"",ROUND(SUMIFS(流水支出,流水账户,$A17,流水日期,AX$6),2)) | AY17: =IF(OR($A17="",AY$6=""),"",ROUND(SUMIFS(流水收入,流水账户,$A17,流水日期,AY$6),2)) | AZ17: =IF(OR($A17="",AZ$6=""),"",ROUND(SUMIFS(流水支出,流水账户,$A17,流水日期,AZ$6),2)) | BA17: =IF(OR($A17="",BA$6=""),"",ROUND(SUMIFS(流水收入,流水账户,$A17,流水日期,BA$6),2)) | BB17: =IF(OR($A17="",BB$6=""),"",ROUND(SUMIFS(流水支出,流水账户,$A17,流水日期,BB$6),2)) | BC17: =IF(OR($A17="",BC$6=""),"",ROUND(SUMIFS(流水收入,流水账户,$A17,流水日期,BC$6),2)) | BD17: =IF(OR($A17="",BD$6=""),"",ROUND(SUMIFS(流水支出,流水账户,$A17,流水日期,BD$6),2)) | BE17: =IF(OR($A17="",BE$6=""),"",ROUND(SUMIFS(流水收入,流水账户,$A17,流水日期,BE$6),2)) | BF17: =IF(OR($A17="",BF$6=""),"",ROUND(SUMIFS(流水支出,流水账户,$A17,流水日期,BF$6),2)) | BG17: =IF(OR($A17="",BG$6=""),"",ROUND(SUMIFS(流水收入,流水账户,$A17,流水日期,BG$6),2)) | BH17: =IF(OR($A17="",BH$6=""),"",ROUND(SUMIFS(流水支出,流水账户,$A17,流水日期,BH$6),2)) | BI17: =IF(OR($A17="",BI$6=""),"",ROUND(SUMIFS(流水收入,流水账户,$A17,流水日期,BI$6),2)) | BJ17: =IF(OR($A17="",BJ$6=""),"",ROUND(SUMIFS(流水支出,流水账户,$A17,流水日期,BJ$6),2)) | BK17: =IF(OR($A17="",BK$6=""),"",ROUND(SUMIFS(流水收入,流水账户,$A17,流水日期,BK$6),2)) | BL17: =IF(OR($A17="",BL$6=""),"",ROUND(SUMIFS(流水支出,流水账户,$A17,流水日期,BL$6),2)) | BM17: =IF($A17="","",ROUND(SUMIF($C$7:$BL$7,"收款",C17:BL17),2)) | BN17: =IF($A17="","",ROUND(SUMIF($C$7:$BL$7,"付款",C17:BL17),2)) | BO17: =IF($A17="","",ROUND(N($B17)+N(BM17)-N(BN17),2))
A18: =IF(基础资料!$B$15="","",基础资料!$B$15) | B18: =IF(OR($A18="",NOT(ISNUMBER($H$3))),"",ROUND(SUMIF(账户表,$A18,账户期初)+SUMIFS(流水收入,流水账户,$A18,流水日期,"<"&$B$3)-SUMIFS(流水支出,流水账户,$A18,流水日期,"<"&$B$3),2)) | C18: =IF(OR($A18="",C$6=""),"",ROUND(SUMIFS(流水收入,流水账户,$A18,流水日期,C$6),2)) | D18: =IF(OR($A18="",D$6=""),"",ROUND(SUMIFS(流水支出,流水账户,$A18,流水日期,D$6),2)) | E18: =IF(OR($A18="",E$6=""),"",ROUND(SUMIFS(流水收入,流水账户,$A18,流水日期,E$6),2)) | F18: =IF(OR($A18="",F$6=""),"",ROUND(SUMIFS(流水支出,流水账户,$A18,流水日期,F$6),2)) | G18: =IF(OR($A18="",G$6=""),"",ROUND(SUMIFS(流水收入,流水账户,$A18,流水日期,G$6),2)) | H18: =IF(OR($A18="",H$6=""),"",ROUND(SUMIFS(流水支出,流水账户,$A18,流水日期,H$6),2)) | I18: =IF(OR($A18="",I$6=""),"",ROUND(SUMIFS(流水收入,流水账户,$A18,流水日期,I$6),2)) | J18: =IF(OR($A18="",J$6=""),"",ROUND(SUMIFS(流水支出,流水账户,$A18,流水日期,J$6),2)) | K18: =IF(OR($A18="",K$6=""),"",ROUND(SUMIFS(流水收入,流水账户,$A18,流水日期,K$6),2)) | L18: =IF(OR($A18="",L$6=""),"",ROUND(SUMIFS(流水支出,流水账户,$A18,流水日期,L$6),2)) | M18: =IF(OR($A18="",M$6=""),"",ROUND(SUMIFS(流水收入,流水账户,$A18,流水日期,M$6),2)) | N18: =IF(OR($A18="",N$6=""),"",ROUND(SUMIFS(流水支出,流水账户,$A18,流水日期,N$6),2)) | O18: =IF(OR($A18="",O$6=""),"",ROUND(SUMIFS(流水收入,流水账户,$A18,流水日期,O$6),2)) | P18: =IF(OR($A18="",P$6=""),"",ROUND(SUMIFS(流水支出,流水账户,$A18,流水日期,P$6),2)) | Q18: =IF(OR($A18="",Q$6=""),"",ROUND(SUMIFS(流水收入,流水账户,$A18,流水日期,Q$6),2)) | R18: =IF(OR($A18="",R$6=""),"",ROUND(SUMIFS(流水支出,流水账户,$A18,流水日期,R$6),2)) | S18: =IF(OR($A18="",S$6=""),"",ROUND(SUMIFS(流水收入,流水账户,$A18,流水日期,S$6),2)) | T18: =IF(OR($A18="",T$6=""),"",ROUND(SUMIFS(流水支出,流水账户,$A18,流水日期,T$6),2)) | U18: =IF(OR($A18="",U$6=""),"",ROUND(SUMIFS(流水收入,流水账户,$A18,流水日期,U$6),2)) | V18: =IF(OR($A18="",V$6=""),"",ROUND(SUMIFS(流水支出,流水账户,$A18,流水日期,V$6),2)) | W18: =IF(OR($A18="",W$6=""),"",ROUND(SUMIFS(流水收入,流水账户,$A18,流水日期,W$6),2)) | X18: =IF(OR($A18="",X$6=""),"",ROUND(SUMIFS(流水支出,流水账户,$A18,流水日期,X$6),2)) | Y18: =IF(OR($A18="",Y$6=""),"",ROUND(SUMIFS(流水收入,流水账户,$A18,流水日期,Y$6),2)) | Z18: =IF(OR($A18="",Z$6=""),"",ROUND(SUMIFS(流水支出,流水账户,$A18,流水日期,Z$6),2)) | AA18: =IF(OR($A18="",AA$6=""),"",ROUND(SUMIFS(流水收入,流水账户,$A18,流水日期,AA$6),2)) | AB18: =IF(OR($A18="",AB$6=""),"",ROUND(SUMIFS(流水支出,流水账户,$A18,流水日期,AB$6),2)) | AC18: =IF(OR($A18="",AC$6=""),"",ROUND(SUMIFS(流水收入,流水账户,$A18,流水日期,AC$6),2)) | AD18: =IF(OR($A18="",AD$6=""),"",ROUND(SUMIFS(流水支出,流水账户,$A18,流水日期,AD$6),2)) | AE18: =IF(OR($A18="",AE$6=""),"",ROUND(SUMIFS(流水收入,流水账户,$A18,流水日期,AE$6),2)) | AF18: =IF(OR($A18="",AF$6=""),"",ROUND(SUMIFS(流水支出,流水账户,$A18,流水日期,AF$6),2)) | AG18: =IF(OR($A18="",AG$6=""),"",ROUND(SUMIFS(流水收入,流水账户,$A18,流水日期,AG$6),2)) | AH18: =IF(OR($A18="",AH$6=""),"",ROUND(SUMIFS(流水支出,流水账户,$A18,流水日期,AH$6),2)) | AI18: =IF(OR($A18="",AI$6=""),"",ROUND(SUMIFS(流水收入,流水账户,$A18,流水日期,AI$6),2)) | AJ18: =IF(OR($A18="",AJ$6=""),"",ROUND(SUMIFS(流水支出,流水账户,$A18,流水日期,AJ$6),2)) | AK18: =IF(OR($A18="",AK$6=""),"",ROUND(SUMIFS(流水收入,流水账户,$A18,流水日期,AK$6),2)) | AL18: =IF(OR($A18="",AL$6=""),"",ROUND(SUMIFS(流水支出,流水账户,$A18,流水日期,AL$6),2)) | AM18: =IF(OR($A18="",AM$6=""),"",ROUND(SUMIFS(流水收入,流水账户,$A18,流水日期,AM$6),2)) | AN18: =IF(OR($A18="",AN$6=""),"",ROUND(SUMIFS(流水支出,流水账户,$A18,流水日期,AN$6),2)) | AO18: =IF(OR($A18="",AO$6=""),"",ROUND(SUMIFS(流水收入,流水账户,$A18,流水日期,AO$6),2)) | AP18: =IF(OR($A18="",AP$6=""),"",ROUND(SUMIFS(流水支出,流水账户,$A18,流水日期,AP$6),2)) | AQ18: =IF(OR($A18="",AQ$6=""),"",ROUND(SUMIFS(流水收入,流水账户,$A18,流水日期,AQ$6),2)) | AR18: =IF(OR($A18="",AR$6=""),"",ROUND(SUMIFS(流水支出,流水账户,$A18,流水日期,AR$6),2)) | AS18: =IF(OR($A18="",AS$6=""),"",ROUND(SUMIFS(流水收入,流水账户,$A18,流水日期,AS$6),2)) | AT18: =IF(OR($A18="",AT$6=""),"",ROUND(SUMIFS(流水支出,流水账户,$A18,流水日期,AT$6),2)) | AU18: =IF(OR($A18="",AU$6=""),"",ROUND(SUMIFS(流水收入,流水账户,$A18,流水日期,AU$6),2)) | AV18: =IF(OR($A18="",AV$6=""),"",ROUND(SUMIFS(流水支出,流水账户,$A18,流水日期,AV$6),2)) | AW18: =IF(OR($A18="",AW$6=""),"",ROUND(SUMIFS(流水收入,流水账户,$A18,流水日期,AW$6),2)) | AX18: =IF(OR($A18="",AX$6=""),"",ROUND(SUMIFS(流水支出,流水账户,$A18,流水日期,AX$6),2)) | AY18: =IF(OR($A18="",AY$6=""),"",ROUND(SUMIFS(流水收入,流水账户,$A18,流水日期,AY$6),2)) | AZ18: =IF(OR($A18="",AZ$6=""),"",ROUND(SUMIFS(流水支出,流水账户,$A18,流水日期,AZ$6),2)) | BA18: =IF(OR($A18="",BA$6=""),"",ROUND(SUMIFS(流水收入,流水账户,$A18,流水日期,BA$6),2)) | BB18: =IF(OR($A18="",BB$6=""),"",ROUND(SUMIFS(流水支出,流水账户,$A18,流水日期,BB$6),2)) | BC18: =IF(OR($A18="",BC$6=""),"",ROUND(SUMIFS(流水收入,流水账户,$A18,流水日期,BC$6),2)) | BD18: =IF(OR($A18="",BD$6=""),"",ROUND(SUMIFS(流水支出,流水账户,$A18,流水日期,BD$6),2)) | BE18: =IF(OR($A18="",BE$6=""),"",ROUND(SUMIFS(流水收入,流水账户,$A18,流水日期,BE$6),2)) | BF18: =IF(OR($A18="",BF$6=""),"",ROUND(SUMIFS(流水支出,流水账户,$A18,流水日期,BF$6),2)) | BG18: =IF(OR($A18="",BG$6=""),"",ROUND(SUMIFS(流水收入,流水账户,$A18,流水日期,BG$6),2)) | BH18: =IF(OR($A18="",BH$6=""),"",ROUND(SUMIFS(流水支出,流水账户,$A18,流水日期,BH$6),2)) | BI18: =IF(OR($A18="",BI$6=""),"",ROUND(SUMIFS(流水收入,流水账户,$A18,流水日期,BI$6),2)) | BJ18: =IF(OR($A18="",BJ$6=""),"",ROUND(SUMIFS(流水支出,流水账户,$A18,流水日期,BJ$6),2)) | BK18: =IF(OR($A18="",BK$6=""),"",ROUND(SUMIFS(流水收入,流水账户,$A18,流水日期,BK$6),2)) | BL18: =IF(OR($A18="",BL$6=""),"",ROUND(SUMIFS(流水支出,流水账户,$A18,流水日期,BL$6),2)) | BM18: =IF($A18="","",ROUND(SUMIF($C$7:$BL$7,"收款",C18:BL18),2)) | BN18: =IF($A18="","",ROUND(SUMIF($C$7:$BL$7,"付款",C18:BL18),2)) | BO18: =IF($A18="","",ROUND(N($B18)+N(BM18)-N(BN18),2))
A19: =IF(基础资料!$B$16="","",基础资料!$B$16) | B19: =IF(OR($A19="",NOT(ISNUMBER($H$3))),"",ROUND(SUMIF(账户表,$A19,账户期初)+SUMIFS(流水收入,流水账户,$A19,流水日期,"<"&$B$3)-SUMIFS(流水支出,流水账户,$A19,流水日期,"<"&$B$3),2)) | C19: =IF(OR($A19="",C$6=""),"",ROUND(SUMIFS(流水收入,流水账户,$A19,流水日期,C$6),2)) | D19: =IF(OR($A19="",D$6=""),"",ROUND(SUMIFS(流水支出,流水账户,$A19,流水日期,D$6),2)) | E19: =IF(OR($A19="",E$6=""),"",ROUND(SUMIFS(流水收入,流水账户,$A19,流水日期,E$6),2)) | F19: =IF(OR($A19="",F$6=""),"",ROUND(SUMIFS(流水支出,流水账户,$A19,流水日期,F$6),2)) | G19: =IF(OR($A19="",G$6=""),"",ROUND(SUMIFS(流水收入,流水账户,$A19,流水日期,G$6),2)) | H19: =IF(OR($A19="",H$6=""),"",ROUND(SUMIFS(流水支出,流水账户,$A19,流水日期,H$6),2)) | I19: =IF(OR($A19="",I$6=""),"",ROUND(SUMIFS(流水收入,流水账户,$A19,流水日期,I$6),2)) | J19: =IF(OR($A19="",J$6=""),"",ROUND(SUMIFS(流水支出,流水账户,$A19,流水日期,J$6),2)) | K19: =IF(OR($A19="",K$6=""),"",ROUND(SUMIFS(流水收入,流水账户,$A19,流水日期,K$6),2)) | L19: =IF(OR($A19="",L$6=""),"",ROUND(SUMIFS(流水支出,流水账户,$A19,流水日期,L$6),2)) | M19: =IF(OR($A19="",M$6=""),"",ROUND(SUMIFS(流水收入,流水账户,$A19,流水日期,M$6),2)) | N19: =IF(OR($A19="",N$6=""),"",ROUND(SUMIFS(流水支出,流水账户,$A19,流水日期,N$6),2)) | O19: =IF(OR($A19="",O$6=""),"",ROUND(SUMIFS(流水收入,流水账户,$A19,流水日期,O$6),2)) | P19: =IF(OR($A19="",P$6=""),"",ROUND(SUMIFS(流水支出,流水账户,$A19,流水日期,P$6),2)) | Q19: =IF(OR($A19="",Q$6=""),"",ROUND(SUMIFS(流水收入,流水账户,$A19,流水日期,Q$6),2)) | R19: =IF(OR($A19="",R$6=""),"",ROUND(SUMIFS(流水支出,流水账户,$A19,流水日期,R$6),2)) | S19: =IF(OR($A19="",S$6=""),"",ROUND(SUMIFS(流水收入,流水账户,$A19,流水日期,S$6),2)) | T19: =IF(OR($A19="",T$6=""),"",ROUND(SUMIFS(流水支出,流水账户,$A19,流水日期,T$6),2)) | U19: =IF(OR($A19="",U$6=""),"",ROUND(SUMIFS(流水收入,流水账户,$A19,流水日期,U$6),2)) | V19: =IF(OR($A19="",V$6=""),"",ROUND(SUMIFS(流水支出,流水账户,$A19,流水日期,V$6),2)) | W19: =IF(OR($A19="",W$6=""),"",ROUND(SUMIFS(流水收入,流水账户,$A19,流水日期,W$6),2)) | X19: =IF(OR($A19="",X$6=""),"",ROUND(SUMIFS(流水支出,流水账户,$A19,流水日期,X$6),2)) | Y19: =IF(OR($A19="",Y$6=""),"",ROUND(SUMIFS(流水收入,流水账户,$A19,流水日期,Y$6),2)) | Z19: =IF(OR($A19="",Z$6=""),"",ROUND(SUMIFS(流水支出,流水账户,$A19,流水日期,Z$6),2)) | AA19: =IF(OR($A19="",AA$6=""),"",ROUND(SUMIFS(流水收入,流水账户,$A19,流水日期,AA$6),2)) | AB19: =IF(OR($A19="",AB$6=""),"",ROUND(SUMIFS(流水支出,流水账户,$A19,流水日期,AB$6),2)) | AC19: =IF(OR($A19="",AC$6=""),"",ROUND(SUMIFS(流水收入,流水账户,$A19,流水日期,AC$6),2)) | AD19: =IF(OR($A19="",AD$6=""),"",ROUND(SUMIFS(流水支出,流水账户,$A19,流水日期,AD$6),2)) | AE19: =IF(OR($A19="",AE$6=""),"",ROUND(SUMIFS(流水收入,流水账户,$A19,流水日期,AE$6),2)) | AF19: =IF(OR($A19="",AF$6=""),"",ROUND(SUMIFS(流水支出,流水账户,$A19,流水日期,AF$6),2)) | AG19: =IF(OR($A19="",AG$6=""),"",ROUND(SUMIFS(流水收入,流水账户,$A19,流水日期,AG$6),2)) | AH19: =IF(OR($A19="",AH$6=""),"",ROUND(SUMIFS(流水支出,流水账户,$A19,流水日期,AH$6),2)) | AI19: =IF(OR($A19="",AI$6=""),"",ROUND(SUMIFS(流水收入,流水账户,$A19,流水日期,AI$6),2)) | AJ19: =IF(OR($A19="",AJ$6=""),"",ROUND(SUMIFS(流水支出,流水账户,$A19,流水日期,AJ$6),2)) | AK19: =IF(OR($A19="",AK$6=""),"",ROUND(SUMIFS(流水收入,流水账户,$A19,流水日期,AK$6),2)) | AL19: =IF(OR($A19="",AL$6=""),"",ROUND(SUMIFS(流水支出,流水账户,$A19,流水日期,AL$6),2)) | AM19: =IF(OR($A19="",AM$6=""),"",ROUND(SUMIFS(流水收入,流水账户,$A19,流水日期,AM$6),2)) | AN19: =IF(OR($A19="",AN$6=""),"",ROUND(SUMIFS(流水支出,流水账户,$A19,流水日期,AN$6),2)) | AO19: =IF(OR($A19="",AO$6=""),"",ROUND(SUMIFS(流水收入,流水账户,$A19,流水日期,AO$6),2)) | AP19: =IF(OR($A19="",AP$6=""),"",ROUND(SUMIFS(流水支出,流水账户,$A19,流水日期,AP$6),2)) | AQ19: =IF(OR($A19="",AQ$6=""),"",ROUND(SUMIFS(流水收入,流水账户,$A19,流水日期,AQ$6),2)) | AR19: =IF(OR($A19="",AR$6=""),"",ROUND(SUMIFS(流水支出,流水账户,$A19,流水日期,AR$6),2)) | AS19: =IF(OR($A19="",AS$6=""),"",ROUND(SUMIFS(流水收入,流水账户,$A19,流水日期,AS$6),2)) | AT19: =IF(OR($A19="",AT$6=""),"",ROUND(SUMIFS(流水支出,流水账户,$A19,流水日期,AT$6),2)) | AU19: =IF(OR($A19="",AU$6=""),"",ROUND(SUMIFS(流水收入,流水账户,$A19,流水日期,AU$6),2)) | AV19: =IF(OR($A19="",AV$6=""),"",ROUND(SUMIFS(流水支出,流水账户,$A19,流水日期,AV$6),2)) | AW19: =IF(OR($A19="",AW$6=""),"",ROUND(SUMIFS(流水收入,流水账户,$A19,流水日期,AW$6),2)) | AX19: =IF(OR($A19="",AX$6=""),"",ROUND(SUMIFS(流水支出,流水账户,$A19,流水日期,AX$6),2)) | AY19: =IF(OR($A19="",AY$6=""),"",ROUND(SUMIFS(流水收入,流水账户,$A19,流水日期,AY$6),2)) | AZ19: =IF(OR($A19="",AZ$6=""),"",ROUND(SUMIFS(流水支出,流水账户,$A19,流水日期,AZ$6),2)) | BA19: =IF(OR($A19="",BA$6=""),"",ROUND(SUMIFS(流水收入,流水账户,$A19,流水日期,BA$6),2)) | BB19: =IF(OR($A19="",BB$6=""),"",ROUND(SUMIFS(流水支出,流水账户,$A19,流水日期,BB$6),2)) | BC19: =IF(OR($A19="",BC$6=""),"",ROUND(SUMIFS(流水收入,流水账户,$A19,流水日期,BC$6),2)) | BD19: =IF(OR($A19="",BD$6=""),"",ROUND(SUMIFS(流水支出,流水账户,$A19,流水日期,BD$6),2)) | BE19: =IF(OR($A19="",BE$6=""),"",ROUND(SUMIFS(流水收入,流水账户,$A19,流水日期,BE$6),2)) | BF19: =IF(OR($A19="",BF$6=""),"",ROUND(SUMIFS(流水支出,流水账户,$A19,流水日期,BF$6),2)) | BG19: =IF(OR($A19="",BG$6=""),"",ROUND(SUMIFS(流水收入,流水账户,$A19,流水日期,BG$6),2)) | BH19: =IF(OR($A19="",BH$6=""),"",ROUND(SUMIFS(流水支出,流水账户,$A19,流水日期,BH$6),2)) | BI19: =IF(OR($A19="",BI$6=""),"",ROUND(SUMIFS(流水收入,流水账户,$A19,流水日期,BI$6),2)) | BJ19: =IF(OR($A19="",BJ$6=""),"",ROUND(SUMIFS(流水支出,流水账户,$A19,流水日期,BJ$6),2)) | BK19: =IF(OR($A19="",BK$6=""),"",ROUND(SUMIFS(流水收入,流水账户,$A19,流水日期,BK$6),2)) | BL19: =IF(OR($A19="",BL$6=""),"",ROUND(SUMIFS(流水支出,流水账户,$A19,流水日期,BL$6),2)) | BM19: =IF($A19="","",ROUND(SUMIF($C$7:$BL$7,"收款",C19:BL19),2)) | BN19: =IF($A19="","",ROUND(SUMIF($C$7:$BL$7,"付款",C19:BL19),2)) | BO19: =IF($A19="","",ROUND(N($B19)+N(BM19)-N(BN19),2))
A20: =IF(基础资料!$B$17="","",基础资料!$B$17) | B20: =IF(OR($A20="",NOT(ISNUMBER($H$3))),"",ROUND(SUMIF(账户表,$A20,账户期初)+SUMIFS(流水收入,流水账户,$A20,流水日期,"<"&$B$3)-SUMIFS(流水支出,流水账户,$A20,流水日期,"<"&$B$3),2)) | C20: =IF(OR($A20="",C$6=""),"",ROUND(SUMIFS(流水收入,流水账户,$A20,流水日期,C$6),2)) | D20: =IF(OR($A20="",D$6=""),"",ROUND(SUMIFS(流水支出,流水账户,$A20,流水日期,D$6),2)) | E20: =IF(OR($A20="",E$6=""),"",ROUND(SUMIFS(流水收入,流水账户,$A20,流水日期,E$6),2)) | F20: =IF(OR($A20="",F$6=""),"",ROUND(SUMIFS(流水支出,流水账户,$A20,流水日期,F$6),2)) | G20: =IF(OR($A20="",G$6=""),"",ROUND(SUMIFS(流水收入,流水账户,$A20,流水日期,G$6),2)) | H20: =IF(OR($A20="",H$6=""),"",ROUND(SUMIFS(流水支出,流水账户,$A20,流水日期,H$6),2)) | I20: =IF(OR($A20="",I$6=""),"",ROUND(SUMIFS(流水收入,流水账户,$A20,流水日期,I$6),2)) | J20: =IF(OR($A20="",J$6=""),"",ROUND(SUMIFS(流水支出,流水账户,$A20,流水日期,J$6),2)) | K20: =IF(OR($A20="",K$6=""),"",ROUND(SUMIFS(流水收入,流水账户,$A20,流水日期,K$6),2)) | L20: =IF(OR($A20="",L$6=""),"",ROUND(SUMIFS(流水支出,流水账户,$A20,流水日期,L$6),2)) | M20: =IF(OR($A20="",M$6=""),"",ROUND(SUMIFS(流水收入,流水账户,$A20,流水日期,M$6),2)) | N20: =IF(OR($A20="",N$6=""),"",ROUND(SUMIFS(流水支出,流水账户,$A20,流水日期,N$6),2)) | O20: =IF(OR($A20="",O$6=""),"",ROUND(SUMIFS(流水收入,流水账户,$A20,流水日期,O$6),2)) | P20: =IF(OR($A20="",P$6=""),"",ROUND(SUMIFS(流水支出,流水账户,$A20,流水日期,P$6),2)) | Q20: =IF(OR($A20="",Q$6=""),"",ROUND(SUMIFS(流水收入,流水账户,$A20,流水日期,Q$6),2)) | R20: =IF(OR($A20="",R$6=""),"",ROUND(SUMIFS(流水支出,流水账户,$A20,流水日期,R$6),2)) | S20: =IF(OR($A20="",S$6=""),"",ROUND(SUMIFS(流水收入,流水账户,$A20,流水日期,S$6),2)) | T20: =IF(OR($A20="",T$6=""),"",ROUND(SUMIFS(流水支出,流水账户,$A20,流水日期,T$6),2)) | U20: =IF(OR($A20="",U$6=""),"",ROUND(SUMIFS(流水收入,流水账户,$A20,流水日期,U$6),2)) | V20: =IF(OR($A20="",V$6=""),"",ROUND(SUMIFS(流水支出,流水账户,$A20,流水日期,V$6),2)) | W20: =IF(OR($A20="",W$6=""),"",ROUND(SUMIFS(流水收入,流水账户,$A20,流水日期,W$6),2)) | X20: =IF(OR($A20="",X$6=""),"",ROUND(SUMIFS(流水支出,流水账户,$A20,流水日期,X$6),2)) | Y20: =IF(OR($A20="",Y$6=""),"",ROUND(SUMIFS(流水收入,流水账户,$A20,流水日期,Y$6),2)) | Z20: =IF(OR($A20="",Z$6=""),"",ROUND(SUMIFS(流水支出,流水账户,$A20,流水日期,Z$6),2)) | AA20: =IF(OR($A20="",AA$6=""),"",ROUND(SUMIFS(流水收入,流水账户,$A20,流水日期,AA$6),2)) | AB20: =IF(OR($A20="",AB$6=""),"",ROUND(SUMIFS(流水支出,流水账户,$A20,流水日期,AB$6),2)) | AC20: =IF(OR($A20="",AC$6=""),"",ROUND(SUMIFS(流水收入,流水账户,$A20,流水日期,AC$6),2)) | AD20: =IF(OR($A20="",AD$6=""),"",ROUND(SUMIFS(流水支出,流水账户,$A20,流水日期,AD$6),2)) | AE20: =IF(OR($A20="",AE$6=""),"",ROUND(SUMIFS(流水收入,流水账户,$A20,流水日期,AE$6),2)) | AF20: =IF(OR($A20="",AF$6=""),"",ROUND(SUMIFS(流水支出,流水账户,$A20,流水日期,AF$6),2)) | AG20: =IF(OR($A20="",AG$6=""),"",ROUND(SUMIFS(流水收入,流水账户,$A20,流水日期,AG$6),2)) | AH20: =IF(OR($A20="",AH$6=""),"",ROUND(SUMIFS(流水支出,流水账户,$A20,流水日期,AH$6),2)) | AI20: =IF(OR($A20="",AI$6=""),"",ROUND(SUMIFS(流水收入,流水账户,$A20,流水日期,AI$6),2)) | AJ20: =IF(OR($A20="",AJ$6=""),"",ROUND(SUMIFS(流水支出,流水账户,$A20,流水日期,AJ$6),2)) | AK20: =IF(OR($A20="",AK$6=""),"",ROUND(SUMIFS(流水收入,流水账户,$A20,流水日期,AK$6),2)) | AL20: =IF(OR($A20="",AL$6=""),"",ROUND(SUMIFS(流水支出,流水账户,$A20,流水日期,AL$6),2)) | AM20: =IF(OR($A20="",AM$6=""),"",ROUND(SUMIFS(流水收入,流水账户,$A20,流水日期,AM$6),2)) | AN20: =IF(OR($A20="",AN$6=""),"",ROUND(SUMIFS(流水支出,流水账户,$A20,流水日期,AN$6),2)) | AO20: =IF(OR($A20="",AO$6=""),"",ROUND(SUMIFS(流水收入,流水账户,$A20,流水日期,AO$6),2)) | AP20: =IF(OR($A20="",AP$6=""),"",ROUND(SUMIFS(流水支出,流水账户,$A20,流水日期,AP$6),2)) | AQ20: =IF(OR($A20="",AQ$6=""),"",ROUND(SUMIFS(流水收入,流水账户,$A20,流水日期,AQ$6),2)) | AR20: =IF(OR($A20="",AR$6=""),"",ROUND(SUMIFS(流水支出,流水账户,$A20,流水日期,AR$6),2)) | AS20: =IF(OR($A20="",AS$6=""),"",ROUND(SUMIFS(流水收入,流水账户,$A20,流水日期,AS$6),2)) | AT20: =IF(OR($A20="",AT$6=""),"",ROUND(SUMIFS(流水支出,流水账户,$A20,流水日期,AT$6),2)) | AU20: =IF(OR($A20="",AU$6=""),"",ROUND(SUMIFS(流水收入,流水账户,$A20,流水日期,AU$6),2)) | AV20: =IF(OR($A20="",AV$6=""),"",ROUND(SUMIFS(流水支出,流水账户,$A20,流水日期,AV$6),2)) | AW20: =IF(OR($A20="",AW$6=""),"",ROUND(SUMIFS(流水收入,流水账户,$A20,流水日期,AW$6),2)) | AX20: =IF(OR($A20="",AX$6=""),"",ROUND(SUMIFS(流水支出,流水账户,$A20,流水日期,AX$6),2)) | AY20: =IF(OR($A20="",AY$6=""),"",ROUND(SUMIFS(流水收入,流水账户,$A20,流水日期,AY$6),2)) | AZ20: =IF(OR($A20="",AZ$6=""),"",ROUND(SUMIFS(流水支出,流水账户,$A20,流水日期,AZ$6),2)) | BA20: =IF(OR($A20="",BA$6=""),"",ROUND(SUMIFS(流水收入,流水账户,$A20,流水日期,BA$6),2)) | BB20: =IF(OR($A20="",BB$6=""),"",ROUND(SUMIFS(流水支出,流水账户,$A20,流水日期,BB$6),2)) | BC20: =IF(OR($A20="",BC$6=""),"",ROUND(SUMIFS(流水收入,流水账户,$A20,流水日期,BC$6),2)) | BD20: =IF(OR($A20="",BD$6=""),"",ROUND(SUMIFS(流水支出,流水账户,$A20,流水日期,BD$6),2)) | BE20: =IF(OR($A20="",BE$6=""),"",ROUND(SUMIFS(流水收入,流水账户,$A20,流水日期,BE$6),2)) | BF20: =IF(OR($A20="",BF$6=""),"",ROUND(SUMIFS(流水支出,流水账户,$A20,流水日期,BF$6),2)) | BG20: =IF(OR($A20="",BG$6=""),"",ROUND(SUMIFS(流水收入,流水账户,$A20,流水日期,BG$6),2)) | BH20: =IF(OR($A20="",BH$6=""),"",ROUND(SUMIFS(流水支出,流水账户,$A20,流水日期,BH$6),2)) | BI20: =IF(OR($A20="",BI$6=""),"",ROUND(SUMIFS(流水收入,流水账户,$A20,流水日期,BI$6),2)) | BJ20: =IF(OR($A20="",BJ$6=""),"",ROUND(SUMIFS(流水支出,流水账户,$A20,流水日期,BJ$6),2)) | BK20: =IF(OR($A20="",BK$6=""),"",ROUND(SUMIFS(流水收入,流水账户,$A20,流水日期,BK$6),2)) | BL20: =IF(OR($A20="",BL$6=""),"",ROUND(SUMIFS(流水支出,流水账户,$A20,流水日期,BL$6),2)) | BM20: =IF($A20="","",ROUND(SUMIF($C$7:$BL$7,"收款",C20:BL20),2)) | BN20: =IF($A20="","",ROUND(SUMIF($C$7:$BL$7,"付款",C20:BL20),2)) | BO20: =IF($A20="","",ROUND(N($B20)+N(BM20)-N(BN20),2))
A21: =IF(基础资料!$B$18="","",基础资料!$B$18) | B21: =IF(OR($A21="",NOT(ISNUMBER($H$3))),"",ROUND(SUMIF(账户表,$A21,账户期初)+SUMIFS(流水收入,流水账户,$A21,流水日期,"<"&$B$3)-SUMIFS(流水支出,流水账户,$A21,流水日期,"<"&$B$3),2)) | C21: =IF(OR($A21="",C$6=""),"",ROUND(SUMIFS(流水收入,流水账户,$A21,流水日期,C$6),2)) | D21: =IF(OR($A21="",D$6=""),"",ROUND(SUMIFS(流水支出,流水账户,$A21,流水日期,D$6),2)) | E21: =IF(OR($A21="",E$6=""),"",ROUND(SUMIFS(流水收入,流水账户,$A21,流水日期,E$6),2)) | F21: =IF(OR($A21="",F$6=""),"",ROUND(SUMIFS(流水支出,流水账户,$A21,流水日期,F$6),2)) | G21: =IF(OR($A21="",G$6=""),"",ROUND(SUMIFS(流水收入,流水账户,$A21,流水日期,G$6),2)) | H21: =IF(OR($A21="",H$6=""),"",ROUND(SUMIFS(流水支出,流水账户,$A21,流水日期,H$6),2)) | I21: =IF(OR($A21="",I$6=""),"",ROUND(SUMIFS(流水收入,流水账户,$A21,流水日期,I$6),2)) | J21: =IF(OR($A21="",J$6=""),"",ROUND(SUMIFS(流水支出,流水账户,$A21,流水日期,J$6),2)) | K21: =IF(OR($A21="",K$6=""),"",ROUND(SUMIFS(流水收入,流水账户,$A21,流水日期,K$6),2)) | L21: =IF(OR($A21="",L$6=""),"",ROUND(SUMIFS(流水支出,流水账户,$A21,流水日期,L$6),2)) | M21: =IF(OR($A21="",M$6=""),"",ROUND(SUMIFS(流水收入,流水账户,$A21,流水日期,M$6),2)) | N21: =IF(OR($A21="",N$6=""),"",ROUND(SUMIFS(流水支出,流水账户,$A21,流水日期,N$6),2)) | O21: =IF(OR($A21="",O$6=""),"",ROUND(SUMIFS(流水收入,流水账户,$A21,流水日期,O$6),2)) | P21: =IF(OR($A21="",P$6=""),"",ROUND(SUMIFS(流水支出,流水账户,$A21,流水日期,P$6),2)) | Q21: =IF(OR($A21="",Q$6=""),"",ROUND(SUMIFS(流水收入,流水账户,$A21,流水日期,Q$6),2)) | R21: =IF(OR($A21="",R$6=""),"",ROUND(SUMIFS(流水支出,流水账户,$A21,流水日期,R$6),2)) | S21: =IF(OR($A21="",S$6=""),"",ROUND(SUMIFS(流水收入,流水账户,$A21,流水日期,S$6),2)) | T21: =IF(OR($A21="",T$6=""),"",ROUND(SUMIFS(流水支出,流水账户,$A21,流水日期,T$6),2)) | U21: =IF(OR($A21="",U$6=""),"",ROUND(SUMIFS(流水收入,流水账户,$A21,流水日期,U$6),2)) | V21: =IF(OR($A21="",V$6=""),"",ROUND(SUMIFS(流水支出,流水账户,$A21,流水日期,V$6),2)) | W21: =IF(OR($A21="",W$6=""),"",ROUND(SUMIFS(流水收入,流水账户,$A21,流水日期,W$6),2)) | X21: =IF(OR($A21="",X$6=""),"",ROUND(SUMIFS(流水支出,流水账户,$A21,流水日期,X$6),2)) | Y21: =IF(OR($A21="",Y$6=""),"",ROUND(SUMIFS(流水收入,流水账户,$A21,流水日期,Y$6),2)) | Z21: =IF(OR($A21="",Z$6=""),"",ROUND(SUMIFS(流水支出,流水账户,$A21,流水日期,Z$6),2)) | AA21: =IF(OR($A21="",AA$6=""),"",ROUND(SUMIFS(流水收入,流水账户,$A21,流水日期,AA$6),2)) | AB21: =IF(OR($A21="",AB$6=""),"",ROUND(SUMIFS(流水支出,流水账户,$A21,流水日期,AB$6),2)) | AC21: =IF(OR($A21="",AC$6=""),"",ROUND(SUMIFS(流水收入,流水账户,$A21,流水日期,AC$6),2)) | AD21: =IF(OR($A21="",AD$6=""),"",ROUND(SUMIFS(流水支出,流水账户,$A21,流水日期,AD$6),2)) | AE21: =IF(OR($A21="",AE$6=""),"",ROUND(SUMIFS(流水收入,流水账户,$A21,流水日期,AE$6),2)) | AF21: =IF(OR($A21="",AF$6=""),"",ROUND(SUMIFS(流水支出,流水账户,$A21,流水日期,AF$6),2)) | AG21: =IF(OR($A21="",AG$6=""),"",ROUND(SUMIFS(流水收入,流水账户,$A21,流水日期,AG$6),2)) | AH21: =IF(OR($A21="",AH$6=""),"",ROUND(SUMIFS(流水支出,流水账户,$A21,流水日期,AH$6),2)) | AI21: =IF(OR($A21="",AI$6=""),"",ROUND(SUMIFS(流水收入,流水账户,$A21,流水日期,AI$6),2)) | AJ21: =IF(OR($A21="",AJ$6=""),"",ROUND(SUMIFS(流水支出,流水账户,$A21,流水日期,AJ$6),2)) | AK21: =IF(OR($A21="",AK$6=""),"",ROUND(SUMIFS(流水收入,流水账户,$A21,流水日期,AK$6),2)) | AL21: =IF(OR($A21="",AL$6=""),"",ROUND(SUMIFS(流水支出,流水账户,$A21,流水日期,AL$6),2)) | AM21: =IF(OR($A21="",AM$6=""),"",ROUND(SUMIFS(流水收入,流水账户,$A21,流水日期,AM$6),2)) | AN21: =IF(OR($A21="",AN$6=""),"",ROUND(SUMIFS(流水支出,流水账户,$A21,流水日期,AN$6),2)) | AO21: =IF(OR($A21="",AO$6=""),"",ROUND(SUMIFS(流水收入,流水账户,$A21,流水日期,AO$6),2)) | AP21: =IF(OR($A21="",AP$6=""),"",ROUND(SUMIFS(流水支出,流水账户,$A21,流水日期,AP$6),2)) | AQ21: =IF(OR($A21="",AQ$6=""),"",ROUND(SUMIFS(流水收入,流水账户,$A21,流水日期,AQ$6),2)) | AR21: =IF(OR($A21="",AR$6=""),"",ROUND(SUMIFS(流水支出,流水账户,$A21,流水日期,AR$6),2)) | AS21: =IF(OR($A21="",AS$6=""),"",ROUND(SUMIFS(流水收入,流水账户,$A21,流水日期,AS$6),2)) | AT21: =IF(OR($A21="",AT$6=""),"",ROUND(SUMIFS(流水支出,流水账户,$A21,流水日期,AT$6),2)) | AU21: =IF(OR($A21="",AU$6=""),"",ROUND(SUMIFS(流水收入,流水账户,$A21,流水日期,AU$6),2)) | AV21: =IF(OR($A21="",AV$6=""),"",ROUND(SUMIFS(流水支出,流水账户,$A21,流水日期,AV$6),2)) | AW21: =IF(OR($A21="",AW$6=""),"",ROUND(SUMIFS(流水收入,流水账户,$A21,流水日期,AW$6),2)) | AX21: =IF(OR($A21="",AX$6=""),"",ROUND(SUMIFS(流水支出,流水账户,$A21,流水日期,AX$6),2)) | AY21: =IF(OR($A21="",AY$6=""),"",ROUND(SUMIFS(流水收入,流水账户,$A21,流水日期,AY$6),2)) | AZ21: =IF(OR($A21="",AZ$6=""),"",ROUND(SUMIFS(流水支出,流水账户,$A21,流水日期,AZ$6),2)) | BA21: =IF(OR($A21="",BA$6=""),"",ROUND(SUMIFS(流水收入,流水账户,$A21,流水日期,BA$6),2)) | BB21: =IF(OR($A21="",BB$6=""),"",ROUND(SUMIFS(流水支出,流水账户,$A21,流水日期,BB$6),2)) | BC21: =IF(OR($A21="",BC$6=""),"",ROUND(SUMIFS(流水收入,流水账户,$A21,流水日期,BC$6),2)) | BD21: =IF(OR($A21="",BD$6=""),"",ROUND(SUMIFS(流水支出,流水账户,$A21,流水日期,BD$6),2)) | BE21: =IF(OR($A21="",BE$6=""),"",ROUND(SUMIFS(流水收入,流水账户,$A21,流水日期,BE$6),2)) | BF21: =IF(OR($A21="",BF$6=""),"",ROUND(SUMIFS(流水支出,流水账户,$A21,流水日期,BF$6),2)) | BG21: =IF(OR($A21="",BG$6=""),"",ROUND(SUMIFS(流水收入,流水账户,$A21,流水日期,BG$6),2)) | BH21: =IF(OR($A21="",BH$6=""),"",ROUND(SUMIFS(流水支出,流水账户,$A21,流水日期,BH$6),2)) | BI21: =IF(OR($A21="",BI$6=""),"",ROUND(SUMIFS(流水收入,流水账户,$A21,流水日期,BI$6),2)) | BJ21: =IF(OR($A21="",BJ$6=""),"",ROUND(SUMIFS(流水支出,流水账户,$A21,流水日期,BJ$6),2)) | BK21: =IF(OR($A21="",BK$6=""),"",ROUND(SUMIFS(流水收入,流水账户,$A21,流水日期,BK$6),2)) | BL21: =IF(OR($A21="",BL$6=""),"",ROUND(SUMIFS(流水支出,流水账户,$A21,流水日期,BL$6),2)) | BM21: =IF($A21="","",ROUND(SUMIF($C$7:$BL$7,"收款",C21:BL21),2)) | BN21: =IF($A21="","",ROUND(SUMIF($C$7:$BL$7,"付款",C21:BL21),2)) | BO21: =IF($A21="","",ROUND(N($B21)+N(BM21)-N(BN21),2))
A22: =IF(基础资料!$B$19="","",基础资料!$B$19) | B22: =IF(OR($A22="",NOT(ISNUMBER($H$3))),"",ROUND(SUMIF(账户表,$A22,账户期初)+SUMIFS(流水收入,流水账户,$A22,流水日期,"<"&$B$3)-SUMIFS(流水支出,流水账户,$A22,流水日期,"<"&$B$3),2)) | C22: =IF(OR($A22="",C$6=""),"",ROUND(SUMIFS(流水收入,流水账户,$A22,流水日期,C$6),2)) | D22: =IF(OR($A22="",D$6=""),"",ROUND(SUMIFS(流水支出,流水账户,$A22,流水日期,D$6),2)) | E22: =IF(OR($A22="",E$6=""),"",ROUND(SUMIFS(流水收入,流水账户,$A22,流水日期,E$6),2)) | F22: =IF(OR($A22="",F$6=""),"",ROUND(SUMIFS(流水支出,流水账户,$A22,流水日期,F$6),2)) | G22: =IF(OR($A22="",G$6=""),"",ROUND(SUMIFS(流水收入,流水账户,$A22,流水日期,G$6),2)) | H22: =IF(OR($A22="",H$6=""),"",ROUND(SUMIFS(流水支出,流水账户,$A22,流水日期,H$6),2)) | I22: =IF(OR($A22="",I$6=""),"",ROUND(SUMIFS(流水收入,流水账户,$A22,流水日期,I$6),2)) | J22: =IF(OR($A22="",J$6=""),"",ROUND(SUMIFS(流水支出,流水账户,$A22,流水日期,J$6),2)) | K22: =IF(OR($A22="",K$6=""),"",ROUND(SUMIFS(流水收入,流水账户,$A22,流水日期,K$6),2)) | L22: =IF(OR($A22="",L$6=""),"",ROUND(SUMIFS(流水支出,流水账户,$A22,流水日期,L$6),2)) | M22: =IF(OR($A22="",M$6=""),"",ROUND(SUMIFS(流水收入,流水账户,$A22,流水日期,M$6),2)) | N22: =IF(OR($A22="",N$6=""),"",ROUND(SUMIFS(流水支出,流水账户,$A22,流水日期,N$6),2)) | O22: =IF(OR($A22="",O$6=""),"",ROUND(SUMIFS(流水收入,流水账户,$A22,流水日期,O$6),2)) | P22: =IF(OR($A22="",P$6=""),"",ROUND(SUMIFS(流水支出,流水账户,$A22,流水日期,P$6),2)) | Q22: =IF(OR($A22="",Q$6=""),"",ROUND(SUMIFS(流水收入,流水账户,$A22,流水日期,Q$6),2)) | R22: =IF(OR($A22="",R$6=""),"",ROUND(SUMIFS(流水支出,流水账户,$A22,流水日期,R$6),2)) | S22: =IF(OR($A22="",S$6=""),"",ROUND(SUMIFS(流水收入,流水账户,$A22,流水日期,S$6),2)) | T22: =IF(OR($A22="",T$6=""),"",ROUND(SUMIFS(流水支出,流水账户,$A22,流水日期,T$6),2)) | U22: =IF(OR($A22="",U$6=""),"",ROUND(SUMIFS(流水收入,流水账户,$A22,流水日期,U$6),2)) | V22: =IF(OR($A22="",V$6=""),"",ROUND(SUMIFS(流水支出,流水账户,$A22,流水日期,V$6),2)) | W22: =IF(OR($A22="",W$6=""),"",ROUND(SUMIFS(流水收入,流水账户,$A22,流水日期,W$6),2)) | X22: =IF(OR($A22="",X$6=""),"",ROUND(SUMIFS(流水支出,流水账户,$A22,流水日期,X$6),2)) | Y22: =IF(OR($A22="",Y$6=""),"",ROUND(SUMIFS(流水收入,流水账户,$A22,流水日期,Y$6),2)) | Z22: =IF(OR($A22="",Z$6=""),"",ROUND(SUMIFS(流水支出,流水账户,$A22,流水日期,Z$6),2)) | AA22: =IF(OR($A22="",AA$6=""),"",ROUND(SUMIFS(流水收入,流水账户,$A22,流水日期,AA$6),2)) | AB22: =IF(OR($A22="",AB$6=""),"",ROUND(SUMIFS(流水支出,流水账户,$A22,流水日期,AB$6),2)) | AC22: =IF(OR($A22="",AC$6=""),"",ROUND(SUMIFS(流水收入,流水账户,$A22,流水日期,AC$6),2)) | AD22: =IF(OR($A22="",AD$6=""),"",ROUND(SUMIFS(流水支出,流水账户,$A22,流水日期,AD$6),2)) | AE22: =IF(OR($A22="",AE$6=""),"",ROUND(SUMIFS(流水收入,流水账户,$A22,流水日期,AE$6),2)) | AF22: =IF(OR($A22="",AF$6=""),"",ROUND(SUMIFS(流水支出,流水账户,$A22,流水日期,AF$6),2)) | AG22: =IF(OR($A22="",AG$6=""),"",ROUND(SUMIFS(流水收入,流水账户,$A22,流水日期,AG$6),2)) | AH22: =IF(OR($A22="",AH$6=""),"",ROUND(SUMIFS(流水支出,流水账户,$A22,流水日期,AH$6),2)) | AI22: =IF(OR($A22="",AI$6=""),"",ROUND(SUMIFS(流水收入,流水账户,$A22,流水日期,AI$6),2)) | AJ22: =IF(OR($A22="",AJ$6=""),"",ROUND(SUMIFS(流水支出,流水账户,$A22,流水日期,AJ$6),2)) | AK22: =IF(OR($A22="",AK$6=""),"",ROUND(SUMIFS(流水收入,流水账户,$A22,流水日期,AK$6),2)) | AL22: =IF(OR($A22="",AL$6=""),"",ROUND(SUMIFS(流水支出,流水账户,$A22,流水日期,AL$6),2)) | AM22: =IF(OR($A22="",AM$6=""),"",ROUND(SUMIFS(流水收入,流水账户,$A22,流水日期,AM$6),2)) | AN22: =IF(OR($A22="",AN$6=""),"",ROUND(SUMIFS(流水支出,流水账户,$A22,流水日期,AN$6),2)) | AO22: =IF(OR($A22="",AO$6=""),"",ROUND(SUMIFS(流水收入,流水账户,$A22,流水日期,AO$6),2)) | AP22: =IF(OR($A22="",AP$6=""),"",ROUND(SUMIFS(流水支出,流水账户,$A22,流水日期,AP$6),2)) | AQ22: =IF(OR($A22="",AQ$6=""),"",ROUND(SUMIFS(流水收入,流水账户,$A22,流水日期,AQ$6),2)) | AR22: =IF(OR($A22="",AR$6=""),"",ROUND(SUMIFS(流水支出,流水账户,$A22,流水日期,AR$6),2)) | AS22: =IF(OR($A22="",AS$6=""),"",ROUND(SUMIFS(流水收入,流水账户,$A22,流水日期,AS$6),2)) | AT22: =IF(OR($A22="",AT$6=""),"",ROUND(SUMIFS(流水支出,流水账户,$A22,流水日期,AT$6),2)) | AU22: =IF(OR($A22="",AU$6=""),"",ROUND(SUMIFS(流水收入,流水账户,$A22,流水日期,AU$6),2)) | AV22: =IF(OR($A22="",AV$6=""),"",ROUND(SUMIFS(流水支出,流水账户,$A22,流水日期,AV$6),2)) | AW22: =IF(OR($A22="",AW$6=""),"",ROUND(SUMIFS(流水收入,流水账户,$A22,流水日期,AW$6),2)) | AX22: =IF(OR($A22="",AX$6=""),"",ROUND(SUMIFS(流水支出,流水账户,$A22,流水日期,AX$6),2)) | AY22: =IF(OR($A22="",AY$6=""),"",ROUND(SUMIFS(流水收入,流水账户,$A22,流水日期,AY$6),2)) | AZ22: =IF(OR($A22="",AZ$6=""),"",ROUND(SUMIFS(流水支出,流水账户,$A22,流水日期,AZ$6),2)) | BA22: =IF(OR($A22="",BA$6=""),"",ROUND(SUMIFS(流水收入,流水账户,$A22,流水日期,BA$6),2)) | BB22: =IF(OR($A22="",BB$6=""),"",ROUND(SUMIFS(流水支出,流水账户,$A22,流水日期,BB$6),2)) | BC22: =IF(OR($A22="",BC$6=""),"",ROUND(SUMIFS(流水收入,流水账户,$A22,流水日期,BC$6),2)) | BD22: =IF(OR($A22="",BD$6=""),"",ROUND(SUMIFS(流水支出,流水账户,$A22,流水日期,BD$6),2)) | BE22: =IF(OR($A22="",BE$6=""),"",ROUND(SUMIFS(流水收入,流水账户,$A22,流水日期,BE$6),2)) | BF22: =IF(OR($A22="",BF$6=""),"",ROUND(SUMIFS(流水支出,流水账户,$A22,流水日期,BF$6),2)) | BG22: =IF(OR($A22="",BG$6=""),"",ROUND(SUMIFS(流水收入,流水账户,$A22,流水日期,BG$6),2)) | BH22: =IF(OR($A22="",BH$6=""),"",ROUND(SUMIFS(流水支出,流水账户,$A22,流水日期,BH$6),2)) | BI22: =IF(OR($A22="",BI$6=""),"",ROUND(SUMIFS(流水收入,流水账户,$A22,流水日期,BI$6),2)) | BJ22: =IF(OR($A22="",BJ$6=""),"",ROUND(SUMIFS(流水支出,流水账户,$A22,流水日期,BJ$6),2)) | BK22: =IF(OR($A22="",BK$6=""),"",ROUND(SUMIFS(流水收入,流水账户,$A22,流水日期,BK$6),2)) | BL22: =IF(OR($A22="",BL$6=""),"",ROUND(SUMIFS(流水支出,流水账户,$A22,流水日期,BL$6),2)) | BM22: =IF($A22="","",ROUND(SUMIF($C$7:$BL$7,"收款",C22:BL22),2)) | BN22: =IF($A22="","",ROUND(SUMIF($C$7:$BL$7,"付款",C22:BL22),2)) | BO22: =IF($A22="","",ROUND(N($B22)+N(BM22)-N(BN22),2))
A23: =IF(基础资料!$B$20="","",基础资料!$B$20) | B23: =IF(OR($A23="",NOT(ISNUMBER($H$3))),"",ROUND(SUMIF(账户表,$A23,账户期初)+SUMIFS(流水收入,流水账户,$A23,流水日期,"<"&$B$3)-SUMIFS(流水支出,流水账户,$A23,流水日期,"<"&$B$3),2)) | C23: =IF(OR($A23="",C$6=""),"",ROUND(SUMIFS(流水收入,流水账户,$A23,流水日期,C$6),2)) | D23: =IF(OR($A23="",D$6=""),"",ROUND(SUMIFS(流水支出,流水账户,$A23,流水日期,D$6),2)) | E23: =IF(OR($A23="",E$6=""),"",ROUND(SUMIFS(流水收入,流水账户,$A23,流水日期,E$6),2)) | F23: =IF(OR($A23="",F$6=""),"",ROUND(SUMIFS(流水支出,流水账户,$A23,流水日期,F$6),2)) | G23: =IF(OR($A23="",G$6=""),"",ROUND(SUMIFS(流水收入,流水账户,$A23,流水日期,G$6),2)) | H23: =IF(OR($A23="",H$6=""),"",ROUND(SUMIFS(流水支出,流水账户,$A23,流水日期,H$6),2)) | I23: =IF(OR($A23="",I$6=""),"",ROUND(SUMIFS(流水收入,流水账户,$A23,流水日期,I$6),2)) | J23: =IF(OR($A23="",J$6=""),"",ROUND(SUMIFS(流水支出,流水账户,$A23,流水日期,J$6),2)) | K23: =IF(OR($A23="",K$6=""),"",ROUND(SUMIFS(流水收入,流水账户,$A23,流水日期,K$6),2)) | L23: =IF(OR($A23="",L$6=""),"",ROUND(SUMIFS(流水支出,流水账户,$A23,流水日期,L$6),2)) | M23: =IF(OR($A23="",M$6=""),"",ROUND(SUMIFS(流水收入,流水账户,$A23,流水日期,M$6),2)) | N23: =IF(OR($A23="",N$6=""),"",ROUND(SUMIFS(流水支出,流水账户,$A23,流水日期,N$6),2)) | O23: =IF(OR($A23="",O$6=""),"",ROUND(SUMIFS(流水收入,流水账户,$A23,流水日期,O$6),2)) | P23: =IF(OR($A23="",P$6=""),"",ROUND(SUMIFS(流水支出,流水账户,$A23,流水日期,P$6),2)) | Q23: =IF(OR($A23="",Q$6=""),"",ROUND(SUMIFS(流水收入,流水账户,$A23,流水日期,Q$6),2)) | R23: =IF(OR($A23="",R$6=""),"",ROUND(SUMIFS(流水支出,流水账户,$A23,流水日期,R$6),2)) | S23: =IF(OR($A23="",S$6=""),"",ROUND(SUMIFS(流水收入,流水账户,$A23,流水日期,S$6),2)) | T23: =IF(OR($A23="",T$6=""),"",ROUND(SUMIFS(流水支出,流水账户,$A23,流水日期,T$6),2)) | U23: =IF(OR($A23="",U$6=""),"",ROUND(SUMIFS(流水收入,流水账户,$A23,流水日期,U$6),2)) | V23: =IF(OR($A23="",V$6=""),"",ROUND(SUMIFS(流水支出,流水账户,$A23,流水日期,V$6),2)) | W23: =IF(OR($A23="",W$6=""),"",ROUND(SUMIFS(流水收入,流水账户,$A23,流水日期,W$6),2)) | X23: =IF(OR($A23="",X$6=""),"",ROUND(SUMIFS(流水支出,流水账户,$A23,流水日期,X$6),2)) | Y23: =IF(OR($A23="",Y$6=""),"",ROUND(SUMIFS(流水收入,流水账户,$A23,流水日期,Y$6),2)) | Z23: =IF(OR($A23="",Z$6=""),"",ROUND(SUMIFS(流水支出,流水账户,$A23,流水日期,Z$6),2)) | AA23: =IF(OR($A23="",AA$6=""),"",ROUND(SUMIFS(流水收入,流水账户,$A23,流水日期,AA$6),2)) | AB23: =IF(OR($A23="",AB$6=""),"",ROUND(SUMIFS(流水支出,流水账户,$A23,流水日期,AB$6),2)) | AC23: =IF(OR($A23="",AC$6=""),"",ROUND(SUMIFS(流水收入,流水账户,$A23,流水日期,AC$6),2)) | AD23: =IF(OR($A23="",AD$6=""),"",ROUND(SUMIFS(流水支出,流水账户,$A23,流水日期,AD$6),2)) | AE23: =IF(OR($A23="",AE$6=""),"",ROUND(SUMIFS(流水收入,流水账户,$A23,流水日期,AE$6),2)) | AF23: =IF(OR($A23="",AF$6=""),"",ROUND(SUMIFS(流水支出,流水账户,$A23,流水日期,AF$6),2)) | AG23: =IF(OR($A23="",AG$6=""),"",ROUND(SUMIFS(流水收入,流水账户,$A23,流水日期,AG$6),2)) | AH23: =IF(OR($A23="",AH$6=""),"",ROUND(SUMIFS(流水支出,流水账户,$A23,流水日期,AH$6),2)) | AI23: =IF(OR($A23="",AI$6=""),"",ROUND(SUMIFS(流水收入,流水账户,$A23,流水日期,AI$6),2)) | AJ23: =IF(OR($A23="",AJ$6=""),"",ROUND(SUMIFS(流水支出,流水账户,$A23,流水日期,AJ$6),2)) | AK23: =IF(OR($A23="",AK$6=""),"",ROUND(SUMIFS(流水收入,流水账户,$A23,流水日期,AK$6),2)) | AL23: =IF(OR($A23="",AL$6=""),"",ROUND(SUMIFS(流水支出,流水账户,$A23,流水日期,AL$6),2)) | AM23: =IF(OR($A23="",AM$6=""),"",ROUND(SUMIFS(流水收入,流水账户,$A23,流水日期,AM$6),2)) | AN23: =IF(OR($A23="",AN$6=""),"",ROUND(SUMIFS(流水支出,流水账户,$A23,流水日期,AN$6),2)) | AO23: =IF(OR($A23="",AO$6=""),"",ROUND(SUMIFS(流水收入,流水账户,$A23,流水日期,AO$6),2)) | AP23: =IF(OR($A23="",AP$6=""),"",ROUND(SUMIFS(流水支出,流水账户,$A23,流水日期,AP$6),2)) | AQ23: =IF(OR($A23="",AQ$6=""),"",ROUND(SUMIFS(流水收入,流水账户,$A23,流水日期,AQ$6),2)) | AR23: =IF(OR($A23="",AR$6=""),"",ROUND(SUMIFS(流水支出,流水账户,$A23,流水日期,AR$6),2)) | AS23: =IF(OR($A23="",AS$6=""),"",ROUND(SUMIFS(流水收入,流水账户,$A23,流水日期,AS$6),2)) | AT23: =IF(OR($A23="",AT$6=""),"",ROUND(SUMIFS(流水支出,流水账户,$A23,流水日期,AT$6),2)) | AU23: =IF(OR($A23="",AU$6=""),"",ROUND(SUMIFS(流水收入,流水账户,$A23,流水日期,AU$6),2)) | AV23: =IF(OR($A23="",AV$6=""),"",ROUND(SUMIFS(流水支出,流水账户,$A23,流水日期,AV$6),2)) | AW23: =IF(OR($A23="",AW$6=""),"",ROUND(SUMIFS(流水收入,流水账户,$A23,流水日期,AW$6),2)) | AX23: =IF(OR($A23="",AX$6=""),"",ROUND(SUMIFS(流水支出,流水账户,$A23,流水日期,AX$6),2)) | AY23: =IF(OR($A23="",AY$6=""),"",ROUND(SUMIFS(流水收入,流水账户,$A23,流水日期,AY$6),2)) | AZ23: =IF(OR($A23="",AZ$6=""),"",ROUND(SUMIFS(流水支出,流水账户,$A23,流水日期,AZ$6),2)) | BA23: =IF(OR($A23="",BA$6=""),"",ROUND(SUMIFS(流水收入,流水账户,$A23,流水日期,BA$6),2)) | BB23: =IF(OR($A23="",BB$6=""),"",ROUND(SUMIFS(流水支出,流水账户,$A23,流水日期,BB$6),2)) | BC23: =IF(OR($A23="",BC$6=""),"",ROUND(SUMIFS(流水收入,流水账户,$A23,流水日期,BC$6),2)) | BD23: =IF(OR($A23="",BD$6=""),"",ROUND(SUMIFS(流水支出,流水账户,$A23,流水日期,BD$6),2)) | BE23: =IF(OR($A23="",BE$6=""),"",ROUND(SUMIFS(流水收入,流水账户,$A23,流水日期,BE$6),2)) | BF23: =IF(OR($A23="",BF$6=""),"",ROUND(SUMIFS(流水支出,流水账户,$A23,流水日期,BF$6),2)) | BG23: =IF(OR($A23="",BG$6=""),"",ROUND(SUMIFS(流水收入,流水账户,$A23,流水日期,BG$6),2)) | BH23: =IF(OR($A23="",BH$6=""),"",ROUND(SUMIFS(流水支出,流水账户,$A23,流水日期,BH$6),2)) | BI23: =IF(OR($A23="",BI$6=""),"",ROUND(SUMIFS(流水收入,流水账户,$A23,流水日期,BI$6),2)) | BJ23: =IF(OR($A23="",BJ$6=""),"",ROUND(SUMIFS(流水支出,流水账户,$A23,流水日期,BJ$6),2)) | BK23: =IF(OR($A23="",BK$6=""),"",ROUND(SUMIFS(流水收入,流水账户,$A23,流水日期,BK$6),2)) | BL23: =IF(OR($A23="",BL$6=""),"",ROUND(SUMIFS(流水支出,流水账户,$A23,流水日期,BL$6),2)) | BM23: =IF($A23="","",ROUND(SUMIF($C$7:$BL$7,"收款",C23:BL23),2)) | BN23: =IF($A23="","",ROUND(SUMIF($C$7:$BL$7,"付款",C23:BL23),2)) | BO23: =IF($A23="","",ROUND(N($B23)+N(BM23)-N(BN23),2))
A24: =IF(基础资料!$B$21="","",基础资料!$B$21) | B24: =IF(OR($A24="",NOT(ISNUMBER($H$3))),"",ROUND(SUMIF(账户表,$A24,账户期初)+SUMIFS(流水收入,流水账户,$A24,流水日期,"<"&$B$3)-SUMIFS(流水支出,流水账户,$A24,流水日期,"<"&$B$3),2)) | C24: =IF(OR($A24="",C$6=""),"",ROUND(SUMIFS(流水收入,流水账户,$A24,流水日期,C$6),2)) | D24: =IF(OR($A24="",D$6=""),"",ROUND(SUMIFS(流水支出,流水账户,$A24,流水日期,D$6),2)) | E24: =IF(OR($A24="",E$6=""),"",ROUND(SUMIFS(流水收入,流水账户,$A24,流水日期,E$6),2)) | F24: =IF(OR($A24="",F$6=""),"",ROUND(SUMIFS(流水支出,流水账户,$A24,流水日期,F$6),2)) | G24: =IF(OR($A24="",G$6=""),"",ROUND(SUMIFS(流水收入,流水账户,$A24,流水日期,G$6),2)) | H24: =IF(OR($A24="",H$6=""),"",ROUND(SUMIFS(流水支出,流水账户,$A24,流水日期,H$6),2)) | I24: =IF(OR($A24="",I$6=""),"",ROUND(SUMIFS(流水收入,流水账户,$A24,流水日期,I$6),2)) | J24: =IF(OR($A24="",J$6=""),"",ROUND(SUMIFS(流水支出,流水账户,$A24,流水日期,J$6),2)) | K24: =IF(OR($A24="",K$6=""),"",ROUND(SUMIFS(流水收入,流水账户,$A24,流水日期,K$6),2)) | L24: =IF(OR($A24="",L$6=""),"",ROUND(SUMIFS(流水支出,流水账户,$A24,流水日期,L$6),2)) | M24: =IF(OR($A24="",M$6=""),"",ROUND(SUMIFS(流水收入,流水账户,$A24,流水日期,M$6),2)) | N24: =IF(OR($A24="",N$6=""),"",ROUND(SUMIFS(流水支出,流水账户,$A24,流水日期,N$6),2)) | O24: =IF(OR($A24="",O$6=""),"",ROUND(SUMIFS(流水收入,流水账户,$A24,流水日期,O$6),2)) | P24: =IF(OR($A24="",P$6=""),"",ROUND(SUMIFS(流水支出,流水账户,$A24,流水日期,P$6),2)) | Q24: =IF(OR($A24="",Q$6=""),"",ROUND(SUMIFS(流水收入,流水账户,$A24,流水日期,Q$6),2)) | R24: =IF(OR($A24="",R$6=""),"",ROUND(SUMIFS(流水支出,流水账户,$A24,流水日期,R$6),2)) | S24: =IF(OR($A24="",S$6=""),"",ROUND(SUMIFS(流水收入,流水账户,$A24,流水日期,S$6),2)) | T24: =IF(OR($A24="",T$6=""),"",ROUND(SUMIFS(流水支出,流水账户,$A24,流水日期,T$6),2)) | U24: =IF(OR($A24="",U$6=""),"",ROUND(SUMIFS(流水收入,流水账户,$A24,流水日期,U$6),2)) | V24: =IF(OR($A24="",V$6=""),"",ROUND(SUMIFS(流水支出,流水账户,$A24,流水日期,V$6),2)) | W24: =IF(OR($A24="",W$6=""),"",ROUND(SUMIFS(流水收入,流水账户,$A24,流水日期,W$6),2)) | X24: =IF(OR($A24="",X$6=""),"",ROUND(SUMIFS(流水支出,流水账户,$A24,流水日期,X$6),2)) | Y24: =IF(OR($A24="",Y$6=""),"",ROUND(SUMIFS(流水收入,流水账户,$A24,流水日期,Y$6),2)) | Z24: =IF(OR($A24="",Z$6=""),"",ROUND(SUMIFS(流水支出,流水账户,$A24,流水日期,Z$6),2)) | AA24: =IF(OR($A24="",AA$6=""),"",ROUND(SUMIFS(流水收入,流水账户,$A24,流水日期,AA$6),2)) | AB24: =IF(OR($A24="",AB$6=""),"",ROUND(SUMIFS(流水支出,流水账户,$A24,流水日期,AB$6),2)) | AC24: =IF(OR($A24="",AC$6=""),"",ROUND(SUMIFS(流水收入,流水账户,$A24,流水日期,AC$6),2)) | AD24: =IF(OR($A24="",AD$6=""),"",ROUND(SUMIFS(流水支出,流水账户,$A24,流水日期,AD$6),2)) | AE24: =IF(OR($A24="",AE$6=""),"",ROUND(SUMIFS(流水收入,流水账户,$A24,流水日期,AE$6),2)) | AF24: =IF(OR($A24="",AF$6=""),"",ROUND(SUMIFS(流水支出,流水账户,$A24,流水日期,AF$6),2)) | AG24: =IF(OR($A24="",AG$6=""),"",ROUND(SUMIFS(流水收入,流水账户,$A24,流水日期,AG$6),2)) | AH24: =IF(OR($A24="",AH$6=""),"",ROUND(SUMIFS(流水支出,流水账户,$A24,流水日期,AH$6),2)) | AI24: =IF(OR($A24="",AI$6=""),"",ROUND(SUMIFS(流水收入,流水账户,$A24,流水日期,AI$6),2)) | AJ24: =IF(OR($A24="",AJ$6=""),"",ROUND(SUMIFS(流水支出,流水账户,$A24,流水日期,AJ$6),2)) | AK24: =IF(OR($A24="",AK$6=""),"",ROUND(SUMIFS(流水收入,流水账户,$A24,流水日期,AK$6),2)) | AL24: =IF(OR($A24="",AL$6=""),"",ROUND(SUMIFS(流水支出,流水账户,$A24,流水日期,AL$6),2)) | AM24: =IF(OR($A24="",AM$6=""),"",ROUND(SUMIFS(流水收入,流水账户,$A24,流水日期,AM$6),2)) | AN24: =IF(OR($A24="",AN$6=""),"",ROUND(SUMIFS(流水支出,流水账户,$A24,流水日期,AN$6),2)) | AO24: =IF(OR($A24="",AO$6=""),"",ROUND(SUMIFS(流水收入,流水账户,$A24,流水日期,AO$6),2)) | AP24: =IF(OR($A24="",AP$6=""),"",ROUND(SUMIFS(流水支出,流水账户,$A24,流水日期,AP$6),2)) | AQ24: =IF(OR($A24="",AQ$6=""),"",ROUND(SUMIFS(流水收入,流水账户,$A24,流水日期,AQ$6),2)) | AR24: =IF(OR($A24="",AR$6=""),"",ROUND(SUMIFS(流水支出,流水账户,$A24,流水日期,AR$6),2)) | AS24: =IF(OR($A24="",AS$6=""),"",ROUND(SUMIFS(流水收入,流水账户,$A24,流水日期,AS$6),2)) | AT24: =IF(OR($A24="",AT$6=""),"",ROUND(SUMIFS(流水支出,流水账户,$A24,流水日期,AT$6),2)) | AU24: =IF(OR($A24="",AU$6=""),"",ROUND(SUMIFS(流水收入,流水账户,$A24,流水日期,AU$6),2)) | AV24: =IF(OR($A24="",AV$6=""),"",ROUND(SUMIFS(流水支出,流水账户,$A24,流水日期,AV$6),2)) | AW24: =IF(OR($A24="",AW$6=""),"",ROUND(SUMIFS(流水收入,流水账户,$A24,流水日期,AW$6),2)) | AX24: =IF(OR($A24="",AX$6=""),"",ROUND(SUMIFS(流水支出,流水账户,$A24,流水日期,AX$6),2)) | AY24: =IF(OR($A24="",AY$6=""),"",ROUND(SUMIFS(流水收入,流水账户,$A24,流水日期,AY$6),2)) | AZ24: =IF(OR($A24="",AZ$6=""),"",ROUND(SUMIFS(流水支出,流水账户,$A24,流水日期,AZ$6),2)) | BA24: =IF(OR($A24="",BA$6=""),"",ROUND(SUMIFS(流水收入,流水账户,$A24,流水日期,BA$6),2)) | BB24: =IF(OR($A24="",BB$6=""),"",ROUND(SUMIFS(流水支出,流水账户,$A24,流水日期,BB$6),2)) | BC24: =IF(OR($A24="",BC$6=""),"",ROUND(SUMIFS(流水收入,流水账户,$A24,流水日期,BC$6),2)) | BD24: =IF(OR($A24="",BD$6=""),"",ROUND(SUMIFS(流水支出,流水账户,$A24,流水日期,BD$6),2)) | BE24: =IF(OR($A24="",BE$6=""),"",ROUND(SUMIFS(流水收入,流水账户,$A24,流水日期,BE$6),2)) | BF24: =IF(OR($A24="",BF$6=""),"",ROUND(SUMIFS(流水支出,流水账户,$A24,流水日期,BF$6),2)) | BG24: =IF(OR($A24="",BG$6=""),"",ROUND(SUMIFS(流水收入,流水账户,$A24,流水日期,BG$6),2)) | BH24: =IF(OR($A24="",BH$6=""),"",ROUND(SUMIFS(流水支出,流水账户,$A24,流水日期,BH$6),2)) | BI24: =IF(OR($A24="",BI$6=""),"",ROUND(SUMIFS(流水收入,流水账户,$A24,流水日期,BI$6),2)) | BJ24: =IF(OR($A24="",BJ$6=""),"",ROUND(SUMIFS(流水支出,流水账户,$A24,流水日期,BJ$6),2)) | BK24: =IF(OR($A24="",BK$6=""),"",ROUND(SUMIFS(流水收入,流水账户,$A24,流水日期,BK$6),2)) | BL24: =IF(OR($A24="",BL$6=""),"",ROUND(SUMIFS(流水支出,流水账户,$A24,流水日期,BL$6),2)) | BM24: =IF($A24="","",ROUND(SUMIF($C$7:$BL$7,"收款",C24:BL24),2)) | BN24: =IF($A24="","",ROUND(SUMIF($C$7:$BL$7,"付款",C24:BL24),2)) | BO24: =IF($A24="","",ROUND(N($B24)+N(BM24)-N(BN24),2))
A25: =IF(基础资料!$B$22="","",基础资料!$B$22) | B25: =IF(OR($A25="",NOT(ISNUMBER($H$3))),"",ROUND(SUMIF(账户表,$A25,账户期初)+SUMIFS(流水收入,流水账户,$A25,流水日期,"<"&$B$3)-SUMIFS(流水支出,流水账户,$A25,流水日期,"<"&$B$3),2)) | C25: =IF(OR($A25="",C$6=""),"",ROUND(SUMIFS(流水收入,流水账户,$A25,流水日期,C$6),2)) | D25: =IF(OR($A25="",D$6=""),"",ROUND(SUMIFS(流水支出,流水账户,$A25,流水日期,D$6),2)) | E25: =IF(OR($A25="",E$6=""),"",ROUND(SUMIFS(流水收入,流水账户,$A25,流水日期,E$6),2)) | F25: =IF(OR($A25="",F$6=""),"",ROUND(SUMIFS(流水支出,流水账户,$A25,流水日期,F$6),2)) | G25: =IF(OR($A25="",G$6=""),"",ROUND(SUMIFS(流水收入,流水账户,$A25,流水日期,G$6),2)) | H25: =IF(OR($A25="",H$6=""),"",ROUND(SUMIFS(流水支出,流水账户,$A25,流水日期,H$6),2)) | I25: =IF(OR($A25="",I$6=""),"",ROUND(SUMIFS(流水收入,流水账户,$A25,流水日期,I$6),2)) | J25: =IF(OR($A25="",J$6=""),"",ROUND(SUMIFS(流水支出,流水账户,$A25,流水日期,J$6),2)) | K25: =IF(OR($A25="",K$6=""),"",ROUND(SUMIFS(流水收入,流水账户,$A25,流水日期,K$6),2)) | L25: =IF(OR($A25="",L$6=""),"",ROUND(SUMIFS(流水支出,流水账户,$A25,流水日期,L$6),2)) | M25: =IF(OR($A25="",M$6=""),"",ROUND(SUMIFS(流水收入,流水账户,$A25,流水日期,M$6),2)) | N25: =IF(OR($A25="",N$6=""),"",ROUND(SUMIFS(流水支出,流水账户,$A25,流水日期,N$6),2)) | O25: =IF(OR($A25="",O$6=""),"",ROUND(SUMIFS(流水收入,流水账户,$A25,流水日期,O$6),2)) | P25: =IF(OR($A25="",P$6=""),"",ROUND(SUMIFS(流水支出,流水账户,$A25,流水日期,P$6),2)) | Q25: =IF(OR($A25="",Q$6=""),"",ROUND(SUMIFS(流水收入,流水账户,$A25,流水日期,Q$6),2)) | R25: =IF(OR($A25="",R$6=""),"",ROUND(SUMIFS(流水支出,流水账户,$A25,流水日期,R$6),2)) | S25: =IF(OR($A25="",S$6=""),"",ROUND(SUMIFS(流水收入,流水账户,$A25,流水日期,S$6),2)) | T25: =IF(OR($A25="",T$6=""),"",ROUND(SUMIFS(流水支出,流水账户,$A25,流水日期,T$6),2)) | U25: =IF(OR($A25="",U$6=""),"",ROUND(SUMIFS(流水收入,流水账户,$A25,流水日期,U$6),2)) | V25: =IF(OR($A25="",V$6=""),"",ROUND(SUMIFS(流水支出,流水账户,$A25,流水日期,V$6),2)) | W25: =IF(OR($A25="",W$6=""),"",ROUND(SUMIFS(流水收入,流水账户,$A25,流水日期,W$6),2)) | X25: =IF(OR($A25="",X$6=""),"",ROUND(SUMIFS(流水支出,流水账户,$A25,流水日期,X$6),2)) | Y25: =IF(OR($A25="",Y$6=""),"",ROUND(SUMIFS(流水收入,流水账户,$A25,流水日期,Y$6),2)) | Z25: =IF(OR($A25="",Z$6=""),"",ROUND(SUMIFS(流水支出,流水账户,$A25,流水日期,Z$6),2)) | AA25: =IF(OR($A25="",AA$6=""),"",ROUND(SUMIFS(流水收入,流水账户,$A25,流水日期,AA$6),2)) | AB25: =IF(OR($A25="",AB$6=""),"",ROUND(SUMIFS(流水支出,流水账户,$A25,流水日期,AB$6),2)) | AC25: =IF(OR($A25="",AC$6=""),"",ROUND(SUMIFS(流水收入,流水账户,$A25,流水日期,AC$6),2)) | AD25: =IF(OR($A25="",AD$6=""),"",ROUND(SUMIFS(流水支出,流水账户,$A25,流水日期,AD$6),2)) | AE25: =IF(OR($A25="",AE$6=""),"",ROUND(SUMIFS(流水收入,流水账户,$A25,流水日期,AE$6),2)) | AF25: =IF(OR($A25="",AF$6=""),"",ROUND(SUMIFS(流水支出,流水账户,$A25,流水日期,AF$6),2)) | AG25: =IF(OR($A25="",AG$6=""),"",ROUND(SUMIFS(流水收入,流水账户,$A25,流水日期,AG$6),2)) | AH25: =IF(OR($A25="",AH$6=""),"",ROUND(SUMIFS(流水支出,流水账户,$A25,流水日期,AH$6),2)) | AI25: =IF(OR($A25="",AI$6=""),"",ROUND(SUMIFS(流水收入,流水账户,$A25,流水日期,AI$6),2)) | AJ25: =IF(OR($A25="",AJ$6=""),"",ROUND(SUMIFS(流水支出,流水账户,$A25,流水日期,AJ$6),2)) | AK25: =IF(OR($A25="",AK$6=""),"",ROUND(SUMIFS(流水收入,流水账户,$A25,流水日期,AK$6),2)) | AL25: =IF(OR($A25="",AL$6=""),"",ROUND(SUMIFS(流水支出,流水账户,$A25,流水日期,AL$6),2)) | AM25: =IF(OR($A25="",AM$6=""),"",ROUND(SUMIFS(流水收入,流水账户,$A25,流水日期,AM$6),2)) | AN25: =IF(OR($A25="",AN$6=""),"",ROUND(SUMIFS(流水支出,流水账户,$A25,流水日期,AN$6),2)) | AO25: =IF(OR($A25="",AO$6=""),"",ROUND(SUMIFS(流水收入,流水账户,$A25,流水日期,AO$6),2)) | AP25: =IF(OR($A25="",AP$6=""),"",ROUND(SUMIFS(流水支出,流水账户,$A25,流水日期,AP$6),2)) | AQ25: =IF(OR($A25="",AQ$6=""),"",ROUND(SUMIFS(流水收入,流水账户,$A25,流水日期,AQ$6),2)) | AR25: =IF(OR($A25="",AR$6=""),"",ROUND(SUMIFS(流水支出,流水账户,$A25,流水日期,AR$6),2)) | AS25: =IF(OR($A25="",AS$6=""),"",ROUND(SUMIFS(流水收入,流水账户,$A25,流水日期,AS$6),2)) | AT25: =IF(OR($A25="",AT$6=""),"",ROUND(SUMIFS(流水支出,流水账户,$A25,流水日期,AT$6),2)) | AU25: =IF(OR($A25="",AU$6=""),"",ROUND(SUMIFS(流水收入,流水账户,$A25,流水日期,AU$6),2)) | AV25: =IF(OR($A25="",AV$6=""),"",ROUND(SUMIFS(流水支出,流水账户,$A25,流水日期,AV$6),2)) | AW25: =IF(OR($A25="",AW$6=""),"",ROUND(SUMIFS(流水收入,流水账户,$A25,流水日期,AW$6),2)) | AX25: =IF(OR($A25="",AX$6=""),"",ROUND(SUMIFS(流水支出,流水账户,$A25,流水日期,AX$6),2)) | AY25: =IF(OR($A25="",AY$6=""),"",ROUND(SUMIFS(流水收入,流水账户,$A25,流水日期,AY$6),2)) | AZ25: =IF(OR($A25="",AZ$6=""),"",ROUND(SUMIFS(流水支出,流水账户,$A25,流水日期,AZ$6),2)) | BA25: =IF(OR($A25="",BA$6=""),"",ROUND(SUMIFS(流水收入,流水账户,$A25,流水日期,BA$6),2)) | BB25: =IF(OR($A25="",BB$6=""),"",ROUND(SUMIFS(流水支出,流水账户,$A25,流水日期,BB$6),2)) | BC25: =IF(OR($A25="",BC$6=""),"",ROUND(SUMIFS(流水收入,流水账户,$A25,流水日期,BC$6),2)) | BD25: =IF(OR($A25="",BD$6=""),"",ROUND(SUMIFS(流水支出,流水账户,$A25,流水日期,BD$6),2)) | BE25: =IF(OR($A25="",BE$6=""),"",ROUND(SUMIFS(流水收入,流水账户,$A25,流水日期,BE$6),2)) | BF25: =IF(OR($A25="",BF$6=""),"",ROUND(SUMIFS(流水支出,流水账户,$A25,流水日期,BF$6),2)) | BG25: =IF(OR($A25="",BG$6=""),"",ROUND(SUMIFS(流水收入,流水账户,$A25,流水日期,BG$6),2)) | BH25: =IF(OR($A25="",BH$6=""),"",ROUND(SUMIFS(流水支出,流水账户,$A25,流水日期,BH$6),2)) | BI25: =IF(OR($A25="",BI$6=""),"",ROUND(SUMIFS(流水收入,流水账户,$A25,流水日期,BI$6),2)) | BJ25: =IF(OR($A25="",BJ$6=""),"",ROUND(SUMIFS(流水支出,流水账户,$A25,流水日期,BJ$6),2)) | BK25: =IF(OR($A25="",BK$6=""),"",ROUND(SUMIFS(流水收入,流水账户,$A25,流水日期,BK$6),2)) | BL25: =IF(OR($A25="",BL$6=""),"",ROUND(SUMIFS(流水支出,流水账户,$A25,流水日期,BL$6),2)) | BM25: =IF($A25="","",ROUND(SUMIF($C$7:$BL$7,"收款",C25:BL25),2)) | BN25: =IF($A25="","",ROUND(SUMIF($C$7:$BL$7,"付款",C25:BL25),2)) | BO25: =IF($A25="","",ROUND(N($B25)+N(BM25)-N(BN25),2))
A26: =IF(基础资料!$B$23="","",基础资料!$B$23) | B26: =IF(OR($A26="",NOT(ISNUMBER($H$3))),"",ROUND(SUMIF(账户表,$A26,账户期初)+SUMIFS(流水收入,流水账户,$A26,流水日期,"<"&$B$3)-SUMIFS(流水支出,流水账户,$A26,流水日期,"<"&$B$3),2)) | C26: =IF(OR($A26="",C$6=""),"",ROUND(SUMIFS(流水收入,流水账户,$A26,流水日期,C$6),2)) | D26: =IF(OR($A26="",D$6=""),"",ROUND(SUMIFS(流水支出,流水账户,$A26,流水日期,D$6),2)) | E26: =IF(OR($A26="",E$6=""),"",ROUND(SUMIFS(流水收入,流水账户,$A26,流水日期,E$6),2)) | F26: =IF(OR($A26="",F$6=""),"",ROUND(SUMIFS(流水支出,流水账户,$A26,流水日期,F$6),2)) | G26: =IF(OR($A26="",G$6=""),"",ROUND(SUMIFS(流水收入,流水账户,$A26,流水日期,G$6),2)) | H26: =IF(OR($A26="",H$6=""),"",ROUND(SUMIFS(流水支出,流水账户,$A26,流水日期,H$6),2)) | I26: =IF(OR($A26="",I$6=""),"",ROUND(SUMIFS(流水收入,流水账户,$A26,流水日期,I$6),2)) | J26: =IF(OR($A26="",J$6=""),"",ROUND(SUMIFS(流水支出,流水账户,$A26,流水日期,J$6),2)) | K26: =IF(OR($A26="",K$6=""),"",ROUND(SUMIFS(流水收入,流水账户,$A26,流水日期,K$6),2)) | L26: =IF(OR($A26="",L$6=""),"",ROUND(SUMIFS(流水支出,流水账户,$A26,流水日期,L$6),2)) | M26: =IF(OR($A26="",M$6=""),"",ROUND(SUMIFS(流水收入,流水账户,$A26,流水日期,M$6),2)) | N26: =IF(OR($A26="",N$6=""),"",ROUND(SUMIFS(流水支出,流水账户,$A26,流水日期,N$6),2)) | O26: =IF(OR($A26="",O$6=""),"",ROUND(SUMIFS(流水收入,流水账户,$A26,流水日期,O$6),2)) | P26: =IF(OR($A26="",P$6=""),"",ROUND(SUMIFS(流水支出,流水账户,$A26,流水日期,P$6),2)) | Q26: =IF(OR($A26="",Q$6=""),"",ROUND(SUMIFS(流水收入,流水账户,$A26,流水日期,Q$6),2)) | R26: =IF(OR($A26="",R$6=""),"",ROUND(SUMIFS(流水支出,流水账户,$A26,流水日期,R$6),2)) | S26: =IF(OR($A26="",S$6=""),"",ROUND(SUMIFS(流水收入,流水账户,$A26,流水日期,S$6),2)) | T26: =IF(OR($A26="",T$6=""),"",ROUND(SUMIFS(流水支出,流水账户,$A26,流水日期,T$6),2)) | U26: =IF(OR($A26="",U$6=""),"",ROUND(SUMIFS(流水收入,流水账户,$A26,流水日期,U$6),2)) | V26: =IF(OR($A26="",V$6=""),"",ROUND(SUMIFS(流水支出,流水账户,$A26,流水日期,V$6),2)) | W26: =IF(OR($A26="",W$6=""),"",ROUND(SUMIFS(流水收入,流水账户,$A26,流水日期,W$6),2)) | X26: =IF(OR($A26="",X$6=""),"",ROUND(SUMIFS(流水支出,流水账户,$A26,流水日期,X$6),2)) | Y26: =IF(OR($A26="",Y$6=""),"",ROUND(SUMIFS(流水收入,流水账户,$A26,流水日期,Y$6),2)) | Z26: =IF(OR($A26="",Z$6=""),"",ROUND(SUMIFS(流水支出,流水账户,$A26,流水日期,Z$6),2)) | AA26: =IF(OR($A26="",AA$6=""),"",ROUND(SUMIFS(流水收入,流水账户,$A26,流水日期,AA$6),2)) | AB26: =IF(OR($A26="",AB$6=""),"",ROUND(SUMIFS(流水支出,流水账户,$A26,流水日期,AB$6),2)) | AC26: =IF(OR($A26="",AC$6=""),"",ROUND(SUMIFS(流水收入,流水账户,$A26,流水日期,AC$6),2)) | AD26: =IF(OR($A26="",AD$6=""),"",ROUND(SUMIFS(流水支出,流水账户,$A26,流水日期,AD$6),2)) | AE26: =IF(OR($A26="",AE$6=""),"",ROUND(SUMIFS(流水收入,流水账户,$A26,流水日期,AE$6),2)) | AF26: =IF(OR($A26="",AF$6=""),"",ROUND(SUMIFS(流水支出,流水账户,$A26,流水日期,AF$6),2)) | AG26: =IF(OR($A26="",AG$6=""),"",ROUND(SUMIFS(流水收入,流水账户,$A26,流水日期,AG$6),2)) | AH26: =IF(OR($A26="",AH$6=""),"",ROUND(SUMIFS(流水支出,流水账户,$A26,流水日期,AH$6),2)) | AI26: =IF(OR($A26="",AI$6=""),"",ROUND(SUMIFS(流水收入,流水账户,$A26,流水日期,AI$6),2)) | AJ26: =IF(OR($A26="",AJ$6=""),"",ROUND(SUMIFS(流水支出,流水账户,$A26,流水日期,AJ$6),2)) | AK26: =IF(OR($A26="",AK$6=""),"",ROUND(SUMIFS(流水收入,流水账户,$A26,流水日期,AK$6),2)) | AL26: =IF(OR($A26="",AL$6=""),"",ROUND(SUMIFS(流水支出,流水账户,$A26,流水日期,AL$6),2)) | AM26: =IF(OR($A26="",AM$6=""),"",ROUND(SUMIFS(流水收入,流水账户,$A26,流水日期,AM$6),2)) | AN26: =IF(OR($A26="",AN$6=""),"",ROUND(SUMIFS(流水支出,流水账户,$A26,流水日期,AN$6),2)) | AO26: =IF(OR($A26="",AO$6=""),"",ROUND(SUMIFS(流水收入,流水账户,$A26,流水日期,AO$6),2)) | AP26: =IF(OR($A26="",AP$6=""),"",ROUND(SUMIFS(流水支出,流水账户,$A26,流水日期,AP$6),2)) | AQ26: =IF(OR($A26="",AQ$6=""),"",ROUND(SUMIFS(流水收入,流水账户,$A26,流水日期,AQ$6),2)) | AR26: =IF(OR($A26="",AR$6=""),"",ROUND(SUMIFS(流水支出,流水账户,$A26,流水日期,AR$6),2)) | AS26: =IF(OR($A26="",AS$6=""),"",ROUND(SUMIFS(流水收入,流水账户,$A26,流水日期,AS$6),2)) | AT26: =IF(OR($A26="",AT$6=""),"",ROUND(SUMIFS(流水支出,流水账户,$A26,流水日期,AT$6),2)) | AU26: =IF(OR($A26="",AU$6=""),"",ROUND(SUMIFS(流水收入,流水账户,$A26,流水日期,AU$6),2)) | AV26: =IF(OR($A26="",AV$6=""),"",ROUND(SUMIFS(流水支出,流水账户,$A26,流水日期,AV$6),2)) | AW26: =IF(OR($A26="",AW$6=""),"",ROUND(SUMIFS(流水收入,流水账户,$A26,流水日期,AW$6),2)) | AX26: =IF(OR($A26="",AX$6=""),"",ROUND(SUMIFS(流水支出,流水账户,$A26,流水日期,AX$6),2)) | AY26: =IF(OR($A26="",AY$6=""),"",ROUND(SUMIFS(流水收入,流水账户,$A26,流水日期,AY$6),2)) | AZ26: =IF(OR($A26="",AZ$6=""),"",ROUND(SUMIFS(流水支出,流水账户,$A26,流水日期,AZ$6),2)) | BA26: =IF(OR($A26="",BA$6=""),"",ROUND(SUMIFS(流水收入,流水账户,$A26,流水日期,BA$6),2)) | BB26: =IF(OR($A26="",BB$6=""),"",ROUND(SUMIFS(流水支出,流水账户,$A26,流水日期,BB$6),2)) | BC26: =IF(OR($A26="",BC$6=""),"",ROUND(SUMIFS(流水收入,流水账户,$A26,流水日期,BC$6),2)) | BD26: =IF(OR($A26="",BD$6=""),"",ROUND(SUMIFS(流水支出,流水账户,$A26,流水日期,BD$6),2)) | BE26: =IF(OR($A26="",BE$6=""),"",ROUND(SUMIFS(流水收入,流水账户,$A26,流水日期,BE$6),2)) | BF26: =IF(OR($A26="",BF$6=""),"",ROUND(SUMIFS(流水支出,流水账户,$A26,流水日期,BF$6),2)) | BG26: =IF(OR($A26="",BG$6=""),"",ROUND(SUMIFS(流水收入,流水账户,$A26,流水日期,BG$6),2)) | BH26: =IF(OR($A26="",BH$6=""),"",ROUND(SUMIFS(流水支出,流水账户,$A26,流水日期,BH$6),2)) | BI26: =IF(OR($A26="",BI$6=""),"",ROUND(SUMIFS(流水收入,流水账户,$A26,流水日期,BI$6),2)) | BJ26: =IF(OR($A26="",BJ$6=""),"",ROUND(SUMIFS(流水支出,流水账户,$A26,流水日期,BJ$6),2)) | BK26: =IF(OR($A26="",BK$6=""),"",ROUND(SUMIFS(流水收入,流水账户,$A26,流水日期,BK$6),2)) | BL26: =IF(OR($A26="",BL$6=""),"",ROUND(SUMIFS(流水支出,流水账户,$A26,流水日期,BL$6),2)) | BM26: =IF($A26="","",ROUND(SUMIF($C$7:$BL$7,"收款",C26:BL26),2)) | BN26: =IF($A26="","",ROUND(SUMIF($C$7:$BL$7,"付款",C26:BL26),2)) | BO26: =IF($A26="","",ROUND(N($B26)+N(BM26)-N(BN26),2))
A27: =IF(基础资料!$B$24="","",基础资料!$B$24) | B27: =IF(OR($A27="",NOT(ISNUMBER($H$3))),"",ROUND(SUMIF(账户表,$A27,账户期初)+SUMIFS(流水收入,流水账户,$A27,流水日期,"<"&$B$3)-SUMIFS(流水支出,流水账户,$A27,流水日期,"<"&$B$3),2)) | C27: =IF(OR($A27="",C$6=""),"",ROUND(SUMIFS(流水收入,流水账户,$A27,流水日期,C$6),2)) | D27: =IF(OR($A27="",D$6=""),"",ROUND(SUMIFS(流水支出,流水账户,$A27,流水日期,D$6),2)) | E27: =IF(OR($A27="",E$6=""),"",ROUND(SUMIFS(流水收入,流水账户,$A27,流水日期,E$6),2)) | F27: =IF(OR($A27="",F$6=""),"",ROUND(SUMIFS(流水支出,流水账户,$A27,流水日期,F$6),2)) | G27: =IF(OR($A27="",G$6=""),"",ROUND(SUMIFS(流水收入,流水账户,$A27,流水日期,G$6),2)) | H27: =IF(OR($A27="",H$6=""),"",ROUND(SUMIFS(流水支出,流水账户,$A27,流水日期,H$6),2)) | I27: =IF(OR($A27="",I$6=""),"",ROUND(SUMIFS(流水收入,流水账户,$A27,流水日期,I$6),2)) | J27: =IF(OR($A27="",J$6=""),"",ROUND(SUMIFS(流水支出,流水账户,$A27,流水日期,J$6),2)) | K27: =IF(OR($A27="",K$6=""),"",ROUND(SUMIFS(流水收入,流水账户,$A27,流水日期,K$6),2)) | L27: =IF(OR($A27="",L$6=""),"",ROUND(SUMIFS(流水支出,流水账户,$A27,流水日期,L$6),2)) | M27: =IF(OR($A27="",M$6=""),"",ROUND(SUMIFS(流水收入,流水账户,$A27,流水日期,M$6),2)) | N27: =IF(OR($A27="",N$6=""),"",ROUND(SUMIFS(流水支出,流水账户,$A27,流水日期,N$6),2)) | O27: =IF(OR($A27="",O$6=""),"",ROUND(SUMIFS(流水收入,流水账户,$A27,流水日期,O$6),2)) | P27: =IF(OR($A27="",P$6=""),"",ROUND(SUMIFS(流水支出,流水账户,$A27,流水日期,P$6),2)) | Q27: =IF(OR($A27="",Q$6=""),"",ROUND(SUMIFS(流水收入,流水账户,$A27,流水日期,Q$6),2)) | R27: =IF(OR($A27="",R$6=""),"",ROUND(SUMIFS(流水支出,流水账户,$A27,流水日期,R$6),2)) | S27: =IF(OR($A27="",S$6=""),"",ROUND(SUMIFS(流水收入,流水账户,$A27,流水日期,S$6),2)) | T27: =IF(OR($A27="",T$6=""),"",ROUND(SUMIFS(流水支出,流水账户,$A27,流水日期,T$6),2)) | U27: =IF(OR($A27="",U$6=""),"",ROUND(SUMIFS(流水收入,流水账户,$A27,流水日期,U$6),2)) | V27: =IF(OR($A27="",V$6=""),"",ROUND(SUMIFS(流水支出,流水账户,$A27,流水日期,V$6),2)) | W27: =IF(OR($A27="",W$6=""),"",ROUND(SUMIFS(流水收入,流水账户,$A27,流水日期,W$6),2)) | X27: =IF(OR($A27="",X$6=""),"",ROUND(SUMIFS(流水支出,流水账户,$A27,流水日期,X$6),2)) | Y27: =IF(OR($A27="",Y$6=""),"",ROUND(SUMIFS(流水收入,流水账户,$A27,流水日期,Y$6),2)) | Z27: =IF(OR($A27="",Z$6=""),"",ROUND(SUMIFS(流水支出,流水账户,$A27,流水日期,Z$6),2)) | AA27: =IF(OR($A27="",AA$6=""),"",ROUND(SUMIFS(流水收入,流水账户,$A27,流水日期,AA$6),2)) | AB27: =IF(OR($A27="",AB$6=""),"",ROUND(SUMIFS(流水支出,流水账户,$A27,流水日期,AB$6),2)) | AC27: =IF(OR($A27="",AC$6=""),"",ROUND(SUMIFS(流水收入,流水账户,$A27,流水日期,AC$6),2)) | AD27: =IF(OR($A27="",AD$6=""),"",ROUND(SUMIFS(流水支出,流水账户,$A27,流水日期,AD$6),2)) | AE27: =IF(OR($A27="",AE$6=""),"",ROUND(SUMIFS(流水收入,流水账户,$A27,流水日期,AE$6),2)) | AF27: =IF(OR($A27="",AF$6=""),"",ROUND(SUMIFS(流水支出,流水账户,$A27,流水日期,AF$6),2)) | AG27: =IF(OR($A27="",AG$6=""),"",ROUND(SUMIFS(流水收入,流水账户,$A27,流水日期,AG$6),2)) | AH27: =IF(OR($A27="",AH$6=""),"",ROUND(SUMIFS(流水支出,流水账户,$A27,流水日期,AH$6),2)) | AI27: =IF(OR($A27="",AI$6=""),"",ROUND(SUMIFS(流水收入,流水账户,$A27,流水日期,AI$6),2)) | AJ27: =IF(OR($A27="",AJ$6=""),"",ROUND(SUMIFS(流水支出,流水账户,$A27,流水日期,AJ$6),2)) | AK27: =IF(OR($A27="",AK$6=""),"",ROUND(SUMIFS(流水收入,流水账户,$A27,流水日期,AK$6),2)) | AL27: =IF(OR($A27="",AL$6=""),"",ROUND(SUMIFS(流水支出,流水账户,$A27,流水日期,AL$6),2)) | AM27: =IF(OR($A27="",AM$6=""),"",ROUND(SUMIFS(流水收入,流水账户,$A27,流水日期,AM$6),2)) | AN27: =IF(OR($A27="",AN$6=""),"",ROUND(SUMIFS(流水支出,流水账户,$A27,流水日期,AN$6),2)) | AO27: =IF(OR($A27="",AO$6=""),"",ROUND(SUMIFS(流水收入,流水账户,$A27,流水日期,AO$6),2)) | AP27: =IF(OR($A27="",AP$6=""),"",ROUND(SUMIFS(流水支出,流水账户,$A27,流水日期,AP$6),2)) | AQ27: =IF(OR($A27="",AQ$6=""),"",ROUND(SUMIFS(流水收入,流水账户,$A27,流水日期,AQ$6),2)) | AR27: =IF(OR($A27="",AR$6=""),"",ROUND(SUMIFS(流水支出,流水账户,$A27,流水日期,AR$6),2)) | AS27: =IF(OR($A27="",AS$6=""),"",ROUND(SUMIFS(流水收入,流水账户,$A27,流水日期,AS$6),2)) | AT27: =IF(OR($A27="",AT$6=""),"",ROUND(SUMIFS(流水支出,流水账户,$A27,流水日期,AT$6),2)) | AU27: =IF(OR($A27="",AU$6=""),"",ROUND(SUMIFS(流水收入,流水账户,$A27,流水日期,AU$6),2)) | AV27: =IF(OR($A27="",AV$6=""),"",ROUND(SUMIFS(流水支出,流水账户,$A27,流水日期,AV$6),2)) | AW27: =IF(OR($A27="",AW$6=""),"",ROUND(SUMIFS(流水收入,流水账户,$A27,流水日期,AW$6),2)) | AX27: =IF(OR($A27="",AX$6=""),"",ROUND(SUMIFS(流水支出,流水账户,$A27,流水日期,AX$6),2)) | AY27: =IF(OR($A27="",AY$6=""),"",ROUND(SUMIFS(流水收入,流水账户,$A27,流水日期,AY$6),2)) | AZ27: =IF(OR($A27="",AZ$6=""),"",ROUND(SUMIFS(流水支出,流水账户,$A27,流水日期,AZ$6),2)) | BA27: =IF(OR($A27="",BA$6=""),"",ROUND(SUMIFS(流水收入,流水账户,$A27,流水日期,BA$6),2)) | BB27: =IF(OR($A27="",BB$6=""),"",ROUND(SUMIFS(流水支出,流水账户,$A27,流水日期,BB$6),2)) | BC27: =IF(OR($A27="",BC$6=""),"",ROUND(SUMIFS(流水收入,流水账户,$A27,流水日期,BC$6),2)) | BD27: =IF(OR($A27="",BD$6=""),"",ROUND(SUMIFS(流水支出,流水账户,$A27,流水日期,BD$6),2)) | BE27: =IF(OR($A27="",BE$6=""),"",ROUND(SUMIFS(流水收入,流水账户,$A27,流水日期,BE$6),2)) | BF27: =IF(OR($A27="",BF$6=""),"",ROUND(SUMIFS(流水支出,流水账户,$A27,流水日期,BF$6),2)) | BG27: =IF(OR($A27="",BG$6=""),"",ROUND(SUMIFS(流水收入,流水账户,$A27,流水日期,BG$6),2)) | BH27: =IF(OR($A27="",BH$6=""),"",ROUND(SUMIFS(流水支出,流水账户,$A27,流水日期,BH$6),2)) | BI27: =IF(OR($A27="",BI$6=""),"",ROUND(SUMIFS(流水收入,流水账户,$A27,流水日期,BI$6),2)) | BJ27: =IF(OR($A27="",BJ$6=""),"",ROUND(SUMIFS(流水支出,流水账户,$A27,流水日期,BJ$6),2)) | BK27: =IF(OR($A27="",BK$6=""),"",ROUND(SUMIFS(流水收入,流水账户,$A27,流水日期,BK$6),2)) | BL27: =IF(OR($A27="",BL$6=""),"",ROUND(SUMIFS(流水支出,流水账户,$A27,流水日期,BL$6),2)) | BM27: =IF($A27="","",ROUND(SUMIF($C$7:$BL$7,"收款",C27:BL27),2)) | BN27: =IF($A27="","",ROUND(SUMIF($C$7:$BL$7,"付款",C27:BL27),2)) | BO27: =IF($A27="","",ROUND(N($B27)+N(BM27)-N(BN27),2))
A28: =IF(基础资料!$B$25="","",基础资料!$B$25) | B28: =IF(OR($A28="",NOT(ISNUMBER($H$3))),"",ROUND(SUMIF(账户表,$A28,账户期初)+SUMIFS(流水收入,流水账户,$A28,流水日期,"<"&$B$3)-SUMIFS(流水支出,流水账户,$A28,流水日期,"<"&$B$3),2)) | C28: =IF(OR($A28="",C$6=""),"",ROUND(SUMIFS(流水收入,流水账户,$A28,流水日期,C$6),2)) | D28: =IF(OR($A28="",D$6=""),"",ROUND(SUMIFS(流水支出,流水账户,$A28,流水日期,D$6),2)) | E28: =IF(OR($A28="",E$6=""),"",ROUND(SUMIFS(流水收入,流水账户,$A28,流水日期,E$6),2)) | F28: =IF(OR($A28="",F$6=""),"",ROUND(SUMIFS(流水支出,流水账户,$A28,流水日期,F$6),2)) | G28: =IF(OR($A28="",G$6=""),"",ROUND(SUMIFS(流水收入,流水账户,$A28,流水日期,G$6),2)) | H28: =IF(OR($A28="",H$6=""),"",ROUND(SUMIFS(流水支出,流水账户,$A28,流水日期,H$6),2)) | I28: =IF(OR($A28="",I$6=""),"",ROUND(SUMIFS(流水收入,流水账户,$A28,流水日期,I$6),2)) | J28: =IF(OR($A28="",J$6=""),"",ROUND(SUMIFS(流水支出,流水账户,$A28,流水日期,J$6),2)) | K28: =IF(OR($A28="",K$6=""),"",ROUND(SUMIFS(流水收入,流水账户,$A28,流水日期,K$6),2)) | L28: =IF(OR($A28="",L$6=""),"",ROUND(SUMIFS(流水支出,流水账户,$A28,流水日期,L$6),2)) | M28: =IF(OR($A28="",M$6=""),"",ROUND(SUMIFS(流水收入,流水账户,$A28,流水日期,M$6),2)) | N28: =IF(OR($A28="",N$6=""),"",ROUND(SUMIFS(流水支出,流水账户,$A28,流水日期,N$6),2)) | O28: =IF(OR($A28="",O$6=""),"",ROUND(SUMIFS(流水收入,流水账户,$A28,流水日期,O$6),2)) | P28: =IF(OR($A28="",P$6=""),"",ROUND(SUMIFS(流水支出,流水账户,$A28,流水日期,P$6),2)) | Q28: =IF(OR($A28="",Q$6=""),"",ROUND(SUMIFS(流水收入,流水账户,$A28,流水日期,Q$6),2)) | R28: =IF(OR($A28="",R$6=""),"",ROUND(SUMIFS(流水支出,流水账户,$A28,流水日期,R$6),2)) | S28: =IF(OR($A28="",S$6=""),"",ROUND(SUMIFS(流水收入,流水账户,$A28,流水日期,S$6),2)) | T28: =IF(OR($A28="",T$6=""),"",ROUND(SUMIFS(流水支出,流水账户,$A28,流水日期,T$6),2)) | U28: =IF(OR($A28="",U$6=""),"",ROUND(SUMIFS(流水收入,流水账户,$A28,流水日期,U$6),2)) | V28: =IF(OR($A28="",V$6=""),"",ROUND(SUMIFS(流水支出,流水账户,$A28,流水日期,V$6),2)) | W28: =IF(OR($A28="",W$6=""),"",ROUND(SUMIFS(流水收入,流水账户,$A28,流水日期,W$6),2)) | X28: =IF(OR($A28="",X$6=""),"",ROUND(SUMIFS(流水支出,流水账户,$A28,流水日期,X$6),2)) | Y28: =IF(OR($A28="",Y$6=""),"",ROUND(SUMIFS(流水收入,流水账户,$A28,流水日期,Y$6),2)) | Z28: =IF(OR($A28="",Z$6=""),"",ROUND(SUMIFS(流水支出,流水账户,$A28,流水日期,Z$6),2)) | AA28: =IF(OR($A28="",AA$6=""),"",ROUND(SUMIFS(流水收入,流水账户,$A28,流水日期,AA$6),2)) | AB28: =IF(OR($A28="",AB$6=""),"",ROUND(SUMIFS(流水支出,流水账户,$A28,流水日期,AB$6),2)) | AC28: =IF(OR($A28="",AC$6=""),"",ROUND(SUMIFS(流水收入,流水账户,$A28,流水日期,AC$6),2)) | AD28: =IF(OR($A28="",AD$6=""),"",ROUND(SUMIFS(流水支出,流水账户,$A28,流水日期,AD$6),2)) | AE28: =IF(OR($A28="",AE$6=""),"",ROUND(SUMIFS(流水收入,流水账户,$A28,流水日期,AE$6),2)) | AF28: =IF(OR($A28="",AF$6=""),"",ROUND(SUMIFS(流水支出,流水账户,$A28,流水日期,AF$6),2)) | AG28: =IF(OR($A28="",AG$6=""),"",ROUND(SUMIFS(流水收入,流水账户,$A28,流水日期,AG$6),2)) | AH28: =IF(OR($A28="",AH$6=""),"",ROUND(SUMIFS(流水支出,流水账户,$A28,流水日期,AH$6),2)) | AI28: =IF(OR($A28="",AI$6=""),"",ROUND(SUMIFS(流水收入,流水账户,$A28,流水日期,AI$6),2)) | AJ28: =IF(OR($A28="",AJ$6=""),"",ROUND(SUMIFS(流水支出,流水账户,$A28,流水日期,AJ$6),2)) | AK28: =IF(OR($A28="",AK$6=""),"",ROUND(SUMIFS(流水收入,流水账户,$A28,流水日期,AK$6),2)) | AL28: =IF(OR($A28="",AL$6=""),"",ROUND(SUMIFS(流水支出,流水账户,$A28,流水日期,AL$6),2)) | AM28: =IF(OR($A28="",AM$6=""),"",ROUND(SUMIFS(流水收入,流水账户,$A28,流水日期,AM$6),2)) | AN28: =IF(OR($A28="",AN$6=""),"",ROUND(SUMIFS(流水支出,流水账户,$A28,流水日期,AN$6),2)) | AO28: =IF(OR($A28="",AO$6=""),"",ROUND(SUMIFS(流水收入,流水账户,$A28,流水日期,AO$6),2)) | AP28: =IF(OR($A28="",AP$6=""),"",ROUND(SUMIFS(流水支出,流水账户,$A28,流水日期,AP$6),2)) | AQ28: =IF(OR($A28="",AQ$6=""),"",ROUND(SUMIFS(流水收入,流水账户,$A28,流水日期,AQ$6),2)) | AR28: =IF(OR($A28="",AR$6=""),"",ROUND(SUMIFS(流水支出,流水账户,$A28,流水日期,AR$6),2)) | AS28: =IF(OR($A28="",AS$6=""),"",ROUND(SUMIFS(流水收入,流水账户,$A28,流水日期,AS$6),2)) | AT28: =IF(OR($A28="",AT$6=""),"",ROUND(SUMIFS(流水支出,流水账户,$A28,流水日期,AT$6),2)) | AU28: =IF(OR($A28="",AU$6=""),"",ROUND(SUMIFS(流水收入,流水账户,$A28,流水日期,AU$6),2)) | AV28: =IF(OR($A28="",AV$6=""),"",ROUND(SUMIFS(流水支出,流水账户,$A28,流水日期,AV$6),2)) | AW28: =IF(OR($A28="",AW$6=""),"",ROUND(SUMIFS(流水收入,流水账户,$A28,流水日期,AW$6),2)) | AX28: =IF(OR($A28="",AX$6=""),"",ROUND(SUMIFS(流水支出,流水账户,$A28,流水日期,AX$6),2)) | AY28: =IF(OR($A28="",AY$6=""),"",ROUND(SUMIFS(流水收入,流水账户,$A28,流水日期,AY$6),2)) | AZ28: =IF(OR($A28="",AZ$6=""),"",ROUND(SUMIFS(流水支出,流水账户,$A28,流水日期,AZ$6),2)) | BA28: =IF(OR($A28="",BA$6=""),"",ROUND(SUMIFS(流水收入,流水账户,$A28,流水日期,BA$6),2)) | BB28: =IF(OR($A28="",BB$6=""),"",ROUND(SUMIFS(流水支出,流水账户,$A28,流水日期,BB$6),2)) | BC28: =IF(OR($A28="",BC$6=""),"",ROUND(SUMIFS(流水收入,流水账户,$A28,流水日期,BC$6),2)) | BD28: =IF(OR($A28="",BD$6=""),"",ROUND(SUMIFS(流水支出,流水账户,$A28,流水日期,BD$6),2)) | BE28: =IF(OR($A28="",BE$6=""),"",ROUND(SUMIFS(流水收入,流水账户,$A28,流水日期,BE$6),2)) | BF28: =IF(OR($A28="",BF$6=""),"",ROUND(SUMIFS(流水支出,流水账户,$A28,流水日期,BF$6),2)) | BG28: =IF(OR($A28="",BG$6=""),"",ROUND(SUMIFS(流水收入,流水账户,$A28,流水日期,BG$6),2)) | BH28: =IF(OR($A28="",BH$6=""),"",ROUND(SUMIFS(流水支出,流水账户,$A28,流水日期,BH$6),2)) | BI28: =IF(OR($A28="",BI$6=""),"",ROUND(SUMIFS(流水收入,流水账户,$A28,流水日期,BI$6),2)) | BJ28: =IF(OR($A28="",BJ$6=""),"",ROUND(SUMIFS(流水支出,流水账户,$A28,流水日期,BJ$6),2)) | BK28: =IF(OR($A28="",BK$6=""),"",ROUND(SUMIFS(流水收入,流水账户,$A28,流水日期,BK$6),2)) | BL28: =IF(OR($A28="",BL$6=""),"",ROUND(SUMIFS(流水支出,流水账户,$A28,流水日期,BL$6),2)) | BM28: =IF($A28="","",ROUND(SUMIF($C$7:$BL$7,"收款",C28:BL28),2)) | BN28: =IF($A28="","",ROUND(SUMIF($C$7:$BL$7,"付款",C28:BL28),2)) | BO28: =IF($A28="","",ROUND(N($B28)+N(BM28)-N(BN28),2))
A29: =IF(基础资料!$B$26="","",基础资料!$B$26) | B29: =IF(OR($A29="",NOT(ISNUMBER($H$3))),"",ROUND(SUMIF(账户表,$A29,账户期初)+SUMIFS(流水收入,流水账户,$A29,流水日期,"<"&$B$3)-SUMIFS(流水支出,流水账户,$A29,流水日期,"<"&$B$3),2)) | C29: =IF(OR($A29="",C$6=""),"",ROUND(SUMIFS(流水收入,流水账户,$A29,流水日期,C$6),2)) | D29: =IF(OR($A29="",D$6=""),"",ROUND(SUMIFS(流水支出,流水账户,$A29,流水日期,D$6),2)) | E29: =IF(OR($A29="",E$6=""),"",ROUND(SUMIFS(流水收入,流水账户,$A29,流水日期,E$6),2)) | F29: =IF(OR($A29="",F$6=""),"",ROUND(SUMIFS(流水支出,流水账户,$A29,流水日期,F$6),2)) | G29: =IF(OR($A29="",G$6=""),"",ROUND(SUMIFS(流水收入,流水账户,$A29,流水日期,G$6),2)) | H29: =IF(OR($A29="",H$6=""),"",ROUND(SUMIFS(流水支出,流水账户,$A29,流水日期,H$6),2)) | I29: =IF(OR($A29="",I$6=""),"",ROUND(SUMIFS(流水收入,流水账户,$A29,流水日期,I$6),2)) | J29: =IF(OR($A29="",J$6=""),"",ROUND(SUMIFS(流水支出,流水账户,$A29,流水日期,J$6),2)) | K29: =IF(OR($A29="",K$6=""),"",ROUND(SUMIFS(流水收入,流水账户,$A29,流水日期,K$6),2)) | L29: =IF(OR($A29="",L$6=""),"",ROUND(SUMIFS(流水支出,流水账户,$A29,流水日期,L$6),2)) | M29: =IF(OR($A29="",M$6=""),"",ROUND(SUMIFS(流水收入,流水账户,$A29,流水日期,M$6),2)) | N29: =IF(OR($A29="",N$6=""),"",ROUND(SUMIFS(流水支出,流水账户,$A29,流水日期,N$6),2)) | O29: =IF(OR($A29="",O$6=""),"",ROUND(SUMIFS(流水收入,流水账户,$A29,流水日期,O$6),2)) | P29: =IF(OR($A29="",P$6=""),"",ROUND(SUMIFS(流水支出,流水账户,$A29,流水日期,P$6),2)) | Q29: =IF(OR($A29="",Q$6=""),"",ROUND(SUMIFS(流水收入,流水账户,$A29,流水日期,Q$6),2)) | R29: =IF(OR($A29="",R$6=""),"",ROUND(SUMIFS(流水支出,流水账户,$A29,流水日期,R$6),2)) | S29: =IF(OR($A29="",S$6=""),"",ROUND(SUMIFS(流水收入,流水账户,$A29,流水日期,S$6),2)) | T29: =IF(OR($A29="",T$6=""),"",ROUND(SUMIFS(流水支出,流水账户,$A29,流水日期,T$6),2)) | U29: =IF(OR($A29="",U$6=""),"",ROUND(SUMIFS(流水收入,流水账户,$A29,流水日期,U$6),2)) | V29: =IF(OR($A29="",V$6=""),"",ROUND(SUMIFS(流水支出,流水账户,$A29,流水日期,V$6),2)) | W29: =IF(OR($A29="",W$6=""),"",ROUND(SUMIFS(流水收入,流水账户,$A29,流水日期,W$6),2)) | X29: =IF(OR($A29="",X$6=""),"",ROUND(SUMIFS(流水支出,流水账户,$A29,流水日期,X$6),2)) | Y29: =IF(OR($A29="",Y$6=""),"",ROUND(SUMIFS(流水收入,流水账户,$A29,流水日期,Y$6),2)) | Z29: =IF(OR($A29="",Z$6=""),"",ROUND(SUMIFS(流水支出,流水账户,$A29,流水日期,Z$6),2)) | AA29: =IF(OR($A29="",AA$6=""),"",ROUND(SUMIFS(流水收入,流水账户,$A29,流水日期,AA$6),2)) | AB29: =IF(OR($A29="",AB$6=""),"",ROUND(SUMIFS(流水支出,流水账户,$A29,流水日期,AB$6),2)) | AC29: =IF(OR($A29="",AC$6=""),"",ROUND(SUMIFS(流水收入,流水账户,$A29,流水日期,AC$6),2)) | AD29: =IF(OR($A29="",AD$6=""),"",ROUND(SUMIFS(流水支出,流水账户,$A29,流水日期,AD$6),2)) | AE29: =IF(OR($A29="",AE$6=""),"",ROUND(SUMIFS(流水收入,流水账户,$A29,流水日期,AE$6),2)) | AF29: =IF(OR($A29="",AF$6=""),"",ROUND(SUMIFS(流水支出,流水账户,$A29,流水日期,AF$6),2)) | AG29: =IF(OR($A29="",AG$6=""),"",ROUND(SUMIFS(流水收入,流水账户,$A29,流水日期,AG$6),2)) | AH29: =IF(OR($A29="",AH$6=""),"",ROUND(SUMIFS(流水支出,流水账户,$A29,流水日期,AH$6),2)) | AI29: =IF(OR($A29="",AI$6=""),"",ROUND(SUMIFS(流水收入,流水账户,$A29,流水日期,AI$6),2)) | AJ29: =IF(OR($A29="",AJ$6=""),"",ROUND(SUMIFS(流水支出,流水账户,$A29,流水日期,AJ$6),2)) | AK29: =IF(OR($A29="",AK$6=""),"",ROUND(SUMIFS(流水收入,流水账户,$A29,流水日期,AK$6),2)) | AL29: =IF(OR($A29="",AL$6=""),"",ROUND(SUMIFS(流水支出,流水账户,$A29,流水日期,AL$6),2)) | AM29: =IF(OR($A29="",AM$6=""),"",ROUND(SUMIFS(流水收入,流水账户,$A29,流水日期,AM$6),2)) | AN29: =IF(OR($A29="",AN$6=""),"",ROUND(SUMIFS(流水支出,流水账户,$A29,流水日期,AN$6),2)) | AO29: =IF(OR($A29="",AO$6=""),"",ROUND(SUMIFS(流水收入,流水账户,$A29,流水日期,AO$6),2)) | AP29: =IF(OR($A29="",AP$6=""),"",ROUND(SUMIFS(流水支出,流水账户,$A29,流水日期,AP$6),2)) | AQ29: =IF(OR($A29="",AQ$6=""),"",ROUND(SUMIFS(流水收入,流水账户,$A29,流水日期,AQ$6),2)) | AR29: =IF(OR($A29="",AR$6=""),"",ROUND(SUMIFS(流水支出,流水账户,$A29,流水日期,AR$6),2)) | AS29: =IF(OR($A29="",AS$6=""),"",ROUND(SUMIFS(流水收入,流水账户,$A29,流水日期,AS$6),2)) | AT29: =IF(OR($A29="",AT$6=""),"",ROUND(SUMIFS(流水支出,流水账户,$A29,流水日期,AT$6),2)) | AU29: =IF(OR($A29="",AU$6=""),"",ROUND(SUMIFS(流水收入,流水账户,$A29,流水日期,AU$6),2)) | AV29: =IF(OR($A29="",AV$6=""),"",ROUND(SUMIFS(流水支出,流水账户,$A29,流水日期,AV$6),2)) | AW29: =IF(OR($A29="",AW$6=""),"",ROUND(SUMIFS(流水收入,流水账户,$A29,流水日期,AW$6),2)) | AX29: =IF(OR($A29="",AX$6=""),"",ROUND(SUMIFS(流水支出,流水账户,$A29,流水日期,AX$6),2)) | AY29: =IF(OR($A29="",AY$6=""),"",ROUND(SUMIFS(流水收入,流水账户,$A29,流水日期,AY$6),2)) | AZ29: =IF(OR($A29="",AZ$6=""),"",ROUND(SUMIFS(流水支出,流水账户,$A29,流水日期,AZ$6),2)) | BA29: =IF(OR($A29="",BA$6=""),"",ROUND(SUMIFS(流水收入,流水账户,$A29,流水日期,BA$6),2)) | BB29: =IF(OR($A29="",BB$6=""),"",ROUND(SUMIFS(流水支出,流水账户,$A29,流水日期,BB$6),2)) | BC29: =IF(OR($A29="",BC$6=""),"",ROUND(SUMIFS(流水收入,流水账户,$A29,流水日期,BC$6),2)) | BD29: =IF(OR($A29="",BD$6=""),"",ROUND(SUMIFS(流水支出,流水账户,$A29,流水日期,BD$6),2)) | BE29: =IF(OR($A29="",BE$6=""),"",ROUND(SUMIFS(流水收入,流水账户,$A29,流水日期,BE$6),2)) | BF29: =IF(OR($A29="",BF$6=""),"",ROUND(SUMIFS(流水支出,流水账户,$A29,流水日期,BF$6),2)) | BG29: =IF(OR($A29="",BG$6=""),"",ROUND(SUMIFS(流水收入,流水账户,$A29,流水日期,BG$6),2)) | BH29: =IF(OR($A29="",BH$6=""),"",ROUND(SUMIFS(流水支出,流水账户,$A29,流水日期,BH$6),2)) | BI29: =IF(OR($A29="",BI$6=""),"",ROUND(SUMIFS(流水收入,流水账户,$A29,流水日期,BI$6),2)) | BJ29: =IF(OR($A29="",BJ$6=""),"",ROUND(SUMIFS(流水支出,流水账户,$A29,流水日期,BJ$6),2)) | BK29: =IF(OR($A29="",BK$6=""),"",ROUND(SUMIFS(流水收入,流水账户,$A29,流水日期,BK$6),2)) | BL29: =IF(OR($A29="",BL$6=""),"",ROUND(SUMIFS(流水支出,流水账户,$A29,流水日期,BL$6),2)) | BM29: =IF($A29="","",ROUND(SUMIF($C$7:$BL$7,"收款",C29:BL29),2)) | BN29: =IF($A29="","",ROUND(SUMIF($C$7:$BL$7,"付款",C29:BL29),2)) | BO29: =IF($A29="","",ROUND(N($B29)+N(BM29)-N(BN29),2))
A30: =IF(基础资料!$B$27="","",基础资料!$B$27) | B30: =IF(OR($A30="",NOT(ISNUMBER($H$3))),"",ROUND(SUMIF(账户表,$A30,账户期初)+SUMIFS(流水收入,流水账户,$A30,流水日期,"<"&$B$3)-SUMIFS(流水支出,流水账户,$A30,流水日期,"<"&$B$3),2)) | C30: =IF(OR($A30="",C$6=""),"",ROUND(SUMIFS(流水收入,流水账户,$A30,流水日期,C$6),2)) | D30: =IF(OR($A30="",D$6=""),"",ROUND(SUMIFS(流水支出,流水账户,$A30,流水日期,D$6),2)) | E30: =IF(OR($A30="",E$6=""),"",ROUND(SUMIFS(流水收入,流水账户,$A30,流水日期,E$6),2)) | F30: =IF(OR($A30="",F$6=""),"",ROUND(SUMIFS(流水支出,流水账户,$A30,流水日期,F$6),2)) | G30: =IF(OR($A30="",G$6=""),"",ROUND(SUMIFS(流水收入,流水账户,$A30,流水日期,G$6),2)) | H30: =IF(OR($A30="",H$6=""),"",ROUND(SUMIFS(流水支出,流水账户,$A30,流水日期,H$6),2)) | I30: =IF(OR($A30="",I$6=""),"",ROUND(SUMIFS(流水收入,流水账户,$A30,流水日期,I$6),2)) | J30: =IF(OR($A30="",J$6=""),"",ROUND(SUMIFS(流水支出,流水账户,$A30,流水日期,J$6),2)) | K30: =IF(OR($A30="",K$6=""),"",ROUND(SUMIFS(流水收入,流水账户,$A30,流水日期,K$6),2)) | L30: =IF(OR($A30="",L$6=""),"",ROUND(SUMIFS(流水支出,流水账户,$A30,流水日期,L$6),2)) | M30: =IF(OR($A30="",M$6=""),"",ROUND(SUMIFS(流水收入,流水账户,$A30,流水日期,M$6),2)) | N30: =IF(OR($A30="",N$6=""),"",ROUND(SUMIFS(流水支出,流水账户,$A30,流水日期,N$6),2)) | O30: =IF(OR($A30="",O$6=""),"",ROUND(SUMIFS(流水收入,流水账户,$A30,流水日期,O$6),2)) | P30: =IF(OR($A30="",P$6=""),"",ROUND(SUMIFS(流水支出,流水账户,$A30,流水日期,P$6),2)) | Q30: =IF(OR($A30="",Q$6=""),"",ROUND(SUMIFS(流水收入,流水账户,$A30,流水日期,Q$6),2)) | R30: =IF(OR($A30="",R$6=""),"",ROUND(SUMIFS(流水支出,流水账户,$A30,流水日期,R$6),2)) | S30: =IF(OR($A30="",S$6=""),"",ROUND(SUMIFS(流水收入,流水账户,$A30,流水日期,S$6),2)) | T30: =IF(OR($A30="",T$6=""),"",ROUND(SUMIFS(流水支出,流水账户,$A30,流水日期,T$6),2)) | U30: =IF(OR($A30="",U$6=""),"",ROUND(SUMIFS(流水收入,流水账户,$A30,流水日期,U$6),2)) | V30: =IF(OR($A30="",V$6=""),"",ROUND(SUMIFS(流水支出,流水账户,$A30,流水日期,V$6),2)) | W30: =IF(OR($A30="",W$6=""),"",ROUND(SUMIFS(流水收入,流水账户,$A30,流水日期,W$6),2)) | X30: =IF(OR($A30="",X$6=""),"",ROUND(SUMIFS(流水支出,流水账户,$A30,流水日期,X$6),2)) | Y30: =IF(OR($A30="",Y$6=""),"",ROUND(SUMIFS(流水收入,流水账户,$A30,流水日期,Y$6),2)) | Z30: =IF(OR($A30="",Z$6=""),"",ROUND(SUMIFS(流水支出,流水账户,$A30,流水日期,Z$6),2)) | AA30: =IF(OR($A30="",AA$6=""),"",ROUND(SUMIFS(流水收入,流水账户,$A30,流水日期,AA$6),2)) | AB30: =IF(OR($A30="",AB$6=""),"",ROUND(SUMIFS(流水支出,流水账户,$A30,流水日期,AB$6),2)) | AC30: =IF(OR($A30="",AC$6=""),"",ROUND(SUMIFS(流水收入,流水账户,$A30,流水日期,AC$6),2)) | AD30: =IF(OR($A30="",AD$6=""),"",ROUND(SUMIFS(流水支出,流水账户,$A30,流水日期,AD$6),2)) | AE30: =IF(OR($A30="",AE$6=""),"",ROUND(SUMIFS(流水收入,流水账户,$A30,流水日期,AE$6),2)) | AF30: =IF(OR($A30="",AF$6=""),"",ROUND(SUMIFS(流水支出,流水账户,$A30,流水日期,AF$6),2)) | AG30: =IF(OR($A30="",AG$6=""),"",ROUND(SUMIFS(流水收入,流水账户,$A30,流水日期,AG$6),2)) | AH30: =IF(OR($A30="",AH$6=""),"",ROUND(SUMIFS(流水支出,流水账户,$A30,流水日期,AH$6),2)) | AI30: =IF(OR($A30="",AI$6=""),"",ROUND(SUMIFS(流水收入,流水账户,$A30,流水日期,AI$6),2)) | AJ30: =IF(OR($A30="",AJ$6=""),"",ROUND(SUMIFS(流水支出,流水账户,$A30,流水日期,AJ$6),2)) | AK30: =IF(OR($A30="",AK$6=""),"",ROUND(SUMIFS(流水收入,流水账户,$A30,流水日期,AK$6),2)) | AL30: =IF(OR($A30="",AL$6=""),"",ROUND(SUMIFS(流水支出,流水账户,$A30,流水日期,AL$6),2)) | AM30: =IF(OR($A30="",AM$6=""),"",ROUND(SUMIFS(流水收入,流水账户,$A30,流水日期,AM$6),2)) | AN30: =IF(OR($A30="",AN$6=""),"",ROUND(SUMIFS(流水支出,流水账户,$A30,流水日期,AN$6),2)) | AO30: =IF(OR($A30="",AO$6=""),"",ROUND(SUMIFS(流水收入,流水账户,$A30,流水日期,AO$6),2)) | AP30: =IF(OR($A30="",AP$6=""),"",ROUND(SUMIFS(流水支出,流水账户,$A30,流水日期,AP$6),2)) | AQ30: =IF(OR($A30="",AQ$6=""),"",ROUND(SUMIFS(流水收入,流水账户,$A30,流水日期,AQ$6),2)) | AR30: =IF(OR($A30="",AR$6=""),"",ROUND(SUMIFS(流水支出,流水账户,$A30,流水日期,AR$6),2)) | AS30: =IF(OR($A30="",AS$6=""),"",ROUND(SUMIFS(流水收入,流水账户,$A30,流水日期,AS$6),2)) | AT30: =IF(OR($A30="",AT$6=""),"",ROUND(SUMIFS(流水支出,流水账户,$A30,流水日期,AT$6),2)) | AU30: =IF(OR($A30="",AU$6=""),"",ROUND(SUMIFS(流水收入,流水账户,$A30,流水日期,AU$6),2)) | AV30: =IF(OR($A30="",AV$6=""),"",ROUND(SUMIFS(流水支出,流水账户,$A30,流水日期,AV$6),2)) | AW30: =IF(OR($A30="",AW$6=""),"",ROUND(SUMIFS(流水收入,流水账户,$A30,流水日期,AW$6),2)) | AX30: =IF(OR($A30="",AX$6=""),"",ROUND(SUMIFS(流水支出,流水账户,$A30,流水日期,AX$6),2)) | AY30: =IF(OR($A30="",AY$6=""),"",ROUND(SUMIFS(流水收入,流水账户,$A30,流水日期,AY$6),2)) | AZ30: =IF(OR($A30="",AZ$6=""),"",ROUND(SUMIFS(流水支出,流水账户,$A30,流水日期,AZ$6),2)) | BA30: =IF(OR($A30="",BA$6=""),"",ROUND(SUMIFS(流水收入,流水账户,$A30,流水日期,BA$6),2)) | BB30: =IF(OR($A30="",BB$6=""),"",ROUND(SUMIFS(流水支出,流水账户,$A30,流水日期,BB$6),2)) | BC30: =IF(OR($A30="",BC$6=""),"",ROUND(SUMIFS(流水收入,流水账户,$A30,流水日期,BC$6),2)) | BD30: =IF(OR($A30="",BD$6=""),"",ROUND(SUMIFS(流水支出,流水账户,$A30,流水日期,BD$6),2)) | BE30: =IF(OR($A30="",BE$6=""),"",ROUND(SUMIFS(流水收入,流水账户,$A30,流水日期,BE$6),2)) | BF30: =IF(OR($A30="",BF$6=""),"",ROUND(SUMIFS(流水支出,流水账户,$A30,流水日期,BF$6),2)) | BG30: =IF(OR($A30="",BG$6=""),"",ROUND(SUMIFS(流水收入,流水账户,$A30,流水日期,BG$6),2)) | BH30: =IF(OR($A30="",BH$6=""),"",ROUND(SUMIFS(流水支出,流水账户,$A30,流水日期,BH$6),2)) | BI30: =IF(OR($A30="",BI$6=""),"",ROUND(SUMIFS(流水收入,流水账户,$A30,流水日期,BI$6),2)) | BJ30: =IF(OR($A30="",BJ$6=""),"",ROUND(SUMIFS(流水支出,流水账户,$A30,流水日期,BJ$6),2)) | BK30: =IF(OR($A30="",BK$6=""),"",ROUND(SUMIFS(流水收入,流水账户,$A30,流水日期,BK$6),2)) | BL30: =IF(OR($A30="",BL$6=""),"",ROUND(SUMIFS(流水支出,流水账户,$A30,流水日期,BL$6),2)) | BM30: =IF($A30="","",ROUND(SUMIF($C$7:$BL$7,"收款",C30:BL30),2)) | BN30: =IF($A30="","",ROUND(SUMIF($C$7:$BL$7,"付款",C30:BL30),2)) | BO30: =IF($A30="","",ROUND(N($B30)+N(BM30)-N(BN30),2))
A31: =IF(基础资料!$B$28="","",基础资料!$B$28) | B31: =IF(OR($A31="",NOT(ISNUMBER($H$3))),"",ROUND(SUMIF(账户表,$A31,账户期初)+SUMIFS(流水收入,流水账户,$A31,流水日期,"<"&$B$3)-SUMIFS(流水支出,流水账户,$A31,流水日期,"<"&$B$3),2)) | C31: =IF(OR($A31="",C$6=""),"",ROUND(SUMIFS(流水收入,流水账户,$A31,流水日期,C$6),2)) | D31: =IF(OR($A31="",D$6=""),"",ROUND(SUMIFS(流水支出,流水账户,$A31,流水日期,D$6),2)) | E31: =IF(OR($A31="",E$6=""),"",ROUND(SUMIFS(流水收入,流水账户,$A31,流水日期,E$6),2)) | F31: =IF(OR($A31="",F$6=""),"",ROUND(SUMIFS(流水支出,流水账户,$A31,流水日期,F$6),2)) | G31: =IF(OR($A31="",G$6=""),"",ROUND(SUMIFS(流水收入,流水账户,$A31,流水日期,G$6),2)) | H31: =IF(OR($A31="",H$6=""),"",ROUND(SUMIFS(流水支出,流水账户,$A31,流水日期,H$6),2)) | I31: =IF(OR($A31="",I$6=""),"",ROUND(SUMIFS(流水收入,流水账户,$A31,流水日期,I$6),2)) | J31: =IF(OR($A31="",J$6=""),"",ROUND(SUMIFS(流水支出,流水账户,$A31,流水日期,J$6),2)) | K31: =IF(OR($A31="",K$6=""),"",ROUND(SUMIFS(流水收入,流水账户,$A31,流水日期,K$6),2)) | L31: =IF(OR($A31="",L$6=""),"",ROUND(SUMIFS(流水支出,流水账户,$A31,流水日期,L$6),2)) | M31: =IF(OR($A31="",M$6=""),"",ROUND(SUMIFS(流水收入,流水账户,$A31,流水日期,M$6),2)) | N31: =IF(OR($A31="",N$6=""),"",ROUND(SUMIFS(流水支出,流水账户,$A31,流水日期,N$6),2)) | O31: =IF(OR($A31="",O$6=""),"",ROUND(SUMIFS(流水收入,流水账户,$A31,流水日期,O$6),2)) | P31: =IF(OR($A31="",P$6=""),"",ROUND(SUMIFS(流水支出,流水账户,$A31,流水日期,P$6),2)) | Q31: =IF(OR($A31="",Q$6=""),"",ROUND(SUMIFS(流水收入,流水账户,$A31,流水日期,Q$6),2)) | R31: =IF(OR($A31="",R$6=""),"",ROUND(SUMIFS(流水支出,流水账户,$A31,流水日期,R$6),2)) | S31: =IF(OR($A31="",S$6=""),"",ROUND(SUMIFS(流水收入,流水账户,$A31,流水日期,S$6),2)) | T31: =IF(OR($A31="",T$6=""),"",ROUND(SUMIFS(流水支出,流水账户,$A31,流水日期,T$6),2)) | U31: =IF(OR($A31="",U$6=""),"",ROUND(SUMIFS(流水收入,流水账户,$A31,流水日期,U$6),2)) | V31: =IF(OR($A31="",V$6=""),"",ROUND(SUMIFS(流水支出,流水账户,$A31,流水日期,V$6),2)) | W31: =IF(OR($A31="",W$6=""),"",ROUND(SUMIFS(流水收入,流水账户,$A31,流水日期,W$6),2)) | X31: =IF(OR($A31="",X$6=""),"",ROUND(SUMIFS(流水支出,流水账户,$A31,流水日期,X$6),2)) | Y31: =IF(OR($A31="",Y$6=""),"",ROUND(SUMIFS(流水收入,流水账户,$A31,流水日期,Y$6),2)) | Z31: =IF(OR($A31="",Z$6=""),"",ROUND(SUMIFS(流水支出,流水账户,$A31,流水日期,Z$6),2)) | AA31: =IF(OR($A31="",AA$6=""),"",ROUND(SUMIFS(流水收入,流水账户,$A31,流水日期,AA$6),2)) | AB31: =IF(OR($A31="",AB$6=""),"",ROUND(SUMIFS(流水支出,流水账户,$A31,流水日期,AB$6),2)) | AC31: =IF(OR($A31="",AC$6=""),"",ROUND(SUMIFS(流水收入,流水账户,$A31,流水日期,AC$6),2)) | AD31: =IF(OR($A31="",AD$6=""),"",ROUND(SUMIFS(流水支出,流水账户,$A31,流水日期,AD$6),2)) | AE31: =IF(OR($A31="",AE$6=""),"",ROUND(SUMIFS(流水收入,流水账户,$A31,流水日期,AE$6),2)) | AF31: =IF(OR($A31="",AF$6=""),"",ROUND(SUMIFS(流水支出,流水账户,$A31,流水日期,AF$6),2)) | AG31: =IF(OR($A31="",AG$6=""),"",ROUND(SUMIFS(流水收入,流水账户,$A31,流水日期,AG$6),2)) | AH31: =IF(OR($A31="",AH$6=""),"",ROUND(SUMIFS(流水支出,流水账户,$A31,流水日期,AH$6),2)) | AI31: =IF(OR($A31="",AI$6=""),"",ROUND(SUMIFS(流水收入,流水账户,$A31,流水日期,AI$6),2)) | AJ31: =IF(OR($A31="",AJ$6=""),"",ROUND(SUMIFS(流水支出,流水账户,$A31,流水日期,AJ$6),2)) | AK31: =IF(OR($A31="",AK$6=""),"",ROUND(SUMIFS(流水收入,流水账户,$A31,流水日期,AK$6),2)) | AL31: =IF(OR($A31="",AL$6=""),"",ROUND(SUMIFS(流水支出,流水账户,$A31,流水日期,AL$6),2)) | AM31: =IF(OR($A31="",AM$6=""),"",ROUND(SUMIFS(流水收入,流水账户,$A31,流水日期,AM$6),2)) | AN31: =IF(OR($A31="",AN$6=""),"",ROUND(SUMIFS(流水支出,流水账户,$A31,流水日期,AN$6),2)) | AO31: =IF(OR($A31="",AO$6=""),"",ROUND(SUMIFS(流水收入,流水账户,$A31,流水日期,AO$6),2)) | AP31: =IF(OR($A31="",AP$6=""),"",ROUND(SUMIFS(流水支出,流水账户,$A31,流水日期,AP$6),2)) | AQ31: =IF(OR($A31="",AQ$6=""),"",ROUND(SUMIFS(流水收入,流水账户,$A31,流水日期,AQ$6),2)) | AR31: =IF(OR($A31="",AR$6=""),"",ROUND(SUMIFS(流水支出,流水账户,$A31,流水日期,AR$6),2)) | AS31: =IF(OR($A31="",AS$6=""),"",ROUND(SUMIFS(流水收入,流水账户,$A31,流水日期,AS$6),2)) | AT31: =IF(OR($A31="",AT$6=""),"",ROUND(SUMIFS(流水支出,流水账户,$A31,流水日期,AT$6),2)) | AU31: =IF(OR($A31="",AU$6=""),"",ROUND(SUMIFS(流水收入,流水账户,$A31,流水日期,AU$6),2)) | AV31: =IF(OR($A31="",AV$6=""),"",ROUND(SUMIFS(流水支出,流水账户,$A31,流水日期,AV$6),2)) | AW31: =IF(OR($A31="",AW$6=""),"",ROUND(SUMIFS(流水收入,流水账户,$A31,流水日期,AW$6),2)) | AX31: =IF(OR($A31="",AX$6=""),"",ROUND(SUMIFS(流水支出,流水账户,$A31,流水日期,AX$6),2)) | AY31: =IF(OR($A31="",AY$6=""),"",ROUND(SUMIFS(流水收入,流水账户,$A31,流水日期,AY$6),2)) | AZ31: =IF(OR($A31="",AZ$6=""),"",ROUND(SUMIFS(流水支出,流水账户,$A31,流水日期,AZ$6),2)) | BA31: =IF(OR($A31="",BA$6=""),"",ROUND(SUMIFS(流水收入,流水账户,$A31,流水日期,BA$6),2)) | BB31: =IF(OR($A31="",BB$6=""),"",ROUND(SUMIFS(流水支出,流水账户,$A31,流水日期,BB$6),2)) | BC31: =IF(OR($A31="",BC$6=""),"",ROUND(SUMIFS(流水收入,流水账户,$A31,流水日期,BC$6),2)) | BD31: =IF(OR($A31="",BD$6=""),"",ROUND(SUMIFS(流水支出,流水账户,$A31,流水日期,BD$6),2)) | BE31: =IF(OR($A31="",BE$6=""),"",ROUND(SUMIFS(流水收入,流水账户,$A31,流水日期,BE$6),2)) | BF31: =IF(OR($A31="",BF$6=""),"",ROUND(SUMIFS(流水支出,流水账户,$A31,流水日期,BF$6),2)) | BG31: =IF(OR($A31="",BG$6=""),"",ROUND(SUMIFS(流水收入,流水账户,$A31,流水日期,BG$6),2)) | BH31: =IF(OR($A31="",BH$6=""),"",ROUND(SUMIFS(流水支出,流水账户,$A31,流水日期,BH$6),2)) | BI31: =IF(OR($A31="",BI$6=""),"",ROUND(SUMIFS(流水收入,流水账户,$A31,流水日期,BI$6),2)) | BJ31: =IF(OR($A31="",BJ$6=""),"",ROUND(SUMIFS(流水支出,流水账户,$A31,流水日期,BJ$6),2)) | BK31: =IF(OR($A31="",BK$6=""),"",ROUND(SUMIFS(流水收入,流水账户,$A31,流水日期,BK$6),2)) | BL31: =IF(OR($A31="",BL$6=""),"",ROUND(SUMIFS(流水支出,流水账户,$A31,流水日期,BL$6),2)) | BM31: =IF($A31="","",ROUND(SUMIF($C$7:$BL$7,"收款",C31:BL31),2)) | BN31: =IF($A31="","",ROUND(SUMIF($C$7:$BL$7,"付款",C31:BL31),2)) | BO31: =IF($A31="","",ROUND(N($B31)+N(BM31)-N(BN31),2))
A32: =IF(基础资料!$B$29="","",基础资料!$B$29) | B32: =IF(OR($A32="",NOT(ISNUMBER($H$3))),"",ROUND(SUMIF(账户表,$A32,账户期初)+SUMIFS(流水收入,流水账户,$A32,流水日期,"<"&$B$3)-SUMIFS(流水支出,流水账户,$A32,流水日期,"<"&$B$3),2)) | C32: =IF(OR($A32="",C$6=""),"",ROUND(SUMIFS(流水收入,流水账户,$A32,流水日期,C$6),2)) | D32: =IF(OR($A32="",D$6=""),"",ROUND(SUMIFS(流水支出,流水账户,$A32,流水日期,D$6),2)) | E32: =IF(OR($A32="",E$6=""),"",ROUND(SUMIFS(流水收入,流水账户,$A32,流水日期,E$6),2)) | F32: =IF(OR($A32="",F$6=""),"",ROUND(SUMIFS(流水支出,流水账户,$A32,流水日期,F$6),2)) | G32: =IF(OR($A32="",G$6=""),"",ROUND(SUMIFS(流水收入,流水账户,$A32,流水日期,G$6),2)) | H32: =IF(OR($A32="",H$6=""),"",ROUND(SUMIFS(流水支出,流水账户,$A32,流水日期,H$6),2)) | I32: =IF(OR($A32="",I$6=""),"",ROUND(SUMIFS(流水收入,流水账户,$A32,流水日期,I$6),2)) | J32: =IF(OR($A32="",J$6=""),"",ROUND(SUMIFS(流水支出,流水账户,$A32,流水日期,J$6),2)) | K32: =IF(OR($A32="",K$6=""),"",ROUND(SUMIFS(流水收入,流水账户,$A32,流水日期,K$6),2)) | L32: =IF(OR($A32="",L$6=""),"",ROUND(SUMIFS(流水支出,流水账户,$A32,流水日期,L$6),2)) | M32: =IF(OR($A32="",M$6=""),"",ROUND(SUMIFS(流水收入,流水账户,$A32,流水日期,M$6),2)) | N32: =IF(OR($A32="",N$6=""),"",ROUND(SUMIFS(流水支出,流水账户,$A32,流水日期,N$6),2)) | O32: =IF(OR($A32="",O$6=""),"",ROUND(SUMIFS(流水收入,流水账户,$A32,流水日期,O$6),2)) | P32: =IF(OR($A32="",P$6=""),"",ROUND(SUMIFS(流水支出,流水账户,$A32,流水日期,P$6),2)) | Q32: =IF(OR($A32="",Q$6=""),"",ROUND(SUMIFS(流水收入,流水账户,$A32,流水日期,Q$6),2)) | R32: =IF(OR($A32="",R$6=""),"",ROUND(SUMIFS(流水支出,流水账户,$A32,流水日期,R$6),2)) | S32: =IF(OR($A32="",S$6=""),"",ROUND(SUMIFS(流水收入,流水账户,$A32,流水日期,S$6),2)) | T32: =IF(OR($A32="",T$6=""),"",ROUND(SUMIFS(流水支出,流水账户,$A32,流水日期,T$6),2)) | U32: =IF(OR($A32="",U$6=""),"",ROUND(SUMIFS(流水收入,流水账户,$A32,流水日期,U$6),2)) | V32: =IF(OR($A32="",V$6=""),"",ROUND(SUMIFS(流水支出,流水账户,$A32,流水日期,V$6),2)) | W32: =IF(OR($A32="",W$6=""),"",ROUND(SUMIFS(流水收入,流水账户,$A32,流水日期,W$6),2)) | X32: =IF(OR($A32="",X$6=""),"",ROUND(SUMIFS(流水支出,流水账户,$A32,流水日期,X$6),2)) | Y32: =IF(OR($A32="",Y$6=""),"",ROUND(SUMIFS(流水收入,流水账户,$A32,流水日期,Y$6),2)) | Z32: =IF(OR($A32="",Z$6=""),"",ROUND(SUMIFS(流水支出,流水账户,$A32,流水日期,Z$6),2)) | AA32: =IF(OR($A32="",AA$6=""),"",ROUND(SUMIFS(流水收入,流水账户,$A32,流水日期,AA$6),2)) | AB32: =IF(OR($A32="",AB$6=""),"",ROUND(SUMIFS(流水支出,流水账户,$A32,流水日期,AB$6),2)) | AC32: =IF(OR($A32="",AC$6=""),"",ROUND(SUMIFS(流水收入,流水账户,$A32,流水日期,AC$6),2)) | AD32: =IF(OR($A32="",AD$6=""),"",ROUND(SUMIFS(流水支出,流水账户,$A32,流水日期,AD$6),2)) | AE32: =IF(OR($A32="",AE$6=""),"",ROUND(SUMIFS(流水收入,流水账户,$A32,流水日期,AE$6),2)) | AF32: =IF(OR($A32="",AF$6=""),"",ROUND(SUMIFS(流水支出,流水账户,$A32,流水日期,AF$6),2)) | AG32: =IF(OR($A32="",AG$6=""),"",ROUND(SUMIFS(流水收入,流水账户,$A32,流水日期,AG$6),2)) | AH32: =IF(OR($A32="",AH$6=""),"",ROUND(SUMIFS(流水支出,流水账户,$A32,流水日期,AH$6),2)) | AI32: =IF(OR($A32="",AI$6=""),"",ROUND(SUMIFS(流水收入,流水账户,$A32,流水日期,AI$6),2)) | AJ32: =IF(OR($A32="",AJ$6=""),"",ROUND(SUMIFS(流水支出,流水账户,$A32,流水日期,AJ$6),2)) | AK32: =IF(OR($A32="",AK$6=""),"",ROUND(SUMIFS(流水收入,流水账户,$A32,流水日期,AK$6),2)) | AL32: =IF(OR($A32="",AL$6=""),"",ROUND(SUMIFS(流水支出,流水账户,$A32,流水日期,AL$6),2)) | AM32: =IF(OR($A32="",AM$6=""),"",ROUND(SUMIFS(流水收入,流水账户,$A32,流水日期,AM$6),2)) | AN32: =IF(OR($A32="",AN$6=""),"",ROUND(SUMIFS(流水支出,流水账户,$A32,流水日期,AN$6),2)) | AO32: =IF(OR($A32="",AO$6=""),"",ROUND(SUMIFS(流水收入,流水账户,$A32,流水日期,AO$6),2)) | AP32: =IF(OR($A32="",AP$6=""),"",ROUND(SUMIFS(流水支出,流水账户,$A32,流水日期,AP$6),2)) | AQ32: =IF(OR($A32="",AQ$6=""),"",ROUND(SUMIFS(流水收入,流水账户,$A32,流水日期,AQ$6),2)) | AR32: =IF(OR($A32="",AR$6=""),"",ROUND(SUMIFS(流水支出,流水账户,$A32,流水日期,AR$6),2)) | AS32: =IF(OR($A32="",AS$6=""),"",ROUND(SUMIFS(流水收入,流水账户,$A32,流水日期,AS$6),2)) | AT32: =IF(OR($A32="",AT$6=""),"",ROUND(SUMIFS(流水支出,流水账户,$A32,流水日期,AT$6),2)) | AU32: =IF(OR($A32="",AU$6=""),"",ROUND(SUMIFS(流水收入,流水账户,$A32,流水日期,AU$6),2)) | AV32: =IF(OR($A32="",AV$6=""),"",ROUND(SUMIFS(流水支出,流水账户,$A32,流水日期,AV$6),2)) | AW32: =IF(OR($A32="",AW$6=""),"",ROUND(SUMIFS(流水收入,流水账户,$A32,流水日期,AW$6),2)) | AX32: =IF(OR($A32="",AX$6=""),"",ROUND(SUMIFS(流水支出,流水账户,$A32,流水日期,AX$6),2)) | AY32: =IF(OR($A32="",AY$6=""),"",ROUND(SUMIFS(流水收入,流水账户,$A32,流水日期,AY$6),2)) | AZ32: =IF(OR($A32="",AZ$6=""),"",ROUND(SUMIFS(流水支出,流水账户,$A32,流水日期,AZ$6),2)) | BA32: =IF(OR($A32="",BA$6=""),"",ROUND(SUMIFS(流水收入,流水账户,$A32,流水日期,BA$6),2)) | BB32: =IF(OR($A32="",BB$6=""),"",ROUND(SUMIFS(流水支出,流水账户,$A32,流水日期,BB$6),2)) | BC32: =IF(OR($A32="",BC$6=""),"",ROUND(SUMIFS(流水收入,流水账户,$A32,流水日期,BC$6),2)) | BD32: =IF(OR($A32="",BD$6=""),"",ROUND(SUMIFS(流水支出,流水账户,$A32,流水日期,BD$6),2)) | BE32: =IF(OR($A32="",BE$6=""),"",ROUND(SUMIFS(流水收入,流水账户,$A32,流水日期,BE$6),2)) | BF32: =IF(OR($A32="",BF$6=""),"",ROUND(SUMIFS(流水支出,流水账户,$A32,流水日期,BF$6),2)) | BG32: =IF(OR($A32="",BG$6=""),"",ROUND(SUMIFS(流水收入,流水账户,$A32,流水日期,BG$6),2)) | BH32: =IF(OR($A32="",BH$6=""),"",ROUND(SUMIFS(流水支出,流水账户,$A32,流水日期,BH$6),2)) | BI32: =IF(OR($A32="",BI$6=""),"",ROUND(SUMIFS(流水收入,流水账户,$A32,流水日期,BI$6),2)) | BJ32: =IF(OR($A32="",BJ$6=""),"",ROUND(SUMIFS(流水支出,流水账户,$A32,流水日期,BJ$6),2)) | BK32: =IF(OR($A32="",BK$6=""),"",ROUND(SUMIFS(流水收入,流水账户,$A32,流水日期,BK$6),2)) | BL32: =IF(OR($A32="",BL$6=""),"",ROUND(SUMIFS(流水支出,流水账户,$A32,流水日期,BL$6),2)) | BM32: =IF($A32="","",ROUND(SUMIF($C$7:$BL$7,"收款",C32:BL32),2)) | BN32: =IF($A32="","",ROUND(SUMIF($C$7:$BL$7,"付款",C32:BL32),2)) | BO32: =IF($A32="","",ROUND(N($B32)+N(BM32)-N(BN32),2))
A33: =IF(基础资料!$B$30="","",基础资料!$B$30) | B33: =IF(OR($A33="",NOT(ISNUMBER($H$3))),"",ROUND(SUMIF(账户表,$A33,账户期初)+SUMIFS(流水收入,流水账户,$A33,流水日期,"<"&$B$3)-SUMIFS(流水支出,流水账户,$A33,流水日期,"<"&$B$3),2)) | C33: =IF(OR($A33="",C$6=""),"",ROUND(SUMIFS(流水收入,流水账户,$A33,流水日期,C$6),2)) | D33: =IF(OR($A33="",D$6=""),"",ROUND(SUMIFS(流水支出,流水账户,$A33,流水日期,D$6),2)) | E33: =IF(OR($A33="",E$6=""),"",ROUND(SUMIFS(流水收入,流水账户,$A33,流水日期,E$6),2)) | F33: =IF(OR($A33="",F$6=""),"",ROUND(SUMIFS(流水支出,流水账户,$A33,流水日期,F$6),2)) | G33: =IF(OR($A33="",G$6=""),"",ROUND(SUMIFS(流水收入,流水账户,$A33,流水日期,G$6),2)) | H33: =IF(OR($A33="",H$6=""),"",ROUND(SUMIFS(流水支出,流水账户,$A33,流水日期,H$6),2)) | I33: =IF(OR($A33="",I$6=""),"",ROUND(SUMIFS(流水收入,流水账户,$A33,流水日期,I$6),2)) | J33: =IF(OR($A33="",J$6=""),"",ROUND(SUMIFS(流水支出,流水账户,$A33,流水日期,J$6),2)) | K33: =IF(OR($A33="",K$6=""),"",ROUND(SUMIFS(流水收入,流水账户,$A33,流水日期,K$6),2)) | L33: =IF(OR($A33="",L$6=""),"",ROUND(SUMIFS(流水支出,流水账户,$A33,流水日期,L$6),2)) | M33: =IF(OR($A33="",M$6=""),"",ROUND(SUMIFS(流水收入,流水账户,$A33,流水日期,M$6),2)) | N33: =IF(OR($A33="",N$6=""),"",ROUND(SUMIFS(流水支出,流水账户,$A33,流水日期,N$6),2)) | O33: =IF(OR($A33="",O$6=""),"",ROUND(SUMIFS(流水收入,流水账户,$A33,流水日期,O$6),2)) | P33: =IF(OR($A33="",P$6=""),"",ROUND(SUMIFS(流水支出,流水账户,$A33,流水日期,P$6),2)) | Q33: =IF(OR($A33="",Q$6=""),"",ROUND(SUMIFS(流水收入,流水账户,$A33,流水日期,Q$6),2)) | R33: =IF(OR($A33="",R$6=""),"",ROUND(SUMIFS(流水支出,流水账户,$A33,流水日期,R$6),2)) | S33: =IF(OR($A33="",S$6=""),"",ROUND(SUMIFS(流水收入,流水账户,$A33,流水日期,S$6),2)) | T33: =IF(OR($A33="",T$6=""),"",ROUND(SUMIFS(流水支出,流水账户,$A33,流水日期,T$6),2)) | U33: =IF(OR($A33="",U$6=""),"",ROUND(SUMIFS(流水收入,流水账户,$A33,流水日期,U$6),2)) | V33: =IF(OR($A33="",V$6=""),"",ROUND(SUMIFS(流水支出,流水账户,$A33,流水日期,V$6),2)) | W33: =IF(OR($A33="",W$6=""),"",ROUND(SUMIFS(流水收入,流水账户,$A33,流水日期,W$6),2)) | X33: =IF(OR($A33="",X$6=""),"",ROUND(SUMIFS(流水支出,流水账户,$A33,流水日期,X$6),2)) | Y33: =IF(OR($A33="",Y$6=""),"",ROUND(SUMIFS(流水收入,流水账户,$A33,流水日期,Y$6),2)) | Z33: =IF(OR($A33="",Z$6=""),"",ROUND(SUMIFS(流水支出,流水账户,$A33,流水日期,Z$6),2)) | AA33: =IF(OR($A33="",AA$6=""),"",ROUND(SUMIFS(流水收入,流水账户,$A33,流水日期,AA$6),2)) | AB33: =IF(OR($A33="",AB$6=""),"",ROUND(SUMIFS(流水支出,流水账户,$A33,流水日期,AB$6),2)) | AC33: =IF(OR($A33="",AC$6=""),"",ROUND(SUMIFS(流水收入,流水账户,$A33,流水日期,AC$6),2)) | AD33: =IF(OR($A33="",AD$6=""),"",ROUND(SUMIFS(流水支出,流水账户,$A33,流水日期,AD$6),2)) | AE33: =IF(OR($A33="",AE$6=""),"",ROUND(SUMIFS(流水收入,流水账户,$A33,流水日期,AE$6),2)) | AF33: =IF(OR($A33="",AF$6=""),"",ROUND(SUMIFS(流水支出,流水账户,$A33,流水日期,AF$6),2)) | AG33: =IF(OR($A33="",AG$6=""),"",ROUND(SUMIFS(流水收入,流水账户,$A33,流水日期,AG$6),2)) | AH33: =IF(OR($A33="",AH$6=""),"",ROUND(SUMIFS(流水支出,流水账户,$A33,流水日期,AH$6),2)) | AI33: =IF(OR($A33="",AI$6=""),"",ROUND(SUMIFS(流水收入,流水账户,$A33,流水日期,AI$6),2)) | AJ33: =IF(OR($A33="",AJ$6=""),"",ROUND(SUMIFS(流水支出,流水账户,$A33,流水日期,AJ$6),2)) | AK33: =IF(OR($A33="",AK$6=""),"",ROUND(SUMIFS(流水收入,流水账户,$A33,流水日期,AK$6),2)) | AL33: =IF(OR($A33="",AL$6=""),"",ROUND(SUMIFS(流水支出,流水账户,$A33,流水日期,AL$6),2)) | AM33: =IF(OR($A33="",AM$6=""),"",ROUND(SUMIFS(流水收入,流水账户,$A33,流水日期,AM$6),2)) | AN33: =IF(OR($A33="",AN$6=""),"",ROUND(SUMIFS(流水支出,流水账户,$A33,流水日期,AN$6),2)) | AO33: =IF(OR($A33="",AO$6=""),"",ROUND(SUMIFS(流水收入,流水账户,$A33,流水日期,AO$6),2)) | AP33: =IF(OR($A33="",AP$6=""),"",ROUND(SUMIFS(流水支出,流水账户,$A33,流水日期,AP$6),2)) | AQ33: =IF(OR($A33="",AQ$6=""),"",ROUND(SUMIFS(流水收入,流水账户,$A33,流水日期,AQ$6),2)) | AR33: =IF(OR($A33="",AR$6=""),"",ROUND(SUMIFS(流水支出,流水账户,$A33,流水日期,AR$6),2)) | AS33: =IF(OR($A33="",AS$6=""),"",ROUND(SUMIFS(流水收入,流水账户,$A33,流水日期,AS$6),2)) | AT33: =IF(OR($A33="",AT$6=""),"",ROUND(SUMIFS(流水支出,流水账户,$A33,流水日期,AT$6),2)) | AU33: =IF(OR($A33="",AU$6=""),"",ROUND(SUMIFS(流水收入,流水账户,$A33,流水日期,AU$6),2)) | AV33: =IF(OR($A33="",AV$6=""),"",ROUND(SUMIFS(流水支出,流水账户,$A33,流水日期,AV$6),2)) | AW33: =IF(OR($A33="",AW$6=""),"",ROUND(SUMIFS(流水收入,流水账户,$A33,流水日期,AW$6),2)) | AX33: =IF(OR($A33="",AX$6=""),"",ROUND(SUMIFS(流水支出,流水账户,$A33,流水日期,AX$6),2)) | AY33: =IF(OR($A33="",AY$6=""),"",ROUND(SUMIFS(流水收入,流水账户,$A33,流水日期,AY$6),2)) | AZ33: =IF(OR($A33="",AZ$6=""),"",ROUND(SUMIFS(流水支出,流水账户,$A33,流水日期,AZ$6),2)) | BA33: =IF(OR($A33="",BA$6=""),"",ROUND(SUMIFS(流水收入,流水账户,$A33,流水日期,BA$6),2)) | BB33: =IF(OR($A33="",BB$6=""),"",ROUND(SUMIFS(流水支出,流水账户,$A33,流水日期,BB$6),2)) | BC33: =IF(OR($A33="",BC$6=""),"",ROUND(SUMIFS(流水收入,流水账户,$A33,流水日期,BC$6),2)) | BD33: =IF(OR($A33="",BD$6=""),"",ROUND(SUMIFS(流水支出,流水账户,$A33,流水日期,BD$6),2)) | BE33: =IF(OR($A33="",BE$6=""),"",ROUND(SUMIFS(流水收入,流水账户,$A33,流水日期,BE$6),2)) | BF33: =IF(OR($A33="",BF$6=""),"",ROUND(SUMIFS(流水支出,流水账户,$A33,流水日期,BF$6),2)) | BG33: =IF(OR($A33="",BG$6=""),"",ROUND(SUMIFS(流水收入,流水账户,$A33,流水日期,BG$6),2)) | BH33: =IF(OR($A33="",BH$6=""),"",ROUND(SUMIFS(流水支出,流水账户,$A33,流水日期,BH$6),2)) | BI33: =IF(OR($A33="",BI$6=""),"",ROUND(SUMIFS(流水收入,流水账户,$A33,流水日期,BI$6),2)) | BJ33: =IF(OR($A33="",BJ$6=""),"",ROUND(SUMIFS(流水支出,流水账户,$A33,流水日期,BJ$6),2)) | BK33: =IF(OR($A33="",BK$6=""),"",ROUND(SUMIFS(流水收入,流水账户,$A33,流水日期,BK$6),2)) | BL33: =IF(OR($A33="",BL$6=""),"",ROUND(SUMIFS(流水支出,流水账户,$A33,流水日期,BL$6),2)) | BM33: =IF($A33="","",ROUND(SUMIF($C$7:$BL$7,"收款",C33:BL33),2)) | BN33: =IF($A33="","",ROUND(SUMIF($C$7:$BL$7,"付款",C33:BL33),2)) | BO33: =IF($A33="","",ROUND(N($B33)+N(BM33)-N(BN33),2))
A34: =IF(基础资料!$B$31="","",基础资料!$B$31) | B34: =IF(OR($A34="",NOT(ISNUMBER($H$3))),"",ROUND(SUMIF(账户表,$A34,账户期初)+SUMIFS(流水收入,流水账户,$A34,流水日期,"<"&$B$3)-SUMIFS(流水支出,流水账户,$A34,流水日期,"<"&$B$3),2)) | C34: =IF(OR($A34="",C$6=""),"",ROUND(SUMIFS(流水收入,流水账户,$A34,流水日期,C$6),2)) | D34: =IF(OR($A34="",D$6=""),"",ROUND(SUMIFS(流水支出,流水账户,$A34,流水日期,D$6),2)) | E34: =IF(OR($A34="",E$6=""),"",ROUND(SUMIFS(流水收入,流水账户,$A34,流水日期,E$6),2)) | F34: =IF(OR($A34="",F$6=""),"",ROUND(SUMIFS(流水支出,流水账户,$A34,流水日期,F$6),2)) | G34: =IF(OR($A34="",G$6=""),"",ROUND(SUMIFS(流水收入,流水账户,$A34,流水日期,G$6),2)) | H34: =IF(OR($A34="",H$6=""),"",ROUND(SUMIFS(流水支出,流水账户,$A34,流水日期,H$6),2)) | I34: =IF(OR($A34="",I$6=""),"",ROUND(SUMIFS(流水收入,流水账户,$A34,流水日期,I$6),2)) | J34: =IF(OR($A34="",J$6=""),"",ROUND(SUMIFS(流水支出,流水账户,$A34,流水日期,J$6),2)) | K34: =IF(OR($A34="",K$6=""),"",ROUND(SUMIFS(流水收入,流水账户,$A34,流水日期,K$6),2)) | L34: =IF(OR($A34="",L$6=""),"",ROUND(SUMIFS(流水支出,流水账户,$A34,流水日期,L$6),2)) | M34: =IF(OR($A34="",M$6=""),"",ROUND(SUMIFS(流水收入,流水账户,$A34,流水日期,M$6),2)) | N34: =IF(OR($A34="",N$6=""),"",ROUND(SUMIFS(流水支出,流水账户,$A34,流水日期,N$6),2)) | O34: =IF(OR($A34="",O$6=""),"",ROUND(SUMIFS(流水收入,流水账户,$A34,流水日期,O$6),2)) | P34: =IF(OR($A34="",P$6=""),"",ROUND(SUMIFS(流水支出,流水账户,$A34,流水日期,P$6),2)) | Q34: =IF(OR($A34="",Q$6=""),"",ROUND(SUMIFS(流水收入,流水账户,$A34,流水日期,Q$6),2)) | R34: =IF(OR($A34="",R$6=""),"",ROUND(SUMIFS(流水支出,流水账户,$A34,流水日期,R$6),2)) | S34: =IF(OR($A34="",S$6=""),"",ROUND(SUMIFS(流水收入,流水账户,$A34,流水日期,S$6),2)) | T34: =IF(OR($A34="",T$6=""),"",ROUND(SUMIFS(流水支出,流水账户,$A34,流水日期,T$6),2)) | U34: =IF(OR($A34="",U$6=""),"",ROUND(SUMIFS(流水收入,流水账户,$A34,流水日期,U$6),2)) | V34: =IF(OR($A34="",V$6=""),"",ROUND(SUMIFS(流水支出,流水账户,$A34,流水日期,V$6),2)) | W34: =IF(OR($A34="",W$6=""),"",ROUND(SUMIFS(流水收入,流水账户,$A34,流水日期,W$6),2)) | X34: =IF(OR($A34="",X$6=""),"",ROUND(SUMIFS(流水支出,流水账户,$A34,流水日期,X$6),2)) | Y34: =IF(OR($A34="",Y$6=""),"",ROUND(SUMIFS(流水收入,流水账户,$A34,流水日期,Y$6),2)) | Z34: =IF(OR($A34="",Z$6=""),"",ROUND(SUMIFS(流水支出,流水账户,$A34,流水日期,Z$6),2)) | AA34: =IF(OR($A34="",AA$6=""),"",ROUND(SUMIFS(流水收入,流水账户,$A34,流水日期,AA$6),2)) | AB34: =IF(OR($A34="",AB$6=""),"",ROUND(SUMIFS(流水支出,流水账户,$A34,流水日期,AB$6),2)) | AC34: =IF(OR($A34="",AC$6=""),"",ROUND(SUMIFS(流水收入,流水账户,$A34,流水日期,AC$6),2)) | AD34: =IF(OR($A34="",AD$6=""),"",ROUND(SUMIFS(流水支出,流水账户,$A34,流水日期,AD$6),2)) | AE34: =IF(OR($A34="",AE$6=""),"",ROUND(SUMIFS(流水收入,流水账户,$A34,流水日期,AE$6),2)) | AF34: =IF(OR($A34="",AF$6=""),"",ROUND(SUMIFS(流水支出,流水账户,$A34,流水日期,AF$6),2)) | AG34: =IF(OR($A34="",AG$6=""),"",ROUND(SUMIFS(流水收入,流水账户,$A34,流水日期,AG$6),2)) | AH34: =IF(OR($A34="",AH$6=""),"",ROUND(SUMIFS(流水支出,流水账户,$A34,流水日期,AH$6),2)) | AI34: =IF(OR($A34="",AI$6=""),"",ROUND(SUMIFS(流水收入,流水账户,$A34,流水日期,AI$6),2)) | AJ34: =IF(OR($A34="",AJ$6=""),"",ROUND(SUMIFS(流水支出,流水账户,$A34,流水日期,AJ$6),2)) | AK34: =IF(OR($A34="",AK$6=""),"",ROUND(SUMIFS(流水收入,流水账户,$A34,流水日期,AK$6),2)) | AL34: =IF(OR($A34="",AL$6=""),"",ROUND(SUMIFS(流水支出,流水账户,$A34,流水日期,AL$6),2)) | AM34: =IF(OR($A34="",AM$6=""),"",ROUND(SUMIFS(流水收入,流水账户,$A34,流水日期,AM$6),2)) | AN34: =IF(OR($A34="",AN$6=""),"",ROUND(SUMIFS(流水支出,流水账户,$A34,流水日期,AN$6),2)) | AO34: =IF(OR($A34="",AO$6=""),"",ROUND(SUMIFS(流水收入,流水账户,$A34,流水日期,AO$6),2)) | AP34: =IF(OR($A34="",AP$6=""),"",ROUND(SUMIFS(流水支出,流水账户,$A34,流水日期,AP$6),2)) | AQ34: =IF(OR($A34="",AQ$6=""),"",ROUND(SUMIFS(流水收入,流水账户,$A34,流水日期,AQ$6),2)) | AR34: =IF(OR($A34="",AR$6=""),"",ROUND(SUMIFS(流水支出,流水账户,$A34,流水日期,AR$6),2)) | AS34: =IF(OR($A34="",AS$6=""),"",ROUND(SUMIFS(流水收入,流水账户,$A34,流水日期,AS$6),2)) | AT34: =IF(OR($A34="",AT$6=""),"",ROUND(SUMIFS(流水支出,流水账户,$A34,流水日期,AT$6),2)) | AU34: =IF(OR($A34="",AU$6=""),"",ROUND(SUMIFS(流水收入,流水账户,$A34,流水日期,AU$6),2)) | AV34: =IF(OR($A34="",AV$6=""),"",ROUND(SUMIFS(流水支出,流水账户,$A34,流水日期,AV$6),2)) | AW34: =IF(OR($A34="",AW$6=""),"",ROUND(SUMIFS(流水收入,流水账户,$A34,流水日期,AW$6),2)) | AX34: =IF(OR($A34="",AX$6=""),"",ROUND(SUMIFS(流水支出,流水账户,$A34,流水日期,AX$6),2)) | AY34: =IF(OR($A34="",AY$6=""),"",ROUND(SUMIFS(流水收入,流水账户,$A34,流水日期,AY$6),2)) | AZ34: =IF(OR($A34="",AZ$6=""),"",ROUND(SUMIFS(流水支出,流水账户,$A34,流水日期,AZ$6),2)) | BA34: =IF(OR($A34="",BA$6=""),"",ROUND(SUMIFS(流水收入,流水账户,$A34,流水日期,BA$6),2)) | BB34: =IF(OR($A34="",BB$6=""),"",ROUND(SUMIFS(流水支出,流水账户,$A34,流水日期,BB$6),2)) | BC34: =IF(OR($A34="",BC$6=""),"",ROUND(SUMIFS(流水收入,流水账户,$A34,流水日期,BC$6),2)) | BD34: =IF(OR($A34="",BD$6=""),"",ROUND(SUMIFS(流水支出,流水账户,$A34,流水日期,BD$6),2)) | BE34: =IF(OR($A34="",BE$6=""),"",ROUND(SUMIFS(流水收入,流水账户,$A34,流水日期,BE$6),2)) | BF34: =IF(OR($A34="",BF$6=""),"",ROUND(SUMIFS(流水支出,流水账户,$A34,流水日期,BF$6),2)) | BG34: =IF(OR($A34="",BG$6=""),"",ROUND(SUMIFS(流水收入,流水账户,$A34,流水日期,BG$6),2)) | BH34: =IF(OR($A34="",BH$6=""),"",ROUND(SUMIFS(流水支出,流水账户,$A34,流水日期,BH$6),2)) | BI34: =IF(OR($A34="",BI$6=""),"",ROUND(SUMIFS(流水收入,流水账户,$A34,流水日期,BI$6),2)) | BJ34: =IF(OR($A34="",BJ$6=""),"",ROUND(SUMIFS(流水支出,流水账户,$A34,流水日期,BJ$6),2)) | BK34: =IF(OR($A34="",BK$6=""),"",ROUND(SUMIFS(流水收入,流水账户,$A34,流水日期,BK$6),2)) | BL34: =IF(OR($A34="",BL$6=""),"",ROUND(SUMIFS(流水支出,流水账户,$A34,流水日期,BL$6),2)) | BM34: =IF($A34="","",ROUND(SUMIF($C$7:$BL$7,"收款",C34:BL34),2)) | BN34: =IF($A34="","",ROUND(SUMIF($C$7:$BL$7,"付款",C34:BL34),2)) | BO34: =IF($A34="","",ROUND(N($B34)+N(BM34)-N(BN34),2))
A35: =IF(基础资料!$B$32="","",基础资料!$B$32) | B35: =IF(OR($A35="",NOT(ISNUMBER($H$3))),"",ROUND(SUMIF(账户表,$A35,账户期初)+SUMIFS(流水收入,流水账户,$A35,流水日期,"<"&$B$3)-SUMIFS(流水支出,流水账户,$A35,流水日期,"<"&$B$3),2)) | C35: =IF(OR($A35="",C$6=""),"",ROUND(SUMIFS(流水收入,流水账户,$A35,流水日期,C$6),2)) | D35: =IF(OR($A35="",D$6=""),"",ROUND(SUMIFS(流水支出,流水账户,$A35,流水日期,D$6),2)) | E35: =IF(OR($A35="",E$6=""),"",ROUND(SUMIFS(流水收入,流水账户,$A35,流水日期,E$6),2)) | F35: =IF(OR($A35="",F$6=""),"",ROUND(SUMIFS(流水支出,流水账户,$A35,流水日期,F$6),2)) | G35: =IF(OR($A35="",G$6=""),"",ROUND(SUMIFS(流水收入,流水账户,$A35,流水日期,G$6),2)) | H35: =IF(OR($A35="",H$6=""),"",ROUND(SUMIFS(流水支出,流水账户,$A35,流水日期,H$6),2)) | I35: =IF(OR($A35="",I$6=""),"",ROUND(SUMIFS(流水收入,流水账户,$A35,流水日期,I$6),2)) | J35: =IF(OR($A35="",J$6=""),"",ROUND(SUMIFS(流水支出,流水账户,$A35,流水日期,J$6),2)) | K35: =IF(OR($A35="",K$6=""),"",ROUND(SUMIFS(流水收入,流水账户,$A35,流水日期,K$6),2)) | L35: =IF(OR($A35="",L$6=""),"",ROUND(SUMIFS(流水支出,流水账户,$A35,流水日期,L$6),2)) | M35: =IF(OR($A35="",M$6=""),"",ROUND(SUMIFS(流水收入,流水账户,$A35,流水日期,M$6),2)) | N35: =IF(OR($A35="",N$6=""),"",ROUND(SUMIFS(流水支出,流水账户,$A35,流水日期,N$6),2)) | O35: =IF(OR($A35="",O$6=""),"",ROUND(SUMIFS(流水收入,流水账户,$A35,流水日期,O$6),2)) | P35: =IF(OR($A35="",P$6=""),"",ROUND(SUMIFS(流水支出,流水账户,$A35,流水日期,P$6),2)) | Q35: =IF(OR($A35="",Q$6=""),"",ROUND(SUMIFS(流水收入,流水账户,$A35,流水日期,Q$6),2)) | R35: =IF(OR($A35="",R$6=""),"",ROUND(SUMIFS(流水支出,流水账户,$A35,流水日期,R$6),2)) | S35: =IF(OR($A35="",S$6=""),"",ROUND(SUMIFS(流水收入,流水账户,$A35,流水日期,S$6),2)) | T35: =IF(OR($A35="",T$6=""),"",ROUND(SUMIFS(流水支出,流水账户,$A35,流水日期,T$6),2)) | U35: =IF(OR($A35="",U$6=""),"",ROUND(SUMIFS(流水收入,流水账户,$A35,流水日期,U$6),2)) | V35: =IF(OR($A35="",V$6=""),"",ROUND(SUMIFS(流水支出,流水账户,$A35,流水日期,V$6),2)) | W35: =IF(OR($A35="",W$6=""),"",ROUND(SUMIFS(流水收入,流水账户,$A35,流水日期,W$6),2)) | X35: =IF(OR($A35="",X$6=""),"",ROUND(SUMIFS(流水支出,流水账户,$A35,流水日期,X$6),2)) | Y35: =IF(OR($A35="",Y$6=""),"",ROUND(SUMIFS(流水收入,流水账户,$A35,流水日期,Y$6),2)) | Z35: =IF(OR($A35="",Z$6=""),"",ROUND(SUMIFS(流水支出,流水账户,$A35,流水日期,Z$6),2)) | AA35: =IF(OR($A35="",AA$6=""),"",ROUND(SUMIFS(流水收入,流水账户,$A35,流水日期,AA$6),2)) | AB35: =IF(OR($A35="",AB$6=""),"",ROUND(SUMIFS(流水支出,流水账户,$A35,流水日期,AB$6),2)) | AC35: =IF(OR($A35="",AC$6=""),"",ROUND(SUMIFS(流水收入,流水账户,$A35,流水日期,AC$6),2)) | AD35: =IF(OR($A35="",AD$6=""),"",ROUND(SUMIFS(流水支出,流水账户,$A35,流水日期,AD$6),2)) | AE35: =IF(OR($A35="",AE$6=""),"",ROUND(SUMIFS(流水收入,流水账户,$A35,流水日期,AE$6),2)) | AF35: =IF(OR($A35="",AF$6=""),"",ROUND(SUMIFS(流水支出,流水账户,$A35,流水日期,AF$6),2)) | AG35: =IF(OR($A35="",AG$6=""),"",ROUND(SUMIFS(流水收入,流水账户,$A35,流水日期,AG$6),2)) | AH35: =IF(OR($A35="",AH$6=""),"",ROUND(SUMIFS(流水支出,流水账户,$A35,流水日期,AH$6),2)) | AI35: =IF(OR($A35="",AI$6=""),"",ROUND(SUMIFS(流水收入,流水账户,$A35,流水日期,AI$6),2)) | AJ35: =IF(OR($A35="",AJ$6=""),"",ROUND(SUMIFS(流水支出,流水账户,$A35,流水日期,AJ$6),2)) | AK35: =IF(OR($A35="",AK$6=""),"",ROUND(SUMIFS(流水收入,流水账户,$A35,流水日期,AK$6),2)) | AL35: =IF(OR($A35="",AL$6=""),"",ROUND(SUMIFS(流水支出,流水账户,$A35,流水日期,AL$6),2)) | AM35: =IF(OR($A35="",AM$6=""),"",ROUND(SUMIFS(流水收入,流水账户,$A35,流水日期,AM$6),2)) | AN35: =IF(OR($A35="",AN$6=""),"",ROUND(SUMIFS(流水支出,流水账户,$A35,流水日期,AN$6),2)) | AO35: =IF(OR($A35="",AO$6=""),"",ROUND(SUMIFS(流水收入,流水账户,$A35,流水日期,AO$6),2)) | AP35: =IF(OR($A35="",AP$6=""),"",ROUND(SUMIFS(流水支出,流水账户,$A35,流水日期,AP$6),2)) | AQ35: =IF(OR($A35="",AQ$6=""),"",ROUND(SUMIFS(流水收入,流水账户,$A35,流水日期,AQ$6),2)) | AR35: =IF(OR($A35="",AR$6=""),"",ROUND(SUMIFS(流水支出,流水账户,$A35,流水日期,AR$6),2)) | AS35: =IF(OR($A35="",AS$6=""),"",ROUND(SUMIFS(流水收入,流水账户,$A35,流水日期,AS$6),2)) | AT35: =IF(OR($A35="",AT$6=""),"",ROUND(SUMIFS(流水支出,流水账户,$A35,流水日期,AT$6),2)) | AU35: =IF(OR($A35="",AU$6=""),"",ROUND(SUMIFS(流水收入,流水账户,$A35,流水日期,AU$6),2)) | AV35: =IF(OR($A35="",AV$6=""),"",ROUND(SUMIFS(流水支出,流水账户,$A35,流水日期,AV$6),2)) | AW35: =IF(OR($A35="",AW$6=""),"",ROUND(SUMIFS(流水收入,流水账户,$A35,流水日期,AW$6),2)) | AX35: =IF(OR($A35="",AX$6=""),"",ROUND(SUMIFS(流水支出,流水账户,$A35,流水日期,AX$6),2)) | AY35: =IF(OR($A35="",AY$6=""),"",ROUND(SUMIFS(流水收入,流水账户,$A35,流水日期,AY$6),2)) | AZ35: =IF(OR($A35="",AZ$6=""),"",ROUND(SUMIFS(流水支出,流水账户,$A35,流水日期,AZ$6),2)) | BA35: =IF(OR($A35="",BA$6=""),"",ROUND(SUMIFS(流水收入,流水账户,$A35,流水日期,BA$6),2)) | BB35: =IF(OR($A35="",BB$6=""),"",ROUND(SUMIFS(流水支出,流水账户,$A35,流水日期,BB$6),2)) | BC35: =IF(OR($A35="",BC$6=""),"",ROUND(SUMIFS(流水收入,流水账户,$A35,流水日期,BC$6),2)) | BD35: =IF(OR($A35="",BD$6=""),"",ROUND(SUMIFS(流水支出,流水账户,$A35,流水日期,BD$6),2)) | BE35: =IF(OR($A35="",BE$6=""),"",ROUND(SUMIFS(流水收入,流水账户,$A35,流水日期,BE$6),2)) | BF35: =IF(OR($A35="",BF$6=""),"",ROUND(SUMIFS(流水支出,流水账户,$A35,流水日期,BF$6),2)) | BG35: =IF(OR($A35="",BG$6=""),"",ROUND(SUMIFS(流水收入,流水账户,$A35,流水日期,BG$6),2)) | BH35: =IF(OR($A35="",BH$6=""),"",ROUND(SUMIFS(流水支出,流水账户,$A35,流水日期,BH$6),2)) | BI35: =IF(OR($A35="",BI$6=""),"",ROUND(SUMIFS(流水收入,流水账户,$A35,流水日期,BI$6),2)) | BJ35: =IF(OR($A35="",BJ$6=""),"",ROUND(SUMIFS(流水支出,流水账户,$A35,流水日期,BJ$6),2)) | BK35: =IF(OR($A35="",BK$6=""),"",ROUND(SUMIFS(流水收入,流水账户,$A35,流水日期,BK$6),2)) | BL35: =IF(OR($A35="",BL$6=""),"",ROUND(SUMIFS(流水支出,流水账户,$A35,流水日期,BL$6),2)) | BM35: =IF($A35="","",ROUND(SUMIF($C$7:$BL$7,"收款",C35:BL35),2)) | BN35: =IF($A35="","",ROUND(SUMIF($C$7:$BL$7,"付款",C35:BL35),2)) | BO35: =IF($A35="","",ROUND(N($B35)+N(BM35)-N(BN35),2))
A36: =IF(基础资料!$B$33="","",基础资料!$B$33) | B36: =IF(OR($A36="",NOT(ISNUMBER($H$3))),"",ROUND(SUMIF(账户表,$A36,账户期初)+SUMIFS(流水收入,流水账户,$A36,流水日期,"<"&$B$3)-SUMIFS(流水支出,流水账户,$A36,流水日期,"<"&$B$3),2)) | C36: =IF(OR($A36="",C$6=""),"",ROUND(SUMIFS(流水收入,流水账户,$A36,流水日期,C$6),2)) | D36: =IF(OR($A36="",D$6=""),"",ROUND(SUMIFS(流水支出,流水账户,$A36,流水日期,D$6),2)) | E36: =IF(OR($A36="",E$6=""),"",ROUND(SUMIFS(流水收入,流水账户,$A36,流水日期,E$6),2)) | F36: =IF(OR($A36="",F$6=""),"",ROUND(SUMIFS(流水支出,流水账户,$A36,流水日期,F$6),2)) | G36: =IF(OR($A36="",G$6=""),"",ROUND(SUMIFS(流水收入,流水账户,$A36,流水日期,G$6),2)) | H36: =IF(OR($A36="",H$6=""),"",ROUND(SUMIFS(流水支出,流水账户,$A36,流水日期,H$6),2)) | I36: =IF(OR($A36="",I$6=""),"",ROUND(SUMIFS(流水收入,流水账户,$A36,流水日期,I$6),2)) | J36: =IF(OR($A36="",J$6=""),"",ROUND(SUMIFS(流水支出,流水账户,$A36,流水日期,J$6),2)) | K36: =IF(OR($A36="",K$6=""),"",ROUND(SUMIFS(流水收入,流水账户,$A36,流水日期,K$6),2)) | L36: =IF(OR($A36="",L$6=""),"",ROUND(SUMIFS(流水支出,流水账户,$A36,流水日期,L$6),2)) | M36: =IF(OR($A36="",M$6=""),"",ROUND(SUMIFS(流水收入,流水账户,$A36,流水日期,M$6),2)) | N36: =IF(OR($A36="",N$6=""),"",ROUND(SUMIFS(流水支出,流水账户,$A36,流水日期,N$6),2)) | O36: =IF(OR($A36="",O$6=""),"",ROUND(SUMIFS(流水收入,流水账户,$A36,流水日期,O$6),2)) | P36: =IF(OR($A36="",P$6=""),"",ROUND(SUMIFS(流水支出,流水账户,$A36,流水日期,P$6),2)) | Q36: =IF(OR($A36="",Q$6=""),"",ROUND(SUMIFS(流水收入,流水账户,$A36,流水日期,Q$6),2)) | R36: =IF(OR($A36="",R$6=""),"",ROUND(SUMIFS(流水支出,流水账户,$A36,流水日期,R$6),2)) | S36: =IF(OR($A36="",S$6=""),"",ROUND(SUMIFS(流水收入,流水账户,$A36,流水日期,S$6),2)) | T36: =IF(OR($A36="",T$6=""),"",ROUND(SUMIFS(流水支出,流水账户,$A36,流水日期,T$6),2)) | U36: =IF(OR($A36="",U$6=""),"",ROUND(SUMIFS(流水收入,流水账户,$A36,流水日期,U$6),2)) | V36: =IF(OR($A36="",V$6=""),"",ROUND(SUMIFS(流水支出,流水账户,$A36,流水日期,V$6),2)) | W36: =IF(OR($A36="",W$6=""),"",ROUND(SUMIFS(流水收入,流水账户,$A36,流水日期,W$6),2)) | X36: =IF(OR($A36="",X$6=""),"",ROUND(SUMIFS(流水支出,流水账户,$A36,流水日期,X$6),2)) | Y36: =IF(OR($A36="",Y$6=""),"",ROUND(SUMIFS(流水收入,流水账户,$A36,流水日期,Y$6),2)) | Z36: =IF(OR($A36="",Z$6=""),"",ROUND(SUMIFS(流水支出,流水账户,$A36,流水日期,Z$6),2)) | AA36: =IF(OR($A36="",AA$6=""),"",ROUND(SUMIFS(流水收入,流水账户,$A36,流水日期,AA$6),2)) | AB36: =IF(OR($A36="",AB$6=""),"",ROUND(SUMIFS(流水支出,流水账户,$A36,流水日期,AB$6),2)) | AC36: =IF(OR($A36="",AC$6=""),"",ROUND(SUMIFS(流水收入,流水账户,$A36,流水日期,AC$6),2)) | AD36: =IF(OR($A36="",AD$6=""),"",ROUND(SUMIFS(流水支出,流水账户,$A36,流水日期,AD$6),2)) | AE36: =IF(OR($A36="",AE$6=""),"",ROUND(SUMIFS(流水收入,流水账户,$A36,流水日期,AE$6),2)) | AF36: =IF(OR($A36="",AF$6=""),"",ROUND(SUMIFS(流水支出,流水账户,$A36,流水日期,AF$6),2)) | AG36: =IF(OR($A36="",AG$6=""),"",ROUND(SUMIFS(流水收入,流水账户,$A36,流水日期,AG$6),2)) | AH36: =IF(OR($A36="",AH$6=""),"",ROUND(SUMIFS(流水支出,流水账户,$A36,流水日期,AH$6),2)) | AI36: =IF(OR($A36="",AI$6=""),"",ROUND(SUMIFS(流水收入,流水账户,$A36,流水日期,AI$6),2)) | AJ36: =IF(OR($A36="",AJ$6=""),"",ROUND(SUMIFS(流水支出,流水账户,$A36,流水日期,AJ$6),2)) | AK36: =IF(OR($A36="",AK$6=""),"",ROUND(SUMIFS(流水收入,流水账户,$A36,流水日期,AK$6),2)) | AL36: =IF(OR($A36="",AL$6=""),"",ROUND(SUMIFS(流水支出,流水账户,$A36,流水日期,AL$6),2)) | AM36: =IF(OR($A36="",AM$6=""),"",ROUND(SUMIFS(流水收入,流水账户,$A36,流水日期,AM$6),2)) | AN36: =IF(OR($A36="",AN$6=""),"",ROUND(SUMIFS(流水支出,流水账户,$A36,流水日期,AN$6),2)) | AO36: =IF(OR($A36="",AO$6=""),"",ROUND(SUMIFS(流水收入,流水账户,$A36,流水日期,AO$6),2)) | AP36: =IF(OR($A36="",AP$6=""),"",ROUND(SUMIFS(流水支出,流水账户,$A36,流水日期,AP$6),2)) | AQ36: =IF(OR($A36="",AQ$6=""),"",ROUND(SUMIFS(流水收入,流水账户,$A36,流水日期,AQ$6),2)) | AR36: =IF(OR($A36="",AR$6=""),"",ROUND(SUMIFS(流水支出,流水账户,$A36,流水日期,AR$6),2)) | AS36: =IF(OR($A36="",AS$6=""),"",ROUND(SUMIFS(流水收入,流水账户,$A36,流水日期,AS$6),2)) | AT36: =IF(OR($A36="",AT$6=""),"",ROUND(SUMIFS(流水支出,流水账户,$A36,流水日期,AT$6),2)) | AU36: =IF(OR($A36="",AU$6=""),"",ROUND(SUMIFS(流水收入,流水账户,$A36,流水日期,AU$6),2)) | AV36: =IF(OR($A36="",AV$6=""),"",ROUND(SUMIFS(流水支出,流水账户,$A36,流水日期,AV$6),2)) | AW36: =IF(OR($A36="",AW$6=""),"",ROUND(SUMIFS(流水收入,流水账户,$A36,流水日期,AW$6),2)) | AX36: =IF(OR($A36="",AX$6=""),"",ROUND(SUMIFS(流水支出,流水账户,$A36,流水日期,AX$6),2)) | AY36: =IF(OR($A36="",AY$6=""),"",ROUND(SUMIFS(流水收入,流水账户,$A36,流水日期,AY$6),2)) | AZ36: =IF(OR($A36="",AZ$6=""),"",ROUND(SUMIFS(流水支出,流水账户,$A36,流水日期,AZ$6),2)) | BA36: =IF(OR($A36="",BA$6=""),"",ROUND(SUMIFS(流水收入,流水账户,$A36,流水日期,BA$6),2)) | BB36: =IF(OR($A36="",BB$6=""),"",ROUND(SUMIFS(流水支出,流水账户,$A36,流水日期,BB$6),2)) | BC36: =IF(OR($A36="",BC$6=""),"",ROUND(SUMIFS(流水收入,流水账户,$A36,流水日期,BC$6),2)) | BD36: =IF(OR($A36="",BD$6=""),"",ROUND(SUMIFS(流水支出,流水账户,$A36,流水日期,BD$6),2)) | BE36: =IF(OR($A36="",BE$6=""),"",ROUND(SUMIFS(流水收入,流水账户,$A36,流水日期,BE$6),2)) | BF36: =IF(OR($A36="",BF$6=""),"",ROUND(SUMIFS(流水支出,流水账户,$A36,流水日期,BF$6),2)) | BG36: =IF(OR($A36="",BG$6=""),"",ROUND(SUMIFS(流水收入,流水账户,$A36,流水日期,BG$6),2)) | BH36: =IF(OR($A36="",BH$6=""),"",ROUND(SUMIFS(流水支出,流水账户,$A36,流水日期,BH$6),2)) | BI36: =IF(OR($A36="",BI$6=""),"",ROUND(SUMIFS(流水收入,流水账户,$A36,流水日期,BI$6),2)) | BJ36: =IF(OR($A36="",BJ$6=""),"",ROUND(SUMIFS(流水支出,流水账户,$A36,流水日期,BJ$6),2)) | BK36: =IF(OR($A36="",BK$6=""),"",ROUND(SUMIFS(流水收入,流水账户,$A36,流水日期,BK$6),2)) | BL36: =IF(OR($A36="",BL$6=""),"",ROUND(SUMIFS(流水支出,流水账户,$A36,流水日期,BL$6),2)) | BM36: =IF($A36="","",ROUND(SUMIF($C$7:$BL$7,"收款",C36:BL36),2)) | BN36: =IF($A36="","",ROUND(SUMIF($C$7:$BL$7,"付款",C36:BL36),2)) | BO36: =IF($A36="","",ROUND(N($B36)+N(BM36)-N(BN36),2))
