Workbook

Sheet 首页
A1: 三公司财务账套 · 2026 年
A2: 农业基地 / 木业 / 科技，一套表三家账。录【购销流水】【资金流水】【生产加工】【其他分录】四张表，报表自己出。一年一套：把【参数设置】的会计年度改成下一年，另存一个文件就是新账。
A4: 会计年度 | B4: =参数设置!$B$5 -> 2026 | C4: 本年凭证数 | D4: =COUNTIF(记账分录!$P$6:$P$5505,"有") -> 222 | E4: =IF(校验中心!$E$42=0,"√ 全部校验通过，可以出报表","✗ 校验中心还有 "&校验中心!$E$42&" 项没过，先去【校验中心】看红色那几行") -> √ 全部校验通过，可以出报表
A6: 一、三家公司关键数（口径＝各报表页当前选的期间，默认整年）
A7: 指 标 | B7: 农业基地公司 | C7: 木业公司 | D7: 科技公司 | E7: 三家合计 | G7: 账户余额 | H7: =资金账户!$K$27 -> 1274240
A8: 营业收入 | B8: ='农业-利润表'!$C$6 -> 329000 | C8: ='木业-利润表'!$C$6 -> 582000 | D8: ='科技-利润表'!$C$6 -> 444750 | E8: =SUM(B8:D8) -> 1355750 | G8: 账实核对 | H8: =资金账户!$G$30 -> √ 账实一致
A9: 营业成本 | B9: ='农业-利润表'!$C$7 -> 177927.62 | C9: ='木业-利润表'!$C$7 -> 366029.05 | D9: ='科技-利润表'!$C$7 -> 138396.43 | E9: =SUM(B9:D9) -> 682353.1 | G9: 内部交易 | H9: =IF(COUNTIF(内部交易核对!$I$6:$I$11,"✗*")=0,"√ 三家之间对得上","✗ 有 "&COUNTIF(内部交易核对!$I$6:$I$11,"✗*")&" 对对不上") -> √ 三家之间对得上
A10: 毛利 | B10: =B8-B9 -> 151072.38 | C10: =C8-C9 -> 215970.95 | D10: =D8-D9 -> 306353.57 | E10: =SUM(B10:D10) -> 673396.9 | G10: 合并后收入 | H10: =三公司合并报表!$G$8 -> 1110750
A11: 营业利润 | B11: ='农业-利润表'!$C$14 -> 22072.38 | C11: ='木业-利润表'!$C$14 -> 71150.95 | D11: ='科技-利润表'!$C$14 -> 169693.57 | E11: =SUM(B11:D11) -> 262916.9 | G11: 合并后净利 | H11: =三公司合并报表!$G$21 -> 244916.9
A12: 利润总额 | B12: ='农业-利润表'!$C$17 -> 22072.38 | C12: ='木业-利润表'!$C$17 -> 71150.95 | D12: ='科技-利润表'!$C$17 -> 169693.57 | E12: =SUM(B12:D12) -> 262916.9
A13: 净利润 | B13: ='农业-利润表'!$C$19 -> 22072.38 | C13: ='木业-利润表'!$C$19 -> 65150.95 | D13: ='科技-利润表'!$C$19 -> 157693.57 | E13: =SUM(B13:D13) -> 244916.9
A14: 资产总计 | B14: ='农业-资产负债表'!$C$25 -> 2310272.4 | C14: ='木业-资产负债表'!$C$25 -> 1686400.9 | D14: ='科技-资产负债表'!$C$25 -> 1267433.6 | E14: =SUM(B14:D14) -> 5264106.9
A15: 货币资金 | B15: ='农业-资产负债表'!$C$7 -> 319200 | C15: ='木业-资产负债表'!$C$7 -> 420380 | D15: ='科技-资产负债表'!$C$7 -> 534660 | E15: =SUM(B15:D15) -> 1274240
A16: 存货 | B16: ='农业-资产负债表'!$C$11 -> 68072.38 | C16: ='木业-资产负债表'!$C$11 -> 212020.95 | D16: ='科技-资产负债表'!$C$11 -> 124023.57 | E16: =SUM(B16:D16) -> 404116.9
A17: 应收账款 | B17: ='农业-资产负债表'!$C$8 -> 73000 | C17: ='木业-资产负债表'!$C$8 -> 368000 | D17: ='科技-资产负债表'!$C$8 -> 202750 | E17: =SUM(B17:D17) -> 643750
A18: 应付账款 | B18: ='农业-资产负债表'!$G$8 -> 48200 | C18: ='木业-资产负债表'!$G$8 -> 127000 | D18: ='科技-资产负债表'!$G$8 -> 61000 | E18: =SUM(B18:D18) -> 236200
A19: 负债合计 | B19: ='农业-资产负债表'!$G$16 -> 328200 | C19: ='木业-资产负债表'!$G$16 -> 620000 | D19: ='科技-资产负债表'!$G$16 -> 90600 | E19: =SUM(B19:D19) -> 1038800
A20: 所有者权益 | B20: ='农业-资产负债表'!$G$22 -> 1982072.4 | C20: ='木业-资产负债表'!$G$22 -> 1066400.9 | D20: ='科技-资产负债表'!$G$22 -> 1176833.6 | E20: =SUM(B20:D20) -> 4225306.9
A21: 毛利率 | B21: =IF(ROUND(B8,2)=0,"—",B10/B8) -> 0.45918657 | C21: =IF(ROUND(C8,2)=0,"—",C10/C8) -> 0.37108411 | D21: =IF(ROUND(D8,2)=0,"—",D10/D8) -> 0.68882197 | E21: =IF(ROUND(E8,2)=0,"—",E10/E8) -> 0.49669696
A23: 二、常用入口
A24: ① 每天录这四张 | B24: =HYPERLINK("#'购销流水'!A1","购销流水") -> 购销流水 | C24: =HYPERLINK("#'资金流水'!A1","资金流水") -> 资金流水 | D24: =HYPERLINK("#'生产加工'!A1","生产加工") -> 生产加工 | E24: =HYPERLINK("#'其他分录'!A1","其他分录") -> 其他分录
A25: ② 先建好档案 | B25: =HYPERLINK("#'参数设置'!A1","参数设置") -> 参数设置 | C25: =HYPERLINK("#'商品档案'!A1","商品档案") -> 商品档案 | D25: =HYPERLINK("#'往来单位'!A1","往来单位") -> 往来单位 | E25: =HYPERLINK("#'资金账户'!A1","资金账户") -> 资金账户
B26: =HYPERLINK("#'期初余额'!A1","期初余额") -> 期初余额 | C26: =HYPERLINK("#'会计科目表'!A1","会计科目表") -> 会计科目表 | D26: =HYPERLINK("#'记账规则'!A1","记账规则") -> 记账规则
A27: ③ 出报表 | B27: =HYPERLINK("#'农业-资产负债表'!A1","农业-资产负债表") -> 农业-资产负债表 | C27: =HYPERLINK("#'农业-利润表'!A1","农业-利润表") -> 农业-利润表 | D27: =HYPERLINK("#'木业-资产负债表'!A1","木业-资产负债表") -> 木业-资产负债表 | E27: =HYPERLINK("#'木业-利润表'!A1","木业-利润表") -> 木业-利润表
B28: =HYPERLINK("#'科技-资产负债表'!A1","科技-资产负债表") -> 科技-资产负债表 | C28: =HYPERLINK("#'科技-利润表'!A1","科技-利润表") -> 科技-利润表 | D28: =HYPERLINK("#'三公司合并报表'!A1","三公司合并报表") -> 三公司合并报表
A29: ④ 查台账 | B29: =HYPERLINK("#'科目余额表'!A1","科目余额表") -> 科目余额表 | C29: =HYPERLINK("#'记账分录'!A1","记账分录") -> 记账分录 | D29: =HYPERLINK("#'进销存台账'!A1","进销存台账") -> 进销存台账 | E29: =HYPERLINK("#'收发存查询'!A1","收发存查询") -> 收发存查询
B30: =HYPERLINK("#'往来台账'!A1","往来台账") -> 往来台账 | C30: =HYPERLINK("#'税费台账'!A1","税费台账") -> 税费台账 | D30: =HYPERLINK("#'费用统计'!A1","费用统计") -> 费用统计 | E30: =HYPERLINK("#'内部交易核对'!A1","内部交易核对") -> 内部交易核对
A31: ⑤ 对数 | B31: =HYPERLINK("#'校验中心'!A1","校验中心") -> 校验中心 | C31: =HYPERLINK("#'使用说明'!A1","使用说明") -> 使用说明
A33: 三、表格容量（快满了就去【生成脚本】把容量数字改大重跑，或直接新开一年）
A34: 购销流水 | B34: =COUNT(购销流水!$B$6:$B$805) -> 20 | C34: 800 | D34: =IF($C34=0,"",$B34/$C34) -> 0.025 | E34: =IF($B34/$C34>0.9,"✗ 快满了","√ 够用") -> √ 够用
A35: 资金流水 | B35: =COUNT(资金流水!$B$6:$B$605) -> 34 | C35: 600 | D35: =IF($C35=0,"",$B35/$C35) -> 0.056666667 | E35: =IF($B35/$C35>0.9,"✗ 快满了","√ 够用") -> √ 够用
A36: 生产加工 | B36: =COUNT(生产加工!$B$6:$B$305) -> 36 | C36: 300 | D36: =IF($C36=0,"",$B36/$C36) -> 0.12 | E36: =IF($B36/$C36>0.9,"✗ 快满了","√ 够用") -> √ 够用
A37: 其他分录 | B37: =COUNT(其他分录!$B$6:$B$255) -> 10 | C37: 250 | D37: =IF($C37=0,"",$B37/$C37) -> 0.04 | E37: =IF($B37/$C37>0.9,"✗ 快满了","√ 够用") -> √ 够用
A38: 商品档案 | B38: =COUNTA(商品档案!$A$6:$A$65) -> 25 | C38: 60 | D38: =IF($C38=0,"",$B38/$C38) -> 0.41666667 | E38: =IF($B38/$C38>0.9,"✗ 快满了","√ 够用") -> √ 够用
A39: 往来单位 | B39: =COUNTA(往来单位!$A$6:$A$85) -> 23 | C39: 80 | D39: =IF($C39=0,"",$B39/$C39) -> 0.2875 | E39: =IF($B39/$C39>0.9,"✗ 快满了","√ 够用") -> √ 够用

Sheet 使用说明
A1: 使用说明
A2: 照着这个顺序走一遍，这套表就能自己跑起来。
B5: 主题 | C5: 说 明
A6: 一、这套表怎么转
B7: 四张录入表 | C7: 【购销流水】进货卖货（只管货和票，一律挂应收应付）｜【资金流水】所有账户的收支｜【生产加工】领料、加工费、产成品入库｜【其他分录】折旧摊销计提结转。
B8: 自动往下走 | C8: 四张表 →【记账分录】按【记账规则】展开成借贷 →【科目余额表】→ 三家的资产负债表、利润表和【三公司合并报表】。中间不用你手工做凭证。
B9: 一年一套 | C9: 【参数设置】把会计年度改成新的一年，把四张录入表的数据清掉，再把上年各表的期末数抄到【期初余额】，就是新一年的账。建议每年另存一个文件。
A10: 二、先把档案建好
B11: 参数设置 | C11: 会计年度、附加税率、所得税率，以及「费用项目」清单（资金流水和其他分录的下拉就取这一列）。
B12: 商品档案 | C12: 三家的料和成品。存货/收入/成本科目决定这个商品记到哪个科目。税率一列只是开票时选哪一档的提醒，内账含税核算，不参与计算。
B13: 往来单位 | C13: 客户、供应商、农户，以及三家公司互相。标了「是否内部＝是」的，购销流水会认成内部交易，合并报表按它抵销。
B14: 资金账户 | C14: 实际开了几个户就登几个。几家公司共用一个账号也照登，账户余额按账户算，账务按公司各记各的。
B15: 期初余额 | C15: 左边科目年初余额（借贷各一列），中间存货年初数量金额，右边往来按单位拆。三块都有对账提示。
B16: 会计科目表 / 记账规则 | C16: 一般不用动。要加科目就照格式加一行，「报表项目」必须用报表上已有的项目名。要改某类业务的借贷走向，就去【记账规则】改那一行。
A17: 三、日常录入
B18: 购销流水 | C18: 选公司、业务类型、往来单位、商品编码，填数量和**含税单价**即可，金额＝数量×单价，不拆税。退货用「销售退回/采购退回」，数量填正数。
B19: 向农户收购原木 | C19: 往来单位选那个农户，发票类型选「收购发票」，单价就填实际收购价。内账含税核算，收购价全额进原材料成本，不再拆 9% 进项——能不能抵扣是外账报税的事，内账只看实际付了多少钱。
B20: 资金流水 | C20: 收支混在一张表上按时间顺序录：收进来填「收入金额」，付出去填「支出金额」，金额都是含税实收实付数，右边「账户余额」逐行滚出来。业务类型决定对方科目怎么走，规则里写「@对方」的才要你自己选对方科目。收付货款记得选往来单位，这样【往来台账】才冲得掉；「关联单号」写对应的购销流水序号，日后好核销。
B21: 几家共用一个账号 | C21: 共用账户在【资金账户】里「使用公司」写清楚。资金流水每一行照样选自己的公司，所以账户余额是这个账号的真实余额，而各公司账上的银行存款是各自的——【资金账户】底下有一行「账实对账」把两边加总对上。
B22: 生产加工 | C22: 一个批次号一次加工：先记「领用投入」和「加工费用」，再记「产成品入库」。产出行不用填金额，本批投入合计会按「权重」自动分摊；一批只有一个产出，权重留空就行。
B23: 其他分录 | C23: 折旧、摊销、计提工资、计提房租，一借一贷。一借多贷拆成几行。**税不在这里计提**——内账按实缴，交税那天在【资金流水】记一笔就行。也不用做「结转本年利润」，报表会自动把损益结进未分配利润，你自己再结一次会重复。
A24: 四、看报表
B25: 按起止日期筛选 | C25: 所有汇总和查询表第 3 行都有「年度 / 起始日期 / 截止日期」。都留空＝全部期间；只填年度＝整年；填了起止就按起止。录入表和明细表不筛选，全部显示。
B26: 资产负债表 | C26: 年初数取期初余额表；期末数算到截止日期。未分配利润＝年初未分配＋本年净利润。最后一行「平衡校验」必须是 √。
B27: 利润表 | C27: 「本期金额」是起止区间的发生额，「本年累计」是年初到截止日的累计。下面附毛利率和净利率。
B28: 合并报表 | C28: 三家单体＋小计＋内部抵销＝合并数。内部销售收入/成本、内部应收应付自动抵；「未实现内部存货利润」要你自己估一个填进去（上面有算法），不填按 0。
B29: 进销存台账 / 收发存查询 | C29: 【进销存台账】是全年口径、成本基准表，加权平均单价就在这张表上算，购销结转成本和生产领用都按它取价，所以它不随日期筛选变。要看某段时间的收发存，用【收发存查询】。
B30: 往来台账 / 税费台账 / 费用统计 | C30: 往来台账按公司看每家客户供应商的应收应付；税费台账按公司按月按税种列实缴税费和税负率；费用统计上半张按费用项目、下半张按会计科目。
A31: 五、几个口径说明
B32: 存货计价 | C32: 全年加权平均（含税口径）：单价＝（期初金额＋采购入库金额＋生产入库金额）÷ 对应数量。不含出库，所以不会循环引用。年中看的成本是按全年均价倒推的，和逐笔移动平均会有小差异。
B33: 含税核算 / 实交税费 | C33: 这是内账，全部含税：卖多少钱记多少收入，进货花多少钱记多少成本，费用付多少记多少，一律不拆进项销项，科目表里也没有进项/销项税额。税走【资金流水】的「缴纳税费」——交增值税、附加税、印花税、个税进「税金及附加」，交企业所得税进「所得税费用」，费用项目里选具体税种，【税费台账】按月按税种摊开、给出全年税负率。内部交易两边都是同一个含税金额，所以【内部交易核对】要求分毫不差。
B34: 税率参数只是参考 | C34: 【参数设置】上的附加税率和所得税率不参与任何计算，只是你自己估税时的提醒。实际交了多少，就在【资金流水】记多少。农林牧渔里的林木种植所得免征企业所得税、自产农产品销售免征增值税，所以农业基地公司示例里全年税费是 0。
B35: 示例数据 | C35: 四张录入表里都放了示例（购销 20 条、资金 34 条、生产 36 条、其他分录 10 条），专门用来现场验公式。正式用之前，把这些行整行删掉即可，【期初余额】和【商品档案】里的示例也一并换成你自己的。

Sheet 参数设置
A1: 参数设置
A2: 一年一套表：先把下面的会计年度改成本年度，再另存为新文件，就是新一年的账。这套表是内账口径——全部含税核算、税按实缴进费用，右边有说明。
A5: 会计年度 | B5: 2026 | C5: 期初日期 | D5: =DATE($B$5,1,1) -> 46023 | E5: 期末日期 | F5: =DATE($B$5,12,31) -> 46387 | G5: 附加税率（参考） | H5: 0.12 | I5: 所得税率（参考） | J5: 0.05
A6: 说明 | B6: 本账套是内账：收入成本费用一律含税核算，税按实际缴纳当期计入费用，不计提、不拆进项销项。这两个税率只是算税时给你参考用（附加税＝城建 7%＋教育费附加 3%＋地方教育附加 2%；所得税按小微实际税负 5%），表里的任何计算都不用它们。农林牧渔中的林木种植所得免征企业所得税、自产农产品销售免征增值税，农业基地公司示例里就没有税。
A8: 一、三家公司
A9: 简称（各表都用这个） | B9: 公司全称 | C9: 纳税人身份 | D9: 主营业务
A10: 农业 | B10: 农业基地公司 | C10: 一般纳税人 | D10: 林木种植（原木）、艾草种植，自产农产品免征增值税 | J10: =COUNTIFS(记账分录!$F$6:$F$5505,$A10) -> 70
A11: 木业 | B11: 木业公司 | C11: 一般纳税人 | D11: 收购原木加工板材、模板、方料并销售 | J11: =COUNTIFS(记账分录!$F$6:$F$5505,$A11) -> 76
A12: 科技 | B12: 科技公司 | C12: 一般纳税人 | D12: 收购干艾草提取艾草精油及衍生品并销售 | J12: =COUNTIFS(记账分录!$F$6:$F$5505,$A12) -> 76
A14: 二、费用项目（资金流水 / 生产加工 / 其他分录 的「费用项目」下拉就是这一列）
A15: 费用项目 | B15: 默认归集科目 | C15: 本年合计（三家）
A16: 办公费 | B16: 管理费用 | C16: =IF($A16="","",费用统计!$E$7) -> 3200 | F16: 内账口径（这套表的核心约定）：
A17: 差旅费 | B17: 管理费用 | C17: =IF($A17="","",费用统计!$E$8) -> 1800 | F17: 含税核算 | G17: 收入、成本、费用一律按实际成交的含税金额入账，不拆进项销项，也不设进项/销项科目
A18: 业务招待费 | B18: 管理费用 | C18: =IF($A18="","",费用统计!$E$9) -> 0 | F18: 实交税费 | G18: 增值税、附加税、所得税、个税都在实际缴纳那个月，按缴的钱直接进费用
A19: 水电费 | B19: 管理费用 | C19: =IF($A19="","",费用统计!$E$10) -> 8600 | F19: 缴税怎么录 | G19: 【资金流水】选「缴纳税费」→ 对方科目选税金及附加或所得税费用 → 费用项目选税种
A20: 燃料动力费 | B20: 生产成本 | C20: =IF($A20="","",费用统计!$E$11) -> 14000 | F20: 不计提税金 | G20: 不做「计提应交税费」的分录，资产负债表上也就没有应交税费余额（期初有欠税除外）
A21: 房租物业 | B21: 管理费用 | C21: =IF($A21="","",费用统计!$E$12) -> 24000 | F21: 开票税率 | G21: 商品档案上的税率只用来提醒开票时选哪一档，不参与任何计算
A22: 工资薪金 | B22: 应付职工薪酬 | C22: =IF($A22="","",费用统计!$E$13) -> 280000
A23: 社保公积金 | B23: 管理费用 | C23: =IF($A23="","",费用统计!$E$14) -> 12000
A24: 折旧费 | B24: 管理费用 | C24: =IF($A24="","",费用统计!$E$15) -> 196000
A25: 摊销费 | B25: 管理费用 | C25: =IF($A25="","",费用统计!$E$16) -> 30000
A26: 修理维护费 | B26: 管理费用 | C26: =IF($A26="","",费用统计!$E$17) -> 0
A27: 低值易耗品 | B27: 管理费用 | C27: =IF($A27="","",费用统计!$E$18) -> 860
A28: 运输费 | B28: 销售费用 | C28: =IF($A28="","",费用统计!$E$19) -> 0
A29: 广告推广费 | B29: 销售费用 | C29: =IF($A29="","",费用统计!$E$20) -> 26500
A30: 平台服务费 | B30: 销售费用 | C30: =IF($A30="","",费用统计!$E$21) -> 9600
A31: 包装费 | B31: 销售费用 | C31: =IF($A31="","",费用统计!$E$22) -> 0
A32: 检测认证费 | B32: 管理费用 | C32: =IF($A32="","",费用统计!$E$23) -> 0
A33: 咨询服务费 | B33: 管理费用 | C33: =IF($A33="","",费用统计!$E$24) -> 0
A34: 利息支出 | B34: 财务费用 | C34: =IF($A34="","",费用统计!$E$25) -> 6000
A35: 银行手续费 | B35: 财务费用 | C35: =IF($A35="","",费用统计!$E$26) -> 0
A36: 保险费 | B36: 管理费用 | C36: =IF($A36="","",费用统计!$E$27) -> 0
A37: 林地管护费 | B37: 生产成本 | C37: =IF($A37="","",费用统计!$E$28) -> 0
A38: 采伐运输费 | B38: 生产成本 | C38: =IF($A38="","",费用统计!$E$29) -> 25000
A39: 研发材料费 | B39: 研发费用 | C39: =IF($A39="","",费用统计!$E$30) -> 0
A40: 增值税 | B40: 税金及附加 | C40: =IF($A40="","",费用统计!$E$31) -> 0
A41: 城建税及附加 | B41: 税金及附加 | C41: =IF($A41="","",费用统计!$E$32) -> 0
A42: 印花税 | B42: 税金及附加 | C42: =IF($A42="","",费用统计!$E$33) -> 0
A43: 企业所得税 | B43: 所得税费用 | C43: =IF($A43="","",费用统计!$E$34) -> 0
A44: 个人所得税 | B44: 税金及附加 | C44: =IF($A44="","",费用统计!$E$35) -> 0
A45: 其他 | B45: 管理费用 | C45: =IF($A45="","",费用统计!$E$36) -> 0

Sheet 会计科目表
A1: 会计科目表
A2: 报表就是按「报表项目」这一列汇总出来的。加科目照着填一行即可；「余额方向」决定期末余额怎么算，「报表项目」必须用资产负债表/利润表上已有的项目名。
A5: 科目编码 | B5: 科目名称 | C5: 科目类别 | D5: 余额方向 | E5: 所属报表 | F5: 报表项目 | G5: 往来核算 | H5: 本年借方发生 | I5: 本年贷方发生 | J5: 备注
A6: 1001 | B6: 库存现金 | C6: 资产 | D6: 借 | E6: 资产负债表 | F6: 货币资金 | G6: 否 | H6: =IF($B6="","",SUMIFS(记账分录!$I$6:$I$5505,记账分录!$H$6:$H$5505,$B6)) -> 0 | I6: =IF($B6="","",SUMIFS(记账分录!$J$6:$J$5505,记账分录!$H$6:$H$5505,$B6)) -> 2660
A7: 1002 | B7: 银行存款 | C7: 资产 | D7: 借 | E7: 资产负债表 | F7: 货币资金 | G7: 否 | H7: =IF($B7="","",SUMIFS(记账分录!$I$6:$I$5505,记账分录!$H$6:$H$5505,$B7)) -> 1206000 | I7: =IF($B7="","",SUMIFS(记账分录!$J$6:$J$5505,记账分录!$H$6:$H$5505,$B7)) -> 699100
A8: 1012 | B8: 其他货币资金 | C8: 资产 | D8: 借 | E8: 资产负债表 | F8: 货币资金 | G8: 否 | H8: =IF($B8="","",SUMIFS(记账分录!$I$6:$I$5505,记账分录!$H$6:$H$5505,$B8)) -> 0 | I8: =IF($B8="","",SUMIFS(记账分录!$J$6:$J$5505,记账分录!$H$6:$H$5505,$B8)) -> 0
A9: 1122 | B9: 应收账款 | C9: 资产 | D9: 借 | E9: 资产负债表 | F9: 应收账款 | G9: 是 | H9: =IF($B9="","",SUMIFS(记账分录!$I$6:$I$5505,记账分录!$H$6:$H$5505,$B9)) -> 1355750 | I9: =IF($B9="","",SUMIFS(记账分录!$J$6:$J$5505,记账分录!$H$6:$H$5505,$B9)) -> 956000
A10: 1123 | B10: 预付账款 | C10: 资产 | D10: 借 | E10: 资产负债表 | F10: 预付款项 | G10: 是 | H10: =IF($B10="","",SUMIFS(记账分录!$I$6:$I$5505,记账分录!$H$6:$H$5505,$B10)) -> 0 | I10: =IF($B10="","",SUMIFS(记账分录!$J$6:$J$5505,记账分录!$H$6:$H$5505,$B10)) -> 0
A11: 1221 | B11: 其他应收款 | C11: 资产 | D11: 借 | E11: 资产负债表 | F11: 其他应收款 | G11: 是 | H11: =IF($B11="","",SUMIFS(记账分录!$I$6:$I$5505,记账分录!$H$6:$H$5505,$B11)) -> 0 | I11: =IF($B11="","",SUMIFS(记账分录!$J$6:$J$5505,记账分录!$H$6:$H$5505,$B11)) -> 0
A12: 1403 | B12: 原材料 | C12: 资产 | D12: 借 | E12: 资产负债表 | F12: 存货 | G12: 否 | H12: =IF($B12="","",SUMIFS(记账分录!$I$6:$I$5505,记账分录!$H$6:$H$5505,$B12)) -> 401080 | I12: =IF($B12="","",SUMIFS(记账分录!$J$6:$J$5505,记账分录!$H$6:$H$5505,$B12)) -> 340766.29
A13: 1405 | B13: 库存商品 | C13: 资产 | D13: 借 | E13: 资产负债表 | F13: 存货 | G13: 否 | H13: =IF($B13="","",SUMIFS(记账分录!$I$6:$I$5505,记账分录!$H$6:$H$5505,$B13)) -> 751441.01 | I13: =IF($B13="","",SUMIFS(记账分录!$J$6:$J$5505,记账分录!$H$6:$H$5505,$B13)) -> 792027.82
A14: 1411 | B14: 周转材料 | C14: 资产 | D14: 借 | E14: 资产负债表 | F14: 存货 | G14: 否 | H14: =IF($B14="","",SUMIFS(记账分录!$I$6:$I$5505,记账分录!$H$6:$H$5505,$B14)) -> 0 | I14: =IF($B14="","",SUMIFS(记账分录!$J$6:$J$5505,记账分录!$H$6:$H$5505,$B14)) -> 0
A15: 1501 | B15: 生产成本 | C15: 成本 | D15: 借 | E15: 资产负债表 | F15: 存货 | G15: 否 | H15: =IF($B15="","",SUMIFS(记账分录!$I$6:$I$5505,记账分录!$H$6:$H$5505,$B15)) -> 751441.01 | I15: =IF($B15="","",SUMIFS(记账分录!$J$6:$J$5505,记账分录!$H$6:$H$5505,$B15)) -> 751441.01
A16: 1601 | B16: 固定资产 | C16: 资产 | D16: 借 | E16: 资产负债表 | F16: 固定资产原价 | G16: 否 | H16: =IF($B16="","",SUMIFS(记账分录!$I$6:$I$5505,记账分录!$H$6:$H$5505,$B16)) -> 0 | I16: =IF($B16="","",SUMIFS(记账分录!$J$6:$J$5505,记账分录!$H$6:$H$5505,$B16)) -> 0
A17: 1602 | B17: 累计折旧 | C17: 资产 | D17: 贷 | E17: 资产负债表 | F17: 累计折旧 | G17: 否 | H17: =IF($B17="","",SUMIFS(记账分录!$I$6:$I$5505,记账分录!$H$6:$H$5505,$B17)) -> 0 | I17: =IF($B17="","",SUMIFS(记账分录!$J$6:$J$5505,记账分录!$H$6:$H$5505,$B17)) -> 176000
... A46: 6801 | B46: 所得税费用 | C46: 损益-费用 | D46: 借 | E46: 利润表 | F46: 所得税费用 | G46: 否 | H46: =IF($B46="","",SUMIFS(记账分录!$I$6:$I$5505,记账分录!$H$6:$H$5505,$B46)) -> 18000 | I46: =IF($B46="","",SUMIFS(记账分录!$J$6:$J$5505,记账分录!$H$6:$H$5505,$B46)) -> 0
H47: =IF($B47="","",SUMIFS(记账分录!$I$6:$I$5505,记账分录!$H$6:$H$5505,$B47)) | I47: =IF($B47="","",SUMIFS(记账分录!$J$6:$J$5505,记账分录!$H$6:$H$5505,$B47))
H48: =IF($B48="","",SUMIFS(记账分录!$I$6:$I$5505,记账分录!$H$6:$H$5505,$B48)) | I48: =IF($B48="","",SUMIFS(记账分录!$J$6:$J$5505,记账分录!$H$6:$H$5505,$B48))
H49: =IF($B49="","",SUMIFS(记账分录!$I$6:$I$5505,记账分录!$H$6:$H$5505,$B49)) | I49: =IF($B49="","",SUMIFS(记账分录!$J$6:$J$5505,记账分录!$H$6:$H$5505,$B49))
H50: =IF($B50="","",SUMIFS(记账分录!$I$6:$I$5505,记账分录!$H$6:$H$5505,$B50)) | I50: =IF($B50="","",SUMIFS(记账分录!$J$6:$J$5505,记账分录!$H$6:$H$5505,$B50))
H51: =IF($B51="","",SUMIFS(记账分录!$I$6:$I$5505,记账分录!$H$6:$H$5505,$B51)) | I51: =IF($B51="","",SUMIFS(记账分录!$J$6:$J$5505,记账分录!$H$6:$H$5505,$B51))
H52: =IF($B52="","",SUMIFS(记账分录!$I$6:$I$5505,记账分录!$H$6:$H$5505,$B52)) | I52: =IF($B52="","",SUMIFS(记账分录!$J$6:$J$5505,记账分录!$H$6:$H$5505,$B52))
H53: =IF($B53="","",SUMIFS(记账分录!$I$6:$I$5505,记账分录!$H$6:$H$5505,$B53)) | I53: =IF($B53="","",SUMIFS(记账分录!$J$6:$J$5505,记账分录!$H$6:$H$5505,$B53))
H54: =IF($B54="","",SUMIFS(记账分录!$I$6:$I$5505,记账分录!$H$6:$H$5505,$B54)) | I54: =IF($B54="","",SUMIFS(记账分录!$J$6:$J$5505,记账分录!$H$6:$H$5505,$B54))
H55: =IF($B55="","",SUMIFS(记账分录!$I$6:$I$5505,记账分录!$H$6:$H$5505,$B55)) | I55: =IF($B55="","",SUMIFS(记账分录!$J$6:$J$5505,记账分录!$H$6:$H$5505,$B55))
H56: =IF($B56="","",SUMIFS(记账分录!$I$6:$I$5505,记账分录!$H$6:$H$5505,$B56)) | I56: =IF($B56="","",SUMIFS(记账分录!$J$6:$J$5505,记账分录!$H$6:$H$5505,$B56))
H57: =IF($B57="","",SUMIFS(记账分录!$I$6:$I$5505,记账分录!$H$6:$H$5505,$B57)) | I57: =IF($B57="","",SUMIFS(记账分录!$J$6:$J$5505,记账分录!$H$6:$H$5505,$B57))
H58: =IF($B58="","",SUMIFS(记账分录!$I$6:$I$5505,记账分录!$H$6:$H$5505,$B58)) | I58: =IF($B58="","",SUMIFS(记账分录!$J$6:$J$5505,记账分录!$H$6:$H$5505,$B58))
... H85: =IF($B85="","",SUMIFS(记账分录!$I$6:$I$5505,记账分录!$H$6:$H$5505,$B85)) | I85: =IF($B85="","",SUMIFS(记账分录!$J$6:$J$5505,记账分录!$H$6:$H$5505,$B85))

Sheet 记账规则
A1: 记账规则（业务类型 → 借贷分录）
A2: 录入表只填业务，借贷两条腿由这张表决定。科目里的 @ 是占位符：@结算＝按结算方式取（挂账→应收/应付、现金→库存现金、银行→银行存款）；@存货/@收入/@成本＝按商品档案该商品设的科目取；@账户＝资金流水那行选的账户；@对方＝那行填的对方科目。看不惯哪条改哪条，改完全表立刻跟着变。
A4: 一、购销流水（4 条腿：结算 / 收入或存货 / 结转成本借 / 结转成本贷）
A5: 业务类型 | B5: 说明 | C5: 腿1 科目 | D5: 腿1 借贷 | E5: 腿1 取值 | F5: 腿2 科目 | G5: 腿2 借贷 | H5: 腿2 取值 | I5: 腿3 科目 | J5: 腿3 借贷 | K5: 腿3 取值 | L5: 腿4 科目 | M5: 腿4 借贷 | N5: 腿4 取值
A6: 销售出库 | B6: 按含税金额确认收入，同时结转销售成本 | C6: @结算 | D6: 借 | E6: 金额 | F6: @收入 | G6: 贷 | H6: 金额 | I6: @成本 | J6: 借 | K6: 成本金额 | L6: @存货 | M6: 贷 | N6: 成本金额
A7: 采购入库 | B7: 按含税金额直接进存货，不拆进项 | C7: @结算 | D7: 贷 | E7: 金额 | F7: @存货 | G7: 借 | H7: 金额
A8: 销售退回 | B8: 客户退货，收入与成本同时冲回 | C8: @结算 | D8: 贷 | E8: 金额 | F8: @收入 | G8: 借 | H8: 金额 | I8: @成本 | J8: 贷 | K8: 成本金额 | L8: @存货 | M8: 借 | N8: 成本金额
A9: 采购退回 | B9: 退货给供应商，按含税金额冲存货 | C9: @结算 | D9: 借 | E9: 金额 | F9: @存货 | G9: 贷 | H9: 金额
A11: 二、资金流水（2 条腿：账户 / 对方）
A12: 业务类型 | B12: 说明 | C12: 腿1 科目 | D12: 腿1 借贷 | E12: 腿1 取值 | F12: 腿2 科目 | G12: 腿2 借贷 | H12: 腿2 取值
A13: 收客户货款 | B13: 收回应收账款 | C13: @账户 | D13: 借 | E13: 金额 | F13: 应收账款 | G13: 贷 | H13: 金额
A14: 付供应商货款 | B14: 支付应付账款 | C14: @账户 | D14: 贷 | E14: 金额 | F14: 应付账款 | G14: 借 | H14: 金额
A15: 收预收款 | B15: 客户预付货款 | C15: @账户 | D15: 借 | E15: 金额 | F15: 预收账款 | G15: 贷 | H15: 金额
A16: 付预付款 | B16: 预付供应商货款 | C16: @账户 | D16: 贷 | E16: 金额 | F16: 预付账款 | G16: 借 | H16: 金额
A17: 收其他应收款 | B17: 收回借出/代垫款 | C17: @账户 | D17: 借 | E17: 金额 | F17: 其他应收款 | G17: 贷 | H17: 金额
A18: 借出代垫款 | B18: 借出或代垫款项 | C18: @账户 | D18: 贷 | E18: 金额 | F18: 其他应收款 | G18: 借 | H18: 金额
A19: 收往来借入款 | B19: 收到关联方/个人借入 | C19: @账户 | D19: 借 | E19: 金额 | F19: 其他应付款 | G19: 贷 | H19: 金额
A20: 付其他应付款 | B20: 归还关联方/个人借入 | C20: @账户 | D20: 贷 | E20: 金额 | F20: 其他应付款 | G20: 借 | H20: 金额
A21: 费用支出 | B21: 付费用，含税全额进费用科目 | C21: @账户 | D21: 贷 | E21: 金额 | F21: @对方 | G21: 借 | H21: 金额
A22: 缴纳税费 | B22: 实际缴的税当期进费用 | C22: @账户 | D22: 贷 | E22: 金额 | F22: @对方 | G22: 借 | H22: 金额
A23: 现销收款 | B23: 不开票或即收即开的收入（含税） | C23: @账户 | D23: 借 | E23: 金额 | F23: @对方 | G23: 贷 | H23: 金额
... A32: 其他支出 | B32: 营业外支出等 | C32: @账户 | D32: 贷 | E32: 金额 | F32: @对方 | G32: 借 | H32: 金额
A34: 三、生产加工（2 条腿）
A35: 业务类型 | B35: 说明 | C35: 腿1 科目 | D35: 腿1 借贷 | E35: 腿1 取值 | F35: 腿2 科目 | G35: 腿2 借贷 | H35: 腿2 取值
A36: 领用投入 | B36: 领原料进车间，按加权平均成本出库 | C36: 生产成本 | D36: 借 | E36: 记账金额 | F36: @存货 | G36: 贷 | H36: 记账金额
A37: 加工费用 | B37: 人工/能耗/折旧等计入本批成本 | C37: 生产成本 | D37: 借 | E37: 记账金额 | F37: @对方 | G37: 贷 | H37: 记账金额
A38: 产成品入库 | B38: 本批投入合计按权重分摊到产出 | C38: @存货 | D38: 借 | E38: 记账金额 | F38: 生产成本 | G38: 贷 | H38: 记账金额
A40: 四、其他分录 | B40: 没有规则表——直接在【其他分录】里填借方科目、贷方科目和金额，一借一贷。一借多贷就拆成几行写。

Sheet 商品档案
A1: 商品档案
A2: 三家公司的料和成品都登在这里，用「所属公司」分开。存货/收入/成本科目决定这个商品的分录进哪个科目。内账是含税核算，「开票参考税率」只是登记开票时用哪档，不参与任何计算。
A5: 商品编码 | B5: 商品名称 | C5: 规格型号 | D5: 单位 | E5: 所属公司 | F5: 存货类别 | G5: 存货科目 | H5: 收入科目 | I5: 成本科目 | J5: 开票参考税率 | K5: 备注 | L5: 本年结存金额 | M5: 校验
A6: NY01 | B6: 原木 | C6: 杉木/松木 4m | D6: 立方米 | E6: 农业 | F6: 产成品 | G6: 库存商品 | H6: 主营业务收入 | I6: 主营业务成本 | J6: 0 | K6: 自产林木采伐，销售免征增值税 | L6: =IF($A6="","",SUMIFS(进销存台账!$U$6:$U$65,进销存台账!$B$6:$B$65,$A6,进销存台账!$A$6:$A$65,$E6)) -> 41322.22 | M6: =IF($A6="","",IF(COUNTIF($A$6:$A$65,$A6)>1,"编码重复",IF($B6="","缺名称",IF(COUNTIF(会计科目表!$B$6:$B$85,$G6)=0,"存货科目不存在",IF(AND($F6<>"原材料",COUNTIF(会计科目表!$B$6:$B$85,$H6)=0),"收入科目不存在","OK"))))) -> OK
A7: NY02 | B7: 湿艾草 | C7: 鲜艾草 | D7: 公斤 | E7: 农业 | F7: 半成品 | G7: 库存商品 | H7: 主营业务收入 | I7: 主营业务成本 | J7: 0 | K7: 采收后未烘干，用于烘制干艾草 | L7: =IF($A7="","",SUMIFS(进销存台账!$U$6:$U$65,进销存台账!$B$6:$B$65,$A7,进销存台账!$A$6:$A$65,$E7)) -> 0 | M7: =IF($A7="","",IF(COUNTIF($A$6:$A$65,$A7)>1,"编码重复",IF($B7="","缺名称",IF(COUNTIF(会计科目表!$B$6:$B$85,$G7)=0,"存货科目不存在",IF(AND($F7<>"原材料",COUNTIF(会计科目表!$B$6:$B$85,$H7)=0),"收入科目不存在","OK"))))) -> OK
A8: NY03 | B8: 干艾草 | C8: 含水率≤12% | D8: 公斤 | E8: 农业 | F8: 产成品 | G8: 库存商品 | H8: 主营业务收入 | I8: 主营业务成本 | J8: 0 | K8: 自产农产品，销售免征增值税 | L8: =IF($A8="","",SUMIFS(进销存台账!$U$6:$U$65,进销存台账!$B$6:$B$65,$A8,进销存台账!$A$6:$A$65,$E8)) -> 14527.94 | M8: =IF($A8="","",IF(COUNTIF($A$6:$A$65,$A8)>1,"编码重复",IF($B8="","缺名称",IF(COUNTIF(会计科目表!$B$6:$B$85,$G8)=0,"存货科目不存在",IF(AND($F8<>"原材料",COUNTIF(会计科目表!$B$6:$B$85,$H8)=0),"收入科目不存在","OK"))))) -> OK
A9: NY04 | B9: 树苗 | C9: 杉木苗 | D9: 株 | E9: 农业 | F9: 原材料 | G9: 原材料 | J9: 0 | K9: 外购苗木免税 | L9: =IF($A9="","",SUMIFS(进销存台账!$U$6:$U$65,进销存台账!$B$6:$B$65,$A9,进销存台账!$A$6:$A$65,$E9)) -> 0 | M9: =IF($A9="","",IF(COUNTIF($A$6:$A$65,$A9)>1,"编码重复",IF($B9="","缺名称",IF(COUNTIF(会计科目表!$B$6:$B$85,$G9)=0,"存货科目不存在",IF(AND($F9<>"原材料",COUNTIF(会计科目表!$B$6:$B$85,$H9)=0),"收入科目不存在","OK"))))) -> OK
A10: NY05 | B10: 肥料 | C10: 复合肥 | D10: 吨 | E10: 农业 | F10: 原材料 | G10: 原材料 | J10: 0 | K10: 化肥免征增值税 | L10: =IF($A10="","",SUMIFS(进销存台账!$U$6:$U$65,进销存台账!$B$6:$B$65,$A10,进销存台账!$A$6:$A$65,$E10)) -> 11222.22 | M10: =IF($A10="","",IF(COUNTIF($A$6:$A$65,$A10)>1,"编码重复",IF($B10="","缺名称",IF(COUNTIF(会计科目表!$B$6:$B$85,$G10)=0,"存货科目不存在",IF(AND($F10<>"原材料",COUNTIF(会计科目表!$B$6:$B$85,$H10)=0),"收入科目不存在","OK"))))) -> OK
A11: NY06 | B11: 农药 | D11: 公斤 | E11: 农业 | F11: 原材料 | G11: 原材料 | J11: 0 | K11: 农药免征增值税 | L11: =IF($A11="","",SUMIFS(进销存台账!$U$6:$U$65,进销存台账!$B$6:$B$65,$A11,进销存台账!$A$6:$A$65,$E11)) -> 1000 | M11: =IF($A11="","",IF(COUNTIF($A$6:$A$65,$A11)>1,"编码重复",IF($B11="","缺名称",IF(COUNTIF(会计科目表!$B$6:$B$85,$G11)=0,"存货科目不存在",IF(AND($F11<>"原材料",COUNTIF(会计科目表!$B$6:$B$85,$H11)=0),"收入科目不存在","OK"))))) -> OK
A12: MY01 | B12: *木制品*木板 | C12: 1220×2440×18mm | D12: 张 | E12: 木业 | F12: 产成品 | G12: 库存商品 | H12: 主营业务收入 | I12: 主营业务成本 | J12: 0.13 | K12: 开票品名按税盘选 | L12: =IF($A12="","",SUMIFS(进销存台账!$U$6:$U$65,进销存台账!$B$6:$B$65,$A12,进销存台账!$A$6:$A$65,$E12)) -> 39699.9 | M12: =IF($A12="","",IF(COUNTIF($A$6:$A$65,$A12)>1,"编码重复",IF($B12="","缺名称",IF(COUNTIF(会计科目表!$B$6:$B$85,$G12)=0,"存货科目不存在",IF(AND($F12<>"原材料",COUNTIF(会计科目表!$B$6:$B$85,$H12)=0),"收入科目不存在","OK"))))) -> OK
A13: MY02 | B13: *木制品*模板 | C13: 1220×2440×15mm | D13: 张 | E13: 木业 | F13: 产成品 | G13: 库存商品 | H13: 主营业务收入 | I13: 主营业务成本 | J13: 0.13 | L13: =IF($A13="","",SUMIFS(进销存台账!$U$6:$U$65,进销存台账!$B$6:$B$65,$A13,进销存台账!$A$6:$A$65,$E13)) -> 18904.11 | M13: =IF($A13="","",IF(COUNTIF($A$6:$A$65,$A13)>1,"编码重复",IF($B13="","缺名称",IF(COUNTIF(会计科目表!$B$6:$B$85,$G13)=0,"存货科目不存在",IF(AND($F13<>"原材料",COUNTIF(会计科目表!$B$6:$B$85,$H13)=0),"收入科目不存在","OK"))))) -> OK
A14: MY03 | B14: *木制品*方料 | D14: 立方米 | E14: 木业 | F14: 产成品 | G14: 库存商品 | H14: 主营业务收入 | I14: 主营业务成本 | J14: 0.13 | L14: =IF($A14="","",SUMIFS(进销存台账!$U$6:$U$65,进销存台账!$B$6:$B$65,$A14,进销存台账!$A$6:$A$65,$E14)) -> 0 | M14: =IF($A14="","",IF(COUNTIF($A$6:$A$65,$A14)>1,"编码重复",IF($B14="","缺名称",IF(COUNTIF(会计科目表!$B$6:$B$85,$G14)=0,"存货科目不存在",IF(AND($F14<>"原材料",COUNTIF(会计科目表!$B$6:$B$85,$H14)=0),"收入科目不存在","OK"))))) -> OK
A15: MY04 | B15: *木制品*建筑方料 | D15: 立方米 | E15: 木业 | F15: 产成品 | G15: 库存商品 | H15: 主营业务收入 | I15: 主营业务成本 | J15: 0.13 | L15: =IF($A15="","",SUMIFS(进销存台账!$U$6:$U$65,进销存台账!$B$6:$B$65,$A15,进销存台账!$A$6:$A$65,$E15)) -> 0 | M15: =IF($A15="","",IF(COUNTIF($A$6:$A$65,$A15)>1,"编码重复",IF($B15="","缺名称",IF(COUNTIF(会计科目表!$B$6:$B$85,$G15)=0,"存货科目不存在",IF(AND($F15<>"原材料",COUNTIF(会计科目表!$B$6:$B$85,$H15)=0),"收入科目不存在","OK"))))) -> OK
A16: MY05 | B16: *木制品*包装箱板材 | D16: 立方米 | E16: 木业 | F16: 产成品 | G16: 库存商品 | H16: 主营业务收入 | I16: 主营业务成本 | J16: 0.13 | L16: =IF($A16="","",SUMIFS(进销存台账!$U$6:$U$65,进销存台账!$B$6:$B$65,$A16,进销存台账!$A$6:$A$65,$E16)) -> 4476.54 | M16: =IF($A16="","",IF(COUNTIF($A$6:$A$65,$A16)>1,"编码重复",IF($B16="","缺名称",IF(COUNTIF(会计科目表!$B$6:$B$85,$G16)=0,"存货科目不存在",IF(AND($F16<>"原材料",COUNTIF(会计科目表!$B$6:$B$85,$H16)=0),"收入科目不存在","OK"))))) -> OK
A17: MY06 | B17: *林业产品*建筑木方料 | D17: 立方米 | E17: 木业 | F17: 产成品 | G17: 库存商品 | H17: 主营业务收入 | I17: 主营业务成本 | J17: 0.09 | K17: 初级林产品开票按 9% | L17: =IF($A17="","",SUMIFS(进销存台账!$U$6:$U$65,进销存台账!$B$6:$B$65,$A17,进销存台账!$A$6:$A$65,$E17)) -> 4789.04 | M17: =IF($A17="","",IF(COUNTIF($A$6:$A$65,$A17)>1,"编码重复",IF($B17="","缺名称",IF(COUNTIF(会计科目表!$B$6:$B$85,$G17)=0,"存货科目不存在",IF(AND($F17<>"原材料",COUNTIF(会计科目表!$B$6:$B$85,$H17)=0),"收入科目不存在","OK"))))) -> OK
A18: MY07 | B18: 原木 | C18: 外购/内购 4m | D18: 立方米 | E18: 木业 | F18: 原材料 | G18: 原材料 | J18: 0.09 | K18: 向农业基地公司和农户收购 | L18: =IF($A18="","",SUMIFS(进销存台账!$U$6:$U$65,进销存台账!$B$6:$B$65,$A18,进销存台账!$A$6:$A$65,$E18)) -> 126301.36 | M18: =IF($A18="","",IF(COUNTIF($A$6:$A$65,$A18)>1,"编码重复",IF($B18="","缺名称",IF(COUNTIF(会计科目表!$B$6:$B$85,$G18)=0,"存货科目不存在",IF(AND($F18<>"原材料",COUNTIF(会计科目表!$B$6:$B$85,$H18)=0),"收入科目不存在","OK"))))) -> OK
A19: MY08 | B19: 胶水 | C19: 脲醛胶 | D19: 公斤 | E19: 木业 | F19: 原材料 | G19: 原材料 | J19: 0.13 | L19: =IF($A19="","",SUMIFS(进销存台账!$U$6:$U$65,进销存台账!$B$6:$B$65,$A19,进销存台账!$A$6:$A$65,$E19)) -> 17850 | M19: =IF($A19="","",IF(COUNTIF($A$6:$A$65,$A19)>1,"编码重复",IF($B19="","缺名称",IF(COUNTIF(会计科目表!$B$6:$B$85,$G19)=0,"存货科目不存在",IF(AND($F19<>"原材料",COUNTIF(会计科目表!$B$6:$B$85,$H19)=0),"收入科目不存在","OK"))))) -> OK
A20: MY09 | B20: 木屑边角料 | D20: 吨 | E20: 木业 | F20: 产成品 | G20: 库存商品 | H20: 其他业务收入 | I20: 其他业务成本 | J20: 0.13 | K20: 副产品 | L20: =IF($A20="","",SUMIFS(进销存台账!$U$6:$U$65,进销存台账!$B$6:$B$65,$A20,进销存台账!$A$6:$A$65,$E20)) -> 0 | M20: =IF($A20="","",IF(COUNTIF($A$6:$A$65,$A20)>1,"编码重复",IF($B20="","缺名称",IF(COUNTIF(会计科目表!$B$6:$B$85,$G20)=0,"存货科目不存在",IF(AND($F20<>"原材料",COUNTIF(会计科目表!$B$6:$B$85,$H20)=0),"收入科目不存在","OK"))))) -> OK
A21: KJ01 | B21: 艾草精油原液 | C21: 10kg/桶 | D21: 公斤 | E21: 科技 | F21: 半成品 | G21: 库存商品 | H21: 主营业务收入 | I21: 主营业务成本 | J21: 0.13 | K21: 提取后待灌装 | L21: =IF($A21="","",SUMIFS(进销存台账!$U$6:$U$65,进销存台账!$B$6:$B$65,$A21,进销存台账!$A$6:$A$65,$E21)) -> 79941.44 | M21: =IF($A21="","",IF(COUNTIF($A$6:$A$65,$A21)>1,"编码重复",IF($B21="","缺名称",IF(COUNTIF(会计科目表!$B$6:$B$85,$G21)=0,"存货科目不存在",IF(AND($F21<>"原材料",COUNTIF(会计科目表!$B$6:$B$85,$H21)=0),"收入科目不存在","OK"))))) -> OK
A22: KJ02 | B22: 艾草精油10ml | C22: 10ml/瓶 | D22: 瓶 | E22: 科技 | F22: 产成品 | G22: 库存商品 | H22: 主营业务收入 | I22: 主营业务成本 | J22: 0.13 | L22: =IF($A22="","",SUMIFS(进销存台账!$U$6:$U$65,进销存台账!$B$6:$B$65,$A22,进销存台账!$A$6:$A$65,$E22)) -> 13113.51 | M22: =IF($A22="","",IF(COUNTIF($A$6:$A$65,$A22)>1,"编码重复",IF($B22="","缺名称",IF(COUNTIF(会计科目表!$B$6:$B$85,$G22)=0,"存货科目不存在",IF(AND($F22<>"原材料",COUNTIF(会计科目表!$B$6:$B$85,$H22)=0),"收入科目不存在","OK"))))) -> OK
A23: KJ03 | B23: 艾草精油30ml | C23: 30ml/瓶 | D23: 瓶 | E23: 科技 | F23: 产成品 | G23: 库存商品 | H23: 主营业务收入 | I23: 主营业务成本 | J23: 0.13 | L23: =IF($A23="","",SUMIFS(进销存台账!$U$6:$U$65,进销存台账!$B$6:$B$65,$A23,进销存台账!$A$6:$A$65,$E23)) -> 0 | M23: =IF($A23="","",IF(COUNTIF($A$6:$A$65,$A23)>1,"编码重复",IF($B23="","缺名称",IF(COUNTIF(会计科目表!$B$6:$B$85,$G23)=0,"存货科目不存在",IF(AND($F23<>"原材料",COUNTIF(会计科目表!$B$6:$B$85,$H23)=0),"收入科目不存在","OK"))))) -> OK
A24: KJ04 | B24: 艾草纯露 | C24: 100ml/瓶 | D24: 瓶 | E24: 科技 | F24: 产成品 | G24: 库存商品 | H24: 主营业务收入 | I24: 主营业务成本 | J24: 0.13 | K24: 蒸馏水相 | L24: =IF($A24="","",SUMIFS(进销存台账!$U$6:$U$65,进销存台账!$B$6:$B$65,$A24,进销存台账!$A$6:$A$65,$E24)) -> 2475.52 | M24: =IF($A24="","",IF(COUNTIF($A$6:$A$65,$A24)>1,"编码重复",IF($B24="","缺名称",IF(COUNTIF(会计科目表!$B$6:$B$85,$G24)=0,"存货科目不存在",IF(AND($F24<>"原材料",COUNTIF(会计科目表!$B$6:$B$85,$H24)=0),"收入科目不存在","OK"))))) -> OK
A25: KJ05 | B25: 艾草精油皂 | C25: 100g/块 | D25: 块 | E25: 科技 | F25: 产成品 | G25: 库存商品 | H25: 主营业务收入 | I25: 主营业务成本 | J25: 0.13 | L25: =IF($A25="","",SUMIFS(进销存台账!$U$6:$U$65,进销存台账!$B$6:$B$65,$A25,进销存台账!$A$6:$A$65,$E25)) -> 2362.97 | M25: =IF($A25="","",IF(COUNTIF($A$6:$A$65,$A25)>1,"编码重复",IF($B25="","缺名称",IF(COUNTIF(会计科目表!$B$6:$B$85,$G25)=0,"存货科目不存在",IF(AND($F25<>"原材料",COUNTIF(会计科目表!$B$6:$B$85,$H25)=0),"收入科目不存在","OK"))))) -> OK
A26: KJ06 | B26: 艾草精油膏 | C26: 20g/盒 | D26: 盒 | E26: 科技 | F26: 产成品 | G26: 库存商品 | H26: 主营业务收入 | I26: 主营业务成本 | J26: 0.13 | L26: =IF($A26="","",SUMIFS(进销存台账!$U$6:$U$65,进销存台账!$B$6:$B$65,$A26,进销存台账!$A$6:$A$65,$E26)) -> 0 | M26: =IF($A26="","",IF(COUNTIF($A$6:$A$65,$A26)>1,"编码重复",IF($B26="","缺名称",IF(COUNTIF(会计科目表!$B$6:$B$85,$G26)=0,"存货科目不存在",IF(AND($F26<>"原材料",COUNTIF(会计科目表!$B$6:$B$85,$H26)=0),"收入科目不存在","OK"))))) -> OK
A27: KJ07 | B27: 艾草香薰 | D27: 盒 | E27: 科技 | F27: 产成品 | G27: 库存商品 | H27: 主营业务收入 | I27: 主营业务成本 | J27: 0.13 | L27: =IF($A27="","",SUMIFS(进销存台账!$U$6:$U$65,进销存台账!$B$6:$B$65,$A27,进销存台账!$A$6:$A$65,$E27)) -> 0 | M27: =IF($A27="","",IF(COUNTIF($A$6:$A$65,$A27)>1,"编码重复",IF($B27="","缺名称",IF(COUNTIF(会计科目表!$B$6:$B$85,$G27)=0,"存货科目不存在",IF(AND($F27<>"原材料",COUNTIF(会计科目表!$B$6:$B$85,$H27)=0),"收入科目不存在","OK"))))) -> OK
A28: KJ08 | B28: 干艾草 | C28: 含水率≤12% | D28: 公斤 | E28: 科技 | F28: 原材料 | G28: 原材料 | J28: 0.09 | K28: 向农业基地公司收购 | L28: =IF($A28="","",SUMIFS(进销存台账!$U$6:$U$65,进销存台账!$B$6:$B$65,$A28,进销存台账!$A$6:$A$65,$E28)) -> 2690.91 | M28: =IF($A28="","",IF(COUNTIF($A$6:$A$65,$A28)>1,"编码重复",IF($B28="","缺名称",IF(COUNTIF(会计科目表!$B$6:$B$85,$G28)=0,"存货科目不存在",IF(AND($F28<>"原材料",COUNTIF(会计科目表!$B$6:$B$85,$H28)=0),"收入科目不存在","OK"))))) -> OK
A29: KJ09 | B29: 包装瓶 | C29: 10ml 玻璃瓶 | D29: 个 | E29: 科技 | F29: 原材料 | G29: 原材料 | J29: 0.13 | L29: =IF($A29="","",SUMIFS(进销存台账!$U$6:$U$65,进销存台账!$B$6:$B$65,$A29,进销存台账!$A$6:$A$65,$E29)) -> 18742.86 | M29: =IF($A29="","",IF(COUNTIF($A$6:$A$65,$A29)>1,"编码重复",IF($B29="","缺名称",IF(COUNTIF(会计科目表!$B$6:$B$85,$G29)=0,"存货科目不存在",IF(AND($F29<>"原材料",COUNTIF(会计科目表!$B$6:$B$85,$H29)=0),"收入科目不存在","OK"))))) -> OK
A30: KJ10 | B30: 纸盒 | D30: 个 | E30: 科技 | F30: 原材料 | G30: 原材料 | J30: 0.13 | L30: =IF($A30="","",SUMIFS(进销存台账!$U$6:$U$65,进销存台账!$B$6:$B$65,$A30,进销存台账!$A$6:$A$65,$E30)) -> 4696.36 | M30: =IF($A30="","",IF(COUNTIF($A$6:$A$65,$A30)>1,"编码重复",IF($B30="","缺名称",IF(COUNTIF(会计科目表!$B$6:$B$85,$G30)=0,"存货科目不存在",IF(AND($F30<>"原材料",COUNTIF(会计科目表!$B$6:$B$85,$H30)=0),"收入科目不存在","OK"))))) -> OK
L31: =IF($A31="","",SUMIFS(进销存台账!$U$6:$U$65,进销存台账!$B$6:$B$65,$A31,进销存台账!$A$6:$A$65,$E31)) | M31: =IF($A31="","",IF(COUNTIF($A$6:$A$65,$A31)>1,"编码重复",IF($B31="","缺名称",IF(COUNTIF(会计科目表!$B$6:$B$85,$G31)=0,"存货科目不存在",IF(AND($F31<>"原材料",COUNTIF(会计科目表!$B$6:$B$85,$H31)=0),"收入科目不存在","OK")))))
L32: =IF($A32="","",SUMIFS(进销存台账!$U$6:$U$65,进销存台账!$B$6:$B$65,$A32,进销存台账!$A$6:$A$65,$E32)) | M32: =IF($A32="","",IF(COUNTIF($A$6:$A$65,$A32)>1,"编码重复",IF($B32="","缺名称",IF(COUNTIF(会计科目表!$B$6:$B$85,$G32)=0,"存货科目不存在",IF(AND($F32<>"原材料",COUNTIF(会计科目表!$B$6:$B$85,$H32)=0),"收入科目不存在","OK")))))
L33: =IF($A33="","",SUMIFS(进销存台账!$U$6:$U$65,进销存台账!$B$6:$B$65,$A33,进销存台账!$A$6:$A$65,$E33)) | M33: =IF($A33="","",IF(COUNTIF($A$6:$A$65,$A33)>1,"编码重复",IF($B33="","缺名称",IF(COUNTIF(会计科目表!$B$6:$B$85,$G33)=0,"存货科目不存在",IF(AND($F33<>"原材料",COUNTIF(会计科目表!$B$6:$B$85,$H33)=0),"收入科目不存在","OK")))))
L34: =IF($A34="","",SUMIFS(进销存台账!$U$6:$U$65,进销存台账!$B$6:$B$65,$A34,进销存台账!$A$6:$A$65,$E34)) | M34: =IF($A34="","",IF(COUNTIF($A$6:$A$65,$A34)>1,"编码重复",IF($B34="","缺名称",IF(COUNTIF(会计科目表!$B$6:$B$85,$G34)=0,"存货科目不存在",IF(AND($F34<>"原材料",COUNTIF(会计科目表!$B$6:$B$85,$H34)=0),"收入科目不存在","OK")))))
L35: =IF($A35="","",SUMIFS(进销存台账!$U$6:$U$65,进销存台账!$B$6:$B$65,$A35,进销存台账!$A$6:$A$65,$E35)) | M35: =IF($A35="","",IF(COUNTIF($A$6:$A$65,$A35)>1,"编码重复",IF($B35="","缺名称",IF(COUNTIF(会计科目表!$B$6:$B$85,$G35)=0,"存货科目不存在",IF(AND($F35<>"原材料",COUNTIF(会计科目表!$B$6:$B$85,$H35)=0),"收入科目不存在","OK")))))
L36: =IF($A36="","",SUMIFS(进销存台账!$U$6:$U$65,进销存台账!$B$6:$B$65,$A36,进销存台账!$A$6:$A$65,$E36)) | M36: =IF($A36="","",IF(COUNTIF($A$6:$A$65,$A36)>1,"编码重复",IF($B36="","缺名称",IF(COUNTIF(会计科目表!$B$6:$B$85,$G36)=0,"存货科目不存在",IF(AND($F36<>"原材料",COUNTIF(会计科目表!$B$6:$B$85,$H36)=0),"收入科目不存在","OK")))))
L37: =IF($A37="","",SUMIFS(进销存台账!$U$6:$U$65,进销存台账!$B$6:$B$65,$A37,进销存台账!$A$6:$A$65,$E37)) | M37: =IF($A37="","",IF(COUNTIF($A$6:$A$65,$A37)>1,"编码重复",IF($B37="","缺名称",IF(COUNTIF(会计科目表!$B$6:$B$85,$G37)=0,"存货科目不存在",IF(AND($F37<>"原材料",COUNTIF(会计科目表!$B$6:$B$85,$H37)=0),"收入科目不存在","OK")))))
L38: =IF($A38="","",SUMIFS(进销存台账!$U$6:$U$65,进销存台账!$B$6:$B$65,$A38,进销存台账!$A$6:$A$65,$E38)) | M38: =IF($A38="","",IF(COUNTIF($A$6:$A$65,$A38)>1,"编码重复",IF($B38="","缺名称",IF(COUNTIF(会计科目表!$B$6:$B$85,$G38)=0,"存货科目不存在",IF(AND($F38<>"原材料",COUNTIF(会计科目表!$B$6:$B$85,$H38)=0),"收入科目不存在","OK")))))
L39: =IF($A39="","",SUMIFS(进销存台账!$U$6:$U$65,进销存台账!$B$6:$B$65,$A39,进销存台账!$A$6:$A$65,$E39)) | M39: =IF($A39="","",IF(COUNTIF($A$6:$A$65,$A39)>1,"编码重复",IF($B39="","缺名称",IF(COUNTIF(会计科目表!$B$6:$B$85,$G39)=0,"存货科目不存在",IF(AND($F39<>"原材料",COUNTIF(会计科目表!$B$6:$B$85,$H39)=0),"收入科目不存在","OK")))))
L40: =IF($A40="","",SUMIFS(进销存台账!$U$6:$U$65,进销存台账!$B$6:$B$65,$A40,进销存台账!$A$6:$A$65,$E40)) | M40: =IF($A40="","",IF(COUNTIF($A$6:$A$65,$A40)>1,"编码重复",IF($B40="","缺名称",IF(COUNTIF(会计科目表!$B$6:$B$85,$G40)=0,"存货科目不存在",IF(AND($F40<>"原材料",COUNTIF(会计科目表!$B$6:$B$85,$H40)=0),"收入科目不存在","OK")))))
L41: =IF($A41="","",SUMIFS(进销存台账!$U$6:$U$65,进销存台账!$B$6:$B$65,$A41,进销存台账!$A$6:$A$65,$E41)) | M41: =IF($A41="","",IF(COUNTIF($A$6:$A$65,$A41)>1,"编码重复",IF($B41="","缺名称",IF(COUNTIF(会计科目表!$B$6:$B$85,$G41)=0,"存货科目不存在",IF(AND($F41<>"原材料",COUNTIF(会计科目表!$B$6:$B$85,$H41)=0),"收入科目不存在","OK")))))
L42: =IF($A42="","",SUMIFS(进销存台账!$U$6:$U$65,进销存台账!$B$6:$B$65,$A42,进销存台账!$A$6:$A$65,$E42)) | M42: =IF($A42="","",IF(COUNTIF($A$6:$A$65,$A42)>1,"编码重复",IF($B42="","缺名称",IF(COUNTIF(会计科目表!$B$6:$B$85,$G42)=0,"存货科目不存在",IF(AND($F42<>"原材料",COUNTIF(会计科目表!$B$6:$B$85,$H42)=0),"收入科目不存在","OK")))))
... L65: =IF($A65="","",SUMIFS(进销存台账!$U$6:$U$65,进销存台账!$B$6:$B$65,$A65,进销存台账!$A$6:$A$65,$E65)) | M65: =IF($A65="","",IF(COUNTIF($A$6:$A$65,$A65)>1,"编码重复",IF($B65="","缺名称",IF(COUNTIF(会计科目表!$B$6:$B$85,$G65)=0,"存货科目不存在",IF(AND($F65<>"原材料",COUNTIF(会计科目表!$B$6:$B$85,$H65)=0),"收入科目不存在","OK")))))

Sheet 往来单位
A1: 往来单位
A2: 客户、供应商、以及三家公司互相之间。「是否内部」标「是」的，购销流水会自动认成内部交易，合并报表按它抵销。
A5: 单位名称 | B5: 类型 | C5: 说明 | D5: 是否内部 | E5: 本年应收发生 | F5: 本年应付发生 | G5: 期末应收余额 | H5: 期末应付余额 | I5: 校验
A6: 农业基地公司 | B6: 内部关联 | C6: 本账套三家之一 | D6: 是 | E6: =IF($A6="","",SUMIFS(记账分录!$I$6:$I$5505,记账分录!$H$6:$H$5505,"应收账款",记账分录!$K$6:$K$5505,$A6)) -> 0 | F6: =IF($A6="","",SUMIFS(记账分录!$J$6:$J$5505,记账分录!$H$6:$H$5505,"应付账款",记账分录!$K$6:$K$5505,$A6)) -> 245000 | G6: =IF($A6="","",$E6-SUMIFS(记账分录!$J$6:$J$5505,记账分录!$H$6:$H$5505,"应收账款",记账分录!$K$6:$K$5505,$A6)) -> 0 | H6: =IF($A6="","",$F6-SUMIFS(记账分录!$I$6:$I$5505,记账分录!$H$6:$H$5505,"应付账款",记账分录!$K$6:$K$5505,$A6)) -> 55000 | I6: =IF($A6="","",IF(COUNTIF($A$6:$A$85,$A6)>1,"名称重复","OK")) -> OK
A7: 木业公司 | B7: 内部关联 | C7: 本账套三家之一 | D7: 是 | E7: =IF($A7="","",SUMIFS(记账分录!$I$6:$I$5505,记账分录!$H$6:$H$5505,"应收账款",记账分录!$K$6:$K$5505,$A7)) -> 189000 | F7: =IF($A7="","",SUMIFS(记账分录!$J$6:$J$5505,记账分录!$H$6:$H$5505,"应付账款",记账分录!$K$6:$K$5505,$A7)) -> 0 | G7: =IF($A7="","",$E7-SUMIFS(记账分录!$J$6:$J$5505,记账分录!$H$6:$H$5505,"应收账款",记账分录!$K$6:$K$5505,$A7)) -> 39000 | H7: =IF($A7="","",$F7-SUMIFS(记账分录!$I$6:$I$5505,记账分录!$H$6:$H$5505,"应付账款",记账分录!$K$6:$K$5505,$A7)) -> 0 | I7: =IF($A7="","",IF(COUNTIF($A$6:$A$85,$A7)>1,"名称重复","OK")) -> OK
A8: 科技公司 | B8: 内部关联 | C8: 本账套三家之一 | D8: 是 | E8: =IF($A8="","",SUMIFS(记账分录!$I$6:$I$5505,记账分录!$H$6:$H$5505,"应收账款",记账分录!$K$6:$K$5505,$A8)) -> 56000 | F8: =IF($A8="","",SUMIFS(记账分录!$J$6:$J$5505,记账分录!$H$6:$H$5505,"应付账款",记账分录!$K$6:$K$5505,$A8)) -> 0 | G8: =IF($A8="","",$E8-SUMIFS(记账分录!$J$6:$J$5505,记账分录!$H$6:$H$5505,"应收账款",记账分录!$K$6:$K$5505,$A8)) -> 16000 | H8: =IF($A8="","",$F8-SUMIFS(记账分录!$I$6:$I$5505,记账分录!$H$6:$H$5505,"应付账款",记账分录!$K$6:$K$5505,$A8)) -> 0 | I8: =IF($A8="","",IF(COUNTIF($A$6:$A$85,$A8)>1,"名称重复","OK")) -> OK
A9: 鑫隆建材 | B9: 客户 | C9: 木业 · 板材 | D9: 否 | E9: =IF($A9="","",SUMIFS(记账分录!$I$6:$I$5505,记账分录!$H$6:$H$5505,"应收账款",记账分录!$K$6:$K$5505,$A9)) -> 363000 | F9: =IF($A9="","",SUMIFS(记账分录!$J$6:$J$5505,记账分录!$H$6:$H$5505,"应付账款",记账分录!$K$6:$K$5505,$A9)) -> 0 | G9: =IF($A9="","",$E9-SUMIFS(记账分录!$J$6:$J$5505,记账分录!$H$6:$H$5505,"应收账款",记账分录!$K$6:$K$5505,$A9)) -> 63000 | H9: =IF($A9="","",$F9-SUMIFS(记账分录!$I$6:$I$5505,记账分录!$H$6:$H$5505,"应付账款",记账分录!$K$6:$K$5505,$A9)) -> 0 | I9: =IF($A9="","",IF(COUNTIF($A$6:$A$85,$A9)>1,"名称重复","OK")) -> OK
A10: 中建八局项目部 | B10: 客户 | C10: 木业 · 模板 | D10: 否 | E10: =IF($A10="","",SUMIFS(记账分录!$I$6:$I$5505,记账分录!$H$6:$H$5505,"应收账款",记账分录!$K$6:$K$5505,$A10)) -> 105000 | F10: =IF($A10="","",SUMIFS(记账分录!$J$6:$J$5505,记账分录!$H$6:$H$5505,"应付账款",记账分录!$K$6:$K$5505,$A10)) -> 0 | G10: =IF($A10="","",$E10-SUMIFS(记账分录!$J$6:$J$5505,记账分录!$H$6:$H$5505,"应收账款",记账分录!$K$6:$K$5505,$A10)) -> 105000 | H10: =IF($A10="","",$F10-SUMIFS(记账分录!$I$6:$I$5505,记账分录!$H$6:$H$5505,"应付账款",记账分录!$K$6:$K$5505,$A10)) -> 0 | I10: =IF($A10="","",IF(COUNTIF($A$6:$A$85,$A10)>1,"名称重复","OK")) -> OK
A11: 顺达包装 | B11: 客户 | C11: 木业 · 包装箱板材 | D11: 否 | E11: =IF($A11="","",SUMIFS(记账分录!$I$6:$I$5505,记账分录!$H$6:$H$5505,"应收账款",记账分录!$K$6:$K$5505,$A11)) -> 92250 | F11: =IF($A11="","",SUMIFS(记账分录!$J$6:$J$5505,记账分录!$H$6:$H$5505,"应付账款",记账分录!$K$6:$K$5505,$A11)) -> 0 | G11: =IF($A11="","",$E11-SUMIFS(记账分录!$J$6:$J$5505,记账分录!$H$6:$H$5505,"应收账款",记账分录!$K$6:$K$5505,$A11)) -> 22250 | H11: =IF($A11="","",$F11-SUMIFS(记账分录!$I$6:$I$5505,记账分录!$H$6:$H$5505,"应付账款",记账分录!$K$6:$K$5505,$A11)) -> 0 | I11: =IF($A11="","",IF(COUNTIF($A$6:$A$85,$A11)>1,"名称重复","OK")) -> OK
A12: 恒诚建筑 | B12: 客户 | C12: 木业 · 建筑木方料 | D12: 否 | E12: =IF($A12="","",SUMIFS(记账分录!$I$6:$I$5505,记账分录!$H$6:$H$5505,"应收账款",记账分录!$K$6:$K$5505,$A12)) -> 21750 | F12: =IF($A12="","",SUMIFS(记账分录!$J$6:$J$5505,记账分录!$H$6:$H$5505,"应付账款",记账分录!$K$6:$K$5505,$A12)) -> 0 | G12: =IF($A12="","",$E12-SUMIFS(记账分录!$J$6:$J$5505,记账分录!$H$6:$H$5505,"应收账款",记账分录!$K$6:$K$5505,$A12)) -> 21750 | H12: =IF($A12="","",$F12-SUMIFS(记账分录!$I$6:$I$5505,记账分录!$H$6:$H$5505,"应付账款",记账分录!$K$6:$K$5505,$A12)) -> 0 | I12: =IF($A12="","",IF(COUNTIF($A$6:$A$85,$A12)>1,"名称重复","OK")) -> OK
A13: 恒信木材行 | B13: 客户 | C13: 农业 · 原木 | D13: 否 | E13: =IF($A13="","",SUMIFS(记账分录!$I$6:$I$5505,记账分录!$H$6:$H$5505,"应收账款",记账分录!$K$6:$K$5505,$A13)) -> 66000 | F13: =IF($A13="","",SUMIFS(记账分录!$J$6:$J$5505,记账分录!$H$6:$H$5505,"应付账款",记账分录!$K$6:$K$5505,$A13)) -> 0 | G13: =IF($A13="","",$E13-SUMIFS(记账分录!$J$6:$J$5505,记账分录!$H$6:$H$5505,"应收账款",记账分录!$K$6:$K$5505,$A13)) -> 0 | H13: =IF($A13="","",$F13-SUMIFS(记账分录!$I$6:$I$5505,记账分录!$H$6:$H$5505,"应付账款",记账分录!$K$6:$K$5505,$A13)) -> 0 | I13: =IF($A13="","",IF(COUNTIF($A$6:$A$85,$A13)>1,"名称重复","OK")) -> OK
A14: 安康艾制品厂 | B14: 客户 | C14: 农业 · 干艾草 | D14: 否 | E14: =IF($A14="","",SUMIFS(记账分录!$I$6:$I$5505,记账分录!$H$6:$H$5505,"应收账款",记账分录!$K$6:$K$5505,$A14)) -> 18000 | F14: =IF($A14="","",SUMIFS(记账分录!$J$6:$J$5505,记账分录!$H$6:$H$5505,"应付账款",记账分录!$K$6:$K$5505,$A14)) -> 0 | G14: =IF($A14="","",$E14-SUMIFS(记账分录!$J$6:$J$5505,记账分录!$H$6:$H$5505,"应收账款",记账分录!$K$6:$K$5505,$A14)) -> 18000 | H14: =IF($A14="","",$F14-SUMIFS(记账分录!$I$6:$I$5505,记账分录!$H$6:$H$5505,"应付账款",记账分录!$K$6:$K$5505,$A14)) -> 0 | I14: =IF($A14="","",IF(COUNTIF($A$6:$A$85,$A14)>1,"名称重复","OK")) -> OK
A15: 康养电商 | B15: 客户 | C15: 科技 · 精油 | D15: 否 | E15: =IF($A15="","",SUMIFS(记账分录!$I$6:$I$5505,记账分录!$H$6:$H$5505,"应收账款",记账分录!$K$6:$K$5505,$A15)) -> 324750 | F15: =IF($A15="","",SUMIFS(记账分录!$J$6:$J$5505,记账分录!$H$6:$H$5505,"应付账款",记账分录!$K$6:$K$5505,$A15)) -> 0 | G15: =IF($A15="","",$E15-SUMIFS(记账分录!$J$6:$J$5505,记账分录!$H$6:$H$5505,"应收账款",记账分录!$K$6:$K$5505,$A15)) -> 84750 | H15: =IF($A15="","",$F15-SUMIFS(记账分录!$I$6:$I$5505,记账分录!$H$6:$H$5505,"应付账款",记账分录!$K$6:$K$5505,$A15)) -> 0 | I15: =IF($A15="","",IF(COUNTIF($A$6:$A$85,$A15)>1,"名称重复","OK")) -> OK
A16: 美悦日化 | B16: 客户 | C16: 科技 · 纯露 | D16: 否 | E16: =IF($A16="","",SUMIFS(记账分录!$I$6:$I$5505,记账分录!$H$6:$H$5505,"应收账款",记账分录!$K$6:$K$5505,$A16)) -> 120000 | F16: =IF($A16="","",SUMIFS(记账分录!$J$6:$J$5505,记账分录!$H$6:$H$5505,"应付账款",记账分录!$K$6:$K$5505,$A16)) -> 0 | G16: =IF($A16="","",$E16-SUMIFS(记账分录!$J$6:$J$5505,记账分录!$H$6:$H$5505,"应收账款",记账分录!$K$6:$K$5505,$A16)) -> 30000 | H16: =IF($A16="","",$F16-SUMIFS(记账分录!$I$6:$I$5505,记账分录!$H$6:$H$5505,"应付账款",记账分录!$K$6:$K$5505,$A16)) -> 0 | I16: =IF($A16="","",IF(COUNTIF($A$6:$A$85,$A16)>1,"名称重复","OK")) -> OK
A17: 张德富（农户） | B17: 供应商 | C17: 木业 · 向农户收购原木，开农产品收购发票 | D17: 否 | E17: =IF($A17="","",SUMIFS(记账分录!$I$6:$I$5505,记账分录!$H$6:$H$5505,"应收账款",记账分录!$K$6:$K$5505,$A17)) -> 0 | F17: =IF($A17="","",SUMIFS(记账分录!$J$6:$J$5505,记账分录!$H$6:$H$5505,"应付账款",记账分录!$K$6:$K$5505,$A17)) -> 58800 | G17: =IF($A17="","",$E17-SUMIFS(记账分录!$J$6:$J$5505,记账分录!$H$6:$H$5505,"应收账款",记账分录!$K$6:$K$5505,$A17)) -> 0 | H17: =IF($A17="","",$F17-SUMIFS(记账分录!$I$6:$I$5505,记账分录!$H$6:$H$5505,"应付账款",记账分录!$K$6:$K$5505,$A17)) -> 0 | I17: =IF($A17="","",IF(COUNTIF($A$6:$A$85,$A17)>1,"名称重复","OK")) -> OK
... A28: 农商银行 | B28: 其他 | C28: 借款开户行 | D28: 否 | E28: =IF($A28="","",SUMIFS(记账分录!$I$6:$I$5505,记账分录!$H$6:$H$5505,"应收账款",记账分录!$K$6:$K$5505,$A28)) -> 0 | F28: =IF($A28="","",SUMIFS(记账分录!$J$6:$J$5505,记账分录!$H$6:$H$5505,"应付账款",记账分录!$K$6:$K$5505,$A28)) -> 0 | G28: =IF($A28="","",$E28-SUMIFS(记账分录!$J$6:$J$5505,记账分录!$H$6:$H$5505,"应收账款",记账分录!$K$6:$K$5505,$A28)) -> 0 | H28: =IF($A28="","",$F28-SUMIFS(记账分录!$I$6:$I$5505,记账分录!$H$6:$H$5505,"应付账款",记账分录!$K$6:$K$5505,$A28)) -> 0 | I28: =IF($A28="","",IF(COUNTIF($A$6:$A$85,$A28)>1,"名称重复","OK")) -> OK
E29: =IF($A29="","",SUMIFS(记账分录!$I$6:$I$5505,记账分录!$H$6:$H$5505,"应收账款",记账分录!$K$6:$K$5505,$A29)) | F29: =IF($A29="","",SUMIFS(记账分录!$J$6:$J$5505,记账分录!$H$6:$H$5505,"应付账款",记账分录!$K$6:$K$5505,$A29)) | G29: =IF($A29="","",$E29-SUMIFS(记账分录!$J$6:$J$5505,记账分录!$H$6:$H$5505,"应收账款",记账分录!$K$6:$K$5505,$A29)) | H29: =IF($A29="","",$F29-SUMIFS(记账分录!$I$6:$I$5505,记账分录!$H$6:$H$5505,"应付账款",记账分录!$K$6:$K$5505,$A29)) | I29: =IF($A29="","",IF(COUNTIF($A$6:$A$85,$A29)>1,"名称重复","OK"))
E30: =IF($A30="","",SUMIFS(记账分录!$I$6:$I$5505,记账分录!$H$6:$H$5505,"应收账款",记账分录!$K$6:$K$5505,$A30)) | F30: =IF($A30="","",SUMIFS(记账分录!$J$6:$J$5505,记账分录!$H$6:$H$5505,"应付账款",记账分录!$K$6:$K$5505,$A30)) | G30: =IF($A30="","",$E30-SUMIFS(记账分录!$J$6:$J$5505,记账分录!$H$6:$H$5505,"应收账款",记账分录!$K$6:$K$5505,$A30)) | H30: =IF($A30="","",$F30-SUMIFS(记账分录!$I$6:$I$5505,记账分录!$H$6:$H$5505,"应付账款",记账分录!$K$6:$K$5505,$A30)) | I30: =IF($A30="","",IF(COUNTIF($A$6:$A$85,$A30)>1,"名称重复","OK"))
E31: =IF($A31="","",SUMIFS(记账分录!$I$6:$I$5505,记账分录!$H$6:$H$5505,"应收账款",记账分录!$K$6:$K$5505,$A31)) | F31: =IF($A31="","",SUMIFS(记账分录!$J$6:$J$5505,记账分录!$H$6:$H$5505,"应付账款",记账分录!$K$6:$K$5505,$A31)) | G31: =IF($A31="","",$E31-SUMIFS(记账分录!$J$6:$J$5505,记账分录!$H$6:$H$5505,"应收账款",记账分录!$K$6:$K$5505,$A31)) | H31: =IF($A31="","",$F31-SUMIFS(记账分录!$I$6:$I$5505,记账分录!$H$6:$H$5505,"应付账款",记账分录!$K$6:$K$5505,$A31)) | I31: =IF($A31="","",IF(COUNTIF($A$6:$A$85,$A31)>1,"名称重复","OK"))
E32: =IF($A32="","",SUMIFS(记账分录!$I$6:$I$5505,记账分录!$H$6:$H$5505,"应收账款",记账分录!$K$6:$K$5505,$A32)) | F32: =IF($A32="","",SUMIFS(记账分录!$J$6:$J$5505,记账分录!$H$6:$H$5505,"应付账款",记账分录!$K$6:$K$5505,$A32)) | G32: =IF($A32="","",$E32-SUMIFS(记账分录!$J$6:$J$5505,记账分录!$H$6:$H$5505,"应收账款",记账分录!$K$6:$K$5505,$A32)) | H32: =IF($A32="","",$F32-SUMIFS(记账分录!$I$6:$I$5505,记账分录!$H$6:$H$5505,"应付账款",记账分录!$K$6:$K$5505,$A32)) | I32: =IF($A32="","",IF(COUNTIF($A$6:$A$85,$A32)>1,"名称重复","OK"))
E33: =IF($A33="","",SUMIFS(记账分录!$I$6:$I$5505,记账分录!$H$6:$H$5505,"应收账款",记账分录!$K$6:$K$5505,$A33)) | F33: =IF($A33="","",SUMIFS(记账分录!$J$6:$J$5505,记账分录!$H$6:$H$5505,"应付账款",记账分录!$K$6:$K$5505,$A33)) | G33: =IF($A33="","",$E33-SUMIFS(记账分录!$J$6:$J$5505,记账分录!$H$6:$H$5505,"应收账款",记账分录!$K$6:$K$5505,$A33)) | H33: =IF($A33="","",$F33-SUMIFS(记账分录!$I$6:$I$5505,记账分录!$H$6:$H$5505,"应付账款",记账分录!$K$6:$K$5505,$A33)) | I33: =IF($A33="","",IF(COUNTIF($A$6:$A$85,$A33)>1,"名称重复","OK"))
E34: =IF($A34="","",SUMIFS(记账分录!$I$6:$I$5505,记账分录!$H$6:$H$5505,"应收账款",记账分录!$K$6:$K$5505,$A34)) | F34: =IF($A34="","",SUMIFS(记账分录!$J$6:$J$5505,记账分录!$H$6:$H$5505,"应付账款",记账分录!$K$6:$K$5505,$A34)) | G34: =IF($A34="","",$E34-SUMIFS(记账分录!$J$6:$J$5505,记账分录!$H$6:$H$5505,"应收账款",记账分录!$K$6:$K$5505,$A34)) | H34: =IF($A34="","",$F34-SUMIFS(记账分录!$I$6:$I$5505,记账分录!$H$6:$H$5505,"应付账款",记账分录!$K$6:$K$5505,$A34)) | I34: =IF($A34="","",IF(COUNTIF($A$6:$A$85,$A34)>1,"名称重复","OK"))
E35: =IF($A35="","",SUMIFS(记账分录!$I$6:$I$5505,记账分录!$H$6:$H$5505,"应收账款",记账分录!$K$6:$K$5505,$A35)) | F35: =IF($A35="","",SUMIFS(记账分录!$J$6:$J$5505,记账分录!$H$6:$H$5505,"应付账款",记账分录!$K$6:$K$5505,$A35)) | G35: =IF($A35="","",$E35-SUMIFS(记账分录!$J$6:$J$5505,记账分录!$H$6:$H$5505,"应收账款",记账分录!$K$6:$K$5505,$A35)) | H35: =IF($A35="","",$F35-SUMIFS(记账分录!$I$6:$I$5505,记账分录!$H$6:$H$5505,"应付账款",记账分录!$K$6:$K$5505,$A35)) | I35: =IF($A35="","",IF(COUNTIF($A$6:$A$85,$A35)>1,"名称重复","OK"))
E36: =IF($A36="","",SUMIFS(记账分录!$I$6:$I$5505,记账分录!$H$6:$H$5505,"应收账款",记账分录!$K$6:$K$5505,$A36)) | F36: =IF($A36="","",SUMIFS(记账分录!$J$6:$J$5505,记账分录!$H$6:$H$5505,"应付账款",记账分录!$K$6:$K$5505,$A36)) | G36: =IF($A36="","",$E36-SUMIFS(记账分录!$J$6:$J$5505,记账分录!$H$6:$H$5505,"应收账款",记账分录!$K$6:$K$5505,$A36)) | H36: =IF($A36="","",$F36-SUMIFS(记账分录!$I$6:$I$5505,记账分录!$H$6:$H$5505,"应付账款",记账分录!$K$6:$K$5505,$A36)) | I36: =IF($A36="","",IF(COUNTIF($A$6:$A$85,$A36)>1,"名称重复","OK"))
E37: =IF($A37="","",SUMIFS(记账分录!$I$6:$I$5505,记账分录!$H$6:$H$5505,"应收账款",记账分录!$K$6:$K$5505,$A37)) | F37: =IF($A37="","",SUMIFS(记账分录!$J$6:$J$5505,记账分录!$H$6:$H$5505,"应付账款",记账分录!$K$6:$K$5505,$A37)) | G37: =IF($A37="","",$E37-SUMIFS(记账分录!$J$6:$J$5505,记账分录!$H$6:$H$5505,"应收账款",记账分录!$K$6:$K$5505,$A37)) | H37: =IF($A37="","",$F37-SUMIFS(记账分录!$I$6:$I$5505,记账分录!$H$6:$H$5505,"应付账款",记账分录!$K$6:$K$5505,$A37)) | I37: =IF($A37="","",IF(COUNTIF($A$6:$A$85,$A37)>1,"名称重复","OK"))
E38: =IF($A38="","",SUMIFS(记账分录!$I$6:$I$5505,记账分录!$H$6:$H$5505,"应收账款",记账分录!$K$6:$K$5505,$A38)) | F38: =IF($A38="","",SUMIFS(记账分录!$J$6:$J$5505,记账分录!$H$6:$H$5505,"应付账款",记账分录!$K$6:$K$5505,$A38)) | G38: =IF($A38="","",$E38-SUMIFS(记账分录!$J$6:$J$5505,记账分录!$H$6:$H$5505,"应收账款",记账分录!$K$6:$K$5505,$A38)) | H38: =IF($A38="","",$F38-SUMIFS(记账分录!$I$6:$I$5505,记账分录!$H$6:$H$5505,"应付账款",记账分录!$K$6:$K$5505,$A38)) | I38: =IF($A38="","",IF(COUNTIF($A$6:$A$85,$A38)>1,"名称重复","OK"))
E39: =IF($A39="","",SUMIFS(记账分录!$I$6:$I$5505,记账分录!$H$6:$H$5505,"应收账款",记账分录!$K$6:$K$5505,$A39)) | F39: =IF($A39="","",SUMIFS(记账分录!$J$6:$J$5505,记账分录!$H$6:$H$5505,"应付账款",记账分录!$K$6:$K$5505,$A39)) | G39: =IF($A39="","",$E39-SUMIFS(记账分录!$J$6:$J$5505,记账分录!$H$6:$H$5505,"应收账款",记账分录!$K$6:$K$5505,$A39)) | H39: =IF($A39="","",$F39-SUMIFS(记账分录!$I$6:$I$5505,记账分录!$H$6:$H$5505,"应付账款",记账分录!$K$6:$K$5505,$A39)) | I39: =IF($A39="","",IF(COUNTIF($A$6:$A$85,$A39)>1,"名称重复","OK"))
E40: =IF($A40="","",SUMIFS(记账分录!$I$6:$I$5505,记账分录!$H$6:$H$5505,"应收账款",记账分录!$K$6:$K$5505,$A40)) | F40: =IF($A40="","",SUMIFS(记账分录!$J$6:$J$5505,记账分录!$H$6:$H$5505,"应付账款",记账分录!$K$6:$K$5505,$A40)) | G40: =IF($A40="","",$E40-SUMIFS(记账分录!$J$6:$J$5505,记账分录!$H$6:$H$5505,"应收账款",记账分录!$K$6:$K$5505,$A40)) | H40: =IF($A40="","",$F40-SUMIFS(记账分录!$I$6:$I$5505,记账分录!$H$6:$H$5505,"应付账款",记账分录!$K$6:$K$5505,$A40)) | I40: =IF($A40="","",IF(COUNTIF($A$6:$A$85,$A40)>1,"名称重复","OK"))
... E85: =IF($A85="","",SUMIFS(记账分录!$I$6:$I$5505,记账分录!$H$6:$H$5505,"应收账款",记账分录!$K$6:$K$5505,$A85)) | F85: =IF($A85="","",SUMIFS(记账分录!$J$6:$J$5505,记账分录!$H$6:$H$5505,"应付账款",记账分录!$K$6:$K$5505,$A85)) | G85: =IF($A85="","",$E85-SUMIFS(记账分录!$J$6:$J$5505,记账分录!$H$6:$H$5505,"应收账款",记账分录!$K$6:$K$5505,$A85)) | H85: =IF($A85="","",$F85-SUMIFS(记账分录!$I$6:$I$5505,记账分录!$H$6:$H$5505,"应付账款",记账分录!$K$6:$K$5505,$A85)) | I85: =IF($A85="","",IF(COUNTIF($A$6:$A$85,$A85)>1,"名称重复","OK"))

Sheet 资金账户
A1: 资金账户
A2: 几家公司共用几个账号，就按实际开的户登在这里。「对应科目」决定这个账户在账上走库存现金还是银行存款；共用账户照样在【资金流水】里按公司分别记账，账户余额是账户的，科目余额是各公司自己的，两边在下面对账。
A5: 账户编码 | B5: 账户名称 | C5: 开户行 / 说明 | D5: 账号 | E5: 账户类型 | F5: 对应科目 | G5: 使用公司 | H5: 期初余额 | I5: 本期收入 | J5: 本期支出 | K5: 期末余额 | L5: 校验
A6: X01 | B6: 现金-总部 | C6: 出纳保管的备用金，三家共用一个钱箱 | D6: — | E6: 现金 | F6: 库存现金 | G6: 三家共用 | H6: 10000 | I6: =IF($B6="","",SUMIFS(资金流水!$I$6:$I$605,资金流水!$D$6:$D$605,$B6)) -> 0 | J6: =IF($B6="","",SUMIFS(资金流水!$J$6:$J$605,资金流水!$D$6:$D$605,$B6)) -> 2660 | K6: =IF($B6="","",ROUND(N($H6)+$I6-$J6,2)) -> 7340 | L6: =IF($B6="","",IF(COUNTIF($B$6:$B$25,$B6)>1,"账户名称重复",IF(ISNA(MATCH($F6,会计科目表!$B$6:$B$85,0)),"对应科目不存在",IF($K6<0,"✗ 期末余额为负","OK")))) -> OK
A7: Y01 | B7: 农商银行-基本户 | C7: 农业基地公司基本户 | D7: 62×××××××××1001 | E7: 银行 | F7: 银行存款 | G7: 农业 | H7: 180000 | I7: =IF($B7="","",SUMIFS(资金流水!$I$6:$I$605,资金流水!$D$6:$D$605,$B7)) -> 256000 | J7: =IF($B7="","",SUMIFS(资金流水!$J$6:$J$605,资金流水!$D$6:$D$605,$B7)) -> 120000 | K7: =IF($B7="","",ROUND(N($H7)+$I7-$J7,2)) -> 316000 | L7: =IF($B7="","",IF(COUNTIF($B$6:$B$25,$B7)>1,"账户名称重复",IF(ISNA(MATCH($F7,会计科目表!$B$6:$B$85,0)),"对应科目不存在",IF($K7<0,"✗ 期末余额为负","OK")))) -> OK
A8: Y02 | B8: 工商银行-基本户 | C8: 木业公司基本户 | D8: 62×××××××××2002 | E8: 银行 | F8: 银行存款 | G8: 木业 | H8: 260000 | I8: =IF($B8="","",SUMIFS(资金流水!$I$6:$I$605,资金流水!$D$6:$D$605,$B8)) -> 220000 | J8: =IF($B8="","",SUMIFS(资金流水!$J$6:$J$605,资金流水!$D$6:$D$605,$B8)) -> 311760 | K8: =IF($B8="","",ROUND(N($H8)+$I8-$J8,2)) -> 168240 | L8: =IF($B8="","",IF(COUNTIF($B$6:$B$25,$B8)>1,"账户名称重复",IF(ISNA(MATCH($F8,会计科目表!$B$6:$B$85,0)),"对应科目不存在",IF($K8<0,"✗ 期末余额为负","OK")))) -> OK
A9: Y03 | B9: 建设银行-基本户 | C9: 科技公司基本户 | D9: 62×××××××××3003 | E9: 银行 | F9: 银行存款 | G9: 科技 | H9: 320000 | I9: =IF($B9="","",SUMIFS(资金流水!$I$6:$I$605,资金流水!$D$6:$D$605,$B9)) -> 190000 | J9: =IF($B9="","",SUMIFS(资金流水!$J$6:$J$605,资金流水!$D$6:$D$605,$B9)) -> 162340 | K9: =IF($B9="","",ROUND(N($H9)+$I9-$J9,2)) -> 347660 | L9: =IF($B9="","",IF(COUNTIF($B$6:$B$25,$B9)>1,"账户名称重复",IF(ISNA(MATCH($F9,会计科目表!$B$6:$B$85,0)),"对应科目不存在",IF($K9<0,"✗ 期末余额为负","OK")))) -> OK
A10: Y04 | B10: 农商银行-共用户 | C10: 木业、科技共用的收款户，按公司分别记账 | D10: 62×××××××××4004 | E10: 银行 | F10: 银行存款 | G10: 木业 / 科技 | H10: 0 | I10: =IF($B10="","",SUMIFS(资金流水!$I$6:$I$605,资金流水!$D$6:$D$605,$B10)) -> 540000 | J10: =IF($B10="","",SUMIFS(资金流水!$J$6:$J$605,资金流水!$D$6:$D$605,$B10)) -> 105000 | K10: =IF($B10="","",ROUND(N($H10)+$I10-$J10,2)) -> 435000 | L10: =IF($B10="","",IF(COUNTIF($B$6:$B$25,$B10)>1,"账户名称重复",IF(ISNA(MATCH($F10,会计科目表!$B$6:$B$85,0)),"对应科目不存在",IF($K10<0,"✗ 期末余额为负","OK")))) -> OK
I11: =IF($B11="","",SUMIFS(资金流水!$I$6:$I$605,资金流水!$D$6:$D$605,$B11)) | J11: =IF($B11="","",SUMIFS(资金流水!$J$6:$J$605,资金流水!$D$6:$D$605,$B11)) | K11: =IF($B11="","",ROUND(N($H11)+$I11-$J11,2)) | L11: =IF($B11="","",IF(COUNTIF($B$6:$B$25,$B11)>1,"账户名称重复",IF(ISNA(MATCH($F11,会计科目表!$B$6:$B$85,0)),"对应科目不存在",IF($K11<0,"✗ 期末余额为负","OK"))))
I12: =IF($B12="","",SUMIFS(资金流水!$I$6:$I$605,资金流水!$D$6:$D$605,$B12)) | J12: =IF($B12="","",SUMIFS(资金流水!$J$6:$J$605,资金流水!$D$6:$D$605,$B12)) | K12: =IF($B12="","",ROUND(N($H12)+$I12-$J12,2)) | L12: =IF($B12="","",IF(COUNTIF($B$6:$B$25,$B12)>1,"账户名称重复",IF(ISNA(MATCH($F12,会计科目表!$B$6:$B$85,0)),"对应科目不存在",IF($K12<0,"✗ 期末余额为负","OK"))))
I13: =IF($B13="","",SUMIFS(资金流水!$I$6:$I$605,资金流水!$D$6:$D$605,$B13)) | J13: =IF($B13="","",SUMIFS(资金流水!$J$6:$J$605,资金流水!$D$6:$D$605,$B13)) | K13: =IF($B13="","",ROUND(N($H13)+$I13-$J13,2)) | L13: =IF($B13="","",IF(COUNTIF($B$6:$B$25,$B13)>1,"账户名称重复",IF(ISNA(MATCH($F13,会计科目表!$B$6:$B$85,0)),"对应科目不存在",IF($K13<0,"✗ 期末余额为负","OK"))))
I14: =IF($B14="","",SUMIFS(资金流水!$I$6:$I$605,资金流水!$D$6:$D$605,$B14)) | J14: =IF($B14="","",SUMIFS(资金流水!$J$6:$J$605,资金流水!$D$6:$D$605,$B14)) | K14: =IF($B14="","",ROUND(N($H14)+$I14-$J14,2)) | L14: =IF($B14="","",IF(COUNTIF($B$6:$B$25,$B14)>1,"账户名称重复",IF(ISNA(MATCH($F14,会计科目表!$B$6:$B$85,0)),"对应科目不存在",IF($K14<0,"✗ 期末余额为负","OK"))))
I15: =IF($B15="","",SUMIFS(资金流水!$I$6:$I$605,资金流水!$D$6:$D$605,$B15)) | J15: =IF($B15="","",SUMIFS(资金流水!$J$6:$J$605,资金流水!$D$6:$D$605,$B15)) | K15: =IF($B15="","",ROUND(N($H15)+$I15-$J15,2)) | L15: =IF($B15="","",IF(COUNTIF($B$6:$B$25,$B15)>1,"账户名称重复",IF(ISNA(MATCH($F15,会计科目表!$B$6:$B$85,0)),"对应科目不存在",IF($K15<0,"✗ 期末余额为负","OK"))))
I16: =IF($B16="","",SUMIFS(资金流水!$I$6:$I$605,资金流水!$D$6:$D$605,$B16)) | J16: =IF($B16="","",SUMIFS(资金流水!$J$6:$J$605,资金流水!$D$6:$D$605,$B16)) | K16: =IF($B16="","",ROUND(N($H16)+$I16-$J16,2)) | L16: =IF($B16="","",IF(COUNTIF($B$6:$B$25,$B16)>1,"账户名称重复",IF(ISNA(MATCH($F16,会计科目表!$B$6:$B$85,0)),"对应科目不存在",IF($K16<0,"✗ 期末余额为负","OK"))))
I17: =IF($B17="","",SUMIFS(资金流水!$I$6:$I$605,资金流水!$D$6:$D$605,$B17)) | J17: =IF($B17="","",SUMIFS(资金流水!$J$6:$J$605,资金流水!$D$6:$D$605,$B17)) | K17: =IF($B17="","",ROUND(N($H17)+$I17-$J17,2)) | L17: =IF($B17="","",IF(COUNTIF($B$6:$B$25,$B17)>1,"账户名称重复",IF(ISNA(MATCH($F17,会计科目表!$B$6:$B$85,0)),"对应科目不存在",IF($K17<0,"✗ 期末余额为负","OK"))))
I18: =IF($B18="","",SUMIFS(资金流水!$I$6:$I$605,资金流水!$D$6:$D$605,$B18)) | J18: =IF($B18="","",SUMIFS(资金流水!$J$6:$J$605,资金流水!$D$6:$D$605,$B18)) | K18: =IF($B18="","",ROUND(N($H18)+$I18-$J18,2)) | L18: =IF($B18="","",IF(COUNTIF($B$6:$B$25,$B18)>1,"账户名称重复",IF(ISNA(MATCH($F18,会计科目表!$B$6:$B$85,0)),"对应科目不存在",IF($K18<0,"✗ 期末余额为负","OK"))))
I19: =IF($B19="","",SUMIFS(资金流水!$I$6:$I$605,资金流水!$D$6:$D$605,$B19)) | J19: =IF($B19="","",SUMIFS(资金流水!$J$6:$J$605,资金流水!$D$6:$D$605,$B19)) | K19: =IF($B19="","",ROUND(N($H19)+$I19-$J19,2)) | L19: =IF($B19="","",IF(COUNTIF($B$6:$B$25,$B19)>1,"账户名称重复",IF(ISNA(MATCH($F19,会计科目表!$B$6:$B$85,0)),"对应科目不存在",IF($K19<0,"✗ 期末余额为负","OK"))))
I20: =IF($B20="","",SUMIFS(资金流水!$I$6:$I$605,资金流水!$D$6:$D$605,$B20)) | J20: =IF($B20="","",SUMIFS(资金流水!$J$6:$J$605,资金流水!$D$6:$D$605,$B20)) | K20: =IF($B20="","",ROUND(N($H20)+$I20-$J20,2)) | L20: =IF($B20="","",IF(COUNTIF($B$6:$B$25,$B20)>1,"账户名称重复",IF(ISNA(MATCH($F20,会计科目表!$B$6:$B$85,0)),"对应科目不存在",IF($K20<0,"✗ 期末余额为负","OK"))))
I21: =IF($B21="","",SUMIFS(资金流水!$I$6:$I$605,资金流水!$D$6:$D$605,$B21)) | J21: =IF($B21="","",SUMIFS(资金流水!$J$6:$J$605,资金流水!$D$6:$D$605,$B21)) | K21: =IF($B21="","",ROUND(N($H21)+$I21-$J21,2)) | L21: =IF($B21="","",IF(COUNTIF($B$6:$B$25,$B21)>1,"账户名称重复",IF(ISNA(MATCH($F21,会计科目表!$B$6:$B$85,0)),"对应科目不存在",IF($K21<0,"✗ 期末余额为负","OK"))))
I22: =IF($B22="","",SUMIFS(资金流水!$I$6:$I$605,资金流水!$D$6:$D$605,$B22)) | J22: =IF($B22="","",SUMIFS(资金流水!$J$6:$J$605,资金流水!$D$6:$D$605,$B22)) | K22: =IF($B22="","",ROUND(N($H22)+$I22-$J22,2)) | L22: =IF($B22="","",IF(COUNTIF($B$6:$B$25,$B22)>1,"账户名称重复",IF(ISNA(MATCH($F22,会计科目表!$B$6:$B$85,0)),"对应科目不存在",IF($K22<0,"✗ 期末余额为负","OK"))))
... I25: =IF($B25="","",SUMIFS(资金流水!$I$6:$I$605,资金流水!$D$6:$D$605,$B25)) | J25: =IF($B25="","",SUMIFS(资金流水!$J$6:$J$605,资金流水!$D$6:$D$605,$B25)) | K25: =IF($B25="","",ROUND(N($H25)+$I25-$J25,2)) | L25: =IF($B25="","",IF(COUNTIF($B$6:$B$25,$B25)>1,"账户名称重复",IF(ISNA(MATCH($F25,会计科目表!$B$6:$B$85,0)),"对应科目不存在",IF($K25<0,"✗ 期末余额为负","OK"))))
A27: 合 计 | B27: 全部账户 | H27: =SUM(H$6:H$25) -> 770000 | I27: =SUM(I$6:I$25) -> 1206000 | J27: =SUM(J$6:J$25) -> 701760 | K27: =SUM(K$6:K$25) -> 1274240
A29: 账实对账 | B29: 全部账户余额合计，应当等于三家公司「库存现金＋银行存款」的科目余额合计。共用账户会让某一家的账面银行存款对不上单个账号，但三家加总一定对得上。
A30: 账户余额合计 | B30: =$K$27 -> 1274240 | D30: 三家科目余额合计 | E30: =SUMIFS(科目余额表!$L$7:$L$246,科目余额表!$A$7:$A$246,参数设置!$A$10,科目余额表!$C$7:$C$246,"库存现金")+SUMIFS(科目余额表!$L$7:$L$246,科目余额表!$A$7:$A$246,参数设置!$A$10,科目余额表!$C$7:$C$246,"银行存款")+SUMIFS(科目余额表!$L$7:$L$246,科目余额表!$A$7:$A$246,参数设置!$A$11,科目余额表!$C$7:$C$246,"库存现金")+SUMIFS(科目余额表!$L$7:$L$246,科目余额表!$A$7:$A$246,参数设置!$A$11,科目余额表!$C$7:$C$246,"银行存款")+SUMIFS(科目余额表!$L$7:$L$246,科目余额表!$A$7:$A$246,参数设置!$A$12,科目余额表!$C$7:$C$246,"库存现金")+SUMIFS(科目余额表!$L$7:$L$246,科目余额表!$A$7:$A$246,参数设置!$A$12,科目余额表!$C$7:$C$246,"银行存款") -> 1274240 | G30: =IF(ROUND($B$30-$E$30,2)=0,"√ 账实一致","✗ 差 "&TEXT($B$30-$E$30,"#,##0.00")&" （多半是购销或其他分录直接动了现金/银行，没走资金流水）") -> √ 账实一致

Sheet 期初余额
A1: 期初余额（2026-01-01）
A2: 左边填各公司的科目年初余额（借贷各一列），右边填存货的年初数量和金额。两边要对得上：右边某公司「库存商品」的金额合计，必须等于左边该公司库存商品的借方余额，下面有校验。
A5: 公司 | B5: 科目名称 | C5: 借方余额 | D5: 贷方余额 | E5: 备注 | F5: 校验 | H5: 公司 | I5: 商品编码 | J5: 商品名称 | K5: 期初数量 | L5: 期初金额 | M5: 期初单价 | N5: 校验 | P5: 公司 | Q5: 往来单位 | R5: 年初应收 | S5: 年初应付 | T5: 校验
A6: 农业 | B6: 库存现金 | C6: 5000 | F6: =IF(AND($A6="",$B6=""),"",IF(SUMPRODUCT(($B$6:$B$185=$B6)*($A$6:$A$185=$A6))>1,"同公司同科目重复",IF(ISNA(MATCH($B6,会计科目表!$B$6:$B$85,0)),"科目不存在",IF(AND(N($C6)<>0,N($D6)<>0),"借贷不能同时有数","OK")))) -> OK | H6: 农业 | I6: NY01 | J6: =IF($I6="","",IFERROR(INDEX(商品档案!$B$6:$B$65,MATCH($I6,商品档案!$A$6:$A$65,0)),"")) -> 原木 | K6: 120 | L6: 60000 | M6: =IF(N($K6)=0,"",ROUND(N($L6)/N($K6),4)) -> 500 | N6: =IF($I6="","",IF(ISNA(MATCH($I6,商品档案!$A$6:$A$65,0)),"商品不存在",IF(IFERROR(INDEX(商品档案!$E$6:$E$65,MATCH($I6,商品档案!$A$6:$A$65,0)),"")<>$H6,"商品不属于该公司","OK"))) -> OK | P6: 农业 | Q6: 县农资公司 | S6: 35000 | T6: =IF($Q6="","",IF(ISNA(MATCH($Q6,往来单位!$A$6:$A$85,0)),"单位未建档","OK")) -> OK
A7: 农业 | B7: 银行存款 | C7: 180000 | F7: =IF(AND($A7="",$B7=""),"",IF(SUMPRODUCT(($B$6:$B$185=$B7)*($A$6:$A$185=$A7))>1,"同公司同科目重复",IF(ISNA(MATCH($B7,会计科目表!$B$6:$B$85,0)),"科目不存在",IF(AND(N($C7)<>0,N($D7)<>0),"借贷不能同时有数","OK")))) -> OK | H7: 农业 | I7: NY03 | J7: =IF($I7="","",IFERROR(INDEX(商品档案!$B$6:$B$65,MATCH($I7,商品档案!$A$6:$A$65,0)),"")) -> 干艾草 | K7: 2000 | L7: 18000 | M7: =IF(N($K7)=0,"",ROUND(N($L7)/N($K7),4)) -> 9 | N7: =IF($I7="","",IF(ISNA(MATCH($I7,商品档案!$A$6:$A$65,0)),"商品不存在",IF(IFERROR(INDEX(商品档案!$E$6:$E$65,MATCH($I7,商品档案!$A$6:$A$65,0)),"")<>$H7,"商品不属于该公司","OK"))) -> OK | P7: 木业 | Q7: 鑫隆建材 | R7: 156000 | T7: =IF($Q7="","",IF(ISNA(MATCH($Q7,往来单位!$A$6:$A$85,0)),"单位未建档","OK")) -> OK
A8: 农业 | B8: 原材料 | C8: 12000 | F8: =IF(AND($A8="",$B8=""),"",IF(SUMPRODUCT(($B$6:$B$185=$B8)*($A$6:$A$185=$A8))>1,"同公司同科目重复",IF(ISNA(MATCH($B8,会计科目表!$B$6:$B$85,0)),"科目不存在",IF(AND(N($C8)<>0,N($D8)<>0),"借贷不能同时有数","OK")))) -> OK | H8: 农业 | I8: NY05 | J8: =IF($I8="","",IFERROR(INDEX(商品档案!$B$6:$B$65,MATCH($I8,商品档案!$A$6:$A$65,0)),"")) -> 肥料 | K8: 10 | L8: 11000 | M8: =IF(N($K8)=0,"",ROUND(N($L8)/N($K8),4)) -> 1100 | N8: =IF($I8="","",IF(ISNA(MATCH($I8,商品档案!$A$6:$A$65,0)),"商品不存在",IF(IFERROR(INDEX(商品档案!$E$6:$E$65,MATCH($I8,商品档案!$A$6:$A$65,0)),"")<>$H8,"商品不属于该公司","OK"))) -> OK | P8: 木业 | Q8: 华鑫化工 | S8: 88000 | T8: =IF($Q8="","",IF(ISNA(MATCH($Q8,往来单位!$A$6:$A$85,0)),"单位未建档","OK")) -> OK
A9: 农业 | B9: 库存商品 | C9: 78000 | F9: =IF(AND($A9="",$B9=""),"",IF(SUMPRODUCT(($B$6:$B$185=$B9)*($A$6:$A$185=$A9))>1,"同公司同科目重复",IF(ISNA(MATCH($B9,会计科目表!$B$6:$B$85,0)),"科目不存在",IF(AND(N($C9)<>0,N($D9)<>0),"借贷不能同时有数","OK")))) -> OK | H9: 农业 | I9: NY06 | J9: =IF($I9="","",IFERROR(INDEX(商品档案!$B$6:$B$65,MATCH($I9,商品档案!$A$6:$A$65,0)),"")) -> 农药 | K9: 100 | L9: 1000 | M9: =IF(N($K9)=0,"",ROUND(N($L9)/N($K9),4)) -> 10 | N9: =IF($I9="","",IF(ISNA(MATCH($I9,商品档案!$A$6:$A$65,0)),"商品不存在",IF(IFERROR(INDEX(商品档案!$E$6:$E$65,MATCH($I9,商品档案!$A$6:$A$65,0)),"")<>$H9,"商品不属于该公司","OK"))) -> OK | P9: 科技 | Q9: 康养电商 | R9: 88000 | T9: =IF($Q9="","",IF(ISNA(MATCH($Q9,往来单位!$A$6:$A$85,0)),"单位未建档","OK")) -> OK
A10: 农业 | B10: 生产性生物资产 | C10: 600000 | F10: =IF(AND($A10="",$B10=""),"",IF(SUMPRODUCT(($B$6:$B$185=$B10)*($A$6:$A$185=$A10))>1,"同公司同科目重复",IF(ISNA(MATCH($B10,会计科目表!$B$6:$B$85,0)),"科目不存在",IF(AND(N($C10)<>0,N($D10)<>0),"借贷不能同时有数","OK")))) -> OK | H10: 木业 | I10: MY07 | J10: =IF($I10="","",IFERROR(INDEX(商品档案!$B$6:$B$65,MATCH($I10,商品档案!$A$6:$A$65,0)),"")) -> 原木 | K10: 80 | L10: 76000 | M10: =IF(N($K10)=0,"",ROUND(N($L10)/N($K10),4)) -> 950 | N10: =IF($I10="","",IF(ISNA(MATCH($I10,商品档案!$A$6:$A$65,0)),"商品不存在",IF(IFERROR(INDEX(商品档案!$E$6:$E$65,MATCH($I10,商品档案!$A$6:$A$65,0)),"")<>$H10,"商品不属于该公司","OK"))) -> OK | P10: 科技 | Q10: 晶诚玻璃 | S10: 45000 | T10: =IF($Q10="","",IF(ISNA(MATCH($Q10,往来单位!$A$6:$A$85,0)),"单位未建档","OK")) -> OK
A11: 农业 | B11: 生物资产累计折旧 | D11: 40000 | F11: =IF(AND($A11="",$B11=""),"",IF(SUMPRODUCT(($B$6:$B$185=$B11)*($A$6:$A$185=$A11))>1,"同公司同科目重复",IF(ISNA(MATCH($B11,会计科目表!$B$6:$B$85,0)),"科目不存在",IF(AND(N($C11)<>0,N($D11)<>0),"借贷不能同时有数","OK")))) -> OK | H11: 木业 | I11: MY08 | J11: =IF($I11="","",IFERROR(INDEX(商品档案!$B$6:$B$65,MATCH($I11,商品档案!$A$6:$A$65,0)),"")) -> 胶水 | K11: 300 | L11: 5850 | M11: =IF(N($K11)=0,"",ROUND(N($L11)/N($K11),4)) -> 19.5 | N11: =IF($I11="","",IF(ISNA(MATCH($I11,商品档案!$A$6:$A$65,0)),"商品不存在",IF(IFERROR(INDEX(商品档案!$E$6:$E$65,MATCH($I11,商品档案!$A$6:$A$65,0)),"")<>$H11,"商品不属于该公司","OK"))) -> OK | T11: =IF($Q11="","",IF(ISNA(MATCH($Q11,往来单位!$A$6:$A$85,0)),"单位未建档","OK"))
A12: 农业 | B12: 无形资产 | C12: 1200000 | F12: =IF(AND($A12="",$B12=""),"",IF(SUMPRODUCT(($B$6:$B$185=$B12)*($A$6:$A$185=$A12))>1,"同公司同科目重复",IF(ISNA(MATCH($B12,会计科目表!$B$6:$B$85,0)),"科目不存在",IF(AND(N($C12)<>0,N($D12)<>0),"借贷不能同时有数","OK")))) -> OK | H12: 木业 | I12: MY01 | J12: =IF($I12="","",IFERROR(INDEX(商品档案!$B$6:$B$65,MATCH($I12,商品档案!$A$6:$A$65,0)),"")) -> *木制品*木板 | K12: 800 | L12: 76800 | M12: =IF(N($K12)=0,"",ROUND(N($L12)/N($K12),4)) -> 96 | N12: =IF($I12="","",IF(ISNA(MATCH($I12,商品档案!$A$6:$A$65,0)),"商品不存在",IF(IFERROR(INDEX(商品档案!$E$6:$E$65,MATCH($I12,商品档案!$A$6:$A$65,0)),"")<>$H12,"商品不属于该公司","OK"))) -> OK | T12: =IF($Q12="","",IF(ISNA(MATCH($Q12,往来单位!$A$6:$A$85,0)),"单位未建档","OK"))
A13: 农业 | B13: 累计摊销 | D13: 48000 | F13: =IF(AND($A13="",$B13=""),"",IF(SUMPRODUCT(($B$6:$B$185=$B13)*($A$6:$A$185=$A13))>1,"同公司同科目重复",IF(ISNA(MATCH($B13,会计科目表!$B$6:$B$85,0)),"科目不存在",IF(AND(N($C13)<>0,N($D13)<>0),"借贷不能同时有数","OK")))) -> OK | H13: 木业 | I13: MY02 | J13: =IF($I13="","",IFERROR(INDEX(商品档案!$B$6:$B$65,MATCH($I13,商品档案!$A$6:$A$65,0)),"")) -> *木制品*模板 | K13: 300 | L13: 27600 | M13: =IF(N($K13)=0,"",ROUND(N($L13)/N($K13),4)) -> 92 | N13: =IF($I13="","",IF(ISNA(MATCH($I13,商品档案!$A$6:$A$65,0)),"商品不存在",IF(IFERROR(INDEX(商品档案!$E$6:$E$65,MATCH($I13,商品档案!$A$6:$A$65,0)),"")<>$H13,"商品不属于该公司","OK"))) -> OK | T13: =IF($Q13="","",IF(ISNA(MATCH($Q13,往来单位!$A$6:$A$85,0)),"单位未建档","OK"))
A14: 农业 | B14: 固定资产 | C14: 260000 | F14: =IF(AND($A14="",$B14=""),"",IF(SUMPRODUCT(($B$6:$B$185=$B14)*($A$6:$A$185=$A14))>1,"同公司同科目重复",IF(ISNA(MATCH($B14,会计科目表!$B$6:$B$85,0)),"科目不存在",IF(AND(N($C14)<>0,N($D14)<>0),"借贷不能同时有数","OK")))) -> OK | H14: 科技 | I14: KJ08 | J14: =IF($I14="","",IFERROR(INDEX(商品档案!$B$6:$B$65,MATCH($I14,商品档案!$A$6:$A$65,0)),"")) -> 干艾草 | K14: 1500 | L14: 18000 | M14: =IF(N($K14)=0,"",ROUND(N($L14)/N($K14),4)) -> 12 | N14: =IF($I14="","",IF(ISNA(MATCH($I14,商品档案!$A$6:$A$65,0)),"商品不存在",IF(IFERROR(INDEX(商品档案!$E$6:$E$65,MATCH($I14,商品档案!$A$6:$A$65,0)),"")<>$H14,"商品不属于该公司","OK"))) -> OK | T14: =IF($Q14="","",IF(ISNA(MATCH($Q14,往来单位!$A$6:$A$85,0)),"单位未建档","OK"))
A15: 农业 | B15: 累计折旧 | D15: 52000 | F15: =IF(AND($A15="",$B15=""),"",IF(SUMPRODUCT(($B$6:$B$185=$B15)*($A$6:$A$185=$A15))>1,"同公司同科目重复",IF(ISNA(MATCH($B15,会计科目表!$B$6:$B$85,0)),"科目不存在",IF(AND(N($C15)<>0,N($D15)<>0),"借贷不能同时有数","OK")))) -> OK | H15: 科技 | I15: KJ09 | J15: =IF($I15="","",IFERROR(INDEX(商品档案!$B$6:$B$65,MATCH($I15,商品档案!$A$6:$A$65,0)),"")) -> 包装瓶 | K15: 8000 | L15: 7040 | M15: =IF(N($K15)=0,"",ROUND(N($L15)/N($K15),4)) -> 0.88 | N15: =IF($I15="","",IF(ISNA(MATCH($I15,商品档案!$A$6:$A$65,0)),"商品不存在",IF(IFERROR(INDEX(商品档案!$E$6:$E$65,MATCH($I15,商品档案!$A$6:$A$65,0)),"")<>$H15,"商品不属于该公司","OK"))) -> OK | T15: =IF($Q15="","",IF(ISNA(MATCH($Q15,往来单位!$A$6:$A$85,0)),"单位未建档","OK"))
A16: 农业 | B16: 应付账款 | D16: 35000 | F16: =IF(AND($A16="",$B16=""),"",IF(SUMPRODUCT(($B$6:$B$185=$B16)*($A$6:$A$185=$A16))>1,"同公司同科目重复",IF(ISNA(MATCH($B16,会计科目表!$B$6:$B$85,0)),"科目不存在",IF(AND(N($C16)<>0,N($D16)<>0),"借贷不能同时有数","OK")))) -> OK | H16: 科技 | I16: KJ10 | J16: =IF($I16="","",IFERROR(INDEX(商品档案!$B$6:$B$65,MATCH($I16,商品档案!$A$6:$A$65,0)),"")) -> 纸盒 | K16: 10000 | L16: 3300 | M16: =IF(N($K16)=0,"",ROUND(N($L16)/N($K16),4)) -> 0.33 | N16: =IF($I16="","",IF(ISNA(MATCH($I16,商品档案!$A$6:$A$65,0)),"商品不存在",IF(IFERROR(INDEX(商品档案!$E$6:$E$65,MATCH($I16,商品档案!$A$6:$A$65,0)),"")<>$H16,"商品不属于该公司","OK"))) -> OK | T16: =IF($Q16="","",IF(ISNA(MATCH($Q16,往来单位!$A$6:$A$85,0)),"单位未建档","OK"))
A17: 农业 | B17: 短期借款 | D17: 200000 | F17: =IF(AND($A17="",$B17=""),"",IF(SUMPRODUCT(($B$6:$B$185=$B17)*($A$6:$A$185=$A17))>1,"同公司同科目重复",IF(ISNA(MATCH($B17,会计科目表!$B$6:$B$85,0)),"科目不存在",IF(AND(N($C17)<>0,N($D17)<>0),"借贷不能同时有数","OK")))) -> OK | H17: 科技 | I17: KJ01 | J17: =IF($I17="","",IFERROR(INDEX(商品档案!$B$6:$B$65,MATCH($I17,商品档案!$A$6:$A$65,0)),"")) -> 艾草精油原液 | K17: 60 | L17: 66000 | M17: =IF(N($K17)=0,"",ROUND(N($L17)/N($K17),4)) -> 1100 | N17: =IF($I17="","",IF(ISNA(MATCH($I17,商品档案!$A$6:$A$65,0)),"商品不存在",IF(IFERROR(INDEX(商品档案!$E$6:$E$65,MATCH($I17,商品档案!$A$6:$A$65,0)),"")<>$H17,"商品不属于该公司","OK"))) -> OK | T17: =IF($Q17="","",IF(ISNA(MATCH($Q17,往来单位!$A$6:$A$85,0)),"单位未建档","OK"))
A18: 农业 | B18: 实收资本 | D18: 1800000 | F18: =IF(AND($A18="",$B18=""),"",IF(SUMPRODUCT(($B$6:$B$185=$B18)*($A$6:$A$185=$A18))>1,"同公司同科目重复",IF(ISNA(MATCH($B18,会计科目表!$B$6:$B$85,0)),"科目不存在",IF(AND(N($C18)<>0,N($D18)<>0),"借贷不能同时有数","OK")))) -> OK | H18: 科技 | I18: KJ02 | J18: =IF($I18="","",IFERROR(INDEX(商品档案!$B$6:$B$65,MATCH($I18,商品档案!$A$6:$A$65,0)),"")) -> 艾草精油10ml | K18: 1200 | L18: 13800 | M18: =IF(N($K18)=0,"",ROUND(N($L18)/N($K18),4)) -> 11.5 | N18: =IF($I18="","",IF(ISNA(MATCH($I18,商品档案!$A$6:$A$65,0)),"商品不存在",IF(IFERROR(INDEX(商品档案!$E$6:$E$65,MATCH($I18,商品档案!$A$6:$A$65,0)),"")<>$H18,"商品不属于该公司","OK"))) -> OK | T18: =IF($Q18="","",IF(ISNA(MATCH($Q18,往来单位!$A$6:$A$85,0)),"单位未建档","OK"))
A19: 农业 | B19: 未分配利润 | D19: 160000 | F19: =IF(AND($A19="",$B19=""),"",IF(SUMPRODUCT(($B$6:$B$185=$B19)*($A$6:$A$185=$A19))>1,"同公司同科目重复",IF(ISNA(MATCH($B19,会计科目表!$B$6:$B$85,0)),"科目不存在",IF(AND(N($C19)<>0,N($D19)<>0),"借贷不能同时有数","OK")))) -> OK | J19: =IF($I19="","",IFERROR(INDEX(商品档案!$B$6:$B$65,MATCH($I19,商品档案!$A$6:$A$65,0)),"")) | M19: =IF(N($K19)=0,"",ROUND(N($L19)/N($K19),4)) | N19: =IF($I19="","",IF(ISNA(MATCH($I19,商品档案!$A$6:$A$65,0)),"商品不存在",IF(IFERROR(INDEX(商品档案!$E$6:$E$65,MATCH($I19,商品档案!$A$6:$A$65,0)),"")<>$H19,"商品不属于该公司","OK"))) | T19: =IF($Q19="","",IF(ISNA(MATCH($Q19,往来单位!$A$6:$A$85,0)),"单位未建档","OK"))
A20: 木业 | B20: 库存现金 | C20: 3000 | F20: =IF(AND($A20="",$B20=""),"",IF(SUMPRODUCT(($B$6:$B$185=$B20)*($A$6:$A$185=$A20))>1,"同公司同科目重复",IF(ISNA(MATCH($B20,会计科目表!$B$6:$B$85,0)),"科目不存在",IF(AND(N($C20)<>0,N($D20)<>0),"借贷不能同时有数","OK")))) -> OK | J20: =IF($I20="","",IFERROR(INDEX(商品档案!$B$6:$B$65,MATCH($I20,商品档案!$A$6:$A$65,0)),"")) | M20: =IF(N($K20)=0,"",ROUND(N($L20)/N($K20),4)) | N20: =IF($I20="","",IF(ISNA(MATCH($I20,商品档案!$A$6:$A$65,0)),"商品不存在",IF(IFERROR(INDEX(商品档案!$E$6:$E$65,MATCH($I20,商品档案!$A$6:$A$65,0)),"")<>$H20,"商品不属于该公司","OK"))) | T20: =IF($Q20="","",IF(ISNA(MATCH($Q20,往来单位!$A$6:$A$85,0)),"单位未建档","OK"))
A21: 木业 | B21: 银行存款 | C21: 260000 | F21: =IF(AND($A21="",$B21=""),"",IF(SUMPRODUCT(($B$6:$B$185=$B21)*($A$6:$A$185=$A21))>1,"同公司同科目重复",IF(ISNA(MATCH($B21,会计科目表!$B$6:$B$85,0)),"科目不存在",IF(AND(N($C21)<>0,N($D21)<>0),"借贷不能同时有数","OK")))) -> OK | J21: =IF($I21="","",IFERROR(INDEX(商品档案!$B$6:$B$65,MATCH($I21,商品档案!$A$6:$A$65,0)),"")) | M21: =IF(N($K21)=0,"",ROUND(N($L21)/N($K21),4)) | N21: =IF($I21="","",IF(ISNA(MATCH($I21,商品档案!$A$6:$A$65,0)),"商品不存在",IF(IFERROR(INDEX(商品档案!$E$6:$E$65,MATCH($I21,商品档案!$A$6:$A$65,0)),"")<>$H21,"商品不属于该公司","OK"))) | T21: =IF($Q21="","",IF(ISNA(MATCH($Q21,往来单位!$A$6:$A$85,0)),"单位未建档","OK"))
A22: 木业 | B22: 应收账款 | C22: 156000 | F22: =IF(AND($A22="",$B22=""),"",IF(SUMPRODUCT(($B$6:$B$185=$B22)*($A$6:$A$185=$A22))>1,"同公司同科目重复",IF(ISNA(MATCH($B22,会计科目表!$B$6:$B$85,0)),"科目不存在",IF(AND(N($C22)<>0,N($D22)<>0),"借贷不能同时有数","OK")))) -> OK | J22: =IF($I22="","",IFERROR(INDEX(商品档案!$B$6:$B$65,MATCH($I22,商品档案!$A$6:$A$65,0)),"")) | M22: =IF(N($K22)=0,"",ROUND(N($L22)/N($K22),4)) | N22: =IF($I22="","",IF(ISNA(MATCH($I22,商品档案!$A$6:$A$65,0)),"商品不存在",IF(IFERROR(INDEX(商品档案!$E$6:$E$65,MATCH($I22,商品档案!$A$6:$A$65,0)),"")<>$H22,"商品不属于该公司","OK"))) | T22: =IF($Q22="","",IF(ISNA(MATCH($Q22,往来单位!$A$6:$A$85,0)),"单位未建档","OK"))
A23: 木业 | B23: 原材料 | C23: 81850 | F23: =IF(AND($A23="",$B23=""),"",IF(SUMPRODUCT(($B$6:$B$185=$B23)*($A$6:$A$185=$A23))>1,"同公司同科目重复",IF(ISNA(MATCH($B23,会计科目表!$B$6:$B$85,0)),"科目不存在",IF(AND(N($C23)<>0,N($D23)<>0),"借贷不能同时有数","OK")))) -> OK | J23: =IF($I23="","",IFERROR(INDEX(商品档案!$B$6:$B$65,MATCH($I23,商品档案!$A$6:$A$65,0)),"")) | M23: =IF(N($K23)=0,"",ROUND(N($L23)/N($K23),4)) | N23: =IF($I23="","",IF(ISNA(MATCH($I23,商品档案!$A$6:$A$65,0)),"商品不存在",IF(IFERROR(INDEX(商品档案!$E$6:$E$65,MATCH($I23,商品档案!$A$6:$A$65,0)),"")<>$H23,"商品不属于该公司","OK"))) | T23: =IF($Q23="","",IF(ISNA(MATCH($Q23,往来单位!$A$6:$A$85,0)),"单位未建档","OK"))
A24: 木业 | B24: 库存商品 | C24: 104400 | F24: =IF(AND($A24="",$B24=""),"",IF(SUMPRODUCT(($B$6:$B$185=$B24)*($A$6:$A$185=$A24))>1,"同公司同科目重复",IF(ISNA(MATCH($B24,会计科目表!$B$6:$B$85,0)),"科目不存在",IF(AND(N($C24)<>0,N($D24)<>0),"借贷不能同时有数","OK")))) -> OK | J24: =IF($I24="","",IFERROR(INDEX(商品档案!$B$6:$B$65,MATCH($I24,商品档案!$A$6:$A$65,0)),"")) | M24: =IF(N($K24)=0,"",ROUND(N($L24)/N($K24),4)) | N24: =IF($I24="","",IF(ISNA(MATCH($I24,商品档案!$A$6:$A$65,0)),"商品不存在",IF(IFERROR(INDEX(商品档案!$E$6:$E$65,MATCH($I24,商品档案!$A$6:$A$65,0)),"")<>$H24,"商品不属于该公司","OK"))) | T24: =IF($Q24="","",IF(ISNA(MATCH($Q24,往来单位!$A$6:$A$85,0)),"单位未建档","OK"))
A25: 木业 | B25: 固定资产 | C25: 980000 | F25: =IF(AND($A25="",$B25=""),"",IF(SUMPRODUCT(($B$6:$B$185=$B25)*($A$6:$A$185=$A25))>1,"同公司同科目重复",IF(ISNA(MATCH($B25,会计科目表!$B$6:$B$85,0)),"科目不存在",IF(AND(N($C25)<>0,N($D25)<>0),"借贷不能同时有数","OK")))) -> OK | J25: =IF($I25="","",IFERROR(INDEX(商品档案!$B$6:$B$65,MATCH($I25,商品档案!$A$6:$A$65,0)),"")) | M25: =IF(N($K25)=0,"",ROUND(N($L25)/N($K25),4)) | N25: =IF($I25="","",IF(ISNA(MATCH($I25,商品档案!$A$6:$A$65,0)),"商品不存在",IF(IFERROR(INDEX(商品档案!$E$6:$E$65,MATCH($I25,商品档案!$A$6:$A$65,0)),"")<>$H25,"商品不属于该公司","OK"))) | T25: =IF($Q25="","",IF(ISNA(MATCH($Q25,往来单位!$A$6:$A$85,0)),"单位未建档","OK"))
A26: 木业 | B26: 累计折旧 | D26: 196000 | F26: =IF(AND($A26="",$B26=""),"",IF(SUMPRODUCT(($B$6:$B$185=$B26)*($A$6:$A$185=$A26))>1,"同公司同科目重复",IF(ISNA(MATCH($B26,会计科目表!$B$6:$B$85,0)),"科目不存在",IF(AND(N($C26)<>0,N($D26)<>0),"借贷不能同时有数","OK")))) -> OK | J26: =IF($I26="","",IFERROR(INDEX(商品档案!$B$6:$B$65,MATCH($I26,商品档案!$A$6:$A$65,0)),"")) | M26: =IF(N($K26)=0,"",ROUND(N($L26)/N($K26),4)) | N26: =IF($I26="","",IF(ISNA(MATCH($I26,商品档案!$A$6:$A$65,0)),"商品不存在",IF(IFERROR(INDEX(商品档案!$E$6:$E$65,MATCH($I26,商品档案!$A$6:$A$65,0)),"")<>$H26,"商品不属于该公司","OK"))) | T26: =IF($Q26="","",IF(ISNA(MATCH($Q26,往来单位!$A$6:$A$85,0)),"单位未建档","OK"))
A27: 木业 | B27: 应付账款 | D27: 88000 | F27: =IF(AND($A27="",$B27=""),"",IF(SUMPRODUCT(($B$6:$B$185=$B27)*($A$6:$A$185=$A27))>1,"同公司同科目重复",IF(ISNA(MATCH($B27,会计科目表!$B$6:$B$85,0)),"科目不存在",IF(AND(N($C27)<>0,N($D27)<>0),"借贷不能同时有数","OK")))) -> OK | J27: =IF($I27="","",IFERROR(INDEX(商品档案!$B$6:$B$65,MATCH($I27,商品档案!$A$6:$A$65,0)),"")) | M27: =IF(N($K27)=0,"",ROUND(N($L27)/N($K27),4)) | N27: =IF($I27="","",IF(ISNA(MATCH($I27,商品档案!$A$6:$A$65,0)),"商品不存在",IF(IFERROR(INDEX(商品档案!$E$6:$E$65,MATCH($I27,商品档案!$A$6:$A$65,0)),"")<>$H27,"商品不属于该公司","OK"))) | T27: =IF($Q27="","",IF(ISNA(MATCH($Q27,往来单位!$A$6:$A$85,0)),"单位未建档","OK"))
A28: 木业 | B28: 短期借款 | D28: 300000 | F28: =IF(AND($A28="",$B28=""),"",IF(SUMPRODUCT(($B$6:$B$185=$B28)*($A$6:$A$185=$A28))>1,"同公司同科目重复",IF(ISNA(MATCH($B28,会计科目表!$B$6:$B$85,0)),"科目不存在",IF(AND(N($C28)<>0,N($D28)<>0),"借贷不能同时有数","OK")))) -> OK | J28: =IF($I28="","",IFERROR(INDEX(商品档案!$B$6:$B$65,MATCH($I28,商品档案!$A$6:$A$65,0)),"")) | M28: =IF(N($K28)=0,"",ROUND(N($L28)/N($K28),4)) | N28: =IF($I28="","",IF(ISNA(MATCH($I28,商品档案!$A$6:$A$65,0)),"商品不存在",IF(IFERROR(INDEX(商品档案!$E$6:$E$65,MATCH($I28,商品档案!$A$6:$A$65,0)),"")<>$H28,"商品不属于该公司","OK"))) | T28: =IF($Q28="","",IF(ISNA(MATCH($Q28,往来单位!$A$6:$A$85,0)),"单位未建档","OK"))
A29: 木业 | B29: 实收资本 | D29: 800000 | F29: =IF(AND($A29="",$B29=""),"",IF(SUMPRODUCT(($B$6:$B$185=$B29)*($A$6:$A$185=$A29))>1,"同公司同科目重复",IF(ISNA(MATCH($B29,会计科目表!$B$6:$B$85,0)),"科目不存在",IF(AND(N($C29)<>0,N($D29)<>0),"借贷不能同时有数","OK")))) -> OK | J29: =IF($I29="","",IFERROR(INDEX(商品档案!$B$6:$B$65,MATCH($I29,商品档案!$A$6:$A$65,0)),"")) | M29: =IF(N($K29)=0,"",ROUND(N($L29)/N($K29),4)) | N29: =IF($I29="","",IF(ISNA(MATCH($I29,商品档案!$A$6:$A$65,0)),"商品不存在",IF(IFERROR(INDEX(商品档案!$E$6:$E$65,MATCH($I29,商品档案!$A$6:$A$65,0)),"")<>$H29,"商品不属于该公司","OK"))) | T29: =IF($Q29="","",IF(ISNA(MATCH($Q29,往来单位!$A$6:$A$85,0)),"单位未建档","OK"))
A30: 木业 | B30: 未分配利润 | D30: 201250 | F30: =IF(AND($A30="",$B30=""),"",IF(SUMPRODUCT(($B$6:$B$185=$B30)*($A$6:$A$185=$A30))>1,"同公司同科目重复",IF(ISNA(MATCH($B30,会计科目表!$B$6:$B$85,0)),"科目不存在",IF(AND(N($C30)<>0,N($D30)<>0),"借贷不能同时有数","OK")))) -> OK | J30: =IF($I30="","",IFERROR(INDEX(商品档案!$B$6:$B$65,MATCH($I30,商品档案!$A$6:$A$65,0)),"")) | M30: =IF(N($K30)=0,"",ROUND(N($L30)/N($K30),4)) | N30: =IF($I30="","",IF(ISNA(MATCH($I30,商品档案!$A$6:$A$65,0)),"商品不存在",IF(IFERROR(INDEX(商品档案!$E$6:$E$65,MATCH($I30,商品档案!$A$6:$A$65,0)),"")<>$H30,"商品不属于该公司","OK"))) | T30: =IF($Q30="","",IF(ISNA(MATCH($Q30,往来单位!$A$6:$A$85,0)),"单位未建档","OK"))
A31: 科技 | B31: 库存现金 | C31: 2000 | F31: =IF(AND($A31="",$B31=""),"",IF(SUMPRODUCT(($B$6:$B$185=$B31)*($A$6:$A$185=$A31))>1,"同公司同科目重复",IF(ISNA(MATCH($B31,会计科目表!$B$6:$B$85,0)),"科目不存在",IF(AND(N($C31)<>0,N($D31)<>0),"借贷不能同时有数","OK")))) -> OK | J31: =IF($I31="","",IFERROR(INDEX(商品档案!$B$6:$B$65,MATCH($I31,商品档案!$A$6:$A$65,0)),"")) | M31: =IF(N($K31)=0,"",ROUND(N($L31)/N($K31),4)) | N31: =IF($I31="","",IF(ISNA(MATCH($I31,商品档案!$A$6:$A$65,0)),"商品不存在",IF(IFERROR(INDEX(商品档案!$E$6:$E$65,MATCH($I31,商品档案!$A$6:$A$65,0)),"")<>$H31,"商品不属于该公司","OK"))) | T31: =IF($Q31="","",IF(ISNA(MATCH($Q31,往来单位!$A$6:$A$85,0)),"单位未建档","OK"))
A32: 科技 | B32: 银行存款 | C32: 320000 | F32: =IF(AND($A32="",$B32=""),"",IF(SUMPRODUCT(($B$6:$B$185=$B32)*($A$6:$A$185=$A32))>1,"同公司同科目重复",IF(ISNA(MATCH($B32,会计科目表!$B$6:$B$85,0)),"科目不存在",IF(AND(N($C32)<>0,N($D32)<>0),"借贷不能同时有数","OK")))) -> OK | J32: =IF($I32="","",IFERROR(INDEX(商品档案!$B$6:$B$65,MATCH($I32,商品档案!$A$6:$A$65,0)),"")) | M32: =IF(N($K32)=0,"",ROUND(N($L32)/N($K32),4)) | N32: =IF($I32="","",IF(ISNA(MATCH($I32,商品档案!$A$6:$A$65,0)),"商品不存在",IF(IFERROR(INDEX(商品档案!$E$6:$E$65,MATCH($I32,商品档案!$A$6:$A$65,0)),"")<>$H32,"商品不属于该公司","OK"))) | T32: =IF($Q32="","",IF(ISNA(MATCH($Q32,往来单位!$A$6:$A$85,0)),"单位未建档","OK"))
A33: 科技 | B33: 应收账款 | C33: 88000 | F33: =IF(AND($A33="",$B33=""),"",IF(SUMPRODUCT(($B$6:$B$185=$B33)*($A$6:$A$185=$A33))>1,"同公司同科目重复",IF(ISNA(MATCH($B33,会计科目表!$B$6:$B$85,0)),"科目不存在",IF(AND(N($C33)<>0,N($D33)<>0),"借贷不能同时有数","OK")))) -> OK | J33: =IF($I33="","",IFERROR(INDEX(商品档案!$B$6:$B$65,MATCH($I33,商品档案!$A$6:$A$65,0)),"")) | M33: =IF(N($K33)=0,"",ROUND(N($L33)/N($K33),4)) | N33: =IF($I33="","",IF(ISNA(MATCH($I33,商品档案!$A$6:$A$65,0)),"商品不存在",IF(IFERROR(INDEX(商品档案!$E$6:$E$65,MATCH($I33,商品档案!$A$6:$A$65,0)),"")<>$H33,"商品不属于该公司","OK"))) | T33: =IF($Q33="","",IF(ISNA(MATCH($Q33,往来单位!$A$6:$A$85,0)),"单位未建档","OK"))
A34: 科技 | B34: 原材料 | C34: 28340 | F34: =IF(AND($A34="",$B34=""),"",IF(SUMPRODUCT(($B$6:$B$185=$B34)*($A$6:$A$185=$A34))>1,"同公司同科目重复",IF(ISNA(MATCH($B34,会计科目表!$B$6:$B$85,0)),"科目不存在",IF(AND(N($C34)<>0,N($D34)<>0),"借贷不能同时有数","OK")))) -> OK | J34: =IF($I34="","",IFERROR(INDEX(商品档案!$B$6:$B$65,MATCH($I34,商品档案!$A$6:$A$65,0)),"")) | M34: =IF(N($K34)=0,"",ROUND(N($L34)/N($K34),4)) | N34: =IF($I34="","",IF(ISNA(MATCH($I34,商品档案!$A$6:$A$65,0)),"商品不存在",IF(IFERROR(INDEX(商品档案!$E$6:$E$65,MATCH($I34,商品档案!$A$6:$A$65,0)),"")<>$H34,"商品不属于该公司","OK"))) | T34: =IF($Q34="","",IF(ISNA(MATCH($Q34,往来单位!$A$6:$A$85,0)),"单位未建档","OK"))
A35: 科技 | B35: 库存商品 | C35: 79800 | F35: =IF(AND($A35="",$B35=""),"",IF(SUMPRODUCT(($B$6:$B$185=$B35)*($A$6:$A$185=$A35))>1,"同公司同科目重复",IF(ISNA(MATCH($B35,会计科目表!$B$6:$B$85,0)),"科目不存在",IF(AND(N($C35)<>0,N($D35)<>0),"借贷不能同时有数","OK")))) -> OK | J35: =IF($I35="","",IFERROR(INDEX(商品档案!$B$6:$B$65,MATCH($I35,商品档案!$A$6:$A$65,0)),"")) | M35: =IF(N($K35)=0,"",ROUND(N($L35)/N($K35),4)) | N35: =IF($I35="","",IF(ISNA(MATCH($I35,商品档案!$A$6:$A$65,0)),"商品不存在",IF(IFERROR(INDEX(商品档案!$E$6:$E$65,MATCH($I35,商品档案!$A$6:$A$65,0)),"")<>$H35,"商品不属于该公司","OK"))) | T35: =IF($Q35="","",IF(ISNA(MATCH($Q35,往来单位!$A$6:$A$85,0)),"单位未建档","OK"))
A36: 科技 | B36: 固定资产 | C36: 520000 | F36: =IF(AND($A36="",$B36=""),"",IF(SUMPRODUCT(($B$6:$B$185=$B36)*($A$6:$A$185=$A36))>1,"同公司同科目重复",IF(ISNA(MATCH($B36,会计科目表!$B$6:$B$85,0)),"科目不存在",IF(AND(N($C36)<>0,N($D36)<>0),"借贷不能同时有数","OK")))) -> OK | J36: =IF($I36="","",IFERROR(INDEX(商品档案!$B$6:$B$65,MATCH($I36,商品档案!$A$6:$A$65,0)),"")) | M36: =IF(N($K36)=0,"",ROUND(N($L36)/N($K36),4)) | N36: =IF($I36="","",IF(ISNA(MATCH($I36,商品档案!$A$6:$A$65,0)),"商品不存在",IF(IFERROR(INDEX(商品档案!$E$6:$E$65,MATCH($I36,商品档案!$A$6:$A$65,0)),"")<>$H36,"商品不属于该公司","OK"))) | T36: =IF($Q36="","",IF(ISNA(MATCH($Q36,往来单位!$A$6:$A$85,0)),"单位未建档","OK"))
A37: 科技 | B37: 累计折旧 | D37: 104000 | F37: =IF(AND($A37="",$B37=""),"",IF(SUMPRODUCT(($B$6:$B$185=$B37)*($A$6:$A$185=$A37))>1,"同公司同科目重复",IF(ISNA(MATCH($B37,会计科目表!$B$6:$B$85,0)),"科目不存在",IF(AND(N($C37)<>0,N($D37)<>0),"借贷不能同时有数","OK")))) -> OK | J37: =IF($I37="","",IFERROR(INDEX(商品档案!$B$6:$B$65,MATCH($I37,商品档案!$A$6:$A$65,0)),"")) | M37: =IF(N($K37)=0,"",ROUND(N($L37)/N($K37),4)) | N37: =IF($I37="","",IF(ISNA(MATCH($I37,商品档案!$A$6:$A$65,0)),"商品不存在",IF(IFERROR(INDEX(商品档案!$E$6:$E$65,MATCH($I37,商品档案!$A$6:$A$65,0)),"")<>$H37,"商品不属于该公司","OK"))) | T37: =IF($Q37="","",IF(ISNA(MATCH($Q37,往来单位!$A$6:$A$85,0)),"单位未建档","OK"))
A38: 科技 | B38: 无形资产 | C38: 60000 | F38: =IF(AND($A38="",$B38=""),"",IF(SUMPRODUCT(($B$6:$B$185=$B38)*($A$6:$A$185=$A38))>1,"同公司同科目重复",IF(ISNA(MATCH($B38,会计科目表!$B$6:$B$85,0)),"科目不存在",IF(AND(N($C38)<>0,N($D38)<>0),"借贷不能同时有数","OK")))) -> OK | J38: =IF($I38="","",IFERROR(INDEX(商品档案!$B$6:$B$65,MATCH($I38,商品档案!$A$6:$A$65,0)),"")) | M38: =IF(N($K38)=0,"",ROUND(N($L38)/N($K38),4)) | N38: =IF($I38="","",IF(ISNA(MATCH($I38,商品档案!$A$6:$A$65,0)),"商品不存在",IF(IFERROR(INDEX(商品档案!$E$6:$E$65,MATCH($I38,商品档案!$A$6:$A$65,0)),"")<>$H38,"商品不属于该公司","OK"))) | T38: =IF($Q38="","",IF(ISNA(MATCH($Q38,往来单位!$A$6:$A$85,0)),"单位未建档","OK"))
A39: 科技 | B39: 累计摊销 | D39: 12000 | F39: =IF(AND($A39="",$B39=""),"",IF(SUMPRODUCT(($B$6:$B$185=$B39)*($A$6:$A$185=$A39))>1,"同公司同科目重复",IF(ISNA(MATCH($B39,会计科目表!$B$6:$B$85,0)),"科目不存在",IF(AND(N($C39)<>0,N($D39)<>0),"借贷不能同时有数","OK")))) -> OK | J39: =IF($I39="","",IFERROR(INDEX(商品档案!$B$6:$B$65,MATCH($I39,商品档案!$A$6:$A$65,0)),"")) | M39: =IF(N($K39)=0,"",ROUND(N($L39)/N($K39),4)) | N39: =IF($I39="","",IF(ISNA(MATCH($I39,商品档案!$A$6:$A$65,0)),"商品不存在",IF(IFERROR(INDEX(商品档案!$E$6:$E$65,MATCH($I39,商品档案!$A$6:$A$65,0)),"")<>$H39,"商品不属于该公司","OK"))) | T39: =IF($Q39="","",IF(ISNA(MATCH($Q39,往来单位!$A$6:$A$85,0)),"单位未建档","OK"))
A40: 科技 | B40: 应付账款 | D40: 45000 | F40: =IF(AND($A40="",$B40=""),"",IF(SUMPRODUCT(($B$6:$B$185=$B40)*($A$6:$A$185=$A40))>1,"同公司同科目重复",IF(ISNA(MATCH($B40,会计科目表!$B$6:$B$85,0)),"科目不存在",IF(AND(N($C40)<>0,N($D40)<>0),"借贷不能同时有数","OK")))) -> OK | J40: =IF($I40="","",IFERROR(INDEX(商品档案!$B$6:$B$65,MATCH($I40,商品档案!$A$6:$A$65,0)),"")) | M40: =IF(N($K40)=0,"",ROUND(N($L40)/N($K40),4)) | N40: =IF($I40="","",IF(ISNA(MATCH($I40,商品档案!$A$6:$A$65,0)),"商品不存在",IF(IFERROR(INDEX(商品档案!$E$6:$E$65,MATCH($I40,商品档案!$A$6:$A$65,0)),"")<>$H40,"商品不属于该公司","OK"))) | T40: =IF($Q40="","",IF(ISNA(MATCH($Q40,往来单位!$A$6:$A$85,0)),"单位未建档","OK"))
A41: 科技 | B41: 应付职工薪酬 | D41: 18000 | F41: =IF(AND($A41="",$B41=""),"",IF(SUMPRODUCT(($B$6:$B$185=$B41)*($A$6:$A$185=$A41))>1,"同公司同科目重复",IF(ISNA(MATCH($B41,会计科目表!$B$6:$B$85,0)),"科目不存在",IF(AND(N($C41)<>0,N($D41)<>0),"借贷不能同时有数","OK")))) -> OK | J41: =IF($I41="","",IFERROR(INDEX(商品档案!$B$6:$B$65,MATCH($I41,商品档案!$A$6:$A$65,0)),"")) | M41: =IF(N($K41)=0,"",ROUND(N($L41)/N($K41),4)) | N41: =IF($I41="","",IF(ISNA(MATCH($I41,商品档案!$A$6:$A$65,0)),"商品不存在",IF(IFERROR(INDEX(商品档案!$E$6:$E$65,MATCH($I41,商品档案!$A$6:$A$65,0)),"")<>$H41,"商品不属于该公司","OK"))) | T41: =IF($Q41="","",IF(ISNA(MATCH($Q41,往来单位!$A$6:$A$85,0)),"单位未建档","OK"))
A42: 科技 | B42: 实收资本 | D42: 700000 | F42: =IF(AND($A42="",$B42=""),"",IF(SUMPRODUCT(($B$6:$B$185=$B42)*($A$6:$A$185=$A42))>1,"同公司同科目重复",IF(ISNA(MATCH($B42,会计科目表!$B$6:$B$85,0)),"科目不存在",IF(AND(N($C42)<>0,N($D42)<>0),"借贷不能同时有数","OK")))) -> OK | J42: =IF($I42="","",IFERROR(INDEX(商品档案!$B$6:$B$65,MATCH($I42,商品档案!$A$6:$A$65,0)),"")) | M42: =IF(N($K42)=0,"",ROUND(N($L42)/N($K42),4)) | N42: =IF($I42="","",IF(ISNA(MATCH($I42,商品档案!$A$6:$A$65,0)),"商品不存在",IF(IFERROR(INDEX(商品档案!$E$6:$E$65,MATCH($I42,商品档案!$A$6:$A$65,0)),"")<>$H42,"商品不属于该公司","OK"))) | T42: =IF($Q42="","",IF(ISNA(MATCH($Q42,往来单位!$A$6:$A$85,0)),"单位未建档","OK"))
A43: 科技 | B43: 未分配利润 | D43: 219140 | F43: =IF(AND($A43="",$B43=""),"",IF(SUMPRODUCT(($B$6:$B$185=$B43)*($A$6:$A$185=$A43))>1,"同公司同科目重复",IF(ISNA(MATCH($B43,会计科目表!$B$6:$B$85,0)),"科目不存在",IF(AND(N($C43)<>0,N($D43)<>0),"借贷不能同时有数","OK")))) -> OK | J43: =IF($I43="","",IFERROR(INDEX(商品档案!$B$6:$B$65,MATCH($I43,商品档案!$A$6:$A$65,0)),"")) | M43: =IF(N($K43)=0,"",ROUND(N($L43)/N($K43),4)) | N43: =IF($I43="","",IF(ISNA(MATCH($I43,商品档案!$A$6:$A$65,0)),"商品不存在",IF(IFERROR(INDEX(商品档案!$E$6:$E$65,MATCH($I43,商品档案!$A$6:$A$65,0)),"")<>$H43,"商品不属于该公司","OK"))) | T43: =IF($Q43="","",IF(ISNA(MATCH($Q43,往来单位!$A$6:$A$85,0)),"单位未建档","OK"))
F44: =IF(AND($A44="",$B44=""),"",IF(SUMPRODUCT(($B$6:$B$185=$B44)*($A$6:$A$185=$A44))>1,"同公司同科目重复",IF(ISNA(MATCH($B44,会计科目表!$B$6:$B$85,0)),"科目不存在",IF(AND(N($C44)<>0,N($D44)<>0),"借贷不能同时有数","OK")))) | J44: =IF($I44="","",IFERROR(INDEX(商品档案!$B$6:$B$65,MATCH($I44,商品档案!$A$6:$A$65,0)),"")) | M44: =IF(N($K44)=0,"",ROUND(N($L44)/N($K44),4)) | N44: =IF($I44="","",IF(ISNA(MATCH($I44,商品档案!$A$6:$A$65,0)),"商品不存在",IF(IFERROR(INDEX(商品档案!$E$6:$E$65,MATCH($I44,商品档案!$A$6:$A$65,0)),"")<>$H44,"商品不属于该公司","OK"))) | T44: =IF($Q44="","",IF(ISNA(MATCH($Q44,往来单位!$A$6:$A$85,0)),"单位未建档","OK"))
F45: =IF(AND($A45="",$B45=""),"",IF(SUMPRODUCT(($B$6:$B$185=$B45)*($A$6:$A$185=$A45))>1,"同公司同科目重复",IF(ISNA(MATCH($B45,会计科目表!$B$6:$B$85,0)),"科目不存在",IF(AND(N($C45)<>0,N($D45)<>0),"借贷不能同时有数","OK")))) | J45: =IF($I45="","",IFERROR(INDEX(商品档案!$B$6:$B$65,MATCH($I45,商品档案!$A$6:$A$65,0)),"")) | M45: =IF(N($K45)=0,"",ROUND(N($L45)/N($K45),4)) | N45: =IF($I45="","",IF(ISNA(MATCH($I45,商品档案!$A$6:$A$65,0)),"商品不存在",IF(IFERROR(INDEX(商品档案!$E$6:$E$65,MATCH($I45,商品档案!$A$6:$A$65,0)),"")<>$H45,"商品不属于该公司","OK"))) | T45: =IF($Q45="","",IF(ISNA(MATCH($Q45,往来单位!$A$6:$A$85,0)),"单位未建档","OK"))
F46: =IF(AND($A46="",$B46=""),"",IF(SUMPRODUCT(($B$6:$B$185=$B46)*($A$6:$A$185=$A46))>1,"同公司同科目重复",IF(ISNA(MATCH($B46,会计科目表!$B$6:$B$85,0)),"科目不存在",IF(AND(N($C46)<>0,N($D46)<>0),"借贷不能同时有数","OK")))) | J46: =IF($I46="","",IFERROR(INDEX(商品档案!$B$6:$B$65,MATCH($I46,商品档案!$A$6:$A$65,0)),"")) | M46: =IF(N($K46)=0,"",ROUND(N($L46)/N($K46),4)) | N46: =IF($I46="","",IF(ISNA(MATCH($I46,商品档案!$A$6:$A$65,0)),"商品不存在",IF(IFERROR(INDEX(商品档案!$E$6:$E$65,MATCH($I46,商品档案!$A$6:$A$65,0)),"")<>$H46,"商品不属于该公司","OK"))) | T46: =IF($Q46="","",IF(ISNA(MATCH($Q46,往来单位!$A$6:$A$85,0)),"单位未建档","OK"))
F47: =IF(AND($A47="",$B47=""),"",IF(SUMPRODUCT(($B$6:$B$185=$B47)*($A$6:$A$185=$A47))>1,"同公司同科目重复",IF(ISNA(MATCH($B47,会计科目表!$B$6:$B$85,0)),"科目不存在",IF(AND(N($C47)<>0,N($D47)<>0),"借贷不能同时有数","OK")))) | J47: =IF($I47="","",IFERROR(INDEX(商品档案!$B$6:$B$65,MATCH($I47,商品档案!$A$6:$A$65,0)),"")) | M47: =IF(N($K47)=0,"",ROUND(N($L47)/N($K47),4)) | N47: =IF($I47="","",IF(ISNA(MATCH($I47,商品档案!$A$6:$A$65,0)),"商品不存在",IF(IFERROR(INDEX(商品档案!$E$6:$E$65,MATCH($I47,商品档案!$A$6:$A$65,0)),"")<>$H47,"商品不属于该公司","OK"))) | T47: =IF($Q47="","",IF(ISNA(MATCH($Q47,往来单位!$A$6:$A$85,0)),"单位未建档","OK"))
F48: =IF(AND($A48="",$B48=""),"",IF(SUMPRODUCT(($B$6:$B$185=$B48)*($A$6:$A$185=$A48))>1,"同公司同科目重复",IF(ISNA(MATCH($B48,会计科目表!$B$6:$B$85,0)),"科目不存在",IF(AND(N($C48)<>0,N($D48)<>0),"借贷不能同时有数","OK")))) | J48: =IF($I48="","",IFERROR(INDEX(商品档案!$B$6:$B$65,MATCH($I48,商品档案!$A$6:$A$65,0)),"")) | M48: =IF(N($K48)=0,"",ROUND(N($L48)/N($K48),4)) | N48: =IF($I48="","",IF(ISNA(MATCH($I48,商品档案!$A$6:$A$65,0)),"商品不存在",IF(IFERROR(INDEX(商品档案!$E$6:$E$65,MATCH($I48,商品档案!$A$6:$A$65,0)),"")<>$H48,"商品不属于该公司","OK"))) | T48: =IF($Q48="","",IF(ISNA(MATCH($Q48,往来单位!$A$6:$A$85,0)),"单位未建档","OK"))
F49: =IF(AND($A49="",$B49=""),"",IF(SUMPRODUCT(($B$6:$B$185=$B49)*($A$6:$A$185=$A49))>1,"同公司同科目重复",IF(ISNA(MATCH($B49,会计科目表!$B$6:$B$85,0)),"科目不存在",IF(AND(N($C49)<>0,N($D49)<>0),"借贷不能同时有数","OK")))) | J49: =IF($I49="","",IFERROR(INDEX(商品档案!$B$6:$B$65,MATCH($I49,商品档案!$A$6:$A$65,0)),"")) | M49: =IF(N($K49)=0,"",ROUND(N($L49)/N($K49),4)) | N49: =IF($I49="","",IF(ISNA(MATCH($I49,商品档案!$A$6:$A$65,0)),"商品不存在",IF(IFERROR(INDEX(商品档案!$E$6:$E$65,MATCH($I49,商品档案!$A$6:$A$65,0)),"")<>$H49,"商品不属于该公司","OK"))) | T49: =IF($Q49="","",IF(ISNA(MATCH($Q49,往来单位!$A$6:$A$85,0)),"单位未建档","OK"))
F50: =IF(AND($A50="",$B50=""),"",IF(SUMPRODUCT(($B$6:$B$185=$B50)*($A$6:$A$185=$A50))>1,"同公司同科目重复",IF(ISNA(MATCH($B50,会计科目表!$B$6:$B$85,0)),"科目不存在",IF(AND(N($C50)<>0,N($D50)<>0),"借贷不能同时有数","OK")))) | J50: =IF($I50="","",IFERROR(INDEX(商品档案!$B$6:$B$65,MATCH($I50,商品档案!$A$6:$A$65,0)),"")) | M50: =IF(N($K50)=0,"",ROUND(N($L50)/N($K50),4)) | N50: =IF($I50="","",IF(ISNA(MATCH($I50,商品档案!$A$6:$A$65,0)),"商品不存在",IF(IFERROR(INDEX(商品档案!$E$6:$E$65,MATCH($I50,商品档案!$A$6:$A$65,0)),"")<>$H50,"商品不属于该公司","OK"))) | T50: =IF($Q50="","",IF(ISNA(MATCH($Q50,往来单位!$A$6:$A$85,0)),"单位未建档","OK"))
F51: =IF(AND($A51="",$B51=""),"",IF(SUMPRODUCT(($B$6:$B$185=$B51)*($A$6:$A$185=$A51))>1,"同公司同科目重复",IF(ISNA(MATCH($B51,会计科目表!$B$6:$B$85,0)),"科目不存在",IF(AND(N($C51)<>0,N($D51)<>0),"借贷不能同时有数","OK")))) | J51: =IF($I51="","",IFERROR(INDEX(商品档案!$B$6:$B$65,MATCH($I51,商品档案!$A$6:$A$65,0)),"")) | M51: =IF(N($K51)=0,"",ROUND(N($L51)/N($K51),4)) | N51: =IF($I51="","",IF(ISNA(MATCH($I51,商品档案!$A$6:$A$65,0)),"商品不存在",IF(IFERROR(INDEX(商品档案!$E$6:$E$65,MATCH($I51,商品档案!$A$6:$A$65,0)),"")<>$H51,"商品不属于该公司","OK"))) | T51: =IF($Q51="","",IF(ISNA(MATCH($Q51,往来单位!$A$6:$A$85,0)),"单位未建档","OK"))
F52: =IF(AND($A52="",$B52=""),"",IF(SUMPRODUCT(($B$6:$B$185=$B52)*($A$6:$A$185=$A52))>1,"同公司同科目重复",IF(ISNA(MATCH($B52,会计科目表!$B$6:$B$85,0)),"科目不存在",IF(AND(N($C52)<>0,N($D52)<>0),"借贷不能同时有数","OK")))) | J52: =IF($I52="","",IFERROR(INDEX(商品档案!$B$6:$B$65,MATCH($I52,商品档案!$A$6:$A$65,0)),"")) | M52: =IF(N($K52)=0,"",ROUND(N($L52)/N($K52),4)) | N52: =IF($I52="","",IF(ISNA(MATCH($I52,商品档案!$A$6:$A$65,0)),"商品不存在",IF(IFERROR(INDEX(商品档案!$E$6:$E$65,MATCH($I52,商品档案!$A$6:$A$65,0)),"")<>$H52,"商品不属于该公司","OK"))) | T52: =IF($Q52="","",IF(ISNA(MATCH($Q52,往来单位!$A$6:$A$85,0)),"单位未建档","OK"))
F53: =IF(AND($A53="",$B53=""),"",IF(SUMPRODUCT(($B$6:$B$185=$B53)*($A$6:$A$185=$A53))>1,"同公司同科目重复",IF(ISNA(MATCH($B53,会计科目表!$B$6:$B$85,0)),"科目不存在",IF(AND(N($C53)<>0,N($D53)<>0),"借贷不能同时有数","OK")))) | J53: =IF($I53="","",IFERROR(INDEX(商品档案!$B$6:$B$65,MATCH($I53,商品档案!$A$6:$A$65,0)),"")) | M53: =IF(N($K53)=0,"",ROUND(N($L53)/N($K53),4)) | N53: =IF($I53="","",IF(ISNA(MATCH($I53,商品档案!$A$6:$A$65,0)),"商品不存在",IF(IFERROR(INDEX(商品档案!$E$6:$E$65,MATCH($I53,商品档案!$A$6:$A$65,0)),"")<>$H53,"商品不属于该公司","OK"))) | T53: =IF($Q53="","",IF(ISNA(MATCH($Q53,往来单位!$A$6:$A$85,0)),"单位未建档","OK"))
F54: =IF(AND($A54="",$B54=""),"",IF(SUMPRODUCT(($B$6:$B$185=$B54)*($A$6:$A$185=$A54))>1,"同公司同科目重复",IF(ISNA(MATCH($B54,会计科目表!$B$6:$B$85,0)),"科目不存在",IF(AND(N($C54)<>0,N($D54)<>0),"借贷不能同时有数","OK")))) | J54: =IF($I54="","",IFERROR(INDEX(商品档案!$B$6:$B$65,MATCH($I54,商品档案!$A$6:$A$65,0)),"")) | M54: =IF(N($K54)=0,"",ROUND(N($L54)/N($K54),4)) | N54: =IF($I54="","",IF(ISNA(MATCH($I54,商品档案!$A$6:$A$65,0)),"商品不存在",IF(IFERROR(INDEX(商品档案!$E$6:$E$65,MATCH($I54,商品档案!$A$6:$A$65,0)),"")<>$H54,"商品不属于该公司","OK"))) | T54: =IF($Q54="","",IF(ISNA(MATCH($Q54,往来单位!$A$6:$A$85,0)),"单位未建档","OK"))
F55: =IF(AND($A55="",$B55=""),"",IF(SUMPRODUCT(($B$6:$B$185=$B55)*($A$6:$A$185=$A55))>1,"同公司同科目重复",IF(ISNA(MATCH($B55,会计科目表!$B$6:$B$85,0)),"科目不存在",IF(AND(N($C55)<>0,N($D55)<>0),"借贷不能同时有数","OK")))) | J55: =IF($I55="","",IFERROR(INDEX(商品档案!$B$6:$B$65,MATCH($I55,商品档案!$A$6:$A$65,0)),"")) | M55: =IF(N($K55)=0,"",ROUND(N($L55)/N($K55),4)) | N55: =IF($I55="","",IF(ISNA(MATCH($I55,商品档案!$A$6:$A$65,0)),"商品不存在",IF(IFERROR(INDEX(商品档案!$E$6:$E$65,MATCH($I55,商品档案!$A$6:$A$65,0)),"")<>$H55,"商品不属于该公司","OK"))) | T55: =IF($Q55="","",IF(ISNA(MATCH($Q55,往来单位!$A$6:$A$85,0)),"单位未建档","OK"))
... F65: =IF(AND($A65="",$B65=""),"",IF(SUMPRODUCT(($B$6:$B$185=$B65)*($A$6:$A$185=$A65))>1,"同公司同科目重复",IF(ISNA(MATCH($B65,会计科目表!$B$6:$B$85,0)),"科目不存在",IF(AND(N($C65)<>0,N($D65)<>0),"借贷不能同时有数","OK")))) | J65: =IF($I65="","",IFERROR(INDEX(商品档案!$B$6:$B$65,MATCH($I65,商品档案!$A$6:$A$65,0)),"")) | M65: =IF(N($K65)=0,"",ROUND(N($L65)/N($K65),4)) | N65: =IF($I65="","",IF(ISNA(MATCH($I65,商品档案!$A$6:$A$65,0)),"商品不存在",IF(IFERROR(INDEX(商品档案!$E$6:$E$65,MATCH($I65,商品档案!$A$6:$A$65,0)),"")<>$H65,"商品不属于该公司","OK"))) | T65: =IF($Q65="","",IF(ISNA(MATCH($Q65,往来单位!$A$6:$A$85,0)),"单位未建档","OK"))
F66: =IF(AND($A66="",$B66=""),"",IF(SUMPRODUCT(($B$6:$B$185=$B66)*($A$6:$A$185=$A66))>1,"同公司同科目重复",IF(ISNA(MATCH($B66,会计科目表!$B$6:$B$85,0)),"科目不存在",IF(AND(N($C66)<>0,N($D66)<>0),"借贷不能同时有数","OK"))))
F67: =IF(AND($A67="",$B67=""),"",IF(SUMPRODUCT(($B$6:$B$185=$B67)*($A$6:$A$185=$A67))>1,"同公司同科目重复",IF(ISNA(MATCH($B67,会计科目表!$B$6:$B$85,0)),"科目不存在",IF(AND(N($C67)<>0,N($D67)<>0),"借贷不能同时有数","OK"))))
F68: =IF(AND($A68="",$B68=""),"",IF(SUMPRODUCT(($B$6:$B$185=$B68)*($A$6:$A$185=$A68))>1,"同公司同科目重复",IF(ISNA(MATCH($B68,会计科目表!$B$6:$B$85,0)),"科目不存在",IF(AND(N($C68)<>0,N($D68)<>0),"借贷不能同时有数","OK"))))
F69: =IF(AND($A69="",$B69=""),"",IF(SUMPRODUCT(($B$6:$B$185=$B69)*($A$6:$A$185=$A69))>1,"同公司同科目重复",IF(ISNA(MATCH($B69,会计科目表!$B$6:$B$85,0)),"科目不存在",IF(AND(N($C69)<>0,N($D69)<>0),"借贷不能同时有数","OK"))))
F70: =IF(AND($A70="",$B70=""),"",IF(SUMPRODUCT(($B$6:$B$185=$B70)*($A$6:$A$185=$A70))>1,"同公司同科目重复",IF(ISNA(MATCH($B70,会计科目表!$B$6:$B$85,0)),"科目不存在",IF(AND(N($C70)<>0,N($D70)<>0),"借贷不能同时有数","OK"))))
F71: =IF(AND($A71="",$B71=""),"",IF(SUMPRODUCT(($B$6:$B$185=$B71)*($A$6:$A$185=$A71))>1,"同公司同科目重复",IF(ISNA(MATCH($B71,会计科目表!$B$6:$B$85,0)),"科目不存在",IF(AND(N($C71)<>0,N($D71)<>0),"借贷不能同时有数","OK"))))
F72: =IF(AND($A72="",$B72=""),"",IF(SUMPRODUCT(($B$6:$B$185=$B72)*($A$6:$A$185=$A72))>1,"同公司同科目重复",IF(ISNA(MATCH($B72,会计科目表!$B$6:$B$85,0)),"科目不存在",IF(AND(N($C72)<>0,N($D72)<>0),"借贷不能同时有数","OK"))))
F73: =IF(AND($A73="",$B73=""),"",IF(SUMPRODUCT(($B$6:$B$185=$B73)*($A$6:$A$185=$A73))>1,"同公司同科目重复",IF(ISNA(MATCH($B73,会计科目表!$B$6:$B$85,0)),"科目不存在",IF(AND(N($C73)<>0,N($D73)<>0),"借贷不能同时有数","OK"))))
F74: =IF(AND($A74="",$B74=""),"",IF(SUMPRODUCT(($B$6:$B$185=$B74)*($A$6:$A$185=$A74))>1,"同公司同科目重复",IF(ISNA(MATCH($B74,会计科目表!$B$6:$B$85,0)),"科目不存在",IF(AND(N($C74)<>0,N($D74)<>0),"借贷不能同时有数","OK"))))
F75: =IF(AND($A75="",$B75=""),"",IF(SUMPRODUCT(($B$6:$B$185=$B75)*($A$6:$A$185=$A75))>1,"同公司同科目重复",IF(ISNA(MATCH($B75,会计科目表!$B$6:$B$85,0)),"科目不存在",IF(AND(N($C75)<>0,N($D75)<>0),"借贷不能同时有数","OK"))))
F76: =IF(AND($A76="",$B76=""),"",IF(SUMPRODUCT(($B$6:$B$185=$B76)*($A$6:$A$185=$A76))>1,"同公司同科目重复",IF(ISNA(MATCH($B76,会计科目表!$B$6:$B$85,0)),"科目不存在",IF(AND(N($C76)<>0,N($D76)<>0),"借贷不能同时有数","OK"))))
F77: =IF(AND($A77="",$B77=""),"",IF(SUMPRODUCT(($B$6:$B$185=$B77)*($A$6:$A$185=$A77))>1,"同公司同科目重复",IF(ISNA(MATCH($B77,会计科目表!$B$6:$B$85,0)),"科目不存在",IF(AND(N($C77)<>0,N($D77)<>0),"借贷不能同时有数","OK"))))
... F185: =IF(AND($A185="",$B185=""),"",IF(SUMPRODUCT(($B$6:$B$185=$B185)*($A$6:$A$185=$A185))>1,"同公司同科目重复",IF(ISNA(MATCH($B185,会计科目表!$B$6:$B$85,0)),"科目不存在",IF(AND(N($C185)<>0,N($D185)<>0),"借贷不能同时有数","OK"))))
H187: 存货两边对账 | I187: 右边存货金额合计 vs 左边「原材料 + 库存商品」借方余额 | P187: 往来两边对账 | Q187: 按单位拆的年初应收/应付合计，要等于左边该公司应收账款/应付账款的余额
H188: 农业 | I188: =SUMIFS($L$6:$L$65,$H$6:$H$65,$H188) -> 90000 | J188: =SUMIFS($C$6:$C$185,$A$6:$A$185,$H188,$B$6:$B$185,"原材料")+SUMIFS($C$6:$C$185,$A$6:$A$185,$H188,$B$6:$B$185,"库存商品") -> 90000 | L188: =IF(ROUND($I188-$J188,2)=0,"√ 一致","✗ 差 "&TEXT($I188-$J188,"#,##0.00")) -> √ 一致 | P188: 农业 | Q188: =SUMIFS($R$6:$R$65,$P$6:$P$65,$P188)-SUMIFS($C$6:$C$185,$A$6:$A$185,$P188,$B$6:$B$185,"应收账款") -> 0 | R188: =IF(ROUND($Q188,2)=0,"√ 应收一致" ,"✗ 差 "&TEXT($Q188,"#,##0.00")) -> √ 应收一致 | S188: =SUMIFS($S$6:$S$65,$P$6:$P$65,$P188)-SUMIFS($D$6:$D$185,$A$6:$A$185,$P188,$B$6:$B$185,"应付账款") -> 0 | T188: =IF(ROUND($S188,2)=0,"√ 应付一致","✗ 差 "&TEXT($S188,"#,##0.00")) -> √ 应付一致
H189: 木业 | I189: =SUMIFS($L$6:$L$65,$H$6:$H$65,$H189) -> 186250 | J189: =SUMIFS($C$6:$C$185,$A$6:$A$185,$H189,$B$6:$B$185,"原材料")+SUMIFS($C$6:$C$185,$A$6:$A$185,$H189,$B$6:$B$185,"库存商品") -> 186250 | L189: =IF(ROUND($I189-$J189,2)=0,"√ 一致","✗ 差 "&TEXT($I189-$J189,"#,##0.00")) -> √ 一致 | P189: 木业 | Q189: =SUMIFS($R$6:$R$65,$P$6:$P$65,$P189)-SUMIFS($C$6:$C$185,$A$6:$A$185,$P189,$B$6:$B$185,"应收账款") -> 0 | R189: =IF(ROUND($Q189,2)=0,"√ 应收一致" ,"✗ 差 "&TEXT($Q189,"#,##0.00")) -> √ 应收一致 | S189: =SUMIFS($S$6:$S$65,$P$6:$P$65,$P189)-SUMIFS($D$6:$D$185,$A$6:$A$185,$P189,$B$6:$B$185,"应付账款") -> 0 | T189: =IF(ROUND($S189,2)=0,"√ 应付一致","✗ 差 "&TEXT($S189,"#,##0.00")) -> √ 应付一致
H190: 科技 | I190: =SUMIFS($L$6:$L$65,$H$6:$H$65,$H190) -> 108140 | J190: =SUMIFS($C$6:$C$185,$A$6:$A$185,$H190,$B$6:$B$185,"原材料")+SUMIFS($C$6:$C$185,$A$6:$A$185,$H190,$B$6:$B$185,"库存商品") -> 108140 | L190: =IF(ROUND($I190-$J190,2)=0,"√ 一致","✗ 差 "&TEXT($I190-$J190,"#,##0.00")) -> √ 一致 | P190: 科技 | Q190: =SUMIFS($R$6:$R$65,$P$6:$P$65,$P190)-SUMIFS($C$6:$C$185,$A$6:$A$185,$P190,$B$6:$B$185,"应收账款") -> 0 | R190: =IF(ROUND($Q190,2)=0,"√ 应收一致" ,"✗ 差 "&TEXT($Q190,"#,##0.00")) -> √ 应收一致 | S190: =SUMIFS($S$6:$S$65,$P$6:$P$65,$P190)-SUMIFS($D$6:$D$185,$A$6:$A$185,$P190,$B$6:$B$185,"应付账款") -> 0 | T190: =IF(ROUND($S190,2)=0,"√ 应付一致","✗ 差 "&TEXT($S190,"#,##0.00")) -> √ 应付一致
A192: 借贷平衡
A193: 农业 | B193: 借方合计 / 贷方合计 | C193: =SUMIFS($C$6:$C$185,$A$6:$A$185,$A193) -> 2335000 | D193: =SUMIFS($D$6:$D$185,$A$6:$A$185,$A193) -> 2335000 | E193: =IF(ROUND($C193-$D193,2)=0,"√ 借贷平衡","✗ 差 "&TEXT($C193-$D193,"#,##0.00")) -> √ 借贷平衡
A194: 木业 | B194: 借方合计 / 贷方合计 | C194: =SUMIFS($C$6:$C$185,$A$6:$A$185,$A194) -> 1585250 | D194: =SUMIFS($D$6:$D$185,$A$6:$A$185,$A194) -> 1585250 | E194: =IF(ROUND($C194-$D194,2)=0,"√ 借贷平衡","✗ 差 "&TEXT($C194-$D194,"#,##0.00")) -> √ 借贷平衡
A195: 科技 | B195: 借方合计 / 贷方合计 | C195: =SUMIFS($C$6:$C$185,$A$6:$A$185,$A195) -> 1098140 | D195: =SUMIFS($D$6:$D$185,$A$6:$A$185,$A195) -> 1098140 | E195: =IF(ROUND($C195-$D195,2)=0,"√ 借贷平衡","✗ 差 "&TEXT($C195-$D195,"#,##0.00")) -> √ 借贷平衡

Sheet 购销流水
A1: 购销流水（录入表 · 全部行都显示）
A2: 进货、卖货都在这一张表上，用「公司」列分开。**内账含税核算**：单价填实际成交的含税价，金额＝数量×单价，不拆进项销项，收入和成本都是含税数。这里只管货和票，一律挂应收/应付；收钱付钱到【资金流水】记一笔，账户余额和往来才对得上。退货用「销售退回 / 采购退回」，数量照正数填。向农户收购原木：往来单位选那个农户，发票类型选「收购发票」，单价就填收购价。
A5: 序号 | B5: 日期 | C5: 公司 | D5: 业务类型 | E5: 往来单位 | F5: 商品编码 | G5: 商品名称 | H5: 规格型号 | I5: 单位 | J5: 数量 | K5: 含税单价 | L5: 发票类型 | M5: 发票号码 | N5: 摘要 | O5: 备注 | P5: 校验 | Q5: 金额（含税） | R5: 结算科目 | S5: 存货科目 | T5: 收入科目 | U5: 成本科目 | V5: 成本单价 | W5: 成本金额 | X5: 内部 | Y5: 年度 | Z5: 所属月份
A6: =IF($B6="","",ROW()-5) -> 1 | B6: 46063 | C6: 农业 | D6: 采购入库 | E6: 县农资公司 | F6: NY05 | G6: =IF($F6="","",IFERROR(INDEX(商品档案!$B$6:$B$65,MATCH($F6,商品档案!$A$6:$A$65,0)),"")) -> 肥料 | H6: =IF($F6="","",IFERROR(INDEX(商品档案!$C$6:$C$65,MATCH($F6,商品档案!$A$6:$A$65,0)),"")) -> 复合肥 | I6: =IF($F6="","",IFERROR(INDEX(商品档案!$D$6:$D$65,MATCH($F6,商品档案!$A$6:$A$65,0)),"")) -> 吨 | J6: 8 | K6: 1150 | L6: 免税发票 | N6: 春季复合肥 | P6: =IF(AND($B6="",$D6="",$F6=""),"",IF(NOT(ISNUMBER($B6)),"日期无效",IF(ISNA(MATCH($C6,参数设置!$A$10:$A$12,0)),"公司无效",IF(ISNA(MATCH($D6,记账规则!$A$6:$A$9,0)),"业务类型无效",IF(ISNA(MATCH($F6,商品档案!$A$6:$A$65,0)),"商品编码无效",IF(IFERROR(INDEX(商品档案!$E$6:$E$65,MATCH($F6,商品档案!$A$6:$A$65,0)),"")<>$C6,"商品不属于该公司",IF(AND($E6<>"",ISNA(MATCH($E6,往来单位!$A$6:$A$85,0))),"往来单位未建档",IF(N($J6)=0,"数量为 0",IF(N($K6)=0,"单价为 0",IF(AND(LEFT($D6,2)="销售",$U6=""),"该商品没设成本科目",IF(YEAR($B6)<>参数设置!$B$5,"不在本会计年度","OK"))))))))))) -> OK | Q6: =IF($F6="","",ROUND(N($J6)*N($K6),2)) -> 9200 | R6: =IF($D6="","",IF(LEFT($D6,2)="销售","应收账款","应付账款")) -> 应付账款 | S6: =IF($F6="","",IFERROR(INDEX(商品档案!$G$6:$G$65,MATCH($F6,商品档案!$A$6:$A$65,0)),"")) -> 原材料 | T6: =IF($F6="","",IFERROR(INDEX(商品档案!$H$6:$H$65,MATCH($F6,商品档案!$A$6:$A$65,0)),"")) -> 0 | U6: =IF($F6="","",IFERROR(INDEX(商品档案!$I$6:$I$65,MATCH($F6,商品档案!$A$6:$A$65,0)),"")) -> 0 | V6: =IF($F6="","",SUMIFS(进销存台账!$N$6:$N$65,进销存台账!$A$6:$A$65,$C6,进销存台账!$B$6:$B$65,$F6)) -> 1122.2222 | W6: =IF(OR($D6="销售出库",$D6="销售退回"),ROUND(N($J6)*N($V6),2),0) -> 0 | X6: =IF($E6="","",IFERROR(INDEX(往来单位!$D$6:$D$85,MATCH($E6,往来单位!$A$6:$A$85,0)),"否")) -> 否 | Y6: =IF($B6="","",YEAR($B6)) -> 2026 | Z6: =IF($B6="","",TEXT($B6,"yyyy-mm")) -> 2026-02
A7: =IF($B7="","",ROW()-5) -> 2 | B7: 46086 | C7: 农业 | D7: 采购入库 | E7: 林业苗圃 | F7: NY04 | G7: =IF($F7="","",IFERROR(INDEX(商品档案!$B$6:$B$65,MATCH($F7,商品档案!$A$6:$A$65,0)),"")) -> 树苗 | H7: =IF($F7="","",IFERROR(INDEX(商品档案!$C$6:$C$65,MATCH($F7,商品档案!$A$6:$A$65,0)),"")) -> 杉木苗 | I7: =IF($F7="","",IFERROR(INDEX(商品档案!$D$6:$D$65,MATCH($F7,商品档案!$A$6:$A$65,0)),"")) -> 株 | J7: 3000 | K7: 2.6 | L7: 免税发票 | N7: 杉木苗 | P7: =IF(AND($B7="",$D7="",$F7=""),"",IF(NOT(ISNUMBER($B7)),"日期无效",IF(ISNA(MATCH($C7,参数设置!$A$10:$A$12,0)),"公司无效",IF(ISNA(MATCH($D7,记账规则!$A$6:$A$9,0)),"业务类型无效",IF(ISNA(MATCH($F7,商品档案!$A$6:$A$65,0)),"商品编码无效",IF(IFERROR(INDEX(商品档案!$E$6:$E$65,MATCH($F7,商品档案!$A$6:$A$65,0)),"")<>$C7,"商品不属于该公司",IF(AND($E7<>"",ISNA(MATCH($E7,往来单位!$A$6:$A$85,0))),"往来单位未建档",IF(N($J7)=0,"数量为 0",IF(N($K7)=0,"单价为 0",IF(AND(LEFT($D7,2)="销售",$U7=""),"该商品没设成本科目",IF(YEAR($B7)<>参数设置!$B$5,"不在本会计年度","OK"))))))))))) -> OK | Q7: =IF($F7="","",ROUND(N($J7)*N($K7),2)) -> 7800 | R7: =IF($D7="","",IF(LEFT($D7,2)="销售","应收账款","应付账款")) -> 应付账款 | S7: =IF($F7="","",IFERROR(INDEX(商品档案!$G$6:$G$65,MATCH($F7,商品档案!$A$6:$A$65,0)),"")) -> 原材料 | T7: =IF($F7="","",IFERROR(INDEX(商品档案!$H$6:$H$65,MATCH($F7,商品档案!$A$6:$A$65,0)),"")) -> 0 | U7: =IF($F7="","",IFERROR(INDEX(商品档案!$I$6:$I$65,MATCH($F7,商品档案!$A$6:$A$65,0)),"")) -> 0 | V7: =IF($F7="","",SUMIFS(进销存台账!$N$6:$N$65,进销存台账!$A$6:$A$65,$C7,进销存台账!$B$6:$B$65,$F7)) -> 2.6 | W7: =IF(OR($D7="销售出库",$D7="销售退回"),ROUND(N($J7)*N($V7),2),0) -> 0 | X7: =IF($E7="","",IFERROR(INDEX(往来单位!$D$6:$D$85,MATCH($E7,往来单位!$A$6:$A$85,0)),"否")) -> 否 | Y7: =IF($B7="","",YEAR($B7)) -> 2026 | Z7: =IF($B7="","",TEXT($B7,"yyyy-mm")) -> 2026-03
A8: =IF($B8="","",ROW()-5) -> 3 | B8: 46193 | C8: 农业 | D8: 销售出库 | E8: 木业公司 | F8: NY01 | G8: =IF($F8="","",IFERROR(INDEX(商品档案!$B$6:$B$65,MATCH($F8,商品档案!$A$6:$A$65,0)),"")) -> 原木 | H8: =IF($F8="","",IFERROR(INDEX(商品档案!$C$6:$C$65,MATCH($F8,商品档案!$A$6:$A$65,0)),"")) -> 杉木/松木 4m | I8: =IF($F8="","",IFERROR(INDEX(商品档案!$D$6:$D$65,MATCH($F8,商品档案!$A$6:$A$65,0)),"")) -> 立方米 | J8: 180 | K8: 1050 | L8: 免税发票 | M8: 0260001 | N8: 销售原木（内部交易） | P8: =IF(AND($B8="",$D8="",$F8=""),"",IF(NOT(ISNUMBER($B8)),"日期无效",IF(ISNA(MATCH($C8,参数设置!$A$10:$A$12,0)),"公司无效",IF(ISNA(MATCH($D8,记账规则!$A$6:$A$9,0)),"业务类型无效",IF(ISNA(MATCH($F8,商品档案!$A$6:$A$65,0)),"商品编码无效",IF(IFERROR(INDEX(商品档案!$E$6:$E$65,MATCH($F8,商品档案!$A$6:$A$65,0)),"")<>$C8,"商品不属于该公司",IF(AND($E8<>"",ISNA(MATCH($E8,往来单位!$A$6:$A$85,0))),"往来单位未建档",IF(N($J8)=0,"数量为 0",IF(N($K8)=0,"单价为 0",IF(AND(LEFT($D8,2)="销售",$U8=""),"该商品没设成本科目",IF(YEAR($B8)<>参数设置!$B$5,"不在本会计年度","OK"))))))))))) -> OK | Q8: =IF($F8="","",ROUND(N($J8)*N($K8),2)) -> 189000 | R8: =IF($D8="","",IF(LEFT($D8,2)="销售","应收账款","应付账款")) -> 应收账款 | S8: =IF($F8="","",IFERROR(INDEX(商品档案!$G$6:$G$65,MATCH($F8,商品档案!$A$6:$A$65,0)),"")) -> 库存商品 | T8: =IF($F8="","",IFERROR(INDEX(商品档案!$H$6:$H$65,MATCH($F8,商品档案!$A$6:$A$65,0)),"")) -> 主营业务收入 | U8: =IF($F8="","",IFERROR(INDEX(商品档案!$I$6:$I$65,MATCH($F8,商品档案!$A$6:$A$65,0)),"")) -> 主营业务成本 | V8: =IF($F8="","",SUMIFS(进销存台账!$N$6:$N$65,进销存台账!$A$6:$A$65,$C8,进销存台账!$B$6:$B$65,$F8)) -> 516.52778 | W8: =IF(OR($D8="销售出库",$D8="销售退回"),ROUND(N($J8)*N($V8),2),0) -> 92975 | X8: =IF($E8="","",IFERROR(INDEX(往来单位!$D$6:$D$85,MATCH($E8,往来单位!$A$6:$A$85,0)),"否")) -> 是 | Y8: =IF($B8="","",YEAR($B8)) -> 2026 | Z8: =IF($B8="","",TEXT($B8,"yyyy-mm")) -> 2026-06
A9: =IF($B9="","",ROW()-5) -> 4 | B9: 46218 | C9: 农业 | D9: 销售出库 | E9: 科技公司 | F9: NY03 | G9: =IF($F9="","",IFERROR(INDEX(商品档案!$B$6:$B$65,MATCH($F9,商品档案!$A$6:$A$65,0)),"")) -> 干艾草 | H9: =IF($F9="","",IFERROR(INDEX(商品档案!$C$6:$C$65,MATCH($F9,商品档案!$A$6:$A$65,0)),"")) -> 含水率≤12% | I9: =IF($F9="","",IFERROR(INDEX(商品档案!$D$6:$D$65,MATCH($F9,商品档案!$A$6:$A$65,0)),"")) -> 公斤 | J9: 4000 | K9: 14 | L9: 免税发票 | M9: 0260002 | N9: 销售干艾草（内部交易） | P9: =IF(AND($B9="",$D9="",$F9=""),"",IF(NOT(ISNUMBER($B9)),"日期无效",IF(ISNA(MATCH($C9,参数设置!$A$10:$A$12,0)),"公司无效",IF(ISNA(MATCH($D9,记账规则!$A$6:$A$9,0)),"业务类型无效",IF(ISNA(MATCH($F9,商品档案!$A$6:$A$65,0)),"商品编码无效",IF(IFERROR(INDEX(商品档案!$E$6:$E$65,MATCH($F9,商品档案!$A$6:$A$65,0)),"")<>$C9,"商品不属于该公司",IF(AND($E9<>"",ISNA(MATCH($E9,往来单位!$A$6:$A$85,0))),"往来单位未建档",IF(N($J9)=0,"数量为 0",IF(N($K9)=0,"单价为 0",IF(AND(LEFT($D9,2)="销售",$U9=""),"该商品没设成本科目",IF(YEAR($B9)<>参数设置!$B$5,"不在本会计年度","OK"))))))))))) -> OK | Q9: =IF($F9="","",ROUND(N($J9)*N($K9),2)) -> 56000 | R9: =IF($D9="","",IF(LEFT($D9,2)="销售","应收账款","应付账款")) -> 应收账款 | S9: =IF($F9="","",IFERROR(INDEX(商品档案!$G$6:$G$65,MATCH($F9,商品档案!$A$6:$A$65,0)),"")) -> 库存商品 | T9: =IF($F9="","",IFERROR(INDEX(商品档案!$H$6:$H$65,MATCH($F9,商品档案!$A$6:$A$65,0)),"")) -> 主营业务收入 | U9: =IF($F9="","",IFERROR(INDEX(商品档案!$I$6:$I$65,MATCH($F9,商品档案!$A$6:$A$65,0)),"")) -> 主营业务成本 | V9: =IF($F9="","",SUMIFS(进销存台账!$N$6:$N$65,进销存台账!$A$6:$A$65,$C9,进销存台账!$B$6:$B$65,$F9)) -> 10.377105 | W9: =IF(OR($D9="销售出库",$D9="销售退回"),ROUND(N($J9)*N($V9),2),0) -> 41508.42 | X9: =IF($E9="","",IFERROR(INDEX(往来单位!$D$6:$D$85,MATCH($E9,往来单位!$A$6:$A$85,0)),"否")) -> 是 | Y9: =IF($B9="","",YEAR($B9)) -> 2026 | Z9: =IF($B9="","",TEXT($B9,"yyyy-mm")) -> 2026-07
A10: =IF($B10="","",ROW()-5) -> 5 | B10: 46262 | C10: 农业 | D10: 销售出库 | E10: 恒信木材行 | F10: NY01 | G10: =IF($F10="","",IFERROR(INDEX(商品档案!$B$6:$B$65,MATCH($F10,商品档案!$A$6:$A$65,0)),"")) -> 原木 | H10: =IF($F10="","",IFERROR(INDEX(商品档案!$C$6:$C$65,MATCH($F10,商品档案!$A$6:$A$65,0)),"")) -> 杉木/松木 4m | I10: =IF($F10="","",IFERROR(INDEX(商品档案!$D$6:$D$65,MATCH($F10,商品档案!$A$6:$A$65,0)),"")) -> 立方米 | J10: 60 | K10: 1100 | L10: 免税发票 | M10: 0260003 | N10: 销售原木 | P10: =IF(AND($B10="",$D10="",$F10=""),"",IF(NOT(ISNUMBER($B10)),"日期无效",IF(ISNA(MATCH($C10,参数设置!$A$10:$A$12,0)),"公司无效",IF(ISNA(MATCH($D10,记账规则!$A$6:$A$9,0)),"业务类型无效",IF(ISNA(MATCH($F10,商品档案!$A$6:$A$65,0)),"商品编码无效",IF(IFERROR(INDEX(商品档案!$E$6:$E$65,MATCH($F10,商品档案!$A$6:$A$65,0)),"")<>$C10,"商品不属于该公司",IF(AND($E10<>"",ISNA(MATCH($E10,往来单位!$A$6:$A$85,0))),"往来单位未建档",IF(N($J10)=0,"数量为 0",IF(N($K10)=0,"单价为 0",IF(AND(LEFT($D10,2)="销售",$U10=""),"该商品没设成本科目",IF(YEAR($B10)<>参数设置!$B$5,"不在本会计年度","OK"))))))))))) -> OK | Q10: =IF($F10="","",ROUND(N($J10)*N($K10),2)) -> 66000 | R10: =IF($D10="","",IF(LEFT($D10,2)="销售","应收账款","应付账款")) -> 应收账款 | S10: =IF($F10="","",IFERROR(INDEX(商品档案!$G$6:$G$65,MATCH($F10,商品档案!$A$6:$A$65,0)),"")) -> 库存商品 | T10: =IF($F10="","",IFERROR(INDEX(商品档案!$H$6:$H$65,MATCH($F10,商品档案!$A$6:$A$65,0)),"")) -> 主营业务收入 | U10: =IF($F10="","",IFERROR(INDEX(商品档案!$I$6:$I$65,MATCH($F10,商品档案!$A$6:$A$65,0)),"")) -> 主营业务成本 | V10: =IF($F10="","",SUMIFS(进销存台账!$N$6:$N$65,进销存台账!$A$6:$A$65,$C10,进销存台账!$B$6:$B$65,$F10)) -> 516.52778 | W10: =IF(OR($D10="销售出库",$D10="销售退回"),ROUND(N($J10)*N($V10),2),0) -> 30991.67 | X10: =IF($E10="","",IFERROR(INDEX(往来单位!$D$6:$D$85,MATCH($E10,往来单位!$A$6:$A$85,0)),"否")) -> 否 | Y10: =IF($B10="","",YEAR($B10)) -> 2026 | Z10: =IF($B10="","",TEXT($B10,"yyyy-mm")) -> 2026-08
A11: =IF($B11="","",ROW()-5) -> 6 | B11: 46270 | C11: 农业 | D11: 销售出库 | E11: 安康艾制品厂 | F11: NY03 | G11: =IF($F11="","",IFERROR(INDEX(商品档案!$B$6:$B$65,MATCH($F11,商品档案!$A$6:$A$65,0)),"")) -> 干艾草 | H11: =IF($F11="","",IFERROR(INDEX(商品档案!$C$6:$C$65,MATCH($F11,商品档案!$A$6:$A$65,0)),"")) -> 含水率≤12% | I11: =IF($F11="","",IFERROR(INDEX(商品档案!$D$6:$D$65,MATCH($F11,商品档案!$A$6:$A$65,0)),"")) -> 公斤 | J11: 1200 | K11: 15 | L11: 免税发票 | M11: 0260004 | N11: 销售干艾草 | P11: =IF(AND($B11="",$D11="",$F11=""),"",IF(NOT(ISNUMBER($B11)),"日期无效",IF(ISNA(MATCH($C11,参数设置!$A$10:$A$12,0)),"公司无效",IF(ISNA(MATCH($D11,记账规则!$A$6:$A$9,0)),"业务类型无效",IF(ISNA(MATCH($F11,商品档案!$A$6:$A$65,0)),"商品编码无效",IF(IFERROR(INDEX(商品档案!$E$6:$E$65,MATCH($F11,商品档案!$A$6:$A$65,0)),"")<>$C11,"商品不属于该公司",IF(AND($E11<>"",ISNA(MATCH($E11,往来单位!$A$6:$A$85,0))),"往来单位未建档",IF(N($J11)=0,"数量为 0",IF(N($K11)=0,"单价为 0",IF(AND(LEFT($D11,2)="销售",$U11=""),"该商品没设成本科目",IF(YEAR($B11)<>参数设置!$B$5,"不在本会计年度","OK"))))))))))) -> OK | Q11: =IF($F11="","",ROUND(N($J11)*N($K11),2)) -> 18000 | R11: =IF($D11="","",IF(LEFT($D11,2)="销售","应收账款","应付账款")) -> 应收账款 | S11: =IF($F11="","",IFERROR(INDEX(商品档案!$G$6:$G$65,MATCH($F11,商品档案!$A$6:$A$65,0)),"")) -> 库存商品 | T11: =IF($F11="","",IFERROR(INDEX(商品档案!$H$6:$H$65,MATCH($F11,商品档案!$A$6:$A$65,0)),"")) -> 主营业务收入 | U11: =IF($F11="","",IFERROR(INDEX(商品档案!$I$6:$I$65,MATCH($F11,商品档案!$A$6:$A$65,0)),"")) -> 主营业务成本 | V11: =IF($F11="","",SUMIFS(进销存台账!$N$6:$N$65,进销存台账!$A$6:$A$65,$C11,进销存台账!$B$6:$B$65,$F11)) -> 10.377105 | W11: =IF(OR($D11="销售出库",$D11="销售退回"),ROUND(N($J11)*N($V11),2),0) -> 12452.53 | X11: =IF($E11="","",IFERROR(INDEX(往来单位!$D$6:$D$85,MATCH($E11,往来单位!$A$6:$A$85,0)),"否")) -> 否 | Y11: =IF($B11="","",YEAR($B11)) -> 2026 | Z11: =IF($B11="","",TEXT($B11,"yyyy-mm")) -> 2026-09
A12: =IF($B12="","",ROW()-5) -> 7 | B12: 46124 | C12: 木业 | D12: 采购入库 | E12: 华鑫化工 | F12: MY08 | G12: =IF($F12="","",IFERROR(INDEX(商品档案!$B$6:$B$65,MATCH($F12,商品档案!$A$6:$A$65,0)),"")) -> 胶水 | H12: =IF($F12="","",IFERROR(INDEX(商品档案!$C$6:$C$65,MATCH($F12,商品档案!$A$6:$A$65,0)),"")) -> 脲醛胶 | I12: =IF($F12="","",IFERROR(INDEX(商品档案!$D$6:$D$65,MATCH($F12,商品档案!$A$6:$A$65,0)),"")) -> 公斤 | J12: 600 | K12: 20 | L12: 专票 | M12: 04121880 | N12: 脲醛胶 | P12: =IF(AND($B12="",$D12="",$F12=""),"",IF(NOT(ISNUMBER($B12)),"日期无效",IF(ISNA(MATCH($C12,参数设置!$A$10:$A$12,0)),"公司无效",IF(ISNA(MATCH($D12,记账规则!$A$6:$A$9,0)),"业务类型无效",IF(ISNA(MATCH($F12,商品档案!$A$6:$A$65,0)),"商品编码无效",IF(IFERROR(INDEX(商品档案!$E$6:$E$65,MATCH($F12,商品档案!$A$6:$A$65,0)),"")<>$C12,"商品不属于该公司",IF(AND($E12<>"",ISNA(MATCH($E12,往来单位!$A$6:$A$85,0))),"往来单位未建档",IF(N($J12)=0,"数量为 0",IF(N($K12)=0,"单价为 0",IF(AND(LEFT($D12,2)="销售",$U12=""),"该商品没设成本科目",IF(YEAR($B12)<>参数设置!$B$5,"不在本会计年度","OK"))))))))))) -> OK | Q12: =IF($F12="","",ROUND(N($J12)*N($K12),2)) -> 12000 | R12: =IF($D12="","",IF(LEFT($D12,2)="销售","应收账款","应付账款")) -> 应付账款 | S12: =IF($F12="","",IFERROR(INDEX(商品档案!$G$6:$G$65,MATCH($F12,商品档案!$A$6:$A$65,0)),"")) -> 原材料 | T12: =IF($F12="","",IFERROR(INDEX(商品档案!$H$6:$H$65,MATCH($F12,商品档案!$A$6:$A$65,0)),"")) -> 0 | U12: =IF($F12="","",IFERROR(INDEX(商品档案!$I$6:$I$65,MATCH($F12,商品档案!$A$6:$A$65,0)),"")) -> 0 | V12: =IF($F12="","",SUMIFS(进销存台账!$N$6:$N$65,进销存台账!$A$6:$A$65,$C12,进销存台账!$B$6:$B$65,$F12)) -> 19.833333 | W12: =IF(OR($D12="销售出库",$D12="销售退回"),ROUND(N($J12)*N($V12),2),0) -> 0 | X12: =IF($E12="","",IFERROR(INDEX(往来单位!$D$6:$D$85,MATCH($E12,往来单位!$A$6:$A$85,0)),"否")) -> 否 | Y12: =IF($B12="","",YEAR($B12)) -> 2026 | Z12: =IF($B12="","",TEXT($B12,"yyyy-mm")) -> 2026-04
A13: =IF($B13="","",ROW()-5) -> 8 | B13: 46154 | C13: 木业 | D13: 采购入库 | E13: 张德富（农户） | F13: MY07 | G13: =IF($F13="","",IFERROR(INDEX(商品档案!$B$6:$B$65,MATCH($F13,商品档案!$A$6:$A$65,0)),"")) -> 原木 | H13: =IF($F13="","",IFERROR(INDEX(商品档案!$C$6:$C$65,MATCH($F13,商品档案!$A$6:$A$65,0)),"")) -> 外购/内购 4m | I13: =IF($F13="","",IFERROR(INDEX(商品档案!$D$6:$D$65,MATCH($F13,商品档案!$A$6:$A$65,0)),"")) -> 立方米 | J13: 60 | K13: 980 | L13: 收购发票 | M13: SG26001 | N13: 向农户收购原木 | P13: =IF(AND($B13="",$D13="",$F13=""),"",IF(NOT(ISNUMBER($B13)),"日期无效",IF(ISNA(MATCH($C13,参数设置!$A$10:$A$12,0)),"公司无效",IF(ISNA(MATCH($D13,记账规则!$A$6:$A$9,0)),"业务类型无效",IF(ISNA(MATCH($F13,商品档案!$A$6:$A$65,0)),"商品编码无效",IF(IFERROR(INDEX(商品档案!$E$6:$E$65,MATCH($F13,商品档案!$A$6:$A$65,0)),"")<>$C13,"商品不属于该公司",IF(AND($E13<>"",ISNA(MATCH($E13,往来单位!$A$6:$A$85,0))),"往来单位未建档",IF(N($J13)=0,"数量为 0",IF(N($K13)=0,"单价为 0",IF(AND(LEFT($D13,2)="销售",$U13=""),"该商品没设成本科目",IF(YEAR($B13)<>参数设置!$B$5,"不在本会计年度","OK"))))))))))) -> OK | Q13: =IF($F13="","",ROUND(N($J13)*N($K13),2)) -> 58800 | R13: =IF($D13="","",IF(LEFT($D13,2)="销售","应收账款","应付账款")) -> 应付账款 | S13: =IF($F13="","",IFERROR(INDEX(商品档案!$G$6:$G$65,MATCH($F13,商品档案!$A$6:$A$65,0)),"")) -> 原材料 | T13: =IF($F13="","",IFERROR(INDEX(商品档案!$H$6:$H$65,MATCH($F13,商品档案!$A$6:$A$65,0)),"")) -> 0 | U13: =IF($F13="","",IFERROR(INDEX(商品档案!$I$6:$I$65,MATCH($F13,商品档案!$A$6:$A$65,0)),"")) -> 0 | V13: =IF($F13="","",SUMIFS(进销存台账!$N$6:$N$65,进销存台账!$A$6:$A$65,$C13,进销存台账!$B$6:$B$65,$F13)) -> 1010.411 | W13: =IF(OR($D13="销售出库",$D13="销售退回"),ROUND(N($J13)*N($V13),2),0) -> 0 | X13: =IF($E13="","",IFERROR(INDEX(往来单位!$D$6:$D$85,MATCH($E13,往来单位!$A$6:$A$85,0)),"否")) -> 否 | Y13: =IF($B13="","",YEAR($B13)) -> 2026 | Z13: =IF($B13="","",TEXT($B13,"yyyy-mm")) -> 2026-05
A14: =IF($B14="","",ROW()-5) -> 9 | B14: 46193 | C14: 木业 | D14: 采购入库 | E14: 农业基地公司 | F14: MY07 | G14: =IF($F14="","",IFERROR(INDEX(商品档案!$B$6:$B$65,MATCH($F14,商品档案!$A$6:$A$65,0)),"")) -> 原木 | H14: =IF($F14="","",IFERROR(INDEX(商品档案!$C$6:$C$65,MATCH($F14,商品档案!$A$6:$A$65,0)),"")) -> 外购/内购 4m | I14: =IF($F14="","",IFERROR(INDEX(商品档案!$D$6:$D$65,MATCH($F14,商品档案!$A$6:$A$65,0)),"")) -> 立方米 | J14: 180 | K14: 1050 | L14: 收购发票 | M14: SG26002 | N14: 收购原木（内部交易） | P14: =IF(AND($B14="",$D14="",$F14=""),"",IF(NOT(ISNUMBER($B14)),"日期无效",IF(ISNA(MATCH($C14,参数设置!$A$10:$A$12,0)),"公司无效",IF(ISNA(MATCH($D14,记账规则!$A$6:$A$9,0)),"业务类型无效",IF(ISNA(MATCH($F14,商品档案!$A$6:$A$65,0)),"商品编码无效",IF(IFERROR(INDEX(商品档案!$E$6:$E$65,MATCH($F14,商品档案!$A$6:$A$65,0)),"")<>$C14,"商品不属于该公司",IF(AND($E14<>"",ISNA(MATCH($E14,往来单位!$A$6:$A$85,0))),"往来单位未建档",IF(N($J14)=0,"数量为 0",IF(N($K14)=0,"单价为 0",IF(AND(LEFT($D14,2)="销售",$U14=""),"该商品没设成本科目",IF(YEAR($B14)<>参数设置!$B$5,"不在本会计年度","OK"))))))))))) -> OK | Q14: =IF($F14="","",ROUND(N($J14)*N($K14),2)) -> 189000 | R14: =IF($D14="","",IF(LEFT($D14,2)="销售","应收账款","应付账款")) -> 应付账款 | S14: =IF($F14="","",IFERROR(INDEX(商品档案!$G$6:$G$65,MATCH($F14,商品档案!$A$6:$A$65,0)),"")) -> 原材料 | T14: =IF($F14="","",IFERROR(INDEX(商品档案!$H$6:$H$65,MATCH($F14,商品档案!$A$6:$A$65,0)),"")) -> 0 | U14: =IF($F14="","",IFERROR(INDEX(商品档案!$I$6:$I$65,MATCH($F14,商品档案!$A$6:$A$65,0)),"")) -> 0 | V14: =IF($F14="","",SUMIFS(进销存台账!$N$6:$N$65,进销存台账!$A$6:$A$65,$C14,进销存台账!$B$6:$B$65,$F14)) -> 1010.411 | W14: =IF(OR($D14="销售出库",$D14="销售退回"),ROUND(N($J14)*N($V14),2),0) -> 0 | X14: =IF($E14="","",IFERROR(INDEX(往来单位!$D$6:$D$85,MATCH($E14,往来单位!$A$6:$A$85,0)),"否")) -> 是 | Y14: =IF($B14="","",YEAR($B14)) -> 2026 | Z14: =IF($B14="","",TEXT($B14,"yyyy-mm")) -> 2026-06
A15: =IF($B15="","",ROW()-5) -> 10 | B15: 46252 | C15: 木业 | D15: 采购入库 | E15: 李长生（农户） | F15: MY07 | G15: =IF($F15="","",IFERROR(INDEX(商品档案!$B$6:$B$65,MATCH($F15,商品档案!$A$6:$A$65,0)),"")) -> 原木 | H15: =IF($F15="","",IFERROR(INDEX(商品档案!$C$6:$C$65,MATCH($F15,商品档案!$A$6:$A$65,0)),"")) -> 外购/内购 4m | I15: =IF($F15="","",IFERROR(INDEX(商品档案!$D$6:$D$65,MATCH($F15,商品档案!$A$6:$A$65,0)),"")) -> 立方米 | J15: 45 | K15: 1000 | L15: 收购发票 | M15: SG26003 | N15: 向农户收购原木 | P15: =IF(AND($B15="",$D15="",$F15=""),"",IF(NOT(ISNUMBER($B15)),"日期无效",IF(ISNA(MATCH($C15,参数设置!$A$10:$A$12,0)),"公司无效",IF(ISNA(MATCH($D15,记账规则!$A$6:$A$9,0)),"业务类型无效",IF(ISNA(MATCH($F15,商品档案!$A$6:$A$65,0)),"商品编码无效",IF(IFERROR(INDEX(商品档案!$E$6:$E$65,MATCH($F15,商品档案!$A$6:$A$65,0)),"")<>$C15,"商品不属于该公司",IF(AND($E15<>"",ISNA(MATCH($E15,往来单位!$A$6:$A$85,0))),"往来单位未建档",IF(N($J15)=0,"数量为 0",IF(N($K15)=0,"单价为 0",IF(AND(LEFT($D15,2)="销售",$U15=""),"该商品没设成本科目",IF(YEAR($B15)<>参数设置!$B$5,"不在本会计年度","OK"))))))))))) -> OK | Q15: =IF($F15="","",ROUND(N($J15)*N($K15),2)) -> 45000 | R15: =IF($D15="","",IF(LEFT($D15,2)="销售","应收账款","应付账款")) -> 应付账款 | S15: =IF($F15="","",IFERROR(INDEX(商品档案!$G$6:$G$65,MATCH($F15,商品档案!$A$6:$A$65,0)),"")) -> 原材料 | T15: =IF($F15="","",IFERROR(INDEX(商品档案!$H$6:$H$65,MATCH($F15,商品档案!$A$6:$A$65,0)),"")) -> 0 | U15: =IF($F15="","",IFERROR(INDEX(商品档案!$I$6:$I$65,MATCH($F15,商品档案!$A$6:$A$65,0)),"")) -> 0 | V15: =IF($F15="","",SUMIFS(进销存台账!$N$6:$N$65,进销存台账!$A$6:$A$65,$C15,进销存台账!$B$6:$B$65,$F15)) -> 1010.411 | W15: =IF(OR($D15="销售出库",$D15="销售退回"),ROUND(N($J15)*N($V15),2),0) -> 0 | X15: =IF($E15="","",IFERROR(INDEX(往来单位!$D$6:$D$85,MATCH($E15,往来单位!$A$6:$A$85,0)),"否")) -> 否 | Y15: =IF($B15="","",YEAR($B15)) -> 2026 | Z15: =IF($B15="","",TEXT($B15,"yyyy-mm")) -> 2026-08
A16: =IF($B16="","",ROW()-5) -> 11 | B16: 46211 | C16: 木业 | D16: 销售出库 | E16: 鑫隆建材 | F16: MY01 | G16: =IF($F16="","",IFERROR(INDEX(商品档案!$B$6:$B$65,MATCH($F16,商品档案!$A$6:$A$65,0)),"")) -> *木制品*木板 | H16: =IF($F16="","",IFERROR(INDEX(商品档案!$C$6:$C$65,MATCH($F16,商品档案!$A$6:$A$65,0)),"")) -> 1220×2440×18mm | I16: =IF($F16="","",IFERROR(INDEX(商品档案!$D$6:$D$65,MATCH($F16,商品档案!$A$6:$A$65,0)),"")) -> 张 | J16: 2200 | K16: 165 | L16: 专票 | M16: 07080231 | N16: 木板 | P16: =IF(AND($B16="",$D16="",$F16=""),"",IF(NOT(ISNUMBER($B16)),"日期无效",IF(ISNA(MATCH($C16,参数设置!$A$10:$A$12,0)),"公司无效",IF(ISNA(MATCH($D16,记账规则!$A$6:$A$9,0)),"业务类型无效",IF(ISNA(MATCH($F16,商品档案!$A$6:$A$65,0)),"商品编码无效",IF(IFERROR(INDEX(商品档案!$E$6:$E$65,MATCH($F16,商品档案!$A$6:$A$65,0)),"")<>$C16,"商品不属于该公司",IF(AND($E16<>"",ISNA(MATCH($E16,往来单位!$A$6:$A$85,0))),"往来单位未建档",IF(N($J16)=0,"数量为 0",IF(N($K16)=0,"单价为 0",IF(AND(LEFT($D16,2)="销售",$U16=""),"该商品没设成本科目",IF(YEAR($B16)<>参数设置!$B$5,"不在本会计年度","OK"))))))))))) -> OK | Q16: =IF($F16="","",ROUND(N($J16)*N($K16),2)) -> 363000 | R16: =IF($D16="","",IF(LEFT($D16,2)="销售","应收账款","应付账款")) -> 应收账款 | S16: =IF($F16="","",IFERROR(INDEX(商品档案!$G$6:$G$65,MATCH($F16,商品档案!$A$6:$A$65,0)),"")) -> 库存商品 | T16: =IF($F16="","",IFERROR(INDEX(商品档案!$H$6:$H$65,MATCH($F16,商品档案!$A$6:$A$65,0)),"")) -> 主营业务收入 | U16: =IF($F16="","",IFERROR(INDEX(商品档案!$I$6:$I$65,MATCH($F16,商品档案!$A$6:$A$65,0)),"")) -> 主营业务成本 | V16: =IF($F16="","",SUMIFS(进销存台账!$N$6:$N$65,进销存台账!$A$6:$A$65,$C16,进销存台账!$B$6:$B$65,$F16)) -> 99.249738 | W16: =IF(OR($D16="销售出库",$D16="销售退回"),ROUND(N($J16)*N($V16),2),0) -> 218349.42 | X16: =IF($E16="","",IFERROR(INDEX(往来单位!$D$6:$D$85,MATCH($E16,往来单位!$A$6:$A$85,0)),"否")) -> 否 | Y16: =IF($B16="","",YEAR($B16)) -> 2026 | Z16: =IF($B16="","",TEXT($B16,"yyyy-mm")) -> 2026-07
A17: =IF($B17="","",ROW()-5) -> 12 | B17: 46240 | C17: 木业 | D17: 销售出库 | E17: 中建八局项目部 | F17: MY02 | G17: =IF($F17="","",IFERROR(INDEX(商品档案!$B$6:$B$65,MATCH($F17,商品档案!$A$6:$A$65,0)),"")) -> *木制品*模板 | H17: =IF($F17="","",IFERROR(INDEX(商品档案!$C$6:$C$65,MATCH($F17,商品档案!$A$6:$A$65,0)),"")) -> 1220×2440×15mm | I17: =IF($F17="","",IFERROR(INDEX(商品档案!$D$6:$D$65,MATCH($F17,商品档案!$A$6:$A$65,0)),"")) -> 张 | J17: 700 | K17: 150 | L17: 专票 | M17: 08060477 | N17: 模板 | P17: =IF(AND($B17="",$D17="",$F17=""),"",IF(NOT(ISNUMBER($B17)),"日期无效",IF(ISNA(MATCH($C17,参数设置!$A$10:$A$12,0)),"公司无效",IF(ISNA(MATCH($D17,记账规则!$A$6:$A$9,0)),"业务类型无效",IF(ISNA(MATCH($F17,商品档案!$A$6:$A$65,0)),"商品编码无效",IF(IFERROR(INDEX(商品档案!$E$6:$E$65,MATCH($F17,商品档案!$A$6:$A$65,0)),"")<>$C17,"商品不属于该公司",IF(AND($E17<>"",ISNA(MATCH($E17,往来单位!$A$6:$A$85,0))),"往来单位未建档",IF(N($J17)=0,"数量为 0",IF(N($K17)=0,"单价为 0",IF(AND(LEFT($D17,2)="销售",$U17=""),"该商品没设成本科目",IF(YEAR($B17)<>参数设置!$B$5,"不在本会计年度","OK"))))))))))) -> OK | Q17: =IF($F17="","",ROUND(N($J17)*N($K17),2)) -> 105000 | R17: =IF($D17="","",IF(LEFT($D17,2)="销售","应收账款","应付账款")) -> 应收账款 | S17: =IF($F17="","",IFERROR(INDEX(商品档案!$G$6:$G$65,MATCH($F17,商品档案!$A$6:$A$65,0)),"")) -> 库存商品 | T17: =IF($F17="","",IFERROR(INDEX(商品档案!$H$6:$H$65,MATCH($F17,商品档案!$A$6:$A$65,0)),"")) -> 主营业务收入 | U17: =IF($F17="","",IFERROR(INDEX(商品档案!$I$6:$I$65,MATCH($F17,商品档案!$A$6:$A$65,0)),"")) -> 主营业务成本 | V17: =IF($F17="","",SUMIFS(进销存台账!$N$6:$N$65,进销存台账!$A$6:$A$65,$C17,进销存台账!$B$6:$B$65,$F17)) -> 94.520556 | W17: =IF(OR($D17="销售出库",$D17="销售退回"),ROUND(N($J17)*N($V17),2),0) -> 66164.39 | X17: =IF($E17="","",IFERROR(INDEX(往来单位!$D$6:$D$85,MATCH($E17,往来单位!$A$6:$A$85,0)),"否")) -> 否 | Y17: =IF($B17="","",YEAR($B17)) -> 2026 | Z17: =IF($B17="","",TEXT($B17,"yyyy-mm")) -> 2026-08
A18: =IF($B18="","",ROW()-5) -> 13 | B18: 46256 | C18: 木业 | D18: 销售出库 | E18: 顺达包装 | F18: MY05 | G18: =IF($F18="","",IFERROR(INDEX(商品档案!$B$6:$B$65,MATCH($F18,商品档案!$A$6:$A$65,0)),"")) -> *木制品*包装箱板材 | H18: =IF($F18="","",IFERROR(INDEX(商品档案!$C$6:$C$65,MATCH($F18,商品档案!$A$6:$A$65,0)),"")) -> 0 | I18: =IF($F18="","",IFERROR(INDEX(商品档案!$D$6:$D$65,MATCH($F18,商品档案!$A$6:$A$65,0)),"")) -> 立方米 | J18: 45 | K18: 2050 | L18: 专票 | M18: 08220512 | N18: 包装箱板材 | P18: =IF(AND($B18="",$D18="",$F18=""),"",IF(NOT(ISNUMBER($B18)),"日期无效",IF(ISNA(MATCH($C18,参数设置!$A$10:$A$12,0)),"公司无效",IF(ISNA(MATCH($D18,记账规则!$A$6:$A$9,0)),"业务类型无效",IF(ISNA(MATCH($F18,商品档案!$A$6:$A$65,0)),"商品编码无效",IF(IFERROR(INDEX(商品档案!$E$6:$E$65,MATCH($F18,商品档案!$A$6:$A$65,0)),"")<>$C18,"商品不属于该公司",IF(AND($E18<>"",ISNA(MATCH($E18,往来单位!$A$6:$A$85,0))),"往来单位未建档",IF(N($J18)=0,"数量为 0",IF(N($K18)=0,"单价为 0",IF(AND(LEFT($D18,2)="销售",$U18=""),"该商品没设成本科目",IF(YEAR($B18)<>参数设置!$B$5,"不在本会计年度","OK"))))))))))) -> OK | Q18: =IF($F18="","",ROUND(N($J18)*N($K18),2)) -> 92250 | R18: =IF($D18="","",IF(LEFT($D18,2)="销售","应收账款","应付账款")) -> 应收账款 | S18: =IF($F18="","",IFERROR(INDEX(商品档案!$G$6:$G$65,MATCH($F18,商品档案!$A$6:$A$65,0)),"")) -> 库存商品 | T18: =IF($F18="","",IFERROR(INDEX(商品档案!$H$6:$H$65,MATCH($F18,商品档案!$A$6:$A$65,0)),"")) -> 主营业务收入 | U18: =IF($F18="","",IFERROR(INDEX(商品档案!$I$6:$I$65,MATCH($F18,商品档案!$A$6:$A$65,0)),"")) -> 主营业务成本 | V18: =IF($F18="","",SUMIFS(进销存台账!$N$6:$N$65,进销存台账!$A$6:$A$65,$C18,进销存台账!$B$6:$B$65,$F18)) -> 1492.1804 | W18: =IF(OR($D18="销售出库",$D18="销售退回"),ROUND(N($J18)*N($V18),2),0) -> 67148.12 | X18: =IF($E18="","",IFERROR(INDEX(往来单位!$D$6:$D$85,MATCH($E18,往来单位!$A$6:$A$85,0)),"否")) -> 否 | Y18: =IF($B18="","",YEAR($B18)) -> 2026 | Z18: =IF($B18="","",TEXT($B18,"yyyy-mm")) -> 2026-08
A19: =IF($B19="","",ROW()-5) -> 14 | B19: 46268 | C19: 木业 | D19: 销售出库 | E19: 恒诚建筑 | F19: MY06 | G19: =IF($F19="","",IFERROR(INDEX(商品档案!$B$6:$B$65,MATCH($F19,商品档案!$A$6:$A$65,0)),"")) -> *林业产品*建筑木方料 | H19: =IF($F19="","",IFERROR(INDEX(商品档案!$C$6:$C$65,MATCH($F19,商品档案!$A$6:$A$65,0)),"")) -> 0 | I19: =IF($F19="","",IFERROR(INDEX(商品档案!$D$6:$D$65,MATCH($F19,商品档案!$A$6:$A$65,0)),"")) -> 立方米 | J19: 15 | K19: 1450 | L19: 专票 | M19: 09030688 | N19: 建筑木方料 | P19: =IF(AND($B19="",$D19="",$F19=""),"",IF(NOT(ISNUMBER($B19)),"日期无效",IF(ISNA(MATCH($C19,参数设置!$A$10:$A$12,0)),"公司无效",IF(ISNA(MATCH($D19,记账规则!$A$6:$A$9,0)),"业务类型无效",IF(ISNA(MATCH($F19,商品档案!$A$6:$A$65,0)),"商品编码无效",IF(IFERROR(INDEX(商品档案!$E$6:$E$65,MATCH($F19,商品档案!$A$6:$A$65,0)),"")<>$C19,"商品不属于该公司",IF(AND($E19<>"",ISNA(MATCH($E19,往来单位!$A$6:$A$85,0))),"往来单位未建档",IF(N($J19)=0,"数量为 0",IF(N($K19)=0,"单价为 0",IF(AND(LEFT($D19,2)="销售",$U19=""),"该商品没设成本科目",IF(YEAR($B19)<>参数设置!$B$5,"不在本会计年度","OK"))))))))))) -> OK | Q19: =IF($F19="","",ROUND(N($J19)*N($K19),2)) -> 21750 | R19: =IF($D19="","",IF(LEFT($D19,2)="销售","应收账款","应付账款")) -> 应收账款 | S19: =IF($F19="","",IFERROR(INDEX(商品档案!$G$6:$G$65,MATCH($F19,商品档案!$A$6:$A$65,0)),"")) -> 库存商品 | T19: =IF($F19="","",IFERROR(INDEX(商品档案!$H$6:$H$65,MATCH($F19,商品档案!$A$6:$A$65,0)),"")) -> 主营业务收入 | U19: =IF($F19="","",IFERROR(INDEX(商品档案!$I$6:$I$65,MATCH($F19,商品档案!$A$6:$A$65,0)),"")) -> 主营业务成本 | V19: =IF($F19="","",SUMIFS(进销存台账!$N$6:$N$65,进销存台账!$A$6:$A$65,$C19,进销存台账!$B$6:$B$65,$F19)) -> 957.808 | W19: =IF(OR($D19="销售出库",$D19="销售退回"),ROUND(N($J19)*N($V19),2),0) -> 14367.12 | X19: =IF($E19="","",IFERROR(INDEX(往来单位!$D$6:$D$85,MATCH($E19,往来单位!$A$6:$A$85,0)),"否")) -> 否 | Y19: =IF($B19="","",YEAR($B19)) -> 2026 | Z19: =IF($B19="","",TEXT($B19,"yyyy-mm")) -> 2026-09
... A25: =IF($B25="","",ROW()-5) -> 20 | B25: 46273 | C25: 科技 | D25: 销售出库 | E25: 康养电商 | F25: KJ05 | G25: =IF($F25="","",IFERROR(INDEX(商品档案!$B$6:$B$65,MATCH($F25,商品档案!$A$6:$A$65,0)),"")) -> 艾草精油皂 | H25: =IF($F25="","",IFERROR(INDEX(商品档案!$C$6:$C$65,MATCH($F25,商品档案!$A$6:$A$65,0)),"")) -> 100g/块 | I25: =IF($F25="","",IFERROR(INDEX(商品档案!$D$6:$D$65,MATCH($F25,商品档案!$A$6:$A$65,0)),"")) -> 块 | J25: 4500 | K25: 13.5 | L25: 专票 | M25: 09081290 | N25: 艾草精油皂 | P25: =IF(AND($B25="",$D25="",$F25=""),"",IF(NOT(ISNUMBER($B25)),"日期无效",IF(ISNA(MATCH($C25,参数设置!$A$10:$A$12,0)),"公司无效",IF(ISNA(MATCH($D25,记账规则!$A$6:$A$9,0)),"业务类型无效",IF(ISNA(MATCH($F25,商品档案!$A$6:$A$65,0)),"商品编码无效",IF(IFERROR(INDEX(商品档案!$E$6:$E$65,MATCH($F25,商品档案!$A$6:$A$65,0)),"")<>$C25,"商品不属于该公司",IF(AND($E25<>"",ISNA(MATCH($E25,往来单位!$A$6:$A$85,0))),"往来单位未建档",IF(N($J25)=0,"数量为 0",IF(N($K25)=0,"单价为 0",IF(AND(LEFT($D25,2)="销售",$U25=""),"该商品没设成本科目",IF(YEAR($B25)<>参数设置!$B$5,"不在本会计年度","OK"))))))))))) -> OK | Q25: =IF($F25="","",ROUND(N($J25)*N($K25),2)) -> 60750 | R25: =IF($D25="","",IF(LEFT($D25,2)="销售","应收账款","应付账款")) -> 应收账款 | S25: =IF($F25="","",IFERROR(INDEX(商品档案!$G$6:$G$65,MATCH($F25,商品档案!$A$6:$A$65,0)),"")) -> 库存商品 | T25: =IF($F25="","",IFERROR(INDEX(商品档案!$H$6:$H$65,MATCH($F25,商品档案!$A$6:$A$65,0)),"")) -> 主营业务收入 | U25: =IF($F25="","",IFERROR(INDEX(商品档案!$I$6:$I$65,MATCH($F25,商品档案!$A$6:$A$65,0)),"")) -> 主营业务成本 | V25: =IF($F25="","",SUMIFS(进销存台账!$N$6:$N$65,进销存台账!$A$6:$A$65,$C25,进销存台账!$B$6:$B$65,$F25)) -> 4.725936 | W25: =IF(OR($D25="销售出库",$D25="销售退回"),ROUND(N($J25)*N($V25),2),0) -> 21266.71 | X25: =IF($E25="","",IFERROR(INDEX(往来单位!$D$6:$D$85,MATCH($E25,往来单位!$A$6:$A$85,0)),"否")) -> 否 | Y25: =IF($B25="","",YEAR($B25)) -> 2026 | Z25: =IF($B25="","",TEXT($B25,"yyyy-mm")) -> 2026-09
A26: =IF($B26="","",ROW()-5) | G26: =IF($F26="","",IFERROR(INDEX(商品档案!$B$6:$B$65,MATCH($F26,商品档案!$A$6:$A$65,0)),"")) | H26: =IF($F26="","",IFERROR(INDEX(商品档案!$C$6:$C$65,MATCH($F26,商品档案!$A$6:$A$65,0)),"")) | I26: =IF($F26="","",IFERROR(INDEX(商品档案!$D$6:$D$65,MATCH($F26,商品档案!$A$6:$A$65,0)),"")) | P26: =IF(AND($B26="",$D26="",$F26=""),"",IF(NOT(ISNUMBER($B26)),"日期无效",IF(ISNA(MATCH($C26,参数设置!$A$10:$A$12,0)),"公司无效",IF(ISNA(MATCH($D26,记账规则!$A$6:$A$9,0)),"业务类型无效",IF(ISNA(MATCH($F26,商品档案!$A$6:$A$65,0)),"商品编码无效",IF(IFERROR(INDEX(商品档案!$E$6:$E$65,MATCH($F26,商品档案!$A$6:$A$65,0)),"")<>$C26,"商品不属于该公司",IF(AND($E26<>"",ISNA(MATCH($E26,往来单位!$A$6:$A$85,0))),"往来单位未建档",IF(N($J26)=0,"数量为 0",IF(N($K26)=0,"单价为 0",IF(AND(LEFT($D26,2)="销售",$U26=""),"该商品没设成本科目",IF(YEAR($B26)<>参数设置!$B$5,"不在本会计年度","OK"))))))))))) | Q26: =IF($F26="","",ROUND(N($J26)*N($K26),2)) | R26: =IF($D26="","",IF(LEFT($D26,2)="销售","应收账款","应付账款")) | S26: =IF($F26="","",IFERROR(INDEX(商品档案!$G$6:$G$65,MATCH($F26,商品档案!$A$6:$A$65,0)),"")) | T26: =IF($F26="","",IFERROR(INDEX(商品档案!$H$6:$H$65,MATCH($F26,商品档案!$A$6:$A$65,0)),"")) | U26: =IF($F26="","",IFERROR(INDEX(商品档案!$I$6:$I$65,MATCH($F26,商品档案!$A$6:$A$65,0)),"")) | V26: =IF($F26="","",SUMIFS(进销存台账!$N$6:$N$65,进销存台账!$A$6:$A$65,$C26,进销存台账!$B$6:$B$65,$F26)) | W26: =IF(OR($D26="销售出库",$D26="销售退回"),ROUND(N($J26)*N($V26),2),0) -> 0 | X26: =IF($E26="","",IFERROR(INDEX(往来单位!$D$6:$D$85,MATCH($E26,往来单位!$A$6:$A$85,0)),"否")) | Y26: =IF($B26="","",YEAR($B26)) | Z26: =IF($B26="","",TEXT($B26,"yyyy-mm"))
A27: =IF($B27="","",ROW()-5) | G27: =IF($F27="","",IFERROR(INDEX(商品档案!$B$6:$B$65,MATCH($F27,商品档案!$A$6:$A$65,0)),"")) | H27: =IF($F27="","",IFERROR(INDEX(商品档案!$C$6:$C$65,MATCH($F27,商品档案!$A$6:$A$65,0)),"")) | I27: =IF($F27="","",IFERROR(INDEX(商品档案!$D$6:$D$65,MATCH($F27,商品档案!$A$6:$A$65,0)),"")) | P27: =IF(AND($B27="",$D27="",$F27=""),"",IF(NOT(ISNUMBER($B27)),"日期无效",IF(ISNA(MATCH($C27,参数设置!$A$10:$A$12,0)),"公司无效",IF(ISNA(MATCH($D27,记账规则!$A$6:$A$9,0)),"业务类型无效",IF(ISNA(MATCH($F27,商品档案!$A$6:$A$65,0)),"商品编码无效",IF(IFERROR(INDEX(商品档案!$E$6:$E$65,MATCH($F27,商品档案!$A$6:$A$65,0)),"")<>$C27,"商品不属于该公司",IF(AND($E27<>"",ISNA(MATCH($E27,往来单位!$A$6:$A$85,0))),"往来单位未建档",IF(N($J27)=0,"数量为 0",IF(N($K27)=0,"单价为 0",IF(AND(LEFT($D27,2)="销售",$U27=""),"该商品没设成本科目",IF(YEAR($B27)<>参数设置!$B$5,"不在本会计年度","OK"))))))))))) | Q27: =IF($F27="","",ROUND(N($J27)*N($K27),2)) | R27: =IF($D27="","",IF(LEFT($D27,2)="销售","应收账款","应付账款")) | S27: =IF($F27="","",IFERROR(INDEX(商品档案!$G$6:$G$65,MATCH($F27,商品档案!$A$6:$A$65,0)),"")) | T27: =IF($F27="","",IFERROR(INDEX(商品档案!$H$6:$H$65,MATCH($F27,商品档案!$A$6:$A$65,0)),"")) | U27: =IF($F27="","",IFERROR(INDEX(商品档案!$I$6:$I$65,MATCH($F27,商品档案!$A$6:$A$65,0)),"")) | V27: =IF($F27="","",SUMIFS(进销存台账!$N$6:$N$65,进销存台账!$A$6:$A$65,$C27,进销存台账!$B$6:$B$65,$F27)) | W27: =IF(OR($D27="销售出库",$D27="销售退回"),ROUND(N($J27)*N($V27),2),0) -> 0 | X27: =IF($E27="","",IFERROR(INDEX(往来单位!$D$6:$D$85,MATCH($E27,往来单位!$A$6:$A$85,0)),"否")) | Y27: =IF($B27="","",YEAR($B27)) | Z27: =IF($B27="","",TEXT($B27,"yyyy-mm"))
A28: =IF($B28="","",ROW()-5) | G28: =IF($F28="","",IFERROR(INDEX(商品档案!$B$6:$B$65,MATCH($F28,商品档案!$A$6:$A$65,0)),"")) | H28: =IF($F28="","",IFERROR(INDEX(商品档案!$C$6:$C$65,MATCH($F28,商品档案!$A$6:$A$65,0)),"")) | I28: =IF($F28="","",IFERROR(INDEX(商品档案!$D$6:$D$65,MATCH($F28,商品档案!$A$6:$A$65,0)),"")) | P28: =IF(AND($B28="",$D28="",$F28=""),"",IF(NOT(ISNUMBER($B28)),"日期无效",IF(ISNA(MATCH($C28,参数设置!$A$10:$A$12,0)),"公司无效",IF(ISNA(MATCH($D28,记账规则!$A$6:$A$9,0)),"业务类型无效",IF(ISNA(MATCH($F28,商品档案!$A$6:$A$65,0)),"商品编码无效",IF(IFERROR(INDEX(商品档案!$E$6:$E$65,MATCH($F28,商品档案!$A$6:$A$65,0)),"")<>$C28,"商品不属于该公司",IF(AND($E28<>"",ISNA(MATCH($E28,往来单位!$A$6:$A$85,0))),"往来单位未建档",IF(N($J28)=0,"数量为 0",IF(N($K28)=0,"单价为 0",IF(AND(LEFT($D28,2)="销售",$U28=""),"该商品没设成本科目",IF(YEAR($B28)<>参数设置!$B$5,"不在本会计年度","OK"))))))))))) | Q28: =IF($F28="","",ROUND(N($J28)*N($K28),2)) | R28: =IF($D28="","",IF(LEFT($D28,2)="销售","应收账款","应付账款")) | S28: =IF($F28="","",IFERROR(INDEX(商品档案!$G$6:$G$65,MATCH($F28,商品档案!$A$6:$A$65,0)),"")) | T28: =IF($F28="","",IFERROR(INDEX(商品档案!$H$6:$H$65,MATCH($F28,商品档案!$A$6:$A$65,0)),"")) | U28: =IF($F28="","",IFERROR(INDEX(商品档案!$I$6:$I$65,MATCH($F28,商品档案!$A$6:$A$65,0)),"")) | V28: =IF($F28="","",SUMIFS(进销存台账!$N$6:$N$65,进销存台账!$A$6:$A$65,$C28,进销存台账!$B$6:$B$65,$F28)) | W28: =IF(OR($D28="销售出库",$D28="销售退回"),ROUND(N($J28)*N($V28),2),0) -> 0 | X28: =IF($E28="","",IFERROR(INDEX(往来单位!$D$6:$D$85,MATCH($E28,往来单位!$A$6:$A$85,0)),"否")) | Y28: =IF($B28="","",YEAR($B28)) | Z28: =IF($B28="","",TEXT($B28,"yyyy-mm"))
A29: =IF($B29="","",ROW()-5) | G29: =IF($F29="","",IFERROR(INDEX(商品档案!$B$6:$B$65,MATCH($F29,商品档案!$A$6:$A$65,0)),"")) | H29: =IF($F29="","",IFERROR(INDEX(商品档案!$C$6:$C$65,MATCH($F29,商品档案!$A$6:$A$65,0)),"")) | I29: =IF($F29="","",IFERROR(INDEX(商品档案!$D$6:$D$65,MATCH($F29,商品档案!$A$6:$A$65,0)),"")) | P29: =IF(AND($B29="",$D29="",$F29=""),"",IF(NOT(ISNUMBER($B29)),"日期无效",IF(ISNA(MATCH($C29,参数设置!$A$10:$A$12,0)),"公司无效",IF(ISNA(MATCH($D29,记账规则!$A$6:$A$9,0)),"业务类型无效",IF(ISNA(MATCH($F29,商品档案!$A$6:$A$65,0)),"商品编码无效",IF(IFERROR(INDEX(商品档案!$E$6:$E$65,MATCH($F29,商品档案!$A$6:$A$65,0)),"")<>$C29,"商品不属于该公司",IF(AND($E29<>"",ISNA(MATCH($E29,往来单位!$A$6:$A$85,0))),"往来单位未建档",IF(N($J29)=0,"数量为 0",IF(N($K29)=0,"单价为 0",IF(AND(LEFT($D29,2)="销售",$U29=""),"该商品没设成本科目",IF(YEAR($B29)<>参数设置!$B$5,"不在本会计年度","OK"))))))))))) | Q29: =IF($F29="","",ROUND(N($J29)*N($K29),2)) | R29: =IF($D29="","",IF(LEFT($D29,2)="销售","应收账款","应付账款")) | S29: =IF($F29="","",IFERROR(INDEX(商品档案!$G$6:$G$65,MATCH($F29,商品档案!$A$6:$A$65,0)),"")) | T29: =IF($F29="","",IFERROR(INDEX(商品档案!$H$6:$H$65,MATCH($F29,商品档案!$A$6:$A$65,0)),"")) | U29: =IF($F29="","",IFERROR(INDEX(商品档案!$I$6:$I$65,MATCH($F29,商品档案!$A$6:$A$65,0)),"")) | V29: =IF($F29="","",SUMIFS(进销存台账!$N$6:$N$65,进销存台账!$A$6:$A$65,$C29,进销存台账!$B$6:$B$65,$F29)) | W29: =IF(OR($D29="销售出库",$D29="销售退回"),ROUND(N($J29)*N($V29),2),0) -> 0 | X29: =IF($E29="","",IFERROR(INDEX(往来单位!$D$6:$D$85,MATCH($E29,往来单位!$A$6:$A$85,0)),"否")) | Y29: =IF($B29="","",YEAR($B29)) | Z29: =IF($B29="","",TEXT($B29,"yyyy-mm"))
A30: =IF($B30="","",ROW()-5) | G30: =IF($F30="","",IFERROR(INDEX(商品档案!$B$6:$B$65,MATCH($F30,商品档案!$A$6:$A$65,0)),"")) | H30: =IF($F30="","",IFERROR(INDEX(商品档案!$C$6:$C$65,MATCH($F30,商品档案!$A$6:$A$65,0)),"")) | I30: =IF($F30="","",IFERROR(INDEX(商品档案!$D$6:$D$65,MATCH($F30,商品档案!$A$6:$A$65,0)),"")) | P30: =IF(AND($B30="",$D30="",$F30=""),"",IF(NOT(ISNUMBER($B30)),"日期无效",IF(ISNA(MATCH($C30,参数设置!$A$10:$A$12,0)),"公司无效",IF(ISNA(MATCH($D30,记账规则!$A$6:$A$9,0)),"业务类型无效",IF(ISNA(MATCH($F30,商品档案!$A$6:$A$65,0)),"商品编码无效",IF(IFERROR(INDEX(商品档案!$E$6:$E$65,MATCH($F30,商品档案!$A$6:$A$65,0)),"")<>$C30,"商品不属于该公司",IF(AND($E30<>"",ISNA(MATCH($E30,往来单位!$A$6:$A$85,0))),"往来单位未建档",IF(N($J30)=0,"数量为 0",IF(N($K30)=0,"单价为 0",IF(AND(LEFT($D30,2)="销售",$U30=""),"该商品没设成本科目",IF(YEAR($B30)<>参数设置!$B$5,"不在本会计年度","OK"))))))))))) | Q30: =IF($F30="","",ROUND(N($J30)*N($K30),2)) | R30: =IF($D30="","",IF(LEFT($D30,2)="销售","应收账款","应付账款")) | S30: =IF($F30="","",IFERROR(INDEX(商品档案!$G$6:$G$65,MATCH($F30,商品档案!$A$6:$A$65,0)),"")) | T30: =IF($F30="","",IFERROR(INDEX(商品档案!$H$6:$H$65,MATCH($F30,商品档案!$A$6:$A$65,0)),"")) | U30: =IF($F30="","",IFERROR(INDEX(商品档案!$I$6:$I$65,MATCH($F30,商品档案!$A$6:$A$65,0)),"")) | V30: =IF($F30="","",SUMIFS(进销存台账!$N$6:$N$65,进销存台账!$A$6:$A$65,$C30,进销存台账!$B$6:$B$65,$F30)) | W30: =IF(OR($D30="销售出库",$D30="销售退回"),ROUND(N($J30)*N($V30),2),0) -> 0 | X30: =IF($E30="","",IFERROR(INDEX(往来单位!$D$6:$D$85,MATCH($E30,往来单位!$A$6:$A$85,0)),"否")) | Y30: =IF($B30="","",YEAR($B30)) | Z30: =IF($B30="","",TEXT($B30,"yyyy-mm"))
A31: =IF($B31="","",ROW()-5) | G31: =IF($F31="","",IFERROR(INDEX(商品档案!$B$6:$B$65,MATCH($F31,商品档案!$A$6:$A$65,0)),"")) | H31: =IF($F31="","",IFERROR(INDEX(商品档案!$C$6:$C$65,MATCH($F31,商品档案!$A$6:$A$65,0)),"")) | I31: =IF($F31="","",IFERROR(INDEX(商品档案!$D$6:$D$65,MATCH($F31,商品档案!$A$6:$A$65,0)),"")) | P31: =IF(AND($B31="",$D31="",$F31=""),"",IF(NOT(ISNUMBER($B31)),"日期无效",IF(ISNA(MATCH($C31,参数设置!$A$10:$A$12,0)),"公司无效",IF(ISNA(MATCH($D31,记账规则!$A$6:$A$9,0)),"业务类型无效",IF(ISNA(MATCH($F31,商品档案!$A$6:$A$65,0)),"商品编码无效",IF(IFERROR(INDEX(商品档案!$E$6:$E$65,MATCH($F31,商品档案!$A$6:$A$65,0)),"")<>$C31,"商品不属于该公司",IF(AND($E31<>"",ISNA(MATCH($E31,往来单位!$A$6:$A$85,0))),"往来单位未建档",IF(N($J31)=0,"数量为 0",IF(N($K31)=0,"单价为 0",IF(AND(LEFT($D31,2)="销售",$U31=""),"该商品没设成本科目",IF(YEAR($B31)<>参数设置!$B$5,"不在本会计年度","OK"))))))))))) | Q31: =IF($F31="","",ROUND(N($J31)*N($K31),2)) | R31: =IF($D31="","",IF(LEFT($D31,2)="销售","应收账款","应付账款")) | S31: =IF($F31="","",IFERROR(INDEX(商品档案!$G$6:$G$65,MATCH($F31,商品档案!$A$6:$A$65,0)),"")) | T31: =IF($F31="","",IFERROR(INDEX(商品档案!$H$6:$H$65,MATCH($F31,商品档案!$A$6:$A$65,0)),"")) | U31: =IF($F31="","",IFERROR(INDEX(商品档案!$I$6:$I$65,MATCH($F31,商品档案!$A$6:$A$65,0)),"")) | V31: =IF($F31="","",SUMIFS(进销存台账!$N$6:$N$65,进销存台账!$A$6:$A$65,$C31,进销存台账!$B$6:$B$65,$F31)) | W31: =IF(OR($D31="销售出库",$D31="销售退回"),ROUND(N($J31)*N($V31),2),0) -> 0 | X31: =IF($E31="","",IFERROR(INDEX(往来单位!$D$6:$D$85,MATCH($E31,往来单位!$A$6:$A$85,0)),"否")) | Y31: =IF($B31="","",YEAR($B31)) | Z31: =IF($B31="","",TEXT($B31,"yyyy-mm"))
A32: =IF($B32="","",ROW()-5) | G32: =IF($F32="","",IFERROR(INDEX(商品档案!$B$6:$B$65,MATCH($F32,商品档案!$A$6:$A$65,0)),"")) | H32: =IF($F32="","",IFERROR(INDEX(商品档案!$C$6:$C$65,MATCH($F32,商品档案!$A$6:$A$65,0)),"")) | I32: =IF($F32="","",IFERROR(INDEX(商品档案!$D$6:$D$65,MATCH($F32,商品档案!$A$6:$A$65,0)),"")) | P32: =IF(AND($B32="",$D32="",$F32=""),"",IF(NOT(ISNUMBER($B32)),"日期无效",IF(ISNA(MATCH($C32,参数设置!$A$10:$A$12,0)),"公司无效",IF(ISNA(MATCH($D32,记账规则!$A$6:$A$9,0)),"业务类型无效",IF(ISNA(MATCH($F32,商品档案!$A$6:$A$65,0)),"商品编码无效",IF(IFERROR(INDEX(商品档案!$E$6:$E$65,MATCH($F32,商品档案!$A$6:$A$65,0)),"")<>$C32,"商品不属于该公司",IF(AND($E32<>"",ISNA(MATCH($E32,往来单位!$A$6:$A$85,0))),"往来单位未建档",IF(N($J32)=0,"数量为 0",IF(N($K32)=0,"单价为 0",IF(AND(LEFT($D32,2)="销售",$U32=""),"该商品没设成本科目",IF(YEAR($B32)<>参数设置!$B$5,"不在本会计年度","OK"))))))))))) | Q32: =IF($F32="","",ROUND(N($J32)*N($K32),2)) | R32: =IF($D32="","",IF(LEFT($D32,2)="销售","应收账款","应付账款")) | S32: =IF($F32="","",IFERROR(INDEX(商品档案!$G$6:$G$65,MATCH($F32,商品档案!$A$6:$A$65,0)),"")) | T32: =IF($F32="","",IFERROR(INDEX(商品档案!$H$6:$H$65,MATCH($F32,商品档案!$A$6:$A$65,0)),"")) | U32: =IF($F32="","",IFERROR(INDEX(商品档案!$I$6:$I$65,MATCH($F32,商品档案!$A$6:$A$65,0)),"")) | V32: =IF($F32="","",SUMIFS(进销存台账!$N$6:$N$65,进销存台账!$A$6:$A$65,$C32,进销存台账!$B$6:$B$65,$F32)) | W32: =IF(OR($D32="销售出库",$D32="销售退回"),ROUND(N($J32)*N($V32),2),0) -> 0 | X32: =IF($E32="","",IFERROR(INDEX(往来单位!$D$6:$D$85,MATCH($E32,往来单位!$A$6:$A$85,0)),"否")) | Y32: =IF($B32="","",YEAR($B32)) | Z32: =IF($B32="","",TEXT($B32,"yyyy-mm"))
A33: =IF($B33="","",ROW()-5) | G33: =IF($F33="","",IFERROR(INDEX(商品档案!$B$6:$B$65,MATCH($F33,商品档案!$A$6:$A$65,0)),"")) | H33: =IF($F33="","",IFERROR(INDEX(商品档案!$C$6:$C$65,MATCH($F33,商品档案!$A$6:$A$65,0)),"")) | I33: =IF($F33="","",IFERROR(INDEX(商品档案!$D$6:$D$65,MATCH($F33,商品档案!$A$6:$A$65,0)),"")) | P33: =IF(AND($B33="",$D33="",$F33=""),"",IF(NOT(ISNUMBER($B33)),"日期无效",IF(ISNA(MATCH($C33,参数设置!$A$10:$A$12,0)),"公司无效",IF(ISNA(MATCH($D33,记账规则!$A$6:$A$9,0)),"业务类型无效",IF(ISNA(MATCH($F33,商品档案!$A$6:$A$65,0)),"商品编码无效",IF(IFERROR(INDEX(商品档案!$E$6:$E$65,MATCH($F33,商品档案!$A$6:$A$65,0)),"")<>$C33,"商品不属于该公司",IF(AND($E33<>"",ISNA(MATCH($E33,往来单位!$A$6:$A$85,0))),"往来单位未建档",IF(N($J33)=0,"数量为 0",IF(N($K33)=0,"单价为 0",IF(AND(LEFT($D33,2)="销售",$U33=""),"该商品没设成本科目",IF(YEAR($B33)<>参数设置!$B$5,"不在本会计年度","OK"))))))))))) | Q33: =IF($F33="","",ROUND(N($J33)*N($K33),2)) | R33: =IF($D33="","",IF(LEFT($D33,2)="销售","应收账款","应付账款")) | S33: =IF($F33="","",IFERROR(INDEX(商品档案!$G$6:$G$65,MATCH($F33,商品档案!$A$6:$A$65,0)),"")) | T33: =IF($F33="","",IFERROR(INDEX(商品档案!$H$6:$H$65,MATCH($F33,商品档案!$A$6:$A$65,0)),"")) | U33: =IF($F33="","",IFERROR(INDEX(商品档案!$I$6:$I$65,MATCH($F33,商品档案!$A$6:$A$65,0)),"")) | V33: =IF($F33="","",SUMIFS(进销存台账!$N$6:$N$65,进销存台账!$A$6:$A$65,$C33,进销存台账!$B$6:$B$65,$F33)) | W33: =IF(OR($D33="销售出库",$D33="销售退回"),ROUND(N($J33)*N($V33),2),0) -> 0 | X33: =IF($E33="","",IFERROR(INDEX(往来单位!$D$6:$D$85,MATCH($E33,往来单位!$A$6:$A$85,0)),"否")) | Y33: =IF($B33="","",YEAR($B33)) | Z33: =IF($B33="","",TEXT($B33,"yyyy-mm"))
A34: =IF($B34="","",ROW()-5) | G34: =IF($F34="","",IFERROR(INDEX(商品档案!$B$6:$B$65,MATCH($F34,商品档案!$A$6:$A$65,0)),"")) | H34: =IF($F34="","",IFERROR(INDEX(商品档案!$C$6:$C$65,MATCH($F34,商品档案!$A$6:$A$65,0)),"")) | I34: =IF($F34="","",IFERROR(INDEX(商品档案!$D$6:$D$65,MATCH($F34,商品档案!$A$6:$A$65,0)),"")) | P34: =IF(AND($B34="",$D34="",$F34=""),"",IF(NOT(ISNUMBER($B34)),"日期无效",IF(ISNA(MATCH($C34,参数设置!$A$10:$A$12,0)),"公司无效",IF(ISNA(MATCH($D34,记账规则!$A$6:$A$9,0)),"业务类型无效",IF(ISNA(MATCH($F34,商品档案!$A$6:$A$65,0)),"商品编码无效",IF(IFERROR(INDEX(商品档案!$E$6:$E$65,MATCH($F34,商品档案!$A$6:$A$65,0)),"")<>$C34,"商品不属于该公司",IF(AND($E34<>"",ISNA(MATCH($E34,往来单位!$A$6:$A$85,0))),"往来单位未建档",IF(N($J34)=0,"数量为 0",IF(N($K34)=0,"单价为 0",IF(AND(LEFT($D34,2)="销售",$U34=""),"该商品没设成本科目",IF(YEAR($B34)<>参数设置!$B$5,"不在本会计年度","OK"))))))))))) | Q34: =IF($F34="","",ROUND(N($J34)*N($K34),2)) | R34: =IF($D34="","",IF(LEFT($D34,2)="销售","应收账款","应付账款")) | S34: =IF($F34="","",IFERROR(INDEX(商品档案!$G$6:$G$65,MATCH($F34,商品档案!$A$6:$A$65,0)),"")) | T34: =IF($F34="","",IFERROR(INDEX(商品档案!$H$6:$H$65,MATCH($F34,商品档案!$A$6:$A$65,0)),"")) | U34: =IF($F34="","",IFERROR(INDEX(商品档案!$I$6:$I$65,MATCH($F34,商品档案!$A$6:$A$65,0)),"")) | V34: =IF($F34="","",SUMIFS(进销存台账!$N$6:$N$65,进销存台账!$A$6:$A$65,$C34,进销存台账!$B$6:$B$65,$F34)) | W34: =IF(OR($D34="销售出库",$D34="销售退回"),ROUND(N($J34)*N($V34),2),0) -> 0 | X34: =IF($E34="","",IFERROR(INDEX(往来单位!$D$6:$D$85,MATCH($E34,往来单位!$A$6:$A$85,0)),"否")) | Y34: =IF($B34="","",YEAR($B34)) | Z34: =IF($B34="","",TEXT($B34,"yyyy-mm"))
A35: =IF($B35="","",ROW()-5) | G35: =IF($F35="","",IFERROR(INDEX(商品档案!$B$6:$B$65,MATCH($F35,商品档案!$A$6:$A$65,0)),"")) | H35: =IF($F35="","",IFERROR(INDEX(商品档案!$C$6:$C$65,MATCH($F35,商品档案!$A$6:$A$65,0)),"")) | I35: =IF($F35="","",IFERROR(INDEX(商品档案!$D$6:$D$65,MATCH($F35,商品档案!$A$6:$A$65,0)),"")) | P35: =IF(AND($B35="",$D35="",$F35=""),"",IF(NOT(ISNUMBER($B35)),"日期无效",IF(ISNA(MATCH($C35,参数设置!$A$10:$A$12,0)),"公司无效",IF(ISNA(MATCH($D35,记账规则!$A$6:$A$9,0)),"业务类型无效",IF(ISNA(MATCH($F35,商品档案!$A$6:$A$65,0)),"商品编码无效",IF(IFERROR(INDEX(商品档案!$E$6:$E$65,MATCH($F35,商品档案!$A$6:$A$65,0)),"")<>$C35,"商品不属于该公司",IF(AND($E35<>"",ISNA(MATCH($E35,往来单位!$A$6:$A$85,0))),"往来单位未建档",IF(N($J35)=0,"数量为 0",IF(N($K35)=0,"单价为 0",IF(AND(LEFT($D35,2)="销售",$U35=""),"该商品没设成本科目",IF(YEAR($B35)<>参数设置!$B$5,"不在本会计年度","OK"))))))))))) | Q35: =IF($F35="","",ROUND(N($J35)*N($K35),2)) | R35: =IF($D35="","",IF(LEFT($D35,2)="销售","应收账款","应付账款")) | S35: =IF($F35="","",IFERROR(INDEX(商品档案!$G$6:$G$65,MATCH($F35,商品档案!$A$6:$A$65,0)),"")) | T35: =IF($F35="","",IFERROR(INDEX(商品档案!$H$6:$H$65,MATCH($F35,商品档案!$A$6:$A$65,0)),"")) | U35: =IF($F35="","",IFERROR(INDEX(商品档案!$I$6:$I$65,MATCH($F35,商品档案!$A$6:$A$65,0)),"")) | V35: =IF($F35="","",SUMIFS(进销存台账!$N$6:$N$65,进销存台账!$A$6:$A$65,$C35,进销存台账!$B$6:$B$65,$F35)) | W35: =IF(OR($D35="销售出库",$D35="销售退回"),ROUND(N($J35)*N($V35),2),0) -> 0 | X35: =IF($E35="","",IFERROR(INDEX(往来单位!$D$6:$D$85,MATCH($E35,往来单位!$A$6:$A$85,0)),"否")) | Y35: =IF($B35="","",YEAR($B35)) | Z35: =IF($B35="","",TEXT($B35,"yyyy-mm"))
A36: =IF($B36="","",ROW()-5) | G36: =IF($F36="","",IFERROR(INDEX(商品档案!$B$6:$B$65,MATCH($F36,商品档案!$A$6:$A$65,0)),"")) | H36: =IF($F36="","",IFERROR(INDEX(商品档案!$C$6:$C$65,MATCH($F36,商品档案!$A$6:$A$65,0)),"")) | I36: =IF($F36="","",IFERROR(INDEX(商品档案!$D$6:$D$65,MATCH($F36,商品档案!$A$6:$A$65,0)),"")) | P36: =IF(AND($B36="",$D36="",$F36=""),"",IF(NOT(ISNUMBER($B36)),"日期无效",IF(ISNA(MATCH($C36,参数设置!$A$10:$A$12,0)),"公司无效",IF(ISNA(MATCH($D36,记账规则!$A$6:$A$9,0)),"业务类型无效",IF(ISNA(MATCH($F36,商品档案!$A$6:$A$65,0)),"商品编码无效",IF(IFERROR(INDEX(商品档案!$E$6:$E$65,MATCH($F36,商品档案!$A$6:$A$65,0)),"")<>$C36,"商品不属于该公司",IF(AND($E36<>"",ISNA(MATCH($E36,往来单位!$A$6:$A$85,0))),"往来单位未建档",IF(N($J36)=0,"数量为 0",IF(N($K36)=0,"单价为 0",IF(AND(LEFT($D36,2)="销售",$U36=""),"该商品没设成本科目",IF(YEAR($B36)<>参数设置!$B$5,"不在本会计年度","OK"))))))))))) | Q36: =IF($F36="","",ROUND(N($J36)*N($K36),2)) | R36: =IF($D36="","",IF(LEFT($D36,2)="销售","应收账款","应付账款")) | S36: =IF($F36="","",IFERROR(INDEX(商品档案!$G$6:$G$65,MATCH($F36,商品档案!$A$6:$A$65,0)),"")) | T36: =IF($F36="","",IFERROR(INDEX(商品档案!$H$6:$H$65,MATCH($F36,商品档案!$A$6:$A$65,0)),"")) | U36: =IF($F36="","",IFERROR(INDEX(商品档案!$I$6:$I$65,MATCH($F36,商品档案!$A$6:$A$65,0)),"")) | V36: =IF($F36="","",SUMIFS(进销存台账!$N$6:$N$65,进销存台账!$A$6:$A$65,$C36,进销存台账!$B$6:$B$65,$F36)) | W36: =IF(OR($D36="销售出库",$D36="销售退回"),ROUND(N($J36)*N($V36),2),0) -> 0 | X36: =IF($E36="","",IFERROR(INDEX(往来单位!$D$6:$D$85,MATCH($E36,往来单位!$A$6:$A$85,0)),"否")) | Y36: =IF($B36="","",YEAR($B36)) | Z36: =IF($B36="","",TEXT($B36,"yyyy-mm"))
A37: =IF($B37="","",ROW()-5) | G37: =IF($F37="","",IFERROR(INDEX(商品档案!$B$6:$B$65,MATCH($F37,商品档案!$A$6:$A$65,0)),"")) | H37: =IF($F37="","",IFERROR(INDEX(商品档案!$C$6:$C$65,MATCH($F37,商品档案!$A$6:$A$65,0)),"")) | I37: =IF($F37="","",IFERROR(INDEX(商品档案!$D$6:$D$65,MATCH($F37,商品档案!$A$6:$A$65,0)),"")) | P37: =IF(AND($B37="",$D37="",$F37=""),"",IF(NOT(ISNUMBER($B37)),"日期无效",IF(ISNA(MATCH($C37,参数设置!$A$10:$A$12,0)),"公司无效",IF(ISNA(MATCH($D37,记账规则!$A$6:$A$9,0)),"业务类型无效",IF(ISNA(MATCH($F37,商品档案!$A$6:$A$65,0)),"商品编码无效",IF(IFERROR(INDEX(商品档案!$E$6:$E$65,MATCH($F37,商品档案!$A$6:$A$65,0)),"")<>$C37,"商品不属于该公司",IF(AND($E37<>"",ISNA(MATCH($E37,往来单位!$A$6:$A$85,0))),"往来单位未建档",IF(N($J37)=0,"数量为 0",IF(N($K37)=0,"单价为 0",IF(AND(LEFT($D37,2)="销售",$U37=""),"该商品没设成本科目",IF(YEAR($B37)<>参数设置!$B$5,"不在本会计年度","OK"))))))))))) | Q37: =IF($F37="","",ROUND(N($J37)*N($K37),2)) | R37: =IF($D37="","",IF(LEFT($D37,2)="销售","应收账款","应付账款")) | S37: =IF($F37="","",IFERROR(INDEX(商品档案!$G$6:$G$65,MATCH($F37,商品档案!$A$6:$A$65,0)),"")) | T37: =IF($F37="","",IFERROR(INDEX(商品档案!$H$6:$H$65,MATCH($F37,商品档案!$A$6:$A$65,0)),"")) | U37: =IF($F37="","",IFERROR(INDEX(商品档案!$I$6:$I$65,MATCH($F37,商品档案!$A$6:$A$65,0)),"")) | V37: =IF($F37="","",SUMIFS(进销存台账!$N$6:$N$65,进销存台账!$A$6:$A$65,$C37,进销存台账!$B$6:$B$65,$F37)) | W37: =IF(OR($D37="销售出库",$D37="销售退回"),ROUND(N($J37)*N($V37),2),0) -> 0 | X37: =IF($E37="","",IFERROR(INDEX(往来单位!$D$6:$D$85,MATCH($E37,往来单位!$A$6:$A$85,0)),"否")) | Y37: =IF($B37="","",YEAR($B37)) | Z37: =IF($B37="","",TEXT($B37,"yyyy-mm"))
... A805: =IF($B805="","",ROW()-5) | G805: =IF($F805="","",IFERROR(INDEX(商品档案!$B$6:$B$65,MATCH($F805,商品档案!$A$6:$A$65,0)),"")) | H805: =IF($F805="","",IFERROR(INDEX(商品档案!$C$6:$C$65,MATCH($F805,商品档案!$A$6:$A$65,0)),"")) | I805: =IF($F805="","",IFERROR(INDEX(商品档案!$D$6:$D$65,MATCH($F805,商品档案!$A$6:$A$65,0)),"")) | P805: =IF(AND($B805="",$D805="",$F805=""),"",IF(NOT(ISNUMBER($B805)),"日期无效",IF(ISNA(MATCH($C805,参数设置!$A$10:$A$12,0)),"公司无效",IF(ISNA(MATCH($D805,记账规则!$A$6:$A$9,0)),"业务类型无效",IF(ISNA(MATCH($F805,商品档案!$A$6:$A$65,0)),"商品编码无效",IF(IFERROR(INDEX(商品档案!$E$6:$E$65,MATCH($F805,商品档案!$A$6:$A$65,0)),"")<>$C805,"商品不属于该公司",IF(AND($E805<>"",ISNA(MATCH($E805,往来单位!$A$6:$A$85,0))),"往来单位未建档",IF(N($J805)=0,"数量为 0",IF(N($K805)=0,"单价为 0",IF(AND(LEFT($D805,2)="销售",$U805=""),"该商品没设成本科目",IF(YEAR($B805)<>参数设置!$B$5,"不在本会计年度","OK"))))))))))) | Q805: =IF($F805="","",ROUND(N($J805)*N($K805),2)) | R805: =IF($D805="","",IF(LEFT($D805,2)="销售","应收账款","应付账款")) | S805: =IF($F805="","",IFERROR(INDEX(商品档案!$G$6:$G$65,MATCH($F805,商品档案!$A$6:$A$65,0)),"")) | T805: =IF($F805="","",IFERROR(INDEX(商品档案!$H$6:$H$65,MATCH($F805,商品档案!$A$6:$A$65,0)),"")) | U805: =IF($F805="","",IFERROR(INDEX(商品档案!$I$6:$I$65,MATCH($F805,商品档案!$A$6:$A$65,0)),"")) | V805: =IF($F805="","",SUMIFS(进销存台账!$N$6:$N$65,进销存台账!$A$6:$A$65,$C805,进销存台账!$B$6:$B$65,$F805)) | W805: =IF(OR($D805="销售出库",$D805="销售退回"),ROUND(N($J805)*N($V805),2),0) -> 0 | X805: =IF($E805="","",IFERROR(INDEX(往来单位!$D$6:$D$85,MATCH($E805,往来单位!$A$6:$A$85,0)),"否")) | Y805: =IF($B805="","",YEAR($B805)) | Z805: =IF($B805="","",TEXT($B805,"yyyy-mm"))

Sheet 资金流水
A1: 资金流水（录入表 · 收支混排、逐行结出账户余额）
A2: 所有账户的收支都按发生顺序记在这一张表上：收进来的填「收入金额」，付出去的填「支出金额」，右边「账户余额」按账户逐行滚出来——几家公司共用一个账号也没关系，余额是按账户算的，账是按「公司」列各记各的。金额一律填实际收付的含税金额，不拆税。按日期先后往下录，余额才有意义（录反了校验列会提示）。收付货款选好「往来单位」，就自动冲【往来台账】里那家的应收/应付；交税选「缴纳税费」，对方科目选税金及附加或所得税费用、费用项目选税种，当期直接进费用。
A5: 序号 | B5: 日期 | C5: 公司 | D5: 账户 | E5: 业务类型 | F5: 往来单位 | G5: 对方科目 | H5: 费用项目 | I5: 收入金额 | J5: 支出金额 | K5: 摘要 | L5: 关联单号 | M5: 备注 | N5: 校验 | O5: 所属月份 | P5: 金额 | Q5: 账户科目 | R5: 收支 | S5: 账户余额 | T5: 年度
A6: =IF($B6="","",ROW()-5) -> 1 | B6: 46040 | C6: 农业 | D6: 农商银行-基本户 | E6: 付供应商货款 | F6: 县农资公司 | J6: 35000 | K6: 支付上年结存货款 | N6: =IF(AND($B6="",$E6="",$I6="",$J6=""),"",IF(NOT(ISNUMBER($B6)),"日期无效",IF(ISNA(MATCH($C6,参数设置!$A$10:$A$12,0)),"公司无效",IF(ISNA(MATCH($D6,资金账户!$B$6:$B$25,0)),"账户未建档",IF(ISNA(MATCH($E6,记账规则!$A$13:$A$32,0)),"业务类型无效",IF(AND(N($I6)<>0,N($J6)<>0),"收入和支出只能填一列",IF($P6=0,"金额为 0",IF(AND($R6="收",N($I6)=0),"这类业务是收款，金额填到收入列",IF(AND($R6="支",N($J6)=0),"这类业务是付款，金额填到支出列",IF(AND(SUMPRODUCT(--(INDEX(记账规则!$A$13:$H$32,MATCH($E6,记账规则!$A$13:$A$32,0),0)="@对方"))>0,$G6=""),"这个类型要填对方科目",IF(AND($G6<>"",ISNA(MATCH($G6,会计科目表!$B$6:$B$85,0))),"对方科目不存在",IF(AND($E6="缴纳税费",$H6=""),"缴税请在费用项目里选税种",IF(AND($F6<>"",ISNA(MATCH($F6,往来单位!$A$6:$A$85,0))),"往来单位未建档",IF(YEAR($B6)<>参数设置!$B$5,"不在本会计年度",IF(AND(""<>"",ISNUMBER(""),$B6<""),"日期比上一行早，余额按行序滚，建议按日期录","OK"))))))))))))))) -> OK | O6: =IF($B6="","",TEXT($B6,"yyyy-mm")) -> 2026-01 | P6: =IF($E6="","",ROUND(N($I6)+N($J6),2)) -> 35000 | Q6: =IF($D6="","",IFERROR(INDEX(资金账户!$F$6:$F$25,MATCH($D6,资金账户!$B$6:$B$25,0)),"")) -> 银行存款 | R6: =IF($E6="","",IFERROR(IF(INDEX(记账规则!$A$13:$H$32,MATCH($E6,记账规则!$A$13:$A$32,0),4)="借","收","支"),"")) -> 支 | S6: =IF($D6="","",ROUND(SUMIFS(资金账户!$H$6:$H$25,资金账户!$B$6:$B$25,$D6)+SUMIFS($I$6:$I6,$D$6:$D6,$D6)-SUMIFS($J$6:$J6,$D$6:$D6,$D6),2)) -> 145000 | T6: =IF($B6="","",YEAR($B6)) -> 2026
A7: =IF($B7="","",ROW()-5) -> 2 | B7: 46063 | C7: 科技 | D7: 建设银行-基本户 | E7: 股东投入 | I7: 100000 | K7: 股东增资 | N7: =IF(AND($B7="",$E7="",$I7="",$J7=""),"",IF(NOT(ISNUMBER($B7)),"日期无效",IF(ISNA(MATCH($C7,参数设置!$A$10:$A$12,0)),"公司无效",IF(ISNA(MATCH($D7,资金账户!$B$6:$B$25,0)),"账户未建档",IF(ISNA(MATCH($E7,记账规则!$A$13:$A$32,0)),"业务类型无效",IF(AND(N($I7)<>0,N($J7)<>0),"收入和支出只能填一列",IF($P7=0,"金额为 0",IF(AND($R7="收",N($I7)=0),"这类业务是收款，金额填到收入列",IF(AND($R7="支",N($J7)=0),"这类业务是付款，金额填到支出列",IF(AND(SUMPRODUCT(--(INDEX(记账规则!$A$13:$H$32,MATCH($E7,记账规则!$A$13:$A$32,0),0)="@对方"))>0,$G7=""),"这个类型要填对方科目",IF(AND($G7<>"",ISNA(MATCH($G7,会计科目表!$B$6:$B$85,0))),"对方科目不存在",IF(AND($E7="缴纳税费",$H7=""),"缴税请在费用项目里选税种",IF(AND($F7<>"",ISNA(MATCH($F7,往来单位!$A$6:$A$85,0))),"往来单位未建档",IF(YEAR($B7)<>参数设置!$B$5,"不在本会计年度",IF(AND($B6<>"",ISNUMBER($B6),$B7<$B6),"日期比上一行早，余额按行序滚，建议按日期录","OK"))))))))))))))) -> OK | O7: =IF($B7="","",TEXT($B7,"yyyy-mm")) -> 2026-02 | P7: =IF($E7="","",ROUND(N($I7)+N($J7),2)) -> 100000 | Q7: =IF($D7="","",IFERROR(INDEX(资金账户!$F$6:$F$25,MATCH($D7,资金账户!$B$6:$B$25,0)),"")) -> 银行存款 | R7: =IF($E7="","",IFERROR(IF(INDEX(记账规则!$A$13:$H$32,MATCH($E7,记账规则!$A$13:$A$32,0),4)="借","收","支"),"")) -> 收 | S7: =IF($D7="","",ROUND(SUMIFS(资金账户!$H$6:$H$25,资金账户!$B$6:$B$25,$D7)+SUMIFS($I$6:$I7,$D$6:$D7,$D7)-SUMIFS($J$6:$J7,$D$6:$D7,$D7),2)) -> 420000 | T7: =IF($B7="","",YEAR($B7)) -> 2026
A8: =IF($B8="","",ROW()-5) -> 3 | B8: 46082 | C8: 木业 | D8: 工商银行-基本户 | E8: 收到借款 | F8: 农商银行 | G8: 短期借款 | I8: 150000 | K8: 流动资金借款 | N8: =IF(AND($B8="",$E8="",$I8="",$J8=""),"",IF(NOT(ISNUMBER($B8)),"日期无效",IF(ISNA(MATCH($C8,参数设置!$A$10:$A$12,0)),"公司无效",IF(ISNA(MATCH($D8,资金账户!$B$6:$B$25,0)),"账户未建档",IF(ISNA(MATCH($E8,记账规则!$A$13:$A$32,0)),"业务类型无效",IF(AND(N($I8)<>0,N($J8)<>0),"收入和支出只能填一列",IF($P8=0,"金额为 0",IF(AND($R8="收",N($I8)=0),"这类业务是收款，金额填到收入列",IF(AND($R8="支",N($J8)=0),"这类业务是付款，金额填到支出列",IF(AND(SUMPRODUCT(--(INDEX(记账规则!$A$13:$H$32,MATCH($E8,记账规则!$A$13:$A$32,0),0)="@对方"))>0,$G8=""),"这个类型要填对方科目",IF(AND($G8<>"",ISNA(MATCH($G8,会计科目表!$B$6:$B$85,0))),"对方科目不存在",IF(AND($E8="缴纳税费",$H8=""),"缴税请在费用项目里选税种",IF(AND($F8<>"",ISNA(MATCH($F8,往来单位!$A$6:$A$85,0))),"往来单位未建档",IF(YEAR($B8)<>参数设置!$B$5,"不在本会计年度",IF(AND($B7<>"",ISNUMBER($B7),$B8<$B7),"日期比上一行早，余额按行序滚，建议按日期录","OK"))))))))))))))) -> OK | O8: =IF($B8="","",TEXT($B8,"yyyy-mm")) -> 2026-03 | P8: =IF($E8="","",ROUND(N($I8)+N($J8),2)) -> 150000 | Q8: =IF($D8="","",IFERROR(INDEX(资金账户!$F$6:$F$25,MATCH($D8,资金账户!$B$6:$B$25,0)),"")) -> 银行存款 | R8: =IF($E8="","",IFERROR(IF(INDEX(记账规则!$A$13:$H$32,MATCH($E8,记账规则!$A$13:$A$32,0),4)="借","收","支"),"")) -> 收 | S8: =IF($D8="","",ROUND(SUMIFS(资金账户!$H$6:$H$25,资金账户!$B$6:$B$25,$D8)+SUMIFS($I$6:$I8,$D$6:$D8,$D8)-SUMIFS($J$6:$J8,$D$6:$D8,$D8),2)) -> 410000 | T8: =IF($B8="","",YEAR($B8)) -> 2026
A9: =IF($B9="","",ROW()-5) -> 4 | B9: 46086 | C9: 农业 | D9: 农商银行-基本户 | E9: 付供应商货款 | F9: 林业苗圃 | J9: 7800 | K9: 支付杉木苗款 | L9: 购销 2 | N9: =IF(AND($B9="",$E9="",$I9="",$J9=""),"",IF(NOT(ISNUMBER($B9)),"日期无效",IF(ISNA(MATCH($C9,参数设置!$A$10:$A$12,0)),"公司无效",IF(ISNA(MATCH($D9,资金账户!$B$6:$B$25,0)),"账户未建档",IF(ISNA(MATCH($E9,记账规则!$A$13:$A$32,0)),"业务类型无效",IF(AND(N($I9)<>0,N($J9)<>0),"收入和支出只能填一列",IF($P9=0,"金额为 0",IF(AND($R9="收",N($I9)=0),"这类业务是收款，金额填到收入列",IF(AND($R9="支",N($J9)=0),"这类业务是付款，金额填到支出列",IF(AND(SUMPRODUCT(--(INDEX(记账规则!$A$13:$H$32,MATCH($E9,记账规则!$A$13:$A$32,0),0)="@对方"))>0,$G9=""),"这个类型要填对方科目",IF(AND($G9<>"",ISNA(MATCH($G9,会计科目表!$B$6:$B$85,0))),"对方科目不存在",IF(AND($E9="缴纳税费",$H9=""),"缴税请在费用项目里选税种",IF(AND($F9<>"",ISNA(MATCH($F9,往来单位!$A$6:$A$85,0))),"往来单位未建档",IF(YEAR($B9)<>参数设置!$B$5,"不在本会计年度",IF(AND($B8<>"",ISNUMBER($B8),$B9<$B8),"日期比上一行早，余额按行序滚，建议按日期录","OK"))))))))))))))) -> OK | O9: =IF($B9="","",TEXT($B9,"yyyy-mm")) -> 2026-03 | P9: =IF($E9="","",ROUND(N($I9)+N($J9),2)) -> 7800 | Q9: =IF($D9="","",IFERROR(INDEX(资金账户!$F$6:$F$25,MATCH($D9,资金账户!$B$6:$B$25,0)),"")) -> 银行存款 | R9: =IF($E9="","",IFERROR(IF(INDEX(记账规则!$A$13:$H$32,MATCH($E9,记账规则!$A$13:$A$32,0),4)="借","收","支"),"")) -> 支 | S9: =IF($D9="","",ROUND(SUMIFS(资金账户!$H$6:$H$25,资金账户!$B$6:$B$25,$D9)+SUMIFS($I$6:$I9,$D$6:$D9,$D9)-SUMIFS($J$6:$J9,$D$6:$D9,$D9),2)) -> 137200 | T9: =IF($B9="","",YEAR($B9)) -> 2026
A10: =IF($B10="","",ROW()-5) -> 5 | B10: 46101 | C10: 农业 | D10: 农商银行-基本户 | E10: 费用支出 | G10: 管理费用 | H10: 办公费 | J10: 3200 | K10: 办公用品 | N10: =IF(AND($B10="",$E10="",$I10="",$J10=""),"",IF(NOT(ISNUMBER($B10)),"日期无效",IF(ISNA(MATCH($C10,参数设置!$A$10:$A$12,0)),"公司无效",IF(ISNA(MATCH($D10,资金账户!$B$6:$B$25,0)),"账户未建档",IF(ISNA(MATCH($E10,记账规则!$A$13:$A$32,0)),"业务类型无效",IF(AND(N($I10)<>0,N($J10)<>0),"收入和支出只能填一列",IF($P10=0,"金额为 0",IF(AND($R10="收",N($I10)=0),"这类业务是收款，金额填到收入列",IF(AND($R10="支",N($J10)=0),"这类业务是付款，金额填到支出列",IF(AND(SUMPRODUCT(--(INDEX(记账规则!$A$13:$H$32,MATCH($E10,记账规则!$A$13:$A$32,0),0)="@对方"))>0,$G10=""),"这个类型要填对方科目",IF(AND($G10<>"",ISNA(MATCH($G10,会计科目表!$B$6:$B$85,0))),"对方科目不存在",IF(AND($E10="缴纳税费",$H10=""),"缴税请在费用项目里选税种",IF(AND($F10<>"",ISNA(MATCH($F10,往来单位!$A$6:$A$85,0))),"往来单位未建档",IF(YEAR($B10)<>参数设置!$B$5,"不在本会计年度",IF(AND($B9<>"",ISNUMBER($B9),$B10<$B9),"日期比上一行早，余额按行序滚，建议按日期录","OK"))))))))))))))) -> OK | O10: =IF($B10="","",TEXT($B10,"yyyy-mm")) -> 2026-03 | P10: =IF($E10="","",ROUND(N($I10)+N($J10),2)) -> 3200 | Q10: =IF($D10="","",IFERROR(INDEX(资金账户!$F$6:$F$25,MATCH($D10,资金账户!$B$6:$B$25,0)),"")) -> 银行存款 | R10: =IF($E10="","",IFERROR(IF(INDEX(记账规则!$A$13:$H$32,MATCH($E10,记账规则!$A$13:$A$32,0),4)="借","收","支"),"")) -> 支 | S10: =IF($D10="","",ROUND(SUMIFS(资金账户!$H$6:$H$25,资金账户!$B$6:$B$25,$D10)+SUMIFS($I$6:$I10,$D$6:$D10,$D10)-SUMIFS($J$6:$J10,$D$6:$D10,$D10),2)) -> 134000 | T10: =IF($B10="","",YEAR($B10)) -> 2026
A11: =IF($B11="","",ROW()-5) -> 6 | B11: 46132 | C11: 木业 | D11: 工商银行-基本户 | E11: 付供应商货款 | F11: 华鑫化工 | J11: 12000 | K11: 支付胶水款 | L11: 购销 7 | N11: =IF(AND($B11="",$E11="",$I11="",$J11=""),"",IF(NOT(ISNUMBER($B11)),"日期无效",IF(ISNA(MATCH($C11,参数设置!$A$10:$A$12,0)),"公司无效",IF(ISNA(MATCH($D11,资金账户!$B$6:$B$25,0)),"账户未建档",IF(ISNA(MATCH($E11,记账规则!$A$13:$A$32,0)),"业务类型无效",IF(AND(N($I11)<>0,N($J11)<>0),"收入和支出只能填一列",IF($P11=0,"金额为 0",IF(AND($R11="收",N($I11)=0),"这类业务是收款，金额填到收入列",IF(AND($R11="支",N($J11)=0),"这类业务是付款，金额填到支出列",IF(AND(SUMPRODUCT(--(INDEX(记账规则!$A$13:$H$32,MATCH($E11,记账规则!$A$13:$A$32,0),0)="@对方"))>0,$G11=""),"这个类型要填对方科目",IF(AND($G11<>"",ISNA(MATCH($G11,会计科目表!$B$6:$B$85,0))),"对方科目不存在",IF(AND($E11="缴纳税费",$H11=""),"缴税请在费用项目里选税种",IF(AND($F11<>"",ISNA(MATCH($F11,往来单位!$A$6:$A$85,0))),"往来单位未建档",IF(YEAR($B11)<>参数设置!$B$5,"不在本会计年度",IF(AND($B10<>"",ISNUMBER($B10),$B11<$B10),"日期比上一行早，余额按行序滚，建议按日期录","OK"))))))))))))))) -> OK | O11: =IF($B11="","",TEXT($B11,"yyyy-mm")) -> 2026-04 | P11: =IF($E11="","",ROUND(N($I11)+N($J11),2)) -> 12000 | Q11: =IF($D11="","",IFERROR(INDEX(资金账户!$F$6:$F$25,MATCH($D11,资金账户!$B$6:$B$25,0)),"")) -> 银行存款 | R11: =IF($E11="","",IFERROR(IF(INDEX(记账规则!$A$13:$H$32,MATCH($E11,记账规则!$A$13:$A$32,0),4)="借","收","支"),"")) -> 支 | S11: =IF($D11="","",ROUND(SUMIFS(资金账户!$H$6:$H$25,资金账户!$B$6:$B$25,$D11)+SUMIFS($I$6:$I11,$D$6:$D11,$D11)-SUMIFS($J$6:$J11,$D$6:$D11,$D11),2)) -> 398000 | T11: =IF($B11="","",YEAR($B11)) -> 2026
A12: =IF($B12="","",ROW()-5) -> 7 | B12: 46154 | C12: 木业 | D12: 工商银行-基本户 | E12: 付供应商货款 | F12: 张德富（农户） | J12: 58800 | K12: 付农户原木收购款 | L12: 购销 8 | N12: =IF(AND($B12="",$E12="",$I12="",$J12=""),"",IF(NOT(ISNUMBER($B12)),"日期无效",IF(ISNA(MATCH($C12,参数设置!$A$10:$A$12,0)),"公司无效",IF(ISNA(MATCH($D12,资金账户!$B$6:$B$25,0)),"账户未建档",IF(ISNA(MATCH($E12,记账规则!$A$13:$A$32,0)),"业务类型无效",IF(AND(N($I12)<>0,N($J12)<>0),"收入和支出只能填一列",IF($P12=0,"金额为 0",IF(AND($R12="收",N($I12)=0),"这类业务是收款，金额填到收入列",IF(AND($R12="支",N($J12)=0),"这类业务是付款，金额填到支出列",IF(AND(SUMPRODUCT(--(INDEX(记账规则!$A$13:$H$32,MATCH($E12,记账规则!$A$13:$A$32,0),0)="@对方"))>0,$G12=""),"这个类型要填对方科目",IF(AND($G12<>"",ISNA(MATCH($G12,会计科目表!$B$6:$B$85,0))),"对方科目不存在",IF(AND($E12="缴纳税费",$H12=""),"缴税请在费用项目里选税种",IF(AND($F12<>"",ISNA(MATCH($F12,往来单位!$A$6:$A$85,0))),"往来单位未建档",IF(YEAR($B12)<>参数设置!$B$5,"不在本会计年度",IF(AND($B11<>"",ISNUMBER($B11),$B12<$B11),"日期比上一行早，余额按行序滚，建议按日期录","OK"))))))))))))))) -> OK | O12: =IF($B12="","",TEXT($B12,"yyyy-mm")) -> 2026-05 | P12: =IF($E12="","",ROUND(N($I12)+N($J12),2)) -> 58800 | Q12: =IF($D12="","",IFERROR(INDEX(资金账户!$F$6:$F$25,MATCH($D12,资金账户!$B$6:$B$25,0)),"")) -> 银行存款 | R12: =IF($E12="","",IFERROR(IF(INDEX(记账规则!$A$13:$H$32,MATCH($E12,记账规则!$A$13:$A$32,0),4)="借","收","支"),"")) -> 支 | S12: =IF($D12="","",ROUND(SUMIFS(资金账户!$H$6:$H$25,资金账户!$B$6:$B$25,$D12)+SUMIFS($I$6:$I12,$D$6:$D12,$D12)-SUMIFS($J$6:$J12,$D$6:$D12,$D12),2)) -> 339200 | T12: =IF($B12="","",YEAR($B12)) -> 2026
A13: =IF($B13="","",ROW()-5) -> 8 | B13: 46167 | C13: 科技 | D13: 建设银行-基本户 | E13: 付供应商货款 | F13: 晶诚玻璃 | J13: 19200 | K13: 支付包装瓶款 | L13: 购销 15 | N13: =IF(AND($B13="",$E13="",$I13="",$J13=""),"",IF(NOT(ISNUMBER($B13)),"日期无效",IF(ISNA(MATCH($C13,参数设置!$A$10:$A$12,0)),"公司无效",IF(ISNA(MATCH($D13,资金账户!$B$6:$B$25,0)),"账户未建档",IF(ISNA(MATCH($E13,记账规则!$A$13:$A$32,0)),"业务类型无效",IF(AND(N($I13)<>0,N($J13)<>0),"收入和支出只能填一列",IF($P13=0,"金额为 0",IF(AND($R13="收",N($I13)=0),"这类业务是收款，金额填到收入列",IF(AND($R13="支",N($J13)=0),"这类业务是付款，金额填到支出列",IF(AND(SUMPRODUCT(--(INDEX(记账规则!$A$13:$H$32,MATCH($E13,记账规则!$A$13:$A$32,0),0)="@对方"))>0,$G13=""),"这个类型要填对方科目",IF(AND($G13<>"",ISNA(MATCH($G13,会计科目表!$B$6:$B$85,0))),"对方科目不存在",IF(AND($E13="缴纳税费",$H13=""),"缴税请在费用项目里选税种",IF(AND($F13<>"",ISNA(MATCH($F13,往来单位!$A$6:$A$85,0))),"往来单位未建档",IF(YEAR($B13)<>参数设置!$B$5,"不在本会计年度",IF(AND($B12<>"",ISNUMBER($B12),$B13<$B12),"日期比上一行早，余额按行序滚，建议按日期录","OK"))))))))))))))) -> OK | O13: =IF($B13="","",TEXT($B13,"yyyy-mm")) -> 2026-05 | P13: =IF($E13="","",ROUND(N($I13)+N($J13),2)) -> 19200 | Q13: =IF($D13="","",IFERROR(INDEX(资金账户!$F$6:$F$25,MATCH($D13,资金账户!$B$6:$B$25,0)),"")) -> 银行存款 | R13: =IF($E13="","",IFERROR(IF(INDEX(记账规则!$A$13:$H$32,MATCH($E13,记账规则!$A$13:$A$32,0),4)="借","收","支"),"")) -> 支 | S13: =IF($D13="","",ROUND(SUMIFS(资金账户!$H$6:$H$25,资金账户!$B$6:$B$25,$D13)+SUMIFS($I$6:$I13,$D$6:$D13,$D13)-SUMIFS($J$6:$J13,$D$6:$D13,$D13),2)) -> 400800 | T13: =IF($B13="","",YEAR($B13)) -> 2026
A14: =IF($B14="","",ROW()-5) -> 9 | B14: 46172 | C14: 科技 | D14: 建设银行-基本户 | E14: 付供应商货款 | F14: 瑞丰纸品 | J14: 4080 | K14: 支付纸盒款 | L14: 购销 16 | N14: =IF(AND($B14="",$E14="",$I14="",$J14=""),"",IF(NOT(ISNUMBER($B14)),"日期无效",IF(ISNA(MATCH($C14,参数设置!$A$10:$A$12,0)),"公司无效",IF(ISNA(MATCH($D14,资金账户!$B$6:$B$25,0)),"账户未建档",IF(ISNA(MATCH($E14,记账规则!$A$13:$A$32,0)),"业务类型无效",IF(AND(N($I14)<>0,N($J14)<>0),"收入和支出只能填一列",IF($P14=0,"金额为 0",IF(AND($R14="收",N($I14)=0),"这类业务是收款，金额填到收入列",IF(AND($R14="支",N($J14)=0),"这类业务是付款，金额填到支出列",IF(AND(SUMPRODUCT(--(INDEX(记账规则!$A$13:$H$32,MATCH($E14,记账规则!$A$13:$A$32,0),0)="@对方"))>0,$G14=""),"这个类型要填对方科目",IF(AND($G14<>"",ISNA(MATCH($G14,会计科目表!$B$6:$B$85,0))),"对方科目不存在",IF(AND($E14="缴纳税费",$H14=""),"缴税请在费用项目里选税种",IF(AND($F14<>"",ISNA(MATCH($F14,往来单位!$A$6:$A$85,0))),"往来单位未建档",IF(YEAR($B14)<>参数设置!$B$5,"不在本会计年度",IF(AND($B13<>"",ISNUMBER($B13),$B14<$B13),"日期比上一行早，余额按行序滚，建议按日期录","OK"))))))))))))))) -> OK | O14: =IF($B14="","",TEXT($B14,"yyyy-mm")) -> 2026-05 | P14: =IF($E14="","",ROUND(N($I14)+N($J14),2)) -> 4080 | Q14: =IF($D14="","",IFERROR(INDEX(资金账户!$F$6:$F$25,MATCH($D14,资金账户!$B$6:$B$25,0)),"")) -> 银行存款 | R14: =IF($E14="","",IFERROR(IF(INDEX(记账规则!$A$13:$H$32,MATCH($E14,记账规则!$A$13:$A$32,0),4)="借","收","支"),"")) -> 支 | S14: =IF($D14="","",ROUND(SUMIFS(资金账户!$H$6:$H$25,资金账户!$B$6:$B$25,$D14)+SUMIFS($I$6:$I14,$D$6:$D14,$D14)-SUMIFS($J$6:$J14,$D$6:$D14,$D14),2)) -> 396720 | T14: =IF($B14="","",YEAR($B14)) -> 2026
A15: =IF($B15="","",ROW()-5) -> 10 | B15: 46201 | C15: 农业 | D15: 农商银行-基本户 | E15: 收客户货款 | F15: 木业公司 | I15: 150000 | K15: 收木业公司原木款（内部） | L15: 购销 3 | N15: =IF(AND($B15="",$E15="",$I15="",$J15=""),"",IF(NOT(ISNUMBER($B15)),"日期无效",IF(ISNA(MATCH($C15,参数设置!$A$10:$A$12,0)),"公司无效",IF(ISNA(MATCH($D15,资金账户!$B$6:$B$25,0)),"账户未建档",IF(ISNA(MATCH($E15,记账规则!$A$13:$A$32,0)),"业务类型无效",IF(AND(N($I15)<>0,N($J15)<>0),"收入和支出只能填一列",IF($P15=0,"金额为 0",IF(AND($R15="收",N($I15)=0),"这类业务是收款，金额填到收入列",IF(AND($R15="支",N($J15)=0),"这类业务是付款，金额填到支出列",IF(AND(SUMPRODUCT(--(INDEX(记账规则!$A$13:$H$32,MATCH($E15,记账规则!$A$13:$A$32,0),0)="@对方"))>0,$G15=""),"这个类型要填对方科目",IF(AND($G15<>"",ISNA(MATCH($G15,会计科目表!$B$6:$B$85,0))),"对方科目不存在",IF(AND($E15="缴纳税费",$H15=""),"缴税请在费用项目里选税种",IF(AND($F15<>"",ISNA(MATCH($F15,往来单位!$A$6:$A$85,0))),"往来单位未建档",IF(YEAR($B15)<>参数设置!$B$5,"不在本会计年度",IF(AND($B14<>"",ISNUMBER($B14),$B15<$B14),"日期比上一行早，余额按行序滚，建议按日期录","OK"))))))))))))))) -> OK | O15: =IF($B15="","",TEXT($B15,"yyyy-mm")) -> 2026-06 | P15: =IF($E15="","",ROUND(N($I15)+N($J15),2)) -> 150000 | Q15: =IF($D15="","",IFERROR(INDEX(资金账户!$F$6:$F$25,MATCH($D15,资金账户!$B$6:$B$25,0)),"")) -> 银行存款 | R15: =IF($E15="","",IFERROR(IF(INDEX(记账规则!$A$13:$H$32,MATCH($E15,记账规则!$A$13:$A$32,0),4)="借","收","支"),"")) -> 收 | S15: =IF($D15="","",ROUND(SUMIFS(资金账户!$H$6:$H$25,资金账户!$B$6:$B$25,$D15)+SUMIFS($I$6:$I15,$D$6:$D15,$D15)-SUMIFS($J$6:$J15,$D$6:$D15,$D15),2)) -> 284000 | T15: =IF($B15="","",YEAR($B15)) -> 2026
A16: =IF($B16="","",ROW()-5) -> 11 | B16: 46201 | C16: 木业 | D16: 工商银行-基本户 | E16: 付供应商货款 | F16: 农业基地公司 | J16: 150000 | K16: 付农业基地原木款（内部） | L16: 购销 9 | N16: =IF(AND($B16="",$E16="",$I16="",$J16=""),"",IF(NOT(ISNUMBER($B16)),"日期无效",IF(ISNA(MATCH($C16,参数设置!$A$10:$A$12,0)),"公司无效",IF(ISNA(MATCH($D16,资金账户!$B$6:$B$25,0)),"账户未建档",IF(ISNA(MATCH($E16,记账规则!$A$13:$A$32,0)),"业务类型无效",IF(AND(N($I16)<>0,N($J16)<>0),"收入和支出只能填一列",IF($P16=0,"金额为 0",IF(AND($R16="收",N($I16)=0),"这类业务是收款，金额填到收入列",IF(AND($R16="支",N($J16)=0),"这类业务是付款，金额填到支出列",IF(AND(SUMPRODUCT(--(INDEX(记账规则!$A$13:$H$32,MATCH($E16,记账规则!$A$13:$A$32,0),0)="@对方"))>0,$G16=""),"这个类型要填对方科目",IF(AND($G16<>"",ISNA(MATCH($G16,会计科目表!$B$6:$B$85,0))),"对方科目不存在",IF(AND($E16="缴纳税费",$H16=""),"缴税请在费用项目里选税种",IF(AND($F16<>"",ISNA(MATCH($F16,往来单位!$A$6:$A$85,0))),"往来单位未建档",IF(YEAR($B16)<>参数设置!$B$5,"不在本会计年度",IF(AND($B15<>"",ISNUMBER($B15),$B16<$B15),"日期比上一行早，余额按行序滚，建议按日期录","OK"))))))))))))))) -> OK | O16: =IF($B16="","",TEXT($B16,"yyyy-mm")) -> 2026-06 | P16: =IF($E16="","",ROUND(N($I16)+N($J16),2)) -> 150000 | Q16: =IF($D16="","",IFERROR(INDEX(资金账户!$F$6:$F$25,MATCH($D16,资金账户!$B$6:$B$25,0)),"")) -> 银行存款 | R16: =IF($E16="","",IFERROR(IF(INDEX(记账规则!$A$13:$H$32,MATCH($E16,记账规则!$A$13:$A$32,0),4)="借","收","支"),"")) -> 支 | S16: =IF($D16="","",ROUND(SUMIFS(资金账户!$H$6:$H$25,资金账户!$B$6:$B$25,$D16)+SUMIFS($I$6:$I16,$D$6:$D16,$D16)-SUMIFS($J$6:$J16,$D$6:$D16,$D16),2)) -> 189200 | T16: =IF($B16="","",YEAR($B16)) -> 2026
A17: =IF($B17="","",ROW()-5) -> 12 | B17: 46203 | C17: 科技 | D17: 建设银行-基本户 | E17: 费用支出 | F17: 天成广告 | G17: 销售费用 | H17: 广告推广费 | J17: 26500 | K17: 电商推广 | N17: =IF(AND($B17="",$E17="",$I17="",$J17=""),"",IF(NOT(ISNUMBER($B17)),"日期无效",IF(ISNA(MATCH($C17,参数设置!$A$10:$A$12,0)),"公司无效",IF(ISNA(MATCH($D17,资金账户!$B$6:$B$25,0)),"账户未建档",IF(ISNA(MATCH($E17,记账规则!$A$13:$A$32,0)),"业务类型无效",IF(AND(N($I17)<>0,N($J17)<>0),"收入和支出只能填一列",IF($P17=0,"金额为 0",IF(AND($R17="收",N($I17)=0),"这类业务是收款，金额填到收入列",IF(AND($R17="支",N($J17)=0),"这类业务是付款，金额填到支出列",IF(AND(SUMPRODUCT(--(INDEX(记账规则!$A$13:$H$32,MATCH($E17,记账规则!$A$13:$A$32,0),0)="@对方"))>0,$G17=""),"这个类型要填对方科目",IF(AND($G17<>"",ISNA(MATCH($G17,会计科目表!$B$6:$B$85,0))),"对方科目不存在",IF(AND($E17="缴纳税费",$H17=""),"缴税请在费用项目里选税种",IF(AND($F17<>"",ISNA(MATCH($F17,往来单位!$A$6:$A$85,0))),"往来单位未建档",IF(YEAR($B17)<>参数设置!$B$5,"不在本会计年度",IF(AND($B16<>"",ISNUMBER($B16),$B17<$B16),"日期比上一行早，余额按行序滚，建议按日期录","OK"))))))))))))))) -> OK | O17: =IF($B17="","",TEXT($B17,"yyyy-mm")) -> 2026-06 | P17: =IF($E17="","",ROUND(N($I17)+N($J17),2)) -> 26500 | Q17: =IF($D17="","",IFERROR(INDEX(资金账户!$F$6:$F$25,MATCH($D17,资金账户!$B$6:$B$25,0)),"")) -> 银行存款 | R17: =IF($E17="","",IFERROR(IF(INDEX(记账规则!$A$13:$H$32,MATCH($E17,记账规则!$A$13:$A$32,0),4)="借","收","支"),"")) -> 支 | S17: =IF($D17="","",ROUND(SUMIFS(资金账户!$H$6:$H$25,资金账户!$B$6:$B$25,$D17)+SUMIFS($I$6:$I17,$D$6:$D17,$D17)-SUMIFS($J$6:$J17,$D$6:$D17,$D17),2)) -> 370220 | T17: =IF($B17="","",YEAR($B17)) -> 2026
A18: =IF($B18="","",ROW()-5) -> 13 | B18: 46223 | C18: 木业 | D18: 农商银行-共用户 | E18: 收客户货款 | F18: 鑫隆建材 | I18: 300000 | K18: 收木板货款（进共用户） | L18: 购销 11 | N18: =IF(AND($B18="",$E18="",$I18="",$J18=""),"",IF(NOT(ISNUMBER($B18)),"日期无效",IF(ISNA(MATCH($C18,参数设置!$A$10:$A$12,0)),"公司无效",IF(ISNA(MATCH($D18,资金账户!$B$6:$B$25,0)),"账户未建档",IF(ISNA(MATCH($E18,记账规则!$A$13:$A$32,0)),"业务类型无效",IF(AND(N($I18)<>0,N($J18)<>0),"收入和支出只能填一列",IF($P18=0,"金额为 0",IF(AND($R18="收",N($I18)=0),"这类业务是收款，金额填到收入列",IF(AND($R18="支",N($J18)=0),"这类业务是付款，金额填到支出列",IF(AND(SUMPRODUCT(--(INDEX(记账规则!$A$13:$H$32,MATCH($E18,记账规则!$A$13:$A$32,0),0)="@对方"))>0,$G18=""),"这个类型要填对方科目",IF(AND($G18<>"",ISNA(MATCH($G18,会计科目表!$B$6:$B$85,0))),"对方科目不存在",IF(AND($E18="缴纳税费",$H18=""),"缴税请在费用项目里选税种",IF(AND($F18<>"",ISNA(MATCH($F18,往来单位!$A$6:$A$85,0))),"往来单位未建档",IF(YEAR($B18)<>参数设置!$B$5,"不在本会计年度",IF(AND($B17<>"",ISNUMBER($B17),$B18<$B17),"日期比上一行早，余额按行序滚，建议按日期录","OK"))))))))))))))) -> OK | O18: =IF($B18="","",TEXT($B18,"yyyy-mm")) -> 2026-07 | P18: =IF($E18="","",ROUND(N($I18)+N($J18),2)) -> 300000 | Q18: =IF($D18="","",IFERROR(INDEX(资金账户!$F$6:$F$25,MATCH($D18,资金账户!$B$6:$B$25,0)),"")) -> 银行存款 | R18: =IF($E18="","",IFERROR(IF(INDEX(记账规则!$A$13:$H$32,MATCH($E18,记账规则!$A$13:$A$32,0),4)="借","收","支"),"")) -> 收 | S18: =IF($D18="","",ROUND(SUMIFS(资金账户!$H$6:$H$25,资金账户!$B$6:$B$25,$D18)+SUMIFS($I$6:$I18,$D$6:$D18,$D18)-SUMIFS($J$6:$J18,$D$6:$D18,$D18),2)) -> 300000 | T18: =IF($B18="","",YEAR($B18)) -> 2026
A19: =IF($B19="","",ROW()-5) -> 14 | B19: 46233 | C19: 农业 | D19: 农商银行-基本户 | E19: 发放工资 | H19: 工资薪金 | J19: 68000 | K19: 发放已计提工资 | N19: =IF(AND($B19="",$E19="",$I19="",$J19=""),"",IF(NOT(ISNUMBER($B19)),"日期无效",IF(ISNA(MATCH($C19,参数设置!$A$10:$A$12,0)),"公司无效",IF(ISNA(MATCH($D19,资金账户!$B$6:$B$25,0)),"账户未建档",IF(ISNA(MATCH($E19,记账规则!$A$13:$A$32,0)),"业务类型无效",IF(AND(N($I19)<>0,N($J19)<>0),"收入和支出只能填一列",IF($P19=0,"金额为 0",IF(AND($R19="收",N($I19)=0),"这类业务是收款，金额填到收入列",IF(AND($R19="支",N($J19)=0),"这类业务是付款，金额填到支出列",IF(AND(SUMPRODUCT(--(INDEX(记账规则!$A$13:$H$32,MATCH($E19,记账规则!$A$13:$A$32,0),0)="@对方"))>0,$G19=""),"这个类型要填对方科目",IF(AND($G19<>"",ISNA(MATCH($G19,会计科目表!$B$6:$B$85,0))),"对方科目不存在",IF(AND($E19="缴纳税费",$H19=""),"缴税请在费用项目里选税种",IF(AND($F19<>"",ISNA(MATCH($F19,往来单位!$A$6:$A$85,0))),"往来单位未建档",IF(YEAR($B19)<>参数设置!$B$5,"不在本会计年度",IF(AND($B18<>"",ISNUMBER($B18),$B19<$B18),"日期比上一行早，余额按行序滚，建议按日期录","OK"))))))))))))))) -> OK | O19: =IF($B19="","",TEXT($B19,"yyyy-mm")) -> 2026-07 | P19: =IF($E19="","",ROUND(N($I19)+N($J19),2)) -> 68000 | Q19: =IF($D19="","",IFERROR(INDEX(资金账户!$F$6:$F$25,MATCH($D19,资金账户!$B$6:$B$25,0)),"")) -> 银行存款 | R19: =IF($E19="","",IFERROR(IF(INDEX(记账规则!$A$13:$H$32,MATCH($E19,记账规则!$A$13:$A$32,0),4)="借","收","支"),"")) -> 支 | S19: =IF($D19="","",ROUND(SUMIFS(资金账户!$H$6:$H$25,资金账户!$B$6:$B$25,$D19)+SUMIFS($I$6:$I19,$D$6:$D19,$D19)-SUMIFS($J$6:$J19,$D$6:$D19,$D19),2)) -> 216000 | T19: =IF($B19="","",YEAR($B19)) -> 2026
A20: =IF($B20="","",ROW()-5) -> 15 | B20: 46244 | C20: 农业 | D20: 农商银行-基本户 | E20: 支付利息 | F20: 农商银行 | H20: 利息支出 | J20: 6000 | K20: 短期借款利息 | N20: =IF(AND($B20="",$E20="",$I20="",$J20=""),"",IF(NOT(ISNUMBER($B20)),"日期无效",IF(ISNA(MATCH($C20,参数设置!$A$10:$A$12,0)),"公司无效",IF(ISNA(MATCH($D20,资金账户!$B$6:$B$25,0)),"账户未建档",IF(ISNA(MATCH($E20,记账规则!$A$13:$A$32,0)),"业务类型无效",IF(AND(N($I20)<>0,N($J20)<>0),"收入和支出只能填一列",IF($P20=0,"金额为 0",IF(AND($R20="收",N($I20)=0),"这类业务是收款，金额填到收入列",IF(AND($R20="支",N($J20)=0),"这类业务是付款，金额填到支出列",IF(AND(SUMPRODUCT(--(INDEX(记账规则!$A$13:$H$32,MATCH($E20,记账规则!$A$13:$A$32,0),0)="@对方"))>0,$G20=""),"这个类型要填对方科目",IF(AND($G20<>"",ISNA(MATCH($G20,会计科目表!$B$6:$B$85,0))),"对方科目不存在",IF(AND($E20="缴纳税费",$H20=""),"缴税请在费用项目里选税种",IF(AND($F20<>"",ISNA(MATCH($F20,往来单位!$A$6:$A$85,0))),"往来单位未建档",IF(YEAR($B20)<>参数设置!$B$5,"不在本会计年度",IF(AND($B19<>"",ISNUMBER($B19),$B20<$B19),"日期比上一行早，余额按行序滚，建议按日期录","OK"))))))))))))))) -> OK | O20: =IF($B20="","",TEXT($B20,"yyyy-mm")) -> 2026-08 | P20: =IF($E20="","",ROUND(N($I20)+N($J20),2)) -> 6000 | Q20: =IF($D20="","",IFERROR(INDEX(资金账户!$F$6:$F$25,MATCH($D20,资金账户!$B$6:$B$25,0)),"")) -> 银行存款 | R20: =IF($E20="","",IFERROR(IF(INDEX(记账规则!$A$13:$H$32,MATCH($E20,记账规则!$A$13:$A$32,0),4)="借","收","支"),"")) -> 支 | S20: =IF($D20="","",ROUND(SUMIFS(资金账户!$H$6:$H$25,资金账户!$B$6:$B$25,$D20)+SUMIFS($I$6:$I20,$D$6:$D20,$D20)-SUMIFS($J$6:$J20,$D$6:$D20,$D20),2)) -> 210000 | T20: =IF($B20="","",YEAR($B20)) -> 2026
A21: =IF($B21="","",ROW()-5) -> 16 | B21: 46249 | C21: 木业 | D21: 工商银行-基本户 | E21: 费用支出 | F21: 国网供电所 | G21: 管理费用 | H21: 水电费 | J21: 8600 | K21: 厂区水电 | N21: =IF(AND($B21="",$E21="",$I21="",$J21=""),"",IF(NOT(ISNUMBER($B21)),"日期无效",IF(ISNA(MATCH($C21,参数设置!$A$10:$A$12,0)),"公司无效",IF(ISNA(MATCH($D21,资金账户!$B$6:$B$25,0)),"账户未建档",IF(ISNA(MATCH($E21,记账规则!$A$13:$A$32,0)),"业务类型无效",IF(AND(N($I21)<>0,N($J21)<>0),"收入和支出只能填一列",IF($P21=0,"金额为 0",IF(AND($R21="收",N($I21)=0),"这类业务是收款，金额填到收入列",IF(AND($R21="支",N($J21)=0),"这类业务是付款，金额填到支出列",IF(AND(SUMPRODUCT(--(INDEX(记账规则!$A$13:$H$32,MATCH($E21,记账规则!$A$13:$A$32,0),0)="@对方"))>0,$G21=""),"这个类型要填对方科目",IF(AND($G21<>"",ISNA(MATCH($G21,会计科目表!$B$6:$B$85,0))),"对方科目不存在",IF(AND($E21="缴纳税费",$H21=""),"缴税请在费用项目里选税种",IF(AND($F21<>"",ISNA(MATCH($F21,往来单位!$A$6:$A$85,0))),"往来单位未建档",IF(YEAR($B21)<>参数设置!$B$5,"不在本会计年度",IF(AND($B20<>"",ISNUMBER($B20),$B21<$B20),"日期比上一行早，余额按行序滚，建议按日期录","OK"))))))))))))))) -> OK | O21: =IF($B21="","",TEXT($B21,"yyyy-mm")) -> 2026-08 | P21: =IF($E21="","",ROUND(N($I21)+N($J21),2)) -> 8600 | Q21: =IF($D21="","",IFERROR(INDEX(资金账户!$F$6:$F$25,MATCH($D21,资金账户!$B$6:$B$25,0)),"")) -> 银行存款 | R21: =IF($E21="","",IFERROR(IF(INDEX(记账规则!$A$13:$H$32,MATCH($E21,记账规则!$A$13:$A$32,0),4)="借","收","支"),"")) -> 支 | S21: =IF($D21="","",ROUND(SUMIFS(资金账户!$H$6:$H$25,资金账户!$B$6:$B$25,$D21)+SUMIFS($I$6:$I21,$D$6:$D21,$D21)-SUMIFS($J$6:$J21,$D$6:$D21,$D21),2)) -> 180600 | T21: =IF($B21="","",YEAR($B21)) -> 2026
A22: =IF($B22="","",ROW()-5) -> 17 | B22: 46252 | C22: 木业 | D22: 工商银行-基本户 | E22: 付供应商货款 | F22: 李长生（农户） | J22: 45000 | K22: 付农户原木收购款 | L22: 购销 10 | N22: =IF(AND($B22="",$E22="",$I22="",$J22=""),"",IF(NOT(ISNUMBER($B22)),"日期无效",IF(ISNA(MATCH($C22,参数设置!$A$10:$A$12,0)),"公司无效",IF(ISNA(MATCH($D22,资金账户!$B$6:$B$25,0)),"账户未建档",IF(ISNA(MATCH($E22,记账规则!$A$13:$A$32,0)),"业务类型无效",IF(AND(N($I22)<>0,N($J22)<>0),"收入和支出只能填一列",IF($P22=0,"金额为 0",IF(AND($R22="收",N($I22)=0),"这类业务是收款，金额填到收入列",IF(AND($R22="支",N($J22)=0),"这类业务是付款，金额填到支出列",IF(AND(SUMPRODUCT(--(INDEX(记账规则!$A$13:$H$32,MATCH($E22,记账规则!$A$13:$A$32,0),0)="@对方"))>0,$G22=""),"这个类型要填对方科目",IF(AND($G22<>"",ISNA(MATCH($G22,会计科目表!$B$6:$B$85,0))),"对方科目不存在",IF(AND($E22="缴纳税费",$H22=""),"缴税请在费用项目里选税种",IF(AND($F22<>"",ISNA(MATCH($F22,往来单位!$A$6:$A$85,0))),"往来单位未建档",IF(YEAR($B22)<>参数设置!$B$5,"不在本会计年度",IF(AND($B21<>"",ISNUMBER($B21),$B22<$B21),"日期比上一行早，余额按行序滚，建议按日期录","OK"))))))))))))))) -> OK | O22: =IF($B22="","",TEXT($B22,"yyyy-mm")) -> 2026-08 | P22: =IF($E22="","",ROUND(N($I22)+N($J22),2)) -> 45000 | Q22: =IF($D22="","",IFERROR(INDEX(资金账户!$F$6:$F$25,MATCH($D22,资金账户!$B$6:$B$25,0)),"")) -> 银行存款 | R22: =IF($E22="","",IFERROR(IF(INDEX(记账规则!$A$13:$H$32,MATCH($E22,记账规则!$A$13:$A$32,0),4)="借","收","支"),"")) -> 支 | S22: =IF($D22="","",ROUND(SUMIFS(资金账户!$H$6:$H$25,资金账户!$B$6:$B$25,$D22)+SUMIFS($I$6:$I22,$D$6:$D22,$D22)-SUMIFS($J$6:$J22,$D$6:$D22,$D22),2)) -> 135600 | T22: =IF($B22="","",YEAR($B22)) -> 2026
A23: =IF($B23="","",ROW()-5) -> 18 | B23: 46254 | C23: 科技 | D23: 农商银行-共用户 | E23: 收客户货款 | F23: 康养电商 | I23: 240000 | K23: 收精油货款（进共用户） | L23: 购销 18 | N23: =IF(AND($B23="",$E23="",$I23="",$J23=""),"",IF(NOT(ISNUMBER($B23)),"日期无效",IF(ISNA(MATCH($C23,参数设置!$A$10:$A$12,0)),"公司无效",IF(ISNA(MATCH($D23,资金账户!$B$6:$B$25,0)),"账户未建档",IF(ISNA(MATCH($E23,记账规则!$A$13:$A$32,0)),"业务类型无效",IF(AND(N($I23)<>0,N($J23)<>0),"收入和支出只能填一列",IF($P23=0,"金额为 0",IF(AND($R23="收",N($I23)=0),"这类业务是收款，金额填到收入列",IF(AND($R23="支",N($J23)=0),"这类业务是付款，金额填到支出列",IF(AND(SUMPRODUCT(--(INDEX(记账规则!$A$13:$H$32,MATCH($E23,记账规则!$A$13:$A$32,0),0)="@对方"))>0,$G23=""),"这个类型要填对方科目",IF(AND($G23<>"",ISNA(MATCH($G23,会计科目表!$B$6:$B$85,0))),"对方科目不存在",IF(AND($E23="缴纳税费",$H23=""),"缴税请在费用项目里选税种",IF(AND($F23<>"",ISNA(MATCH($F23,往来单位!$A$6:$A$85,0))),"往来单位未建档",IF(YEAR($B23)<>参数设置!$B$5,"不在本会计年度",IF(AND($B22<>"",ISNUMBER($B22),$B23<$B22),"日期比上一行早，余额按行序滚，建议按日期录","OK"))))))))))))))) -> OK | O23: =IF($B23="","",TEXT($B23,"yyyy-mm")) -> 2026-08 | P23: =IF($E23="","",ROUND(N($I23)+N($J23),2)) -> 240000 | Q23: =IF($D23="","",IFERROR(INDEX(资金账户!$F$6:$F$25,MATCH($D23,资金账户!$B$6:$B$25,0)),"")) -> 银行存款 | R23: =IF($E23="","",IFERROR(IF(INDEX(记账规则!$A$13:$H$32,MATCH($E23,记账规则!$A$13:$A$32,0),4)="借","收","支"),"")) -> 收 | S23: =IF($D23="","",ROUND(SUMIFS(资金账户!$H$6:$H$25,资金账户!$B$6:$B$25,$D23)+SUMIFS($I$6:$I23,$D$6:$D23,$D23)-SUMIFS($J$6:$J23,$D$6:$D23,$D23),2)) -> 540000 | T23: =IF($B23="","",YEAR($B23)) -> 2026
A24: =IF($B24="","",ROW()-5) -> 19 | B24: 46265 | C24: 木业 | D24: 农商银行-共用户 | E24: 发放工资 | H24: 工资薪金 | J24: 50000 | K24: 发放车间及管理人员工资 | N24: =IF(AND($B24="",$E24="",$I24="",$J24=""),"",IF(NOT(ISNUMBER($B24)),"日期无效",IF(ISNA(MATCH($C24,参数设置!$A$10:$A$12,0)),"公司无效",IF(ISNA(MATCH($D24,资金账户!$B$6:$B$25,0)),"账户未建档",IF(ISNA(MATCH($E24,记账规则!$A$13:$A$32,0)),"业务类型无效",IF(AND(N($I24)<>0,N($J24)<>0),"收入和支出只能填一列",IF($P24=0,"金额为 0",IF(AND($R24="收",N($I24)=0),"这类业务是收款，金额填到收入列",IF(AND($R24="支",N($J24)=0),"这类业务是付款，金额填到支出列",IF(AND(SUMPRODUCT(--(INDEX(记账规则!$A$13:$H$32,MATCH($E24,记账规则!$A$13:$A$32,0),0)="@对方"))>0,$G24=""),"这个类型要填对方科目",IF(AND($G24<>"",ISNA(MATCH($G24,会计科目表!$B$6:$B$85,0))),"对方科目不存在",IF(AND($E24="缴纳税费",$H24=""),"缴税请在费用项目里选税种",IF(AND($F24<>"",ISNA(MATCH($F24,往来单位!$A$6:$A$85,0))),"往来单位未建档",IF(YEAR($B24)<>参数设置!$B$5,"不在本会计年度",IF(AND($B23<>"",ISNUMBER($B23),$B24<$B23),"日期比上一行早，余额按行序滚，建议按日期录","OK"))))))))))))))) -> OK | O24: =IF($B24="","",TEXT($B24,"yyyy-mm")) -> 2026-08 | P24: =IF($E24="","",ROUND(N($I24)+N($J24),2)) -> 50000 | Q24: =IF($D24="","",IFERROR(INDEX(资金账户!$F$6:$F$25,MATCH($D24,资金账户!$B$6:$B$25,0)),"")) -> 银行存款 | R24: =IF($E24="","",IFERROR(IF(INDEX(记账规则!$A$13:$H$32,MATCH($E24,记账规则!$A$13:$A$32,0),4)="借","收","支"),"")) -> 支 | S24: =IF($D24="","",ROUND(SUMIFS(资金账户!$H$6:$H$25,资金账户!$B$6:$B$25,$D24)+SUMIFS($I$6:$I24,$D$6:$D24,$D24)-SUMIFS($J$6:$J24,$D$6:$D24,$D24),2)) -> 490000 | T24: =IF($B24="","",YEAR($B24)) -> 2026
A25: =IF($B25="","",ROW()-5) -> 20 | B25: 46267 | C25: 农业 | D25: 农商银行-基本户 | E25: 收客户货款 | F25: 恒信木材行 | I25: 66000 | K25: 收原木货款 | L25: 购销 5 | N25: =IF(AND($B25="",$E25="",$I25="",$J25=""),"",IF(NOT(ISNUMBER($B25)),"日期无效",IF(ISNA(MATCH($C25,参数设置!$A$10:$A$12,0)),"公司无效",IF(ISNA(MATCH($D25,资金账户!$B$6:$B$25,0)),"账户未建档",IF(ISNA(MATCH($E25,记账规则!$A$13:$A$32,0)),"业务类型无效",IF(AND(N($I25)<>0,N($J25)<>0),"收入和支出只能填一列",IF($P25=0,"金额为 0",IF(AND($R25="收",N($I25)=0),"这类业务是收款，金额填到收入列",IF(AND($R25="支",N($J25)=0),"这类业务是付款，金额填到支出列",IF(AND(SUMPRODUCT(--(INDEX(记账规则!$A$13:$H$32,MATCH($E25,记账规则!$A$13:$A$32,0),0)="@对方"))>0,$G25=""),"这个类型要填对方科目",IF(AND($G25<>"",ISNA(MATCH($G25,会计科目表!$B$6:$B$85,0))),"对方科目不存在",IF(AND($E25="缴纳税费",$H25=""),"缴税请在费用项目里选税种",IF(AND($F25<>"",ISNA(MATCH($F25,往来单位!$A$6:$A$85,0))),"往来单位未建档",IF(YEAR($B25)<>参数设置!$B$5,"不在本会计年度",IF(AND($B24<>"",ISNUMBER($B24),$B25<$B24),"日期比上一行早，余额按行序滚，建议按日期录","OK"))))))))))))))) -> OK | O25: =IF($B25="","",TEXT($B25,"yyyy-mm")) -> 2026-09 | P25: =IF($E25="","",ROUND(N($I25)+N($J25),2)) -> 66000 | Q25: =IF($D25="","",IFERROR(INDEX(资金账户!$F$6:$F$25,MATCH($D25,资金账户!$B$6:$B$25,0)),"")) -> 银行存款 | R25: =IF($E25="","",IFERROR(IF(INDEX(记账规则!$A$13:$H$32,MATCH($E25,记账规则!$A$13:$A$32,0),4)="借","收","支"),"")) -> 收 | S25: =IF($D25="","",ROUND(SUMIFS(资金账户!$H$6:$H$25,资金账户!$B$6:$B$25,$D25)+SUMIFS($I$6:$I25,$D$6:$D25,$D25)-SUMIFS($J$6:$J25,$D$6:$D25,$D25),2)) -> 276000 | T25: =IF($B25="","",YEAR($B25)) -> 2026
A26: =IF($B26="","",ROW()-5) -> 21 | B26: 46267 | C26: 木业 | D26: 工商银行-基本户 | E26: 收客户货款 | F26: 顺达包装 | I26: 70000 | K26: 收包装箱板材货款 | L26: 购销 13 | N26: =IF(AND($B26="",$E26="",$I26="",$J26=""),"",IF(NOT(ISNUMBER($B26)),"日期无效",IF(ISNA(MATCH($C26,参数设置!$A$10:$A$12,0)),"公司无效",IF(ISNA(MATCH($D26,资金账户!$B$6:$B$25,0)),"账户未建档",IF(ISNA(MATCH($E26,记账规则!$A$13:$A$32,0)),"业务类型无效",IF(AND(N($I26)<>0,N($J26)<>0),"收入和支出只能填一列",IF($P26=0,"金额为 0",IF(AND($R26="收",N($I26)=0),"这类业务是收款，金额填到收入列",IF(AND($R26="支",N($J26)=0),"这类业务是付款，金额填到支出列",IF(AND(SUMPRODUCT(--(INDEX(记账规则!$A$13:$H$32,MATCH($E26,记账规则!$A$13:$A$32,0),0)="@对方"))>0,$G26=""),"这个类型要填对方科目",IF(AND($G26<>"",ISNA(MATCH($G26,会计科目表!$B$6:$B$85,0))),"对方科目不存在",IF(AND($E26="缴纳税费",$H26=""),"缴税请在费用项目里选税种",IF(AND($F26<>"",ISNA(MATCH($F26,往来单位!$A$6:$A$85,0))),"往来单位未建档",IF(YEAR($B26)<>参数设置!$B$5,"不在本会计年度",IF(AND($B25<>"",ISNUMBER($B25),$B26<$B25),"日期比上一行早，余额按行序滚，建议按日期录","OK"))))))))))))))) -> OK | O26: =IF($B26="","",TEXT($B26,"yyyy-mm")) -> 2026-09 | P26: =IF($E26="","",ROUND(N($I26)+N($J26),2)) -> 70000 | Q26: =IF($D26="","",IFERROR(INDEX(资金账户!$F$6:$F$25,MATCH($D26,资金账户!$B$6:$B$25,0)),"")) -> 银行存款 | R26: =IF($E26="","",IFERROR(IF(INDEX(记账规则!$A$13:$H$32,MATCH($E26,记账规则!$A$13:$A$32,0),4)="借","收","支"),"")) -> 收 | S26: =IF($D26="","",ROUND(SUMIFS(资金账户!$H$6:$H$25,资金账户!$B$6:$B$25,$D26)+SUMIFS($I$6:$I26,$D$6:$D26,$D26)-SUMIFS($J$6:$J26,$D$6:$D26,$D26),2)) -> 205600 | T26: =IF($B26="","",YEAR($B26)) -> 2026
A27: =IF($B27="","",ROW()-5) -> 22 | B27: 46270 | C27: 科技 | D27: 建设银行-基本户 | E27: 发放工资 | H27: 工资薪金 | J27: 18000 | K27: 发放上年计提工资 | N27: =IF(AND($B27="",$E27="",$I27="",$J27=""),"",IF(NOT(ISNUMBER($B27)),"日期无效",IF(ISNA(MATCH($C27,参数设置!$A$10:$A$12,0)),"公司无效",IF(ISNA(MATCH($D27,资金账户!$B$6:$B$25,0)),"账户未建档",IF(ISNA(MATCH($E27,记账规则!$A$13:$A$32,0)),"业务类型无效",IF(AND(N($I27)<>0,N($J27)<>0),"收入和支出只能填一列",IF($P27=0,"金额为 0",IF(AND($R27="收",N($I27)=0),"这类业务是收款，金额填到收入列",IF(AND($R27="支",N($J27)=0),"这类业务是付款，金额填到支出列",IF(AND(SUMPRODUCT(--(INDEX(记账规则!$A$13:$H$32,MATCH($E27,记账规则!$A$13:$A$32,0),0)="@对方"))>0,$G27=""),"这个类型要填对方科目",IF(AND($G27<>"",ISNA(MATCH($G27,会计科目表!$B$6:$B$85,0))),"对方科目不存在",IF(AND($E27="缴纳税费",$H27=""),"缴税请在费用项目里选税种",IF(AND($F27<>"",ISNA(MATCH($F27,往来单位!$A$6:$A$85,0))),"往来单位未建档",IF(YEAR($B27)<>参数设置!$B$5,"不在本会计年度",IF(AND($B26<>"",ISNUMBER($B26),$B27<$B26),"日期比上一行早，余额按行序滚，建议按日期录","OK"))))))))))))))) -> OK | O27: =IF($B27="","",TEXT($B27,"yyyy-mm")) -> 2026-09 | P27: =IF($E27="","",ROUND(N($I27)+N($J27),2)) -> 18000 | Q27: =IF($D27="","",IFERROR(INDEX(资金账户!$F$6:$F$25,MATCH($D27,资金账户!$B$6:$B$25,0)),"")) -> 银行存款 | R27: =IF($E27="","",IFERROR(IF(INDEX(记账规则!$A$13:$H$32,MATCH($E27,记账规则!$A$13:$A$32,0),4)="借","收","支"),"")) -> 支 | S27: =IF($D27="","",ROUND(SUMIFS(资金账户!$H$6:$H$25,资金账户!$B$6:$B$25,$D27)+SUMIFS($I$6:$I27,$D$6:$D27,$D27)-SUMIFS($J$6:$J27,$D$6:$D27,$D27),2)) -> 352220 | T27: =IF($B27="","",YEAR($B27)) -> 2026
A28: =IF($B28="","",ROW()-5) -> 23 | B28: 46275 | C28: 木业 | D28: 工商银行-基本户 | E28: 缴纳税费 | F28: 税务局 | G28: 税金及附加 | H28: 增值税 | J28: 28000 | K28: 申报缴纳增值税 | N28: =IF(AND($B28="",$E28="",$I28="",$J28=""),"",IF(NOT(ISNUMBER($B28)),"日期无效",IF(ISNA(MATCH($C28,参数设置!$A$10:$A$12,0)),"公司无效",IF(ISNA(MATCH($D28,资金账户!$B$6:$B$25,0)),"账户未建档",IF(ISNA(MATCH($E28,记账规则!$A$13:$A$32,0)),"业务类型无效",IF(AND(N($I28)<>0,N($J28)<>0),"收入和支出只能填一列",IF($P28=0,"金额为 0",IF(AND($R28="收",N($I28)=0),"这类业务是收款，金额填到收入列",IF(AND($R28="支",N($J28)=0),"这类业务是付款，金额填到支出列",IF(AND(SUMPRODUCT(--(INDEX(记账规则!$A$13:$H$32,MATCH($E28,记账规则!$A$13:$A$32,0),0)="@对方"))>0,$G28=""),"这个类型要填对方科目",IF(AND($G28<>"",ISNA(MATCH($G28,会计科目表!$B$6:$B$85,0))),"对方科目不存在",IF(AND($E28="缴纳税费",$H28=""),"缴税请在费用项目里选税种",IF(AND($F28<>"",ISNA(MATCH($F28,往来单位!$A$6:$A$85,0))),"往来单位未建档",IF(YEAR($B28)<>参数设置!$B$5,"不在本会计年度",IF(AND($B27<>"",ISNUMBER($B27),$B28<$B27),"日期比上一行早，余额按行序滚，建议按日期录","OK"))))))))))))))) -> OK | O28: =IF($B28="","",TEXT($B28,"yyyy-mm")) -> 2026-09 | P28: =IF($E28="","",ROUND(N($I28)+N($J28),2)) -> 28000 | Q28: =IF($D28="","",IFERROR(INDEX(资金账户!$F$6:$F$25,MATCH($D28,资金账户!$B$6:$B$25,0)),"")) -> 银行存款 | R28: =IF($E28="","",IFERROR(IF(INDEX(记账规则!$A$13:$H$32,MATCH($E28,记账规则!$A$13:$A$32,0),4)="借","收","支"),"")) -> 支 | S28: =IF($D28="","",ROUND(SUMIFS(资金账户!$H$6:$H$25,资金账户!$B$6:$B$25,$D28)+SUMIFS($I$6:$I28,$D$6:$D28,$D28)-SUMIFS($J$6:$J28,$D$6:$D28,$D28),2)) -> 177600 | T28: =IF($B28="","",YEAR($B28)) -> 2026
A29: =IF($B29="","",ROW()-5) -> 24 | B29: 46277 | C29: 木业 | D29: 现金-总部 | E29: 费用支出 | G29: 管理费用 | H29: 低值易耗品 | J29: 860 | K29: 零星用品 | N29: =IF(AND($B29="",$E29="",$I29="",$J29=""),"",IF(NOT(ISNUMBER($B29)),"日期无效",IF(ISNA(MATCH($C29,参数设置!$A$10:$A$12,0)),"公司无效",IF(ISNA(MATCH($D29,资金账户!$B$6:$B$25,0)),"账户未建档",IF(ISNA(MATCH($E29,记账规则!$A$13:$A$32,0)),"业务类型无效",IF(AND(N($I29)<>0,N($J29)<>0),"收入和支出只能填一列",IF($P29=0,"金额为 0",IF(AND($R29="收",N($I29)=0),"这类业务是收款，金额填到收入列",IF(AND($R29="支",N($J29)=0),"这类业务是付款，金额填到支出列",IF(AND(SUMPRODUCT(--(INDEX(记账规则!$A$13:$H$32,MATCH($E29,记账规则!$A$13:$A$32,0),0)="@对方"))>0,$G29=""),"这个类型要填对方科目",IF(AND($G29<>"",ISNA(MATCH($G29,会计科目表!$B$6:$B$85,0))),"对方科目不存在",IF(AND($E29="缴纳税费",$H29=""),"缴税请在费用项目里选税种",IF(AND($F29<>"",ISNA(MATCH($F29,往来单位!$A$6:$A$85,0))),"往来单位未建档",IF(YEAR($B29)<>参数设置!$B$5,"不在本会计年度",IF(AND($B28<>"",ISNUMBER($B28),$B29<$B28),"日期比上一行早，余额按行序滚，建议按日期录","OK"))))))))))))))) -> OK | O29: =IF($B29="","",TEXT($B29,"yyyy-mm")) -> 2026-09 | P29: =IF($E29="","",ROUND(N($I29)+N($J29),2)) -> 860 | Q29: =IF($D29="","",IFERROR(INDEX(资金账户!$F$6:$F$25,MATCH($D29,资金账户!$B$6:$B$25,0)),"")) -> 库存现金 | R29: =IF($E29="","",IFERROR(IF(INDEX(记账规则!$A$13:$H$32,MATCH($E29,记账规则!$A$13:$A$32,0),4)="借","收","支"),"")) -> 支 | S29: =IF($D29="","",ROUND(SUMIFS(资金账户!$H$6:$H$25,资金账户!$B$6:$B$25,$D29)+SUMIFS($I$6:$I29,$D$6:$D29,$D29)-SUMIFS($J$6:$J29,$D$6:$D29,$D29),2)) -> 9140 | T29: =IF($B29="","",YEAR($B29)) -> 2026
A30: =IF($B30="","",ROW()-5) -> 25 | B30: 46285 | C30: 农业 | D30: 农商银行-基本户 | E30: 收客户货款 | F30: 科技公司 | I30: 40000 | K30: 收科技公司干艾草款（内部） | L30: 购销 17 | N30: =IF(AND($B30="",$E30="",$I30="",$J30=""),"",IF(NOT(ISNUMBER($B30)),"日期无效",IF(ISNA(MATCH($C30,参数设置!$A$10:$A$12,0)),"公司无效",IF(ISNA(MATCH($D30,资金账户!$B$6:$B$25,0)),"账户未建档",IF(ISNA(MATCH($E30,记账规则!$A$13:$A$32,0)),"业务类型无效",IF(AND(N($I30)<>0,N($J30)<>0),"收入和支出只能填一列",IF($P30=0,"金额为 0",IF(AND($R30="收",N($I30)=0),"这类业务是收款，金额填到收入列",IF(AND($R30="支",N($J30)=0),"这类业务是付款，金额填到支出列",IF(AND(SUMPRODUCT(--(INDEX(记账规则!$A$13:$H$32,MATCH($E30,记账规则!$A$13:$A$32,0),0)="@对方"))>0,$G30=""),"这个类型要填对方科目",IF(AND($G30<>"",ISNA(MATCH($G30,会计科目表!$B$6:$B$85,0))),"对方科目不存在",IF(AND($E30="缴纳税费",$H30=""),"缴税请在费用项目里选税种",IF(AND($F30<>"",ISNA(MATCH($F30,往来单位!$A$6:$A$85,0))),"往来单位未建档",IF(YEAR($B30)<>参数设置!$B$5,"不在本会计年度",IF(AND($B29<>"",ISNUMBER($B29),$B30<$B29),"日期比上一行早，余额按行序滚，建议按日期录","OK"))))))))))))))) -> OK | O30: =IF($B30="","",TEXT($B30,"yyyy-mm")) -> 2026-09 | P30: =IF($E30="","",ROUND(N($I30)+N($J30),2)) -> 40000 | Q30: =IF($D30="","",IFERROR(INDEX(资金账户!$F$6:$F$25,MATCH($D30,资金账户!$B$6:$B$25,0)),"")) -> 银行存款 | R30: =IF($E30="","",IFERROR(IF(INDEX(记账规则!$A$13:$H$32,MATCH($E30,记账规则!$A$13:$A$32,0),4)="借","收","支"),"")) -> 收 | S30: =IF($D30="","",ROUND(SUMIFS(资金账户!$H$6:$H$25,资金账户!$B$6:$B$25,$D30)+SUMIFS($I$6:$I30,$D$6:$D30,$D30)-SUMIFS($J$6:$J30,$D$6:$D30,$D30),2)) -> 316000 | T30: =IF($B30="","",YEAR($B30)) -> 2026
A31: =IF($B31="","",ROW()-5) -> 26 | B31: 46285 | C31: 科技 | D31: 建设银行-基本户 | E31: 付供应商货款 | F31: 农业基地公司 | J31: 40000 | K31: 付农业基地干艾草款（内部） | L31: 购销 17 | N31: =IF(AND($B31="",$E31="",$I31="",$J31=""),"",IF(NOT(ISNUMBER($B31)),"日期无效",IF(ISNA(MATCH($C31,参数设置!$A$10:$A$12,0)),"公司无效",IF(ISNA(MATCH($D31,资金账户!$B$6:$B$25,0)),"账户未建档",IF(ISNA(MATCH($E31,记账规则!$A$13:$A$32,0)),"业务类型无效",IF(AND(N($I31)<>0,N($J31)<>0),"收入和支出只能填一列",IF($P31=0,"金额为 0",IF(AND($R31="收",N($I31)=0),"这类业务是收款，金额填到收入列",IF(AND($R31="支",N($J31)=0),"这类业务是付款，金额填到支出列",IF(AND(SUMPRODUCT(--(INDEX(记账规则!$A$13:$H$32,MATCH($E31,记账规则!$A$13:$A$32,0),0)="@对方"))>0,$G31=""),"这个类型要填对方科目",IF(AND($G31<>"",ISNA(MATCH($G31,会计科目表!$B$6:$B$85,0))),"对方科目不存在",IF(AND($E31="缴纳税费",$H31=""),"缴税请在费用项目里选税种",IF(AND($F31<>"",ISNA(MATCH($F31,往来单位!$A$6:$A$85,0))),"往来单位未建档",IF(YEAR($B31)<>参数设置!$B$5,"不在本会计年度",IF(AND($B30<>"",ISNUMBER($B30),$B31<$B30),"日期比上一行早，余额按行序滚，建议按日期录","OK"))))))))))))))) -> OK | O31: =IF($B31="","",TEXT($B31,"yyyy-mm")) -> 2026-09 | P31: =IF($E31="","",ROUND(N($I31)+N($J31),2)) -> 40000 | Q31: =IF($D31="","",IFERROR(INDEX(资金账户!$F$6:$F$25,MATCH($D31,资金账户!$B$6:$B$25,0)),"")) -> 银行存款 | R31: =IF($E31="","",IFERROR(IF(INDEX(记账规则!$A$13:$H$32,MATCH($E31,记账规则!$A$13:$A$32,0),4)="借","收","支"),"")) -> 支 | S31: =IF($D31="","",ROUND(SUMIFS(资金账户!$H$6:$H$25,资金账户!$B$6:$B$25,$D31)+SUMIFS($I$6:$I31,$D$6:$D31,$D31)-SUMIFS($J$6:$J31,$D$6:$D31,$D31),2)) -> 312220 | T31: =IF($B31="","",YEAR($B31)) -> 2026
A32: =IF($B32="","",ROW()-5) -> 27 | B32: 46295 | C32: 科技 | D32: 农商银行-共用户 | E32: 发放工资 | H32: 工资薪金 | J32: 55000 | K32: 发放三季度工资 | N32: =IF(AND($B32="",$E32="",$I32="",$J32=""),"",IF(NOT(ISNUMBER($B32)),"日期无效",IF(ISNA(MATCH($C32,参数设置!$A$10:$A$12,0)),"公司无效",IF(ISNA(MATCH($D32,资金账户!$B$6:$B$25,0)),"账户未建档",IF(ISNA(MATCH($E32,记账规则!$A$13:$A$32,0)),"业务类型无效",IF(AND(N($I32)<>0,N($J32)<>0),"收入和支出只能填一列",IF($P32=0,"金额为 0",IF(AND($R32="收",N($I32)=0),"这类业务是收款，金额填到收入列",IF(AND($R32="支",N($J32)=0),"这类业务是付款，金额填到支出列",IF(AND(SUMPRODUCT(--(INDEX(记账规则!$A$13:$H$32,MATCH($E32,记账规则!$A$13:$A$32,0),0)="@对方"))>0,$G32=""),"这个类型要填对方科目",IF(AND($G32<>"",ISNA(MATCH($G32,会计科目表!$B$6:$B$85,0))),"对方科目不存在",IF(AND($E32="缴纳税费",$H32=""),"缴税请在费用项目里选税种",IF(AND($F32<>"",ISNA(MATCH($F32,往来单位!$A$6:$A$85,0))),"往来单位未建档",IF(YEAR($B32)<>参数设置!$B$5,"不在本会计年度",IF(AND($B31<>"",ISNUMBER($B31),$B32<$B31),"日期比上一行早，余额按行序滚，建议按日期录","OK"))))))))))))))) -> OK | O32: =IF($B32="","",TEXT($B32,"yyyy-mm")) -> 2026-09 | P32: =IF($E32="","",ROUND(N($I32)+N($J32),2)) -> 55000 | Q32: =IF($D32="","",IFERROR(INDEX(资金账户!$F$6:$F$25,MATCH($D32,资金账户!$B$6:$B$25,0)),"")) -> 银行存款 | R32: =IF($E32="","",IFERROR(IF(INDEX(记账规则!$A$13:$H$32,MATCH($E32,记账规则!$A$13:$A$32,0),4)="借","收","支"),"")) -> 支 | S32: =IF($D32="","",ROUND(SUMIFS(资金账户!$H$6:$H$25,资金账户!$B$6:$B$25,$D32)+SUMIFS($I$6:$I32,$D$6:$D32,$D32)-SUMIFS($J$6:$J32,$D$6:$D32,$D32),2)) -> 435000 | T32: =IF($B32="","",YEAR($B32)) -> 2026
A33: =IF($B33="","",ROW()-5) -> 28 | B33: 46305 | C33: 科技 | D33: 建设银行-基本户 | E33: 收客户货款 | F33: 美悦日化 | I33: 90000 | K33: 收纯露货款 | L33: 购销 19 | N33: =IF(AND($B33="",$E33="",$I33="",$J33=""),"",IF(NOT(ISNUMBER($B33)),"日期无效",IF(ISNA(MATCH($C33,参数设置!$A$10:$A$12,0)),"公司无效",IF(ISNA(MATCH($D33,资金账户!$B$6:$B$25,0)),"账户未建档",IF(ISNA(MATCH($E33,记账规则!$A$13:$A$32,0)),"业务类型无效",IF(AND(N($I33)<>0,N($J33)<>0),"收入和支出只能填一列",IF($P33=0,"金额为 0",IF(AND($R33="收",N($I33)=0),"这类业务是收款，金额填到收入列",IF(AND($R33="支",N($J33)=0),"这类业务是付款，金额填到支出列",IF(AND(SUMPRODUCT(--(INDEX(记账规则!$A$13:$H$32,MATCH($E33,记账规则!$A$13:$A$32,0),0)="@对方"))>0,$G33=""),"这个类型要填对方科目",IF(AND($G33<>"",ISNA(MATCH($G33,会计科目表!$B$6:$B$85,0))),"对方科目不存在",IF(AND($E33="缴纳税费",$H33=""),"缴税请在费用项目里选税种",IF(AND($F33<>"",ISNA(MATCH($F33,往来单位!$A$6:$A$85,0))),"往来单位未建档",IF(YEAR($B33)<>参数设置!$B$5,"不在本会计年度",IF(AND($B32<>"",ISNUMBER($B32),$B33<$B32),"日期比上一行早，余额按行序滚，建议按日期录","OK"))))))))))))))) -> OK | O33: =IF($B33="","",TEXT($B33,"yyyy-mm")) -> 2026-10 | P33: =IF($E33="","",ROUND(N($I33)+N($J33),2)) -> 90000 | Q33: =IF($D33="","",IFERROR(INDEX(资金账户!$F$6:$F$25,MATCH($D33,资金账户!$B$6:$B$25,0)),"")) -> 银行存款 | R33: =IF($E33="","",IFERROR(IF(INDEX(记账规则!$A$13:$H$32,MATCH($E33,记账规则!$A$13:$A$32,0),4)="借","收","支"),"")) -> 收 | S33: =IF($D33="","",ROUND(SUMIFS(资金账户!$H$6:$H$25,资金账户!$B$6:$B$25,$D33)+SUMIFS($I$6:$I33,$D$6:$D33,$D33)-SUMIFS($J$6:$J33,$D$6:$D33,$D33),2)) -> 402220 | T33: =IF($B33="","",YEAR($B33)) -> 2026
A34: =IF($B34="","",ROW()-5) -> 29 | B34: 46310 | C34: 农业 | D34: 现金-总部 | E34: 费用支出 | G34: 管理费用 | H34: 差旅费 | J34: 1800 | K34: 林区巡查差旅 | N34: =IF(AND($B34="",$E34="",$I34="",$J34=""),"",IF(NOT(ISNUMBER($B34)),"日期无效",IF(ISNA(MATCH($C34,参数设置!$A$10:$A$12,0)),"公司无效",IF(ISNA(MATCH($D34,资金账户!$B$6:$B$25,0)),"账户未建档",IF(ISNA(MATCH($E34,记账规则!$A$13:$A$32,0)),"业务类型无效",IF(AND(N($I34)<>0,N($J34)<>0),"收入和支出只能填一列",IF($P34=0,"金额为 0",IF(AND($R34="收",N($I34)=0),"这类业务是收款，金额填到收入列",IF(AND($R34="支",N($J34)=0),"这类业务是付款，金额填到支出列",IF(AND(SUMPRODUCT(--(INDEX(记账规则!$A$13:$H$32,MATCH($E34,记账规则!$A$13:$A$32,0),0)="@对方"))>0,$G34=""),"这个类型要填对方科目",IF(AND($G34<>"",ISNA(MATCH($G34,会计科目表!$B$6:$B$85,0))),"对方科目不存在",IF(AND($E34="缴纳税费",$H34=""),"缴税请在费用项目里选税种",IF(AND($F34<>"",ISNA(MATCH($F34,往来单位!$A$6:$A$85,0))),"往来单位未建档",IF(YEAR($B34)<>参数设置!$B$5,"不在本会计年度",IF(AND($B33<>"",ISNUMBER($B33),$B34<$B33),"日期比上一行早，余额按行序滚，建议按日期录","OK"))))))))))))))) -> OK | O34: =IF($B34="","",TEXT($B34,"yyyy-mm")) -> 2026-10 | P34: =IF($E34="","",ROUND(N($I34)+N($J34),2)) -> 1800 | Q34: =IF($D34="","",IFERROR(INDEX(资金账户!$F$6:$F$25,MATCH($D34,资金账户!$B$6:$B$25,0)),"")) -> 库存现金 | R34: =IF($E34="","",IFERROR(IF(INDEX(记账规则!$A$13:$H$32,MATCH($E34,记账规则!$A$13:$A$32,0),4)="借","收","支"),"")) -> 支 | S34: =IF($D34="","",ROUND(SUMIFS(资金账户!$H$6:$H$25,资金账户!$B$6:$B$25,$D34)+SUMIFS($I$6:$I34,$D$6:$D34,$D34)-SUMIFS($J$6:$J34,$D$6:$D34,$D34),2)) -> 7340 | T34: =IF($B34="","",YEAR($B34)) -> 2026
A35: =IF($B35="","",ROW()-5) -> 30 | B35: 46315 | C35: 木业 | D35: 工商银行-基本户 | E35: 缴纳税费 | F35: 税务局 | G35: 税金及附加 | H35: 城建税及附加 | J35: 3360 | K35: 缴纳城建税及教育费附加 | N35: =IF(AND($B35="",$E35="",$I35="",$J35=""),"",IF(NOT(ISNUMBER($B35)),"日期无效",IF(ISNA(MATCH($C35,参数设置!$A$10:$A$12,0)),"公司无效",IF(ISNA(MATCH($D35,资金账户!$B$6:$B$25,0)),"账户未建档",IF(ISNA(MATCH($E35,记账规则!$A$13:$A$32,0)),"业务类型无效",IF(AND(N($I35)<>0,N($J35)<>0),"收入和支出只能填一列",IF($P35=0,"金额为 0",IF(AND($R35="收",N($I35)=0),"这类业务是收款，金额填到收入列",IF(AND($R35="支",N($J35)=0),"这类业务是付款，金额填到支出列",IF(AND(SUMPRODUCT(--(INDEX(记账规则!$A$13:$H$32,MATCH($E35,记账规则!$A$13:$A$32,0),0)="@对方"))>0,$G35=""),"这个类型要填对方科目",IF(AND($G35<>"",ISNA(MATCH($G35,会计科目表!$B$6:$B$85,0))),"对方科目不存在",IF(AND($E35="缴纳税费",$H35=""),"缴税请在费用项目里选税种",IF(AND($F35<>"",ISNA(MATCH($F35,往来单位!$A$6:$A$85,0))),"往来单位未建档",IF(YEAR($B35)<>参数设置!$B$5,"不在本会计年度",IF(AND($B34<>"",ISNUMBER($B34),$B35<$B34),"日期比上一行早，余额按行序滚，建议按日期录","OK"))))))))))))))) -> OK | O35: =IF($B35="","",TEXT($B35,"yyyy-mm")) -> 2026-10 | P35: =IF($E35="","",ROUND(N($I35)+N($J35),2)) -> 3360 | Q35: =IF($D35="","",IFERROR(INDEX(资金账户!$F$6:$F$25,MATCH($D35,资金账户!$B$6:$B$25,0)),"")) -> 银行存款 | R35: =IF($E35="","",IFERROR(IF(INDEX(记账规则!$A$13:$H$32,MATCH($E35,记账规则!$A$13:$A$32,0),4)="借","收","支"),"")) -> 支 | S35: =IF($D35="","",ROUND(SUMIFS(资金账户!$H$6:$H$25,资金账户!$B$6:$B$25,$D35)+SUMIFS($I$6:$I35,$D$6:$D35,$D35)-SUMIFS($J$6:$J35,$D$6:$D35,$D35),2)) -> 174240 | T35: =IF($B35="","",YEAR($B35)) -> 2026
A36: =IF($B36="","",ROW()-5) -> 31 | B36: 46315 | C36: 科技 | D36: 建设银行-基本户 | E36: 缴纳税费 | F36: 税务局 | G36: 税金及附加 | H36: 增值税 | J36: 38000 | K36: 申报缴纳增值税 | N36: =IF(AND($B36="",$E36="",$I36="",$J36=""),"",IF(NOT(ISNUMBER($B36)),"日期无效",IF(ISNA(MATCH($C36,参数设置!$A$10:$A$12,0)),"公司无效",IF(ISNA(MATCH($D36,资金账户!$B$6:$B$25,0)),"账户未建档",IF(ISNA(MATCH($E36,记账规则!$A$13:$A$32,0)),"业务类型无效",IF(AND(N($I36)<>0,N($J36)<>0),"收入和支出只能填一列",IF($P36=0,"金额为 0",IF(AND($R36="收",N($I36)=0),"这类业务是收款，金额填到收入列",IF(AND($R36="支",N($J36)=0),"这类业务是付款，金额填到支出列",IF(AND(SUMPRODUCT(--(INDEX(记账规则!$A$13:$H$32,MATCH($E36,记账规则!$A$13:$A$32,0),0)="@对方"))>0,$G36=""),"这个类型要填对方科目",IF(AND($G36<>"",ISNA(MATCH($G36,会计科目表!$B$6:$B$85,0))),"对方科目不存在",IF(AND($E36="缴纳税费",$H36=""),"缴税请在费用项目里选税种",IF(AND($F36<>"",ISNA(MATCH($F36,往来单位!$A$6:$A$85,0))),"往来单位未建档",IF(YEAR($B36)<>参数设置!$B$5,"不在本会计年度",IF(AND($B35<>"",ISNUMBER($B35),$B36<$B35),"日期比上一行早，余额按行序滚，建议按日期录","OK"))))))))))))))) -> OK | O36: =IF($B36="","",TEXT($B36,"yyyy-mm")) -> 2026-10 | P36: =IF($E36="","",ROUND(N($I36)+N($J36),2)) -> 38000 | Q36: =IF($D36="","",IFERROR(INDEX(资金账户!$F$6:$F$25,MATCH($D36,资金账户!$B$6:$B$25,0)),"")) -> 银行存款 | R36: =IF($E36="","",IFERROR(IF(INDEX(记账规则!$A$13:$H$32,MATCH($E36,记账规则!$A$13:$A$32,0),4)="借","收","支"),"")) -> 支 | S36: =IF($D36="","",ROUND(SUMIFS(资金账户!$H$6:$H$25,资金账户!$B$6:$B$25,$D36)+SUMIFS($I$6:$I36,$D$6:$D36,$D36)-SUMIFS($J$6:$J36,$D$6:$D36,$D36),2)) -> 364220 | T36: =IF($B36="","",YEAR($B36)) -> 2026
A37: =IF($B37="","",ROW()-5) -> 32 | B37: 46346 | C37: 科技 | D37: 建设银行-基本户 | E37: 缴纳税费 | F37: 税务局 | G37: 税金及附加 | H37: 城建税及附加 | J37: 4560 | K37: 缴纳城建税及教育费附加 | N37: =IF(AND($B37="",$E37="",$I37="",$J37=""),"",IF(NOT(ISNUMBER($B37)),"日期无效",IF(ISNA(MATCH($C37,参数设置!$A$10:$A$12,0)),"公司无效",IF(ISNA(MATCH($D37,资金账户!$B$6:$B$25,0)),"账户未建档",IF(ISNA(MATCH($E37,记账规则!$A$13:$A$32,0)),"业务类型无效",IF(AND(N($I37)<>0,N($J37)<>0),"收入和支出只能填一列",IF($P37=0,"金额为 0",IF(AND($R37="收",N($I37)=0),"这类业务是收款，金额填到收入列",IF(AND($R37="支",N($J37)=0),"这类业务是付款，金额填到支出列",IF(AND(SUMPRODUCT(--(INDEX(记账规则!$A$13:$H$32,MATCH($E37,记账规则!$A$13:$A$32,0),0)="@对方"))>0,$G37=""),"这个类型要填对方科目",IF(AND($G37<>"",ISNA(MATCH($G37,会计科目表!$B$6:$B$85,0))),"对方科目不存在",IF(AND($E37="缴纳税费",$H37=""),"缴税请在费用项目里选税种",IF(AND($F37<>"",ISNA(MATCH($F37,往来单位!$A$6:$A$85,0))),"往来单位未建档",IF(YEAR($B37)<>参数设置!$B$5,"不在本会计年度",IF(AND($B36<>"",ISNUMBER($B36),$B37<$B36),"日期比上一行早，余额按行序滚，建议按日期录","OK"))))))))))))))) -> OK | O37: =IF($B37="","",TEXT($B37,"yyyy-mm")) -> 2026-11 | P37: =IF($E37="","",ROUND(N($I37)+N($J37),2)) -> 4560 | Q37: =IF($D37="","",IFERROR(INDEX(资金账户!$F$6:$F$25,MATCH($D37,资金账户!$B$6:$B$25,0)),"")) -> 银行存款 | R37: =IF($E37="","",IFERROR(IF(INDEX(记账规则!$A$13:$H$32,MATCH($E37,记账规则!$A$13:$A$32,0),4)="借","收","支"),"")) -> 支 | S37: =IF($D37="","",ROUND(SUMIFS(资金账户!$H$6:$H$25,资金账户!$B$6:$B$25,$D37)+SUMIFS($I$6:$I37,$D$6:$D37,$D37)-SUMIFS($J$6:$J37,$D$6:$D37,$D37),2)) -> 359660 | T37: =IF($B37="","",YEAR($B37)) -> 2026
A38: =IF($B38="","",ROW()-5) -> 33 | B38: 46376 | C38: 木业 | D38: 工商银行-基本户 | E38: 缴纳税费 | F38: 税务局 | G38: 所得税费用 | H38: 企业所得税 | J38: 6000 | K38: 预缴企业所得税 | N38: =IF(AND($B38="",$E38="",$I38="",$J38=""),"",IF(NOT(ISNUMBER($B38)),"日期无效",IF(ISNA(MATCH($C38,参数设置!$A$10:$A$12,0)),"公司无效",IF(ISNA(MATCH($D38,资金账户!$B$6:$B$25,0)),"账户未建档",IF(ISNA(MATCH($E38,记账规则!$A$13:$A$32,0)),"业务类型无效",IF(AND(N($I38)<>0,N($J38)<>0),"收入和支出只能填一列",IF($P38=0,"金额为 0",IF(AND($R38="收",N($I38)=0),"这类业务是收款，金额填到收入列",IF(AND($R38="支",N($J38)=0),"这类业务是付款，金额填到支出列",IF(AND(SUMPRODUCT(--(INDEX(记账规则!$A$13:$H$32,MATCH($E38,记账规则!$A$13:$A$32,0),0)="@对方"))>0,$G38=""),"这个类型要填对方科目",IF(AND($G38<>"",ISNA(MATCH($G38,会计科目表!$B$6:$B$85,0))),"对方科目不存在",IF(AND($E38="缴纳税费",$H38=""),"缴税请在费用项目里选税种",IF(AND($F38<>"",ISNA(MATCH($F38,往来单位!$A$6:$A$85,0))),"往来单位未建档",IF(YEAR($B38)<>参数设置!$B$5,"不在本会计年度",IF(AND($B37<>"",ISNUMBER($B37),$B38<$B37),"日期比上一行早，余额按行序滚，建议按日期录","OK"))))))))))))))) -> OK | O38: =IF($B38="","",TEXT($B38,"yyyy-mm")) -> 2026-12 | P38: =IF($E38="","",ROUND(N($I38)+N($J38),2)) -> 6000 | Q38: =IF($D38="","",IFERROR(INDEX(资金账户!$F$6:$F$25,MATCH($D38,资金账户!$B$6:$B$25,0)),"")) -> 银行存款 | R38: =IF($E38="","",IFERROR(IF(INDEX(记账规则!$A$13:$H$32,MATCH($E38,记账规则!$A$13:$A$32,0),4)="借","收","支"),"")) -> 支 | S38: =IF($D38="","",ROUND(SUMIFS(资金账户!$H$6:$H$25,资金账户!$B$6:$B$25,$D38)+SUMIFS($I$6:$I38,$D$6:$D38,$D38)-SUMIFS($J$6:$J38,$D$6:$D38,$D38),2)) -> 168240 | T38: =IF($B38="","",YEAR($B38)) -> 2026
A39: =IF($B39="","",ROW()-5) -> 34 | B39: 46376 | C39: 科技 | D39: 建设银行-基本户 | E39: 缴纳税费 | F39: 税务局 | G39: 所得税费用 | H39: 企业所得税 | J39: 12000 | K39: 预缴企业所得税 | N39: =IF(AND($B39="",$E39="",$I39="",$J39=""),"",IF(NOT(ISNUMBER($B39)),"日期无效",IF(ISNA(MATCH($C39,参数设置!$A$10:$A$12,0)),"公司无效",IF(ISNA(MATCH($D39,资金账户!$B$6:$B$25,0)),"账户未建档",IF(ISNA(MATCH($E39,记账规则!$A$13:$A$32,0)),"业务类型无效",IF(AND(N($I39)<>0,N($J39)<>0),"收入和支出只能填一列",IF($P39=0,"金额为 0",IF(AND($R39="收",N($I39)=0),"这类业务是收款，金额填到收入列",IF(AND($R39="支",N($J39)=0),"这类业务是付款，金额填到支出列",IF(AND(SUMPRODUCT(--(INDEX(记账规则!$A$13:$H$32,MATCH($E39,记账规则!$A$13:$A$32,0),0)="@对方"))>0,$G39=""),"这个类型要填对方科目",IF(AND($G39<>"",ISNA(MATCH($G39,会计科目表!$B$6:$B$85,0))),"对方科目不存在",IF(AND($E39="缴纳税费",$H39=""),"缴税请在费用项目里选税种",IF(AND($F39<>"",ISNA(MATCH($F39,往来单位!$A$6:$A$85,0))),"往来单位未建档",IF(YEAR($B39)<>参数设置!$B$5,"不在本会计年度",IF(AND($B38<>"",ISNUMBER($B38),$B39<$B38),"日期比上一行早，余额按行序滚，建议按日期录","OK"))))))))))))))) -> OK | O39: =IF($B39="","",TEXT($B39,"yyyy-mm")) -> 2026-12 | P39: =IF($E39="","",ROUND(N($I39)+N($J39),2)) -> 12000 | Q39: =IF($D39="","",IFERROR(INDEX(资金账户!$F$6:$F$25,MATCH($D39,资金账户!$B$6:$B$25,0)),"")) -> 银行存款 | R39: =IF($E39="","",IFERROR(IF(INDEX(记账规则!$A$13:$H$32,MATCH($E39,记账规则!$A$13:$A$32,0),4)="借","收","支"),"")) -> 支 | S39: =IF($D39="","",ROUND(SUMIFS(资金账户!$H$6:$H$25,资金账户!$B$6:$B$25,$D39)+SUMIFS($I$6:$I39,$D$6:$D39,$D39)-SUMIFS($J$6:$J39,$D$6:$D39,$D39),2)) -> 347660 | T39: =IF($B39="","",YEAR($B39)) -> 2026
A40: =IF($B40="","",ROW()-5) | N40: =IF(AND($B40="",$E40="",$I40="",$J40=""),"",IF(NOT(ISNUMBER($B40)),"日期无效",IF(ISNA(MATCH($C40,参数设置!$A$10:$A$12,0)),"公司无效",IF(ISNA(MATCH($D40,资金账户!$B$6:$B$25,0)),"账户未建档",IF(ISNA(MATCH($E40,记账规则!$A$13:$A$32,0)),"业务类型无效",IF(AND(N($I40)<>0,N($J40)<>0),"收入和支出只能填一列",IF($P40=0,"金额为 0",IF(AND($R40="收",N($I40)=0),"这类业务是收款，金额填到收入列",IF(AND($R40="支",N($J40)=0),"这类业务是付款，金额填到支出列",IF(AND(SUMPRODUCT(--(INDEX(记账规则!$A$13:$H$32,MATCH($E40,记账规则!$A$13:$A$32,0),0)="@对方"))>0,$G40=""),"这个类型要填对方科目",IF(AND($G40<>"",ISNA(MATCH($G40,会计科目表!$B$6:$B$85,0))),"对方科目不存在",IF(AND($E40="缴纳税费",$H40=""),"缴税请在费用项目里选税种",IF(AND($F40<>"",ISNA(MATCH($F40,往来单位!$A$6:$A$85,0))),"往来单位未建档",IF(YEAR($B40)<>参数设置!$B$5,"不在本会计年度",IF(AND($B39<>"",ISNUMBER($B39),$B40<$B39),"日期比上一行早，余额按行序滚，建议按日期录","OK"))))))))))))))) | O40: =IF($B40="","",TEXT($B40,"yyyy-mm")) | P40: =IF($E40="","",ROUND(N($I40)+N($J40),2)) | Q40: =IF($D40="","",IFERROR(INDEX(资金账户!$F$6:$F$25,MATCH($D40,资金账户!$B$6:$B$25,0)),"")) | R40: =IF($E40="","",IFERROR(IF(INDEX(记账规则!$A$13:$H$32,MATCH($E40,记账规则!$A$13:$A$32,0),4)="借","收","支"),"")) | S40: =IF($D40="","",ROUND(SUMIFS(资金账户!$H$6:$H$25,资金账户!$B$6:$B$25,$D40)+SUMIFS($I$6:$I40,$D$6:$D40,$D40)-SUMIFS($J$6:$J40,$D$6:$D40,$D40),2)) | T40: =IF($B40="","",YEAR($B40))
A41: =IF($B41="","",ROW()-5) | N41: =IF(AND($B41="",$E41="",$I41="",$J41=""),"",IF(NOT(ISNUMBER($B41)),"日期无效",IF(ISNA(MATCH($C41,参数设置!$A$10:$A$12,0)),"公司无效",IF(ISNA(MATCH($D41,资金账户!$B$6:$B$25,0)),"账户未建档",IF(ISNA(MATCH($E41,记账规则!$A$13:$A$32,0)),"业务类型无效",IF(AND(N($I41)<>0,N($J41)<>0),"收入和支出只能填一列",IF($P41=0,"金额为 0",IF(AND($R41="收",N($I41)=0),"这类业务是收款，金额填到收入列",IF(AND($R41="支",N($J41)=0),"这类业务是付款，金额填到支出列",IF(AND(SUMPRODUCT(--(INDEX(记账规则!$A$13:$H$32,MATCH($E41,记账规则!$A$13:$A$32,0),0)="@对方"))>0,$G41=""),"这个类型要填对方科目",IF(AND($G41<>"",ISNA(MATCH($G41,会计科目表!$B$6:$B$85,0))),"对方科目不存在",IF(AND($E41="缴纳税费",$H41=""),"缴税请在费用项目里选税种",IF(AND($F41<>"",ISNA(MATCH($F41,往来单位!$A$6:$A$85,0))),"往来单位未建档",IF(YEAR($B41)<>参数设置!$B$5,"不在本会计年度",IF(AND($B40<>"",ISNUMBER($B40),$B41<$B40),"日期比上一行早，余额按行序滚，建议按日期录","OK"))))))))))))))) | O41: =IF($B41="","",TEXT($B41,"yyyy-mm")) | P41: =IF($E41="","",ROUND(N($I41)+N($J41),2)) | Q41: =IF($D41="","",IFERROR(INDEX(资金账户!$F$6:$F$25,MATCH($D41,资金账户!$B$6:$B$25,0)),"")) | R41: =IF($E41="","",IFERROR(IF(INDEX(记账规则!$A$13:$H$32,MATCH($E41,记账规则!$A$13:$A$32,0),4)="借","收","支"),"")) | S41: =IF($D41="","",ROUND(SUMIFS(资金账户!$H$6:$H$25,资金账户!$B$6:$B$25,$D41)+SUMIFS($I$6:$I41,$D$6:$D41,$D41)-SUMIFS($J$6:$J41,$D$6:$D41,$D41),2)) | T41: =IF($B41="","",YEAR($B41))
A42: =IF($B42="","",ROW()-5) | N42: =IF(AND($B42="",$E42="",$I42="",$J42=""),"",IF(NOT(ISNUMBER($B42)),"日期无效",IF(ISNA(MATCH($C42,参数设置!$A$10:$A$12,0)),"公司无效",IF(ISNA(MATCH($D42,资金账户!$B$6:$B$25,0)),"账户未建档",IF(ISNA(MATCH($E42,记账规则!$A$13:$A$32,0)),"业务类型无效",IF(AND(N($I42)<>0,N($J42)<>0),"收入和支出只能填一列",IF($P42=0,"金额为 0",IF(AND($R42="收",N($I42)=0),"这类业务是收款，金额填到收入列",IF(AND($R42="支",N($J42)=0),"这类业务是付款，金额填到支出列",IF(AND(SUMPRODUCT(--(INDEX(记账规则!$A$13:$H$32,MATCH($E42,记账规则!$A$13:$A$32,0),0)="@对方"))>0,$G42=""),"这个类型要填对方科目",IF(AND($G42<>"",ISNA(MATCH($G42,会计科目表!$B$6:$B$85,0))),"对方科目不存在",IF(AND($E42="缴纳税费",$H42=""),"缴税请在费用项目里选税种",IF(AND($F42<>"",ISNA(MATCH($F42,往来单位!$A$6:$A$85,0))),"往来单位未建档",IF(YEAR($B42)<>参数设置!$B$5,"不在本会计年度",IF(AND($B41<>"",ISNUMBER($B41),$B42<$B41),"日期比上一行早，余额按行序滚，建议按日期录","OK"))))))))))))))) | O42: =IF($B42="","",TEXT($B42,"yyyy-mm")) | P42: =IF($E42="","",ROUND(N($I42)+N($J42),2)) | Q42: =IF($D42="","",IFERROR(INDEX(资金账户!$F$6:$F$25,MATCH($D42,资金账户!$B$6:$B$25,0)),"")) | R42: =IF($E42="","",IFERROR(IF(INDEX(记账规则!$A$13:$H$32,MATCH($E42,记账规则!$A$13:$A$32,0),4)="借","收","支"),"")) | S42: =IF($D42="","",ROUND(SUMIFS(资金账户!$H$6:$H$25,资金账户!$B$6:$B$25,$D42)+SUMIFS($I$6:$I42,$D$6:$D42,$D42)-SUMIFS($J$6:$J42,$D$6:$D42,$D42),2)) | T42: =IF($B42="","",YEAR($B42))
A43: =IF($B43="","",ROW()-5) | N43: =IF(AND($B43="",$E43="",$I43="",$J43=""),"",IF(NOT(ISNUMBER($B43)),"日期无效",IF(ISNA(MATCH($C43,参数设置!$A$10:$A$12,0)),"公司无效",IF(ISNA(MATCH($D43,资金账户!$B$6:$B$25,0)),"账户未建档",IF(ISNA(MATCH($E43,记账规则!$A$13:$A$32,0)),"业务类型无效",IF(AND(N($I43)<>0,N($J43)<>0),"收入和支出只能填一列",IF($P43=0,"金额为 0",IF(AND($R43="收",N($I43)=0),"这类业务是收款，金额填到收入列",IF(AND($R43="支",N($J43)=0),"这类业务是付款，金额填到支出列",IF(AND(SUMPRODUCT(--(INDEX(记账规则!$A$13:$H$32,MATCH($E43,记账规则!$A$13:$A$32,0),0)="@对方"))>0,$G43=""),"这个类型要填对方科目",IF(AND($G43<>"",ISNA(MATCH($G43,会计科目表!$B$6:$B$85,0))),"对方科目不存在",IF(AND($E43="缴纳税费",$H43=""),"缴税请在费用项目里选税种",IF(AND($F43<>"",ISNA(MATCH($F43,往来单位!$A$6:$A$85,0))),"往来单位未建档",IF(YEAR($B43)<>参数设置!$B$5,"不在本会计年度",IF(AND($B42<>"",ISNUMBER($B42),$B43<$B42),"日期比上一行早，余额按行序滚，建议按日期录","OK"))))))))))))))) | O43: =IF($B43="","",TEXT($B43,"yyyy-mm")) | P43: =IF($E43="","",ROUND(N($I43)+N($J43),2)) | Q43: =IF($D43="","",IFERROR(INDEX(资金账户!$F$6:$F$25,MATCH($D43,资金账户!$B$6:$B$25,0)),"")) | R43: =IF($E43="","",IFERROR(IF(INDEX(记账规则!$A$13:$H$32,MATCH($E43,记账规则!$A$13:$A$32,0),4)="借","收","支"),"")) | S43: =IF($D43="","",ROUND(SUMIFS(资金账户!$H$6:$H$25,资金账户!$B$6:$B$25,$D43)+SUMIFS($I$6:$I43,$D$6:$D43,$D43)-SUMIFS($J$6:$J43,$D$6:$D43,$D43),2)) | T43: =IF($B43="","",YEAR($B43))
A44: =IF($B44="","",ROW()-5) | N44: =IF(AND($B44="",$E44="",$I44="",$J44=""),"",IF(NOT(ISNUMBER($B44)),"日期无效",IF(ISNA(MATCH($C44,参数设置!$A$10:$A$12,0)),"公司无效",IF(ISNA(MATCH($D44,资金账户!$B$6:$B$25,0)),"账户未建档",IF(ISNA(MATCH($E44,记账规则!$A$13:$A$32,0)),"业务类型无效",IF(AND(N($I44)<>0,N($J44)<>0),"收入和支出只能填一列",IF($P44=0,"金额为 0",IF(AND($R44="收",N($I44)=0),"这类业务是收款，金额填到收入列",IF(AND($R44="支",N($J44)=0),"这类业务是付款，金额填到支出列",IF(AND(SUMPRODUCT(--(INDEX(记账规则!$A$13:$H$32,MATCH($E44,记账规则!$A$13:$A$32,0),0)="@对方"))>0,$G44=""),"这个类型要填对方科目",IF(AND($G44<>"",ISNA(MATCH($G44,会计科目表!$B$6:$B$85,0))),"对方科目不存在",IF(AND($E44="缴纳税费",$H44=""),"缴税请在费用项目里选税种",IF(AND($F44<>"",ISNA(MATCH($F44,往来单位!$A$6:$A$85,0))),"往来单位未建档",IF(YEAR($B44)<>参数设置!$B$5,"不在本会计年度",IF(AND($B43<>"",ISNUMBER($B43),$B44<$B43),"日期比上一行早，余额按行序滚，建议按日期录","OK"))))))))))))))) | O44: =IF($B44="","",TEXT($B44,"yyyy-mm")) | P44: =IF($E44="","",ROUND(N($I44)+N($J44),2)) | Q44: =IF($D44="","",IFERROR(INDEX(资金账户!$F$6:$F$25,MATCH($D44,资金账户!$B$6:$B$25,0)),"")) | R44: =IF($E44="","",IFERROR(IF(INDEX(记账规则!$A$13:$H$32,MATCH($E44,记账规则!$A$13:$A$32,0),4)="借","收","支"),"")) | S44: =IF($D44="","",ROUND(SUMIFS(资金账户!$H$6:$H$25,资金账户!$B$6:$B$25,$D44)+SUMIFS($I$6:$I44,$D$6:$D44,$D44)-SUMIFS($J$6:$J44,$D$6:$D44,$D44),2)) | T44: =IF($B44="","",YEAR($B44))
A45: =IF($B45="","",ROW()-5) | N45: =IF(AND($B45="",$E45="",$I45="",$J45=""),"",IF(NOT(ISNUMBER($B45)),"日期无效",IF(ISNA(MATCH($C45,参数设置!$A$10:$A$12,0)),"公司无效",IF(ISNA(MATCH($D45,资金账户!$B$6:$B$25,0)),"账户未建档",IF(ISNA(MATCH($E45,记账规则!$A$13:$A$32,0)),"业务类型无效",IF(AND(N($I45)<>0,N($J45)<>0),"收入和支出只能填一列",IF($P45=0,"金额为 0",IF(AND($R45="收",N($I45)=0),"这类业务是收款，金额填到收入列",IF(AND($R45="支",N($J45)=0),"这类业务是付款，金额填到支出列",IF(AND(SUMPRODUCT(--(INDEX(记账规则!$A$13:$H$32,MATCH($E45,记账规则!$A$13:$A$32,0),0)="@对方"))>0,$G45=""),"这个类型要填对方科目",IF(AND($G45<>"",ISNA(MATCH($G45,会计科目表!$B$6:$B$85,0))),"对方科目不存在",IF(AND($E45="缴纳税费",$H45=""),"缴税请在费用项目里选税种",IF(AND($F45<>"",ISNA(MATCH($F45,往来单位!$A$6:$A$85,0))),"往来单位未建档",IF(YEAR($B45)<>参数设置!$B$5,"不在本会计年度",IF(AND($B44<>"",ISNUMBER($B44),$B45<$B44),"日期比上一行早，余额按行序滚，建议按日期录","OK"))))))))))))))) | O45: =IF($B45="","",TEXT($B45,"yyyy-mm")) | P45: =IF($E45="","",ROUND(N($I45)+N($J45),2)) | Q45: =IF($D45="","",IFERROR(INDEX(资金账户!$F$6:$F$25,MATCH($D45,资金账户!$B$6:$B$25,0)),"")) | R45: =IF($E45="","",IFERROR(IF(INDEX(记账规则!$A$13:$H$32,MATCH($E45,记账规则!$A$13:$A$32,0),4)="借","收","支"),"")) | S45: =IF($D45="","",ROUND(SUMIFS(资金账户!$H$6:$H$25,资金账户!$B$6:$B$25,$D45)+SUMIFS($I$6:$I45,$D$6:$D45,$D45)-SUMIFS($J$6:$J45,$D$6:$D45,$D45),2)) | T45: =IF($B45="","",YEAR($B45))
A46: =IF($B46="","",ROW()-5) | N46: =IF(AND($B46="",$E46="",$I46="",$J46=""),"",IF(NOT(ISNUMBER($B46)),"日期无效",IF(ISNA(MATCH($C46,参数设置!$A$10:$A$12,0)),"公司无效",IF(ISNA(MATCH($D46,资金账户!$B$6:$B$25,0)),"账户未建档",IF(ISNA(MATCH($E46,记账规则!$A$13:$A$32,0)),"业务类型无效",IF(AND(N($I46)<>0,N($J46)<>0),"收入和支出只能填一列",IF($P46=0,"金额为 0",IF(AND($R46="收",N($I46)=0),"这类业务是收款，金额填到收入列",IF(AND($R46="支",N($J46)=0),"这类业务是付款，金额填到支出列",IF(AND(SUMPRODUCT(--(INDEX(记账规则!$A$13:$H$32,MATCH($E46,记账规则!$A$13:$A$32,0),0)="@对方"))>0,$G46=""),"这个类型要填对方科目",IF(AND($G46<>"",ISNA(MATCH($G46,会计科目表!$B$6:$B$85,0))),"对方科目不存在",IF(AND($E46="缴纳税费",$H46=""),"缴税请在费用项目里选税种",IF(AND($F46<>"",ISNA(MATCH($F46,往来单位!$A$6:$A$85,0))),"往来单位未建档",IF(YEAR($B46)<>参数设置!$B$5,"不在本会计年度",IF(AND($B45<>"",ISNUMBER($B45),$B46<$B45),"日期比上一行早，余额按行序滚，建议按日期录","OK"))))))))))))))) | O46: =IF($B46="","",TEXT($B46,"yyyy-mm")) | P46: =IF($E46="","",ROUND(N($I46)+N($J46),2)) | Q46: =IF($D46="","",IFERROR(INDEX(资金账户!$F$6:$F$25,MATCH($D46,资金账户!$B$6:$B$25,0)),"")) | R46: =IF($E46="","",IFERROR(IF(INDEX(记账规则!$A$13:$H$32,MATCH($E46,记账规则!$A$13:$A$32,0),4)="借","收","支"),"")) | S46: =IF($D46="","",ROUND(SUMIFS(资金账户!$H$6:$H$25,资金账户!$B$6:$B$25,$D46)+SUMIFS($I$6:$I46,$D$6:$D46,$D46)-SUMIFS($J$6:$J46,$D$6:$D46,$D46),2)) | T46: =IF($B46="","",YEAR($B46))
A47: =IF($B47="","",ROW()-5) | N47: =IF(AND($B47="",$E47="",$I47="",$J47=""),"",IF(NOT(ISNUMBER($B47)),"日期无效",IF(ISNA(MATCH($C47,参数设置!$A$10:$A$12,0)),"公司无效",IF(ISNA(MATCH($D47,资金账户!$B$6:$B$25,0)),"账户未建档",IF(ISNA(MATCH($E47,记账规则!$A$13:$A$32,0)),"业务类型无效",IF(AND(N($I47)<>0,N($J47)<>0),"收入和支出只能填一列",IF($P47=0,"金额为 0",IF(AND($R47="收",N($I47)=0),"这类业务是收款，金额填到收入列",IF(AND($R47="支",N($J47)=0),"这类业务是付款，金额填到支出列",IF(AND(SUMPRODUCT(--(INDEX(记账规则!$A$13:$H$32,MATCH($E47,记账规则!$A$13:$A$32,0),0)="@对方"))>0,$G47=""),"这个类型要填对方科目",IF(AND($G47<>"",ISNA(MATCH($G47,会计科目表!$B$6:$B$85,0))),"对方科目不存在",IF(AND($E47="缴纳税费",$H47=""),"缴税请在费用项目里选税种",IF(AND($F47<>"",ISNA(MATCH($F47,往来单位!$A$6:$A$85,0))),"往来单位未建档",IF(YEAR($B47)<>参数设置!$B$5,"不在本会计年度",IF(AND($B46<>"",ISNUMBER($B46),$B47<$B46),"日期比上一行早，余额按行序滚，建议按日期录","OK"))))))))))))))) | O47: =IF($B47="","",TEXT($B47,"yyyy-mm")) | P47: =IF($E47="","",ROUND(N($I47)+N($J47),2)) | Q47: =IF($D47="","",IFERROR(INDEX(资金账户!$F$6:$F$25,MATCH($D47,资金账户!$B$6:$B$25,0)),"")) | R47: =IF($E47="","",IFERROR(IF(INDEX(记账规则!$A$13:$H$32,MATCH($E47,记账规则!$A$13:$A$32,0),4)="借","收","支"),"")) | S47: =IF($D47="","",ROUND(SUMIFS(资金账户!$H$6:$H$25,资金账户!$B$6:$B$25,$D47)+SUMIFS($I$6:$I47,$D$6:$D47,$D47)-SUMIFS($J$6:$J47,$D$6:$D47,$D47),2)) | T47: =IF($B47="","",YEAR($B47))
A48: =IF($B48="","",ROW()-5) | N48: =IF(AND($B48="",$E48="",$I48="",$J48=""),"",IF(NOT(ISNUMBER($B48)),"日期无效",IF(ISNA(MATCH($C48,参数设置!$A$10:$A$12,0)),"公司无效",IF(ISNA(MATCH($D48,资金账户!$B$6:$B$25,0)),"账户未建档",IF(ISNA(MATCH($E48,记账规则!$A$13:$A$32,0)),"业务类型无效",IF(AND(N($I48)<>0,N($J48)<>0),"收入和支出只能填一列",IF($P48=0,"金额为 0",IF(AND($R48="收",N($I48)=0),"这类业务是收款，金额填到收入列",IF(AND($R48="支",N($J48)=0),"这类业务是付款，金额填到支出列",IF(AND(SUMPRODUCT(--(INDEX(记账规则!$A$13:$H$32,MATCH($E48,记账规则!$A$13:$A$32,0),0)="@对方"))>0,$G48=""),"这个类型要填对方科目",IF(AND($G48<>"",ISNA(MATCH($G48,会计科目表!$B$6:$B$85,0))),"对方科目不存在",IF(AND($E48="缴纳税费",$H48=""),"缴税请在费用项目里选税种",IF(AND($F48<>"",ISNA(MATCH($F48,往来单位!$A$6:$A$85,0))),"往来单位未建档",IF(YEAR($B48)<>参数设置!$B$5,"不在本会计年度",IF(AND($B47<>"",ISNUMBER($B47),$B48<$B47),"日期比上一行早，余额按行序滚，建议按日期录","OK"))))))))))))))) | O48: =IF($B48="","",TEXT($B48,"yyyy-mm")) | P48: =IF($E48="","",ROUND(N($I48)+N($J48),2)) | Q48: =IF($D48="","",IFERROR(INDEX(资金账户!$F$6:$F$25,MATCH($D48,资金账户!$B$6:$B$25,0)),"")) | R48: =IF($E48="","",IFERROR(IF(INDEX(记账规则!$A$13:$H$32,MATCH($E48,记账规则!$A$13:$A$32,0),4)="借","收","支"),"")) | S48: =IF($D48="","",ROUND(SUMIFS(资金账户!$H$6:$H$25,资金账户!$B$6:$B$25,$D48)+SUMIFS($I$6:$I48,$D$6:$D48,$D48)-SUMIFS($J$6:$J48,$D$6:$D48,$D48),2)) | T48: =IF($B48="","",YEAR($B48))
A49: =IF($B49="","",ROW()-5) | N49: =IF(AND($B49="",$E49="",$I49="",$J49=""),"",IF(NOT(ISNUMBER($B49)),"日期无效",IF(ISNA(MATCH($C49,参数设置!$A$10:$A$12,0)),"公司无效",IF(ISNA(MATCH($D49,资金账户!$B$6:$B$25,0)),"账户未建档",IF(ISNA(MATCH($E49,记账规则!$A$13:$A$32,0)),"业务类型无效",IF(AND(N($I49)<>0,N($J49)<>0),"收入和支出只能填一列",IF($P49=0,"金额为 0",IF(AND($R49="收",N($I49)=0),"这类业务是收款，金额填到收入列",IF(AND($R49="支",N($J49)=0),"这类业务是付款，金额填到支出列",IF(AND(SUMPRODUCT(--(INDEX(记账规则!$A$13:$H$32,MATCH($E49,记账规则!$A$13:$A$32,0),0)="@对方"))>0,$G49=""),"这个类型要填对方科目",IF(AND($G49<>"",ISNA(MATCH($G49,会计科目表!$B$6:$B$85,0))),"对方科目不存在",IF(AND($E49="缴纳税费",$H49=""),"缴税请在费用项目里选税种",IF(AND($F49<>"",ISNA(MATCH($F49,往来单位!$A$6:$A$85,0))),"往来单位未建档",IF(YEAR($B49)<>参数设置!$B$5,"不在本会计年度",IF(AND($B48<>"",ISNUMBER($B48),$B49<$B48),"日期比上一行早，余额按行序滚，建议按日期录","OK"))))))))))))))) | O49: =IF($B49="","",TEXT($B49,"yyyy-mm")) | P49: =IF($E49="","",ROUND(N($I49)+N($J49),2)) | Q49: =IF($D49="","",IFERROR(INDEX(资金账户!$F$6:$F$25,MATCH($D49,资金账户!$B$6:$B$25,0)),"")) | R49: =IF($E49="","",IFERROR(IF(INDEX(记账规则!$A$13:$H$32,MATCH($E49,记账规则!$A$13:$A$32,0),4)="借","收","支"),"")) | S49: =IF($D49="","",ROUND(SUMIFS(资金账户!$H$6:$H$25,资金账户!$B$6:$B$25,$D49)+SUMIFS($I$6:$I49,$D$6:$D49,$D49)-SUMIFS($J$6:$J49,$D$6:$D49,$D49),2)) | T49: =IF($B49="","",YEAR($B49))
A50: =IF($B50="","",ROW()-5) | N50: =IF(AND($B50="",$E50="",$I50="",$J50=""),"",IF(NOT(ISNUMBER($B50)),"日期无效",IF(ISNA(MATCH($C50,参数设置!$A$10:$A$12,0)),"公司无效",IF(ISNA(MATCH($D50,资金账户!$B$6:$B$25,0)),"账户未建档",IF(ISNA(MATCH($E50,记账规则!$A$13:$A$32,0)),"业务类型无效",IF(AND(N($I50)<>0,N($J50)<>0),"收入和支出只能填一列",IF($P50=0,"金额为 0",IF(AND($R50="收",N($I50)=0),"这类业务是收款，金额填到收入列",IF(AND($R50="支",N($J50)=0),"这类业务是付款，金额填到支出列",IF(AND(SUMPRODUCT(--(INDEX(记账规则!$A$13:$H$32,MATCH($E50,记账规则!$A$13:$A$32,0),0)="@对方"))>0,$G50=""),"这个类型要填对方科目",IF(AND($G50<>"",ISNA(MATCH($G50,会计科目表!$B$6:$B$85,0))),"对方科目不存在",IF(AND($E50="缴纳税费",$H50=""),"缴税请在费用项目里选税种",IF(AND($F50<>"",ISNA(MATCH($F50,往来单位!$A$6:$A$85,0))),"往来单位未建档",IF(YEAR($B50)<>参数设置!$B$5,"不在本会计年度",IF(AND($B49<>"",ISNUMBER($B49),$B50<$B49),"日期比上一行早，余额按行序滚，建议按日期录","OK"))))))))))))))) | O50: =IF($B50="","",TEXT($B50,"yyyy-mm")) | P50: =IF($E50="","",ROUND(N($I50)+N($J50),2)) | Q50: =IF($D50="","",IFERROR(INDEX(资金账户!$F$6:$F$25,MATCH($D50,资金账户!$B$6:$B$25,0)),"")) | R50: =IF($E50="","",IFERROR(IF(INDEX(记账规则!$A$13:$H$32,MATCH($E50,记账规则!$A$13:$A$32,0),4)="借","收","支"),"")) | S50: =IF($D50="","",ROUND(SUMIFS(资金账户!$H$6:$H$25,资金账户!$B$6:$B$25,$D50)+SUMIFS($I$6:$I50,$D$6:$D50,$D50)-SUMIFS($J$6:$J50,$D$6:$D50,$D50),2)) | T50: =IF($B50="","",YEAR($B50))
