Workbook

Sheet 汇总
A1: 维 保 汇 总 · 梯子状态、数量、回款情况（全自动，不用填）
A2: ★ 这张表只读不填。数字全部从《电梯档案》和各维保组的表里自动汇总，那边改了这边跟着变。 ★ 只有第 3 行三个淡黄格可以改：统计年度（④ 按年度用）、到期提醒天数（到期 / 年检 / 免保提醒都按它）、付款宽限天数（每期期初过了这几天还没收才算逾期，原表多数写「七日内付」，默认 7）。
A3: 统计年度 | B3: 2026 | C3: 到期提醒天数 | D3: 30 | E3: 付款宽限天数 | F3: 7 | G3: 今天 | H3: =TODAY() -> 46288
A5: ① 梯子情况（来自《电梯档案》）：维保状态 / 梯型 / 维保人员 / 年检与免保提醒
A6: 维保状态 | B6: 台量 | C6: 占比 | D6: 免保已到期或 30天内到期 | F6: 梯型 | G6: 台量 | H6: 占比 | J6: 维保人员 | K6: 台量 | M6: 提醒 | N6: 台数
A7: 正常维保 | B7: =SUMIF(电梯档案!$W$2:$W$800,$A7,电梯档案!$N$2:$N$800) -> 0 | C7: =IFERROR($B7/$B$14,"") -> 0 | F7: 客梯 | G7: =SUMIF(电梯档案!$H$2:$H$800,"客梯",电梯档案!$N$2:$N$800) -> 127 | H7: =IFERROR($G7/$G$14,"") -> 0.42192691 | J7: 已排维保人员 | K7: =SUMIF(电梯档案!$V$2:$V$800,"?*",电梯档案!$N$2:$N$800)-$K$8 -> 39 | M7: 年检/限速器/载重 已过期 | N7: =COUNTIF(电梯档案!$Z$2:$Z$800,"*已过期*") -> 0
A8: 安装免保 | B8: =SUMIF(电梯档案!$W$2:$W$800,$A8,电梯档案!$N$2:$N$800) -> 0 | C8: =IFERROR($B8/$B$14,"") -> 0 | D8: =COUNTIFS(电梯档案!$W$2:$W$800,$A8,电梯档案!$Y$2:$Y$800,"▲免保已到期*")+COUNTIFS(电梯档案!$W$2:$W$800,$A8,电梯档案!$Y$2:$Y$800,"免保剩*") -> 0 | F8: 客梯(无机房) | G8: =SUMIF(电梯档案!$H$2:$H$800,"客梯(无机房)",电梯档案!$N$2:$N$800)+SUMIF(电梯档案!$H$2:$H$800,"客梯（无机房）",电梯档案!$N$2:$N$800) -> 80 | H8: =IFERROR($G8/$G$14,"") -> 0.26578073 | J8: 写着「未排」 | K8: =SUMIF(电梯档案!$V$2:$V$800,"未排",电梯档案!$N$2:$N$800) -> 8 | M8: 年检/限速器/载重 快到期 | N8: =COUNTIFS(电梯档案!$Z$2:$Z$800,"*剩*",电梯档案!$Z$2:$Z$800,"<>*已过期*") -> 3
A9: 技术免保 | B9: =SUMIF(电梯档案!$W$2:$W$800,$A9,电梯档案!$N$2:$N$800) -> 0 | C9: =IFERROR($B9/$B$14,"") -> 0 | D9: =COUNTIFS(电梯档案!$W$2:$W$800,$A9,电梯档案!$Y$2:$Y$800,"▲免保已到期*")+COUNTIFS(电梯档案!$W$2:$W$800,$A9,电梯档案!$Y$2:$Y$800,"免保剩*") -> 0 | F9: 货梯 | G9: =SUMIF(电梯档案!$H$2:$H$800,"货梯",电梯档案!$N$2:$N$800) -> 25 | H9: =IFERROR($G9/$G$14,"") -> 0.083056478 | J9: 维保人员没填 | K9: =$K$10-$K$7-$K$8 -> 254 | M9: 免保已到期该转收费 | N9: =COUNTIF(电梯档案!$Y$2:$Y$800,"▲免保已到期*") -> 0
A10: 质保期内 | B10: =SUMIF(电梯档案!$W$2:$W$800,$A10,电梯档案!$N$2:$N$800) -> 0 | C10: =IFERROR($B10/$B$14,"") -> 0 | D10: =COUNTIFS(电梯档案!$W$2:$W$800,$A10,电梯档案!$Y$2:$Y$800,"▲免保已到期*")+COUNTIFS(电梯档案!$W$2:$W$800,$A10,电梯档案!$Y$2:$Y$800,"免保剩*") -> 0 | F10: 扶梯 | G10: =SUMIF(电梯档案!$H$2:$H$800,"扶梯",电梯档案!$N$2:$N$800) -> 3 | H10: =IFERROR($G10/$G$14,"") -> 0.0099667774 | J10: 合计 | K10: =SUM(电梯档案!$N$2:$N$800) -> 301 | M10: 免保快到期 | N10: =COUNTIF(电梯档案!$Y$2:$Y$800,"免保剩*") -> 0
A11: 暂停维保 | B11: =SUMIF(电梯档案!$W$2:$W$800,$A11,电梯档案!$N$2:$N$800) -> 0 | C11: =IFERROR($B11/$B$14,"") -> 0 | F11: 人行道 | G11: =SUMIF(电梯档案!$H$2:$H$800,"人行道",电梯档案!$N$2:$N$800) -> 4 | H11: =IFERROR($G11/$G$14,"") -> 0.013289037 | M11: 免保没填到期日 | N11: =COUNTIF(电梯档案!$Y$2:$Y$800,"▲免保到期日没填") -> 0
A12: 已解约 | B12: =SUMIF(电梯档案!$W$2:$W$800,$A12,电梯档案!$N$2:$N$800) -> 0 | C12: =IFERROR($B12/$B$14,"") -> 0 | F12: 杂物梯 | G12: =SUMIF(电梯档案!$H$2:$H$800,"杂物梯",电梯档案!$N$2:$N$800) -> 1 | H12: =IFERROR($G12/$G$14,"") -> 0.0033222591 | M12: 档案在册台量 | N12: =SUM(电梯档案!$N$2:$N$800) -> 301
A13: 还没填维保状态 | B13: =$B$14-SUM($B$7:$B$12) -> 301 | C13: =IFERROR($B13/$B$14,"") -> 1 | F13: 其他 / 梯型没填 | G13: =$G$14-SUM($G$7:$G$12) -> 61 | H13: =IFERROR($G13/$G$14,"") -> 0.20265781 | M13: 各组合同台量合计 | N13: =$C$25 -> 218
A14: 在册总台量 | B14: =SUM(电梯档案!$N$2:$N$800) -> 301 | C14: =IF($B$14=0,"",1) -> 1 | D14: =SUM($D$7:$D$12) -> 0 | F14: 合计 | G14: =SUM(电梯档案!$N$2:$N$800) -> 301 | H14: =IF($G$14=0,"",1) -> 1 | M14: 档案比合同多出的台量 | N14: =$N$12-$N$13 -> 83
M15: ↑ 多出来的就是在档案里、但还没挂到任何一张维保组合同上的梯子（或合同台量没填）。
A17: ② 各维保组：合同与回款（每组一行）
A18: 维保组 | B18: 项目 行数 | C18: 合同 台量 | D18: 合同 未回 | E18: 已到期 | F18: 即将 到期 | G18: 免保 项目 | H18: 合同应收 | I18: 合同外 维修费 | J18: 总应收 | K18: 开票金额 | L18: 收款金额 | M18: 收现金额 | N18: 收款不开票 | O18: 已收合计 | P18: 回款率 | Q18: 开票应收额 (开票未到账) | R18: 到账未开票 (待补票) | S18: 未开票应收 | T18: 应收余额 (欠款) | U18: 截至今天应收 (按付款周期) | V18: 逾期未收
A19: 刘丕斌徐少斌夏凯 | B19: =COUNTIF(刘丕斌徐少斌夏凯!$AJ$3:$AJ$1001,"?*") -> 10 | C19: =SUM(刘丕斌徐少斌夏凯!$H$3:$H$1001) -> 15 | D19: =COUNTIF(刘丕斌徐少斌夏凯!$F$3:$F$1001,"*合同未回*") -> 0 | E19: =COUNTIF(刘丕斌徐少斌夏凯!$F$3:$F$1001,"*已到期*") -> 0 | F19: =COUNTIF(刘丕斌徐少斌夏凯!$F$3:$F$1001,"*即将到期*") -> 0 | G19: =COUNTIF(刘丕斌徐少斌夏凯!$AC$3:$AC$1001,"安装免保")+COUNTIF(刘丕斌徐少斌夏凯!$AC$3:$AC$1001,"技术免保")+COUNTIF(刘丕斌徐少斌夏凯!$AC$3:$AC$1001,"质保期内") -> 0 | H19: =SUM(刘丕斌徐少斌夏凯!$J$3:$J$1001) -> 56600 | I19: =SUM(刘丕斌徐少斌夏凯!$K$3:$K$1001) -> 0 | J19: =SUM(刘丕斌徐少斌夏凯!$L$3:$L$1001) -> 56600 | K19: =SUM(刘丕斌徐少斌夏凯!$N$3:$N$1001) -> 0 | L19: =SUM(刘丕斌徐少斌夏凯!$P$3:$P$1001) -> 0 | M19: =SUM(刘丕斌徐少斌夏凯!$Q$3:$Q$1001) -> 0 | N19: =SUM(刘丕斌徐少斌夏凯!$R$3:$R$1001) -> 0 | O19: =$L19+$M19+$N19 -> 0 | P19: =IFERROR($O19/$J19,"") -> 0 | Q19: =SUM(刘丕斌徐少斌夏凯!$S$3:$S$1001) -> 0 | R19: =SUM(刘丕斌徐少斌夏凯!$T$3:$T$1001) -> 0 | S19: =SUM(刘丕斌徐少斌夏凯!$U$3:$U$1001) -> 56600 | T19: =SUM(刘丕斌徐少斌夏凯!$V$3:$V$1001) -> 56600 | U19: =SUM(刘丕斌徐少斌夏凯!$AF$3:$AF$1001) -> 3200 | V19: =SUM(刘丕斌徐少斌夏凯!$AG$3:$AG$1001) -> 3200
A20: 陆莹杨凯 | B20: =COUNTIF(陆莹杨凯!$AI$3:$AI$1001,"?*") -> 31 | C20: =SUM(陆莹杨凯!$H$3:$H$1001) -> 4 | D20: =COUNTIF(陆莹杨凯!$F$3:$F$1001,"*合同未回*") -> 30 | E20: =COUNTIF(陆莹杨凯!$F$3:$F$1001,"*已到期*") -> 0 | F20: =COUNTIF(陆莹杨凯!$F$3:$F$1001,"*即将到期*") -> 0 | G20: =COUNTIF(陆莹杨凯!$AB$3:$AB$1001,"安装免保")+COUNTIF(陆莹杨凯!$AB$3:$AB$1001,"技术免保")+COUNTIF(陆莹杨凯!$AB$3:$AB$1001,"质保期内") -> 0 | H20: =SUM(陆莹杨凯!$J$3:$J$1001) -> 14400 | I20: =SUM(陆莹杨凯!$L$3:$L$1001) -> 350 | J20: =SUM(陆莹杨凯!$M$3:$M$1001) -> 14750 | K20: =SUM(陆莹杨凯!$O$3:$O$1001) -> 0 | L20: =SUM(陆莹杨凯!$Q$3:$Q$1001) -> 0 | M20: =SUM(陆莹杨凯!$R$3:$R$1001) -> 0 | N20: =SUM(陆莹杨凯!$S$3:$S$1001) -> 0 | O20: =$L20+$M20+$N20 -> 0 | P20: =IFERROR($O20/$J20,"") -> 0 | Q20: =SUM(陆莹杨凯!$T$3:$T$1001) -> 0 | R20: =SUM(陆莹杨凯!$U$3:$U$1001) -> 0 | S20: =SUM(陆莹杨凯!$V$3:$V$1001) -> 14750 | T20: =SUM(陆莹杨凯!$W$3:$W$1001) -> 14750 | U20: =SUM(陆莹杨凯!$AE$3:$AE$1001) -> 350 | V20: =SUM(陆莹杨凯!$AF$3:$AF$1001) -> 350
A21: 刘坤田超 | B21: =COUNTIF(刘坤田超!$AK$3:$AK$1001,"?*") -> 11 | C21: =SUM(刘坤田超!$I$3:$I$1001) -> 55 | D21: =COUNTIF(刘坤田超!$F$3:$F$1001,"*合同未回*") -> 8 | E21: =COUNTIF(刘坤田超!$F$3:$F$1001,"*已到期*") -> 0 | F21: =COUNTIF(刘坤田超!$F$3:$F$1001,"*即将到期*") -> 0 | G21: =COUNTIF(刘坤田超!$AD$3:$AD$1001,"安装免保")+COUNTIF(刘坤田超!$AD$3:$AD$1001,"技术免保")+COUNTIF(刘坤田超!$AD$3:$AD$1001,"质保期内") -> 0 | H21: =SUM(刘坤田超!$K$3:$K$1001) -> 10000 | I21: =SUM(刘坤田超!$L$3:$L$1001) -> 0 | J21: =SUM(刘坤田超!$M$3:$M$1001) -> 10000 | K21: =SUM(刘坤田超!$O$3:$O$1001) -> 0 | L21: =SUM(刘坤田超!$Q$3:$Q$1001) -> 0 | M21: =SUM(刘坤田超!$R$3:$R$1001) -> 0 | N21: =SUM(刘坤田超!$S$3:$S$1001) -> 0 | O21: =$L21+$M21+$N21 -> 0 | P21: =IFERROR($O21/$J21,"") -> 0 | Q21: =SUM(刘坤田超!$T$3:$T$1001) -> 0 | R21: =SUM(刘坤田超!$U$3:$U$1001) -> 0 | S21: =SUM(刘坤田超!$V$3:$V$1001) -> 10000 | T21: =SUM(刘坤田超!$W$3:$W$1001) -> 10000 | U21: =SUM(刘坤田超!$AG$3:$AG$1001) -> 0 | V21: =SUM(刘坤田超!$AH$3:$AH$1001) -> 0
A22: 陈彪姚永华梅思阳 | B22: =COUNTIF(陈彪姚永华梅思阳!$AK$3:$AK$1001,"?*") -> 88 | C22: =SUM(陈彪姚永华梅思阳!$I$3:$I$1001) -> 95 | D22: =COUNTIF(陈彪姚永华梅思阳!$F$3:$F$1001,"*合同未回*") -> 79 | E22: =COUNTIF(陈彪姚永华梅思阳!$F$3:$F$1001,"*已到期*") -> 0 | F22: =COUNTIF(陈彪姚永华梅思阳!$F$3:$F$1001,"*即将到期*") -> 0 | G22: =COUNTIF(陈彪姚永华梅思阳!$AD$3:$AD$1001,"安装免保")+COUNTIF(陈彪姚永华梅思阳!$AD$3:$AD$1001,"技术免保")+COUNTIF(陈彪姚永华梅思阳!$AD$3:$AD$1001,"质保期内") -> 0 | H22: =SUM(陈彪姚永华梅思阳!$K$3:$K$1001) -> 25300 | I22: =SUM(陈彪姚永华梅思阳!$L$3:$L$1001) -> 0 | J22: =SUM(陈彪姚永华梅思阳!$M$3:$M$1001) -> 25300 | K22: =SUM(陈彪姚永华梅思阳!$O$3:$O$1001) -> 0 | L22: =SUM(陈彪姚永华梅思阳!$Q$3:$Q$1001) -> 0 | M22: =SUM(陈彪姚永华梅思阳!$R$3:$R$1001) -> 0 | N22: =SUM(陈彪姚永华梅思阳!$S$3:$S$1001) -> 0 | O22: =$L22+$M22+$N22 -> 0 | P22: =IFERROR($O22/$J22,"") -> 0 | Q22: =SUM(陈彪姚永华梅思阳!$T$3:$T$1001) -> 0 | R22: =SUM(陈彪姚永华梅思阳!$U$3:$U$1001) -> 0 | S22: =SUM(陈彪姚永华梅思阳!$V$3:$V$1001) -> 25300 | T22: =SUM(陈彪姚永华梅思阳!$W$3:$W$1001) -> 25300 | U22: =SUM(陈彪姚永华梅思阳!$AG$3:$AG$1001) -> 15300 | V22: =SUM(陈彪姚永华梅思阳!$AH$3:$AH$1001) -> 15300
A23: 胡春平 | B23: =COUNTIF(胡春平!$AJ$3:$AJ$1001,"?*") -> 45 | C23: =SUM(胡春平!$H$3:$H$1001) -> 49 | D23: =COUNTIF(胡春平!$F$3:$F$1001,"*合同未回*") -> 24 | E23: =COUNTIF(胡春平!$F$3:$F$1001,"*已到期*") -> 0 | F23: =COUNTIF(胡春平!$F$3:$F$1001,"*即将到期*") -> 0 | G23: =COUNTIF(胡春平!$AC$3:$AC$1001,"安装免保")+COUNTIF(胡春平!$AC$3:$AC$1001,"技术免保")+COUNTIF(胡春平!$AC$3:$AC$1001,"质保期内") -> 0 | H23: =SUM(胡春平!$J$3:$J$1001) -> 91800 | I23: =SUM(胡春平!$K$3:$K$1001) -> -20 | J23: =SUM(胡春平!$L$3:$L$1001) -> 91780 | K23: =SUM(胡春平!$N$3:$N$1001) -> 15480 | L23: =SUM(胡春平!$P$3:$P$1001) -> 7700 | M23: =SUM(胡春平!$Q$3:$Q$1001) -> 0 | N23: =SUM(胡春平!$R$3:$R$1001) -> 0 | O23: =$L23+$M23+$N23 -> 7700 | P23: =IFERROR($O23/$J23,"") -> 0.083896274 | Q23: =SUM(胡春平!$S$3:$S$1001) -> 7780 | R23: =SUM(胡春平!$T$3:$T$1001) -> 0 | S23: =SUM(胡春平!$U$3:$U$1001) -> 76300 | T23: =SUM(胡春平!$V$3:$V$1001) -> 84080 | U23: =SUM(胡春平!$AF$3:$AF$1001) -> 87600 | V23: =SUM(胡春平!$AG$3:$AG$1001) -> 79900
A24: Sheet5（空白模板） | B24: =COUNTIF(Sheet5!$AJ$3:$AJ$1001,"?*") -> 0 | C24: =SUM(Sheet5!$H$3:$H$1001) -> 0 | D24: =COUNTIF(Sheet5!$F$3:$F$1001,"*合同未回*") -> 0 | E24: =COUNTIF(Sheet5!$F$3:$F$1001,"*已到期*") -> 0 | F24: =COUNTIF(Sheet5!$F$3:$F$1001,"*即将到期*") -> 0 | G24: =COUNTIF(Sheet5!$AC$3:$AC$1001,"安装免保")+COUNTIF(Sheet5!$AC$3:$AC$1001,"技术免保")+COUNTIF(Sheet5!$AC$3:$AC$1001,"质保期内") -> 0 | H24: =SUM(Sheet5!$J$3:$J$1001) -> 0 | I24: =SUM(Sheet5!$K$3:$K$1001) -> 0 | J24: =SUM(Sheet5!$L$3:$L$1001) -> 0 | K24: =SUM(Sheet5!$N$3:$N$1001) -> 0 | L24: =SUM(Sheet5!$P$3:$P$1001) -> 0 | M24: =SUM(Sheet5!$Q$3:$Q$1001) -> 0 | N24: =SUM(Sheet5!$R$3:$R$1001) -> 0 | O24: =$L24+$M24+$N24 -> 0 | P24: =IFERROR($O24/$J24,"") | Q24: =SUM(Sheet5!$S$3:$S$1001) -> 0 | R24: =SUM(Sheet5!$T$3:$T$1001) -> 0 | S24: =SUM(Sheet5!$U$3:$U$1001) -> 0 | T24: =SUM(Sheet5!$V$3:$V$1001) -> 0 | U24: =SUM(Sheet5!$AF$3:$AF$1001) -> 0 | V24: =SUM(Sheet5!$AG$3:$AG$1001) -> 0
A25: 合计 | B25: =SUM(B19:B24) -> 185 | C25: =SUM(C19:C24) -> 218 | D25: =SUM(D19:D24) -> 141 | E25: =SUM(E19:E24) -> 0 | F25: =SUM(F19:F24) -> 0 | G25: =SUM(G19:G24) -> 0 | H25: =SUM(H19:H24) -> 198100 | I25: =SUM(I19:I24) -> 330 | ... O25: =SUM(O19:O24) -> 7700 | P25: =IFERROR($O25/$J25,"") -> 0.038804616 | Q25: =SUM(Q19:Q24) -> 7780 | R25: =SUM(R19:R24) -> 0 | S25: =SUM(S19:S24) -> 182950 | T25: =SUM(T19:T24) -> 190730 | U25: =SUM(U19:U24) -> 106450 | V25: =SUM(V19:V24) -> 98750
A28: ③ 收款五种情况（按维保组拆开）：钱是怎么收的、票是怎么开的
A29: 情况 | B29: 在组表里怎么填 | C29: 刘丕斌徐少斌夏凯 | D29: 陆莹杨凯 | E29: 刘坤田超 | F29: 陈彪姚永华梅思阳 | G29: 胡春平 | H29: Sheet5（空白模板） | I29: 合计 | J29: 涉及行数
A30: ① 不开票的现金账 | B30: 只填「收现金额」 | C30: =SUM(刘丕斌徐少斌夏凯!$Q$3:$Q$1001) -> 0 | D30: =SUM(陆莹杨凯!$R$3:$R$1001) -> 0 | E30: =SUM(刘坤田超!$R$3:$R$1001) -> 0 | F30: =SUM(陈彪姚永华梅思阳!$R$3:$R$1001) -> 0 | G30: =SUM(胡春平!$Q$3:$Q$1001) -> 0 | H30: =SUM(Sheet5!$Q$3:$Q$1001) -> 0 | I30: =SUM(C30:H30) -> 0 | J30: =COUNTIF(刘丕斌徐少斌夏凯!$Q$3:$Q$1001,">0")+COUNTIF(陆莹杨凯!$R$3:$R$1001,">0")+COUNTIF(刘坤田超!$R$3:$R$1001,">0")+COUNTIF(陈彪姚永华梅思阳!$R$3:$R$1001,">0")+COUNTIF(胡春平!$Q$3:$Q$1001,">0")+COUNTIF(Sheet5!$Q$3:$Q$1001,">0") -> 0
A31: ② 收款不开票（转账/微信/收据，不开票） | B31: 只填「收款不开票」 | C31: =SUM(刘丕斌徐少斌夏凯!$R$3:$R$1001) -> 0 | D31: =SUM(陆莹杨凯!$S$3:$S$1001) -> 0 | E31: =SUM(刘坤田超!$S$3:$S$1001) -> 0 | F31: =SUM(陈彪姚永华梅思阳!$S$3:$S$1001) -> 0 | G31: =SUM(胡春平!$R$3:$R$1001) -> 0 | H31: =SUM(Sheet5!$R$3:$R$1001) -> 0 | I31: =SUM(C31:H31) -> 0 | J31: =COUNTIF(刘丕斌徐少斌夏凯!$R$3:$R$1001,">0")+COUNTIF(陆莹杨凯!$S$3:$S$1001,">0")+COUNTIF(刘坤田超!$S$3:$S$1001,">0")+COUNTIF(陈彪姚永华梅思阳!$S$3:$S$1001,">0")+COUNTIF(胡春平!$R$3:$R$1001,">0")+COUNTIF(Sheet5!$R$3:$R$1001,">0") -> 0
A32: ③ 开票收款（票开了、钱也到了） | B32: 「开票金额」和「收款金额」都填 | C32: =SUM(刘丕斌徐少斌夏凯!$AK$3:$AK$1001) -> 0 | D32: =SUM(陆莹杨凯!$AJ$3:$AJ$1001) -> 0 | E32: =SUM(刘坤田超!$AL$3:$AL$1001) -> 0 | F32: =SUM(陈彪姚永华梅思阳!$AL$3:$AL$1001) -> 0 | G32: =SUM(胡春平!$AK$3:$AK$1001) -> 7700 | H32: =SUM(Sheet5!$AK$3:$AK$1001) -> 0 | I32: =SUM(C32:H32) -> 7700 | J32: =COUNTIF(刘丕斌徐少斌夏凯!$AK$3:$AK$1001,">0")+COUNTIF(陆莹杨凯!$AJ$3:$AJ$1001,">0")+COUNTIF(刘坤田超!$AL$3:$AL$1001,">0")+COUNTIF(陈彪姚永华梅思阳!$AL$3:$AL$1001,">0")+COUNTIF(胡春平!$AK$3:$AK$1001,">0")+COUNTIF(Sheet5!$AK$3:$AK$1001,">0") -> 2
A33: ④ 开票未到账（开票应收额） | B33: 只填「开票金额」，钱没到 | C33: =SUM(刘丕斌徐少斌夏凯!$S$3:$S$1001) -> 0 | D33: =SUM(陆莹杨凯!$T$3:$T$1001) -> 0 | E33: =SUM(刘坤田超!$T$3:$T$1001) -> 0 | F33: =SUM(陈彪姚永华梅思阳!$T$3:$T$1001) -> 0 | G33: =SUM(胡春平!$S$3:$S$1001) -> 7780 | H33: =SUM(Sheet5!$S$3:$S$1001) -> 0 | I33: =SUM(C33:H33) -> 7780 | J33: =COUNTIF(刘丕斌徐少斌夏凯!$S$3:$S$1001,">0")+COUNTIF(陆莹杨凯!$T$3:$T$1001,">0")+COUNTIF(刘坤田超!$T$3:$T$1001,">0")+COUNTIF(陈彪姚永华梅思阳!$T$3:$T$1001,">0")+COUNTIF(胡春平!$S$3:$S$1001,">0")+COUNTIF(Sheet5!$S$3:$S$1001,">0") -> 2
A34: ⑤ 到账未开票（待补票） | B34: 只填「收款金额」，票还没开 | C34: =SUM(刘丕斌徐少斌夏凯!$T$3:$T$1001) -> 0 | D34: =SUM(陆莹杨凯!$U$3:$U$1001) -> 0 | E34: =SUM(刘坤田超!$U$3:$U$1001) -> 0 | F34: =SUM(陈彪姚永华梅思阳!$U$3:$U$1001) -> 0 | G34: =SUM(胡春平!$T$3:$T$1001) -> 0 | H34: =SUM(Sheet5!$T$3:$T$1001) -> 0 | I34: =SUM(C34:H34) -> 0 | J34: =COUNTIF(刘丕斌徐少斌夏凯!$T$3:$T$1001,">0")+COUNTIF(陆莹杨凯!$U$3:$U$1001,">0")+COUNTIF(刘坤田超!$U$3:$U$1001,">0")+COUNTIF(陈彪姚永华梅思阳!$U$3:$U$1001,">0")+COUNTIF(胡春平!$T$3:$T$1001,">0")+COUNTIF(Sheet5!$T$3:$T$1001,">0") -> 0
A35: 未开票也未收（未开票应收） | B35: 自动：还欠的钱里没开票的部分 | C35: =SUM(刘丕斌徐少斌夏凯!$U$3:$U$1001) -> 56600 | D35: =SUM(陆莹杨凯!$V$3:$V$1001) -> 14750 | E35: =SUM(刘坤田超!$V$3:$V$1001) -> 10000 | F35: =SUM(陈彪姚永华梅思阳!$V$3:$V$1001) -> 25300 | G35: =SUM(胡春平!$U$3:$U$1001) -> 76300 | H35: =SUM(Sheet5!$U$3:$U$1001) -> 0 | I35: =SUM(C35:H35) -> 182950 | J35: =COUNTIF(刘丕斌徐少斌夏凯!$U$3:$U$1001,">0")+COUNTIF(陆莹杨凯!$V$3:$V$1001,">0")+COUNTIF(刘坤田超!$V$3:$V$1001,">0")+COUNTIF(陈彪姚永华梅思阳!$V$3:$V$1001,">0")+COUNTIF(胡春平!$U$3:$U$1001,">0")+COUNTIF(Sheet5!$U$3:$U$1001,">0") -> 35
A36: 应收余额（最后还欠多少） | B36: 自动：总应收 − 收款 − 收现 − 收款不开票 | C36: =SUM(刘丕斌徐少斌夏凯!$V$3:$V$1001) -> 56600 | D36: =SUM(陆莹杨凯!$W$3:$W$1001) -> 14750 | E36: =SUM(刘坤田超!$W$3:$W$1001) -> 10000 | F36: =SUM(陈彪姚永华梅思阳!$W$3:$W$1001) -> 25300 | G36: =SUM(胡春平!$V$3:$V$1001) -> 84080 | H36: =SUM(Sheet5!$V$3:$V$1001) -> 0 | I36: =SUM(C36:H36) -> 190730 | J36: =COUNTIF(刘丕斌徐少斌夏凯!$V$3:$V$1001,">0")+COUNTIF(陆莹杨凯!$W$3:$W$1001,">0")+COUNTIF(刘坤田超!$W$3:$W$1001,">0")+COUNTIF(陈彪姚永华梅思阳!$W$3:$W$1001,">0")+COUNTIF(胡春平!$V$3:$V$1001,">0")+COUNTIF(Sheet5!$V$3:$V$1001,">0") -> 37
A39: ④ 按年度看欠款（年度＝合同起始日所在年份；「统计年度」在第 3 行改）：26 年没收完的，27 年在「往年合同」里接着看
A40: 维保组 | B40: 本年度合同 总应收 | C40: 本年度合同 已收 | D40: 本年度合同 应收余额 | E40: 往年合同 应收余额(结转) | F40: 以后年度合同 应收余额 | G40: 没填合同期的 应收余额 | H40: 累计应收余额 (全部)
A41: 刘丕斌徐少斌夏凯 | B41: =SUMIFS(刘丕斌徐少斌夏凯!$L$3:$L$1001,刘丕斌徐少斌夏凯!$AL$3:$AL$1001,统计年度) -> 11200 | C41: =SUMIFS(刘丕斌徐少斌夏凯!$P$3:$P$1001,刘丕斌徐少斌夏凯!$AL$3:$AL$1001,统计年度)+SUMIFS(刘丕斌徐少斌夏凯!$Q$3:$Q$1001,刘丕斌徐少斌夏凯!$AL$3:$AL$1001,统计年度)+SUMIFS(刘丕斌徐少斌夏凯!$R$3:$R$1001,刘丕斌徐少斌夏凯!$AL$3:$AL$1001,统计年度) -> 0 | D41: =SUMIFS(刘丕斌徐少斌夏凯!$V$3:$V$1001,刘丕斌徐少斌夏凯!$AL$3:$AL$1001,统计年度) -> 11200 | E41: =SUMIFS(刘丕斌徐少斌夏凯!$V$3:$V$1001,刘丕斌徐少斌夏凯!$AL$3:$AL$1001,"<"&统计年度) -> 0 | F41: =SUMIFS(刘丕斌徐少斌夏凯!$V$3:$V$1001,刘丕斌徐少斌夏凯!$AL$3:$AL$1001,">"&统计年度) -> 0 | G41: =ROUND($H41-$D41-$E41-$F41,2) -> 45400 | H41: =SUM(刘丕斌徐少斌夏凯!$V$3:$V$1001) -> 56600
A42: 陆莹杨凯 | B42: =SUMIFS(陆莹杨凯!$M$3:$M$1001,陆莹杨凯!$AK$3:$AK$1001,统计年度) -> 14750 | C42: =SUMIFS(陆莹杨凯!$Q$3:$Q$1001,陆莹杨凯!$AK$3:$AK$1001,统计年度)+SUMIFS(陆莹杨凯!$R$3:$R$1001,陆莹杨凯!$AK$3:$AK$1001,统计年度)+SUMIFS(陆莹杨凯!$S$3:$S$1001,陆莹杨凯!$AK$3:$AK$1001,统计年度) -> 0 | D42: =SUMIFS(陆莹杨凯!$W$3:$W$1001,陆莹杨凯!$AK$3:$AK$1001,统计年度) -> 14750 | E42: =SUMIFS(陆莹杨凯!$W$3:$W$1001,陆莹杨凯!$AK$3:$AK$1001,"<"&统计年度) -> 0 | F42: =SUMIFS(陆莹杨凯!$W$3:$W$1001,陆莹杨凯!$AK$3:$AK$1001,">"&统计年度) -> 0 | G42: =ROUND($H42-$D42-$E42-$F42,2) -> 0 | H42: =SUM(陆莹杨凯!$W$3:$W$1001) -> 14750
A43: 刘坤田超 | B43: =SUMIFS(刘坤田超!$M$3:$M$1001,刘坤田超!$AM$3:$AM$1001,统计年度) -> 0 | C43: =SUMIFS(刘坤田超!$Q$3:$Q$1001,刘坤田超!$AM$3:$AM$1001,统计年度)+SUMIFS(刘坤田超!$R$3:$R$1001,刘坤田超!$AM$3:$AM$1001,统计年度)+SUMIFS(刘坤田超!$S$3:$S$1001,刘坤田超!$AM$3:$AM$1001,统计年度) -> 0 | D43: =SUMIFS(刘坤田超!$W$3:$W$1001,刘坤田超!$AM$3:$AM$1001,统计年度) -> 0 | E43: =SUMIFS(刘坤田超!$W$3:$W$1001,刘坤田超!$AM$3:$AM$1001,"<"&统计年度) -> 0 | F43: =SUMIFS(刘坤田超!$W$3:$W$1001,刘坤田超!$AM$3:$AM$1001,">"&统计年度) -> 0 | G43: =ROUND($H43-$D43-$E43-$F43,2) -> 10000 | H43: =SUM(刘坤田超!$W$3:$W$1001) -> 10000
A44: 陈彪姚永华梅思阳 | B44: =SUMIFS(陈彪姚永华梅思阳!$M$3:$M$1001,陈彪姚永华梅思阳!$AM$3:$AM$1001,统计年度) -> 15300 | C44: =SUMIFS(陈彪姚永华梅思阳!$Q$3:$Q$1001,陈彪姚永华梅思阳!$AM$3:$AM$1001,统计年度)+SUMIFS(陈彪姚永华梅思阳!$R$3:$R$1001,陈彪姚永华梅思阳!$AM$3:$AM$1001,统计年度)+SUMIFS(陈彪姚永华梅思阳!$S$3:$S$1001,陈彪姚永华梅思阳!$AM$3:$AM$1001,统计年度) -> 0 | D44: =SUMIFS(陈彪姚永华梅思阳!$W$3:$W$1001,陈彪姚永华梅思阳!$AM$3:$AM$1001,统计年度) -> 15300 | E44: =SUMIFS(陈彪姚永华梅思阳!$W$3:$W$1001,陈彪姚永华梅思阳!$AM$3:$AM$1001,"<"&统计年度) -> 0 | F44: =SUMIFS(陈彪姚永华梅思阳!$W$3:$W$1001,陈彪姚永华梅思阳!$AM$3:$AM$1001,">"&统计年度) -> 0 | G44: =ROUND($H44-$D44-$E44-$F44,2) -> 10000 | H44: =SUM(陈彪姚永华梅思阳!$W$3:$W$1001) -> 25300
A45: 胡春平 | B45: =SUMIFS(胡春平!$L$3:$L$1001,胡春平!$AL$3:$AL$1001,统计年度) -> 59200 | C45: =SUMIFS(胡春平!$P$3:$P$1001,胡春平!$AL$3:$AL$1001,统计年度)+SUMIFS(胡春平!$Q$3:$Q$1001,胡春平!$AL$3:$AL$1001,统计年度)+SUMIFS(胡春平!$R$3:$R$1001,胡春平!$AL$3:$AL$1001,统计年度) -> 7700 | D45: =SUMIFS(胡春平!$V$3:$V$1001,胡春平!$AL$3:$AL$1001,统计年度) -> 51500 | E45: =SUMIFS(胡春平!$V$3:$V$1001,胡春平!$AL$3:$AL$1001,"<"&统计年度) -> 28400 | F45: =SUMIFS(胡春平!$V$3:$V$1001,胡春平!$AL$3:$AL$1001,">"&统计年度) -> 0 | G45: =ROUND($H45-$D45-$E45-$F45,2) -> 4180 | H45: =SUM(胡春平!$V$3:$V$1001) -> 84080
A46: Sheet5（空白模板） | B46: =SUMIFS(Sheet5!$L$3:$L$1001,Sheet5!$AL$3:$AL$1001,统计年度) -> 0 | C46: =SUMIFS(Sheet5!$P$3:$P$1001,Sheet5!$AL$3:$AL$1001,统计年度)+SUMIFS(Sheet5!$Q$3:$Q$1001,Sheet5!$AL$3:$AL$1001,统计年度)+SUMIFS(Sheet5!$R$3:$R$1001,Sheet5!$AL$3:$AL$1001,统计年度) -> 0 | D46: =SUMIFS(Sheet5!$V$3:$V$1001,Sheet5!$AL$3:$AL$1001,统计年度) -> 0 | E46: =SUMIFS(Sheet5!$V$3:$V$1001,Sheet5!$AL$3:$AL$1001,"<"&统计年度) -> 0 | F46: =SUMIFS(Sheet5!$V$3:$V$1001,Sheet5!$AL$3:$AL$1001,">"&统计年度) -> 0 | G46: =ROUND($H46-$D46-$E46-$F46,2) -> 0 | H46: =SUM(Sheet5!$V$3:$V$1001) -> 0
A47: 合计 | B47: =SUM(B41:B46) -> 100450 | C47: =SUM(C41:C46) -> 7700 | D47: =SUM(D41:D46) -> 92750 | E47: =SUM(E41:E46) -> 28400 | F47: =SUM(F41:F46) -> 0 | G47: =SUM(G41:G46) -> 69580 | H47: =SUM(H41:H46) -> 190730
A50: ⑤ 核对与留意
A51: 项目 | B51: 数值 / 口径一 | C51: 口径二 | D51: 结论
A52: 应收余额合计 ＝ 总应收 − 已收合计 | B52: =$T$25 -> 190730 | C52: =ROUND($J$25-$O$25,2) -> 190730 | D52: =IF(ABS(N($B52)-N($C52))<0.005,"✔ 平","★ 差 "&TEXT(N($B52)-N($C52),"#,##0.00")) -> ✔ 平 | E52: 不平说明有行填了收款 / 金额，却没写使用单位和项目名称（这种行不会算进应收余额），或者数写在了第 500 行以后。
A53: 开票应收额 ＋ 未开票应收 ＝ 还欠的钱 | B53: =ROUND($Q$25+$S$25,2) -> 190730 | C53: =ROUND(SUMIF(刘丕斌徐少斌夏凯!$V$3:$V$1001,">0")+SUMIF(陆莹杨凯!$W$3:$W$1001,">0")+SUMIF(刘坤田超!$W$3:$W$1001,">0")+SUMIF(陈彪姚永华梅思阳!$W$3:$W$1001,">0")+SUMIF(胡春平!$V$3:$V$1001,">0")+SUMIF(Sheet5!$V$3:$V$1001,">0"),2) -> 190730 | D53: =IF(ABS(N($B53)-N($C53))<0.005,"✔ 平","★ 差 "&TEXT(N($B53)-N($C53),"#,##0.00")) -> ✔ 平
A54: 五种情况表的应收余额 ＝ ② 表应收余额 | B54: =I36 -> 190730 | C54: =$T$25 -> 190730 | D54: =IF(ABS(N($B54)-N($C54))<0.005,"✔ 平","★ 差 "&TEXT(N($B54)-N($C54),"#,##0.00")) -> ✔ 平
A55: 按年度拆开之后加回去 ＝ 累计应收余额 | B55: =ROUND($D$47+$E$47+$F$47+$G$47,2) -> 190730 | C55: =$H$47 -> 190730 | D55: =IF(ABS(N($B55)-N($C55))<0.005,"✔ 平","★ 差 "&TEXT(N($B55)-N($C55),"#,##0.00")) -> ✔ 平
A56: 多收了的行（应收余额是负数） | B56: =COUNTIF(刘丕斌徐少斌夏凯!$V$3:$V$1001,"<-0.005")+COUNTIF(陆莹杨凯!$W$3:$W$1001,"<-0.005")+COUNTIF(刘坤田超!$W$3:$W$1001,"<-0.005")+COUNTIF(陈彪姚永华梅思阳!$W$3:$W$1001,"<-0.005")+COUNTIF(胡春平!$V$3:$V$1001,"<-0.005")+COUNTIF(Sheet5!$V$3:$V$1001,"<-0.005") -> 0 | D56: =IF(N($B56)=0,"✔ 没有","留意 "&N($B56)&" 行") -> ✔ 没有 | E56: 一般是单价 / 台量没填全，或者预收了下一期。
A57: 没填单价却已经收了钱的行 | B57: =COUNTIF(刘丕斌徐少斌夏凯!$W$3:$W$1001,"未填单价，已收*")+COUNTIF(陆莹杨凯!$X$3:$X$1001,"未填单价，已收*")+COUNTIF(刘坤田超!$X$3:$X$1001,"未填单价，已收*")+COUNTIF(陈彪姚永华梅思阳!$X$3:$X$1001,"未填单价，已收*")+COUNTIF(胡春平!$W$3:$W$1001,"未填单价，已收*")+COUNTIF(Sheet5!$W$3:$W$1001,"未填单价，已收*") -> 0 | D57: =IF(N($B57)=0,"✔ 没有","留意 "&N($B57)&" 行") -> ✔ 没有 | E57: 补上单价、台量，应收余额才准。
A58: 选了付款周期但没填合同起止的行 | B58: =(COUNTIF(刘丕斌徐少斌夏凯!$AD$3:$AD$1001,"?*")-COUNTIFS(刘丕斌徐少斌夏凯!$AD$3:$AD$1001,"?*",刘丕斌徐少斌夏凯!$AM$3:$AM$1001,">0"))+(COUNTIF(陆莹杨凯!$AC$3:$AC$1001,"?*")-COUNTIFS(陆莹杨凯!$AC$3:$AC$1001,"?*",陆莹杨凯!$AL$3:$AL$1001,">0"))+(COUNTIF(刘坤田超!$AE$3:$AE$1001,"?*")-COUNTIFS(刘坤田超!$AE$3:$AE$1001,"?*",刘坤田超!$AN$3:$AN$1001,">0"))+(COUNTIF(陈彪姚永华梅思阳!$AE$3:$AE$1001,"?*")-COUNTIFS(陈彪姚永华梅思阳!$AE$3:$AE$1001,"?*",陈彪姚永华梅思阳!$AN$3:$AN$1001,">0"))+(COUNTIF(胡春平!$AD$3:$AD$1001,"?*")-COUNTIFS(胡春平!$AD$3:$AD$1001,"?*",胡春平!$AM$3:$AM$1001,">0"))+(COUNTIF(Sheet5!$AD$3:$AD$1001,"?*")-COUNTIFS(Sheet5!$AD$3:$AD$1001,"?*",Sheet5!$AM$3:$AM$1001,">0")) -> 12 | D58: =IF(N($B58)=0,"✔ 没有","留意 "&N($B58)&" 行") -> 留意 12 行 | E58: 没有合同起止日，算不出分期到了第几期。

Sheet 电梯档案
A1: 注意事项 | B1: 使用单位 | C1: 项目名称 | D1: 型号 | E1: 注册代码 | F1: 963333应急救 援标识牌编号 | G1: 生产厂家 | H1: 梯型 | I1: 层 | J1: 站 | K1: 门 | L1: 载重 | M1: 速度/宽度 | N1: 台量 | O1: 设备编号 | P1: 使用编号 | Q1: 其它(下次年检日期) | R1: 制造 日期 | S1: 限速器校验（下次） | T1: 载重试验125%（下次） | U1: 维保性质 | V1: 维保人员 | W1: 维保状态 | X1: 免保/质保 到期日 | Y1: 维保状态提醒 | Z1: 年检/校验提醒 | AA1: 年检(认出的日期) | AB1: 限速器(认出的日期) | AC1: 载重试验(认出的日期)
B2: 武汉中海联机电工程有限公司 | C2: 滨江苑一期7号楼（汪益新） | D2: KLWG | E2: 3110420100201911Z156 | F2: 110647 | G2: 康力电梯 | H2: 客梯 | I2: 8 | J2: 8 | L2: 800kg | M2: 1.0m/s | N2: 1 | O2: 10045590-0010 | P2: 1#客 | Y2: =IF(TRIM($B2&$C2)="","",IF(OR($W2="安装免保",$W2="技术免保",$W2="质保期内"),IF(NOT(ISNUMBER($X2)),"▲免保到期日没填",IF($X2<TODAY(),"▲免保已到期，转收费",IF($X2-TODAY()<=提醒天数,"免保剩"&($X2-TODAY())&"天","免保中"))),IF($W2="暂停维保","暂停中",IF($W2="已解约","已解约","")))) | Z2: =IF(TRIM($B2&$C2)="","",TRIM(IF($AA2="","",IF($AA2<TODAY(),"年检已过期"&(TODAY()-$AA2)&"天 ",IF($AA2-TODAY()<=提醒天数,"年检剩"&($AA2-TODAY())&"天 ","")))&IF($AB2="","",IF($AB2<TODAY(),"限速器已过期"&(TODAY()-$AB2)&"天 ",IF($AB2-TODAY()<=提醒天数,"限速器剩"&($AB2-TODAY())&"天 ","")))&IF($AC2="","",IF($AC2<TODAY(),"载重试验已过期"&(TODAY()-$AC2)&"天 ",IF($AC2-TODAY()<=提醒天数,"载重试验剩"&($AC2-TODAY())&"天 ",""))))) | AA2: =IF(TRIM($Q2&"")="","",IF(ISNUMBER($Q2),IF($Q2>10000,$Q2,IFERROR(DATE(INT($Q2),IF(ROUND(MOD($Q2,1)*100,0)>12,ROUND(MOD($Q2,1)*10,0),ROUND(MOD($Q2,1)*100,0))+1,0),"")),IFERROR(IF(LEN($Q2)-LEN(SUBSTITUTE($Q2,".",""))>=2,DATEVALUE(SUBSTITUTE(TRIM($Q2),".","-")),DATE(VALUE(LEFT(TRIM($Q2),4)),VALUE(MID(TRIM($Q2),6,2))+1,0)),""))) | AB2: =IF(TRIM($S2&"")="","",IF(ISNUMBER($S2),IF($S2>10000,$S2,IFERROR(DATE(INT($S2),IF(ROUND(MOD($S2,1)*100,0)>12,ROUND(MOD($S2,1)*10,0),ROUND(MOD($S2,1)*100,0))+1,0),"")),IFERROR(IF(LEN($S2)-LEN(SUBSTITUTE($S2,".",""))>=2,DATEVALUE(SUBSTITUTE(TRIM($S2),".","-")),DATE(VALUE(LEFT(TRIM($S2),4)),VALUE(MID(TRIM($S2),6,2))+1,0)),""))) | AC2: =IF(TRIM($T2&"")="","",IF(ISNUMBER($T2),IF($T2>10000,$T2,IFERROR(DATE(INT($T2),IF(ROUND(MOD($T2,1)*100,0)>12,ROUND(MOD($T2,1)*10,0),ROUND(MOD($T2,1)*100,0))+1,0),"")),IFERROR(IF(LEN($T2)-LEN(SUBSTITUTE($T2,".",""))>=2,DATEVALUE(SUBSTITUTE(TRIM($T2),".","-")),DATE(VALUE(LEFT(TRIM($T2),4)),VALUE(MID(TRIM($T2),6,2))+1,0)),"")))
B3: 武汉明海定慧商业管理有限公司 | C3: 六渡桥 | D3: FSLK | E3: 31104201032017070035 | F3: 010829 | G3: 浙江梅轮电梯公司 | H3: 客梯 | I3: 10 | J3: 7 | K3: 7 | L3: 800kg | M3: 1.5m/s | N3: 1 | O3: 17ML-2601 | P3: L1#客 | Y3: =IF(TRIM($B3&$C3)="","",IF(OR($W3="安装免保",$W3="技术免保",$W3="质保期内"),IF(NOT(ISNUMBER($X3)),"▲免保到期日没填",IF($X3<TODAY(),"▲免保已到期，转收费",IF($X3-TODAY()<=提醒天数,"免保剩"&($X3-TODAY())&"天","免保中"))),IF($W3="暂停维保","暂停中",IF($W3="已解约","已解约","")))) | Z3: =IF(TRIM($B3&$C3)="","",TRIM(IF($AA3="","",IF($AA3<TODAY(),"年检已过期"&(TODAY()-$AA3)&"天 ",IF($AA3-TODAY()<=提醒天数,"年检剩"&($AA3-TODAY())&"天 ","")))&IF($AB3="","",IF($AB3<TODAY(),"限速器已过期"&(TODAY()-$AB3)&"天 ",IF($AB3-TODAY()<=提醒天数,"限速器剩"&($AB3-TODAY())&"天 ","")))&IF($AC3="","",IF($AC3<TODAY(),"载重试验已过期"&(TODAY()-$AC3)&"天 ",IF($AC3-TODAY()<=提醒天数,"载重试验剩"&($AC3-TODAY())&"天 ",""))))) | AA3: =IF(TRIM($Q3&"")="","",IF(ISNUMBER($Q3),IF($Q3>10000,$Q3,IFERROR(DATE(INT($Q3),IF(ROUND(MOD($Q3,1)*100,0)>12,ROUND(MOD($Q3,1)*10,0),ROUND(MOD($Q3,1)*100,0))+1,0),"")),IFERROR(IF(LEN($Q3)-LEN(SUBSTITUTE($Q3,".",""))>=2,DATEVALUE(SUBSTITUTE(TRIM($Q3),".","-")),DATE(VALUE(LEFT(TRIM($Q3),4)),VALUE(MID(TRIM($Q3),6,2))+1,0)),""))) | AB3: =IF(TRIM($S3&"")="","",IF(ISNUMBER($S3),IF($S3>10000,$S3,IFERROR(DATE(INT($S3),IF(ROUND(MOD($S3,1)*100,0)>12,ROUND(MOD($S3,1)*10,0),ROUND(MOD($S3,1)*100,0))+1,0),"")),IFERROR(IF(LEN($S3)-LEN(SUBSTITUTE($S3,".",""))>=2,DATEVALUE(SUBSTITUTE(TRIM($S3),".","-")),DATE(VALUE(LEFT(TRIM($S3),4)),VALUE(MID(TRIM($S3),6,2))+1,0)),""))) | AC3: =IF(TRIM($T3&"")="","",IF(ISNUMBER($T3),IF($T3>10000,$T3,IFERROR(DATE(INT($T3),IF(ROUND(MOD($T3,1)*100,0)>12,ROUND(MOD($T3,1)*10,0),ROUND(MOD($T3,1)*100,0))+1,0),"")),IFERROR(IF(LEN($T3)-LEN(SUBSTITUTE($T3,".",""))>=2,DATEVALUE(SUBSTITUTE(TRIM($T3),".","-")),DATE(VALUE(LEFT(TRIM($T3),4)),VALUE(MID(TRIM($T3),6,2))+1,0)),"")))
B4: 武汉华茂医院有限公司 | C4: 圣心医院 | D4: EBJ30 | E4: 3110420100201811X814 | F4: 102951 | G4: 怡达快速电梯 | H4: 客梯 | I4: 4 | J4: 4 | K4: 4 | L4: 1600kg | M4: 1.0m/s | N4: 1 | O4: H070058.1 | P4: 医梯1# | Y4: =IF(TRIM($B4&$C4)="","",IF(OR($W4="安装免保",$W4="技术免保",$W4="质保期内"),IF(NOT(ISNUMBER($X4)),"▲免保到期日没填",IF($X4<TODAY(),"▲免保已到期，转收费",IF($X4-TODAY()<=提醒天数,"免保剩"&($X4-TODAY())&"天","免保中"))),IF($W4="暂停维保","暂停中",IF($W4="已解约","已解约","")))) | Z4: =IF(TRIM($B4&$C4)="","",TRIM(IF($AA4="","",IF($AA4<TODAY(),"年检已过期"&(TODAY()-$AA4)&"天 ",IF($AA4-TODAY()<=提醒天数,"年检剩"&($AA4-TODAY())&"天 ","")))&IF($AB4="","",IF($AB4<TODAY(),"限速器已过期"&(TODAY()-$AB4)&"天 ",IF($AB4-TODAY()<=提醒天数,"限速器剩"&($AB4-TODAY())&"天 ","")))&IF($AC4="","",IF($AC4<TODAY(),"载重试验已过期"&(TODAY()-$AC4)&"天 ",IF($AC4-TODAY()<=提醒天数,"载重试验剩"&($AC4-TODAY())&"天 ",""))))) | AA4: =IF(TRIM($Q4&"")="","",IF(ISNUMBER($Q4),IF($Q4>10000,$Q4,IFERROR(DATE(INT($Q4),IF(ROUND(MOD($Q4,1)*100,0)>12,ROUND(MOD($Q4,1)*10,0),ROUND(MOD($Q4,1)*100,0))+1,0),"")),IFERROR(IF(LEN($Q4)-LEN(SUBSTITUTE($Q4,".",""))>=2,DATEVALUE(SUBSTITUTE(TRIM($Q4),".","-")),DATE(VALUE(LEFT(TRIM($Q4),4)),VALUE(MID(TRIM($Q4),6,2))+1,0)),""))) | AB4: =IF(TRIM($S4&"")="","",IF(ISNUMBER($S4),IF($S4>10000,$S4,IFERROR(DATE(INT($S4),IF(ROUND(MOD($S4,1)*100,0)>12,ROUND(MOD($S4,1)*10,0),ROUND(MOD($S4,1)*100,0))+1,0),"")),IFERROR(IF(LEN($S4)-LEN(SUBSTITUTE($S4,".",""))>=2,DATEVALUE(SUBSTITUTE(TRIM($S4),".","-")),DATE(VALUE(LEFT(TRIM($S4),4)),VALUE(MID(TRIM($S4),6,2))+1,0)),""))) | AC4: =IF(TRIM($T4&"")="","",IF(ISNUMBER($T4),IF($T4>10000,$T4,IFERROR(DATE(INT($T4),IF(ROUND(MOD($T4,1)*100,0)>12,ROUND(MOD($T4,1)*10,0),ROUND(MOD($T4,1)*100,0))+1,0),"")),IFERROR(IF(LEN($T4)-LEN(SUBSTITUTE($T4,".",""))>=2,DATEVALUE(SUBSTITUTE(TRIM($T4),".","-")),DATE(VALUE(LEFT(TRIM($T4),4)),VALUE(MID(TRIM($T4),6,2))+1,0)),"")))
B5: 武汉华茂医院有限公司 | C5: 圣心医院 | D5: EBJ30 | E5: 3110420100201811X815 | F5: 102952 | G5: 怡达快速电梯 | H5: 客梯 | I5: 4 | J5: 4 | K5: 4 | L5: 1600kg | M5: 1.0m/s | N5: 1 | O5: H070058.2 | P5: 医梯2# | Y5: =IF(TRIM($B5&$C5)="","",IF(OR($W5="安装免保",$W5="技术免保",$W5="质保期内"),IF(NOT(ISNUMBER($X5)),"▲免保到期日没填",IF($X5<TODAY(),"▲免保已到期，转收费",IF($X5-TODAY()<=提醒天数,"免保剩"&($X5-TODAY())&"天","免保中"))),IF($W5="暂停维保","暂停中",IF($W5="已解约","已解约","")))) | Z5: =IF(TRIM($B5&$C5)="","",TRIM(IF($AA5="","",IF($AA5<TODAY(),"年检已过期"&(TODAY()-$AA5)&"天 ",IF($AA5-TODAY()<=提醒天数,"年检剩"&($AA5-TODAY())&"天 ","")))&IF($AB5="","",IF($AB5<TODAY(),"限速器已过期"&(TODAY()-$AB5)&"天 ",IF($AB5-TODAY()<=提醒天数,"限速器剩"&($AB5-TODAY())&"天 ","")))&IF($AC5="","",IF($AC5<TODAY(),"载重试验已过期"&(TODAY()-$AC5)&"天 ",IF($AC5-TODAY()<=提醒天数,"载重试验剩"&($AC5-TODAY())&"天 ",""))))) | AA5: =IF(TRIM($Q5&"")="","",IF(ISNUMBER($Q5),IF($Q5>10000,$Q5,IFERROR(DATE(INT($Q5),IF(ROUND(MOD($Q5,1)*100,0)>12,ROUND(MOD($Q5,1)*10,0),ROUND(MOD($Q5,1)*100,0))+1,0),"")),IFERROR(IF(LEN($Q5)-LEN(SUBSTITUTE($Q5,".",""))>=2,DATEVALUE(SUBSTITUTE(TRIM($Q5),".","-")),DATE(VALUE(LEFT(TRIM($Q5),4)),VALUE(MID(TRIM($Q5),6,2))+1,0)),""))) | AB5: =IF(TRIM($S5&"")="","",IF(ISNUMBER($S5),IF($S5>10000,$S5,IFERROR(DATE(INT($S5),IF(ROUND(MOD($S5,1)*100,0)>12,ROUND(MOD($S5,1)*10,0),ROUND(MOD($S5,1)*100,0))+1,0),"")),IFERROR(IF(LEN($S5)-LEN(SUBSTITUTE($S5,".",""))>=2,DATEVALUE(SUBSTITUTE(TRIM($S5),".","-")),DATE(VALUE(LEFT(TRIM($S5),4)),VALUE(MID(TRIM($S5),6,2))+1,0)),""))) | AC5: =IF(TRIM($T5&"")="","",IF(ISNUMBER($T5),IF($T5>10000,$T5,IFERROR(DATE(INT($T5),IF(ROUND(MOD($T5,1)*100,0)>12,ROUND(MOD($T5,1)*10,0),ROUND(MOD($T5,1)*100,0))+1,0),"")),IFERROR(IF(LEN($T5)-LEN(SUBSTITUTE($T5,".",""))>=2,DATEVALUE(SUBSTITUTE(TRIM($T5),".","-")),DATE(VALUE(LEFT(TRIM($T5),4)),VALUE(MID(TRIM($T5),6,2))+1,0)),"")))
B6: 湖北长江人民艺术剧院有限责任公司 | C6: 长江人艺D8小剧场 | D6: MEGA-P | E6: 31104201062025120001 | G6: 住富电梯科技有限公司 | H6: 客梯 | I6: 8 | J6: 8 | K6: 8 | L6: 1500kg | M6: 1.5m/s | N6: 1 | O6: F09193 | P6: 3#客 | Y6: =IF(TRIM($B6&$C6)="","",IF(OR($W6="安装免保",$W6="技术免保",$W6="质保期内"),IF(NOT(ISNUMBER($X6)),"▲免保到期日没填",IF($X6<TODAY(),"▲免保已到期，转收费",IF($X6-TODAY()<=提醒天数,"免保剩"&($X6-TODAY())&"天","免保中"))),IF($W6="暂停维保","暂停中",IF($W6="已解约","已解约","")))) | Z6: =IF(TRIM($B6&$C6)="","",TRIM(IF($AA6="","",IF($AA6<TODAY(),"年检已过期"&(TODAY()-$AA6)&"天 ",IF($AA6-TODAY()<=提醒天数,"年检剩"&($AA6-TODAY())&"天 ","")))&IF($AB6="","",IF($AB6<TODAY(),"限速器已过期"&(TODAY()-$AB6)&"天 ",IF($AB6-TODAY()<=提醒天数,"限速器剩"&($AB6-TODAY())&"天 ","")))&IF($AC6="","",IF($AC6<TODAY(),"载重试验已过期"&(TODAY()-$AC6)&"天 ",IF($AC6-TODAY()<=提醒天数,"载重试验剩"&($AC6-TODAY())&"天 ",""))))) | AA6: =IF(TRIM($Q6&"")="","",IF(ISNUMBER($Q6),IF($Q6>10000,$Q6,IFERROR(DATE(INT($Q6),IF(ROUND(MOD($Q6,1)*100,0)>12,ROUND(MOD($Q6,1)*10,0),ROUND(MOD($Q6,1)*100,0))+1,0),"")),IFERROR(IF(LEN($Q6)-LEN(SUBSTITUTE($Q6,".",""))>=2,DATEVALUE(SUBSTITUTE(TRIM($Q6),".","-")),DATE(VALUE(LEFT(TRIM($Q6),4)),VALUE(MID(TRIM($Q6),6,2))+1,0)),""))) | AB6: =IF(TRIM($S6&"")="","",IF(ISNUMBER($S6),IF($S6>10000,$S6,IFERROR(DATE(INT($S6),IF(ROUND(MOD($S6,1)*100,0)>12,ROUND(MOD($S6,1)*10,0),ROUND(MOD($S6,1)*100,0))+1,0),"")),IFERROR(IF(LEN($S6)-LEN(SUBSTITUTE($S6,".",""))>=2,DATEVALUE(SUBSTITUTE(TRIM($S6),".","-")),DATE(VALUE(LEFT(TRIM($S6),4)),VALUE(MID(TRIM($S6),6,2))+1,0)),""))) | AC6: =IF(TRIM($T6&"")="","",IF(ISNUMBER($T6),IF($T6>10000,$T6,IFERROR(DATE(INT($T6),IF(ROUND(MOD($T6,1)*100,0)>12,ROUND(MOD($T6,1)*10,0),ROUND(MOD($T6,1)*100,0))+1,0),"")),IFERROR(IF(LEN($T6)-LEN(SUBSTITUTE($T6,".",""))>=2,DATEVALUE(SUBSTITUTE(TRIM($T6),".","-")),DATE(VALUE(LEFT(TRIM($T6),4)),VALUE(MID(TRIM($T6),6,2))+1,0)),"")))
B7: 湖北长江人民艺术剧院有限责任公司 | C7: 小东门华中村64号 | D7: MEGA-MRL | E7: 31104201062022100030 | G7: 住友富士 | H7: 客梯(无机房) | I7: 7 | J7: 7 | L7: 1000kg | M7: 1.0m/s | N7: 1 | O7: 908133 | P7: 1#客 | Y7: =IF(TRIM($B7&$C7)="","",IF(OR($W7="安装免保",$W7="技术免保",$W7="质保期内"),IF(NOT(ISNUMBER($X7)),"▲免保到期日没填",IF($X7<TODAY(),"▲免保已到期，转收费",IF($X7-TODAY()<=提醒天数,"免保剩"&($X7-TODAY())&"天","免保中"))),IF($W7="暂停维保","暂停中",IF($W7="已解约","已解约","")))) | Z7: =IF(TRIM($B7&$C7)="","",TRIM(IF($AA7="","",IF($AA7<TODAY(),"年检已过期"&(TODAY()-$AA7)&"天 ",IF($AA7-TODAY()<=提醒天数,"年检剩"&($AA7-TODAY())&"天 ","")))&IF($AB7="","",IF($AB7<TODAY(),"限速器已过期"&(TODAY()-$AB7)&"天 ",IF($AB7-TODAY()<=提醒天数,"限速器剩"&($AB7-TODAY())&"天 ","")))&IF($AC7="","",IF($AC7<TODAY(),"载重试验已过期"&(TODAY()-$AC7)&"天 ",IF($AC7-TODAY()<=提醒天数,"载重试验剩"&($AC7-TODAY())&"天 ",""))))) | AA7: =IF(TRIM($Q7&"")="","",IF(ISNUMBER($Q7),IF($Q7>10000,$Q7,IFERROR(DATE(INT($Q7),IF(ROUND(MOD($Q7,1)*100,0)>12,ROUND(MOD($Q7,1)*10,0),ROUND(MOD($Q7,1)*100,0))+1,0),"")),IFERROR(IF(LEN($Q7)-LEN(SUBSTITUTE($Q7,".",""))>=2,DATEVALUE(SUBSTITUTE(TRIM($Q7),".","-")),DATE(VALUE(LEFT(TRIM($Q7),4)),VALUE(MID(TRIM($Q7),6,2))+1,0)),""))) | AB7: =IF(TRIM($S7&"")="","",IF(ISNUMBER($S7),IF($S7>10000,$S7,IFERROR(DATE(INT($S7),IF(ROUND(MOD($S7,1)*100,0)>12,ROUND(MOD($S7,1)*10,0),ROUND(MOD($S7,1)*100,0))+1,0),"")),IFERROR(IF(LEN($S7)-LEN(SUBSTITUTE($S7,".",""))>=2,DATEVALUE(SUBSTITUTE(TRIM($S7),".","-")),DATE(VALUE(LEFT(TRIM($S7),4)),VALUE(MID(TRIM($S7),6,2))+1,0)),""))) | AC7: =IF(TRIM($T7&"")="","",IF(ISNUMBER($T7),IF($T7>10000,$T7,IFERROR(DATE(INT($T7),IF(ROUND(MOD($T7,1)*100,0)>12,ROUND(MOD($T7,1)*10,0),ROUND(MOD($T7,1)*100,0))+1,0),"")),IFERROR(IF(LEN($T7)-LEN(SUBSTITUTE($T7,".",""))>=2,DATEVALUE(SUBSTITUTE(TRIM($T7),".","-")),DATE(VALUE(LEFT(TRIM($T7),4)),VALUE(MID(TRIM($T7),6,2))+1,0)),"")))
B8: 湖北长江人民艺术剧院有限责任公司 | C8: 小东门华中村64号 | D8: MEGA-MRL | E8: 31104201062022100031 | G8: 住友富士 | H8: 客梯(无机房) | I8: 7 | J8: 7 | L8: 1000kg | M8: 1.0m/s | N8: 1 | O8: 908134 | P8: 2#客 | Y8: =IF(TRIM($B8&$C8)="","",IF(OR($W8="安装免保",$W8="技术免保",$W8="质保期内"),IF(NOT(ISNUMBER($X8)),"▲免保到期日没填",IF($X8<TODAY(),"▲免保已到期，转收费",IF($X8-TODAY()<=提醒天数,"免保剩"&($X8-TODAY())&"天","免保中"))),IF($W8="暂停维保","暂停中",IF($W8="已解约","已解约","")))) | Z8: =IF(TRIM($B8&$C8)="","",TRIM(IF($AA8="","",IF($AA8<TODAY(),"年检已过期"&(TODAY()-$AA8)&"天 ",IF($AA8-TODAY()<=提醒天数,"年检剩"&($AA8-TODAY())&"天 ","")))&IF($AB8="","",IF($AB8<TODAY(),"限速器已过期"&(TODAY()-$AB8)&"天 ",IF($AB8-TODAY()<=提醒天数,"限速器剩"&($AB8-TODAY())&"天 ","")))&IF($AC8="","",IF($AC8<TODAY(),"载重试验已过期"&(TODAY()-$AC8)&"天 ",IF($AC8-TODAY()<=提醒天数,"载重试验剩"&($AC8-TODAY())&"天 ",""))))) | AA8: =IF(TRIM($Q8&"")="","",IF(ISNUMBER($Q8),IF($Q8>10000,$Q8,IFERROR(DATE(INT($Q8),IF(ROUND(MOD($Q8,1)*100,0)>12,ROUND(MOD($Q8,1)*10,0),ROUND(MOD($Q8,1)*100,0))+1,0),"")),IFERROR(IF(LEN($Q8)-LEN(SUBSTITUTE($Q8,".",""))>=2,DATEVALUE(SUBSTITUTE(TRIM($Q8),".","-")),DATE(VALUE(LEFT(TRIM($Q8),4)),VALUE(MID(TRIM($Q8),6,2))+1,0)),""))) | AB8: =IF(TRIM($S8&"")="","",IF(ISNUMBER($S8),IF($S8>10000,$S8,IFERROR(DATE(INT($S8),IF(ROUND(MOD($S8,1)*100,0)>12,ROUND(MOD($S8,1)*10,0),ROUND(MOD($S8,1)*100,0))+1,0),"")),IFERROR(IF(LEN($S8)-LEN(SUBSTITUTE($S8,".",""))>=2,DATEVALUE(SUBSTITUTE(TRIM($S8),".","-")),DATE(VALUE(LEFT(TRIM($S8),4)),VALUE(MID(TRIM($S8),6,2))+1,0)),""))) | AC8: =IF(TRIM($T8&"")="","",IF(ISNUMBER($T8),IF($T8>10000,$T8,IFERROR(DATE(INT($T8),IF(ROUND(MOD($T8,1)*100,0)>12,ROUND(MOD($T8,1)*10,0),ROUND(MOD($T8,1)*100,0))+1,0),"")),IFERROR(IF(LEN($T8)-LEN(SUBSTITUTE($T8,".",""))>=2,DATEVALUE(SUBSTITUTE(TRIM($T8),".","-")),DATE(VALUE(LEFT(TRIM($T8),4)),VALUE(MID(TRIM($T8),6,2))+1,0)),"")))
B9: 金禧建设集团有限公司 | C9: 金禧中北路221号 | D9: MTP | E9: 31104201062019090001 | F9: 095986 | G9: 曼隆蒂森克虏伯电梯 | H9: 客梯 | I9: 11 | J9: 11 | L9: 1000kg | M9: 1.75m/s | N9: 1 | O9: M19NJ1136 | P9: 1# | Y9: =IF(TRIM($B9&$C9)="","",IF(OR($W9="安装免保",$W9="技术免保",$W9="质保期内"),IF(NOT(ISNUMBER($X9)),"▲免保到期日没填",IF($X9<TODAY(),"▲免保已到期，转收费",IF($X9-TODAY()<=提醒天数,"免保剩"&($X9-TODAY())&"天","免保中"))),IF($W9="暂停维保","暂停中",IF($W9="已解约","已解约","")))) | Z9: =IF(TRIM($B9&$C9)="","",TRIM(IF($AA9="","",IF($AA9<TODAY(),"年检已过期"&(TODAY()-$AA9)&"天 ",IF($AA9-TODAY()<=提醒天数,"年检剩"&($AA9-TODAY())&"天 ","")))&IF($AB9="","",IF($AB9<TODAY(),"限速器已过期"&(TODAY()-$AB9)&"天 ",IF($AB9-TODAY()<=提醒天数,"限速器剩"&($AB9-TODAY())&"天 ","")))&IF($AC9="","",IF($AC9<TODAY(),"载重试验已过期"&(TODAY()-$AC9)&"天 ",IF($AC9-TODAY()<=提醒天数,"载重试验剩"&($AC9-TODAY())&"天 ",""))))) | AA9: =IF(TRIM($Q9&"")="","",IF(ISNUMBER($Q9),IF($Q9>10000,$Q9,IFERROR(DATE(INT($Q9),IF(ROUND(MOD($Q9,1)*100,0)>12,ROUND(MOD($Q9,1)*10,0),ROUND(MOD($Q9,1)*100,0))+1,0),"")),IFERROR(IF(LEN($Q9)-LEN(SUBSTITUTE($Q9,".",""))>=2,DATEVALUE(SUBSTITUTE(TRIM($Q9),".","-")),DATE(VALUE(LEFT(TRIM($Q9),4)),VALUE(MID(TRIM($Q9),6,2))+1,0)),""))) | AB9: =IF(TRIM($S9&"")="","",IF(ISNUMBER($S9),IF($S9>10000,$S9,IFERROR(DATE(INT($S9),IF(ROUND(MOD($S9,1)*100,0)>12,ROUND(MOD($S9,1)*10,0),ROUND(MOD($S9,1)*100,0))+1,0),"")),IFERROR(IF(LEN($S9)-LEN(SUBSTITUTE($S9,".",""))>=2,DATEVALUE(SUBSTITUTE(TRIM($S9),".","-")),DATE(VALUE(LEFT(TRIM($S9),4)),VALUE(MID(TRIM($S9),6,2))+1,0)),""))) | AC9: =IF(TRIM($T9&"")="","",IF(ISNUMBER($T9),IF($T9>10000,$T9,IFERROR(DATE(INT($T9),IF(ROUND(MOD($T9,1)*100,0)>12,ROUND(MOD($T9,1)*10,0),ROUND(MOD($T9,1)*100,0))+1,0),"")),IFERROR(IF(LEN($T9)-LEN(SUBSTITUTE($T9,".",""))>=2,DATEVALUE(SUBSTITUTE(TRIM($T9),".","-")),DATE(VALUE(LEFT(TRIM($T9),4)),VALUE(MID(TRIM($T9),6,2))+1,0)),"")))
B10: 湖北南远电缆科技有限公司 | C10: 南远电缆 | D10: LTHX2000/0.5-VF | E10: 31204201002018051055 | F10: 099118 | G10: 菱王电梯股份有限公司 | H10: 货梯 | I10: 4 | J10: 4 | L10: 2000kg | M10: 0.5m/s | N10: 1 | O10: 17H002199 | P10: 1#货梯 | Y10: =IF(TRIM($B10&$C10)="","",IF(OR($W10="安装免保",$W10="技术免保",$W10="质保期内"),IF(NOT(ISNUMBER($X10)),"▲免保到期日没填",IF($X10<TODAY(),"▲免保已到期，转收费",IF($X10-TODAY()<=提醒天数,"免保剩"&($X10-TODAY())&"天","免保中"))),IF($W10="暂停维保","暂停中",IF($W10="已解约","已解约","")))) | Z10: =IF(TRIM($B10&$C10)="","",TRIM(IF($AA10="","",IF($AA10<TODAY(),"年检已过期"&(TODAY()-$AA10)&"天 ",IF($AA10-TODAY()<=提醒天数,"年检剩"&($AA10-TODAY())&"天 ","")))&IF($AB10="","",IF($AB10<TODAY(),"限速器已过期"&(TODAY()-$AB10)&"天 ",IF($AB10-TODAY()<=提醒天数,"限速器剩"&($AB10-TODAY())&"天 ","")))&IF($AC10="","",IF($AC10<TODAY(),"载重试验已过期"&(TODAY()-$AC10)&"天 ",IF($AC10-TODAY()<=提醒天数,"载重试验剩"&($AC10-TODAY())&"天 ",""))))) | AA10: =IF(TRIM($Q10&"")="","",IF(ISNUMBER($Q10),IF($Q10>10000,$Q10,IFERROR(DATE(INT($Q10),IF(ROUND(MOD($Q10,1)*100,0)>12,ROUND(MOD($Q10,1)*10,0),ROUND(MOD($Q10,1)*100,0))+1,0),"")),IFERROR(IF(LEN($Q10)-LEN(SUBSTITUTE($Q10,".",""))>=2,DATEVALUE(SUBSTITUTE(TRIM($Q10),".","-")),DATE(VALUE(LEFT(TRIM($Q10),4)),VALUE(MID(TRIM($Q10),6,2))+1,0)),""))) | AB10: =IF(TRIM($S10&"")="","",IF(ISNUMBER($S10),IF($S10>10000,$S10,IFERROR(DATE(INT($S10),IF(ROUND(MOD($S10,1)*100,0)>12,ROUND(MOD($S10,1)*10,0),ROUND(MOD($S10,1)*100,0))+1,0),"")),IFERROR(IF(LEN($S10)-LEN(SUBSTITUTE($S10,".",""))>=2,DATEVALUE(SUBSTITUTE(TRIM($S10),".","-")),DATE(VALUE(LEFT(TRIM($S10),4)),VALUE(MID(TRIM($S10),6,2))+1,0)),""))) | AC10: =IF(TRIM($T10&"")="","",IF(ISNUMBER($T10),IF($T10>10000,$T10,IFERROR(DATE(INT($T10),IF(ROUND(MOD($T10,1)*100,0)>12,ROUND(MOD($T10,1)*10,0),ROUND(MOD($T10,1)*100,0))+1,0),"")),IFERROR(IF(LEN($T10)-LEN(SUBSTITUTE($T10,".",""))>=2,DATEVALUE(SUBSTITUTE(TRIM($T10),".","-")),DATE(VALUE(LEFT(TRIM($T10),4)),VALUE(MID(TRIM($T10),6,2))+1,0)),"")))
B11: 湖北南远电缆科技有限公司 | C11: 南远电缆 | D11: CHOI-III | E11: 31104201012022107422 | G11: 沈阳远大智能工业集团 | H11: 客梯 | I11: 6 | J11: 6 | K11: 6 | L11: 1600kg | M11: 1.0m/s | N11: 1 | O11: BLTSY22K/20366 | P11: L1#客梯 | Y11: =IF(TRIM($B11&$C11)="","",IF(OR($W11="安装免保",$W11="技术免保",$W11="质保期内"),IF(NOT(ISNUMBER($X11)),"▲免保到期日没填",IF($X11<TODAY(),"▲免保已到期，转收费",IF($X11-TODAY()<=提醒天数,"免保剩"&($X11-TODAY())&"天","免保中"))),IF($W11="暂停维保","暂停中",IF($W11="已解约","已解约","")))) | Z11: =IF(TRIM($B11&$C11)="","",TRIM(IF($AA11="","",IF($AA11<TODAY(),"年检已过期"&(TODAY()-$AA11)&"天 ",IF($AA11-TODAY()<=提醒天数,"年检剩"&($AA11-TODAY())&"天 ","")))&IF($AB11="","",IF($AB11<TODAY(),"限速器已过期"&(TODAY()-$AB11)&"天 ",IF($AB11-TODAY()<=提醒天数,"限速器剩"&($AB11-TODAY())&"天 ","")))&IF($AC11="","",IF($AC11<TODAY(),"载重试验已过期"&(TODAY()-$AC11)&"天 ",IF($AC11-TODAY()<=提醒天数,"载重试验剩"&($AC11-TODAY())&"天 ",""))))) | AA11: =IF(TRIM($Q11&"")="","",IF(ISNUMBER($Q11),IF($Q11>10000,$Q11,IFERROR(DATE(INT($Q11),IF(ROUND(MOD($Q11,1)*100,0)>12,ROUND(MOD($Q11,1)*10,0),ROUND(MOD($Q11,1)*100,0))+1,0),"")),IFERROR(IF(LEN($Q11)-LEN(SUBSTITUTE($Q11,".",""))>=2,DATEVALUE(SUBSTITUTE(TRIM($Q11),".","-")),DATE(VALUE(LEFT(TRIM($Q11),4)),VALUE(MID(TRIM($Q11),6,2))+1,0)),""))) | AB11: =IF(TRIM($S11&"")="","",IF(ISNUMBER($S11),IF($S11>10000,$S11,IFERROR(DATE(INT($S11),IF(ROUND(MOD($S11,1)*100,0)>12,ROUND(MOD($S11,1)*10,0),ROUND(MOD($S11,1)*100,0))+1,0),"")),IFERROR(IF(LEN($S11)-LEN(SUBSTITUTE($S11,".",""))>=2,DATEVALUE(SUBSTITUTE(TRIM($S11),".","-")),DATE(VALUE(LEFT(TRIM($S11),4)),VALUE(MID(TRIM($S11),6,2))+1,0)),""))) | AC11: =IF(TRIM($T11&"")="","",IF(ISNUMBER($T11),IF($T11>10000,$T11,IFERROR(DATE(INT($T11),IF(ROUND(MOD($T11,1)*100,0)>12,ROUND(MOD($T11,1)*10,0),ROUND(MOD($T11,1)*100,0))+1,0),"")),IFERROR(IF(LEN($T11)-LEN(SUBSTITUTE($T11,".",""))>=2,DATEVALUE(SUBSTITUTE(TRIM($T11),".","-")),DATE(VALUE(LEFT(TRIM($T11),4)),VALUE(MID(TRIM($T11),6,2))+1,0)),"")))
B12: 武汉市黄陂区鑫捷惠超市（个体工商户） | C12: 黄陂雅迪 | D12: F2000D05S-C0 | E12: 30134201162013060001 | F12: 092260 | G12: 江南嘉捷电梯 | H12: 货梯 | I12: 4 | J12: 4 | L12: 2000kg | M12: 0.5m/s | N12: 1 | O12: 12J50060 | P12: 1#货 | Y12: =IF(TRIM($B12&$C12)="","",IF(OR($W12="安装免保",$W12="技术免保",$W12="质保期内"),IF(NOT(ISNUMBER($X12)),"▲免保到期日没填",IF($X12<TODAY(),"▲免保已到期，转收费",IF($X12-TODAY()<=提醒天数,"免保剩"&($X12-TODAY())&"天","免保中"))),IF($W12="暂停维保","暂停中",IF($W12="已解约","已解约","")))) | Z12: =IF(TRIM($B12&$C12)="","",TRIM(IF($AA12="","",IF($AA12<TODAY(),"年检已过期"&(TODAY()-$AA12)&"天 ",IF($AA12-TODAY()<=提醒天数,"年检剩"&($AA12-TODAY())&"天 ","")))&IF($AB12="","",IF($AB12<TODAY(),"限速器已过期"&(TODAY()-$AB12)&"天 ",IF($AB12-TODAY()<=提醒天数,"限速器剩"&($AB12-TODAY())&"天 ","")))&IF($AC12="","",IF($AC12<TODAY(),"载重试验已过期"&(TODAY()-$AC12)&"天 ",IF($AC12-TODAY()<=提醒天数,"载重试验剩"&($AC12-TODAY())&"天 ",""))))) | AA12: =IF(TRIM($Q12&"")="","",IF(ISNUMBER($Q12),IF($Q12>10000,$Q12,IFERROR(DATE(INT($Q12),IF(ROUND(MOD($Q12,1)*100,0)>12,ROUND(MOD($Q12,1)*10,0),ROUND(MOD($Q12,1)*100,0))+1,0),"")),IFERROR(IF(LEN($Q12)-LEN(SUBSTITUTE($Q12,".",""))>=2,DATEVALUE(SUBSTITUTE(TRIM($Q12),".","-")),DATE(VALUE(LEFT(TRIM($Q12),4)),VALUE(MID(TRIM($Q12),6,2))+1,0)),""))) | AB12: =IF(TRIM($S12&"")="","",IF(ISNUMBER($S12),IF($S12>10000,$S12,IFERROR(DATE(INT($S12),IF(ROUND(MOD($S12,1)*100,0)>12,ROUND(MOD($S12,1)*10,0),ROUND(MOD($S12,1)*100,0))+1,0),"")),IFERROR(IF(LEN($S12)-LEN(SUBSTITUTE($S12,".",""))>=2,DATEVALUE(SUBSTITUTE(TRIM($S12),".","-")),DATE(VALUE(LEFT(TRIM($S12),4)),VALUE(MID(TRIM($S12),6,2))+1,0)),""))) | AC12: =IF(TRIM($T12&"")="","",IF(ISNUMBER($T12),IF($T12>10000,$T12,IFERROR(DATE(INT($T12),IF(ROUND(MOD($T12,1)*100,0)>12,ROUND(MOD($T12,1)*10,0),ROUND(MOD($T12,1)*100,0))+1,0),"")),IFERROR(IF(LEN($T12)-LEN(SUBSTITUTE($T12,".",""))>=2,DATEVALUE(SUBSTITUTE(TRIM($T12),".","-")),DATE(VALUE(LEFT(TRIM($T12),4)),VALUE(MID(TRIM($T12),6,2))+1,0)),"")))
B13: 武汉尊品益康意食品有限公司 | C13: 意康意厂房 | D13: LTHX | E13: 31204201002019073047 | F13: 108416 | G13: 菱王电梯股份有限公司 | H13: 货梯 | I13: 5 | J13: 5 | L13: 2000kg | M13: 0.5m/s | N13: 1 | O13: 18H001296 | P13: 1#货 | Y13: =IF(TRIM($B13&$C13)="","",IF(OR($W13="安装免保",$W13="技术免保",$W13="质保期内"),IF(NOT(ISNUMBER($X13)),"▲免保到期日没填",IF($X13<TODAY(),"▲免保已到期，转收费",IF($X13-TODAY()<=提醒天数,"免保剩"&($X13-TODAY())&"天","免保中"))),IF($W13="暂停维保","暂停中",IF($W13="已解约","已解约","")))) | Z13: =IF(TRIM($B13&$C13)="","",TRIM(IF($AA13="","",IF($AA13<TODAY(),"年检已过期"&(TODAY()-$AA13)&"天 ",IF($AA13-TODAY()<=提醒天数,"年检剩"&($AA13-TODAY())&"天 ","")))&IF($AB13="","",IF($AB13<TODAY(),"限速器已过期"&(TODAY()-$AB13)&"天 ",IF($AB13-TODAY()<=提醒天数,"限速器剩"&($AB13-TODAY())&"天 ","")))&IF($AC13="","",IF($AC13<TODAY(),"载重试验已过期"&(TODAY()-$AC13)&"天 ",IF($AC13-TODAY()<=提醒天数,"载重试验剩"&($AC13-TODAY())&"天 ",""))))) | AA13: =IF(TRIM($Q13&"")="","",IF(ISNUMBER($Q13),IF($Q13>10000,$Q13,IFERROR(DATE(INT($Q13),IF(ROUND(MOD($Q13,1)*100,0)>12,ROUND(MOD($Q13,1)*10,0),ROUND(MOD($Q13,1)*100,0))+1,0),"")),IFERROR(IF(LEN($Q13)-LEN(SUBSTITUTE($Q13,".",""))>=2,DATEVALUE(SUBSTITUTE(TRIM($Q13),".","-")),DATE(VALUE(LEFT(TRIM($Q13),4)),VALUE(MID(TRIM($Q13),6,2))+1,0)),""))) | AB13: =IF(TRIM($S13&"")="","",IF(ISNUMBER($S13),IF($S13>10000,$S13,IFERROR(DATE(INT($S13),IF(ROUND(MOD($S13,1)*100,0)>12,ROUND(MOD($S13,1)*10,0),ROUND(MOD($S13,1)*100,0))+1,0),"")),IFERROR(IF(LEN($S13)-LEN(SUBSTITUTE($S13,".",""))>=2,DATEVALUE(SUBSTITUTE(TRIM($S13),".","-")),DATE(VALUE(LEFT(TRIM($S13),4)),VALUE(MID(TRIM($S13),6,2))+1,0)),""))) | AC13: =IF(TRIM($T13&"")="","",IF(ISNUMBER($T13),IF($T13>10000,$T13,IFERROR(DATE(INT($T13),IF(ROUND(MOD($T13,1)*100,0)>12,ROUND(MOD($T13,1)*10,0),ROUND(MOD($T13,1)*100,0))+1,0),"")),IFERROR(IF(LEN($T13)-LEN(SUBSTITUTE($T13,".",""))>=2,DATEVALUE(SUBSTITUTE(TRIM($T13),".","-")),DATE(VALUE(LEFT(TRIM($T13),4)),VALUE(MID(TRIM($T13),6,2))+1,0)),"")))
B14: 武汉尊品益康意食品有限公司 | C14: 意康意厂房 | D14: LTHX | E14: 31204201002019073048 | F14: 108417 | G14: 菱王电梯股份有限公司 | H14: 货梯 | I14: 5 | J14: 5 | L14: 2000kg | M14: 0.5m/s | N14: 1 | O14: 18H001297 | P14: 2#货 | Y14: =IF(TRIM($B14&$C14)="","",IF(OR($W14="安装免保",$W14="技术免保",$W14="质保期内"),IF(NOT(ISNUMBER($X14)),"▲免保到期日没填",IF($X14<TODAY(),"▲免保已到期，转收费",IF($X14-TODAY()<=提醒天数,"免保剩"&($X14-TODAY())&"天","免保中"))),IF($W14="暂停维保","暂停中",IF($W14="已解约","已解约","")))) | Z14: =IF(TRIM($B14&$C14)="","",TRIM(IF($AA14="","",IF($AA14<TODAY(),"年检已过期"&(TODAY()-$AA14)&"天 ",IF($AA14-TODAY()<=提醒天数,"年检剩"&($AA14-TODAY())&"天 ","")))&IF($AB14="","",IF($AB14<TODAY(),"限速器已过期"&(TODAY()-$AB14)&"天 ",IF($AB14-TODAY()<=提醒天数,"限速器剩"&($AB14-TODAY())&"天 ","")))&IF($AC14="","",IF($AC14<TODAY(),"载重试验已过期"&(TODAY()-$AC14)&"天 ",IF($AC14-TODAY()<=提醒天数,"载重试验剩"&($AC14-TODAY())&"天 ",""))))) | AA14: =IF(TRIM($Q14&"")="","",IF(ISNUMBER($Q14),IF($Q14>10000,$Q14,IFERROR(DATE(INT($Q14),IF(ROUND(MOD($Q14,1)*100,0)>12,ROUND(MOD($Q14,1)*10,0),ROUND(MOD($Q14,1)*100,0))+1,0),"")),IFERROR(IF(LEN($Q14)-LEN(SUBSTITUTE($Q14,".",""))>=2,DATEVALUE(SUBSTITUTE(TRIM($Q14),".","-")),DATE(VALUE(LEFT(TRIM($Q14),4)),VALUE(MID(TRIM($Q14),6,2))+1,0)),""))) | AB14: =IF(TRIM($S14&"")="","",IF(ISNUMBER($S14),IF($S14>10000,$S14,IFERROR(DATE(INT($S14),IF(ROUND(MOD($S14,1)*100,0)>12,ROUND(MOD($S14,1)*10,0),ROUND(MOD($S14,1)*100,0))+1,0),"")),IFERROR(IF(LEN($S14)-LEN(SUBSTITUTE($S14,".",""))>=2,DATEVALUE(SUBSTITUTE(TRIM($S14),".","-")),DATE(VALUE(LEFT(TRIM($S14),4)),VALUE(MID(TRIM($S14),6,2))+1,0)),""))) | AC14: =IF(TRIM($T14&"")="","",IF(ISNUMBER($T14),IF($T14>10000,$T14,IFERROR(DATE(INT($T14),IF(ROUND(MOD($T14,1)*100,0)>12,ROUND(MOD($T14,1)*10,0),ROUND(MOD($T14,1)*100,0))+1,0),"")),IFERROR(IF(LEN($T14)-LEN(SUBSTITUTE($T14,".",""))>=2,DATEVALUE(SUBSTITUTE(TRIM($T14),".","-")),DATE(VALUE(LEFT(TRIM($T14),4)),VALUE(MID(TRIM($T14),6,2))+1,0)),"")))
B15: 武汉尊品益康意食品有限公司 | C15: 意康意厂房 | D15: LTHX | E15: 31204201002019073049 | F15: 108418 | G15: 菱王电梯股份有限公司 | H15: 货梯 | I15: 5 | J15: 5 | L15: 2000kg | M15: 0.5m/s | N15: 1 | O15: 18H001298 | P15: 3#货 | Y15: =IF(TRIM($B15&$C15)="","",IF(OR($W15="安装免保",$W15="技术免保",$W15="质保期内"),IF(NOT(ISNUMBER($X15)),"▲免保到期日没填",IF($X15<TODAY(),"▲免保已到期，转收费",IF($X15-TODAY()<=提醒天数,"免保剩"&($X15-TODAY())&"天","免保中"))),IF($W15="暂停维保","暂停中",IF($W15="已解约","已解约","")))) | Z15: =IF(TRIM($B15&$C15)="","",TRIM(IF($AA15="","",IF($AA15<TODAY(),"年检已过期"&(TODAY()-$AA15)&"天 ",IF($AA15-TODAY()<=提醒天数,"年检剩"&($AA15-TODAY())&"天 ","")))&IF($AB15="","",IF($AB15<TODAY(),"限速器已过期"&(TODAY()-$AB15)&"天 ",IF($AB15-TODAY()<=提醒天数,"限速器剩"&($AB15-TODAY())&"天 ","")))&IF($AC15="","",IF($AC15<TODAY(),"载重试验已过期"&(TODAY()-$AC15)&"天 ",IF($AC15-TODAY()<=提醒天数,"载重试验剩"&($AC15-TODAY())&"天 ",""))))) | AA15: =IF(TRIM($Q15&"")="","",IF(ISNUMBER($Q15),IF($Q15>10000,$Q15,IFERROR(DATE(INT($Q15),IF(ROUND(MOD($Q15,1)*100,0)>12,ROUND(MOD($Q15,1)*10,0),ROUND(MOD($Q15,1)*100,0))+1,0),"")),IFERROR(IF(LEN($Q15)-LEN(SUBSTITUTE($Q15,".",""))>=2,DATEVALUE(SUBSTITUTE(TRIM($Q15),".","-")),DATE(VALUE(LEFT(TRIM($Q15),4)),VALUE(MID(TRIM($Q15),6,2))+1,0)),""))) | AB15: =IF(TRIM($S15&"")="","",IF(ISNUMBER($S15),IF($S15>10000,$S15,IFERROR(DATE(INT($S15),IF(ROUND(MOD($S15,1)*100,0)>12,ROUND(MOD($S15,1)*10,0),ROUND(MOD($S15,1)*100,0))+1,0),"")),IFERROR(IF(LEN($S15)-LEN(SUBSTITUTE($S15,".",""))>=2,DATEVALUE(SUBSTITUTE(TRIM($S15),".","-")),DATE(VALUE(LEFT(TRIM($S15),4)),VALUE(MID(TRIM($S15),6,2))+1,0)),""))) | AC15: =IF(TRIM($T15&"")="","",IF(ISNUMBER($T15),IF($T15>10000,$T15,IFERROR(DATE(INT($T15),IF(ROUND(MOD($T15,1)*100,0)>12,ROUND(MOD($T15,1)*10,0),ROUND(MOD($T15,1)*100,0))+1,0),"")),IFERROR(IF(LEN($T15)-LEN(SUBSTITUTE($T15,".",""))>=2,DATEVALUE(SUBSTITUTE(TRIM($T15),".","-")),DATE(VALUE(LEFT(TRIM($T15),4)),VALUE(MID(TRIM($T15),6,2))+1,0)),"")))
B16: 武汉尊品益康意食品有限公司 | C16: 意康意厂房 | D16: LTHX | E16: 31204201002019073050 | F16: 108419 | G16: 菱王电梯股份有限公司 | H16: 货梯 | I16: 6 | J16: 6 | L16: 2000kg | M16: 0.5m/s | N16: 1 | O16: 18H001299 | P16: 4#货 | Y16: =IF(TRIM($B16&$C16)="","",IF(OR($W16="安装免保",$W16="技术免保",$W16="质保期内"),IF(NOT(ISNUMBER($X16)),"▲免保到期日没填",IF($X16<TODAY(),"▲免保已到期，转收费",IF($X16-TODAY()<=提醒天数,"免保剩"&($X16-TODAY())&"天","免保中"))),IF($W16="暂停维保","暂停中",IF($W16="已解约","已解约","")))) | Z16: =IF(TRIM($B16&$C16)="","",TRIM(IF($AA16="","",IF($AA16<TODAY(),"年检已过期"&(TODAY()-$AA16)&"天 ",IF($AA16-TODAY()<=提醒天数,"年检剩"&($AA16-TODAY())&"天 ","")))&IF($AB16="","",IF($AB16<TODAY(),"限速器已过期"&(TODAY()-$AB16)&"天 ",IF($AB16-TODAY()<=提醒天数,"限速器剩"&($AB16-TODAY())&"天 ","")))&IF($AC16="","",IF($AC16<TODAY(),"载重试验已过期"&(TODAY()-$AC16)&"天 ",IF($AC16-TODAY()<=提醒天数,"载重试验剩"&($AC16-TODAY())&"天 ",""))))) | AA16: =IF(TRIM($Q16&"")="","",IF(ISNUMBER($Q16),IF($Q16>10000,$Q16,IFERROR(DATE(INT($Q16),IF(ROUND(MOD($Q16,1)*100,0)>12,ROUND(MOD($Q16,1)*10,0),ROUND(MOD($Q16,1)*100,0))+1,0),"")),IFERROR(IF(LEN($Q16)-LEN(SUBSTITUTE($Q16,".",""))>=2,DATEVALUE(SUBSTITUTE(TRIM($Q16),".","-")),DATE(VALUE(LEFT(TRIM($Q16),4)),VALUE(MID(TRIM($Q16),6,2))+1,0)),""))) | AB16: =IF(TRIM($S16&"")="","",IF(ISNUMBER($S16),IF($S16>10000,$S16,IFERROR(DATE(INT($S16),IF(ROUND(MOD($S16,1)*100,0)>12,ROUND(MOD($S16,1)*10,0),ROUND(MOD($S16,1)*100,0))+1,0),"")),IFERROR(IF(LEN($S16)-LEN(SUBSTITUTE($S16,".",""))>=2,DATEVALUE(SUBSTITUTE(TRIM($S16),".","-")),DATE(VALUE(LEFT(TRIM($S16),4)),VALUE(MID(TRIM($S16),6,2))+1,0)),""))) | AC16: =IF(TRIM($T16&"")="","",IF(ISNUMBER($T16),IF($T16>10000,$T16,IFERROR(DATE(INT($T16),IF(ROUND(MOD($T16,1)*100,0)>12,ROUND(MOD($T16,1)*10,0),ROUND(MOD($T16,1)*100,0))+1,0),"")),IFERROR(IF(LEN($T16)-LEN(SUBSTITUTE($T16,".",""))>=2,DATEVALUE(SUBSTITUTE(TRIM($T16),".","-")),DATE(VALUE(LEFT(TRIM($T16),4)),VALUE(MID(TRIM($T16),6,2))+1,0)),"")))
B17: 武汉尊品益康意食品有限公司 | C17: 意康意厂房 | D17: LTK | E17: 3110420100201907Z115 | F17: 108415 | G17: 菱王电梯股份有限公司 | H17: 客梯 | I17: 6 | J17: 6 | L17: 1050kg | M17: 1.0m/s | N17: 1 | O17: 18K001875 | P17: 1#客 | Y17: =IF(TRIM($B17&$C17)="","",IF(OR($W17="安装免保",$W17="技术免保",$W17="质保期内"),IF(NOT(ISNUMBER($X17)),"▲免保到期日没填",IF($X17<TODAY(),"▲免保已到期，转收费",IF($X17-TODAY()<=提醒天数,"免保剩"&($X17-TODAY())&"天","免保中"))),IF($W17="暂停维保","暂停中",IF($W17="已解约","已解约","")))) | Z17: =IF(TRIM($B17&$C17)="","",TRIM(IF($AA17="","",IF($AA17<TODAY(),"年检已过期"&(TODAY()-$AA17)&"天 ",IF($AA17-TODAY()<=提醒天数,"年检剩"&($AA17-TODAY())&"天 ","")))&IF($AB17="","",IF($AB17<TODAY(),"限速器已过期"&(TODAY()-$AB17)&"天 ",IF($AB17-TODAY()<=提醒天数,"限速器剩"&($AB17-TODAY())&"天 ","")))&IF($AC17="","",IF($AC17<TODAY(),"载重试验已过期"&(TODAY()-$AC17)&"天 ",IF($AC17-TODAY()<=提醒天数,"载重试验剩"&($AC17-TODAY())&"天 ",""))))) | AA17: =IF(TRIM($Q17&"")="","",IF(ISNUMBER($Q17),IF($Q17>10000,$Q17,IFERROR(DATE(INT($Q17),IF(ROUND(MOD($Q17,1)*100,0)>12,ROUND(MOD($Q17,1)*10,0),ROUND(MOD($Q17,1)*100,0))+1,0),"")),IFERROR(IF(LEN($Q17)-LEN(SUBSTITUTE($Q17,".",""))>=2,DATEVALUE(SUBSTITUTE(TRIM($Q17),".","-")),DATE(VALUE(LEFT(TRIM($Q17),4)),VALUE(MID(TRIM($Q17),6,2))+1,0)),""))) | AB17: =IF(TRIM($S17&"")="","",IF(ISNUMBER($S17),IF($S17>10000,$S17,IFERROR(DATE(INT($S17),IF(ROUND(MOD($S17,1)*100,0)>12,ROUND(MOD($S17,1)*10,0),ROUND(MOD($S17,1)*100,0))+1,0),"")),IFERROR(IF(LEN($S17)-LEN(SUBSTITUTE($S17,".",""))>=2,DATEVALUE(SUBSTITUTE(TRIM($S17),".","-")),DATE(VALUE(LEFT(TRIM($S17),4)),VALUE(MID(TRIM($S17),6,2))+1,0)),""))) | AC17: =IF(TRIM($T17&"")="","",IF(ISNUMBER($T17),IF($T17>10000,$T17,IFERROR(DATE(INT($T17),IF(ROUND(MOD($T17,1)*100,0)>12,ROUND(MOD($T17,1)*10,0),ROUND(MOD($T17,1)*100,0))+1,0),"")),IFERROR(IF(LEN($T17)-LEN(SUBSTITUTE($T17,".",""))>=2,DATEVALUE(SUBSTITUTE(TRIM($T17),".","-")),DATE(VALUE(LEFT(TRIM($T17),4)),VALUE(MID(TRIM($T17),6,2))+1,0)),"")))
B18: 武汉光谷铁神新材料孵化器有限公司 | C18: 光谷铁神孵化器 | D18: MAX-E1050-C01.75 | E18: 31104201192020010040 | F18: 梯11鄂A28927（20） | G18: 广州广日 | H18: 客梯 | I18: 17 | J18: 17 | K18: 17 | L18: 1050kg | M18: 1.75m/s | N18: 1 | O18: 19278033001 | P18: 1号楼1#梯 | Y18: =IF(TRIM($B18&$C18)="","",IF(OR($W18="安装免保",$W18="技术免保",$W18="质保期内"),IF(NOT(ISNUMBER($X18)),"▲免保到期日没填",IF($X18<TODAY(),"▲免保已到期，转收费",IF($X18-TODAY()<=提醒天数,"免保剩"&($X18-TODAY())&"天","免保中"))),IF($W18="暂停维保","暂停中",IF($W18="已解约","已解约","")))) | Z18: =IF(TRIM($B18&$C18)="","",TRIM(IF($AA18="","",IF($AA18<TODAY(),"年检已过期"&(TODAY()-$AA18)&"天 ",IF($AA18-TODAY()<=提醒天数,"年检剩"&($AA18-TODAY())&"天 ","")))&IF($AB18="","",IF($AB18<TODAY(),"限速器已过期"&(TODAY()-$AB18)&"天 ",IF($AB18-TODAY()<=提醒天数,"限速器剩"&($AB18-TODAY())&"天 ","")))&IF($AC18="","",IF($AC18<TODAY(),"载重试验已过期"&(TODAY()-$AC18)&"天 ",IF($AC18-TODAY()<=提醒天数,"载重试验剩"&($AC18-TODAY())&"天 ",""))))) | AA18: =IF(TRIM($Q18&"")="","",IF(ISNUMBER($Q18),IF($Q18>10000,$Q18,IFERROR(DATE(INT($Q18),IF(ROUND(MOD($Q18,1)*100,0)>12,ROUND(MOD($Q18,1)*10,0),ROUND(MOD($Q18,1)*100,0))+1,0),"")),IFERROR(IF(LEN($Q18)-LEN(SUBSTITUTE($Q18,".",""))>=2,DATEVALUE(SUBSTITUTE(TRIM($Q18),".","-")),DATE(VALUE(LEFT(TRIM($Q18),4)),VALUE(MID(TRIM($Q18),6,2))+1,0)),""))) | AB18: =IF(TRIM($S18&"")="","",IF(ISNUMBER($S18),IF($S18>10000,$S18,IFERROR(DATE(INT($S18),IF(ROUND(MOD($S18,1)*100,0)>12,ROUND(MOD($S18,1)*10,0),ROUND(MOD($S18,1)*100,0))+1,0),"")),IFERROR(IF(LEN($S18)-LEN(SUBSTITUTE($S18,".",""))>=2,DATEVALUE(SUBSTITUTE(TRIM($S18),".","-")),DATE(VALUE(LEFT(TRIM($S18),4)),VALUE(MID(TRIM($S18),6,2))+1,0)),""))) | AC18: =IF(TRIM($T18&"")="","",IF(ISNUMBER($T18),IF($T18>10000,$T18,IFERROR(DATE(INT($T18),IF(ROUND(MOD($T18,1)*100,0)>12,ROUND(MOD($T18,1)*10,0),ROUND(MOD($T18,1)*100,0))+1,0),"")),IFERROR(IF(LEN($T18)-LEN(SUBSTITUTE($T18,".",""))>=2,DATEVALUE(SUBSTITUTE(TRIM($T18),".","-")),DATE(VALUE(LEFT(TRIM($T18),4)),VALUE(MID(TRIM($T18),6,2))+1,0)),"")))
B19: 武汉光谷铁神新材料孵化器有限公司 | C19: 光谷铁神孵化器 | D19: MAX-E1050-C01.75 | E19: 31104201192020010041 | F19: 梯11鄂A28928（20） | G19: 广州广日 | H19: 客梯 | I19: 16 | J19: 16 | K19: 16 | L19: 1050kg | M19: 1.75m/s | N19: 1 | O19: 19278033002 | P19: 1号楼2#梯 | Y19: =IF(TRIM($B19&$C19)="","",IF(OR($W19="安装免保",$W19="技术免保",$W19="质保期内"),IF(NOT(ISNUMBER($X19)),"▲免保到期日没填",IF($X19<TODAY(),"▲免保已到期，转收费",IF($X19-TODAY()<=提醒天数,"免保剩"&($X19-TODAY())&"天","免保中"))),IF($W19="暂停维保","暂停中",IF($W19="已解约","已解约","")))) | Z19: =IF(TRIM($B19&$C19)="","",TRIM(IF($AA19="","",IF($AA19<TODAY(),"年检已过期"&(TODAY()-$AA19)&"天 ",IF($AA19-TODAY()<=提醒天数,"年检剩"&($AA19-TODAY())&"天 ","")))&IF($AB19="","",IF($AB19<TODAY(),"限速器已过期"&(TODAY()-$AB19)&"天 ",IF($AB19-TODAY()<=提醒天数,"限速器剩"&($AB19-TODAY())&"天 ","")))&IF($AC19="","",IF($AC19<TODAY(),"载重试验已过期"&(TODAY()-$AC19)&"天 ",IF($AC19-TODAY()<=提醒天数,"载重试验剩"&($AC19-TODAY())&"天 ",""))))) | AA19: =IF(TRIM($Q19&"")="","",IF(ISNUMBER($Q19),IF($Q19>10000,$Q19,IFERROR(DATE(INT($Q19),IF(ROUND(MOD($Q19,1)*100,0)>12,ROUND(MOD($Q19,1)*10,0),ROUND(MOD($Q19,1)*100,0))+1,0),"")),IFERROR(IF(LEN($Q19)-LEN(SUBSTITUTE($Q19,".",""))>=2,DATEVALUE(SUBSTITUTE(TRIM($Q19),".","-")),DATE(VALUE(LEFT(TRIM($Q19),4)),VALUE(MID(TRIM($Q19),6,2))+1,0)),""))) | AB19: =IF(TRIM($S19&"")="","",IF(ISNUMBER($S19),IF($S19>10000,$S19,IFERROR(DATE(INT($S19),IF(ROUND(MOD($S19,1)*100,0)>12,ROUND(MOD($S19,1)*10,0),ROUND(MOD($S19,1)*100,0))+1,0),"")),IFERROR(IF(LEN($S19)-LEN(SUBSTITUTE($S19,".",""))>=2,DATEVALUE(SUBSTITUTE(TRIM($S19),".","-")),DATE(VALUE(LEFT(TRIM($S19),4)),VALUE(MID(TRIM($S19),6,2))+1,0)),""))) | AC19: =IF(TRIM($T19&"")="","",IF(ISNUMBER($T19),IF($T19>10000,$T19,IFERROR(DATE(INT($T19),IF(ROUND(MOD($T19,1)*100,0)>12,ROUND(MOD($T19,1)*10,0),ROUND(MOD($T19,1)*100,0))+1,0),"")),IFERROR(IF(LEN($T19)-LEN(SUBSTITUTE($T19,".",""))>=2,DATEVALUE(SUBSTITUTE(TRIM($T19),".","-")),DATE(VALUE(LEFT(TRIM($T19),4)),VALUE(MID(TRIM($T19),6,2))+1,0)),"")))
B20: 武汉光谷铁神新材料孵化器有限公司 | C20: 光谷铁神孵化器 | D20: MAX-E1050-C01.75 | E20: 31104201192020010042 | F20: 梯11鄂A28929（20） | G20: 广州广日 | H20: 客梯 | I20: 14 | J20: 14 | K20: 14 | L20: 1050kg | M20: 1.75m/s | N20: 1 | O20: 19278033003 | P20: 2号楼1#梯 | Y20: =IF(TRIM($B20&$C20)="","",IF(OR($W20="安装免保",$W20="技术免保",$W20="质保期内"),IF(NOT(ISNUMBER($X20)),"▲免保到期日没填",IF($X20<TODAY(),"▲免保已到期，转收费",IF($X20-TODAY()<=提醒天数,"免保剩"&($X20-TODAY())&"天","免保中"))),IF($W20="暂停维保","暂停中",IF($W20="已解约","已解约","")))) | Z20: =IF(TRIM($B20&$C20)="","",TRIM(IF($AA20="","",IF($AA20<TODAY(),"年检已过期"&(TODAY()-$AA20)&"天 ",IF($AA20-TODAY()<=提醒天数,"年检剩"&($AA20-TODAY())&"天 ","")))&IF($AB20="","",IF($AB20<TODAY(),"限速器已过期"&(TODAY()-$AB20)&"天 ",IF($AB20-TODAY()<=提醒天数,"限速器剩"&($AB20-TODAY())&"天 ","")))&IF($AC20="","",IF($AC20<TODAY(),"载重试验已过期"&(TODAY()-$AC20)&"天 ",IF($AC20-TODAY()<=提醒天数,"载重试验剩"&($AC20-TODAY())&"天 ",""))))) | AA20: =IF(TRIM($Q20&"")="","",IF(ISNUMBER($Q20),IF($Q20>10000,$Q20,IFERROR(DATE(INT($Q20),IF(ROUND(MOD($Q20,1)*100,0)>12,ROUND(MOD($Q20,1)*10,0),ROUND(MOD($Q20,1)*100,0))+1,0),"")),IFERROR(IF(LEN($Q20)-LEN(SUBSTITUTE($Q20,".",""))>=2,DATEVALUE(SUBSTITUTE(TRIM($Q20),".","-")),DATE(VALUE(LEFT(TRIM($Q20),4)),VALUE(MID(TRIM($Q20),6,2))+1,0)),""))) | AB20: =IF(TRIM($S20&"")="","",IF(ISNUMBER($S20),IF($S20>10000,$S20,IFERROR(DATE(INT($S20),IF(ROUND(MOD($S20,1)*100,0)>12,ROUND(MOD($S20,1)*10,0),ROUND(MOD($S20,1)*100,0))+1,0),"")),IFERROR(IF(LEN($S20)-LEN(SUBSTITUTE($S20,".",""))>=2,DATEVALUE(SUBSTITUTE(TRIM($S20),".","-")),DATE(VALUE(LEFT(TRIM($S20),4)),VALUE(MID(TRIM($S20),6,2))+1,0)),""))) | AC20: =IF(TRIM($T20&"")="","",IF(ISNUMBER($T20),IF($T20>10000,$T20,IFERROR(DATE(INT($T20),IF(ROUND(MOD($T20,1)*100,0)>12,ROUND(MOD($T20,1)*10,0),ROUND(MOD($T20,1)*100,0))+1,0),"")),IFERROR(IF(LEN($T20)-LEN(SUBSTITUTE($T20,".",""))>=2,DATEVALUE(SUBSTITUTE(TRIM($T20),".","-")),DATE(VALUE(LEFT(TRIM($T20),4)),VALUE(MID(TRIM($T20),6,2))+1,0)),"")))
B21: 武汉光谷铁神新材料孵化器有限公司 | C21: 光谷铁神孵化器 | D21: MAX-E1050-C01.75 | E21: 31104201192020010043 | F21: 梯11鄂A28930（20） | G21: 广州广日 | H21: 客梯 | I21: 14 | J21: 14 | K21: 14 | L21: 1050kg | M21: 1.75m/s | N21: 1 | O21: 19278033004 | P21: 3号楼1#梯 | Y21: =IF(TRIM($B21&$C21)="","",IF(OR($W21="安装免保",$W21="技术免保",$W21="质保期内"),IF(NOT(ISNUMBER($X21)),"▲免保到期日没填",IF($X21<TODAY(),"▲免保已到期，转收费",IF($X21-TODAY()<=提醒天数,"免保剩"&($X21-TODAY())&"天","免保中"))),IF($W21="暂停维保","暂停中",IF($W21="已解约","已解约","")))) | Z21: =IF(TRIM($B21&$C21)="","",TRIM(IF($AA21="","",IF($AA21<TODAY(),"年检已过期"&(TODAY()-$AA21)&"天 ",IF($AA21-TODAY()<=提醒天数,"年检剩"&($AA21-TODAY())&"天 ","")))&IF($AB21="","",IF($AB21<TODAY(),"限速器已过期"&(TODAY()-$AB21)&"天 ",IF($AB21-TODAY()<=提醒天数,"限速器剩"&($AB21-TODAY())&"天 ","")))&IF($AC21="","",IF($AC21<TODAY(),"载重试验已过期"&(TODAY()-$AC21)&"天 ",IF($AC21-TODAY()<=提醒天数,"载重试验剩"&($AC21-TODAY())&"天 ",""))))) | AA21: =IF(TRIM($Q21&"")="","",IF(ISNUMBER($Q21),IF($Q21>10000,$Q21,IFERROR(DATE(INT($Q21),IF(ROUND(MOD($Q21,1)*100,0)>12,ROUND(MOD($Q21,1)*10,0),ROUND(MOD($Q21,1)*100,0))+1,0),"")),IFERROR(IF(LEN($Q21)-LEN(SUBSTITUTE($Q21,".",""))>=2,DATEVALUE(SUBSTITUTE(TRIM($Q21),".","-")),DATE(VALUE(LEFT(TRIM($Q21),4)),VALUE(MID(TRIM($Q21),6,2))+1,0)),""))) | AB21: =IF(TRIM($S21&"")="","",IF(ISNUMBER($S21),IF($S21>10000,$S21,IFERROR(DATE(INT($S21),IF(ROUND(MOD($S21,1)*100,0)>12,ROUND(MOD($S21,1)*10,0),ROUND(MOD($S21,1)*100,0))+1,0),"")),IFERROR(IF(LEN($S21)-LEN(SUBSTITUTE($S21,".",""))>=2,DATEVALUE(SUBSTITUTE(TRIM($S21),".","-")),DATE(VALUE(LEFT(TRIM($S21),4)),VALUE(MID(TRIM($S21),6,2))+1,0)),""))) | AC21: =IF(TRIM($T21&"")="","",IF(ISNUMBER($T21),IF($T21>10000,$T21,IFERROR(DATE(INT($T21),IF(ROUND(MOD($T21,1)*100,0)>12,ROUND(MOD($T21,1)*10,0),ROUND(MOD($T21,1)*100,0))+1,0),"")),IFERROR(IF(LEN($T21)-LEN(SUBSTITUTE($T21,".",""))>=2,DATEVALUE(SUBSTITUTE(TRIM($T21),".","-")),DATE(VALUE(LEFT(TRIM($T21),4)),VALUE(MID(TRIM($T21),6,2))+1,0)),"")))
B22: 武汉光谷铁神新材料孵化器有限公司 | C22: 光谷铁神孵化器 | D22: MAX-E1050-C01.75 | E22: 31104201192020010044 | F22: 梯11鄂A28931（20） | G22: 广州广日 | H22: 客梯 | I22: 13 | J22: 13 | K22: 13 | L22: 1050kg | M22: 1.75m/s | N22: 1 | O22: 19278033005 | P22: 2号楼2#梯 | Y22: =IF(TRIM($B22&$C22)="","",IF(OR($W22="安装免保",$W22="技术免保",$W22="质保期内"),IF(NOT(ISNUMBER($X22)),"▲免保到期日没填",IF($X22<TODAY(),"▲免保已到期，转收费",IF($X22-TODAY()<=提醒天数,"免保剩"&($X22-TODAY())&"天","免保中"))),IF($W22="暂停维保","暂停中",IF($W22="已解约","已解约","")))) | Z22: =IF(TRIM($B22&$C22)="","",TRIM(IF($AA22="","",IF($AA22<TODAY(),"年检已过期"&(TODAY()-$AA22)&"天 ",IF($AA22-TODAY()<=提醒天数,"年检剩"&($AA22-TODAY())&"天 ","")))&IF($AB22="","",IF($AB22<TODAY(),"限速器已过期"&(TODAY()-$AB22)&"天 ",IF($AB22-TODAY()<=提醒天数,"限速器剩"&($AB22-TODAY())&"天 ","")))&IF($AC22="","",IF($AC22<TODAY(),"载重试验已过期"&(TODAY()-$AC22)&"天 ",IF($AC22-TODAY()<=提醒天数,"载重试验剩"&($AC22-TODAY())&"天 ",""))))) | AA22: =IF(TRIM($Q22&"")="","",IF(ISNUMBER($Q22),IF($Q22>10000,$Q22,IFERROR(DATE(INT($Q22),IF(ROUND(MOD($Q22,1)*100,0)>12,ROUND(MOD($Q22,1)*10,0),ROUND(MOD($Q22,1)*100,0))+1,0),"")),IFERROR(IF(LEN($Q22)-LEN(SUBSTITUTE($Q22,".",""))>=2,DATEVALUE(SUBSTITUTE(TRIM($Q22),".","-")),DATE(VALUE(LEFT(TRIM($Q22),4)),VALUE(MID(TRIM($Q22),6,2))+1,0)),""))) | AB22: =IF(TRIM($S22&"")="","",IF(ISNUMBER($S22),IF($S22>10000,$S22,IFERROR(DATE(INT($S22),IF(ROUND(MOD($S22,1)*100,0)>12,ROUND(MOD($S22,1)*10,0),ROUND(MOD($S22,1)*100,0))+1,0),"")),IFERROR(IF(LEN($S22)-LEN(SUBSTITUTE($S22,".",""))>=2,DATEVALUE(SUBSTITUTE(TRIM($S22),".","-")),DATE(VALUE(LEFT(TRIM($S22),4)),VALUE(MID(TRIM($S22),6,2))+1,0)),""))) | AC22: =IF(TRIM($T22&"")="","",IF(ISNUMBER($T22),IF($T22>10000,$T22,IFERROR(DATE(INT($T22),IF(ROUND(MOD($T22,1)*100,0)>12,ROUND(MOD($T22,1)*10,0),ROUND(MOD($T22,1)*100,0))+1,0),"")),IFERROR(IF(LEN($T22)-LEN(SUBSTITUTE($T22,".",""))>=2,DATEVALUE(SUBSTITUTE(TRIM($T22),".","-")),DATE(VALUE(LEFT(TRIM($T22),4)),VALUE(MID(TRIM($T22),6,2))+1,0)),"")))
B23: 武汉光谷铁神新材料孵化器有限公司 | C23: 光谷铁神孵化器 | D23: MAX-E1050-C01.75 | E23: 31104201192020010045 | F23: 梯11鄂A28932（20） | G23: 广州广日 | H23: 客梯 | I23: 13 | J23: 13 | K23: 13 | L23: 1050kg | M23: 1.75m/s | N23: 1 | O23: 19278033006 | P23: 3号楼2#梯 | Y23: =IF(TRIM($B23&$C23)="","",IF(OR($W23="安装免保",$W23="技术免保",$W23="质保期内"),IF(NOT(ISNUMBER($X23)),"▲免保到期日没填",IF($X23<TODAY(),"▲免保已到期，转收费",IF($X23-TODAY()<=提醒天数,"免保剩"&($X23-TODAY())&"天","免保中"))),IF($W23="暂停维保","暂停中",IF($W23="已解约","已解约","")))) | Z23: =IF(TRIM($B23&$C23)="","",TRIM(IF($AA23="","",IF($AA23<TODAY(),"年检已过期"&(TODAY()-$AA23)&"天 ",IF($AA23-TODAY()<=提醒天数,"年检剩"&($AA23-TODAY())&"天 ","")))&IF($AB23="","",IF($AB23<TODAY(),"限速器已过期"&(TODAY()-$AB23)&"天 ",IF($AB23-TODAY()<=提醒天数,"限速器剩"&($AB23-TODAY())&"天 ","")))&IF($AC23="","",IF($AC23<TODAY(),"载重试验已过期"&(TODAY()-$AC23)&"天 ",IF($AC23-TODAY()<=提醒天数,"载重试验剩"&($AC23-TODAY())&"天 ",""))))) | AA23: =IF(TRIM($Q23&"")="","",IF(ISNUMBER($Q23),IF($Q23>10000,$Q23,IFERROR(DATE(INT($Q23),IF(ROUND(MOD($Q23,1)*100,0)>12,ROUND(MOD($Q23,1)*10,0),ROUND(MOD($Q23,1)*100,0))+1,0),"")),IFERROR(IF(LEN($Q23)-LEN(SUBSTITUTE($Q23,".",""))>=2,DATEVALUE(SUBSTITUTE(TRIM($Q23),".","-")),DATE(VALUE(LEFT(TRIM($Q23),4)),VALUE(MID(TRIM($Q23),6,2))+1,0)),""))) | AB23: =IF(TRIM($S23&"")="","",IF(ISNUMBER($S23),IF($S23>10000,$S23,IFERROR(DATE(INT($S23),IF(ROUND(MOD($S23,1)*100,0)>12,ROUND(MOD($S23,1)*10,0),ROUND(MOD($S23,1)*100,0))+1,0),"")),IFERROR(IF(LEN($S23)-LEN(SUBSTITUTE($S23,".",""))>=2,DATEVALUE(SUBSTITUTE(TRIM($S23),".","-")),DATE(VALUE(LEFT(TRIM($S23),4)),VALUE(MID(TRIM($S23),6,2))+1,0)),""))) | AC23: =IF(TRIM($T23&"")="","",IF(ISNUMBER($T23),IF($T23>10000,$T23,IFERROR(DATE(INT($T23),IF(ROUND(MOD($T23,1)*100,0)>12,ROUND(MOD($T23,1)*10,0),ROUND(MOD($T23,1)*100,0))+1,0),"")),IFERROR(IF(LEN($T23)-LEN(SUBSTITUTE($T23,".",""))>=2,DATEVALUE(SUBSTITUTE(TRIM($T23),".","-")),DATE(VALUE(LEFT(TRIM($T23),4)),VALUE(MID(TRIM($T23),6,2))+1,0)),"")))
B24: 湖北京通建材有限公司 | C24: 蔡甸老水泥厂 | D24: CTRL80 | E24: 30104201142013070007 | G24: 快意电梯 | H24: 客梯 | I24: 5 | J24: 5 | L24: 1050kg | M24: 1.0m/s | N24: 1 | O24: K14777 | P24: 1#客梯 | Y24: =IF(TRIM($B24&$C24)="","",IF(OR($W24="安装免保",$W24="技术免保",$W24="质保期内"),IF(NOT(ISNUMBER($X24)),"▲免保到期日没填",IF($X24<TODAY(),"▲免保已到期，转收费",IF($X24-TODAY()<=提醒天数,"免保剩"&($X24-TODAY())&"天","免保中"))),IF($W24="暂停维保","暂停中",IF($W24="已解约","已解约","")))) | Z24: =IF(TRIM($B24&$C24)="","",TRIM(IF($AA24="","",IF($AA24<TODAY(),"年检已过期"&(TODAY()-$AA24)&"天 ",IF($AA24-TODAY()<=提醒天数,"年检剩"&($AA24-TODAY())&"天 ","")))&IF($AB24="","",IF($AB24<TODAY(),"限速器已过期"&(TODAY()-$AB24)&"天 ",IF($AB24-TODAY()<=提醒天数,"限速器剩"&($AB24-TODAY())&"天 ","")))&IF($AC24="","",IF($AC24<TODAY(),"载重试验已过期"&(TODAY()-$AC24)&"天 ",IF($AC24-TODAY()<=提醒天数,"载重试验剩"&($AC24-TODAY())&"天 ",""))))) | AA24: =IF(TRIM($Q24&"")="","",IF(ISNUMBER($Q24),IF($Q24>10000,$Q24,IFERROR(DATE(INT($Q24),IF(ROUND(MOD($Q24,1)*100,0)>12,ROUND(MOD($Q24,1)*10,0),ROUND(MOD($Q24,1)*100,0))+1,0),"")),IFERROR(IF(LEN($Q24)-LEN(SUBSTITUTE($Q24,".",""))>=2,DATEVALUE(SUBSTITUTE(TRIM($Q24),".","-")),DATE(VALUE(LEFT(TRIM($Q24),4)),VALUE(MID(TRIM($Q24),6,2))+1,0)),""))) | AB24: =IF(TRIM($S24&"")="","",IF(ISNUMBER($S24),IF($S24>10000,$S24,IFERROR(DATE(INT($S24),IF(ROUND(MOD($S24,1)*100,0)>12,ROUND(MOD($S24,1)*10,0),ROUND(MOD($S24,1)*100,0))+1,0),"")),IFERROR(IF(LEN($S24)-LEN(SUBSTITUTE($S24,".",""))>=2,DATEVALUE(SUBSTITUTE(TRIM($S24),".","-")),DATE(VALUE(LEFT(TRIM($S24),4)),VALUE(MID(TRIM($S24),6,2))+1,0)),""))) | AC24: =IF(TRIM($T24&"")="","",IF(ISNUMBER($T24),IF($T24>10000,$T24,IFERROR(DATE(INT($T24),IF(ROUND(MOD($T24,1)*100,0)>12,ROUND(MOD($T24,1)*10,0),ROUND(MOD($T24,1)*100,0))+1,0),"")),IFERROR(IF(LEN($T24)-LEN(SUBSTITUTE($T24,".",""))>=2,DATEVALUE(SUBSTITUTE(TRIM($T24),".","-")),DATE(VALUE(LEFT(TRIM($T24),4)),VALUE(MID(TRIM($T24),6,2))+1,0)),"")))
B25: 湖北波罗金环保科技有限公司 | C25: 金澜湾工业园 | D25: XO-HIVF | E25: 31204201132016090002 | F25: 119757 | G25: 杭州西奥 | H25: 货梯 | I25: 5 | J25: 5 | K25: 5 | L25: 2000kg | M25: 1.0m/s | N25: 1 | O25: XOH A74744 | P25: 1#货 | Y25: =IF(TRIM($B25&$C25)="","",IF(OR($W25="安装免保",$W25="技术免保",$W25="质保期内"),IF(NOT(ISNUMBER($X25)),"▲免保到期日没填",IF($X25<TODAY(),"▲免保已到期，转收费",IF($X25-TODAY()<=提醒天数,"免保剩"&($X25-TODAY())&"天","免保中"))),IF($W25="暂停维保","暂停中",IF($W25="已解约","已解约","")))) | Z25: =IF(TRIM($B25&$C25)="","",TRIM(IF($AA25="","",IF($AA25<TODAY(),"年检已过期"&(TODAY()-$AA25)&"天 ",IF($AA25-TODAY()<=提醒天数,"年检剩"&($AA25-TODAY())&"天 ","")))&IF($AB25="","",IF($AB25<TODAY(),"限速器已过期"&(TODAY()-$AB25)&"天 ",IF($AB25-TODAY()<=提醒天数,"限速器剩"&($AB25-TODAY())&"天 ","")))&IF($AC25="","",IF($AC25<TODAY(),"载重试验已过期"&(TODAY()-$AC25)&"天 ",IF($AC25-TODAY()<=提醒天数,"载重试验剩"&($AC25-TODAY())&"天 ",""))))) | AA25: =IF(TRIM($Q25&"")="","",IF(ISNUMBER($Q25),IF($Q25>10000,$Q25,IFERROR(DATE(INT($Q25),IF(ROUND(MOD($Q25,1)*100,0)>12,ROUND(MOD($Q25,1)*10,0),ROUND(MOD($Q25,1)*100,0))+1,0),"")),IFERROR(IF(LEN($Q25)-LEN(SUBSTITUTE($Q25,".",""))>=2,DATEVALUE(SUBSTITUTE(TRIM($Q25),".","-")),DATE(VALUE(LEFT(TRIM($Q25),4)),VALUE(MID(TRIM($Q25),6,2))+1,0)),""))) | AB25: =IF(TRIM($S25&"")="","",IF(ISNUMBER($S25),IF($S25>10000,$S25,IFERROR(DATE(INT($S25),IF(ROUND(MOD($S25,1)*100,0)>12,ROUND(MOD($S25,1)*10,0),ROUND(MOD($S25,1)*100,0))+1,0),"")),IFERROR(IF(LEN($S25)-LEN(SUBSTITUTE($S25,".",""))>=2,DATEVALUE(SUBSTITUTE(TRIM($S25),".","-")),DATE(VALUE(LEFT(TRIM($S25),4)),VALUE(MID(TRIM($S25),6,2))+1,0)),""))) | AC25: =IF(TRIM($T25&"")="","",IF(ISNUMBER($T25),IF($T25>10000,$T25,IFERROR(DATE(INT($T25),IF(ROUND(MOD($T25,1)*100,0)>12,ROUND(MOD($T25,1)*10,0),ROUND(MOD($T25,1)*100,0))+1,0),"")),IFERROR(IF(LEN($T25)-LEN(SUBSTITUTE($T25,".",""))>=2,DATEVALUE(SUBSTITUTE(TRIM($T25),".","-")),DATE(VALUE(LEFT(TRIM($T25),4)),VALUE(MID(TRIM($T25),6,2))+1,0)),"")))
B26: 湖北波罗金环保科技有限公司 | C26: 金澜湾工业园 | D26: XO-REBO | E26: 31104201132016090038 | F26: 119759 | G26: 杭州西奥 | H26: 客梯 | I26: 5 | J26: 5 | K26: 5 | L26: 1000kg | M26: 1.0m/s | N26: 1 | O26: XOK A74745 | P26: 1#客 | Y26: =IF(TRIM($B26&$C26)="","",IF(OR($W26="安装免保",$W26="技术免保",$W26="质保期内"),IF(NOT(ISNUMBER($X26)),"▲免保到期日没填",IF($X26<TODAY(),"▲免保已到期，转收费",IF($X26-TODAY()<=提醒天数,"免保剩"&($X26-TODAY())&"天","免保中"))),IF($W26="暂停维保","暂停中",IF($W26="已解约","已解约","")))) | Z26: =IF(TRIM($B26&$C26)="","",TRIM(IF($AA26="","",IF($AA26<TODAY(),"年检已过期"&(TODAY()-$AA26)&"天 ",IF($AA26-TODAY()<=提醒天数,"年检剩"&($AA26-TODAY())&"天 ","")))&IF($AB26="","",IF($AB26<TODAY(),"限速器已过期"&(TODAY()-$AB26)&"天 ",IF($AB26-TODAY()<=提醒天数,"限速器剩"&($AB26-TODAY())&"天 ","")))&IF($AC26="","",IF($AC26<TODAY(),"载重试验已过期"&(TODAY()-$AC26)&"天 ",IF($AC26-TODAY()<=提醒天数,"载重试验剩"&($AC26-TODAY())&"天 ",""))))) | AA26: =IF(TRIM($Q26&"")="","",IF(ISNUMBER($Q26),IF($Q26>10000,$Q26,IFERROR(DATE(INT($Q26),IF(ROUND(MOD($Q26,1)*100,0)>12,ROUND(MOD($Q26,1)*10,0),ROUND(MOD($Q26,1)*100,0))+1,0),"")),IFERROR(IF(LEN($Q26)-LEN(SUBSTITUTE($Q26,".",""))>=2,DATEVALUE(SUBSTITUTE(TRIM($Q26),".","-")),DATE(VALUE(LEFT(TRIM($Q26),4)),VALUE(MID(TRIM($Q26),6,2))+1,0)),""))) | AB26: =IF(TRIM($S26&"")="","",IF(ISNUMBER($S26),IF($S26>10000,$S26,IFERROR(DATE(INT($S26),IF(ROUND(MOD($S26,1)*100,0)>12,ROUND(MOD($S26,1)*10,0),ROUND(MOD($S26,1)*100,0))+1,0),"")),IFERROR(IF(LEN($S26)-LEN(SUBSTITUTE($S26,".",""))>=2,DATEVALUE(SUBSTITUTE(TRIM($S26),".","-")),DATE(VALUE(LEFT(TRIM($S26),4)),VALUE(MID(TRIM($S26),6,2))+1,0)),""))) | AC26: =IF(TRIM($T26&"")="","",IF(ISNUMBER($T26),IF($T26>10000,$T26,IFERROR(DATE(INT($T26),IF(ROUND(MOD($T26,1)*100,0)>12,ROUND(MOD($T26,1)*10,0),ROUND(MOD($T26,1)*100,0))+1,0),"")),IFERROR(IF(LEN($T26)-LEN(SUBSTITUTE($T26,".",""))>=2,DATEVALUE(SUBSTITUTE(TRIM($T26),".","-")),DATE(VALUE(LEFT(TRIM($T26),4)),VALUE(MID(TRIM($T26),6,2))+1,0)),"")))
B27: 湖北波罗金环保科技有限公司 | C27: 金澜湾工业园 | D27: XO-REBO | E27: 31104201132016090039 | F27: 119760 | G27: 杭州西奥 | H27: 客梯 | I27: 5 | J27: 5 | K27: 5 | L27: 1000kg | M27: 1.0m/s | N27: 1 | O27: XOK A74743 | P27: 2#客 | Y27: =IF(TRIM($B27&$C27)="","",IF(OR($W27="安装免保",$W27="技术免保",$W27="质保期内"),IF(NOT(ISNUMBER($X27)),"▲免保到期日没填",IF($X27<TODAY(),"▲免保已到期，转收费",IF($X27-TODAY()<=提醒天数,"免保剩"&($X27-TODAY())&"天","免保中"))),IF($W27="暂停维保","暂停中",IF($W27="已解约","已解约","")))) | Z27: =IF(TRIM($B27&$C27)="","",TRIM(IF($AA27="","",IF($AA27<TODAY(),"年检已过期"&(TODAY()-$AA27)&"天 ",IF($AA27-TODAY()<=提醒天数,"年检剩"&($AA27-TODAY())&"天 ","")))&IF($AB27="","",IF($AB27<TODAY(),"限速器已过期"&(TODAY()-$AB27)&"天 ",IF($AB27-TODAY()<=提醒天数,"限速器剩"&($AB27-TODAY())&"天 ","")))&IF($AC27="","",IF($AC27<TODAY(),"载重试验已过期"&(TODAY()-$AC27)&"天 ",IF($AC27-TODAY()<=提醒天数,"载重试验剩"&($AC27-TODAY())&"天 ",""))))) | AA27: =IF(TRIM($Q27&"")="","",IF(ISNUMBER($Q27),IF($Q27>10000,$Q27,IFERROR(DATE(INT($Q27),IF(ROUND(MOD($Q27,1)*100,0)>12,ROUND(MOD($Q27,1)*10,0),ROUND(MOD($Q27,1)*100,0))+1,0),"")),IFERROR(IF(LEN($Q27)-LEN(SUBSTITUTE($Q27,".",""))>=2,DATEVALUE(SUBSTITUTE(TRIM($Q27),".","-")),DATE(VALUE(LEFT(TRIM($Q27),4)),VALUE(MID(TRIM($Q27),6,2))+1,0)),""))) | AB27: =IF(TRIM($S27&"")="","",IF(ISNUMBER($S27),IF($S27>10000,$S27,IFERROR(DATE(INT($S27),IF(ROUND(MOD($S27,1)*100,0)>12,ROUND(MOD($S27,1)*10,0),ROUND(MOD($S27,1)*100,0))+1,0),"")),IFERROR(IF(LEN($S27)-LEN(SUBSTITUTE($S27,".",""))>=2,DATEVALUE(SUBSTITUTE(TRIM($S27),".","-")),DATE(VALUE(LEFT(TRIM($S27),4)),VALUE(MID(TRIM($S27),6,2))+1,0)),""))) | AC27: =IF(TRIM($T27&"")="","",IF(ISNUMBER($T27),IF($T27>10000,$T27,IFERROR(DATE(INT($T27),IF(ROUND(MOD($T27,1)*100,0)>12,ROUND(MOD($T27,1)*10,0),ROUND(MOD($T27,1)*100,0))+1,0),"")),IFERROR(IF(LEN($T27)-LEN(SUBSTITUTE($T27,".",""))>=2,DATEVALUE(SUBSTITUTE(TRIM($T27),".","-")),DATE(VALUE(LEFT(TRIM($T27),4)),VALUE(MID(TRIM($T27),6,2))+1,0)),"")))
B28: 武汉鑫承丰市政工程有限公司 | C28: 汉南薇湖路鑫承丰办公楼 | D28: METIS | E28: 31104201132020090009 | F28: 137209 | G28: 快意电梯 | H28: 客梯 | I28: 5 | J28: 5 | K28: 5 | L28: 1050kg | M28: 1.0m/s | N28: 1 | O28: ZT2000003645 | P28: 1#客 | Y28: =IF(TRIM($B28&$C28)="","",IF(OR($W28="安装免保",$W28="技术免保",$W28="质保期内"),IF(NOT(ISNUMBER($X28)),"▲免保到期日没填",IF($X28<TODAY(),"▲免保已到期，转收费",IF($X28-TODAY()<=提醒天数,"免保剩"&($X28-TODAY())&"天","免保中"))),IF($W28="暂停维保","暂停中",IF($W28="已解约","已解约","")))) | Z28: =IF(TRIM($B28&$C28)="","",TRIM(IF($AA28="","",IF($AA28<TODAY(),"年检已过期"&(TODAY()-$AA28)&"天 ",IF($AA28-TODAY()<=提醒天数,"年检剩"&($AA28-TODAY())&"天 ","")))&IF($AB28="","",IF($AB28<TODAY(),"限速器已过期"&(TODAY()-$AB28)&"天 ",IF($AB28-TODAY()<=提醒天数,"限速器剩"&($AB28-TODAY())&"天 ","")))&IF($AC28="","",IF($AC28<TODAY(),"载重试验已过期"&(TODAY()-$AC28)&"天 ",IF($AC28-TODAY()<=提醒天数,"载重试验剩"&($AC28-TODAY())&"天 ",""))))) | AA28: =IF(TRIM($Q28&"")="","",IF(ISNUMBER($Q28),IF($Q28>10000,$Q28,IFERROR(DATE(INT($Q28),IF(ROUND(MOD($Q28,1)*100,0)>12,ROUND(MOD($Q28,1)*10,0),ROUND(MOD($Q28,1)*100,0))+1,0),"")),IFERROR(IF(LEN($Q28)-LEN(SUBSTITUTE($Q28,".",""))>=2,DATEVALUE(SUBSTITUTE(TRIM($Q28),".","-")),DATE(VALUE(LEFT(TRIM($Q28),4)),VALUE(MID(TRIM($Q28),6,2))+1,0)),""))) | AB28: =IF(TRIM($S28&"")="","",IF(ISNUMBER($S28),IF($S28>10000,$S28,IFERROR(DATE(INT($S28),IF(ROUND(MOD($S28,1)*100,0)>12,ROUND(MOD($S28,1)*10,0),ROUND(MOD($S28,1)*100,0))+1,0),"")),IFERROR(IF(LEN($S28)-LEN(SUBSTITUTE($S28,".",""))>=2,DATEVALUE(SUBSTITUTE(TRIM($S28),".","-")),DATE(VALUE(LEFT(TRIM($S28),4)),VALUE(MID(TRIM($S28),6,2))+1,0)),""))) | AC28: =IF(TRIM($T28&"")="","",IF(ISNUMBER($T28),IF($T28>10000,$T28,IFERROR(DATE(INT($T28),IF(ROUND(MOD($T28,1)*100,0)>12,ROUND(MOD($T28,1)*10,0),ROUND(MOD($T28,1)*100,0))+1,0),"")),IFERROR(IF(LEN($T28)-LEN(SUBSTITUTE($T28,".",""))>=2,DATEVALUE(SUBSTITUTE(TRIM($T28),".","-")),DATE(VALUE(LEFT(TRIM($T28),4)),VALUE(MID(TRIM($T28),6,2))+1,0)),"")))
B29: 武汉市宝嘉丽酒店管理有限公司 | C29: 纽宾凯拦江路店 | D29: EKW56 | E29: 31104201052020120038 | F29: 137210 | G29: 怡达快速电梯 | H29: 客梯 | I29: 2 | J29: 2 | K29: 2 | L29: 800kg | M29: 1.0m/s | N29: 1 | O29: K090258 | P29: 1#客梯 | Y29: =IF(TRIM($B29&$C29)="","",IF(OR($W29="安装免保",$W29="技术免保",$W29="质保期内"),IF(NOT(ISNUMBER($X29)),"▲免保到期日没填",IF($X29<TODAY(),"▲免保已到期，转收费",IF($X29-TODAY()<=提醒天数,"免保剩"&($X29-TODAY())&"天","免保中"))),IF($W29="暂停维保","暂停中",IF($W29="已解约","已解约","")))) | Z29: =IF(TRIM($B29&$C29)="","",TRIM(IF($AA29="","",IF($AA29<TODAY(),"年检已过期"&(TODAY()-$AA29)&"天 ",IF($AA29-TODAY()<=提醒天数,"年检剩"&($AA29-TODAY())&"天 ","")))&IF($AB29="","",IF($AB29<TODAY(),"限速器已过期"&(TODAY()-$AB29)&"天 ",IF($AB29-TODAY()<=提醒天数,"限速器剩"&($AB29-TODAY())&"天 ","")))&IF($AC29="","",IF($AC29<TODAY(),"载重试验已过期"&(TODAY()-$AC29)&"天 ",IF($AC29-TODAY()<=提醒天数,"载重试验剩"&($AC29-TODAY())&"天 ",""))))) | AA29: =IF(TRIM($Q29&"")="","",IF(ISNUMBER($Q29),IF($Q29>10000,$Q29,IFERROR(DATE(INT($Q29),IF(ROUND(MOD($Q29,1)*100,0)>12,ROUND(MOD($Q29,1)*10,0),ROUND(MOD($Q29,1)*100,0))+1,0),"")),IFERROR(IF(LEN($Q29)-LEN(SUBSTITUTE($Q29,".",""))>=2,DATEVALUE(SUBSTITUTE(TRIM($Q29),".","-")),DATE(VALUE(LEFT(TRIM($Q29),4)),VALUE(MID(TRIM($Q29),6,2))+1,0)),""))) | AB29: =IF(TRIM($S29&"")="","",IF(ISNUMBER($S29),IF($S29>10000,$S29,IFERROR(DATE(INT($S29),IF(ROUND(MOD($S29,1)*100,0)>12,ROUND(MOD($S29,1)*10,0),ROUND(MOD($S29,1)*100,0))+1,0),"")),IFERROR(IF(LEN($S29)-LEN(SUBSTITUTE($S29,".",""))>=2,DATEVALUE(SUBSTITUTE(TRIM($S29),".","-")),DATE(VALUE(LEFT(TRIM($S29),4)),VALUE(MID(TRIM($S29),6,2))+1,0)),""))) | AC29: =IF(TRIM($T29&"")="","",IF(ISNUMBER($T29),IF($T29>10000,$T29,IFERROR(DATE(INT($T29),IF(ROUND(MOD($T29,1)*100,0)>12,ROUND(MOD($T29,1)*10,0),ROUND(MOD($T29,1)*100,0))+1,0),"")),IFERROR(IF(LEN($T29)-LEN(SUBSTITUTE($T29,".",""))>=2,DATEVALUE(SUBSTITUTE(TRIM($T29),".","-")),DATE(VALUE(LEFT(TRIM($T29),4)),VALUE(MID(TRIM($T29),6,2))+1,0)),"")))
B30: 湖北海推智能装备有限公司 | C30: 东西湖年产1000台 | D30: EKJ10 | E30: 31204201122020110008 | F30: 123868 | G30: 怡达快速电梯 | H30: 客梯 | I30: 6 | J30: 6 | K30: 6 | L30: 1000kg | M30: 1.0m/s | N30: 1 | O30: J070208.5 | P30: 办公楼5# | Y30: =IF(TRIM($B30&$C30)="","",IF(OR($W30="安装免保",$W30="技术免保",$W30="质保期内"),IF(NOT(ISNUMBER($X30)),"▲免保到期日没填",IF($X30<TODAY(),"▲免保已到期，转收费",IF($X30-TODAY()<=提醒天数,"免保剩"&($X30-TODAY())&"天","免保中"))),IF($W30="暂停维保","暂停中",IF($W30="已解约","已解约","")))) | Z30: =IF(TRIM($B30&$C30)="","",TRIM(IF($AA30="","",IF($AA30<TODAY(),"年检已过期"&(TODAY()-$AA30)&"天 ",IF($AA30-TODAY()<=提醒天数,"年检剩"&($AA30-TODAY())&"天 ","")))&IF($AB30="","",IF($AB30<TODAY(),"限速器已过期"&(TODAY()-$AB30)&"天 ",IF($AB30-TODAY()<=提醒天数,"限速器剩"&($AB30-TODAY())&"天 ","")))&IF($AC30="","",IF($AC30<TODAY(),"载重试验已过期"&(TODAY()-$AC30)&"天 ",IF($AC30-TODAY()<=提醒天数,"载重试验剩"&($AC30-TODAY())&"天 ",""))))) | AA30: =IF(TRIM($Q30&"")="","",IF(ISNUMBER($Q30),IF($Q30>10000,$Q30,IFERROR(DATE(INT($Q30),IF(ROUND(MOD($Q30,1)*100,0)>12,ROUND(MOD($Q30,1)*10,0),ROUND(MOD($Q30,1)*100,0))+1,0),"")),IFERROR(IF(LEN($Q30)-LEN(SUBSTITUTE($Q30,".",""))>=2,DATEVALUE(SUBSTITUTE(TRIM($Q30),".","-")),DATE(VALUE(LEFT(TRIM($Q30),4)),VALUE(MID(TRIM($Q30),6,2))+1,0)),""))) | AB30: =IF(TRIM($S30&"")="","",IF(ISNUMBER($S30),IF($S30>10000,$S30,IFERROR(DATE(INT($S30),IF(ROUND(MOD($S30,1)*100,0)>12,ROUND(MOD($S30,1)*10,0),ROUND(MOD($S30,1)*100,0))+1,0),"")),IFERROR(IF(LEN($S30)-LEN(SUBSTITUTE($S30,".",""))>=2,DATEVALUE(SUBSTITUTE(TRIM($S30),".","-")),DATE(VALUE(LEFT(TRIM($S30),4)),VALUE(MID(TRIM($S30),6,2))+1,0)),""))) | AC30: =IF(TRIM($T30&"")="","",IF(ISNUMBER($T30),IF($T30>10000,$T30,IFERROR(DATE(INT($T30),IF(ROUND(MOD($T30,1)*100,0)>12,ROUND(MOD($T30,1)*10,0),ROUND(MOD($T30,1)*100,0))+1,0),"")),IFERROR(IF(LEN($T30)-LEN(SUBSTITUTE($T30,".",""))>=2,DATEVALUE(SUBSTITUTE(TRIM($T30),".","-")),DATE(VALUE(LEFT(TRIM($T30),4)),VALUE(MID(TRIM($T30),6,2))+1,0)),"")))
B31: 武汉中海联机电工程有限公司 | C31: 滨江苑一期3-1（任侠） | D31: KLWG | E31: 31104201002021031929 | F31: 137211 | G31: 康力电梯 | H31: 客梯 | I31: 7 | J31: 7 | K31: 7 | L31: 800kg | M31: 1.0m/s | N31: 1 | O31: 10052351-0010 | P31: 3栋1单元1#梯 | Y31: =IF(TRIM($B31&$C31)="","",IF(OR($W31="安装免保",$W31="技术免保",$W31="质保期内"),IF(NOT(ISNUMBER($X31)),"▲免保到期日没填",IF($X31<TODAY(),"▲免保已到期，转收费",IF($X31-TODAY()<=提醒天数,"免保剩"&($X31-TODAY())&"天","免保中"))),IF($W31="暂停维保","暂停中",IF($W31="已解约","已解约","")))) | Z31: =IF(TRIM($B31&$C31)="","",TRIM(IF($AA31="","",IF($AA31<TODAY(),"年检已过期"&(TODAY()-$AA31)&"天 ",IF($AA31-TODAY()<=提醒天数,"年检剩"&($AA31-TODAY())&"天 ","")))&IF($AB31="","",IF($AB31<TODAY(),"限速器已过期"&(TODAY()-$AB31)&"天 ",IF($AB31-TODAY()<=提醒天数,"限速器剩"&($AB31-TODAY())&"天 ","")))&IF($AC31="","",IF($AC31<TODAY(),"载重试验已过期"&(TODAY()-$AC31)&"天 ",IF($AC31-TODAY()<=提醒天数,"载重试验剩"&($AC31-TODAY())&"天 ",""))))) | AA31: =IF(TRIM($Q31&"")="","",IF(ISNUMBER($Q31),IF($Q31>10000,$Q31,IFERROR(DATE(INT($Q31),IF(ROUND(MOD($Q31,1)*100,0)>12,ROUND(MOD($Q31,1)*10,0),ROUND(MOD($Q31,1)*100,0))+1,0),"")),IFERROR(IF(LEN($Q31)-LEN(SUBSTITUTE($Q31,".",""))>=2,DATEVALUE(SUBSTITUTE(TRIM($Q31),".","-")),DATE(VALUE(LEFT(TRIM($Q31),4)),VALUE(MID(TRIM($Q31),6,2))+1,0)),""))) | AB31: =IF(TRIM($S31&"")="","",IF(ISNUMBER($S31),IF($S31>10000,$S31,IFERROR(DATE(INT($S31),IF(ROUND(MOD($S31,1)*100,0)>12,ROUND(MOD($S31,1)*10,0),ROUND(MOD($S31,1)*100,0))+1,0),"")),IFERROR(IF(LEN($S31)-LEN(SUBSTITUTE($S31,".",""))>=2,DATEVALUE(SUBSTITUTE(TRIM($S31),".","-")),DATE(VALUE(LEFT(TRIM($S31),4)),VALUE(MID(TRIM($S31),6,2))+1,0)),""))) | AC31: =IF(TRIM($T31&"")="","",IF(ISNUMBER($T31),IF($T31>10000,$T31,IFERROR(DATE(INT($T31),IF(ROUND(MOD($T31,1)*100,0)>12,ROUND(MOD($T31,1)*10,0),ROUND(MOD($T31,1)*100,0))+1,0),"")),IFERROR(IF(LEN($T31)-LEN(SUBSTITUTE($T31,".",""))>=2,DATEVALUE(SUBSTITUTE(TRIM($T31),".","-")),DATE(VALUE(LEFT(TRIM($T31),4)),VALUE(MID(TRIM($T31),6,2))+1,0)),"")))
B32: 湖北海推智能装备有限公司 | C32: 东西湖年产1000台 | D32: EHJ20 | E32: 31204201122020110009 | F32: 123869 | G32: 怡达快速电梯 | H32: 货梯 | I32: 5 | J32: 5 | K32: 6 | L32: 3000kg | M32: 0.5m/s | N32: 1 | O32: J070208.1 | P32: 1#货 | Y32: =IF(TRIM($B32&$C32)="","",IF(OR($W32="安装免保",$W32="技术免保",$W32="质保期内"),IF(NOT(ISNUMBER($X32)),"▲免保到期日没填",IF($X32<TODAY(),"▲免保已到期，转收费",IF($X32-TODAY()<=提醒天数,"免保剩"&($X32-TODAY())&"天","免保中"))),IF($W32="暂停维保","暂停中",IF($W32="已解约","已解约","")))) | Z32: =IF(TRIM($B32&$C32)="","",TRIM(IF($AA32="","",IF($AA32<TODAY(),"年检已过期"&(TODAY()-$AA32)&"天 ",IF($AA32-TODAY()<=提醒天数,"年检剩"&($AA32-TODAY())&"天 ","")))&IF($AB32="","",IF($AB32<TODAY(),"限速器已过期"&(TODAY()-$AB32)&"天 ",IF($AB32-TODAY()<=提醒天数,"限速器剩"&($AB32-TODAY())&"天 ","")))&IF($AC32="","",IF($AC32<TODAY(),"载重试验已过期"&(TODAY()-$AC32)&"天 ",IF($AC32-TODAY()<=提醒天数,"载重试验剩"&($AC32-TODAY())&"天 ",""))))) | AA32: =IF(TRIM($Q32&"")="","",IF(ISNUMBER($Q32),IF($Q32>10000,$Q32,IFERROR(DATE(INT($Q32),IF(ROUND(MOD($Q32,1)*100,0)>12,ROUND(MOD($Q32,1)*10,0),ROUND(MOD($Q32,1)*100,0))+1,0),"")),IFERROR(IF(LEN($Q32)-LEN(SUBSTITUTE($Q32,".",""))>=2,DATEVALUE(SUBSTITUTE(TRIM($Q32),".","-")),DATE(VALUE(LEFT(TRIM($Q32),4)),VALUE(MID(TRIM($Q32),6,2))+1,0)),""))) | AB32: =IF(TRIM($S32&"")="","",IF(ISNUMBER($S32),IF($S32>10000,$S32,IFERROR(DATE(INT($S32),IF(ROUND(MOD($S32,1)*100,0)>12,ROUND(MOD($S32,1)*10,0),ROUND(MOD($S32,1)*100,0))+1,0),"")),IFERROR(IF(LEN($S32)-LEN(SUBSTITUTE($S32,".",""))>=2,DATEVALUE(SUBSTITUTE(TRIM($S32),".","-")),DATE(VALUE(LEFT(TRIM($S32),4)),VALUE(MID(TRIM($S32),6,2))+1,0)),""))) | AC32: =IF(TRIM($T32&"")="","",IF(ISNUMBER($T32),IF($T32>10000,$T32,IFERROR(DATE(INT($T32),IF(ROUND(MOD($T32,1)*100,0)>12,ROUND(MOD($T32,1)*10,0),ROUND(MOD($T32,1)*100,0))+1,0),"")),IFERROR(IF(LEN($T32)-LEN(SUBSTITUTE($T32,".",""))>=2,DATEVALUE(SUBSTITUTE(TRIM($T32),".","-")),DATE(VALUE(LEFT(TRIM($T32),4)),VALUE(MID(TRIM($T32),6,2))+1,0)),"")))
B33: 湖北海推智能装备有限公司 | C33: 东西湖年产1000台 | D33: EHJ20 | E33: 31204201122020110012 | F33: 123872 | G33: 怡达快速电梯 | H33: 货梯 | I33: 5 | J33: 5 | K33: 6 | L33: 3000kg | M33: 0.5m/s | N33: 1 | O33: J070208.4 | P33: 4#货 | Y33: =IF(TRIM($B33&$C33)="","",IF(OR($W33="安装免保",$W33="技术免保",$W33="质保期内"),IF(NOT(ISNUMBER($X33)),"▲免保到期日没填",IF($X33<TODAY(),"▲免保已到期，转收费",IF($X33-TODAY()<=提醒天数,"免保剩"&($X33-TODAY())&"天","免保中"))),IF($W33="暂停维保","暂停中",IF($W33="已解约","已解约","")))) | Z33: =IF(TRIM($B33&$C33)="","",TRIM(IF($AA33="","",IF($AA33<TODAY(),"年检已过期"&(TODAY()-$AA33)&"天 ",IF($AA33-TODAY()<=提醒天数,"年检剩"&($AA33-TODAY())&"天 ","")))&IF($AB33="","",IF($AB33<TODAY(),"限速器已过期"&(TODAY()-$AB33)&"天 ",IF($AB33-TODAY()<=提醒天数,"限速器剩"&($AB33-TODAY())&"天 ","")))&IF($AC33="","",IF($AC33<TODAY(),"载重试验已过期"&(TODAY()-$AC33)&"天 ",IF($AC33-TODAY()<=提醒天数,"载重试验剩"&($AC33-TODAY())&"天 ",""))))) | AA33: =IF(TRIM($Q33&"")="","",IF(ISNUMBER($Q33),IF($Q33>10000,$Q33,IFERROR(DATE(INT($Q33),IF(ROUND(MOD($Q33,1)*100,0)>12,ROUND(MOD($Q33,1)*10,0),ROUND(MOD($Q33,1)*100,0))+1,0),"")),IFERROR(IF(LEN($Q33)-LEN(SUBSTITUTE($Q33,".",""))>=2,DATEVALUE(SUBSTITUTE(TRIM($Q33),".","-")),DATE(VALUE(LEFT(TRIM($Q33),4)),VALUE(MID(TRIM($Q33),6,2))+1,0)),""))) | AB33: =IF(TRIM($S33&"")="","",IF(ISNUMBER($S33),IF($S33>10000,$S33,IFERROR(DATE(INT($S33),IF(ROUND(MOD($S33,1)*100,0)>12,ROUND(MOD($S33,1)*10,0),ROUND(MOD($S33,1)*100,0))+1,0),"")),IFERROR(IF(LEN($S33)-LEN(SUBSTITUTE($S33,".",""))>=2,DATEVALUE(SUBSTITUTE(TRIM($S33),".","-")),DATE(VALUE(LEFT(TRIM($S33),4)),VALUE(MID(TRIM($S33),6,2))+1,0)),""))) | AC33: =IF(TRIM($T33&"")="","",IF(ISNUMBER($T33),IF($T33>10000,$T33,IFERROR(DATE(INT($T33),IF(ROUND(MOD($T33,1)*100,0)>12,ROUND(MOD($T33,1)*10,0),ROUND(MOD($T33,1)*100,0))+1,0),"")),IFERROR(IF(LEN($T33)-LEN(SUBSTITUTE($T33,".",""))>=2,DATEVALUE(SUBSTITUTE(TRIM($T33),".","-")),DATE(VALUE(LEFT(TRIM($T33),4)),VALUE(MID(TRIM($T33),6,2))+1,0)),"")))
B34: 湖北海推智能装备有限公司 | C34: 东西湖年产1000台 | D34: EHJ20 | E34: 31204201122020110010 | F34: 123870 | G34: 怡达快速电梯 | H34: 货梯 | I34: 5 | J34: 5 | K34: 6 | L34: 3000kg | M34: 0.5m/s | N34: 1 | O34: J070208.2 | P34: 2#货 | Y34: =IF(TRIM($B34&$C34)="","",IF(OR($W34="安装免保",$W34="技术免保",$W34="质保期内"),IF(NOT(ISNUMBER($X34)),"▲免保到期日没填",IF($X34<TODAY(),"▲免保已到期，转收费",IF($X34-TODAY()<=提醒天数,"免保剩"&($X34-TODAY())&"天","免保中"))),IF($W34="暂停维保","暂停中",IF($W34="已解约","已解约","")))) | Z34: =IF(TRIM($B34&$C34)="","",TRIM(IF($AA34="","",IF($AA34<TODAY(),"年检已过期"&(TODAY()-$AA34)&"天 ",IF($AA34-TODAY()<=提醒天数,"年检剩"&($AA34-TODAY())&"天 ","")))&IF($AB34="","",IF($AB34<TODAY(),"限速器已过期"&(TODAY()-$AB34)&"天 ",IF($AB34-TODAY()<=提醒天数,"限速器剩"&($AB34-TODAY())&"天 ","")))&IF($AC34="","",IF($AC34<TODAY(),"载重试验已过期"&(TODAY()-$AC34)&"天 ",IF($AC34-TODAY()<=提醒天数,"载重试验剩"&($AC34-TODAY())&"天 ",""))))) | AA34: =IF(TRIM($Q34&"")="","",IF(ISNUMBER($Q34),IF($Q34>10000,$Q34,IFERROR(DATE(INT($Q34),IF(ROUND(MOD($Q34,1)*100,0)>12,ROUND(MOD($Q34,1)*10,0),ROUND(MOD($Q34,1)*100,0))+1,0),"")),IFERROR(IF(LEN($Q34)-LEN(SUBSTITUTE($Q34,".",""))>=2,DATEVALUE(SUBSTITUTE(TRIM($Q34),".","-")),DATE(VALUE(LEFT(TRIM($Q34),4)),VALUE(MID(TRIM($Q34),6,2))+1,0)),""))) | AB34: =IF(TRIM($S34&"")="","",IF(ISNUMBER($S34),IF($S34>10000,$S34,IFERROR(DATE(INT($S34),IF(ROUND(MOD($S34,1)*100,0)>12,ROUND(MOD($S34,1)*10,0),ROUND(MOD($S34,1)*100,0))+1,0),"")),IFERROR(IF(LEN($S34)-LEN(SUBSTITUTE($S34,".",""))>=2,DATEVALUE(SUBSTITUTE(TRIM($S34),".","-")),DATE(VALUE(LEFT(TRIM($S34),4)),VALUE(MID(TRIM($S34),6,2))+1,0)),""))) | AC34: =IF(TRIM($T34&"")="","",IF(ISNUMBER($T34),IF($T34>10000,$T34,IFERROR(DATE(INT($T34),IF(ROUND(MOD($T34,1)*100,0)>12,ROUND(MOD($T34,1)*10,0),ROUND(MOD($T34,1)*100,0))+1,0),"")),IFERROR(IF(LEN($T34)-LEN(SUBSTITUTE($T34,".",""))>=2,DATEVALUE(SUBSTITUTE(TRIM($T34),".","-")),DATE(VALUE(LEFT(TRIM($T34),4)),VALUE(MID(TRIM($T34),6,2))+1,0)),"")))
B35: 湖北海推智能装备有限公司 | C35: 东西湖年产1000台 | D35: EHJ20 | E35: 31204201122020110011 | F35: 123871 | G35: 怡达快速电梯 | H35: 货梯 | I35: 5 | J35: 5 | K35: 6 | L35: 3000kg | M35: 0.5m/s | N35: 1 | O35: J070208.3 | P35: 3#货 | Y35: =IF(TRIM($B35&$C35)="","",IF(OR($W35="安装免保",$W35="技术免保",$W35="质保期内"),IF(NOT(ISNUMBER($X35)),"▲免保到期日没填",IF($X35<TODAY(),"▲免保已到期，转收费",IF($X35-TODAY()<=提醒天数,"免保剩"&($X35-TODAY())&"天","免保中"))),IF($W35="暂停维保","暂停中",IF($W35="已解约","已解约","")))) | Z35: =IF(TRIM($B35&$C35)="","",TRIM(IF($AA35="","",IF($AA35<TODAY(),"年检已过期"&(TODAY()-$AA35)&"天 ",IF($AA35-TODAY()<=提醒天数,"年检剩"&($AA35-TODAY())&"天 ","")))&IF($AB35="","",IF($AB35<TODAY(),"限速器已过期"&(TODAY()-$AB35)&"天 ",IF($AB35-TODAY()<=提醒天数,"限速器剩"&($AB35-TODAY())&"天 ","")))&IF($AC35="","",IF($AC35<TODAY(),"载重试验已过期"&(TODAY()-$AC35)&"天 ",IF($AC35-TODAY()<=提醒天数,"载重试验剩"&($AC35-TODAY())&"天 ",""))))) | AA35: =IF(TRIM($Q35&"")="","",IF(ISNUMBER($Q35),IF($Q35>10000,$Q35,IFERROR(DATE(INT($Q35),IF(ROUND(MOD($Q35,1)*100,0)>12,ROUND(MOD($Q35,1)*10,0),ROUND(MOD($Q35,1)*100,0))+1,0),"")),IFERROR(IF(LEN($Q35)-LEN(SUBSTITUTE($Q35,".",""))>=2,DATEVALUE(SUBSTITUTE(TRIM($Q35),".","-")),DATE(VALUE(LEFT(TRIM($Q35),4)),VALUE(MID(TRIM($Q35),6,2))+1,0)),""))) | AB35: =IF(TRIM($S35&"")="","",IF(ISNUMBER($S35),IF($S35>10000,$S35,IFERROR(DATE(INT($S35),IF(ROUND(MOD($S35,1)*100,0)>12,ROUND(MOD($S35,1)*10,0),ROUND(MOD($S35,1)*100,0))+1,0),"")),IFERROR(IF(LEN($S35)-LEN(SUBSTITUTE($S35,".",""))>=2,DATEVALUE(SUBSTITUTE(TRIM($S35),".","-")),DATE(VALUE(LEFT(TRIM($S35),4)),VALUE(MID(TRIM($S35),6,2))+1,0)),""))) | AC35: =IF(TRIM($T35&"")="","",IF(ISNUMBER($T35),IF($T35>10000,$T35,IFERROR(DATE(INT($T35),IF(ROUND(MOD($T35,1)*100,0)>12,ROUND(MOD($T35,1)*10,0),ROUND(MOD($T35,1)*100,0))+1,0),"")),IFERROR(IF(LEN($T35)-LEN(SUBSTITUTE($T35,".",""))>=2,DATEVALUE(SUBSTITUTE(TRIM($T35),".","-")),DATE(VALUE(LEFT(TRIM($T35),4)),VALUE(MID(TRIM($T35),6,2))+1,0)),"")))
B36: 武汉北方能源股份有限公司 | C36: 北方能源 | D36: EKJ35 | E36: 31104201122020110001 | F36: 137215 | G36: 怡达快速电梯 | H36: 客梯 | I36: 5 | J36: 5 | K36: 5 | L36: 1000kg | M36: 1.0m/s | N36: 1 | O36: J070233.1 | P36: 工业园1#楼1#客 | Y36: =IF(TRIM($B36&$C36)="","",IF(OR($W36="安装免保",$W36="技术免保",$W36="质保期内"),IF(NOT(ISNUMBER($X36)),"▲免保到期日没填",IF($X36<TODAY(),"▲免保已到期，转收费",IF($X36-TODAY()<=提醒天数,"免保剩"&($X36-TODAY())&"天","免保中"))),IF($W36="暂停维保","暂停中",IF($W36="已解约","已解约","")))) | Z36: =IF(TRIM($B36&$C36)="","",TRIM(IF($AA36="","",IF($AA36<TODAY(),"年检已过期"&(TODAY()-$AA36)&"天 ",IF($AA36-TODAY()<=提醒天数,"年检剩"&($AA36-TODAY())&"天 ","")))&IF($AB36="","",IF($AB36<TODAY(),"限速器已过期"&(TODAY()-$AB36)&"天 ",IF($AB36-TODAY()<=提醒天数,"限速器剩"&($AB36-TODAY())&"天 ","")))&IF($AC36="","",IF($AC36<TODAY(),"载重试验已过期"&(TODAY()-$AC36)&"天 ",IF($AC36-TODAY()<=提醒天数,"载重试验剩"&($AC36-TODAY())&"天 ",""))))) | AA36: =IF(TRIM($Q36&"")="","",IF(ISNUMBER($Q36),IF($Q36>10000,$Q36,IFERROR(DATE(INT($Q36),IF(ROUND(MOD($Q36,1)*100,0)>12,ROUND(MOD($Q36,1)*10,0),ROUND(MOD($Q36,1)*100,0))+1,0),"")),IFERROR(IF(LEN($Q36)-LEN(SUBSTITUTE($Q36,".",""))>=2,DATEVALUE(SUBSTITUTE(TRIM($Q36),".","-")),DATE(VALUE(LEFT(TRIM($Q36),4)),VALUE(MID(TRIM($Q36),6,2))+1,0)),""))) | AB36: =IF(TRIM($S36&"")="","",IF(ISNUMBER($S36),IF($S36>10000,$S36,IFERROR(DATE(INT($S36),IF(ROUND(MOD($S36,1)*100,0)>12,ROUND(MOD($S36,1)*10,0),ROUND(MOD($S36,1)*100,0))+1,0),"")),IFERROR(IF(LEN($S36)-LEN(SUBSTITUTE($S36,".",""))>=2,DATEVALUE(SUBSTITUTE(TRIM($S36),".","-")),DATE(VALUE(LEFT(TRIM($S36),4)),VALUE(MID(TRIM($S36),6,2))+1,0)),""))) | AC36: =IF(TRIM($T36&"")="","",IF(ISNUMBER($T36),IF($T36>10000,$T36,IFERROR(DATE(INT($T36),IF(ROUND(MOD($T36,1)*100,0)>12,ROUND(MOD($T36,1)*10,0),ROUND(MOD($T36,1)*100,0))+1,0),"")),IFERROR(IF(LEN($T36)-LEN(SUBSTITUTE($T36,".",""))>=2,DATEVALUE(SUBSTITUTE(TRIM($T36),".","-")),DATE(VALUE(LEFT(TRIM($T36),4)),VALUE(MID(TRIM($T36),6,2))+1,0)),"")))
... B39: 武汉北方能源股份有限公司 | C39: 北方能源 | D39: EHJ20 | E39: 31204201122020110008 | F39: 137218 | G39: 怡达快速电梯 | H39: 货梯 | I39: 5 | J39: 5 | K39: 5 | L39: 3000kg | M39: 0.5m/s | N39: 1 | O39: J070233.8 | P39: 工业园1#楼4#客 | Y39: =IF(TRIM($B39&$C39)="","",IF(OR($W39="安装免保",$W39="技术免保",$W39="质保期内"),IF(NOT(ISNUMBER($X39)),"▲免保到期日没填",IF($X39<TODAY(),"▲免保已到期，转收费",IF($X39-TODAY()<=提醒天数,"免保剩"&($X39-TODAY())&"天","免保中"))),IF($W39="暂停维保","暂停中",IF($W39="已解约","已解约","")))) | Z39: =IF(TRIM($B39&$C39)="","",TRIM(IF($AA39="","",IF($AA39<TODAY(),"年检已过期"&(TODAY()-$AA39)&"天 ",IF($AA39-TODAY()<=提醒天数,"年检剩"&($AA39-TODAY())&"天 ","")))&IF($AB39="","",IF($AB39<TODAY(),"限速器已过期"&(TODAY()-$AB39)&"天 ",IF($AB39-TODAY()<=提醒天数,"限速器剩"&($AB39-TODAY())&"天 ","")))&IF($AC39="","",IF($AC39<TODAY(),"载重试验已过期"&(TODAY()-$AC39)&"天 ",IF($AC39-TODAY()<=提醒天数,"载重试验剩"&($AC39-TODAY())&"天 ",""))))) | AA39: =IF(TRIM($Q39&"")="","",IF(ISNUMBER($Q39),IF($Q39>10000,$Q39,IFERROR(DATE(INT($Q39),IF(ROUND(MOD($Q39,1)*100,0)>12,ROUND(MOD($Q39,1)*10,0),ROUND(MOD($Q39,1)*100,0))+1,0),"")),IFERROR(IF(LEN($Q39)-LEN(SUBSTITUTE($Q39,".",""))>=2,DATEVALUE(SUBSTITUTE(TRIM($Q39),".","-")),DATE(VALUE(LEFT(TRIM($Q39),4)),VALUE(MID(TRIM($Q39),6,2))+1,0)),""))) | AB39: =IF(TRIM($S39&"")="","",IF(ISNUMBER($S39),IF($S39>10000,$S39,IFERROR(DATE(INT($S39),IF(ROUND(MOD($S39,1)*100,0)>12,ROUND(MOD($S39,1)*10,0),ROUND(MOD($S39,1)*100,0))+1,0),"")),IFERROR(IF(LEN($S39)-LEN(SUBSTITUTE($S39,".",""))>=2,DATEVALUE(SUBSTITUTE(TRIM($S39),".","-")),DATE(VALUE(LEFT(TRIM($S39),4)),VALUE(MID(TRIM($S39),6,2))+1,0)),""))) | AC39: =IF(TRIM($T39&"")="","",IF(ISNUMBER($T39),IF($T39>10000,$T39,IFERROR(DATE(INT($T39),IF(ROUND(MOD($T39,1)*100,0)>12,ROUND(MOD($T39,1)*10,0),ROUND(MOD($T39,1)*100,0))+1,0),"")),IFERROR(IF(LEN($T39)-LEN(SUBSTITUTE($T39,".",""))>=2,DATEVALUE(SUBSTITUTE(TRIM($T39),".","-")),DATE(VALUE(LEFT(TRIM($T39),4)),VALUE(MID(TRIM($T39),6,2))+1,0)),"")))
B40: 武汉北方能源股份有限公司 | C40: 北方能源 | D40: THJ | E40: 31204201122020110013 | G40: 广东台菱 | H40: 货梯 | I40: 5 | J40: 5 | L40: 3000kg | M40: 0.5m/s | N40: 1 | O40: E2007154 | P40: 2#厂房1#货 | Y40: =IF(TRIM($B40&$C40)="","",IF(OR($W40="安装免保",$W40="技术免保",$W40="质保期内"),IF(NOT(ISNUMBER($X40)),"▲免保到期日没填",IF($X40<TODAY(),"▲免保已到期，转收费",IF($X40-TODAY()<=提醒天数,"免保剩"&($X40-TODAY())&"天","免保中"))),IF($W40="暂停维保","暂停中",IF($W40="已解约","已解约","")))) | Z40: =IF(TRIM($B40&$C40)="","",TRIM(IF($AA40="","",IF($AA40<TODAY(),"年检已过期"&(TODAY()-$AA40)&"天 ",IF($AA40-TODAY()<=提醒天数,"年检剩"&($AA40-TODAY())&"天 ","")))&IF($AB40="","",IF($AB40<TODAY(),"限速器已过期"&(TODAY()-$AB40)&"天 ",IF($AB40-TODAY()<=提醒天数,"限速器剩"&($AB40-TODAY())&"天 ","")))&IF($AC40="","",IF($AC40<TODAY(),"载重试验已过期"&(TODAY()-$AC40)&"天 ",IF($AC40-TODAY()<=提醒天数,"载重试验剩"&($AC40-TODAY())&"天 ",""))))) | AA40: =IF(TRIM($Q40&"")="","",IF(ISNUMBER($Q40),IF($Q40>10000,$Q40,IFERROR(DATE(INT($Q40),IF(ROUND(MOD($Q40,1)*100,0)>12,ROUND(MOD($Q40,1)*10,0),ROUND(MOD($Q40,1)*100,0))+1,0),"")),IFERROR(IF(LEN($Q40)-LEN(SUBSTITUTE($Q40,".",""))>=2,DATEVALUE(SUBSTITUTE(TRIM($Q40),".","-")),DATE(VALUE(LEFT(TRIM($Q40),4)),VALUE(MID(TRIM($Q40),6,2))+1,0)),""))) | AB40: =IF(TRIM($S40&"")="","",IF(ISNUMBER($S40),IF($S40>10000,$S40,IFERROR(DATE(INT($S40),IF(ROUND(MOD($S40,1)*100,0)>12,ROUND(MOD($S40,1)*10,0),ROUND(MOD($S40,1)*100,0))+1,0),"")),IFERROR(IF(LEN($S40)-LEN(SUBSTITUTE($S40,".",""))>=2,DATEVALUE(SUBSTITUTE(TRIM($S40),".","-")),DATE(VALUE(LEFT(TRIM($S40),4)),VALUE(MID(TRIM($S40),6,2))+1,0)),""))) | AC40: =IF(TRIM($T40&"")="","",IF(ISNUMBER($T40),IF($T40>10000,$T40,IFERROR(DATE(INT($T40),IF(ROUND(MOD($T40,1)*100,0)>12,ROUND(MOD($T40,1)*10,0),ROUND(MOD($T40,1)*100,0))+1,0),"")),IFERROR(IF(LEN($T40)-LEN(SUBSTITUTE($T40,".",""))>=2,DATEVALUE(SUBSTITUTE(TRIM($T40),".","-")),DATE(VALUE(LEFT(TRIM($T40),4)),VALUE(MID(TRIM($T40),6,2))+1,0)),"")))
B41: 武汉北方能源股份有限公司 | C41: 北方能源 | D41: THJ | E41: 31204201122020110014 | G41: 广东台菱 | H41: 货梯 | I41: 5 | J41: 5 | L41: 3000kg | M41: 0.5m/s | N41: 1 | O41: E2007155 | P41: 2#厂房2#货 | Y41: =IF(TRIM($B41&$C41)="","",IF(OR($W41="安装免保",$W41="技术免保",$W41="质保期内"),IF(NOT(ISNUMBER($X41)),"▲免保到期日没填",IF($X41<TODAY(),"▲免保已到期，转收费",IF($X41-TODAY()<=提醒天数,"免保剩"&($X41-TODAY())&"天","免保中"))),IF($W41="暂停维保","暂停中",IF($W41="已解约","已解约","")))) | Z41: =IF(TRIM($B41&$C41)="","",TRIM(IF($AA41="","",IF($AA41<TODAY(),"年检已过期"&(TODAY()-$AA41)&"天 ",IF($AA41-TODAY()<=提醒天数,"年检剩"&($AA41-TODAY())&"天 ","")))&IF($AB41="","",IF($AB41<TODAY(),"限速器已过期"&(TODAY()-$AB41)&"天 ",IF($AB41-TODAY()<=提醒天数,"限速器剩"&($AB41-TODAY())&"天 ","")))&IF($AC41="","",IF($AC41<TODAY(),"载重试验已过期"&(TODAY()-$AC41)&"天 ",IF($AC41-TODAY()<=提醒天数,"载重试验剩"&($AC41-TODAY())&"天 ",""))))) | AA41: =IF(TRIM($Q41&"")="","",IF(ISNUMBER($Q41),IF($Q41>10000,$Q41,IFERROR(DATE(INT($Q41),IF(ROUND(MOD($Q41,1)*100,0)>12,ROUND(MOD($Q41,1)*10,0),ROUND(MOD($Q41,1)*100,0))+1,0),"")),IFERROR(IF(LEN($Q41)-LEN(SUBSTITUTE($Q41,".",""))>=2,DATEVALUE(SUBSTITUTE(TRIM($Q41),".","-")),DATE(VALUE(LEFT(TRIM($Q41),4)),VALUE(MID(TRIM($Q41),6,2))+1,0)),""))) | AB41: =IF(TRIM($S41&"")="","",IF(ISNUMBER($S41),IF($S41>10000,$S41,IFERROR(DATE(INT($S41),IF(ROUND(MOD($S41,1)*100,0)>12,ROUND(MOD($S41,1)*10,0),ROUND(MOD($S41,1)*100,0))+1,0),"")),IFERROR(IF(LEN($S41)-LEN(SUBSTITUTE($S41,".",""))>=2,DATEVALUE(SUBSTITUTE(TRIM($S41),".","-")),DATE(VALUE(LEFT(TRIM($S41),4)),VALUE(MID(TRIM($S41),6,2))+1,0)),""))) | AC41: =IF(TRIM($T41&"")="","",IF(ISNUMBER($T41),IF($T41>10000,$T41,IFERROR(DATE(INT($T41),IF(ROUND(MOD($T41,1)*100,0)>12,ROUND(MOD($T41,1)*10,0),ROUND(MOD($T41,1)*100,0))+1,0),"")),IFERROR(IF(LEN($T41)-LEN(SUBSTITUTE($T41,".",""))>=2,DATEVALUE(SUBSTITUTE(TRIM($T41),".","-")),DATE(VALUE(LEFT(TRIM($T41),4)),VALUE(MID(TRIM($T41),6,2))+1,0)),"")))
B42: 武汉北方能源股份有限公司 | C42: 北方能源 | D42: TKJ | E42: 31104201122020110097 | G42: 广东台菱 | H42: 客梯 | I42: 5 | J42: 5 | K42: 5 | L42: 1000kg | M42: 1.5m/s | N42: 1 | O42: E2007152 | P42: 2#厂房1#客 | Y42: =IF(TRIM($B42&$C42)="","",IF(OR($W42="安装免保",$W42="技术免保",$W42="质保期内"),IF(NOT(ISNUMBER($X42)),"▲免保到期日没填",IF($X42<TODAY(),"▲免保已到期，转收费",IF($X42-TODAY()<=提醒天数,"免保剩"&($X42-TODAY())&"天","免保中"))),IF($W42="暂停维保","暂停中",IF($W42="已解约","已解约","")))) | Z42: =IF(TRIM($B42&$C42)="","",TRIM(IF($AA42="","",IF($AA42<TODAY(),"年检已过期"&(TODAY()-$AA42)&"天 ",IF($AA42-TODAY()<=提醒天数,"年检剩"&($AA42-TODAY())&"天 ","")))&IF($AB42="","",IF($AB42<TODAY(),"限速器已过期"&(TODAY()-$AB42)&"天 ",IF($AB42-TODAY()<=提醒天数,"限速器剩"&($AB42-TODAY())&"天 ","")))&IF($AC42="","",IF($AC42<TODAY(),"载重试验已过期"&(TODAY()-$AC42)&"天 ",IF($AC42-TODAY()<=提醒天数,"载重试验剩"&($AC42-TODAY())&"天 ",""))))) | AA42: =IF(TRIM($Q42&"")="","",IF(ISNUMBER($Q42),IF($Q42>10000,$Q42,IFERROR(DATE(INT($Q42),IF(ROUND(MOD($Q42,1)*100,0)>12,ROUND(MOD($Q42,1)*10,0),ROUND(MOD($Q42,1)*100,0))+1,0),"")),IFERROR(IF(LEN($Q42)-LEN(SUBSTITUTE($Q42,".",""))>=2,DATEVALUE(SUBSTITUTE(TRIM($Q42),".","-")),DATE(VALUE(LEFT(TRIM($Q42),4)),VALUE(MID(TRIM($Q42),6,2))+1,0)),""))) | AB42: =IF(TRIM($S42&"")="","",IF(ISNUMBER($S42),IF($S42>10000,$S42,IFERROR(DATE(INT($S42),IF(ROUND(MOD($S42,1)*100,0)>12,ROUND(MOD($S42,1)*10,0),ROUND(MOD($S42,1)*100,0))+1,0),"")),IFERROR(IF(LEN($S42)-LEN(SUBSTITUTE($S42,".",""))>=2,DATEVALUE(SUBSTITUTE(TRIM($S42),".","-")),DATE(VALUE(LEFT(TRIM($S42),4)),VALUE(MID(TRIM($S42),6,2))+1,0)),""))) | AC42: =IF(TRIM($T42&"")="","",IF(ISNUMBER($T42),IF($T42>10000,$T42,IFERROR(DATE(INT($T42),IF(ROUND(MOD($T42,1)*100,0)>12,ROUND(MOD($T42,1)*10,0),ROUND(MOD($T42,1)*100,0))+1,0),"")),IFERROR(IF(LEN($T42)-LEN(SUBSTITUTE($T42,".",""))>=2,DATEVALUE(SUBSTITUTE(TRIM($T42),".","-")),DATE(VALUE(LEFT(TRIM($T42),4)),VALUE(MID(TRIM($T42),6,2))+1,0)),"")))
B43: 武汉北方能源股份有限公司 | C43: 北方能源 | D43: TKJ | E43: 31104201122020110098 | G43: 广东台菱 | H43: 客梯 | I43: 5 | J43: 5 | K43: 5 | L43: 1000kg | M43: 1.5m/s | N43: 1 | O43: E2007153 | P43: 2#厂房2#客 | Y43: =IF(TRIM($B43&$C43)="","",IF(OR($W43="安装免保",$W43="技术免保",$W43="质保期内"),IF(NOT(ISNUMBER($X43)),"▲免保到期日没填",IF($X43<TODAY(),"▲免保已到期，转收费",IF($X43-TODAY()<=提醒天数,"免保剩"&($X43-TODAY())&"天","免保中"))),IF($W43="暂停维保","暂停中",IF($W43="已解约","已解约","")))) | Z43: =IF(TRIM($B43&$C43)="","",TRIM(IF($AA43="","",IF($AA43<TODAY(),"年检已过期"&(TODAY()-$AA43)&"天 ",IF($AA43-TODAY()<=提醒天数,"年检剩"&($AA43-TODAY())&"天 ","")))&IF($AB43="","",IF($AB43<TODAY(),"限速器已过期"&(TODAY()-$AB43)&"天 ",IF($AB43-TODAY()<=提醒天数,"限速器剩"&($AB43-TODAY())&"天 ","")))&IF($AC43="","",IF($AC43<TODAY(),"载重试验已过期"&(TODAY()-$AC43)&"天 ",IF($AC43-TODAY()<=提醒天数,"载重试验剩"&($AC43-TODAY())&"天 ",""))))) | AA43: =IF(TRIM($Q43&"")="","",IF(ISNUMBER($Q43),IF($Q43>10000,$Q43,IFERROR(DATE(INT($Q43),IF(ROUND(MOD($Q43,1)*100,0)>12,ROUND(MOD($Q43,1)*10,0),ROUND(MOD($Q43,1)*100,0))+1,0),"")),IFERROR(IF(LEN($Q43)-LEN(SUBSTITUTE($Q43,".",""))>=2,DATEVALUE(SUBSTITUTE(TRIM($Q43),".","-")),DATE(VALUE(LEFT(TRIM($Q43),4)),VALUE(MID(TRIM($Q43),6,2))+1,0)),""))) | AB43: =IF(TRIM($S43&"")="","",IF(ISNUMBER($S43),IF($S43>10000,$S43,IFERROR(DATE(INT($S43),IF(ROUND(MOD($S43,1)*100,0)>12,ROUND(MOD($S43,1)*10,0),ROUND(MOD($S43,1)*100,0))+1,0),"")),IFERROR(IF(LEN($S43)-LEN(SUBSTITUTE($S43,".",""))>=2,DATEVALUE(SUBSTITUTE(TRIM($S43),".","-")),DATE(VALUE(LEFT(TRIM($S43),4)),VALUE(MID(TRIM($S43),6,2))+1,0)),""))) | AC43: =IF(TRIM($T43&"")="","",IF(ISNUMBER($T43),IF($T43>10000,$T43,IFERROR(DATE(INT($T43),IF(ROUND(MOD($T43,1)*100,0)>12,ROUND(MOD($T43,1)*10,0),ROUND(MOD($T43,1)*100,0))+1,0),"")),IFERROR(IF(LEN($T43)-LEN(SUBSTITUTE($T43,".",""))>=2,DATEVALUE(SUBSTITUTE(TRIM($T43),".","-")),DATE(VALUE(LEFT(TRIM($T43),4)),VALUE(MID(TRIM($T43),6,2))+1,0)),"")))
B44: 武汉北方能源股份有限公司 | C44: 北方能源 | D44: LGE-050-C0105 | E44: 31104201122020110125 | G44: 日立电梯 | H44: 客梯(无机房) | I44: 11 | J44: 11 | K44: 11 | L44: 1050kg | M44: 1.75m/s | N44: 1 | O44: 19G077819 | P44: 研发楼Y1#客 | Y44: =IF(TRIM($B44&$C44)="","",IF(OR($W44="安装免保",$W44="技术免保",$W44="质保期内"),IF(NOT(ISNUMBER($X44)),"▲免保到期日没填",IF($X44<TODAY(),"▲免保已到期，转收费",IF($X44-TODAY()<=提醒天数,"免保剩"&($X44-TODAY())&"天","免保中"))),IF($W44="暂停维保","暂停中",IF($W44="已解约","已解约","")))) | Z44: =IF(TRIM($B44&$C44)="","",TRIM(IF($AA44="","",IF($AA44<TODAY(),"年检已过期"&(TODAY()-$AA44)&"天 ",IF($AA44-TODAY()<=提醒天数,"年检剩"&($AA44-TODAY())&"天 ","")))&IF($AB44="","",IF($AB44<TODAY(),"限速器已过期"&(TODAY()-$AB44)&"天 ",IF($AB44-TODAY()<=提醒天数,"限速器剩"&($AB44-TODAY())&"天 ","")))&IF($AC44="","",IF($AC44<TODAY(),"载重试验已过期"&(TODAY()-$AC44)&"天 ",IF($AC44-TODAY()<=提醒天数,"载重试验剩"&($AC44-TODAY())&"天 ",""))))) | AA44: =IF(TRIM($Q44&"")="","",IF(ISNUMBER($Q44),IF($Q44>10000,$Q44,IFERROR(DATE(INT($Q44),IF(ROUND(MOD($Q44,1)*100,0)>12,ROUND(MOD($Q44,1)*10,0),ROUND(MOD($Q44,1)*100,0))+1,0),"")),IFERROR(IF(LEN($Q44)-LEN(SUBSTITUTE($Q44,".",""))>=2,DATEVALUE(SUBSTITUTE(TRIM($Q44),".","-")),DATE(VALUE(LEFT(TRIM($Q44),4)),VALUE(MID(TRIM($Q44),6,2))+1,0)),""))) | AB44: =IF(TRIM($S44&"")="","",IF(ISNUMBER($S44),IF($S44>10000,$S44,IFERROR(DATE(INT($S44),IF(ROUND(MOD($S44,1)*100,0)>12,ROUND(MOD($S44,1)*10,0),ROUND(MOD($S44,1)*100,0))+1,0),"")),IFERROR(IF(LEN($S44)-LEN(SUBSTITUTE($S44,".",""))>=2,DATEVALUE(SUBSTITUTE(TRIM($S44),".","-")),DATE(VALUE(LEFT(TRIM($S44),4)),VALUE(MID(TRIM($S44),6,2))+1,0)),""))) | AC44: =IF(TRIM($T44&"")="","",IF(ISNUMBER($T44),IF($T44>10000,$T44,IFERROR(DATE(INT($T44),IF(ROUND(MOD($T44,1)*100,0)>12,ROUND(MOD($T44,1)*10,0),ROUND(MOD($T44,1)*100,0))+1,0),"")),IFERROR(IF(LEN($T44)-LEN(SUBSTITUTE($T44,".",""))>=2,DATEVALUE(SUBSTITUTE(TRIM($T44),".","-")),DATE(VALUE(LEFT(TRIM($T44),4)),VALUE(MID(TRIM($T44),6,2))+1,0)),"")))
B45: 武汉北方能源股份有限公司 | C45: 北方能源 | D45: LGE-050-C0105 | E45: 31104201122020110126 | G45: 日立电梯 | H45: 客梯(无机房) | I45: 11 | J45: 11 | K45: 11 | L45: 1050kg | M45: 1.75m/s | N45: 1 | O45: 19G077820 | P45: 研发楼Y2#客 | Y45: =IF(TRIM($B45&$C45)="","",IF(OR($W45="安装免保",$W45="技术免保",$W45="质保期内"),IF(NOT(ISNUMBER($X45)),"▲免保到期日没填",IF($X45<TODAY(),"▲免保已到期，转收费",IF($X45-TODAY()<=提醒天数,"免保剩"&($X45-TODAY())&"天","免保中"))),IF($W45="暂停维保","暂停中",IF($W45="已解约","已解约","")))) | Z45: =IF(TRIM($B45&$C45)="","",TRIM(IF($AA45="","",IF($AA45<TODAY(),"年检已过期"&(TODAY()-$AA45)&"天 ",IF($AA45-TODAY()<=提醒天数,"年检剩"&($AA45-TODAY())&"天 ","")))&IF($AB45="","",IF($AB45<TODAY(),"限速器已过期"&(TODAY()-$AB45)&"天 ",IF($AB45-TODAY()<=提醒天数,"限速器剩"&($AB45-TODAY())&"天 ","")))&IF($AC45="","",IF($AC45<TODAY(),"载重试验已过期"&(TODAY()-$AC45)&"天 ",IF($AC45-TODAY()<=提醒天数,"载重试验剩"&($AC45-TODAY())&"天 ",""))))) | AA45: =IF(TRIM($Q45&"")="","",IF(ISNUMBER($Q45),IF($Q45>10000,$Q45,IFERROR(DATE(INT($Q45),IF(ROUND(MOD($Q45,1)*100,0)>12,ROUND(MOD($Q45,1)*10,0),ROUND(MOD($Q45,1)*100,0))+1,0),"")),IFERROR(IF(LEN($Q45)-LEN(SUBSTITUTE($Q45,".",""))>=2,DATEVALUE(SUBSTITUTE(TRIM($Q45),".","-")),DATE(VALUE(LEFT(TRIM($Q45),4)),VALUE(MID(TRIM($Q45),6,2))+1,0)),""))) | AB45: =IF(TRIM($S45&"")="","",IF(ISNUMBER($S45),IF($S45>10000,$S45,IFERROR(DATE(INT($S45),IF(ROUND(MOD($S45,1)*100,0)>12,ROUND(MOD($S45,1)*10,0),ROUND(MOD($S45,1)*100,0))+1,0),"")),IFERROR(IF(LEN($S45)-LEN(SUBSTITUTE($S45,".",""))>=2,DATEVALUE(SUBSTITUTE(TRIM($S45),".","-")),DATE(VALUE(LEFT(TRIM($S45),4)),VALUE(MID(TRIM($S45),6,2))+1,0)),""))) | AC45: =IF(TRIM($T45&"")="","",IF(ISNUMBER($T45),IF($T45>10000,$T45,IFERROR(DATE(INT($T45),IF(ROUND(MOD($T45,1)*100,0)>12,ROUND(MOD($T45,1)*10,0),ROUND(MOD($T45,1)*100,0))+1,0),"")),IFERROR(IF(LEN($T45)-LEN(SUBSTITUTE($T45,".",""))>=2,DATEVALUE(SUBSTITUTE(TRIM($T45),".","-")),DATE(VALUE(LEFT(TRIM($T45),4)),VALUE(MID(TRIM($T45),6,2))+1,0)),"")))
B46: 武汉博语文化传媒有限公司 | C46: 吴家花园 | D46: MEGA-H | E46: / | F46: / | G46: 住友富士电梯有限公司 | H46: 客梯 | I46: 3 | J46: 3 | K46: 3 | L46: 400kg | M46: 0.4m/s | N46: 1 | O46: 1102016 | P46: 别墅电梯 | Y46: =IF(TRIM($B46&$C46)="","",IF(OR($W46="安装免保",$W46="技术免保",$W46="质保期内"),IF(NOT(ISNUMBER($X46)),"▲免保到期日没填",IF($X46<TODAY(),"▲免保已到期，转收费",IF($X46-TODAY()<=提醒天数,"免保剩"&($X46-TODAY())&"天","免保中"))),IF($W46="暂停维保","暂停中",IF($W46="已解约","已解约","")))) | Z46: =IF(TRIM($B46&$C46)="","",TRIM(IF($AA46="","",IF($AA46<TODAY(),"年检已过期"&(TODAY()-$AA46)&"天 ",IF($AA46-TODAY()<=提醒天数,"年检剩"&($AA46-TODAY())&"天 ","")))&IF($AB46="","",IF($AB46<TODAY(),"限速器已过期"&(TODAY()-$AB46)&"天 ",IF($AB46-TODAY()<=提醒天数,"限速器剩"&($AB46-TODAY())&"天 ","")))&IF($AC46="","",IF($AC46<TODAY(),"载重试验已过期"&(TODAY()-$AC46)&"天 ",IF($AC46-TODAY()<=提醒天数,"载重试验剩"&($AC46-TODAY())&"天 ",""))))) | AA46: =IF(TRIM($Q46&"")="","",IF(ISNUMBER($Q46),IF($Q46>10000,$Q46,IFERROR(DATE(INT($Q46),IF(ROUND(MOD($Q46,1)*100,0)>12,ROUND(MOD($Q46,1)*10,0),ROUND(MOD($Q46,1)*100,0))+1,0),"")),IFERROR(IF(LEN($Q46)-LEN(SUBSTITUTE($Q46,".",""))>=2,DATEVALUE(SUBSTITUTE(TRIM($Q46),".","-")),DATE(VALUE(LEFT(TRIM($Q46),4)),VALUE(MID(TRIM($Q46),6,2))+1,0)),""))) | AB46: =IF(TRIM($S46&"")="","",IF(ISNUMBER($S46),IF($S46>10000,$S46,IFERROR(DATE(INT($S46),IF(ROUND(MOD($S46,1)*100,0)>12,ROUND(MOD($S46,1)*10,0),ROUND(MOD($S46,1)*100,0))+1,0),"")),IFERROR(IF(LEN($S46)-LEN(SUBSTITUTE($S46,".",""))>=2,DATEVALUE(SUBSTITUTE(TRIM($S46),".","-")),DATE(VALUE(LEFT(TRIM($S46),4)),VALUE(MID(TRIM($S46),6,2))+1,0)),""))) | AC46: =IF(TRIM($T46&"")="","",IF(ISNUMBER($T46),IF($T46>10000,$T46,IFERROR(DATE(INT($T46),IF(ROUND(MOD($T46,1)*100,0)>12,ROUND(MOD($T46,1)*10,0),ROUND(MOD($T46,1)*100,0))+1,0),"")),IFERROR(IF(LEN($T46)-LEN(SUBSTITUTE($T46,".",""))>=2,DATEVALUE(SUBSTITUTE(TRIM($T46),".","-")),DATE(VALUE(LEFT(TRIM($T46),4)),VALUE(MID(TRIM($T46),6,2))+1,0)),"")))
B47: 武汉力托投资有限公司 | C47: 力托工业园 | D47: CHOI-III | E47: 31104201132021050002 | F47: 129254 | G47: 沈阳远大智能工业集团 | H47: 客梯 | I47: 5 | J47: 5 | K47: 5 | L47: 1000kg | M47: 1.0m/s | N47: 1 | O47: BLTSY20K/20412 | P47: 1#客 | Y47: =IF(TRIM($B47&$C47)="","",IF(OR($W47="安装免保",$W47="技术免保",$W47="质保期内"),IF(NOT(ISNUMBER($X47)),"▲免保到期日没填",IF($X47<TODAY(),"▲免保已到期，转收费",IF($X47-TODAY()<=提醒天数,"免保剩"&($X47-TODAY())&"天","免保中"))),IF($W47="暂停维保","暂停中",IF($W47="已解约","已解约","")))) | Z47: =IF(TRIM($B47&$C47)="","",TRIM(IF($AA47="","",IF($AA47<TODAY(),"年检已过期"&(TODAY()-$AA47)&"天 ",IF($AA47-TODAY()<=提醒天数,"年检剩"&($AA47-TODAY())&"天 ","")))&IF($AB47="","",IF($AB47<TODAY(),"限速器已过期"&(TODAY()-$AB47)&"天 ",IF($AB47-TODAY()<=提醒天数,"限速器剩"&($AB47-TODAY())&"天 ","")))&IF($AC47="","",IF($AC47<TODAY(),"载重试验已过期"&(TODAY()-$AC47)&"天 ",IF($AC47-TODAY()<=提醒天数,"载重试验剩"&($AC47-TODAY())&"天 ",""))))) | AA47: =IF(TRIM($Q47&"")="","",IF(ISNUMBER($Q47),IF($Q47>10000,$Q47,IFERROR(DATE(INT($Q47),IF(ROUND(MOD($Q47,1)*100,0)>12,ROUND(MOD($Q47,1)*10,0),ROUND(MOD($Q47,1)*100,0))+1,0),"")),IFERROR(IF(LEN($Q47)-LEN(SUBSTITUTE($Q47,".",""))>=2,DATEVALUE(SUBSTITUTE(TRIM($Q47),".","-")),DATE(VALUE(LEFT(TRIM($Q47),4)),VALUE(MID(TRIM($Q47),6,2))+1,0)),""))) | AB47: =IF(TRIM($S47&"")="","",IF(ISNUMBER($S47),IF($S47>10000,$S47,IFERROR(DATE(INT($S47),IF(ROUND(MOD($S47,1)*100,0)>12,ROUND(MOD($S47,1)*10,0),ROUND(MOD($S47,1)*100,0))+1,0),"")),IFERROR(IF(LEN($S47)-LEN(SUBSTITUTE($S47,".",""))>=2,DATEVALUE(SUBSTITUTE(TRIM($S47),".","-")),DATE(VALUE(LEFT(TRIM($S47),4)),VALUE(MID(TRIM($S47),6,2))+1,0)),""))) | AC47: =IF(TRIM($T47&"")="","",IF(ISNUMBER($T47),IF($T47>10000,$T47,IFERROR(DATE(INT($T47),IF(ROUND(MOD($T47,1)*100,0)>12,ROUND(MOD($T47,1)*10,0),ROUND(MOD($T47,1)*100,0))+1,0),"")),IFERROR(IF(LEN($T47)-LEN(SUBSTITUTE($T47,".",""))>=2,DATEVALUE(SUBSTITUTE(TRIM($T47),".","-")),DATE(VALUE(LEFT(TRIM($T47),4)),VALUE(MID(TRIM($T47),6,2))+1,0)),"")))
B48: 武汉力托投资有限公司 | C48: 力托工业园 | D48: CHOI-III | E48: 31104201132021050003 | F48: 129255 | G48: 沈阳远大智能工业集团 | H48: 客梯 | I48: 5 | J48: 5 | K48: 5 | L48: 1000kg | M48: 1.0m/s | N48: 1 | O48: BLTSY20K/20413 | P48: 2#客 | Y48: =IF(TRIM($B48&$C48)="","",IF(OR($W48="安装免保",$W48="技术免保",$W48="质保期内"),IF(NOT(ISNUMBER($X48)),"▲免保到期日没填",IF($X48<TODAY(),"▲免保已到期，转收费",IF($X48-TODAY()<=提醒天数,"免保剩"&($X48-TODAY())&"天","免保中"))),IF($W48="暂停维保","暂停中",IF($W48="已解约","已解约","")))) | Z48: =IF(TRIM($B48&$C48)="","",TRIM(IF($AA48="","",IF($AA48<TODAY(),"年检已过期"&(TODAY()-$AA48)&"天 ",IF($AA48-TODAY()<=提醒天数,"年检剩"&($AA48-TODAY())&"天 ","")))&IF($AB48="","",IF($AB48<TODAY(),"限速器已过期"&(TODAY()-$AB48)&"天 ",IF($AB48-TODAY()<=提醒天数,"限速器剩"&($AB48-TODAY())&"天 ","")))&IF($AC48="","",IF($AC48<TODAY(),"载重试验已过期"&(TODAY()-$AC48)&"天 ",IF($AC48-TODAY()<=提醒天数,"载重试验剩"&($AC48-TODAY())&"天 ",""))))) | AA48: =IF(TRIM($Q48&"")="","",IF(ISNUMBER($Q48),IF($Q48>10000,$Q48,IFERROR(DATE(INT($Q48),IF(ROUND(MOD($Q48,1)*100,0)>12,ROUND(MOD($Q48,1)*10,0),ROUND(MOD($Q48,1)*100,0))+1,0),"")),IFERROR(IF(LEN($Q48)-LEN(SUBSTITUTE($Q48,".",""))>=2,DATEVALUE(SUBSTITUTE(TRIM($Q48),".","-")),DATE(VALUE(LEFT(TRIM($Q48),4)),VALUE(MID(TRIM($Q48),6,2))+1,0)),""))) | AB48: =IF(TRIM($S48&"")="","",IF(ISNUMBER($S48),IF($S48>10000,$S48,IFERROR(DATE(INT($S48),IF(ROUND(MOD($S48,1)*100,0)>12,ROUND(MOD($S48,1)*10,0),ROUND(MOD($S48,1)*100,0))+1,0),"")),IFERROR(IF(LEN($S48)-LEN(SUBSTITUTE($S48,".",""))>=2,DATEVALUE(SUBSTITUTE(TRIM($S48),".","-")),DATE(VALUE(LEFT(TRIM($S48),4)),VALUE(MID(TRIM($S48),6,2))+1,0)),""))) | AC48: =IF(TRIM($T48&"")="","",IF(ISNUMBER($T48),IF($T48>10000,$T48,IFERROR(DATE(INT($T48),IF(ROUND(MOD($T48,1)*100,0)>12,ROUND(MOD($T48,1)*10,0),ROUND(MOD($T48,1)*100,0))+1,0),"")),IFERROR(IF(LEN($T48)-LEN(SUBSTITUTE($T48,".",""))>=2,DATEVALUE(SUBSTITUTE(TRIM($T48),".","-")),DATE(VALUE(LEFT(TRIM($T48),4)),VALUE(MID(TRIM($T48),6,2))+1,0)),"")))
B49: 武汉彤明汽车零部件有限公司 | C49: 金澜湾工业园彤明23#楼 | D49: CHOI-III | E49: 31104201132021050005 | F49: 129257 | G49: 沈阳远大智能工业集团 | H49: 客梯 | I49: 7 | J49: 7 | K49: 7 | L49: 1000kg | M49: 1.0m/s | N49: 1 | O49: BLTSY20K/20414 | P49: 23号楼1#客 | Y49: =IF(TRIM($B49&$C49)="","",IF(OR($W49="安装免保",$W49="技术免保",$W49="质保期内"),IF(NOT(ISNUMBER($X49)),"▲免保到期日没填",IF($X49<TODAY(),"▲免保已到期，转收费",IF($X49-TODAY()<=提醒天数,"免保剩"&($X49-TODAY())&"天","免保中"))),IF($W49="暂停维保","暂停中",IF($W49="已解约","已解约","")))) | Z49: =IF(TRIM($B49&$C49)="","",TRIM(IF($AA49="","",IF($AA49<TODAY(),"年检已过期"&(TODAY()-$AA49)&"天 ",IF($AA49-TODAY()<=提醒天数,"年检剩"&($AA49-TODAY())&"天 ","")))&IF($AB49="","",IF($AB49<TODAY(),"限速器已过期"&(TODAY()-$AB49)&"天 ",IF($AB49-TODAY()<=提醒天数,"限速器剩"&($AB49-TODAY())&"天 ","")))&IF($AC49="","",IF($AC49<TODAY(),"载重试验已过期"&(TODAY()-$AC49)&"天 ",IF($AC49-TODAY()<=提醒天数,"载重试验剩"&($AC49-TODAY())&"天 ",""))))) | AA49: =IF(TRIM($Q49&"")="","",IF(ISNUMBER($Q49),IF($Q49>10000,$Q49,IFERROR(DATE(INT($Q49),IF(ROUND(MOD($Q49,1)*100,0)>12,ROUND(MOD($Q49,1)*10,0),ROUND(MOD($Q49,1)*100,0))+1,0),"")),IFERROR(IF(LEN($Q49)-LEN(SUBSTITUTE($Q49,".",""))>=2,DATEVALUE(SUBSTITUTE(TRIM($Q49),".","-")),DATE(VALUE(LEFT(TRIM($Q49),4)),VALUE(MID(TRIM($Q49),6,2))+1,0)),""))) | AB49: =IF(TRIM($S49&"")="","",IF(ISNUMBER($S49),IF($S49>10000,$S49,IFERROR(DATE(INT($S49),IF(ROUND(MOD($S49,1)*100,0)>12,ROUND(MOD($S49,1)*10,0),ROUND(MOD($S49,1)*100,0))+1,0),"")),IFERROR(IF(LEN($S49)-LEN(SUBSTITUTE($S49,".",""))>=2,DATEVALUE(SUBSTITUTE(TRIM($S49),".","-")),DATE(VALUE(LEFT(TRIM($S49),4)),VALUE(MID(TRIM($S49),6,2))+1,0)),""))) | AC49: =IF(TRIM($T49&"")="","",IF(ISNUMBER($T49),IF($T49>10000,$T49,IFERROR(DATE(INT($T49),IF(ROUND(MOD($T49,1)*100,0)>12,ROUND(MOD($T49,1)*10,0),ROUND(MOD($T49,1)*100,0))+1,0),"")),IFERROR(IF(LEN($T49)-LEN(SUBSTITUTE($T49,".",""))>=2,DATEVALUE(SUBSTITUTE(TRIM($T49),".","-")),DATE(VALUE(LEFT(TRIM($T49),4)),VALUE(MID(TRIM($T49),6,2))+1,0)),"")))
B50: 武汉彤明汽车零部件有限公司 | C50: 金澜湾工业园彤明23#楼 | D50: CHOI-III | E50: 31104201132021050006 | F50: 129258 | G50: 沈阳远大智能工业集团 | H50: 客梯 | I50: 7 | J50: 7 | K50: 7 | L50: 1000kg | M50: 1.0m/s | N50: 1 | O50: BLTSY20K/20415 | P50: 23号楼2#客 | Y50: =IF(TRIM($B50&$C50)="","",IF(OR($W50="安装免保",$W50="技术免保",$W50="质保期内"),IF(NOT(ISNUMBER($X50)),"▲免保到期日没填",IF($X50<TODAY(),"▲免保已到期，转收费",IF($X50-TODAY()<=提醒天数,"免保剩"&($X50-TODAY())&"天","免保中"))),IF($W50="暂停维保","暂停中",IF($W50="已解约","已解约","")))) | Z50: =IF(TRIM($B50&$C50)="","",TRIM(IF($AA50="","",IF($AA50<TODAY(),"年检已过期"&(TODAY()-$AA50)&"天 ",IF($AA50-TODAY()<=提醒天数,"年检剩"&($AA50-TODAY())&"天 ","")))&IF($AB50="","",IF($AB50<TODAY(),"限速器已过期"&(TODAY()-$AB50)&"天 ",IF($AB50-TODAY()<=提醒天数,"限速器剩"&($AB50-TODAY())&"天 ","")))&IF($AC50="","",IF($AC50<TODAY(),"载重试验已过期"&(TODAY()-$AC50)&"天 ",IF($AC50-TODAY()<=提醒天数,"载重试验剩"&($AC50-TODAY())&"天 ",""))))) | AA50: =IF(TRIM($Q50&"")="","",IF(ISNUMBER($Q50),IF($Q50>10000,$Q50,IFERROR(DATE(INT($Q50),IF(ROUND(MOD($Q50,1)*100,0)>12,ROUND(MOD($Q50,1)*10,0),ROUND(MOD($Q50,1)*100,0))+1,0),"")),IFERROR(IF(LEN($Q50)-LEN(SUBSTITUTE($Q50,".",""))>=2,DATEVALUE(SUBSTITUTE(TRIM($Q50),".","-")),DATE(VALUE(LEFT(TRIM($Q50),4)),VALUE(MID(TRIM($Q50),6,2))+1,0)),""))) | AB50: =IF(TRIM($S50&"")="","",IF(ISNUMBER($S50),IF($S50>10000,$S50,IFERROR(DATE(INT($S50),IF(ROUND(MOD($S50,1)*100,0)>12,ROUND(MOD($S50,1)*10,0),ROUND(MOD($S50,1)*100,0))+1,0),"")),IFERROR(IF(LEN($S50)-LEN(SUBSTITUTE($S50,".",""))>=2,DATEVALUE(SUBSTITUTE(TRIM($S50),".","-")),DATE(VALUE(LEFT(TRIM($S50),4)),VALUE(MID(TRIM($S50),6,2))+1,0)),""))) | AC50: =IF(TRIM($T50&"")="","",IF(ISNUMBER($T50),IF($T50>10000,$T50,IFERROR(DATE(INT($T50),IF(ROUND(MOD($T50,1)*100,0)>12,ROUND(MOD($T50,1)*10,0),ROUND(MOD($T50,1)*100,0))+1,0),"")),IFERROR(IF(LEN($T50)-LEN(SUBSTITUTE($T50,".",""))>=2,DATEVALUE(SUBSTITUTE(TRIM($T50),".","-")),DATE(VALUE(LEFT(TRIM($T50),4)),VALUE(MID(TRIM($T50),6,2))+1,0)),"")))
B51: 武汉三工光电设备制造有限公司 | C51: 武大园办公楼 | D51: MEGA-MRL | E51: 31104201192021070025 | F51: 137220 | G51: 住友富士 | H51: 客梯(无机房) | I51: 5 | J51: 5 | K51: 5 | L51: 1600kg | M51: 1.0m/s | N51: 1 | O51: 1103081 | P51: 1#客 | Y51: =IF(TRIM($B51&$C51)="","",IF(OR($W51="安装免保",$W51="技术免保",$W51="质保期内"),IF(NOT(ISNUMBER($X51)),"▲免保到期日没填",IF($X51<TODAY(),"▲免保已到期，转收费",IF($X51-TODAY()<=提醒天数,"免保剩"&($X51-TODAY())&"天","免保中"))),IF($W51="暂停维保","暂停中",IF($W51="已解约","已解约","")))) | Z51: =IF(TRIM($B51&$C51)="","",TRIM(IF($AA51="","",IF($AA51<TODAY(),"年检已过期"&(TODAY()-$AA51)&"天 ",IF($AA51-TODAY()<=提醒天数,"年检剩"&($AA51-TODAY())&"天 ","")))&IF($AB51="","",IF($AB51<TODAY(),"限速器已过期"&(TODAY()-$AB51)&"天 ",IF($AB51-TODAY()<=提醒天数,"限速器剩"&($AB51-TODAY())&"天 ","")))&IF($AC51="","",IF($AC51<TODAY(),"载重试验已过期"&(TODAY()-$AC51)&"天 ",IF($AC51-TODAY()<=提醒天数,"载重试验剩"&($AC51-TODAY())&"天 ",""))))) | AA51: =IF(TRIM($Q51&"")="","",IF(ISNUMBER($Q51),IF($Q51>10000,$Q51,IFERROR(DATE(INT($Q51),IF(ROUND(MOD($Q51,1)*100,0)>12,ROUND(MOD($Q51,1)*10,0),ROUND(MOD($Q51,1)*100,0))+1,0),"")),IFERROR(IF(LEN($Q51)-LEN(SUBSTITUTE($Q51,".",""))>=2,DATEVALUE(SUBSTITUTE(TRIM($Q51),".","-")),DATE(VALUE(LEFT(TRIM($Q51),4)),VALUE(MID(TRIM($Q51),6,2))+1,0)),""))) | AB51: =IF(TRIM($S51&"")="","",IF(ISNUMBER($S51),IF($S51>10000,$S51,IFERROR(DATE(INT($S51),IF(ROUND(MOD($S51,1)*100,0)>12,ROUND(MOD($S51,1)*10,0),ROUND(MOD($S51,1)*100,0))+1,0),"")),IFERROR(IF(LEN($S51)-LEN(SUBSTITUTE($S51,".",""))>=2,DATEVALUE(SUBSTITUTE(TRIM($S51),".","-")),DATE(VALUE(LEFT(TRIM($S51),4)),VALUE(MID(TRIM($S51),6,2))+1,0)),""))) | AC51: =IF(TRIM($T51&"")="","",IF(ISNUMBER($T51),IF($T51>10000,$T51,IFERROR(DATE(INT($T51),IF(ROUND(MOD($T51,1)*100,0)>12,ROUND(MOD($T51,1)*10,0),ROUND(MOD($T51,1)*100,0))+1,0),"")),IFERROR(IF(LEN($T51)-LEN(SUBSTITUTE($T51,".",""))>=2,DATEVALUE(SUBSTITUTE(TRIM($T51),".","-")),DATE(VALUE(LEFT(TRIM($T51),4)),VALUE(MID(TRIM($T51),6,2))+1,0)),"")))
B52: 武汉中海联机电工程有限公司 | C52: 电建小区41栋1单元（涂晓慧） | D52: WJK | E52: 31104201032021080035 | F52: 137221 | G52: 福州快科电梯 | H52: 客梯（无机房） | I52: 9 | J52: 9 | K52: 9 | L52: 800kg | M52: 1.0m/s | N52: 1 | O52: K.E30-2100076 | P52: 1#客梯 | Y52: =IF(TRIM($B52&$C52)="","",IF(OR($W52="安装免保",$W52="技术免保",$W52="质保期内"),IF(NOT(ISNUMBER($X52)),"▲免保到期日没填",IF($X52<TODAY(),"▲免保已到期，转收费",IF($X52-TODAY()<=提醒天数,"免保剩"&($X52-TODAY())&"天","免保中"))),IF($W52="暂停维保","暂停中",IF($W52="已解约","已解约","")))) | Z52: =IF(TRIM($B52&$C52)="","",TRIM(IF($AA52="","",IF($AA52<TODAY(),"年检已过期"&(TODAY()-$AA52)&"天 ",IF($AA52-TODAY()<=提醒天数,"年检剩"&($AA52-TODAY())&"天 ","")))&IF($AB52="","",IF($AB52<TODAY(),"限速器已过期"&(TODAY()-$AB52)&"天 ",IF($AB52-TODAY()<=提醒天数,"限速器剩"&($AB52-TODAY())&"天 ","")))&IF($AC52="","",IF($AC52<TODAY(),"载重试验已过期"&(TODAY()-$AC52)&"天 ",IF($AC52-TODAY()<=提醒天数,"载重试验剩"&($AC52-TODAY())&"天 ",""))))) | AA52: =IF(TRIM($Q52&"")="","",IF(ISNUMBER($Q52),IF($Q52>10000,$Q52,IFERROR(DATE(INT($Q52),IF(ROUND(MOD($Q52,1)*100,0)>12,ROUND(MOD($Q52,1)*10,0),ROUND(MOD($Q52,1)*100,0))+1,0),"")),IFERROR(IF(LEN($Q52)-LEN(SUBSTITUTE($Q52,".",""))>=2,DATEVALUE(SUBSTITUTE(TRIM($Q52),".","-")),DATE(VALUE(LEFT(TRIM($Q52),4)),VALUE(MID(TRIM($Q52),6,2))+1,0)),""))) | AB52: =IF(TRIM($S52&"")="","",IF(ISNUMBER($S52),IF($S52>10000,$S52,IFERROR(DATE(INT($S52),IF(ROUND(MOD($S52,1)*100,0)>12,ROUND(MOD($S52,1)*10,0),ROUND(MOD($S52,1)*100,0))+1,0),"")),IFERROR(IF(LEN($S52)-LEN(SUBSTITUTE($S52,".",""))>=2,DATEVALUE(SUBSTITUTE(TRIM($S52),".","-")),DATE(VALUE(LEFT(TRIM($S52),4)),VALUE(MID(TRIM($S52),6,2))+1,0)),""))) | AC52: =IF(TRIM($T52&"")="","",IF(ISNUMBER($T52),IF($T52>10000,$T52,IFERROR(DATE(INT($T52),IF(ROUND(MOD($T52,1)*100,0)>12,ROUND(MOD($T52,1)*10,0),ROUND(MOD($T52,1)*100,0))+1,0),"")),IFERROR(IF(LEN($T52)-LEN(SUBSTITUTE($T52,".",""))>=2,DATEVALUE(SUBSTITUTE(TRIM($T52),".","-")),DATE(VALUE(LEFT(TRIM($T52),4)),VALUE(MID(TRIM($T52),6,2))+1,0)),"")))
B53: 湖北星安电梯有限公司 | C53: 滨江苑一期11栋1单元（陈俊群） | D53: WJK | E53: 31104201022021110017 | F53: 137222 | G53: 福州快科电梯 | H53: 客梯（无机房） | I53: 7 | J53: 7 | K53: 7 | L53: 1000kg | M53: 1.0m/s | N53: 1 | O53: K.E30-2100167 | P53: 1#客梯 | Y53: =IF(TRIM($B53&$C53)="","",IF(OR($W53="安装免保",$W53="技术免保",$W53="质保期内"),IF(NOT(ISNUMBER($X53)),"▲免保到期日没填",IF($X53<TODAY(),"▲免保已到期，转收费",IF($X53-TODAY()<=提醒天数,"免保剩"&($X53-TODAY())&"天","免保中"))),IF($W53="暂停维保","暂停中",IF($W53="已解约","已解约","")))) | Z53: =IF(TRIM($B53&$C53)="","",TRIM(IF($AA53="","",IF($AA53<TODAY(),"年检已过期"&(TODAY()-$AA53)&"天 ",IF($AA53-TODAY()<=提醒天数,"年检剩"&($AA53-TODAY())&"天 ","")))&IF($AB53="","",IF($AB53<TODAY(),"限速器已过期"&(TODAY()-$AB53)&"天 ",IF($AB53-TODAY()<=提醒天数,"限速器剩"&($AB53-TODAY())&"天 ","")))&IF($AC53="","",IF($AC53<TODAY(),"载重试验已过期"&(TODAY()-$AC53)&"天 ",IF($AC53-TODAY()<=提醒天数,"载重试验剩"&($AC53-TODAY())&"天 ",""))))) | AA53: =IF(TRIM($Q53&"")="","",IF(ISNUMBER($Q53),IF($Q53>10000,$Q53,IFERROR(DATE(INT($Q53),IF(ROUND(MOD($Q53,1)*100,0)>12,ROUND(MOD($Q53,1)*10,0),ROUND(MOD($Q53,1)*100,0))+1,0),"")),IFERROR(IF(LEN($Q53)-LEN(SUBSTITUTE($Q53,".",""))>=2,DATEVALUE(SUBSTITUTE(TRIM($Q53),".","-")),DATE(VALUE(LEFT(TRIM($Q53),4)),VALUE(MID(TRIM($Q53),6,2))+1,0)),""))) | AB53: =IF(TRIM($S53&"")="","",IF(ISNUMBER($S53),IF($S53>10000,$S53,IFERROR(DATE(INT($S53),IF(ROUND(MOD($S53,1)*100,0)>12,ROUND(MOD($S53,1)*10,0),ROUND(MOD($S53,1)*100,0))+1,0),"")),IFERROR(IF(LEN($S53)-LEN(SUBSTITUTE($S53,".",""))>=2,DATEVALUE(SUBSTITUTE(TRIM($S53),".","-")),DATE(VALUE(LEFT(TRIM($S53),4)),VALUE(MID(TRIM($S53),6,2))+1,0)),""))) | AC53: =IF(TRIM($T53&"")="","",IF(ISNUMBER($T53),IF($T53>10000,$T53,IFERROR(DATE(INT($T53),IF(ROUND(MOD($T53,1)*100,0)>12,ROUND(MOD($T53,1)*10,0),ROUND(MOD($T53,1)*100,0))+1,0),"")),IFERROR(IF(LEN($T53)-LEN(SUBSTITUTE($T53,".",""))>=2,DATEVALUE(SUBSTITUTE(TRIM($T53),".","-")),DATE(VALUE(LEFT(TRIM($T53),4)),VALUE(MID(TRIM($T53),6,2))+1,0)),"")))
B54: 武汉北港建工集团开发有限公司 | C54: 佳和云居 | D54: XO-REZ0II | E54: 31104201112022060060 | F54: 154205 | G54: 杭州西奥电梯 | H54: 客梯 | I54: 18 | J54: 18 | K54: 18 | L54: 800kg | M54: 1.75m/s | N54: 1 | O54: XODTS17457 | P54: 9-2-2#客 | Y54: =IF(TRIM($B54&$C54)="","",IF(OR($W54="安装免保",$W54="技术免保",$W54="质保期内"),IF(NOT(ISNUMBER($X54)),"▲免保到期日没填",IF($X54<TODAY(),"▲免保已到期，转收费",IF($X54-TODAY()<=提醒天数,"免保剩"&($X54-TODAY())&"天","免保中"))),IF($W54="暂停维保","暂停中",IF($W54="已解约","已解约","")))) | Z54: =IF(TRIM($B54&$C54)="","",TRIM(IF($AA54="","",IF($AA54<TODAY(),"年检已过期"&(TODAY()-$AA54)&"天 ",IF($AA54-TODAY()<=提醒天数,"年检剩"&($AA54-TODAY())&"天 ","")))&IF($AB54="","",IF($AB54<TODAY(),"限速器已过期"&(TODAY()-$AB54)&"天 ",IF($AB54-TODAY()<=提醒天数,"限速器剩"&($AB54-TODAY())&"天 ","")))&IF($AC54="","",IF($AC54<TODAY(),"载重试验已过期"&(TODAY()-$AC54)&"天 ",IF($AC54-TODAY()<=提醒天数,"载重试验剩"&($AC54-TODAY())&"天 ",""))))) | AA54: =IF(TRIM($Q54&"")="","",IF(ISNUMBER($Q54),IF($Q54>10000,$Q54,IFERROR(DATE(INT($Q54),IF(ROUND(MOD($Q54,1)*100,0)>12,ROUND(MOD($Q54,1)*10,0),ROUND(MOD($Q54,1)*100,0))+1,0),"")),IFERROR(IF(LEN($Q54)-LEN(SUBSTITUTE($Q54,".",""))>=2,DATEVALUE(SUBSTITUTE(TRIM($Q54),".","-")),DATE(VALUE(LEFT(TRIM($Q54),4)),VALUE(MID(TRIM($Q54),6,2))+1,0)),""))) | AB54: =IF(TRIM($S54&"")="","",IF(ISNUMBER($S54),IF($S54>10000,$S54,IFERROR(DATE(INT($S54),IF(ROUND(MOD($S54,1)*100,0)>12,ROUND(MOD($S54,1)*10,0),ROUND(MOD($S54,1)*100,0))+1,0),"")),IFERROR(IF(LEN($S54)-LEN(SUBSTITUTE($S54,".",""))>=2,DATEVALUE(SUBSTITUTE(TRIM($S54),".","-")),DATE(VALUE(LEFT(TRIM($S54),4)),VALUE(MID(TRIM($S54),6,2))+1,0)),""))) | AC54: =IF(TRIM($T54&"")="","",IF(ISNUMBER($T54),IF($T54>10000,$T54,IFERROR(DATE(INT($T54),IF(ROUND(MOD($T54,1)*100,0)>12,ROUND(MOD($T54,1)*10,0),ROUND(MOD($T54,1)*100,0))+1,0),"")),IFERROR(IF(LEN($T54)-LEN(SUBSTITUTE($T54,".",""))>=2,DATEVALUE(SUBSTITUTE(TRIM($T54),".","-")),DATE(VALUE(LEFT(TRIM($T54),4)),VALUE(MID(TRIM($T54),6,2))+1,0)),"")))
B55: 武汉北港建工集团开发有限公司 | C55: 佳和云居 | D55: XO-REZ0II | E55: 31104201112022030072 | F55: 134748 | G55: 杭州西奥电梯 | H55: 客梯 | I55: 19 | J55: 19 | K55: 19 | L55: 800kg | M55: 1.75m/s | N55: 1 | O55: XODTS17461 | P55: 9栋2单元1#客 | Y55: =IF(TRIM($B55&$C55)="","",IF(OR($W55="安装免保",$W55="技术免保",$W55="质保期内"),IF(NOT(ISNUMBER($X55)),"▲免保到期日没填",IF($X55<TODAY(),"▲免保已到期，转收费",IF($X55-TODAY()<=提醒天数,"免保剩"&($X55-TODAY())&"天","免保中"))),IF($W55="暂停维保","暂停中",IF($W55="已解约","已解约","")))) | Z55: =IF(TRIM($B55&$C55)="","",TRIM(IF($AA55="","",IF($AA55<TODAY(),"年检已过期"&(TODAY()-$AA55)&"天 ",IF($AA55-TODAY()<=提醒天数,"年检剩"&($AA55-TODAY())&"天 ","")))&IF($AB55="","",IF($AB55<TODAY(),"限速器已过期"&(TODAY()-$AB55)&"天 ",IF($AB55-TODAY()<=提醒天数,"限速器剩"&($AB55-TODAY())&"天 ","")))&IF($AC55="","",IF($AC55<TODAY(),"载重试验已过期"&(TODAY()-$AC55)&"天 ",IF($AC55-TODAY()<=提醒天数,"载重试验剩"&($AC55-TODAY())&"天 ",""))))) | AA55: =IF(TRIM($Q55&"")="","",IF(ISNUMBER($Q55),IF($Q55>10000,$Q55,IFERROR(DATE(INT($Q55),IF(ROUND(MOD($Q55,1)*100,0)>12,ROUND(MOD($Q55,1)*10,0),ROUND(MOD($Q55,1)*100,0))+1,0),"")),IFERROR(IF(LEN($Q55)-LEN(SUBSTITUTE($Q55,".",""))>=2,DATEVALUE(SUBSTITUTE(TRIM($Q55),".","-")),DATE(VALUE(LEFT(TRIM($Q55),4)),VALUE(MID(TRIM($Q55),6,2))+1,0)),""))) | AB55: =IF(TRIM($S55&"")="","",IF(ISNUMBER($S55),IF($S55>10000,$S55,IFERROR(DATE(INT($S55),IF(ROUND(MOD($S55,1)*100,0)>12,ROUND(MOD($S55,1)*10,0),ROUND(MOD($S55,1)*100,0))+1,0),"")),IFERROR(IF(LEN($S55)-LEN(SUBSTITUTE($S55,".",""))>=2,DATEVALUE(SUBSTITUTE(TRIM($S55),".","-")),DATE(VALUE(LEFT(TRIM($S55),4)),VALUE(MID(TRIM($S55),6,2))+1,0)),""))) | AC55: =IF(TRIM($T55&"")="","",IF(ISNUMBER($T55),IF($T55>10000,$T55,IFERROR(DATE(INT($T55),IF(ROUND(MOD($T55,1)*100,0)>12,ROUND(MOD($T55,1)*10,0),ROUND(MOD($T55,1)*100,0))+1,0),"")),IFERROR(IF(LEN($T55)-LEN(SUBSTITUTE($T55,".",""))>=2,DATEVALUE(SUBSTITUTE(TRIM($T55),".","-")),DATE(VALUE(LEFT(TRIM($T55),4)),VALUE(MID(TRIM($T55),6,2))+1,0)),"")))
B56: 武汉北港建工集团开发有限公司 | C56: 佳和云居 | D56: XO-REZ0II | E56: 31104201112022060059 | F56: 154204 | G56: 杭州西奥电梯 | H56: 客梯 | I56: 18 | J56: 18 | K56: 18 | L56: 800kg | M56: 1.75m/s | N56: 1 | O56: XODTS17456 | P56: 9-1-2#客 | Y56: =IF(TRIM($B56&$C56)="","",IF(OR($W56="安装免保",$W56="技术免保",$W56="质保期内"),IF(NOT(ISNUMBER($X56)),"▲免保到期日没填",IF($X56<TODAY(),"▲免保已到期，转收费",IF($X56-TODAY()<=提醒天数,"免保剩"&($X56-TODAY())&"天","免保中"))),IF($W56="暂停维保","暂停中",IF($W56="已解约","已解约","")))) | Z56: =IF(TRIM($B56&$C56)="","",TRIM(IF($AA56="","",IF($AA56<TODAY(),"年检已过期"&(TODAY()-$AA56)&"天 ",IF($AA56-TODAY()<=提醒天数,"年检剩"&($AA56-TODAY())&"天 ","")))&IF($AB56="","",IF($AB56<TODAY(),"限速器已过期"&(TODAY()-$AB56)&"天 ",IF($AB56-TODAY()<=提醒天数,"限速器剩"&($AB56-TODAY())&"天 ","")))&IF($AC56="","",IF($AC56<TODAY(),"载重试验已过期"&(TODAY()-$AC56)&"天 ",IF($AC56-TODAY()<=提醒天数,"载重试验剩"&($AC56-TODAY())&"天 ",""))))) | AA56: =IF(TRIM($Q56&"")="","",IF(ISNUMBER($Q56),IF($Q56>10000,$Q56,IFERROR(DATE(INT($Q56),IF(ROUND(MOD($Q56,1)*100,0)>12,ROUND(MOD($Q56,1)*10,0),ROUND(MOD($Q56,1)*100,0))+1,0),"")),IFERROR(IF(LEN($Q56)-LEN(SUBSTITUTE($Q56,".",""))>=2,DATEVALUE(SUBSTITUTE(TRIM($Q56),".","-")),DATE(VALUE(LEFT(TRIM($Q56),4)),VALUE(MID(TRIM($Q56),6,2))+1,0)),""))) | AB56: =IF(TRIM($S56&"")="","",IF(ISNUMBER($S56),IF($S56>10000,$S56,IFERROR(DATE(INT($S56),IF(ROUND(MOD($S56,1)*100,0)>12,ROUND(MOD($S56,1)*10,0),ROUND(MOD($S56,1)*100,0))+1,0),"")),IFERROR(IF(LEN($S56)-LEN(SUBSTITUTE($S56,".",""))>=2,DATEVALUE(SUBSTITUTE(TRIM($S56),".","-")),DATE(VALUE(LEFT(TRIM($S56),4)),VALUE(MID(TRIM($S56),6,2))+1,0)),""))) | AC56: =IF(TRIM($T56&"")="","",IF(ISNUMBER($T56),IF($T56>10000,$T56,IFERROR(DATE(INT($T56),IF(ROUND(MOD($T56,1)*100,0)>12,ROUND(MOD($T56,1)*10,0),ROUND(MOD($T56,1)*100,0))+1,0),"")),IFERROR(IF(LEN($T56)-LEN(SUBSTITUTE($T56,".",""))>=2,DATEVALUE(SUBSTITUTE(TRIM($T56),".","-")),DATE(VALUE(LEFT(TRIM($T56),4)),VALUE(MID(TRIM($T56),6,2))+1,0)),"")))
B57: 武汉北港建工集团开发有限公司 | C57: 佳和云居 | D57: XO-REZ0II | E57: 31104201112022030071 | F57: 134747 | G57: 杭州西奥电梯 | H57: 客梯 | I57: 19 | J57: 19 | K57: 19 | L57: 800kg | M57: 1.75m/s | N57: 1 | O57: XODTS17460 | P57: 9栋1单元1#客 | Y57: =IF(TRIM($B57&$C57)="","",IF(OR($W57="安装免保",$W57="技术免保",$W57="质保期内"),IF(NOT(ISNUMBER($X57)),"▲免保到期日没填",IF($X57<TODAY(),"▲免保已到期，转收费",IF($X57-TODAY()<=提醒天数,"免保剩"&($X57-TODAY())&"天","免保中"))),IF($W57="暂停维保","暂停中",IF($W57="已解约","已解约","")))) | Z57: =IF(TRIM($B57&$C57)="","",TRIM(IF($AA57="","",IF($AA57<TODAY(),"年检已过期"&(TODAY()-$AA57)&"天 ",IF($AA57-TODAY()<=提醒天数,"年检剩"&($AA57-TODAY())&"天 ","")))&IF($AB57="","",IF($AB57<TODAY(),"限速器已过期"&(TODAY()-$AB57)&"天 ",IF($AB57-TODAY()<=提醒天数,"限速器剩"&($AB57-TODAY())&"天 ","")))&IF($AC57="","",IF($AC57<TODAY(),"载重试验已过期"&(TODAY()-$AC57)&"天 ",IF($AC57-TODAY()<=提醒天数,"载重试验剩"&($AC57-TODAY())&"天 ",""))))) | AA57: =IF(TRIM($Q57&"")="","",IF(ISNUMBER($Q57),IF($Q57>10000,$Q57,IFERROR(DATE(INT($Q57),IF(ROUND(MOD($Q57,1)*100,0)>12,ROUND(MOD($Q57,1)*10,0),ROUND(MOD($Q57,1)*100,0))+1,0),"")),IFERROR(IF(LEN($Q57)-LEN(SUBSTITUTE($Q57,".",""))>=2,DATEVALUE(SUBSTITUTE(TRIM($Q57),".","-")),DATE(VALUE(LEFT(TRIM($Q57),4)),VALUE(MID(TRIM($Q57),6,2))+1,0)),""))) | AB57: =IF(TRIM($S57&"")="","",IF(ISNUMBER($S57),IF($S57>10000,$S57,IFERROR(DATE(INT($S57),IF(ROUND(MOD($S57,1)*100,0)>12,ROUND(MOD($S57,1)*10,0),ROUND(MOD($S57,1)*100,0))+1,0),"")),IFERROR(IF(LEN($S57)-LEN(SUBSTITUTE($S57,".",""))>=2,DATEVALUE(SUBSTITUTE(TRIM($S57),".","-")),DATE(VALUE(LEFT(TRIM($S57),4)),VALUE(MID(TRIM($S57),6,2))+1,0)),""))) | AC57: =IF(TRIM($T57&"")="","",IF(ISNUMBER($T57),IF($T57>10000,$T57,IFERROR(DATE(INT($T57),IF(ROUND(MOD($T57,1)*100,0)>12,ROUND(MOD($T57,1)*10,0),ROUND(MOD($T57,1)*100,0))+1,0),"")),IFERROR(IF(LEN($T57)-LEN(SUBSTITUTE($T57,".",""))>=2,DATEVALUE(SUBSTITUTE(TRIM($T57),".","-")),DATE(VALUE(LEFT(TRIM($T57),4)),VALUE(MID(TRIM($T57),6,2))+1,0)),"")))
... B113: 好利来食品科技（武汉）有限公司 | C113: 好利来 | D113: GF10 | E113: 31204201142022050010 | F113: 153702 | G113: 巨立电梯 | H113: 货梯 | I113: 4 | J113: 4 | K113: 4 | L113: 3000kg | M113: 0.5m/s | N113: 1 | O113: 21G04468 | P113: 生产车间6#货 | Y113: =IF(TRIM($B113&$C113)="","",IF(OR($W113="安装免保",$W113="技术免保",$W113="质保期内"),IF(NOT(ISNUMBER($X113)),"▲免保到期日没填",IF($X113<TODAY(),"▲免保已到期，转收费",IF($X113-TODAY()<=提醒天数,"免保剩"&($X113-TODAY())&"天","免保中"))),IF($W113="暂停维保","暂停中",IF($W113="已解约","已解约","")))) | Z113: =IF(TRIM($B113&$C113)="","",TRIM(IF($AA113="","",IF($AA113<TODAY(),"年检已过期"&(TODAY()-$AA113)&"天 ",IF($AA113-TODAY()<=提醒天数,"年检剩"&($AA113-TODAY())&"天 ","")))&IF($AB113="","",IF($AB113<TODAY(),"限速器已过期"&(TODAY()-$AB113)&"天 ",IF($AB113-TODAY()<=提醒天数,"限速器剩"&($AB113-TODAY())&"天 ","")))&IF($AC113="","",IF($AC113<TODAY(),"载重试验已过期"&(TODAY()-$AC113)&"天 ",IF($AC113-TODAY()<=提醒天数,"载重试验剩"&($AC113-TODAY())&"天 ",""))))) | AA113: =IF(TRIM($Q113&"")="","",IF(ISNUMBER($Q113),IF($Q113>10000,$Q113,IFERROR(DATE(INT($Q113),IF(ROUND(MOD($Q113,1)*100,0)>12,ROUND(MOD($Q113,1)*10,0),ROUND(MOD($Q113,1)*100,0))+1,0),"")),IFERROR(IF(LEN($Q113)-LEN(SUBSTITUTE($Q113,".",""))>=2,DATEVALUE(SUBSTITUTE(TRIM($Q113),".","-")),DATE(VALUE(LEFT(TRIM($Q113),4)),VALUE(MID(TRIM($Q113),6,2))+1,0)),""))) | AB113: =IF(TRIM($S113&"")="","",IF(ISNUMBER($S113),IF($S113>10000,$S113,IFERROR(DATE(INT($S113),IF(ROUND(MOD($S113,1)*100,0)>12,ROUND(MOD($S113,1)*10,0),ROUND(MOD($S113,1)*100,0))+1,0),"")),IFERROR(IF(LEN($S113)-LEN(SUBSTITUTE($S113,".",""))>=2,DATEVALUE(SUBSTITUTE(TRIM($S113),".","-")),DATE(VALUE(LEFT(TRIM($S113),4)),VALUE(MID(TRIM($S113),6,2))+1,0)),""))) | AC113: =IF(TRIM($T113&"")="","",IF(ISNUMBER($T113),IF($T113>10000,$T113,IFERROR(DATE(INT($T113),IF(ROUND(MOD($T113,1)*100,0)>12,ROUND(MOD($T113,1)*10,0),ROUND(MOD($T113,1)*100,0))+1,0),"")),IFERROR(IF(LEN($T113)-LEN(SUBSTITUTE($T113,".",""))>=2,DATEVALUE(SUBSTITUTE(TRIM($T113),".","-")),DATE(VALUE(LEFT(TRIM($T113),4)),VALUE(MID(TRIM($T113),6,2))+1,0)),"")))
B114: 武汉中海联机电工程有限公司 | C114: 花桥一村18号（李青） | D114: KLW | E114: 31104201022022080029 | G114: 康力电梯 | H114: 客梯 | I114: 7 | J114: 6 | K114: 6 | L114: 800kg | M114: 1.0m/s | N114: 1 | O114: 10063446-0010 | P114: 1#客 | Y114: =IF(TRIM($B114&$C114)="","",IF(OR($W114="安装免保",$W114="技术免保",$W114="质保期内"),IF(NOT(ISNUMBER($X114)),"▲免保到期日没填",IF($X114<TODAY(),"▲免保已到期，转收费",IF($X114-TODAY()<=提醒天数,"免保剩"&($X114-TODAY())&"天","免保中"))),IF($W114="暂停维保","暂停中",IF($W114="已解约","已解约","")))) | Z114: =IF(TRIM($B114&$C114)="","",TRIM(IF($AA114="","",IF($AA114<TODAY(),"年检已过期"&(TODAY()-$AA114)&"天 ",IF($AA114-TODAY()<=提醒天数,"年检剩"&($AA114-TODAY())&"天 ","")))&IF($AB114="","",IF($AB114<TODAY(),"限速器已过期"&(TODAY()-$AB114)&"天 ",IF($AB114-TODAY()<=提醒天数,"限速器剩"&($AB114-TODAY())&"天 ","")))&IF($AC114="","",IF($AC114<TODAY(),"载重试验已过期"&(TODAY()-$AC114)&"天 ",IF($AC114-TODAY()<=提醒天数,"载重试验剩"&($AC114-TODAY())&"天 ",""))))) | AA114: =IF(TRIM($Q114&"")="","",IF(ISNUMBER($Q114),IF($Q114>10000,$Q114,IFERROR(DATE(INT($Q114),IF(ROUND(MOD($Q114,1)*100,0)>12,ROUND(MOD($Q114,1)*10,0),ROUND(MOD($Q114,1)*100,0))+1,0),"")),IFERROR(IF(LEN($Q114)-LEN(SUBSTITUTE($Q114,".",""))>=2,DATEVALUE(SUBSTITUTE(TRIM($Q114),".","-")),DATE(VALUE(LEFT(TRIM($Q114),4)),VALUE(MID(TRIM($Q114),6,2))+1,0)),""))) | AB114: =IF(TRIM($S114&"")="","",IF(ISNUMBER($S114),IF($S114>10000,$S114,IFERROR(DATE(INT($S114),IF(ROUND(MOD($S114,1)*100,0)>12,ROUND(MOD($S114,1)*10,0),ROUND(MOD($S114,1)*100,0))+1,0),"")),IFERROR(IF(LEN($S114)-LEN(SUBSTITUTE($S114,".",""))>=2,DATEVALUE(SUBSTITUTE(TRIM($S114),".","-")),DATE(VALUE(LEFT(TRIM($S114),4)),VALUE(MID(TRIM($S114),6,2))+1,0)),""))) | AC114: =IF(TRIM($T114&"")="","",IF(ISNUMBER($T114),IF($T114>10000,$T114,IFERROR(DATE(INT($T114),IF(ROUND(MOD($T114,1)*100,0)>12,ROUND(MOD($T114,1)*10,0),ROUND(MOD($T114,1)*100,0))+1,0),"")),IFERROR(IF(LEN($T114)-LEN(SUBSTITUTE($T114,".",""))>=2,DATEVALUE(SUBSTITUTE(TRIM($T114),".","-")),DATE(VALUE(LEFT(TRIM($T114),4)),VALUE(MID(TRIM($T114),6,2))+1,0)),"")))
B115: 武汉君派创新科技有限公司 | C115: 江夏金地威新9-3栋 | D115: MEGA-F | E115: 31204201152022100003 | G115: 住友富士 | H115: 客梯 | I115: 4 | J115: 4 | K115: 4 | L115: 3000kg | M115: 0.5m/s | N115: 1 | O115: 907257 | P115: 9号厂房 | Y115: =IF(TRIM($B115&$C115)="","",IF(OR($W115="安装免保",$W115="技术免保",$W115="质保期内"),IF(NOT(ISNUMBER($X115)),"▲免保到期日没填",IF($X115<TODAY(),"▲免保已到期，转收费",IF($X115-TODAY()<=提醒天数,"免保剩"&($X115-TODAY())&"天","免保中"))),IF($W115="暂停维保","暂停中",IF($W115="已解约","已解约","")))) | Z115: =IF(TRIM($B115&$C115)="","",TRIM(IF($AA115="","",IF($AA115<TODAY(),"年检已过期"&(TODAY()-$AA115)&"天 ",IF($AA115-TODAY()<=提醒天数,"年检剩"&($AA115-TODAY())&"天 ","")))&IF($AB115="","",IF($AB115<TODAY(),"限速器已过期"&(TODAY()-$AB115)&"天 ",IF($AB115-TODAY()<=提醒天数,"限速器剩"&($AB115-TODAY())&"天 ","")))&IF($AC115="","",IF($AC115<TODAY(),"载重试验已过期"&(TODAY()-$AC115)&"天 ",IF($AC115-TODAY()<=提醒天数,"载重试验剩"&($AC115-TODAY())&"天 ",""))))) | AA115: =IF(TRIM($Q115&"")="","",IF(ISNUMBER($Q115),IF($Q115>10000,$Q115,IFERROR(DATE(INT($Q115),IF(ROUND(MOD($Q115,1)*100,0)>12,ROUND(MOD($Q115,1)*10,0),ROUND(MOD($Q115,1)*100,0))+1,0),"")),IFERROR(IF(LEN($Q115)-LEN(SUBSTITUTE($Q115,".",""))>=2,DATEVALUE(SUBSTITUTE(TRIM($Q115),".","-")),DATE(VALUE(LEFT(TRIM($Q115),4)),VALUE(MID(TRIM($Q115),6,2))+1,0)),""))) | AB115: =IF(TRIM($S115&"")="","",IF(ISNUMBER($S115),IF($S115>10000,$S115,IFERROR(DATE(INT($S115),IF(ROUND(MOD($S115,1)*100,0)>12,ROUND(MOD($S115,1)*10,0),ROUND(MOD($S115,1)*100,0))+1,0),"")),IFERROR(IF(LEN($S115)-LEN(SUBSTITUTE($S115,".",""))>=2,DATEVALUE(SUBSTITUTE(TRIM($S115),".","-")),DATE(VALUE(LEFT(TRIM($S115),4)),VALUE(MID(TRIM($S115),6,2))+1,0)),""))) | AC115: =IF(TRIM($T115&"")="","",IF(ISNUMBER($T115),IF($T115>10000,$T115,IFERROR(DATE(INT($T115),IF(ROUND(MOD($T115,1)*100,0)>12,ROUND(MOD($T115,1)*10,0),ROUND(MOD($T115,1)*100,0))+1,0),"")),IFERROR(IF(LEN($T115)-LEN(SUBSTITUTE($T115,".",""))>=2,DATEVALUE(SUBSTITUTE(TRIM($T115),".","-")),DATE(VALUE(LEFT(TRIM($T115),4)),VALUE(MID(TRIM($T115),6,2))+1,0)),"")))
B116: 武汉中海联机电工程有限公司 | C116: 花桥一村25号（张锋） | D116: GPN65 | E116: 31104201022023010018 | G116: 巨人通力电梯 | H116: 客梯(无机房) | I116: 7 | J116: 6 | K116: 6 | L116: 800kg | M116: 1.0m/s | N116: 1 | O116: 45012742 | P116: 25-1#客梯 | Y116: =IF(TRIM($B116&$C116)="","",IF(OR($W116="安装免保",$W116="技术免保",$W116="质保期内"),IF(NOT(ISNUMBER($X116)),"▲免保到期日没填",IF($X116<TODAY(),"▲免保已到期，转收费",IF($X116-TODAY()<=提醒天数,"免保剩"&($X116-TODAY())&"天","免保中"))),IF($W116="暂停维保","暂停中",IF($W116="已解约","已解约","")))) | Z116: =IF(TRIM($B116&$C116)="","",TRIM(IF($AA116="","",IF($AA116<TODAY(),"年检已过期"&(TODAY()-$AA116)&"天 ",IF($AA116-TODAY()<=提醒天数,"年检剩"&($AA116-TODAY())&"天 ","")))&IF($AB116="","",IF($AB116<TODAY(),"限速器已过期"&(TODAY()-$AB116)&"天 ",IF($AB116-TODAY()<=提醒天数,"限速器剩"&($AB116-TODAY())&"天 ","")))&IF($AC116="","",IF($AC116<TODAY(),"载重试验已过期"&(TODAY()-$AC116)&"天 ",IF($AC116-TODAY()<=提醒天数,"载重试验剩"&($AC116-TODAY())&"天 ",""))))) | AA116: =IF(TRIM($Q116&"")="","",IF(ISNUMBER($Q116),IF($Q116>10000,$Q116,IFERROR(DATE(INT($Q116),IF(ROUND(MOD($Q116,1)*100,0)>12,ROUND(MOD($Q116,1)*10,0),ROUND(MOD($Q116,1)*100,0))+1,0),"")),IFERROR(IF(LEN($Q116)-LEN(SUBSTITUTE($Q116,".",""))>=2,DATEVALUE(SUBSTITUTE(TRIM($Q116),".","-")),DATE(VALUE(LEFT(TRIM($Q116),4)),VALUE(MID(TRIM($Q116),6,2))+1,0)),""))) | AB116: =IF(TRIM($S116&"")="","",IF(ISNUMBER($S116),IF($S116>10000,$S116,IFERROR(DATE(INT($S116),IF(ROUND(MOD($S116,1)*100,0)>12,ROUND(MOD($S116,1)*10,0),ROUND(MOD($S116,1)*100,0))+1,0),"")),IFERROR(IF(LEN($S116)-LEN(SUBSTITUTE($S116,".",""))>=2,DATEVALUE(SUBSTITUTE(TRIM($S116),".","-")),DATE(VALUE(LEFT(TRIM($S116),4)),VALUE(MID(TRIM($S116),6,2))+1,0)),""))) | AC116: =IF(TRIM($T116&"")="","",IF(ISNUMBER($T116),IF($T116>10000,$T116,IFERROR(DATE(INT($T116),IF(ROUND(MOD($T116,1)*100,0)>12,ROUND(MOD($T116,1)*10,0),ROUND(MOD($T116,1)*100,0))+1,0),"")),IFERROR(IF(LEN($T116)-LEN(SUBSTITUTE($T116,".",""))>=2,DATEVALUE(SUBSTITUTE(TRIM($T116),".","-")),DATE(VALUE(LEFT(TRIM($T116),4)),VALUE(MID(TRIM($T116),6,2))+1,0)),"")))
B117: 湖北慧科检测有限公司 | C117: 江夏金地威新9-4栋 | D117: G.plus | E117: 31104201152022080029 | G117: 广州广日 | H117: 客梯 | I117: 4 | J117: 4 | K117: 4 | L117: 1050kg | M117: 1.0m/s | N117: 1 | O117: 22T49838001 | P117: 厂房1#客 | Y117: =IF(TRIM($B117&$C117)="","",IF(OR($W117="安装免保",$W117="技术免保",$W117="质保期内"),IF(NOT(ISNUMBER($X117)),"▲免保到期日没填",IF($X117<TODAY(),"▲免保已到期，转收费",IF($X117-TODAY()<=提醒天数,"免保剩"&($X117-TODAY())&"天","免保中"))),IF($W117="暂停维保","暂停中",IF($W117="已解约","已解约","")))) | Z117: =IF(TRIM($B117&$C117)="","",TRIM(IF($AA117="","",IF($AA117<TODAY(),"年检已过期"&(TODAY()-$AA117)&"天 ",IF($AA117-TODAY()<=提醒天数,"年检剩"&($AA117-TODAY())&"天 ","")))&IF($AB117="","",IF($AB117<TODAY(),"限速器已过期"&(TODAY()-$AB117)&"天 ",IF($AB117-TODAY()<=提醒天数,"限速器剩"&($AB117-TODAY())&"天 ","")))&IF($AC117="","",IF($AC117<TODAY(),"载重试验已过期"&(TODAY()-$AC117)&"天 ",IF($AC117-TODAY()<=提醒天数,"载重试验剩"&($AC117-TODAY())&"天 ",""))))) | AA117: =IF(TRIM($Q117&"")="","",IF(ISNUMBER($Q117),IF($Q117>10000,$Q117,IFERROR(DATE(INT($Q117),IF(ROUND(MOD($Q117,1)*100,0)>12,ROUND(MOD($Q117,1)*10,0),ROUND(MOD($Q117,1)*100,0))+1,0),"")),IFERROR(IF(LEN($Q117)-LEN(SUBSTITUTE($Q117,".",""))>=2,DATEVALUE(SUBSTITUTE(TRIM($Q117),".","-")),DATE(VALUE(LEFT(TRIM($Q117),4)),VALUE(MID(TRIM($Q117),6,2))+1,0)),""))) | AB117: =IF(TRIM($S117&"")="","",IF(ISNUMBER($S117),IF($S117>10000,$S117,IFERROR(DATE(INT($S117),IF(ROUND(MOD($S117,1)*100,0)>12,ROUND(MOD($S117,1)*10,0),ROUND(MOD($S117,1)*100,0))+1,0),"")),IFERROR(IF(LEN($S117)-LEN(SUBSTITUTE($S117,".",""))>=2,DATEVALUE(SUBSTITUTE(TRIM($S117),".","-")),DATE(VALUE(LEFT(TRIM($S117),4)),VALUE(MID(TRIM($S117),6,2))+1,0)),""))) | AC117: =IF(TRIM($T117&"")="","",IF(ISNUMBER($T117),IF($T117>10000,$T117,IFERROR(DATE(INT($T117),IF(ROUND(MOD($T117,1)*100,0)>12,ROUND(MOD($T117,1)*10,0),ROUND(MOD($T117,1)*100,0))+1,0),"")),IFERROR(IF(LEN($T117)-LEN(SUBSTITUTE($T117,".",""))>=2,DATEVALUE(SUBSTITUTE(TRIM($T117),".","-")),DATE(VALUE(LEFT(TRIM($T117),4)),VALUE(MID(TRIM($T117),6,2))+1,0)),"")))
B118: 武汉和颐旅馆有限责任公司 | C118: 铁神宜尚酒店 | D118: GLP500 | E118: 31104201012022075318 | F118: 165703 | G118: 巨龙电梯 | I118: 3 | J118: 3 | K118: 3 | L118: 800kg | M118: 1.0m/s | N118: 1 | O118: 011861 | P118: L1#客 | Y118: =IF(TRIM($B118&$C118)="","",IF(OR($W118="安装免保",$W118="技术免保",$W118="质保期内"),IF(NOT(ISNUMBER($X118)),"▲免保到期日没填",IF($X118<TODAY(),"▲免保已到期，转收费",IF($X118-TODAY()<=提醒天数,"免保剩"&($X118-TODAY())&"天","免保中"))),IF($W118="暂停维保","暂停中",IF($W118="已解约","已解约","")))) | Z118: =IF(TRIM($B118&$C118)="","",TRIM(IF($AA118="","",IF($AA118<TODAY(),"年检已过期"&(TODAY()-$AA118)&"天 ",IF($AA118-TODAY()<=提醒天数,"年检剩"&($AA118-TODAY())&"天 ","")))&IF($AB118="","",IF($AB118<TODAY(),"限速器已过期"&(TODAY()-$AB118)&"天 ",IF($AB118-TODAY()<=提醒天数,"限速器剩"&($AB118-TODAY())&"天 ","")))&IF($AC118="","",IF($AC118<TODAY(),"载重试验已过期"&(TODAY()-$AC118)&"天 ",IF($AC118-TODAY()<=提醒天数,"载重试验剩"&($AC118-TODAY())&"天 ",""))))) | AA118: =IF(TRIM($Q118&"")="","",IF(ISNUMBER($Q118),IF($Q118>10000,$Q118,IFERROR(DATE(INT($Q118),IF(ROUND(MOD($Q118,1)*100,0)>12,ROUND(MOD($Q118,1)*10,0),ROUND(MOD($Q118,1)*100,0))+1,0),"")),IFERROR(IF(LEN($Q118)-LEN(SUBSTITUTE($Q118,".",""))>=2,DATEVALUE(SUBSTITUTE(TRIM($Q118),".","-")),DATE(VALUE(LEFT(TRIM($Q118),4)),VALUE(MID(TRIM($Q118),6,2))+1,0)),""))) | AB118: =IF(TRIM($S118&"")="","",IF(ISNUMBER($S118),IF($S118>10000,$S118,IFERROR(DATE(INT($S118),IF(ROUND(MOD($S118,1)*100,0)>12,ROUND(MOD($S118,1)*10,0),ROUND(MOD($S118,1)*100,0))+1,0),"")),IFERROR(IF(LEN($S118)-LEN(SUBSTITUTE($S118,".",""))>=2,DATEVALUE(SUBSTITUTE(TRIM($S118),".","-")),DATE(VALUE(LEFT(TRIM($S118),4)),VALUE(MID(TRIM($S118),6,2))+1,0)),""))) | AC118: =IF(TRIM($T118&"")="","",IF(ISNUMBER($T118),IF($T118>10000,$T118,IFERROR(DATE(INT($T118),IF(ROUND(MOD($T118,1)*100,0)>12,ROUND(MOD($T118,1)*10,0),ROUND(MOD($T118,1)*100,0))+1,0),"")),IFERROR(IF(LEN($T118)-LEN(SUBSTITUTE($T118,".",""))>=2,DATEVALUE(SUBSTITUTE(TRIM($T118),".","-")),DATE(VALUE(LEFT(TRIM($T118),4)),VALUE(MID(TRIM($T118),6,2))+1,0)),"")))
B119: 武汉十三堡慈苑农业专业合作社 | C119: 原雄一风 | D119: MEGA-F | E119: 31204201162023090030 | F119: 075878 | G119: 住友富士 | H119: 货梯 | I119: 5 | J119: 5 | K119: 5 | L119: 1600kg | M119: 0.5m/s | N119: 1 | O119: 308106 | P119: 1#货梯 | Y119: =IF(TRIM($B119&$C119)="","",IF(OR($W119="安装免保",$W119="技术免保",$W119="质保期内"),IF(NOT(ISNUMBER($X119)),"▲免保到期日没填",IF($X119<TODAY(),"▲免保已到期，转收费",IF($X119-TODAY()<=提醒天数,"免保剩"&($X119-TODAY())&"天","免保中"))),IF($W119="暂停维保","暂停中",IF($W119="已解约","已解约","")))) | Z119: =IF(TRIM($B119&$C119)="","",TRIM(IF($AA119="","",IF($AA119<TODAY(),"年检已过期"&(TODAY()-$AA119)&"天 ",IF($AA119-TODAY()<=提醒天数,"年检剩"&($AA119-TODAY())&"天 ","")))&IF($AB119="","",IF($AB119<TODAY(),"限速器已过期"&(TODAY()-$AB119)&"天 ",IF($AB119-TODAY()<=提醒天数,"限速器剩"&($AB119-TODAY())&"天 ","")))&IF($AC119="","",IF($AC119<TODAY(),"载重试验已过期"&(TODAY()-$AC119)&"天 ",IF($AC119-TODAY()<=提醒天数,"载重试验剩"&($AC119-TODAY())&"天 ",""))))) | AA119: =IF(TRIM($Q119&"")="","",IF(ISNUMBER($Q119),IF($Q119>10000,$Q119,IFERROR(DATE(INT($Q119),IF(ROUND(MOD($Q119,1)*100,0)>12,ROUND(MOD($Q119,1)*10,0),ROUND(MOD($Q119,1)*100,0))+1,0),"")),IFERROR(IF(LEN($Q119)-LEN(SUBSTITUTE($Q119,".",""))>=2,DATEVALUE(SUBSTITUTE(TRIM($Q119),".","-")),DATE(VALUE(LEFT(TRIM($Q119),4)),VALUE(MID(TRIM($Q119),6,2))+1,0)),""))) | AB119: =IF(TRIM($S119&"")="","",IF(ISNUMBER($S119),IF($S119>10000,$S119,IFERROR(DATE(INT($S119),IF(ROUND(MOD($S119,1)*100,0)>12,ROUND(MOD($S119,1)*10,0),ROUND(MOD($S119,1)*100,0))+1,0),"")),IFERROR(IF(LEN($S119)-LEN(SUBSTITUTE($S119,".",""))>=2,DATEVALUE(SUBSTITUTE(TRIM($S119),".","-")),DATE(VALUE(LEFT(TRIM($S119),4)),VALUE(MID(TRIM($S119),6,2))+1,0)),""))) | AC119: =IF(TRIM($T119&"")="","",IF(ISNUMBER($T119),IF($T119>10000,$T119,IFERROR(DATE(INT($T119),IF(ROUND(MOD($T119,1)*100,0)>12,ROUND(MOD($T119,1)*10,0),ROUND(MOD($T119,1)*100,0))+1,0),"")),IFERROR(IF(LEN($T119)-LEN(SUBSTITUTE($T119,".",""))>=2,DATEVALUE(SUBSTITUTE(TRIM($T119),".","-")),DATE(VALUE(LEFT(TRIM($T119),4)),VALUE(MID(TRIM($T119),6,2))+1,0)),"")))
B120: 武汉中海联机电工程有限公司 | C120: 滨江苑一期11栋3单元 | D120: WJK | E120: 31104201022023090025 | F120: 192359 | G120: 福州快科电梯 | H120: 客梯(无机房) | I120: 7 | J120: 6 | K120: 6 | L120: 1000kg | M120: 1.0m/s | N120: 1 | O120: K.E30-2300157 | P120: 1#客 | Y120: =IF(TRIM($B120&$C120)="","",IF(OR($W120="安装免保",$W120="技术免保",$W120="质保期内"),IF(NOT(ISNUMBER($X120)),"▲免保到期日没填",IF($X120<TODAY(),"▲免保已到期，转收费",IF($X120-TODAY()<=提醒天数,"免保剩"&($X120-TODAY())&"天","免保中"))),IF($W120="暂停维保","暂停中",IF($W120="已解约","已解约","")))) | Z120: =IF(TRIM($B120&$C120)="","",TRIM(IF($AA120="","",IF($AA120<TODAY(),"年检已过期"&(TODAY()-$AA120)&"天 ",IF($AA120-TODAY()<=提醒天数,"年检剩"&($AA120-TODAY())&"天 ","")))&IF($AB120="","",IF($AB120<TODAY(),"限速器已过期"&(TODAY()-$AB120)&"天 ",IF($AB120-TODAY()<=提醒天数,"限速器剩"&($AB120-TODAY())&"天 ","")))&IF($AC120="","",IF($AC120<TODAY(),"载重试验已过期"&(TODAY()-$AC120)&"天 ",IF($AC120-TODAY()<=提醒天数,"载重试验剩"&($AC120-TODAY())&"天 ",""))))) | AA120: =IF(TRIM($Q120&"")="","",IF(ISNUMBER($Q120),IF($Q120>10000,$Q120,IFERROR(DATE(INT($Q120),IF(ROUND(MOD($Q120,1)*100,0)>12,ROUND(MOD($Q120,1)*10,0),ROUND(MOD($Q120,1)*100,0))+1,0),"")),IFERROR(IF(LEN($Q120)-LEN(SUBSTITUTE($Q120,".",""))>=2,DATEVALUE(SUBSTITUTE(TRIM($Q120),".","-")),DATE(VALUE(LEFT(TRIM($Q120),4)),VALUE(MID(TRIM($Q120),6,2))+1,0)),""))) | AB120: =IF(TRIM($S120&"")="","",IF(ISNUMBER($S120),IF($S120>10000,$S120,IFERROR(DATE(INT($S120),IF(ROUND(MOD($S120,1)*100,0)>12,ROUND(MOD($S120,1)*10,0),ROUND(MOD($S120,1)*100,0))+1,0),"")),IFERROR(IF(LEN($S120)-LEN(SUBSTITUTE($S120,".",""))>=2,DATEVALUE(SUBSTITUTE(TRIM($S120),".","-")),DATE(VALUE(LEFT(TRIM($S120),4)),VALUE(MID(TRIM($S120),6,2))+1,0)),""))) | AC120: =IF(TRIM($T120&"")="","",IF(ISNUMBER($T120),IF($T120>10000,$T120,IFERROR(DATE(INT($T120),IF(ROUND(MOD($T120,1)*100,0)>12,ROUND(MOD($T120,1)*10,0),ROUND(MOD($T120,1)*100,0))+1,0),"")),IFERROR(IF(LEN($T120)-LEN(SUBSTITUTE($T120,".",""))>=2,DATEVALUE(SUBSTITUTE(TRIM($T120),".","-")),DATE(VALUE(LEFT(TRIM($T120),4)),VALUE(MID(TRIM($T120),6,2))+1,0)),"")))
B121: 武汉中海联机电工程有限公司 | C121: 滨江苑一期5栋 | D121: KLW | E121: 31104201022023110041 | F121: 192361 | G121: 康力电梯 | H121: 客梯(无机房) | I121: 6 | J121: 6 | K121: 6 | L121: 1050kg | M121: 1.0m/s | N121: 1 | O121: 10073007-0010 | P121: 1#客梯 | Y121: =IF(TRIM($B121&$C121)="","",IF(OR($W121="安装免保",$W121="技术免保",$W121="质保期内"),IF(NOT(ISNUMBER($X121)),"▲免保到期日没填",IF($X121<TODAY(),"▲免保已到期，转收费",IF($X121-TODAY()<=提醒天数,"免保剩"&($X121-TODAY())&"天","免保中"))),IF($W121="暂停维保","暂停中",IF($W121="已解约","已解约","")))) | Z121: =IF(TRIM($B121&$C121)="","",TRIM(IF($AA121="","",IF($AA121<TODAY(),"年检已过期"&(TODAY()-$AA121)&"天 ",IF($AA121-TODAY()<=提醒天数,"年检剩"&($AA121-TODAY())&"天 ","")))&IF($AB121="","",IF($AB121<TODAY(),"限速器已过期"&(TODAY()-$AB121)&"天 ",IF($AB121-TODAY()<=提醒天数,"限速器剩"&($AB121-TODAY())&"天 ","")))&IF($AC121="","",IF($AC121<TODAY(),"载重试验已过期"&(TODAY()-$AC121)&"天 ",IF($AC121-TODAY()<=提醒天数,"载重试验剩"&($AC121-TODAY())&"天 ",""))))) | AA121: =IF(TRIM($Q121&"")="","",IF(ISNUMBER($Q121),IF($Q121>10000,$Q121,IFERROR(DATE(INT($Q121),IF(ROUND(MOD($Q121,1)*100,0)>12,ROUND(MOD($Q121,1)*10,0),ROUND(MOD($Q121,1)*100,0))+1,0),"")),IFERROR(IF(LEN($Q121)-LEN(SUBSTITUTE($Q121,".",""))>=2,DATEVALUE(SUBSTITUTE(TRIM($Q121),".","-")),DATE(VALUE(LEFT(TRIM($Q121),4)),VALUE(MID(TRIM($Q121),6,2))+1,0)),""))) | AB121: =IF(TRIM($S121&"")="","",IF(ISNUMBER($S121),IF($S121>10000,$S121,IFERROR(DATE(INT($S121),IF(ROUND(MOD($S121,1)*100,0)>12,ROUND(MOD($S121,1)*10,0),ROUND(MOD($S121,1)*100,0))+1,0),"")),IFERROR(IF(LEN($S121)-LEN(SUBSTITUTE($S121,".",""))>=2,DATEVALUE(SUBSTITUTE(TRIM($S121),".","-")),DATE(VALUE(LEFT(TRIM($S121),4)),VALUE(MID(TRIM($S121),6,2))+1,0)),""))) | AC121: =IF(TRIM($T121&"")="","",IF(ISNUMBER($T121),IF($T121>10000,$T121,IFERROR(DATE(INT($T121),IF(ROUND(MOD($T121,1)*100,0)>12,ROUND(MOD($T121,1)*10,0),ROUND(MOD($T121,1)*100,0))+1,0),"")),IFERROR(IF(LEN($T121)-LEN(SUBSTITUTE($T121,".",""))>=2,DATEVALUE(SUBSTITUTE(TRIM($T121),".","-")),DATE(VALUE(LEFT(TRIM($T121),4)),VALUE(MID(TRIM($T121),6,2))+1,0)),"")))
B122: 武汉中海联机电工程有限公司 | C122: 滨江苑一期4栋（原龚翠红） | D122: KLW | E122: 31104201022022010029 | F122: 137224 | G122: 康力电梯 | H122: 客梯(无机房) | I122: 7 | J122: 12 | K122: 12 | L122: 1050kg | M122: 1.0m/s | N122: 1 | O122: 10059069-0010 | P122: 1#客 | Y122: =IF(TRIM($B122&$C122)="","",IF(OR($W122="安装免保",$W122="技术免保",$W122="质保期内"),IF(NOT(ISNUMBER($X122)),"▲免保到期日没填",IF($X122<TODAY(),"▲免保已到期，转收费",IF($X122-TODAY()<=提醒天数,"免保剩"&($X122-TODAY())&"天","免保中"))),IF($W122="暂停维保","暂停中",IF($W122="已解约","已解约","")))) | Z122: =IF(TRIM($B122&$C122)="","",TRIM(IF($AA122="","",IF($AA122<TODAY(),"年检已过期"&(TODAY()-$AA122)&"天 ",IF($AA122-TODAY()<=提醒天数,"年检剩"&($AA122-TODAY())&"天 ","")))&IF($AB122="","",IF($AB122<TODAY(),"限速器已过期"&(TODAY()-$AB122)&"天 ",IF($AB122-TODAY()<=提醒天数,"限速器剩"&($AB122-TODAY())&"天 ","")))&IF($AC122="","",IF($AC122<TODAY(),"载重试验已过期"&(TODAY()-$AC122)&"天 ",IF($AC122-TODAY()<=提醒天数,"载重试验剩"&($AC122-TODAY())&"天 ",""))))) | AA122: =IF(TRIM($Q122&"")="","",IF(ISNUMBER($Q122),IF($Q122>10000,$Q122,IFERROR(DATE(INT($Q122),IF(ROUND(MOD($Q122,1)*100,0)>12,ROUND(MOD($Q122,1)*10,0),ROUND(MOD($Q122,1)*100,0))+1,0),"")),IFERROR(IF(LEN($Q122)-LEN(SUBSTITUTE($Q122,".",""))>=2,DATEVALUE(SUBSTITUTE(TRIM($Q122),".","-")),DATE(VALUE(LEFT(TRIM($Q122),4)),VALUE(MID(TRIM($Q122),6,2))+1,0)),""))) | AB122: =IF(TRIM($S122&"")="","",IF(ISNUMBER($S122),IF($S122>10000,$S122,IFERROR(DATE(INT($S122),IF(ROUND(MOD($S122,1)*100,0)>12,ROUND(MOD($S122,1)*10,0),ROUND(MOD($S122,1)*100,0))+1,0),"")),IFERROR(IF(LEN($S122)-LEN(SUBSTITUTE($S122,".",""))>=2,DATEVALUE(SUBSTITUTE(TRIM($S122),".","-")),DATE(VALUE(LEFT(TRIM($S122),4)),VALUE(MID(TRIM($S122),6,2))+1,0)),""))) | AC122: =IF(TRIM($T122&"")="","",IF(ISNUMBER($T122),IF($T122>10000,$T122,IFERROR(DATE(INT($T122),IF(ROUND(MOD($T122,1)*100,0)>12,ROUND(MOD($T122,1)*10,0),ROUND(MOD($T122,1)*100,0))+1,0),"")),IFERROR(IF(LEN($T122)-LEN(SUBSTITUTE($T122,".",""))>=2,DATEVALUE(SUBSTITUTE(TRIM($T122),".","-")),DATE(VALUE(LEFT(TRIM($T122),4)),VALUE(MID(TRIM($T122),6,2))+1,0)),"")))
B123: 武汉中海联机电工程有限公司 | C123: 滨江苑一期9栋3单元 | D123: GPN65 | E123: 31104201022023110040 | F123: 192360 | G123: 巨人通力电梯 | H123: 客梯(无机房) | I123: 8 | J123: 7 | K123: 7 | L123: 1000kg | M123: 1.0m/s | N123: 1 | O123: 45049272 | P123: 1#客梯 | Y123: =IF(TRIM($B123&$C123)="","",IF(OR($W123="安装免保",$W123="技术免保",$W123="质保期内"),IF(NOT(ISNUMBER($X123)),"▲免保到期日没填",IF($X123<TODAY(),"▲免保已到期，转收费",IF($X123-TODAY()<=提醒天数,"免保剩"&($X123-TODAY())&"天","免保中"))),IF($W123="暂停维保","暂停中",IF($W123="已解约","已解约","")))) | Z123: =IF(TRIM($B123&$C123)="","",TRIM(IF($AA123="","",IF($AA123<TODAY(),"年检已过期"&(TODAY()-$AA123)&"天 ",IF($AA123-TODAY()<=提醒天数,"年检剩"&($AA123-TODAY())&"天 ","")))&IF($AB123="","",IF($AB123<TODAY(),"限速器已过期"&(TODAY()-$AB123)&"天 ",IF($AB123-TODAY()<=提醒天数,"限速器剩"&($AB123-TODAY())&"天 ","")))&IF($AC123="","",IF($AC123<TODAY(),"载重试验已过期"&(TODAY()-$AC123)&"天 ",IF($AC123-TODAY()<=提醒天数,"载重试验剩"&($AC123-TODAY())&"天 ",""))))) | AA123: =IF(TRIM($Q123&"")="","",IF(ISNUMBER($Q123),IF($Q123>10000,$Q123,IFERROR(DATE(INT($Q123),IF(ROUND(MOD($Q123,1)*100,0)>12,ROUND(MOD($Q123,1)*10,0),ROUND(MOD($Q123,1)*100,0))+1,0),"")),IFERROR(IF(LEN($Q123)-LEN(SUBSTITUTE($Q123,".",""))>=2,DATEVALUE(SUBSTITUTE(TRIM($Q123),".","-")),DATE(VALUE(LEFT(TRIM($Q123),4)),VALUE(MID(TRIM($Q123),6,2))+1,0)),""))) | AB123: =IF(TRIM($S123&"")="","",IF(ISNUMBER($S123),IF($S123>10000,$S123,IFERROR(DATE(INT($S123),IF(ROUND(MOD($S123,1)*100,0)>12,ROUND(MOD($S123,1)*10,0),ROUND(MOD($S123,1)*100,0))+1,0),"")),IFERROR(IF(LEN($S123)-LEN(SUBSTITUTE($S123,".",""))>=2,DATEVALUE(SUBSTITUTE(TRIM($S123),".","-")),DATE(VALUE(LEFT(TRIM($S123),4)),VALUE(MID(TRIM($S123),6,2))+1,0)),""))) | AC123: =IF(TRIM($T123&"")="","",IF(ISNUMBER($T123),IF($T123>10000,$T123,IFERROR(DATE(INT($T123),IF(ROUND(MOD($T123,1)*100,0)>12,ROUND(MOD($T123,1)*10,0),ROUND(MOD($T123,1)*100,0))+1,0),"")),IFERROR(IF(LEN($T123)-LEN(SUBSTITUTE($T123,".",""))>=2,DATEVALUE(SUBSTITUTE(TRIM($T123),".","-")),DATE(VALUE(LEFT(TRIM($T123),4)),VALUE(MID(TRIM($T123),6,2))+1,0)),"")))
B124: 武汉中海联机电工程有限公司 | C124: 滨江苑一期10栋4单元 | D124: GPN65 | E124: 31104201022024010047 | G124: 巨人通力电梯 | H124: 客梯(无机房) | I124: 8 | J124: 7 | K124: 7 | L124: 1000kg | M124: 1.0m/s | N124: 1 | O124: 45369661 | P124: 1#客梯 | Y124: =IF(TRIM($B124&$C124)="","",IF(OR($W124="安装免保",$W124="技术免保",$W124="质保期内"),IF(NOT(ISNUMBER($X124)),"▲免保到期日没填",IF($X124<TODAY(),"▲免保已到期，转收费",IF($X124-TODAY()<=提醒天数,"免保剩"&($X124-TODAY())&"天","免保中"))),IF($W124="暂停维保","暂停中",IF($W124="已解约","已解约","")))) | Z124: =IF(TRIM($B124&$C124)="","",TRIM(IF($AA124="","",IF($AA124<TODAY(),"年检已过期"&(TODAY()-$AA124)&"天 ",IF($AA124-TODAY()<=提醒天数,"年检剩"&($AA124-TODAY())&"天 ","")))&IF($AB124="","",IF($AB124<TODAY(),"限速器已过期"&(TODAY()-$AB124)&"天 ",IF($AB124-TODAY()<=提醒天数,"限速器剩"&($AB124-TODAY())&"天 ","")))&IF($AC124="","",IF($AC124<TODAY(),"载重试验已过期"&(TODAY()-$AC124)&"天 ",IF($AC124-TODAY()<=提醒天数,"载重试验剩"&($AC124-TODAY())&"天 ",""))))) | AA124: =IF(TRIM($Q124&"")="","",IF(ISNUMBER($Q124),IF($Q124>10000,$Q124,IFERROR(DATE(INT($Q124),IF(ROUND(MOD($Q124,1)*100,0)>12,ROUND(MOD($Q124,1)*10,0),ROUND(MOD($Q124,1)*100,0))+1,0),"")),IFERROR(IF(LEN($Q124)-LEN(SUBSTITUTE($Q124,".",""))>=2,DATEVALUE(SUBSTITUTE(TRIM($Q124),".","-")),DATE(VALUE(LEFT(TRIM($Q124),4)),VALUE(MID(TRIM($Q124),6,2))+1,0)),""))) | AB124: =IF(TRIM($S124&"")="","",IF(ISNUMBER($S124),IF($S124>10000,$S124,IFERROR(DATE(INT($S124),IF(ROUND(MOD($S124,1)*100,0)>12,ROUND(MOD($S124,1)*10,0),ROUND(MOD($S124,1)*100,0))+1,0),"")),IFERROR(IF(LEN($S124)-LEN(SUBSTITUTE($S124,".",""))>=2,DATEVALUE(SUBSTITUTE(TRIM($S124),".","-")),DATE(VALUE(LEFT(TRIM($S124),4)),VALUE(MID(TRIM($S124),6,2))+1,0)),""))) | AC124: =IF(TRIM($T124&"")="","",IF(ISNUMBER($T124),IF($T124>10000,$T124,IFERROR(DATE(INT($T124),IF(ROUND(MOD($T124,1)*100,0)>12,ROUND(MOD($T124,1)*10,0),ROUND(MOD($T124,1)*100,0))+1,0),"")),IFERROR(IF(LEN($T124)-LEN(SUBSTITUTE($T124,".",""))>=2,DATEVALUE(SUBSTITUTE(TRIM($T124),".","-")),DATE(VALUE(LEFT(TRIM($T124),4)),VALUE(MID(TRIM($T124),6,2))+1,0)),"")))
B125: 武汉中海联机电工程有限公司 | C125: 青青美庐东区5栋1单元 | D125: XO-REZO(MRL) | E125: 31104201022023110064 | F125: 192358 | G125: 杭州西奥电梯 | H125: 客梯(无机房) | I125: 7 | J125: 5 | K125: 5 | L125: 800kg | M125: 1.0m/s | N125: 1 | O125: XODTG19971 | P125: 1#客 | Y125: =IF(TRIM($B125&$C125)="","",IF(OR($W125="安装免保",$W125="技术免保",$W125="质保期内"),IF(NOT(ISNUMBER($X125)),"▲免保到期日没填",IF($X125<TODAY(),"▲免保已到期，转收费",IF($X125-TODAY()<=提醒天数,"免保剩"&($X125-TODAY())&"天","免保中"))),IF($W125="暂停维保","暂停中",IF($W125="已解约","已解约","")))) | Z125: =IF(TRIM($B125&$C125)="","",TRIM(IF($AA125="","",IF($AA125<TODAY(),"年检已过期"&(TODAY()-$AA125)&"天 ",IF($AA125-TODAY()<=提醒天数,"年检剩"&($AA125-TODAY())&"天 ","")))&IF($AB125="","",IF($AB125<TODAY(),"限速器已过期"&(TODAY()-$AB125)&"天 ",IF($AB125-TODAY()<=提醒天数,"限速器剩"&($AB125-TODAY())&"天 ","")))&IF($AC125="","",IF($AC125<TODAY(),"载重试验已过期"&(TODAY()-$AC125)&"天 ",IF($AC125-TODAY()<=提醒天数,"载重试验剩"&($AC125-TODAY())&"天 ",""))))) | AA125: =IF(TRIM($Q125&"")="","",IF(ISNUMBER($Q125),IF($Q125>10000,$Q125,IFERROR(DATE(INT($Q125),IF(ROUND(MOD($Q125,1)*100,0)>12,ROUND(MOD($Q125,1)*10,0),ROUND(MOD($Q125,1)*100,0))+1,0),"")),IFERROR(IF(LEN($Q125)-LEN(SUBSTITUTE($Q125,".",""))>=2,DATEVALUE(SUBSTITUTE(TRIM($Q125),".","-")),DATE(VALUE(LEFT(TRIM($Q125),4)),VALUE(MID(TRIM($Q125),6,2))+1,0)),""))) | AB125: =IF(TRIM($S125&"")="","",IF(ISNUMBER($S125),IF($S125>10000,$S125,IFERROR(DATE(INT($S125),IF(ROUND(MOD($S125,1)*100,0)>12,ROUND(MOD($S125,1)*10,0),ROUND(MOD($S125,1)*100,0))+1,0),"")),IFERROR(IF(LEN($S125)-LEN(SUBSTITUTE($S125,".",""))>=2,DATEVALUE(SUBSTITUTE(TRIM($S125),".","-")),DATE(VALUE(LEFT(TRIM($S125),4)),VALUE(MID(TRIM($S125),6,2))+1,0)),""))) | AC125: =IF(TRIM($T125&"")="","",IF(ISNUMBER($T125),IF($T125>10000,$T125,IFERROR(DATE(INT($T125),IF(ROUND(MOD($T125,1)*100,0)>12,ROUND(MOD($T125,1)*10,0),ROUND(MOD($T125,1)*100,0))+1,0),"")),IFERROR(IF(LEN($T125)-LEN(SUBSTITUTE($T125,".",""))>=2,DATEVALUE(SUBSTITUTE(TRIM($T125),".","-")),DATE(VALUE(LEFT(TRIM($T125),4)),VALUE(MID(TRIM($T125),6,2))+1,0)),"")))
B126: 武汉中海联机电工程有限公司 | C126: 生态花园小区22栋1单元 | D126: XO-REZO(MRL) | E126: 31104201022023110065 | F126: 192357 | G126: 杭州西奥电梯 | H126: 客梯(无机房) | I126: 7 | J126: 6 | K126: 6 | L126: 800kg | M126: 1.0m/s | N126: 1 | O126: XSDTS24497 | P126: 1#客 | Y126: =IF(TRIM($B126&$C126)="","",IF(OR($W126="安装免保",$W126="技术免保",$W126="质保期内"),IF(NOT(ISNUMBER($X126)),"▲免保到期日没填",IF($X126<TODAY(),"▲免保已到期，转收费",IF($X126-TODAY()<=提醒天数,"免保剩"&($X126-TODAY())&"天","免保中"))),IF($W126="暂停维保","暂停中",IF($W126="已解约","已解约","")))) | Z126: =IF(TRIM($B126&$C126)="","",TRIM(IF($AA126="","",IF($AA126<TODAY(),"年检已过期"&(TODAY()-$AA126)&"天 ",IF($AA126-TODAY()<=提醒天数,"年检剩"&($AA126-TODAY())&"天 ","")))&IF($AB126="","",IF($AB126<TODAY(),"限速器已过期"&(TODAY()-$AB126)&"天 ",IF($AB126-TODAY()<=提醒天数,"限速器剩"&($AB126-TODAY())&"天 ","")))&IF($AC126="","",IF($AC126<TODAY(),"载重试验已过期"&(TODAY()-$AC126)&"天 ",IF($AC126-TODAY()<=提醒天数,"载重试验剩"&($AC126-TODAY())&"天 ",""))))) | AA126: =IF(TRIM($Q126&"")="","",IF(ISNUMBER($Q126),IF($Q126>10000,$Q126,IFERROR(DATE(INT($Q126),IF(ROUND(MOD($Q126,1)*100,0)>12,ROUND(MOD($Q126,1)*10,0),ROUND(MOD($Q126,1)*100,0))+1,0),"")),IFERROR(IF(LEN($Q126)-LEN(SUBSTITUTE($Q126,".",""))>=2,DATEVALUE(SUBSTITUTE(TRIM($Q126),".","-")),DATE(VALUE(LEFT(TRIM($Q126),4)),VALUE(MID(TRIM($Q126),6,2))+1,0)),""))) | AB126: =IF(TRIM($S126&"")="","",IF(ISNUMBER($S126),IF($S126>10000,$S126,IFERROR(DATE(INT($S126),IF(ROUND(MOD($S126,1)*100,0)>12,ROUND(MOD($S126,1)*10,0),ROUND(MOD($S126,1)*100,0))+1,0),"")),IFERROR(IF(LEN($S126)-LEN(SUBSTITUTE($S126,".",""))>=2,DATEVALUE(SUBSTITUTE(TRIM($S126),".","-")),DATE(VALUE(LEFT(TRIM($S126),4)),VALUE(MID(TRIM($S126),6,2))+1,0)),""))) | AC126: =IF(TRIM($T126&"")="","",IF(ISNUMBER($T126),IF($T126>10000,$T126,IFERROR(DATE(INT($T126),IF(ROUND(MOD($T126,1)*100,0)>12,ROUND(MOD($T126,1)*10,0),ROUND(MOD($T126,1)*100,0))+1,0),"")),IFERROR(IF(LEN($T126)-LEN(SUBSTITUTE($T126,".",""))>=2,DATEVALUE(SUBSTITUTE(TRIM($T126),".","-")),DATE(VALUE(LEFT(TRIM($T126),4)),VALUE(MID(TRIM($T126),6,2))+1,0)),"")))
B127: 武汉中海联机电工程有限公司 | C127: 武装部宿舍1栋1 | D127: XO-REZO(MRL) | E127: 31104201022023110066 | G127: 杭州西奥电梯 | H127: 客梯(无机房) | I127: 8 | J127: 8 | K127: 8 | L127: 800kg | M127: 1.0m/s | N127: 1 | O127: XSDTS24498 | P127: 1#客 | Y127: =IF(TRIM($B127&$C127)="","",IF(OR($W127="安装免保",$W127="技术免保",$W127="质保期内"),IF(NOT(ISNUMBER($X127)),"▲免保到期日没填",IF($X127<TODAY(),"▲免保已到期，转收费",IF($X127-TODAY()<=提醒天数,"免保剩"&($X127-TODAY())&"天","免保中"))),IF($W127="暂停维保","暂停中",IF($W127="已解约","已解约","")))) | Z127: =IF(TRIM($B127&$C127)="","",TRIM(IF($AA127="","",IF($AA127<TODAY(),"年检已过期"&(TODAY()-$AA127)&"天 ",IF($AA127-TODAY()<=提醒天数,"年检剩"&($AA127-TODAY())&"天 ","")))&IF($AB127="","",IF($AB127<TODAY(),"限速器已过期"&(TODAY()-$AB127)&"天 ",IF($AB127-TODAY()<=提醒天数,"限速器剩"&($AB127-TODAY())&"天 ","")))&IF($AC127="","",IF($AC127<TODAY(),"载重试验已过期"&(TODAY()-$AC127)&"天 ",IF($AC127-TODAY()<=提醒天数,"载重试验剩"&($AC127-TODAY())&"天 ",""))))) | AA127: =IF(TRIM($Q127&"")="","",IF(ISNUMBER($Q127),IF($Q127>10000,$Q127,IFERROR(DATE(INT($Q127),IF(ROUND(MOD($Q127,1)*100,0)>12,ROUND(MOD($Q127,1)*10,0),ROUND(MOD($Q127,1)*100,0))+1,0),"")),IFERROR(IF(LEN($Q127)-LEN(SUBSTITUTE($Q127,".",""))>=2,DATEVALUE(SUBSTITUTE(TRIM($Q127),".","-")),DATE(VALUE(LEFT(TRIM($Q127),4)),VALUE(MID(TRIM($Q127),6,2))+1,0)),""))) | AB127: =IF(TRIM($S127&"")="","",IF(ISNUMBER($S127),IF($S127>10000,$S127,IFERROR(DATE(INT($S127),IF(ROUND(MOD($S127,1)*100,0)>12,ROUND(MOD($S127,1)*10,0),ROUND(MOD($S127,1)*100,0))+1,0),"")),IFERROR(IF(LEN($S127)-LEN(SUBSTITUTE($S127,".",""))>=2,DATEVALUE(SUBSTITUTE(TRIM($S127),".","-")),DATE(VALUE(LEFT(TRIM($S127),4)),VALUE(MID(TRIM($S127),6,2))+1,0)),""))) | AC127: =IF(TRIM($T127&"")="","",IF(ISNUMBER($T127),IF($T127>10000,$T127,IFERROR(DATE(INT($T127),IF(ROUND(MOD($T127,1)*100,0)>12,ROUND(MOD($T127,1)*10,0),ROUND(MOD($T127,1)*100,0))+1,0),"")),IFERROR(IF(LEN($T127)-LEN(SUBSTITUTE($T127,".",""))>=2,DATEVALUE(SUBSTITUTE(TRIM($T127),".","-")),DATE(VALUE(LEFT(TRIM($T127),4)),VALUE(MID(TRIM($T127),6,2))+1,0)),"")))
B128: 武汉中海联机电工程有限公司 | C128: 武装部宿舍1栋2 | D128: XO-REZO(MRL) | E128: 31104201022023110067 | G128: 杭州西奥电梯 | H128: 客梯(无机房) | I128: 8 | J128: 8 | K128: 8 | L128: 800kg | M128: 1.0m/s | N128: 1 | O128: XSDTS24499 | P128: 2#客 | Y128: =IF(TRIM($B128&$C128)="","",IF(OR($W128="安装免保",$W128="技术免保",$W128="质保期内"),IF(NOT(ISNUMBER($X128)),"▲免保到期日没填",IF($X128<TODAY(),"▲免保已到期，转收费",IF($X128-TODAY()<=提醒天数,"免保剩"&($X128-TODAY())&"天","免保中"))),IF($W128="暂停维保","暂停中",IF($W128="已解约","已解约","")))) | Z128: =IF(TRIM($B128&$C128)="","",TRIM(IF($AA128="","",IF($AA128<TODAY(),"年检已过期"&(TODAY()-$AA128)&"天 ",IF($AA128-TODAY()<=提醒天数,"年检剩"&($AA128-TODAY())&"天 ","")))&IF($AB128="","",IF($AB128<TODAY(),"限速器已过期"&(TODAY()-$AB128)&"天 ",IF($AB128-TODAY()<=提醒天数,"限速器剩"&($AB128-TODAY())&"天 ","")))&IF($AC128="","",IF($AC128<TODAY(),"载重试验已过期"&(TODAY()-$AC128)&"天 ",IF($AC128-TODAY()<=提醒天数,"载重试验剩"&($AC128-TODAY())&"天 ",""))))) | AA128: =IF(TRIM($Q128&"")="","",IF(ISNUMBER($Q128),IF($Q128>10000,$Q128,IFERROR(DATE(INT($Q128),IF(ROUND(MOD($Q128,1)*100,0)>12,ROUND(MOD($Q128,1)*10,0),ROUND(MOD($Q128,1)*100,0))+1,0),"")),IFERROR(IF(LEN($Q128)-LEN(SUBSTITUTE($Q128,".",""))>=2,DATEVALUE(SUBSTITUTE(TRIM($Q128),".","-")),DATE(VALUE(LEFT(TRIM($Q128),4)),VALUE(MID(TRIM($Q128),6,2))+1,0)),""))) | AB128: =IF(TRIM($S128&"")="","",IF(ISNUMBER($S128),IF($S128>10000,$S128,IFERROR(DATE(INT($S128),IF(ROUND(MOD($S128,1)*100,0)>12,ROUND(MOD($S128,1)*10,0),ROUND(MOD($S128,1)*100,0))+1,0),"")),IFERROR(IF(LEN($S128)-LEN(SUBSTITUTE($S128,".",""))>=2,DATEVALUE(SUBSTITUTE(TRIM($S128),".","-")),DATE(VALUE(LEFT(TRIM($S128),4)),VALUE(MID(TRIM($S128),6,2))+1,0)),""))) | AC128: =IF(TRIM($T128&"")="","",IF(ISNUMBER($T128),IF($T128>10000,$T128,IFERROR(DATE(INT($T128),IF(ROUND(MOD($T128,1)*100,0)>12,ROUND(MOD($T128,1)*10,0),ROUND(MOD($T128,1)*100,0))+1,0),"")),IFERROR(IF(LEN($T128)-LEN(SUBSTITUTE($T128,".",""))>=2,DATEVALUE(SUBSTITUTE(TRIM($T128),".","-")),DATE(VALUE(LEFT(TRIM($T128),4)),VALUE(MID(TRIM($T128),6,2))+1,0)),"")))
B129: 武汉中海联机电工程有限公司 | C129: 台北教师公寓 | D129: Xmodel 3(MRL) | E129: 31104201012024052609 | G129: 杭州西奥电梯 | H129: 客梯(无机房) | I129: 8 | J129: 7 | K129: 7 | L129: 800kg | M129: 1.0m/s | N129: 1 | O129: XODTS25197 | P129: 1#客 | Y129: =IF(TRIM($B129&$C129)="","",IF(OR($W129="安装免保",$W129="技术免保",$W129="质保期内"),IF(NOT(ISNUMBER($X129)),"▲免保到期日没填",IF($X129<TODAY(),"▲免保已到期，转收费",IF($X129-TODAY()<=提醒天数,"免保剩"&($X129-TODAY())&"天","免保中"))),IF($W129="暂停维保","暂停中",IF($W129="已解约","已解约","")))) | Z129: =IF(TRIM($B129&$C129)="","",TRIM(IF($AA129="","",IF($AA129<TODAY(),"年检已过期"&(TODAY()-$AA129)&"天 ",IF($AA129-TODAY()<=提醒天数,"年检剩"&($AA129-TODAY())&"天 ","")))&IF($AB129="","",IF($AB129<TODAY(),"限速器已过期"&(TODAY()-$AB129)&"天 ",IF($AB129-TODAY()<=提醒天数,"限速器剩"&($AB129-TODAY())&"天 ","")))&IF($AC129="","",IF($AC129<TODAY(),"载重试验已过期"&(TODAY()-$AC129)&"天 ",IF($AC129-TODAY()<=提醒天数,"载重试验剩"&($AC129-TODAY())&"天 ",""))))) | AA129: =IF(TRIM($Q129&"")="","",IF(ISNUMBER($Q129),IF($Q129>10000,$Q129,IFERROR(DATE(INT($Q129),IF(ROUND(MOD($Q129,1)*100,0)>12,ROUND(MOD($Q129,1)*10,0),ROUND(MOD($Q129,1)*100,0))+1,0),"")),IFERROR(IF(LEN($Q129)-LEN(SUBSTITUTE($Q129,".",""))>=2,DATEVALUE(SUBSTITUTE(TRIM($Q129),".","-")),DATE(VALUE(LEFT(TRIM($Q129),4)),VALUE(MID(TRIM($Q129),6,2))+1,0)),""))) | AB129: =IF(TRIM($S129&"")="","",IF(ISNUMBER($S129),IF($S129>10000,$S129,IFERROR(DATE(INT($S129),IF(ROUND(MOD($S129,1)*100,0)>12,ROUND(MOD($S129,1)*10,0),ROUND(MOD($S129,1)*100,0))+1,0),"")),IFERROR(IF(LEN($S129)-LEN(SUBSTITUTE($S129,".",""))>=2,DATEVALUE(SUBSTITUTE(TRIM($S129),".","-")),DATE(VALUE(LEFT(TRIM($S129),4)),VALUE(MID(TRIM($S129),6,2))+1,0)),""))) | AC129: =IF(TRIM($T129&"")="","",IF(ISNUMBER($T129),IF($T129>10000,$T129,IFERROR(DATE(INT($T129),IF(ROUND(MOD($T129,1)*100,0)>12,ROUND(MOD($T129,1)*10,0),ROUND(MOD($T129,1)*100,0))+1,0),"")),IFERROR(IF(LEN($T129)-LEN(SUBSTITUTE($T129,".",""))>=2,DATEVALUE(SUBSTITUTE(TRIM($T129),".","-")),DATE(VALUE(LEFT(TRIM($T129),4)),VALUE(MID(TRIM($T129),6,2))+1,0)),"")))
B130: 武汉彤明汽车零部件有限公司 | C130: 彤明24#楼 | D130: CHOI-III | E130: 31104201012023117805 | F130: 187389 | G130: 沈阳远大智能工业集团 | H130: 客梯 | I130: 6 | J130: 6 | K130: 6 | L130: 1000kg | M130: 1.0m/s | N130: 1 | O130: BLTSY20K/20416 | P130: 24#楼4#客 | Y130: =IF(TRIM($B130&$C130)="","",IF(OR($W130="安装免保",$W130="技术免保",$W130="质保期内"),IF(NOT(ISNUMBER($X130)),"▲免保到期日没填",IF($X130<TODAY(),"▲免保已到期，转收费",IF($X130-TODAY()<=提醒天数,"免保剩"&($X130-TODAY())&"天","免保中"))),IF($W130="暂停维保","暂停中",IF($W130="已解约","已解约","")))) | Z130: =IF(TRIM($B130&$C130)="","",TRIM(IF($AA130="","",IF($AA130<TODAY(),"年检已过期"&(TODAY()-$AA130)&"天 ",IF($AA130-TODAY()<=提醒天数,"年检剩"&($AA130-TODAY())&"天 ","")))&IF($AB130="","",IF($AB130<TODAY(),"限速器已过期"&(TODAY()-$AB130)&"天 ",IF($AB130-TODAY()<=提醒天数,"限速器剩"&($AB130-TODAY())&"天 ","")))&IF($AC130="","",IF($AC130<TODAY(),"载重试验已过期"&(TODAY()-$AC130)&"天 ",IF($AC130-TODAY()<=提醒天数,"载重试验剩"&($AC130-TODAY())&"天 ",""))))) | AA130: =IF(TRIM($Q130&"")="","",IF(ISNUMBER($Q130),IF($Q130>10000,$Q130,IFERROR(DATE(INT($Q130),IF(ROUND(MOD($Q130,1)*100,0)>12,ROUND(MOD($Q130,1)*10,0),ROUND(MOD($Q130,1)*100,0))+1,0),"")),IFERROR(IF(LEN($Q130)-LEN(SUBSTITUTE($Q130,".",""))>=2,DATEVALUE(SUBSTITUTE(TRIM($Q130),".","-")),DATE(VALUE(LEFT(TRIM($Q130),4)),VALUE(MID(TRIM($Q130),6,2))+1,0)),""))) | AB130: =IF(TRIM($S130&"")="","",IF(ISNUMBER($S130),IF($S130>10000,$S130,IFERROR(DATE(INT($S130),IF(ROUND(MOD($S130,1)*100,0)>12,ROUND(MOD($S130,1)*10,0),ROUND(MOD($S130,1)*100,0))+1,0),"")),IFERROR(IF(LEN($S130)-LEN(SUBSTITUTE($S130,".",""))>=2,DATEVALUE(SUBSTITUTE(TRIM($S130),".","-")),DATE(VALUE(LEFT(TRIM($S130),4)),VALUE(MID(TRIM($S130),6,2))+1,0)),""))) | AC130: =IF(TRIM($T130&"")="","",IF(ISNUMBER($T130),IF($T130>10000,$T130,IFERROR(DATE(INT($T130),IF(ROUND(MOD($T130,1)*100,0)>12,ROUND(MOD($T130,1)*10,0),ROUND(MOD($T130,1)*100,0))+1,0),"")),IFERROR(IF(LEN($T130)-LEN(SUBSTITUTE($T130,".",""))>=2,DATEVALUE(SUBSTITUTE(TRIM($T130),".","-")),DATE(VALUE(LEFT(TRIM($T130),4)),VALUE(MID(TRIM($T130),6,2))+1,0)),"")))
B131: 武汉中海联机电工程有限公司 | C131: 百步亭温馨苑AB区116栋1单元 | D131: GPN65 | E131: 31104201022024010045 | G131: 巨人通力电梯 | H131: 客梯 | I131: 6 | J131: 5 | K131: 5 | L131: 800kg | M131: 1.0m/s | N131: 1 | O131: 45350969 | P131: 1#客 | Y131: =IF(TRIM($B131&$C131)="","",IF(OR($W131="安装免保",$W131="技术免保",$W131="质保期内"),IF(NOT(ISNUMBER($X131)),"▲免保到期日没填",IF($X131<TODAY(),"▲免保已到期，转收费",IF($X131-TODAY()<=提醒天数,"免保剩"&($X131-TODAY())&"天","免保中"))),IF($W131="暂停维保","暂停中",IF($W131="已解约","已解约","")))) | Z131: =IF(TRIM($B131&$C131)="","",TRIM(IF($AA131="","",IF($AA131<TODAY(),"年检已过期"&(TODAY()-$AA131)&"天 ",IF($AA131-TODAY()<=提醒天数,"年检剩"&($AA131-TODAY())&"天 ","")))&IF($AB131="","",IF($AB131<TODAY(),"限速器已过期"&(TODAY()-$AB131)&"天 ",IF($AB131-TODAY()<=提醒天数,"限速器剩"&($AB131-TODAY())&"天 ","")))&IF($AC131="","",IF($AC131<TODAY(),"载重试验已过期"&(TODAY()-$AC131)&"天 ",IF($AC131-TODAY()<=提醒天数,"载重试验剩"&($AC131-TODAY())&"天 ",""))))) | AA131: =IF(TRIM($Q131&"")="","",IF(ISNUMBER($Q131),IF($Q131>10000,$Q131,IFERROR(DATE(INT($Q131),IF(ROUND(MOD($Q131,1)*100,0)>12,ROUND(MOD($Q131,1)*10,0),ROUND(MOD($Q131,1)*100,0))+1,0),"")),IFERROR(IF(LEN($Q131)-LEN(SUBSTITUTE($Q131,".",""))>=2,DATEVALUE(SUBSTITUTE(TRIM($Q131),".","-")),DATE(VALUE(LEFT(TRIM($Q131),4)),VALUE(MID(TRIM($Q131),6,2))+1,0)),""))) | AB131: =IF(TRIM($S131&"")="","",IF(ISNUMBER($S131),IF($S131>10000,$S131,IFERROR(DATE(INT($S131),IF(ROUND(MOD($S131,1)*100,0)>12,ROUND(MOD($S131,1)*10,0),ROUND(MOD($S131,1)*100,0))+1,0),"")),IFERROR(IF(LEN($S131)-LEN(SUBSTITUTE($S131,".",""))>=2,DATEVALUE(SUBSTITUTE(TRIM($S131),".","-")),DATE(VALUE(LEFT(TRIM($S131),4)),VALUE(MID(TRIM($S131),6,2))+1,0)),""))) | AC131: =IF(TRIM($T131&"")="","",IF(ISNUMBER($T131),IF($T131>10000,$T131,IFERROR(DATE(INT($T131),IF(ROUND(MOD($T131,1)*100,0)>12,ROUND(MOD($T131,1)*10,0),ROUND(MOD($T131,1)*100,0))+1,0),"")),IFERROR(IF(LEN($T131)-LEN(SUBSTITUTE($T131,".",""))>=2,DATEVALUE(SUBSTITUTE(TRIM($T131),".","-")),DATE(VALUE(LEFT(TRIM($T131),4)),VALUE(MID(TRIM($T131),6,2))+1,0)),"")))
B132: 武汉中海联机电工程有限公司 | C132: 武昌区东一路26号 | D132: GPN65 | E132: 31104201062024040001 | F132: 148913 | G132: 巨人通力电梯 | H132: 客梯(无机房) | I132: 6 | J132: 3 | K132: 3 | L132: 630kg | M132: 1.0m/s | N132: 1 | O132: 45209935 | P132: 26-1# | Y132: =IF(TRIM($B132&$C132)="","",IF(OR($W132="安装免保",$W132="技术免保",$W132="质保期内"),IF(NOT(ISNUMBER($X132)),"▲免保到期日没填",IF($X132<TODAY(),"▲免保已到期，转收费",IF($X132-TODAY()<=提醒天数,"免保剩"&($X132-TODAY())&"天","免保中"))),IF($W132="暂停维保","暂停中",IF($W132="已解约","已解约","")))) | Z132: =IF(TRIM($B132&$C132)="","",TRIM(IF($AA132="","",IF($AA132<TODAY(),"年检已过期"&(TODAY()-$AA132)&"天 ",IF($AA132-TODAY()<=提醒天数,"年检剩"&($AA132-TODAY())&"天 ","")))&IF($AB132="","",IF($AB132<TODAY(),"限速器已过期"&(TODAY()-$AB132)&"天 ",IF($AB132-TODAY()<=提醒天数,"限速器剩"&($AB132-TODAY())&"天 ","")))&IF($AC132="","",IF($AC132<TODAY(),"载重试验已过期"&(TODAY()-$AC132)&"天 ",IF($AC132-TODAY()<=提醒天数,"载重试验剩"&($AC132-TODAY())&"天 ",""))))) | AA132: =IF(TRIM($Q132&"")="","",IF(ISNUMBER($Q132),IF($Q132>10000,$Q132,IFERROR(DATE(INT($Q132),IF(ROUND(MOD($Q132,1)*100,0)>12,ROUND(MOD($Q132,1)*10,0),ROUND(MOD($Q132,1)*100,0))+1,0),"")),IFERROR(IF(LEN($Q132)-LEN(SUBSTITUTE($Q132,".",""))>=2,DATEVALUE(SUBSTITUTE(TRIM($Q132),".","-")),DATE(VALUE(LEFT(TRIM($Q132),4)),VALUE(MID(TRIM($Q132),6,2))+1,0)),""))) | AB132: =IF(TRIM($S132&"")="","",IF(ISNUMBER($S132),IF($S132>10000,$S132,IFERROR(DATE(INT($S132),IF(ROUND(MOD($S132,1)*100,0)>12,ROUND(MOD($S132,1)*10,0),ROUND(MOD($S132,1)*100,0))+1,0),"")),IFERROR(IF(LEN($S132)-LEN(SUBSTITUTE($S132,".",""))>=2,DATEVALUE(SUBSTITUTE(TRIM($S132),".","-")),DATE(VALUE(LEFT(TRIM($S132),4)),VALUE(MID(TRIM($S132),6,2))+1,0)),""))) | AC132: =IF(TRIM($T132&"")="","",IF(ISNUMBER($T132),IF($T132>10000,$T132,IFERROR(DATE(INT($T132),IF(ROUND(MOD($T132,1)*100,0)>12,ROUND(MOD($T132,1)*10,0),ROUND(MOD($T132,1)*100,0))+1,0),"")),IFERROR(IF(LEN($T132)-LEN(SUBSTITUTE($T132,".",""))>=2,DATEVALUE(SUBSTITUTE(TRIM($T132),".","-")),DATE(VALUE(LEFT(TRIM($T132),4)),VALUE(MID(TRIM($T132),6,2))+1,0)),"")))
B133: 武汉中海联机电工程有限公司 | C133: 瑞安街陆总花园 | D133: Xmodel 3(MRL) | E133: 31104201112025040008 | F133: 207636 | G133: 杭州西奥 | H133: 客梯(无机房) | I133: 7 | J133: 7 | K133: 7 | L133: 800kg | M133: 1.0m/s | N133: 1 | O133: XODTS28089 | P133: 1# 客 | Y133: =IF(TRIM($B133&$C133)="","",IF(OR($W133="安装免保",$W133="技术免保",$W133="质保期内"),IF(NOT(ISNUMBER($X133)),"▲免保到期日没填",IF($X133<TODAY(),"▲免保已到期，转收费",IF($X133-TODAY()<=提醒天数,"免保剩"&($X133-TODAY())&"天","免保中"))),IF($W133="暂停维保","暂停中",IF($W133="已解约","已解约","")))) | Z133: =IF(TRIM($B133&$C133)="","",TRIM(IF($AA133="","",IF($AA133<TODAY(),"年检已过期"&(TODAY()-$AA133)&"天 ",IF($AA133-TODAY()<=提醒天数,"年检剩"&($AA133-TODAY())&"天 ","")))&IF($AB133="","",IF($AB133<TODAY(),"限速器已过期"&(TODAY()-$AB133)&"天 ",IF($AB133-TODAY()<=提醒天数,"限速器剩"&($AB133-TODAY())&"天 ","")))&IF($AC133="","",IF($AC133<TODAY(),"载重试验已过期"&(TODAY()-$AC133)&"天 ",IF($AC133-TODAY()<=提醒天数,"载重试验剩"&($AC133-TODAY())&"天 ",""))))) | AA133: =IF(TRIM($Q133&"")="","",IF(ISNUMBER($Q133),IF($Q133>10000,$Q133,IFERROR(DATE(INT($Q133),IF(ROUND(MOD($Q133,1)*100,0)>12,ROUND(MOD($Q133,1)*10,0),ROUND(MOD($Q133,1)*100,0))+1,0),"")),IFERROR(IF(LEN($Q133)-LEN(SUBSTITUTE($Q133,".",""))>=2,DATEVALUE(SUBSTITUTE(TRIM($Q133),".","-")),DATE(VALUE(LEFT(TRIM($Q133),4)),VALUE(MID(TRIM($Q133),6,2))+1,0)),""))) | AB133: =IF(TRIM($S133&"")="","",IF(ISNUMBER($S133),IF($S133>10000,$S133,IFERROR(DATE(INT($S133),IF(ROUND(MOD($S133,1)*100,0)>12,ROUND(MOD($S133,1)*10,0),ROUND(MOD($S133,1)*100,0))+1,0),"")),IFERROR(IF(LEN($S133)-LEN(SUBSTITUTE($S133,".",""))>=2,DATEVALUE(SUBSTITUTE(TRIM($S133),".","-")),DATE(VALUE(LEFT(TRIM($S133),4)),VALUE(MID(TRIM($S133),6,2))+1,0)),""))) | AC133: =IF(TRIM($T133&"")="","",IF(ISNUMBER($T133),IF($T133>10000,$T133,IFERROR(DATE(INT($T133),IF(ROUND(MOD($T133,1)*100,0)>12,ROUND(MOD($T133,1)*10,0),ROUND(MOD($T133,1)*100,0))+1,0),"")),IFERROR(IF(LEN($T133)-LEN(SUBSTITUTE($T133,".",""))>=2,DATEVALUE(SUBSTITUTE(TRIM($T133),".","-")),DATE(VALUE(LEFT(TRIM($T133),4)),VALUE(MID(TRIM($T133),6,2))+1,0)),"")))
B134: 武汉中海联机电工程有限公司 | C134: 滨江苑一期1栋2单元 | D134: GPN65 | E134: 31104201022024070008 | F134: 197745 | G134: 巨人通力电梯 | H134: 客梯(无机房) | I134: 8 | J134: 8 | K134: 8 | L134: 1000kg | M134: 1.0m/s | N134: 1 | O134: 45049258 | P134: 1#客 | Y134: =IF(TRIM($B134&$C134)="","",IF(OR($W134="安装免保",$W134="技术免保",$W134="质保期内"),IF(NOT(ISNUMBER($X134)),"▲免保到期日没填",IF($X134<TODAY(),"▲免保已到期，转收费",IF($X134-TODAY()<=提醒天数,"免保剩"&($X134-TODAY())&"天","免保中"))),IF($W134="暂停维保","暂停中",IF($W134="已解约","已解约","")))) | Z134: =IF(TRIM($B134&$C134)="","",TRIM(IF($AA134="","",IF($AA134<TODAY(),"年检已过期"&(TODAY()-$AA134)&"天 ",IF($AA134-TODAY()<=提醒天数,"年检剩"&($AA134-TODAY())&"天 ","")))&IF($AB134="","",IF($AB134<TODAY(),"限速器已过期"&(TODAY()-$AB134)&"天 ",IF($AB134-TODAY()<=提醒天数,"限速器剩"&($AB134-TODAY())&"天 ","")))&IF($AC134="","",IF($AC134<TODAY(),"载重试验已过期"&(TODAY()-$AC134)&"天 ",IF($AC134-TODAY()<=提醒天数,"载重试验剩"&($AC134-TODAY())&"天 ",""))))) | AA134: =IF(TRIM($Q134&"")="","",IF(ISNUMBER($Q134),IF($Q134>10000,$Q134,IFERROR(DATE(INT($Q134),IF(ROUND(MOD($Q134,1)*100,0)>12,ROUND(MOD($Q134,1)*10,0),ROUND(MOD($Q134,1)*100,0))+1,0),"")),IFERROR(IF(LEN($Q134)-LEN(SUBSTITUTE($Q134,".",""))>=2,DATEVALUE(SUBSTITUTE(TRIM($Q134),".","-")),DATE(VALUE(LEFT(TRIM($Q134),4)),VALUE(MID(TRIM($Q134),6,2))+1,0)),""))) | AB134: =IF(TRIM($S134&"")="","",IF(ISNUMBER($S134),IF($S134>10000,$S134,IFERROR(DATE(INT($S134),IF(ROUND(MOD($S134,1)*100,0)>12,ROUND(MOD($S134,1)*10,0),ROUND(MOD($S134,1)*100,0))+1,0),"")),IFERROR(IF(LEN($S134)-LEN(SUBSTITUTE($S134,".",""))>=2,DATEVALUE(SUBSTITUTE(TRIM($S134),".","-")),DATE(VALUE(LEFT(TRIM($S134),4)),VALUE(MID(TRIM($S134),6,2))+1,0)),""))) | AC134: =IF(TRIM($T134&"")="","",IF(ISNUMBER($T134),IF($T134>10000,$T134,IFERROR(DATE(INT($T134),IF(ROUND(MOD($T134,1)*100,0)>12,ROUND(MOD($T134,1)*10,0),ROUND(MOD($T134,1)*100,0))+1,0),"")),IFERROR(IF(LEN($T134)-LEN(SUBSTITUTE($T134,".",""))>=2,DATEVALUE(SUBSTITUTE(TRIM($T134),".","-")),DATE(VALUE(LEFT(TRIM($T134),4)),VALUE(MID(TRIM($T134),6,2))+1,0)),"")))
B135: 武汉中海联机电工程有限公司 | C135: 东方花都A9栋1单元 | D135: XO-GMEIII | E135: 31104201022023070033 | F135: 174663 | G135: 杭州西奥电梯 | H135: 客梯(无机房) | I135: 6 | J135: 6 | K135: 6 | L135: 800kg | M135: 1.0m/s | N135: 1 | O135: XODTG04336 | P135: 1#客 | Y135: =IF(TRIM($B135&$C135)="","",IF(OR($W135="安装免保",$W135="技术免保",$W135="质保期内"),IF(NOT(ISNUMBER($X135)),"▲免保到期日没填",IF($X135<TODAY(),"▲免保已到期，转收费",IF($X135-TODAY()<=提醒天数,"免保剩"&($X135-TODAY())&"天","免保中"))),IF($W135="暂停维保","暂停中",IF($W135="已解约","已解约","")))) | Z135: =IF(TRIM($B135&$C135)="","",TRIM(IF($AA135="","",IF($AA135<TODAY(),"年检已过期"&(TODAY()-$AA135)&"天 ",IF($AA135-TODAY()<=提醒天数,"年检剩"&($AA135-TODAY())&"天 ","")))&IF($AB135="","",IF($AB135<TODAY(),"限速器已过期"&(TODAY()-$AB135)&"天 ",IF($AB135-TODAY()<=提醒天数,"限速器剩"&($AB135-TODAY())&"天 ","")))&IF($AC135="","",IF($AC135<TODAY(),"载重试验已过期"&(TODAY()-$AC135)&"天 ",IF($AC135-TODAY()<=提醒天数,"载重试验剩"&($AC135-TODAY())&"天 ",""))))) | AA135: =IF(TRIM($Q135&"")="","",IF(ISNUMBER($Q135),IF($Q135>10000,$Q135,IFERROR(DATE(INT($Q135),IF(ROUND(MOD($Q135,1)*100,0)>12,ROUND(MOD($Q135,1)*10,0),ROUND(MOD($Q135,1)*100,0))+1,0),"")),IFERROR(IF(LEN($Q135)-LEN(SUBSTITUTE($Q135,".",""))>=2,DATEVALUE(SUBSTITUTE(TRIM($Q135),".","-")),DATE(VALUE(LEFT(TRIM($Q135),4)),VALUE(MID(TRIM($Q135),6,2))+1,0)),""))) | AB135: =IF(TRIM($S135&"")="","",IF(ISNUMBER($S135),IF($S135>10000,$S135,IFERROR(DATE(INT($S135),IF(ROUND(MOD($S135,1)*100,0)>12,ROUND(MOD($S135,1)*10,0),ROUND(MOD($S135,1)*100,0))+1,0),"")),IFERROR(IF(LEN($S135)-LEN(SUBSTITUTE($S135,".",""))>=2,DATEVALUE(SUBSTITUTE(TRIM($S135),".","-")),DATE(VALUE(LEFT(TRIM($S135),4)),VALUE(MID(TRIM($S135),6,2))+1,0)),""))) | AC135: =IF(TRIM($T135&"")="","",IF(ISNUMBER($T135),IF($T135>10000,$T135,IFERROR(DATE(INT($T135),IF(ROUND(MOD($T135,1)*100,0)>12,ROUND(MOD($T135,1)*10,0),ROUND(MOD($T135,1)*100,0))+1,0),"")),IFERROR(IF(LEN($T135)-LEN(SUBSTITUTE($T135,".",""))>=2,DATEVALUE(SUBSTITUTE(TRIM($T135),".","-")),DATE(VALUE(LEFT(TRIM($T135),4)),VALUE(MID(TRIM($T135),6,2))+1,0)),"")))
B136: 武汉中海联机电工程有限公司 | C136: 花桥一村20号 | D136: GPN65 | E136: 31104201022024080006 | G136: 巨人通力电梯 | H136: 客梯(无机房) | I136: 7 | J136: 6 | K136: 6 | L136: 800kg | M136: 1.0m/s | N136: 1 | O136: 45404777 | P136: 花桥一村20#客梯 | Y136: =IF(TRIM($B136&$C136)="","",IF(OR($W136="安装免保",$W136="技术免保",$W136="质保期内"),IF(NOT(ISNUMBER($X136)),"▲免保到期日没填",IF($X136<TODAY(),"▲免保已到期，转收费",IF($X136-TODAY()<=提醒天数,"免保剩"&($X136-TODAY())&"天","免保中"))),IF($W136="暂停维保","暂停中",IF($W136="已解约","已解约","")))) | Z136: =IF(TRIM($B136&$C136)="","",TRIM(IF($AA136="","",IF($AA136<TODAY(),"年检已过期"&(TODAY()-$AA136)&"天 ",IF($AA136-TODAY()<=提醒天数,"年检剩"&($AA136-TODAY())&"天 ","")))&IF($AB136="","",IF($AB136<TODAY(),"限速器已过期"&(TODAY()-$AB136)&"天 ",IF($AB136-TODAY()<=提醒天数,"限速器剩"&($AB136-TODAY())&"天 ","")))&IF($AC136="","",IF($AC136<TODAY(),"载重试验已过期"&(TODAY()-$AC136)&"天 ",IF($AC136-TODAY()<=提醒天数,"载重试验剩"&($AC136-TODAY())&"天 ",""))))) | AA136: =IF(TRIM($Q136&"")="","",IF(ISNUMBER($Q136),IF($Q136>10000,$Q136,IFERROR(DATE(INT($Q136),IF(ROUND(MOD($Q136,1)*100,0)>12,ROUND(MOD($Q136,1)*10,0),ROUND(MOD($Q136,1)*100,0))+1,0),"")),IFERROR(IF(LEN($Q136)-LEN(SUBSTITUTE($Q136,".",""))>=2,DATEVALUE(SUBSTITUTE(TRIM($Q136),".","-")),DATE(VALUE(LEFT(TRIM($Q136),4)),VALUE(MID(TRIM($Q136),6,2))+1,0)),""))) | AB136: =IF(TRIM($S136&"")="","",IF(ISNUMBER($S136),IF($S136>10000,$S136,IFERROR(DATE(INT($S136),IF(ROUND(MOD($S136,1)*100,0)>12,ROUND(MOD($S136,1)*10,0),ROUND(MOD($S136,1)*100,0))+1,0),"")),IFERROR(IF(LEN($S136)-LEN(SUBSTITUTE($S136,".",""))>=2,DATEVALUE(SUBSTITUTE(TRIM($S136),".","-")),DATE(VALUE(LEFT(TRIM($S136),4)),VALUE(MID(TRIM($S136),6,2))+1,0)),""))) | AC136: =IF(TRIM($T136&"")="","",IF(ISNUMBER($T136),IF($T136>10000,$T136,IFERROR(DATE(INT($T136),IF(ROUND(MOD($T136,1)*100,0)>12,ROUND(MOD($T136,1)*10,0),ROUND(MOD($T136,1)*100,0))+1,0),"")),IFERROR(IF(LEN($T136)-LEN(SUBSTITUTE($T136,".",""))>=2,DATEVALUE(SUBSTITUTE(TRIM($T136),".","-")),DATE(VALUE(LEFT(TRIM($T136),4)),VALUE(MID(TRIM($T136),6,2))+1,0)),"")))
B137: 武汉中海联机电工程有限公司 | C137: 花桥一村12号 | D137: GPN65 | E137: 31104201022024080007 | G137: 巨人通力电梯 | H137: 客梯(无机房) | I137: 7 | J137: 6 | K137: 6 | L137: 800kg | M137: 1.0m/s | N137: 1 | O137: 45404775 | P137: 花桥一村12#客梯 | Y137: =IF(TRIM($B137&$C137)="","",IF(OR($W137="安装免保",$W137="技术免保",$W137="质保期内"),IF(NOT(ISNUMBER($X137)),"▲免保到期日没填",IF($X137<TODAY(),"▲免保已到期，转收费",IF($X137-TODAY()<=提醒天数,"免保剩"&($X137-TODAY())&"天","免保中"))),IF($W137="暂停维保","暂停中",IF($W137="已解约","已解约","")))) | Z137: =IF(TRIM($B137&$C137)="","",TRIM(IF($AA137="","",IF($AA137<TODAY(),"年检已过期"&(TODAY()-$AA137)&"天 ",IF($AA137-TODAY()<=提醒天数,"年检剩"&($AA137-TODAY())&"天 ","")))&IF($AB137="","",IF($AB137<TODAY(),"限速器已过期"&(TODAY()-$AB137)&"天 ",IF($AB137-TODAY()<=提醒天数,"限速器剩"&($AB137-TODAY())&"天 ","")))&IF($AC137="","",IF($AC137<TODAY(),"载重试验已过期"&(TODAY()-$AC137)&"天 ",IF($AC137-TODAY()<=提醒天数,"载重试验剩"&($AC137-TODAY())&"天 ",""))))) | AA137: =IF(TRIM($Q137&"")="","",IF(ISNUMBER($Q137),IF($Q137>10000,$Q137,IFERROR(DATE(INT($Q137),IF(ROUND(MOD($Q137,1)*100,0)>12,ROUND(MOD($Q137,1)*10,0),ROUND(MOD($Q137,1)*100,0))+1,0),"")),IFERROR(IF(LEN($Q137)-LEN(SUBSTITUTE($Q137,".",""))>=2,DATEVALUE(SUBSTITUTE(TRIM($Q137),".","-")),DATE(VALUE(LEFT(TRIM($Q137),4)),VALUE(MID(TRIM($Q137),6,2))+1,0)),""))) | AB137: =IF(TRIM($S137&"")="","",IF(ISNUMBER($S137),IF($S137>10000,$S137,IFERROR(DATE(INT($S137),IF(ROUND(MOD($S137,1)*100,0)>12,ROUND(MOD($S137,1)*10,0),ROUND(MOD($S137,1)*100,0))+1,0),"")),IFERROR(IF(LEN($S137)-LEN(SUBSTITUTE($S137,".",""))>=2,DATEVALUE(SUBSTITUTE(TRIM($S137),".","-")),DATE(VALUE(LEFT(TRIM($S137),4)),VALUE(MID(TRIM($S137),6,2))+1,0)),""))) | AC137: =IF(TRIM($T137&"")="","",IF(ISNUMBER($T137),IF($T137>10000,$T137,IFERROR(DATE(INT($T137),IF(ROUND(MOD($T137,1)*100,0)>12,ROUND(MOD($T137,1)*10,0),ROUND(MOD($T137,1)*100,0))+1,0),"")),IFERROR(IF(LEN($T137)-LEN(SUBSTITUTE($T137,".",""))>=2,DATEVALUE(SUBSTITUTE(TRIM($T137),".","-")),DATE(VALUE(LEFT(TRIM($T137),4)),VALUE(MID(TRIM($T137),6,2))+1,0)),"")))
B138: 武汉中海联机电工程有限公司 | C138: 花桥一村17号 | D138: GPN65 | E138: 31104201012024115255 | G138: 巨人通力电梯 | H138: 客梯(无机房) | I138: 7 | J138: 6 | K138: 6 | L138: 800kg | M138: 1.0m/s | N138: 1 | O138: 45404776 | P138: 花桥一村17#客梯 | Y138: =IF(TRIM($B138&$C138)="","",IF(OR($W138="安装免保",$W138="技术免保",$W138="质保期内"),IF(NOT(ISNUMBER($X138)),"▲免保到期日没填",IF($X138<TODAY(),"▲免保已到期，转收费",IF($X138-TODAY()<=提醒天数,"免保剩"&($X138-TODAY())&"天","免保中"))),IF($W138="暂停维保","暂停中",IF($W138="已解约","已解约","")))) | Z138: =IF(TRIM($B138&$C138)="","",TRIM(IF($AA138="","",IF($AA138<TODAY(),"年检已过期"&(TODAY()-$AA138)&"天 ",IF($AA138-TODAY()<=提醒天数,"年检剩"&($AA138-TODAY())&"天 ","")))&IF($AB138="","",IF($AB138<TODAY(),"限速器已过期"&(TODAY()-$AB138)&"天 ",IF($AB138-TODAY()<=提醒天数,"限速器剩"&($AB138-TODAY())&"天 ","")))&IF($AC138="","",IF($AC138<TODAY(),"载重试验已过期"&(TODAY()-$AC138)&"天 ",IF($AC138-TODAY()<=提醒天数,"载重试验剩"&($AC138-TODAY())&"天 ",""))))) | AA138: =IF(TRIM($Q138&"")="","",IF(ISNUMBER($Q138),IF($Q138>10000,$Q138,IFERROR(DATE(INT($Q138),IF(ROUND(MOD($Q138,1)*100,0)>12,ROUND(MOD($Q138,1)*10,0),ROUND(MOD($Q138,1)*100,0))+1,0),"")),IFERROR(IF(LEN($Q138)-LEN(SUBSTITUTE($Q138,".",""))>=2,DATEVALUE(SUBSTITUTE(TRIM($Q138),".","-")),DATE(VALUE(LEFT(TRIM($Q138),4)),VALUE(MID(TRIM($Q138),6,2))+1,0)),""))) | AB138: =IF(TRIM($S138&"")="","",IF(ISNUMBER($S138),IF($S138>10000,$S138,IFERROR(DATE(INT($S138),IF(ROUND(MOD($S138,1)*100,0)>12,ROUND(MOD($S138,1)*10,0),ROUND(MOD($S138,1)*100,0))+1,0),"")),IFERROR(IF(LEN($S138)-LEN(SUBSTITUTE($S138,".",""))>=2,DATEVALUE(SUBSTITUTE(TRIM($S138),".","-")),DATE(VALUE(LEFT(TRIM($S138),4)),VALUE(MID(TRIM($S138),6,2))+1,0)),""))) | AC138: =IF(TRIM($T138&"")="","",IF(ISNUMBER($T138),IF($T138>10000,$T138,IFERROR(DATE(INT($T138),IF(ROUND(MOD($T138,1)*100,0)>12,ROUND(MOD($T138,1)*10,0),ROUND(MOD($T138,1)*100,0))+1,0),"")),IFERROR(IF(LEN($T138)-LEN(SUBSTITUTE($T138,".",""))>=2,DATEVALUE(SUBSTITUTE(TRIM($T138),".","-")),DATE(VALUE(LEFT(TRIM($T138),4)),VALUE(MID(TRIM($T138),6,2))+1,0)),"")))
B139: 武汉中海联机电工程有限公司 | C139: 怡康苑北区204栋1单元 | D139: GPN65 | E139: 31104201022024070017 | G139: 巨人通力电梯 | H139: 客梯(无机房) | I139: 6 | J139: 6 | K139: 6 | L139: 800kg | M139: 1.0m/s | N139: 1 | O139: 45475378 | P139: 204栋1单元1#客 | Y139: =IF(TRIM($B139&$C139)="","",IF(OR($W139="安装免保",$W139="技术免保",$W139="质保期内"),IF(NOT(ISNUMBER($X139)),"▲免保到期日没填",IF($X139<TODAY(),"▲免保已到期，转收费",IF($X139-TODAY()<=提醒天数,"免保剩"&($X139-TODAY())&"天","免保中"))),IF($W139="暂停维保","暂停中",IF($W139="已解约","已解约","")))) | Z139: =IF(TRIM($B139&$C139)="","",TRIM(IF($AA139="","",IF($AA139<TODAY(),"年检已过期"&(TODAY()-$AA139)&"天 ",IF($AA139-TODAY()<=提醒天数,"年检剩"&($AA139-TODAY())&"天 ","")))&IF($AB139="","",IF($AB139<TODAY(),"限速器已过期"&(TODAY()-$AB139)&"天 ",IF($AB139-TODAY()<=提醒天数,"限速器剩"&($AB139-TODAY())&"天 ","")))&IF($AC139="","",IF($AC139<TODAY(),"载重试验已过期"&(TODAY()-$AC139)&"天 ",IF($AC139-TODAY()<=提醒天数,"载重试验剩"&($AC139-TODAY())&"天 ",""))))) | AA139: =IF(TRIM($Q139&"")="","",IF(ISNUMBER($Q139),IF($Q139>10000,$Q139,IFERROR(DATE(INT($Q139),IF(ROUND(MOD($Q139,1)*100,0)>12,ROUND(MOD($Q139,1)*10,0),ROUND(MOD($Q139,1)*100,0))+1,0),"")),IFERROR(IF(LEN($Q139)-LEN(SUBSTITUTE($Q139,".",""))>=2,DATEVALUE(SUBSTITUTE(TRIM($Q139),".","-")),DATE(VALUE(LEFT(TRIM($Q139),4)),VALUE(MID(TRIM($Q139),6,2))+1,0)),""))) | AB139: =IF(TRIM($S139&"")="","",IF(ISNUMBER($S139),IF($S139>10000,$S139,IFERROR(DATE(INT($S139),IF(ROUND(MOD($S139,1)*100,0)>12,ROUND(MOD($S139,1)*10,0),ROUND(MOD($S139,1)*100,0))+1,0),"")),IFERROR(IF(LEN($S139)-LEN(SUBSTITUTE($S139,".",""))>=2,DATEVALUE(SUBSTITUTE(TRIM($S139),".","-")),DATE(VALUE(LEFT(TRIM($S139),4)),VALUE(MID(TRIM($S139),6,2))+1,0)),""))) | AC139: =IF(TRIM($T139&"")="","",IF(ISNUMBER($T139),IF($T139>10000,$T139,IFERROR(DATE(INT($T139),IF(ROUND(MOD($T139,1)*100,0)>12,ROUND(MOD($T139,1)*10,0),ROUND(MOD($T139,1)*100,0))+1,0),"")),IFERROR(IF(LEN($T139)-LEN(SUBSTITUTE($T139,".",""))>=2,DATEVALUE(SUBSTITUTE(TRIM($T139),".","-")),DATE(VALUE(LEFT(TRIM($T139),4)),VALUE(MID(TRIM($T139),6,2))+1,0)),"")))
B140: 武汉中海联机电工程有限公司 | C140: 怡和苑北区408栋1单元 | D140: GPN65 | E140: 31104201012024083993 | G140: 巨人通力电梯 | H140: 客梯(无机房) | I140: 5 | J140: 5 | K140: 5 | L140: 800kg | M140: 1.0m/s | N140: 1 | O140: 45475379 | P140: 408栋1单元1#客 | Y140: =IF(TRIM($B140&$C140)="","",IF(OR($W140="安装免保",$W140="技术免保",$W140="质保期内"),IF(NOT(ISNUMBER($X140)),"▲免保到期日没填",IF($X140<TODAY(),"▲免保已到期，转收费",IF($X140-TODAY()<=提醒天数,"免保剩"&($X140-TODAY())&"天","免保中"))),IF($W140="暂停维保","暂停中",IF($W140="已解约","已解约","")))) | Z140: =IF(TRIM($B140&$C140)="","",TRIM(IF($AA140="","",IF($AA140<TODAY(),"年检已过期"&(TODAY()-$AA140)&"天 ",IF($AA140-TODAY()<=提醒天数,"年检剩"&($AA140-TODAY())&"天 ","")))&IF($AB140="","",IF($AB140<TODAY(),"限速器已过期"&(TODAY()-$AB140)&"天 ",IF($AB140-TODAY()<=提醒天数,"限速器剩"&($AB140-TODAY())&"天 ","")))&IF($AC140="","",IF($AC140<TODAY(),"载重试验已过期"&(TODAY()-$AC140)&"天 ",IF($AC140-TODAY()<=提醒天数,"载重试验剩"&($AC140-TODAY())&"天 ",""))))) | AA140: =IF(TRIM($Q140&"")="","",IF(ISNUMBER($Q140),IF($Q140>10000,$Q140,IFERROR(DATE(INT($Q140),IF(ROUND(MOD($Q140,1)*100,0)>12,ROUND(MOD($Q140,1)*10,0),ROUND(MOD($Q140,1)*100,0))+1,0),"")),IFERROR(IF(LEN($Q140)-LEN(SUBSTITUTE($Q140,".",""))>=2,DATEVALUE(SUBSTITUTE(TRIM($Q140),".","-")),DATE(VALUE(LEFT(TRIM($Q140),4)),VALUE(MID(TRIM($Q140),6,2))+1,0)),""))) | AB140: =IF(TRIM($S140&"")="","",IF(ISNUMBER($S140),IF($S140>10000,$S140,IFERROR(DATE(INT($S140),IF(ROUND(MOD($S140,1)*100,0)>12,ROUND(MOD($S140,1)*10,0),ROUND(MOD($S140,1)*100,0))+1,0),"")),IFERROR(IF(LEN($S140)-LEN(SUBSTITUTE($S140,".",""))>=2,DATEVALUE(SUBSTITUTE(TRIM($S140),".","-")),DATE(VALUE(LEFT(TRIM($S140),4)),VALUE(MID(TRIM($S140),6,2))+1,0)),""))) | AC140: =IF(TRIM($T140&"")="","",IF(ISNUMBER($T140),IF($T140>10000,$T140,IFERROR(DATE(INT($T140),IF(ROUND(MOD($T140,1)*100,0)>12,ROUND(MOD($T140,1)*10,0),ROUND(MOD($T140,1)*100,0))+1,0),"")),IFERROR(IF(LEN($T140)-LEN(SUBSTITUTE($T140,".",""))>=2,DATEVALUE(SUBSTITUTE(TRIM($T140),".","-")),DATE(VALUE(LEFT(TRIM($T140),4)),VALUE(MID(TRIM($T140),6,2))+1,0)),"")))
B141: 武汉中海联机电工程有限公司 | C141: 怡和苑北区407栋2单元 | D141: GPN65 | E141: 31104201022024120099 | G141: 巨人通力电梯 | H141: 客梯(无机房) | I141: 5 | J141: 5 | K141: 5 | L141: 800kg | M141: 1.0m/s | N141: 1 | O141: 45475377 | P141: 407栋2单元1#客 | Y141: =IF(TRIM($B141&$C141)="","",IF(OR($W141="安装免保",$W141="技术免保",$W141="质保期内"),IF(NOT(ISNUMBER($X141)),"▲免保到期日没填",IF($X141<TODAY(),"▲免保已到期，转收费",IF($X141-TODAY()<=提醒天数,"免保剩"&($X141-TODAY())&"天","免保中"))),IF($W141="暂停维保","暂停中",IF($W141="已解约","已解约","")))) | Z141: =IF(TRIM($B141&$C141)="","",TRIM(IF($AA141="","",IF($AA141<TODAY(),"年检已过期"&(TODAY()-$AA141)&"天 ",IF($AA141-TODAY()<=提醒天数,"年检剩"&($AA141-TODAY())&"天 ","")))&IF($AB141="","",IF($AB141<TODAY(),"限速器已过期"&(TODAY()-$AB141)&"天 ",IF($AB141-TODAY()<=提醒天数,"限速器剩"&($AB141-TODAY())&"天 ","")))&IF($AC141="","",IF($AC141<TODAY(),"载重试验已过期"&(TODAY()-$AC141)&"天 ",IF($AC141-TODAY()<=提醒天数,"载重试验剩"&($AC141-TODAY())&"天 ",""))))) | AA141: =IF(TRIM($Q141&"")="","",IF(ISNUMBER($Q141),IF($Q141>10000,$Q141,IFERROR(DATE(INT($Q141),IF(ROUND(MOD($Q141,1)*100,0)>12,ROUND(MOD($Q141,1)*10,0),ROUND(MOD($Q141,1)*100,0))+1,0),"")),IFERROR(IF(LEN($Q141)-LEN(SUBSTITUTE($Q141,".",""))>=2,DATEVALUE(SUBSTITUTE(TRIM($Q141),".","-")),DATE(VALUE(LEFT(TRIM($Q141),4)),VALUE(MID(TRIM($Q141),6,2))+1,0)),""))) | AB141: =IF(TRIM($S141&"")="","",IF(ISNUMBER($S141),IF($S141>10000,$S141,IFERROR(DATE(INT($S141),IF(ROUND(MOD($S141,1)*100,0)>12,ROUND(MOD($S141,1)*10,0),ROUND(MOD($S141,1)*100,0))+1,0),"")),IFERROR(IF(LEN($S141)-LEN(SUBSTITUTE($S141,".",""))>=2,DATEVALUE(SUBSTITUTE(TRIM($S141),".","-")),DATE(VALUE(LEFT(TRIM($S141),4)),VALUE(MID(TRIM($S141),6,2))+1,0)),""))) | AC141: =IF(TRIM($T141&"")="","",IF(ISNUMBER($T141),IF($T141>10000,$T141,IFERROR(DATE(INT($T141),IF(ROUND(MOD($T141,1)*100,0)>12,ROUND(MOD($T141,1)*10,0),ROUND(MOD($T141,1)*100,0))+1,0),"")),IFERROR(IF(LEN($T141)-LEN(SUBSTITUTE($T141,".",""))>=2,DATEVALUE(SUBSTITUTE(TRIM($T141),".","-")),DATE(VALUE(LEFT(TRIM($T141),4)),VALUE(MID(TRIM($T141),6,2))+1,0)),"")))
B142: 武汉中海联机电工程有限公司 | C142: 生态花园小区18㠉（号）1单元 | D142: Xmodel 3(MRL) | E142: 31104201022024080014 | G142: 杭州西奥电梯 | H142: 客梯(无机房) | I142: 6 | J142: 6 | K142: 6 | L142: 800kg | M142: 1.0m/s | N142: 1 | O142: XODTS28090 | P142: 1#客 | Y142: =IF(TRIM($B142&$C142)="","",IF(OR($W142="安装免保",$W142="技术免保",$W142="质保期内"),IF(NOT(ISNUMBER($X142)),"▲免保到期日没填",IF($X142<TODAY(),"▲免保已到期，转收费",IF($X142-TODAY()<=提醒天数,"免保剩"&($X142-TODAY())&"天","免保中"))),IF($W142="暂停维保","暂停中",IF($W142="已解约","已解约","")))) | Z142: =IF(TRIM($B142&$C142)="","",TRIM(IF($AA142="","",IF($AA142<TODAY(),"年检已过期"&(TODAY()-$AA142)&"天 ",IF($AA142-TODAY()<=提醒天数,"年检剩"&($AA142-TODAY())&"天 ","")))&IF($AB142="","",IF($AB142<TODAY(),"限速器已过期"&(TODAY()-$AB142)&"天 ",IF($AB142-TODAY()<=提醒天数,"限速器剩"&($AB142-TODAY())&"天 ","")))&IF($AC142="","",IF($AC142<TODAY(),"载重试验已过期"&(TODAY()-$AC142)&"天 ",IF($AC142-TODAY()<=提醒天数,"载重试验剩"&($AC142-TODAY())&"天 ",""))))) | AA142: =IF(TRIM($Q142&"")="","",IF(ISNUMBER($Q142),IF($Q142>10000,$Q142,IFERROR(DATE(INT($Q142),IF(ROUND(MOD($Q142,1)*100,0)>12,ROUND(MOD($Q142,1)*10,0),ROUND(MOD($Q142,1)*100,0))+1,0),"")),IFERROR(IF(LEN($Q142)-LEN(SUBSTITUTE($Q142,".",""))>=2,DATEVALUE(SUBSTITUTE(TRIM($Q142),".","-")),DATE(VALUE(LEFT(TRIM($Q142),4)),VALUE(MID(TRIM($Q142),6,2))+1,0)),""))) | AB142: =IF(TRIM($S142&"")="","",IF(ISNUMBER($S142),IF($S142>10000,$S142,IFERROR(DATE(INT($S142),IF(ROUND(MOD($S142,1)*100,0)>12,ROUND(MOD($S142,1)*10,0),ROUND(MOD($S142,1)*100,0))+1,0),"")),IFERROR(IF(LEN($S142)-LEN(SUBSTITUTE($S142,".",""))>=2,DATEVALUE(SUBSTITUTE(TRIM($S142),".","-")),DATE(VALUE(LEFT(TRIM($S142),4)),VALUE(MID(TRIM($S142),6,2))+1,0)),""))) | AC142: =IF(TRIM($T142&"")="","",IF(ISNUMBER($T142),IF($T142>10000,$T142,IFERROR(DATE(INT($T142),IF(ROUND(MOD($T142,1)*100,0)>12,ROUND(MOD($T142,1)*10,0),ROUND(MOD($T142,1)*100,0))+1,0),"")),IFERROR(IF(LEN($T142)-LEN(SUBSTITUTE($T142,".",""))>=2,DATEVALUE(SUBSTITUTE(TRIM($T142),".","-")),DATE(VALUE(LEFT(TRIM($T142),4)),VALUE(MID(TRIM($T142),6,2))+1,0)),"")))
B143: 中国农业科学院油料作物研究所 | C143: 油料所3号楼改造更新项目 | D143: GPS35S | E143: 31104201062024120006 | F143: 147079 | G143: 巨人通力电梯 | H143: 客梯 | I143: 5 | J143: 5 | K143: 5 | L143: 1000kg | M143: 1.0m/s | N143: 1 | O143: 45686423 | P143: 3-1 | Y143: =IF(TRIM($B143&$C143)="","",IF(OR($W143="安装免保",$W143="技术免保",$W143="质保期内"),IF(NOT(ISNUMBER($X143)),"▲免保到期日没填",IF($X143<TODAY(),"▲免保已到期，转收费",IF($X143-TODAY()<=提醒天数,"免保剩"&($X143-TODAY())&"天","免保中"))),IF($W143="暂停维保","暂停中",IF($W143="已解约","已解约","")))) | Z143: =IF(TRIM($B143&$C143)="","",TRIM(IF($AA143="","",IF($AA143<TODAY(),"年检已过期"&(TODAY()-$AA143)&"天 ",IF($AA143-TODAY()<=提醒天数,"年检剩"&($AA143-TODAY())&"天 ","")))&IF($AB143="","",IF($AB143<TODAY(),"限速器已过期"&(TODAY()-$AB143)&"天 ",IF($AB143-TODAY()<=提醒天数,"限速器剩"&($AB143-TODAY())&"天 ","")))&IF($AC143="","",IF($AC143<TODAY(),"载重试验已过期"&(TODAY()-$AC143)&"天 ",IF($AC143-TODAY()<=提醒天数,"载重试验剩"&($AC143-TODAY())&"天 ",""))))) | AA143: =IF(TRIM($Q143&"")="","",IF(ISNUMBER($Q143),IF($Q143>10000,$Q143,IFERROR(DATE(INT($Q143),IF(ROUND(MOD($Q143,1)*100,0)>12,ROUND(MOD($Q143,1)*10,0),ROUND(MOD($Q143,1)*100,0))+1,0),"")),IFERROR(IF(LEN($Q143)-LEN(SUBSTITUTE($Q143,".",""))>=2,DATEVALUE(SUBSTITUTE(TRIM($Q143),".","-")),DATE(VALUE(LEFT(TRIM($Q143),4)),VALUE(MID(TRIM($Q143),6,2))+1,0)),""))) | AB143: =IF(TRIM($S143&"")="","",IF(ISNUMBER($S143),IF($S143>10000,$S143,IFERROR(DATE(INT($S143),IF(ROUND(MOD($S143,1)*100,0)>12,ROUND(MOD($S143,1)*10,0),ROUND(MOD($S143,1)*100,0))+1,0),"")),IFERROR(IF(LEN($S143)-LEN(SUBSTITUTE($S143,".",""))>=2,DATEVALUE(SUBSTITUTE(TRIM($S143),".","-")),DATE(VALUE(LEFT(TRIM($S143),4)),VALUE(MID(TRIM($S143),6,2))+1,0)),""))) | AC143: =IF(TRIM($T143&"")="","",IF(ISNUMBER($T143),IF($T143>10000,$T143,IFERROR(DATE(INT($T143),IF(ROUND(MOD($T143,1)*100,0)>12,ROUND(MOD($T143,1)*10,0),ROUND(MOD($T143,1)*100,0))+1,0),"")),IFERROR(IF(LEN($T143)-LEN(SUBSTITUTE($T143,".",""))>=2,DATEVALUE(SUBSTITUTE(TRIM($T143),".","-")),DATE(VALUE(LEFT(TRIM($T143),4)),VALUE(MID(TRIM($T143),6,2))+1,0)),"")))
B144: 武汉市洪山区悟空星火休闲娱乐馆（个体工商户） | C144: 佳和丽枫酒店 | D144: WGJ1000/1.0 | E144: 30104201112011110130 | F144: 049427 | G144: 北京优力维特 | H144: 客梯 | I144: 4 | J144: 4 | K144: 4 | L144: 1000kg | M144: 1.0m/s | N144: 1 | O144: UL10746 | P144: 2#观 | Y144: =IF(TRIM($B144&$C144)="","",IF(OR($W144="安装免保",$W144="技术免保",$W144="质保期内"),IF(NOT(ISNUMBER($X144)),"▲免保到期日没填",IF($X144<TODAY(),"▲免保已到期，转收费",IF($X144-TODAY()<=提醒天数,"免保剩"&($X144-TODAY())&"天","免保中"))),IF($W144="暂停维保","暂停中",IF($W144="已解约","已解约","")))) | Z144: =IF(TRIM($B144&$C144)="","",TRIM(IF($AA144="","",IF($AA144<TODAY(),"年检已过期"&(TODAY()-$AA144)&"天 ",IF($AA144-TODAY()<=提醒天数,"年检剩"&($AA144-TODAY())&"天 ","")))&IF($AB144="","",IF($AB144<TODAY(),"限速器已过期"&(TODAY()-$AB144)&"天 ",IF($AB144-TODAY()<=提醒天数,"限速器剩"&($AB144-TODAY())&"天 ","")))&IF($AC144="","",IF($AC144<TODAY(),"载重试验已过期"&(TODAY()-$AC144)&"天 ",IF($AC144-TODAY()<=提醒天数,"载重试验剩"&($AC144-TODAY())&"天 ",""))))) | AA144: =IF(TRIM($Q144&"")="","",IF(ISNUMBER($Q144),IF($Q144>10000,$Q144,IFERROR(DATE(INT($Q144),IF(ROUND(MOD($Q144,1)*100,0)>12,ROUND(MOD($Q144,1)*10,0),ROUND(MOD($Q144,1)*100,0))+1,0),"")),IFERROR(IF(LEN($Q144)-LEN(SUBSTITUTE($Q144,".",""))>=2,DATEVALUE(SUBSTITUTE(TRIM($Q144),".","-")),DATE(VALUE(LEFT(TRIM($Q144),4)),VALUE(MID(TRIM($Q144),6,2))+1,0)),""))) | AB144: =IF(TRIM($S144&"")="","",IF(ISNUMBER($S144),IF($S144>10000,$S144,IFERROR(DATE(INT($S144),IF(ROUND(MOD($S144,1)*100,0)>12,ROUND(MOD($S144,1)*10,0),ROUND(MOD($S144,1)*100,0))+1,0),"")),IFERROR(IF(LEN($S144)-LEN(SUBSTITUTE($S144,".",""))>=2,DATEVALUE(SUBSTITUTE(TRIM($S144),".","-")),DATE(VALUE(LEFT(TRIM($S144),4)),VALUE(MID(TRIM($S144),6,2))+1,0)),""))) | AC144: =IF(TRIM($T144&"")="","",IF(ISNUMBER($T144),IF($T144>10000,$T144,IFERROR(DATE(INT($T144),IF(ROUND(MOD($T144,1)*100,0)>12,ROUND(MOD($T144,1)*10,0),ROUND(MOD($T144,1)*100,0))+1,0),"")),IFERROR(IF(LEN($T144)-LEN(SUBSTITUTE($T144,".",""))>=2,DATEVALUE(SUBSTITUTE(TRIM($T144),".","-")),DATE(VALUE(LEFT(TRIM($T144),4)),VALUE(MID(TRIM($T144),6,2))+1,0)),"")))
B145: 武汉中海联机电工程有限公司 | C145: 安友花园A栋3单元 | D145: KTKJ | E145: 31104201032025010004 | F145: 203833 | G145: 福州快科 | H145: 客梯(无机房) | I145: 8 | J145: 7 | K145: 7 | L145: 630kg | M145: 1.0m/s | N145: 1 | O145: K.E30-2400145 | P145: 1#客 | Y145: =IF(TRIM($B145&$C145)="","",IF(OR($W145="安装免保",$W145="技术免保",$W145="质保期内"),IF(NOT(ISNUMBER($X145)),"▲免保到期日没填",IF($X145<TODAY(),"▲免保已到期，转收费",IF($X145-TODAY()<=提醒天数,"免保剩"&($X145-TODAY())&"天","免保中"))),IF($W145="暂停维保","暂停中",IF($W145="已解约","已解约","")))) | Z145: =IF(TRIM($B145&$C145)="","",TRIM(IF($AA145="","",IF($AA145<TODAY(),"年检已过期"&(TODAY()-$AA145)&"天 ",IF($AA145-TODAY()<=提醒天数,"年检剩"&($AA145-TODAY())&"天 ","")))&IF($AB145="","",IF($AB145<TODAY(),"限速器已过期"&(TODAY()-$AB145)&"天 ",IF($AB145-TODAY()<=提醒天数,"限速器剩"&($AB145-TODAY())&"天 ","")))&IF($AC145="","",IF($AC145<TODAY(),"载重试验已过期"&(TODAY()-$AC145)&"天 ",IF($AC145-TODAY()<=提醒天数,"载重试验剩"&($AC145-TODAY())&"天 ",""))))) | AA145: =IF(TRIM($Q145&"")="","",IF(ISNUMBER($Q145),IF($Q145>10000,$Q145,IFERROR(DATE(INT($Q145),IF(ROUND(MOD($Q145,1)*100,0)>12,ROUND(MOD($Q145,1)*10,0),ROUND(MOD($Q145,1)*100,0))+1,0),"")),IFERROR(IF(LEN($Q145)-LEN(SUBSTITUTE($Q145,".",""))>=2,DATEVALUE(SUBSTITUTE(TRIM($Q145),".","-")),DATE(VALUE(LEFT(TRIM($Q145),4)),VALUE(MID(TRIM($Q145),6,2))+1,0)),""))) | AB145: =IF(TRIM($S145&"")="","",IF(ISNUMBER($S145),IF($S145>10000,$S145,IFERROR(DATE(INT($S145),IF(ROUND(MOD($S145,1)*100,0)>12,ROUND(MOD($S145,1)*10,0),ROUND(MOD($S145,1)*100,0))+1,0),"")),IFERROR(IF(LEN($S145)-LEN(SUBSTITUTE($S145,".",""))>=2,DATEVALUE(SUBSTITUTE(TRIM($S145),".","-")),DATE(VALUE(LEFT(TRIM($S145),4)),VALUE(MID(TRIM($S145),6,2))+1,0)),""))) | AC145: =IF(TRIM($T145&"")="","",IF(ISNUMBER($T145),IF($T145>10000,$T145,IFERROR(DATE(INT($T145),IF(ROUND(MOD($T145,1)*100,0)>12,ROUND(MOD($T145,1)*10,0),ROUND(MOD($T145,1)*100,0))+1,0),"")),IFERROR(IF(LEN($T145)-LEN(SUBSTITUTE($T145,".",""))>=2,DATEVALUE(SUBSTITUTE(TRIM($T145),".","-")),DATE(VALUE(LEFT(TRIM($T145),4)),VALUE(MID(TRIM($T145),6,2))+1,0)),"")))
B146: 武汉中海联机电工程有限公司（法院宿舍） | C146: 后湖法院宿舍 | D146: FUJI-WK | E146: 31104201022025040006 | F146: 203832 | G146: 亚洲富士电梯 | H146: 客梯(无机房) | I146: 7 | J146: 6 | K146: 6 | L146: 800kg | M146: 1.0m/s | N146: 1 | O146: FUJI2025010003 | P146: 1#客 | Y146: =IF(TRIM($B146&$C146)="","",IF(OR($W146="安装免保",$W146="技术免保",$W146="质保期内"),IF(NOT(ISNUMBER($X146)),"▲免保到期日没填",IF($X146<TODAY(),"▲免保已到期，转收费",IF($X146-TODAY()<=提醒天数,"免保剩"&($X146-TODAY())&"天","免保中"))),IF($W146="暂停维保","暂停中",IF($W146="已解约","已解约","")))) | Z146: =IF(TRIM($B146&$C146)="","",TRIM(IF($AA146="","",IF($AA146<TODAY(),"年检已过期"&(TODAY()-$AA146)&"天 ",IF($AA146-TODAY()<=提醒天数,"年检剩"&($AA146-TODAY())&"天 ","")))&IF($AB146="","",IF($AB146<TODAY(),"限速器已过期"&(TODAY()-$AB146)&"天 ",IF($AB146-TODAY()<=提醒天数,"限速器剩"&($AB146-TODAY())&"天 ","")))&IF($AC146="","",IF($AC146<TODAY(),"载重试验已过期"&(TODAY()-$AC146)&"天 ",IF($AC146-TODAY()<=提醒天数,"载重试验剩"&($AC146-TODAY())&"天 ",""))))) | AA146: =IF(TRIM($Q146&"")="","",IF(ISNUMBER($Q146),IF($Q146>10000,$Q146,IFERROR(DATE(INT($Q146),IF(ROUND(MOD($Q146,1)*100,0)>12,ROUND(MOD($Q146,1)*10,0),ROUND(MOD($Q146,1)*100,0))+1,0),"")),IFERROR(IF(LEN($Q146)-LEN(SUBSTITUTE($Q146,".",""))>=2,DATEVALUE(SUBSTITUTE(TRIM($Q146),".","-")),DATE(VALUE(LEFT(TRIM($Q146),4)),VALUE(MID(TRIM($Q146),6,2))+1,0)),""))) | AB146: =IF(TRIM($S146&"")="","",IF(ISNUMBER($S146),IF($S146>10000,$S146,IFERROR(DATE(INT($S146),IF(ROUND(MOD($S146,1)*100,0)>12,ROUND(MOD($S146,1)*10,0),ROUND(MOD($S146,1)*100,0))+1,0),"")),IFERROR(IF(LEN($S146)-LEN(SUBSTITUTE($S146,".",""))>=2,DATEVALUE(SUBSTITUTE(TRIM($S146),".","-")),DATE(VALUE(LEFT(TRIM($S146),4)),VALUE(MID(TRIM($S146),6,2))+1,0)),""))) | AC146: =IF(TRIM($T146&"")="","",IF(ISNUMBER($T146),IF($T146>10000,$T146,IFERROR(DATE(INT($T146),IF(ROUND(MOD($T146,1)*100,0)>12,ROUND(MOD($T146,1)*10,0),ROUND(MOD($T146,1)*100,0))+1,0),"")),IFERROR(IF(LEN($T146)-LEN(SUBSTITUTE($T146,".",""))>=2,DATEVALUE(SUBSTITUTE(TRIM($T146),".","-")),DATE(VALUE(LEFT(TRIM($T146),4)),VALUE(MID(TRIM($T146),6,2))+1,0)),"")))
B147: 武汉鑫润塑业有限公司 | C147: （汉南）纱帽街/幸福园路与解放河路交汇处 | D147: TKJ1050/1.0 | E147: 31104201132025073136 | F147: 213600 | G147: 赛奥智能电梯（苏州）有限公司 | H147: 客梯 | I147: 4 | J147: 4 | K147: 4 | L147: 1050kg | M147: 1.0m/s | N147: 1 | O147: S241666 | P147: 1#客 | Y147: =IF(TRIM($B147&$C147)="","",IF(OR($W147="安装免保",$W147="技术免保",$W147="质保期内"),IF(NOT(ISNUMBER($X147)),"▲免保到期日没填",IF($X147<TODAY(),"▲免保已到期，转收费",IF($X147-TODAY()<=提醒天数,"免保剩"&($X147-TODAY())&"天","免保中"))),IF($W147="暂停维保","暂停中",IF($W147="已解约","已解约","")))) | Z147: =IF(TRIM($B147&$C147)="","",TRIM(IF($AA147="","",IF($AA147<TODAY(),"年检已过期"&(TODAY()-$AA147)&"天 ",IF($AA147-TODAY()<=提醒天数,"年检剩"&($AA147-TODAY())&"天 ","")))&IF($AB147="","",IF($AB147<TODAY(),"限速器已过期"&(TODAY()-$AB147)&"天 ",IF($AB147-TODAY()<=提醒天数,"限速器剩"&($AB147-TODAY())&"天 ","")))&IF($AC147="","",IF($AC147<TODAY(),"载重试验已过期"&(TODAY()-$AC147)&"天 ",IF($AC147-TODAY()<=提醒天数,"载重试验剩"&($AC147-TODAY())&"天 ",""))))) | AA147: =IF(TRIM($Q147&"")="","",IF(ISNUMBER($Q147),IF($Q147>10000,$Q147,IFERROR(DATE(INT($Q147),IF(ROUND(MOD($Q147,1)*100,0)>12,ROUND(MOD($Q147,1)*10,0),ROUND(MOD($Q147,1)*100,0))+1,0),"")),IFERROR(IF(LEN($Q147)-LEN(SUBSTITUTE($Q147,".",""))>=2,DATEVALUE(SUBSTITUTE(TRIM($Q147),".","-")),DATE(VALUE(LEFT(TRIM($Q147),4)),VALUE(MID(TRIM($Q147),6,2))+1,0)),""))) | AB147: =IF(TRIM($S147&"")="","",IF(ISNUMBER($S147),IF($S147>10000,$S147,IFERROR(DATE(INT($S147),IF(ROUND(MOD($S147,1)*100,0)>12,ROUND(MOD($S147,1)*10,0),ROUND(MOD($S147,1)*100,0))+1,0),"")),IFERROR(IF(LEN($S147)-LEN(SUBSTITUTE($S147,".",""))>=2,DATEVALUE(SUBSTITUTE(TRIM($S147),".","-")),DATE(VALUE(LEFT(TRIM($S147),4)),VALUE(MID(TRIM($S147),6,2))+1,0)),""))) | AC147: =IF(TRIM($T147&"")="","",IF(ISNUMBER($T147),IF($T147>10000,$T147,IFERROR(DATE(INT($T147),IF(ROUND(MOD($T147,1)*100,0)>12,ROUND(MOD($T147,1)*10,0),ROUND(MOD($T147,1)*100,0))+1,0),"")),IFERROR(IF(LEN($T147)-LEN(SUBSTITUTE($T147,".",""))>=2,DATEVALUE(SUBSTITUTE(TRIM($T147),".","-")),DATE(VALUE(LEFT(TRIM($T147),4)),VALUE(MID(TRIM($T147),6,2))+1,0)),"")))
B148: 武汉中海联机电工程有限公司 | C148: 百步亭温馨苑AB区306栋1单元 | D148: GPN65 | E148: 31104201022025070005 | F148: 212640 | G148: 巨人通力电梯 | H148: 客梯(无机房) | I148: 7 | J148: 7 | K148: 7 | L148: 800kg | M148: 1.0m/s | N148: 1 | O148: 45842384 | P148: 1#客 | Y148: =IF(TRIM($B148&$C148)="","",IF(OR($W148="安装免保",$W148="技术免保",$W148="质保期内"),IF(NOT(ISNUMBER($X148)),"▲免保到期日没填",IF($X148<TODAY(),"▲免保已到期，转收费",IF($X148-TODAY()<=提醒天数,"免保剩"&($X148-TODAY())&"天","免保中"))),IF($W148="暂停维保","暂停中",IF($W148="已解约","已解约","")))) | Z148: =IF(TRIM($B148&$C148)="","",TRIM(IF($AA148="","",IF($AA148<TODAY(),"年检已过期"&(TODAY()-$AA148)&"天 ",IF($AA148-TODAY()<=提醒天数,"年检剩"&($AA148-TODAY())&"天 ","")))&IF($AB148="","",IF($AB148<TODAY(),"限速器已过期"&(TODAY()-$AB148)&"天 ",IF($AB148-TODAY()<=提醒天数,"限速器剩"&($AB148-TODAY())&"天 ","")))&IF($AC148="","",IF($AC148<TODAY(),"载重试验已过期"&(TODAY()-$AC148)&"天 ",IF($AC148-TODAY()<=提醒天数,"载重试验剩"&($AC148-TODAY())&"天 ",""))))) | AA148: =IF(TRIM($Q148&"")="","",IF(ISNUMBER($Q148),IF($Q148>10000,$Q148,IFERROR(DATE(INT($Q148),IF(ROUND(MOD($Q148,1)*100,0)>12,ROUND(MOD($Q148,1)*10,0),ROUND(MOD($Q148,1)*100,0))+1,0),"")),IFERROR(IF(LEN($Q148)-LEN(SUBSTITUTE($Q148,".",""))>=2,DATEVALUE(SUBSTITUTE(TRIM($Q148),".","-")),DATE(VALUE(LEFT(TRIM($Q148),4)),VALUE(MID(TRIM($Q148),6,2))+1,0)),""))) | AB148: =IF(TRIM($S148&"")="","",IF(ISNUMBER($S148),IF($S148>10000,$S148,IFERROR(DATE(INT($S148),IF(ROUND(MOD($S148,1)*100,0)>12,ROUND(MOD($S148,1)*10,0),ROUND(MOD($S148,1)*100,0))+1,0),"")),IFERROR(IF(LEN($S148)-LEN(SUBSTITUTE($S148,".",""))>=2,DATEVALUE(SUBSTITUTE(TRIM($S148),".","-")),DATE(VALUE(LEFT(TRIM($S148),4)),VALUE(MID(TRIM($S148),6,2))+1,0)),""))) | AC148: =IF(TRIM($T148&"")="","",IF(ISNUMBER($T148),IF($T148>10000,$T148,IFERROR(DATE(INT($T148),IF(ROUND(MOD($T148,1)*100,0)>12,ROUND(MOD($T148,1)*10,0),ROUND(MOD($T148,1)*100,0))+1,0),"")),IFERROR(IF(LEN($T148)-LEN(SUBSTITUTE($T148,".",""))>=2,DATEVALUE(SUBSTITUTE(TRIM($T148),".","-")),DATE(VALUE(LEFT(TRIM($T148),4)),VALUE(MID(TRIM($T148),6,2))+1,0)),"")))
B149: 武汉中海联机电工程有限公司（百合苑） | C149: 百步亭百合苑208栋1单元 | D149: GPN65 | E149: 31104201022025050129 | F149: 212641 | G149: 巨人通力电梯 | H149: 客梯(无机房) | I149: 6 | J149: 6 | K149: 6 | L149: 800kg | M149: 1.0m/s | N149: 1 | O149: 45475376 | P149: 1#客 | Q149: 2027.8 | Y149: =IF(TRIM($B149&$C149)="","",IF(OR($W149="安装免保",$W149="技术免保",$W149="质保期内"),IF(NOT(ISNUMBER($X149)),"▲免保到期日没填",IF($X149<TODAY(),"▲免保已到期，转收费",IF($X149-TODAY()<=提醒天数,"免保剩"&($X149-TODAY())&"天","免保中"))),IF($W149="暂停维保","暂停中",IF($W149="已解约","已解约","")))) | Z149: =IF(TRIM($B149&$C149)="","",TRIM(IF($AA149="","",IF($AA149<TODAY(),"年检已过期"&(TODAY()-$AA149)&"天 ",IF($AA149-TODAY()<=提醒天数,"年检剩"&($AA149-TODAY())&"天 ","")))&IF($AB149="","",IF($AB149<TODAY(),"限速器已过期"&(TODAY()-$AB149)&"天 ",IF($AB149-TODAY()<=提醒天数,"限速器剩"&($AB149-TODAY())&"天 ","")))&IF($AC149="","",IF($AC149<TODAY(),"载重试验已过期"&(TODAY()-$AC149)&"天 ",IF($AC149-TODAY()<=提醒天数,"载重试验剩"&($AC149-TODAY())&"天 ",""))))) | AA149: =IF(TRIM($Q149&"")="","",IF(ISNUMBER($Q149),IF($Q149>10000,$Q149,IFERROR(DATE(INT($Q149),IF(ROUND(MOD($Q149,1)*100,0)>12,ROUND(MOD($Q149,1)*10,0),ROUND(MOD($Q149,1)*100,0))+1,0),"")),IFERROR(IF(LEN($Q149)-LEN(SUBSTITUTE($Q149,".",""))>=2,DATEVALUE(SUBSTITUTE(TRIM($Q149),".","-")),DATE(VALUE(LEFT(TRIM($Q149),4)),VALUE(MID(TRIM($Q149),6,2))+1,0)),""))) -> 46630 | AB149: =IF(TRIM($S149&"")="","",IF(ISNUMBER($S149),IF($S149>10000,$S149,IFERROR(DATE(INT($S149),IF(ROUND(MOD($S149,1)*100,0)>12,ROUND(MOD($S149,1)*10,0),ROUND(MOD($S149,1)*100,0))+1,0),"")),IFERROR(IF(LEN($S149)-LEN(SUBSTITUTE($S149,".",""))>=2,DATEVALUE(SUBSTITUTE(TRIM($S149),".","-")),DATE(VALUE(LEFT(TRIM($S149),4)),VALUE(MID(TRIM($S149),6,2))+1,0)),""))) | AC149: =IF(TRIM($T149&"")="","",IF(ISNUMBER($T149),IF($T149>10000,$T149,IFERROR(DATE(INT($T149),IF(ROUND(MOD($T149,1)*100,0)>12,ROUND(MOD($T149,1)*10,0),ROUND(MOD($T149,1)*100,0))+1,0),"")),IFERROR(IF(LEN($T149)-LEN(SUBSTITUTE($T149,".",""))>=2,DATEVALUE(SUBSTITUTE(TRIM($T149),".","-")),DATE(VALUE(LEFT(TRIM($T149),4)),VALUE(MID(TRIM($T149),6,2))+1,0)),"")))
B150: 武汉中海联机电工程有限公司 | C150: 幸乐村小区8幢（号）1单元 | D150: XO-GMEIII（MRL)-1 | E150: 31104201042025060007 | F150: 212871 | G150: 杭州西奥 | H150: 客梯 | I150: 5 | J150: 5 | K150: 5 | L150: 550kg | M150: 1.0m/s | N150: 1 | O150: XODTJ25931 | P150: 1#客 | Y150: =IF(TRIM($B150&$C150)="","",IF(OR($W150="安装免保",$W150="技术免保",$W150="质保期内"),IF(NOT(ISNUMBER($X150)),"▲免保到期日没填",IF($X150<TODAY(),"▲免保已到期，转收费",IF($X150-TODAY()<=提醒天数,"免保剩"&($X150-TODAY())&"天","免保中"))),IF($W150="暂停维保","暂停中",IF($W150="已解约","已解约","")))) | Z150: =IF(TRIM($B150&$C150)="","",TRIM(IF($AA150="","",IF($AA150<TODAY(),"年检已过期"&(TODAY()-$AA150)&"天 ",IF($AA150-TODAY()<=提醒天数,"年检剩"&($AA150-TODAY())&"天 ","")))&IF($AB150="","",IF($AB150<TODAY(),"限速器已过期"&(TODAY()-$AB150)&"天 ",IF($AB150-TODAY()<=提醒天数,"限速器剩"&($AB150-TODAY())&"天 ","")))&IF($AC150="","",IF($AC150<TODAY(),"载重试验已过期"&(TODAY()-$AC150)&"天 ",IF($AC150-TODAY()<=提醒天数,"载重试验剩"&($AC150-TODAY())&"天 ",""))))) | AA150: =IF(TRIM($Q150&"")="","",IF(ISNUMBER($Q150),IF($Q150>10000,$Q150,IFERROR(DATE(INT($Q150),IF(ROUND(MOD($Q150,1)*100,0)>12,ROUND(MOD($Q150,1)*10,0),ROUND(MOD($Q150,1)*100,0))+1,0),"")),IFERROR(IF(LEN($Q150)-LEN(SUBSTITUTE($Q150,".",""))>=2,DATEVALUE(SUBSTITUTE(TRIM($Q150),".","-")),DATE(VALUE(LEFT(TRIM($Q150),4)),VALUE(MID(TRIM($Q150),6,2))+1,0)),""))) | AB150: =IF(TRIM($S150&"")="","",IF(ISNUMBER($S150),IF($S150>10000,$S150,IFERROR(DATE(INT($S150),IF(ROUND(MOD($S150,1)*100,0)>12,ROUND(MOD($S150,1)*10,0),ROUND(MOD($S150,1)*100,0))+1,0),"")),IFERROR(IF(LEN($S150)-LEN(SUBSTITUTE($S150,".",""))>=2,DATEVALUE(SUBSTITUTE(TRIM($S150),".","-")),DATE(VALUE(LEFT(TRIM($S150),4)),VALUE(MID(TRIM($S150),6,2))+1,0)),""))) | AC150: =IF(TRIM($T150&"")="","",IF(ISNUMBER($T150),IF($T150>10000,$T150,IFERROR(DATE(INT($T150),IF(ROUND(MOD($T150,1)*100,0)>12,ROUND(MOD($T150,1)*10,0),ROUND(MOD($T150,1)*100,0))+1,0),"")),IFERROR(IF(LEN($T150)-LEN(SUBSTITUTE($T150,".",""))>=2,DATEVALUE(SUBSTITUTE(TRIM($T150),".","-")),DATE(VALUE(LEFT(TRIM($T150),4)),VALUE(MID(TRIM($T150),6,2))+1,0)),"")))
B151: 升福楼宇工程有限公司 | C151: 百步亭怡康苑北区214栋一单元 | D151: TKJW | E151: 31104201022023080029 | G151: 通用电梯 | H151: 客梯(无机房) | I151: 6 | J151: 6 | K151: 6 | L151: 800kg | M151: 1.0m/s | N151: 1 | O151: GE2301102K | Y151: =IF(TRIM($B151&$C151)="","",IF(OR($W151="安装免保",$W151="技术免保",$W151="质保期内"),IF(NOT(ISNUMBER($X151)),"▲免保到期日没填",IF($X151<TODAY(),"▲免保已到期，转收费",IF($X151-TODAY()<=提醒天数,"免保剩"&($X151-TODAY())&"天","免保中"))),IF($W151="暂停维保","暂停中",IF($W151="已解约","已解约","")))) | Z151: =IF(TRIM($B151&$C151)="","",TRIM(IF($AA151="","",IF($AA151<TODAY(),"年检已过期"&(TODAY()-$AA151)&"天 ",IF($AA151-TODAY()<=提醒天数,"年检剩"&($AA151-TODAY())&"天 ","")))&IF($AB151="","",IF($AB151<TODAY(),"限速器已过期"&(TODAY()-$AB151)&"天 ",IF($AB151-TODAY()<=提醒天数,"限速器剩"&($AB151-TODAY())&"天 ","")))&IF($AC151="","",IF($AC151<TODAY(),"载重试验已过期"&(TODAY()-$AC151)&"天 ",IF($AC151-TODAY()<=提醒天数,"载重试验剩"&($AC151-TODAY())&"天 ",""))))) | AA151: =IF(TRIM($Q151&"")="","",IF(ISNUMBER($Q151),IF($Q151>10000,$Q151,IFERROR(DATE(INT($Q151),IF(ROUND(MOD($Q151,1)*100,0)>12,ROUND(MOD($Q151,1)*10,0),ROUND(MOD($Q151,1)*100,0))+1,0),"")),IFERROR(IF(LEN($Q151)-LEN(SUBSTITUTE($Q151,".",""))>=2,DATEVALUE(SUBSTITUTE(TRIM($Q151),".","-")),DATE(VALUE(LEFT(TRIM($Q151),4)),VALUE(MID(TRIM($Q151),6,2))+1,0)),""))) | AB151: =IF(TRIM($S151&"")="","",IF(ISNUMBER($S151),IF($S151>10000,$S151,IFERROR(DATE(INT($S151),IF(ROUND(MOD($S151,1)*100,0)>12,ROUND(MOD($S151,1)*10,0),ROUND(MOD($S151,1)*100,0))+1,0),"")),IFERROR(IF(LEN($S151)-LEN(SUBSTITUTE($S151,".",""))>=2,DATEVALUE(SUBSTITUTE(TRIM($S151),".","-")),DATE(VALUE(LEFT(TRIM($S151),4)),VALUE(MID(TRIM($S151),6,2))+1,0)),""))) | AC151: =IF(TRIM($T151&"")="","",IF(ISNUMBER($T151),IF($T151>10000,$T151,IFERROR(DATE(INT($T151),IF(ROUND(MOD($T151,1)*100,0)>12,ROUND(MOD($T151,1)*10,0),ROUND(MOD($T151,1)*100,0))+1,0),"")),IFERROR(IF(LEN($T151)-LEN(SUBSTITUTE($T151,".",""))>=2,DATEVALUE(SUBSTITUTE(TRIM($T151),".","-")),DATE(VALUE(LEFT(TRIM($T151),4)),VALUE(MID(TRIM($T151),6,2))+1,0)),"")))
