Workbook

Sheet 主页
A1: 02 物 料 与 周 转 物 台 账
A2: 包装物料 / 公司周转筐 / 客户自备筐 / 次果筐与托盘 ｜ 逐笔对账请到《04 综合查询对账单》 ｜ 点蓝色表名跳转
A3: =IF(N(对接源_01水果筐数!$S$1)=0,"联动状态：★★ 01 水果台账的筐数没接进来 —— 请打开【对接源_01水果筐数】按提示修复链接",IF(N(对接源_01水果筐数!$S$4)=0,"联动状态：⚠ 正在用【应急备份】的筐数（不是实时数），共 "&N(对接源_01水果筐数!$S$1)&" 行，请尽快修复链接","联动状态：✔ 正常 —— 已从《01 水果进销存台账》自动接入 "&N(对接源_01水果筐数!$S$1)&" 行筐子进出数据")) -> 联动状态：✔ 正常 —— 已从《01 水果进销存台账》自动接入 22 行筐子进出数据
A5: 一、日常录入（每天要填的表）
A6: 序号 | B6: 子表名称 | C6: 用途说明 | D6: 属性
A7: 1 | B7: 包装物料出入库明细 | C7: 物料进出与销售；计价数量和合计金额自动算 | D7: 手工录入
A8: 2 | B8: 周转筐出入库明细 | C8: 公司筐的采购、发出、客户退回、卖断；剩余库存按类型自动滚动；含收退押金 | D8: 手工录入
A9: 3 | B9: 客户自备筐明细 | C9: 客户自己带来的筐子，表外备查 | D9: 手工录入
A10: 4 | B10: 次果筐明细 | C10: 次果筐与托盘合并在这一张；含押金与退款情况 | D10: 手工录入
A11: 5 | B11: 实盘库存盘点 | C11: 只在右半边录实盘数量，左半边账面数与盘盈盘亏全自动 | D11: 半自动
A13: 二、库存与往来（全部自动，不用填）
A14: 序号 | B14: 子表名称 | C14: 用途说明 | D14: 属性
A15: 6 | B15: 物料库存结余 | C15: 按物料看期初/采购/退回/领用/销售与剩余库存、库存金额 | D15: 全自动
A16: 7 | B16: 筐子库存汇总 | C16: 公司每种筐子还剩多少、客户手上多少、公司筐总量 | D16: 全自动
A17: 8 | B17: 筐子往来汇总 | C17: 按客户/供应商看发出、退回、采购三组，已含01册带出带回的筐数 | D17: 全自动
A18: 9 | B18: 筐子销售汇总 | C18: 卖断给客户的筐子数量、金额、已收未收 | D18: 全自动
A19: 10 | B19: 自备筐汇总 | C19: 客户自备筐进出与结存，联动01册成品出库带走的自备筐 | D19: 全自动
A20: 11 | B20: 次果筐汇总 | C20: 次果筐/托盘按客户的出库、退回、未回与押金 | D20: 全自动
A21: 12 | B21: 押金汇总 | C21: 每家客户收了多少、退了多少、还欠客户多少押金 | D21: 全自动
A22: 13 | B22: 客户领用物料汇总 | C22: 按客户看各物料领用量、退回量、净领用与销售应收 | D22: 全自动
A23: 14 | B23: 收入结算汇总 | C23: 筐子销售、物料销售两项收入 ＋ 押金专区 ＋ 期末存货 | D23: 全自动
A25: 三、对接与码表
A26: 序号 | B26: 子表名称 | C26: 用途说明 | D26: 属性
A27: 15 | B27: 对接源_01水果筐数 | C27: 跨文件取《01 水果进销存台账》的筐子进出数，断链自动切备份 | D27: 全自动
A28: 16 | B28: 财务取数接口 | C28: 给《03 财务账套》按月取数用 | D28: 全自动
A29: 17 | B29: 基础资料 | C29: 物料、筐子类型、托盘类型、客户、供应商等下拉选项来源 | D29: 码表
A30: 18 | B30: 字段对照 | C30: 原有 Excel 字段 → 本册字段的对照表，存档备查 | D30: 说明
A32: 图例：浅绿＝公式自动生成，请勿覆盖 ｜ 浅蓝＝需要手工录入 ｜ 浅黄＝码表/规则，偶尔维护

Sheet 使用说明
A1: 物料与周转物台账 使 用 说 明
A2: 替代原《2025年包装物料出入库明细》《2025年筐子出入库明细》及《杨威威杨元威黄红梅》筐子部分
B4: 一、六条业务线，六张明细表
B6: ① 包装物料（气泡垫、无纺布、香梨网、苹果网、纸垫板…）→【包装物料出入库明细】
B7: ② 公司周转筐（一次性筐/杂周转筐/新周转筐/白周转筐）发放与回收 →【周转筐出入库明细】
B8: ③ 筐子卖给客户 →【筐子销售明细】（不再走②，避免重复冲减库存）
B9: ④ 客户自己带来的筐子 →【客户自备筐明细】
B10: ⑤ 拉次果专用的租借筐 →【次果筐明细】（含应收使用费）
B11: ⑥ 托盘 →【托盘出入库明细】
B13: 二、关键约定
B15: · 客户随原料车带回来的公司筐子，请在【周转筐出入库明细】登记为“退回数量”，归还者填客户名。
B16: 这样【筐子往来汇总】的“未回库数量＝发出−退回”就是完整的，不用再去水果册对数。
B17: · 筐子卖断（不再收回）的走【筐子销售明细】；只是借出的走【周转筐出入库明细】。
B18: · 【周转筐出入库明细】的“剩余库存”是公司全部筐子的滚动结存（与原表口径一致，不分类型），
... B65: "净领用"＝两者相减，才是客户真正用掉的。
A67: ★ 本 次 更 新（2026-09）
A68: 1、【自备筐汇总】口径扩大：＝【客户自备加工筐明细】＋《01》原料入库带回、原料出库带走、成品出库带走中筐子类型以「自备」开头的随货筐数。入库合计＝C＋D，出库合计＝E＋J＋K，剩余在库＝入库合计−出库合计。
A69: 2、【筐子往来汇总】V/W 两列只取《01》里筐子类型不以「自备」开头的（即公司筐）；【筐子库存汇总】也不再统计自备类型。
A70: 3、筐子类型下拉已统一加「公司…／自备…」前缀，见【基础资料】B 列。
A71: 4、【对账明细接口】新增 N～S 列（筐子类型、发出筐数、退回筐数、入库筐数、车牌号、筐子归属），供《04》的分类对账单取数，请勿改动结构。
A73: ★ 本 次 更 新（2026-09 · 第三版）
A74: 1、【筐子往来汇总】重建为 5 种公司筐（一次性/杂周转/新周转/白周转/红周转）分列：发出、退回、采购入库、销售各 5 列＋合计，再加《01》的 原料入库／原料出库／成品出库 各 5 列，最后是未回库 5 列＋合计。01 册三张明细按「筐子类型」一一对应取数，不再混在一起。
A75: 2、新增【筐子采购汇总】：按供应商汇总【周转筐出入库明细】里业务类型＝「采购入库」的数量、金额、已付与未付。
A76: 3、所有汇总界面第 2 行右边新增「开始日期／结束日期」，留空＝不限时间。
A77: 4、「退回数量」「退押金」「客户退回入库」「随货回库」等一律显示为红色负数（录入仍填正数），未回库数量＝发出＋退回（负）＋随货回库（负），可以直接相加。
A79: ★ 修 正 记 录（2026-09 · 第四版）
A80: 1、修正【对接源_01水果筐数】：原来 B 列（客户/货主）被写死指向 01 的第 4 行，导致整列都显示同一个客户、下面全是空白。现在 300 行逐行一一对应，取数正常。
... A88: 4、【财务取数接口】第四块改成每家客户两行：筐子销售款 / 物料销售款，供《03 往来对账单》分项显示。

Sheet 基础资料
A1: 基 础 资 料（下拉选项来源 + 物料价目表，可自行增删）
A2: ★ 右侧“物料价目表”的参考单价是明细表自动带价的依据，价格调整请直接改这里
A3: 物料种类 | B3: 筐子类型 | C3: 托盘类型 | D3: 客户/领取人 | E3: 供应商 | F3: 物料业务类型 | G3: 筐子业务类型 | H3: 装卸方式 | I3: 核查结果 | J3: 结算方式 | K3: 收/付款状态 | L3: 筐子用途 | N3: 物料名称 | O3: 规格 | P3: 计量单位 | R3: 库存阈值 | S3: 数量
A4: 气泡垫 | B4: 公司一次性筐 | C4: 大托盘 | D4: 聂新平 | E4: 鑫旺塑业 | F4: 期初库存 | G4: 期初库存 | H4: 依力 | I4: 1 | J4: 现金 | K4: 已收讫 | L4: 拉次果 | N4: 气泡垫 | O4: *1000 | P4: 片 | R4: 充足 | S4: 5000
A5: 无纺布 | B5: 公司杂周转筐 | D5: 王照雪 | E5: 华鑫塑业 | F5: 采购入库 | G5: 采购入库 | H5: 叉车 | I5: 待核对 | J5: 银行转账 | K5: 部分收款 | L5: 拉原料 | N5: 无纺布 | O5: *400 | P5: 个 | R5: 正常 | S5: 50
A6: 香梨网 | B6: 公司新周转筐 | D6: 伍元虎 | E6: 全修塑业 | F6: 退回入库 | G6: 退回入库 | H6: 自卸 | I6: 异常 | J6: 微信 | K6: 未收款 | L6: 拉扎伤果 | N6: 香梨网 | O6: *包 | P6: 包 | R6: 不足 | S6: 0
A7: 苹果网 | B7: 公司白周转筐 | D7: 麦麦提 | E7: 新顺发泡网 | F7: 领用出库 | G7: 领用出库 | H7: 自装 | J7: 支付宝 | K7: 无需收款 | L7: 租筐退回 | N7: 苹果网 | O7: *包 | P7: 包
A8: 纸垫板 | B8: 公司红周转筐 | D8: 热合曼 | E8: 武宁气泡垫 | F8: 销售出库 | G8: 销售出库 | H8: 快递 | J8: 承兑汇票 | K8: 已付款 | L8: 原筐出库 | N8: 纸垫板 | O8: *100张 | P8: 张
A9: 香梨纸 | B9: 自备一次性筐 | D9: 王灵云 | F9: 果然鲜自用 | G9: 果然鲜自用 | H9: 筐厂 | J9: 抵账 | K9: 部分付款 | L9: 粉碎加工 | N9: 香梨纸 | O9: *捆 | P9: 捆
A10: 苹果纸 | B10: 自备杂周转筐 | D10: 马锦祥 | F10: 报损 | G10: 报损 | H10: 自提 | J10: 赊销挂账 | K10: 未付款 | L10: 购买次果 | N10: 保温棉 | O10: *两卷/套 | P10: 套
A11: 保温棉 | D11: 贾建国 | F11: 调拨 | G11: 调拨 | H11: 无 | J11: 预收冲抵 | K11: 无需付款 | L11: 退回 | N11: 塑料布 | O11: *张 | P11: 张
A12: 塑料布 | D12: 荆建君 | L12: 其他 | N12: 五合板0.5 | O12: *块 | P12: 块
A13: 五合板0.5 | D13: 艾合买提 | N13: 五合板0.3 | O13: *块 | P13: 块
A14: 五合板0.3 | D14: 王浩 | N14: 打包带 | O14: *卷 | P14: 卷
A15: 打包带 | D15: 电商/主播 | N15: 封口袋 | P15: 个
A16: 封口袋 | D16: 吐尔逊 | N16: 打包器 | P16: 个
A17: 打包器 | D17: 张艺 | N17: 胶带 | O17: *30卷 | P17: 卷
A18: 胶带 | D18: 郭勇义 | N18: 保鲜膜 | P18: 卷
A19: 保鲜膜 | D19: 王庆文 | N19: 保鲜袋 | P19: 个
A20: 保鲜袋 | D20: 果然鲜 | N20: 一级标签 | P20: 张
A21: 一级标签 | D21: 努尔敦 | N21: 副特标签 | P21: 张
A22: 副特标签 | D22: 吐尔洪 | N22: 香梨标签 | P22: 张
A23: 香梨标签 | N23: 冷煤/氟利昂 | O23: *瓶 | P23: 瓶
A24: 冷煤/氟利昂 | N24: 新周转筐 | O24: *个 | P24: 个
A25: 公司新周转筐 | N25: 杂筐/一次性 | O25: *个 | P25: 个
A26: 公司杂周转筐
A27: 公司一次性筐
A28: 公司白周转筐
A29: 公司红周转筐

Sheet 对接源_01水果筐数
A1: 对 接 源 · 01 水 果 台 账 筐 数（跨文件自动取数 · 断链时自动改用应急备份） | R1: 有效行数 | S1: =MAX($P$5:$P$304) -> 22
A2: =IF($S$4=1,"✔ 链接正常，已自动取到 "&$S$1&" 行 ｜ 本表 1:1 对应《01 水果进销存台账模板》的【筐子进出接口】，两个文件必须放在同一个文件夹，文件名也不要改","★★ 链接没接上！当前取数来源："&$S$5&" → 请看本表右边 R6 格的修复说明（往右拉一屏）") -> ✔ 链接正常，已自动取到 22 行 ｜ 本表 1:1 对应《01 水果进销存台账模板》的【筐子进出接口】，两个文件必须放在同一个文件夹，文件名也不要改 | R2: 链接探针 | S2: =IFERROR(IF([1]筐子进出接口!$C$4=0,"未更新",[1]筐子进出接口!$C$4),"断开") -> 自备一次性筐
A3: 一、实 际 使 用 值（链接正常＝自动取数；链接断了自动切到右边备份） | I3: 二、应 急 备 份 区（手工粘贴数值） | O3: 状态 | R3: 备份行数 | S3: =COUNTIF($J$5:$J$304,"?*") -> 0
A4: 源行 | B4: 客户/货主 | C4: 筐子类型 | D4: 原料入库带回筐数 | E4: 原料出库带走筐数 | F4: 成品出库带走筐数 | G4: 发出合计 | H4: 收回合计 | I4: 备份-客户 | J4: 备份-类型 | K4: 备份-入库带回 | L4: 备份-出库带走 | M4: 备份-成品带走 | N4: 备份-发出合计 | O4: 有效 | P4: 累计 | R4: 链接可用 | S4: =IF(OR($S$2="断开",$S$2="未更新"),0,1) -> 1
A5: 4 | B5: =IF($S$4=0,IF($I5="","",$I5),IFERROR(IF([1]筐子进出接口!$B$4=0,"",[1]筐子进出接口!$B$4),"")) -> 聂新平 | C5: =IF($S$4=0,IF($J5="","",$J5),IFERROR(IF([1]筐子进出接口!$C$4=0,"",[1]筐子进出接口!$C$4),"")) -> 自备一次性筐 | D5: =IF($S$4=0,IF($K5="","",$K5),IFERROR(IF([1]筐子进出接口!$D$4=0,"",[1]筐子进出接口!$D$4),"")) -> 11421 | E5: =IF($S$4=0,IF($L5="","",$L5),IFERROR(IF([1]筐子进出接口!$E$4=0,"",[1]筐子进出接口!$E$4),"")) -> 10143 | F5: =IF($S$4=0,IF($M5="","",$M5),IFERROR(IF([1]筐子进出接口!$F$4=0,"",[1]筐子进出接口!$F$4),"")) -> 1260 | G5: =IF($S$4=0,IF($N5="","",$N5),IFERROR(IF([1]筐子进出接口!$G$4=0,"",[1]筐子进出接口!$G$4),"")) -> 11403 | H5: =IF($B5="","",N($D5)) -> 11421 | O5: =IF(AND($B5<>"",$C5<>""),1,0) -> 1 | P5: =N(P4)+$O5 -> 1 | R5: 当前取数来源 | S5: =IF($S$4=1,"自动（跨文件链接）",IF($S$3>0,"应急备份","无数据")) -> 自动（跨文件链接）
A6: 5 | B6: =IF($S$4=0,IF($I6="","",$I6),IFERROR(IF([1]筐子进出接口!$B$5=0,"",[1]筐子进出接口!$B$5),"")) -> 王照雪 | C6: =IF($S$4=0,IF($J6="","",$J6),IFERROR(IF([1]筐子进出接口!$C$5=0,"",[1]筐子进出接口!$C$5),"")) -> 公司杂周转筐 | D6: =IF($S$4=0,IF($K6="","",$K6),IFERROR(IF([1]筐子进出接口!$D$5=0,"",[1]筐子进出接口!$D$5),"")) -> 1670 | E6: =IF($S$4=0,IF($L6="","",$L6),IFERROR(IF([1]筐子进出接口!$E$5=0,"",[1]筐子进出接口!$E$5),"")) -> 1 | F6: =IF($S$4=0,IF($M6="","",$M6),IFERROR(IF([1]筐子进出接口!$F$5=0,"",[1]筐子进出接口!$F$5),"")) -> 4 | G6: =IF($S$4=0,IF($N6="","",$N6),IFERROR(IF([1]筐子进出接口!$G$5=0,"",[1]筐子进出接口!$G$5),"")) -> 5 | H6: =IF($B6="","",N($D6)) -> 1670 | O6: =IF(AND($B6<>"",$C6<>""),1,0) -> 1 | P6: =N(P5)+$O6 -> 2 | R6: =IF($S$2="断开",IF($S$3>0,"✘ 链接已断开，正在用【应急备份区】的 "&$S$3&" 行数据。修复：菜单【数据】→【编辑链接】→【更改源】，重新指向《01_水果进销存台账模板.xlsx》","✘ 链接已断开，且应急备份区是空的，筐子往来汇总里不会包含 01 水果台账带出带回的筐数。修复：菜单【数据】→【编辑链接】→【更改源】，重新指向《01_水果进销存台账模板.xlsx》"),IF($S$2="未更新",IF($S$3>0,"★ 链接还没更新，或那个文件被改名、挪走了。正在用【应急备份区】的 "&$S$3&" 行数据。修复：【数据】→【编辑链接】→先点【立即更新值】；还取不到数就点【更改源】重新指向《01_水果进销存台账模板.xlsx》","★ 链接还没更新，或那个文件被改名、挪走了，且没有应急备份。修复：【数据】→【编辑链接】→先点【立即更新值】；还取不到数就点【更改源】重新指向《01_水果进销存台账模板.xlsx》"),"✔ 链接正常，已自动取到 "&$S$1&" 行。备份区现有 "&$S$3&" 行。建议每月底把 B5:G304 复制→选择性粘贴【数值】到 I5，作为断链时的兜底")) -> ✔ 链接正常，已自动取到 22 行。备份区现有 0 行。建议每月底把 B5:G304 复制→选择性粘贴【数值】到 I5，作为断链时的兜底
A7: 6 | B7: =IF($S$4=0,IF($I7="","",$I7),IFERROR(IF([1]筐子进出接口!$B$6=0,"",[1]筐子进出接口!$B$6),"")) -> 伍元虎 | C7: =IF($S$4=0,IF($J7="","",$J7),IFERROR(IF([1]筐子进出接口!$C$6=0,"",[1]筐子进出接口!$C$6),"")) -> 自备一次性筐 | D7: =IF($S$4=0,IF($K7="","",$K7),IFERROR(IF([1]筐子进出接口!$D$6=0,"",[1]筐子进出接口!$D$6),"")) -> 87 | E7: =IF($S$4=0,IF($L7="","",$L7),IFERROR(IF([1]筐子进出接口!$E$6=0,"",[1]筐子进出接口!$E$6),"")) -> 87 | F7: =IF($S$4=0,IF($M7="","",$M7),IFERROR(IF([1]筐子进出接口!$F$6=0,"",[1]筐子进出接口!$F$6),"")) | G7: =IF($S$4=0,IF($N7="","",$N7),IFERROR(IF([1]筐子进出接口!$G$6=0,"",[1]筐子进出接口!$G$6),"")) -> 87 | H7: =IF($B7="","",N($D7)) -> 87 | O7: =IF(AND($B7<>"",$C7<>""),1,0) -> 1 | P7: =N(P6)+$O7 -> 3
A8: 7 | B8: =IF($S$4=0,IF($I8="","",$I8),IFERROR(IF([1]筐子进出接口!$B$7=0,"",[1]筐子进出接口!$B$7),"")) -> 王照雪 | C8: =IF($S$4=0,IF($J8="","",$J8),IFERROR(IF([1]筐子进出接口!$C$7=0,"",[1]筐子进出接口!$C$7),"")) -> 自备一次性筐 | D8: =IF($S$4=0,IF($K8="","",$K8),IFERROR(IF([1]筐子进出接口!$D$7=0,"",[1]筐子进出接口!$D$7),"")) -> 422 | E8: =IF($S$4=0,IF($L8="","",$L8),IFERROR(IF([1]筐子进出接口!$E$7=0,"",[1]筐子进出接口!$E$7),"")) -> 422 | F8: =IF($S$4=0,IF($M8="","",$M8),IFERROR(IF([1]筐子进出接口!$F$7=0,"",[1]筐子进出接口!$F$7),"")) | G8: =IF($S$4=0,IF($N8="","",$N8),IFERROR(IF([1]筐子进出接口!$G$7=0,"",[1]筐子进出接口!$G$7),"")) -> 422 | H8: =IF($B8="","",N($D8)) -> 422 | O8: =IF(AND($B8<>"",$C8<>""),1,0) -> 1 | P8: =N(P7)+$O8 -> 4
A9: 8 | B9: =IF($S$4=0,IF($I9="","",$I9),IFERROR(IF([1]筐子进出接口!$B$8=0,"",[1]筐子进出接口!$B$8),"")) -> 马锦祥 | C9: =IF($S$4=0,IF($J9="","",$J9),IFERROR(IF([1]筐子进出接口!$C$8=0,"",[1]筐子进出接口!$C$8),"")) -> 自备一次性筐 | D9: =IF($S$4=0,IF($K9="","",$K9),IFERROR(IF([1]筐子进出接口!$D$8=0,"",[1]筐子进出接口!$D$8),"")) -> 68 | E9: =IF($S$4=0,IF($L9="","",$L9),IFERROR(IF([1]筐子进出接口!$E$8=0,"",[1]筐子进出接口!$E$8),"")) -> 2 | F9: =IF($S$4=0,IF($M9="","",$M9),IFERROR(IF([1]筐子进出接口!$F$8=0,"",[1]筐子进出接口!$F$8),"")) | G9: =IF($S$4=0,IF($N9="","",$N9),IFERROR(IF([1]筐子进出接口!$G$8=0,"",[1]筐子进出接口!$G$8),"")) -> 2 | H9: =IF($B9="","",N($D9)) -> 68 | O9: =IF(AND($B9<>"",$C9<>""),1,0) -> 1 | P9: =N(P8)+$O9 -> 5
A10: 9 | B10: =IF($S$4=0,IF($I10="","",$I10),IFERROR(IF([1]筐子进出接口!$B$9=0,"",[1]筐子进出接口!$B$9),"")) -> 马锦祥 | C10: =IF($S$4=0,IF($J10="","",$J10),IFERROR(IF([1]筐子进出接口!$C$9=0,"",[1]筐子进出接口!$C$9),"")) -> 公司杂周转筐 | D10: =IF($S$4=0,IF($K10="","",$K10),IFERROR(IF([1]筐子进出接口!$D$9=0,"",[1]筐子进出接口!$D$9),"")) -> 1900 | E10: =IF($S$4=0,IF($L10="","",$L10),IFERROR(IF([1]筐子进出接口!$E$9=0,"",[1]筐子进出接口!$E$9),"")) | F10: =IF($S$4=0,IF($M10="","",$M10),IFERROR(IF([1]筐子进出接口!$F$9=0,"",[1]筐子进出接口!$F$9),"")) | G10: =IF($S$4=0,IF($N10="","",$N10),IFERROR(IF([1]筐子进出接口!$G$9=0,"",[1]筐子进出接口!$G$9),"")) | H10: =IF($B10="","",N($D10)) -> 1900 | O10: =IF(AND($B10<>"",$C10<>""),1,0) -> 1 | P10: =N(P9)+$O10 -> 6
A11: 10 | B11: =IF($S$4=0,IF($I11="","",$I11),IFERROR(IF([1]筐子进出接口!$B$10=0,"",[1]筐子进出接口!$B$10),"")) -> 麦麦提 | C11: =IF($S$4=0,IF($J11="","",$J11),IFERROR(IF([1]筐子进出接口!$C$10=0,"",[1]筐子进出接口!$C$10),"")) -> 公司红周转筐 | D11: =IF($S$4=0,IF($K11="","",$K11),IFERROR(IF([1]筐子进出接口!$D$10=0,"",[1]筐子进出接口!$D$10),"")) -> 2537 | E11: =IF($S$4=0,IF($L11="","",$L11),IFERROR(IF([1]筐子进出接口!$E$10=0,"",[1]筐子进出接口!$E$10),"")) | F11: =IF($S$4=0,IF($M11="","",$M11),IFERROR(IF([1]筐子进出接口!$F$10=0,"",[1]筐子进出接口!$F$10),"")) | G11: =IF($S$4=0,IF($N11="","",$N11),IFERROR(IF([1]筐子进出接口!$G$10=0,"",[1]筐子进出接口!$G$10),"")) | H11: =IF($B11="","",N($D11)) -> 2537 | O11: =IF(AND($B11<>"",$C11<>""),1,0) -> 1 | P11: =N(P10)+$O11 -> 7
A12: 11 | B12: =IF($S$4=0,IF($I12="","",$I12),IFERROR(IF([1]筐子进出接口!$B$11=0,"",[1]筐子进出接口!$B$11),"")) -> 吐尔洪 | C12: =IF($S$4=0,IF($J12="","",$J12),IFERROR(IF([1]筐子进出接口!$C$11=0,"",[1]筐子进出接口!$C$11),"")) -> 公司红周转筐 | D12: =IF($S$4=0,IF($K12="","",$K12),IFERROR(IF([1]筐子进出接口!$D$11=0,"",[1]筐子进出接口!$D$11),"")) -> 1195 | E12: =IF($S$4=0,IF($L12="","",$L12),IFERROR(IF([1]筐子进出接口!$E$11=0,"",[1]筐子进出接口!$E$11),"")) | F12: =IF($S$4=0,IF($M12="","",$M12),IFERROR(IF([1]筐子进出接口!$F$11=0,"",[1]筐子进出接口!$F$11),"")) | G12: =IF($S$4=0,IF($N12="","",$N12),IFERROR(IF([1]筐子进出接口!$G$11=0,"",[1]筐子进出接口!$G$11),"")) | H12: =IF($B12="","",N($D12)) -> 1195 | O12: =IF(AND($B12<>"",$C12<>""),1,0) -> 1 | P12: =N(P11)+$O12 -> 8
A13: 12 | B13: =IF($S$4=0,IF($I13="","",$I13),IFERROR(IF([1]筐子进出接口!$B$12=0,"",[1]筐子进出接口!$B$12),"")) -> 热合曼 | C13: =IF($S$4=0,IF($J13="","",$J13),IFERROR(IF([1]筐子进出接口!$C$12=0,"",[1]筐子进出接口!$C$12),"")) -> 公司红周转筐 | D13: =IF($S$4=0,IF($K13="","",$K13),IFERROR(IF([1]筐子进出接口!$D$12=0,"",[1]筐子进出接口!$D$12),"")) -> 1521 | E13: =IF($S$4=0,IF($L13="","",$L13),IFERROR(IF([1]筐子进出接口!$E$12=0,"",[1]筐子进出接口!$E$12),"")) | F13: =IF($S$4=0,IF($M13="","",$M13),IFERROR(IF([1]筐子进出接口!$F$12=0,"",[1]筐子进出接口!$F$12),"")) | G13: =IF($S$4=0,IF($N13="","",$N13),IFERROR(IF([1]筐子进出接口!$G$12=0,"",[1]筐子进出接口!$G$12),"")) | H13: =IF($B13="","",N($D13)) -> 1521 | O13: =IF(AND($B13<>"",$C13<>""),1,0) -> 1 | P13: =N(P12)+$O13 -> 9
A14: 13 | B14: =IF($S$4=0,IF($I14="","",$I14),IFERROR(IF([1]筐子进出接口!$B$13=0,"",[1]筐子进出接口!$B$13),"")) -> 贾建国 | C14: =IF($S$4=0,IF($J14="","",$J14),IFERROR(IF([1]筐子进出接口!$C$13=0,"",[1]筐子进出接口!$C$13),"")) -> 自备一次性筐 | D14: =IF($S$4=0,IF($K14="","",$K14),IFERROR(IF([1]筐子进出接口!$D$13=0,"",[1]筐子进出接口!$D$13),"")) -> 832 | E14: =IF($S$4=0,IF($L14="","",$L14),IFERROR(IF([1]筐子进出接口!$E$13=0,"",[1]筐子进出接口!$E$13),"")) | F14: =IF($S$4=0,IF($M14="","",$M14),IFERROR(IF([1]筐子进出接口!$F$13=0,"",[1]筐子进出接口!$F$13),"")) | G14: =IF($S$4=0,IF($N14="","",$N14),IFERROR(IF([1]筐子进出接口!$G$13=0,"",[1]筐子进出接口!$G$13),"")) | H14: =IF($B14="","",N($D14)) -> 832 | O14: =IF(AND($B14<>"",$C14<>""),1,0) -> 1 | P14: =N(P13)+$O14 -> 10
A15: 14 | B15: =IF($S$4=0,IF($I15="","",$I15),IFERROR(IF([1]筐子进出接口!$B$14=0,"",[1]筐子进出接口!$B$14),"")) -> 贾建国 | C15: =IF($S$4=0,IF($J15="","",$J15),IFERROR(IF([1]筐子进出接口!$C$14=0,"",[1]筐子进出接口!$C$14),"")) -> 自备杂周转筐 | D15: =IF($S$4=0,IF($K15="","",$K15),IFERROR(IF([1]筐子进出接口!$D$14=0,"",[1]筐子进出接口!$D$14),"")) -> 354 | E15: =IF($S$4=0,IF($L15="","",$L15),IFERROR(IF([1]筐子进出接口!$E$14=0,"",[1]筐子进出接口!$E$14),"")) | F15: =IF($S$4=0,IF($M15="","",$M15),IFERROR(IF([1]筐子进出接口!$F$14=0,"",[1]筐子进出接口!$F$14),"")) | G15: =IF($S$4=0,IF($N15="","",$N15),IFERROR(IF([1]筐子进出接口!$G$14=0,"",[1]筐子进出接口!$G$14),"")) | H15: =IF($B15="","",N($D15)) -> 354 | O15: =IF(AND($B15<>"",$C15<>""),1,0) -> 1 | P15: =N(P14)+$O15 -> 11
A16: 15 | B16: =IF($S$4=0,IF($I16="","",$I16),IFERROR(IF([1]筐子进出接口!$B$15=0,"",[1]筐子进出接口!$B$15),"")) -> 王灵云 | C16: =IF($S$4=0,IF($J16="","",$J16),IFERROR(IF([1]筐子进出接口!$C$15=0,"",[1]筐子进出接口!$C$15),"")) -> 公司红周转筐 | D16: =IF($S$4=0,IF($K16="","",$K16),IFERROR(IF([1]筐子进出接口!$D$15=0,"",[1]筐子进出接口!$D$15),"")) -> 1037 | E16: =IF($S$4=0,IF($L16="","",$L16),IFERROR(IF([1]筐子进出接口!$E$15=0,"",[1]筐子进出接口!$E$15),"")) | F16: =IF($S$4=0,IF($M16="","",$M16),IFERROR(IF([1]筐子进出接口!$F$15=0,"",[1]筐子进出接口!$F$15),"")) | G16: =IF($S$4=0,IF($N16="","",$N16),IFERROR(IF([1]筐子进出接口!$G$15=0,"",[1]筐子进出接口!$G$15),"")) | H16: =IF($B16="","",N($D16)) -> 1037 | O16: =IF(AND($B16<>"",$C16<>""),1,0) -> 1 | P16: =N(P15)+$O16 -> 12
A17: 16 | B17: =IF($S$4=0,IF($I17="","",$I17),IFERROR(IF([1]筐子进出接口!$B$16=0,"",[1]筐子进出接口!$B$16),"")) -> 杨艳玲 | C17: =IF($S$4=0,IF($J17="","",$J17),IFERROR(IF([1]筐子进出接口!$C$16=0,"",[1]筐子进出接口!$C$16),"")) -> 自备一次性筐 | D17: =IF($S$4=0,IF($K17="","",$K17),IFERROR(IF([1]筐子进出接口!$D$16=0,"",[1]筐子进出接口!$D$16),"")) -> 104 | E17: =IF($S$4=0,IF($L17="","",$L17),IFERROR(IF([1]筐子进出接口!$E$16=0,"",[1]筐子进出接口!$E$16),"")) | F17: =IF($S$4=0,IF($M17="","",$M17),IFERROR(IF([1]筐子进出接口!$F$16=0,"",[1]筐子进出接口!$F$16),"")) | G17: =IF($S$4=0,IF($N17="","",$N17),IFERROR(IF([1]筐子进出接口!$G$16=0,"",[1]筐子进出接口!$G$16),"")) | H17: =IF($B17="","",N($D17)) -> 104 | O17: =IF(AND($B17<>"",$C17<>""),1,0) -> 1 | P17: =N(P16)+$O17 -> 13
A18: 17 | B18: =IF($S$4=0,IF($I18="","",$I18),IFERROR(IF([1]筐子进出接口!$B$17=0,"",[1]筐子进出接口!$B$17),"")) -> 荆建君 | C18: =IF($S$4=0,IF($J18="","",$J18),IFERROR(IF([1]筐子进出接口!$C$17=0,"",[1]筐子进出接口!$C$17),"")) -> 公司红周转筐 | D18: =IF($S$4=0,IF($K18="","",$K18),IFERROR(IF([1]筐子进出接口!$D$17=0,"",[1]筐子进出接口!$D$17),"")) -> 1216 | E18: =IF($S$4=0,IF($L18="","",$L18),IFERROR(IF([1]筐子进出接口!$E$17=0,"",[1]筐子进出接口!$E$17),"")) | F18: =IF($S$4=0,IF($M18="","",$M18),IFERROR(IF([1]筐子进出接口!$F$17=0,"",[1]筐子进出接口!$F$17),"")) | G18: =IF($S$4=0,IF($N18="","",$N18),IFERROR(IF([1]筐子进出接口!$G$17=0,"",[1]筐子进出接口!$G$17),"")) | H18: =IF($B18="","",N($D18)) -> 1216 | O18: =IF(AND($B18<>"",$C18<>""),1,0) -> 1 | P18: =N(P17)+$O18 -> 14
A19: 18 | B19: =IF($S$4=0,IF($I19="","",$I19),IFERROR(IF([1]筐子进出接口!$B$18=0,"",[1]筐子进出接口!$B$18),"")) -> 贾建国 | C19: =IF($S$4=0,IF($J19="","",$J19),IFERROR(IF([1]筐子进出接口!$C$18=0,"",[1]筐子进出接口!$C$18),"")) -> 公司新周转筐 | D19: =IF($S$4=0,IF($K19="","",$K19),IFERROR(IF([1]筐子进出接口!$D$18=0,"",[1]筐子进出接口!$D$18),"")) -> 74 | E19: =IF($S$4=0,IF($L19="","",$L19),IFERROR(IF([1]筐子进出接口!$E$18=0,"",[1]筐子进出接口!$E$18),"")) | F19: =IF($S$4=0,IF($M19="","",$M19),IFERROR(IF([1]筐子进出接口!$F$18=0,"",[1]筐子进出接口!$F$18),"")) | G19: =IF($S$4=0,IF($N19="","",$N19),IFERROR(IF([1]筐子进出接口!$G$18=0,"",[1]筐子进出接口!$G$18),"")) | H19: =IF($B19="","",N($D19)) -> 74 | O19: =IF(AND($B19<>"",$C19<>""),1,0) -> 1 | P19: =N(P18)+$O19 -> 15
A20: 19 | B20: =IF($S$4=0,IF($I20="","",$I20),IFERROR(IF([1]筐子进出接口!$B$19=0,"",[1]筐子进出接口!$B$19),"")) -> 王照雪 | C20: =IF($S$4=0,IF($J20="","",$J20),IFERROR(IF([1]筐子进出接口!$C$19=0,"",[1]筐子进出接口!$C$19),"")) -> 公司一次性筐 | D20: =IF($S$4=0,IF($K20="","",$K20),IFERROR(IF([1]筐子进出接口!$D$19=0,"",[1]筐子进出接口!$D$19),"")) -> 543 | E20: =IF($S$4=0,IF($L20="","",$L20),IFERROR(IF([1]筐子进出接口!$E$19=0,"",[1]筐子进出接口!$E$19),"")) | F20: =IF($S$4=0,IF($M20="","",$M20),IFERROR(IF([1]筐子进出接口!$F$19=0,"",[1]筐子进出接口!$F$19),"")) | G20: =IF($S$4=0,IF($N20="","",$N20),IFERROR(IF([1]筐子进出接口!$G$19=0,"",[1]筐子进出接口!$G$19),"")) | H20: =IF($B20="","",N($D20)) -> 543 | O20: =IF(AND($B20<>"",$C20<>""),1,0) -> 1 | P20: =N(P19)+$O20 -> 16
A21: 20 | B21: =IF($S$4=0,IF($I21="","",$I21),IFERROR(IF([1]筐子进出接口!$B$20=0,"",[1]筐子进出接口!$B$20),"")) -> 努尔敦 | C21: =IF($S$4=0,IF($J21="","",$J21),IFERROR(IF([1]筐子进出接口!$C$20=0,"",[1]筐子进出接口!$C$20),"")) -> 公司红周转筐 | D21: =IF($S$4=0,IF($K21="","",$K21),IFERROR(IF([1]筐子进出接口!$D$20=0,"",[1]筐子进出接口!$D$20),"")) -> 1290 | E21: =IF($S$4=0,IF($L21="","",$L21),IFERROR(IF([1]筐子进出接口!$E$20=0,"",[1]筐子进出接口!$E$20),"")) | F21: =IF($S$4=0,IF($M21="","",$M21),IFERROR(IF([1]筐子进出接口!$F$20=0,"",[1]筐子进出接口!$F$20),"")) | G21: =IF($S$4=0,IF($N21="","",$N21),IFERROR(IF([1]筐子进出接口!$G$20=0,"",[1]筐子进出接口!$G$20),"")) | H21: =IF($B21="","",N($D21)) -> 1290 | O21: =IF(AND($B21<>"",$C21<>""),1,0) -> 1 | P21: =N(P20)+$O21 -> 17
A22: 21 | B22: =IF($S$4=0,IF($I22="","",$I22),IFERROR(IF([1]筐子进出接口!$B$21=0,"",[1]筐子进出接口!$B$21),"")) -> 王浩 | C22: =IF($S$4=0,IF($J22="","",$J22),IFERROR(IF([1]筐子进出接口!$C$21=0,"",[1]筐子进出接口!$C$21),"")) -> 公司一次性筐 | D22: =IF($S$4=0,IF($K22="","",$K22),IFERROR(IF([1]筐子进出接口!$D$21=0,"",[1]筐子进出接口!$D$21),"")) -> 1184 | E22: =IF($S$4=0,IF($L22="","",$L22),IFERROR(IF([1]筐子进出接口!$E$21=0,"",[1]筐子进出接口!$E$21),"")) | F22: =IF($S$4=0,IF($M22="","",$M22),IFERROR(IF([1]筐子进出接口!$F$21=0,"",[1]筐子进出接口!$F$21),"")) | G22: =IF($S$4=0,IF($N22="","",$N22),IFERROR(IF([1]筐子进出接口!$G$21=0,"",[1]筐子进出接口!$G$21),"")) | H22: =IF($B22="","",N($D22)) -> 1184 | O22: =IF(AND($B22<>"",$C22<>""),1,0) -> 1 | P22: =N(P21)+$O22 -> 18
A23: 22 | B23: =IF($S$4=0,IF($I23="","",$I23),IFERROR(IF([1]筐子进出接口!$B$22=0,"",[1]筐子进出接口!$B$22),"")) -> 贾建国 | C23: =IF($S$4=0,IF($J23="","",$J23),IFERROR(IF([1]筐子进出接口!$C$22=0,"",[1]筐子进出接口!$C$22),"")) -> 公司一次性筐 | D23: =IF($S$4=0,IF($K23="","",$K23),IFERROR(IF([1]筐子进出接口!$D$22=0,"",[1]筐子进出接口!$D$22),"")) -> 5 | E23: =IF($S$4=0,IF($L23="","",$L23),IFERROR(IF([1]筐子进出接口!$E$22=0,"",[1]筐子进出接口!$E$22),"")) | F23: =IF($S$4=0,IF($M23="","",$M23),IFERROR(IF([1]筐子进出接口!$F$22=0,"",[1]筐子进出接口!$F$22),"")) | G23: =IF($S$4=0,IF($N23="","",$N23),IFERROR(IF([1]筐子进出接口!$G$22=0,"",[1]筐子进出接口!$G$22),"")) | H23: =IF($B23="","",N($D23)) -> 5 | O23: =IF(AND($B23<>"",$C23<>""),1,0) -> 1 | P23: =N(P22)+$O23 -> 19
A24: 23 | B24: =IF($S$4=0,IF($I24="","",$I24),IFERROR(IF([1]筐子进出接口!$B$23=0,"",[1]筐子进出接口!$B$23),"")) -> 电商/主播 | C24: =IF($S$4=0,IF($J24="","",$J24),IFERROR(IF([1]筐子进出接口!$C$23=0,"",[1]筐子进出接口!$C$23),"")) -> 纸箱 | D24: =IF($S$4=0,IF($K24="","",$K24),IFERROR(IF([1]筐子进出接口!$D$23=0,"",[1]筐子进出接口!$D$23),"")) | E24: =IF($S$4=0,IF($L24="","",$L24),IFERROR(IF([1]筐子进出接口!$E$23=0,"",[1]筐子进出接口!$E$23),"")) | F24: =IF($S$4=0,IF($M24="","",$M24),IFERROR(IF([1]筐子进出接口!$F$23=0,"",[1]筐子进出接口!$F$23),"")) | G24: =IF($S$4=0,IF($N24="","",$N24),IFERROR(IF([1]筐子进出接口!$G$23=0,"",[1]筐子进出接口!$G$23),"")) | H24: =IF($B24="","",N($D24)) -> 0 | O24: =IF(AND($B24<>"",$C24<>""),1,0) -> 1 | P24: =N(P23)+$O24 -> 20
A25: 24 | B25: =IF($S$4=0,IF($I25="","",$I25),IFERROR(IF([1]筐子进出接口!$B$24=0,"",[1]筐子进出接口!$B$24),"")) -> 伍元虎 | C25: =IF($S$4=0,IF($J25="","",$J25),IFERROR(IF([1]筐子进出接口!$C$24=0,"",[1]筐子进出接口!$C$24),"")) -> 公司一次性筐 | D25: =IF($S$4=0,IF($K25="","",$K25),IFERROR(IF([1]筐子进出接口!$D$24=0,"",[1]筐子进出接口!$D$24),"")) | E25: =IF($S$4=0,IF($L25="","",$L25),IFERROR(IF([1]筐子进出接口!$E$24=0,"",[1]筐子进出接口!$E$24),"")) | F25: =IF($S$4=0,IF($M25="","",$M25),IFERROR(IF([1]筐子进出接口!$F$24=0,"",[1]筐子进出接口!$F$24),"")) -> 113 | G25: =IF($S$4=0,IF($N25="","",$N25),IFERROR(IF([1]筐子进出接口!$G$24=0,"",[1]筐子进出接口!$G$24),"")) -> 113 | H25: =IF($B25="","",N($D25)) -> 0 | O25: =IF(AND($B25<>"",$C25<>""),1,0) -> 1 | P25: =N(P24)+$O25 -> 21
A26: 25 | B26: =IF($S$4=0,IF($I26="","",$I26),IFERROR(IF([1]筐子进出接口!$B$25=0,"",[1]筐子进出接口!$B$25),"")) -> 王照雪 | C26: =IF($S$4=0,IF($J26="","",$J26),IFERROR(IF([1]筐子进出接口!$C$25=0,"",[1]筐子进出接口!$C$25),"")) -> 纸箱 | D26: =IF($S$4=0,IF($K26="","",$K26),IFERROR(IF([1]筐子进出接口!$D$25=0,"",[1]筐子进出接口!$D$25),"")) | E26: =IF($S$4=0,IF($L26="","",$L26),IFERROR(IF([1]筐子进出接口!$E$25=0,"",[1]筐子进出接口!$E$25),"")) | F26: =IF($S$4=0,IF($M26="","",$M26),IFERROR(IF([1]筐子进出接口!$F$25=0,"",[1]筐子进出接口!$F$25),"")) | G26: =IF($S$4=0,IF($N26="","",$N26),IFERROR(IF([1]筐子进出接口!$G$25=0,"",[1]筐子进出接口!$G$25),"")) | H26: =IF($B26="","",N($D26)) -> 0 | O26: =IF(AND($B26<>"",$C26<>""),1,0) -> 1 | P26: =N(P25)+$O26 -> 22
A27: 26 | B27: =IF($S$4=0,IF($I27="","",$I27),IFERROR(IF([1]筐子进出接口!$B$26=0,"",[1]筐子进出接口!$B$26),"")) | C27: =IF($S$4=0,IF($J27="","",$J27),IFERROR(IF([1]筐子进出接口!$C$26=0,"",[1]筐子进出接口!$C$26),"")) | D27: =IF($S$4=0,IF($K27="","",$K27),IFERROR(IF([1]筐子进出接口!$D$26=0,"",[1]筐子进出接口!$D$26),"")) | E27: =IF($S$4=0,IF($L27="","",$L27),IFERROR(IF([1]筐子进出接口!$E$26=0,"",[1]筐子进出接口!$E$26),"")) | F27: =IF($S$4=0,IF($M27="","",$M27),IFERROR(IF([1]筐子进出接口!$F$26=0,"",[1]筐子进出接口!$F$26),"")) | G27: =IF($S$4=0,IF($N27="","",$N27),IFERROR(IF([1]筐子进出接口!$G$26=0,"",[1]筐子进出接口!$G$26),"")) | H27: =IF($B27="","",N($D27)) | O27: =IF(AND($B27<>"",$C27<>""),1,0) -> 0 | P27: =N(P26)+$O27 -> 22
A28: 27 | B28: =IF($S$4=0,IF($I28="","",$I28),IFERROR(IF([1]筐子进出接口!$B$27=0,"",[1]筐子进出接口!$B$27),"")) | C28: =IF($S$4=0,IF($J28="","",$J28),IFERROR(IF([1]筐子进出接口!$C$27=0,"",[1]筐子进出接口!$C$27),"")) | D28: =IF($S$4=0,IF($K28="","",$K28),IFERROR(IF([1]筐子进出接口!$D$27=0,"",[1]筐子进出接口!$D$27),"")) | E28: =IF($S$4=0,IF($L28="","",$L28),IFERROR(IF([1]筐子进出接口!$E$27=0,"",[1]筐子进出接口!$E$27),"")) | F28: =IF($S$4=0,IF($M28="","",$M28),IFERROR(IF([1]筐子进出接口!$F$27=0,"",[1]筐子进出接口!$F$27),"")) | G28: =IF($S$4=0,IF($N28="","",$N28),IFERROR(IF([1]筐子进出接口!$G$27=0,"",[1]筐子进出接口!$G$27),"")) | H28: =IF($B28="","",N($D28)) | O28: =IF(AND($B28<>"",$C28<>""),1,0) -> 0 | P28: =N(P27)+$O28 -> 22
A29: 28 | B29: =IF($S$4=0,IF($I29="","",$I29),IFERROR(IF([1]筐子进出接口!$B$28=0,"",[1]筐子进出接口!$B$28),"")) | C29: =IF($S$4=0,IF($J29="","",$J29),IFERROR(IF([1]筐子进出接口!$C$28=0,"",[1]筐子进出接口!$C$28),"")) | D29: =IF($S$4=0,IF($K29="","",$K29),IFERROR(IF([1]筐子进出接口!$D$28=0,"",[1]筐子进出接口!$D$28),"")) | E29: =IF($S$4=0,IF($L29="","",$L29),IFERROR(IF([1]筐子进出接口!$E$28=0,"",[1]筐子进出接口!$E$28),"")) | F29: =IF($S$4=0,IF($M29="","",$M29),IFERROR(IF([1]筐子进出接口!$F$28=0,"",[1]筐子进出接口!$F$28),"")) | G29: =IF($S$4=0,IF($N29="","",$N29),IFERROR(IF([1]筐子进出接口!$G$28=0,"",[1]筐子进出接口!$G$28),"")) | H29: =IF($B29="","",N($D29)) | O29: =IF(AND($B29<>"",$C29<>""),1,0) -> 0 | P29: =N(P28)+$O29 -> 22
A30: 29 | B30: =IF($S$4=0,IF($I30="","",$I30),IFERROR(IF([1]筐子进出接口!$B$29=0,"",[1]筐子进出接口!$B$29),"")) | C30: =IF($S$4=0,IF($J30="","",$J30),IFERROR(IF([1]筐子进出接口!$C$29=0,"",[1]筐子进出接口!$C$29),"")) | D30: =IF($S$4=0,IF($K30="","",$K30),IFERROR(IF([1]筐子进出接口!$D$29=0,"",[1]筐子进出接口!$D$29),"")) | E30: =IF($S$4=0,IF($L30="","",$L30),IFERROR(IF([1]筐子进出接口!$E$29=0,"",[1]筐子进出接口!$E$29),"")) | F30: =IF($S$4=0,IF($M30="","",$M30),IFERROR(IF([1]筐子进出接口!$F$29=0,"",[1]筐子进出接口!$F$29),"")) | G30: =IF($S$4=0,IF($N30="","",$N30),IFERROR(IF([1]筐子进出接口!$G$29=0,"",[1]筐子进出接口!$G$29),"")) | H30: =IF($B30="","",N($D30)) | O30: =IF(AND($B30<>"",$C30<>""),1,0) -> 0 | P30: =N(P29)+$O30 -> 22
A31: 30 | B31: =IF($S$4=0,IF($I31="","",$I31),IFERROR(IF([1]筐子进出接口!$B$30=0,"",[1]筐子进出接口!$B$30),"")) | C31: =IF($S$4=0,IF($J31="","",$J31),IFERROR(IF([1]筐子进出接口!$C$30=0,"",[1]筐子进出接口!$C$30),"")) | D31: =IF($S$4=0,IF($K31="","",$K31),IFERROR(IF([1]筐子进出接口!$D$30=0,"",[1]筐子进出接口!$D$30),"")) | E31: =IF($S$4=0,IF($L31="","",$L31),IFERROR(IF([1]筐子进出接口!$E$30=0,"",[1]筐子进出接口!$E$30),"")) | F31: =IF($S$4=0,IF($M31="","",$M31),IFERROR(IF([1]筐子进出接口!$F$30=0,"",[1]筐子进出接口!$F$30),"")) | G31: =IF($S$4=0,IF($N31="","",$N31),IFERROR(IF([1]筐子进出接口!$G$30=0,"",[1]筐子进出接口!$G$30),"")) | H31: =IF($B31="","",N($D31)) | O31: =IF(AND($B31<>"",$C31<>""),1,0) -> 0 | P31: =N(P30)+$O31 -> 22
A32: 31 | B32: =IF($S$4=0,IF($I32="","",$I32),IFERROR(IF([1]筐子进出接口!$B$31=0,"",[1]筐子进出接口!$B$31),"")) | C32: =IF($S$4=0,IF($J32="","",$J32),IFERROR(IF([1]筐子进出接口!$C$31=0,"",[1]筐子进出接口!$C$31),"")) | D32: =IF($S$4=0,IF($K32="","",$K32),IFERROR(IF([1]筐子进出接口!$D$31=0,"",[1]筐子进出接口!$D$31),"")) | E32: =IF($S$4=0,IF($L32="","",$L32),IFERROR(IF([1]筐子进出接口!$E$31=0,"",[1]筐子进出接口!$E$31),"")) | F32: =IF($S$4=0,IF($M32="","",$M32),IFERROR(IF([1]筐子进出接口!$F$31=0,"",[1]筐子进出接口!$F$31),"")) | G32: =IF($S$4=0,IF($N32="","",$N32),IFERROR(IF([1]筐子进出接口!$G$31=0,"",[1]筐子进出接口!$G$31),"")) | H32: =IF($B32="","",N($D32)) | O32: =IF(AND($B32<>"",$C32<>""),1,0) -> 0 | P32: =N(P31)+$O32 -> 22
A33: 32 | B33: =IF($S$4=0,IF($I33="","",$I33),IFERROR(IF([1]筐子进出接口!$B$32=0,"",[1]筐子进出接口!$B$32),"")) | C33: =IF($S$4=0,IF($J33="","",$J33),IFERROR(IF([1]筐子进出接口!$C$32=0,"",[1]筐子进出接口!$C$32),"")) | D33: =IF($S$4=0,IF($K33="","",$K33),IFERROR(IF([1]筐子进出接口!$D$32=0,"",[1]筐子进出接口!$D$32),"")) | E33: =IF($S$4=0,IF($L33="","",$L33),IFERROR(IF([1]筐子进出接口!$E$32=0,"",[1]筐子进出接口!$E$32),"")) | F33: =IF($S$4=0,IF($M33="","",$M33),IFERROR(IF([1]筐子进出接口!$F$32=0,"",[1]筐子进出接口!$F$32),"")) | G33: =IF($S$4=0,IF($N33="","",$N33),IFERROR(IF([1]筐子进出接口!$G$32=0,"",[1]筐子进出接口!$G$32),"")) | H33: =IF($B33="","",N($D33)) | O33: =IF(AND($B33<>"",$C33<>""),1,0) -> 0 | P33: =N(P32)+$O33 -> 22
A34: 33 | B34: =IF($S$4=0,IF($I34="","",$I34),IFERROR(IF([1]筐子进出接口!$B$33=0,"",[1]筐子进出接口!$B$33),"")) | C34: =IF($S$4=0,IF($J34="","",$J34),IFERROR(IF([1]筐子进出接口!$C$33=0,"",[1]筐子进出接口!$C$33),"")) | D34: =IF($S$4=0,IF($K34="","",$K34),IFERROR(IF([1]筐子进出接口!$D$33=0,"",[1]筐子进出接口!$D$33),"")) | E34: =IF($S$4=0,IF($L34="","",$L34),IFERROR(IF([1]筐子进出接口!$E$33=0,"",[1]筐子进出接口!$E$33),"")) | F34: =IF($S$4=0,IF($M34="","",$M34),IFERROR(IF([1]筐子进出接口!$F$33=0,"",[1]筐子进出接口!$F$33),"")) | G34: =IF($S$4=0,IF($N34="","",$N34),IFERROR(IF([1]筐子进出接口!$G$33=0,"",[1]筐子进出接口!$G$33),"")) | H34: =IF($B34="","",N($D34)) | O34: =IF(AND($B34<>"",$C34<>""),1,0) -> 0 | P34: =N(P33)+$O34 -> 22
A35: 34 | B35: =IF($S$4=0,IF($I35="","",$I35),IFERROR(IF([1]筐子进出接口!$B$34=0,"",[1]筐子进出接口!$B$34),"")) | C35: =IF($S$4=0,IF($J35="","",$J35),IFERROR(IF([1]筐子进出接口!$C$34=0,"",[1]筐子进出接口!$C$34),"")) | D35: =IF($S$4=0,IF($K35="","",$K35),IFERROR(IF([1]筐子进出接口!$D$34=0,"",[1]筐子进出接口!$D$34),"")) | E35: =IF($S$4=0,IF($L35="","",$L35),IFERROR(IF([1]筐子进出接口!$E$34=0,"",[1]筐子进出接口!$E$34),"")) | F35: =IF($S$4=0,IF($M35="","",$M35),IFERROR(IF([1]筐子进出接口!$F$34=0,"",[1]筐子进出接口!$F$34),"")) | G35: =IF($S$4=0,IF($N35="","",$N35),IFERROR(IF([1]筐子进出接口!$G$34=0,"",[1]筐子进出接口!$G$34),"")) | H35: =IF($B35="","",N($D35)) | O35: =IF(AND($B35<>"",$C35<>""),1,0) -> 0 | P35: =N(P34)+$O35 -> 22
A36: 35 | B36: =IF($S$4=0,IF($I36="","",$I36),IFERROR(IF([1]筐子进出接口!$B$35=0,"",[1]筐子进出接口!$B$35),"")) | C36: =IF($S$4=0,IF($J36="","",$J36),IFERROR(IF([1]筐子进出接口!$C$35=0,"",[1]筐子进出接口!$C$35),"")) | D36: =IF($S$4=0,IF($K36="","",$K36),IFERROR(IF([1]筐子进出接口!$D$35=0,"",[1]筐子进出接口!$D$35),"")) | E36: =IF($S$4=0,IF($L36="","",$L36),IFERROR(IF([1]筐子进出接口!$E$35=0,"",[1]筐子进出接口!$E$35),"")) | F36: =IF($S$4=0,IF($M36="","",$M36),IFERROR(IF([1]筐子进出接口!$F$35=0,"",[1]筐子进出接口!$F$35),"")) | G36: =IF($S$4=0,IF($N36="","",$N36),IFERROR(IF([1]筐子进出接口!$G$35=0,"",[1]筐子进出接口!$G$35),"")) | H36: =IF($B36="","",N($D36)) | O36: =IF(AND($B36<>"",$C36<>""),1,0) -> 0 | P36: =N(P35)+$O36 -> 22
A37: 36 | B37: =IF($S$4=0,IF($I37="","",$I37),IFERROR(IF([1]筐子进出接口!$B$36=0,"",[1]筐子进出接口!$B$36),"")) | C37: =IF($S$4=0,IF($J37="","",$J37),IFERROR(IF([1]筐子进出接口!$C$36=0,"",[1]筐子进出接口!$C$36),"")) | D37: =IF($S$4=0,IF($K37="","",$K37),IFERROR(IF([1]筐子进出接口!$D$36=0,"",[1]筐子进出接口!$D$36),"")) | E37: =IF($S$4=0,IF($L37="","",$L37),IFERROR(IF([1]筐子进出接口!$E$36=0,"",[1]筐子进出接口!$E$36),"")) | F37: =IF($S$4=0,IF($M37="","",$M37),IFERROR(IF([1]筐子进出接口!$F$36=0,"",[1]筐子进出接口!$F$36),"")) | G37: =IF($S$4=0,IF($N37="","",$N37),IFERROR(IF([1]筐子进出接口!$G$36=0,"",[1]筐子进出接口!$G$36),"")) | H37: =IF($B37="","",N($D37)) | O37: =IF(AND($B37<>"",$C37<>""),1,0) -> 0 | P37: =N(P36)+$O37 -> 22
A38: 37 | B38: =IF($S$4=0,IF($I38="","",$I38),IFERROR(IF([1]筐子进出接口!$B$37=0,"",[1]筐子进出接口!$B$37),"")) | C38: =IF($S$4=0,IF($J38="","",$J38),IFERROR(IF([1]筐子进出接口!$C$37=0,"",[1]筐子进出接口!$C$37),"")) | D38: =IF($S$4=0,IF($K38="","",$K38),IFERROR(IF([1]筐子进出接口!$D$37=0,"",[1]筐子进出接口!$D$37),"")) | E38: =IF($S$4=0,IF($L38="","",$L38),IFERROR(IF([1]筐子进出接口!$E$37=0,"",[1]筐子进出接口!$E$37),"")) | F38: =IF($S$4=0,IF($M38="","",$M38),IFERROR(IF([1]筐子进出接口!$F$37=0,"",[1]筐子进出接口!$F$37),"")) | G38: =IF($S$4=0,IF($N38="","",$N38),IFERROR(IF([1]筐子进出接口!$G$37=0,"",[1]筐子进出接口!$G$37),"")) | H38: =IF($B38="","",N($D38)) | O38: =IF(AND($B38<>"",$C38<>""),1,0) -> 0 | P38: =N(P37)+$O38 -> 22
A39: 38 | B39: =IF($S$4=0,IF($I39="","",$I39),IFERROR(IF([1]筐子进出接口!$B$38=0,"",[1]筐子进出接口!$B$38),"")) | C39: =IF($S$4=0,IF($J39="","",$J39),IFERROR(IF([1]筐子进出接口!$C$38=0,"",[1]筐子进出接口!$C$38),"")) | D39: =IF($S$4=0,IF($K39="","",$K39),IFERROR(IF([1]筐子进出接口!$D$38=0,"",[1]筐子进出接口!$D$38),"")) | E39: =IF($S$4=0,IF($L39="","",$L39),IFERROR(IF([1]筐子进出接口!$E$38=0,"",[1]筐子进出接口!$E$38),"")) | F39: =IF($S$4=0,IF($M39="","",$M39),IFERROR(IF([1]筐子进出接口!$F$38=0,"",[1]筐子进出接口!$F$38),"")) | G39: =IF($S$4=0,IF($N39="","",$N39),IFERROR(IF([1]筐子进出接口!$G$38=0,"",[1]筐子进出接口!$G$38),"")) | H39: =IF($B39="","",N($D39)) | O39: =IF(AND($B39<>"",$C39<>""),1,0) -> 0 | P39: =N(P38)+$O39 -> 22
A40: 39 | B40: =IF($S$4=0,IF($I40="","",$I40),IFERROR(IF([1]筐子进出接口!$B$39=0,"",[1]筐子进出接口!$B$39),"")) | C40: =IF($S$4=0,IF($J40="","",$J40),IFERROR(IF([1]筐子进出接口!$C$39=0,"",[1]筐子进出接口!$C$39),"")) | D40: =IF($S$4=0,IF($K40="","",$K40),IFERROR(IF([1]筐子进出接口!$D$39=0,"",[1]筐子进出接口!$D$39),"")) | E40: =IF($S$4=0,IF($L40="","",$L40),IFERROR(IF([1]筐子进出接口!$E$39=0,"",[1]筐子进出接口!$E$39),"")) | F40: =IF($S$4=0,IF($M40="","",$M40),IFERROR(IF([1]筐子进出接口!$F$39=0,"",[1]筐子进出接口!$F$39),"")) | G40: =IF($S$4=0,IF($N40="","",$N40),IFERROR(IF([1]筐子进出接口!$G$39=0,"",[1]筐子进出接口!$G$39),"")) | H40: =IF($B40="","",N($D40)) | O40: =IF(AND($B40<>"",$C40<>""),1,0) -> 0 | P40: =N(P39)+$O40 -> 22
A41: 40 | B41: =IF($S$4=0,IF($I41="","",$I41),IFERROR(IF([1]筐子进出接口!$B$40=0,"",[1]筐子进出接口!$B$40),"")) | C41: =IF($S$4=0,IF($J41="","",$J41),IFERROR(IF([1]筐子进出接口!$C$40=0,"",[1]筐子进出接口!$C$40),"")) | D41: =IF($S$4=0,IF($K41="","",$K41),IFERROR(IF([1]筐子进出接口!$D$40=0,"",[1]筐子进出接口!$D$40),"")) | E41: =IF($S$4=0,IF($L41="","",$L41),IFERROR(IF([1]筐子进出接口!$E$40=0,"",[1]筐子进出接口!$E$40),"")) | F41: =IF($S$4=0,IF($M41="","",$M41),IFERROR(IF([1]筐子进出接口!$F$40=0,"",[1]筐子进出接口!$F$40),"")) | G41: =IF($S$4=0,IF($N41="","",$N41),IFERROR(IF([1]筐子进出接口!$G$40=0,"",[1]筐子进出接口!$G$40),"")) | H41: =IF($B41="","",N($D41)) | O41: =IF(AND($B41<>"",$C41<>""),1,0) -> 0 | P41: =N(P40)+$O41 -> 22
A42: 41 | B42: =IF($S$4=0,IF($I42="","",$I42),IFERROR(IF([1]筐子进出接口!$B$41=0,"",[1]筐子进出接口!$B$41),"")) | C42: =IF($S$4=0,IF($J42="","",$J42),IFERROR(IF([1]筐子进出接口!$C$41=0,"",[1]筐子进出接口!$C$41),"")) | D42: =IF($S$4=0,IF($K42="","",$K42),IFERROR(IF([1]筐子进出接口!$D$41=0,"",[1]筐子进出接口!$D$41),"")) | E42: =IF($S$4=0,IF($L42="","",$L42),IFERROR(IF([1]筐子进出接口!$E$41=0,"",[1]筐子进出接口!$E$41),"")) | F42: =IF($S$4=0,IF($M42="","",$M42),IFERROR(IF([1]筐子进出接口!$F$41=0,"",[1]筐子进出接口!$F$41),"")) | G42: =IF($S$4=0,IF($N42="","",$N42),IFERROR(IF([1]筐子进出接口!$G$41=0,"",[1]筐子进出接口!$G$41),"")) | H42: =IF($B42="","",N($D42)) | O42: =IF(AND($B42<>"",$C42<>""),1,0) -> 0 | P42: =N(P41)+$O42 -> 22
A43: 42 | B43: =IF($S$4=0,IF($I43="","",$I43),IFERROR(IF([1]筐子进出接口!$B$42=0,"",[1]筐子进出接口!$B$42),"")) | C43: =IF($S$4=0,IF($J43="","",$J43),IFERROR(IF([1]筐子进出接口!$C$42=0,"",[1]筐子进出接口!$C$42),"")) | D43: =IF($S$4=0,IF($K43="","",$K43),IFERROR(IF([1]筐子进出接口!$D$42=0,"",[1]筐子进出接口!$D$42),"")) | E43: =IF($S$4=0,IF($L43="","",$L43),IFERROR(IF([1]筐子进出接口!$E$42=0,"",[1]筐子进出接口!$E$42),"")) | F43: =IF($S$4=0,IF($M43="","",$M43),IFERROR(IF([1]筐子进出接口!$F$42=0,"",[1]筐子进出接口!$F$42),"")) | G43: =IF($S$4=0,IF($N43="","",$N43),IFERROR(IF([1]筐子进出接口!$G$42=0,"",[1]筐子进出接口!$G$42),"")) | H43: =IF($B43="","",N($D43)) | O43: =IF(AND($B43<>"",$C43<>""),1,0) -> 0 | P43: =N(P42)+$O43 -> 22
A44: 43 | B44: =IF($S$4=0,IF($I44="","",$I44),IFERROR(IF([1]筐子进出接口!$B$43=0,"",[1]筐子进出接口!$B$43),"")) | C44: =IF($S$4=0,IF($J44="","",$J44),IFERROR(IF([1]筐子进出接口!$C$43=0,"",[1]筐子进出接口!$C$43),"")) | D44: =IF($S$4=0,IF($K44="","",$K44),IFERROR(IF([1]筐子进出接口!$D$43=0,"",[1]筐子进出接口!$D$43),"")) | E44: =IF($S$4=0,IF($L44="","",$L44),IFERROR(IF([1]筐子进出接口!$E$43=0,"",[1]筐子进出接口!$E$43),"")) | F44: =IF($S$4=0,IF($M44="","",$M44),IFERROR(IF([1]筐子进出接口!$F$43=0,"",[1]筐子进出接口!$F$43),"")) | G44: =IF($S$4=0,IF($N44="","",$N44),IFERROR(IF([1]筐子进出接口!$G$43=0,"",[1]筐子进出接口!$G$43),"")) | H44: =IF($B44="","",N($D44)) | O44: =IF(AND($B44<>"",$C44<>""),1,0) -> 0 | P44: =N(P43)+$O44 -> 22
A45: 44 | B45: =IF($S$4=0,IF($I45="","",$I45),IFERROR(IF([1]筐子进出接口!$B$44=0,"",[1]筐子进出接口!$B$44),"")) | C45: =IF($S$4=0,IF($J45="","",$J45),IFERROR(IF([1]筐子进出接口!$C$44=0,"",[1]筐子进出接口!$C$44),"")) | D45: =IF($S$4=0,IF($K45="","",$K45),IFERROR(IF([1]筐子进出接口!$D$44=0,"",[1]筐子进出接口!$D$44),"")) | E45: =IF($S$4=0,IF($L45="","",$L45),IFERROR(IF([1]筐子进出接口!$E$44=0,"",[1]筐子进出接口!$E$44),"")) | F45: =IF($S$4=0,IF($M45="","",$M45),IFERROR(IF([1]筐子进出接口!$F$44=0,"",[1]筐子进出接口!$F$44),"")) | G45: =IF($S$4=0,IF($N45="","",$N45),IFERROR(IF([1]筐子进出接口!$G$44=0,"",[1]筐子进出接口!$G$44),"")) | H45: =IF($B45="","",N($D45)) | O45: =IF(AND($B45<>"",$C45<>""),1,0) -> 0 | P45: =N(P44)+$O45 -> 22
A46: 45 | B46: =IF($S$4=0,IF($I46="","",$I46),IFERROR(IF([1]筐子进出接口!$B$45=0,"",[1]筐子进出接口!$B$45),"")) | C46: =IF($S$4=0,IF($J46="","",$J46),IFERROR(IF([1]筐子进出接口!$C$45=0,"",[1]筐子进出接口!$C$45),"")) | D46: =IF($S$4=0,IF($K46="","",$K46),IFERROR(IF([1]筐子进出接口!$D$45=0,"",[1]筐子进出接口!$D$45),"")) | E46: =IF($S$4=0,IF($L46="","",$L46),IFERROR(IF([1]筐子进出接口!$E$45=0,"",[1]筐子进出接口!$E$45),"")) | F46: =IF($S$4=0,IF($M46="","",$M46),IFERROR(IF([1]筐子进出接口!$F$45=0,"",[1]筐子进出接口!$F$45),"")) | G46: =IF($S$4=0,IF($N46="","",$N46),IFERROR(IF([1]筐子进出接口!$G$45=0,"",[1]筐子进出接口!$G$45),"")) | H46: =IF($B46="","",N($D46)) | O46: =IF(AND($B46<>"",$C46<>""),1,0) -> 0 | P46: =N(P45)+$O46 -> 22
A47: 46 | B47: =IF($S$4=0,IF($I47="","",$I47),IFERROR(IF([1]筐子进出接口!$B$46=0,"",[1]筐子进出接口!$B$46),"")) | C47: =IF($S$4=0,IF($J47="","",$J47),IFERROR(IF([1]筐子进出接口!$C$46=0,"",[1]筐子进出接口!$C$46),"")) | D47: =IF($S$4=0,IF($K47="","",$K47),IFERROR(IF([1]筐子进出接口!$D$46=0,"",[1]筐子进出接口!$D$46),"")) | E47: =IF($S$4=0,IF($L47="","",$L47),IFERROR(IF([1]筐子进出接口!$E$46=0,"",[1]筐子进出接口!$E$46),"")) | F47: =IF($S$4=0,IF($M47="","",$M47),IFERROR(IF([1]筐子进出接口!$F$46=0,"",[1]筐子进出接口!$F$46),"")) | G47: =IF($S$4=0,IF($N47="","",$N47),IFERROR(IF([1]筐子进出接口!$G$46=0,"",[1]筐子进出接口!$G$46),"")) | H47: =IF($B47="","",N($D47)) | O47: =IF(AND($B47<>"",$C47<>""),1,0) -> 0 | P47: =N(P46)+$O47 -> 22
A48: 47 | B48: =IF($S$4=0,IF($I48="","",$I48),IFERROR(IF([1]筐子进出接口!$B$47=0,"",[1]筐子进出接口!$B$47),"")) | C48: =IF($S$4=0,IF($J48="","",$J48),IFERROR(IF([1]筐子进出接口!$C$47=0,"",[1]筐子进出接口!$C$47),"")) | D48: =IF($S$4=0,IF($K48="","",$K48),IFERROR(IF([1]筐子进出接口!$D$47=0,"",[1]筐子进出接口!$D$47),"")) | E48: =IF($S$4=0,IF($L48="","",$L48),IFERROR(IF([1]筐子进出接口!$E$47=0,"",[1]筐子进出接口!$E$47),"")) | F48: =IF($S$4=0,IF($M48="","",$M48),IFERROR(IF([1]筐子进出接口!$F$47=0,"",[1]筐子进出接口!$F$47),"")) | G48: =IF($S$4=0,IF($N48="","",$N48),IFERROR(IF([1]筐子进出接口!$G$47=0,"",[1]筐子进出接口!$G$47),"")) | H48: =IF($B48="","",N($D48)) | O48: =IF(AND($B48<>"",$C48<>""),1,0) -> 0 | P48: =N(P47)+$O48 -> 22
A49: 48 | B49: =IF($S$4=0,IF($I49="","",$I49),IFERROR(IF([1]筐子进出接口!$B$48=0,"",[1]筐子进出接口!$B$48),"")) | C49: =IF($S$4=0,IF($J49="","",$J49),IFERROR(IF([1]筐子进出接口!$C$48=0,"",[1]筐子进出接口!$C$48),"")) | D49: =IF($S$4=0,IF($K49="","",$K49),IFERROR(IF([1]筐子进出接口!$D$48=0,"",[1]筐子进出接口!$D$48),"")) | E49: =IF($S$4=0,IF($L49="","",$L49),IFERROR(IF([1]筐子进出接口!$E$48=0,"",[1]筐子进出接口!$E$48),"")) | F49: =IF($S$4=0,IF($M49="","",$M49),IFERROR(IF([1]筐子进出接口!$F$48=0,"",[1]筐子进出接口!$F$48),"")) | G49: =IF($S$4=0,IF($N49="","",$N49),IFERROR(IF([1]筐子进出接口!$G$48=0,"",[1]筐子进出接口!$G$48),"")) | H49: =IF($B49="","",N($D49)) | O49: =IF(AND($B49<>"",$C49<>""),1,0) -> 0 | P49: =N(P48)+$O49 -> 22
A50: 49 | B50: =IF($S$4=0,IF($I50="","",$I50),IFERROR(IF([1]筐子进出接口!$B$49=0,"",[1]筐子进出接口!$B$49),"")) | C50: =IF($S$4=0,IF($J50="","",$J50),IFERROR(IF([1]筐子进出接口!$C$49=0,"",[1]筐子进出接口!$C$49),"")) | D50: =IF($S$4=0,IF($K50="","",$K50),IFERROR(IF([1]筐子进出接口!$D$49=0,"",[1]筐子进出接口!$D$49),"")) | E50: =IF($S$4=0,IF($L50="","",$L50),IFERROR(IF([1]筐子进出接口!$E$49=0,"",[1]筐子进出接口!$E$49),"")) | F50: =IF($S$4=0,IF($M50="","",$M50),IFERROR(IF([1]筐子进出接口!$F$49=0,"",[1]筐子进出接口!$F$49),"")) | G50: =IF($S$4=0,IF($N50="","",$N50),IFERROR(IF([1]筐子进出接口!$G$49=0,"",[1]筐子进出接口!$G$49),"")) | H50: =IF($B50="","",N($D50)) | O50: =IF(AND($B50<>"",$C50<>""),1,0) -> 0 | P50: =N(P49)+$O50 -> 22
A51: 50 | B51: =IF($S$4=0,IF($I51="","",$I51),IFERROR(IF([1]筐子进出接口!$B$50=0,"",[1]筐子进出接口!$B$50),"")) | C51: =IF($S$4=0,IF($J51="","",$J51),IFERROR(IF([1]筐子进出接口!$C$50=0,"",[1]筐子进出接口!$C$50),"")) | D51: =IF($S$4=0,IF($K51="","",$K51),IFERROR(IF([1]筐子进出接口!$D$50=0,"",[1]筐子进出接口!$D$50),"")) | E51: =IF($S$4=0,IF($L51="","",$L51),IFERROR(IF([1]筐子进出接口!$E$50=0,"",[1]筐子进出接口!$E$50),"")) | F51: =IF($S$4=0,IF($M51="","",$M51),IFERROR(IF([1]筐子进出接口!$F$50=0,"",[1]筐子进出接口!$F$50),"")) | G51: =IF($S$4=0,IF($N51="","",$N51),IFERROR(IF([1]筐子进出接口!$G$50=0,"",[1]筐子进出接口!$G$50),"")) | H51: =IF($B51="","",N($D51)) | O51: =IF(AND($B51<>"",$C51<>""),1,0) -> 0 | P51: =N(P50)+$O51 -> 22
A52: 51 | B52: =IF($S$4=0,IF($I52="","",$I52),IFERROR(IF([1]筐子进出接口!$B$51=0,"",[1]筐子进出接口!$B$51),"")) | C52: =IF($S$4=0,IF($J52="","",$J52),IFERROR(IF([1]筐子进出接口!$C$51=0,"",[1]筐子进出接口!$C$51),"")) | D52: =IF($S$4=0,IF($K52="","",$K52),IFERROR(IF([1]筐子进出接口!$D$51=0,"",[1]筐子进出接口!$D$51),"")) | E52: =IF($S$4=0,IF($L52="","",$L52),IFERROR(IF([1]筐子进出接口!$E$51=0,"",[1]筐子进出接口!$E$51),"")) | F52: =IF($S$4=0,IF($M52="","",$M52),IFERROR(IF([1]筐子进出接口!$F$51=0,"",[1]筐子进出接口!$F$51),"")) | G52: =IF($S$4=0,IF($N52="","",$N52),IFERROR(IF([1]筐子进出接口!$G$51=0,"",[1]筐子进出接口!$G$51),"")) | H52: =IF($B52="","",N($D52)) | O52: =IF(AND($B52<>"",$C52<>""),1,0) -> 0 | P52: =N(P51)+$O52 -> 22
A53: 52 | B53: =IF($S$4=0,IF($I53="","",$I53),IFERROR(IF([1]筐子进出接口!$B$52=0,"",[1]筐子进出接口!$B$52),"")) | C53: =IF($S$4=0,IF($J53="","",$J53),IFERROR(IF([1]筐子进出接口!$C$52=0,"",[1]筐子进出接口!$C$52),"")) | D53: =IF($S$4=0,IF($K53="","",$K53),IFERROR(IF([1]筐子进出接口!$D$52=0,"",[1]筐子进出接口!$D$52),"")) | E53: =IF($S$4=0,IF($L53="","",$L53),IFERROR(IF([1]筐子进出接口!$E$52=0,"",[1]筐子进出接口!$E$52),"")) | F53: =IF($S$4=0,IF($M53="","",$M53),IFERROR(IF([1]筐子进出接口!$F$52=0,"",[1]筐子进出接口!$F$52),"")) | G53: =IF($S$4=0,IF($N53="","",$N53),IFERROR(IF([1]筐子进出接口!$G$52=0,"",[1]筐子进出接口!$G$52),"")) | H53: =IF($B53="","",N($D53)) | O53: =IF(AND($B53<>"",$C53<>""),1,0) -> 0 | P53: =N(P52)+$O53 -> 22
A54: 53 | B54: =IF($S$4=0,IF($I54="","",$I54),IFERROR(IF([1]筐子进出接口!$B$53=0,"",[1]筐子进出接口!$B$53),"")) | C54: =IF($S$4=0,IF($J54="","",$J54),IFERROR(IF([1]筐子进出接口!$C$53=0,"",[1]筐子进出接口!$C$53),"")) | D54: =IF($S$4=0,IF($K54="","",$K54),IFERROR(IF([1]筐子进出接口!$D$53=0,"",[1]筐子进出接口!$D$53),"")) | E54: =IF($S$4=0,IF($L54="","",$L54),IFERROR(IF([1]筐子进出接口!$E$53=0,"",[1]筐子进出接口!$E$53),"")) | F54: =IF($S$4=0,IF($M54="","",$M54),IFERROR(IF([1]筐子进出接口!$F$53=0,"",[1]筐子进出接口!$F$53),"")) | G54: =IF($S$4=0,IF($N54="","",$N54),IFERROR(IF([1]筐子进出接口!$G$53=0,"",[1]筐子进出接口!$G$53),"")) | H54: =IF($B54="","",N($D54)) | O54: =IF(AND($B54<>"",$C54<>""),1,0) -> 0 | P54: =N(P53)+$O54 -> 22
A55: 54 | B55: =IF($S$4=0,IF($I55="","",$I55),IFERROR(IF([1]筐子进出接口!$B$54=0,"",[1]筐子进出接口!$B$54),"")) | C55: =IF($S$4=0,IF($J55="","",$J55),IFERROR(IF([1]筐子进出接口!$C$54=0,"",[1]筐子进出接口!$C$54),"")) | D55: =IF($S$4=0,IF($K55="","",$K55),IFERROR(IF([1]筐子进出接口!$D$54=0,"",[1]筐子进出接口!$D$54),"")) | E55: =IF($S$4=0,IF($L55="","",$L55),IFERROR(IF([1]筐子进出接口!$E$54=0,"",[1]筐子进出接口!$E$54),"")) | F55: =IF($S$4=0,IF($M55="","",$M55),IFERROR(IF([1]筐子进出接口!$F$54=0,"",[1]筐子进出接口!$F$54),"")) | G55: =IF($S$4=0,IF($N55="","",$N55),IFERROR(IF([1]筐子进出接口!$G$54=0,"",[1]筐子进出接口!$G$54),"")) | H55: =IF($B55="","",N($D55)) | O55: =IF(AND($B55<>"",$C55<>""),1,0) -> 0 | P55: =N(P54)+$O55 -> 22
A56: 55 | B56: =IF($S$4=0,IF($I56="","",$I56),IFERROR(IF([1]筐子进出接口!$B$55=0,"",[1]筐子进出接口!$B$55),"")) | C56: =IF($S$4=0,IF($J56="","",$J56),IFERROR(IF([1]筐子进出接口!$C$55=0,"",[1]筐子进出接口!$C$55),"")) | D56: =IF($S$4=0,IF($K56="","",$K56),IFERROR(IF([1]筐子进出接口!$D$55=0,"",[1]筐子进出接口!$D$55),"")) | E56: =IF($S$4=0,IF($L56="","",$L56),IFERROR(IF([1]筐子进出接口!$E$55=0,"",[1]筐子进出接口!$E$55),"")) | F56: =IF($S$4=0,IF($M56="","",$M56),IFERROR(IF([1]筐子进出接口!$F$55=0,"",[1]筐子进出接口!$F$55),"")) | G56: =IF($S$4=0,IF($N56="","",$N56),IFERROR(IF([1]筐子进出接口!$G$55=0,"",[1]筐子进出接口!$G$55),"")) | H56: =IF($B56="","",N($D56)) | O56: =IF(AND($B56<>"",$C56<>""),1,0) -> 0 | P56: =N(P55)+$O56 -> 22
A57: 56 | B57: =IF($S$4=0,IF($I57="","",$I57),IFERROR(IF([1]筐子进出接口!$B$56=0,"",[1]筐子进出接口!$B$56),"")) | C57: =IF($S$4=0,IF($J57="","",$J57),IFERROR(IF([1]筐子进出接口!$C$56=0,"",[1]筐子进出接口!$C$56),"")) | D57: =IF($S$4=0,IF($K57="","",$K57),IFERROR(IF([1]筐子进出接口!$D$56=0,"",[1]筐子进出接口!$D$56),"")) | E57: =IF($S$4=0,IF($L57="","",$L57),IFERROR(IF([1]筐子进出接口!$E$56=0,"",[1]筐子进出接口!$E$56),"")) | F57: =IF($S$4=0,IF($M57="","",$M57),IFERROR(IF([1]筐子进出接口!$F$56=0,"",[1]筐子进出接口!$F$56),"")) | G57: =IF($S$4=0,IF($N57="","",$N57),IFERROR(IF([1]筐子进出接口!$G$56=0,"",[1]筐子进出接口!$G$56),"")) | H57: =IF($B57="","",N($D57)) | O57: =IF(AND($B57<>"",$C57<>""),1,0) -> 0 | P57: =N(P56)+$O57 -> 22
A58: 57 | B58: =IF($S$4=0,IF($I58="","",$I58),IFERROR(IF([1]筐子进出接口!$B$57=0,"",[1]筐子进出接口!$B$57),"")) | C58: =IF($S$4=0,IF($J58="","",$J58),IFERROR(IF([1]筐子进出接口!$C$57=0,"",[1]筐子进出接口!$C$57),"")) | D58: =IF($S$4=0,IF($K58="","",$K58),IFERROR(IF([1]筐子进出接口!$D$57=0,"",[1]筐子进出接口!$D$57),"")) | E58: =IF($S$4=0,IF($L58="","",$L58),IFERROR(IF([1]筐子进出接口!$E$57=0,"",[1]筐子进出接口!$E$57),"")) | F58: =IF($S$4=0,IF($M58="","",$M58),IFERROR(IF([1]筐子进出接口!$F$57=0,"",[1]筐子进出接口!$F$57),"")) | G58: =IF($S$4=0,IF($N58="","",$N58),IFERROR(IF([1]筐子进出接口!$G$57=0,"",[1]筐子进出接口!$G$57),"")) | H58: =IF($B58="","",N($D58)) | O58: =IF(AND($B58<>"",$C58<>""),1,0) -> 0 | P58: =N(P57)+$O58 -> 22
A59: 58 | B59: =IF($S$4=0,IF($I59="","",$I59),IFERROR(IF([1]筐子进出接口!$B$58=0,"",[1]筐子进出接口!$B$58),"")) | C59: =IF($S$4=0,IF($J59="","",$J59),IFERROR(IF([1]筐子进出接口!$C$58=0,"",[1]筐子进出接口!$C$58),"")) | D59: =IF($S$4=0,IF($K59="","",$K59),IFERROR(IF([1]筐子进出接口!$D$58=0,"",[1]筐子进出接口!$D$58),"")) | E59: =IF($S$4=0,IF($L59="","",$L59),IFERROR(IF([1]筐子进出接口!$E$58=0,"",[1]筐子进出接口!$E$58),"")) | F59: =IF($S$4=0,IF($M59="","",$M59),IFERROR(IF([1]筐子进出接口!$F$58=0,"",[1]筐子进出接口!$F$58),"")) | G59: =IF($S$4=0,IF($N59="","",$N59),IFERROR(IF([1]筐子进出接口!$G$58=0,"",[1]筐子进出接口!$G$58),"")) | H59: =IF($B59="","",N($D59)) | O59: =IF(AND($B59<>"",$C59<>""),1,0) -> 0 | P59: =N(P58)+$O59 -> 22
A60: 59 | B60: =IF($S$4=0,IF($I60="","",$I60),IFERROR(IF([1]筐子进出接口!$B$59=0,"",[1]筐子进出接口!$B$59),"")) | C60: =IF($S$4=0,IF($J60="","",$J60),IFERROR(IF([1]筐子进出接口!$C$59=0,"",[1]筐子进出接口!$C$59),"")) | D60: =IF($S$4=0,IF($K60="","",$K60),IFERROR(IF([1]筐子进出接口!$D$59=0,"",[1]筐子进出接口!$D$59),"")) | E60: =IF($S$4=0,IF($L60="","",$L60),IFERROR(IF([1]筐子进出接口!$E$59=0,"",[1]筐子进出接口!$E$59),"")) | F60: =IF($S$4=0,IF($M60="","",$M60),IFERROR(IF([1]筐子进出接口!$F$59=0,"",[1]筐子进出接口!$F$59),"")) | G60: =IF($S$4=0,IF($N60="","",$N60),IFERROR(IF([1]筐子进出接口!$G$59=0,"",[1]筐子进出接口!$G$59),"")) | H60: =IF($B60="","",N($D60)) | O60: =IF(AND($B60<>"",$C60<>""),1,0) -> 0 | P60: =N(P59)+$O60 -> 22
A61: 60 | B61: =IF($S$4=0,IF($I61="","",$I61),IFERROR(IF([1]筐子进出接口!$B$60=0,"",[1]筐子进出接口!$B$60),"")) | C61: =IF($S$4=0,IF($J61="","",$J61),IFERROR(IF([1]筐子进出接口!$C$60=0,"",[1]筐子进出接口!$C$60),"")) | D61: =IF($S$4=0,IF($K61="","",$K61),IFERROR(IF([1]筐子进出接口!$D$60=0,"",[1]筐子进出接口!$D$60),"")) | E61: =IF($S$4=0,IF($L61="","",$L61),IFERROR(IF([1]筐子进出接口!$E$60=0,"",[1]筐子进出接口!$E$60),"")) | F61: =IF($S$4=0,IF($M61="","",$M61),IFERROR(IF([1]筐子进出接口!$F$60=0,"",[1]筐子进出接口!$F$60),"")) | G61: =IF($S$4=0,IF($N61="","",$N61),IFERROR(IF([1]筐子进出接口!$G$60=0,"",[1]筐子进出接口!$G$60),"")) | H61: =IF($B61="","",N($D61)) | O61: =IF(AND($B61<>"",$C61<>""),1,0) -> 0 | P61: =N(P60)+$O61 -> 22
A62: 61 | B62: =IF($S$4=0,IF($I62="","",$I62),IFERROR(IF([1]筐子进出接口!$B$61=0,"",[1]筐子进出接口!$B$61),"")) | C62: =IF($S$4=0,IF($J62="","",$J62),IFERROR(IF([1]筐子进出接口!$C$61=0,"",[1]筐子进出接口!$C$61),"")) | D62: =IF($S$4=0,IF($K62="","",$K62),IFERROR(IF([1]筐子进出接口!$D$61=0,"",[1]筐子进出接口!$D$61),"")) | E62: =IF($S$4=0,IF($L62="","",$L62),IFERROR(IF([1]筐子进出接口!$E$61=0,"",[1]筐子进出接口!$E$61),"")) | F62: =IF($S$4=0,IF($M62="","",$M62),IFERROR(IF([1]筐子进出接口!$F$61=0,"",[1]筐子进出接口!$F$61),"")) | G62: =IF($S$4=0,IF($N62="","",$N62),IFERROR(IF([1]筐子进出接口!$G$61=0,"",[1]筐子进出接口!$G$61),"")) | H62: =IF($B62="","",N($D62)) | O62: =IF(AND($B62<>"",$C62<>""),1,0) -> 0 | P62: =N(P61)+$O62 -> 22
A63: 62 | B63: =IF($S$4=0,IF($I63="","",$I63),IFERROR(IF([1]筐子进出接口!$B$62=0,"",[1]筐子进出接口!$B$62),"")) | C63: =IF($S$4=0,IF($J63="","",$J63),IFERROR(IF([1]筐子进出接口!$C$62=0,"",[1]筐子进出接口!$C$62),"")) | D63: =IF($S$4=0,IF($K63="","",$K63),IFERROR(IF([1]筐子进出接口!$D$62=0,"",[1]筐子进出接口!$D$62),"")) | E63: =IF($S$4=0,IF($L63="","",$L63),IFERROR(IF([1]筐子进出接口!$E$62=0,"",[1]筐子进出接口!$E$62),"")) | F63: =IF($S$4=0,IF($M63="","",$M63),IFERROR(IF([1]筐子进出接口!$F$62=0,"",[1]筐子进出接口!$F$62),"")) | G63: =IF($S$4=0,IF($N63="","",$N63),IFERROR(IF([1]筐子进出接口!$G$62=0,"",[1]筐子进出接口!$G$62),"")) | H63: =IF($B63="","",N($D63)) | O63: =IF(AND($B63<>"",$C63<>""),1,0) -> 0 | P63: =N(P62)+$O63 -> 22
A64: 63 | B64: =IF($S$4=0,IF($I64="","",$I64),IFERROR(IF([1]筐子进出接口!$B$63=0,"",[1]筐子进出接口!$B$63),"")) | C64: =IF($S$4=0,IF($J64="","",$J64),IFERROR(IF([1]筐子进出接口!$C$63=0,"",[1]筐子进出接口!$C$63),"")) | D64: =IF($S$4=0,IF($K64="","",$K64),IFERROR(IF([1]筐子进出接口!$D$63=0,"",[1]筐子进出接口!$D$63),"")) | E64: =IF($S$4=0,IF($L64="","",$L64),IFERROR(IF([1]筐子进出接口!$E$63=0,"",[1]筐子进出接口!$E$63),"")) | F64: =IF($S$4=0,IF($M64="","",$M64),IFERROR(IF([1]筐子进出接口!$F$63=0,"",[1]筐子进出接口!$F$63),"")) | G64: =IF($S$4=0,IF($N64="","",$N64),IFERROR(IF([1]筐子进出接口!$G$63=0,"",[1]筐子进出接口!$G$63),"")) | H64: =IF($B64="","",N($D64)) | O64: =IF(AND($B64<>"",$C64<>""),1,0) -> 0 | P64: =N(P63)+$O64 -> 22
A65: 64 | B65: =IF($S$4=0,IF($I65="","",$I65),IFERROR(IF([1]筐子进出接口!$B$64=0,"",[1]筐子进出接口!$B$64),"")) | C65: =IF($S$4=0,IF($J65="","",$J65),IFERROR(IF([1]筐子进出接口!$C$64=0,"",[1]筐子进出接口!$C$64),"")) | D65: =IF($S$4=0,IF($K65="","",$K65),IFERROR(IF([1]筐子进出接口!$D$64=0,"",[1]筐子进出接口!$D$64),"")) | E65: =IF($S$4=0,IF($L65="","",$L65),IFERROR(IF([1]筐子进出接口!$E$64=0,"",[1]筐子进出接口!$E$64),"")) | F65: =IF($S$4=0,IF($M65="","",$M65),IFERROR(IF([1]筐子进出接口!$F$64=0,"",[1]筐子进出接口!$F$64),"")) | G65: =IF($S$4=0,IF($N65="","",$N65),IFERROR(IF([1]筐子进出接口!$G$64=0,"",[1]筐子进出接口!$G$64),"")) | H65: =IF($B65="","",N($D65)) | O65: =IF(AND($B65<>"",$C65<>""),1,0) -> 0 | P65: =N(P64)+$O65 -> 22
A66: 65 | B66: =IF($S$4=0,IF($I66="","",$I66),IFERROR(IF([1]筐子进出接口!$B$65=0,"",[1]筐子进出接口!$B$65),"")) | C66: =IF($S$4=0,IF($J66="","",$J66),IFERROR(IF([1]筐子进出接口!$C$65=0,"",[1]筐子进出接口!$C$65),"")) | D66: =IF($S$4=0,IF($K66="","",$K66),IFERROR(IF([1]筐子进出接口!$D$65=0,"",[1]筐子进出接口!$D$65),"")) | E66: =IF($S$4=0,IF($L66="","",$L66),IFERROR(IF([1]筐子进出接口!$E$65=0,"",[1]筐子进出接口!$E$65),"")) | F66: =IF($S$4=0,IF($M66="","",$M66),IFERROR(IF([1]筐子进出接口!$F$65=0,"",[1]筐子进出接口!$F$65),"")) | G66: =IF($S$4=0,IF($N66="","",$N66),IFERROR(IF([1]筐子进出接口!$G$65=0,"",[1]筐子进出接口!$G$65),"")) | H66: =IF($B66="","",N($D66)) | O66: =IF(AND($B66<>"",$C66<>""),1,0) -> 0 | P66: =N(P65)+$O66 -> 22
A67: 66 | B67: =IF($S$4=0,IF($I67="","",$I67),IFERROR(IF([1]筐子进出接口!$B$66=0,"",[1]筐子进出接口!$B$66),"")) | C67: =IF($S$4=0,IF($J67="","",$J67),IFERROR(IF([1]筐子进出接口!$C$66=0,"",[1]筐子进出接口!$C$66),"")) | D67: =IF($S$4=0,IF($K67="","",$K67),IFERROR(IF([1]筐子进出接口!$D$66=0,"",[1]筐子进出接口!$D$66),"")) | E67: =IF($S$4=0,IF($L67="","",$L67),IFERROR(IF([1]筐子进出接口!$E$66=0,"",[1]筐子进出接口!$E$66),"")) | F67: =IF($S$4=0,IF($M67="","",$M67),IFERROR(IF([1]筐子进出接口!$F$66=0,"",[1]筐子进出接口!$F$66),"")) | G67: =IF($S$4=0,IF($N67="","",$N67),IFERROR(IF([1]筐子进出接口!$G$66=0,"",[1]筐子进出接口!$G$66),"")) | H67: =IF($B67="","",N($D67)) | O67: =IF(AND($B67<>"",$C67<>""),1,0) -> 0 | P67: =N(P66)+$O67 -> 22
A68: 67 | B68: =IF($S$4=0,IF($I68="","",$I68),IFERROR(IF([1]筐子进出接口!$B$67=0,"",[1]筐子进出接口!$B$67),"")) | C68: =IF($S$4=0,IF($J68="","",$J68),IFERROR(IF([1]筐子进出接口!$C$67=0,"",[1]筐子进出接口!$C$67),"")) | D68: =IF($S$4=0,IF($K68="","",$K68),IFERROR(IF([1]筐子进出接口!$D$67=0,"",[1]筐子进出接口!$D$67),"")) | E68: =IF($S$4=0,IF($L68="","",$L68),IFERROR(IF([1]筐子进出接口!$E$67=0,"",[1]筐子进出接口!$E$67),"")) | F68: =IF($S$4=0,IF($M68="","",$M68),IFERROR(IF([1]筐子进出接口!$F$67=0,"",[1]筐子进出接口!$F$67),"")) | G68: =IF($S$4=0,IF($N68="","",$N68),IFERROR(IF([1]筐子进出接口!$G$67=0,"",[1]筐子进出接口!$G$67),"")) | H68: =IF($B68="","",N($D68)) | O68: =IF(AND($B68<>"",$C68<>""),1,0) -> 0 | P68: =N(P67)+$O68 -> 22
A69: 68 | B69: =IF($S$4=0,IF($I69="","",$I69),IFERROR(IF([1]筐子进出接口!$B$68=0,"",[1]筐子进出接口!$B$68),"")) | C69: =IF($S$4=0,IF($J69="","",$J69),IFERROR(IF([1]筐子进出接口!$C$68=0,"",[1]筐子进出接口!$C$68),"")) | D69: =IF($S$4=0,IF($K69="","",$K69),IFERROR(IF([1]筐子进出接口!$D$68=0,"",[1]筐子进出接口!$D$68),"")) | E69: =IF($S$4=0,IF($L69="","",$L69),IFERROR(IF([1]筐子进出接口!$E$68=0,"",[1]筐子进出接口!$E$68),"")) | F69: =IF($S$4=0,IF($M69="","",$M69),IFERROR(IF([1]筐子进出接口!$F$68=0,"",[1]筐子进出接口!$F$68),"")) | G69: =IF($S$4=0,IF($N69="","",$N69),IFERROR(IF([1]筐子进出接口!$G$68=0,"",[1]筐子进出接口!$G$68),"")) | H69: =IF($B69="","",N($D69)) | O69: =IF(AND($B69<>"",$C69<>""),1,0) -> 0 | P69: =N(P68)+$O69 -> 22
A70: 69 | B70: =IF($S$4=0,IF($I70="","",$I70),IFERROR(IF([1]筐子进出接口!$B$69=0,"",[1]筐子进出接口!$B$69),"")) | C70: =IF($S$4=0,IF($J70="","",$J70),IFERROR(IF([1]筐子进出接口!$C$69=0,"",[1]筐子进出接口!$C$69),"")) | D70: =IF($S$4=0,IF($K70="","",$K70),IFERROR(IF([1]筐子进出接口!$D$69=0,"",[1]筐子进出接口!$D$69),"")) | E70: =IF($S$4=0,IF($L70="","",$L70),IFERROR(IF([1]筐子进出接口!$E$69=0,"",[1]筐子进出接口!$E$69),"")) | F70: =IF($S$4=0,IF($M70="","",$M70),IFERROR(IF([1]筐子进出接口!$F$69=0,"",[1]筐子进出接口!$F$69),"")) | G70: =IF($S$4=0,IF($N70="","",$N70),IFERROR(IF([1]筐子进出接口!$G$69=0,"",[1]筐子进出接口!$G$69),"")) | H70: =IF($B70="","",N($D70)) | O70: =IF(AND($B70<>"",$C70<>""),1,0) -> 0 | P70: =N(P69)+$O70 -> 22
A71: 70 | B71: =IF($S$4=0,IF($I71="","",$I71),IFERROR(IF([1]筐子进出接口!$B$70=0,"",[1]筐子进出接口!$B$70),"")) | C71: =IF($S$4=0,IF($J71="","",$J71),IFERROR(IF([1]筐子进出接口!$C$70=0,"",[1]筐子进出接口!$C$70),"")) | D71: =IF($S$4=0,IF($K71="","",$K71),IFERROR(IF([1]筐子进出接口!$D$70=0,"",[1]筐子进出接口!$D$70),"")) | E71: =IF($S$4=0,IF($L71="","",$L71),IFERROR(IF([1]筐子进出接口!$E$70=0,"",[1]筐子进出接口!$E$70),"")) | F71: =IF($S$4=0,IF($M71="","",$M71),IFERROR(IF([1]筐子进出接口!$F$70=0,"",[1]筐子进出接口!$F$70),"")) | G71: =IF($S$4=0,IF($N71="","",$N71),IFERROR(IF([1]筐子进出接口!$G$70=0,"",[1]筐子进出接口!$G$70),"")) | H71: =IF($B71="","",N($D71)) | O71: =IF(AND($B71<>"",$C71<>""),1,0) -> 0 | P71: =N(P70)+$O71 -> 22
A72: 71 | B72: =IF($S$4=0,IF($I72="","",$I72),IFERROR(IF([1]筐子进出接口!$B$71=0,"",[1]筐子进出接口!$B$71),"")) | C72: =IF($S$4=0,IF($J72="","",$J72),IFERROR(IF([1]筐子进出接口!$C$71=0,"",[1]筐子进出接口!$C$71),"")) | D72: =IF($S$4=0,IF($K72="","",$K72),IFERROR(IF([1]筐子进出接口!$D$71=0,"",[1]筐子进出接口!$D$71),"")) | E72: =IF($S$4=0,IF($L72="","",$L72),IFERROR(IF([1]筐子进出接口!$E$71=0,"",[1]筐子进出接口!$E$71),"")) | F72: =IF($S$4=0,IF($M72="","",$M72),IFERROR(IF([1]筐子进出接口!$F$71=0,"",[1]筐子进出接口!$F$71),"")) | G72: =IF($S$4=0,IF($N72="","",$N72),IFERROR(IF([1]筐子进出接口!$G$71=0,"",[1]筐子进出接口!$G$71),"")) | H72: =IF($B72="","",N($D72)) | O72: =IF(AND($B72<>"",$C72<>""),1,0) -> 0 | P72: =N(P71)+$O72 -> 22
A73: 72 | B73: =IF($S$4=0,IF($I73="","",$I73),IFERROR(IF([1]筐子进出接口!$B$72=0,"",[1]筐子进出接口!$B$72),"")) | C73: =IF($S$4=0,IF($J73="","",$J73),IFERROR(IF([1]筐子进出接口!$C$72=0,"",[1]筐子进出接口!$C$72),"")) | D73: =IF($S$4=0,IF($K73="","",$K73),IFERROR(IF([1]筐子进出接口!$D$72=0,"",[1]筐子进出接口!$D$72),"")) | E73: =IF($S$4=0,IF($L73="","",$L73),IFERROR(IF([1]筐子进出接口!$E$72=0,"",[1]筐子进出接口!$E$72),"")) | F73: =IF($S$4=0,IF($M73="","",$M73),IFERROR(IF([1]筐子进出接口!$F$72=0,"",[1]筐子进出接口!$F$72),"")) | G73: =IF($S$4=0,IF($N73="","",$N73),IFERROR(IF([1]筐子进出接口!$G$72=0,"",[1]筐子进出接口!$G$72),"")) | H73: =IF($B73="","",N($D73)) | O73: =IF(AND($B73<>"",$C73<>""),1,0) -> 0 | P73: =N(P72)+$O73 -> 22
A74: 73 | B74: =IF($S$4=0,IF($I74="","",$I74),IFERROR(IF([1]筐子进出接口!$B$73=0,"",[1]筐子进出接口!$B$73),"")) | C74: =IF($S$4=0,IF($J74="","",$J74),IFERROR(IF([1]筐子进出接口!$C$73=0,"",[1]筐子进出接口!$C$73),"")) | D74: =IF($S$4=0,IF($K74="","",$K74),IFERROR(IF([1]筐子进出接口!$D$73=0,"",[1]筐子进出接口!$D$73),"")) | E74: =IF($S$4=0,IF($L74="","",$L74),IFERROR(IF([1]筐子进出接口!$E$73=0,"",[1]筐子进出接口!$E$73),"")) | F74: =IF($S$4=0,IF($M74="","",$M74),IFERROR(IF([1]筐子进出接口!$F$73=0,"",[1]筐子进出接口!$F$73),"")) | G74: =IF($S$4=0,IF($N74="","",$N74),IFERROR(IF([1]筐子进出接口!$G$73=0,"",[1]筐子进出接口!$G$73),"")) | H74: =IF($B74="","",N($D74)) | O74: =IF(AND($B74<>"",$C74<>""),1,0) -> 0 | P74: =N(P73)+$O74 -> 22
A75: 74 | B75: =IF($S$4=0,IF($I75="","",$I75),IFERROR(IF([1]筐子进出接口!$B$74=0,"",[1]筐子进出接口!$B$74),"")) | C75: =IF($S$4=0,IF($J75="","",$J75),IFERROR(IF([1]筐子进出接口!$C$74=0,"",[1]筐子进出接口!$C$74),"")) | D75: =IF($S$4=0,IF($K75="","",$K75),IFERROR(IF([1]筐子进出接口!$D$74=0,"",[1]筐子进出接口!$D$74),"")) | E75: =IF($S$4=0,IF($L75="","",$L75),IFERROR(IF([1]筐子进出接口!$E$74=0,"",[1]筐子进出接口!$E$74),"")) | F75: =IF($S$4=0,IF($M75="","",$M75),IFERROR(IF([1]筐子进出接口!$F$74=0,"",[1]筐子进出接口!$F$74),"")) | G75: =IF($S$4=0,IF($N75="","",$N75),IFERROR(IF([1]筐子进出接口!$G$74=0,"",[1]筐子进出接口!$G$74),"")) | H75: =IF($B75="","",N($D75)) | O75: =IF(AND($B75<>"",$C75<>""),1,0) -> 0 | P75: =N(P74)+$O75 -> 22
A76: 75 | B76: =IF($S$4=0,IF($I76="","",$I76),IFERROR(IF([1]筐子进出接口!$B$75=0,"",[1]筐子进出接口!$B$75),"")) | C76: =IF($S$4=0,IF($J76="","",$J76),IFERROR(IF([1]筐子进出接口!$C$75=0,"",[1]筐子进出接口!$C$75),"")) | D76: =IF($S$4=0,IF($K76="","",$K76),IFERROR(IF([1]筐子进出接口!$D$75=0,"",[1]筐子进出接口!$D$75),"")) | E76: =IF($S$4=0,IF($L76="","",$L76),IFERROR(IF([1]筐子进出接口!$E$75=0,"",[1]筐子进出接口!$E$75),"")) | F76: =IF($S$4=0,IF($M76="","",$M76),IFERROR(IF([1]筐子进出接口!$F$75=0,"",[1]筐子进出接口!$F$75),"")) | G76: =IF($S$4=0,IF($N76="","",$N76),IFERROR(IF([1]筐子进出接口!$G$75=0,"",[1]筐子进出接口!$G$75),"")) | H76: =IF($B76="","",N($D76)) | O76: =IF(AND($B76<>"",$C76<>""),1,0) -> 0 | P76: =N(P75)+$O76 -> 22
A77: 76 | B77: =IF($S$4=0,IF($I77="","",$I77),IFERROR(IF([1]筐子进出接口!$B$76=0,"",[1]筐子进出接口!$B$76),"")) | C77: =IF($S$4=0,IF($J77="","",$J77),IFERROR(IF([1]筐子进出接口!$C$76=0,"",[1]筐子进出接口!$C$76),"")) | D77: =IF($S$4=0,IF($K77="","",$K77),IFERROR(IF([1]筐子进出接口!$D$76=0,"",[1]筐子进出接口!$D$76),"")) | E77: =IF($S$4=0,IF($L77="","",$L77),IFERROR(IF([1]筐子进出接口!$E$76=0,"",[1]筐子进出接口!$E$76),"")) | F77: =IF($S$4=0,IF($M77="","",$M77),IFERROR(IF([1]筐子进出接口!$F$76=0,"",[1]筐子进出接口!$F$76),"")) | G77: =IF($S$4=0,IF($N77="","",$N77),IFERROR(IF([1]筐子进出接口!$G$76=0,"",[1]筐子进出接口!$G$76),"")) | H77: =IF($B77="","",N($D77)) | O77: =IF(AND($B77<>"",$C77<>""),1,0) -> 0 | P77: =N(P76)+$O77 -> 22
A78: 77 | B78: =IF($S$4=0,IF($I78="","",$I78),IFERROR(IF([1]筐子进出接口!$B$77=0,"",[1]筐子进出接口!$B$77),"")) | C78: =IF($S$4=0,IF($J78="","",$J78),IFERROR(IF([1]筐子进出接口!$C$77=0,"",[1]筐子进出接口!$C$77),"")) | D78: =IF($S$4=0,IF($K78="","",$K78),IFERROR(IF([1]筐子进出接口!$D$77=0,"",[1]筐子进出接口!$D$77),"")) | E78: =IF($S$4=0,IF($L78="","",$L78),IFERROR(IF([1]筐子进出接口!$E$77=0,"",[1]筐子进出接口!$E$77),"")) | F78: =IF($S$4=0,IF($M78="","",$M78),IFERROR(IF([1]筐子进出接口!$F$77=0,"",[1]筐子进出接口!$F$77),"")) | G78: =IF($S$4=0,IF($N78="","",$N78),IFERROR(IF([1]筐子进出接口!$G$77=0,"",[1]筐子进出接口!$G$77),"")) | H78: =IF($B78="","",N($D78)) | O78: =IF(AND($B78<>"",$C78<>""),1,0) -> 0 | P78: =N(P77)+$O78 -> 22
A79: 78 | B79: =IF($S$4=0,IF($I79="","",$I79),IFERROR(IF([1]筐子进出接口!$B$78=0,"",[1]筐子进出接口!$B$78),"")) | C79: =IF($S$4=0,IF($J79="","",$J79),IFERROR(IF([1]筐子进出接口!$C$78=0,"",[1]筐子进出接口!$C$78),"")) | D79: =IF($S$4=0,IF($K79="","",$K79),IFERROR(IF([1]筐子进出接口!$D$78=0,"",[1]筐子进出接口!$D$78),"")) | E79: =IF($S$4=0,IF($L79="","",$L79),IFERROR(IF([1]筐子进出接口!$E$78=0,"",[1]筐子进出接口!$E$78),"")) | F79: =IF($S$4=0,IF($M79="","",$M79),IFERROR(IF([1]筐子进出接口!$F$78=0,"",[1]筐子进出接口!$F$78),"")) | G79: =IF($S$4=0,IF($N79="","",$N79),IFERROR(IF([1]筐子进出接口!$G$78=0,"",[1]筐子进出接口!$G$78),"")) | H79: =IF($B79="","",N($D79)) | O79: =IF(AND($B79<>"",$C79<>""),1,0) -> 0 | P79: =N(P78)+$O79 -> 22
A80: 79 | B80: =IF($S$4=0,IF($I80="","",$I80),IFERROR(IF([1]筐子进出接口!$B$79=0,"",[1]筐子进出接口!$B$79),"")) | C80: =IF($S$4=0,IF($J80="","",$J80),IFERROR(IF([1]筐子进出接口!$C$79=0,"",[1]筐子进出接口!$C$79),"")) | D80: =IF($S$4=0,IF($K80="","",$K80),IFERROR(IF([1]筐子进出接口!$D$79=0,"",[1]筐子进出接口!$D$79),"")) | E80: =IF($S$4=0,IF($L80="","",$L80),IFERROR(IF([1]筐子进出接口!$E$79=0,"",[1]筐子进出接口!$E$79),"")) | F80: =IF($S$4=0,IF($M80="","",$M80),IFERROR(IF([1]筐子进出接口!$F$79=0,"",[1]筐子进出接口!$F$79),"")) | G80: =IF($S$4=0,IF($N80="","",$N80),IFERROR(IF([1]筐子进出接口!$G$79=0,"",[1]筐子进出接口!$G$79),"")) | H80: =IF($B80="","",N($D80)) | O80: =IF(AND($B80<>"",$C80<>""),1,0) -> 0 | P80: =N(P79)+$O80 -> 22
A81: 80 | B81: =IF($S$4=0,IF($I81="","",$I81),IFERROR(IF([1]筐子进出接口!$B$80=0,"",[1]筐子进出接口!$B$80),"")) | C81: =IF($S$4=0,IF($J81="","",$J81),IFERROR(IF([1]筐子进出接口!$C$80=0,"",[1]筐子进出接口!$C$80),"")) | D81: =IF($S$4=0,IF($K81="","",$K81),IFERROR(IF([1]筐子进出接口!$D$80=0,"",[1]筐子进出接口!$D$80),"")) | E81: =IF($S$4=0,IF($L81="","",$L81),IFERROR(IF([1]筐子进出接口!$E$80=0,"",[1]筐子进出接口!$E$80),"")) | F81: =IF($S$4=0,IF($M81="","",$M81),IFERROR(IF([1]筐子进出接口!$F$80=0,"",[1]筐子进出接口!$F$80),"")) | G81: =IF($S$4=0,IF($N81="","",$N81),IFERROR(IF([1]筐子进出接口!$G$80=0,"",[1]筐子进出接口!$G$80),"")) | H81: =IF($B81="","",N($D81)) | O81: =IF(AND($B81<>"",$C81<>""),1,0) -> 0 | P81: =N(P80)+$O81 -> 22
A82: 81 | B82: =IF($S$4=0,IF($I82="","",$I82),IFERROR(IF([1]筐子进出接口!$B$81=0,"",[1]筐子进出接口!$B$81),"")) | C82: =IF($S$4=0,IF($J82="","",$J82),IFERROR(IF([1]筐子进出接口!$C$81=0,"",[1]筐子进出接口!$C$81),"")) | D82: =IF($S$4=0,IF($K82="","",$K82),IFERROR(IF([1]筐子进出接口!$D$81=0,"",[1]筐子进出接口!$D$81),"")) | E82: =IF($S$4=0,IF($L82="","",$L82),IFERROR(IF([1]筐子进出接口!$E$81=0,"",[1]筐子进出接口!$E$81),"")) | F82: =IF($S$4=0,IF($M82="","",$M82),IFERROR(IF([1]筐子进出接口!$F$81=0,"",[1]筐子进出接口!$F$81),"")) | G82: =IF($S$4=0,IF($N82="","",$N82),IFERROR(IF([1]筐子进出接口!$G$81=0,"",[1]筐子进出接口!$G$81),"")) | H82: =IF($B82="","",N($D82)) | O82: =IF(AND($B82<>"",$C82<>""),1,0) -> 0 | P82: =N(P81)+$O82 -> 22
A83: 82 | B83: =IF($S$4=0,IF($I83="","",$I83),IFERROR(IF([1]筐子进出接口!$B$82=0,"",[1]筐子进出接口!$B$82),"")) | C83: =IF($S$4=0,IF($J83="","",$J83),IFERROR(IF([1]筐子进出接口!$C$82=0,"",[1]筐子进出接口!$C$82),"")) | D83: =IF($S$4=0,IF($K83="","",$K83),IFERROR(IF([1]筐子进出接口!$D$82=0,"",[1]筐子进出接口!$D$82),"")) | E83: =IF($S$4=0,IF($L83="","",$L83),IFERROR(IF([1]筐子进出接口!$E$82=0,"",[1]筐子进出接口!$E$82),"")) | F83: =IF($S$4=0,IF($M83="","",$M83),IFERROR(IF([1]筐子进出接口!$F$82=0,"",[1]筐子进出接口!$F$82),"")) | G83: =IF($S$4=0,IF($N83="","",$N83),IFERROR(IF([1]筐子进出接口!$G$82=0,"",[1]筐子进出接口!$G$82),"")) | H83: =IF($B83="","",N($D83)) | O83: =IF(AND($B83<>"",$C83<>""),1,0) -> 0 | P83: =N(P82)+$O83 -> 22
A84: 83 | B84: =IF($S$4=0,IF($I84="","",$I84),IFERROR(IF([1]筐子进出接口!$B$83=0,"",[1]筐子进出接口!$B$83),"")) | C84: =IF($S$4=0,IF($J84="","",$J84),IFERROR(IF([1]筐子进出接口!$C$83=0,"",[1]筐子进出接口!$C$83),"")) | D84: =IF($S$4=0,IF($K84="","",$K84),IFERROR(IF([1]筐子进出接口!$D$83=0,"",[1]筐子进出接口!$D$83),"")) | E84: =IF($S$4=0,IF($L84="","",$L84),IFERROR(IF([1]筐子进出接口!$E$83=0,"",[1]筐子进出接口!$E$83),"")) | F84: =IF($S$4=0,IF($M84="","",$M84),IFERROR(IF([1]筐子进出接口!$F$83=0,"",[1]筐子进出接口!$F$83),"")) | G84: =IF($S$4=0,IF($N84="","",$N84),IFERROR(IF([1]筐子进出接口!$G$83=0,"",[1]筐子进出接口!$G$83),"")) | H84: =IF($B84="","",N($D84)) | O84: =IF(AND($B84<>"",$C84<>""),1,0) -> 0 | P84: =N(P83)+$O84 -> 22
A85: 84 | B85: =IF($S$4=0,IF($I85="","",$I85),IFERROR(IF([1]筐子进出接口!$B$84=0,"",[1]筐子进出接口!$B$84),"")) | C85: =IF($S$4=0,IF($J85="","",$J85),IFERROR(IF([1]筐子进出接口!$C$84=0,"",[1]筐子进出接口!$C$84),"")) | D85: =IF($S$4=0,IF($K85="","",$K85),IFERROR(IF([1]筐子进出接口!$D$84=0,"",[1]筐子进出接口!$D$84),"")) | E85: =IF($S$4=0,IF($L85="","",$L85),IFERROR(IF([1]筐子进出接口!$E$84=0,"",[1]筐子进出接口!$E$84),"")) | F85: =IF($S$4=0,IF($M85="","",$M85),IFERROR(IF([1]筐子进出接口!$F$84=0,"",[1]筐子进出接口!$F$84),"")) | G85: =IF($S$4=0,IF($N85="","",$N85),IFERROR(IF([1]筐子进出接口!$G$84=0,"",[1]筐子进出接口!$G$84),"")) | H85: =IF($B85="","",N($D85)) | O85: =IF(AND($B85<>"",$C85<>""),1,0) -> 0 | P85: =N(P84)+$O85 -> 22
A86: 85 | B86: =IF($S$4=0,IF($I86="","",$I86),IFERROR(IF([1]筐子进出接口!$B$85=0,"",[1]筐子进出接口!$B$85),"")) | C86: =IF($S$4=0,IF($J86="","",$J86),IFERROR(IF([1]筐子进出接口!$C$85=0,"",[1]筐子进出接口!$C$85),"")) | D86: =IF($S$4=0,IF($K86="","",$K86),IFERROR(IF([1]筐子进出接口!$D$85=0,"",[1]筐子进出接口!$D$85),"")) | E86: =IF($S$4=0,IF($L86="","",$L86),IFERROR(IF([1]筐子进出接口!$E$85=0,"",[1]筐子进出接口!$E$85),"")) | F86: =IF($S$4=0,IF($M86="","",$M86),IFERROR(IF([1]筐子进出接口!$F$85=0,"",[1]筐子进出接口!$F$85),"")) | G86: =IF($S$4=0,IF($N86="","",$N86),IFERROR(IF([1]筐子进出接口!$G$85=0,"",[1]筐子进出接口!$G$85),"")) | H86: =IF($B86="","",N($D86)) | O86: =IF(AND($B86<>"",$C86<>""),1,0) -> 0 | P86: =N(P85)+$O86 -> 22
A87: 86 | B87: =IF($S$4=0,IF($I87="","",$I87),IFERROR(IF([1]筐子进出接口!$B$86=0,"",[1]筐子进出接口!$B$86),"")) | C87: =IF($S$4=0,IF($J87="","",$J87),IFERROR(IF([1]筐子进出接口!$C$86=0,"",[1]筐子进出接口!$C$86),"")) | D87: =IF($S$4=0,IF($K87="","",$K87),IFERROR(IF([1]筐子进出接口!$D$86=0,"",[1]筐子进出接口!$D$86),"")) | E87: =IF($S$4=0,IF($L87="","",$L87),IFERROR(IF([1]筐子进出接口!$E$86=0,"",[1]筐子进出接口!$E$86),"")) | F87: =IF($S$4=0,IF($M87="","",$M87),IFERROR(IF([1]筐子进出接口!$F$86=0,"",[1]筐子进出接口!$F$86),"")) | G87: =IF($S$4=0,IF($N87="","",$N87),IFERROR(IF([1]筐子进出接口!$G$86=0,"",[1]筐子进出接口!$G$86),"")) | H87: =IF($B87="","",N($D87)) | O87: =IF(AND($B87<>"",$C87<>""),1,0) -> 0 | P87: =N(P86)+$O87 -> 22
A88: 87 | B88: =IF($S$4=0,IF($I88="","",$I88),IFERROR(IF([1]筐子进出接口!$B$87=0,"",[1]筐子进出接口!$B$87),"")) | C88: =IF($S$4=0,IF($J88="","",$J88),IFERROR(IF([1]筐子进出接口!$C$87=0,"",[1]筐子进出接口!$C$87),"")) | D88: =IF($S$4=0,IF($K88="","",$K88),IFERROR(IF([1]筐子进出接口!$D$87=0,"",[1]筐子进出接口!$D$87),"")) | E88: =IF($S$4=0,IF($L88="","",$L88),IFERROR(IF([1]筐子进出接口!$E$87=0,"",[1]筐子进出接口!$E$87),"")) | F88: =IF($S$4=0,IF($M88="","",$M88),IFERROR(IF([1]筐子进出接口!$F$87=0,"",[1]筐子进出接口!$F$87),"")) | G88: =IF($S$4=0,IF($N88="","",$N88),IFERROR(IF([1]筐子进出接口!$G$87=0,"",[1]筐子进出接口!$G$87),"")) | H88: =IF($B88="","",N($D88)) | O88: =IF(AND($B88<>"",$C88<>""),1,0) -> 0 | P88: =N(P87)+$O88 -> 22
A89: 88 | B89: =IF($S$4=0,IF($I89="","",$I89),IFERROR(IF([1]筐子进出接口!$B$88=0,"",[1]筐子进出接口!$B$88),"")) | C89: =IF($S$4=0,IF($J89="","",$J89),IFERROR(IF([1]筐子进出接口!$C$88=0,"",[1]筐子进出接口!$C$88),"")) | D89: =IF($S$4=0,IF($K89="","",$K89),IFERROR(IF([1]筐子进出接口!$D$88=0,"",[1]筐子进出接口!$D$88),"")) | E89: =IF($S$4=0,IF($L89="","",$L89),IFERROR(IF([1]筐子进出接口!$E$88=0,"",[1]筐子进出接口!$E$88),"")) | F89: =IF($S$4=0,IF($M89="","",$M89),IFERROR(IF([1]筐子进出接口!$F$88=0,"",[1]筐子进出接口!$F$88),"")) | G89: =IF($S$4=0,IF($N89="","",$N89),IFERROR(IF([1]筐子进出接口!$G$88=0,"",[1]筐子进出接口!$G$88),"")) | H89: =IF($B89="","",N($D89)) | O89: =IF(AND($B89<>"",$C89<>""),1,0) -> 0 | P89: =N(P88)+$O89 -> 22
A90: 89 | B90: =IF($S$4=0,IF($I90="","",$I90),IFERROR(IF([1]筐子进出接口!$B$89=0,"",[1]筐子进出接口!$B$89),"")) | C90: =IF($S$4=0,IF($J90="","",$J90),IFERROR(IF([1]筐子进出接口!$C$89=0,"",[1]筐子进出接口!$C$89),"")) | D90: =IF($S$4=0,IF($K90="","",$K90),IFERROR(IF([1]筐子进出接口!$D$89=0,"",[1]筐子进出接口!$D$89),"")) | E90: =IF($S$4=0,IF($L90="","",$L90),IFERROR(IF([1]筐子进出接口!$E$89=0,"",[1]筐子进出接口!$E$89),"")) | F90: =IF($S$4=0,IF($M90="","",$M90),IFERROR(IF([1]筐子进出接口!$F$89=0,"",[1]筐子进出接口!$F$89),"")) | G90: =IF($S$4=0,IF($N90="","",$N90),IFERROR(IF([1]筐子进出接口!$G$89=0,"",[1]筐子进出接口!$G$89),"")) | H90: =IF($B90="","",N($D90)) | O90: =IF(AND($B90<>"",$C90<>""),1,0) -> 0 | P90: =N(P89)+$O90 -> 22
A91: 90 | B91: =IF($S$4=0,IF($I91="","",$I91),IFERROR(IF([1]筐子进出接口!$B$90=0,"",[1]筐子进出接口!$B$90),"")) | C91: =IF($S$4=0,IF($J91="","",$J91),IFERROR(IF([1]筐子进出接口!$C$90=0,"",[1]筐子进出接口!$C$90),"")) | D91: =IF($S$4=0,IF($K91="","",$K91),IFERROR(IF([1]筐子进出接口!$D$90=0,"",[1]筐子进出接口!$D$90),"")) | E91: =IF($S$4=0,IF($L91="","",$L91),IFERROR(IF([1]筐子进出接口!$E$90=0,"",[1]筐子进出接口!$E$90),"")) | F91: =IF($S$4=0,IF($M91="","",$M91),IFERROR(IF([1]筐子进出接口!$F$90=0,"",[1]筐子进出接口!$F$90),"")) | G91: =IF($S$4=0,IF($N91="","",$N91),IFERROR(IF([1]筐子进出接口!$G$90=0,"",[1]筐子进出接口!$G$90),"")) | H91: =IF($B91="","",N($D91)) | O91: =IF(AND($B91<>"",$C91<>""),1,0) -> 0 | P91: =N(P90)+$O91 -> 22
A92: 91 | B92: =IF($S$4=0,IF($I92="","",$I92),IFERROR(IF([1]筐子进出接口!$B$91=0,"",[1]筐子进出接口!$B$91),"")) | C92: =IF($S$4=0,IF($J92="","",$J92),IFERROR(IF([1]筐子进出接口!$C$91=0,"",[1]筐子进出接口!$C$91),"")) | D92: =IF($S$4=0,IF($K92="","",$K92),IFERROR(IF([1]筐子进出接口!$D$91=0,"",[1]筐子进出接口!$D$91),"")) | E92: =IF($S$4=0,IF($L92="","",$L92),IFERROR(IF([1]筐子进出接口!$E$91=0,"",[1]筐子进出接口!$E$91),"")) | F92: =IF($S$4=0,IF($M92="","",$M92),IFERROR(IF([1]筐子进出接口!$F$91=0,"",[1]筐子进出接口!$F$91),"")) | G92: =IF($S$4=0,IF($N92="","",$N92),IFERROR(IF([1]筐子进出接口!$G$91=0,"",[1]筐子进出接口!$G$91),"")) | H92: =IF($B92="","",N($D92)) | O92: =IF(AND($B92<>"",$C92<>""),1,0) -> 0 | P92: =N(P91)+$O92 -> 22
A93: 92 | B93: =IF($S$4=0,IF($I93="","",$I93),IFERROR(IF([1]筐子进出接口!$B$92=0,"",[1]筐子进出接口!$B$92),"")) | C93: =IF($S$4=0,IF($J93="","",$J93),IFERROR(IF([1]筐子进出接口!$C$92=0,"",[1]筐子进出接口!$C$92),"")) | D93: =IF($S$4=0,IF($K93="","",$K93),IFERROR(IF([1]筐子进出接口!$D$92=0,"",[1]筐子进出接口!$D$92),"")) | E93: =IF($S$4=0,IF($L93="","",$L93),IFERROR(IF([1]筐子进出接口!$E$92=0,"",[1]筐子进出接口!$E$92),"")) | F93: =IF($S$4=0,IF($M93="","",$M93),IFERROR(IF([1]筐子进出接口!$F$92=0,"",[1]筐子进出接口!$F$92),"")) | G93: =IF($S$4=0,IF($N93="","",$N93),IFERROR(IF([1]筐子进出接口!$G$92=0,"",[1]筐子进出接口!$G$92),"")) | H93: =IF($B93="","",N($D93)) | O93: =IF(AND($B93<>"",$C93<>""),1,0) -> 0 | P93: =N(P92)+$O93 -> 22
A94: 93 | B94: =IF($S$4=0,IF($I94="","",$I94),IFERROR(IF([1]筐子进出接口!$B$93=0,"",[1]筐子进出接口!$B$93),"")) | C94: =IF($S$4=0,IF($J94="","",$J94),IFERROR(IF([1]筐子进出接口!$C$93=0,"",[1]筐子进出接口!$C$93),"")) | D94: =IF($S$4=0,IF($K94="","",$K94),IFERROR(IF([1]筐子进出接口!$D$93=0,"",[1]筐子进出接口!$D$93),"")) | E94: =IF($S$4=0,IF($L94="","",$L94),IFERROR(IF([1]筐子进出接口!$E$93=0,"",[1]筐子进出接口!$E$93),"")) | F94: =IF($S$4=0,IF($M94="","",$M94),IFERROR(IF([1]筐子进出接口!$F$93=0,"",[1]筐子进出接口!$F$93),"")) | G94: =IF($S$4=0,IF($N94="","",$N94),IFERROR(IF([1]筐子进出接口!$G$93=0,"",[1]筐子进出接口!$G$93),"")) | H94: =IF($B94="","",N($D94)) | O94: =IF(AND($B94<>"",$C94<>""),1,0) -> 0 | P94: =N(P93)+$O94 -> 22
A95: 94 | B95: =IF($S$4=0,IF($I95="","",$I95),IFERROR(IF([1]筐子进出接口!$B$94=0,"",[1]筐子进出接口!$B$94),"")) | C95: =IF($S$4=0,IF($J95="","",$J95),IFERROR(IF([1]筐子进出接口!$C$94=0,"",[1]筐子进出接口!$C$94),"")) | D95: =IF($S$4=0,IF($K95="","",$K95),IFERROR(IF([1]筐子进出接口!$D$94=0,"",[1]筐子进出接口!$D$94),"")) | E95: =IF($S$4=0,IF($L95="","",$L95),IFERROR(IF([1]筐子进出接口!$E$94=0,"",[1]筐子进出接口!$E$94),"")) | F95: =IF($S$4=0,IF($M95="","",$M95),IFERROR(IF([1]筐子进出接口!$F$94=0,"",[1]筐子进出接口!$F$94),"")) | G95: =IF($S$4=0,IF($N95="","",$N95),IFERROR(IF([1]筐子进出接口!$G$94=0,"",[1]筐子进出接口!$G$94),"")) | H95: =IF($B95="","",N($D95)) | O95: =IF(AND($B95<>"",$C95<>""),1,0) -> 0 | P95: =N(P94)+$O95 -> 22
A96: 95 | B96: =IF($S$4=0,IF($I96="","",$I96),IFERROR(IF([1]筐子进出接口!$B$95=0,"",[1]筐子进出接口!$B$95),"")) | C96: =IF($S$4=0,IF($J96="","",$J96),IFERROR(IF([1]筐子进出接口!$C$95=0,"",[1]筐子进出接口!$C$95),"")) | D96: =IF($S$4=0,IF($K96="","",$K96),IFERROR(IF([1]筐子进出接口!$D$95=0,"",[1]筐子进出接口!$D$95),"")) | E96: =IF($S$4=0,IF($L96="","",$L96),IFERROR(IF([1]筐子进出接口!$E$95=0,"",[1]筐子进出接口!$E$95),"")) | F96: =IF($S$4=0,IF($M96="","",$M96),IFERROR(IF([1]筐子进出接口!$F$95=0,"",[1]筐子进出接口!$F$95),"")) | G96: =IF($S$4=0,IF($N96="","",$N96),IFERROR(IF([1]筐子进出接口!$G$95=0,"",[1]筐子进出接口!$G$95),"")) | H96: =IF($B96="","",N($D96)) | O96: =IF(AND($B96<>"",$C96<>""),1,0) -> 0 | P96: =N(P95)+$O96 -> 22
A97: 96 | B97: =IF($S$4=0,IF($I97="","",$I97),IFERROR(IF([1]筐子进出接口!$B$96=0,"",[1]筐子进出接口!$B$96),"")) | C97: =IF($S$4=0,IF($J97="","",$J97),IFERROR(IF([1]筐子进出接口!$C$96=0,"",[1]筐子进出接口!$C$96),"")) | D97: =IF($S$4=0,IF($K97="","",$K97),IFERROR(IF([1]筐子进出接口!$D$96=0,"",[1]筐子进出接口!$D$96),"")) | E97: =IF($S$4=0,IF($L97="","",$L97),IFERROR(IF([1]筐子进出接口!$E$96=0,"",[1]筐子进出接口!$E$96),"")) | F97: =IF($S$4=0,IF($M97="","",$M97),IFERROR(IF([1]筐子进出接口!$F$96=0,"",[1]筐子进出接口!$F$96),"")) | G97: =IF($S$4=0,IF($N97="","",$N97),IFERROR(IF([1]筐子进出接口!$G$96=0,"",[1]筐子进出接口!$G$96),"")) | H97: =IF($B97="","",N($D97)) | O97: =IF(AND($B97<>"",$C97<>""),1,0) -> 0 | P97: =N(P96)+$O97 -> 22
A98: 97 | B98: =IF($S$4=0,IF($I98="","",$I98),IFERROR(IF([1]筐子进出接口!$B$97=0,"",[1]筐子进出接口!$B$97),"")) | C98: =IF($S$4=0,IF($J98="","",$J98),IFERROR(IF([1]筐子进出接口!$C$97=0,"",[1]筐子进出接口!$C$97),"")) | D98: =IF($S$4=0,IF($K98="","",$K98),IFERROR(IF([1]筐子进出接口!$D$97=0,"",[1]筐子进出接口!$D$97),"")) | E98: =IF($S$4=0,IF($L98="","",$L98),IFERROR(IF([1]筐子进出接口!$E$97=0,"",[1]筐子进出接口!$E$97),"")) | F98: =IF($S$4=0,IF($M98="","",$M98),IFERROR(IF([1]筐子进出接口!$F$97=0,"",[1]筐子进出接口!$F$97),"")) | G98: =IF($S$4=0,IF($N98="","",$N98),IFERROR(IF([1]筐子进出接口!$G$97=0,"",[1]筐子进出接口!$G$97),"")) | H98: =IF($B98="","",N($D98)) | O98: =IF(AND($B98<>"",$C98<>""),1,0) -> 0 | P98: =N(P97)+$O98 -> 22
A99: 98 | B99: =IF($S$4=0,IF($I99="","",$I99),IFERROR(IF([1]筐子进出接口!$B$98=0,"",[1]筐子进出接口!$B$98),"")) | C99: =IF($S$4=0,IF($J99="","",$J99),IFERROR(IF([1]筐子进出接口!$C$98=0,"",[1]筐子进出接口!$C$98),"")) | D99: =IF($S$4=0,IF($K99="","",$K99),IFERROR(IF([1]筐子进出接口!$D$98=0,"",[1]筐子进出接口!$D$98),"")) | E99: =IF($S$4=0,IF($L99="","",$L99),IFERROR(IF([1]筐子进出接口!$E$98=0,"",[1]筐子进出接口!$E$98),"")) | F99: =IF($S$4=0,IF($M99="","",$M99),IFERROR(IF([1]筐子进出接口!$F$98=0,"",[1]筐子进出接口!$F$98),"")) | G99: =IF($S$4=0,IF($N99="","",$N99),IFERROR(IF([1]筐子进出接口!$G$98=0,"",[1]筐子进出接口!$G$98),"")) | H99: =IF($B99="","",N($D99)) | O99: =IF(AND($B99<>"",$C99<>""),1,0) -> 0 | P99: =N(P98)+$O99 -> 22
A100: 99 | B100: =IF($S$4=0,IF($I100="","",$I100),IFERROR(IF([1]筐子进出接口!$B$99=0,"",[1]筐子进出接口!$B$99),"")) | C100: =IF($S$4=0,IF($J100="","",$J100),IFERROR(IF([1]筐子进出接口!$C$99=0,"",[1]筐子进出接口!$C$99),"")) | D100: =IF($S$4=0,IF($K100="","",$K100),IFERROR(IF([1]筐子进出接口!$D$99=0,"",[1]筐子进出接口!$D$99),"")) | E100: =IF($S$4=0,IF($L100="","",$L100),IFERROR(IF([1]筐子进出接口!$E$99=0,"",[1]筐子进出接口!$E$99),"")) | F100: =IF($S$4=0,IF($M100="","",$M100),IFERROR(IF([1]筐子进出接口!$F$99=0,"",[1]筐子进出接口!$F$99),"")) | G100: =IF($S$4=0,IF($N100="","",$N100),IFERROR(IF([1]筐子进出接口!$G$99=0,"",[1]筐子进出接口!$G$99),"")) | H100: =IF($B100="","",N($D100)) | O100: =IF(AND($B100<>"",$C100<>""),1,0) -> 0 | P100: =N(P99)+$O100 -> 22
...

Sheet 周转筐出入库明细
A1: 周 转 筐 出 / 入 库 明 细 表
A2: ★"剩余库存"已改为按筐子类型分别滚动结存＝该类型的 期初＋采购入库＋客户退回入库 − 发出出库 − 销售出库，不再是不分类型的总数。押金：收押金/退押金按实收实退填，押金余额在【押金汇总】看
A3: 序号 | B3: 日期 | C3: 供应商/客户 | D3: 筐子类型 | E3: 票据单号 | F3: 业务类型 | G3: 期初库存 | H3: 入库数量 | I3: 退回数量(显示为负) | J3: 出库数量 | K3: 销售数量 | L3: 剩余库存 | M3: 车牌号 | N3: 装卸 | O3: 采购/销售单价 | P3: 采购/销售金额 | Q3: 收付款状态 | R3: 结算方式 | S3: 收押金 | T3: 退押金 (显示为负) | U3: 押金结清 | V3: 核查结果 | W3: 备注
A4: =IF($D4="","",ROW()-3) -> 1 | D4: 公司一次性筐 | F4: 期初库存 | G4: =IF($D4="","",N($L4)-N($H4)-N($I4)+N($J4)+N($K4)) -> 0 | H4: 69840 | I4: 0 | J4: 0 | K4: 0 | L4: =IF($D4="","",SUMIFS($H$4:$H4,$D$4:$D4,$D4)+SUMIFS($I$4:$I4,$D$4:$D4,$D4)-SUMIFS($J$4:$J4,$D$4:$D4,$D4)-SUMIFS($K$4:$K4,$D$4:$D4,$D4)) -> 69840 | P4: =IF($D4="","",ROUND((N($H4)+N($K4))*N($O4),2)) -> 0
A5: =IF($D5="","",ROW()-3) -> 2 | D5: 公司杂周转筐 | F5: 期初库存 | G5: =IF($D5="","",N($L5)-N($H5)-N($I5)+N($J5)+N($K5)) -> 0 | H5: 35928 | I5: 0 | J5: 0 | K5: 0 | L5: =IF($D5="","",SUMIFS($H$4:$H5,$D$4:$D5,$D5)+SUMIFS($I$4:$I5,$D$4:$D5,$D5)-SUMIFS($J$4:$J5,$D$4:$D5,$D5)-SUMIFS($K$4:$K5,$D$4:$D5,$D5)) -> 35928 | P5: =IF($D5="","",ROUND((N($H5)+N($K5))*N($O5),2)) -> 0
A6: =IF($D6="","",ROW()-3) -> 3 | D6: 公司新周转筐 | F6: 期初库存 | G6: =IF($D6="","",N($L6)-N($H6)-N($I6)+N($J6)+N($K6)) -> 0 | H6: 58032 | I6: 0 | J6: 0 | K6: 0 | L6: =IF($D6="","",SUMIFS($H$4:$H6,$D$4:$D6,$D6)+SUMIFS($I$4:$I6,$D$4:$D6,$D6)-SUMIFS($J$4:$J6,$D$4:$D6,$D6)-SUMIFS($K$4:$K6,$D$4:$D6,$D6)) -> 58032 | P6: =IF($D6="","",ROUND((N($H6)+N($K6))*N($O6),2)) -> 0
A7: =IF($D7="","",ROW()-3) -> 4 | D7: 公司白周转筐 | F7: 期初库存 | G7: =IF($D7="","",N($L7)-N($H7)-N($I7)+N($J7)+N($K7)) -> 0 | H7: 13968 | I7: 0 | J7: 0 | K7: 0 | L7: =IF($D7="","",SUMIFS($H$4:$H7,$D$4:$D7,$D7)+SUMIFS($I$4:$I7,$D$4:$D7,$D7)-SUMIFS($J$4:$J7,$D$4:$D7,$D7)-SUMIFS($K$4:$K7,$D$4:$D7,$D7)) -> 13968 | P7: =IF($D7="","",ROUND((N($H7)+N($K7))*N($O7),2)) -> 0
A8: =IF($D8="","",ROW()-3) -> 5 | B8: 46245 | C8: 王照雪 | D8: 公司杂周转筐 | E8: NO:0001015 | F8: 领用出库 | G8: =IF($D8="","",N($L8)-N($H8)-N($I8)+N($J8)+N($K8)) -> 35928 | H8: - | I8: - | J8: 351 | K8: - | L8: =IF($D8="","",SUMIFS($H$4:$H8,$D$4:$D8,$D8)+SUMIFS($I$4:$I8,$D$4:$D8,$D8)-SUMIFS($J$4:$J8,$D$4:$D8,$D8)-SUMIFS($K$4:$K8,$D$4:$D8,$D8)) -> 35577 | M8: 豫L*88X19 | N8: 依力 | P8: =IF($D8="","",ROUND((N($H8)+N($K8))*N($O8),2)) -> 0
A9: =IF($D9="","",ROW()-3) -> 6 | B9: 46255 | C9: 王照雪 | D9: 公司杂周转筐 | E9: NO:0001022 | F9: 领用出库 | G9: =IF($D9="","",N($L9)-N($H9)-N($I9)+N($J9)+N($K9)) -> 35577 | H9: - | I9: - | J9: 432 | K9: - | L9: =IF($D9="","",SUMIFS($H$4:$H9,$D$4:$D9,$D9)+SUMIFS($I$4:$I9,$D$4:$D9,$D9)-SUMIFS($J$4:$J9,$D$4:$D9,$D9)-SUMIFS($K$4:$K9,$D$4:$D9,$D9)) -> 35145 | M9: 豫L*88X19 | N9: 依力 | P9: =IF($D9="","",ROUND((N($H9)+N($K9))*N($O9),2)) -> 0
A10: =IF($D10="","",ROW()-3) -> 7 | B10: 46258 | C10: 王照雪 | D10: 公司杂周转筐 | E10: NO:0001031 | F10: 领用出库 | G10: =IF($D10="","",N($L10)-N($H10)-N($I10)+N($J10)+N($K10)) -> 35145 | H10: - | I10: - | J10: 282 | K10: - | L10: =IF($D10="","",SUMIFS($H$4:$H10,$D$4:$D10,$D10)+SUMIFS($I$4:$I10,$D$4:$D10,$D10)-SUMIFS($J$4:$J10,$D$4:$D10,$D10)-SUMIFS($K$4:$K10,$D$4:$D10,$D10)) -> 34863 | M10: 豫L*88X19 | N10: 依力 | P10: =IF($D10="","",ROUND((N($H10)+N($K10))*N($O10),2)) -> 0
A11: =IF($D11="","",ROW()-3) -> 8 | B11: 46260 | C11: 王照雪 | D11: 公司杂周转筐 | E11: NO:0001037 | F11: 领用出库 | G11: =IF($D11="","",N($L11)-N($H11)-N($I11)+N($J11)+N($K11)) -> 34863 | H11: - | I11: - | J11: 144 | K11: - | L11: =IF($D11="","",SUMIFS($H$4:$H11,$D$4:$D11,$D11)+SUMIFS($I$4:$I11,$D$4:$D11,$D11)-SUMIFS($J$4:$J11,$D$4:$D11,$D11)-SUMIFS($K$4:$K11,$D$4:$D11,$D11)) -> 34719 | M11: 豫L*88X19 | N11: 依力 | P11: =IF($D11="","",ROUND((N($H11)+N($K11))*N($O11),2)) -> 0
A12: =IF($D12="","",ROW()-3) -> 9 | B12: 46258 | C12: 王照雪 | D12: 公司杂周转筐 | E12: NO:0000721 | F12: 退回入库 | G12: =IF($D12="","",N($L12)-N($H12)-N($I12)+N($J12)+N($K12)) -> 34719 | H12: - | I12: 4 | J12: - | K12: - | L12: =IF($D12="","",SUMIFS($H$4:$H12,$D$4:$D12,$D12)+SUMIFS($I$4:$I12,$D$4:$D12,$D12)-SUMIFS($J$4:$J12,$D$4:$D12,$D12)-SUMIFS($K$4:$K12,$D$4:$D12,$D12)) -> 34723 | M12: 豫L*88X19 | N12: 依力 | P12: =IF($D12="","",ROUND((N($H12)+N($K12))*N($O12),2)) -> 0
A13: =IF($D13="","",ROW()-3) -> 10 | B13: 46265 | C13: 王浩 | D13: 公司一次性筐 | E13: NO:0001057 | F13: 领用出库 | G13: =IF($D13="","",N($L13)-N($H13)-N($I13)+N($J13)+N($K13)) -> 69840 | H13: - | I13: - | J13: 2040 | K13: - | L13: =IF($D13="","",SUMIFS($H$4:$H13,$D$4:$D13,$D13)+SUMIFS($I$4:$I13,$D$4:$D13,$D13)-SUMIFS($J$4:$J13,$D$4:$D13,$D13)-SUMIFS($K$4:$K13,$D$4:$D13,$D13)) -> 67800 | M13: 新Q*67674 | N13: 依力 | P13: =IF($D13="","",ROUND((N($H13)+N($K13))*N($O13),2)) -> 0
A14: =IF($D14="","",ROW()-3) -> 11 | B14: 46266 | C14: 马锦祥 | D14: 公司杂周转筐 | E14: NO:0001061 | F14: 领用出库 | G14: =IF($D14="","",N($L14)-N($H14)-N($I14)+N($J14)+N($K14)) -> 34723 | H14: - | I14: - | J14: 588 | K14: - | L14: =IF($D14="","",SUMIFS($H$4:$H14,$D$4:$D14,$D14)+SUMIFS($I$4:$I14,$D$4:$D14,$D14)-SUMIFS($J$4:$J14,$D$4:$D14,$D14)-SUMIFS($K$4:$K14,$D$4:$D14,$D14)) -> 34135 | M14: 新N*K7V85 | N14: 依力 | P14: =IF($D14="","",ROUND((N($H14)+N($K14))*N($O14),2)) -> 0
A15: =IF($D15="","",ROW()-3) -> 12 | B15: 46266 | C15: 王照雪 | D15: 公司杂周转筐 | E15: NO:0000742 | F15: 退回入库 | G15: =IF($D15="","",N($L15)-N($H15)-N($I15)+N($J15)+N($K15)) -> 34135 | H15: - | I15: 30 | J15: - | K15: - | L15: =IF($D15="","",SUMIFS($H$4:$H15,$D$4:$D15,$D15)+SUMIFS($I$4:$I15,$D$4:$D15,$D15)-SUMIFS($J$4:$J15,$D$4:$D15,$D15)-SUMIFS($K$4:$K15,$D$4:$D15,$D15)) -> 34165 | M15: 新N*D1W48 | N15: 依力 | P15: =IF($D15="","",ROUND((N($H15)+N($K15))*N($O15),2)) -> 0
A16: =IF($D16="","",ROW()-3) -> 13 | B16: 46267 | C16: 全修塑业 | D16: 公司红周转筐 | E16: NO:0000744 | F16: 采购入库 | G16: =IF($D16="","",N($L16)-N($H16)-N($I16)+N($J16)+N($K16)) -> 0 | H16: 315 | I16: - | J16: - | K16: - | L16: =IF($D16="","",SUMIFS($H$4:$H16,$D$4:$D16,$D16)+SUMIFS($I$4:$I16,$D$4:$D16,$D16)-SUMIFS($J$4:$J16,$D$4:$D16,$D16)-SUMIFS($K$4:$K16,$D$4:$D16,$D16)) -> 315 | M16: 新N*X8S48 | N16: 筐厂 | O16: 10 | P16: =IF($D16="","",ROUND((N($H16)+N($K16))*N($O16),2)) -> 3150 | Q16: 未付款 | W16: NO:2745225
A17: =IF($D17="","",ROW()-3) -> 14 | B17: 46267 | C17: 吐尔洪 | D17: 公司红周转筐 | E17: NO:0001067 | F17: 领用出库 | G17: =IF($D17="","",N($L17)-N($H17)-N($I17)+N($J17)+N($K17)) -> 315 | H17: - | I17: - | J17: 315 | K17: - | L17: =IF($D17="","",SUMIFS($H$4:$H17,$D$4:$D17,$D17)+SUMIFS($I$4:$I17,$D$4:$D17,$D17)-SUMIFS($J$4:$J17,$D$4:$D17,$D17)-SUMIFS($K$4:$K17,$D$4:$D17,$D17)) -> 0 | M17: 新N*X8S48 | N17: 筐厂 | P17: =IF($D17="","",ROUND((N($H17)+N($K17))*N($O17),2)) -> 0
A18: =IF($D18="","",ROW()-3) -> 15 | B18: 46268 | C18: 全修塑业 | D18: 公司红周转筐 | E18: NO:0000745 | F18: 采购入库 | G18: =IF($D18="","",N($L18)-N($H18)-N($I18)+N($J18)+N($K18)) -> 0 | H18: 315 | I18: - | J18: - | K18: - | L18: =IF($D18="","",SUMIFS($H$4:$H18,$D$4:$D18,$D18)+SUMIFS($I$4:$I18,$D$4:$D18,$D18)-SUMIFS($J$4:$J18,$D$4:$D18,$D18)-SUMIFS($K$4:$K18,$D$4:$D18,$D18)) -> 315 | M18: 新N*X8S48 | N18: 筐厂 | O18: 10 | P18: =IF($D18="","",ROUND((N($H18)+N($K18))*N($O18),2)) -> 3150 | Q18: 未付款 | W18: NO:2745241
A19: =IF($D19="","",ROW()-3) -> 16 | B19: 46268 | C19: 吐尔洪 | D19: 公司红周转筐 | E19: NO:0001068 | F19: 领用出库 | G19: =IF($D19="","",N($L19)-N($H19)-N($I19)+N($J19)+N($K19)) -> 315 | H19: - | I19: - | J19: 315 | K19: - | L19: =IF($D19="","",SUMIFS($H$4:$H19,$D$4:$D19,$D19)+SUMIFS($I$4:$I19,$D$4:$D19,$D19)-SUMIFS($J$4:$J19,$D$4:$D19,$D19)-SUMIFS($K$4:$K19,$D$4:$D19,$D19)) -> 0 | M19: 新N*X8S48 | N19: 筐厂 | P19: =IF($D19="","",ROUND((N($H19)+N($K19))*N($O19),2)) -> 0
A20: =IF($D20="","",ROW()-3) -> 17 | B20: 46268 | C20: 全修塑业 | D20: 公司红周转筐 | E20: NO:0000746 | F20: 采购入库 | G20: =IF($D20="","",N($L20)-N($H20)-N($I20)+N($J20)+N($K20)) -> 0 | H20: 846 | I20: - | J20: - | K20: - | L20: =IF($D20="","",SUMIFS($H$4:$H20,$D$4:$D20,$D20)+SUMIFS($I$4:$I20,$D$4:$D20,$D20)-SUMIFS($J$4:$J20,$D$4:$D20,$D20)-SUMIFS($K$4:$K20,$D$4:$D20,$D20)) -> 846 | M20: 新A*G0554 | N20: 筐厂 | O20: 10 | P20: =IF($D20="","",ROUND((N($H20)+N($K20))*N($O20),2)) -> 8460 | Q20: 未付款 | W20: NO:2745242
A21: =IF($D21="","",ROW()-3) -> 18 | B21: 46268 | C21: 热合曼 | D21: 公司红周转筐 | E21: NO:0001069 | F21: 领用出库 | G21: =IF($D21="","",N($L21)-N($H21)-N($I21)+N($J21)+N($K21)) -> 846 | H21: - | I21: - | J21: 846 | K21: - | L21: =IF($D21="","",SUMIFS($H$4:$H21,$D$4:$D21,$D21)+SUMIFS($I$4:$I21,$D$4:$D21,$D21)-SUMIFS($J$4:$J21,$D$4:$D21,$D21)-SUMIFS($K$4:$K21,$D$4:$D21,$D21)) -> 0 | M21: 新A*G0554 | N21: 筐厂 | P21: =IF($D21="","",ROUND((N($H21)+N($K21))*N($O21),2)) -> 0
A22: =IF($D22="","",ROW()-3) -> 19 | B22: 46268 | C22: 全修塑业 | D22: 公司红周转筐 | E22: NO:0000747 | F22: 采购入库 | G22: =IF($D22="","",N($L22)-N($H22)-N($I22)+N($J22)+N($K22)) -> 0 | H22: 960 | I22: - | J22: - | K22: - | L22: =IF($D22="","",SUMIFS($H$4:$H22,$D$4:$D22,$D22)+SUMIFS($I$4:$I22,$D$4:$D22,$D22)-SUMIFS($J$4:$J22,$D$4:$D22,$D22)-SUMIFS($K$4:$K22,$D$4:$D22,$D22)) -> 960 | M22: 新N*49209 | N22: 筐厂 | O22: 10 | P22: =IF($D22="","",ROUND((N($H22)+N($K22))*N($O22),2)) -> 9600 | Q22: 未付款 | W22: NO:2745243
A23: =IF($D23="","",ROW()-3) -> 20 | B23: 46268 | C23: 王灵云 | D23: 公司红周转筐 | E23: NO:0001072 | F23: 领用出库 | G23: =IF($D23="","",N($L23)-N($H23)-N($I23)+N($J23)+N($K23)) -> 960 | H23: - | I23: - | J23: 960 | K23: - | L23: =IF($D23="","",SUMIFS($H$4:$H23,$D$4:$D23,$D23)+SUMIFS($I$4:$I23,$D$4:$D23,$D23)-SUMIFS($J$4:$J23,$D$4:$D23,$D23)-SUMIFS($K$4:$K23,$D$4:$D23,$D23)) -> 0 | M23: 新N*49209 | N23: 筐厂 | P23: =IF($D23="","",ROUND((N($H23)+N($K23))*N($O23),2)) -> 0 | S23: 3000 | T23: 3000 | U23: 是
A24: =IF($D24="","",ROW()-3) -> 21 | B24: 46268 | C24: 全修塑业 | D24: 公司红周转筐 | E24: NO:0000748 | F24: 采购入库 | G24: =IF($D24="","",N($L24)-N($H24)-N($I24)+N($J24)+N($K24)) -> 0 | H24: 846 | I24: - | J24: - | K24: - | L24: =IF($D24="","",SUMIFS($H$4:$H24,$D$4:$D24,$D24)+SUMIFS($I$4:$I24,$D$4:$D24,$D24)-SUMIFS($J$4:$J24,$D$4:$D24,$D24)-SUMIFS($K$4:$K24,$D$4:$D24,$D24)) -> 846 | M24: 新A*G0554 | N24: 筐厂 | O24: 10 | P24: =IF($D24="","",ROUND((N($H24)+N($K24))*N($O24),2)) -> 8460 | Q24: 未付款 | W24: NO:2745244
A25: =IF($D25="","",ROW()-3) -> 22 | B25: 46268 | C25: 麦麦提 | D25: 公司红周转筐 | E25: NO:0001074 | F25: 领用出库 | G25: =IF($D25="","",N($L25)-N($H25)-N($I25)+N($J25)+N($K25)) -> 846 | H25: - | I25: - | J25: 846 | K25: - | L25: =IF($D25="","",SUMIFS($H$4:$H25,$D$4:$D25,$D25)+SUMIFS($I$4:$I25,$D$4:$D25,$D25)-SUMIFS($J$4:$J25,$D$4:$D25,$D25)-SUMIFS($K$4:$K25,$D$4:$D25,$D25)) -> 0 | M25: 新A*G0554 | N25: 筐厂 | P25: =IF($D25="","",ROUND((N($H25)+N($K25))*N($O25),2)) -> 0
A26: =IF($D26="","",ROW()-3) -> 23 | B26: 46268 | C26: 全修塑业 | D26: 公司红周转筐 | E26: NO:0000749 | F26: 采购入库 | G26: =IF($D26="","",N($L26)-N($H26)-N($I26)+N($J26)+N($K26)) -> 0 | H26: 936 | I26: - | J26: - | K26: - | L26: =IF($D26="","",SUMIFS($H$4:$H26,$D$4:$D26,$D26)+SUMIFS($I$4:$I26,$D$4:$D26,$D26)-SUMIFS($J$4:$J26,$D$4:$D26,$D26)-SUMIFS($K$4:$K26,$D$4:$D26,$D26)) -> 936 | M26: 新F*75240 | N26: 筐厂 | O26: 10 | P26: =IF($D26="","",ROUND((N($H26)+N($K26))*N($O26),2)) -> 9360 | Q26: 未付款 | W26: NO:2745245
A27: =IF($D27="","",ROW()-3) -> 24 | B27: 46268 | C27: 努尔敦 | D27: 公司红周转筐 | E27: NO:0001075 | F27: 领用出库 | G27: =IF($D27="","",N($L27)-N($H27)-N($I27)+N($J27)+N($K27)) -> 936 | H27: - | I27: - | J27: 936 | K27: - | L27: =IF($D27="","",SUMIFS($H$4:$H27,$D$4:$D27,$D27)+SUMIFS($I$4:$I27,$D$4:$D27,$D27)-SUMIFS($J$4:$J27,$D$4:$D27,$D27)-SUMIFS($K$4:$K27,$D$4:$D27,$D27)) -> 0 | M27: 新F*75240 | N27: 筐厂 | P27: =IF($D27="","",ROUND((N($H27)+N($K27))*N($O27),2)) -> 0
A28: =IF($D28="","",ROW()-3) -> 25 | B28: 46269 | C28: 全修塑业 | D28: 公司红周转筐 | E28: NO:0000750 | F28: 采购入库 | G28: =IF($D28="","",N($L28)-N($H28)-N($I28)+N($J28)+N($K28)) -> 0 | H28: 960 | I28: - | J28: - | K28: - | L28: =IF($D28="","",SUMIFS($H$4:$H28,$D$4:$D28,$D28)+SUMIFS($I$4:$I28,$D$4:$D28,$D28)-SUMIFS($J$4:$J28,$D$4:$D28,$D28)-SUMIFS($K$4:$K28,$D$4:$D28,$D28)) -> 960 | M28: 豫A*2737K | N28: 筐厂 | O28: 10 | P28: =IF($D28="","",ROUND((N($H28)+N($K28))*N($O28),2)) -> 9600 | Q28: 未付款 | W28: NO:2745247
A29: =IF($D29="","",ROW()-3) -> 26 | B29: 46269 | C29: 荆建君 | D29: 公司红周转筐 | E29: NO:0001077 | F29: 领用出库 | G29: =IF($D29="","",N($L29)-N($H29)-N($I29)+N($J29)+N($K29)) -> 960 | H29: - | I29: - | J29: 960 | K29: - | L29: =IF($D29="","",SUMIFS($H$4:$H29,$D$4:$D29,$D29)+SUMIFS($I$4:$I29,$D$4:$D29,$D29)-SUMIFS($J$4:$J29,$D$4:$D29,$D29)-SUMIFS($K$4:$K29,$D$4:$D29,$D29)) -> 0 | M29: 豫A*2737K | N29: 筐厂 | P29: =IF($D29="","",ROUND((N($H29)+N($K29))*N($O29),2)) -> 0
A30: =IF($D30="","",ROW()-3) -> 27 | B30: 46269 | C30: 马锦祥 | D30: 公司杂周转筐 | E30: NO:0001076 | F30: 领用出库 | G30: =IF($D30="","",N($L30)-N($H30)-N($I30)+N($J30)+N($K30)) -> 34165 | H30: - | I30: - | J30: 574 | K30: - | L30: =IF($D30="","",SUMIFS($H$4:$H30,$D$4:$D30,$D30)+SUMIFS($I$4:$I30,$D$4:$D30,$D30)-SUMIFS($J$4:$J30,$D$4:$D30,$D30)-SUMIFS($K$4:$K30,$D$4:$D30,$D30)) -> 33591 | M30: 新N*K7V85 | N30: 依力 | P30: =IF($D30="","",ROUND((N($H30)+N($K30))*N($O30),2)) -> 0
A31: =IF($D31="","",ROW()-3) -> 28 | B31: 46269 | C31: 全修塑业 | D31: 公司红周转筐 | E31: NO:0000751 | F31: 采购入库 | G31: =IF($D31="","",N($L31)-N($H31)-N($I31)+N($J31)+N($K31)) -> 0 | H31: 936 | I31: - | J31: - | K31: - | L31: =IF($D31="","",SUMIFS($H$4:$H31,$D$4:$D31,$D31)+SUMIFS($I$4:$I31,$D$4:$D31,$D31)-SUMIFS($J$4:$J31,$D$4:$D31,$D31)-SUMIFS($K$4:$K31,$D$4:$D31,$D31)) -> 936 | M31: 新F*75240 | N31: 筐厂 | O31: 10 | P31: =IF($D31="","",ROUND((N($H31)+N($K31))*N($O31),2)) -> 9360 | Q31: 未付款 | W31: NO:2745248
A32: =IF($D32="","",ROW()-3) -> 29 | B32: 46269 | C32: 努尔敦 | D32: 公司红周转筐 | E32: NO:0001078 | F32: 领用出库 | G32: =IF($D32="","",N($L32)-N($H32)-N($I32)+N($J32)+N($K32)) -> 936 | H32: - | I32: - | J32: 936 | K32: - | L32: =IF($D32="","",SUMIFS($H$4:$H32,$D$4:$D32,$D32)+SUMIFS($I$4:$I32,$D$4:$D32,$D32)-SUMIFS($J$4:$J32,$D$4:$D32,$D32)-SUMIFS($K$4:$K32,$D$4:$D32,$D32)) -> 0 | M32: 新F*75240 | N32: 筐厂 | P32: =IF($D32="","",ROUND((N($H32)+N($K32))*N($O32),2)) -> 0
A33: =IF($D33="","",ROW()-3) -> 30 | B33: 46269 | C33: 全修塑业 | D33: 公司红周转筐 | E33: NO:0000753 | F33: 采购入库 | G33: =IF($D33="","",N($L33)-N($H33)-N($I33)+N($J33)+N($K33)) -> 0 | H33: 582 | I33: - | J33: - | K33: - | L33: =IF($D33="","",SUMIFS($H$4:$H33,$D$4:$D33,$D33)+SUMIFS($I$4:$I33,$D$4:$D33,$D33)-SUMIFS($J$4:$J33,$D$4:$D33,$D33)-SUMIFS($K$4:$K33,$D$4:$D33,$D33)) -> 582 | M33: 豫A*2737K | N33: 筐厂 | O33: 10 | P33: =IF($D33="","",ROUND((N($H33)+N($K33))*N($O33),2)) -> 5820 | Q33: 未付款 | W33: NO:2745249
A34: =IF($D34="","",ROW()-3) -> 31 | B34: 46269 | C34: 荆建君 | D34: 公司红周转筐 | E34: NO:0001079 | F34: 领用出库 | G34: =IF($D34="","",N($L34)-N($H34)-N($I34)+N($J34)+N($K34)) -> 582 | H34: - | I34: - | J34: 582 | K34: - | L34: =IF($D34="","",SUMIFS($H$4:$H34,$D$4:$D34,$D34)+SUMIFS($I$4:$I34,$D$4:$D34,$D34)-SUMIFS($J$4:$J34,$D$4:$D34,$D34)-SUMIFS($K$4:$K34,$D$4:$D34,$D34)) -> 0 | M34: 豫A*2737K | N34: 筐厂 | P34: =IF($D34="","",ROUND((N($H34)+N($K34))*N($O34),2)) -> 0
A35: =IF($D35="","",ROW()-3) -> 32 | B35: 46270 | C35: 王浩 | D35: 公司一次性筐 | E35: NO:0001086 | F35: 领用出库 | G35: =IF($D35="","",N($L35)-N($H35)-N($I35)+N($J35)+N($K35)) -> 67800 | H35: - | I35: - | J35: 1320 | K35: - | L35: =IF($D35="","",SUMIFS($H$4:$H35,$D$4:$D35,$D35)+SUMIFS($I$4:$I35,$D$4:$D35,$D35)-SUMIFS($J$4:$J35,$D$4:$D35,$D35)-SUMIFS($K$4:$K35,$D$4:$D35,$D35)) -> 66480 | M35: 新M*79997 | N35: 依力 | P35: =IF($D35="","",ROUND((N($H35)+N($K35))*N($O35),2)) -> 0
A36: =IF($D36="","",ROW()-3) -> 33 | B36: 46271 | C36: 贾建国 | D36: 公司新周转筐 | E36: NO:0001087 | F36: 领用出库 | G36: =IF($D36="","",N($L36)-N($H36)-N($I36)+N($J36)+N($K36)) -> 58032 | H36: - | I36: - | J36: 252 | K36: - | L36: =IF($D36="","",SUMIFS($H$4:$H36,$D$4:$D36,$D36)+SUMIFS($I$4:$I36,$D$4:$D36,$D36)-SUMIFS($J$4:$J36,$D$4:$D36,$D36)-SUMIFS($K$4:$K36,$D$4:$D36,$D36)) -> 57780 | M36: 新N*56508 | N36: 依力 | P36: =IF($D36="","",ROUND((N($H36)+N($K36))*N($O36),2)) -> 0
A37: =IF($D37="","",ROW()-3) -> 34 | B37: 46272 | C37: 全修塑业 | D37: 公司红周转筐 | E37: NO:0000755 | F37: 采购入库 | G37: =IF($D37="","",N($L37)-N($H37)-N($I37)+N($J37)+N($K37)) -> 0 | H37: 846 | I37: - | J37: - | K37: - | L37: =IF($D37="","",SUMIFS($H$4:$H37,$D$4:$D37,$D37)+SUMIFS($I$4:$I37,$D$4:$D37,$D37)-SUMIFS($J$4:$J37,$D$4:$D37,$D37)-SUMIFS($K$4:$K37,$D$4:$D37,$D37)) -> 846 | M37: 新A*G0554 | N37: 筐厂 | O37: 10 | P37: =IF($D37="","",ROUND((N($H37)+N($K37))*N($O37),2)) -> 8460 | Q37: 未付款 | W37: NO:2745250
A38: =IF($D38="","",ROW()-3) -> 35 | B38: 46272 | C38: 麦麦提 | D38: 公司红周转筐 | E38: NO:0001089 | F38: 领用出库 | G38: =IF($D38="","",N($L38)-N($H38)-N($I38)+N($J38)+N($K38)) -> 846 | H38: - | I38: - | J38: 846 | K38: - | L38: =IF($D38="","",SUMIFS($H$4:$H38,$D$4:$D38,$D38)+SUMIFS($I$4:$I38,$D$4:$D38,$D38)-SUMIFS($J$4:$J38,$D$4:$D38,$D38)-SUMIFS($K$4:$K38,$D$4:$D38,$D38)) -> 0 | M38: 新A*G0554 | N38: 筐厂 | P38: =IF($D38="","",ROUND((N($H38)+N($K38))*N($O38),2)) -> 0
A39: =IF($D39="","",ROW()-3) -> 36 | B39: 46272 | C39: 全修塑业 | D39: 公司红周转筐 | E39: NO:0000759 | F39: 采购入库 | G39: =IF($D39="","",N($L39)-N($H39)-N($I39)+N($J39)+N($K39)) -> 0 | H39: 846 | I39: - | J39: - | K39: - | L39: =IF($D39="","",SUMIFS($H$4:$H39,$D$4:$D39,$D39)+SUMIFS($I$4:$I39,$D$4:$D39,$D39)-SUMIFS($J$4:$J39,$D$4:$D39,$D39)-SUMIFS($K$4:$K39,$D$4:$D39,$D39)) -> 846 | M39: 新A*G0554 | N39: 筐厂 | O39: 10 | P39: =IF($D39="","",ROUND((N($H39)+N($K39))*N($O39),2)) -> 8460 | Q39: 未付款 | W39: NO:2745251
A40: =IF($D40="","",ROW()-3) -> 37 | B40: 46272 | C40: 马锦祥 | D40: 公司杂周转筐 | E40: NO:0001090 | F40: 领用出库 | G40: =IF($D40="","",N($L40)-N($H40)-N($I40)+N($J40)+N($K40)) -> 33591 | H40: - | I40: - | J40: 588 | K40: - | L40: =IF($D40="","",SUMIFS($H$4:$H40,$D$4:$D40,$D40)+SUMIFS($I$4:$I40,$D$4:$D40,$D40)-SUMIFS($J$4:$J40,$D$4:$D40,$D40)-SUMIFS($K$4:$K40,$D$4:$D40,$D40)) -> 33003 | M40: 新N*K7V85 | N40: 依力 | P40: =IF($D40="","",ROUND((N($H40)+N($K40))*N($O40),2)) -> 0
A41: =IF($D41="","",ROW()-3) -> 38 | B41: 46272 | C41: 贾建国 | D41: 公司新周转筐 | E41: NO:0001092 | F41: 领用出库 | G41: =IF($D41="","",N($L41)-N($H41)-N($I41)+N($J41)+N($K41)) -> 57780 | H41: - | I41: - | J41: 759 | K41: - | L41: =IF($D41="","",SUMIFS($H$4:$H41,$D$4:$D41,$D41)+SUMIFS($I$4:$I41,$D$4:$D41,$D41)-SUMIFS($J$4:$J41,$D$4:$D41,$D41)-SUMIFS($K$4:$K41,$D$4:$D41,$D41)) -> 57021 | M41: 豫Q*H5591 | N41: 依力 | P41: =IF($D41="","",ROUND((N($H41)+N($K41))*N($O41),2)) -> 0
A42: =IF($D42="","",ROW()-3) -> 39 | B42: 46272 | C42: 热合曼 | D42: 公司红周转筐 | E42: NO:0001094 | F42: 领用出库 | G42: =IF($D42="","",N($L42)-N($H42)-N($I42)+N($J42)+N($K42)) -> 846 | H42: - | I42: - | J42: 846 | K42: - | L42: =IF($D42="","",SUMIFS($H$4:$H42,$D$4:$D42,$D42)+SUMIFS($I$4:$I42,$D$4:$D42,$D42)-SUMIFS($J$4:$J42,$D$4:$D42,$D42)-SUMIFS($K$4:$K42,$D$4:$D42,$D42)) -> 0 | M42: 新A*G0554 | N42: 筐厂 | P42: =IF($D42="","",ROUND((N($H42)+N($K42))*N($O42),2)) -> 0
A43: =IF($D43="","",ROW()-3) -> 40 | B43: 46273 | C43: 王照雪 | D43: 公司杂周转筐 | E43: NO:000761 | F43: 退回入库 | G43: =IF($D43="","",N($L43)-N($H43)-N($I43)+N($J43)+N($K43)) -> 33003 | H43: 0 | I43: 2 | J43: 0 | K43: 0 | L43: =IF($D43="","",SUMIFS($H$4:$H43,$D$4:$D43,$D43)+SUMIFS($I$4:$I43,$D$4:$D43,$D43)-SUMIFS($J$4:$J43,$D$4:$D43,$D43)-SUMIFS($K$4:$K43,$D$4:$D43,$D43)) -> 33005 | N43: 自卸 | P43: =IF($D43="","",ROUND((N($H43)+N($K43))*N($O43),2)) -> 0 | W43: 装扎伤退回
A44: =IF($D44="","",ROW()-3) -> 41 | B44: 46274 | C44: 王照雪 | D44: 公司一次性筐 | E44: NO:0001098 | F44: 领用出库 | G44: =IF($D44="","",N($L44)-N($H44)-N($I44)+N($J44)+N($K44)) -> 66480 | H44: - | I44: - | J44: 423 | K44: - | L44: =IF($D44="","",SUMIFS($H$4:$H44,$D$4:$D44,$D44)+SUMIFS($I$4:$I44,$D$4:$D44,$D44)-SUMIFS($J$4:$J44,$D$4:$D44,$D44)-SUMIFS($K$4:$K44,$D$4:$D44,$D44)) -> 66057 | M44: 豫L*88X19 | N44: 依力 | P44: =IF($D44="","",ROUND((N($H44)+N($K44))*N($O44),2)) -> 0
A45: =IF($D45="","",ROW()-3) -> 42 | B45: 46274 | C45: 吐尔逊 | D45: 公司一次性筐 | E45: NO:0001099 | F45: 领用出库 | G45: =IF($D45="","",N($L45)-N($H45)-N($I45)+N($J45)+N($K45)) -> 66057 | H45: - | I45: - | J45: 1008 | K45: - | L45: =IF($D45="","",SUMIFS($H$4:$H45,$D$4:$D45,$D45)+SUMIFS($I$4:$I45,$D$4:$D45,$D45)-SUMIFS($J$4:$J45,$D$4:$D45,$D45)-SUMIFS($K$4:$K45,$D$4:$D45,$D45)) -> 65049 | M45: 新M*87613 | N45: 依力 | P45: =IF($D45="","",ROUND((N($H45)+N($K45))*N($O45),2)) -> 0
A46: =IF($D46="","",ROW()-3) -> 43 | B46: 46274 | C46: 全修塑业 | D46: 公司红周转筐 | E46: NO:0000763 | F46: 采购入库 | G46: =IF($D46="","",N($L46)-N($H46)-N($I46)+N($J46)+N($K46)) -> 0 | H46: 378 | I46: 0 | J46: 0 | K46: 0 | L46: =IF($D46="","",SUMIFS($H$4:$H46,$D$4:$D46,$D46)+SUMIFS($I$4:$I46,$D$4:$D46,$D46)-SUMIFS($J$4:$J46,$D$4:$D46,$D46)-SUMIFS($K$4:$K46,$D$4:$D46,$D46)) -> 378 | M46: 新N*X8S48 | N46: 筐厂 | O46: 10 | P46: =IF($D46="","",ROUND((N($H46)+N($K46))*N($O46),2)) -> 3780 | Q46: 未付款 | W46: NO:2745254
A47: =IF($D47="","",ROW()-3) -> 44 | B47: 46274 | C47: 全修塑业 | D47: 公司红周转筐 | E47: NO:0000765 | F47: 采购入库 | G47: =IF($D47="","",N($L47)-N($H47)-N($I47)+N($J47)+N($K47)) -> 378 | H47: 759 | I47: 0 | J47: 0 | K47: 0 | L47: =IF($D47="","",SUMIFS($H$4:$H47,$D$4:$D47,$D47)+SUMIFS($I$4:$I47,$D$4:$D47,$D47)-SUMIFS($J$4:$J47,$D$4:$D47,$D47)-SUMIFS($K$4:$K47,$D$4:$D47,$D47)) -> 1137 | M47: 豫A*2737K | N47: 筐厂 | O47: 10 | P47: =IF($D47="","",ROUND((N($H47)+N($K47))*N($O47),2)) -> 7590 | Q47: 未付款 | W47: NO:0017201
A48: =IF($D48="","",ROW()-3) -> 45 | B48: 46274 | C48: 全修塑业 | D48: 公司红周转筐 | E48: NO:0000766 | F48: 采购入库 | G48: =IF($D48="","",N($L48)-N($H48)-N($I48)+N($J48)+N($K48)) -> 1137 | H48: 846 | I48: 0 | J48: 0 | K48: 0 | L48: =IF($D48="","",SUMIFS($H$4:$H48,$D$4:$D48,$D48)+SUMIFS($I$4:$I48,$D$4:$D48,$D48)-SUMIFS($J$4:$J48,$D$4:$D48,$D48)-SUMIFS($K$4:$K48,$D$4:$D48,$D48)) -> 1983 | M48: 新A*G0554 | N48: 筐厂 | O48: 10 | P48: =IF($D48="","",ROUND((N($H48)+N($K48))*N($O48),2)) -> 8460 | Q48: 未付款 | W48: NO:0017203
A49: =IF($D49="","",ROW()-3) -> 46 | B49: 46274 | C49: 吐尔洪 | D49: 公司红周转筐 | E49: NO:0001102 | F49: 领用出库 | G49: =IF($D49="","",N($L49)-N($H49)-N($I49)+N($J49)+N($K49)) -> 1983 | H49: 0 | I49: 0 | J49: 378 | K49: 0 | L49: =IF($D49="","",SUMIFS($H$4:$H49,$D$4:$D49,$D49)+SUMIFS($I$4:$I49,$D$4:$D49,$D49)-SUMIFS($J$4:$J49,$D$4:$D49,$D49)-SUMIFS($K$4:$K49,$D$4:$D49,$D49)) -> 1605 | M49: 新N*X8S48 | N49: 筐厂 | P49: =IF($D49="","",ROUND((N($H49)+N($K49))*N($O49),2)) -> 0
A50: =IF($D50="","",ROW()-3) -> 47 | B50: 46274 | C50: 荆建君 | D50: 公司红周转筐 | E50: NO:0001105 | F50: 领用出库 | G50: =IF($D50="","",N($L50)-N($H50)-N($I50)+N($J50)+N($K50)) -> 1605 | H50: 0 | I50: 0 | J50: 759 | K50: 0 | L50: =IF($D50="","",SUMIFS($H$4:$H50,$D$4:$D50,$D50)+SUMIFS($I$4:$I50,$D$4:$D50,$D50)-SUMIFS($J$4:$J50,$D$4:$D50,$D50)-SUMIFS($K$4:$K50,$D$4:$D50,$D50)) -> 846 | M50: 豫A*2737K | N50: 筐厂 | P50: =IF($D50="","",ROUND((N($H50)+N($K50))*N($O50),2)) -> 0
A51: =IF($D51="","",ROW()-3) -> 48 | B51: 46274 | C51: 麦麦提 | D51: 公司红周转筐 | E51: NO:0001106 | F51: 领用出库 | G51: =IF($D51="","",N($L51)-N($H51)-N($I51)+N($J51)+N($K51)) -> 846 | H51: 0 | I51: 0 | J51: 846 | K51: 0 | L51: =IF($D51="","",SUMIFS($H$4:$H51,$D$4:$D51,$D51)+SUMIFS($I$4:$I51,$D$4:$D51,$D51)-SUMIFS($J$4:$J51,$D$4:$D51,$D51)-SUMIFS($K$4:$K51,$D$4:$D51,$D51)) -> 0 | M51: 新A*G0554 | N51: 筐厂 | P51: =IF($D51="","",ROUND((N($H51)+N($K51))*N($O51),2)) -> 0
A52: =IF($D52="","",ROW()-3) -> 49 | B52: 46275 | C52: 王照雪 | D52: 公司一次性筐 | E52: NO:0001107 | F52: 领用出库 | G52: =IF($D52="","",N($L52)-N($H52)-N($I52)+N($J52)+N($K52)) -> 65049 | H52: 0 | I52: 0 | J52: 423 | K52: 0 | L52: =IF($D52="","",SUMIFS($H$4:$H52,$D$4:$D52,$D52)+SUMIFS($I$4:$I52,$D$4:$D52,$D52)-SUMIFS($J$4:$J52,$D$4:$D52,$D52)-SUMIFS($K$4:$K52,$D$4:$D52,$D52)) -> 64626 | M52: 豫L*88X19 | N52: 依力 | P52: =IF($D52="","",ROUND((N($H52)+N($K52))*N($O52),2)) -> 0
A53: =IF($D53="","",ROW()-3) -> 50 | B53: 46275 | C53: 全修塑业 | D53: 公司红周转筐 | E53: NO:0000771 | F53: 采购入库 | G53: =IF($D53="","",N($L53)-N($H53)-N($I53)+N($J53)+N($K53)) -> 0 | H53: 960 | I53: 0 | J53: 0 | K53: 0 | L53: =IF($D53="","",SUMIFS($H$4:$H53,$D$4:$D53,$D53)+SUMIFS($I$4:$I53,$D$4:$D53,$D53)-SUMIFS($J$4:$J53,$D$4:$D53,$D53)-SUMIFS($K$4:$K53,$D$4:$D53,$D53)) -> 960 | M53: 新N*49209 | N53: 筐厂 | O53: 10 | P53: =IF($D53="","",ROUND((N($H53)+N($K53))*N($O53),2)) -> 9600 | Q53: 未付款 | W53: NO:0017204
A54: =IF($D54="","",ROW()-3) -> 51 | B54: 46275 | C54: 王灵云 | D54: 公司红周转筐 | E54: NO:0001108 | F54: 领用出库 | G54: =IF($D54="","",N($L54)-N($H54)-N($I54)+N($J54)+N($K54)) -> 960 | H54: 0 | I54: 0 | J54: 960 | K54: 0 | L54: =IF($D54="","",SUMIFS($H$4:$H54,$D$4:$D54,$D54)+SUMIFS($I$4:$I54,$D$4:$D54,$D54)-SUMIFS($J$4:$J54,$D$4:$D54,$D54)-SUMIFS($K$4:$K54,$D$4:$D54,$D54)) -> 0 | M54: 新N*49209 | N54: 筐厂 | P54: =IF($D54="","",ROUND((N($H54)+N($K54))*N($O54),2)) -> 0
A55: =IF($D55="","",ROW()-3) -> 52 | B55: 46275 | C55: 全修塑业 | D55: 公司红周转筐 | E55: NO:0000774 | F55: 采购入库 | G55: =IF($D55="","",N($L55)-N($H55)-N($I55)+N($J55)+N($K55)) -> 0 | H55: 369 | I55: 0 | J55: 0 | K55: 0 | L55: =IF($D55="","",SUMIFS($H$4:$H55,$D$4:$D55,$D55)+SUMIFS($I$4:$I55,$D$4:$D55,$D55)-SUMIFS($J$4:$J55,$D$4:$D55,$D55)-SUMIFS($K$4:$K55,$D$4:$D55,$D55)) -> 369 | M55: 新N*X8S48 | N55: 筐厂 | O55: 10 | P55: =IF($D55="","",ROUND((N($H55)+N($K55))*N($O55),2)) -> 3690 | Q55: 未付款 | W55: NO:0017205
A56: =IF($D56="","",ROW()-3) -> 53 | B56: 46275 | C56: 吐尔洪 | D56: 公司红周转筐 | E56: NO:0001110 | F56: 领用出库 | G56: =IF($D56="","",N($L56)-N($H56)-N($I56)+N($J56)+N($K56)) -> 369 | H56: 0 | I56: 0 | J56: 369 | K56: 0 | L56: =IF($D56="","",SUMIFS($H$4:$H56,$D$4:$D56,$D56)+SUMIFS($I$4:$I56,$D$4:$D56,$D56)-SUMIFS($J$4:$J56,$D$4:$D56,$D56)-SUMIFS($K$4:$K56,$D$4:$D56,$D56)) -> 0 | M56: 新N*X8S48 | N56: 筐厂 | P56: =IF($D56="","",ROUND((N($H56)+N($K56))*N($O56),2)) -> 0
A57: =IF($D57="","",ROW()-3) -> 54 | B57: 46276 | C57: 全修塑业 | D57: 公司红周转筐 | E57: NO:0000778 | F57: 采购入库 | G57: =IF($D57="","",N($L57)-N($H57)-N($I57)+N($J57)+N($K57)) -> 0 | H57: 846 | I57: 0 | J57: 0 | K57: 0 | L57: =IF($D57="","",SUMIFS($H$4:$H57,$D$4:$D57,$D57)+SUMIFS($I$4:$I57,$D$4:$D57,$D57)-SUMIFS($J$4:$J57,$D$4:$D57,$D57)-SUMIFS($K$4:$K57,$D$4:$D57,$D57)) -> 846 | M57: 新A*G0554 | N57: 筐厂 | O57: 10 | P57: =IF($D57="","",ROUND((N($H57)+N($K57))*N($O57),2)) -> 8460 | Q57: 未付款 | W57: NO:0017207
A58: =IF($D58="","",ROW()-3) -> 55 | B58: 46276 | C58: 麦麦提 | D58: 公司红周转筐 | E58: NO:0001113 | F58: 领用出库 | G58: =IF($D58="","",N($L58)-N($H58)-N($I58)+N($J58)+N($K58)) -> 846 | H58: 0 | I58: 0 | J58: 846 | K58: 0 | L58: =IF($D58="","",SUMIFS($H$4:$H58,$D$4:$D58,$D58)+SUMIFS($I$4:$I58,$D$4:$D58,$D58)-SUMIFS($J$4:$J58,$D$4:$D58,$D58)-SUMIFS($K$4:$K58,$D$4:$D58,$D58)) -> 0 | M58: 新A*G0554 | N58: 筐厂 | P58: =IF($D58="","",ROUND((N($H58)+N($K58))*N($O58),2)) -> 0
A59: =IF($D59="","",ROW()-3) -> 56 | B59: 46276 | C59: 全修塑业 | D59: 公司红周转筐 | E59: NO:0000784 | F59: 采购入库 | G59: =IF($D59="","",N($L59)-N($H59)-N($I59)+N($J59)+N($K59)) -> 0 | H59: 936 | I59: 0 | J59: 0 | K59: 0 | L59: =IF($D59="","",SUMIFS($H$4:$H59,$D$4:$D59,$D59)+SUMIFS($I$4:$I59,$D$4:$D59,$D59)-SUMIFS($J$4:$J59,$D$4:$D59,$D59)-SUMIFS($K$4:$K59,$D$4:$D59,$D59)) -> 936 | M59: 新F*75240 | N59: 筐厂 | O59: 10 | P59: =IF($D59="","",ROUND((N($H59)+N($K59))*N($O59),2)) -> 9360 | Q59: 未付款 | W59: NO:0017209
A60: =IF($D60="","",ROW()-3) -> 57 | B60: 46276 | C60: 马锦祥 | D60: 公司杂周转筐 | E60: NO:0001114 | F60: 领用出库 | G60: =IF($D60="","",N($L60)-N($H60)-N($I60)+N($J60)+N($K60)) -> 33005 | H60: 0 | I60: 0 | J60: 588 | K60: 0 | L60: =IF($D60="","",SUMIFS($H$4:$H60,$D$4:$D60,$D60)+SUMIFS($I$4:$I60,$D$4:$D60,$D60)-SUMIFS($J$4:$J60,$D$4:$D60,$D60)-SUMIFS($K$4:$K60,$D$4:$D60,$D60)) -> 32417 | M60: 新N*K7V85 | N60: 依力 | P60: =IF($D60="","",ROUND((N($H60)+N($K60))*N($O60),2)) -> 0
A61: =IF($D61="","",ROW()-3) -> 58 | B61: 46276 | C61: 王照雪 | D61: 公司杂周转筐 | E61: NO:0001115 | F61: 领用出库 | G61: =IF($D61="","",N($L61)-N($H61)-N($I61)+N($J61)+N($K61)) -> 32417 | H61: 0 | I61: 0 | J61: 213 | K61: 0 | L61: =IF($D61="","",SUMIFS($H$4:$H61,$D$4:$D61,$D61)+SUMIFS($I$4:$I61,$D$4:$D61,$D61)-SUMIFS($J$4:$J61,$D$4:$D61,$D61)-SUMIFS($K$4:$K61,$D$4:$D61,$D61)) -> 32204 | M61: 豫L*88X19 | N61: 依力 | P61: =IF($D61="","",ROUND((N($H61)+N($K61))*N($O61),2)) -> 0
A62: =IF($D62="","",ROW()-3) -> 59 | B62: 46276 | C62: 王照雪 | D62: 公司杂周转筐 | E62: NO:0001116 | F62: 领用出库 | G62: =IF($D62="","",N($L62)-N($H62)-N($I62)+N($J62)+N($K62)) -> 32204 | H62: 0 | I62: 0 | J62: 423 | K62: 0 | L62: =IF($D62="","",SUMIFS($H$4:$H62,$D$4:$D62,$D62)+SUMIFS($I$4:$I62,$D$4:$D62,$D62)-SUMIFS($J$4:$J62,$D$4:$D62,$D62)-SUMIFS($K$4:$K62,$D$4:$D62,$D62)) -> 31781 | M62: 豫L*88X19 | N62: 依力 | P62: =IF($D62="","",ROUND((N($H62)+N($K62))*N($O62),2)) -> 0
A63: =IF($D63="","",ROW()-3) -> 60 | B63: 46276 | C63: 努尔敦 | D63: 公司红周转筐 | E63: NO:0001118 | F63: 领用出库 | G63: =IF($D63="","",N($L63)-N($H63)-N($I63)+N($J63)+N($K63)) -> 936 | H63: 0 | I63: 0 | J63: 936 | K63: 0 | L63: =IF($D63="","",SUMIFS($H$4:$H63,$D$4:$D63,$D63)+SUMIFS($I$4:$I63,$D$4:$D63,$D63)-SUMIFS($J$4:$J63,$D$4:$D63,$D63)-SUMIFS($K$4:$K63,$D$4:$D63,$D63)) -> 0 | M63: 新F*75240 | N63: 筐厂 | P63: =IF($D63="","",ROUND((N($H63)+N($K63))*N($O63),2)) -> 0
A64: =IF($D64="","",ROW()-3) -> 61 | B64: 46276 | C64: 全修塑业 | D64: 公司红周转筐 | E64: NO:0000785 | F64: 采购入库 | G64: =IF($D64="","",N($L64)-N($H64)-N($I64)+N($J64)+N($K64)) -> 0 | H64: 846 | I64: 0 | J64: 0 | K64: 0 | L64: =IF($D64="","",SUMIFS($H$4:$H64,$D$4:$D64,$D64)+SUMIFS($I$4:$I64,$D$4:$D64,$D64)-SUMIFS($J$4:$J64,$D$4:$D64,$D64)-SUMIFS($K$4:$K64,$D$4:$D64,$D64)) -> 846 | M64: 新A*G0554 | N64: 筐厂 | O64: 10 | P64: =IF($D64="","",ROUND((N($H64)+N($K64))*N($O64),2)) -> 8460 | Q64: 未付款 | W64: NO:0017211
A65: =IF($D65="","",ROW()-3) -> 62 | B65: 46276 | C65: 热合曼 | D65: 公司红周转筐 | E65: NO:0001120 | F65: 领用出库 | G65: =IF($D65="","",N($L65)-N($H65)-N($I65)+N($J65)+N($K65)) -> 846 | H65: 0 | I65: 0 | J65: 846 | K65: 0 | L65: =IF($D65="","",SUMIFS($H$4:$H65,$D$4:$D65,$D65)+SUMIFS($I$4:$I65,$D$4:$D65,$D65)-SUMIFS($J$4:$J65,$D$4:$D65,$D65)-SUMIFS($K$4:$K65,$D$4:$D65,$D65)) -> 0 | M65: 新A*G0554 | N65: 筐厂 | P65: =IF($D65="","",ROUND((N($H65)+N($K65))*N($O65),2)) -> 0
A66: =IF($D66="","",ROW()-3) -> 63 | B66: 46276 | C66: 全修塑业 | D66: 公司红周转筐 | E66: NO:0000788 | F66: 采购入库 | G66: =IF($D66="","",N($L66)-N($H66)-N($I66)+N($J66)+N($K66)) -> 0 | H66: 378 | I66: 0 | J66: 0 | K66: 0 | L66: =IF($D66="","",SUMIFS($H$4:$H66,$D$4:$D66,$D66)+SUMIFS($I$4:$I66,$D$4:$D66,$D66)-SUMIFS($J$4:$J66,$D$4:$D66,$D66)-SUMIFS($K$4:$K66,$D$4:$D66,$D66)) -> 378 | M66: 新N*X8S48 | N66: 筐厂 | O66: 10 | P66: =IF($D66="","",ROUND((N($H66)+N($K66))*N($O66),2)) -> 3780 | Q66: 未付款 | W66: NO:0017212
A67: =IF($D67="","",ROW()-3) -> 64 | B67: 46276 | C67: 吐尔洪 | D67: 公司红周转筐 | E67: NO:0001122 | F67: 领用出库 | G67: =IF($D67="","",N($L67)-N($H67)-N($I67)+N($J67)+N($K67)) -> 378 | H67: 0 | I67: 0 | J67: 378 | K67: 0 | L67: =IF($D67="","",SUMIFS($H$4:$H67,$D$4:$D67,$D67)+SUMIFS($I$4:$I67,$D$4:$D67,$D67)-SUMIFS($J$4:$J67,$D$4:$D67,$D67)-SUMIFS($K$4:$K67,$D$4:$D67,$D67)) -> 0 | M67: 新N*X8S48 | N67: 筐厂 | P67: =IF($D67="","",ROUND((N($H67)+N($K67))*N($O67),2)) -> 0
A68: =IF($D68="","",ROW()-3) -> 65 | B68: 46277 | C68: 王照雪 | D68: 公司一次性筐 | E68: NO:0000789 | F68: 退回入库 | G68: =IF($D68="","",N($L68)-N($H68)-N($I68)+N($J68)+N($K68)) -> 64626 | H68: 0 | I68: 1 | J68: 0 | K68: 0 | L68: =IF($D68="","",SUMIFS($H$4:$H68,$D$4:$D68,$D68)+SUMIFS($I$4:$I68,$D$4:$D68,$D68)-SUMIFS($J$4:$J68,$D$4:$D68,$D68)-SUMIFS($K$4:$K68,$D$4:$D68,$D68)) -> 64627 | M68: 豫L*88X19 | N68: 依力 | P68: =IF($D68="","",ROUND((N($H68)+N($K68))*N($O68),2)) -> 0
A69: =IF($D69="","",ROW()-3) -> 66 | B69: 46277 | C69: 王照雪 | D69: 公司杂周转筐 | E69: NO:0000792 | F69: 退回入库 | G69: =IF($D69="","",N($L69)-N($H69)-N($I69)+N($J69)+N($K69)) -> 31781 | H69: 0 | I69: 45 | J69: 0 | K69: 0 | L69: =IF($D69="","",SUMIFS($H$4:$H69,$D$4:$D69,$D69)+SUMIFS($I$4:$I69,$D$4:$D69,$D69)-SUMIFS($J$4:$J69,$D$4:$D69,$D69)-SUMIFS($K$4:$K69,$D$4:$D69,$D69)) -> 31826 | M69: 豫L*88X19 | N69: 依力 | P69: =IF($D69="","",ROUND((N($H69)+N($K69))*N($O69),2)) -> 0
A70: =IF($D70="","",ROW()-3) -> 67 | B70: 46277 | C70: 全修塑业 | D70: 公司红周转筐 | E70: NO:0000795 | F70: 采购入库 | G70: =IF($D70="","",N($L70)-N($H70)-N($I70)+N($J70)+N($K70)) -> 0 | H70: 846 | I70: 0 | J70: 0 | K70: 0 | L70: =IF($D70="","",SUMIFS($H$4:$H70,$D$4:$D70,$D70)+SUMIFS($I$4:$I70,$D$4:$D70,$D70)-SUMIFS($J$4:$J70,$D$4:$D70,$D70)-SUMIFS($K$4:$K70,$D$4:$D70,$D70)) -> 846 | M70: 新A*G0554 | N70: 筐厂 | O70: 10 | P70: =IF($D70="","",ROUND((N($H70)+N($K70))*N($O70),2)) -> 8460 | Q70: 未付款 | W70: NO:0017213
A71: =IF($D71="","",ROW()-3) -> 68 | B71: 46277 | C71: 麦麦提 | D71: 公司红周转筐 | E71: NO:0001125 | F71: 领用出库 | G71: =IF($D71="","",N($L71)-N($H71)-N($I71)+N($J71)+N($K71)) -> 846 | H71: 0 | I71: 0 | J71: 846 | K71: 0 | L71: =IF($D71="","",SUMIFS($H$4:$H71,$D$4:$D71,$D71)+SUMIFS($I$4:$I71,$D$4:$D71,$D71)-SUMIFS($J$4:$J71,$D$4:$D71,$D71)-SUMIFS($K$4:$K71,$D$4:$D71,$D71)) -> 0 | M71: 新A*G0555 | N71: 筐厂 | P71: =IF($D71="","",ROUND((N($H71)+N($K71))*N($O71),2)) -> 0
A72: =IF($D72="","",ROW()-3) -> 69 | B72: 46278 | C72: 全修塑业 | D72: 公司红周转筐 | E72: NO:0000798 | F72: 采购入库 | G72: =IF($D72="","",N($L72)-N($H72)-N($I72)+N($J72)+N($K72)) -> 0 | H72: 960 | I72: 0 | J72: 0 | K72: 0 | L72: =IF($D72="","",SUMIFS($H$4:$H72,$D$4:$D72,$D72)+SUMIFS($I$4:$I72,$D$4:$D72,$D72)-SUMIFS($J$4:$J72,$D$4:$D72,$D72)-SUMIFS($K$4:$K72,$D$4:$D72,$D72)) -> 960 | M72: 新N*49209 | N72: 筐厂 | O72: 10 | P72: =IF($D72="","",ROUND((N($H72)+N($K72))*N($O72),2)) -> 9600 | Q72: 未付款 | W72: NO:0017215
A73: =IF($D73="","",ROW()-3) -> 70 | B73: 46278 | C73: 王照雪 | D73: 公司杂周转筐 | E73: NO:0001129 | F73: 领用出库 | G73: =IF($D73="","",N($L73)-N($H73)-N($I73)+N($J73)+N($K73)) -> 31826 | H73: 0 | I73: 0 | J73: 423 | K73: 0 | L73: =IF($D73="","",SUMIFS($H$4:$H73,$D$4:$D73,$D73)+SUMIFS($I$4:$I73,$D$4:$D73,$D73)-SUMIFS($J$4:$J73,$D$4:$D73,$D73)-SUMIFS($K$4:$K73,$D$4:$D73,$D73)) -> 31403 | M73: 豫L*88X19 | N73: 依力 | P73: =IF($D73="","",ROUND((N($H73)+N($K73))*N($O73),2)) -> 0
A74: =IF($D74="","",ROW()-3) -> 71 | B74: 46278 | C74: 王灵云 | D74: 公司红周转筐 | E74: NO:0001130 | F74: 领用出库 | G74: =IF($D74="","",N($L74)-N($H74)-N($I74)+N($J74)+N($K74)) -> 960 | H74: 0 | K74: 960 | L74: =IF($D74="","",SUMIFS($H$4:$H74,$D$4:$D74,$D74)+SUMIFS($I$4:$I74,$D$4:$D74,$D74)-SUMIFS($J$4:$J74,$D$4:$D74,$D74)-SUMIFS($K$4:$K74,$D$4:$D74,$D74)) -> 0 | M74: 新N*49209 | N74: 筐厂 | P74: =IF($D74="","",ROUND((N($H74)+N($K74))*N($O74),2)) -> 0
A75: =IF($D75="","",ROW()-3) -> 72 | B75: 46278 | C75: 马锦祥 | D75: 公司杂周转筐 | E75: NO:0001131 | F75: 领用出库 | G75: =IF($D75="","",N($L75)-N($H75)-N($I75)+N($J75)+N($K75)) -> 31403 | H75: 0 | I75: 0 | J75: 588 | K75: 0 | L75: =IF($D75="","",SUMIFS($H$4:$H75,$D$4:$D75,$D75)+SUMIFS($I$4:$I75,$D$4:$D75,$D75)-SUMIFS($J$4:$J75,$D$4:$D75,$D75)-SUMIFS($K$4:$K75,$D$4:$D75,$D75)) -> 30815 | M75: 新N*K7V85 | N75: 依力 | P75: =IF($D75="","",ROUND((N($H75)+N($K75))*N($O75),2)) -> 0
A76: =IF($D76="","",ROW()-3) -> 73 | B76: 46278 | C76: 全修塑业 | D76: 公司红周转筐 | E76: NO:0000853 | F76: 采购入库 | G76: =IF($D76="","",N($L76)-N($H76)-N($I76)+N($J76)+N($K76)) -> 0 | H76: 960 | I76: 0 | J76: 0 | K76: 0 | L76: =IF($D76="","",SUMIFS($H$4:$H76,$D$4:$D76,$D76)+SUMIFS($I$4:$I76,$D$4:$D76,$D76)-SUMIFS($J$4:$J76,$D$4:$D76,$D76)-SUMIFS($K$4:$K76,$D$4:$D76,$D76)) -> 960 | M76: 新N*49209 | N76: 筐厂 | O76: 10 | P76: =IF($D76="","",ROUND((N($H76)+N($K76))*N($O76),2)) -> 9600 | Q76: 未付款 | W76: NO:0017217
A77: =IF($D77="","",ROW()-3) -> 74 | B77: 46278 | C77: 王灵云 | D77: 公司红周转筐 | E77: NO:0001135 | F77: 领用出库 | G77: =IF($D77="","",N($L77)-N($H77)-N($I77)+N($J77)+N($K77)) -> 960 | H77: 0 | I77: 0 | J77: 960 | K77: 0 | L77: =IF($D77="","",SUMIFS($H$4:$H77,$D$4:$D77,$D77)+SUMIFS($I$4:$I77,$D$4:$D77,$D77)-SUMIFS($J$4:$J77,$D$4:$D77,$D77)-SUMIFS($K$4:$K77,$D$4:$D77,$D77)) -> 0 | M77: 新N*49209 | N77: 筐厂 | P77: =IF($D77="","",ROUND((N($H77)+N($K77))*N($O77),2)) -> 0
A78: =IF($D78="","",ROW()-3) -> 75 | B78: 46278 | C78: 王照雪 | D78: 公司杂周转筐 | E78: NO:0001137 | F78: 领用出库 | G78: =IF($D78="","",N($L78)-N($H78)-N($I78)+N($J78)+N($K78)) -> 30815 | H78: 0 | I78: 0 | J78: 711 | K78: 0 | L78: =IF($D78="","",SUMIFS($H$4:$H78,$D$4:$D78,$D78)+SUMIFS($I$4:$I78,$D$4:$D78,$D78)-SUMIFS($J$4:$J78,$D$4:$D78,$D78)-SUMIFS($K$4:$K78,$D$4:$D78,$D78)) -> 30104 | M78: 新N*53045 | N78: 依力 | P78: =IF($D78="","",ROUND((N($H78)+N($K78))*N($O78),2)) -> 0 | W78: 李现东
A79: =IF($D79="","",ROW()-3) -> 76 | B79: 46279 | C79: 王照雪 | D79: 公司杂周转筐 | E79: NO:0001140 | F79: 领用出库 | G79: =IF($D79="","",N($L79)-N($H79)-N($I79)+N($J79)+N($K79)) -> 30104 | H79: 0 | I79: 0 | J79: 702 | K79: 0 | L79: =IF($D79="","",SUMIFS($H$4:$H79,$D$4:$D79,$D79)+SUMIFS($I$4:$I79,$D$4:$D79,$D79)-SUMIFS($J$4:$J79,$D$4:$D79,$D79)-SUMIFS($K$4:$K79,$D$4:$D79,$D79)) -> 29402 | M79: 新N*53045 | N79: 依力 | P79: =IF($D79="","",ROUND((N($H79)+N($K79))*N($O79),2)) -> 0 | W79: 李现东
A80: =IF($D80="","",ROW()-3) | G80: =IF($D80="","",N($L80)-N($H80)-N($I80)+N($J80)+N($K80)) | L80: =IF($D80="","",SUMIFS($H$4:$H80,$D$4:$D80,$D80)+SUMIFS($I$4:$I80,$D$4:$D80,$D80)-SUMIFS($J$4:$J80,$D$4:$D80,$D80)-SUMIFS($K$4:$K80,$D$4:$D80,$D80)) | P80: =IF($D80="","",ROUND((N($H80)+N($K80))*N($O80),2))
A81: =IF($D81="","",ROW()-3) | G81: =IF($D81="","",N($L81)-N($H81)-N($I81)+N($J81)+N($K81)) | L81: =IF($D81="","",SUMIFS($H$4:$H81,$D$4:$D81,$D81)+SUMIFS($I$4:$I81,$D$4:$D81,$D81)-SUMIFS($J$4:$J81,$D$4:$D81,$D81)-SUMIFS($K$4:$K81,$D$4:$D81,$D81)) | P81: =IF($D81="","",ROUND((N($H81)+N($K81))*N($O81),2))
A82: =IF($D82="","",ROW()-3) | G82: =IF($D82="","",N($L82)-N($H82)-N($I82)+N($J82)+N($K82)) | L82: =IF($D82="","",SUMIFS($H$4:$H82,$D$4:$D82,$D82)+SUMIFS($I$4:$I82,$D$4:$D82,$D82)-SUMIFS($J$4:$J82,$D$4:$D82,$D82)-SUMIFS($K$4:$K82,$D$4:$D82,$D82)) | P82: =IF($D82="","",ROUND((N($H82)+N($K82))*N($O82),2))
A83: =IF($D83="","",ROW()-3) | G83: =IF($D83="","",N($L83)-N($H83)-N($I83)+N($J83)+N($K83)) | L83: =IF($D83="","",SUMIFS($H$4:$H83,$D$4:$D83,$D83)+SUMIFS($I$4:$I83,$D$4:$D83,$D83)-SUMIFS($J$4:$J83,$D$4:$D83,$D83)-SUMIFS($K$4:$K83,$D$4:$D83,$D83)) | P83: =IF($D83="","",ROUND((N($H83)+N($K83))*N($O83),2))
A84: =IF($D84="","",ROW()-3) | G84: =IF($D84="","",N($L84)-N($H84)-N($I84)+N($J84)+N($K84)) | L84: =IF($D84="","",SUMIFS($H$4:$H84,$D$4:$D84,$D84)+SUMIFS($I$4:$I84,$D$4:$D84,$D84)-SUMIFS($J$4:$J84,$D$4:$D84,$D84)-SUMIFS($K$4:$K84,$D$4:$D84,$D84)) | P84: =IF($D84="","",ROUND((N($H84)+N($K84))*N($O84),2))
A85: =IF($D85="","",ROW()-3) | G85: =IF($D85="","",N($L85)-N($H85)-N($I85)+N($J85)+N($K85)) | L85: =IF($D85="","",SUMIFS($H$4:$H85,$D$4:$D85,$D85)+SUMIFS($I$4:$I85,$D$4:$D85,$D85)-SUMIFS($J$4:$J85,$D$4:$D85,$D85)-SUMIFS($K$4:$K85,$D$4:$D85,$D85)) | P85: =IF($D85="","",ROUND((N($H85)+N($K85))*N($O85),2))
A86: =IF($D86="","",ROW()-3) | G86: =IF($D86="","",N($L86)-N($H86)-N($I86)+N($J86)+N($K86)) | L86: =IF($D86="","",SUMIFS($H$4:$H86,$D$4:$D86,$D86)+SUMIFS($I$4:$I86,$D$4:$D86,$D86)-SUMIFS($J$4:$J86,$D$4:$D86,$D86)-SUMIFS($K$4:$K86,$D$4:$D86,$D86)) | P86: =IF($D86="","",ROUND((N($H86)+N($K86))*N($O86),2))
A87: =IF($D87="","",ROW()-3) | G87: =IF($D87="","",N($L87)-N($H87)-N($I87)+N($J87)+N($K87)) | L87: =IF($D87="","",SUMIFS($H$4:$H87,$D$4:$D87,$D87)+SUMIFS($I$4:$I87,$D$4:$D87,$D87)-SUMIFS($J$4:$J87,$D$4:$D87,$D87)-SUMIFS($K$4:$K87,$D$4:$D87,$D87)) | P87: =IF($D87="","",ROUND((N($H87)+N($K87))*N($O87),2))
A88: =IF($D88="","",ROW()-3) | G88: =IF($D88="","",N($L88)-N($H88)-N($I88)+N($J88)+N($K88)) | L88: =IF($D88="","",SUMIFS($H$4:$H88,$D$4:$D88,$D88)+SUMIFS($I$4:$I88,$D$4:$D88,$D88)-SUMIFS($J$4:$J88,$D$4:$D88,$D88)-SUMIFS($K$4:$K88,$D$4:$D88,$D88)) | P88: =IF($D88="","",ROUND((N($H88)+N($K88))*N($O88),2))
A89: =IF($D89="","",ROW()-3) | G89: =IF($D89="","",N($L89)-N($H89)-N($I89)+N($J89)+N($K89)) | L89: =IF($D89="","",SUMIFS($H$4:$H89,$D$4:$D89,$D89)+SUMIFS($I$4:$I89,$D$4:$D89,$D89)-SUMIFS($J$4:$J89,$D$4:$D89,$D89)-SUMIFS($K$4:$K89,$D$4:$D89,$D89)) | P89: =IF($D89="","",ROUND((N($H89)+N($K89))*N($O89),2))
A90: =IF($D90="","",ROW()-3) | G90: =IF($D90="","",N($L90)-N($H90)-N($I90)+N($J90)+N($K90)) | L90: =IF($D90="","",SUMIFS($H$4:$H90,$D$4:$D90,$D90)+SUMIFS($I$4:$I90,$D$4:$D90,$D90)-SUMIFS($J$4:$J90,$D$4:$D90,$D90)-SUMIFS($K$4:$K90,$D$4:$D90,$D90)) | P90: =IF($D90="","",ROUND((N($H90)+N($K90))*N($O90),2))
A91: =IF($D91="","",ROW()-3) | G91: =IF($D91="","",N($L91)-N($H91)-N($I91)+N($J91)+N($K91)) | L91: =IF($D91="","",SUMIFS($H$4:$H91,$D$4:$D91,$D91)+SUMIFS($I$4:$I91,$D$4:$D91,$D91)-SUMIFS($J$4:$J91,$D$4:$D91,$D91)-SUMIFS($K$4:$K91,$D$4:$D91,$D91)) | P91: =IF($D91="","",ROUND((N($H91)+N($K91))*N($O91),2))
... A2004: =IF($D2004="","",ROW()-3) | G2004: =IF($D2004="","",N($L2004)-N($H2004)-N($I2004)+N($J2004)+N($K2004)) | L2004: =IF($D2004="","",SUMIFS($H$4:$H2004,$D$4:$D2004,$D2004)+SUMIFS($I$4:$I2004,$D$4:$D2004,$D2004)-SUMIFS($J$4:$J2004,$D$4:$D2004,$D2004)-SUMIFS($K$4:$K2004,$D$4:$D2004,$D2004)) | P2004: =IF($D2004="","",ROUND((N($H2004)+N($K2004))*N($O2004),2))

Sheet 包装物料出入库明细
A1: 包 装 物 料 出 入 库 明 细 表
A2: ★ 计价数量＝入库＋出库−退回（退回自动冲减，不会重复收款）；合计金额＝计价数量×单价。「退回数量」照常填正数，显示成红色负数。
A3: 序号 | B3: 日期 | C3: 票据单号 | D3: 供应商/客户 | E3: 物料种类 | F3: 规格 | G3: 计量单位 | H3: 业务类型 | I3: 入库数量 | J3: 出库数量 | K3: 退回数量(显示为负) | L3: 计价数量 (退回已冲减) | M3: 单价 | N3: 合计金额 | O3: 车牌号 | P3: 收/付款 状态 | Q3: 核查结果 | R3: 备注
A4: =IF($E4="","",ROW()-3) -> 1 | B4: 46266 | D4: 果然鲜 | E4: 气泡垫 | F4: =IF($E4="","",IFERROR(INDEX(基础资料!$O$4:$O$34,MATCH($E4,基础资料!$N$4:$N$34,0))&"","")) -> *1000 | G4: =IF($E4="","",IFERROR(INDEX(基础资料!$P$4:$P$34,MATCH($E4,基础资料!$N$4:$N$34,0))&"","")) -> 片 | H4: 期初库存 | I4: 13800 | L4: =IF($E4="","",N($I4)+N($J4)-N($K4)) -> 13800 | N4: =IF($E4="","",ROUND(N($L4)*N($M4),2)) -> 0
A5: =IF($E5="","",ROW()-3) -> 2 | B5: 46266 | D5: 果然鲜 | E5: 无纺布 | F5: =IF($E5="","",IFERROR(INDEX(基础资料!$O$4:$O$34,MATCH($E5,基础资料!$N$4:$N$34,0))&"","")) -> *400 | G5: =IF($E5="","",IFERROR(INDEX(基础资料!$P$4:$P$34,MATCH($E5,基础资料!$N$4:$N$34,0))&"","")) -> 个 | H5: 期初库存 | I5: 2400 | L5: =IF($E5="","",N($I5)+N($J5)-N($K5)) -> 2400 | N5: =IF($E5="","",ROUND(N($L5)*N($M5),2)) -> 0
A6: =IF($E6="","",ROW()-3) -> 3 | B6: 46266 | D6: 果然鲜 | E6: 纸垫板 | F6: =IF($E6="","",IFERROR(INDEX(基础资料!$O$4:$O$34,MATCH($E6,基础资料!$N$4:$N$34,0))&"","")) -> *100张 | G6: =IF($E6="","",IFERROR(INDEX(基础资料!$P$4:$P$34,MATCH($E6,基础资料!$N$4:$N$34,0))&"","")) -> 张 | H6: 期初库存 | I6: 8700 | L6: =IF($E6="","",N($I6)+N($J6)-N($K6)) -> 8700 | N6: =IF($E6="","",ROUND(N($L6)*N($M6),2)) -> 0
A7: =IF($E7="","",ROW()-3) -> 4 | B7: 46266 | D7: 果然鲜 | E7: 香梨纸 | F7: =IF($E7="","",IFERROR(INDEX(基础资料!$O$4:$O$34,MATCH($E7,基础资料!$N$4:$N$34,0))&"","")) -> *捆 | G7: =IF($E7="","",IFERROR(INDEX(基础资料!$P$4:$P$34,MATCH($E7,基础资料!$N$4:$N$34,0))&"","")) -> 捆 | H7: 期初库存 | I7: 48 | L7: =IF($E7="","",N($I7)+N($J7)-N($K7)) -> 48 | N7: =IF($E7="","",ROUND(N($L7)*N($M7),2)) -> 0
A8: =IF($E8="","",ROW()-3) -> 5 | B8: 46266 | D8: 果然鲜 | E8: 冷煤/氟利昂 | F8: =IF($E8="","",IFERROR(INDEX(基础资料!$O$4:$O$34,MATCH($E8,基础资料!$N$4:$N$34,0))&"","")) -> *瓶 | G8: =IF($E8="","",IFERROR(INDEX(基础资料!$P$4:$P$34,MATCH($E8,基础资料!$N$4:$N$34,0))&"","")) -> 瓶 | H8: 期初库存 | I8: 23 | L8: =IF($E8="","",N($I8)+N($J8)-N($K8)) -> 23 | N8: =IF($E8="","",ROUND(N($L8)*N($M8),2)) -> 0
A9: =IF($E9="","",ROW()-3) -> 6 | B9: 46266 | D9: 果然鲜 | E9: 胶带 | F9: =IF($E9="","",IFERROR(INDEX(基础资料!$O$4:$O$34,MATCH($E9,基础资料!$N$4:$N$34,0))&"","")) -> *30卷 | G9: =IF($E9="","",IFERROR(INDEX(基础资料!$P$4:$P$34,MATCH($E9,基础资料!$N$4:$N$34,0))&"","")) -> 卷 | H9: 期初库存 | I9: 2 | L9: =IF($E9="","",N($I9)+N($J9)-N($K9)) -> 2 | N9: =IF($E9="","",ROUND(N($L9)*N($M9),2)) -> 0
A10: =IF($E10="","",ROW()-3) -> 7 | B10: 46266 | C10: NO:0000743 | D10: 新顺发泡网 | E10: 香梨网 | F10: =IF($E10="","",IFERROR(INDEX(基础资料!$O$4:$O$34,MATCH($E10,基础资料!$N$4:$N$34,0))&"","")) -> *包 | G10: =IF($E10="","",IFERROR(INDEX(基础资料!$P$4:$P$34,MATCH($E10,基础资料!$N$4:$N$34,0))&"","")) -> 包 | H10: 采购入库 | I10: 644 | J10: - | K10: - | L10: =IF($E10="","",N($I10)+N($J10)-N($K10)) -> 644 | M10: 37 | N10: =IF($E10="","",ROUND(N($L10)*N($M10),2)) -> 23828 | O10: 新Q*48887 | P10: 已付款 | R10: 12#
A11: =IF($E11="","",ROW()-3) -> 8 | B11: 46267 | C11: NO:0001067 | D11: 吐尔洪 | E11: 香梨网 | F11: =IF($E11="","",IFERROR(INDEX(基础资料!$O$4:$O$34,MATCH($E11,基础资料!$N$4:$N$34,0))&"","")) -> *包 | G11: =IF($E11="","",IFERROR(INDEX(基础资料!$P$4:$P$34,MATCH($E11,基础资料!$N$4:$N$34,0))&"","")) -> 包 | H11: 领用出库 | I11: - | J11: 24 | K11: - | L11: =IF($E11="","",N($I11)+N($J11)-N($K11)) -> 24 | M11: 45 | N11: =IF($E11="","",ROUND(N($L11)*N($M11),2)) -> 1080 | O11: 新N*X8S48 | P11: 未付款
A12: =IF($E12="","",ROW()-3) -> 9 | B12: 46268 | C12: NO:0001069 | D12: 热合曼 | E12: 香梨网 | F12: =IF($E12="","",IFERROR(INDEX(基础资料!$O$4:$O$34,MATCH($E12,基础资料!$N$4:$N$34,0))&"","")) -> *包 | G12: =IF($E12="","",IFERROR(INDEX(基础资料!$P$4:$P$34,MATCH($E12,基础资料!$N$4:$N$34,0))&"","")) -> 包 | H12: 领用出库 | I12: - | J12: 44 | K12: - | L12: =IF($E12="","",N($I12)+N($J12)-N($K12)) -> 44 | M12: 45 | N12: =IF($E12="","",ROUND(N($L12)*N($M12),2)) -> 1980 | O12: 新A*G0544 | P12: 未付款
A13: =IF($E13="","",ROW()-3) -> 10 | B13: 46268 | C13: NO:0001070 | D13: 麦麦提 | E13: 香梨纸 | F13: =IF($E13="","",IFERROR(INDEX(基础资料!$O$4:$O$34,MATCH($E13,基础资料!$N$4:$N$34,0))&"","")) -> *捆 | G13: =IF($E13="","",IFERROR(INDEX(基础资料!$P$4:$P$34,MATCH($E13,基础资料!$N$4:$N$34,0))&"","")) -> 捆 | H13: 领用出库 | I13: - | J13: 2 | K13: - | L13: =IF($E13="","",N($I13)+N($J13)-N($K13)) -> 2 | M13: 48 | N13: =IF($E13="","",ROUND(N($L13)*N($M13),2)) -> 96 | O13: 自提 | P13: 已收讫
A14: =IF($E14="","",ROW()-3) -> 11 | B14: 46268 | C14: NO:0001071 | D14: 热合曼 | E14: 香梨纸 | F14: =IF($E14="","",IFERROR(INDEX(基础资料!$O$4:$O$34,MATCH($E14,基础资料!$N$4:$N$34,0))&"","")) -> *捆 | G14: =IF($E14="","",IFERROR(INDEX(基础资料!$P$4:$P$34,MATCH($E14,基础资料!$N$4:$N$34,0))&"","")) -> 捆 | H14: 领用出库 | I14: - | J14: 2 | K14: - | L14: =IF($E14="","",N($I14)+N($J14)-N($K14)) -> 2 | M14: 48 | N14: =IF($E14="","",ROUND(N($L14)*N($M14),2)) -> 96 | O14: 自提 | P14: 已收讫
A15: =IF($E15="","",ROW()-3) -> 12 | B15: 46268 | C15: NO:0001074 | D15: 麦麦提 | E15: 香梨网 | F15: =IF($E15="","",IFERROR(INDEX(基础资料!$O$4:$O$34,MATCH($E15,基础资料!$N$4:$N$34,0))&"","")) -> *包 | G15: =IF($E15="","",IFERROR(INDEX(基础资料!$P$4:$P$34,MATCH($E15,基础资料!$N$4:$N$34,0))&"","")) -> 包 | H15: 领用出库 | I15: - | J15: 44 | K15: - | L15: =IF($E15="","",N($I15)+N($J15)-N($K15)) -> 44 | M15: 45 | N15: =IF($E15="","",ROUND(N($L15)*N($M15),2)) -> 1980 | O15: 新A*G0544 | P15: 未付款
A16: =IF($E16="","",ROW()-3) -> 13 | B16: 46269 | C16: NO:0001079 | D16: 荆建君 | E16: 香梨网 | F16: =IF($E16="","",IFERROR(INDEX(基础资料!$O$4:$O$34,MATCH($E16,基础资料!$N$4:$N$34,0))&"","")) -> *包 | G16: =IF($E16="","",IFERROR(INDEX(基础资料!$P$4:$P$34,MATCH($E16,基础资料!$N$4:$N$34,0))&"","")) -> 包 | H16: 领用出库 | I16: - | J16: 64 | K16: - | L16: =IF($E16="","",N($I16)+N($J16)-N($K16)) -> 64 | M16: 45 | N16: =IF($E16="","",ROUND(N($L16)*N($M16),2)) -> 2880 | O16: 豫A*2737K | P16: 未付款
A17: =IF($E17="","",ROW()-3) -> 14 | B17: 46269 | C17: NO:0001080 | D17: 努尔敦 | E17: 香梨网 | F17: =IF($E17="","",IFERROR(INDEX(基础资料!$O$4:$O$34,MATCH($E17,基础资料!$N$4:$N$34,0))&"","")) -> *包 | G17: =IF($E17="","",IFERROR(INDEX(基础资料!$P$4:$P$34,MATCH($E17,基础资料!$N$4:$N$34,0))&"","")) -> 包 | H17: 领用出库 | I17: - | J17: 120 | K17: - | L17: =IF($E17="","",N($I17)+N($J17)-N($K17)) -> 120 | M17: 45 | N17: =IF($E17="","",ROUND(N($L17)*N($M17),2)) -> 5400 | O17: 新F*75240 | P17: 未付款
A18: =IF($E18="","",ROW()-3) -> 15 | B18: 46270 | C18: NO:0001084 | D18: 热合曼 | E18: 香梨纸 | F18: =IF($E18="","",IFERROR(INDEX(基础资料!$O$4:$O$34,MATCH($E18,基础资料!$N$4:$N$34,0))&"","")) -> *捆 | G18: =IF($E18="","",IFERROR(INDEX(基础资料!$P$4:$P$34,MATCH($E18,基础资料!$N$4:$N$34,0))&"","")) -> 捆 | H18: 领用出库 | I18: - | J18: 10 | K18: - | L18: =IF($E18="","",N($I18)+N($J18)-N($K18)) -> 10 | M18: 56 | N18: =IF($E18="","",ROUND(N($L18)*N($M18),2)) -> 560 | O18: 新N*FJ0676 | P18: 未付款
A19: =IF($E19="","",ROW()-3) -> 16 | B19: 46272 | C19: NO:0001089 | D19: 麦麦提 | E19: 香梨网 | F19: =IF($E19="","",IFERROR(INDEX(基础资料!$O$4:$O$34,MATCH($E19,基础资料!$N$4:$N$34,0))&"","")) -> *包 | G19: =IF($E19="","",IFERROR(INDEX(基础资料!$P$4:$P$34,MATCH($E19,基础资料!$N$4:$N$34,0))&"","")) -> 包 | H19: 领用出库 | I19: - | J19: 48 | K19: - | L19: =IF($E19="","",N($I19)+N($J19)-N($K19)) -> 48 | M19: 45 | N19: =IF($E19="","",ROUND(N($L19)*N($M19),2)) -> 2160 | O19: 新A*G0544 | P19: 未付款
A20: =IF($E20="","",ROW()-3) -> 17 | B20: 46272 | C20: NO:0001092 | D20: 贾建国 | E20: 香梨网 | F20: =IF($E20="","",IFERROR(INDEX(基础资料!$O$4:$O$34,MATCH($E20,基础资料!$N$4:$N$34,0))&"","")) -> *包 | G20: =IF($E20="","",IFERROR(INDEX(基础资料!$P$4:$P$34,MATCH($E20,基础资料!$N$4:$N$34,0))&"","")) -> 包 | H20: 领用出库 | I20: - | J20: 32 | K20: - | L20: =IF($E20="","",N($I20)+N($J20)-N($K20)) -> 32 | M20: 45 | N20: =IF($E20="","",ROUND(N($L20)*N($M20),2)) -> 1440 | O20: 豫Q*H5591 | P20: 未付款
A21: =IF($E21="","",ROW()-3) -> 18 | B21: 46272 | C21: NO:0001092 | D21: 贾建国 | E21: 无纺布 | F21: =IF($E21="","",IFERROR(INDEX(基础资料!$O$4:$O$34,MATCH($E21,基础资料!$N$4:$N$34,0))&"","")) -> *400 | G21: =IF($E21="","",IFERROR(INDEX(基础资料!$P$4:$P$34,MATCH($E21,基础资料!$N$4:$N$34,0))&"","")) -> 个 | H21: 领用出库 | I21: - | J21: 800 | K21: - | L21: =IF($E21="","",N($I21)+N($J21)-N($K21)) -> 800 | M21: 0.5 | N21: =IF($E21="","",ROUND(N($L21)*N($M21),2)) -> 400 | O21: 豫Q*H5591 | P21: 未付款
A22: =IF($E22="","",ROW()-3) -> 19 | B22: 46272 | C22: NO:0001094 | D22: 热合曼 | E22: 香梨网 | F22: =IF($E22="","",IFERROR(INDEX(基础资料!$O$4:$O$34,MATCH($E22,基础资料!$N$4:$N$34,0))&"","")) -> *包 | G22: =IF($E22="","",IFERROR(INDEX(基础资料!$P$4:$P$34,MATCH($E22,基础资料!$N$4:$N$34,0))&"","")) -> 包 | H22: 领用出库 | I22: - | J22: 48 | K22: - | L22: =IF($E22="","",N($I22)+N($J22)-N($K22)) -> 48 | M22: 45 | N22: =IF($E22="","",ROUND(N($L22)*N($M22),2)) -> 2160 | O22: 新A*G0544 | P22: 未付款
A23: =IF($E23="","",ROW()-3) -> 20 | B23: 46273 | C23: NO:0000760 | D23: 贾建国 | E23: 无纺布 | F23: =IF($E23="","",IFERROR(INDEX(基础资料!$O$4:$O$34,MATCH($E23,基础资料!$N$4:$N$34,0))&"","")) -> *400 | G23: =IF($E23="","",IFERROR(INDEX(基础资料!$P$4:$P$34,MATCH($E23,基础资料!$N$4:$N$34,0))&"","")) -> 个 | H23: 退回入库 | I23: - | J23: - | K23: -800 | L23: =IF($E23="","",N($I23)+N($J23)-N($K23)) -> 800 | M23: -0.5 | N23: =IF($E23="","",ROUND(N($L23)*N($M23),2)) -> -400 | O23: 豫Q*H5591 | P23: 无需付款
A24: =IF($E24="","",ROW()-3) -> 21 | B24: 46274 | C24: NO:0001099 | D24: 吐尔逊 | E24: 香梨网 | F24: =IF($E24="","",IFERROR(INDEX(基础资料!$O$4:$O$34,MATCH($E24,基础资料!$N$4:$N$34,0))&"","")) -> *包 | G24: =IF($E24="","",IFERROR(INDEX(基础资料!$P$4:$P$34,MATCH($E24,基础资料!$N$4:$N$34,0))&"","")) -> 包 | H24: 领用出库 | I24: - | J24: 16 | K24: - | L24: =IF($E24="","",N($I24)+N($J24)-N($K24)) -> 16 | M24: 45 | N24: =IF($E24="","",ROUND(N($L24)*N($M24),2)) -> 720 | O24: 新M*87613 | P24: 未付款
A25: =IF($E25="","",ROW()-3) -> 22 | B25: 46274 | C25: NO:0001099 | D25: 吐尔逊 | E25: 香梨纸 | F25: =IF($E25="","",IFERROR(INDEX(基础资料!$O$4:$O$34,MATCH($E25,基础资料!$N$4:$N$34,0))&"","")) -> *捆 | G25: =IF($E25="","",IFERROR(INDEX(基础资料!$P$4:$P$34,MATCH($E25,基础资料!$N$4:$N$34,0))&"","")) -> 捆 | H25: 领用出库 | I25: - | J25: 2 | K25: - | L25: =IF($E25="","",N($I25)+N($J25)-N($K25)) -> 2 | M25: 60 | N25: =IF($E25="","",ROUND(N($L25)*N($M25),2)) -> 120 | O25: 新M*87613 | P25: 未付款
A26: =IF($E26="","",ROW()-3) -> 23 | B26: 46274 | C26: NO:0001100 | D26: 吐尔洪 | E26: 香梨网 | F26: =IF($E26="","",IFERROR(INDEX(基础资料!$O$4:$O$34,MATCH($E26,基础资料!$N$4:$N$34,0))&"","")) -> *包 | G26: =IF($E26="","",IFERROR(INDEX(基础资料!$P$4:$P$34,MATCH($E26,基础资料!$N$4:$N$34,0))&"","")) -> 包 | H26: 领用出库 | I26: - | J26: 12 | K26: - | L26: =IF($E26="","",N($I26)+N($J26)-N($K26)) -> 12 | M26: 45 | N26: =IF($E26="","",ROUND(N($L26)*N($M26),2)) -> 540 | O26: 新N*X8S48 | P26: 未付款
A27: =IF($E27="","",ROW()-3) -> 24 | B27: 46274 | C27: NO:0001105 | D27: 荆建君 | E27: 香梨网 | F27: =IF($E27="","",IFERROR(INDEX(基础资料!$O$4:$O$34,MATCH($E27,基础资料!$N$4:$N$34,0))&"","")) -> *包 | G27: =IF($E27="","",IFERROR(INDEX(基础资料!$P$4:$P$34,MATCH($E27,基础资料!$N$4:$N$34,0))&"","")) -> 包 | H27: 领用出库 | I27: 0 | J27: 48 | K27: 0 | L27: =IF($E27="","",N($I27)+N($J27)-N($K27)) -> 48 | M27: 45 | N27: =IF($E27="","",ROUND(N($L27)*N($M27),2)) -> 2160 | O27: 豫A*2737K | P27: 未付款
A28: =IF($E28="","",ROW()-3) -> 25 | B28: 46274 | C28: NO:0001106 | D28: 麦麦提 | E28: 香梨网 | F28: =IF($E28="","",IFERROR(INDEX(基础资料!$O$4:$O$34,MATCH($E28,基础资料!$N$4:$N$34,0))&"","")) -> *包 | G28: =IF($E28="","",IFERROR(INDEX(基础资料!$P$4:$P$34,MATCH($E28,基础资料!$N$4:$N$34,0))&"","")) -> 包 | H28: 领用出库 | I28: 0 | J28: 48 | K28: 0 | L28: =IF($E28="","",N($I28)+N($J28)-N($K28)) -> 48 | M28: 45 | N28: =IF($E28="","",ROUND(N($L28)*N($M28),2)) -> 2160 | O28: 新A*G0544 | P28: 未付款
A29: =IF($E29="","",ROW()-3) -> 26 | B29: 46276 | C29: NO:0000777 | D29: 新顺发泡网 | E29: 香梨网 | F29: =IF($E29="","",IFERROR(INDEX(基础资料!$O$4:$O$34,MATCH($E29,基础资料!$N$4:$N$34,0))&"","")) -> *包 | G29: =IF($E29="","",IFERROR(INDEX(基础资料!$P$4:$P$34,MATCH($E29,基础资料!$N$4:$N$34,0))&"","")) -> 包 | H29: 采购入库 | I29: 120 | J29: 0 | K29: 0 | L29: =IF($E29="","",N($I29)+N($J29)-N($K29)) -> 120 | M29: 37 | N29: =IF($E29="","",ROUND(N($L29)*N($M29),2)) -> 4440 | O29: 皖L*SD929 | P29: 未付款 | R29: 12#
A30: =IF($E30="","",ROW()-3) -> 27 | B30: 46276 | C30: NO:0001113 | D30: 麦麦提 | E30: 香梨网 | F30: =IF($E30="","",IFERROR(INDEX(基础资料!$O$4:$O$34,MATCH($E30,基础资料!$N$4:$N$34,0))&"","")) -> *包 | G30: =IF($E30="","",IFERROR(INDEX(基础资料!$P$4:$P$34,MATCH($E30,基础资料!$N$4:$N$34,0))&"","")) -> 包 | H30: 领用出库 | I30: 0 | J30: 48 | K30: 0 | L30: =IF($E30="","",N($I30)+N($J30)-N($K30)) -> 48 | M30: 45 | N30: =IF($E30="","",ROUND(N($L30)*N($M30),2)) -> 2160 | O30: 新A*G0544 | P30: 未付款
A31: =IF($E31="","",ROW()-3) -> 28 | B31: 46276 | C31: NO:0000779 | D31: 新顺发泡网 | E31: 香梨网 | F31: =IF($E31="","",IFERROR(INDEX(基础资料!$O$4:$O$34,MATCH($E31,基础资料!$N$4:$N$34,0))&"","")) -> *包 | G31: =IF($E31="","",IFERROR(INDEX(基础资料!$P$4:$P$34,MATCH($E31,基础资料!$N$4:$N$34,0))&"","")) -> 包 | H31: 采购入库 | I31: 120 | J31: 0 | K31: 0 | L31: =IF($E31="","",N($I31)+N($J31)-N($K31)) -> 120 | M31: 37 | N31: =IF($E31="","",ROUND(N($L31)*N($M31),2)) -> 4440 | O31: 皖L*KW876 | P31: 未付款 | R31: 12#
A32: =IF($E32="","",ROW()-3) -> 29 | B32: 46276 | C32: NO:0001117 | D32: 吐尔洪 | E32: 香梨网 | F32: =IF($E32="","",IFERROR(INDEX(基础资料!$O$4:$O$34,MATCH($E32,基础资料!$N$4:$N$34,0))&"","")) -> *包 | G32: =IF($E32="","",IFERROR(INDEX(基础资料!$P$4:$P$34,MATCH($E32,基础资料!$N$4:$N$34,0))&"","")) -> 包 | H32: 领用出库 | I32: 0 | J32: 3 | K32: 0 | L32: =IF($E32="","",N($I32)+N($J32)-N($K32)) -> 3 | M32: 45 | N32: =IF($E32="","",ROUND(N($L32)*N($M32),2)) -> 135 | O32: 新N*Z0305 | P32: 未付款
A33: =IF($E33="","",ROW()-3) -> 30 | B33: 46276 | C33: NO:0001120 | D33: 热合曼 | E33: 香梨网 | F33: =IF($E33="","",IFERROR(INDEX(基础资料!$O$4:$O$34,MATCH($E33,基础资料!$N$4:$N$34,0))&"","")) -> *包 | G33: =IF($E33="","",IFERROR(INDEX(基础资料!$P$4:$P$34,MATCH($E33,基础资料!$N$4:$N$34,0))&"","")) -> 包 | H33: 领用出库 | I33: 0 | J33: 48 | K33: 0 | L33: =IF($E33="","",N($I33)+N($J33)-N($K33)) -> 48 | M33: 45 | N33: =IF($E33="","",ROUND(N($L33)*N($M33),2)) -> 2160 | O33: 新A*G0544 | P33: 未付款
A34: =IF($E34="","",ROW()-3) -> 31 | B34: 46276 | C34: NO:0001121 | D34: 吐尔洪 | E34: 香梨网 | F34: =IF($E34="","",IFERROR(INDEX(基础资料!$O$4:$O$34,MATCH($E34,基础资料!$N$4:$N$34,0))&"","")) -> *包 | G34: =IF($E34="","",IFERROR(INDEX(基础资料!$P$4:$P$34,MATCH($E34,基础资料!$N$4:$N$34,0))&"","")) -> 包 | H34: 领用出库 | I34: 0 | J34: 12 | K34: 0 | L34: =IF($E34="","",N($I34)+N($J34)-N($K34)) -> 12 | M34: 45 | N34: =IF($E34="","",ROUND(N($L34)*N($M34),2)) -> 540 | O34: 新N*X8S48 | P34: 未付款
A35: =IF($E35="","",ROW()-3) -> 32 | B35: 46277 | C35: NO:0000791 | D35: 新顺发泡网 | E35: 香梨网 | F35: =IF($E35="","",IFERROR(INDEX(基础资料!$O$4:$O$34,MATCH($E35,基础资料!$N$4:$N$34,0))&"","")) -> *包 | G35: =IF($E35="","",IFERROR(INDEX(基础资料!$P$4:$P$34,MATCH($E35,基础资料!$N$4:$N$34,0))&"","")) -> 包 | H35: 采购入库 | I35: 120 | J35: 0 | K35: 0 | L35: =IF($E35="","",N($I35)+N($J35)-N($K35)) -> 120 | M35: 37 | N35: =IF($E35="","",ROUND(N($L35)*N($M35),2)) -> 4440 | O35: 皖L*SD929 | P35: 未付款 | R35: 12#
A36: =IF($E36="","",ROW()-3) -> 33 | B36: 46277 | C36: NO:0001125 | D36: 麦麦提 | E36: 香梨网 | F36: =IF($E36="","",IFERROR(INDEX(基础资料!$O$4:$O$34,MATCH($E36,基础资料!$N$4:$N$34,0))&"","")) -> *包 | G36: =IF($E36="","",IFERROR(INDEX(基础资料!$P$4:$P$34,MATCH($E36,基础资料!$N$4:$N$34,0))&"","")) -> 包 | H36: 领用出库 | I36: 0 | J36: 48 | K36: 0 | L36: =IF($E36="","",N($I36)+N($J36)-N($K36)) -> 48 | M36: 45 | N36: =IF($E36="","",ROUND(N($L36)*N($M36),2)) -> 2160 | O36: 新A*G0544 | P36: 未付款
A37: =IF($E37="","",ROW()-3) -> 34 | B37: 46278 | C37: NO:0001126 | D37: 荆建君 | E37: 香梨网 | F37: =IF($E37="","",IFERROR(INDEX(基础资料!$O$4:$O$34,MATCH($E37,基础资料!$N$4:$N$34,0))&"","")) -> *包 | G37: =IF($E37="","",IFERROR(INDEX(基础资料!$P$4:$P$34,MATCH($E37,基础资料!$N$4:$N$34,0))&"","")) -> 包 | H37: 领用出库 | I37: 0 | J37: 120 | K37: 0 | L37: =IF($E37="","",N($I37)+N($J37)-N($K37)) -> 120 | M37: 45 | N37: =IF($E37="","",ROUND(N($L37)*N($M37),2)) -> 5400 | O37: 豫A*2737K | P37: 未付款
A38: =IF($E38="","",ROW()-3) -> 35 | B38: 46278 | C38: NO:0001132 | D38: 吐尔洪 | E38: 香梨网 | F38: =IF($E38="","",IFERROR(INDEX(基础资料!$O$4:$O$34,MATCH($E38,基础资料!$N$4:$N$34,0))&"","")) -> *包 | G38: =IF($E38="","",IFERROR(INDEX(基础资料!$P$4:$P$34,MATCH($E38,基础资料!$N$4:$N$34,0))&"","")) -> 包 | H38: 领用出库 | I38: 0 | J38: 24 | K38: 0 | L38: =IF($E38="","",N($I38)+N($J38)-N($K38)) -> 24 | M38: 45 | N38: =IF($E38="","",ROUND(N($L38)*N($M38),2)) -> 1080 | O38: 新N*X8S48 | P38: 未付款
A39: =IF($E39="","",ROW()-3) -> 36 | B39: 46278 | C39: NO:0001133 | D39: 努尔敦 | E39: 香梨网 | F39: =IF($E39="","",IFERROR(INDEX(基础资料!$O$4:$O$34,MATCH($E39,基础资料!$N$4:$N$34,0))&"","")) -> *包 | G39: =IF($E39="","",IFERROR(INDEX(基础资料!$P$4:$P$34,MATCH($E39,基础资料!$N$4:$N$34,0))&"","")) -> 包 | H39: 领用出库 | I39: 0 | J39: 120 | K39: 0 | L39: =IF($E39="","",N($I39)+N($J39)-N($K39)) -> 120 | M39: 45 | N39: =IF($E39="","",ROUND(N($L39)*N($M39),2)) -> 5400 | O39: 新F*75240 | P39: 未付款
A40: =IF($E40="","",ROW()-3) -> 37 | B40: 46279 | C40: NO:0000856 | D40: 新顺发泡网 | E40: 香梨网 | F40: =IF($E40="","",IFERROR(INDEX(基础资料!$O$4:$O$34,MATCH($E40,基础资料!$N$4:$N$34,0))&"","")) -> *包 | G40: =IF($E40="","",IFERROR(INDEX(基础资料!$P$4:$P$34,MATCH($E40,基础资料!$N$4:$N$34,0))&"","")) -> 包 | H40: 采购入库 | I40: 100 | J40: 0 | K40: 0 | L40: =IF($E40="","",N($I40)+N($J40)-N($K40)) -> 100 | M40: 37 | N40: =IF($E40="","",ROUND(N($L40)*N($M40),2)) -> 3700 | O40: 新N*2698H | P40: 未付款 | R40: 12#
A41: =IF($E41="","",ROW()-3) | F41: =IF($E41="","",IFERROR(INDEX(基础资料!$O$4:$O$34,MATCH($E41,基础资料!$N$4:$N$34,0))&"","")) | G41: =IF($E41="","",IFERROR(INDEX(基础资料!$P$4:$P$34,MATCH($E41,基础资料!$N$4:$N$34,0))&"","")) | L41: =IF($E41="","",N($I41)+N($J41)-N($K41)) | N41: =IF($E41="","",ROUND(N($L41)*N($M41),2))
A42: =IF($E42="","",ROW()-3) | F42: =IF($E42="","",IFERROR(INDEX(基础资料!$O$4:$O$34,MATCH($E42,基础资料!$N$4:$N$34,0))&"","")) | G42: =IF($E42="","",IFERROR(INDEX(基础资料!$P$4:$P$34,MATCH($E42,基础资料!$N$4:$N$34,0))&"","")) | L42: =IF($E42="","",N($I42)+N($J42)-N($K42)) | N42: =IF($E42="","",ROUND(N($L42)*N($M42),2))
A43: =IF($E43="","",ROW()-3) | F43: =IF($E43="","",IFERROR(INDEX(基础资料!$O$4:$O$34,MATCH($E43,基础资料!$N$4:$N$34,0))&"","")) | G43: =IF($E43="","",IFERROR(INDEX(基础资料!$P$4:$P$34,MATCH($E43,基础资料!$N$4:$N$34,0))&"","")) | L43: =IF($E43="","",N($I43)+N($J43)-N($K43)) | N43: =IF($E43="","",ROUND(N($L43)*N($M43),2))
A44: =IF($E44="","",ROW()-3) | F44: =IF($E44="","",IFERROR(INDEX(基础资料!$O$4:$O$34,MATCH($E44,基础资料!$N$4:$N$34,0))&"","")) | G44: =IF($E44="","",IFERROR(INDEX(基础资料!$P$4:$P$34,MATCH($E44,基础资料!$N$4:$N$34,0))&"","")) | L44: =IF($E44="","",N($I44)+N($J44)-N($K44)) | N44: =IF($E44="","",ROUND(N($L44)*N($M44),2))
A45: =IF($E45="","",ROW()-3) | F45: =IF($E45="","",IFERROR(INDEX(基础资料!$O$4:$O$34,MATCH($E45,基础资料!$N$4:$N$34,0))&"","")) | G45: =IF($E45="","",IFERROR(INDEX(基础资料!$P$4:$P$34,MATCH($E45,基础资料!$N$4:$N$34,0))&"","")) | L45: =IF($E45="","",N($I45)+N($J45)-N($K45)) | N45: =IF($E45="","",ROUND(N($L45)*N($M45),2))
A46: =IF($E46="","",ROW()-3) | F46: =IF($E46="","",IFERROR(INDEX(基础资料!$O$4:$O$34,MATCH($E46,基础资料!$N$4:$N$34,0))&"","")) | G46: =IF($E46="","",IFERROR(INDEX(基础资料!$P$4:$P$34,MATCH($E46,基础资料!$N$4:$N$34,0))&"","")) | L46: =IF($E46="","",N($I46)+N($J46)-N($K46)) | N46: =IF($E46="","",ROUND(N($L46)*N($M46),2))
A47: =IF($E47="","",ROW()-3) | F47: =IF($E47="","",IFERROR(INDEX(基础资料!$O$4:$O$34,MATCH($E47,基础资料!$N$4:$N$34,0))&"","")) | G47: =IF($E47="","",IFERROR(INDEX(基础资料!$P$4:$P$34,MATCH($E47,基础资料!$N$4:$N$34,0))&"","")) | L47: =IF($E47="","",N($I47)+N($J47)-N($K47)) | N47: =IF($E47="","",ROUND(N($L47)*N($M47),2))
A48: =IF($E48="","",ROW()-3) | F48: =IF($E48="","",IFERROR(INDEX(基础资料!$O$4:$O$34,MATCH($E48,基础资料!$N$4:$N$34,0))&"","")) | G48: =IF($E48="","",IFERROR(INDEX(基础资料!$P$4:$P$34,MATCH($E48,基础资料!$N$4:$N$34,0))&"","")) | L48: =IF($E48="","",N($I48)+N($J48)-N($K48)) | N48: =IF($E48="","",ROUND(N($L48)*N($M48),2))
A49: =IF($E49="","",ROW()-3) | F49: =IF($E49="","",IFERROR(INDEX(基础资料!$O$4:$O$34,MATCH($E49,基础资料!$N$4:$N$34,0))&"","")) | G49: =IF($E49="","",IFERROR(INDEX(基础资料!$P$4:$P$34,MATCH($E49,基础资料!$N$4:$N$34,0))&"","")) | L49: =IF($E49="","",N($I49)+N($J49)-N($K49)) | N49: =IF($E49="","",ROUND(N($L49)*N($M49),2))
A50: =IF($E50="","",ROW()-3) | F50: =IF($E50="","",IFERROR(INDEX(基础资料!$O$4:$O$34,MATCH($E50,基础资料!$N$4:$N$34,0))&"","")) | G50: =IF($E50="","",IFERROR(INDEX(基础资料!$P$4:$P$34,MATCH($E50,基础资料!$N$4:$N$34,0))&"","")) | L50: =IF($E50="","",N($I50)+N($J50)-N($K50)) | N50: =IF($E50="","",ROUND(N($L50)*N($M50),2))
A51: =IF($E51="","",ROW()-3) | F51: =IF($E51="","",IFERROR(INDEX(基础资料!$O$4:$O$34,MATCH($E51,基础资料!$N$4:$N$34,0))&"","")) | G51: =IF($E51="","",IFERROR(INDEX(基础资料!$P$4:$P$34,MATCH($E51,基础资料!$N$4:$N$34,0))&"","")) | L51: =IF($E51="","",N($I51)+N($J51)-N($K51)) | N51: =IF($E51="","",ROUND(N($L51)*N($M51),2))
A52: =IF($E52="","",ROW()-3) | F52: =IF($E52="","",IFERROR(INDEX(基础资料!$O$4:$O$34,MATCH($E52,基础资料!$N$4:$N$34,0))&"","")) | G52: =IF($E52="","",IFERROR(INDEX(基础资料!$P$4:$P$34,MATCH($E52,基础资料!$N$4:$N$34,0))&"","")) | L52: =IF($E52="","",N($I52)+N($J52)-N($K52)) | N52: =IF($E52="","",ROUND(N($L52)*N($M52),2))
... A2003: =IF($E2003="","",ROW()-3) | F2003: =IF($E2003="","",IFERROR(INDEX(基础资料!$O$4:$O$34,MATCH($E2003,基础资料!$N$4:$N$34,0))&"","")) | G2003: =IF($E2003="","",IFERROR(INDEX(基础资料!$P$4:$P$34,MATCH($E2003,基础资料!$N$4:$N$34,0))&"","")) | L2003: =IF($E2003="","",N($I2003)+N($J2003)-N($K2003)) | N2003: =IF($E2003="","",ROUND(N($L2003)*N($M2003),2))

Sheet 客户自备加工筐明细
A1: 客 户 自 备 加 工 筐 出 / 入 库 明 细 表
A2: 客户自己带来的筐子，表外备查，不进公司资产。★随成品出库带走的自备筐，会从《01 水果进销存台账》的【筐子进出接口】自动带过来，见【自备筐汇总】右侧两列
A3: 序号 | B3: 日期 | C3: 筐子类型 | D3: 票据单号 | E3: 客户姓名 | F3: 入库数量 | G3: 出库数量 | H3: 车牌号 | I3: 装卸 | J3: 用途 | K3: 核查结果 | L3: 备注
A4: =IF($C4="","",ROW()-3) -> 1 | B4: 46277 | C4: 自备一次性筐 | E4: 王照雪 | F4: 1000 | G4: 12 | J4: 拉扎伤果
A5: =IF($C5="","",ROW()-3)
A6: =IF($C6="","",ROW()-3)
A7: =IF($C7="","",ROW()-3)
A8: =IF($C8="","",ROW()-3)
A9: =IF($C9="","",ROW()-3)
A10: =IF($C10="","",ROW()-3)
A11: =IF($C11="","",ROW()-3)
A12: =IF($C12="","",ROW()-3)
A13: =IF($C13="","",ROW()-3)
A14: =IF($C14="","",ROW()-3)
A15: =IF($C15="","",ROW()-3)
A16: =IF($C16="","",ROW()-3)
... A1203: =IF($C1203="","",ROW()-3)

Sheet 次果筐明细
A1: 次 果 筐 子 明 细 表
A2: ★次果筐/托盘合并在这一张表：类型列可选筐子类型，也可选托盘类型。业务类型区分出库/退回；押金按实收填，退款情况填已退金额，押金余额在【押金汇总】看
A3: 序号 | B3: 日期 | C3: 客户 | D3: 筐子/托盘类型 | E3: 票据单号 | F3: 业务类型 | G3: 数量 | H3: 承运人车牌号(出) | I3: 装卸 | J3: 押金金额 | K3: 退款情况（显示为负） | L3: 应收使用费 | M3: 使用费收款状态 | N3: 用途 | O3: 核查结果 | P3: 备注
A4: =IF($D4="","",ROW()-3) -> 1 | C4: 王照雪 | D4: 公司杂周转筐 | F4: 领用出库
A5: =IF($D5="","",ROW()-3)
A6: =IF($D6="","",ROW()-3)
A7: =IF($D7="","",ROW()-3)
A8: =IF($D8="","",ROW()-3)
A9: =IF($D9="","",ROW()-3)
A10: =IF($D10="","",ROW()-3)
A11: =IF($D11="","",ROW()-3)
A12: =IF($D12="","",ROW()-3)
A13: =IF($D13="","",ROW()-3)
A14: =IF($D14="","",ROW()-3)
A15: =IF($D15="","",ROW()-3)
A16: =IF($D16="","",ROW()-3)
... A603: =IF($D603="","",ROW()-3)

Sheet 物料库存结余
A1: 物 料 库 存 结 余 表（全自动） | S1: =IF($M2="",DATE(1900,1,1),$M2) -> 1
A2: ★ 全自动。填右边【开始日期／结束日期】即可按区间统计（留空＝不限时间）。明细表始终全显示。 | L2: 开始日期 | N2: 结束日期 | S2: =IF($O2="",DATE(2999,12,31),$O2) -> 401768
A3: 序号 | B3: 物料种类 | C3: 规格 | D3: 计量单位 | E3: 参考单价 | F3: 期初库存 | G3: 采购入库 | H3: 客户退回入库（显示为负） | I3: 领用出库 | J3: 销售出库 | K3: 其他减少 | L3: 剩余库存 | M3: 库存金额 | N3: 库存状态 | O3: 备注
A4: =IF($B4="","",ROW()-3) -> 1 | B4: =IFERROR(INDEX(_自动清单!$G$4:$G$63,ROW()-3),"") -> 气泡垫 | C4: =IF($B4="","",IFERROR(IF(INDEX(基础资料!$O$4:$O$103,MATCH($B4,基础资料!$N$4:$N$103,0))="",IFERROR(INDEX(_自动清单!$H$4:$H$63,ROW()-3),""),INDEX(基础资料!$O$4:$O$103,MATCH($B4,基础资料!$N$4:$N$103,0))),IFERROR(INDEX(_自动清单!$H$4:$H$63,ROW()-3),""))) -> *1000 | D4: =IF($B4="","",IFERROR(IF(INDEX(基础资料!$P$4:$P$103,MATCH($B4,基础资料!$N$4:$N$103,0))="",IFERROR(INDEX(_自动清单!$I$4:$I$63,ROW()-3),""),INDEX(基础资料!$P$4:$P$103,MATCH($B4,基础资料!$N$4:$N$103,0))),IFERROR(INDEX(_自动清单!$I$4:$I$63,ROW()-3),""))) -> 片 | E4: =IF($B4="","",IFERROR(ROUND(SUMIFS(包装物料出入库明细!$N$4:$N$2003,包装物料出入库明细!$E$4:$E$2003,$B4,包装物料出入库明细!$H$4:$H$2003,"采购入库",包装物料出入库明细!$B$4:$B$2003,">="&$S$1,包装物料出入库明细!$B$4:$B$2003,"<="&$S$2)/SUMIFS(包装物料出入库明细!$I$4:$I$2003,包装物料出入库明细!$E$4:$E$2003,$B4,包装物料出入库明细!$H$4:$H$2003,"采购入库",包装物料出入库明细!$B$4:$B$2003,">="&$S$1,包装物料出入库明细!$B$4:$B$2003,"<="&$S$2),4),0)) -> 0 | F4: =IF($B4="","",SUMIFS(包装物料出入库明细!$I$4:$I$2003,包装物料出入库明细!$E$4:$E$2003,$B4,包装物料出入库明细!$H$4:$H$2003,"期初库存",包装物料出入库明细!$B$4:$B$2003,">="&$S$1,包装物料出入库明细!$B$4:$B$2003,"<="&$S$2)) -> 13800 | G4: =IF($B4="","",SUMIFS(包装物料出入库明细!$I$4:$I$2003,包装物料出入库明细!$E$4:$E$2003,$B4,包装物料出入库明细!$H$4:$H$2003,"采购入库",包装物料出入库明细!$B$4:$B$2003,">="&$S$1,包装物料出入库明细!$B$4:$B$2003,"<="&$S$2)) -> 0 | H4: =IF($B4="","",SUMIFS(包装物料出入库明细!$K$4:$K$2003,包装物料出入库明细!$E$4:$E$2003,$B4,包装物料出入库明细!$B$4:$B$2003,">="&$S$1,包装物料出入库明细!$B$4:$B$2003,"<="&$S$2)) -> 0 | I4: =IF($B4="","",SUMIFS(包装物料出入库明细!$J$4:$J$2003,包装物料出入库明细!$E$4:$E$2003,$B4,包装物料出入库明细!$H$4:$H$2003,"领用出库",包装物料出入库明细!$B$4:$B$2003,">="&$S$1,包装物料出入库明细!$B$4:$B$2003,"<="&$S$2)) -> 0 | J4: =IF($B4="","",SUMIFS(包装物料出入库明细!$J$4:$J$2003,包装物料出入库明细!$E$4:$E$2003,$B4,包装物料出入库明细!$H$4:$H$2003,"销售出库",包装物料出入库明细!$B$4:$B$2003,">="&$S$1,包装物料出入库明细!$B$4:$B$2003,"<="&$S$2)) -> 0 | K4: =IF($B4="","",SUMIFS(包装物料出入库明细!$J$4:$J$2003,包装物料出入库明细!$E$4:$E$2003,$B4,包装物料出入库明细!$B$4:$B$2003,">="&$S$1,包装物料出入库明细!$B$4:$B$2003,"<="&$S$2)-$I4-$J4) -> 0 | L4: =IF($B4="","",$F4+$G4+$H4-$I4-$J4-$K4) -> 13800 | M4: =IF($B4="","",ROUND($L4*$E4,2)) -> 0 | N4: =IF($B4="","",IF($L4<=0,"无库存",IF($L4>=基础资料!$S$4,"充足",IF($L4>=基础资料!$S$5,"正常","不足")))) -> 充足
A5: =IF($B5="","",ROW()-3) -> 2 | B5: =IFERROR(INDEX(_自动清单!$G$4:$G$63,ROW()-3),"") -> 无纺布 | C5: =IF($B5="","",IFERROR(IF(INDEX(基础资料!$O$4:$O$103,MATCH($B5,基础资料!$N$4:$N$103,0))="",IFERROR(INDEX(_自动清单!$H$4:$H$63,ROW()-3),""),INDEX(基础资料!$O$4:$O$103,MATCH($B5,基础资料!$N$4:$N$103,0))),IFERROR(INDEX(_自动清单!$H$4:$H$63,ROW()-3),""))) -> *400 | D5: =IF($B5="","",IFERROR(IF(INDEX(基础资料!$P$4:$P$103,MATCH($B5,基础资料!$N$4:$N$103,0))="",IFERROR(INDEX(_自动清单!$I$4:$I$63,ROW()-3),""),INDEX(基础资料!$P$4:$P$103,MATCH($B5,基础资料!$N$4:$N$103,0))),IFERROR(INDEX(_自动清单!$I$4:$I$63,ROW()-3),""))) -> 个 | E5: =IF($B5="","",IFERROR(ROUND(SUMIFS(包装物料出入库明细!$N$4:$N$2003,包装物料出入库明细!$E$4:$E$2003,$B5,包装物料出入库明细!$H$4:$H$2003,"采购入库",包装物料出入库明细!$B$4:$B$2003,">="&$S$1,包装物料出入库明细!$B$4:$B$2003,"<="&$S$2)/SUMIFS(包装物料出入库明细!$I$4:$I$2003,包装物料出入库明细!$E$4:$E$2003,$B5,包装物料出入库明细!$H$4:$H$2003,"采购入库",包装物料出入库明细!$B$4:$B$2003,">="&$S$1,包装物料出入库明细!$B$4:$B$2003,"<="&$S$2),4),0)) -> 0 | F5: =IF($B5="","",SUMIFS(包装物料出入库明细!$I$4:$I$2003,包装物料出入库明细!$E$4:$E$2003,$B5,包装物料出入库明细!$H$4:$H$2003,"期初库存",包装物料出入库明细!$B$4:$B$2003,">="&$S$1,包装物料出入库明细!$B$4:$B$2003,"<="&$S$2)) -> 2400 | G5: =IF($B5="","",SUMIFS(包装物料出入库明细!$I$4:$I$2003,包装物料出入库明细!$E$4:$E$2003,$B5,包装物料出入库明细!$H$4:$H$2003,"采购入库",包装物料出入库明细!$B$4:$B$2003,">="&$S$1,包装物料出入库明细!$B$4:$B$2003,"<="&$S$2)) -> 0 | H5: =IF($B5="","",SUMIFS(包装物料出入库明细!$K$4:$K$2003,包装物料出入库明细!$E$4:$E$2003,$B5,包装物料出入库明细!$B$4:$B$2003,">="&$S$1,包装物料出入库明细!$B$4:$B$2003,"<="&$S$2)) -> -800 | I5: =IF($B5="","",SUMIFS(包装物料出入库明细!$J$4:$J$2003,包装物料出入库明细!$E$4:$E$2003,$B5,包装物料出入库明细!$H$4:$H$2003,"领用出库",包装物料出入库明细!$B$4:$B$2003,">="&$S$1,包装物料出入库明细!$B$4:$B$2003,"<="&$S$2)) -> 800 | J5: =IF($B5="","",SUMIFS(包装物料出入库明细!$J$4:$J$2003,包装物料出入库明细!$E$4:$E$2003,$B5,包装物料出入库明细!$H$4:$H$2003,"销售出库",包装物料出入库明细!$B$4:$B$2003,">="&$S$1,包装物料出入库明细!$B$4:$B$2003,"<="&$S$2)) -> 0 | K5: =IF($B5="","",SUMIFS(包装物料出入库明细!$J$4:$J$2003,包装物料出入库明细!$E$4:$E$2003,$B5,包装物料出入库明细!$B$4:$B$2003,">="&$S$1,包装物料出入库明细!$B$4:$B$2003,"<="&$S$2)-$I5-$J5) -> 0 | L5: =IF($B5="","",$F5+$G5+$H5-$I5-$J5-$K5) -> 800 | M5: =IF($B5="","",ROUND($L5*$E5,2)) -> 0 | N5: =IF($B5="","",IF($L5<=0,"无库存",IF($L5>=基础资料!$S$4,"充足",IF($L5>=基础资料!$S$5,"正常","不足")))) -> 正常
A6: =IF($B6="","",ROW()-3) -> 3 | B6: =IFERROR(INDEX(_自动清单!$G$4:$G$63,ROW()-3),"") -> 纸垫板 | C6: =IF($B6="","",IFERROR(IF(INDEX(基础资料!$O$4:$O$103,MATCH($B6,基础资料!$N$4:$N$103,0))="",IFERROR(INDEX(_自动清单!$H$4:$H$63,ROW()-3),""),INDEX(基础资料!$O$4:$O$103,MATCH($B6,基础资料!$N$4:$N$103,0))),IFERROR(INDEX(_自动清单!$H$4:$H$63,ROW()-3),""))) -> *100张 | D6: =IF($B6="","",IFERROR(IF(INDEX(基础资料!$P$4:$P$103,MATCH($B6,基础资料!$N$4:$N$103,0))="",IFERROR(INDEX(_自动清单!$I$4:$I$63,ROW()-3),""),INDEX(基础资料!$P$4:$P$103,MATCH($B6,基础资料!$N$4:$N$103,0))),IFERROR(INDEX(_自动清单!$I$4:$I$63,ROW()-3),""))) -> 张 | E6: =IF($B6="","",IFERROR(ROUND(SUMIFS(包装物料出入库明细!$N$4:$N$2003,包装物料出入库明细!$E$4:$E$2003,$B6,包装物料出入库明细!$H$4:$H$2003,"采购入库",包装物料出入库明细!$B$4:$B$2003,">="&$S$1,包装物料出入库明细!$B$4:$B$2003,"<="&$S$2)/SUMIFS(包装物料出入库明细!$I$4:$I$2003,包装物料出入库明细!$E$4:$E$2003,$B6,包装物料出入库明细!$H$4:$H$2003,"采购入库",包装物料出入库明细!$B$4:$B$2003,">="&$S$1,包装物料出入库明细!$B$4:$B$2003,"<="&$S$2),4),0)) -> 0 | F6: =IF($B6="","",SUMIFS(包装物料出入库明细!$I$4:$I$2003,包装物料出入库明细!$E$4:$E$2003,$B6,包装物料出入库明细!$H$4:$H$2003,"期初库存",包装物料出入库明细!$B$4:$B$2003,">="&$S$1,包装物料出入库明细!$B$4:$B$2003,"<="&$S$2)) -> 8700 | G6: =IF($B6="","",SUMIFS(包装物料出入库明细!$I$4:$I$2003,包装物料出入库明细!$E$4:$E$2003,$B6,包装物料出入库明细!$H$4:$H$2003,"采购入库",包装物料出入库明细!$B$4:$B$2003,">="&$S$1,包装物料出入库明细!$B$4:$B$2003,"<="&$S$2)) -> 0 | H6: =IF($B6="","",SUMIFS(包装物料出入库明细!$K$4:$K$2003,包装物料出入库明细!$E$4:$E$2003,$B6,包装物料出入库明细!$B$4:$B$2003,">="&$S$1,包装物料出入库明细!$B$4:$B$2003,"<="&$S$2)) -> 0 | I6: =IF($B6="","",SUMIFS(包装物料出入库明细!$J$4:$J$2003,包装物料出入库明细!$E$4:$E$2003,$B6,包装物料出入库明细!$H$4:$H$2003,"领用出库",包装物料出入库明细!$B$4:$B$2003,">="&$S$1,包装物料出入库明细!$B$4:$B$2003,"<="&$S$2)) -> 0 | J6: =IF($B6="","",SUMIFS(包装物料出入库明细!$J$4:$J$2003,包装物料出入库明细!$E$4:$E$2003,$B6,包装物料出入库明细!$H$4:$H$2003,"销售出库",包装物料出入库明细!$B$4:$B$2003,">="&$S$1,包装物料出入库明细!$B$4:$B$2003,"<="&$S$2)) -> 0 | K6: =IF($B6="","",SUMIFS(包装物料出入库明细!$J$4:$J$2003,包装物料出入库明细!$E$4:$E$2003,$B6,包装物料出入库明细!$B$4:$B$2003,">="&$S$1,包装物料出入库明细!$B$4:$B$2003,"<="&$S$2)-$I6-$J6) -> 0 | L6: =IF($B6="","",$F6+$G6+$H6-$I6-$J6-$K6) -> 8700 | M6: =IF($B6="","",ROUND($L6*$E6,2)) -> 0 | N6: =IF($B6="","",IF($L6<=0,"无库存",IF($L6>=基础资料!$S$4,"充足",IF($L6>=基础资料!$S$5,"正常","不足")))) -> 充足
A7: =IF($B7="","",ROW()-3) -> 4 | B7: =IFERROR(INDEX(_自动清单!$G$4:$G$63,ROW()-3),"") -> 香梨纸 | C7: =IF($B7="","",IFERROR(IF(INDEX(基础资料!$O$4:$O$103,MATCH($B7,基础资料!$N$4:$N$103,0))="",IFERROR(INDEX(_自动清单!$H$4:$H$63,ROW()-3),""),INDEX(基础资料!$O$4:$O$103,MATCH($B7,基础资料!$N$4:$N$103,0))),IFERROR(INDEX(_自动清单!$H$4:$H$63,ROW()-3),""))) -> *捆 | D7: =IF($B7="","",IFERROR(IF(INDEX(基础资料!$P$4:$P$103,MATCH($B7,基础资料!$N$4:$N$103,0))="",IFERROR(INDEX(_自动清单!$I$4:$I$63,ROW()-3),""),INDEX(基础资料!$P$4:$P$103,MATCH($B7,基础资料!$N$4:$N$103,0))),IFERROR(INDEX(_自动清单!$I$4:$I$63,ROW()-3),""))) -> 捆 | E7: =IF($B7="","",IFERROR(ROUND(SUMIFS(包装物料出入库明细!$N$4:$N$2003,包装物料出入库明细!$E$4:$E$2003,$B7,包装物料出入库明细!$H$4:$H$2003,"采购入库",包装物料出入库明细!$B$4:$B$2003,">="&$S$1,包装物料出入库明细!$B$4:$B$2003,"<="&$S$2)/SUMIFS(包装物料出入库明细!$I$4:$I$2003,包装物料出入库明细!$E$4:$E$2003,$B7,包装物料出入库明细!$H$4:$H$2003,"采购入库",包装物料出入库明细!$B$4:$B$2003,">="&$S$1,包装物料出入库明细!$B$4:$B$2003,"<="&$S$2),4),0)) -> 0 | F7: =IF($B7="","",SUMIFS(包装物料出入库明细!$I$4:$I$2003,包装物料出入库明细!$E$4:$E$2003,$B7,包装物料出入库明细!$H$4:$H$2003,"期初库存",包装物料出入库明细!$B$4:$B$2003,">="&$S$1,包装物料出入库明细!$B$4:$B$2003,"<="&$S$2)) -> 48 | G7: =IF($B7="","",SUMIFS(包装物料出入库明细!$I$4:$I$2003,包装物料出入库明细!$E$4:$E$2003,$B7,包装物料出入库明细!$H$4:$H$2003,"采购入库",包装物料出入库明细!$B$4:$B$2003,">="&$S$1,包装物料出入库明细!$B$4:$B$2003,"<="&$S$2)) -> 0 | H7: =IF($B7="","",SUMIFS(包装物料出入库明细!$K$4:$K$2003,包装物料出入库明细!$E$4:$E$2003,$B7,包装物料出入库明细!$B$4:$B$2003,">="&$S$1,包装物料出入库明细!$B$4:$B$2003,"<="&$S$2)) -> 0 | I7: =IF($B7="","",SUMIFS(包装物料出入库明细!$J$4:$J$2003,包装物料出入库明细!$E$4:$E$2003,$B7,包装物料出入库明细!$H$4:$H$2003,"领用出库",包装物料出入库明细!$B$4:$B$2003,">="&$S$1,包装物料出入库明细!$B$4:$B$2003,"<="&$S$2)) -> 16 | J7: =IF($B7="","",SUMIFS(包装物料出入库明细!$J$4:$J$2003,包装物料出入库明细!$E$4:$E$2003,$B7,包装物料出入库明细!$H$4:$H$2003,"销售出库",包装物料出入库明细!$B$4:$B$2003,">="&$S$1,包装物料出入库明细!$B$4:$B$2003,"<="&$S$2)) -> 0 | K7: =IF($B7="","",SUMIFS(包装物料出入库明细!$J$4:$J$2003,包装物料出入库明细!$E$4:$E$2003,$B7,包装物料出入库明细!$B$4:$B$2003,">="&$S$1,包装物料出入库明细!$B$4:$B$2003,"<="&$S$2)-$I7-$J7) -> 0 | L7: =IF($B7="","",$F7+$G7+$H7-$I7-$J7-$K7) -> 32 | M7: =IF($B7="","",ROUND($L7*$E7,2)) -> 0 | N7: =IF($B7="","",IF($L7<=0,"无库存",IF($L7>=基础资料!$S$4,"充足",IF($L7>=基础资料!$S$5,"正常","不足")))) -> 不足
A8: =IF($B8="","",ROW()-3) -> 5 | B8: =IFERROR(INDEX(_自动清单!$G$4:$G$63,ROW()-3),"") -> 冷煤/氟利昂 | C8: =IF($B8="","",IFERROR(IF(INDEX(基础资料!$O$4:$O$103,MATCH($B8,基础资料!$N$4:$N$103,0))="",IFERROR(INDEX(_自动清单!$H$4:$H$63,ROW()-3),""),INDEX(基础资料!$O$4:$O$103,MATCH($B8,基础资料!$N$4:$N$103,0))),IFERROR(INDEX(_自动清单!$H$4:$H$63,ROW()-3),""))) -> *瓶 | D8: =IF($B8="","",IFERROR(IF(INDEX(基础资料!$P$4:$P$103,MATCH($B8,基础资料!$N$4:$N$103,0))="",IFERROR(INDEX(_自动清单!$I$4:$I$63,ROW()-3),""),INDEX(基础资料!$P$4:$P$103,MATCH($B8,基础资料!$N$4:$N$103,0))),IFERROR(INDEX(_自动清单!$I$4:$I$63,ROW()-3),""))) -> 瓶 | E8: =IF($B8="","",IFERROR(ROUND(SUMIFS(包装物料出入库明细!$N$4:$N$2003,包装物料出入库明细!$E$4:$E$2003,$B8,包装物料出入库明细!$H$4:$H$2003,"采购入库",包装物料出入库明细!$B$4:$B$2003,">="&$S$1,包装物料出入库明细!$B$4:$B$2003,"<="&$S$2)/SUMIFS(包装物料出入库明细!$I$4:$I$2003,包装物料出入库明细!$E$4:$E$2003,$B8,包装物料出入库明细!$H$4:$H$2003,"采购入库",包装物料出入库明细!$B$4:$B$2003,">="&$S$1,包装物料出入库明细!$B$4:$B$2003,"<="&$S$2),4),0)) -> 0 | F8: =IF($B8="","",SUMIFS(包装物料出入库明细!$I$4:$I$2003,包装物料出入库明细!$E$4:$E$2003,$B8,包装物料出入库明细!$H$4:$H$2003,"期初库存",包装物料出入库明细!$B$4:$B$2003,">="&$S$1,包装物料出入库明细!$B$4:$B$2003,"<="&$S$2)) -> 23 | G8: =IF($B8="","",SUMIFS(包装物料出入库明细!$I$4:$I$2003,包装物料出入库明细!$E$4:$E$2003,$B8,包装物料出入库明细!$H$4:$H$2003,"采购入库",包装物料出入库明细!$B$4:$B$2003,">="&$S$1,包装物料出入库明细!$B$4:$B$2003,"<="&$S$2)) -> 0 | H8: =IF($B8="","",SUMIFS(包装物料出入库明细!$K$4:$K$2003,包装物料出入库明细!$E$4:$E$2003,$B8,包装物料出入库明细!$B$4:$B$2003,">="&$S$1,包装物料出入库明细!$B$4:$B$2003,"<="&$S$2)) -> 0 | I8: =IF($B8="","",SUMIFS(包装物料出入库明细!$J$4:$J$2003,包装物料出入库明细!$E$4:$E$2003,$B8,包装物料出入库明细!$H$4:$H$2003,"领用出库",包装物料出入库明细!$B$4:$B$2003,">="&$S$1,包装物料出入库明细!$B$4:$B$2003,"<="&$S$2)) -> 0 | J8: =IF($B8="","",SUMIFS(包装物料出入库明细!$J$4:$J$2003,包装物料出入库明细!$E$4:$E$2003,$B8,包装物料出入库明细!$H$4:$H$2003,"销售出库",包装物料出入库明细!$B$4:$B$2003,">="&$S$1,包装物料出入库明细!$B$4:$B$2003,"<="&$S$2)) -> 0 | K8: =IF($B8="","",SUMIFS(包装物料出入库明细!$J$4:$J$2003,包装物料出入库明细!$E$4:$E$2003,$B8,包装物料出入库明细!$B$4:$B$2003,">="&$S$1,包装物料出入库明细!$B$4:$B$2003,"<="&$S$2)-$I8-$J8) -> 0 | L8: =IF($B8="","",$F8+$G8+$H8-$I8-$J8-$K8) -> 23 | M8: =IF($B8="","",ROUND($L8*$E8,2)) -> 0 | N8: =IF($B8="","",IF($L8<=0,"无库存",IF($L8>=基础资料!$S$4,"充足",IF($L8>=基础资料!$S$5,"正常","不足")))) -> 不足
A9: =IF($B9="","",ROW()-3) -> 6 | B9: =IFERROR(INDEX(_自动清单!$G$4:$G$63,ROW()-3),"") -> 胶带 | C9: =IF($B9="","",IFERROR(IF(INDEX(基础资料!$O$4:$O$103,MATCH($B9,基础资料!$N$4:$N$103,0))="",IFERROR(INDEX(_自动清单!$H$4:$H$63,ROW()-3),""),INDEX(基础资料!$O$4:$O$103,MATCH($B9,基础资料!$N$4:$N$103,0))),IFERROR(INDEX(_自动清单!$H$4:$H$63,ROW()-3),""))) -> *30卷 | D9: =IF($B9="","",IFERROR(IF(INDEX(基础资料!$P$4:$P$103,MATCH($B9,基础资料!$N$4:$N$103,0))="",IFERROR(INDEX(_自动清单!$I$4:$I$63,ROW()-3),""),INDEX(基础资料!$P$4:$P$103,MATCH($B9,基础资料!$N$4:$N$103,0))),IFERROR(INDEX(_自动清单!$I$4:$I$63,ROW()-3),""))) -> 卷 | E9: =IF($B9="","",IFERROR(ROUND(SUMIFS(包装物料出入库明细!$N$4:$N$2003,包装物料出入库明细!$E$4:$E$2003,$B9,包装物料出入库明细!$H$4:$H$2003,"采购入库",包装物料出入库明细!$B$4:$B$2003,">="&$S$1,包装物料出入库明细!$B$4:$B$2003,"<="&$S$2)/SUMIFS(包装物料出入库明细!$I$4:$I$2003,包装物料出入库明细!$E$4:$E$2003,$B9,包装物料出入库明细!$H$4:$H$2003,"采购入库",包装物料出入库明细!$B$4:$B$2003,">="&$S$1,包装物料出入库明细!$B$4:$B$2003,"<="&$S$2),4),0)) -> 0 | F9: =IF($B9="","",SUMIFS(包装物料出入库明细!$I$4:$I$2003,包装物料出入库明细!$E$4:$E$2003,$B9,包装物料出入库明细!$H$4:$H$2003,"期初库存",包装物料出入库明细!$B$4:$B$2003,">="&$S$1,包装物料出入库明细!$B$4:$B$2003,"<="&$S$2)) -> 2 | G9: =IF($B9="","",SUMIFS(包装物料出入库明细!$I$4:$I$2003,包装物料出入库明细!$E$4:$E$2003,$B9,包装物料出入库明细!$H$4:$H$2003,"采购入库",包装物料出入库明细!$B$4:$B$2003,">="&$S$1,包装物料出入库明细!$B$4:$B$2003,"<="&$S$2)) -> 0 | H9: =IF($B9="","",SUMIFS(包装物料出入库明细!$K$4:$K$2003,包装物料出入库明细!$E$4:$E$2003,$B9,包装物料出入库明细!$B$4:$B$2003,">="&$S$1,包装物料出入库明细!$B$4:$B$2003,"<="&$S$2)) -> 0 | I9: =IF($B9="","",SUMIFS(包装物料出入库明细!$J$4:$J$2003,包装物料出入库明细!$E$4:$E$2003,$B9,包装物料出入库明细!$H$4:$H$2003,"领用出库",包装物料出入库明细!$B$4:$B$2003,">="&$S$1,包装物料出入库明细!$B$4:$B$2003,"<="&$S$2)) -> 0 | J9: =IF($B9="","",SUMIFS(包装物料出入库明细!$J$4:$J$2003,包装物料出入库明细!$E$4:$E$2003,$B9,包装物料出入库明细!$H$4:$H$2003,"销售出库",包装物料出入库明细!$B$4:$B$2003,">="&$S$1,包装物料出入库明细!$B$4:$B$2003,"<="&$S$2)) -> 0 | K9: =IF($B9="","",SUMIFS(包装物料出入库明细!$J$4:$J$2003,包装物料出入库明细!$E$4:$E$2003,$B9,包装物料出入库明细!$B$4:$B$2003,">="&$S$1,包装物料出入库明细!$B$4:$B$2003,"<="&$S$2)-$I9-$J9) -> 0 | L9: =IF($B9="","",$F9+$G9+$H9-$I9-$J9-$K9) -> 2 | M9: =IF($B9="","",ROUND($L9*$E9,2)) -> 0 | N9: =IF($B9="","",IF($L9<=0,"无库存",IF($L9>=基础资料!$S$4,"充足",IF($L9>=基础资料!$S$5,"正常","不足")))) -> 不足
A10: =IF($B10="","",ROW()-3) -> 7 | B10: =IFERROR(INDEX(_自动清单!$G$4:$G$63,ROW()-3),"") -> 香梨网 | C10: =IF($B10="","",IFERROR(IF(INDEX(基础资料!$O$4:$O$103,MATCH($B10,基础资料!$N$4:$N$103,0))="",IFERROR(INDEX(_自动清单!$H$4:$H$63,ROW()-3),""),INDEX(基础资料!$O$4:$O$103,MATCH($B10,基础资料!$N$4:$N$103,0))),IFERROR(INDEX(_自动清单!$H$4:$H$63,ROW()-3),""))) -> *包 | D10: =IF($B10="","",IFERROR(IF(INDEX(基础资料!$P$4:$P$103,MATCH($B10,基础资料!$N$4:$N$103,0))="",IFERROR(INDEX(_自动清单!$I$4:$I$63,ROW()-3),""),INDEX(基础资料!$P$4:$P$103,MATCH($B10,基础资料!$N$4:$N$103,0))),IFERROR(INDEX(_自动清单!$I$4:$I$63,ROW()-3),""))) -> 包 | E10: =IF($B10="","",IFERROR(ROUND(SUMIFS(包装物料出入库明细!$N$4:$N$2003,包装物料出入库明细!$E$4:$E$2003,$B10,包装物料出入库明细!$H$4:$H$2003,"采购入库",包装物料出入库明细!$B$4:$B$2003,">="&$S$1,包装物料出入库明细!$B$4:$B$2003,"<="&$S$2)/SUMIFS(包装物料出入库明细!$I$4:$I$2003,包装物料出入库明细!$E$4:$E$2003,$B10,包装物料出入库明细!$H$4:$H$2003,"采购入库",包装物料出入库明细!$B$4:$B$2003,">="&$S$1,包装物料出入库明细!$B$4:$B$2003,"<="&$S$2),4),0)) -> 37 | F10: =IF($B10="","",SUMIFS(包装物料出入库明细!$I$4:$I$2003,包装物料出入库明细!$E$4:$E$2003,$B10,包装物料出入库明细!$H$4:$H$2003,"期初库存",包装物料出入库明细!$B$4:$B$2003,">="&$S$1,包装物料出入库明细!$B$4:$B$2003,"<="&$S$2)) -> 0 | G10: =IF($B10="","",SUMIFS(包装物料出入库明细!$I$4:$I$2003,包装物料出入库明细!$E$4:$E$2003,$B10,包装物料出入库明细!$H$4:$H$2003,"采购入库",包装物料出入库明细!$B$4:$B$2003,">="&$S$1,包装物料出入库明细!$B$4:$B$2003,"<="&$S$2)) -> 1104 | H10: =IF($B10="","",SUMIFS(包装物料出入库明细!$K$4:$K$2003,包装物料出入库明细!$E$4:$E$2003,$B10,包装物料出入库明细!$B$4:$B$2003,">="&$S$1,包装物料出入库明细!$B$4:$B$2003,"<="&$S$2)) -> 0 | I10: =IF($B10="","",SUMIFS(包装物料出入库明细!$J$4:$J$2003,包装物料出入库明细!$E$4:$E$2003,$B10,包装物料出入库明细!$H$4:$H$2003,"领用出库",包装物料出入库明细!$B$4:$B$2003,">="&$S$1,包装物料出入库明细!$B$4:$B$2003,"<="&$S$2)) -> 971 | J10: =IF($B10="","",SUMIFS(包装物料出入库明细!$J$4:$J$2003,包装物料出入库明细!$E$4:$E$2003,$B10,包装物料出入库明细!$H$4:$H$2003,"销售出库",包装物料出入库明细!$B$4:$B$2003,">="&$S$1,包装物料出入库明细!$B$4:$B$2003,"<="&$S$2)) -> 0 | K10: =IF($B10="","",SUMIFS(包装物料出入库明细!$J$4:$J$2003,包装物料出入库明细!$E$4:$E$2003,$B10,包装物料出入库明细!$B$4:$B$2003,">="&$S$1,包装物料出入库明细!$B$4:$B$2003,"<="&$S$2)-$I10-$J10) -> 0 | L10: =IF($B10="","",$F10+$G10+$H10-$I10-$J10-$K10) -> 133 | M10: =IF($B10="","",ROUND($L10*$E10,2)) -> 4921 | N10: =IF($B10="","",IF($L10<=0,"无库存",IF($L10>=基础资料!$S$4,"充足",IF($L10>=基础资料!$S$5,"正常","不足")))) -> 正常
A11: =IF($B11="","",ROW()-3) | B11: =IFERROR(INDEX(_自动清单!$G$4:$G$63,ROW()-3),"") | C11: =IF($B11="","",IFERROR(IF(INDEX(基础资料!$O$4:$O$103,MATCH($B11,基础资料!$N$4:$N$103,0))="",IFERROR(INDEX(_自动清单!$H$4:$H$63,ROW()-3),""),INDEX(基础资料!$O$4:$O$103,MATCH($B11,基础资料!$N$4:$N$103,0))),IFERROR(INDEX(_自动清单!$H$4:$H$63,ROW()-3),""))) | D11: =IF($B11="","",IFERROR(IF(INDEX(基础资料!$P$4:$P$103,MATCH($B11,基础资料!$N$4:$N$103,0))="",IFERROR(INDEX(_自动清单!$I$4:$I$63,ROW()-3),""),INDEX(基础资料!$P$4:$P$103,MATCH($B11,基础资料!$N$4:$N$103,0))),IFERROR(INDEX(_自动清单!$I$4:$I$63,ROW()-3),""))) | E11: =IF($B11="","",IFERROR(ROUND(SUMIFS(包装物料出入库明细!$N$4:$N$2003,包装物料出入库明细!$E$4:$E$2003,$B11,包装物料出入库明细!$H$4:$H$2003,"采购入库",包装物料出入库明细!$B$4:$B$2003,">="&$S$1,包装物料出入库明细!$B$4:$B$2003,"<="&$S$2)/SUMIFS(包装物料出入库明细!$I$4:$I$2003,包装物料出入库明细!$E$4:$E$2003,$B11,包装物料出入库明细!$H$4:$H$2003,"采购入库",包装物料出入库明细!$B$4:$B$2003,">="&$S$1,包装物料出入库明细!$B$4:$B$2003,"<="&$S$2),4),0)) | F11: =IF($B11="","",SUMIFS(包装物料出入库明细!$I$4:$I$2003,包装物料出入库明细!$E$4:$E$2003,$B11,包装物料出入库明细!$H$4:$H$2003,"期初库存",包装物料出入库明细!$B$4:$B$2003,">="&$S$1,包装物料出入库明细!$B$4:$B$2003,"<="&$S$2)) | G11: =IF($B11="","",SUMIFS(包装物料出入库明细!$I$4:$I$2003,包装物料出入库明细!$E$4:$E$2003,$B11,包装物料出入库明细!$H$4:$H$2003,"采购入库",包装物料出入库明细!$B$4:$B$2003,">="&$S$1,包装物料出入库明细!$B$4:$B$2003,"<="&$S$2)) | H11: =IF($B11="","",SUMIFS(包装物料出入库明细!$K$4:$K$2003,包装物料出入库明细!$E$4:$E$2003,$B11,包装物料出入库明细!$B$4:$B$2003,">="&$S$1,包装物料出入库明细!$B$4:$B$2003,"<="&$S$2)) | I11: =IF($B11="","",SUMIFS(包装物料出入库明细!$J$4:$J$2003,包装物料出入库明细!$E$4:$E$2003,$B11,包装物料出入库明细!$H$4:$H$2003,"领用出库",包装物料出入库明细!$B$4:$B$2003,">="&$S$1,包装物料出入库明细!$B$4:$B$2003,"<="&$S$2)) | J11: =IF($B11="","",SUMIFS(包装物料出入库明细!$J$4:$J$2003,包装物料出入库明细!$E$4:$E$2003,$B11,包装物料出入库明细!$H$4:$H$2003,"销售出库",包装物料出入库明细!$B$4:$B$2003,">="&$S$1,包装物料出入库明细!$B$4:$B$2003,"<="&$S$2)) | K11: =IF($B11="","",SUMIFS(包装物料出入库明细!$J$4:$J$2003,包装物料出入库明细!$E$4:$E$2003,$B11,包装物料出入库明细!$B$4:$B$2003,">="&$S$1,包装物料出入库明细!$B$4:$B$2003,"<="&$S$2)-$I11-$J11) | L11: =IF($B11="","",$F11+$G11+$H11-$I11-$J11-$K11) | M11: =IF($B11="","",ROUND($L11*$E11,2)) | N11: =IF($B11="","",IF($L11<=0,"无库存",IF($L11>=基础资料!$S$4,"充足",IF($L11>=基础资料!$S$5,"正常","不足"))))
A12: =IF($B12="","",ROW()-3) | B12: =IFERROR(INDEX(_自动清单!$G$4:$G$63,ROW()-3),"") | C12: =IF($B12="","",IFERROR(IF(INDEX(基础资料!$O$4:$O$103,MATCH($B12,基础资料!$N$4:$N$103,0))="",IFERROR(INDEX(_自动清单!$H$4:$H$63,ROW()-3),""),INDEX(基础资料!$O$4:$O$103,MATCH($B12,基础资料!$N$4:$N$103,0))),IFERROR(INDEX(_自动清单!$H$4:$H$63,ROW()-3),""))) | D12: =IF($B12="","",IFERROR(IF(INDEX(基础资料!$P$4:$P$103,MATCH($B12,基础资料!$N$4:$N$103,0))="",IFERROR(INDEX(_自动清单!$I$4:$I$63,ROW()-3),""),INDEX(基础资料!$P$4:$P$103,MATCH($B12,基础资料!$N$4:$N$103,0))),IFERROR(INDEX(_自动清单!$I$4:$I$63,ROW()-3),""))) | E12: =IF($B12="","",IFERROR(ROUND(SUMIFS(包装物料出入库明细!$N$4:$N$2003,包装物料出入库明细!$E$4:$E$2003,$B12,包装物料出入库明细!$H$4:$H$2003,"采购入库",包装物料出入库明细!$B$4:$B$2003,">="&$S$1,包装物料出入库明细!$B$4:$B$2003,"<="&$S$2)/SUMIFS(包装物料出入库明细!$I$4:$I$2003,包装物料出入库明细!$E$4:$E$2003,$B12,包装物料出入库明细!$H$4:$H$2003,"采购入库",包装物料出入库明细!$B$4:$B$2003,">="&$S$1,包装物料出入库明细!$B$4:$B$2003,"<="&$S$2),4),0)) | F12: =IF($B12="","",SUMIFS(包装物料出入库明细!$I$4:$I$2003,包装物料出入库明细!$E$4:$E$2003,$B12,包装物料出入库明细!$H$4:$H$2003,"期初库存",包装物料出入库明细!$B$4:$B$2003,">="&$S$1,包装物料出入库明细!$B$4:$B$2003,"<="&$S$2)) | G12: =IF($B12="","",SUMIFS(包装物料出入库明细!$I$4:$I$2003,包装物料出入库明细!$E$4:$E$2003,$B12,包装物料出入库明细!$H$4:$H$2003,"采购入库",包装物料出入库明细!$B$4:$B$2003,">="&$S$1,包装物料出入库明细!$B$4:$B$2003,"<="&$S$2)) | H12: =IF($B12="","",SUMIFS(包装物料出入库明细!$K$4:$K$2003,包装物料出入库明细!$E$4:$E$2003,$B12,包装物料出入库明细!$B$4:$B$2003,">="&$S$1,包装物料出入库明细!$B$4:$B$2003,"<="&$S$2)) | I12: =IF($B12="","",SUMIFS(包装物料出入库明细!$J$4:$J$2003,包装物料出入库明细!$E$4:$E$2003,$B12,包装物料出入库明细!$H$4:$H$2003,"领用出库",包装物料出入库明细!$B$4:$B$2003,">="&$S$1,包装物料出入库明细!$B$4:$B$2003,"<="&$S$2)) | J12: =IF($B12="","",SUMIFS(包装物料出入库明细!$J$4:$J$2003,包装物料出入库明细!$E$4:$E$2003,$B12,包装物料出入库明细!$H$4:$H$2003,"销售出库",包装物料出入库明细!$B$4:$B$2003,">="&$S$1,包装物料出入库明细!$B$4:$B$2003,"<="&$S$2)) | K12: =IF($B12="","",SUMIFS(包装物料出入库明细!$J$4:$J$2003,包装物料出入库明细!$E$4:$E$2003,$B12,包装物料出入库明细!$B$4:$B$2003,">="&$S$1,包装物料出入库明细!$B$4:$B$2003,"<="&$S$2)-$I12-$J12) | L12: =IF($B12="","",$F12+$G12+$H12-$I12-$J12-$K12) | M12: =IF($B12="","",ROUND($L12*$E12,2)) | N12: =IF($B12="","",IF($L12<=0,"无库存",IF($L12>=基础资料!$S$4,"充足",IF($L12>=基础资料!$S$5,"正常","不足"))))
A13: =IF($B13="","",ROW()-3) | B13: =IFERROR(INDEX(_自动清单!$G$4:$G$63,ROW()-3),"") | C13: =IF($B13="","",IFERROR(IF(INDEX(基础资料!$O$4:$O$103,MATCH($B13,基础资料!$N$4:$N$103,0))="",IFERROR(INDEX(_自动清单!$H$4:$H$63,ROW()-3),""),INDEX(基础资料!$O$4:$O$103,MATCH($B13,基础资料!$N$4:$N$103,0))),IFERROR(INDEX(_自动清单!$H$4:$H$63,ROW()-3),""))) | D13: =IF($B13="","",IFERROR(IF(INDEX(基础资料!$P$4:$P$103,MATCH($B13,基础资料!$N$4:$N$103,0))="",IFERROR(INDEX(_自动清单!$I$4:$I$63,ROW()-3),""),INDEX(基础资料!$P$4:$P$103,MATCH($B13,基础资料!$N$4:$N$103,0))),IFERROR(INDEX(_自动清单!$I$4:$I$63,ROW()-3),""))) | E13: =IF($B13="","",IFERROR(ROUND(SUMIFS(包装物料出入库明细!$N$4:$N$2003,包装物料出入库明细!$E$4:$E$2003,$B13,包装物料出入库明细!$H$4:$H$2003,"采购入库",包装物料出入库明细!$B$4:$B$2003,">="&$S$1,包装物料出入库明细!$B$4:$B$2003,"<="&$S$2)/SUMIFS(包装物料出入库明细!$I$4:$I$2003,包装物料出入库明细!$E$4:$E$2003,$B13,包装物料出入库明细!$H$4:$H$2003,"采购入库",包装物料出入库明细!$B$4:$B$2003,">="&$S$1,包装物料出入库明细!$B$4:$B$2003,"<="&$S$2),4),0)) | F13: =IF($B13="","",SUMIFS(包装物料出入库明细!$I$4:$I$2003,包装物料出入库明细!$E$4:$E$2003,$B13,包装物料出入库明细!$H$4:$H$2003,"期初库存",包装物料出入库明细!$B$4:$B$2003,">="&$S$1,包装物料出入库明细!$B$4:$B$2003,"<="&$S$2)) | G13: =IF($B13="","",SUMIFS(包装物料出入库明细!$I$4:$I$2003,包装物料出入库明细!$E$4:$E$2003,$B13,包装物料出入库明细!$H$4:$H$2003,"采购入库",包装物料出入库明细!$B$4:$B$2003,">="&$S$1,包装物料出入库明细!$B$4:$B$2003,"<="&$S$2)) | H13: =IF($B13="","",SUMIFS(包装物料出入库明细!$K$4:$K$2003,包装物料出入库明细!$E$4:$E$2003,$B13,包装物料出入库明细!$B$4:$B$2003,">="&$S$1,包装物料出入库明细!$B$4:$B$2003,"<="&$S$2)) | I13: =IF($B13="","",SUMIFS(包装物料出入库明细!$J$4:$J$2003,包装物料出入库明细!$E$4:$E$2003,$B13,包装物料出入库明细!$H$4:$H$2003,"领用出库",包装物料出入库明细!$B$4:$B$2003,">="&$S$1,包装物料出入库明细!$B$4:$B$2003,"<="&$S$2)) | J13: =IF($B13="","",SUMIFS(包装物料出入库明细!$J$4:$J$2003,包装物料出入库明细!$E$4:$E$2003,$B13,包装物料出入库明细!$H$4:$H$2003,"销售出库",包装物料出入库明细!$B$4:$B$2003,">="&$S$1,包装物料出入库明细!$B$4:$B$2003,"<="&$S$2)) | K13: =IF($B13="","",SUMIFS(包装物料出入库明细!$J$4:$J$2003,包装物料出入库明细!$E$4:$E$2003,$B13,包装物料出入库明细!$B$4:$B$2003,">="&$S$1,包装物料出入库明细!$B$4:$B$2003,"<="&$S$2)-$I13-$J13) | L13: =IF($B13="","",$F13+$G13+$H13-$I13-$J13-$K13) | M13: =IF($B13="","",ROUND($L13*$E13,2)) | N13: =IF($B13="","",IF($L13<=0,"无库存",IF($L13>=基础资料!$S$4,"充足",IF($L13>=基础资料!$S$5,"正常","不足"))))
A14: =IF($B14="","",ROW()-3) | B14: =IFERROR(INDEX(_自动清单!$G$4:$G$63,ROW()-3),"") | C14: =IF($B14="","",IFERROR(IF(INDEX(基础资料!$O$4:$O$103,MATCH($B14,基础资料!$N$4:$N$103,0))="",IFERROR(INDEX(_自动清单!$H$4:$H$63,ROW()-3),""),INDEX(基础资料!$O$4:$O$103,MATCH($B14,基础资料!$N$4:$N$103,0))),IFERROR(INDEX(_自动清单!$H$4:$H$63,ROW()-3),""))) | D14: =IF($B14="","",IFERROR(IF(INDEX(基础资料!$P$4:$P$103,MATCH($B14,基础资料!$N$4:$N$103,0))="",IFERROR(INDEX(_自动清单!$I$4:$I$63,ROW()-3),""),INDEX(基础资料!$P$4:$P$103,MATCH($B14,基础资料!$N$4:$N$103,0))),IFERROR(INDEX(_自动清单!$I$4:$I$63,ROW()-3),""))) | E14: =IF($B14="","",IFERROR(ROUND(SUMIFS(包装物料出入库明细!$N$4:$N$2003,包装物料出入库明细!$E$4:$E$2003,$B14,包装物料出入库明细!$H$4:$H$2003,"采购入库",包装物料出入库明细!$B$4:$B$2003,">="&$S$1,包装物料出入库明细!$B$4:$B$2003,"<="&$S$2)/SUMIFS(包装物料出入库明细!$I$4:$I$2003,包装物料出入库明细!$E$4:$E$2003,$B14,包装物料出入库明细!$H$4:$H$2003,"采购入库",包装物料出入库明细!$B$4:$B$2003,">="&$S$1,包装物料出入库明细!$B$4:$B$2003,"<="&$S$2),4),0)) | F14: =IF($B14="","",SUMIFS(包装物料出入库明细!$I$4:$I$2003,包装物料出入库明细!$E$4:$E$2003,$B14,包装物料出入库明细!$H$4:$H$2003,"期初库存",包装物料出入库明细!$B$4:$B$2003,">="&$S$1,包装物料出入库明细!$B$4:$B$2003,"<="&$S$2)) | G14: =IF($B14="","",SUMIFS(包装物料出入库明细!$I$4:$I$2003,包装物料出入库明细!$E$4:$E$2003,$B14,包装物料出入库明细!$H$4:$H$2003,"采购入库",包装物料出入库明细!$B$4:$B$2003,">="&$S$1,包装物料出入库明细!$B$4:$B$2003,"<="&$S$2)) | H14: =IF($B14="","",SUMIFS(包装物料出入库明细!$K$4:$K$2003,包装物料出入库明细!$E$4:$E$2003,$B14,包装物料出入库明细!$B$4:$B$2003,">="&$S$1,包装物料出入库明细!$B$4:$B$2003,"<="&$S$2)) | I14: =IF($B14="","",SUMIFS(包装物料出入库明细!$J$4:$J$2003,包装物料出入库明细!$E$4:$E$2003,$B14,包装物料出入库明细!$H$4:$H$2003,"领用出库",包装物料出入库明细!$B$4:$B$2003,">="&$S$1,包装物料出入库明细!$B$4:$B$2003,"<="&$S$2)) | J14: =IF($B14="","",SUMIFS(包装物料出入库明细!$J$4:$J$2003,包装物料出入库明细!$E$4:$E$2003,$B14,包装物料出入库明细!$H$4:$H$2003,"销售出库",包装物料出入库明细!$B$4:$B$2003,">="&$S$1,包装物料出入库明细!$B$4:$B$2003,"<="&$S$2)) | K14: =IF($B14="","",SUMIFS(包装物料出入库明细!$J$4:$J$2003,包装物料出入库明细!$E$4:$E$2003,$B14,包装物料出入库明细!$B$4:$B$2003,">="&$S$1,包装物料出入库明细!$B$4:$B$2003,"<="&$S$2)-$I14-$J14) | L14: =IF($B14="","",$F14+$G14+$H14-$I14-$J14-$K14) | M14: =IF($B14="","",ROUND($L14*$E14,2)) | N14: =IF($B14="","",IF($L14<=0,"无库存",IF($L14>=基础资料!$S$4,"充足",IF($L14>=基础资料!$S$5,"正常","不足"))))
A15: =IF($B15="","",ROW()-3) | B15: =IFERROR(INDEX(_自动清单!$G$4:$G$63,ROW()-3),"") | C15: =IF($B15="","",IFERROR(IF(INDEX(基础资料!$O$4:$O$103,MATCH($B15,基础资料!$N$4:$N$103,0))="",IFERROR(INDEX(_自动清单!$H$4:$H$63,ROW()-3),""),INDEX(基础资料!$O$4:$O$103,MATCH($B15,基础资料!$N$4:$N$103,0))),IFERROR(INDEX(_自动清单!$H$4:$H$63,ROW()-3),""))) | D15: =IF($B15="","",IFERROR(IF(INDEX(基础资料!$P$4:$P$103,MATCH($B15,基础资料!$N$4:$N$103,0))="",IFERROR(INDEX(_自动清单!$I$4:$I$63,ROW()-3),""),INDEX(基础资料!$P$4:$P$103,MATCH($B15,基础资料!$N$4:$N$103,0))),IFERROR(INDEX(_自动清单!$I$4:$I$63,ROW()-3),""))) | E15: =IF($B15="","",IFERROR(ROUND(SUMIFS(包装物料出入库明细!$N$4:$N$2003,包装物料出入库明细!$E$4:$E$2003,$B15,包装物料出入库明细!$H$4:$H$2003,"采购入库",包装物料出入库明细!$B$4:$B$2003,">="&$S$1,包装物料出入库明细!$B$4:$B$2003,"<="&$S$2)/SUMIFS(包装物料出入库明细!$I$4:$I$2003,包装物料出入库明细!$E$4:$E$2003,$B15,包装物料出入库明细!$H$4:$H$2003,"采购入库",包装物料出入库明细!$B$4:$B$2003,">="&$S$1,包装物料出入库明细!$B$4:$B$2003,"<="&$S$2),4),0)) | F15: =IF($B15="","",SUMIFS(包装物料出入库明细!$I$4:$I$2003,包装物料出入库明细!$E$4:$E$2003,$B15,包装物料出入库明细!$H$4:$H$2003,"期初库存",包装物料出入库明细!$B$4:$B$2003,">="&$S$1,包装物料出入库明细!$B$4:$B$2003,"<="&$S$2)) | G15: =IF($B15="","",SUMIFS(包装物料出入库明细!$I$4:$I$2003,包装物料出入库明细!$E$4:$E$2003,$B15,包装物料出入库明细!$H$4:$H$2003,"采购入库",包装物料出入库明细!$B$4:$B$2003,">="&$S$1,包装物料出入库明细!$B$4:$B$2003,"<="&$S$2)) | H15: =IF($B15="","",SUMIFS(包装物料出入库明细!$K$4:$K$2003,包装物料出入库明细!$E$4:$E$2003,$B15,包装物料出入库明细!$B$4:$B$2003,">="&$S$1,包装物料出入库明细!$B$4:$B$2003,"<="&$S$2)) | I15: =IF($B15="","",SUMIFS(包装物料出入库明细!$J$4:$J$2003,包装物料出入库明细!$E$4:$E$2003,$B15,包装物料出入库明细!$H$4:$H$2003,"领用出库",包装物料出入库明细!$B$4:$B$2003,">="&$S$1,包装物料出入库明细!$B$4:$B$2003,"<="&$S$2)) | J15: =IF($B15="","",SUMIFS(包装物料出入库明细!$J$4:$J$2003,包装物料出入库明细!$E$4:$E$2003,$B15,包装物料出入库明细!$H$4:$H$2003,"销售出库",包装物料出入库明细!$B$4:$B$2003,">="&$S$1,包装物料出入库明细!$B$4:$B$2003,"<="&$S$2)) | K15: =IF($B15="","",SUMIFS(包装物料出入库明细!$J$4:$J$2003,包装物料出入库明细!$E$4:$E$2003,$B15,包装物料出入库明细!$B$4:$B$2003,">="&$S$1,包装物料出入库明细!$B$4:$B$2003,"<="&$S$2)-$I15-$J15) | L15: =IF($B15="","",$F15+$G15+$H15-$I15-$J15-$K15) | M15: =IF($B15="","",ROUND($L15*$E15,2)) | N15: =IF($B15="","",IF($L15<=0,"无库存",IF($L15>=基础资料!$S$4,"充足",IF($L15>=基础资料!$S$5,"正常","不足"))))
... A53: =IF($B53="","",ROW()-3) | B53: =IFERROR(INDEX(_自动清单!$G$4:$G$63,ROW()-3),"") | C53: =IF($B53="","",IFERROR(IF(INDEX(基础资料!$O$4:$O$103,MATCH($B53,基础资料!$N$4:$N$103,0))="",IFERROR(INDEX(_自动清单!$H$4:$H$63,ROW()-3),""),INDEX(基础资料!$O$4:$O$103,MATCH($B53,基础资料!$N$4:$N$103,0))),IFERROR(INDEX(_自动清单!$H$4:$H$63,ROW()-3),""))) | D53: =IF($B53="","",IFERROR(IF(INDEX(基础资料!$P$4:$P$103,MATCH($B53,基础资料!$N$4:$N$103,0))="",IFERROR(INDEX(_自动清单!$I$4:$I$63,ROW()-3),""),INDEX(基础资料!$P$4:$P$103,MATCH($B53,基础资料!$N$4:$N$103,0))),IFERROR(INDEX(_自动清单!$I$4:$I$63,ROW()-3),""))) | E53: =IF($B53="","",IFERROR(ROUND(SUMIFS(包装物料出入库明细!$N$4:$N$2003,包装物料出入库明细!$E$4:$E$2003,$B53,包装物料出入库明细!$H$4:$H$2003,"采购入库",包装物料出入库明细!$B$4:$B$2003,">="&$S$1,包装物料出入库明细!$B$4:$B$2003,"<="&$S$2)/SUMIFS(包装物料出入库明细!$I$4:$I$2003,包装物料出入库明细!$E$4:$E$2003,$B53,包装物料出入库明细!$H$4:$H$2003,"采购入库",包装物料出入库明细!$B$4:$B$2003,">="&$S$1,包装物料出入库明细!$B$4:$B$2003,"<="&$S$2),4),0)) | F53: =IF($B53="","",SUMIFS(包装物料出入库明细!$I$4:$I$2003,包装物料出入库明细!$E$4:$E$2003,$B53,包装物料出入库明细!$H$4:$H$2003,"期初库存",包装物料出入库明细!$B$4:$B$2003,">="&$S$1,包装物料出入库明细!$B$4:$B$2003,"<="&$S$2)) | G53: =IF($B53="","",SUMIFS(包装物料出入库明细!$I$4:$I$2003,包装物料出入库明细!$E$4:$E$2003,$B53,包装物料出入库明细!$H$4:$H$2003,"采购入库",包装物料出入库明细!$B$4:$B$2003,">="&$S$1,包装物料出入库明细!$B$4:$B$2003,"<="&$S$2)) | H53: =IF($B53="","",SUMIFS(包装物料出入库明细!$K$4:$K$2003,包装物料出入库明细!$E$4:$E$2003,$B53,包装物料出入库明细!$B$4:$B$2003,">="&$S$1,包装物料出入库明细!$B$4:$B$2003,"<="&$S$2)) | I53: =IF($B53="","",SUMIFS(包装物料出入库明细!$J$4:$J$2003,包装物料出入库明细!$E$4:$E$2003,$B53,包装物料出入库明细!$H$4:$H$2003,"领用出库",包装物料出入库明细!$B$4:$B$2003,">="&$S$1,包装物料出入库明细!$B$4:$B$2003,"<="&$S$2)) | J53: =IF($B53="","",SUMIFS(包装物料出入库明细!$J$4:$J$2003,包装物料出入库明细!$E$4:$E$2003,$B53,包装物料出入库明细!$H$4:$H$2003,"销售出库",包装物料出入库明细!$B$4:$B$2003,">="&$S$1,包装物料出入库明细!$B$4:$B$2003,"<="&$S$2)) | K53: =IF($B53="","",SUMIFS(包装物料出入库明细!$J$4:$J$2003,包装物料出入库明细!$E$4:$E$2003,$B53,包装物料出入库明细!$B$4:$B$2003,">="&$S$1,包装物料出入库明细!$B$4:$B$2003,"<="&$S$2)-$I53-$J53) | L53: =IF($B53="","",$F53+$G53+$H53-$I53-$J53-$K53) | M53: =IF($B53="","",ROUND($L53*$E53,2)) | N53: =IF($B53="","",IF($L53<=0,"无库存",IF($L53>=基础资料!$S$4,"充足",IF($L53>=基础资料!$S$5,"正常","不足"))))
B54: 合计 | F54: =ROUND(SUM(F4:F53),2) -> 24973 | G54: =ROUND(SUM(G4:G53),2) -> 1104 | H54: =ROUND(SUM(H4:H53),2) -> -800 | I54: =ROUND(SUM(I4:I53),2) -> 1787 | J54: =ROUND(SUM(J4:J53),2) -> 0 | K54: =ROUND(SUM(K4:K53),2) -> 0 | L54: =ROUND(SUM(L4:L53),2) -> 23490 | M54: =ROUND(SUM(M4:M53),2) -> 4921

Sheet 筐子库存汇总
A1: 筐 子 / 托 盘 库 存 汇 总（公司自有筐子还剩多少 · 全自动） | Q1: =IF($K2="",DATE(1900,1,1),$K2) -> 1
A2: ★ 全自动：只统计公司自有筐子/托盘。「期初库存」是建账初始数，不受起止日期影响；其余各列按右边起止日期统计（留空＝不限时间）。筐子类型以「自备」开头的是客户自备筐，不计公司资产，请看【自备筐汇总】。 | J2: 开始日期 | L2: 结束日期 | Q2: =IF($M2="",DATE(2999,12,31),$M2) -> 401768
A3: 序号 | B3: 筐子 / 托盘类型 | C3: 期初库存 (不受日期限制） | D3: 采购入库 | E3: 客户退回入库（显示为负） | F3: 发出出库 | G3: 销售出库 | H3: 其他入库（调拨等） | I3: 公司在库结存 | J3: 客户未回库 (本册) | K3: 客户未回库 (01水果册·公司筐) | L3: 公司筐总量 | M3: 备注
A4: =IF($B4="","",ROW()-3) -> 1 | B4: =IFERROR(INDEX(_自动清单!$BQ$4:$BQ$63,ROW()-3),"") -> 公司一次性筐 | C4: =IF(OR($B4="",LEFT($B4,2)="自备"),"",SUMIFS(周转筐出入库明细!$H$4:$H$2004,周转筐出入库明细!$D$4:$D$2004,$B4,周转筐出入库明细!$F$4:$F$2004,"期初库存")) -> 69840 | D4: =IF(OR($B4="",LEFT($B4,2)="自备"),"",SUMIFS(周转筐出入库明细!$H$4:$H$2004,周转筐出入库明细!$D$4:$D$2004,$B4,周转筐出入库明细!$F$4:$F$2004,"采购入库",周转筐出入库明细!$B$4:$B$2004,">="&$Q$1,周转筐出入库明细!$B$4:$B$2004,"<="&$Q$2)) -> 0 | E4: =IF(OR($B4="",LEFT($B4,2)="自备"),"",SUMIFS(周转筐出入库明细!$I$4:$I$2004,周转筐出入库明细!$D$4:$D$2004,$B4,周转筐出入库明细!$B$4:$B$2004,">="&$Q$1,周转筐出入库明细!$B$4:$B$2004,"<="&$Q$2)) -> 1 | F4: =IF(OR($B4="",LEFT($B4,2)="自备"),"",SUMIFS(周转筐出入库明细!$J$4:$J$2004,周转筐出入库明细!$D$4:$D$2004,$B4,周转筐出入库明细!$B$4:$B$2004,">="&$Q$1,周转筐出入库明细!$B$4:$B$2004,"<="&$Q$2)) -> 5214 | G4: =IF(OR($B4="",LEFT($B4,2)="自备"),"",SUMIFS(周转筐出入库明细!$K$4:$K$2004,周转筐出入库明细!$D$4:$D$2004,$B4,周转筐出入库明细!$B$4:$B$2004,">="&$Q$1,周转筐出入库明细!$B$4:$B$2004,"<="&$Q$2)) -> 0 | H4: =IF(OR($B4="",LEFT($B4,2)="自备"),"",SUMIFS(周转筐出入库明细!$H$4:$H$2004,周转筐出入库明细!$D$4:$D$2004,$B4,周转筐出入库明细!$B$4:$B$2004,">="&$Q$1,周转筐出入库明细!$B$4:$B$2004,"<="&$Q$2)-SUMIFS(周转筐出入库明细!$H$4:$H$2004,周转筐出入库明细!$D$4:$D$2004,$B4,周转筐出入库明细!$F$4:$F$2004,"采购入库",周转筐出入库明细!$B$4:$B$2004,">="&$Q$1,周转筐出入库明细!$B$4:$B$2004,"<="&$Q$2)) -> 0 | I4: =IF(OR($B4="",LEFT($B4,2)="自备"),"",N($C4)+N($D4)+N($E4)-N($F4)-N($G4)+N($H4)) -> 64627 | J4: =IF(OR($B4="",LEFT($B4,2)="自备"),"",N($F4)-N($E4)) -> 5213 | K4: =IF(OR($B4="",LEFT($B4,2)="自备"),"",SUMIFS(对接源_01水果筐数!$E$5:$E$304,对接源_01水果筐数!$C$5:$C$304,$B4)+SUMIFS(对接源_01水果筐数!$F$5:$F$304,对接源_01水果筐数!$C$5:$C$304,$B4)-SUMIFS(对接源_01水果筐数!$D$5:$D$304,对接源_01水果筐数!$C$5:$C$304,$B4)) -> -1619 | L4: =IF(OR($B4="",LEFT($B4,2)="自备"),"",N($I4)+N($J4)+N($K4)) -> 68221 | M4: =IF($B4="","",IF(LEFT($B4,2)="自备","客户自备筐，不计公司资产，见【自备筐汇总】",""))
A5: =IF($B5="","",ROW()-3) -> 2 | B5: =IFERROR(INDEX(_自动清单!$BQ$4:$BQ$63,ROW()-3),"") -> 公司杂周转筐 | C5: =IF(OR($B5="",LEFT($B5,2)="自备"),"",SUMIFS(周转筐出入库明细!$H$4:$H$2004,周转筐出入库明细!$D$4:$D$2004,$B5,周转筐出入库明细!$F$4:$F$2004,"期初库存")) -> 35928 | D5: =IF(OR($B5="",LEFT($B5,2)="自备"),"",SUMIFS(周转筐出入库明细!$H$4:$H$2004,周转筐出入库明细!$D$4:$D$2004,$B5,周转筐出入库明细!$F$4:$F$2004,"采购入库",周转筐出入库明细!$B$4:$B$2004,">="&$Q$1,周转筐出入库明细!$B$4:$B$2004,"<="&$Q$2)) -> 0 | E5: =IF(OR($B5="",LEFT($B5,2)="自备"),"",SUMIFS(周转筐出入库明细!$I$4:$I$2004,周转筐出入库明细!$D$4:$D$2004,$B5,周转筐出入库明细!$B$4:$B$2004,">="&$Q$1,周转筐出入库明细!$B$4:$B$2004,"<="&$Q$2)) -> 81 | F5: =IF(OR($B5="",LEFT($B5,2)="自备"),"",SUMIFS(周转筐出入库明细!$J$4:$J$2004,周转筐出入库明细!$D$4:$D$2004,$B5,周转筐出入库明细!$B$4:$B$2004,">="&$Q$1,周转筐出入库明细!$B$4:$B$2004,"<="&$Q$2)) -> 6607 | G5: =IF(OR($B5="",LEFT($B5,2)="自备"),"",SUMIFS(周转筐出入库明细!$K$4:$K$2004,周转筐出入库明细!$D$4:$D$2004,$B5,周转筐出入库明细!$B$4:$B$2004,">="&$Q$1,周转筐出入库明细!$B$4:$B$2004,"<="&$Q$2)) -> 0 | H5: =IF(OR($B5="",LEFT($B5,2)="自备"),"",SUMIFS(周转筐出入库明细!$H$4:$H$2004,周转筐出入库明细!$D$4:$D$2004,$B5,周转筐出入库明细!$B$4:$B$2004,">="&$Q$1,周转筐出入库明细!$B$4:$B$2004,"<="&$Q$2)-SUMIFS(周转筐出入库明细!$H$4:$H$2004,周转筐出入库明细!$D$4:$D$2004,$B5,周转筐出入库明细!$F$4:$F$2004,"采购入库",周转筐出入库明细!$B$4:$B$2004,">="&$Q$1,周转筐出入库明细!$B$4:$B$2004,"<="&$Q$2)) -> 0 | I5: =IF(OR($B5="",LEFT($B5,2)="自备"),"",N($C5)+N($D5)+N($E5)-N($F5)-N($G5)+N($H5)) -> 29402 | J5: =IF(OR($B5="",LEFT($B5,2)="自备"),"",N($F5)-N($E5)) -> 6526 | K5: =IF(OR($B5="",LEFT($B5,2)="自备"),"",SUMIFS(对接源_01水果筐数!$E$5:$E$304,对接源_01水果筐数!$C$5:$C$304,$B5)+SUMIFS(对接源_01水果筐数!$F$5:$F$304,对接源_01水果筐数!$C$5:$C$304,$B5)-SUMIFS(对接源_01水果筐数!$D$5:$D$304,对接源_01水果筐数!$C$5:$C$304,$B5)) -> -3565 | L5: =IF(OR($B5="",LEFT($B5,2)="自备"),"",N($I5)+N($J5)+N($K5)) -> 32363 | M5: =IF($B5="","",IF(LEFT($B5,2)="自备","客户自备筐，不计公司资产，见【自备筐汇总】",""))
A6: =IF($B6="","",ROW()-3) -> 3 | B6: =IFERROR(INDEX(_自动清单!$BQ$4:$BQ$63,ROW()-3),"") -> 公司新周转筐 | C6: =IF(OR($B6="",LEFT($B6,2)="自备"),"",SUMIFS(周转筐出入库明细!$H$4:$H$2004,周转筐出入库明细!$D$4:$D$2004,$B6,周转筐出入库明细!$F$4:$F$2004,"期初库存")) -> 58032 | D6: =IF(OR($B6="",LEFT($B6,2)="自备"),"",SUMIFS(周转筐出入库明细!$H$4:$H$2004,周转筐出入库明细!$D$4:$D$2004,$B6,周转筐出入库明细!$F$4:$F$2004,"采购入库",周转筐出入库明细!$B$4:$B$2004,">="&$Q$1,周转筐出入库明细!$B$4:$B$2004,"<="&$Q$2)) -> 0 | E6: =IF(OR($B6="",LEFT($B6,2)="自备"),"",SUMIFS(周转筐出入库明细!$I$4:$I$2004,周转筐出入库明细!$D$4:$D$2004,$B6,周转筐出入库明细!$B$4:$B$2004,">="&$Q$1,周转筐出入库明细!$B$4:$B$2004,"<="&$Q$2)) -> 0 | F6: =IF(OR($B6="",LEFT($B6,2)="自备"),"",SUMIFS(周转筐出入库明细!$J$4:$J$2004,周转筐出入库明细!$D$4:$D$2004,$B6,周转筐出入库明细!$B$4:$B$2004,">="&$Q$1,周转筐出入库明细!$B$4:$B$2004,"<="&$Q$2)) -> 1011 | G6: =IF(OR($B6="",LEFT($B6,2)="自备"),"",SUMIFS(周转筐出入库明细!$K$4:$K$2004,周转筐出入库明细!$D$4:$D$2004,$B6,周转筐出入库明细!$B$4:$B$2004,">="&$Q$1,周转筐出入库明细!$B$4:$B$2004,"<="&$Q$2)) -> 0 | H6: =IF(OR($B6="",LEFT($B6,2)="自备"),"",SUMIFS(周转筐出入库明细!$H$4:$H$2004,周转筐出入库明细!$D$4:$D$2004,$B6,周转筐出入库明细!$B$4:$B$2004,">="&$Q$1,周转筐出入库明细!$B$4:$B$2004,"<="&$Q$2)-SUMIFS(周转筐出入库明细!$H$4:$H$2004,周转筐出入库明细!$D$4:$D$2004,$B6,周转筐出入库明细!$F$4:$F$2004,"采购入库",周转筐出入库明细!$B$4:$B$2004,">="&$Q$1,周转筐出入库明细!$B$4:$B$2004,"<="&$Q$2)) -> 0 | I6: =IF(OR($B6="",LEFT($B6,2)="自备"),"",N($C6)+N($D6)+N($E6)-N($F6)-N($G6)+N($H6)) -> 57021 | J6: =IF(OR($B6="",LEFT($B6,2)="自备"),"",N($F6)-N($E6)) -> 1011 | K6: =IF(OR($B6="",LEFT($B6,2)="自备"),"",SUMIFS(对接源_01水果筐数!$E$5:$E$304,对接源_01水果筐数!$C$5:$C$304,$B6)+SUMIFS(对接源_01水果筐数!$F$5:$F$304,对接源_01水果筐数!$C$5:$C$304,$B6)-SUMIFS(对接源_01水果筐数!$D$5:$D$304,对接源_01水果筐数!$C$5:$C$304,$B6)) -> -74 | L6: =IF(OR($B6="",LEFT($B6,2)="自备"),"",N($I6)+N($J6)+N($K6)) -> 57958 | M6: =IF($B6="","",IF(LEFT($B6,2)="自备","客户自备筐，不计公司资产，见【自备筐汇总】",""))
A7: =IF($B7="","",ROW()-3) -> 4 | B7: =IFERROR(INDEX(_自动清单!$BQ$4:$BQ$63,ROW()-3),"") -> 公司白周转筐 | C7: =IF(OR($B7="",LEFT($B7,2)="自备"),"",SUMIFS(周转筐出入库明细!$H$4:$H$2004,周转筐出入库明细!$D$4:$D$2004,$B7,周转筐出入库明细!$F$4:$F$2004,"期初库存")) -> 13968 | D7: =IF(OR($B7="",LEFT($B7,2)="自备"),"",SUMIFS(周转筐出入库明细!$H$4:$H$2004,周转筐出入库明细!$D$4:$D$2004,$B7,周转筐出入库明细!$F$4:$F$2004,"采购入库",周转筐出入库明细!$B$4:$B$2004,">="&$Q$1,周转筐出入库明细!$B$4:$B$2004,"<="&$Q$2)) -> 0 | E7: =IF(OR($B7="",LEFT($B7,2)="自备"),"",SUMIFS(周转筐出入库明细!$I$4:$I$2004,周转筐出入库明细!$D$4:$D$2004,$B7,周转筐出入库明细!$B$4:$B$2004,">="&$Q$1,周转筐出入库明细!$B$4:$B$2004,"<="&$Q$2)) -> 0 | F7: =IF(OR($B7="",LEFT($B7,2)="自备"),"",SUMIFS(周转筐出入库明细!$J$4:$J$2004,周转筐出入库明细!$D$4:$D$2004,$B7,周转筐出入库明细!$B$4:$B$2004,">="&$Q$1,周转筐出入库明细!$B$4:$B$2004,"<="&$Q$2)) -> 0 | G7: =IF(OR($B7="",LEFT($B7,2)="自备"),"",SUMIFS(周转筐出入库明细!$K$4:$K$2004,周转筐出入库明细!$D$4:$D$2004,$B7,周转筐出入库明细!$B$4:$B$2004,">="&$Q$1,周转筐出入库明细!$B$4:$B$2004,"<="&$Q$2)) -> 0 | H7: =IF(OR($B7="",LEFT($B7,2)="自备"),"",SUMIFS(周转筐出入库明细!$H$4:$H$2004,周转筐出入库明细!$D$4:$D$2004,$B7,周转筐出入库明细!$B$4:$B$2004,">="&$Q$1,周转筐出入库明细!$B$4:$B$2004,"<="&$Q$2)-SUMIFS(周转筐出入库明细!$H$4:$H$2004,周转筐出入库明细!$D$4:$D$2004,$B7,周转筐出入库明细!$F$4:$F$2004,"采购入库",周转筐出入库明细!$B$4:$B$2004,">="&$Q$1,周转筐出入库明细!$B$4:$B$2004,"<="&$Q$2)) -> 0 | I7: =IF(OR($B7="",LEFT($B7,2)="自备"),"",N($C7)+N($D7)+N($E7)-N($F7)-N($G7)+N($H7)) -> 13968 | J7: =IF(OR($B7="",LEFT($B7,2)="自备"),"",N($F7)-N($E7)) -> 0 | K7: =IF(OR($B7="",LEFT($B7,2)="自备"),"",SUMIFS(对接源_01水果筐数!$E$5:$E$304,对接源_01水果筐数!$C$5:$C$304,$B7)+SUMIFS(对接源_01水果筐数!$F$5:$F$304,对接源_01水果筐数!$C$5:$C$304,$B7)-SUMIFS(对接源_01水果筐数!$D$5:$D$304,对接源_01水果筐数!$C$5:$C$304,$B7)) -> 0 | L7: =IF(OR($B7="",LEFT($B7,2)="自备"),"",N($I7)+N($J7)+N($K7)) -> 13968 | M7: =IF($B7="","",IF(LEFT($B7,2)="自备","客户自备筐，不计公司资产，见【自备筐汇总】",""))
A8: =IF($B8="","",ROW()-3) -> 5 | B8: =IFERROR(INDEX(_自动清单!$BQ$4:$BQ$63,ROW()-3),"") -> 公司红周转筐 | C8: =IF(OR($B8="",LEFT($B8,2)="自备"),"",SUMIFS(周转筐出入库明细!$H$4:$H$2004,周转筐出入库明细!$D$4:$D$2004,$B8,周转筐出入库明细!$F$4:$F$2004,"期初库存")) -> 0 | D8: =IF(OR($B8="",LEFT($B8,2)="自备"),"",SUMIFS(周转筐出入库明细!$H$4:$H$2004,周转筐出入库明细!$D$4:$D$2004,$B8,周转筐出入库明细!$F$4:$F$2004,"采购入库",周转筐出入库明细!$B$4:$B$2004,">="&$Q$1,周转筐出入库明细!$B$4:$B$2004,"<="&$Q$2)) -> 17472 | E8: =IF(OR($B8="",LEFT($B8,2)="自备"),"",SUMIFS(周转筐出入库明细!$I$4:$I$2004,周转筐出入库明细!$D$4:$D$2004,$B8,周转筐出入库明细!$B$4:$B$2004,">="&$Q$1,周转筐出入库明细!$B$4:$B$2004,"<="&$Q$2)) -> 0 | F8: =IF(OR($B8="",LEFT($B8,2)="自备"),"",SUMIFS(周转筐出入库明细!$J$4:$J$2004,周转筐出入库明细!$D$4:$D$2004,$B8,周转筐出入库明细!$B$4:$B$2004,">="&$Q$1,周转筐出入库明细!$B$4:$B$2004,"<="&$Q$2)) -> 16512 | G8: =IF(OR($B8="",LEFT($B8,2)="自备"),"",SUMIFS(周转筐出入库明细!$K$4:$K$2004,周转筐出入库明细!$D$4:$D$2004,$B8,周转筐出入库明细!$B$4:$B$2004,">="&$Q$1,周转筐出入库明细!$B$4:$B$2004,"<="&$Q$2)) -> 960 | H8: =IF(OR($B8="",LEFT($B8,2)="自备"),"",SUMIFS(周转筐出入库明细!$H$4:$H$2004,周转筐出入库明细!$D$4:$D$2004,$B8,周转筐出入库明细!$B$4:$B$2004,">="&$Q$1,周转筐出入库明细!$B$4:$B$2004,"<="&$Q$2)-SUMIFS(周转筐出入库明细!$H$4:$H$2004,周转筐出入库明细!$D$4:$D$2004,$B8,周转筐出入库明细!$F$4:$F$2004,"采购入库",周转筐出入库明细!$B$4:$B$2004,">="&$Q$1,周转筐出入库明细!$B$4:$B$2004,"<="&$Q$2)) -> 0 | I8: =IF(OR($B8="",LEFT($B8,2)="自备"),"",N($C8)+N($D8)+N($E8)-N($F8)-N($G8)+N($H8)) -> 0 | J8: =IF(OR($B8="",LEFT($B8,2)="自备"),"",N($F8)-N($E8)) -> 16512 | K8: =IF(OR($B8="",LEFT($B8,2)="自备"),"",SUMIFS(对接源_01水果筐数!$E$5:$E$304,对接源_01水果筐数!$C$5:$C$304,$B8)+SUMIFS(对接源_01水果筐数!$F$5:$F$304,对接源_01水果筐数!$C$5:$C$304,$B8)-SUMIFS(对接源_01水果筐数!$D$5:$D$304,对接源_01水果筐数!$C$5:$C$304,$B8)) -> -8796 | L8: =IF(OR($B8="",LEFT($B8,2)="自备"),"",N($I8)+N($J8)+N($K8)) -> 7716 | M8: =IF($B8="","",IF(LEFT($B8,2)="自备","客户自备筐，不计公司资产，见【自备筐汇总】",""))
A9: =IF($B9="","",ROW()-3) -> 6 | B9: =IFERROR(INDEX(_自动清单!$BQ$4:$BQ$63,ROW()-3),"") -> 自备一次性筐 | C9: =IF(OR($B9="",LEFT($B9,2)="自备"),"",SUMIFS(周转筐出入库明细!$H$4:$H$2004,周转筐出入库明细!$D$4:$D$2004,$B9,周转筐出入库明细!$F$4:$F$2004,"期初库存")) | D9: =IF(OR($B9="",LEFT($B9,2)="自备"),"",SUMIFS(周转筐出入库明细!$H$4:$H$2004,周转筐出入库明细!$D$4:$D$2004,$B9,周转筐出入库明细!$F$4:$F$2004,"采购入库",周转筐出入库明细!$B$4:$B$2004,">="&$Q$1,周转筐出入库明细!$B$4:$B$2004,"<="&$Q$2)) | E9: =IF(OR($B9="",LEFT($B9,2)="自备"),"",SUMIFS(周转筐出入库明细!$I$4:$I$2004,周转筐出入库明细!$D$4:$D$2004,$B9,周转筐出入库明细!$B$4:$B$2004,">="&$Q$1,周转筐出入库明细!$B$4:$B$2004,"<="&$Q$2)) | F9: =IF(OR($B9="",LEFT($B9,2)="自备"),"",SUMIFS(周转筐出入库明细!$J$4:$J$2004,周转筐出入库明细!$D$4:$D$2004,$B9,周转筐出入库明细!$B$4:$B$2004,">="&$Q$1,周转筐出入库明细!$B$4:$B$2004,"<="&$Q$2)) | G9: =IF(OR($B9="",LEFT($B9,2)="自备"),"",SUMIFS(周转筐出入库明细!$K$4:$K$2004,周转筐出入库明细!$D$4:$D$2004,$B9,周转筐出入库明细!$B$4:$B$2004,">="&$Q$1,周转筐出入库明细!$B$4:$B$2004,"<="&$Q$2)) | H9: =IF(OR($B9="",LEFT($B9,2)="自备"),"",SUMIFS(周转筐出入库明细!$H$4:$H$2004,周转筐出入库明细!$D$4:$D$2004,$B9,周转筐出入库明细!$B$4:$B$2004,">="&$Q$1,周转筐出入库明细!$B$4:$B$2004,"<="&$Q$2)-SUMIFS(周转筐出入库明细!$H$4:$H$2004,周转筐出入库明细!$D$4:$D$2004,$B9,周转筐出入库明细!$F$4:$F$2004,"采购入库",周转筐出入库明细!$B$4:$B$2004,">="&$Q$1,周转筐出入库明细!$B$4:$B$2004,"<="&$Q$2)) | I9: =IF(OR($B9="",LEFT($B9,2)="自备"),"",N($C9)+N($D9)+N($E9)-N($F9)-N($G9)+N($H9)) | J9: =IF(OR($B9="",LEFT($B9,2)="自备"),"",N($F9)-N($E9)) | K9: =IF(OR($B9="",LEFT($B9,2)="自备"),"",SUMIFS(对接源_01水果筐数!$E$5:$E$304,对接源_01水果筐数!$C$5:$C$304,$B9)+SUMIFS(对接源_01水果筐数!$F$5:$F$304,对接源_01水果筐数!$C$5:$C$304,$B9)-SUMIFS(对接源_01水果筐数!$D$5:$D$304,对接源_01水果筐数!$C$5:$C$304,$B9)) | L9: =IF(OR($B9="",LEFT($B9,2)="自备"),"",N($I9)+N($J9)+N($K9)) | M9: =IF($B9="","",IF(LEFT($B9,2)="自备","客户自备筐，不计公司资产，见【自备筐汇总】","")) -> 客户自备筐，不计公司资产，见【自备筐汇总】
A10: =IF($B10="","",ROW()-3) -> 7 | B10: =IFERROR(INDEX(_自动清单!$BQ$4:$BQ$63,ROW()-3),"") -> 自备杂周转筐 | C10: =IF(OR($B10="",LEFT($B10,2)="自备"),"",SUMIFS(周转筐出入库明细!$H$4:$H$2004,周转筐出入库明细!$D$4:$D$2004,$B10,周转筐出入库明细!$F$4:$F$2004,"期初库存")) | D10: =IF(OR($B10="",LEFT($B10,2)="自备"),"",SUMIFS(周转筐出入库明细!$H$4:$H$2004,周转筐出入库明细!$D$4:$D$2004,$B10,周转筐出入库明细!$F$4:$F$2004,"采购入库",周转筐出入库明细!$B$4:$B$2004,">="&$Q$1,周转筐出入库明细!$B$4:$B$2004,"<="&$Q$2)) | E10: =IF(OR($B10="",LEFT($B10,2)="自备"),"",SUMIFS(周转筐出入库明细!$I$4:$I$2004,周转筐出入库明细!$D$4:$D$2004,$B10,周转筐出入库明细!$B$4:$B$2004,">="&$Q$1,周转筐出入库明细!$B$4:$B$2004,"<="&$Q$2)) | F10: =IF(OR($B10="",LEFT($B10,2)="自备"),"",SUMIFS(周转筐出入库明细!$J$4:$J$2004,周转筐出入库明细!$D$4:$D$2004,$B10,周转筐出入库明细!$B$4:$B$2004,">="&$Q$1,周转筐出入库明细!$B$4:$B$2004,"<="&$Q$2)) | G10: =IF(OR($B10="",LEFT($B10,2)="自备"),"",SUMIFS(周转筐出入库明细!$K$4:$K$2004,周转筐出入库明细!$D$4:$D$2004,$B10,周转筐出入库明细!$B$4:$B$2004,">="&$Q$1,周转筐出入库明细!$B$4:$B$2004,"<="&$Q$2)) | H10: =IF(OR($B10="",LEFT($B10,2)="自备"),"",SUMIFS(周转筐出入库明细!$H$4:$H$2004,周转筐出入库明细!$D$4:$D$2004,$B10,周转筐出入库明细!$B$4:$B$2004,">="&$Q$1,周转筐出入库明细!$B$4:$B$2004,"<="&$Q$2)-SUMIFS(周转筐出入库明细!$H$4:$H$2004,周转筐出入库明细!$D$4:$D$2004,$B10,周转筐出入库明细!$F$4:$F$2004,"采购入库",周转筐出入库明细!$B$4:$B$2004,">="&$Q$1,周转筐出入库明细!$B$4:$B$2004,"<="&$Q$2)) | I10: =IF(OR($B10="",LEFT($B10,2)="自备"),"",N($C10)+N($D10)+N($E10)-N($F10)-N($G10)+N($H10)) | J10: =IF(OR($B10="",LEFT($B10,2)="自备"),"",N($F10)-N($E10)) | K10: =IF(OR($B10="",LEFT($B10,2)="自备"),"",SUMIFS(对接源_01水果筐数!$E$5:$E$304,对接源_01水果筐数!$C$5:$C$304,$B10)+SUMIFS(对接源_01水果筐数!$F$5:$F$304,对接源_01水果筐数!$C$5:$C$304,$B10)-SUMIFS(对接源_01水果筐数!$D$5:$D$304,对接源_01水果筐数!$C$5:$C$304,$B10)) | L10: =IF(OR($B10="",LEFT($B10,2)="自备"),"",N($I10)+N($J10)+N($K10)) | M10: =IF($B10="","",IF(LEFT($B10,2)="自备","客户自备筐，不计公司资产，见【自备筐汇总】","")) -> 客户自备筐，不计公司资产，见【自备筐汇总】
A11: =IF($B11="","",ROW()-3) -> 8 | B11: =IFERROR(INDEX(_自动清单!$BQ$4:$BQ$63,ROW()-3),"") -> 纸箱 | C11: =IF(OR($B11="",LEFT($B11,2)="自备"),"",SUMIFS(周转筐出入库明细!$H$4:$H$2004,周转筐出入库明细!$D$4:$D$2004,$B11,周转筐出入库明细!$F$4:$F$2004,"期初库存")) -> 0 | D11: =IF(OR($B11="",LEFT($B11,2)="自备"),"",SUMIFS(周转筐出入库明细!$H$4:$H$2004,周转筐出入库明细!$D$4:$D$2004,$B11,周转筐出入库明细!$F$4:$F$2004,"采购入库",周转筐出入库明细!$B$4:$B$2004,">="&$Q$1,周转筐出入库明细!$B$4:$B$2004,"<="&$Q$2)) -> 0 | E11: =IF(OR($B11="",LEFT($B11,2)="自备"),"",SUMIFS(周转筐出入库明细!$I$4:$I$2004,周转筐出入库明细!$D$4:$D$2004,$B11,周转筐出入库明细!$B$4:$B$2004,">="&$Q$1,周转筐出入库明细!$B$4:$B$2004,"<="&$Q$2)) -> 0 | F11: =IF(OR($B11="",LEFT($B11,2)="自备"),"",SUMIFS(周转筐出入库明细!$J$4:$J$2004,周转筐出入库明细!$D$4:$D$2004,$B11,周转筐出入库明细!$B$4:$B$2004,">="&$Q$1,周转筐出入库明细!$B$4:$B$2004,"<="&$Q$2)) -> 0 | G11: =IF(OR($B11="",LEFT($B11,2)="自备"),"",SUMIFS(周转筐出入库明细!$K$4:$K$2004,周转筐出入库明细!$D$4:$D$2004,$B11,周转筐出入库明细!$B$4:$B$2004,">="&$Q$1,周转筐出入库明细!$B$4:$B$2004,"<="&$Q$2)) -> 0 | H11: =IF(OR($B11="",LEFT($B11,2)="自备"),"",SUMIFS(周转筐出入库明细!$H$4:$H$2004,周转筐出入库明细!$D$4:$D$2004,$B11,周转筐出入库明细!$B$4:$B$2004,">="&$Q$1,周转筐出入库明细!$B$4:$B$2004,"<="&$Q$2)-SUMIFS(周转筐出入库明细!$H$4:$H$2004,周转筐出入库明细!$D$4:$D$2004,$B11,周转筐出入库明细!$F$4:$F$2004,"采购入库",周转筐出入库明细!$B$4:$B$2004,">="&$Q$1,周转筐出入库明细!$B$4:$B$2004,"<="&$Q$2)) -> 0 | I11: =IF(OR($B11="",LEFT($B11,2)="自备"),"",N($C11)+N($D11)+N($E11)-N($F11)-N($G11)+N($H11)) -> 0 | J11: =IF(OR($B11="",LEFT($B11,2)="自备"),"",N($F11)-N($E11)) -> 0 | K11: =IF(OR($B11="",LEFT($B11,2)="自备"),"",SUMIFS(对接源_01水果筐数!$E$5:$E$304,对接源_01水果筐数!$C$5:$C$304,$B11)+SUMIFS(对接源_01水果筐数!$F$5:$F$304,对接源_01水果筐数!$C$5:$C$304,$B11)-SUMIFS(对接源_01水果筐数!$D$5:$D$304,对接源_01水果筐数!$C$5:$C$304,$B11)) -> 0 | L11: =IF(OR($B11="",LEFT($B11,2)="自备"),"",N($I11)+N($J11)+N($K11)) -> 0 | M11: =IF($B11="","",IF(LEFT($B11,2)="自备","客户自备筐，不计公司资产，见【自备筐汇总】",""))
A12: =IF($B12="","",ROW()-3) | B12: =IFERROR(INDEX(_自动清单!$BQ$4:$BQ$63,ROW()-3),"") | C12: =IF(OR($B12="",LEFT($B12,2)="自备"),"",SUMIFS(周转筐出入库明细!$H$4:$H$2004,周转筐出入库明细!$D$4:$D$2004,$B12,周转筐出入库明细!$F$4:$F$2004,"期初库存")) | D12: =IF(OR($B12="",LEFT($B12,2)="自备"),"",SUMIFS(周转筐出入库明细!$H$4:$H$2004,周转筐出入库明细!$D$4:$D$2004,$B12,周转筐出入库明细!$F$4:$F$2004,"采购入库",周转筐出入库明细!$B$4:$B$2004,">="&$Q$1,周转筐出入库明细!$B$4:$B$2004,"<="&$Q$2)) | E12: =IF(OR($B12="",LEFT($B12,2)="自备"),"",SUMIFS(周转筐出入库明细!$I$4:$I$2004,周转筐出入库明细!$D$4:$D$2004,$B12,周转筐出入库明细!$B$4:$B$2004,">="&$Q$1,周转筐出入库明细!$B$4:$B$2004,"<="&$Q$2)) | F12: =IF(OR($B12="",LEFT($B12,2)="自备"),"",SUMIFS(周转筐出入库明细!$J$4:$J$2004,周转筐出入库明细!$D$4:$D$2004,$B12,周转筐出入库明细!$B$4:$B$2004,">="&$Q$1,周转筐出入库明细!$B$4:$B$2004,"<="&$Q$2)) | G12: =IF(OR($B12="",LEFT($B12,2)="自备"),"",SUMIFS(周转筐出入库明细!$K$4:$K$2004,周转筐出入库明细!$D$4:$D$2004,$B12,周转筐出入库明细!$B$4:$B$2004,">="&$Q$1,周转筐出入库明细!$B$4:$B$2004,"<="&$Q$2)) | H12: =IF(OR($B12="",LEFT($B12,2)="自备"),"",SUMIFS(周转筐出入库明细!$H$4:$H$2004,周转筐出入库明细!$D$4:$D$2004,$B12,周转筐出入库明细!$B$4:$B$2004,">="&$Q$1,周转筐出入库明细!$B$4:$B$2004,"<="&$Q$2)-SUMIFS(周转筐出入库明细!$H$4:$H$2004,周转筐出入库明细!$D$4:$D$2004,$B12,周转筐出入库明细!$F$4:$F$2004,"采购入库",周转筐出入库明细!$B$4:$B$2004,">="&$Q$1,周转筐出入库明细!$B$4:$B$2004,"<="&$Q$2)) | I12: =IF(OR($B12="",LEFT($B12,2)="自备"),"",N($C12)+N($D12)+N($E12)-N($F12)-N($G12)+N($H12)) | J12: =IF(OR($B12="",LEFT($B12,2)="自备"),"",N($F12)-N($E12)) | K12: =IF(OR($B12="",LEFT($B12,2)="自备"),"",SUMIFS(对接源_01水果筐数!$E$5:$E$304,对接源_01水果筐数!$C$5:$C$304,$B12)+SUMIFS(对接源_01水果筐数!$F$5:$F$304,对接源_01水果筐数!$C$5:$C$304,$B12)-SUMIFS(对接源_01水果筐数!$D$5:$D$304,对接源_01水果筐数!$C$5:$C$304,$B12)) | L12: =IF(OR($B12="",LEFT($B12,2)="自备"),"",N($I12)+N($J12)+N($K12)) | M12: =IF($B12="","",IF(LEFT($B12,2)="自备","客户自备筐，不计公司资产，见【自备筐汇总】",""))
A13: =IF($B13="","",ROW()-3) | B13: =IFERROR(INDEX(_自动清单!$BQ$4:$BQ$63,ROW()-3),"") | C13: =IF(OR($B13="",LEFT($B13,2)="自备"),"",SUMIFS(周转筐出入库明细!$H$4:$H$2004,周转筐出入库明细!$D$4:$D$2004,$B13,周转筐出入库明细!$F$4:$F$2004,"期初库存")) | D13: =IF(OR($B13="",LEFT($B13,2)="自备"),"",SUMIFS(周转筐出入库明细!$H$4:$H$2004,周转筐出入库明细!$D$4:$D$2004,$B13,周转筐出入库明细!$F$4:$F$2004,"采购入库",周转筐出入库明细!$B$4:$B$2004,">="&$Q$1,周转筐出入库明细!$B$4:$B$2004,"<="&$Q$2)) | E13: =IF(OR($B13="",LEFT($B13,2)="自备"),"",SUMIFS(周转筐出入库明细!$I$4:$I$2004,周转筐出入库明细!$D$4:$D$2004,$B13,周转筐出入库明细!$B$4:$B$2004,">="&$Q$1,周转筐出入库明细!$B$4:$B$2004,"<="&$Q$2)) | F13: =IF(OR($B13="",LEFT($B13,2)="自备"),"",SUMIFS(周转筐出入库明细!$J$4:$J$2004,周转筐出入库明细!$D$4:$D$2004,$B13,周转筐出入库明细!$B$4:$B$2004,">="&$Q$1,周转筐出入库明细!$B$4:$B$2004,"<="&$Q$2)) | G13: =IF(OR($B13="",LEFT($B13,2)="自备"),"",SUMIFS(周转筐出入库明细!$K$4:$K$2004,周转筐出入库明细!$D$4:$D$2004,$B13,周转筐出入库明细!$B$4:$B$2004,">="&$Q$1,周转筐出入库明细!$B$4:$B$2004,"<="&$Q$2)) | H13: =IF(OR($B13="",LEFT($B13,2)="自备"),"",SUMIFS(周转筐出入库明细!$H$4:$H$2004,周转筐出入库明细!$D$4:$D$2004,$B13,周转筐出入库明细!$B$4:$B$2004,">="&$Q$1,周转筐出入库明细!$B$4:$B$2004,"<="&$Q$2)-SUMIFS(周转筐出入库明细!$H$4:$H$2004,周转筐出入库明细!$D$4:$D$2004,$B13,周转筐出入库明细!$F$4:$F$2004,"采购入库",周转筐出入库明细!$B$4:$B$2004,">="&$Q$1,周转筐出入库明细!$B$4:$B$2004,"<="&$Q$2)) | I13: =IF(OR($B13="",LEFT($B13,2)="自备"),"",N($C13)+N($D13)+N($E13)-N($F13)-N($G13)+N($H13)) | J13: =IF(OR($B13="",LEFT($B13,2)="自备"),"",N($F13)-N($E13)) | K13: =IF(OR($B13="",LEFT($B13,2)="自备"),"",SUMIFS(对接源_01水果筐数!$E$5:$E$304,对接源_01水果筐数!$C$5:$C$304,$B13)+SUMIFS(对接源_01水果筐数!$F$5:$F$304,对接源_01水果筐数!$C$5:$C$304,$B13)-SUMIFS(对接源_01水果筐数!$D$5:$D$304,对接源_01水果筐数!$C$5:$C$304,$B13)) | L13: =IF(OR($B13="",LEFT($B13,2)="自备"),"",N($I13)+N($J13)+N($K13)) | M13: =IF($B13="","",IF(LEFT($B13,2)="自备","客户自备筐，不计公司资产，见【自备筐汇总】",""))
A14: =IF($B14="","",ROW()-3) | B14: =IFERROR(INDEX(_自动清单!$BQ$4:$BQ$63,ROW()-3),"") | C14: =IF(OR($B14="",LEFT($B14,2)="自备"),"",SUMIFS(周转筐出入库明细!$H$4:$H$2004,周转筐出入库明细!$D$4:$D$2004,$B14,周转筐出入库明细!$F$4:$F$2004,"期初库存")) | D14: =IF(OR($B14="",LEFT($B14,2)="自备"),"",SUMIFS(周转筐出入库明细!$H$4:$H$2004,周转筐出入库明细!$D$4:$D$2004,$B14,周转筐出入库明细!$F$4:$F$2004,"采购入库",周转筐出入库明细!$B$4:$B$2004,">="&$Q$1,周转筐出入库明细!$B$4:$B$2004,"<="&$Q$2)) | E14: =IF(OR($B14="",LEFT($B14,2)="自备"),"",SUMIFS(周转筐出入库明细!$I$4:$I$2004,周转筐出入库明细!$D$4:$D$2004,$B14,周转筐出入库明细!$B$4:$B$2004,">="&$Q$1,周转筐出入库明细!$B$4:$B$2004,"<="&$Q$2)) | F14: =IF(OR($B14="",LEFT($B14,2)="自备"),"",SUMIFS(周转筐出入库明细!$J$4:$J$2004,周转筐出入库明细!$D$4:$D$2004,$B14,周转筐出入库明细!$B$4:$B$2004,">="&$Q$1,周转筐出入库明细!$B$4:$B$2004,"<="&$Q$2)) | G14: =IF(OR($B14="",LEFT($B14,2)="自备"),"",SUMIFS(周转筐出入库明细!$K$4:$K$2004,周转筐出入库明细!$D$4:$D$2004,$B14,周转筐出入库明细!$B$4:$B$2004,">="&$Q$1,周转筐出入库明细!$B$4:$B$2004,"<="&$Q$2)) | H14: =IF(OR($B14="",LEFT($B14,2)="自备"),"",SUMIFS(周转筐出入库明细!$H$4:$H$2004,周转筐出入库明细!$D$4:$D$2004,$B14,周转筐出入库明细!$B$4:$B$2004,">="&$Q$1,周转筐出入库明细!$B$4:$B$2004,"<="&$Q$2)-SUMIFS(周转筐出入库明细!$H$4:$H$2004,周转筐出入库明细!$D$4:$D$2004,$B14,周转筐出入库明细!$F$4:$F$2004,"采购入库",周转筐出入库明细!$B$4:$B$2004,">="&$Q$1,周转筐出入库明细!$B$4:$B$2004,"<="&$Q$2)) | I14: =IF(OR($B14="",LEFT($B14,2)="自备"),"",N($C14)+N($D14)+N($E14)-N($F14)-N($G14)+N($H14)) | J14: =IF(OR($B14="",LEFT($B14,2)="自备"),"",N($F14)-N($E14)) | K14: =IF(OR($B14="",LEFT($B14,2)="自备"),"",SUMIFS(对接源_01水果筐数!$E$5:$E$304,对接源_01水果筐数!$C$5:$C$304,$B14)+SUMIFS(对接源_01水果筐数!$F$5:$F$304,对接源_01水果筐数!$C$5:$C$304,$B14)-SUMIFS(对接源_01水果筐数!$D$5:$D$304,对接源_01水果筐数!$C$5:$C$304,$B14)) | L14: =IF(OR($B14="",LEFT($B14,2)="自备"),"",N($I14)+N($J14)+N($K14)) | M14: =IF($B14="","",IF(LEFT($B14,2)="自备","客户自备筐，不计公司资产，见【自备筐汇总】",""))
A15: =IF($B15="","",ROW()-3) | B15: =IFERROR(INDEX(_自动清单!$BQ$4:$BQ$63,ROW()-3),"") | C15: =IF(OR($B15="",LEFT($B15,2)="自备"),"",SUMIFS(周转筐出入库明细!$H$4:$H$2004,周转筐出入库明细!$D$4:$D$2004,$B15,周转筐出入库明细!$F$4:$F$2004,"期初库存")) | D15: =IF(OR($B15="",LEFT($B15,2)="自备"),"",SUMIFS(周转筐出入库明细!$H$4:$H$2004,周转筐出入库明细!$D$4:$D$2004,$B15,周转筐出入库明细!$F$4:$F$2004,"采购入库",周转筐出入库明细!$B$4:$B$2004,">="&$Q$1,周转筐出入库明细!$B$4:$B$2004,"<="&$Q$2)) | E15: =IF(OR($B15="",LEFT($B15,2)="自备"),"",SUMIFS(周转筐出入库明细!$I$4:$I$2004,周转筐出入库明细!$D$4:$D$2004,$B15,周转筐出入库明细!$B$4:$B$2004,">="&$Q$1,周转筐出入库明细!$B$4:$B$2004,"<="&$Q$2)) | F15: =IF(OR($B15="",LEFT($B15,2)="自备"),"",SUMIFS(周转筐出入库明细!$J$4:$J$2004,周转筐出入库明细!$D$4:$D$2004,$B15,周转筐出入库明细!$B$4:$B$2004,">="&$Q$1,周转筐出入库明细!$B$4:$B$2004,"<="&$Q$2)) | G15: =IF(OR($B15="",LEFT($B15,2)="自备"),"",SUMIFS(周转筐出入库明细!$K$4:$K$2004,周转筐出入库明细!$D$4:$D$2004,$B15,周转筐出入库明细!$B$4:$B$2004,">="&$Q$1,周转筐出入库明细!$B$4:$B$2004,"<="&$Q$2)) | H15: =IF(OR($B15="",LEFT($B15,2)="自备"),"",SUMIFS(周转筐出入库明细!$H$4:$H$2004,周转筐出入库明细!$D$4:$D$2004,$B15,周转筐出入库明细!$B$4:$B$2004,">="&$Q$1,周转筐出入库明细!$B$4:$B$2004,"<="&$Q$2)-SUMIFS(周转筐出入库明细!$H$4:$H$2004,周转筐出入库明细!$D$4:$D$2004,$B15,周转筐出入库明细!$F$4:$F$2004,"采购入库",周转筐出入库明细!$B$4:$B$2004,">="&$Q$1,周转筐出入库明细!$B$4:$B$2004,"<="&$Q$2)) | I15: =IF(OR($B15="",LEFT($B15,2)="自备"),"",N($C15)+N($D15)+N($E15)-N($F15)-N($G15)+N($H15)) | J15: =IF(OR($B15="",LEFT($B15,2)="自备"),"",N($F15)-N($E15)) | K15: =IF(OR($B15="",LEFT($B15,2)="自备"),"",SUMIFS(对接源_01水果筐数!$E$5:$E$304,对接源_01水果筐数!$C$5:$C$304,$B15)+SUMIFS(对接源_01水果筐数!$F$5:$F$304,对接源_01水果筐数!$C$5:$C$304,$B15)-SUMIFS(对接源_01水果筐数!$D$5:$D$304,对接源_01水果筐数!$C$5:$C$304,$B15)) | L15: =IF(OR($B15="",LEFT($B15,2)="自备"),"",N($I15)+N($J15)+N($K15)) | M15: =IF($B15="","",IF(LEFT($B15,2)="自备","客户自备筐，不计公司资产，见【自备筐汇总】",""))
... A63: =IF($B63="","",ROW()-3) | B63: =IFERROR(INDEX(_自动清单!$BQ$4:$BQ$63,ROW()-3),"") | C63: =IF(OR($B63="",LEFT($B63,2)="自备"),"",SUMIFS(周转筐出入库明细!$H$4:$H$2004,周转筐出入库明细!$D$4:$D$2004,$B63,周转筐出入库明细!$F$4:$F$2004,"期初库存")) | D63: =IF(OR($B63="",LEFT($B63,2)="自备"),"",SUMIFS(周转筐出入库明细!$H$4:$H$2004,周转筐出入库明细!$D$4:$D$2004,$B63,周转筐出入库明细!$F$4:$F$2004,"采购入库",周转筐出入库明细!$B$4:$B$2004,">="&$Q$1,周转筐出入库明细!$B$4:$B$2004,"<="&$Q$2)) | E63: =IF(OR($B63="",LEFT($B63,2)="自备"),"",SUMIFS(周转筐出入库明细!$I$4:$I$2004,周转筐出入库明细!$D$4:$D$2004,$B63,周转筐出入库明细!$B$4:$B$2004,">="&$Q$1,周转筐出入库明细!$B$4:$B$2004,"<="&$Q$2)) | F63: =IF(OR($B63="",LEFT($B63,2)="自备"),"",SUMIFS(周转筐出入库明细!$J$4:$J$2004,周转筐出入库明细!$D$4:$D$2004,$B63,周转筐出入库明细!$B$4:$B$2004,">="&$Q$1,周转筐出入库明细!$B$4:$B$2004,"<="&$Q$2)) | G63: =IF(OR($B63="",LEFT($B63,2)="自备"),"",SUMIFS(周转筐出入库明细!$K$4:$K$2004,周转筐出入库明细!$D$4:$D$2004,$B63,周转筐出入库明细!$B$4:$B$2004,">="&$Q$1,周转筐出入库明细!$B$4:$B$2004,"<="&$Q$2)) | H63: =IF(OR($B63="",LEFT($B63,2)="自备"),"",SUMIFS(周转筐出入库明细!$H$4:$H$2004,周转筐出入库明细!$D$4:$D$2004,$B63,周转筐出入库明细!$B$4:$B$2004,">="&$Q$1,周转筐出入库明细!$B$4:$B$2004,"<="&$Q$2)-SUMIFS(周转筐出入库明细!$H$4:$H$2004,周转筐出入库明细!$D$4:$D$2004,$B63,周转筐出入库明细!$F$4:$F$2004,"采购入库",周转筐出入库明细!$B$4:$B$2004,">="&$Q$1,周转筐出入库明细!$B$4:$B$2004,"<="&$Q$2)) | I63: =IF(OR($B63="",LEFT($B63,2)="自备"),"",N($C63)+N($D63)+N($E63)-N($F63)-N($G63)+N($H63)) | J63: =IF(OR($B63="",LEFT($B63,2)="自备"),"",N($F63)-N($E63)) | K63: =IF(OR($B63="",LEFT($B63,2)="自备"),"",SUMIFS(对接源_01水果筐数!$E$5:$E$304,对接源_01水果筐数!$C$5:$C$304,$B63)+SUMIFS(对接源_01水果筐数!$F$5:$F$304,对接源_01水果筐数!$C$5:$C$304,$B63)-SUMIFS(对接源_01水果筐数!$D$5:$D$304,对接源_01水果筐数!$C$5:$C$304,$B63)) | L63: =IF(OR($B63="",LEFT($B63,2)="自备"),"",N($I63)+N($J63)+N($K63)) | M63: =IF($B63="","",IF(LEFT($B63,2)="自备","客户自备筐，不计公司资产，见【自备筐汇总】",""))
B64: 合计 | C64: =ROUND(SUM(C4:C63),2) -> 177768 | D64: =ROUND(SUM(D4:D63),2) -> 17472 | E64: =ROUND(SUM(E4:E63),2) -> 82 | F64: =ROUND(SUM(F4:F63),2) -> 29344 | G64: =ROUND(SUM(G4:G63),2) -> 960 | H64: =ROUND(SUM(H4:H63),2) -> 0 | I64: =ROUND(SUM(I4:I63),2) -> 165018 | J64: =ROUND(SUM(J4:J63),2) -> 29262 | ... L64: =ROUND(SUM(L4:L63),2) -> 180226

Sheet 筐子往来汇总
A1: 筐 子 往 来 汇 总（按客户 / 供应商 · 全自动） | BC1: =IF($J2="",DATE(1900,1,1),$J2) -> 1
A2: ★ 全自动。C～Z 列来自本册【周转筐出入库明细】，可按右边起止日期筛选；AA～AO 列来自《01 水果台账》的【筐子进出接口】（区间在 01 册里设）。退回与随货回库显示为负数。 | I2: 开始日期 | K2: 结束日期 | BC2: =IF($L2="",DATE(2999,12,31),$L2) -> 401768
A3: 序号 | B3: 客户 / 供应商 | C3: ="发出-"&基础资料!$B$4 -> 发出-公司一次性筐 | D3: ="发出-"&基础资料!$B$5 -> 发出-公司杂周转筐 | E3: ="发出-"&基础资料!$B$6 -> 发出-公司新周转筐 | F3: ="发出-"&基础资料!$B$7 -> 发出-公司白周转筐 | G3: ="发出-"&基础资料!$B$8 -> 发出-公司红周转筐 | H3: 发出合计 | I3: ="退回-"&基础资料!$B$4 -> 退回-公司一次性筐 | J3: ="退回-"&基础资料!$B$5 -> 退回-公司杂周转筐 | K3: ="退回-"&基础资料!$B$6 -> 退回-公司新周转筐 | L3: ="退回-"&基础资料!$B$7 -> 退回-公司白周转筐 | M3: ="退回-"&基础资料!$B$8 -> 退回-公司红周转筐 | N3: 退回合计 | O3: ="采购入库-"&基础资料!$B$4 -> 采购入库-公司一次性筐 | P3: ="采购入库-"&基础资料!$B$5 -> 采购入库-公司杂周转筐 | Q3: ="采购入库-"&基础资料!$B$6 -> 采购入库-公司新周转筐 | R3: ="采购入库-"&基础资料!$B$7 -> 采购入库-公司白周转筐 | S3: ="采购入库-"&基础资料!$B$8 -> 采购入库-公司红周转筐 | T3: 采购入库合计 | U3: ="销售数量-"&基础资料!$B$4 -> 销售数量-公司一次性筐 | V3: ="销售数量-"&基础资料!$B$5 -> 销售数量-公司杂周转筐 | W3: ="销售数量-"&基础资料!$B$6 -> 销售数量-公司新周转筐 | X3: ="销售数量-"&基础资料!$B$7 -> 销售数量-公司白周转筐 | Y3: ="销售数量-"&基础资料!$B$8 -> 销售数量-公司红周转筐 | Z3: 销售数量合计 | AA3: ="01册原料入库-"&基础资料!$B$4 -> 01册原料入库-公司一次性筐 | AB3: ="01册原料入库-"&基础资料!$B$5 -> 01册原料入库-公司杂周转筐 | AC3: ="01册原料入库-"&基础资料!$B$6 -> 01册原料入库-公司新周转筐 | AD3: ="01册原料入库-"&基础资料!$B$7 -> 01册原料入库-公司白周转筐 | AE3: ="01册原料入库-"&基础资料!$B$8 -> 01册原料入库-公司红周转筐 | AF3: ="01册原料出库-"&基础资料!$B$4 -> 01册原料出库-公司一次性筐 | AG3: ="01册原料出库-"&基础资料!$B$5 -> 01册原料出库-公司杂周转筐 | AH3: ="01册原料出库-"&基础资料!$B$6 -> 01册原料出库-公司新周转筐 | AI3: ="01册原料出库-"&基础资料!$B$7 -> 01册原料出库-公司白周转筐 | AJ3: ="01册原料出库-"&基础资料!$B$8 -> 01册原料出库-公司红周转筐 | AK3: ="01册成品出库-"&基础资料!$B$4 -> 01册成品出库-公司一次性筐 | AL3: ="01册成品出库-"&基础资料!$B$5 -> 01册成品出库-公司杂周转筐 | AM3: ="01册成品出库-"&基础资料!$B$6 -> 01册成品出库-公司新周转筐 | AN3: ="01册成品出库-"&基础资料!$B$7 -> 01册成品出库-公司白周转筐 | AO3: ="01册成品出库-"&基础资料!$B$8 -> 01册成品出库-公司红周转筐 | AP3: ="未回库-"&基础资料!$B$4 -> 未回库-公司一次性筐 | AQ3: ="未回库-"&基础资料!$B$5 -> 未回库-公司杂周转筐 | AR3: ="未回库-"&基础资料!$B$6 -> 未回库-公司新周转筐 | AS3: ="未回库-"&基础资料!$B$7 -> 未回库-公司白周转筐 | AT3: ="未回库-"&基础资料!$B$8 -> 未回库-公司红周转筐 | AU3: 未回库合计 | AV3: 核查结果 | AW3: 备注
A4: =IF($B4="","",ROW()-3) -> 1 | B4: =IFERROR(INDEX(_自动清单!$CC$4:$CC$253,ROW()-3),"") -> 王照雪 | C4: =IF(OR($B4="",基础资料!$B$4=""),"",SUMIFS(周转筐出入库明细!$J$4:$J$2004,周转筐出入库明细!$C$4:$C$2004,$B4,周转筐出入库明细!$D$4:$D$2004,基础资料!$B$4,周转筐出入库明细!$B$4:$B$2004,">="&$BC$1,周转筐出入库明细!$B$4:$B$2004,"<="&$BC$2)) -> 846 | D4: =IF(OR($B4="",基础资料!$B$5=""),"",SUMIFS(周转筐出入库明细!$J$4:$J$2004,周转筐出入库明细!$C$4:$C$2004,$B4,周转筐出入库明细!$D$4:$D$2004,基础资料!$B$5,周转筐出入库明细!$B$4:$B$2004,">="&$BC$1,周转筐出入库明细!$B$4:$B$2004,"<="&$BC$2)) -> 3681 | E4: =IF(OR($B4="",基础资料!$B$6=""),"",SUMIFS(周转筐出入库明细!$J$4:$J$2004,周转筐出入库明细!$C$4:$C$2004,$B4,周转筐出入库明细!$D$4:$D$2004,基础资料!$B$6,周转筐出入库明细!$B$4:$B$2004,">="&$BC$1,周转筐出入库明细!$B$4:$B$2004,"<="&$BC$2)) -> 0 | F4: =IF(OR($B4="",基础资料!$B$7=""),"",SUMIFS(周转筐出入库明细!$J$4:$J$2004,周转筐出入库明细!$C$4:$C$2004,$B4,周转筐出入库明细!$D$4:$D$2004,基础资料!$B$7,周转筐出入库明细!$B$4:$B$2004,">="&$BC$1,周转筐出入库明细!$B$4:$B$2004,"<="&$BC$2)) -> 0 | G4: =IF(OR($B4="",基础资料!$B$8=""),"",SUMIFS(周转筐出入库明细!$J$4:$J$2004,周转筐出入库明细!$C$4:$C$2004,$B4,周转筐出入库明细!$D$4:$D$2004,基础资料!$B$8,周转筐出入库明细!$B$4:$B$2004,">="&$BC$1,周转筐出入库明细!$B$4:$B$2004,"<="&$BC$2)) -> 0 | H4: =IF($B4="","",SUM(C4:G4)) -> 4527 | I4: =IF(OR($B4="",基础资料!$B$4=""),"",-SUMIFS(周转筐出入库明细!$I$4:$I$2004,周转筐出入库明细!$C$4:$C$2004,$B4,周转筐出入库明细!$D$4:$D$2004,基础资料!$B$4,周转筐出入库明细!$B$4:$B$2004,">="&$BC$1,周转筐出入库明细!$B$4:$B$2004,"<="&$BC$2)) -> -1 | J4: =IF(OR($B4="",基础资料!$B$5=""),"",-SUMIFS(周转筐出入库明细!$I$4:$I$2004,周转筐出入库明细!$C$4:$C$2004,$B4,周转筐出入库明细!$D$4:$D$2004,基础资料!$B$5,周转筐出入库明细!$B$4:$B$2004,">="&$BC$1,周转筐出入库明细!$B$4:$B$2004,"<="&$BC$2)) -> -81 | K4: =IF(OR($B4="",基础资料!$B$6=""),"",-SUMIFS(周转筐出入库明细!$I$4:$I$2004,周转筐出入库明细!$C$4:$C$2004,$B4,周转筐出入库明细!$D$4:$D$2004,基础资料!$B$6,周转筐出入库明细!$B$4:$B$2004,">="&$BC$1,周转筐出入库明细!$B$4:$B$2004,"<="&$BC$2)) -> 0 | L4: =IF(OR($B4="",基础资料!$B$7=""),"",-SUMIFS(周转筐出入库明细!$I$4:$I$2004,周转筐出入库明细!$C$4:$C$2004,$B4,周转筐出入库明细!$D$4:$D$2004,基础资料!$B$7,周转筐出入库明细!$B$4:$B$2004,">="&$BC$1,周转筐出入库明细!$B$4:$B$2004,"<="&$BC$2)) -> 0 | M4: =IF(OR($B4="",基础资料!$B$8=""),"",-SUMIFS(周转筐出入库明细!$I$4:$I$2004,周转筐出入库明细!$C$4:$C$2004,$B4,周转筐出入库明细!$D$4:$D$2004,基础资料!$B$8,周转筐出入库明细!$B$4:$B$2004,">="&$BC$1,周转筐出入库明细!$B$4:$B$2004,"<="&$BC$2)) -> 0 | N4: =IF($B4="","",SUM(I4:M4)) -> -82 | O4: =IF(OR($B4="",基础资料!$B$4=""),"",SUMIFS(周转筐出入库明细!$H$4:$H$2004,周转筐出入库明细!$C$4:$C$2004,$B4,周转筐出入库明细!$D$4:$D$2004,基础资料!$B$4,周转筐出入库明细!$F$4:$F$2004,"采购入库",周转筐出入库明细!$B$4:$B$2004,">="&$BC$1,周转筐出入库明细!$B$4:$B$2004,"<="&$BC$2)) -> 0 | P4: =IF(OR($B4="",基础资料!$B$5=""),"",SUMIFS(周转筐出入库明细!$H$4:$H$2004,周转筐出入库明细!$C$4:$C$2004,$B4,周转筐出入库明细!$D$4:$D$2004,基础资料!$B$5,周转筐出入库明细!$F$4:$F$2004,"采购入库",周转筐出入库明细!$B$4:$B$2004,">="&$BC$1,周转筐出入库明细!$B$4:$B$2004,"<="&$BC$2)) -> 0 | Q4: =IF(OR($B4="",基础资料!$B$6=""),"",SUMIFS(周转筐出入库明细!$H$4:$H$2004,周转筐出入库明细!$C$4:$C$2004,$B4,周转筐出入库明细!$D$4:$D$2004,基础资料!$B$6,周转筐出入库明细!$F$4:$F$2004,"采购入库",周转筐出入库明细!$B$4:$B$2004,">="&$BC$1,周转筐出入库明细!$B$4:$B$2004,"<="&$BC$2)) -> 0 | R4: =IF(OR($B4="",基础资料!$B$7=""),"",SUMIFS(周转筐出入库明细!$H$4:$H$2004,周转筐出入库明细!$C$4:$C$2004,$B4,周转筐出入库明细!$D$4:$D$2004,基础资料!$B$7,周转筐出入库明细!$F$4:$F$2004,"采购入库",周转筐出入库明细!$B$4:$B$2004,">="&$BC$1,周转筐出入库明细!$B$4:$B$2004,"<="&$BC$2)) -> 0 | S4: =IF(OR($B4="",基础资料!$B$8=""),"",SUMIFS(周转筐出入库明细!$H$4:$H$2004,周转筐出入库明细!$C$4:$C$2004,$B4,周转筐出入库明细!$D$4:$D$2004,基础资料!$B$8,周转筐出入库明细!$F$4:$F$2004,"采购入库",周转筐出入库明细!$B$4:$B$2004,">="&$BC$1,周转筐出入库明细!$B$4:$B$2004,"<="&$BC$2)) -> 0 | T4: =IF($B4="","",SUM(O4:S4)) -> 0 | U4: =IF(OR($B4="",基础资料!$B$4=""),"",SUMIFS(周转筐出入库明细!$K$4:$K$2004,周转筐出入库明细!$C$4:$C$2004,$B4,周转筐出入库明细!$D$4:$D$2004,基础资料!$B$4,周转筐出入库明细!$B$4:$B$2004,">="&$BC$1,周转筐出入库明细!$B$4:$B$2004,"<="&$BC$2)) -> 0 | V4: =IF(OR($B4="",基础资料!$B$5=""),"",SUMIFS(周转筐出入库明细!$K$4:$K$2004,周转筐出入库明细!$C$4:$C$2004,$B4,周转筐出入库明细!$D$4:$D$2004,基础资料!$B$5,周转筐出入库明细!$B$4:$B$2004,">="&$BC$1,周转筐出入库明细!$B$4:$B$2004,"<="&$BC$2)) -> 0 | W4: =IF(OR($B4="",基础资料!$B$6=""),"",SUMIFS(周转筐出入库明细!$K$4:$K$2004,周转筐出入库明细!$C$4:$C$2004,$B4,周转筐出入库明细!$D$4:$D$2004,基础资料!$B$6,周转筐出入库明细!$B$4:$B$2004,">="&$BC$1,周转筐出入库明细!$B$4:$B$2004,"<="&$BC$2)) -> 0 | X4: =IF(OR($B4="",基础资料!$B$7=""),"",SUMIFS(周转筐出入库明细!$K$4:$K$2004,周转筐出入库明细!$C$4:$C$2004,$B4,周转筐出入库明细!$D$4:$D$2004,基础资料!$B$7,周转筐出入库明细!$B$4:$B$2004,">="&$BC$1,周转筐出入库明细!$B$4:$B$2004,"<="&$BC$2)) -> 0 | Y4: =IF(OR($B4="",基础资料!$B$8=""),"",SUMIFS(周转筐出入库明细!$K$4:$K$2004,周转筐出入库明细!$C$4:$C$2004,$B4,周转筐出入库明细!$D$4:$D$2004,基础资料!$B$8,周转筐出入库明细!$B$4:$B$2004,">="&$BC$1,周转筐出入库明细!$B$4:$B$2004,"<="&$BC$2)) -> 0 | Z4: =IF($B4="","",SUM(U4:Y4)) -> 0 | AA4: =IF(OR($B4="",基础资料!$B$4=""),"",-SUMIFS(对接源_01水果筐数!$D$5:$D$304,对接源_01水果筐数!$B$5:$B$304,$B4,对接源_01水果筐数!$C$5:$C$304,基础资料!$B$4)) -> -543 | AB4: =IF(OR($B4="",基础资料!$B$5=""),"",-SUMIFS(对接源_01水果筐数!$D$5:$D$304,对接源_01水果筐数!$B$5:$B$304,$B4,对接源_01水果筐数!$C$5:$C$304,基础资料!$B$5)) -> -1670 | AC4: =IF(OR($B4="",基础资料!$B$6=""),"",-SUMIFS(对接源_01水果筐数!$D$5:$D$304,对接源_01水果筐数!$B$5:$B$304,$B4,对接源_01水果筐数!$C$5:$C$304,基础资料!$B$6)) -> 0 | AD4: =IF(OR($B4="",基础资料!$B$7=""),"",-SUMIFS(对接源_01水果筐数!$D$5:$D$304,对接源_01水果筐数!$B$5:$B$304,$B4,对接源_01水果筐数!$C$5:$C$304,基础资料!$B$7)) -> 0 | AE4: =IF(OR($B4="",基础资料!$B$8=""),"",-SUMIFS(对接源_01水果筐数!$D$5:$D$304,对接源_01水果筐数!$B$5:$B$304,$B4,对接源_01水果筐数!$C$5:$C$304,基础资料!$B$8)) -> 0 | AF4: =IF(OR($B4="",基础资料!$B$4=""),"",SUMIFS(对接源_01水果筐数!$E$5:$E$304,对接源_01水果筐数!$B$5:$B$304,$B4,对接源_01水果筐数!$C$5:$C$304,基础资料!$B$4)) -> 0 | AG4: =IF(OR($B4="",基础资料!$B$5=""),"",SUMIFS(对接源_01水果筐数!$E$5:$E$304,对接源_01水果筐数!$B$5:$B$304,$B4,对接源_01水果筐数!$C$5:$C$304,基础资料!$B$5)) -> 1 | AH4: =IF(OR($B4="",基础资料!$B$6=""),"",SUMIFS(对接源_01水果筐数!$E$5:$E$304,对接源_01水果筐数!$B$5:$B$304,$B4,对接源_01水果筐数!$C$5:$C$304,基础资料!$B$6)) -> 0 | AI4: =IF(OR($B4="",基础资料!$B$7=""),"",SUMIFS(对接源_01水果筐数!$E$5:$E$304,对接源_01水果筐数!$B$5:$B$304,$B4,对接源_01水果筐数!$C$5:$C$304,基础资料!$B$7)) -> 0 | AJ4: =IF(OR($B4="",基础资料!$B$8=""),"",SUMIFS(对接源_01水果筐数!$E$5:$E$304,对接源_01水果筐数!$B$5:$B$304,$B4,对接源_01水果筐数!$C$5:$C$304,基础资料!$B$8)) -> 0 | AK4: =IF(OR($B4="",基础资料!$B$4=""),"",SUMIFS(对接源_01水果筐数!$F$5:$F$304,对接源_01水果筐数!$B$5:$B$304,$B4,对接源_01水果筐数!$C$5:$C$304,基础资料!$B$4)) -> 0 | AL4: =IF(OR($B4="",基础资料!$B$5=""),"",SUMIFS(对接源_01水果筐数!$F$5:$F$304,对接源_01水果筐数!$B$5:$B$304,$B4,对接源_01水果筐数!$C$5:$C$304,基础资料!$B$5)) -> 4 | AM4: =IF(OR($B4="",基础资料!$B$6=""),"",SUMIFS(对接源_01水果筐数!$F$5:$F$304,对接源_01水果筐数!$B$5:$B$304,$B4,对接源_01水果筐数!$C$5:$C$304,基础资料!$B$6)) -> 0 | AN4: =IF(OR($B4="",基础资料!$B$7=""),"",SUMIFS(对接源_01水果筐数!$F$5:$F$304,对接源_01水果筐数!$B$5:$B$304,$B4,对接源_01水果筐数!$C$5:$C$304,基础资料!$B$7)) -> 0 | AO4: =IF(OR($B4="",基础资料!$B$8=""),"",SUMIFS(对接源_01水果筐数!$F$5:$F$304,对接源_01水果筐数!$B$5:$B$304,$B4,对接源_01水果筐数!$C$5:$C$304,基础资料!$B$8)) -> 0 | AP4: =IF($B4="","",N(C4)+N(I4)+N(AA4)+N(AF4)+N(AK4)) -> 302 | AQ4: =IF($B4="","",N(D4)+N(J4)+N(AB4)+N(AG4)+N(AL4)) -> 1935 | AR4: =IF($B4="","",N(E4)+N(K4)+N(AC4)+N(AH4)+N(AM4)) -> 0 | AS4: =IF($B4="","",N(F4)+N(L4)+N(AD4)+N(AI4)+N(AN4)) -> 0 | AT4: =IF($B4="","",N(G4)+N(M4)+N(AE4)+N(AJ4)+N(AO4)) -> 0 | AU4: =IF($B4="","",SUM(AP4:AT4)) -> 2237 | AV4: =IF($B4="","",IF(N($AU4)>0,"⚠ 有 "&N($AU4)&" 个筐未回","✔ 已回清")) -> ⚠ 有 2237 个筐未回
