Workbook
Name 日滞纳金率: 资料!$L$4
Name 机构表: 资料!$A$4:$A$13
Name 物品表: 资料!$C$4:$C$43
Name 状态表: 资料!$E$4:$E$33
Name 付息表: 资料!$G$4:$G$13
Name 客户名单: 资料!$I$4:$I$503

Sheet 使用说明
A1: 典当登记表 · 使用说明
A3: 一、八张表，各管一段
A4: 表名 | B4: 谁用 | C4: 干什么
A5: 资料 | B5: 管理员 | C5: 所有下拉菜单的来源：抵押机构、抵押物品、状态、付息方式、客户名单、日滞纳金率。
A6: 表1不动产登记 | B6: 登记员 | C6: 金辉典当的不动产，单独一张，跟表2不混。逾期天数、应收滞纳金自动算。
A7: 表2客户典当登记 | B7: 登记员 | C7: 客户典当总表，所有机构都在这里登记。这是唯一要填的主表。
A8: 金辉典当 | B8: 看 | C8: 自动从表2拆出来，不用填。
A9: 明道典当 | B9: 看 | C9: 同上（这次新增的机构）。
A10: 个人典当 | B10: 看 | C10: 同上。原来叫「个人借款」，统一改成「个人典当」，跟子表名对上。
A11: 查询表（新） | B11: 查客户 | C11: ★ 主用这张。第 1 行输姓名（同名才补身份证号），左边典当明细、右边资金收付并排看，下面是不动产。
A12: 查询表 | B12: 查客户 | C12: 旧版，三块竖着排，内容一样，保留备用。不想要可以右键删掉。
A14: 二、三张子表是怎么自动拆出来的
A15: 公式 | B15: FILTER | C15: 每张子表的 A4 是一条 FILTER：把表2里「抵押机构 = 本表名字」的行整块搬过来。
A16: 所以 | B16: 别在子表里打字 | C16: 子表整块是一条公式的结果，手动输入会把公式顶掉。要改去表2改。
A17: 新增机构 | B17: 两步 | C17: ① 在【资料】A 列加机构名；② 复制一张子表，把 B2 改成新机构名即可。
A19: 三、【查询表（新）】怎么用
A20: 第 1 步 | B20: 打开两个文件 | C20: 《A061_典当登记表.xlsx》和《A061_资金台账.xlsx》都要打开。
A21: 第 2 步 | B21: B1 选姓名 | C21: 第 1 行 B1 那格选（或直接打）客户姓名，三块明细和汇总条全部自动跳出来。
A22: 第 3 步（一般用不上） | B22: E1 填身份证号 | C22: 只有碰到同名客户才要填。B1 右边的黄条会提示：「这个姓名下登了 N 个不同的身份证号」，看到了再去 E1 填身份证号，左边典当那块就只剩这个人的。没同名就别填。
A23: 身份证号从哪来 | B23: 表2 的 F 列 | C23: 在【表2客户典当登记】的「身份证号」列登。表1 不动产和资金台账里没有这一列，那两块只能按姓名查——黄条里也写着。
A24: 为什么要都打开 | B24: Excel 的规矩 | C24: FILTER、SUMIF 这类公式读不了「关着的」工作簿，只能读打开着的。关着的时候右边那块会显示「取不到数」，把资金台账打开就回来了。
A25: 两个文件要放一起 | B25: 同一个文件夹 | C25: 文件名一个字都不能改。从聊天里下载重名会变成「(1)」，要把括号那段删掉。
A27: 四、颜色和符号
A28: 淡黄色格子 | B28: 请填写 | C28: 这是要人填的。
A29: 灰色格子 | B29: 公式自动算 | C29: 别手动改。
A30: ※ 开头的红字 | B30: 有问题 | C30: 「核对」列会自己挑毛病：机构/状态不在名单、已还本金大于典当金额、到期日早于当票日期、当票号重复。
A32: 五、这次从原表搬过来的
A33: · 表2（原 Sheet2）201 行全部搬过来，「个人借款」统一改名「个人典当」（134 笔），金辉典当 67 笔。
A34: · 表1（原 Sheet1）67 行全部搬过来。
A35: · 新加了「身份证号」「客户电话」两列（空着，你自己补），查询表按姓名查，身份证号自动带出来。
A36: · 新加了「当前在当」列 = 典当金额 − 已还本金，自动算。
A37: · 新加了「核对」列，逐行挑毛病。
A38: · 原来「应收金额」改叫「应收利息」，位置挪到「典当系统费率」后面，看起来更顺。
A39: · ⚠ 查过了：【表1】那 67 行，跟【表2】里机构=金辉典当的 67 行是同一批当（姓名+金额+当票号 66 行完全一致）。
A40: 表1 多出来的是收款拆分（对公/林总/建行民生/微信）、违约金、滞纳金。所以两张表的金额**不能相加**，
A41: 查询表里也分成两块单独列，就是这个原因。
A42: · 「典当系统费率」这一列各行口径不一样（有的按月、有的按日），所以没拿它去反推利息对错，
A43: 免得整屏报警。要核利息请直接看「应收利息」那一列。

Sheet 资料
A1: 资料 · 下拉菜单的来源
A2: 要加机构、加抵押物品、加状态，就在这里往下接着写，别留空行。
A3: 抵押机构 | C3: 抵押物品 | E3: 状态 | G3: 付息方式 | I3: 客户名单(自动) | K3: 参数 | L3: 数值
A4: 金辉典当 | C4: 房产 | E4: 在当 | G4: 先息 | I4: 严为志 | K4: 日滞纳金率 | L4: 0.001 | M4: 表1「应收滞纳金」用它算：典当金额 × 本比率 × 逾期天数 − 已收违约金
A5: 明道典当 | C5: 车子 | E5: 在当-无息 | G5: 后息 | I5: 何博文 | K5: 名单没收到的新客户 | L5: =SUMPRODUCT((表2客户典当登记!$E$4:$E$403<>"")*(COUNTIF($I$4:$I$503,表2客户典当登记!$E$4:$E$403)=0)) | M5: 大于 0 说明表2里有新客户还没加进 I 列名单（查询表的下拉会找不到他）
A6: 个人典当 | C6: 车位 | E6: 结款未赎 | G6: 一次性 | I6: 何松
C7: 黄金 | E7: 赎当 | I7: 刘万富
C8: 包包 | E8: 虚当 | I8: 刘振祥
C9: 手表 | E9: 起诉 | I9: 刘署明
C10: 名品 | E10: 起诉还款 | I10: 叶守芳
C11: 无抵押借款 | E11: 结款（个人） | I11: 叶敏
C12: 钻戒 | E12: 逾期-未起诉 | I12: 叶榕
C13: 私人借款 | E13: 无法回款 | I13: 叶金
C14: 法拍垫资 | E14: 绝当未处置 | I14: 叶银
C15: 手机 | I15: 吴丽玲
C16: 解押/过桥 | I16: 吴伟鸿
C17: 寿山石 | I17: 吴吉翔
C18: 白金 | I18: 吴彬
C19: 车贷-没押车 | I19: 吴水明
C20: 黄金+钻戒 | I20: 吴灵铭
C21: 玉佩 | I21: 周晓斌
C22: 动产 | I22: 唐俊俊
C23: 股票配资 | I23: 夏薇薇
C24: 不动产 | I24: 姚民威
I25: 姜玉枝
I26: 孙长健
I27: 宋磊华
I28: 常虹
I29: 廖浴波
I30: 张品洲
I31: 张天龙
I32: 张妍
I33: 张帆
I34: 张建云
I35: 张黎晖
I36: 徐昊昱
... I144: 黄飞

Sheet 表1不动产登记
A1: 表1 · 金辉典当不动产登记（单独一张，跟表2不混）
A2: 日滞纳金比率填在 W2 那格（原表是 0.001）。逾期天数和应收滞纳金自动算。
A3: 序号 | B3: 抵押物品 ★ | C3: 状态 ★ | D3: 客户姓名 ★ | E3: 客户电话 | F3: 当票号 | G3: 当票日期 | H3: 当票到期日 | I3: 出款日期 | J3: 典当金额 ★ | K3: 典当系统费率 | L3: 应收金额(利息) | M3: 开票金额 | N3: 对公 | O3: 林总 | P3: 建行/民生 | Q3: 微信 | R3: 违约金 | S3: 合计收款 | T3: 应付利息日 | U3: 实际付利息日 | V3: 逾期天数 | W3: 应收滞纳金 | X3: 付息方式 | Y3: 回款时间 | Z3: 回款金额 | AA3: 核对
A4: =IF($D4="","",COUNTA($D$4:$D4)) | B4: 不动产 | C4: 起诉 | D4: 李佳敏 | E4: 13027200576 | F4: 3519121393 | G4: 44326 | I4: 45240 | J4: 150000 | K4: 0.025 | L4: 3750 | M4: 3750 | S4: =IF($D4="","",ROUND(N($N4)+N($O4)+N($P4)+N($Q4)+N($R4),2)) | T4: 45332 | V4: =IF($D4="","",IF(OR($T4="",$U4=""),0,MAX(0,INT($U4)-INT($T4)))) | W4: =IF($D4="","",ROUND(MAX(0,N($J4)*日滞纳金率*N($V4)-N($R4)),2)) | X4: 先息 | AA4: =IF($D4="","",IF(AND($C4<>"",ISNA(MATCH($C4,状态表,0))),"※状态不在【资料】里",IF(AND($G4<>"",$H4<>"",$H4<$G4),"※到期日早于当票日期",IF(AND($F4<>"",COUNTIF($F$4:$F$123,$F4)>1),"※当票号在本表里出现了不止一次",IF(AND(N($U4)>0,N($T4)=0),"※填了实际付息日但没填应付息日","")))))
A5: =IF($D5="","",COUNTA($D$4:$D5)) | B5: 车位 | C5: 在当 | D5: 方楚钰 | E5: 18558706859 | F5: 3519121346 | G5: 44453 | I5: 45246 | J5: 50000 | K5: 0.025 | L5: 1250 | M5: 2500 | S5: =IF($D5="","",ROUND(N($N5)+N($O5)+N($P5)+N($Q5)+N($R5),2)) | T5: 46280 | V5: =IF($D5="","",IF(OR($T5="",$U5=""),0,MAX(0,INT($U5)-INT($T5)))) | W5: =IF($D5="","",ROUND(MAX(0,N($J5)*日滞纳金率*N($V5)-N($R5)),2)) | X5: 先息 | AA5: =IF($D5="","",IF(AND($C5<>"",ISNA(MATCH($C5,状态表,0))),"※状态不在【资料】里",IF(AND($G5<>"",$H5<>"",$H5<$G5),"※到期日早于当票日期",IF(AND($F5<>"",COUNTIF($F$4:$F$123,$F5)>1),"※当票号在本表里出现了不止一次",IF(AND(N($U5)>0,N($T5)=0),"※填了实际付息日但没填应付息日","")))))
A6: =IF($D6="","",COUNTA($D$4:$D6)) | B6: 不动产 | C6: 起诉 | D6: 王晓红 | E6: 13850106873 | F6: 3519123861 | G6: 44456 | I6: 45247 | J6: 70000 | K6: 0.025 | L6: 1750 | M6: 1750 | S6: =IF($D6="","",ROUND(N($N6)+N($O6)+N($P6)+N($Q6)+N($R6),2)) | T6: 45700 | V6: =IF($D6="","",IF(OR($T6="",$U6=""),0,MAX(0,INT($U6)-INT($T6)))) | W6: =IF($D6="","",ROUND(MAX(0,N($J6)*日滞纳金率*N($V6)-N($R6)),2)) | X6: 先息 | AA6: =IF($D6="","",IF(AND($C6<>"",ISNA(MATCH($C6,状态表,0))),"※状态不在【资料】里",IF(AND($G6<>"",$H6<>"",$H6<$G6),"※到期日早于当票日期",IF(AND($F6<>"",COUNTIF($F$4:$F$123,$F6)>1),"※当票号在本表里出现了不止一次",IF(AND(N($U6)>0,N($T6)=0),"※填了实际付息日但没填应付息日","")))))
A7: =IF($D7="","",COUNTA($D$4:$D7)) | B7: 不动产 | C7: 在当 | D7: 罗淑珍 | E7: 13635268478 | F7: 3519121360 | G7: 44485 | I7: 45250 | J7: 40000 | K7: 0.025 | L7: 1000 | M7: 1250 | S7: =IF($D7="","",ROUND(N($N7)+N($O7)+N($P7)+N($Q7)+N($R7),2)) | T7: 46279 | V7: =IF($D7="","",IF(OR($T7="",$U7=""),0,MAX(0,INT($U7)-INT($T7)))) | W7: =IF($D7="","",ROUND(MAX(0,N($J7)*日滞纳金率*N($V7)-N($R7)),2)) | X7: 先息 | AA7: =IF($D7="","",IF(AND($C7<>"",ISNA(MATCH($C7,状态表,0))),"※状态不在【资料】里",IF(AND($G7<>"",$H7<>"",$H7<$G7),"※到期日早于当票日期",IF(AND($F7<>"",COUNTIF($F$4:$F$123,$F7)>1),"※当票号在本表里出现了不止一次",IF(AND(N($U7)>0,N($T7)=0),"※填了实际付息日但没填应付息日","")))))
A8: =IF($D8="","",COUNTA($D$4:$D8)) | B8: 车位 | C8: 在当 | D8: 郭联兵 | E8: 13799989896 | F8: 3519156582 | G8: 44578 | I8: 45250 | J8: 100000 | K8: 0.027 | L8: 2700 | M8: 2700 | S8: =IF($D8="","",ROUND(N($N8)+N($O8)+N($P8)+N($Q8)+N($R8),2)) | T8: 46280 | V8: =IF($D8="","",IF(OR($T8="",$U8=""),0,MAX(0,INT($U8)-INT($T8)))) | W8: =IF($D8="","",ROUND(MAX(0,N($J8)*日滞纳金率*N($V8)-N($R8)),2)) | X8: 先息 | AA8: =IF($D8="","",IF(AND($C8<>"",ISNA(MATCH($C8,状态表,0))),"※状态不在【资料】里",IF(AND($G8<>"",$H8<>"",$H8<$G8),"※到期日早于当票日期",IF(AND($F8<>"",COUNTIF($F$4:$F$123,$F8)>1),"※当票号在本表里出现了不止一次",IF(AND(N($U8)>0,N($T8)=0),"※填了实际付息日但没填应付息日","")))))
A9: =IF($D9="","",COUNTA($D$4:$D9)) | B9: 不动产 | C9: 在当 | D9: 郑大可 | E9: 13615013016 | F9: 3519156586 | G9: 44587 | I9: 45256 | J9: 40000 | K9: 0.025 | L9: 1500 | M9: 2500 | S9: =IF($D9="","",ROUND(N($N9)+N($O9)+N($P9)+N($Q9)+N($R9),2)) | T9: 45834 | V9: =IF($D9="","",IF(OR($T9="",$U9=""),0,MAX(0,INT($U9)-INT($T9)))) | W9: =IF($D9="","",ROUND(MAX(0,N($J9)*日滞纳金率*N($V9)-N($R9)),2)) | X9: 先息 | AA9: =IF($D9="","",IF(AND($C9<>"",ISNA(MATCH($C9,状态表,0))),"※状态不在【资料】里",IF(AND($G9<>"",$H9<>"",$H9<$G9),"※到期日早于当票日期",IF(AND($F9<>"",COUNTIF($F$4:$F$123,$F9)>1),"※当票号在本表里出现了不止一次",IF(AND(N($U9)>0,N($T9)=0),"※填了实际付息日但没填应付息日","")))))
A10: =IF($D10="","",COUNTA($D$4:$D10)) | B10: 不动产 | C10: 起诉 | D10: 念武 | E10: 18359178289 | F10: 3519156594 | G10: 44645 | I10: 45255 | J10: 300000 | K10: 0.025 | L10: 7500 | M10: 7500 | S10: =IF($D10="","",ROUND(N($N10)+N($O10)+N($P10)+N($Q10)+N($R10),2)) | T10: 45285 | V10: =IF($D10="","",IF(OR($T10="",$U10=""),0,MAX(0,INT($U10)-INT($T10)))) | W10: =IF($D10="","",ROUND(MAX(0,N($J10)*日滞纳金率*N($V10)-N($R10)),2)) | X10: 先息 | AA10: =IF($D10="","",IF(AND($C10<>"",ISNA(MATCH($C10,状态表,0))),"※状态不在【资料】里",IF(AND($G10<>"",$H10<>"",$H10<$G10),"※到期日早于当票日期",IF(AND($F10<>"",COUNTIF($F$4:$F$123,$F10)>1),"※当票号在本表里出现了不止一次",IF(AND(N($U10)>0,N($T10)=0),"※填了实际付息日但没填应付息日","")))))
A11: =IF($D11="","",COUNTA($D$4:$D11)) | B11: 不动产 | C11: 结款未赎 | D11: 郑祥波 | E11: 13850175177 | G11: 44649 | I11: 45258 | J11: 100000 | K11: 0.025 | L11: 2500 | M11: 3000 | S11: =IF($D11="","",ROUND(N($N11)+N($O11)+N($P11)+N($Q11)+N($R11),2)) | T11: 45743 | V11: =IF($D11="","",IF(OR($T11="",$U11=""),0,MAX(0,INT($U11)-INT($T11)))) | W11: =IF($D11="","",ROUND(MAX(0,N($J11)*日滞纳金率*N($V11)-N($R11)),2)) | X11: 先息 | Y11: 有两万未回典当对公 | AA11: =IF($D11="","",IF(AND($C11<>"",ISNA(MATCH($C11,状态表,0))),"※状态不在【资料】里",IF(AND($G11<>"",$H11<>"",$H11<$G11),"※到期日早于当票日期",IF(AND($F11<>"",COUNTIF($F$4:$F$123,$F11)>1),"※当票号在本表里出现了不止一次",IF(AND(N($U11)>0,N($T11)=0),"※填了实际付息日但没填应付息日","")))))
A12: =IF($D12="","",COUNTA($D$4:$D12)) | B12: 不动产 | C12: 起诉 | D12: 周晓斌 | E12: 13705967988 | F12: 3519121345 | G12: 44818 | I12: 45244 | J12: 200000 | K12: 0.025 | L12: 5000 | M12: 5000 | S12: =IF($D12="","",ROUND(N($N12)+N($O12)+N($P12)+N($Q12)+N($R12),2)) | T12: 45336 | V12: =IF($D12="","",IF(OR($T12="",$U12=""),0,MAX(0,INT($U12)-INT($T12)))) | W12: =IF($D12="","",ROUND(MAX(0,N($J12)*日滞纳金率*N($V12)-N($R12)),2)) | X12: 先息 | AA12: =IF($D12="","",IF(AND($C12<>"",ISNA(MATCH($C12,状态表,0))),"※状态不在【资料】里",IF(AND($G12<>"",$H12<>"",$H12<$G12),"※到期日早于当票日期",IF(AND($F12<>"",COUNTIF($F$4:$F$123,$F12)>1),"※当票号在本表里出现了不止一次",IF(AND(N($U12)>0,N($T12)=0),"※填了实际付息日但没填应付息日","")))))
A13: =IF($D13="","",COUNTA($D$4:$D13)) | B13: 不动产 | C13: 起诉还款 | D13: 朱俊良 | E13: 18065160734 | F13: 3519123869 | G13: 44834 | I13: 45214 | J13: 75000 | K13: 0.025 | L13: 1875 | M13: 1875 | S13: =IF($D13="","",ROUND(N($N13)+N($O13)+N($P13)+N($Q13)+N($R13),2)) | T13: 45229 | V13: =IF($D13="","",IF(OR($T13="",$U13=""),0,MAX(0,INT($U13)-INT($T13)))) | W13: =IF($D13="","",ROUND(MAX(0,N($J13)*日滞纳金率*N($V13)-N($R13)),2)) | X13: 先息 | AA13: =IF($D13="","",IF(AND($C13<>"",ISNA(MATCH($C13,状态表,0))),"※状态不在【资料】里",IF(AND($G13<>"",$H13<>"",$H13<$G13),"※到期日早于当票日期",IF(AND($F13<>"",COUNTIF($F$4:$F$123,$F13)>1),"※当票号在本表里出现了不止一次",IF(AND(N($U13)>0,N($T13)=0),"※填了实际付息日但没填应付息日","")))))
A14: =IF($D14="","",COUNTA($D$4:$D14)) | B14: 不动产 | C14: 起诉 | D14: 念武 | E14: 18359178289 | G14: 44861 | I14: 45258 | J14: 150000 | K14: 0.025 | L14: 3750 | M14: 3750 | S14: =IF($D14="","",ROUND(N($N14)+N($O14)+N($P14)+N($Q14)+N($R14),2)) | T14: 45257 | V14: =IF($D14="","",IF(OR($T14="",$U14=""),0,MAX(0,INT($U14)-INT($T14)))) | W14: =IF($D14="","",ROUND(MAX(0,N($J14)*日滞纳金率*N($V14)-N($R14)),2)) | X14: 先息 | AA14: =IF($D14="","",IF(AND($C14<>"",ISNA(MATCH($C14,状态表,0))),"※状态不在【资料】里",IF(AND($G14<>"",$H14<>"",$H14<$G14),"※到期日早于当票日期",IF(AND($F14<>"",COUNTIF($F$4:$F$123,$F14)>1),"※当票号在本表里出现了不止一次",IF(AND(N($U14)>0,N($T14)=0),"※填了实际付息日但没填应付息日","")))))
A15: =IF($D15="","",COUNTA($D$4:$D15)) | B15: 不动产 | C15: 起诉 | D15: 吴灵铭 | E15: 13950344383 | G15: 44887 | I15: 45220 | J15: 150000 | K15: 0.01 | L15: 3750 | M15: 1500 | S15: =IF($D15="","",ROUND(N($N15)+N($O15)+N($P15)+N($Q15)+N($R15),2)) | T15: 45190 | V15: =IF($D15="","",IF(OR($T15="",$U15=""),0,MAX(0,INT($U15)-INT($T15)))) | W15: =IF($D15="","",ROUND(MAX(0,N($J15)*日滞纳金率*N($V15)-N($R15)),2)) | X15: 先息 | AA15: =IF($D15="","",IF(AND($C15<>"",ISNA(MATCH($C15,状态表,0))),"※状态不在【资料】里",IF(AND($G15<>"",$H15<>"",$H15<$G15),"※到期日早于当票日期",IF(AND($F15<>"",COUNTIF($F$4:$F$123,$F15)>1),"※当票号在本表里出现了不止一次",IF(AND(N($U15)>0,N($T15)=0),"※填了实际付息日但没填应付息日","")))))
A16: =IF($D16="","",COUNTA($D$4:$D16)) | B16: 不动产 | C16: 起诉 | D16: 吴灵铭 | E16: 13950344383 | G16: 44888 | I16: 45221 | J16: 150000 | K16: 0.025 | L16: 3750 | M16: 3750 | S16: =IF($D16="","",ROUND(N($N16)+N($O16)+N($P16)+N($Q16)+N($R16),2)) | T16: 45191 | V16: =IF($D16="","",IF(OR($T16="",$U16=""),0,MAX(0,INT($U16)-INT($T16)))) | W16: =IF($D16="","",ROUND(MAX(0,N($J16)*日滞纳金率*N($V16)-N($R16)),2)) | X16: 先息 | AA16: =IF($D16="","",IF(AND($C16<>"",ISNA(MATCH($C16,状态表,0))),"※状态不在【资料】里",IF(AND($G16<>"",$H16<>"",$H16<$G16),"※到期日早于当票日期",IF(AND($F16<>"",COUNTIF($F$4:$F$123,$F16)>1),"※当票号在本表里出现了不止一次",IF(AND(N($U16)>0,N($T16)=0),"※填了实际付息日但没填应付息日","")))))
A17: =IF($D17="","",COUNTA($D$4:$D17)) | B17: 不动产 | C17: 起诉 | D17: 陈勇 | E17: 13706982320 | G17: 44893 | I17: 45227 | J17: 50000 | K17: 0.025 | L17: 1250 | M17: 1250 | S17: =IF($D17="","",ROUND(N($N17)+N($O17)+N($P17)+N($Q17)+N($R17),2)) | T17: 45197 | V17: =IF($D17="","",IF(OR($T17="",$U17=""),0,MAX(0,INT($U17)-INT($T17)))) | W17: =IF($D17="","",ROUND(MAX(0,N($J17)*日滞纳金率*N($V17)-N($R17)),2)) | X17: 先息 | AA17: =IF($D17="","",IF(AND($C17<>"",ISNA(MATCH($C17,状态表,0))),"※状态不在【资料】里",IF(AND($G17<>"",$H17<>"",$H17<$G17),"※到期日早于当票日期",IF(AND($F17<>"",COUNTIF($F$4:$F$123,$F17)>1),"※当票号在本表里出现了不止一次",IF(AND(N($U17)>0,N($T17)=0),"※填了实际付息日但没填应付息日","")))))
A18: =IF($D18="","",COUNTA($D$4:$D18)) | B18: 房产 | C18: 在当 | D18: 朱颜 | E18: 13706988853 | G18: 45034 | I18: 45248 | J18: 150000 | K18: 0.028 | L18: 4200 | M18: 4200 | S18: =IF($D18="","",ROUND(N($N18)+N($O18)+N($P18)+N($Q18)+N($R18),2)) | T18: 45700 | V18: =IF($D18="","",IF(OR($T18="",$U18=""),0,MAX(0,INT($U18)-INT($T18)))) | W18: =IF($D18="","",ROUND(MAX(0,N($J18)*日滞纳金率*N($V18)-N($R18)),2)) | X18: 先息 | AA18: =IF($D18="","",IF(AND($C18<>"",ISNA(MATCH($C18,状态表,0))),"※状态不在【资料】里",IF(AND($G18<>"",$H18<>"",$H18<$G18),"※到期日早于当票日期",IF(AND($F18<>"",COUNTIF($F$4:$F$123,$F18)>1),"※当票号在本表里出现了不止一次",IF(AND(N($U18)>0,N($T18)=0),"※填了实际付息日但没填应付息日","")))))
A19: =IF($D19="","",COUNTA($D$4:$D19)) | B19: 不动产 | C19: 起诉还款 | D19: 林华 | E19: 13960788050 | G19: 45132 | I19: 45255 | J19: 20000 | K19: 0.03 | L19: 500 | M19: 500 | S19: =IF($D19="","",ROUND(N($N19)+N($O19)+N($P19)+N($Q19)+N($R19),2)) | T19: 45404 | V19: =IF($D19="","",IF(OR($T19="",$U19=""),0,MAX(0,INT($U19)-INT($T19)))) | W19: =IF($D19="","",ROUND(MAX(0,N($J19)*日滞纳金率*N($V19)-N($R19)),2)) | X19: 先息 | AA19: =IF($D19="","",IF(AND($C19<>"",ISNA(MATCH($C19,状态表,0))),"※状态不在【资料】里",IF(AND($G19<>"",$H19<>"",$H19<$G19),"※到期日早于当票日期",IF(AND($F19<>"",COUNTIF($F$4:$F$123,$F19)>1),"※当票号在本表里出现了不止一次",IF(AND(N($U19)>0,N($T19)=0),"※填了实际付息日但没填应付息日","")))))
A20: =IF($D20="","",COUNTA($D$4:$D20)) | B20: 不动产 | C20: 起诉还款 | D20: 林晓霞 | E20: 15396066658 | G20: 45132 | I20: 45255 | J20: 60000 | K20: 0.03 | L20: 1800 | M20: 1500 | S20: =IF($D20="","",ROUND(N($N20)+N($O20)+N($P20)+N($Q20)+N($R20),2)) | T20: 45404 | V20: =IF($D20="","",IF(OR($T20="",$U20=""),0,MAX(0,INT($U20)-INT($T20)))) | W20: =IF($D20="","",ROUND(MAX(0,N($J20)*日滞纳金率*N($V20)-N($R20)),2)) | X20: 先息 | AA20: =IF($D20="","",IF(AND($C20<>"",ISNA(MATCH($C20,状态表,0))),"※状态不在【资料】里",IF(AND($G20<>"",$H20<>"",$H20<$G20),"※到期日早于当票日期",IF(AND($F20<>"",COUNTIF($F$4:$F$123,$F20)>1),"※当票号在本表里出现了不止一次",IF(AND(N($U20)>0,N($T20)=0),"※填了实际付息日但没填应付息日","")))))
A21: =IF($D21="","",COUNTA($D$4:$D21)) | B21: 不动产 | C21: 起诉 | D21: 何松 | F21: 3519211804 | G21: 45189 | I21: 45250 | J21: 60000 | K21: 0.025 | L21: 1500 | M21: 2500 | S21: =IF($D21="","",ROUND(N($N21)+N($O21)+N($P21)+N($Q21)+N($R21),2)) | T21: 45703 | V21: =IF($D21="","",IF(OR($T21="",$U21=""),0,MAX(0,INT($U21)-INT($T21)))) | W21: =IF($D21="","",ROUND(MAX(0,N($J21)*日滞纳金率*N($V21)-N($R21)),2)) | X21: 先息 | AA21: =IF($D21="","",IF(AND($C21<>"",ISNA(MATCH($C21,状态表,0))),"※状态不在【资料】里",IF(AND($G21<>"",$H21<>"",$H21<$G21),"※到期日早于当票日期",IF(AND($F21<>"",COUNTIF($F$4:$F$123,$F21)>1),"※当票号在本表里出现了不止一次",IF(AND(N($U21)>0,N($T21)=0),"※填了实际付息日但没填应付息日","")))))
A22: =IF($D22="","",COUNTA($D$4:$D22)) | B22: 不动产 | C22: 起诉 | D22: 黄平香 | E22: 13358278680 | F22: 3519211817 | G22: 45254 | I22: 45254 | J22: 90000 | K22: 0.025 | L22: 2500 | M22: 2500 | S22: =IF($D22="","",ROUND(N($N22)+N($O22)+N($P22)+N($Q22)+N($R22),2)) | T22: 45706 | V22: =IF($D22="","",IF(OR($T22="",$U22=""),0,MAX(0,INT($U22)-INT($T22)))) | W22: =IF($D22="","",ROUND(MAX(0,N($J22)*日滞纳金率*N($V22)-N($R22)),2)) | X22: 先息 | AA22: =IF($D22="","",IF(AND($C22<>"",ISNA(MATCH($C22,状态表,0))),"※状态不在【资料】里",IF(AND($G22<>"",$H22<>"",$H22<$G22),"※到期日早于当票日期",IF(AND($F22<>"",COUNTIF($F$4:$F$123,$F22)>1),"※当票号在本表里出现了不止一次",IF(AND(N($U22)>0,N($T22)=0),"※填了实际付息日但没填应付息日","")))))
A23: =IF($D23="","",COUNTA($D$4:$D23)) | B23: 不动产 | C23: 在当 | D23: 姚民威 | E23: 18050267666 | F23: 3519228936 | G23: 45383 | I23: 45383 | J23: 40000 | K23: 0.025 | L23: 1000 | M23: 2000 | S23: =IF($D23="","",ROUND(N($N23)+N($O23)+N($P23)+N($Q23)+N($R23),2)) | T23: 46275 | V23: =IF($D23="","",IF(OR($T23="",$U23=""),0,MAX(0,INT($U23)-INT($T23)))) | W23: =IF($D23="","",ROUND(MAX(0,N($J23)*日滞纳金率*N($V23)-N($R23)),2)) | X23: 先息 | Y23: 11月开始这笔就是5万，利息2.5%，就是1250元 | AA23: =IF($D23="","",IF(AND($C23<>"",ISNA(MATCH($C23,状态表,0))),"※状态不在【资料】里",IF(AND($G23<>"",$H23<>"",$H23<$G23),"※到期日早于当票日期",IF(AND($F23<>"",COUNTIF($F$4:$F$123,$F23)>1),"※当票号在本表里出现了不止一次",IF(AND(N($U23)>0,N($T23)=0),"※填了实际付息日但没填应付息日","")))))
A24: =IF($D24="","",COUNTA($D$4:$D24)) | B24: 不动产 | C24: 在当 | D24: 杨惠慧（徐波） | E24: 13559198275 | G24: 45412 | H24: 45500 | I24: 45412 | J24: 100000 | K24: 0.025 | L24: 2500 | M24: 2500 | S24: =IF($D24="","",ROUND(N($N24)+N($O24)+N($P24)+N($Q24)+N($R24),2)) | T24: 45708 | V24: =IF($D24="","",IF(OR($T24="",$U24=""),0,MAX(0,INT($U24)-INT($T24)))) | W24: =IF($D24="","",ROUND(MAX(0,N($J24)*日滞纳金率*N($V24)-N($R24)),2)) | X24: 先息 | AA24: =IF($D24="","",IF(AND($C24<>"",ISNA(MATCH($C24,状态表,0))),"※状态不在【资料】里",IF(AND($G24<>"",$H24<>"",$H24<$G24),"※到期日早于当票日期",IF(AND($F24<>"",COUNTIF($F$4:$F$123,$F24)>1),"※当票号在本表里出现了不止一次",IF(AND(N($U24)>0,N($T24)=0),"※填了实际付息日但没填应付息日","")))))
A25: =IF($D25="","",COUNTA($D$4:$D25)) | B25: 不动产 | C25: 在当 | D25: 章俊 | G25: 45419 | H25: 45478 | I25: 45421 | J25: 36500 | K25: 0.025 | L25: 912.5 | M25: 2500 | S25: =IF($D25="","",ROUND(N($N25)+N($O25)+N($P25)+N($Q25)+N($R25),2)) | T25: 46280 | V25: =IF($D25="","",IF(OR($T25="",$U25=""),0,MAX(0,INT($U25)-INT($T25)))) | W25: =IF($D25="","",ROUND(MAX(0,N($J25)*日滞纳金率*N($V25)-N($R25)),2)) | X25: 先息 | AA25: =IF($D25="","",IF(AND($C25<>"",ISNA(MATCH($C25,状态表,0))),"※状态不在【资料】里",IF(AND($G25<>"",$H25<>"",$H25<$G25),"※到期日早于当票日期",IF(AND($F25<>"",COUNTIF($F$4:$F$123,$F25)>1),"※当票号在本表里出现了不止一次",IF(AND(N($U25)>0,N($T25)=0),"※填了实际付息日但没填应付息日","")))))
A26: =IF($D26="","",COUNTA($D$4:$D26)) | B26: 不动产 | C26: 在当 | D26: 陈锦珍 | E26: 13705954599 | F26: 3519228949 | G26: 45457 | H26: 45636 | I26: 45460 | J26: 1000000 | K26: 0.018 | L26: 18000 | S26: =IF($D26="","",ROUND(N($N26)+N($O26)+N($P26)+N($Q26)+N($R26),2)) | T26: 46124 | V26: =IF($D26="","",IF(OR($T26="",$U26=""),0,MAX(0,INT($U26)-INT($T26)))) | W26: =IF($D26="","",ROUND(MAX(0,N($J26)*日滞纳金率*N($V26)-N($R26)),2)) | X26: 先息 | AA26: =IF($D26="","",IF(AND($C26<>"",ISNA(MATCH($C26,状态表,0))),"※状态不在【资料】里",IF(AND($G26<>"",$H26<>"",$H26<$G26),"※到期日早于当票日期",IF(AND($F26<>"",COUNTIF($F$4:$F$123,$F26)>1),"※当票号在本表里出现了不止一次",IF(AND(N($U26)>0,N($T26)=0),"※填了实际付息日但没填应付息日","")))))
A27: =IF($D27="","",COUNTA($D$4:$D27)) | B27: 名品 | C27: 虚当 | D27: 陈乐贵 | F27: 3519237782 | G27: 45484 | H27: 45663 | I27: 45484 | J27: 500000 | K27: 0.005 | S27: =IF($D27="","",ROUND(N($N27)+N($O27)+N($P27)+N($Q27)+N($R27),2)) | T27: 45513 | V27: =IF($D27="","",IF(OR($T27="",$U27=""),0,MAX(0,INT($U27)-INT($T27)))) | W27: =IF($D27="","",ROUND(MAX(0,N($J27)*日滞纳金率*N($V27)-N($R27)),2)) | X27: 后息 | AA27: =IF($D27="","",IF(AND($C27<>"",ISNA(MATCH($C27,状态表,0))),"※状态不在【资料】里",IF(AND($G27<>"",$H27<>"",$H27<$G27),"※到期日早于当票日期",IF(AND($F27<>"",COUNTIF($F$4:$F$123,$F27)>1),"※当票号在本表里出现了不止一次",IF(AND(N($U27)>0,N($T27)=0),"※填了实际付息日但没填应付息日","")))))
A28: =IF($D28="","",COUNTA($D$4:$D28)) | B28: 不动产 | C28: 起诉 | D28: 王建南 | E28: 13705971124 | F28: 3519252753 | G28: 45574 | H28: 45663 | I28: 45575 | J28: 150000 | K28: 0.025 | L28: 8500 | S28: =IF($D28="","",ROUND(N($N28)+N($O28)+N($P28)+N($Q28)+N($R28),2)) | T28: 45782 | V28: =IF($D28="","",IF(OR($T28="",$U28=""),0,MAX(0,INT($U28)-INT($T28)))) | W28: =IF($D28="","",ROUND(MAX(0,N($J28)*日滞纳金率*N($V28)-N($R28)),2)) | X28: 先息 | AA28: =IF($D28="","",IF(AND($C28<>"",ISNA(MATCH($C28,状态表,0))),"※状态不在【资料】里",IF(AND($G28<>"",$H28<>"",$H28<$G28),"※到期日早于当票日期",IF(AND($F28<>"",COUNTIF($F$4:$F$123,$F28)>1),"※当票号在本表里出现了不止一次",IF(AND(N($U28)>0,N($T28)=0),"※填了实际付息日但没填应付息日","")))))
A29: =IF($D29="","",COUNTA($D$4:$D29)) | B29: 动产 | C29: 虚当 | D29: 柯志宏 | F29: 3519252757 | G29: 45590 | H29: 45679 | J29: 260000 | K29: 0.008 | L29: 2080 | S29: =IF($D29="","",ROUND(N($N29)+N($O29)+N($P29)+N($Q29)+N($R29),2)) | T29: 45677 | V29: =IF($D29="","",IF(OR($T29="",$U29=""),0,MAX(0,INT($U29)-INT($T29)))) | W29: =IF($D29="","",ROUND(MAX(0,N($J29)*日滞纳金率*N($V29)-N($R29)),2)) | Y29: 25.2.20还吴姐建行，未还典当 | AA29: =IF($D29="","",IF(AND($C29<>"",ISNA(MATCH($C29,状态表,0))),"※状态不在【资料】里",IF(AND($G29<>"",$H29<>"",$H29<$G29),"※到期日早于当票日期",IF(AND($F29<>"",COUNTIF($F$4:$F$123,$F29)>1),"※当票号在本表里出现了不止一次",IF(AND(N($U29)>0,N($T29)=0),"※填了实际付息日但没填应付息日","")))))
A30: =IF($D30="","",COUNTA($D$4:$D30)) | B30: 不动产 | C30: 在当 | D30: 杨惠慧（徐波） | E30: 13559198275 | F30: 3519252755 | G30: 45590 | H30: 45619 | J30: 200000 | K30: 0.025 | L30: 5000 | S30: =IF($D30="","",ROUND(N($N30)+N($O30)+N($P30)+N($Q30)+N($R30),2)) | T30: 45692 | V30: =IF($D30="","",IF(OR($T30="",$U30=""),0,MAX(0,INT($U30)-INT($T30)))) | W30: =IF($D30="","",ROUND(MAX(0,N($J30)*日滞纳金率*N($V30)-N($R30)),2)) | X30: 先息 | AA30: =IF($D30="","",IF(AND($C30<>"",ISNA(MATCH($C30,状态表,0))),"※状态不在【资料】里",IF(AND($G30<>"",$H30<>"",$H30<$G30),"※到期日早于当票日期",IF(AND($F30<>"",COUNTIF($F$4:$F$123,$F30)>1),"※当票号在本表里出现了不止一次",IF(AND(N($U30)>0,N($T30)=0),"※填了实际付息日但没填应付息日","")))))
A31: =IF($D31="","",COUNTA($D$4:$D31)) | B31: 不动产 | C31: 在当 | D31: 潘立文 | E31: 18659109900 | F31: 3519252767 | G31: 45633 | H31: 45722 | I31: 45636 | J31: 220000 | K31: 0.025 | L31: 5500 | S31: =IF($D31="","",ROUND(N($N31)+N($O31)+N($P31)+N($Q31)+N($R31),2)) | T31: 46270 | V31: =IF($D31="","",IF(OR($T31="",$U31=""),0,MAX(0,INT($U31)-INT($T31)))) | W31: =IF($D31="","",ROUND(MAX(0,N($J31)*日滞纳金率*N($V31)-N($R31)),2)) | X31: 先息 | AA31: =IF($D31="","",IF(AND($C31<>"",ISNA(MATCH($C31,状态表,0))),"※状态不在【资料】里",IF(AND($G31<>"",$H31<>"",$H31<$G31),"※到期日早于当票日期",IF(AND($F31<>"",COUNTIF($F$4:$F$123,$F31)>1),"※当票号在本表里出现了不止一次",IF(AND(N($U31)>0,N($T31)=0),"※填了实际付息日但没填应付息日","")))))
A32: =IF($D32="","",COUNTA($D$4:$D32)) | B32: 不动产 | C32: 起诉 | D32: 郑永贵 | E32: 13809505675 | F32: 3519252780 | G32: 45723 | H32: 45812 | J32: 250000 | K32: 0.025 | L32: 13750 | S32: =IF($D32="","",ROUND(N($N32)+N($O32)+N($P32)+N($Q32)+N($R32),2)) | T32: 45968 | V32: =IF($D32="","",IF(OR($T32="",$U32=""),0,MAX(0,INT($U32)-INT($T32)))) | W32: =IF($D32="","",ROUND(MAX(0,N($J32)*日滞纳金率*N($V32)-N($R32)),2)) | X32: 先息 | AA32: =IF($D32="","",IF(AND($C32<>"",ISNA(MATCH($C32,状态表,0))),"※状态不在【资料】里",IF(AND($G32<>"",$H32<>"",$H32<$G32),"※到期日早于当票日期",IF(AND($F32<>"",COUNTIF($F$4:$F$123,$F32)>1),"※当票号在本表里出现了不止一次",IF(AND(N($U32)>0,N($T32)=0),"※填了实际付息日但没填应付息日","")))))
A33: =IF($D33="","",COUNTA($D$4:$D33)) | B33: 车位 | C33: 在当 | D33: 方士雯 | E33: 18859197777 | F33: 3519252785 | G33: 45758 | H33: 45846 | J33: 45000 | K33: 0.03 | L33: 1350 | S33: =IF($D33="","",ROUND(N($N33)+N($O33)+N($P33)+N($Q33)+N($R33),2)) | T33: 46275 | U33: 46275 | V33: =IF($D33="","",IF(OR($T33="",$U33=""),0,MAX(0,INT($U33)-INT($T33)))) | W33: =IF($D33="","",ROUND(MAX(0,N($J33)*日滞纳金率*N($V33)-N($R33)),2)) | X33: 先息 | AA33: =IF($D33="","",IF(AND($C33<>"",ISNA(MATCH($C33,状态表,0))),"※状态不在【资料】里",IF(AND($G33<>"",$H33<>"",$H33<$G33),"※到期日早于当票日期",IF(AND($F33<>"",COUNTIF($F$4:$F$123,$F33)>1),"※当票号在本表里出现了不止一次",IF(AND(N($U33)>0,N($T33)=0),"※填了实际付息日但没填应付息日","")))))
A34: =IF($D34="","",COUNTA($D$4:$D34)) | B34: 车位 | C34: 在当 | D34: 王毅 | E34: 15605917733 | F34: 3519252784 | G34: 45754 | H34: 45933 | J34: 40000 | K34: 0.025 | L34: 1000 | S34: =IF($D34="","",ROUND(N($N34)+N($O34)+N($P34)+N($Q34)+N($R34),2)) | T34: 46147 | V34: =IF($D34="","",IF(OR($T34="",$U34=""),0,MAX(0,INT($U34)-INT($T34)))) | W34: =IF($D34="","",ROUND(MAX(0,N($J34)*日滞纳金率*N($V34)-N($R34)),2)) | X34: 先息 | AA34: =IF($D34="","",IF(AND($C34<>"",ISNA(MATCH($C34,状态表,0))),"※状态不在【资料】里",IF(AND($G34<>"",$H34<>"",$H34<$G34),"※到期日早于当票日期",IF(AND($F34<>"",COUNTIF($F$4:$F$123,$F34)>1),"※当票号在本表里出现了不止一次",IF(AND(N($U34)>0,N($T34)=0),"※填了实际付息日但没填应付息日","")))))
A35: =IF($D35="","",COUNTA($D$4:$D35)) | B35: 不动产 | C35: 在当 | D35: 陈跃飞 | E35: 13509389773 | F35: 3519252793 | G35: 45821 | H35: 45910 | J35: 60000 | K35: 0.025 | L35: 1500 | S35: =IF($D35="","",ROUND(N($N35)+N($O35)+N($P35)+N($Q35)+N($R35),2)) | T35: 46279 | V35: =IF($D35="","",IF(OR($T35="",$U35=""),0,MAX(0,INT($U35)-INT($T35)))) | W35: =IF($D35="","",ROUND(MAX(0,N($J35)*日滞纳金率*N($V35)-N($R35)),2)) | X35: 先息 | AA35: =IF($D35="","",IF(AND($C35<>"",ISNA(MATCH($C35,状态表,0))),"※状态不在【资料】里",IF(AND($G35<>"",$H35<>"",$H35<$G35),"※到期日早于当票日期",IF(AND($F35<>"",COUNTIF($F$4:$F$123,$F35)>1),"※当票号在本表里出现了不止一次",IF(AND(N($U35)>0,N($T35)=0),"※填了实际付息日但没填应付息日","")))))
A36: =IF($D36="","",COUNTA($D$4:$D36)) | B36: 不动产 | C36: 起诉 | D36: 郑怡 | E36: 13850169648 | F36: 3519252792 | G36: 45819 | H36: 45998 | J36: 790000 | K36: 0.025 | L36: 19750 | S36: =IF($D36="","",ROUND(N($N36)+N($O36)+N($P36)+N($Q36)+N($R36),2)) | T36: 45819 | V36: =IF($D36="","",IF(OR($T36="",$U36=""),0,MAX(0,INT($U36)-INT($T36)))) | W36: =IF($D36="","",ROUND(MAX(0,N($J36)*日滞纳金率*N($V36)-N($R36)),2)) | X36: 先息 | AA36: =IF($D36="","",IF(AND($C36<>"",ISNA(MATCH($C36,状态表,0))),"※状态不在【资料】里",IF(AND($G36<>"",$H36<>"",$H36<$G36),"※到期日早于当票日期",IF(AND($F36<>"",COUNTIF($F$4:$F$123,$F36)>1),"※当票号在本表里出现了不止一次",IF(AND(N($U36)>0,N($T36)=0),"※填了实际付息日但没填应付息日","")))))
A37: =IF($D37="","",COUNTA($D$4:$D37)) | B37: 不动产 | C37: 在当 | D37: 涂志高 | E37: 13788892386 | F37: 3519252800 | G37: 45895 | H37: 45924 | J37: 340000 | K37: 0.016 | L37: 5440 | S37: =IF($D37="","",ROUND(N($N37)+N($O37)+N($P37)+N($Q37)+N($R37),2)) | T37: 46137 | V37: =IF($D37="","",IF(OR($T37="",$U37=""),0,MAX(0,INT($U37)-INT($T37)))) | W37: =IF($D37="","",ROUND(MAX(0,N($J37)*日滞纳金率*N($V37)-N($R37)),2)) | X37: 先息 | AA37: =IF($D37="","",IF(AND($C37<>"",ISNA(MATCH($C37,状态表,0))),"※状态不在【资料】里",IF(AND($G37<>"",$H37<>"",$H37<$G37),"※到期日早于当票日期",IF(AND($F37<>"",COUNTIF($F$4:$F$123,$F37)>1),"※当票号在本表里出现了不止一次",IF(AND(N($U37)>0,N($T37)=0),"※填了实际付息日但没填应付息日","")))))
A38: =IF($D38="","",COUNTA($D$4:$D38)) | B38: 不动产 | C38: 在当 | D38: 潘淑萍 | E38: 13960929966 | F38: 3519260505 | G38: 45951 | H38: 46010 | J38: 100000 | K38: 0.025 | L38: 2500 | S38: =IF($D38="","",ROUND(N($N38)+N($O38)+N($P38)+N($Q38)+N($R38),2)) | T38: 46273 | U38: 46273 | V38: =IF($D38="","",IF(OR($T38="",$U38=""),0,MAX(0,INT($U38)-INT($T38)))) | W38: =IF($D38="","",ROUND(MAX(0,N($J38)*日滞纳金率*N($V38)-N($R38)),2)) | X38: 先息 | AA38: =IF($D38="","",IF(AND($C38<>"",ISNA(MATCH($C38,状态表,0))),"※状态不在【资料】里",IF(AND($G38<>"",$H38<>"",$H38<$G38),"※到期日早于当票日期",IF(AND($F38<>"",COUNTIF($F$4:$F$123,$F38)>1),"※当票号在本表里出现了不止一次",IF(AND(N($U38)>0,N($T38)=0),"※填了实际付息日但没填应付息日","")))))
A39: =IF($D39="","",COUNTA($D$4:$D39)) | B39: 动产 | C39: 虚当 | D39: 胡建通 | E39: 13805082625 | F39: 3519260503 | G39: 45900 | H39: 45959 | J39: 500000 | S39: =IF($D39="","",ROUND(N($N39)+N($O39)+N($P39)+N($Q39)+N($R39),2)) | T39: 45900 | V39: =IF($D39="","",IF(OR($T39="",$U39=""),0,MAX(0,INT($U39)-INT($T39)))) | W39: =IF($D39="","",ROUND(MAX(0,N($J39)*日滞纳金率*N($V39)-N($R39)),2)) | AA39: =IF($D39="","",IF(AND($C39<>"",ISNA(MATCH($C39,状态表,0))),"※状态不在【资料】里",IF(AND($G39<>"",$H39<>"",$H39<$G39),"※到期日早于当票日期",IF(AND($F39<>"",COUNTIF($F$4:$F$123,$F39)>1),"※当票号在本表里出现了不止一次",IF(AND(N($U39)>0,N($T39)=0),"※填了实际付息日但没填应付息日","")))))
A40: =IF($D40="","",COUNTA($D$4:$D40)) | B40: 不动产 | C40: 在当 | D40: 林昌耿 | E40: 13705954599 | F40: 3519260506 | G40: 45953 | H40: 46132 | J40: 200000 | K40: 0.018 | L40: 3300 | S40: =IF($D40="","",ROUND(N($N40)+N($O40)+N($P40)+N($Q40)+N($R40),2)) | T40: 46135 | V40: =IF($D40="","",IF(OR($T40="",$U40=""),0,MAX(0,INT($U40)-INT($T40)))) | W40: =IF($D40="","",ROUND(MAX(0,N($J40)*日滞纳金率*N($V40)-N($R40)),2)) | X40: 先息 | AA40: =IF($D40="","",IF(AND($C40<>"",ISNA(MATCH($C40,状态表,0))),"※状态不在【资料】里",IF(AND($G40<>"",$H40<>"",$H40<$G40),"※到期日早于当票日期",IF(AND($F40<>"",COUNTIF($F$4:$F$123,$F40)>1),"※当票号在本表里出现了不止一次",IF(AND(N($U40)>0,N($T40)=0),"※填了实际付息日但没填应付息日","")))))
A41: =IF($D41="","",COUNTA($D$4:$D41)) | B41: 不动产 | C41: 在当 | D41: 王晶琰 | G41: 45964 | H41: 45778 | J41: 300000 | K41: 0.018 | L41: 5400 | S41: =IF($D41="","",ROUND(N($N41)+N($O41)+N($P41)+N($Q41)+N($R41),2)) | T41: 46268 | U41: 46268 | V41: =IF($D41="","",IF(OR($T41="",$U41=""),0,MAX(0,INT($U41)-INT($T41)))) | W41: =IF($D41="","",ROUND(MAX(0,N($J41)*日滞纳金率*N($V41)-N($R41)),2)) | X41: 后息 | AA41: =IF($D41="","",IF(AND($C41<>"",ISNA(MATCH($C41,状态表,0))),"※状态不在【资料】里",IF(AND($G41<>"",$H41<>"",$H41<$G41),"※到期日早于当票日期",IF(AND($F41<>"",COUNTIF($F$4:$F$123,$F41)>1),"※当票号在本表里出现了不止一次",IF(AND(N($U41)>0,N($T41)=0),"※填了实际付息日但没填应付息日","")))))
A42: =IF($D42="","",COUNTA($D$4:$D42)) | B42: 不动产 | C42: 在当 | D42: 陈征 | E42: 18605916313 | G42: 45982 | H42: 46072 | J42: 200000 | K42: 0.025 | L42: 5000 | S42: =IF($D42="","",ROUND(N($N42)+N($O42)+N($P42)+N($Q42)+N($R42),2)) | T42: 46285 | V42: =IF($D42="","",IF(OR($T42="",$U42=""),0,MAX(0,INT($U42)-INT($T42)))) | W42: =IF($D42="","",ROUND(MAX(0,N($J42)*日滞纳金率*N($V42)-N($R42)),2)) | X42: 先息 | AA42: =IF($D42="","",IF(AND($C42<>"",ISNA(MATCH($C42,状态表,0))),"※状态不在【资料】里",IF(AND($G42<>"",$H42<>"",$H42<$G42),"※到期日早于当票日期",IF(AND($F42<>"",COUNTIF($F$4:$F$123,$F42)>1),"※当票号在本表里出现了不止一次",IF(AND(N($U42)>0,N($T42)=0),"※填了实际付息日但没填应付息日","")))))
A43: =IF($D43="","",COUNTA($D$4:$D43)) | B43: 车位 | C43: 在当 | D43: 汤静 | E43: 13860608323 | F43: 3519260513 | G43: 46037 | H43: 46216 | J43: 53000 | K43: 0.025 | L43: 1500 | S43: =IF($D43="","",ROUND(N($N43)+N($O43)+N($P43)+N($Q43)+N($R43),2)) | T43: 46188 | V43: =IF($D43="","",IF(OR($T43="",$U43=""),0,MAX(0,INT($U43)-INT($T43)))) | W43: =IF($D43="","",ROUND(MAX(0,N($J43)*日滞纳金率*N($V43)-N($R43)),2)) | AA43: =IF($D43="","",IF(AND($C43<>"",ISNA(MATCH($C43,状态表,0))),"※状态不在【资料】里",IF(AND($G43<>"",$H43<>"",$H43<$G43),"※到期日早于当票日期",IF(AND($F43<>"",COUNTIF($F$4:$F$123,$F43)>1),"※当票号在本表里出现了不止一次",IF(AND(N($U43)>0,N($T43)=0),"※填了实际付息日但没填应付息日","")))))
A44: =IF($D44="","",COUNTA($D$4:$D44)) | B44: 不动产 | C44: 在当 | D44: 林浩 | E44: 13067317996 | F44: 3519260512 | G44: 46037 | H44: 46096 | J44: 100000 | K44: 0.025 | L44: 2500 | S44: =IF($D44="","",ROUND(N($N44)+N($O44)+N($P44)+N($Q44)+N($R44),2)) | T44: 46280 | V44: =IF($D44="","",IF(OR($T44="",$U44=""),0,MAX(0,INT($U44)-INT($T44)))) | W44: =IF($D44="","",ROUND(MAX(0,N($J44)*日滞纳金率*N($V44)-N($R44)),2)) | AA44: =IF($D44="","",IF(AND($C44<>"",ISNA(MATCH($C44,状态表,0))),"※状态不在【资料】里",IF(AND($G44<>"",$H44<>"",$H44<$G44),"※到期日早于当票日期",IF(AND($F44<>"",COUNTIF($F$4:$F$123,$F44)>1),"※当票号在本表里出现了不止一次",IF(AND(N($U44)>0,N($T44)=0),"※填了实际付息日但没填应付息日","")))))
A45: =IF($D45="","",COUNTA($D$4:$D45)) | B45: 动产 | C45: 虚当 | D45: 陈乐贵 | F45: 3519260516 | G45: 46059 | I45: 45484 | J45: 500000 | K45: 0.005 | S45: =IF($D45="","",ROUND(N($N45)+N($O45)+N($P45)+N($Q45)+N($R45),2)) | T45: 46059 | V45: =IF($D45="","",IF(OR($T45="",$U45=""),0,MAX(0,INT($U45)-INT($T45)))) | W45: =IF($D45="","",ROUND(MAX(0,N($J45)*日滞纳金率*N($V45)-N($R45)),2)) | X45: 后息 | AA45: =IF($D45="","",IF(AND($C45<>"",ISNA(MATCH($C45,状态表,0))),"※状态不在【资料】里",IF(AND($G45<>"",$H45<>"",$H45<$G45),"※到期日早于当票日期",IF(AND($F45<>"",COUNTIF($F$4:$F$123,$F45)>1),"※当票号在本表里出现了不止一次",IF(AND(N($U45)>0,N($T45)=0),"※填了实际付息日但没填应付息日","")))))
A46: =IF($D46="","",COUNTA($D$4:$D46)) | B46: 不动产 | C46: 在当 | D46: 马昱 | E46: 13515003389 | F46: 3519260517 | G46: 46066 | H46: 46244 | J46: 500000 | K46: 0.025 | L46: 12500 | S46: =IF($D46="","",ROUND(N($N46)+N($O46)+N($P46)+N($Q46)+N($R46),2)) | T46: 46278 | V46: =IF($D46="","",IF(OR($T46="",$U46=""),0,MAX(0,INT($U46)-INT($T46)))) | W46: =IF($D46="","",ROUND(MAX(0,N($J46)*日滞纳金率*N($V46)-N($R46)),2)) | AA46: =IF($D46="","",IF(AND($C46<>"",ISNA(MATCH($C46,状态表,0))),"※状态不在【资料】里",IF(AND($G46<>"",$H46<>"",$H46<$G46),"※到期日早于当票日期",IF(AND($F46<>"",COUNTIF($F$4:$F$123,$F46)>1),"※当票号在本表里出现了不止一次",IF(AND(N($U46)>0,N($T46)=0),"※填了实际付息日但没填应付息日","")))))
A47: =IF($D47="","",COUNTA($D$4:$D47)) | B47: 名品 | C47: 虚当 | D47: 胡建通 | E47: 13805082625 | F47: 3519260519 | G47: 46097 | J47: 330000 | K47: 0.0007 | L47: 231 | S47: =IF($D47="","",ROUND(N($N47)+N($O47)+N($P47)+N($Q47)+N($R47),2)) | T47: 46097 | V47: =IF($D47="","",IF(OR($T47="",$U47=""),0,MAX(0,INT($U47)-INT($T47)))) | W47: =IF($D47="","",ROUND(MAX(0,N($J47)*日滞纳金率*N($V47)-N($R47)),2)) | AA47: =IF($D47="","",IF(AND($C47<>"",ISNA(MATCH($C47,状态表,0))),"※状态不在【资料】里",IF(AND($G47<>"",$H47<>"",$H47<$G47),"※到期日早于当票日期",IF(AND($F47<>"",COUNTIF($F$4:$F$123,$F47)>1),"※当票号在本表里出现了不止一次",IF(AND(N($U47)>0,N($T47)=0),"※填了实际付息日但没填应付息日","")))))
A48: =IF($D48="","",COUNTA($D$4:$D48)) | B48: 黄金 | C48: 在当 | D48: 廖浴波 | E48: 13960987280 | F48: 3519260520 | G48: 46099 | H48: 46278 | J48: 35000 | K48: 0.003 | L48: 800 | N48: 105 | S48: =IF($D48="","",ROUND(N($N48)+N($O48)+N($P48)+N($Q48)+N($R48),2)) | T48: 46282 | V48: =IF($D48="","",IF(OR($T48="",$U48=""),0,MAX(0,INT($U48)-INT($T48)))) | W48: =IF($D48="","",ROUND(MAX(0,N($J48)*日滞纳金率*N($V48)-N($R48)),2)) | AA48: =IF($D48="","",IF(AND($C48<>"",ISNA(MATCH($C48,状态表,0))),"※状态不在【资料】里",IF(AND($G48<>"",$H48<>"",$H48<$G48),"※到期日早于当票日期",IF(AND($F48<>"",COUNTIF($F$4:$F$123,$F48)>1),"※当票号在本表里出现了不止一次",IF(AND(N($U48)>0,N($T48)=0),"※填了实际付息日但没填应付息日","")))))
A49: =IF($D49="","",COUNTA($D$4:$D49)) | B49: 不动产 | C49: 在当 | D49: 林鹏 | E49: 15005914264 | F49: 3519260522 | G49: 46111 | H49: 46290 | J49: 100000 | K49: 0.02 | L49: 2000 | S49: =IF($D49="","",ROUND(N($N49)+N($O49)+N($P49)+N($Q49)+N($R49),2)) | T49: 46294 | V49: =IF($D49="","",IF(OR($T49="",$U49=""),0,MAX(0,INT($U49)-INT($T49)))) | W49: =IF($D49="","",ROUND(MAX(0,N($J49)*日滞纳金率*N($V49)-N($R49)),2)) | AA49: =IF($D49="","",IF(AND($C49<>"",ISNA(MATCH($C49,状态表,0))),"※状态不在【资料】里",IF(AND($G49<>"",$H49<>"",$H49<$G49),"※到期日早于当票日期",IF(AND($F49<>"",COUNTIF($F$4:$F$123,$F49)>1),"※当票号在本表里出现了不止一次",IF(AND(N($U49)>0,N($T49)=0),"※填了实际付息日但没填应付息日","")))))
A50: =IF($D50="","",COUNTA($D$4:$D50)) | B50: 不动产 | C50: 在当 | D50: 林鹏 | E50: 18805023484 | F50: 3524019227 | G50: 46163 | H50: 46252 | J50: 50000 | K50: 0.02 | L50: 1000 | S50: =IF($D50="","",ROUND(N($N50)+N($O50)+N($P50)+N($Q50)+N($R50),2)) | T50: 46285 | V50: =IF($D50="","",IF(OR($T50="",$U50=""),0,MAX(0,INT($U50)-INT($T50)))) | W50: =IF($D50="","",ROUND(MAX(0,N($J50)*日滞纳金率*N($V50)-N($R50)),2)) | AA50: =IF($D50="","",IF(AND($C50<>"",ISNA(MATCH($C50,状态表,0))),"※状态不在【资料】里",IF(AND($G50<>"",$H50<>"",$H50<$G50),"※到期日早于当票日期",IF(AND($F50<>"",COUNTIF($F$4:$F$123,$F50)>1),"※当票号在本表里出现了不止一次",IF(AND(N($U50)>0,N($T50)=0),"※填了实际付息日但没填应付息日","")))))
A51: =IF($D51="","",COUNTA($D$4:$D51)) | B51: 不动产 | C51: 结款未赎 | D51: 郑祥波 | E51: 13850175177 | F51: 3519260523 | G51: 46149 | H51: 46238 | J51: 20000 | K51: 0.025 | L51: 500 | S51: =IF($D51="","",ROUND(N($N51)+N($O51)+N($P51)+N($Q51)+N($R51),2)) | T51: 46149 | V51: =IF($D51="","",IF(OR($T51="",$U51=""),0,MAX(0,INT($U51)-INT($T51)))) | W51: =IF($D51="","",ROUND(MAX(0,N($J51)*日滞纳金率*N($V51)-N($R51)),2)) | AA51: =IF($D51="","",IF(AND($C51<>"",ISNA(MATCH($C51,状态表,0))),"※状态不在【资料】里",IF(AND($G51<>"",$H51<>"",$H51<$G51),"※到期日早于当票日期",IF(AND($F51<>"",COUNTIF($F$4:$F$123,$F51)>1),"※当票号在本表里出现了不止一次",IF(AND(N($U51)>0,N($T51)=0),"※填了实际付息日但没填应付息日","")))))
A52: =IF($D52="","",COUNTA($D$4:$D52)) | B52: 包包 | C52: 在当 | D52: 魏洁 | E52: 13306046018 | F52: 3519260525 | G52: 46156 | H52: 46185 | J52: 100000 | K52: 0.005 | L52: 3000 | N52: 500 | S52: =IF($D52="","",ROUND(N($N52)+N($O52)+N($P52)+N($Q52)+N($R52),2)) | T52: 46277 | V52: =IF($D52="","",IF(OR($T52="",$U52=""),0,MAX(0,INT($U52)-INT($T52)))) | W52: =IF($D52="","",ROUND(MAX(0,N($J52)*日滞纳金率*N($V52)-N($R52)),2)) | AA52: =IF($D52="","",IF(AND($C52<>"",ISNA(MATCH($C52,状态表,0))),"※状态不在【资料】里",IF(AND($G52<>"",$H52<>"",$H52<$G52),"※到期日早于当票日期",IF(AND($F52<>"",COUNTIF($F$4:$F$123,$F52)>1),"※当票号在本表里出现了不止一次",IF(AND(N($U52)>0,N($T52)=0),"※填了实际付息日但没填应付息日","")))))
A53: =IF($D53="","",COUNTA($D$4:$D53)) | B53: 车子 | C53: 在当 | D53: 陈忠军 | E53: 18105915567 | F53: 3524019226 | G53: 46160 | H53: 46219 | J53: 93000 | K53: 0.005 | L53: 2875 | N53: 465 | S53: =IF($D53="","",ROUND(N($N53)+N($O53)+N($P53)+N($Q53)+N($R53),2)) | T53: 46282 | V53: =IF($D53="","",IF(OR($T53="",$U53=""),0,MAX(0,INT($U53)-INT($T53)))) | W53: =IF($D53="","",ROUND(MAX(0,N($J53)*日滞纳金率*N($V53)-N($R53)),2)) | AA53: =IF($D53="","",IF(AND($C53<>"",ISNA(MATCH($C53,状态表,0))),"※状态不在【资料】里",IF(AND($G53<>"",$H53<>"",$H53<$G53),"※到期日早于当票日期",IF(AND($F53<>"",COUNTIF($F$4:$F$123,$F53)>1),"※当票号在本表里出现了不止一次",IF(AND(N($U53)>0,N($T53)=0),"※填了实际付息日但没填应付息日","")))))
A54: =IF($D54="","",COUNTA($D$4:$D54)) | B54: 名品 | C54: 虚当 | D54: 柯志宏 | E54: 15060433337 | G54: 46168 | H54: 46183 | J54: 300000 | K54: 0.004 | L54: 1200 | S54: =IF($D54="","",ROUND(N($N54)+N($O54)+N($P54)+N($Q54)+N($R54),2)) | T54: 46168 | V54: =IF($D54="","",IF(OR($T54="",$U54=""),0,MAX(0,INT($U54)-INT($T54)))) | W54: =IF($D54="","",ROUND(MAX(0,N($J54)*日滞纳金率*N($V54)-N($R54)),2)) | AA54: =IF($D54="","",IF(AND($C54<>"",ISNA(MATCH($C54,状态表,0))),"※状态不在【资料】里",IF(AND($G54<>"",$H54<>"",$H54<$G54),"※到期日早于当票日期",IF(AND($F54<>"",COUNTIF($F$4:$F$123,$F54)>1),"※当票号在本表里出现了不止一次",IF(AND(N($U54)>0,N($T54)=0),"※填了实际付息日但没填应付息日","")))))
A55: =IF($D55="","",COUNTA($D$4:$D55)) | B55: 黄金 | C55: 在当 | D55: 叶敏 | E55: 13003800159 | F55: 3524019231 | G55: 46174 | H55: 46353 | J55: 208000 | K55: 0.0045 | L55: 5200 | N55: 936 | S55: =IF($D55="","",ROUND(N($N55)+N($O55)+N($P55)+N($Q55)+N($R55),2)) | T55: 46295 | V55: =IF($D55="","",IF(OR($T55="",$U55=""),0,MAX(0,INT($U55)-INT($T55)))) | W55: =IF($D55="","",ROUND(MAX(0,N($J55)*日滞纳金率*N($V55)-N($R55)),2)) | AA55: =IF($D55="","",IF(AND($C55<>"",ISNA(MATCH($C55,状态表,0))),"※状态不在【资料】里",IF(AND($G55<>"",$H55<>"",$H55<$G55),"※到期日早于当票日期",IF(AND($F55<>"",COUNTIF($F$4:$F$123,$F55)>1),"※当票号在本表里出现了不止一次",IF(AND(N($U55)>0,N($T55)=0),"※填了实际付息日但没填应付息日","")))))
A56: =IF($D56="","",COUNTA($D$4:$D56)) | B56: 不动产 | C56: 在当 | D56: 陈建华 | E56: 13609595117 | F56: 3524019230 | G56: 46173 | H56: 46202 | J56: 200000 | K56: 0.025 | L56: 5000 | S56: =IF($D56="","",ROUND(N($N56)+N($O56)+N($P56)+N($Q56)+N($R56),2)) | T56: 46266 | U56: 46266 | V56: =IF($D56="","",IF(OR($T56="",$U56=""),0,MAX(0,INT($U56)-INT($T56)))) | W56: =IF($D56="","",ROUND(MAX(0,N($J56)*日滞纳金率*N($V56)-N($R56)),2)) | AA56: =IF($D56="","",IF(AND($C56<>"",ISNA(MATCH($C56,状态表,0))),"※状态不在【资料】里",IF(AND($G56<>"",$H56<>"",$H56<$G56),"※到期日早于当票日期",IF(AND($F56<>"",COUNTIF($F$4:$F$123,$F56)>1),"※当票号在本表里出现了不止一次",IF(AND(N($U56)>0,N($T56)=0),"※填了实际付息日但没填应付息日","")))))
A57: =IF($D57="","",COUNTA($D$4:$D57)) | B57: 黄金 | C57: 虚当 | D57: 魏文冬 | E57: 15159647120 | F57: 3524019232 | G57: 46182 | H57: 46211 | J57: 350000 | K57: 0.001 | L57: 350 | S57: =IF($D57="","",ROUND(N($N57)+N($O57)+N($P57)+N($Q57)+N($R57),2)) | T57: 46182 | V57: =IF($D57="","",IF(OR($T57="",$U57=""),0,MAX(0,INT($U57)-INT($T57)))) | W57: =IF($D57="","",ROUND(MAX(0,N($J57)*日滞纳金率*N($V57)-N($R57)),2)) | AA57: =IF($D57="","",IF(AND($C57<>"",ISNA(MATCH($C57,状态表,0))),"※状态不在【资料】里",IF(AND($G57<>"",$H57<>"",$H57<$G57),"※到期日早于当票日期",IF(AND($F57<>"",COUNTIF($F$4:$F$123,$F57)>1),"※当票号在本表里出现了不止一次",IF(AND(N($U57)>0,N($T57)=0),"※填了实际付息日但没填应付息日","")))))
A58: =IF($D58="","",COUNTA($D$4:$D58)) | B58: 黄金 | C58: 在当 | D58: 何博文 | E58: 13763816036 | F58: 3524019233 | G58: 46183 | H58: 46362 | J58: 18000 | K58: 0.005 | L58: 540 | N58: 90 | S58: =IF($D58="","",ROUND(N($N58)+N($O58)+N($P58)+N($Q58)+N($R58),2)) | T58: 46274 | U58: 46274 | V58: =IF($D58="","",IF(OR($T58="",$U58=""),0,MAX(0,INT($U58)-INT($T58)))) | W58: =IF($D58="","",ROUND(MAX(0,N($J58)*日滞纳金率*N($V58)-N($R58)),2)) | AA58: =IF($D58="","",IF(AND($C58<>"",ISNA(MATCH($C58,状态表,0))),"※状态不在【资料】里",IF(AND($G58<>"",$H58<>"",$H58<$G58),"※到期日早于当票日期",IF(AND($F58<>"",COUNTIF($F$4:$F$123,$F58)>1),"※当票号在本表里出现了不止一次",IF(AND(N($U58)>0,N($T58)=0),"※填了实际付息日但没填应付息日","")))))
A59: =IF($D59="","",COUNTA($D$4:$D59)) | B59: 手表 | C59: 在当 | D59: 黄远枝 | E59: 13509523067 | F59: 3524019235 | G59: 46195 | H59: 46374 | J59: 60000 | K59: 0.004 | L59: 1500 | N59: 240 | S59: =IF($D59="","",ROUND(N($N59)+N($O59)+N($P59)+N($Q59)+N($R59),2)) | T59: 46286 | V59: =IF($D59="","",IF(OR($T59="",$U59=""),0,MAX(0,INT($U59)-INT($T59)))) | W59: =IF($D59="","",ROUND(MAX(0,N($J59)*日滞纳金率*N($V59)-N($R59)),2)) | AA59: =IF($D59="","",IF(AND($C59<>"",ISNA(MATCH($C59,状态表,0))),"※状态不在【资料】里",IF(AND($G59<>"",$H59<>"",$H59<$G59),"※到期日早于当票日期",IF(AND($F59<>"",COUNTIF($F$4:$F$123,$F59)>1),"※当票号在本表里出现了不止一次",IF(AND(N($U59)>0,N($T59)=0),"※填了实际付息日但没填应付息日","")))))
A60: =IF($D60="","",COUNTA($D$4:$D60)) | B60: 车子 | C60: 在当 | D60: 蒙媛媛 | E60: 18259980798 | F60: 3524019237 | G60: 46210 | H60: 46389 | J60: 43750.01 | K60: 0.025 | L60: 1250 | S60: =IF($D60="","",ROUND(N($N60)+N($O60)+N($P60)+N($Q60)+N($R60),2)) | T60: 46271 | U60: 46271 | V60: =IF($D60="","",IF(OR($T60="",$U60=""),0,MAX(0,INT($U60)-INT($T60)))) | W60: =IF($D60="","",ROUND(MAX(0,N($J60)*日滞纳金率*N($V60)-N($R60)),2)) | AA60: =IF($D60="","",IF(AND($C60<>"",ISNA(MATCH($C60,状态表,0))),"※状态不在【资料】里",IF(AND($G60<>"",$H60<>"",$H60<$G60),"※到期日早于当票日期",IF(AND($F60<>"",COUNTIF($F$4:$F$123,$F60)>1),"※当票号在本表里出现了不止一次",IF(AND(N($U60)>0,N($T60)=0),"※填了实际付息日但没填应付息日","")))))
A61: =IF($D61="","",COUNTA($D$4:$D61)) | B61: 房产 | C61: 结款未赎 | D61: 汪琼宇 | E61: 13860629781 | F61: 3524019243 | G61: 46219 | H61: 46398 | J61: 400000 | K61: 0.018 | L61: 7200 | S61: =IF($D61="","",ROUND(N($N61)+N($O61)+N($P61)+N($Q61)+N($R61),2)) | T61: 46250 | V61: =IF($D61="","",IF(OR($T61="",$U61=""),0,MAX(0,INT($U61)-INT($T61)))) | W61: =IF($D61="","",ROUND(MAX(0,N($J61)*日滞纳金率*N($V61)-N($R61)),2)) | AA61: =IF($D61="","",IF(AND($C61<>"",ISNA(MATCH($C61,状态表,0))),"※状态不在【资料】里",IF(AND($G61<>"",$H61<>"",$H61<$G61),"※到期日早于当票日期",IF(AND($F61<>"",COUNTIF($F$4:$F$123,$F61)>1),"※当票号在本表里出现了不止一次",IF(AND(N($U61)>0,N($T61)=0),"※填了实际付息日但没填应付息日","")))))
A62: =IF($D62="","",COUNTA($D$4:$D62)) | B62: 房产 | C62: 结款未赎 | D62: 汪琼宇 | E62: 13860629781 | G62: 46230 | H62: 46407 | J62: 200000 | K62: 0.018 | L62: 3600 | S62: =IF($D62="","",ROUND(N($N62)+N($O62)+N($P62)+N($Q62)+N($R62),2)) | T62: 46261 | V62: =IF($D62="","",IF(OR($T62="",$U62=""),0,MAX(0,INT($U62)-INT($T62)))) | W62: =IF($D62="","",ROUND(MAX(0,N($J62)*日滞纳金率*N($V62)-N($R62)),2)) | AA62: =IF($D62="","",IF(AND($C62<>"",ISNA(MATCH($C62,状态表,0))),"※状态不在【资料】里",IF(AND($G62<>"",$H62<>"",$H62<$G62),"※到期日早于当票日期",IF(AND($F62<>"",COUNTIF($F$4:$F$123,$F62)>1),"※当票号在本表里出现了不止一次",IF(AND(N($U62)>0,N($T62)=0),"※填了实际付息日但没填应付息日","")))))
A63: =IF($D63="","",COUNTA($D$4:$D63)) | B63: 房产 | C63: 结款未赎 | D63: 汪琼宇 | E63: 13860629781 | G63: 46234 | H63: 46412 | J63: 100000 | K63: 0.018 | L63: 1800 | S63: =IF($D63="","",ROUND(N($N63)+N($O63)+N($P63)+N($Q63)+N($R63),2)) | T63: 46264 | V63: =IF($D63="","",IF(OR($T63="",$U63=""),0,MAX(0,INT($U63)-INT($T63)))) | W63: =IF($D63="","",ROUND(MAX(0,N($J63)*日滞纳金率*N($V63)-N($R63)),2)) | AA63: =IF($D63="","",IF(AND($C63<>"",ISNA(MATCH($C63,状态表,0))),"※状态不在【资料】里",IF(AND($G63<>"",$H63<>"",$H63<$G63),"※到期日早于当票日期",IF(AND($F63<>"",COUNTIF($F$4:$F$123,$F63)>1),"※当票号在本表里出现了不止一次",IF(AND(N($U63)>0,N($T63)=0),"※填了实际付息日但没填应付息日","")))))
A64: =IF($D64="","",COUNTA($D$4:$D64)) | B64: 房产 | C64: 在当 | D64: 林昌耿 | E64: 13705954599 | F64: 3524019239 | G64: 46223 | H64: 46402 | J64: 200000 | K64: 0.025 | L64: 5000 | S64: =IF($D64="","",ROUND(N($N64)+N($O64)+N($P64)+N($Q64)+N($R64),2)) | T64: 46223 | V64: =IF($D64="","",IF(OR($T64="",$U64=""),0,MAX(0,INT($U64)-INT($T64)))) | W64: =IF($D64="","",ROUND(MAX(0,N($J64)*日滞纳金率*N($V64)-N($R64)),2)) | AA64: =IF($D64="","",IF(AND($C64<>"",ISNA(MATCH($C64,状态表,0))),"※状态不在【资料】里",IF(AND($G64<>"",$H64<>"",$H64<$G64),"※到期日早于当票日期",IF(AND($F64<>"",COUNTIF($F$4:$F$123,$F64)>1),"※当票号在本表里出现了不止一次",IF(AND(N($U64)>0,N($T64)=0),"※填了实际付息日但没填应付息日","")))))
A65: =IF($D65="","",COUNTA($D$4:$D65)) | B65: 黄金 | C65: 在当 | D65: 施鉴波 | E65: 15695902836 | F65: 3524019242 | G65: 46226 | H65: 46405 | J65: 17000 | K65: 0.005 | L65: 425 | N65: 85 | S65: =IF($D65="","",ROUND(N($N65)+N($O65)+N($P65)+N($Q65)+N($R65),2)) | T65: 46256 | U65: 46255 | V65: =IF($D65="","",IF(OR($T65="",$U65=""),0,MAX(0,INT($U65)-INT($T65)))) | W65: =IF($D65="","",ROUND(MAX(0,N($J65)*日滞纳金率*N($V65)-N($R65)),2)) | AA65: =IF($D65="","",IF(AND($C65<>"",ISNA(MATCH($C65,状态表,0))),"※状态不在【资料】里",IF(AND($G65<>"",$H65<>"",$H65<$G65),"※到期日早于当票日期",IF(AND($F65<>"",COUNTIF($F$4:$F$123,$F65)>1),"※当票号在本表里出现了不止一次",IF(AND(N($U65)>0,N($T65)=0),"※填了实际付息日但没填应付息日","")))))
A66: =IF($D66="","",COUNTA($D$4:$D66)) | B66: 不动产 | C66: 在当 | D66: 叶守芳 | E66: 13860651148 | F66: 3524019241 | G66: 46225 | H66: 46314 | J66: 200000 | K66: 0.023 | L66: 4600 | S66: =IF($D66="","",ROUND(N($N66)+N($O66)+N($P66)+N($Q66)+N($R66),2)) | T66: 46295 | V66: =IF($D66="","",IF(OR($T66="",$U66=""),0,MAX(0,INT($U66)-INT($T66)))) | W66: =IF($D66="","",ROUND(MAX(0,N($J66)*日滞纳金率*N($V66)-N($R66)),2)) | AA66: =IF($D66="","",IF(AND($C66<>"",ISNA(MATCH($C66,状态表,0))),"※状态不在【资料】里",IF(AND($G66<>"",$H66<>"",$H66<$G66),"※到期日早于当票日期",IF(AND($F66<>"",COUNTIF($F$4:$F$123,$F66)>1),"※当票号在本表里出现了不止一次",IF(AND(N($U66)>0,N($T66)=0),"※填了实际付息日但没填应付息日","")))))
A67: =IF($D67="","",COUNTA($D$4:$D67)) | B67: 房产 | C67: 在当 | D67: 黄飞 | E67: 17759887551 | F67: 3524019245 | G67: 46261 | H67: 46350 | J67: 120000 | K67: 0.025 | L67: 3000 | S67: =IF($D67="","",ROUND(N($N67)+N($O67)+N($P67)+N($Q67)+N($R67),2)) | T67: 46291 | V67: =IF($D67="","",IF(OR($T67="",$U67=""),0,MAX(0,INT($U67)-INT($T67)))) | W67: =IF($D67="","",ROUND(MAX(0,N($J67)*日滞纳金率*N($V67)-N($R67)),2)) | AA67: =IF($D67="","",IF(AND($C67<>"",ISNA(MATCH($C67,状态表,0))),"※状态不在【资料】里",IF(AND($G67<>"",$H67<>"",$H67<$G67),"※到期日早于当票日期",IF(AND($F67<>"",COUNTIF($F$4:$F$123,$F67)>1),"※当票号在本表里出现了不止一次",IF(AND(N($U67)>0,N($T67)=0),"※填了实际付息日但没填应付息日","")))))
A68: =IF($D68="","",COUNTA($D$4:$D68)) | B68: 黄金 | C68: 在当 | D68: 林凯鑫 | E68: 15880077948 | F68: 3524019246 | G68: 46266 | H68: 46445 | J68: 90000 | K68: 0.003 | L68: 1350 | N68: 270 | S68: =IF($D68="","",ROUND(N($N68)+N($O68)+N($P68)+N($Q68)+N($R68),2)) | T68: 46266 | U68: 46266 | V68: =IF($D68="","",IF(OR($T68="",$U68=""),0,MAX(0,INT($U68)-INT($T68)))) | W68: =IF($D68="","",ROUND(MAX(0,N($J68)*日滞纳金率*N($V68)-N($R68)),2)) | AA68: =IF($D68="","",IF(AND($C68<>"",ISNA(MATCH($C68,状态表,0))),"※状态不在【资料】里",IF(AND($G68<>"",$H68<>"",$H68<$G68),"※到期日早于当票日期",IF(AND($F68<>"",COUNTIF($F$4:$F$123,$F68)>1),"※当票号在本表里出现了不止一次",IF(AND(N($U68)>0,N($T68)=0),"※填了实际付息日但没填应付息日","")))))
A69: =IF($D69="","",COUNTA($D$4:$D69)) | B69: 黄金 | C69: 在当 | D69: 曾云 | E69: 15232998080 | F69: 3524019247 | G69: 46274 | H69: 46453 | J69: 85000 | K69: 0.003 | L69: 2000 | N69: 255 | S69: =IF($D69="","",ROUND(N($N69)+N($O69)+N($P69)+N($Q69)+N($R69),2)) | T69: 46274 | U69: 46274 | V69: =IF($D69="","",IF(OR($T69="",$U69=""),0,MAX(0,INT($U69)-INT($T69)))) | W69: =IF($D69="","",ROUND(MAX(0,N($J69)*日滞纳金率*N($V69)-N($R69)),2)) | AA69: =IF($D69="","",IF(AND($C69<>"",ISNA(MATCH($C69,状态表,0))),"※状态不在【资料】里",IF(AND($G69<>"",$H69<>"",$H69<$G69),"※到期日早于当票日期",IF(AND($F69<>"",COUNTIF($F$4:$F$123,$F69)>1),"※当票号在本表里出现了不止一次",IF(AND(N($U69)>0,N($T69)=0),"※填了实际付息日但没填应付息日","")))))
A70: =IF($D70="","",COUNTA($D$4:$D70)) | B70: 黄金 | C70: 在当 | D70: 张帆 | E70: 18859177111 | F70: 3524019249 | G70: 46275 | H70: 46090 | J70: 70000 | K70: 0.003 | L70: 1400 | N70: 210 | S70: =IF($D70="","",ROUND(N($N70)+N($O70)+N($P70)+N($Q70)+N($R70),2)) | T70: 46275 | U70: 46275 | V70: =IF($D70="","",IF(OR($T70="",$U70=""),0,MAX(0,INT($U70)-INT($T70)))) | W70: =IF($D70="","",ROUND(MAX(0,N($J70)*日滞纳金率*N($V70)-N($R70)),2)) | AA70: =IF($D70="","",IF(AND($C70<>"",ISNA(MATCH($C70,状态表,0))),"※状态不在【资料】里",IF(AND($G70<>"",$H70<>"",$H70<$G70),"※到期日早于当票日期",IF(AND($F70<>"",COUNTIF($F$4:$F$123,$F70)>1),"※当票号在本表里出现了不止一次",IF(AND(N($U70)>0,N($T70)=0),"※填了实际付息日但没填应付息日","")))))
A71: =IF($D71="","",COUNTA($D$4:$D71)) | S71: =IF($D71="","",ROUND(N($N71)+N($O71)+N($P71)+N($Q71)+N($R71),2)) | V71: =IF($D71="","",IF(OR($T71="",$U71=""),0,MAX(0,INT($U71)-INT($T71)))) | W71: =IF($D71="","",ROUND(MAX(0,N($J71)*日滞纳金率*N($V71)-N($R71)),2)) | AA71: =IF($D71="","",IF(AND($C71<>"",ISNA(MATCH($C71,状态表,0))),"※状态不在【资料】里",IF(AND($G71<>"",$H71<>"",$H71<$G71),"※到期日早于当票日期",IF(AND($F71<>"",COUNTIF($F$4:$F$123,$F71)>1),"※当票号在本表里出现了不止一次",IF(AND(N($U71)>0,N($T71)=0),"※填了实际付息日但没填应付息日","")))))
A72: =IF($D72="","",COUNTA($D$4:$D72)) | S72: =IF($D72="","",ROUND(N($N72)+N($O72)+N($P72)+N($Q72)+N($R72),2)) | V72: =IF($D72="","",IF(OR($T72="",$U72=""),0,MAX(0,INT($U72)-INT($T72)))) | W72: =IF($D72="","",ROUND(MAX(0,N($J72)*日滞纳金率*N($V72)-N($R72)),2)) | AA72: =IF($D72="","",IF(AND($C72<>"",ISNA(MATCH($C72,状态表,0))),"※状态不在【资料】里",IF(AND($G72<>"",$H72<>"",$H72<$G72),"※到期日早于当票日期",IF(AND($F72<>"",COUNTIF($F$4:$F$123,$F72)>1),"※当票号在本表里出现了不止一次",IF(AND(N($U72)>0,N($T72)=0),"※填了实际付息日但没填应付息日","")))))
A73: =IF($D73="","",COUNTA($D$4:$D73)) | S73: =IF($D73="","",ROUND(N($N73)+N($O73)+N($P73)+N($Q73)+N($R73),2)) | V73: =IF($D73="","",IF(OR($T73="",$U73=""),0,MAX(0,INT($U73)-INT($T73)))) | W73: =IF($D73="","",ROUND(MAX(0,N($J73)*日滞纳金率*N($V73)-N($R73)),2)) | AA73: =IF($D73="","",IF(AND($C73<>"",ISNA(MATCH($C73,状态表,0))),"※状态不在【资料】里",IF(AND($G73<>"",$H73<>"",$H73<$G73),"※到期日早于当票日期",IF(AND($F73<>"",COUNTIF($F$4:$F$123,$F73)>1),"※当票号在本表里出现了不止一次",IF(AND(N($U73)>0,N($T73)=0),"※填了实际付息日但没填应付息日","")))))
A74: =IF($D74="","",COUNTA($D$4:$D74)) | S74: =IF($D74="","",ROUND(N($N74)+N($O74)+N($P74)+N($Q74)+N($R74),2)) | V74: =IF($D74="","",IF(OR($T74="",$U74=""),0,MAX(0,INT($U74)-INT($T74)))) | W74: =IF($D74="","",ROUND(MAX(0,N($J74)*日滞纳金率*N($V74)-N($R74)),2)) | AA74: =IF($D74="","",IF(AND($C74<>"",ISNA(MATCH($C74,状态表,0))),"※状态不在【资料】里",IF(AND($G74<>"",$H74<>"",$H74<$G74),"※到期日早于当票日期",IF(AND($F74<>"",COUNTIF($F$4:$F$123,$F74)>1),"※当票号在本表里出现了不止一次",IF(AND(N($U74)>0,N($T74)=0),"※填了实际付息日但没填应付息日","")))))
A75: =IF($D75="","",COUNTA($D$4:$D75)) | S75: =IF($D75="","",ROUND(N($N75)+N($O75)+N($P75)+N($Q75)+N($R75),2)) | V75: =IF($D75="","",IF(OR($T75="",$U75=""),0,MAX(0,INT($U75)-INT($T75)))) | W75: =IF($D75="","",ROUND(MAX(0,N($J75)*日滞纳金率*N($V75)-N($R75)),2)) | AA75: =IF($D75="","",IF(AND($C75<>"",ISNA(MATCH($C75,状态表,0))),"※状态不在【资料】里",IF(AND($G75<>"",$H75<>"",$H75<$G75),"※到期日早于当票日期",IF(AND($F75<>"",COUNTIF($F$4:$F$123,$F75)>1),"※当票号在本表里出现了不止一次",IF(AND(N($U75)>0,N($T75)=0),"※填了实际付息日但没填应付息日","")))))
A76: =IF($D76="","",COUNTA($D$4:$D76)) | S76: =IF($D76="","",ROUND(N($N76)+N($O76)+N($P76)+N($Q76)+N($R76),2)) | V76: =IF($D76="","",IF(OR($T76="",$U76=""),0,MAX(0,INT($U76)-INT($T76)))) | W76: =IF($D76="","",ROUND(MAX(0,N($J76)*日滞纳金率*N($V76)-N($R76)),2)) | AA76: =IF($D76="","",IF(AND($C76<>"",ISNA(MATCH($C76,状态表,0))),"※状态不在【资料】里",IF(AND($G76<>"",$H76<>"",$H76<$G76),"※到期日早于当票日期",IF(AND($F76<>"",COUNTIF($F$4:$F$123,$F76)>1),"※当票号在本表里出现了不止一次",IF(AND(N($U76)>0,N($T76)=0),"※填了实际付息日但没填应付息日","")))))
A77: =IF($D77="","",COUNTA($D$4:$D77)) | S77: =IF($D77="","",ROUND(N($N77)+N($O77)+N($P77)+N($Q77)+N($R77),2)) | V77: =IF($D77="","",IF(OR($T77="",$U77=""),0,MAX(0,INT($U77)-INT($T77)))) | W77: =IF($D77="","",ROUND(MAX(0,N($J77)*日滞纳金率*N($V77)-N($R77)),2)) | AA77: =IF($D77="","",IF(AND($C77<>"",ISNA(MATCH($C77,状态表,0))),"※状态不在【资料】里",IF(AND($G77<>"",$H77<>"",$H77<$G77),"※到期日早于当票日期",IF(AND($F77<>"",COUNTIF($F$4:$F$123,$F77)>1),"※当票号在本表里出现了不止一次",IF(AND(N($U77)>0,N($T77)=0),"※填了实际付息日但没填应付息日","")))))
A78: =IF($D78="","",COUNTA($D$4:$D78)) | S78: =IF($D78="","",ROUND(N($N78)+N($O78)+N($P78)+N($Q78)+N($R78),2)) | V78: =IF($D78="","",IF(OR($T78="",$U78=""),0,MAX(0,INT($U78)-INT($T78)))) | W78: =IF($D78="","",ROUND(MAX(0,N($J78)*日滞纳金率*N($V78)-N($R78)),2)) | AA78: =IF($D78="","",IF(AND($C78<>"",ISNA(MATCH($C78,状态表,0))),"※状态不在【资料】里",IF(AND($G78<>"",$H78<>"",$H78<$G78),"※到期日早于当票日期",IF(AND($F78<>"",COUNTIF($F$4:$F$123,$F78)>1),"※当票号在本表里出现了不止一次",IF(AND(N($U78)>0,N($T78)=0),"※填了实际付息日但没填应付息日","")))))
A79: =IF($D79="","",COUNTA($D$4:$D79)) | S79: =IF($D79="","",ROUND(N($N79)+N($O79)+N($P79)+N($Q79)+N($R79),2)) | V79: =IF($D79="","",IF(OR($T79="",$U79=""),0,MAX(0,INT($U79)-INT($T79)))) | W79: =IF($D79="","",ROUND(MAX(0,N($J79)*日滞纳金率*N($V79)-N($R79)),2)) | AA79: =IF($D79="","",IF(AND($C79<>"",ISNA(MATCH($C79,状态表,0))),"※状态不在【资料】里",IF(AND($G79<>"",$H79<>"",$H79<$G79),"※到期日早于当票日期",IF(AND($F79<>"",COUNTIF($F$4:$F$123,$F79)>1),"※当票号在本表里出现了不止一次",IF(AND(N($U79)>0,N($T79)=0),"※填了实际付息日但没填应付息日","")))))
A80: =IF($D80="","",COUNTA($D$4:$D80)) | S80: =IF($D80="","",ROUND(N($N80)+N($O80)+N($P80)+N($Q80)+N($R80),2)) | V80: =IF($D80="","",IF(OR($T80="",$U80=""),0,MAX(0,INT($U80)-INT($T80)))) | W80: =IF($D80="","",ROUND(MAX(0,N($J80)*日滞纳金率*N($V80)-N($R80)),2)) | AA80: =IF($D80="","",IF(AND($C80<>"",ISNA(MATCH($C80,状态表,0))),"※状态不在【资料】里",IF(AND($G80<>"",$H80<>"",$H80<$G80),"※到期日早于当票日期",IF(AND($F80<>"",COUNTIF($F$4:$F$123,$F80)>1),"※当票号在本表里出现了不止一次",IF(AND(N($U80)>0,N($T80)=0),"※填了实际付息日但没填应付息日","")))))
A81: =IF($D81="","",COUNTA($D$4:$D81)) | S81: =IF($D81="","",ROUND(N($N81)+N($O81)+N($P81)+N($Q81)+N($R81),2)) | V81: =IF($D81="","",IF(OR($T81="",$U81=""),0,MAX(0,INT($U81)-INT($T81)))) | W81: =IF($D81="","",ROUND(MAX(0,N($J81)*日滞纳金率*N($V81)-N($R81)),2)) | AA81: =IF($D81="","",IF(AND($C81<>"",ISNA(MATCH($C81,状态表,0))),"※状态不在【资料】里",IF(AND($G81<>"",$H81<>"",$H81<$G81),"※到期日早于当票日期",IF(AND($F81<>"",COUNTIF($F$4:$F$123,$F81)>1),"※当票号在本表里出现了不止一次",IF(AND(N($U81)>0,N($T81)=0),"※填了实际付息日但没填应付息日","")))))
A82: =IF($D82="","",COUNTA($D$4:$D82)) | S82: =IF($D82="","",ROUND(N($N82)+N($O82)+N($P82)+N($Q82)+N($R82),2)) | V82: =IF($D82="","",IF(OR($T82="",$U82=""),0,MAX(0,INT($U82)-INT($T82)))) | W82: =IF($D82="","",ROUND(MAX(0,N($J82)*日滞纳金率*N($V82)-N($R82)),2)) | AA82: =IF($D82="","",IF(AND($C82<>"",ISNA(MATCH($C82,状态表,0))),"※状态不在【资料】里",IF(AND($G82<>"",$H82<>"",$H82<$G82),"※到期日早于当票日期",IF(AND($F82<>"",COUNTIF($F$4:$F$123,$F82)>1),"※当票号在本表里出现了不止一次",IF(AND(N($U82)>0,N($T82)=0),"※填了实际付息日但没填应付息日","")))))
... A123: =IF($D123="","",COUNTA($D$4:$D123)) | S123: =IF($D123="","",ROUND(N($N123)+N($O123)+N($P123)+N($Q123)+N($R123),2)) | V123: =IF($D123="","",IF(OR($T123="",$U123=""),0,MAX(0,INT($U123)-INT($T123)))) | W123: =IF($D123="","",ROUND(MAX(0,N($J123)*日滞纳金率*N($V123)-N($R123)),2)) | AA123: =IF($D123="","",IF(AND($C123<>"",ISNA(MATCH($C123,状态表,0))),"※状态不在【资料】里",IF(AND($G123<>"",$H123<>"",$H123<$G123),"※到期日早于当票日期",IF(AND($F123<>"",COUNTIF($F$4:$F$123,$F123)>1),"※当票号在本表里出现了不止一次",IF(AND(N($U123)>0,N($T123)=0),"※填了实际付息日但没填应付息日","")))))

Sheet 表2客户典当登记
A1: 表2 · 客户典当登记（总表，在这里登记）
A2: 登记完，【金辉典当】【明道典当】【个人典当】三张子表自动拆出来，不用手工分。「当前在当」= 典当金额 − 已还本金。最后一列「核对」会自己挑毛病，红字的去改。
A3: 序号 | B3: 抵押机构 ★ | C3: 抵押物品 ★ | D3: 状态 ★ | E3: 客户姓名 ★ | F3: 身份证号 | G3: 客户电话 | H3: 当票号 | I3: 当票日期 | J3: 当票到期日 | K3: 出款日期 | L3: 典当金额 ★ | M3: 已还本金 | N3: 当前在当 | O3: 典当系统费率 | P3: 应收利息 | Q3: 利息日 | R3: 应付利息日 | S3: 对公 | T3: 违约金 | U3: 开票金额 | V3: 付息方式 | W3: 详情/备注 | X3: 核对
A4: =IF($E4="","",COUNTA($E$4:$E4)) | B4: 个人典当 | C4: LV包包 | D4: 在当 | E4: 曹玉洁 | K4: 46165 | L4: 5000 | N4: =IF($E4="","",ROUND(N($L4)-N($M4),2)) | P4: 200 | Q4: 22 | R4: 46287 | X4: =IF($E4="","",IF(AND($B4<>"",ISNA(MATCH($B4,机构表,0))),"※机构不在【资料】里",IF(AND($D4<>"",ISNA(MATCH($D4,状态表,0))),"※状态不在【资料】里",IF(N($M4)>N($L4),"※已还本金大于典当金额",IF(AND($I4<>"",$J4<>"",$J4<$I4),"※到期日早于当票日期",IF(AND($H4<>"",COUNTIF($H$4:$H$403,$H4)>1),"※当票号在本表里出现了不止一次",IF(AND($L4<>"",$E4=""),"※有金额没写客户","")))))))
A5: =IF($E5="","",COUNTA($E$4:$E5)) | B5: 个人典当 | C5: 黄金 | D5: 在当 | E5: 曾光雄 | J5: 45670 | K5: 46006 | L5: 6000 | N5: =IF($E5="","",ROUND(N($L5)-N($M5),2)) | P5: 150 | Q5: 15 | R5: 46280 | X5: =IF($E5="","",IF(AND($B5<>"",ISNA(MATCH($B5,机构表,0))),"※机构不在【资料】里",IF(AND($D5<>"",ISNA(MATCH($D5,状态表,0))),"※状态不在【资料】里",IF(N($M5)>N($L5),"※已还本金大于典当金额",IF(AND($I5<>"",$J5<>"",$J5<$I5),"※到期日早于当票日期",IF(AND($H5<>"",COUNTIF($H$4:$H$403,$H5)>1),"※当票号在本表里出现了不止一次",IF(AND($L5<>"",$E5=""),"※有金额没写客户","")))))))
A6: =IF($E6="","",COUNTA($E$4:$E6)) | B6: 个人典当 | C6: 黄金 | D6: 在当 | E6: 曾光雄 | K6: 46121 | L6: 20000 | N6: =IF($E6="","",ROUND(N($L6)-N($M6),2)) | P6: 500 | Q6: 9 | R6: 46274 | X6: =IF($E6="","",IF(AND($B6<>"",ISNA(MATCH($B6,机构表,0))),"※机构不在【资料】里",IF(AND($D6<>"",ISNA(MATCH($D6,状态表,0))),"※状态不在【资料】里",IF(N($M6)>N($L6),"※已还本金大于典当金额",IF(AND($I6<>"",$J6<>"",$J6<$I6),"※到期日早于当票日期",IF(AND($H6<>"",COUNTIF($H$4:$H$403,$H6)>1),"※当票号在本表里出现了不止一次",IF(AND($L6<>"",$E6=""),"※有金额没写客户","")))))))
A7: =IF($E7="","",COUNTA($E$4:$E7)) | B7: 个人典当 | C7: 黄金 | D7: 在当 | E7: 曾光雄 | K7: 46173 | L7: 3000 | N7: =IF($E7="","",ROUND(N($L7)-N($M7),2)) | P7: 100 | Q7: 30 | R7: 46295 | X7: =IF($E7="","",IF(AND($B7<>"",ISNA(MATCH($B7,机构表,0))),"※机构不在【资料】里",IF(AND($D7<>"",ISNA(MATCH($D7,状态表,0))),"※状态不在【资料】里",IF(N($M7)>N($L7),"※已还本金大于典当金额",IF(AND($I7<>"",$J7<>"",$J7<$I7),"※到期日早于当票日期",IF(AND($H7<>"",COUNTIF($H$4:$H$403,$H7)>1),"※当票号在本表里出现了不止一次",IF(AND($L7<>"",$E7=""),"※有金额没写客户","")))))))
A8: =IF($E8="","",COUNTA($E$4:$E8)) | B8: 金辉典当 | C8: 黄金 | D8: 在当 | E8: 曾云 | H8: 3524019247 | I8: 46274 | J8: 46453 | L8: 85000 | N8: =IF($E8="","",ROUND(N($L8)-N($M8),2)) | O8: 0.003 | P8: 2000 | Q8: 9 | R8: 46274 | S8: 255 | X8: =IF($E8="","",IF(AND($B8<>"",ISNA(MATCH($B8,机构表,0))),"※机构不在【资料】里",IF(AND($D8<>"",ISNA(MATCH($D8,状态表,0))),"※状态不在【资料】里",IF(N($M8)>N($L8),"※已还本金大于典当金额",IF(AND($I8<>"",$J8<>"",$J8<$I8),"※到期日早于当票日期",IF(AND($H8<>"",COUNTIF($H$4:$H$403,$H8)>1),"※当票号在本表里出现了不止一次",IF(AND($L8<>"",$E8=""),"※有金额没写客户","")))))))
A9: =IF($E9="","",COUNTA($E$4:$E9)) | B9: 个人典当 | C9: 黄金 | D9: 在当 | E9: 常虹 | J9: 46178 | K9: 46149 | L9: 3000 | N9: =IF($E9="","",ROUND(N($L9)-N($M9),2)) | P9: 100 | Q9: 6 | R9: 46271 | X9: =IF($E9="","",IF(AND($B9<>"",ISNA(MATCH($B9,机构表,0))),"※机构不在【资料】里",IF(AND($D9<>"",ISNA(MATCH($D9,状态表,0))),"※状态不在【资料】里",IF(N($M9)>N($L9),"※已还本金大于典当金额",IF(AND($I9<>"",$J9<>"",$J9<$I9),"※到期日早于当票日期",IF(AND($H9<>"",COUNTIF($H$4:$H$403,$H9)>1),"※当票号在本表里出现了不止一次",IF(AND($L9<>"",$E9=""),"※有金额没写客户","")))))))
A10: =IF($E10="","",COUNTA($E$4:$E10)) | B10: 个人典当 | C10: 黄金 | D10: 结款（个人） | E10: 陈承辉 | J10: 46118 | K10: 46088 | L10: 0 | N10: =IF($E10="","",ROUND(N($L10)-N($M10),2)) | P10: 800 | R10: 46271 | X10: =IF($E10="","",IF(AND($B10<>"",ISNA(MATCH($B10,机构表,0))),"※机构不在【资料】里",IF(AND($D10<>"",ISNA(MATCH($D10,状态表,0))),"※状态不在【资料】里",IF(N($M10)>N($L10),"※已还本金大于典当金额",IF(AND($I10<>"",$J10<>"",$J10<$I10),"※到期日早于当票日期",IF(AND($H10<>"",COUNTIF($H$4:$H$403,$H10)>1),"※当票号在本表里出现了不止一次",IF(AND($L10<>"",$E10=""),"※有金额没写客户","")))))))
A11: =IF($E11="","",COUNTA($E$4:$E11)) | B11: 个人典当 | C11: 黄金 | D11: 在当 | E11: 陈大鑫 | J11: 45666 | K11: 46002 | L11: 18000 | N11: =IF($E11="","",ROUND(N($L11)-N($M11),2)) | P11: 450 | Q11: 10 | R11: 46275 | X11: =IF($E11="","",IF(AND($B11<>"",ISNA(MATCH($B11,机构表,0))),"※机构不在【资料】里",IF(AND($D11<>"",ISNA(MATCH($D11,状态表,0))),"※状态不在【资料】里",IF(N($M11)>N($L11),"※已还本金大于典当金额",IF(AND($I11<>"",$J11<>"",$J11<$I11),"※到期日早于当票日期",IF(AND($H11<>"",COUNTIF($H$4:$H$403,$H11)>1),"※当票号在本表里出现了不止一次",IF(AND($L11<>"",$E11=""),"※有金额没写客户","")))))))
A12: =IF($E12="","",COUNTA($E$4:$E12)) | B12: 个人典当 | C12: 黄金 | D12: 在当 | E12: 陈东 | K12: 46059 | L12: 40000 | N12: =IF($E12="","",ROUND(N($L12)-N($M12),2)) | P12: 1000 | Q12: 5 | R12: 46270 | X12: =IF($E12="","",IF(AND($B12<>"",ISNA(MATCH($B12,机构表,0))),"※机构不在【资料】里",IF(AND($D12<>"",ISNA(MATCH($D12,状态表,0))),"※状态不在【资料】里",IF(N($M12)>N($L12),"※已还本金大于典当金额",IF(AND($I12<>"",$J12<>"",$J12<$I12),"※到期日早于当票日期",IF(AND($H12<>"",COUNTIF($H$4:$H$403,$H12)>1),"※当票号在本表里出现了不止一次",IF(AND($L12<>"",$E12=""),"※有金额没写客户","")))))))
A13: =IF($E13="","",COUNTA($E$4:$E13)) | B13: 个人典当 | C13: 黄金 | D13: 在当 | E13: 陈东 | K13: 46097 | L13: 20000 | N13: =IF($E13="","",ROUND(N($L13)-N($M13),2)) | P13: 500 | Q13: 15 | R13: 46280 | X13: =IF($E13="","",IF(AND($B13<>"",ISNA(MATCH($B13,机构表,0))),"※机构不在【资料】里",IF(AND($D13<>"",ISNA(MATCH($D13,状态表,0))),"※状态不在【资料】里",IF(N($M13)>N($L13),"※已还本金大于典当金额",IF(AND($I13<>"",$J13<>"",$J13<$I13),"※到期日早于当票日期",IF(AND($H13<>"",COUNTIF($H$4:$H$403,$H13)>1),"※当票号在本表里出现了不止一次",IF(AND($L13<>"",$E13=""),"※有金额没写客户","")))))))
A14: =IF($E14="","",COUNTA($E$4:$E14)) | B14: 个人典当 | C14: 黄金+钻戒 | D14: 在当 | E14: 陈东 | J14: 46135 | K14: 46105 | L14: 16000 | N14: =IF($E14="","",ROUND(N($L14)-N($M14),2)) | P14: 400 | Q14: 23 | R14: 46288 | X14: =IF($E14="","",IF(AND($B14<>"",ISNA(MATCH($B14,机构表,0))),"※机构不在【资料】里",IF(AND($D14<>"",ISNA(MATCH($D14,状态表,0))),"※状态不在【资料】里",IF(N($M14)>N($L14),"※已还本金大于典当金额",IF(AND($I14<>"",$J14<>"",$J14<$I14),"※到期日早于当票日期",IF(AND($H14<>"",COUNTIF($H$4:$H$403,$H14)>1),"※当票号在本表里出现了不止一次",IF(AND($L14<>"",$E14=""),"※有金额没写客户","")))))))
A15: =IF($E15="","",COUNTA($E$4:$E15)) | B15: 个人典当 | C15: 黄金+钻戒 | D15: 在当 | E15: 陈东 | K15: 46209 | L15: 3600 | N15: =IF($E15="","",ROUND(N($L15)-N($M15),2)) | P15: 200 | Q15: 6 | R15: 46271 | X15: =IF($E15="","",IF(AND($B15<>"",ISNA(MATCH($B15,机构表,0))),"※机构不在【资料】里",IF(AND($D15<>"",ISNA(MATCH($D15,状态表,0))),"※状态不在【资料】里",IF(N($M15)>N($L15),"※已还本金大于典当金额",IF(AND($I15<>"",$J15<>"",$J15<$I15),"※到期日早于当票日期",IF(AND($H15<>"",COUNTIF($H$4:$H$403,$H15)>1),"※当票号在本表里出现了不止一次",IF(AND($L15<>"",$E15=""),"※有金额没写客户","")))))))
A16: =IF($E16="","",COUNTA($E$4:$E16)) | B16: 个人典当 | C16: 黄金 | D16: 在当 | E16: 陈福荣 | K16: 45594 | L16: 1500 | N16: =IF($E16="","",ROUND(N($L16)-N($M16),2)) | P16: 70 | Q16: 28 | R16: 46293 | X16: =IF($E16="","",IF(AND($B16<>"",ISNA(MATCH($B16,机构表,0))),"※机构不在【资料】里",IF(AND($D16<>"",ISNA(MATCH($D16,状态表,0))),"※状态不在【资料】里",IF(N($M16)>N($L16),"※已还本金大于典当金额",IF(AND($I16<>"",$J16<>"",$J16<$I16),"※到期日早于当票日期",IF(AND($H16<>"",COUNTIF($H$4:$H$403,$H16)>1),"※当票号在本表里出现了不止一次",IF(AND($L16<>"",$E16=""),"※有金额没写客户","")))))))
A17: =IF($E17="","",COUNTA($E$4:$E17)) | B17: 金辉典当 | C17: 房产 | D17: 在当 | E17: 陈建华 | H17: 3524019230 | I17: 46173 | J17: 46202 | L17: 200000 | N17: =IF($E17="","",ROUND(N($L17)-N($M17),2)) | O17: 0.025 | P17: 5000 | Q17: 1 | R17: 46266 | X17: =IF($E17="","",IF(AND($B17<>"",ISNA(MATCH($B17,机构表,0))),"※机构不在【资料】里",IF(AND($D17<>"",ISNA(MATCH($D17,状态表,0))),"※状态不在【资料】里",IF(N($M17)>N($L17),"※已还本金大于典当金额",IF(AND($I17<>"",$J17<>"",$J17<$I17),"※到期日早于当票日期",IF(AND($H17<>"",COUNTIF($H$4:$H$403,$H17)>1),"※当票号在本表里出现了不止一次",IF(AND($L17<>"",$E17=""),"※有金额没写客户","")))))))
A18: =IF($E18="","",COUNTA($E$4:$E18)) | B18: 金辉典当 | C18: 房产 | D18: 在当 | E18: 陈锦珍 | H18: 3519228949 | I18: 45457 | J18: 45636 | K18: 45460 | L18: 1000000 | N18: =IF($E18="","",ROUND(N($L18)-N($M18),2)) | O18: 0.018 | P18: 18000 | Q18: 12 | R18: 46124 | V18: 先息 | X18: =IF($E18="","",IF(AND($B18<>"",ISNA(MATCH($B18,机构表,0))),"※机构不在【资料】里",IF(AND($D18<>"",ISNA(MATCH($D18,状态表,0))),"※状态不在【资料】里",IF(N($M18)>N($L18),"※已还本金大于典当金额",IF(AND($I18<>"",$J18<>"",$J18<$I18),"※到期日早于当票日期",IF(AND($H18<>"",COUNTIF($H$4:$H$403,$H18)>1),"※当票号在本表里出现了不止一次",IF(AND($L18<>"",$E18=""),"※有金额没写客户","")))))))
A19: =IF($E19="","",COUNTA($E$4:$E19)) | B19: 个人典当 | C19: 车子 | D19: 逾期-未起诉 | E19: 陈景昭 | K19: 45584 | L19: 100000 | N19: =IF($E19="","",ROUND(N($L19)-N($M19),2)) | P19: 2850 | Q19: 19 | R19: 46161 | X19: =IF($E19="","",IF(AND($B19<>"",ISNA(MATCH($B19,机构表,0))),"※机构不在【资料】里",IF(AND($D19<>"",ISNA(MATCH($D19,状态表,0))),"※状态不在【资料】里",IF(N($M19)>N($L19),"※已还本金大于典当金额",IF(AND($I19<>"",$J19<>"",$J19<$I19),"※到期日早于当票日期",IF(AND($H19<>"",COUNTIF($H$4:$H$403,$H19)>1),"※当票号在本表里出现了不止一次",IF(AND($L19<>"",$E19=""),"※有金额没写客户","")))))))
A20: =IF($E20="","",COUNTA($E$4:$E20)) | B20: 金辉典当 | C20: 名品 | D20: 虚当 | E20: 陈乐贵 | H20: 3519237782 | I20: 45484 | J20: 45663 | K20: 45484 | L20: 500000 | N20: =IF($E20="","",ROUND(N($L20)-N($M20),2)) | O20: 0.005 | R20: 45513 | V20: 后息 | X20: =IF($E20="","",IF(AND($B20<>"",ISNA(MATCH($B20,机构表,0))),"※机构不在【资料】里",IF(AND($D20<>"",ISNA(MATCH($D20,状态表,0))),"※状态不在【资料】里",IF(N($M20)>N($L20),"※已还本金大于典当金额",IF(AND($I20<>"",$J20<>"",$J20<$I20),"※到期日早于当票日期",IF(AND($H20<>"",COUNTIF($H$4:$H$403,$H20)>1),"※当票号在本表里出现了不止一次",IF(AND($L20<>"",$E20=""),"※有金额没写客户","")))))))
A21: =IF($E21="","",COUNTA($E$4:$E21)) | B21: 金辉典当 | C21: 动产 | D21: 虚当 | E21: 陈乐贵 | H21: 3519260516 | I21: 46059 | K21: 45484 | L21: 500000 | N21: =IF($E21="","",ROUND(N($L21)-N($M21),2)) | O21: 0.005 | R21: 46059 | V21: 后息 | X21: =IF($E21="","",IF(AND($B21<>"",ISNA(MATCH($B21,机构表,0))),"※机构不在【资料】里",IF(AND($D21<>"",ISNA(MATCH($D21,状态表,0))),"※状态不在【资料】里",IF(N($M21)>N($L21),"※已还本金大于典当金额",IF(AND($I21<>"",$J21<>"",$J21<$I21),"※到期日早于当票日期",IF(AND($H21<>"",COUNTIF($H$4:$H$403,$H21)>1),"※当票号在本表里出现了不止一次",IF(AND($L21<>"",$E21=""),"※有金额没写客户","")))))))
A22: =IF($E22="","",COUNTA($E$4:$E22)) | B22: 个人典当 | C22: 股票配资 | D22: 虚当 | E22: 陈乐贵 | K22: 46174 | L22: 600000 | N22: =IF($E22="","",ROUND(N($L22)-N($M22),2)) | P22: 9000 | R22: 46235 | X22: =IF($E22="","",IF(AND($B22<>"",ISNA(MATCH($B22,机构表,0))),"※机构不在【资料】里",IF(AND($D22<>"",ISNA(MATCH($D22,状态表,0))),"※状态不在【资料】里",IF(N($M22)>N($L22),"※已还本金大于典当金额",IF(AND($I22<>"",$J22<>"",$J22<$I22),"※到期日早于当票日期",IF(AND($H22<>"",COUNTIF($H$4:$H$403,$H22)>1),"※当票号在本表里出现了不止一次",IF(AND($L22<>"",$E22=""),"※有金额没写客户","")))))))
A23: =IF($E23="","",COUNTA($E$4:$E23)) | B23: 个人典当 | C23: 黄金 | D23: 在当 | E23: 陈立 | J23: 45978 | K23: 45949 | L23: 8500 | N23: =IF($E23="","",ROUND(N($L23)-N($M23),2)) | P23: 210 | Q23: 17 | R23: 46282 | X23: =IF($E23="","",IF(AND($B23<>"",ISNA(MATCH($B23,机构表,0))),"※机构不在【资料】里",IF(AND($D23<>"",ISNA(MATCH($D23,状态表,0))),"※状态不在【资料】里",IF(N($M23)>N($L23),"※已还本金大于典当金额",IF(AND($I23<>"",$J23<>"",$J23<$I23),"※到期日早于当票日期",IF(AND($H23<>"",COUNTIF($H$4:$H$403,$H23)>1),"※当票号在本表里出现了不止一次",IF(AND($L23<>"",$E23=""),"※有金额没写客户","")))))))
A24: =IF($E24="","",COUNTA($E$4:$E24)) | B24: 个人典当 | C24: 黄金+钻戒 | D24: 在当 | E24: 陈隆鑫 | J24: 46156 | K24: 46127 | L24: 26000 | N24: =IF($E24="","",ROUND(N($L24)-N($M24),2)) | P24: 600 | Q24: 14 | R24: 46279 | X24: =IF($E24="","",IF(AND($B24<>"",ISNA(MATCH($B24,机构表,0))),"※机构不在【资料】里",IF(AND($D24<>"",ISNA(MATCH($D24,状态表,0))),"※状态不在【资料】里",IF(N($M24)>N($L24),"※已还本金大于典当金额",IF(AND($I24<>"",$J24<>"",$J24<$I24),"※到期日早于当票日期",IF(AND($H24<>"",COUNTIF($H$4:$H$403,$H24)>1),"※当票号在本表里出现了不止一次",IF(AND($L24<>"",$E24=""),"※有金额没写客户","")))))))
A25: =IF($E25="","",COUNTA($E$4:$E25)) | B25: 个人典当 | C25: 黄金 | D25: 在当 | E25: 陈隆鑫 | J25: 46156 | K25: 46127 | L25: 4700 | N25: =IF($E25="","",ROUND(N($L25)-N($M25),2)) | P25: 120 | Q25: 14 | R25: 46279 | X25: =IF($E25="","",IF(AND($B25<>"",ISNA(MATCH($B25,机构表,0))),"※机构不在【资料】里",IF(AND($D25<>"",ISNA(MATCH($D25,状态表,0))),"※状态不在【资料】里",IF(N($M25)>N($L25),"※已还本金大于典当金额",IF(AND($I25<>"",$J25<>"",$J25<$I25),"※到期日早于当票日期",IF(AND($H25<>"",COUNTIF($H$4:$H$403,$H25)>1),"※当票号在本表里出现了不止一次",IF(AND($L25<>"",$E25=""),"※有金额没写客户","")))))))
A26: =IF($E26="","",COUNTA($E$4:$E26)) | B26: 个人典当 | C26: 黄金 | D26: 在当 | E26: 陈敏峰 | K26: 46158 | L26: 5000 | N26: =IF($E26="","",ROUND(N($L26)-N($M26),2)) | P26: 120 | Q26: 15 | R26: 46280 | X26: =IF($E26="","",IF(AND($B26<>"",ISNA(MATCH($B26,机构表,0))),"※机构不在【资料】里",IF(AND($D26<>"",ISNA(MATCH($D26,状态表,0))),"※状态不在【资料】里",IF(N($M26)>N($L26),"※已还本金大于典当金额",IF(AND($I26<>"",$J26<>"",$J26<$I26),"※到期日早于当票日期",IF(AND($H26<>"",COUNTIF($H$4:$H$403,$H26)>1),"※当票号在本表里出现了不止一次",IF(AND($L26<>"",$E26=""),"※有金额没写客户","")))))))
A27: =IF($E27="","",COUNTA($E$4:$E27)) | B27: 个人典当 | C27: 私人借款 | D27: 在当-无息 | E27: 陈庆生 | J27: 46182 | K27: 46169 | L27: 700000 | N27: =IF($E27="","",ROUND(N($L27)-N($M27),2)) | Q27: 27 | R27: 46169 | X27: =IF($E27="","",IF(AND($B27<>"",ISNA(MATCH($B27,机构表,0))),"※机构不在【资料】里",IF(AND($D27<>"",ISNA(MATCH($D27,状态表,0))),"※状态不在【资料】里",IF(N($M27)>N($L27),"※已还本金大于典当金额",IF(AND($I27<>"",$J27<>"",$J27<$I27),"※到期日早于当票日期",IF(AND($H27<>"",COUNTIF($H$4:$H$403,$H27)>1),"※当票号在本表里出现了不止一次",IF(AND($L27<>"",$E27=""),"※有金额没写客户","")))))))
A28: =IF($E28="","",COUNTA($E$4:$E28)) | B28: 个人典当 | C28: 私人借款 | D28: 逾期-未起诉 | E28: 陈秋龙 | K28: 45333 | L28: 150000 | N28: =IF($E28="","",ROUND(N($L28)-N($M28),2)) | P28: 3750 | Q28: 10 | R28: 46001 | X28: =IF($E28="","",IF(AND($B28<>"",ISNA(MATCH($B28,机构表,0))),"※机构不在【资料】里",IF(AND($D28<>"",ISNA(MATCH($D28,状态表,0))),"※状态不在【资料】里",IF(N($M28)>N($L28),"※已还本金大于典当金额",IF(AND($I28<>"",$J28<>"",$J28<$I28),"※到期日早于当票日期",IF(AND($H28<>"",COUNTIF($H$4:$H$403,$H28)>1),"※当票号在本表里出现了不止一次",IF(AND($L28<>"",$E28=""),"※有金额没写客户","")))))))
A29: =IF($E29="","",COUNTA($E$4:$E29)) | B29: 金辉典当 | C29: 房产 | D29: 起诉 | E29: 陈勇 | I29: 44893 | K29: 45227 | L29: 50000 | N29: =IF($E29="","",ROUND(N($L29)-N($M29),2)) | O29: 0.025 | P29: 1250 | Q29: 28 | R29: 45197 | U29: 1250 | V29: 先息 | X29: =IF($E29="","",IF(AND($B29<>"",ISNA(MATCH($B29,机构表,0))),"※机构不在【资料】里",IF(AND($D29<>"",ISNA(MATCH($D29,状态表,0))),"※状态不在【资料】里",IF(N($M29)>N($L29),"※已还本金大于典当金额",IF(AND($I29<>"",$J29<>"",$J29<$I29),"※到期日早于当票日期",IF(AND($H29<>"",COUNTIF($H$4:$H$403,$H29)>1),"※当票号在本表里出现了不止一次",IF(AND($L29<>"",$E29=""),"※有金额没写客户","")))))))
A30: =IF($E30="","",COUNTA($E$4:$E30)) | B30: 金辉典当 | C30: 房产 | D30: 在当 | E30: 陈跃飞 | H30: 3519252793 | I30: 45821 | J30: 45910 | L30: 60000 | N30: =IF($E30="","",ROUND(N($L30)-N($M30),2)) | O30: 0.025 | P30: 1500 | Q30: 14 | R30: 46279 | V30: 先息 | X30: =IF($E30="","",IF(AND($B30<>"",ISNA(MATCH($B30,机构表,0))),"※机构不在【资料】里",IF(AND($D30<>"",ISNA(MATCH($D30,状态表,0))),"※状态不在【资料】里",IF(N($M30)>N($L30),"※已还本金大于典当金额",IF(AND($I30<>"",$J30<>"",$J30<$I30),"※到期日早于当票日期",IF(AND($H30<>"",COUNTIF($H$4:$H$403,$H30)>1),"※当票号在本表里出现了不止一次",IF(AND($L30<>"",$E30=""),"※有金额没写客户","")))))))
A31: =IF($E31="","",COUNTA($E$4:$E31)) | B31: 金辉典当 | C31: 房产 | D31: 在当 | E31: 陈征 | I31: 45982 | J31: 46072 | L31: 200000 | N31: =IF($E31="","",ROUND(N($L31)-N($M31),2)) | O31: 0.025 | P31: 5000 | Q31: 20 | R31: 46285 | V31: 先息 | X31: =IF($E31="","",IF(AND($B31<>"",ISNA(MATCH($B31,机构表,0))),"※机构不在【资料】里",IF(AND($D31<>"",ISNA(MATCH($D31,状态表,0))),"※状态不在【资料】里",IF(N($M31)>N($L31),"※已还本金大于典当金额",IF(AND($I31<>"",$J31<>"",$J31<$I31),"※到期日早于当票日期",IF(AND($H31<>"",COUNTIF($H$4:$H$403,$H31)>1),"※当票号在本表里出现了不止一次",IF(AND($L31<>"",$E31=""),"※有金额没写客户","")))))))
A32: =IF($E32="","",COUNTA($E$4:$E32)) | B32: 个人典当 | C32: 车子 | D32: 在当 | E32: 陈征 | K32: 45919 | L32: 100000 | N32: =IF($E32="","",ROUND(N($L32)-N($M32),2)) | P32: 3000 | Q32: 18 | R32: 46283 | X32: =IF($E32="","",IF(AND($B32<>"",ISNA(MATCH($B32,机构表,0))),"※机构不在【资料】里",IF(AND($D32<>"",ISNA(MATCH($D32,状态表,0))),"※状态不在【资料】里",IF(N($M32)>N($L32),"※已还本金大于典当金额",IF(AND($I32<>"",$J32<>"",$J32<$I32),"※到期日早于当票日期",IF(AND($H32<>"",COUNTIF($H$4:$H$403,$H32)>1),"※当票号在本表里出现了不止一次",IF(AND($L32<>"",$E32=""),"※有金额没写客户","")))))))
A33: =IF($E33="","",COUNTA($E$4:$E33)) | B33: 金辉典当 | C33: 车子 | D33: 在当 | E33: 陈忠军 | H33: 3524019226 | I33: 46160 | J33: 46219 | L33: 93000 | N33: =IF($E33="","",ROUND(N($L33)-N($M33),2)) | O33: 0.005 | P33: 2875 | Q33: 17 | R33: 46282 | S33: 465 | X33: =IF($E33="","",IF(AND($B33<>"",ISNA(MATCH($B33,机构表,0))),"※机构不在【资料】里",IF(AND($D33<>"",ISNA(MATCH($D33,状态表,0))),"※状态不在【资料】里",IF(N($M33)>N($L33),"※已还本金大于典当金额",IF(AND($I33<>"",$J33<>"",$J33<$I33),"※到期日早于当票日期",IF(AND($H33<>"",COUNTIF($H$4:$H$403,$H33)>1),"※当票号在本表里出现了不止一次",IF(AND($L33<>"",$E33=""),"※有金额没写客户","")))))))
A34: =IF($E34="","",COUNTA($E$4:$E34)) | B34: 个人典当 | C34: 手表 | D34: 在当 | E34: 池鸿 | K34: 46135 | L34: 60000 | N34: =IF($E34="","",ROUND(N($L34)-N($M34),2)) | P34: 1500 | Q34: 22 | R34: 46287 | X34: =IF($E34="","",IF(AND($B34<>"",ISNA(MATCH($B34,机构表,0))),"※机构不在【资料】里",IF(AND($D34<>"",ISNA(MATCH($D34,状态表,0))),"※状态不在【资料】里",IF(N($M34)>N($L34),"※已还本金大于典当金额",IF(AND($I34<>"",$J34<>"",$J34<$I34),"※到期日早于当票日期",IF(AND($H34<>"",COUNTIF($H$4:$H$403,$H34)>1),"※当票号在本表里出现了不止一次",IF(AND($L34<>"",$E34=""),"※有金额没写客户","")))))))
A35: =IF($E35="","",COUNTA($E$4:$E35)) | B35: 个人典当 | C35: 黄金 | D35: 在当 | E35: 董智宇 | K35: 46171 | L35: 6000 | N35: =IF($E35="","",ROUND(N($L35)-N($M35),2)) | P35: 200 | Q35: 28 | R35: 46293 | X35: =IF($E35="","",IF(AND($B35<>"",ISNA(MATCH($B35,机构表,0))),"※机构不在【资料】里",IF(AND($D35<>"",ISNA(MATCH($D35,状态表,0))),"※状态不在【资料】里",IF(N($M35)>N($L35),"※已还本金大于典当金额",IF(AND($I35<>"",$J35<>"",$J35<$I35),"※到期日早于当票日期",IF(AND($H35<>"",COUNTIF($H$4:$H$403,$H35)>1),"※当票号在本表里出现了不止一次",IF(AND($L35<>"",$E35=""),"※有金额没写客户","")))))))
A36: =IF($E36="","",COUNTA($E$4:$E36)) | B36: 个人典当 | C36: 房产 | D36: 在当 | E36: 杜若 | J36: 45690 | K36: 45631 | L36: 2600000 | N36: =IF($E36="","",ROUND(N($L36)-N($M36),2)) | P36: 72800 | Q36: 3 | R36: 46268 | X36: =IF($E36="","",IF(AND($B36<>"",ISNA(MATCH($B36,机构表,0))),"※机构不在【资料】里",IF(AND($D36<>"",ISNA(MATCH($D36,状态表,0))),"※状态不在【资料】里",IF(N($M36)>N($L36),"※已还本金大于典当金额",IF(AND($I36<>"",$J36<>"",$J36<$I36),"※到期日早于当票日期",IF(AND($H36<>"",COUNTIF($H$4:$H$403,$H36)>1),"※当票号在本表里出现了不止一次",IF(AND($L36<>"",$E36=""),"※有金额没写客户","")))))))
A37: =IF($E37="","",COUNTA($E$4:$E37)) | B37: 金辉典当 | C37: 车位 | D37: 在当 | E37: 方楚钰 | H37: 3519121346 | I37: 44453 | K37: 45246 | L37: 50000 | N37: =IF($E37="","",ROUND(N($L37)-N($M37),2)) | O37: 0.025 | P37: 1250 | Q37: 15 | R37: 46280 | U37: 2500 | V37: 先息 | W37: 个人账户收款2500元/月 | X37: =IF($E37="","",IF(AND($B37<>"",ISNA(MATCH($B37,机构表,0))),"※机构不在【资料】里",IF(AND($D37<>"",ISNA(MATCH($D37,状态表,0))),"※状态不在【资料】里",IF(N($M37)>N($L37),"※已还本金大于典当金额",IF(AND($I37<>"",$J37<>"",$J37<$I37),"※到期日早于当票日期",IF(AND($H37<>"",COUNTIF($H$4:$H$403,$H37)>1),"※当票号在本表里出现了不止一次",IF(AND($L37<>"",$E37=""),"※有金额没写客户","")))))))
A38: =IF($E38="","",COUNTA($E$4:$E38)) | B38: 个人典当 | C38: 渠道 | D38: 在当 | E38: 方楚钰 | K38: 44088 | L38: 50000 | N38: =IF($E38="","",ROUND(N($L38)-N($M38),2)) | P38: 1250 | Q38: 15 | R38: 46280 | W38: 转林木英1250元/月 | X38: =IF($E38="","",IF(AND($B38<>"",ISNA(MATCH($B38,机构表,0))),"※机构不在【资料】里",IF(AND($D38<>"",ISNA(MATCH($D38,状态表,0))),"※状态不在【资料】里",IF(N($M38)>N($L38),"※已还本金大于典当金额",IF(AND($I38<>"",$J38<>"",$J38<$I38),"※到期日早于当票日期",IF(AND($H38<>"",COUNTIF($H$4:$H$403,$H38)>1),"※当票号在本表里出现了不止一次",IF(AND($L38<>"",$E38=""),"※有金额没写客户","")))))))
A39: =IF($E39="","",COUNTA($E$4:$E39)) | B39: 金辉典当 | C39: 车位 | D39: 在当 | E39: 方士雯 | H39: 3519252785 | I39: 45758 | J39: 45846 | L39: 45000 | N39: =IF($E39="","",ROUND(N($L39)-N($M39),2)) | O39: 0.03 | P39: 1350 | Q39: 10 | R39: 46275 | V39: 先息 | X39: =IF($E39="","",IF(AND($B39<>"",ISNA(MATCH($B39,机构表,0))),"※机构不在【资料】里",IF(AND($D39<>"",ISNA(MATCH($D39,状态表,0))),"※状态不在【资料】里",IF(N($M39)>N($L39),"※已还本金大于典当金额",IF(AND($I39<>"",$J39<>"",$J39<$I39),"※到期日早于当票日期",IF(AND($H39<>"",COUNTIF($H$4:$H$403,$H39)>1),"※当票号在本表里出现了不止一次",IF(AND($L39<>"",$E39=""),"※有金额没写客户","")))))))
A40: =IF($E40="","",COUNTA($E$4:$E40)) | B40: 个人典当 | C40: 私人借款 | D40: 在当 | E40: 高文玉 | J40: 45576 | K40: 45519 | L40: 154000 | N40: =IF($E40="","",ROUND(N($L40)-N($M40),2)) | P40: 7000 | Q40: 10 | R40: 45787 | X40: =IF($E40="","",IF(AND($B40<>"",ISNA(MATCH($B40,机构表,0))),"※机构不在【资料】里",IF(AND($D40<>"",ISNA(MATCH($D40,状态表,0))),"※状态不在【资料】里",IF(N($M40)>N($L40),"※已还本金大于典当金额",IF(AND($I40<>"",$J40<>"",$J40<$I40),"※到期日早于当票日期",IF(AND($H40<>"",COUNTIF($H$4:$H$403,$H40)>1),"※当票号在本表里出现了不止一次",IF(AND($L40<>"",$E40=""),"※有金额没写客户","")))))))
A41: =IF($E41="","",COUNTA($E$4:$E41)) | B41: 金辉典当 | C41: 车位 | D41: 在当 | E41: 郭联兵 | H41: 3519156582 | I41: 44578 | K41: 45250 | L41: 100000 | N41: =IF($E41="","",ROUND(N($L41)-N($M41),2)) | O41: 0.027 | P41: 2700 | Q41: 15 | R41: 46280 | U41: 2700 | V41: 先息 | X41: =IF($E41="","",IF(AND($B41<>"",ISNA(MATCH($B41,机构表,0))),"※机构不在【资料】里",IF(AND($D41<>"",ISNA(MATCH($D41,状态表,0))),"※状态不在【资料】里",IF(N($M41)>N($L41),"※已还本金大于典当金额",IF(AND($I41<>"",$J41<>"",$J41<$I41),"※到期日早于当票日期",IF(AND($H41<>"",COUNTIF($H$4:$H$403,$H41)>1),"※当票号在本表里出现了不止一次",IF(AND($L41<>"",$E41=""),"※有金额没写客户","")))))))
A42: =IF($E42="","",COUNTA($E$4:$E42)) | B42: 金辉典当 | C42: 黄金 | D42: 在当 | E42: 何博文 | H42: 3524019233 | I42: 46183 | J42: 46362 | L42: 18000 | N42: =IF($E42="","",ROUND(N($L42)-N($M42),2)) | O42: 0.005 | P42: 540 | Q42: 9 | R42: 46274 | S42: 90 | X42: =IF($E42="","",IF(AND($B42<>"",ISNA(MATCH($B42,机构表,0))),"※机构不在【资料】里",IF(AND($D42<>"",ISNA(MATCH($D42,状态表,0))),"※状态不在【资料】里",IF(N($M42)>N($L42),"※已还本金大于典当金额",IF(AND($I42<>"",$J42<>"",$J42<$I42),"※到期日早于当票日期",IF(AND($H42<>"",COUNTIF($H$4:$H$403,$H42)>1),"※当票号在本表里出现了不止一次",IF(AND($L42<>"",$E42=""),"※有金额没写客户","")))))))
A43: =IF($E43="","",COUNTA($E$4:$E43)) | B43: 个人典当 | C43: 黄金 | D43: 在当 | E43: 何博文 | K43: 46134 | L43: 20000 | N43: =IF($E43="","",ROUND(N($L43)-N($M43),2)) | P43: 600 | Q43: 21 | R43: 46286 | X43: =IF($E43="","",IF(AND($B43<>"",ISNA(MATCH($B43,机构表,0))),"※机构不在【资料】里",IF(AND($D43<>"",ISNA(MATCH($D43,状态表,0))),"※状态不在【资料】里",IF(N($M43)>N($L43),"※已还本金大于典当金额",IF(AND($I43<>"",$J43<>"",$J43<$I43),"※到期日早于当票日期",IF(AND($H43<>"",COUNTIF($H$4:$H$403,$H43)>1),"※当票号在本表里出现了不止一次",IF(AND($L43<>"",$E43=""),"※有金额没写客户","")))))))
A44: =IF($E44="","",COUNTA($E$4:$E44)) | B44: 个人典当 | C44: 黄金 | D44: 在当 | E44: 张妍 | K44: 46123 | L44: 9600 | N44: =IF($E44="","",ROUND(N($L44)-N($M44),2)) | P44: 300 | Q44: 10 | R44: 46275 | X44: =IF($E44="","",IF(AND($B44<>"",ISNA(MATCH($B44,机构表,0))),"※机构不在【资料】里",IF(AND($D44<>"",ISNA(MATCH($D44,状态表,0))),"※状态不在【资料】里",IF(N($M44)>N($L44),"※已还本金大于典当金额",IF(AND($I44<>"",$J44<>"",$J44<$I44),"※到期日早于当票日期",IF(AND($H44<>"",COUNTIF($H$4:$H$403,$H44)>1),"※当票号在本表里出现了不止一次",IF(AND($L44<>"",$E44=""),"※有金额没写客户","")))))))
A45: =IF($E45="","",COUNTA($E$4:$E45)) | B45: 金辉典当 | C45: 房产 | D45: 起诉 | E45: 何松 | H45: 3519211804 | I45: 45189 | K45: 45250 | L45: 60000 | N45: =IF($E45="","",ROUND(N($L45)-N($M45),2)) | O45: 0.025 | P45: 1500 | Q45: 15 | R45: 45703 | U45: 2500 | V45: 先息 | X45: =IF($E45="","",IF(AND($B45<>"",ISNA(MATCH($B45,机构表,0))),"※机构不在【资料】里",IF(AND($D45<>"",ISNA(MATCH($D45,状态表,0))),"※状态不在【资料】里",IF(N($M45)>N($L45),"※已还本金大于典当金额",IF(AND($I45<>"",$J45<>"",$J45<$I45),"※到期日早于当票日期",IF(AND($H45<>"",COUNTIF($H$4:$H$403,$H45)>1),"※当票号在本表里出现了不止一次",IF(AND($L45<>"",$E45=""),"※有金额没写客户","")))))))
A46: =IF($E46="","",COUNTA($E$4:$E46)) | B46: 金辉典当 | C46: 动产 | D46: 虚当 | E46: 胡建通 | H46: 3519260503 | I46: 45900 | J46: 45959 | L46: 500000 | N46: =IF($E46="","",ROUND(N($L46)-N($M46),2)) | R46: 45900 | X46: =IF($E46="","",IF(AND($B46<>"",ISNA(MATCH($B46,机构表,0))),"※机构不在【资料】里",IF(AND($D46<>"",ISNA(MATCH($D46,状态表,0))),"※状态不在【资料】里",IF(N($M46)>N($L46),"※已还本金大于典当金额",IF(AND($I46<>"",$J46<>"",$J46<$I46),"※到期日早于当票日期",IF(AND($H46<>"",COUNTIF($H$4:$H$403,$H46)>1),"※当票号在本表里出现了不止一次",IF(AND($L46<>"",$E46=""),"※有金额没写客户","")))))))
A47: =IF($E47="","",COUNTA($E$4:$E47)) | B47: 金辉典当 | C47: 名品 | D47: 虚当 | E47: 胡建通 | H47: 3519260519 | I47: 46097 | L47: 330000 | N47: =IF($E47="","",ROUND(N($L47)-N($M47),2)) | O47: 0.0007 | P47: 231 | R47: 46097 | X47: =IF($E47="","",IF(AND($B47<>"",ISNA(MATCH($B47,机构表,0))),"※机构不在【资料】里",IF(AND($D47<>"",ISNA(MATCH($D47,状态表,0))),"※状态不在【资料】里",IF(N($M47)>N($L47),"※已还本金大于典当金额",IF(AND($I47<>"",$J47<>"",$J47<$I47),"※到期日早于当票日期",IF(AND($H47<>"",COUNTIF($H$4:$H$403,$H47)>1),"※当票号在本表里出现了不止一次",IF(AND($L47<>"",$E47=""),"※有金额没写客户","")))))))
A48: =IF($E48="","",COUNTA($E$4:$E48)) | B48: 个人典当 | C48: 黄金 | D48: 在当 | E48: 黄发锦 | J48: 45743 | K48: 45713 | L48: 27000 | N48: =IF($E48="","",ROUND(N($L48)-N($M48),2)) | P48: 675 | Q48: 24 | R48: 46289 | X48: =IF($E48="","",IF(AND($B48<>"",ISNA(MATCH($B48,机构表,0))),"※机构不在【资料】里",IF(AND($D48<>"",ISNA(MATCH($D48,状态表,0))),"※状态不在【资料】里",IF(N($M48)>N($L48),"※已还本金大于典当金额",IF(AND($I48<>"",$J48<>"",$J48<$I48),"※到期日早于当票日期",IF(AND($H48<>"",COUNTIF($H$4:$H$403,$H48)>1),"※当票号在本表里出现了不止一次",IF(AND($L48<>"",$E48=""),"※有金额没写客户","")))))))
A49: =IF($E49="","",COUNTA($E$4:$E49)) | B49: 金辉典当 | C49: 房产 | D49: 在当 | E49: 黄飞 | H49: 3524019245 | I49: 46261 | J49: 46350 | L49: 120000 | N49: =IF($E49="","",ROUND(N($L49)-N($M49),2)) | O49: 0.025 | P49: 3000 | Q49: 26 | R49: 46291 | X49: =IF($E49="","",IF(AND($B49<>"",ISNA(MATCH($B49,机构表,0))),"※机构不在【资料】里",IF(AND($D49<>"",ISNA(MATCH($D49,状态表,0))),"※状态不在【资料】里",IF(N($M49)>N($L49),"※已还本金大于典当金额",IF(AND($I49<>"",$J49<>"",$J49<$I49),"※到期日早于当票日期",IF(AND($H49<>"",COUNTIF($H$4:$H$403,$H49)>1),"※当票号在本表里出现了不止一次",IF(AND($L49<>"",$E49=""),"※有金额没写客户","")))))))
A50: =IF($E50="","",COUNTA($E$4:$E50)) | B50: 个人典当 | C50: 玉佩 | D50: 在当 | E50: 黄军 | K50: 46263 | L50: 2000 | N50: =IF($E50="","",ROUND(N($L50)-N($M50),2)) | P50: 200 | Q50: 27 | R50: 46292 | X50: =IF($E50="","",IF(AND($B50<>"",ISNA(MATCH($B50,机构表,0))),"※机构不在【资料】里",IF(AND($D50<>"",ISNA(MATCH($D50,状态表,0))),"※状态不在【资料】里",IF(N($M50)>N($L50),"※已还本金大于典当金额",IF(AND($I50<>"",$J50<>"",$J50<$I50),"※到期日早于当票日期",IF(AND($H50<>"",COUNTIF($H$4:$H$403,$H50)>1),"※当票号在本表里出现了不止一次",IF(AND($L50<>"",$E50=""),"※有金额没写客户","")))))))
A51: =IF($E51="","",COUNTA($E$4:$E51)) | B51: 金辉典当 | C51: 房产 | D51: 起诉 | E51: 黄平香 | H51: 3519211817 | I51: 45254 | K51: 45254 | L51: 90000 | N51: =IF($E51="","",ROUND(N($L51)-N($M51),2)) | O51: 0.025 | P51: 2500 | Q51: 18 | R51: 45706 | U51: 2500 | V51: 先息 | X51: =IF($E51="","",IF(AND($B51<>"",ISNA(MATCH($B51,机构表,0))),"※机构不在【资料】里",IF(AND($D51<>"",ISNA(MATCH($D51,状态表,0))),"※状态不在【资料】里",IF(N($M51)>N($L51),"※已还本金大于典当金额",IF(AND($I51<>"",$J51<>"",$J51<$I51),"※到期日早于当票日期",IF(AND($H51<>"",COUNTIF($H$4:$H$403,$H51)>1),"※当票号在本表里出现了不止一次",IF(AND($L51<>"",$E51=""),"※有金额没写客户","")))))))
A52: =IF($E52="","",COUNTA($E$4:$E52)) | B52: 金辉典当 | C52: 手表 | D52: 在当 | E52: 黄远枝 | H52: 3524019235 | I52: 46195 | J52: 46374 | L52: 60000 | N52: =IF($E52="","",ROUND(N($L52)-N($M52),2)) | O52: 0.004 | P52: 1500 | Q52: 21 | R52: 46286 | S52: 240 | X52: =IF($E52="","",IF(AND($B52<>"",ISNA(MATCH($B52,机构表,0))),"※机构不在【资料】里",IF(AND($D52<>"",ISNA(MATCH($D52,状态表,0))),"※状态不在【资料】里",IF(N($M52)>N($L52),"※已还本金大于典当金额",IF(AND($I52<>"",$J52<>"",$J52<$I52),"※到期日早于当票日期",IF(AND($H52<>"",COUNTIF($H$4:$H$403,$H52)>1),"※当票号在本表里出现了不止一次",IF(AND($L52<>"",$E52=""),"※有金额没写客户","")))))))
A53: =IF($E53="","",COUNTA($E$4:$E53)) | B53: 个人典当 | C53: 黄金 | D53: 在当 | E53: 黄长燕 | J53: 46088 | K53: 46060 | L53: 2200 | N53: =IF($E53="","",ROUND(N($L53)-N($M53),2)) | P53: 200 | Q53: 6 | R53: 46271 | X53: =IF($E53="","",IF(AND($B53<>"",ISNA(MATCH($B53,机构表,0))),"※机构不在【资料】里",IF(AND($D53<>"",ISNA(MATCH($D53,状态表,0))),"※状态不在【资料】里",IF(N($M53)>N($L53),"※已还本金大于典当金额",IF(AND($I53<>"",$J53<>"",$J53<$I53),"※到期日早于当票日期",IF(AND($H53<>"",COUNTIF($H$4:$H$403,$H53)>1),"※当票号在本表里出现了不止一次",IF(AND($L53<>"",$E53=""),"※有金额没写客户","")))))))
A54: =IF($E54="","",COUNTA($E$4:$E54)) | B54: 个人典当 | C54: 黄金 | D54: 在当 | E54: 黄长燕 | J54: 46117 | K54: 46087 | L54: 1000 | N54: =IF($E54="","",ROUND(N($L54)-N($M54),2)) | P54: 100 | Q54: 6 | R54: 46271 | X54: =IF($E54="","",IF(AND($B54<>"",ISNA(MATCH($B54,机构表,0))),"※机构不在【资料】里",IF(AND($D54<>"",ISNA(MATCH($D54,状态表,0))),"※状态不在【资料】里",IF(N($M54)>N($L54),"※已还本金大于典当金额",IF(AND($I54<>"",$J54<>"",$J54<$I54),"※到期日早于当票日期",IF(AND($H54<>"",COUNTIF($H$4:$H$403,$H54)>1),"※当票号在本表里出现了不止一次",IF(AND($L54<>"",$E54=""),"※有金额没写客户","")))))))
A55: =IF($E55="","",COUNTA($E$4:$E55)) | B55: 个人典当 | C55: 黄金 | D55: 在当 | E55: 纪昌杰 | K55: 46262 | L55: 7500 | N55: =IF($E55="","",ROUND(N($L55)-N($M55),2)) | P55: 200 | Q55: 26 | R55: 46291 | X55: =IF($E55="","",IF(AND($B55<>"",ISNA(MATCH($B55,机构表,0))),"※机构不在【资料】里",IF(AND($D55<>"",ISNA(MATCH($D55,状态表,0))),"※状态不在【资料】里",IF(N($M55)>N($L55),"※已还本金大于典当金额",IF(AND($I55<>"",$J55<>"",$J55<$I55),"※到期日早于当票日期",IF(AND($H55<>"",COUNTIF($H$4:$H$403,$H55)>1),"※当票号在本表里出现了不止一次",IF(AND($L55<>"",$E55=""),"※有金额没写客户","")))))))
A56: =IF($E56="","",COUNTA($E$4:$E56)) | B56: 个人典当 | C56: 私人借款 | D56: 无法回款 | E56: 纪文瑞 | K56: 44295 | L56: 60000 | N56: =IF($E56="","",ROUND(N($L56)-N($M56),2)) | X56: =IF($E56="","",IF(AND($B56<>"",ISNA(MATCH($B56,机构表,0))),"※机构不在【资料】里",IF(AND($D56<>"",ISNA(MATCH($D56,状态表,0))),"※状态不在【资料】里",IF(N($M56)>N($L56),"※已还本金大于典当金额",IF(AND($I56<>"",$J56<>"",$J56<$I56),"※到期日早于当票日期",IF(AND($H56<>"",COUNTIF($H$4:$H$403,$H56)>1),"※当票号在本表里出现了不止一次",IF(AND($L56<>"",$E56=""),"※有金额没写客户","")))))))
A57: =IF($E57="","",COUNTA($E$4:$E57)) | B57: 个人典当 | C57: 黄金 | D57: 在当 | E57: 姜玉枝 | K57: 46174 | L57: 90000 | N57: =IF($E57="","",ROUND(N($L57)-N($M57),2)) | P57: 2250 | Q57: 1 | R57: 46266 | X57: =IF($E57="","",IF(AND($B57<>"",ISNA(MATCH($B57,机构表,0))),"※机构不在【资料】里",IF(AND($D57<>"",ISNA(MATCH($D57,状态表,0))),"※状态不在【资料】里",IF(N($M57)>N($L57),"※已还本金大于典当金额",IF(AND($I57<>"",$J57<>"",$J57<$I57),"※到期日早于当票日期",IF(AND($H57<>"",COUNTIF($H$4:$H$403,$H57)>1),"※当票号在本表里出现了不止一次",IF(AND($L57<>"",$E57=""),"※有金额没写客户","")))))))
A58: =IF($E58="","",COUNTA($E$4:$E58)) | B58: 个人典当 | C58: 私人借款 | D58: 无法回款 | E58: 蒋淋淋 | K58: 44617 | L58: 34000 | N58: =IF($E58="","",ROUND(N($L58)-N($M58),2)) | X58: =IF($E58="","",IF(AND($B58<>"",ISNA(MATCH($B58,机构表,0))),"※机构不在【资料】里",IF(AND($D58<>"",ISNA(MATCH($D58,状态表,0))),"※状态不在【资料】里",IF(N($M58)>N($L58),"※已还本金大于典当金额",IF(AND($I58<>"",$J58<>"",$J58<$I58),"※到期日早于当票日期",IF(AND($H58<>"",COUNTIF($H$4:$H$403,$H58)>1),"※当票号在本表里出现了不止一次",IF(AND($L58<>"",$E58=""),"※有金额没写客户","")))))))
A59: =IF($E59="","",COUNTA($E$4:$E59)) | B59: 金辉典当 | C59: 动产 | D59: 虚当 | E59: 柯志宏 | H59: 3519252757 | I59: 45590 | J59: 45679 | L59: 260000 | N59: =IF($E59="","",ROUND(N($L59)-N($M59),2)) | O59: 0.008 | P59: 2080 | R59: 45677 | X59: =IF($E59="","",IF(AND($B59<>"",ISNA(MATCH($B59,机构表,0))),"※机构不在【资料】里",IF(AND($D59<>"",ISNA(MATCH($D59,状态表,0))),"※状态不在【资料】里",IF(N($M59)>N($L59),"※已还本金大于典当金额",IF(AND($I59<>"",$J59<>"",$J59<$I59),"※到期日早于当票日期",IF(AND($H59<>"",COUNTIF($H$4:$H$403,$H59)>1),"※当票号在本表里出现了不止一次",IF(AND($L59<>"",$E59=""),"※有金额没写客户","")))))))
A60: =IF($E60="","",COUNTA($E$4:$E60)) | B60: 金辉典当 | C60: 名品 | D60: 虚当 | E60: 柯志宏 | I60: 46168 | J60: 46183 | L60: 300000 | N60: =IF($E60="","",ROUND(N($L60)-N($M60),2)) | O60: 0.004 | P60: 1200 | R60: 46168 | X60: =IF($E60="","",IF(AND($B60<>"",ISNA(MATCH($B60,机构表,0))),"※机构不在【资料】里",IF(AND($D60<>"",ISNA(MATCH($D60,状态表,0))),"※状态不在【资料】里",IF(N($M60)>N($L60),"※已还本金大于典当金额",IF(AND($I60<>"",$J60<>"",$J60<$I60),"※到期日早于当票日期",IF(AND($H60<>"",COUNTIF($H$4:$H$403,$H60)>1),"※当票号在本表里出现了不止一次",IF(AND($L60<>"",$E60=""),"※有金额没写客户","")))))))
A61: =IF($E61="","",COUNTA($E$4:$E61)) | B61: 个人典当 | C61: 私人借款 | D61: 在当 | E61: 柯志宏 | J61: 46270 | K61: 46086 | L61: 200000 | N61: =IF($E61="","",ROUND(N($L61)-N($M61),2)) | Q61: 5 | R61: 46086 | X61: =IF($E61="","",IF(AND($B61<>"",ISNA(MATCH($B61,机构表,0))),"※机构不在【资料】里",IF(AND($D61<>"",ISNA(MATCH($D61,状态表,0))),"※状态不在【资料】里",IF(N($M61)>N($L61),"※已还本金大于典当金额",IF(AND($I61<>"",$J61<>"",$J61<$I61),"※到期日早于当票日期",IF(AND($H61<>"",COUNTIF($H$4:$H$403,$H61)>1),"※当票号在本表里出现了不止一次",IF(AND($L61<>"",$E61=""),"※有金额没写客户","")))))))
A62: =IF($E62="","",COUNTA($E$4:$E62)) | B62: 个人典当 | C62: 私人借款 | D62: 在当 | E62: 柯志宏 | J62: 46287 | K62: 46103 | L62: 100000 | N62: =IF($E62="","",ROUND(N($L62)-N($M62),2)) | Q62: 22 | R62: 46103 | X62: =IF($E62="","",IF(AND($B62<>"",ISNA(MATCH($B62,机构表,0))),"※机构不在【资料】里",IF(AND($D62<>"",ISNA(MATCH($D62,状态表,0))),"※状态不在【资料】里",IF(N($M62)>N($L62),"※已还本金大于典当金额",IF(AND($I62<>"",$J62<>"",$J62<$I62),"※到期日早于当票日期",IF(AND($H62<>"",COUNTIF($H$4:$H$403,$H62)>1),"※当票号在本表里出现了不止一次",IF(AND($L62<>"",$E62=""),"※有金额没写客户","")))))))
A63: =IF($E63="","",COUNTA($E$4:$E63)) | B63: 个人典当 | C63: 私人借款 | D63: 在当 | E63: 柯志宏 | K63: 46140 | L63: 500000 | N63: =IF($E63="","",ROUND(N($L63)-N($M63),2)) | Q63: 28 | R63: 46140 | X63: =IF($E63="","",IF(AND($B63<>"",ISNA(MATCH($B63,机构表,0))),"※机构不在【资料】里",IF(AND($D63<>"",ISNA(MATCH($D63,状态表,0))),"※状态不在【资料】里",IF(N($M63)>N($L63),"※已还本金大于典当金额",IF(AND($I63<>"",$J63<>"",$J63<$I63),"※到期日早于当票日期",IF(AND($H63<>"",COUNTIF($H$4:$H$403,$H63)>1),"※当票号在本表里出现了不止一次",IF(AND($L63<>"",$E63=""),"※有金额没写客户","")))))))
A64: =IF($E64="","",COUNTA($E$4:$E64)) | B64: 个人典当 | C64: 解押/过桥 | D64: 在当 | E64: 柯志宏 | J64: 46267 | K64: 46258 | L64: 400000 | N64: =IF($E64="","",ROUND(N($L64)-N($M64),2)) | Q64: 24 | R64: 46258 | X64: =IF($E64="","",IF(AND($B64<>"",ISNA(MATCH($B64,机构表,0))),"※机构不在【资料】里",IF(AND($D64<>"",ISNA(MATCH($D64,状态表,0))),"※状态不在【资料】里",IF(N($M64)>N($L64),"※已还本金大于典当金额",IF(AND($I64<>"",$J64<>"",$J64<$I64),"※到期日早于当票日期",IF(AND($H64<>"",COUNTIF($H$4:$H$403,$H64)>1),"※当票号在本表里出现了不止一次",IF(AND($L64<>"",$E64=""),"※有金额没写客户","")))))))
A65: =IF($E65="","",COUNTA($E$4:$E65)) | B65: 个人典当 | C65: 黄金 | D65: 在当 | E65: 柯重文 | J65: 46059 | K65: 46030 | L65: 8000 | N65: =IF($E65="","",ROUND(N($L65)-N($M65),2)) | P65: 200 | Q65: 7 | R65: 46272 | X65: =IF($E65="","",IF(AND($B65<>"",ISNA(MATCH($B65,机构表,0))),"※机构不在【资料】里",IF(AND($D65<>"",ISNA(MATCH($D65,状态表,0))),"※状态不在【资料】里",IF(N($M65)>N($L65),"※已还本金大于典当金额",IF(AND($I65<>"",$J65<>"",$J65<$I65),"※到期日早于当票日期",IF(AND($H65<>"",COUNTIF($H$4:$H$403,$H65)>1),"※当票号在本表里出现了不止一次",IF(AND($L65<>"",$E65=""),"※有金额没写客户","")))))))
A66: =IF($E66="","",COUNTA($E$4:$E66)) | B66: 个人典当 | C66: 黄金 | D66: 结款（个人） | E66: 李北茉 | K66: 46184 | L66: 0 | N66: =IF($E66="","",ROUND(N($L66)-N($M66),2)) | P66: 700 | R66: 46275 | X66: =IF($E66="","",IF(AND($B66<>"",ISNA(MATCH($B66,机构表,0))),"※机构不在【资料】里",IF(AND($D66<>"",ISNA(MATCH($D66,状态表,0))),"※状态不在【资料】里",IF(N($M66)>N($L66),"※已还本金大于典当金额",IF(AND($I66<>"",$J66<>"",$J66<$I66),"※到期日早于当票日期",IF(AND($H66<>"",COUNTIF($H$4:$H$403,$H66)>1),"※当票号在本表里出现了不止一次",IF(AND($L66<>"",$E66=""),"※有金额没写客户","")))))))
A67: =IF($E67="","",COUNTA($E$4:$E67)) | B67: 金辉典当 | C67: 房产 | D67: 起诉 | E67: 李佳敏 | H67: 3519121393 | I67: 44326 | K67: 45240 | L67: 150000 | N67: =IF($E67="","",ROUND(N($L67)-N($M67),2)) | O67: 0.025 | P67: 3750 | Q67: 10 | R67: 45332 | U67: 3750 | V67: 先息 | X67: =IF($E67="","",IF(AND($B67<>"",ISNA(MATCH($B67,机构表,0))),"※机构不在【资料】里",IF(AND($D67<>"",ISNA(MATCH($D67,状态表,0))),"※状态不在【资料】里",IF(N($M67)>N($L67),"※已还本金大于典当金额",IF(AND($I67<>"",$J67<>"",$J67<$I67),"※到期日早于当票日期",IF(AND($H67<>"",COUNTIF($H$4:$H$403,$H67)>1),"※当票号在本表里出现了不止一次",IF(AND($L67<>"",$E67=""),"※有金额没写客户","")))))))
A68: =IF($E68="","",COUNTA($E$4:$E68)) | B68: 个人典当 | C68: 车子 | D68: 在当 | E68: 李元 | J68: 46147 | K68: 46029 | L68: 15000 | N68: =IF($E68="","",ROUND(N($L68)-N($M68),2)) | P68: 875 | Q68: 6 | R68: 46271 | X68: =IF($E68="","",IF(AND($B68<>"",ISNA(MATCH($B68,机构表,0))),"※机构不在【资料】里",IF(AND($D68<>"",ISNA(MATCH($D68,状态表,0))),"※状态不在【资料】里",IF(N($M68)>N($L68),"※已还本金大于典当金额",IF(AND($I68<>"",$J68<>"",$J68<$I68),"※到期日早于当票日期",IF(AND($H68<>"",COUNTIF($H$4:$H$403,$H68)>1),"※当票号在本表里出现了不止一次",IF(AND($L68<>"",$E68=""),"※有金额没写客户","")))))))
A69: =IF($E69="","",COUNTA($E$4:$E69)) | B69: 个人典当 | C69: 车子 | D69: 结款（个人） | E69: 李忠浩 | K69: 46136 | L69: 15000 | N69: =IF($E69="","",ROUND(N($L69)-N($M69),2)) | P69: 900 | R69: 46226 | W69: 车子已售卖，售价1.6万，回款在林总建行 | X69: =IF($E69="","",IF(AND($B69<>"",ISNA(MATCH($B69,机构表,0))),"※机构不在【资料】里",IF(AND($D69<>"",ISNA(MATCH($D69,状态表,0))),"※状态不在【资料】里",IF(N($M69)>N($L69),"※已还本金大于典当金额",IF(AND($I69<>"",$J69<>"",$J69<$I69),"※到期日早于当票日期",IF(AND($H69<>"",COUNTIF($H$4:$H$403,$H69)>1),"※当票号在本表里出现了不止一次",IF(AND($L69<>"",$E69=""),"※有金额没写客户","")))))))
A70: =IF($E70="","",COUNTA($E$4:$E70)) | B70: 金辉典当 | C70: 黄金 | D70: 在当 | E70: 廖浴波 | H70: 3519260520 | I70: 46099 | J70: 46278 | L70: 35000 | N70: =IF($E70="","",ROUND(N($L70)-N($M70),2)) | O70: 0.003 | P70: 800 | Q70: 17 | R70: 46282 | S70: 105 | X70: =IF($E70="","",IF(AND($B70<>"",ISNA(MATCH($B70,机构表,0))),"※机构不在【资料】里",IF(AND($D70<>"",ISNA(MATCH($D70,状态表,0))),"※状态不在【资料】里",IF(N($M70)>N($L70),"※已还本金大于典当金额",IF(AND($I70<>"",$J70<>"",$J70<$I70),"※到期日早于当票日期",IF(AND($H70<>"",COUNTIF($H$4:$H$403,$H70)>1),"※当票号在本表里出现了不止一次",IF(AND($L70<>"",$E70=""),"※有金额没写客户","")))))))
A71: =IF($E71="","",COUNTA($E$4:$E71)) | B71: 个人典当 | C71: 黄金+手表 | D71: 在当 | E71: 林斌 | J71: 46049 | K71: 46020 | L71: 80000 | N71: =IF($E71="","",ROUND(N($L71)-N($M71),2)) | P71: 1900 | Q71: 28 | R71: 46293 | X71: =IF($E71="","",IF(AND($B71<>"",ISNA(MATCH($B71,机构表,0))),"※机构不在【资料】里",IF(AND($D71<>"",ISNA(MATCH($D71,状态表,0))),"※状态不在【资料】里",IF(N($M71)>N($L71),"※已还本金大于典当金额",IF(AND($I71<>"",$J71<>"",$J71<$I71),"※到期日早于当票日期",IF(AND($H71<>"",COUNTIF($H$4:$H$403,$H71)>1),"※当票号在本表里出现了不止一次",IF(AND($L71<>"",$E71=""),"※有金额没写客户","")))))))
A72: =IF($E72="","",COUNTA($E$4:$E72)) | B72: 金辉典当 | C72: 房产 | D72: 在当 | E72: 林昌耿 | H72: 3519260506 | I72: 45953 | J72: 46132 | L72: 200000 | N72: =IF($E72="","",ROUND(N($L72)-N($M72),2)) | O72: 0.018 | P72: 3300 | Q72: 23 | R72: 46135 | V72: 先息 | X72: =IF($E72="","",IF(AND($B72<>"",ISNA(MATCH($B72,机构表,0))),"※机构不在【资料】里",IF(AND($D72<>"",ISNA(MATCH($D72,状态表,0))),"※状态不在【资料】里",IF(N($M72)>N($L72),"※已还本金大于典当金额",IF(AND($I72<>"",$J72<>"",$J72<$I72),"※到期日早于当票日期",IF(AND($H72<>"",COUNTIF($H$4:$H$403,$H72)>1),"※当票号在本表里出现了不止一次",IF(AND($L72<>"",$E72=""),"※有金额没写客户","")))))))
A73: =IF($E73="","",COUNTA($E$4:$E73)) | B73: 金辉典当 | C73: 房产 | D73: 在当 | E73: 林昌耿 | H73: 3524019239 | I73: 46223 | J73: 46402 | L73: 200000 | N73: =IF($E73="","",ROUND(N($L73)-N($M73),2)) | O73: 0.025 | P73: 5000 | Q73: 20 | R73: 46223 | X73: =IF($E73="","",IF(AND($B73<>"",ISNA(MATCH($B73,机构表,0))),"※机构不在【资料】里",IF(AND($D73<>"",ISNA(MATCH($D73,状态表,0))),"※状态不在【资料】里",IF(N($M73)>N($L73),"※已还本金大于典当金额",IF(AND($I73<>"",$J73<>"",$J73<$I73),"※到期日早于当票日期",IF(AND($H73<>"",COUNTIF($H$4:$H$403,$H73)>1),"※当票号在本表里出现了不止一次",IF(AND($L73<>"",$E73=""),"※有金额没写客户","")))))))
A74: =IF($E74="","",COUNTA($E$4:$E74)) | B74: 个人典当 | C74: 私人借款 | D74: 在当 | E74: 林昌耿 | J74: 46007 | K74: 45978 | L74: 200000 | N74: =IF($E74="","",ROUND(N($L74)-N($M74),2)) | P74: 4000 | Q74: 16 | R74: 46128 | X74: =IF($E74="","",IF(AND($B74<>"",ISNA(MATCH($B74,机构表,0))),"※机构不在【资料】里",IF(AND($D74<>"",ISNA(MATCH($D74,状态表,0))),"※状态不在【资料】里",IF(N($M74)>N($L74),"※已还本金大于典当金额",IF(AND($I74<>"",$J74<>"",$J74<$I74),"※到期日早于当票日期",IF(AND($H74<>"",COUNTIF($H$4:$H$403,$H74)>1),"※当票号在本表里出现了不止一次",IF(AND($L74<>"",$E74=""),"※有金额没写客户","")))))))
A75: =IF($E75="","",COUNTA($E$4:$E75)) | B75: 个人典当 | C75: 私人借款 | D75: 在当 | E75: 林昌耿 | K75: 46021 | L75: 200000 | N75: =IF($E75="","",ROUND(N($L75)-N($M75),2)) | P75: 4000 | Q75: 28 | R75: 46140 | X75: =IF($E75="","",IF(AND($B75<>"",ISNA(MATCH($B75,机构表,0))),"※机构不在【资料】里",IF(AND($D75<>"",ISNA(MATCH($D75,状态表,0))),"※状态不在【资料】里",IF(N($M75)>N($L75),"※已还本金大于典当金额",IF(AND($I75<>"",$J75<>"",$J75<$I75),"※到期日早于当票日期",IF(AND($H75<>"",COUNTIF($H$4:$H$403,$H75)>1),"※当票号在本表里出现了不止一次",IF(AND($L75<>"",$E75=""),"※有金额没写客户","")))))))
A76: =IF($E76="","",COUNTA($E$4:$E76)) | B76: 个人典当 | C76: 私人借款 | D76: 在当 | E76: 林昌耿 | K76: 46092 | L76: 150000 | N76: =IF($E76="","",ROUND(N($L76)-N($M76),2)) | P76: 3000 | Q76: 11 | R76: 46123 | X76: =IF($E76="","",IF(AND($B76<>"",ISNA(MATCH($B76,机构表,0))),"※机构不在【资料】里",IF(AND($D76<>"",ISNA(MATCH($D76,状态表,0))),"※状态不在【资料】里",IF(N($M76)>N($L76),"※已还本金大于典当金额",IF(AND($I76<>"",$J76<>"",$J76<$I76),"※到期日早于当票日期",IF(AND($H76<>"",COUNTIF($H$4:$H$403,$H76)>1),"※当票号在本表里出现了不止一次",IF(AND($L76<>"",$E76=""),"※有金额没写客户","")))))))
A77: =IF($E77="","",COUNTA($E$4:$E77)) | B77: 个人典当 | C77: 私人借款 | D77: 在当 | E77: 林昌耿 | K77: 46093 | L77: 150000 | N77: =IF($E77="","",ROUND(N($L77)-N($M77),2)) | P77: 3000 | Q77: 12 | R77: 46124 | X77: =IF($E77="","",IF(AND($B77<>"",ISNA(MATCH($B77,机构表,0))),"※机构不在【资料】里",IF(AND($D77<>"",ISNA(MATCH($D77,状态表,0))),"※状态不在【资料】里",IF(N($M77)>N($L77),"※已还本金大于典当金额",IF(AND($I77<>"",$J77<>"",$J77<$I77),"※到期日早于当票日期",IF(AND($H77<>"",COUNTIF($H$4:$H$403,$H77)>1),"※当票号在本表里出现了不止一次",IF(AND($L77<>"",$E77=""),"※有金额没写客户","")))))))
A78: =IF($E78="","",COUNTA($E$4:$E78)) | B78: 个人典当 | C78: 无抵押借款 | D78: 在当 | E78: 林昌耿 | K78: 46158 | L78: 20000 | N78: =IF($E78="","",ROUND(N($L78)-N($M78),2)) | P78: 400 | Q78: 15 | R78: 46280 | X78: =IF($E78="","",IF(AND($B78<>"",ISNA(MATCH($B78,机构表,0))),"※机构不在【资料】里",IF(AND($D78<>"",ISNA(MATCH($D78,状态表,0))),"※状态不在【资料】里",IF(N($M78)>N($L78),"※已还本金大于典当金额",IF(AND($I78<>"",$J78<>"",$J78<$I78),"※到期日早于当票日期",IF(AND($H78<>"",COUNTIF($H$4:$H$403,$H78)>1),"※当票号在本表里出现了不止一次",IF(AND($L78<>"",$E78=""),"※有金额没写客户","")))))))
A79: =IF($E79="","",COUNTA($E$4:$E79)) | B79: 个人典当 | C79: 无抵押借款 | D79: 在当 | E79: 林昌耿 | K79: 46161 | L79: 30000 | N79: =IF($E79="","",ROUND(N($L79)-N($M79),2)) | P79: 600 | Q79: 19 | R79: 46284 | X79: =IF($E79="","",IF(AND($B79<>"",ISNA(MATCH($B79,机构表,0))),"※机构不在【资料】里",IF(AND($D79<>"",ISNA(MATCH($D79,状态表,0))),"※状态不在【资料】里",IF(N($M79)>N($L79),"※已还本金大于典当金额",IF(AND($I79<>"",$J79<>"",$J79<$I79),"※到期日早于当票日期",IF(AND($H79<>"",COUNTIF($H$4:$H$403,$H79)>1),"※当票号在本表里出现了不止一次",IF(AND($L79<>"",$E79=""),"※有金额没写客户","")))))))
A80: =IF($E80="","",COUNTA($E$4:$E80)) | B80: 个人典当 | C80: 无抵押借款 | D80: 在当 | E80: 林昌耿 | K80: 46197 | L80: 50000 | N80: =IF($E80="","",ROUND(N($L80)-N($M80),2)) | P80: 1250 | Q80: 23 | R80: 46288 | X80: =IF($E80="","",IF(AND($B80<>"",ISNA(MATCH($B80,机构表,0))),"※机构不在【资料】里",IF(AND($D80<>"",ISNA(MATCH($D80,状态表,0))),"※状态不在【资料】里",IF(N($M80)>N($L80),"※已还本金大于典当金额",IF(AND($I80<>"",$J80<>"",$J80<$I80),"※到期日早于当票日期",IF(AND($H80<>"",COUNTIF($H$4:$H$403,$H80)>1),"※当票号在本表里出现了不止一次",IF(AND($L80<>"",$E80=""),"※有金额没写客户","")))))))
A81: =IF($E81="","",COUNTA($E$4:$E81)) | B81: 个人典当 | C81: 无抵押借款 | D81: 在当 | E81: 林昌耿 | K81: 46223 | L81: 50000 | N81: =IF($E81="","",ROUND(N($L81)-N($M81),2)) | P81: 1250 | Q81: 20 | R81: 46285 | X81: =IF($E81="","",IF(AND($B81<>"",ISNA(MATCH($B81,机构表,0))),"※机构不在【资料】里",IF(AND($D81<>"",ISNA(MATCH($D81,状态表,0))),"※状态不在【资料】里",IF(N($M81)>N($L81),"※已还本金大于典当金额",IF(AND($I81<>"",$J81<>"",$J81<$I81),"※到期日早于当票日期",IF(AND($H81<>"",COUNTIF($H$4:$H$403,$H81)>1),"※当票号在本表里出现了不止一次",IF(AND($L81<>"",$E81=""),"※有金额没写客户","")))))))
A82: =IF($E82="","",COUNTA($E$4:$E82)) | B82: 个人典当 | C82: 无抵押借款 | D82: 在当 | E82: 林昌耿 | K82: 46254 | L82: 50000 | N82: =IF($E82="","",ROUND(N($L82)-N($M82),2)) | P82: 1250 | Q82: 20 | R82: 46285 | X82: =IF($E82="","",IF(AND($B82<>"",ISNA(MATCH($B82,机构表,0))),"※机构不在【资料】里",IF(AND($D82<>"",ISNA(MATCH($D82,状态表,0))),"※状态不在【资料】里",IF(N($M82)>N($L82),"※已还本金大于典当金额",IF(AND($I82<>"",$J82<>"",$J82<$I82),"※到期日早于当票日期",IF(AND($H82<>"",COUNTIF($H$4:$H$403,$H82)>1),"※当票号在本表里出现了不止一次",IF(AND($L82<>"",$E82=""),"※有金额没写客户","")))))))
A83: =IF($E83="","",COUNTA($E$4:$E83)) | B83: 个人典当 | C83: 无抵押借款 | D83: 在当 | E83: 林昌耿 | K83: 46258 | L83: 30000 | N83: =IF($E83="","",ROUND(N($L83)-N($M83),2)) | P83: 750 | Q83: 24 | R83: 46289 | X83: =IF($E83="","",IF(AND($B83<>"",ISNA(MATCH($B83,机构表,0))),"※机构不在【资料】里",IF(AND($D83<>"",ISNA(MATCH($D83,状态表,0))),"※状态不在【资料】里",IF(N($M83)>N($L83),"※已还本金大于典当金额",IF(AND($I83<>"",$J83<>"",$J83<$I83),"※到期日早于当票日期",IF(AND($H83<>"",COUNTIF($H$4:$H$403,$H83)>1),"※当票号在本表里出现了不止一次",IF(AND($L83<>"",$E83=""),"※有金额没写客户","")))))))
A84: =IF($E84="","",COUNTA($E$4:$E84)) | B84: 个人典当 | C84: 无抵押借款 | D84: 在当 | E84: 林昌耿 | K84: 46269 | L84: 60000 | N84: =IF($E84="","",ROUND(N($L84)-N($M84),2)) | P84: 1500 | Q84: 4 | R84: 46269 | X84: =IF($E84="","",IF(AND($B84<>"",ISNA(MATCH($B84,机构表,0))),"※机构不在【资料】里",IF(AND($D84<>"",ISNA(MATCH($D84,状态表,0))),"※状态不在【资料】里",IF(N($M84)>N($L84),"※已还本金大于典当金额",IF(AND($I84<>"",$J84<>"",$J84<$I84),"※到期日早于当票日期",IF(AND($H84<>"",COUNTIF($H$4:$H$403,$H84)>1),"※当票号在本表里出现了不止一次",IF(AND($L84<>"",$E84=""),"※有金额没写客户","")))))))
A85: =IF($E85="","",COUNTA($E$4:$E85)) | B85: 个人典当 | C85: 钻戒 | D85: 在当 | E85: 林芬 | J85: 45906 | K85: 45877 | L85: 9000 | N85: =IF($E85="","",ROUND(N($L85)-N($M85),2)) | P85: 230 | Q85: 7 | R85: 46272 | X85: =IF($E85="","",IF(AND($B85<>"",ISNA(MATCH($B85,机构表,0))),"※机构不在【资料】里",IF(AND($D85<>"",ISNA(MATCH($D85,状态表,0))),"※状态不在【资料】里",IF(N($M85)>N($L85),"※已还本金大于典当金额",IF(AND($I85<>"",$J85<>"",$J85<$I85),"※到期日早于当票日期",IF(AND($H85<>"",COUNTIF($H$4:$H$403,$H85)>1),"※当票号在本表里出现了不止一次",IF(AND($L85<>"",$E85=""),"※有金额没写客户","")))))))
A86: =IF($E86="","",COUNTA($E$4:$E86)) | B86: 金辉典当 | C86: 房产 | D86: 在当 | E86: 林浩 | H86: 3519260512 | I86: 46037 | J86: 46096 | L86: 100000 | N86: =IF($E86="","",ROUND(N($L86)-N($M86),2)) | O86: 0.025 | P86: 2500 | Q86: 15 | R86: 46280 | X86: =IF($E86="","",IF(AND($B86<>"",ISNA(MATCH($B86,机构表,0))),"※机构不在【资料】里",IF(AND($D86<>"",ISNA(MATCH($D86,状态表,0))),"※状态不在【资料】里",IF(N($M86)>N($L86),"※已还本金大于典当金额",IF(AND($I86<>"",$J86<>"",$J86<$I86),"※到期日早于当票日期",IF(AND($H86<>"",COUNTIF($H$4:$H$403,$H86)>1),"※当票号在本表里出现了不止一次",IF(AND($L86<>"",$E86=""),"※有金额没写客户","")))))))
A87: =IF($E87="","",COUNTA($E$4:$E87)) | B87: 金辉典当 | C87: 房产 | D87: 起诉还款 | E87: 林华 | I87: 45132 | K87: 45255 | L87: 20000 | N87: =IF($E87="","",ROUND(N($L87)-N($M87),2)) | O87: 0.03 | P87: 500 | Q87: 22 | R87: 45404 | U87: 500 | V87: 先息 | X87: =IF($E87="","",IF(AND($B87<>"",ISNA(MATCH($B87,机构表,0))),"※机构不在【资料】里",IF(AND($D87<>"",ISNA(MATCH($D87,状态表,0))),"※状态不在【资料】里",IF(N($M87)>N($L87),"※已还本金大于典当金额",IF(AND($I87<>"",$J87<>"",$J87<$I87),"※到期日早于当票日期",IF(AND($H87<>"",COUNTIF($H$4:$H$403,$H87)>1),"※当票号在本表里出现了不止一次",IF(AND($L87<>"",$E87=""),"※有金额没写客户","")))))))
A88: =IF($E88="","",COUNTA($E$4:$E88)) | B88: 个人典当 | C88: 黄金 | D88: 在当 | E88: 林惠明 | J88: 45707 | K88: 45678 | L88: 33000 | N88: =IF($E88="","",ROUND(N($L88)-N($M88),2)) | P88: 825 | Q88: 19 | R88: 46284 | X88: =IF($E88="","",IF(AND($B88<>"",ISNA(MATCH($B88,机构表,0))),"※机构不在【资料】里",IF(AND($D88<>"",ISNA(MATCH($D88,状态表,0))),"※状态不在【资料】里",IF(N($M88)>N($L88),"※已还本金大于典当金额",IF(AND($I88<>"",$J88<>"",$J88<$I88),"※到期日早于当票日期",IF(AND($H88<>"",COUNTIF($H$4:$H$403,$H88)>1),"※当票号在本表里出现了不止一次",IF(AND($L88<>"",$E88=""),"※有金额没写客户","")))))))
A89: =IF($E89="","",COUNTA($E$4:$E89)) | B89: 个人典当 | C89: 私人借款 | D89: 无法回款 | E89: 林剑凡 | J89: 45244 | K89: 45225 | L89: 150000 | N89: =IF($E89="","",ROUND(N($L89)-N($M89),2)) | X89: =IF($E89="","",IF(AND($B89<>"",ISNA(MATCH($B89,机构表,0))),"※机构不在【资料】里",IF(AND($D89<>"",ISNA(MATCH($D89,状态表,0))),"※状态不在【资料】里",IF(N($M89)>N($L89),"※已还本金大于典当金额",IF(AND($I89<>"",$J89<>"",$J89<$I89),"※到期日早于当票日期",IF(AND($H89<>"",COUNTIF($H$4:$H$403,$H89)>1),"※当票号在本表里出现了不止一次",IF(AND($L89<>"",$E89=""),"※有金额没写客户","")))))))
A90: =IF($E90="","",COUNTA($E$4:$E90)) | B90: 个人典当 | C90: 私人借款 | D90: 无法回款 | E90: 林俊行 | K90: 45391 | L90: 20000 | N90: =IF($E90="","",ROUND(N($L90)-N($M90),2)) | X90: =IF($E90="","",IF(AND($B90<>"",ISNA(MATCH($B90,机构表,0))),"※机构不在【资料】里",IF(AND($D90<>"",ISNA(MATCH($D90,状态表,0))),"※状态不在【资料】里",IF(N($M90)>N($L90),"※已还本金大于典当金额",IF(AND($I90<>"",$J90<>"",$J90<$I90),"※到期日早于当票日期",IF(AND($H90<>"",COUNTIF($H$4:$H$403,$H90)>1),"※当票号在本表里出现了不止一次",IF(AND($L90<>"",$E90=""),"※有金额没写客户","")))))))
A91: =IF($E91="","",COUNTA($E$4:$E91)) | B91: 金辉典当 | C91: 黄金 | D91: 在当 | E91: 林凯鑫 | H91: 3524019246 | I91: 46266 | J91: 46445 | L91: 90000 | N91: =IF($E91="","",ROUND(N($L91)-N($M91),2)) | O91: 0.003 | P91: 1350 | Q91: 1 | R91: 46266 | S91: 270 | X91: =IF($E91="","",IF(AND($B91<>"",ISNA(MATCH($B91,机构表,0))),"※机构不在【资料】里",IF(AND($D91<>"",ISNA(MATCH($D91,状态表,0))),"※状态不在【资料】里",IF(N($M91)>N($L91),"※已还本金大于典当金额",IF(AND($I91<>"",$J91<>"",$J91<$I91),"※到期日早于当票日期",IF(AND($H91<>"",COUNTIF($H$4:$H$403,$H91)>1),"※当票号在本表里出现了不止一次",IF(AND($L91<>"",$E91=""),"※有金额没写客户","")))))))
A92: =IF($E92="","",COUNTA($E$4:$E92)) | B92: 金辉典当 | C92: 房产 | D92: 在当 | E92: 林鹏 | H92: 3519260522 | I92: 46111 | J92: 46290 | L92: 100000 | N92: =IF($E92="","",ROUND(N($L92)-N($M92),2)) | O92: 0.02 | P92: 2000 | Q92: 29 | R92: 46294 | W92: 对公收利息 | X92: =IF($E92="","",IF(AND($B92<>"",ISNA(MATCH($B92,机构表,0))),"※机构不在【资料】里",IF(AND($D92<>"",ISNA(MATCH($D92,状态表,0))),"※状态不在【资料】里",IF(N($M92)>N($L92),"※已还本金大于典当金额",IF(AND($I92<>"",$J92<>"",$J92<$I92),"※到期日早于当票日期",IF(AND($H92<>"",COUNTIF($H$4:$H$403,$H92)>1),"※当票号在本表里出现了不止一次",IF(AND($L92<>"",$E92=""),"※有金额没写客户","")))))))
A93: =IF($E93="","",COUNTA($E$4:$E93)) | B93: 金辉典当 | C93: 房产 | D93: 在当 | E93: 林鹏 | H93: 3524019227 | I93: 46163 | J93: 46252 | L93: 50000 | N93: =IF($E93="","",ROUND(N($L93)-N($M93),2)) | O93: 0.02 | P93: 1000 | Q93: 20 | R93: 46285 | W93: 对公收利息 | X93: =IF($E93="","",IF(AND($B93<>"",ISNA(MATCH($B93,机构表,0))),"※机构不在【资料】里",IF(AND($D93<>"",ISNA(MATCH($D93,状态表,0))),"※状态不在【资料】里",IF(N($M93)>N($L93),"※已还本金大于典当金额",IF(AND($I93<>"",$J93<>"",$J93<$I93),"※到期日早于当票日期",IF(AND($H93<>"",COUNTIF($H$4:$H$403,$H93)>1),"※当票号在本表里出现了不止一次",IF(AND($L93<>"",$E93=""),"※有金额没写客户","")))))))
A94: =IF($E94="","",COUNTA($E$4:$E94)) | B94: 个人典当 | C94: 私人借款 | D94: 无法回款 | E94: 林瑞腾 | J94: 45544 | K94: 45540 | L94: 20000 | N94: =IF($E94="","",ROUND(N($L94)-N($M94),2)) | X94: =IF($E94="","",IF(AND($B94<>"",ISNA(MATCH($B94,机构表,0))),"※机构不在【资料】里",IF(AND($D94<>"",ISNA(MATCH($D94,状态表,0))),"※状态不在【资料】里",IF(N($M94)>N($L94),"※已还本金大于典当金额",IF(AND($I94<>"",$J94<>"",$J94<$I94),"※到期日早于当票日期",IF(AND($H94<>"",COUNTIF($H$4:$H$403,$H94)>1),"※当票号在本表里出现了不止一次",IF(AND($L94<>"",$E94=""),"※有金额没写客户","")))))))
A95: =IF($E95="","",COUNTA($E$4:$E95)) | B95: 个人典当 | C95: 黄金 | D95: 在当 | E95: 林文福 | K95: 46172 | L95: 85000 | N95: =IF($E95="","",ROUND(N($L95)-N($M95),2)) | P95: 1275 | Q95: 29 | R95: 46294 | X95: =IF($E95="","",IF(AND($B95<>"",ISNA(MATCH($B95,机构表,0))),"※机构不在【资料】里",IF(AND($D95<>"",ISNA(MATCH($D95,状态表,0))),"※状态不在【资料】里",IF(N($M95)>N($L95),"※已还本金大于典当金额",IF(AND($I95<>"",$J95<>"",$J95<$I95),"※到期日早于当票日期",IF(AND($H95<>"",COUNTIF($H$4:$H$403,$H95)>1),"※当票号在本表里出现了不止一次",IF(AND($L95<>"",$E95=""),"※有金额没写客户","")))))))
A96: =IF($E96="","",COUNTA($E$4:$E96)) | B96: 个人典当 | C96: 黄金 | D96: 在当 | E96: 林文福 | K96: 46216 | L96: 55000 | N96: =IF($E96="","",ROUND(N($L96)-N($M96),2)) | P96: 825 | Q96: 13 | R96: 46278 | X96: =IF($E96="","",IF(AND($B96<>"",ISNA(MATCH($B96,机构表,0))),"※机构不在【资料】里",IF(AND($D96<>"",ISNA(MATCH($D96,状态表,0))),"※状态不在【资料】里",IF(N($M96)>N($L96),"※已还本金大于典当金额",IF(AND($I96<>"",$J96<>"",$J96<$I96),"※到期日早于当票日期",IF(AND($H96<>"",COUNTIF($H$4:$H$403,$H96)>1),"※当票号在本表里出现了不止一次",IF(AND($L96<>"",$E96=""),"※有金额没写客户","")))))))
A97: =IF($E97="","",COUNTA($E$4:$E97)) | B97: 个人典当 | C97: 车子 | D97: 在当 | E97: 林文福 | K97: 46248 | L97: 80000 | N97: =IF($E97="","",ROUND(N($L97)-N($M97),2)) | P97: 1700 | Q97: 13 | R97: 46278 | X97: =IF($E97="","",IF(AND($B97<>"",ISNA(MATCH($B97,机构表,0))),"※机构不在【资料】里",IF(AND($D97<>"",ISNA(MATCH($D97,状态表,0))),"※状态不在【资料】里",IF(N($M97)>N($L97),"※已还本金大于典当金额",IF(AND($I97<>"",$J97<>"",$J97<$I97),"※到期日早于当票日期",IF(AND($H97<>"",COUNTIF($H$4:$H$403,$H97)>1),"※当票号在本表里出现了不止一次",IF(AND($L97<>"",$E97=""),"※有金额没写客户","")))))))
A98: =IF($E98="","",COUNTA($E$4:$E98)) | B98: 个人典当 | C98: 私人借款 | D98: 在当 | E98: 林文维 | J98: 46211 | K98: 46030 | L98: 20000 | N98: =IF($E98="","",ROUND(N($L98)-N($M98),2)) | P98: 300 | Q98: 8 | R98: 46273 | X98: =IF($E98="","",IF(AND($B98<>"",ISNA(MATCH($B98,机构表,0))),"※机构不在【资料】里",IF(AND($D98<>"",ISNA(MATCH($D98,状态表,0))),"※状态不在【资料】里",IF(N($M98)>N($L98),"※已还本金大于典当金额",IF(AND($I98<>"",$J98<>"",$J98<$I98),"※到期日早于当票日期",IF(AND($H98<>"",COUNTIF($H$4:$H$403,$H98)>1),"※当票号在本表里出现了不止一次",IF(AND($L98<>"",$E98=""),"※有金额没写客户","")))))))
A99: =IF($E99="","",COUNTA($E$4:$E99)) | B99: 金辉典当 | C99: 房产 | D99: 起诉还款 | E99: 林晓霞 | I99: 45132 | K99: 45255 | L99: 60000 | N99: =IF($E99="","",ROUND(N($L99)-N($M99),2)) | O99: 0.03 | P99: 1800 | Q99: 22 | R99: 45404 | U99: 1500 | V99: 先息 | X99: =IF($E99="","",IF(AND($B99<>"",ISNA(MATCH($B99,机构表,0))),"※机构不在【资料】里",IF(AND($D99<>"",ISNA(MATCH($D99,状态表,0))),"※状态不在【资料】里",IF(N($M99)>N($L99),"※已还本金大于典当金额",IF(AND($I99<>"",$J99<>"",$J99<$I99),"※到期日早于当票日期",IF(AND($H99<>"",COUNTIF($H$4:$H$403,$H99)>1),"※当票号在本表里出现了不止一次",IF(AND($L99<>"",$E99=""),"※有金额没写客户","")))))))
A100: =IF($E100="","",COUNTA($E$4:$E100)) | B100: 个人典当 | C100: 黄金 | D100: 在当 | E100: 林燕 | J100: 45682 | K100: 45653 | L100: 3500 | N100: =IF($E100="","",ROUND(N($L100)-N($M100),2)) | P100: 100 | Q100: 24 | R100: 46289 | X100: =IF($E100="","",IF(AND($B100<>"",ISNA(MATCH($B100,机构表,0))),"※机构不在【资料】里",IF(AND($D100<>"",ISNA(MATCH($D100,状态表,0))),"※状态不在【资料】里",IF(N($M100)>N($L100),"※已还本金大于典当金额",IF(AND($I100<>"",$J100<>"",$J100<$I100),"※到期日早于当票日期",IF(AND($H100<>"",COUNTIF($H$4:$H$403,$H100)>1),"※当票号在本表里出现了不止一次",IF(AND($L100<>"",$E100=""),"※有金额没写客户","")))))))
...

Sheet 金辉典当
A1: 【金辉典当】明细 · 自动从表2拆出来，不用填
A2: 机构名称 | B2: 金辉典当 | C2: ← 这格是拆分依据，别改。整张表是一条公式的结果，要改数据去【表2客户典当登记】改，手动在这里打字会把公式顶掉。 | AA2: 机构 | AB2: ="金辉典当" | AC2: 笔数 | AD2: =COUNTIF(表2客户典当登记!$B$4:$B$403,"金辉典当") | AE2: 典当金额 | AF2: =ROUND(SUMIF(表2客户典当登记!$B$4:$B$403,"金辉典当",表2客户典当登记!$L$4:$L$403),2) | AG2: 已还本金 | AH2: =ROUND(SUMIF(表2客户典当登记!$B$4:$B$403,"金辉典当",表2客户典当登记!$M$4:$M$403),2) | AI2: 当前在当 | AJ2: =ROUND(SUMIF(表2客户典当登记!$B$4:$B$403,"金辉典当",表2客户典当登记!$N$4:$N$403),2) | AK2: 应收利息 | AL2: =ROUND(SUMIF(表2客户典当登记!$B$4:$B$403,"金辉典当",表2客户典当登记!$P$4:$P$403),2)
A3: 序号 | B3: 抵押机构 ★ | C3: 抵押物品 ★ | D3: 状态 ★ | E3: 客户姓名 ★ | F3: 身份证号 | G3: 客户电话 | H3: 当票号 | I3: 当票日期 | J3: 当票到期日 | K3: 出款日期 | L3: 典当金额 ★ | M3: 已还本金 | N3: 当前在当 | O3: 典当系统费率 | P3: 应收利息 | Q3: 利息日 | R3: 应付利息日 | S3: 对公 | T3: 违约金 | U3: 开票金额 | V3: 付息方式 | W3: 详情/备注 | X3: 核对
A4: {=_xlfn._xlws.FILTER(IF(表2客户典当登记!$A$4:$X$403="","",表2客户典当登记!$A$4:$X$403),表2客户典当登记!$B$4:$B$403=$B$2,"这个机构还没有记录")}

Sheet 明道典当
A1: 【明道典当】明细 · 自动从表2拆出来，不用填
A2: 机构名称 | B2: 明道典当 | C2: ← 这格是拆分依据，别改。整张表是一条公式的结果，要改数据去【表2客户典当登记】改，手动在这里打字会把公式顶掉。 | AA2: 机构 | AB2: ="明道典当" | AC2: 笔数 | AD2: =COUNTIF(表2客户典当登记!$B$4:$B$403,"明道典当") | AE2: 典当金额 | AF2: =ROUND(SUMIF(表2客户典当登记!$B$4:$B$403,"明道典当",表2客户典当登记!$L$4:$L$403),2) | AG2: 已还本金 | AH2: =ROUND(SUMIF(表2客户典当登记!$B$4:$B$403,"明道典当",表2客户典当登记!$M$4:$M$403),2) | AI2: 当前在当 | AJ2: =ROUND(SUMIF(表2客户典当登记!$B$4:$B$403,"明道典当",表2客户典当登记!$N$4:$N$403),2) | AK2: 应收利息 | AL2: =ROUND(SUMIF(表2客户典当登记!$B$4:$B$403,"明道典当",表2客户典当登记!$P$4:$P$403),2)
A3: 序号 | B3: 抵押机构 ★ | C3: 抵押物品 ★ | D3: 状态 ★ | E3: 客户姓名 ★ | F3: 身份证号 | G3: 客户电话 | H3: 当票号 | I3: 当票日期 | J3: 当票到期日 | K3: 出款日期 | L3: 典当金额 ★ | M3: 已还本金 | N3: 当前在当 | O3: 典当系统费率 | P3: 应收利息 | Q3: 利息日 | R3: 应付利息日 | S3: 对公 | T3: 违约金 | U3: 开票金额 | V3: 付息方式 | W3: 详情/备注 | X3: 核对
A4: {=_xlfn._xlws.FILTER(IF(表2客户典当登记!$A$4:$X$403="","",表2客户典当登记!$A$4:$X$403),表2客户典当登记!$B$4:$B$403=$B$2,"这个机构还没有记录")}

Sheet 个人典当
A1: 【个人典当】明细 · 自动从表2拆出来，不用填
A2: 机构名称 | B2: 个人典当 | C2: ← 这格是拆分依据，别改。整张表是一条公式的结果，要改数据去【表2客户典当登记】改，手动在这里打字会把公式顶掉。 | AA2: 机构 | AB2: ="个人典当" | AC2: 笔数 | AD2: =COUNTIF(表2客户典当登记!$B$4:$B$403,"个人典当") | AE2: 典当金额 | AF2: =ROUND(SUMIF(表2客户典当登记!$B$4:$B$403,"个人典当",表2客户典当登记!$L$4:$L$403),2) | AG2: 已还本金 | AH2: =ROUND(SUMIF(表2客户典当登记!$B$4:$B$403,"个人典当",表2客户典当登记!$M$4:$M$403),2) | AI2: 当前在当 | AJ2: =ROUND(SUMIF(表2客户典当登记!$B$4:$B$403,"个人典当",表2客户典当登记!$N$4:$N$403),2) | AK2: 应收利息 | AL2: =ROUND(SUMIF(表2客户典当登记!$B$4:$B$403,"个人典当",表2客户典当登记!$P$4:$P$403),2)
A3: 序号 | B3: 抵押机构 ★ | C3: 抵押物品 ★ | D3: 状态 ★ | E3: 客户姓名 ★ | F3: 身份证号 | G3: 客户电话 | H3: 当票号 | I3: 当票日期 | J3: 当票到期日 | K3: 出款日期 | L3: 典当金额 ★ | M3: 已还本金 | N3: 当前在当 | O3: 典当系统费率 | P3: 应收利息 | Q3: 利息日 | R3: 应付利息日 | S3: 对公 | T3: 违约金 | U3: 开票金额 | V3: 付息方式 | W3: 详情/备注 | X3: 核对
A4: {=_xlfn._xlws.FILTER(IF(表2客户典当登记!$A$4:$X$403="","",表2客户典当登记!$A$4:$X$403),表2客户典当登记!$B$4:$B$403=$B$2,"这个机构还没有记录")}

Sheet 查询表（新）
A1: 客户姓名 | B1: 严为志 | D1: 身份证号 | G1: =IF($B$1="","← 先选客户姓名。身份证号只有碰到同名客户时才要填。",IF($E$1<>"","已按【姓名+身份证】筛选，典当命中 "&COUNTIFS(表2客户典当登记!$E$4:$E$403,$B$1,表2客户典当登记!$F$4:$F$403,$E$1)&" 笔。（不动产和资金台账没有身份证号这一列，那两块仍然只能按姓名查）",IF(IFERROR(SUMPRODUCT((表2客户典当登记!$E$4:$E$403=$B$1)*(表2客户典当登记!$F$4:$F$403<>"")/(COUNTIFS(表2客户典当登记!$E$4:$E$403,$B$1,表2客户典当登记!$F$4:$F$403,表2客户典当登记!$F$4:$F$403&"")+(表2客户典当登记!$E$4:$E$403<>$B$1))),0)>1,"※这个姓名下登了 "&IFERROR(SUMPRODUCT((表2客户典当登记!$E$4:$E$403=$B$1)*(表2客户典当登记!$F$4:$F$403<>"")/(COUNTIFS(表2客户典当登记!$E$4:$E$403,$B$1,表2客户典当登记!$F$4:$F$403,表2客户典当登记!$F$4:$F$403&"")+(表2客户典当登记!$E$4:$E$403<>$B$1))),0)&" 个不同的身份证号，请把身份证号填到左边 E1 再查。","按姓名查，典当 "&COUNTIF(表2客户典当登记!$E$4:$E$403,$B$1)&" 笔。"&IF(SUMPRODUCT((表2客户典当登记!$E$4:$E$403=$B$1)*(表2客户典当登记!$F$4:$F$403<>""))=0,"（这个客户还没登身份证号，没有同名就不用管）","")))) | N1: ※ 右边这块取的是《A061_资金台账.xlsx》，查的时候那个文件要一起打开。
A2: 典当笔数 | B2: =IF($B$1="","",IF($E$1="",COUNTIF(表2客户典当登记!$E$4:$E$403,$B$1),COUNTIFS(表2客户典当登记!$E$4:$E$403,$B$1,表2客户典当登记!$F$4:$F$403,$E$1))) | C2: 典当金额 | D2: =IF($B$1="","",ROUND(IF($E$1="",SUMIF(表2客户典当登记!$E$4:$E$403,$B$1,表2客户典当登记!$L$4:$L$403),SUMIFS(表2客户典当登记!$L$4:$L$403,表2客户典当登记!$E$4:$E$403,$B$1,表2客户典当登记!$F$4:$F$403,$E$1)),2)) | E2: 已还本金 | F2: =IF($B$1="","",ROUND(IF($E$1="",SUMIF(表2客户典当登记!$E$4:$E$403,$B$1,表2客户典当登记!$M$4:$M$403),SUMIFS(表2客户典当登记!$M$4:$M$403,表2客户典当登记!$E$4:$E$403,$B$1,表2客户典当登记!$F$4:$F$403,$E$1)),2)) | G2: 当前在当 | H2: =IF($B$1="","",ROUND(IF($E$1="",SUMIF(表2客户典当登记!$E$4:$E$403,$B$1,表2客户典当登记!$N$4:$N$403),SUMIFS(表2客户典当登记!$N$4:$N$403,表2客户典当登记!$E$4:$E$403,$B$1,表2客户典当登记!$F$4:$F$403,$E$1)),2)) | I2: 应收利息 | J2: =IF($B$1="","",ROUND(IF($E$1="",SUMIF(表2客户典当登记!$E$4:$E$403,$B$1,表2客户典当登记!$P$4:$P$403),SUMIFS(表2客户典当登记!$P$4:$P$403,表2客户典当登记!$E$4:$E$403,$B$1,表2客户典当登记!$F$4:$F$403,$E$1)),2)) | K2: 不动产金额 | L2: =IF($B$1="","",ROUND(SUMIF(表1不动产登记!$D$4:$D$123,$B$1,表1不动产登记!$J$4:$J$123),2)) | N2: 资金·收到 | O2: =IF($B$1="","",IFERROR(ROUND(SUMIF([1]数据录入!$I$19:$I$5078,$B$1,[1]数据录入!$F$19:$F$5078)+SUMIF([1]数据录入!$J$19:$J$5078,$B$1,[1]数据录入!$F$19:$F$5078),2),"—")) | P2: 资金·付出 | Q2: =IF($B$1="","",IFERROR(ROUND(SUMIF([1]数据录入!$I$19:$I$5078,$B$1,[1]数据录入!$G$19:$G$5078)+SUMIF([1]数据录入!$J$19:$J$5078,$B$1,[1]数据录入!$G$19:$G$5078),2),"—")) | R2: 资金笔数 | S2: =IF($B$1="","",IFERROR(COUNTIF([1]数据录入!$I$19:$I$5078,$B$1)+COUNTIF([1]数据录入!$J$19:$J$5078,$B$1),"—"))
A3: =IF($B$1="","一、典当记录（表2） ← 先选客户姓名","一、典当记录（表2） 共 "&IF($E$1="",COUNTIF(表2客户典当登记!$E$4:$E$403,$B$1),COUNTIFS(表2客户典当登记!$E$4:$E$403,$B$1,表2客户典当登记!$F$4:$F$403,$E$1))&" 笔"&IF(IF($E$1="",COUNTIF(表2客户典当登记!$E$4:$E$403,$B$1),COUNTIFS(表2客户典当登记!$E$4:$E$403,$B$1,表2客户典当登记!$F$4:$F$403,$E$1))>40," ※超过预留的 40 行了，告诉我加行","")) | N3: =IF($B$1="","二、资金收付流水（《A061_资金台账.xlsx》数据录入） ← 先选客户姓名",IFERROR("二、资金收付流水（《A061_资金台账.xlsx》数据录入） 共 "&COUNTIF([1]数据录入!$I$19:$I$5078,$B$1)+COUNTIF([1]数据录入!$J$19:$J$5078,$B$1)&" 笔"&IF(COUNTIF([1]数据录入!$I$19:$I$5078,$B$1)+COUNTIF([1]数据录入!$J$19:$J$5078,$B$1)>60," ※超过预留的 60 行了，告诉我加行",""),"二、资金收付流水（《A061_资金台账.xlsx》数据录入） ← 取不到数：请把《A061_资金台账.xlsx》一起打开"))
A4: 序号 | B4: 抵押机构 | C4: 抵押物品 | D4: 状 态 | E4: 当票号 | F4: 出款日期 | G4: 典当金额 | H4: 已还本金 | I4: 当前在当 | J4: 应收利息 | K4: 利息日 | L4: 详情/备注 | N4: 序号 | O4: 日 期 | P4: 公司账户 | Q4: 收/支项目类别 | R4: 摘 要 | S4: 收入金额 | T4: 支出金额
A5: {=IF($B$1="","",IFERROR(_xlfn._xlws.FILTER(IF(表2客户典当登记!$A$4:$D$403="","",表2客户典当登记!$A$4:$D$403),(表2客户典当登记!$E$4:$E$403=$B$1)*IF($E$1="",1,(表2客户典当登记!$F$4:$F$403&"")=($E$1&"")),""),""))} | E5: {=IF($B$1="","",IFERROR(_xlfn._xlws.FILTER(IF(表2客户典当登记!$H$4:$H$403="","",表2客户典当登记!$H$4:$H$403),(表2客户典当登记!$E$4:$E$403=$B$1)*IF($E$1="",1,(表2客户典当登记!$F$4:$F$403&"")=($E$1&"")),""),""))} | F5: {=IF($B$1="","",IFERROR(_xlfn._xlws.FILTER(IF(表2客户典当登记!$K$4:$N$403="","",表2客户典当登记!$K$4:$N$403),(表2客户典当登记!$E$4:$E$403=$B$1)*IF($E$1="",1,(表2客户典当登记!$F$4:$F$403&"")=($E$1&"")),""),""))} | J5: {=IF($B$1="","",IFERROR(_xlfn._xlws.FILTER(IF(表2客户典当登记!$P$4:$Q$403="","",表2客户典当登记!$P$4:$Q$403),(表2客户典当登记!$E$4:$E$403=$B$1)*IF($E$1="",1,(表2客户典当登记!$F$4:$F$403&"")=($E$1&"")),""),""))} | L5: {=IF($B$1="","",IFERROR(_xlfn._xlws.FILTER(IF(表2客户典当登记!$W$4:$W$403="","",表2客户典当登记!$W$4:$W$403),(表2客户典当登记!$E$4:$E$403=$B$1)*IF($E$1="",1,(表2客户典当登记!$F$4:$F$403&"")=($E$1&"")),""),""))} | N5: {=IF($B$1="","",IFERROR(_xlfn._xlws.FILTER(IF([1]数据录入!$A$19:$G$5078="","",[1]数据录入!$A$19:$G$5078),(([1]数据录入!$I$19:$I$5078=$B$1)+([1]数据录入!$J$19:$J$5078=$B$1))>0,""),""))}
A46: =IF($B$1="","三、不动产记录（表1 · 就是上面金辉典当那几笔的收款明细，别跟上面相加） ← 先选客户姓名","三、不动产记录（表1 · 就是上面金辉典当那几笔的收款明细，别跟上面相加） 共 "&COUNTIF(表1不动产登记!$D$4:$D$123,$B$1)&" 笔"&IF(COUNTIF(表1不动产登记!$D$4:$D$123,$B$1)>20," ※超过预留的 20 行了，告诉我加行",""))
A47: 序号 | B47: 抵押物品 | C47: 状 态 | D47: 当票号 | E47: 当票日期 | F47: 到期日 | G47: 出款日期 | H47: 典当金额 | I47: 应收利息 | J47: 合计收款 | K47: 逾期天数 | L47: 应收滞纳金
A48: {=IF($B$1="","",IFERROR(_xlfn._xlws.FILTER(IF(表1不动产登记!$A$4:$C$123="","",表1不动产登记!$A$4:$C$123),表1不动产登记!$D$4:$D$123=$B$1,""),""))} | D48: {=IF($B$1="","",IFERROR(_xlfn._xlws.FILTER(IF(表1不动产登记!$F$4:$J$123="","",表1不动产登记!$F$4:$J$123),表1不动产登记!$D$4:$D$123=$B$1,""),""))} | I48: {=IF($B$1="","",IFERROR(_xlfn._xlws.FILTER(IF(表1不动产登记!$L$4:$L$123="","",表1不动产登记!$L$4:$L$123),表1不动产登记!$D$4:$D$123=$B$1,""),""))} | J48: {=IF($B$1="","",IFERROR(_xlfn._xlws.FILTER(IF(表1不动产登记!$S$4:$S$123="","",表1不动产登记!$S$4:$S$123),表1不动产登记!$D$4:$D$123=$B$1,""),""))} | K48: {=IF($B$1="","",IFERROR(_xlfn._xlws.FILTER(IF(表1不动产登记!$V$4:$W$123="","",表1不动产登记!$V$4:$W$123),表1不动产登记!$D$4:$D$123=$B$1,""),""))}

Sheet 查询表
A1: 查询表（旧版·竖着排，保留备用）· 输入客户姓名，一次看全他的典当和资金往来
A2: 最下面那块「资金收付流水」是从《A061_资金台账.xlsx》取的，查的时候两个文件要同时打开（Excel 读不了关着的工作簿，这是规矩不是设置问题）。
A3: 客户姓名 → | B3: 严为志 | D3: 身份证号 | E3: =IF($B$3="","",IFERROR(VLOOKUP($B$3,表2客户典当登记!$E$4:$F$403,2,0),"")) | G3: 客户电话 | H3: =IF($B$3="","",IFERROR(VLOOKUP($B$3,表2客户典当登记!$E$4:$G$403,3,0),IFERROR(VLOOKUP($B$3,表1不动产登记!$D$4:$E$123,2,0),"")))
A5: 典当笔数 | B5: =COUNTIF(表2客户典当登记!$E$4:$E$403,$B$3) | C5: 典当金额 | D5: =ROUND(SUMIF(表2客户典当登记!$E$4:$E$403,$B$3,表2客户典当登记!$L$4:$L$403),2) | E5: 已还本金 | F5: =ROUND(SUMIF(表2客户典当登记!$E$4:$E$403,$B$3,表2客户典当登记!$M$4:$M$403),2) | G5: 当前在当 | H5: =ROUND(SUMIF(表2客户典当登记!$E$4:$E$403,$B$3,表2客户典当登记!$N$4:$N$403),2) | I5: 应收利息 | J5: =ROUND(SUMIF(表2客户典当登记!$E$4:$E$403,$B$3,表2客户典当登记!$P$4:$P$403),2) | K5: 不动产笔数 | L5: =COUNTIF(表1不动产登记!$D$4:$D$123,$B$3) | M5: 不动产金额 | N5: =ROUND(SUMIF(表1不动产登记!$D$4:$D$123,$B$3,表1不动产登记!$J$4:$J$123),2) | O5: 资金·收到 | P5: =ROUND(SUMIF([1]数据录入!$I$19:$I$5078,$B$3,[1]数据录入!$F$19:$F$5078),2) | Q5: 资金·付出 | R5: =ROUND(SUMIF([1]数据录入!$I$19:$I$5078,$B$3,[1]数据录入!$G$19:$G$5078),2)
A8: 一、典当记录（来自【表2客户典当登记】·所有机构） | T8: =IF(COUNTIF(表2客户典当登记!$E$4:$E$403,$B$3)>40,"※记录超过预留的 40 行，会显示 #SPILL!，告诉我加行","")
A9: 序号 | B9: 抵押机构 ★ | C9: 抵押物品 ★ | D9: 状态 ★ | E9: 客户姓名 ★ | F9: 身份证号 | G9: 客户电话 | H9: 当票号 | I9: 当票日期 | J9: 当票到期日 | K9: 出款日期 | L9: 典当金额 ★ | M9: 已还本金 | N9: 当前在当 | O9: 典当系统费率 | P9: 应收利息 | Q9: 利息日 | R9: 应付利息日
A10: {=_xlfn._xlws.FILTER(IF(表2客户典当登记!$A$4:$R$403="","",表2客户典当登记!$A$4:$R$403),表2客户典当登记!$E$4:$E$403=$B$3,"这个客户在表2里没有典当记录")}
A52: 二、不动产记录（来自【表1不动产登记】·就是上面金辉典当那几笔的收款明细，别跟上面相加） | O52: =IF(COUNTIF(表1不动产登记!$D$4:$D$123,$B$3)>20,"※记录超过预留的 20 行，会显示 #SPILL!，告诉我加行","")
A53: 序号 | B53: 抵押物品 ★ | C53: 状态 ★ | D53: 客户姓名 ★ | E53: 客户电话 | F53: 当票号 | G53: 当票日期 | H53: 当票到期日 | I53: 出款日期 | J53: 典当金额 ★ | K53: 典当系统费率 | L53: 应收金额(利息) | M53: 开票金额
A54: {=_xlfn._xlws.FILTER(IF(表1不动产登记!$A$4:$M$123="","",表1不动产登记!$A$4:$M$123),表1不动产登记!$D$4:$D$123=$B$3,"这个客户在表1里没有不动产记录")}
A76: 三、资金收付流水（来自《A061_资金台账.xlsx》的「数据录入」，要同时打开那个文件） | M76: =IF(COUNTIF([1]数据录入!$I$19:$I$5078,$B$3)>80,"※记录超过预留的 80 行，会显示 #SPILL!，告诉我加行","")
A77: 序号 | B77: 日期 | C77: 公司账户 | D77: 收/支项目类别 | E77: 摘要内容 | F77: 收入 | G77: 支出 | H77: 账户余额 | I77: 客户 | J77: 供应商 | K77: 月份
A78: {=_xlfn._xlws.FILTER(IF([1]数据录入!$A$19:$K$5078="","",[1]数据录入!$A$19:$K$5078),[1]数据录入!$I$19:$I$5078=$B$3,"这个客户在资金台账里没有流水，或者《A061_资金台账.xlsx》没打开")}
